{
  "type": "Feature",
  "properties": {
    "gn:admin1_code":"84",
    "gn:admin2_code":"2003.0",
    "gn:admin3_code":"200389.0",
    "gn:admin4_code":"20038976.0",
    "gn:asciiname":"Nathaindipara",
    "gn:country_code":"BD",
    "gn:dem":23,
    "gn:feature_class":"P",
    "gn:feature_code":"PPL",
    "gn:name":"Nathaindipara",
    "gn:population":0,
    "gn:timezone":"Asia/Dhaka",
    "iso:country":"BD",
    "name:ben_x_preferred":[
        "Nathaindipara"
    ],
    "wof:name":"Nathaindipara",
    "wof:placetype":"locality"
},
  "geometry": {"coordinates":[92.23129,22.17629],"type":"Point"}
}