{
  "type": "Feature",
  "properties": {
    "gn:admin1_code":"84",
    "gn:admin2_code":"2015.0",
    "gn:admin3_code":"201533.0",
    "gn:admin4_code":"20153357.0",
    "gn:asciiname":"Fenua",
    "gn:country_code":"BD",
    "gn:dem":15,
    "gn:feature_class":"P",
    "gn:feature_code":"PPL",
    "gn:name":"Fenua",
    "gn:population":0,
    "gn:timezone":"Asia/Dhaka",
    "iso:country":"BD",
    "wof:name":"Fenua",
    "wof:placetype":"locality"
},
  "geometry": {"coordinates":[91.84860999999999,22.69083],"type":"Point"}
}