{
  "type": "Feature",
  "properties": {
    "gn:admin1_code":"87",
    "gn:admin2_code":"5552",
    "gn:admin3_code":"555255.0",
    "gn:admin4_code":"55525507.0",
    "gn:asciiname":"Shibram",
    "gn:country_code":"BD",
    "gn:dem":35,
    "gn:feature_class":"P",
    "gn:feature_code":"PPL",
    "gn:name":"Shibr\u0101m",
    "gn:population":0,
    "gn:timezone":"Asia/Dhaka",
    "iso:country":"BD",
    "name:ben_x_preferred":[
        "Shibr\u0101m"
    ],
    "name:ben_x_variant":[
        "Sibram",
        "Sibar\u0101m"
    ],
    "wof:name":"Shibram",
    "wof:placetype":"locality"
},
  "geometry": {"coordinates":[89.51076999999999,25.87217],"type":"Point"}
}