{
  "type": "Feature",
  "properties": {
    "gn:admin1_code":"83",
    "gn:admin2_code":"5064",
    "gn:admin3_code":"506406.0",
    "gn:admin4_code":"50640610.0",
    "gn:asciiname":"Uttar Mirzapur",
    "gn:country_code":"BD",
    "gn:dem":25,
    "gn:feature_class":"P",
    "gn:feature_code":"PPL",
    "gn:name":"Uttar Mirz\u0101pur",
    "gn:population":0,
    "gn:timezone":"Asia/Dhaka",
    "iso:country":"BD",
    "name:ben_x_preferred":[
        "Uttar Mirz\u0101pur"
    ],
    "name:und_x_variant":[
        "Uttar Mirjapur"
    ],
    "wof:name":"Uttar Mirzapur",
    "wof:placetype":"locality"
},
  "geometry": {"coordinates":[88.91656999999999,24.97292],"type":"Point"}
}