{
  "type": "Feature",
  "properties": {
    "gn:admin1_code":"86",
    "gn:admin2_code":"6058",
    "gn:admin3_code":"605865.0",
    "gn:admin4_code":"60586511.0",
    "gn:asciiname":"Jabda",
    "gn:cc2":"BD",
    "gn:country_code":"BD",
    "gn:dem":13,
    "gn:feature_class":"P",
    "gn:feature_code":"PPL",
    "gn:name":"Jabda",
    "gn:population":0,
    "gn:timezone":"Asia/Dhaka",
    "iso:country":"BD",
    "name:und_x_variant":[
        "Jabdha",
        "Jabda"
    ],
    "wof:name":"Jabda",
    "wof:placetype":"locality"
},
  "geometry": {"coordinates":[92.01667,24.58333],"type":"Point"}
}