{
  "type": "Feature",
  "properties": {
    "gn:admin1_code":"87",
    "gn:admin2_code":"5594.0",
    "gn:admin3_code":"559482.0",
    "gn:admin4_code":"55948243.0",
    "gn:asciiname":"Lakshmipur",
    "gn:country_code":"BD",
    "gn:dem":47,
    "gn:feature_class":"P",
    "gn:feature_code":"PPL",
    "gn:name":"Lakshmipur",
    "gn:population":0,
    "gn:timezone":"Asia/Dhaka",
    "iso:country":"BD",
    "name:ben_x_preferred":[
        "Lakshmipur"
    ],
    "name:ceb_x_preferred":[
        "Lakshmipur"
    ],
    "name:fra_x_preferred":[
        "Lakshmipur"
    ],
    "name:swe_x_preferred":[
        "Lakshmipur"
    ],
    "wof:name":"Lakshmipur",
    "wof:placetype":"locality"
},
  "geometry": {"coordinates":[88.27956999999998,25.83911],"type":"Point"}
}