{
  "type": "Feature",
  "properties": {
    "gn:admin1_code":"81",
    "gn:admin2_code":"3068",
    "gn:admin3_code":"306876.0",
    "gn:admin4_code":"30687694.0",
    "gn:asciiname":"Khupi",
    "gn:country_code":"BD",
    "gn:dem":13,
    "gn:feature_class":"P",
    "gn:feature_code":"PPL",
    "gn:name":"Khupi",
    "gn:population":0,
    "gn:timezone":"Asia/Dhaka",
    "iso:country":"BD",
    "wof:name":"Khupi",
    "wof:placetype":"locality"
},
  "geometry": {"coordinates":[90.67555,24.02155],"type":"Point"}
}