{
  "type": "Feature",
  "properties": {
    "gn:admin1_code":"81",
    "gn:admin2_code":"3033.0",
    "gn:admin3_code":"303334.0",
    "gn:admin4_code":"30333469.0",
    "gn:asciiname":"Chhatiani",
    "gn:country_code":"BD",
    "gn:dem":14,
    "gn:feature_class":"P",
    "gn:feature_code":"PPL",
    "gn:name":"Chh\u0101ti\u0101ni",
    "gn:population":0,
    "gn:timezone":"Asia/Dhaka",
    "iso:country":"BD",
    "wof:name":"Chhatiani",
    "wof:placetype":"locality"
},
  "geometry": {"coordinates":[90.52513999999999,23.99883],"type":"Point"}
}