{
  "type": "Feature",
  "properties": {
    "gn:admin1_code":"87",
    "gn:admin2_code":"5552.0",
    "gn:admin3_code":"555270.0",
    "gn:admin4_code":"55527019.0",
    "gn:asciiname":"Dahagram",
    "gn:country_code":"BD",
    "gn:dem":66,
    "gn:feature_class":"P",
    "gn:feature_code":"PPL",
    "gn:name":"Dah\u0101gr\u0101m",
    "gn:population":0,
    "gn:timezone":"Asia/Dhaka",
    "iso:country":"BD",
    "name:ben_x_preferred":[
        "Dah\u0101gr\u0101m"
    ],
    "wof:name":"Dahagram",
    "wof:placetype":"locality"
},
  "geometry": {"coordinates":[88.94735,26.3092],"type":"Point"}
}