{
  "type": "Feature",
  "properties": {
    "gn:admin1_code":"85",
    "gn:admin2_code":"1009.0",
    "gn:admin3_code":"100954.0",
    "gn:admin4_code":"10095476.0",
    "gn:asciiname":"Ramaganj",
    "gn:country_code":"BD",
    "gn:dem":7,
    "gn:feature_class":"P",
    "gn:feature_code":"PPL",
    "gn:name":"Ram\u0101ganj",
    "gn:population":0,
    "gn:timezone":"Asia/Dhaka",
    "iso:country":"BD",
    "name:ben_x_preferred":[
        "Ram\u0101ganj"
    ],
    "wof:name":"Ramaganj",
    "wof:placetype":"locality"
},
  "geometry": {"coordinates":[90.76007,22.27273],"type":"Point"}
}