{
  "type": "Feature",
  "properties": {
    "gn:admin1_code":"81",
    "gn:admin2_code":"3093",
    "gn:admin3_code":"309357.0",
    "gn:admin4_code":"30935728.0",
    "gn:asciiname":"Keutai",
    "gn:country_code":"BD",
    "gn:dem":19,
    "gn:feature_class":"P",
    "gn:feature_code":"PPL",
    "gn:name":"Keut\u0101i",
    "gn:population":0,
    "gn:timezone":"Asia/Dhaka",
    "iso:country":"BD",
    "wof:name":"Keutai",
    "wof:placetype":"locality"
},
  "geometry": {"coordinates":[90.07832000000001,24.58804],"type":"Point"}
}