{
  "type": "Feature",
  "properties": {
    "gn:admin1_code":"81",
    "gn:admin2_code":"3048.0",
    "gn:admin3_code":"304833.0",
    "gn:admin4_code":"30483317.0",
    "gn:asciiname":"Barsikura",
    "gn:country_code":"BD",
    "gn:dem":12,
    "gn:feature_class":"P",
    "gn:feature_code":"PPL",
    "gn:name":"Barsikura",
    "gn:population":0,
    "gn:timezone":"Asia/Dhaka",
    "iso:country":"BD",
    "wof:name":"Barsikura",
    "wof:placetype":"locality"
},
  "geometry": {"coordinates":[91.01409,24.56071],"type":"Point"}
}