{
  "type": "Feature",
  "properties": {
    "gn:admin1_code":"83",
    "gn:admin2_code":"5081.0",
    "gn:admin3_code":"508112.0",
    "gn:admin4_code":"50811218.0",
    "gn:asciiname":"Birkaya",
    "gn:country_code":"BD",
    "gn:dem":20,
    "gn:feature_class":"P",
    "gn:feature_code":"PPL",
    "gn:name":"Birkaya",
    "gn:population":0,
    "gn:timezone":"Asia/Dhaka",
    "iso:country":"BD",
    "name:ben_x_preferred":[
        "Birkaya"
    ],
    "wof:name":"Birkaya",
    "wof:placetype":"locality"
},
  "geometry": {"coordinates":[88.79734000000001,24.62685],"type":"Point"}
}