{
  "type": "Feature",
  "properties": {
    "gn:admin1_code":"84",
    "gn:admin2_code":"2022.0",
    "gn:admin3_code":"202290.0",
    "gn:admin4_code":"20229063.0",
    "gn:asciiname":"Godarbil",
    "gn:country_code":"BD",
    "gn:dem":11,
    "gn:feature_class":"P",
    "gn:feature_code":"PPL",
    "gn:name":"God\u0101rb\u012bl",
    "gn:population":0,
    "gn:timezone":"Asia/Dhaka",
    "iso:country":"BD",
    "name:ben_x_preferred":[
        "God\u0101rb\u012bl"
    ],
    "wof:name":"Godarbil",
    "wof:placetype":"locality"
},
  "geometry": {"coordinates":[92.28368,20.85865],"type":"Point"}
}