{
  "type": "Feature",
  "properties": {
    "gn:admin1_code":"85",
    "gn:admin2_code":"1004.0",
    "gn:admin3_code":"100485.0",
    "gn:admin4_code":"10048535.0",
    "gn:asciiname":"Dakshin Kupdon",
    "gn:country_code":"BD",
    "gn:dem":9,
    "gn:feature_class":"P",
    "gn:feature_code":"PPL",
    "gn:name":"Dakshin Kupdon",
    "gn:population":0,
    "gn:timezone":"Asia/Dhaka",
    "iso:country":"BD",
    "name:ben_x_preferred":[
        "Dakshin Kupdon"
    ],
    "wof:name":"Dakshin Kupdon",
    "wof:placetype":"locality"
},
  "geometry": {"coordinates":[90.00617,22.09881],"type":"Point"}
}