{
  "type": "Feature",
  "properties": {
    "gn:admin1_code":"82",
    "gn:admin2_code":"4044.0",
    "gn:admin3_code":"404480.0",
    "gn:admin4_code":"40448037.0",
    "gn:asciiname":"Hetampur",
    "gn:country_code":"BD",
    "gn:dem":14,
    "gn:feature_class":"P",
    "gn:feature_code":"PPL",
    "gn:name":"Hetampur",
    "gn:population":0,
    "gn:timezone":"Asia/Dhaka",
    "iso:country":"BD",
    "name:ben_x_preferred":[
        "\u09b9\u09c7\u09a4\u09ae\u09aa\u09c1\u09b0"
    ],
    "wof:name":"Hetampur",
    "wof:placetype":"locality"
},
  "geometry": {"coordinates":[89.26347,23.67757000000001],"type":"Point"}
}