{
  "type": "Feature",
  "properties": {
    "gn:admin1_code":"87",
    "gn:admin2_code":"5527.0",
    "gn:admin3_code":"552710.0",
    "gn:admin4_code":"55271047.0",
    "gn:asciiname":"Lohagaria",
    "gn:country_code":"BD",
    "gn:dem":33,
    "gn:feature_class":"P",
    "gn:feature_code":"PPL",
    "gn:name":"Loh\u0101garia",
    "gn:population":0,
    "gn:timezone":"Asia/Dhaka",
    "iso:country":"BD",
    "name:ben_x_preferred":[
        "Loh\u0101garia"
    ],
    "wof:name":"Lohagaria",
    "wof:placetype":"locality"
},
  "geometry": {"coordinates":[88.9211,25.35885],"type":"Point"}
}