{
  "type": "Feature",
  "properties": {
    "gn:admin1_code":"83",
    "gn:asciiname":"Simulbaria",
    "gn:country_code":"BD",
    "gn:dem":21,
    "gn:feature_class":"P",
    "gn:feature_code":"PPL",
    "gn:name":"Simulb\u0101ria",
    "gn:population":0,
    "gn:timezone":"Asia/Dhaka",
    "iso:country":"BD",
    "name:ben_x_preferred":[
        "Simulb\u0101ria"
    ],
    "wof:name":"Simulbaria",
    "wof:placetype":"locality"
},
  "geometry": {"coordinates":[89.52731999999997,25.05384],"type":"Point"}
}