{
  "type": "Feature",
  "properties": {
    "gn:admin1_code":"82",
    "gn:admin2_code":"4041.0",
    "gn:admin3_code":"404109.0",
    "gn:admin4_code":"40410919.0",
    "gn:asciiname":"Nimta",
    "gn:country_code":"BD",
    "gn:dem":14,
    "gn:feature_class":"P",
    "gn:feature_code":"PPL",
    "gn:name":"Nimta",
    "gn:population":0,
    "gn:timezone":"Asia/Dhaka",
    "iso:country":"BD",
    "name:ben_x_preferred":[
        "Nimta"
    ],
    "wof:name":"Nimta",
    "wof:placetype":"locality"
},
  "geometry": {"coordinates":[89.28375,23.30738],"type":"Point"}
}