{
  "type": "Feature",
  "properties": {
    "gn:admin1_code":"84",
    "gn:admin2_code":"2003.0",
    "gn:admin3_code":"200373.0",
    "gn:admin4_code":"20037319.0",
    "gn:asciiname":"Arakajapara",
    "gn:country_code":"BD",
    "gn:dem":27,
    "gn:feature_class":"P",
    "gn:feature_code":"PPL",
    "gn:name":"Arakaj\u0101para",
    "gn:population":0,
    "gn:timezone":"Asia/Dhaka",
    "iso:country":"BD",
    "name:ben_x_preferred":[
        "Arakaj\u0101para"
    ],
    "wof:name":"Arakajapara",
    "wof:placetype":"locality"
},
  "geometry": {"coordinates":[92.11998,21.63761],"type":"Point"}
}