{
  "type": "Feature",
  "properties": {
    "gn:admin1_code":"81",
    "gn:admin2_code":"3093.0",
    "gn:admin3_code":"309357.0",
    "gn:admin4_code":"30935728.0",
    "gn:asciiname":"Gangahari",
    "gn:country_code":"BD",
    "gn:dem":16,
    "gn:feature_class":"P",
    "gn:feature_code":"PPL",
    "gn:name":"Gang\u0101hari",
    "gn:population":0,
    "gn:timezone":"Asia/Dhaka",
    "iso:country":"BD",
    "name:und_x_variant":[
        "Gangabari",
        "Gang\u0101hari"
    ],
    "wof:name":"Gangahari",
    "wof:placetype":"locality"
},
  "geometry": {"coordinates":[90.06313,24.59281],"type":"Point"}
}