{
  "type": "Feature",
  "properties": {
    "gn:admin1_code":"82",
    "gn:asciiname":"Chandra",
    "gn:country_code":"BD",
    "gn:dem":10,
    "gn:feature_class":"P",
    "gn:feature_code":"PPL",
    "gn:name":"Chandra",
    "gn:population":0,
    "gn:timezone":"Asia/Dhaka",
    "iso:country":"BD",
    "name:ben_x_preferred":[
        "Chandra"
    ],
    "wof:name":"Chandra",
    "wof:placetype":"locality"
},
  "geometry": {"coordinates":[90.24894999999999,22.14629],"type":"Point"}
}