{
  "type": "Feature",
  "properties": {
    "gn:admin1_code":"81",
    "gn:admin2_code":"3026",
    "gn:admin3_code":"302618.0",
    "gn:admin4_code":"30261842.0",
    "gn:asciiname":"Maitpara",
    "gn:country_code":"BD",
    "gn:dem":13,
    "gn:feature_class":"P",
    "gn:feature_code":"PPL",
    "gn:name":"M\u0101itp\u0101ra",
    "gn:population":0,
    "gn:timezone":"Asia/Dhaka",
    "iso:country":"BD",
    "wof:name":"Maitpara",
    "wof:placetype":"locality"
},
  "geometry": {"coordinates":[90.17565999999999,23.55954],"type":"Point"}
}