{
  "type": "Feature",
  "properties": {
    "gn:admin1_code":"82",
    "gn:admin2_code":"4018.0",
    "gn:admin3_code":"401831.0",
    "gn:admin4_code":"40183111.0",
    "gn:asciiname":"Bhengula",
    "gn:country_code":"BD",
    "gn:dem":17,
    "gn:feature_class":"P",
    "gn:feature_code":"PPL",
    "gn:name":"Bhengula",
    "gn:population":0,
    "gn:timezone":"Asia/Dhaka",
    "iso:country":"BD",
    "name:ben_x_preferred":[
        "Bhengula"
    ],
    "wof:name":"Bhengula",
    "wof:placetype":"locality"
},
  "geometry": {"coordinates":[88.81192,23.62817],"type":"Point"}
}