{
  "type": "Feature",
  "properties": {
    "gn:admin1_code":"87",
    "gn:admin2_code":"5577.0",
    "gn:admin3_code":"557734.0",
    "gn:admin4_code":"55773409.0",
    "gn:asciiname":"Hazradanga",
    "gn:country_code":"BD",
    "gn:dem":56,
    "gn:feature_class":"P",
    "gn:feature_code":"PPL",
    "gn:name":"H\u0101zrad\u0101nga",
    "gn:population":0,
    "gn:timezone":"Asia/Dhaka",
    "iso:country":"BD",
    "name:ben_x_preferred":[
        "H\u0101zrad\u0101nga"
    ],
    "wof:name":"Hazradanga",
    "wof:placetype":"locality"
},
  "geometry": {"coordinates":[88.66653000000002,26.05553],"type":"Point"}
}