{
  "type": "Feature",
  "properties": {
    "gn:admin1_code":"85",
    "gn:admin2_code":"1042.0",
    "gn:admin3_code":"104240.0",
    "gn:admin4_code":"10424019.0",
    "gn:asciiname":"Asiar",
    "gn:country_code":"BD",
    "gn:dem":9,
    "gn:feature_class":"P",
    "gn:feature_code":"PPL",
    "gn:name":"Asiar",
    "gn:population":0,
    "gn:timezone":"Asia/Dhaka",
    "iso:country":"BD",
    "wof:name":"Asiar",
    "wof:placetype":"locality"
},
  "geometry": {"coordinates":[90.24003,22.74477000000001],"type":"Point"}
}