{
  "type": "Feature",
  "properties": {
    "gn:admin1_code":"85",
    "gn:admin2_code":"1006.0",
    "gn:admin3_code":"100610.0",
    "gn:admin4_code":"10061073.0",
    "gn:asciiname":"Harta",
    "gn:country_code":"BD",
    "gn:dem":8,
    "gn:feature_class":"P",
    "gn:feature_code":"PPL",
    "gn:name":"H\u0101rta",
    "gn:population":0,
    "gn:timezone":"Asia/Dhaka",
    "iso:country":"BD",
    "name:ceb_x_preferred":[
        "Harta"
    ],
    "name:ces_x_preferred":[
        "Harta"
    ],
    "name:deu_x_preferred":[
        "Harta"
    ],
    "name:fra_x_preferred":[
        "Harta"
    ],
    "name:hun_x_preferred":[
        "Harta"
    ],
    "name:ita_x_preferred":[
        "Harta"
    ],
    "name:nld_x_preferred":[
        "Harta"
    ],
    "name:swe_x_preferred":[
        "Harta"
    ],
    "wof:name":"Harta",
    "wof:placetype":"locality"
},
  "geometry": {"coordinates":[90.13075000000001,22.85166],"type":"Point"}
}