{
  "type": "Feature",
  "properties": {
    "gn:admin1_code":"81",
    "gn:admin2_code":"3093",
    "gn:admin3_code":"309328.0",
    "gn:admin4_code":"30932817.0",
    "gn:asciiname":"Ramjibanpur",
    "gn:country_code":"BD",
    "gn:dem":18,
    "gn:feature_class":"P",
    "gn:feature_code":"PPL",
    "gn:name":"R\u0101mjibanpur",
    "gn:population":0,
    "gn:timezone":"Asia/Dhaka",
    "iso:country":"BD",
    "wof:name":"Ramjibanpur",
    "wof:placetype":"locality"
},
  "geometry": {"coordinates":[89.97575999999999,24.53082],"type":"Point"}
}