{
  "type": "Feature",
  "properties": {
    "gn:admin1_code":"83",
    "gn:admin2_code":"5010",
    "gn:admin3_code":"501027.0",
    "gn:admin4_code":"50102785.0",
    "gn:asciiname":"Mathurapur",
    "gn:country_code":"BD",
    "gn:dem":18,
    "gn:feature_class":"P",
    "gn:feature_code":"PPL",
    "gn:name":"Mathur\u0101pur",
    "gn:population":0,
    "gn:timezone":"Asia/Dhaka",
    "iso:country":"BD",
    "wof:name":"Mathurapur",
    "wof:placetype":"locality"
},
  "geometry": {"coordinates":[89.54899999999998,24.59919],"type":"Point"}
}