{
  "type": "Feature",
  "properties": {
    "gn:admin1_code":"81",
    "gn:admin2_code":"3093",
    "gn:admin3_code":"309357.0",
    "gn:admin4_code":"30935766.0",
    "gn:asciiname":"Konabari",
    "gn:country_code":"BD",
    "gn:dem":20,
    "gn:feature_class":"P",
    "gn:feature_code":"PPL",
    "gn:name":"Kon\u0101b\u0101ri",
    "gn:population":0,
    "gn:timezone":"Asia/Dhaka",
    "iso:country":"BD",
    "wof:name":"Konabari",
    "wof:placetype":"locality"
},
  "geometry": {"coordinates":[89.99661999999999,24.60652],"type":"Point"}
}