{
  "type": "Feature",
  "properties": {
    "gn:admin1_code":"83",
    "gn:admin2_code":"5070",
    "gn:admin3_code":"507066.0",
    "gn:admin4_code":"50706644.0",
    "gn:asciiname":"Jamtara",
    "gn:country_code":"BD",
    "gn:dem":33,
    "gn:feature_class":"P",
    "gn:feature_code":"PPL",
    "gn:name":"Jamtara",
    "gn:population":0,
    "gn:timezone":"Asia/Dhaka",
    "iso:country":"BD",
    "name:ben_x_preferred":[
        "Jamtara"
    ],
    "wof:name":"Jamtara",
    "wof:placetype":"locality"
},
  "geometry": {"coordinates":[88.34929,24.6308],"type":"Point"}
}