{
  "type": "Feature",
  "properties": {
    "gn:admin1_code":"83",
    "gn:admin2_code":"5070",
    "gn:admin3_code":"507066.0",
    "gn:admin4_code":"50706644.0",
    "gn:asciiname":"Jamtara",
    "gn:country_code":"BD",
    "gn:dem":33,
    "gn:feature_class":"P",
    "gn:feature_code":"PPL",
    "gn:name":"Jamtara",
    "gn:population":0,
    "gn:timezone":"Asia/Dhaka",
    "iso:country":"BD",
    "name:ben_x_preferred":[
        "Jamtara"
    ],
    "name:ben_x_variant":[
        "\u099c\u09be\u09ae\u09a4\u09be\u09a1\u09bc\u09be"
    ],
    "name:bih_x_preferred":[
        "\u091c\u093e\u092e\u0924\u093e\u0921\u093c\u093e"
    ],
    "name:bpy_x_preferred":[
        "\u099c\u09be\u09ae\u09a4\u09be\u09b0\u09be"
    ],
    "name:ceb_x_preferred":[
        "J\u0101mt\u0101ra"
    ],
    "name:fra_x_preferred":[
        "Jamtara"
    ],
    "name:hin_x_preferred":[
        "\u091c\u093e\u092e\u0924\u093e\u0921\u093c\u093e"
    ],
    "name:ita_x_preferred":[
        "Jamtara"
    ],
    "name:mlg_x_preferred":[
        "Jamtara"
    ],
    "name:msa_x_preferred":[
        "Jamtara"
    ],
    "name:new_x_preferred":[
        "\u091c\u092e\u094d\u0924\u093e\u0930\u093e"
    ],
    "name:nld_x_preferred":[
        "Jamtara"
    ],
    "name:rus_x_preferred":[
        "\u0414\u0436\u0430\u043c\u0442\u0430\u0440\u0430"
    ],
    "name:san_x_preferred":[
        "\u091c\u093e\u092e\u0924\u093e\u0921\u093c\u093e"
    ],
    "name:spa_x_preferred":[
        "Jamtara"
    ],
    "name:swe_x_preferred":[
        "Jamtara"
    ],
    "name:urd_x_preferred":[
        "\u062c\u0645\u062a\u0627\u0631\u0627"
    ],
    "name:vie_x_preferred":[
        "Jamtara"
    ],
    "name:zho_x_preferred":[
        "\u8d3e\u59c6\u5854\u62c9"
    ],
    "wof:name":"Jamtara",
    "wof:placetype":"locality"
},
  "geometry": {"coordinates":[88.34929,24.6308],"type":"Point"}
}