{
  "type": "Feature",
  "properties": {
    "gn:admin1_code":"87",
    "gn:admin2_code":"5527.0",
    "gn:admin3_code":"552730.0",
    "gn:admin4_code":"55273039.0",
    "gn:asciiname":"Jaypur",
    "gn:country_code":"BD",
    "gn:dem":38,
    "gn:feature_class":"P",
    "gn:feature_code":"PPL",
    "gn:name":"Jaypur",
    "gn:population":0,
    "gn:timezone":"Asia/Dhaka",
    "iso:country":"BD",
    "name:ben_x_preferred":[
        "Jaypur"
    ],
    "wof:name":"Jaypur",
    "wof:placetype":"locality"
},
  "geometry": {"coordinates":[88.77814000000002,25.59975],"type":"Point"}
}