{
  "type": "Feature",
  "properties": {
    "gn:admin1_code":"81",
    "gn:admin2_code":"3029.0",
    "gn:admin3_code":"302956.0",
    "gn:admin4_code":"30295631.0",
    "gn:asciiname":"Dhopaganti",
    "gn:country_code":"BD",
    "gn:dem":14,
    "gn:feature_class":"P",
    "gn:feature_code":"PPL",
    "gn:name":"Dhop\u0101g\u0101nti",
    "gn:population":0,
    "gn:timezone":"Asia/Dhaka",
    "iso:country":"BD",
    "name:und_x_variant":[
        "Dhopagati",
        "Dhop\u0101g\u0101nti"
    ],
    "wof:name":"Dhopaganti",
    "wof:placetype":"locality"
},
  "geometry": {"coordinates":[89.65813,23.57399],"type":"Point"}
}