{
  "type": "Feature",
  "properties": {
    "gn:admin1_code":"85",
    "gn:admin2_code":"1004.0",
    "gn:admin3_code":"100409.0",
    "gn:admin4_code":"10040939.0",
    "gn:asciiname":"Bhaijora",
    "gn:country_code":"BD",
    "gn:dem":9,
    "gn:feature_class":"P",
    "gn:feature_code":"PPL",
    "gn:name":"Bh\u0101ijora",
    "gn:population":0,
    "gn:timezone":"Asia/Dhaka",
    "iso:country":"BD",
    "name:ben_x_preferred":[
        "Bh\u0101ijora"
    ],
    "wof:name":"Bhaijora",
    "wof:placetype":"locality"
},
  "geometry": {"coordinates":[90.12002,21.97164],"type":"Point"}
}