{
  "type": "Feature",
  "properties": {
    "gn:admin1_code":"81",
    "gn:admin2_code":"3029",
    "gn:admin3_code":"302910.0",
    "gn:admin4_code":"30291063.0",
    "gn:asciiname":"Paranpur",
    "gn:country_code":"BD",
    "gn:dem":14,
    "gn:feature_class":"P",
    "gn:feature_code":"PPL",
    "gn:name":"Par\u0101npur",
    "gn:population":0,
    "gn:timezone":"Asia/Dhaka",
    "iso:country":"BD",
    "name:und_x_variant":[
        "Poranpur",
        "Par\u0101npur"
    ],
    "wof:name":"Paranpur",
    "wof:placetype":"locality"
},
  "geometry": {"coordinates":[90.03561999999999,23.44844],"type":"Point"}
}