{
  "type": "Feature",
  "properties": {
    "gn:admin1_code":"87",
    "gn:admin2_code":"5573.0",
    "gn:admin3_code":"557336.0",
    "gn:admin4_code":"55733636.0",
    "gn:asciiname":"Rashidpur",
    "gn:country_code":"BD",
    "gn:dem":54,
    "gn:feature_class":"P",
    "gn:feature_code":"PPL",
    "gn:name":"Rashidpur",
    "gn:population":0,
    "gn:timezone":"Asia/Dhaka",
    "iso:country":"BD",
    "name:ben_x_preferred":[
        "Rashidpur"
    ],
    "wof:name":"Rashidpur",
    "wof:placetype":"locality"
},
  "geometry": {"coordinates":[88.94065000000001,26.06693],"type":"Point"}
}