{
  "type": "Feature",
  "properties": {
    "gn:admin1_code":"83",
    "gn:admin2_code":"5064.0",
    "gn:admin3_code":"506428.0",
    "gn:admin4_code":"50642831.0",
    "gn:asciiname":"Chak Bhabani",
    "gn:country_code":"BD",
    "gn:dem":25,
    "gn:feature_class":"P",
    "gn:feature_code":"PPL",
    "gn:name":"Chak Bhab\u0101ni",
    "gn:population":0,
    "gn:timezone":"Asia/Dhaka",
    "iso:country":"BD",
    "name:ben_x_preferred":[
        "Chak Bhab\u0101ni"
    ],
    "wof:name":"Chak Bhabani",
    "wof:placetype":"locality"
},
  "geometry": {"coordinates":[88.83041999999998,25.10127],"type":"Point"}
}