{
  "type": "Feature",
  "properties": {
    "gn:admin1_code":"82",
    "gn:admin2_code":"4050.0",
    "gn:admin3_code":"405039.0",
    "gn:admin4_code":"40503947.0",
    "gn:asciiname":"Maubria",
    "gn:country_code":"BD",
    "gn:dem":19,
    "gn:feature_class":"P",
    "gn:feature_code":"PPL",
    "gn:name":"Maubria",
    "gn:population":0,
    "gn:timezone":"Asia/Dhaka",
    "iso:country":"BD",
    "name:ben_x_preferred":[
        "Maubria"
    ],
    "wof:name":"Maubria",
    "wof:placetype":"locality"
},
  "geometry": {"coordinates":[88.87505999999998,23.91711],"type":"Point"}
}