{
  "type": "Feature",
  "properties": {
    "gn:admin1_code":"84",
    "gn:admin2_code":"2015.0",
    "gn:admin3_code":"201504.0",
    "gn:admin4_code":"20150476.0",
    "gn:asciiname":"Pirkhain",
    "gn:country_code":"BD",
    "gn:dem":9,
    "gn:feature_class":"P",
    "gn:feature_code":"PPL",
    "gn:name":"Pirkh\u0101in",
    "gn:population":0,
    "gn:timezone":"Asia/Dhaka",
    "iso:country":"BD",
    "name:ben_x_preferred":[
        "Pirkh\u0101in"
    ],
    "wof:name":"Pirkhain",
    "wof:placetype":"locality"
},
  "geometry": {"coordinates":[91.94768999999999,22.19675],"type":"Point"}
}