{
  "type": "Feature",
  "properties": {
    "gn:admin1_code":"84",
    "gn:admin2_code":"2015.0",
    "gn:admin3_code":"201582.0",
    "gn:admin4_code":"20158276.0",
    "gn:asciiname":"Baitarani",
    "gn:country_code":"BD",
    "gn:dem":15,
    "gn:feature_class":"P",
    "gn:feature_code":"PPL",
    "gn:name":"Baitar\u0101ni",
    "gn:population":0,
    "gn:timezone":"Asia/Dhaka",
    "iso:country":"BD",
    "name:ben_x_preferred":[
        "Baitar\u0101ni"
    ],
    "wof:name":"Baitarani",
    "wof:placetype":"locality"
},
  "geometry": {"coordinates":[92.13890000000001,22.17625],"type":"Point"}
}