{
  "type": "Feature",
  "properties": {
    "gn:admin1_code":"85",
    "gn:admin2_code":"1009",
    "gn:admin3_code":"100954.0",
    "gn:admin4_code":"10095409.0",
    "gn:asciiname":"Titia",
    "gn:country_code":"BD",
    "gn:dem":8,
    "gn:feature_class":"P",
    "gn:feature_code":"PPL",
    "gn:name":"Titia",
    "gn:population":0,
    "gn:timezone":"Asia/Dhaka",
    "iso:country":"BD",
    "name:ben_x_preferred":[
        "Titia"
    ],
    "wof:name":"Titia",
    "wof:placetype":"locality"
},
  "geometry": {"coordinates":[90.70872,22.3757],"type":"Point"}
}