{
  "type": "Feature",
  "properties": {
    "gn:admin1_code":"84",
    "gn:admin2_code":"2013",
    "gn:admin3_code":"201395.0",
    "gn:admin4_code":"20139590.0",
    "gn:asciiname":"Narasinhapur",
    "gn:country_code":"BD",
    "gn:dem":13,
    "gn:feature_class":"P",
    "gn:feature_code":"PPL",
    "gn:name":"Narasinhapur",
    "gn:population":0,
    "gn:timezone":"Asia/Dhaka",
    "iso:country":"BD",
    "name:und_x_variant":[
        "Narasinghapur",
        "Narasinhapur"
    ],
    "wof:name":"Narasinhapur",
    "wof:placetype":"locality"
},
  "geometry": {"coordinates":[90.93962999999999,23.15316],"type":"Point"}
}