{
  "type": "Feature",
  "properties": {
    "gn:admin1_code":"81",
    "gn:admin2_code":"3029.0",
    "gn:admin3_code":"302956.0",
    "gn:admin4_code":"30295663.0",
    "gn:asciiname":"Bamandi",
    "gn:country_code":"BD",
    "gn:dem":12,
    "gn:feature_class":"P",
    "gn:feature_code":"PPL",
    "gn:name":"B\u0101mandi",
    "gn:population":0,
    "gn:timezone":"Asia/Dhaka",
    "iso:country":"BD",
    "name:und_x_variant":[
        "Bamundi",
        "B\u0101mandi"
    ],
    "wof:name":"Bamandi",
    "wof:placetype":"locality"
},
  "geometry": {"coordinates":[89.58963,23.57051],"type":"Point"}
}