{
  "type": "Feature",
  "properties": {
    "gn:admin1_code":"81",
    "gn:admin2_code":"3067",
    "gn:admin3_code":"306758.0",
    "gn:admin4_code":"30675831.0",
    "gn:asciiname":"Masdair",
    "gn:country_code":"BD",
    "gn:dem":12,
    "gn:feature_class":"P",
    "gn:feature_code":"PPL",
    "gn:name":"M\u0101sd\u0101ir",
    "gn:population":0,
    "gn:timezone":"Asia/Dhaka",
    "iso:country":"BD",
    "wof:name":"Masdair",
    "wof:placetype":"locality"
},
  "geometry": {"coordinates":[90.48905999999999,23.62543],"type":"Point"}
}