{
  "type": "Feature",
  "properties": {
    "gn:admin1_code":"82",
    "gn:asciiname":"Kapulabania",
    "gn:country_code":"BD",
    "gn:dem":9,
    "gn:feature_class":"P",
    "gn:feature_code":"PPL",
    "gn:name":"K\u0101pul\u0101bania",
    "gn:population":0,
    "gn:timezone":"Asia/Dhaka",
    "iso:country":"BD",
    "name:ben_x_preferred":[
        "K\u0101pul\u0101bania"
    ],
    "wof:name":"Kapulabania",
    "wof:placetype":"locality"
},
  "geometry": {"coordinates":[90.36415,22.38777],"type":"Point"}
}