{
  "type": "Feature",
  "properties": {
    "gn:admin1_code":"81",
    "gn:admin2_code":"3054",
    "gn:admin3_code":"305454.0",
    "gn:admin4_code":"30545429.0",
    "gn:asciiname":"Thantali",
    "gn:country_code":"BD",
    "gn:dem":10,
    "gn:feature_class":"P",
    "gn:feature_code":"PPL",
    "gn:name":"Th\u0101ntali",
    "gn:population":0,
    "gn:timezone":"Asia/Dhaka",
    "iso:country":"BD",
    "wof:name":"Thantali",
    "wof:placetype":"locality"
},
  "geometry": {"coordinates":[90.18333,23.16667],"type":"Point"}
}