{
  "type": "Feature",
  "properties": {
    "gn:admin1_code":"87",
    "gn:admin2_code":"5527.0",
    "gn:admin3_code":"552710.0",
    "gn:admin4_code":"55271011.0",
    "gn:asciiname":"Ayra",
    "gn:country_code":"BD",
    "gn:dem":28,
    "gn:feature_class":"P",
    "gn:feature_code":"PPL",
    "gn:name":"\u0100yra",
    "gn:population":0,
    "gn:timezone":"Asia/Dhaka",
    "iso:country":"BD",
    "name:ben_x_preferred":[
        "\u0100yra"
    ],
    "wof:name":"Ayra",
    "wof:placetype":"locality"
},
  "geometry": {"coordinates":[88.88445,25.3567],"type":"Point"}
}