{
  "type": "Feature",
  "properties": {
    "gn:admin1_code":"87",
    "gn:admin2_code":"5577.0",
    "gn:admin3_code":"557773.0",
    "gn:admin4_code":"55777383.0",
    "gn:asciiname":"Chekarmari",
    "gn:country_code":"BD",
    "gn:dem":82,
    "gn:feature_class":"P",
    "gn:feature_code":"PPL",
    "gn:name":"Chekarm\u0101ri",
    "gn:population":0,
    "gn:timezone":"Asia/Dhaka",
    "iso:country":"BD",
    "name:ben_x_preferred":[
        "Chekarm\u0101ri"
    ],
    "wof:name":"Chekarmari",
    "wof:placetype":"locality"
},
  "geometry": {"coordinates":[88.55056,26.44872],"type":"Point"}
}