{
  "type": "Feature",
  "properties": {
    "gn:admin1_code":"83",
    "gn:admin2_code":"5081.0",
    "gn:admin3_code":"508153.0",
    "gn:admin4_code":"50815313.0",
    "gn:asciiname":"Saipara",
    "gn:country_code":"BD",
    "gn:dem":21,
    "gn:feature_class":"P",
    "gn:feature_code":"PPL",
    "gn:name":"Saip\u0101ra",
    "gn:population":0,
    "gn:timezone":"Asia/Dhaka",
    "iso:country":"BD",
    "name:ben_x_preferred":[
        "Saip\u0101ra"
    ],
    "wof:name":"Saipara",
    "wof:placetype":"locality"
},
  "geometry": {"coordinates":[88.65016,24.56161],"type":"Point"}
}