{
  "type": "Feature",
  "properties": {
    "gn:admin1_code":"87",
    "gn:admin2_code":"5527.0",
    "gn:admin3_code":"552747.0",
    "gn:admin4_code":"55274781.0",
    "gn:asciiname":"Balarampur",
    "gn:country_code":"BD",
    "gn:dem":32,
    "gn:feature_class":"P",
    "gn:feature_code":"PPL",
    "gn:name":"Balar\u0101mpur",
    "gn:population":0,
    "gn:timezone":"Asia/Dhaka",
    "iso:country":"BD",
    "name:ben_x_preferred":[
        "Balar\u0101mpur"
    ],
    "wof:name":"Balarampur",
    "wof:placetype":"locality"
},
  "geometry": {"coordinates":[88.98255999999998,25.33562],"type":"Point"}
}