{
  "type": "Feature",
  "properties": {
    "gn:admin1_code":"87",
    "gn:admin2_code":"5527.0",
    "gn:admin3_code":"552721.0",
    "gn:admin4_code":"55272154.0",
    "gn:asciiname":"Karai",
    "gn:country_code":"BD",
    "gn:dem":44,
    "gn:feature_class":"P",
    "gn:feature_code":"PPL",
    "gn:name":"Kar\u0101i",
    "gn:population":0,
    "gn:timezone":"Asia/Dhaka",
    "iso:country":"BD",
    "name:ben_x_preferred":[
        "Kar\u0101i"
    ],
    "name:ceb_x_preferred":[
        "Karai"
    ],
    "name:deu_x_preferred":[
        "Karai"
    ],
    "name:fra_x_preferred":[
        "Karai"
    ],
    "wof:name":"Karai",
    "wof:placetype":"locality"
},
  "geometry": {"coordinates":[88.44311999999999,25.80409],"type":"Point"}
}