{
  "type": "Feature",
  "properties": {
    "gn:admin1_code":"85",
    "gn:admin2_code":"1042.0",
    "gn:admin3_code":"104243.0",
    "gn:admin4_code":"10424394.0",
    "gn:asciiname":"Khaserhat",
    "gn:country_code":"BD",
    "gn:dem":8,
    "gn:feature_class":"P",
    "gn:feature_code":"PPL",
    "gn:name":"Kh\u0101serh\u0101t",
    "gn:population":0,
    "gn:timezone":"Asia/Dhaka",
    "iso:country":"BD",
    "name:ben_x_preferred":[
        "Kh\u0101serh\u0101t"
    ],
    "wof:name":"Khaserhat",
    "wof:placetype":"locality"
},
  "geometry": {"coordinates":[90.15366,22.46699],"type":"Point"}
}