{
  "type": "Feature",
  "properties": {
    "gn:admin1_code":"86",
    "gn:admin2_code":"6091",
    "gn:admin3_code":"609135.0",
    "gn:admin4_code":"60913571.0",
    "gn:asciiname":"Majgram",
    "gn:country_code":"BD",
    "gn:dem":27,
    "gn:feature_class":"P",
    "gn:feature_code":"PPL",
    "gn:name":"M\u0101jgr\u0101m",
    "gn:population":0,
    "gn:timezone":"Asia/Dhaka",
    "iso:country":"BD",
    "name:und_x_variant":[
        "Maijgaon",
        "Maiglaon",
        "Maijoan",
        "M\u0101jgr\u0101m"
    ],
    "wof:name":"Majgram",
    "wof:placetype":"locality"
},
  "geometry": {"coordinates":[91.94901,24.68646],"type":"Point"}
}