{
  "type": "Feature",
  "properties": {
    "gn:admin1_code":"83",
    "gn:admin2_code":"5064",
    "gn:admin3_code":"506475.0",
    "gn:admin4_code":"50647551.0",
    "gn:asciiname":"Parbatipur",
    "gn:country_code":"BD",
    "gn:dem":23,
    "gn:feature_class":"P",
    "gn:feature_code":"PPL",
    "gn:name":"P\u0101rbatipur",
    "gn:population":0,
    "gn:timezone":"Asia/Dhaka",
    "iso:country":"BD",
    "name:ben_x_preferred":[
        "P\u0101rbatipur"
    ],
    "name:ceb_x_preferred":[
        "Parbatipur"
    ],
    "name:swe_x_preferred":[
        "Parbatipur"
    ],
    "wof:name":"Parbatipur",
    "wof:placetype":"locality"
},
  "geometry": {"coordinates":[88.64009,25.00618],"type":"Point"}
}