{
  "type": "Feature",
  "properties": {
    "gn:admin1_code":"81",
    "gn:admin2_code":"3067.0",
    "gn:admin3_code":"306704.0",
    "gn:admin4_code":"30670469.0",
    "gn:asciiname":"Bhatibanda",
    "gn:country_code":"BD",
    "gn:dem":8,
    "gn:feature_class":"P",
    "gn:feature_code":"PPL",
    "gn:name":"Bh\u0101tibanda",
    "gn:population":0,
    "gn:timezone":"Asia/Dhaka",
    "iso:country":"BD",
    "wof:name":"Bhatibanda",
    "wof:placetype":"locality"
},
  "geometry": {"coordinates":[90.6225,23.6418],"type":"Point"}
}