{
  "type": "Feature",
  "properties": {
    "gn:admin1_code":"85",
    "gn:admin2_code":"1004.0",
    "gn:admin3_code":"100485.0",
    "gn:admin4_code":"10048571.0",
    "gn:asciiname":"Char Latnimara",
    "gn:country_code":"BD",
    "gn:dem":11,
    "gn:feature_class":"P",
    "gn:feature_code":"PPL",
    "gn:name":"Char Latnim\u0101ra",
    "gn:population":0,
    "gn:timezone":"Asia/Dhaka",
    "iso:country":"BD",
    "name:ben_x_preferred":[
        "Char Latnim\u0101ra"
    ],
    "wof:name":"Char Latnimara",
    "wof:placetype":"locality"
},
  "geometry": {"coordinates":[89.95747,21.99048],"type":"Point"}
}