{
  "type": "Feature",
  "properties": {
    "gn:admin1_code":"83",
    "gn:admin2_code":"5081.0",
    "gn:admin3_code":"508172.0",
    "gn:admin4_code":"50817255.0",
    "gn:asciiname":"Batasmolla",
    "gn:country_code":"BD",
    "gn:dem":15,
    "gn:feature_class":"P",
    "gn:feature_code":"PPL",
    "gn:name":"B\u0101t\u0101smolla",
    "gn:population":0,
    "gn:timezone":"Asia/Dhaka",
    "iso:country":"BD",
    "wof:name":"Batasmolla",
    "wof:placetype":"locality"
},
  "geometry": {"coordinates":[88.55,24.43333],"type":"Point"}
}