{
  "type": "Feature",
  "properties": {
    "gn:admin1_code":"H",
    "gn:admin2_code":"3089",
    "gn:admin3_code":"308937.0",
    "gn:admin4_code":"30893760.0",
    "gn:asciiname":"Nunkhala Mat",
    "gn:country_code":"BD",
    "gn:dem":27,
    "gn:feature_class":"P",
    "gn:feature_code":"PPL",
    "gn:name":"Nunkhala Mat",
    "gn:population":0,
    "gn:timezone":"Asia/Dhaka",
    "iso:country":"BD",
    "name:ben_x_preferred":[
        "Nunkhala Mat"
    ],
    "wof:name":"Nunkhala Mat",
    "wof:placetype":"locality"
},
  "geometry": {"coordinates":[90.06562,25.19779],"type":"Point"}
}