{
  "type": "Feature",
  "properties": {
    "gn:admin1_code":"81",
    "gn:admin2_code":"3048.0",
    "gn:admin3_code":"304854.0",
    "gn:admin4_code":"30485483.0",
    "gn:asciiname":"Domrakanda",
    "gn:country_code":"BD",
    "gn:dem":14,
    "gn:feature_class":"P",
    "gn:feature_code":"PPL",
    "gn:name":"Domr\u0101k\u0101nda",
    "gn:population":0,
    "gn:timezone":"Asia/Dhaka",
    "iso:country":"BD",
    "wof:name":"Domrakanda",
    "wof:placetype":"locality"
},
  "geometry": {"coordinates":[90.87318,24.14199],"type":"Point"}
}