{
  "type": "Feature",
  "properties": {
    "gn:admin1_code":"87",
    "gn:admin2_code":"5527.0",
    "gn:admin3_code":"552738.0",
    "gn:admin4_code":"55273828.0",
    "gn:asciiname":"Nandigram",
    "gn:country_code":"BD",
    "gn:dem":33,
    "gn:feature_class":"P",
    "gn:feature_code":"PPL",
    "gn:name":"Nandigr\u0101m",
    "gn:population":0,
    "gn:timezone":"Asia/Dhaka",
    "iso:country":"BD",
    "name:ben_x_preferred":[
        "Nandigr\u0101m"
    ],
    "wof:name":"Nandigram",
    "wof:placetype":"locality"
},
  "geometry": {"coordinates":[88.88894999999999,25.41498],"type":"Point"}
}