{
  "type": "Feature",
  "properties": {
    "gn:admin1_code":"84",
    "gn:admin2_code":"2022",
    "gn:admin3_code":"202245.0",
    "gn:admin4_code":"20224567.0",
    "gn:asciiname":"Lemsikhali",
    "gn:country_code":"BD",
    "gn:dem":10,
    "gn:feature_class":"P",
    "gn:feature_code":"PPL",
    "gn:name":"Lems\u012bkh\u0101li",
    "gn:population":0,
    "gn:timezone":"Asia/Dhaka",
    "iso:country":"BD",
    "name:ben_x_preferred":[
        "Lems\u012bkh\u0101li"
    ],
    "wof:name":"Lemsikhali",
    "wof:placetype":"locality"
},
  "geometry": {"coordinates":[91.87188,21.85152],"type":"Point"}
}