{
  "type": "Feature",
  "properties": {
    "gn:admin1_code":"85",
    "gn:admin2_code":"1042.0",
    "gn:admin3_code":"104284.0",
    "gn:admin4_code":"10428427.0",
    "gn:asciiname":"Galua Durgapur",
    "gn:country_code":"BD",
    "gn:dem":12,
    "gn:feature_class":"P",
    "gn:feature_code":"PPL",
    "gn:name":"G\u0101lua Durg\u0101pur",
    "gn:population":0,
    "gn:timezone":"Asia/Dhaka",
    "iso:country":"BD",
    "wof:name":"Galua Durgapur",
    "wof:placetype":"locality"
},
  "geometry": {"coordinates":[90.09859,22.51918],"type":"Point"}
}