{
  "type": "Feature",
  "properties": {
    "gn:admin1_code":"81",
    "gn:admin2_code":"3048",
    "gn:admin3_code":"304892.0",
    "gn:admin4_code":"30489267.0",
    "gn:asciiname":"Sibpur",
    "gn:country_code":"BD",
    "gn:dem":14,
    "gn:feature_class":"P",
    "gn:feature_code":"PPL",
    "gn:name":"Sibpur",
    "gn:population":0,
    "gn:timezone":"Asia/Dhaka",
    "iso:country":"BD",
    "wof:name":"Sibpur",
    "wof:placetype":"locality"
},
  "geometry": {"coordinates":[90.84809,24.56573],"type":"Point"}
}