{
  "type": "Feature",
  "properties": {
    "gn:admin1_code":"83",
    "gn:admin2_code":"5064.0",
    "gn:admin3_code":"506475.0",
    "gn:admin4_code":"50647594.0",
    "gn:asciiname":"Hatakanda",
    "gn:country_code":"BD",
    "gn:dem":37,
    "gn:feature_class":"P",
    "gn:feature_code":"PPL",
    "gn:name":"Hat\u0101kanda",
    "gn:population":0,
    "gn:timezone":"Asia/Dhaka",
    "iso:country":"BD",
    "name:ben_x_preferred":[
        "Hat\u0101kanda"
    ],
    "wof:name":"Hatakanda",
    "wof:placetype":"locality"
},
  "geometry": {"coordinates":[88.65203000000002,25.15942],"type":"Point"}
}