{
  "type": "Feature",
  "properties": {
    "gn:admin1_code":"83",
    "gn:admin2_code":"5081",
    "gn:admin3_code":"508110.0",
    "gn:admin4_code":"50811079.0",
    "gn:asciiname":"Padampur",
    "gn:country_code":"BD",
    "gn:dem":16,
    "gn:feature_class":"P",
    "gn:feature_code":"PPL",
    "gn:name":"Padampur",
    "gn:population":0,
    "gn:timezone":"Asia/Dhaka",
    "iso:country":"BD",
    "wof:name":"Padampur",
    "wof:placetype":"locality"
},
  "geometry": {"coordinates":[88.81667,24.16667],"type":"Point"}
}