{
  "type": "Feature",
  "properties": {
    "gn:admin1_code":"84",
    "gn:admin2_code":"2019.0",
    "gn:admin3_code":"201954.0",
    "gn:admin4_code":"20195485.0",
    "gn:asciiname":"Chandi Char",
    "gn:country_code":"BD",
    "gn:dem":14,
    "gn:feature_class":"P",
    "gn:feature_code":"PPL",
    "gn:name":"Chandi Char",
    "gn:population":0,
    "gn:timezone":"Asia/Dhaka",
    "iso:country":"BD",
    "wof:name":"Chandi Char",
    "wof:placetype":"locality"
},
  "geometry": {"coordinates":[90.8505,23.67447],"type":"Point"}
}