{
  "type": "Feature",
  "properties": {
    "gn:admin1_code":"H",
    "gn:admin2_code":"3089",
    "gn:admin3_code":"308990.0",
    "gn:admin4_code":"30899086.0",
    "gn:asciiname":"Dayerpar",
    "gn:country_code":"BD",
    "gn:dem":24,
    "gn:feature_class":"P",
    "gn:feature_code":"PPL",
    "gn:name":"Dayerpar",
    "gn:population":0,
    "gn:timezone":"Asia/Dhaka",
    "iso:country":"BD",
    "wof:name":"Dayerpar",
    "wof:placetype":"locality"
},
  "geometry": {"coordinates":[89.92133000000003,25.13365],"type":"Point"}
}