{
  "type": "Feature",
  "properties": {
    "gn:admin1_code":"83",
    "gn:admin2_code":"5064",
    "gn:admin3_code":"506460.0",
    "gn:admin4_code":"50646058.0",
    "gn:asciiname":"Narchi",
    "gn:country_code":"BD",
    "gn:dem":18,
    "gn:feature_class":"P",
    "gn:feature_code":"PPL",
    "gn:name":"Narchi",
    "gn:population":0,
    "gn:timezone":"Asia/Dhaka",
    "iso:country":"BD",
    "name:ben_x_preferred":[
        "Narchi"
    ],
    "wof:name":"Narchi",
    "wof:placetype":"locality"
},
  "geometry": {"coordinates":[88.87688,24.83154],"type":"Point"}
}