{
  "type": "Feature",
  "properties": {
    "gn:admin1_code":"87",
    "gn:admin2_code":"5573.0",
    "gn:admin3_code":"557315.0",
    "gn:admin4_code":"55731528.0",
    "gn:asciiname":"Purba Boragari",
    "gn:country_code":"BD",
    "gn:dem":58,
    "gn:feature_class":"P",
    "gn:feature_code":"PPL",
    "gn:name":"Purba Borag\u0101ri",
    "gn:population":0,
    "gn:timezone":"Asia/Dhaka",
    "iso:country":"BD",
    "name:ben_x_preferred":[
        "Purba Borag\u0101ri"
    ],
    "wof:name":"Purba Boragari",
    "wof:placetype":"locality"
},
  "geometry": {"coordinates":[88.87687,26.13537],"type":"Point"}
}