{
  "type": "Feature",
  "properties": {
    "gn:admin1_code":"83",
    "gn:admin2_code":"5010",
    "gn:admin3_code":"501033.0",
    "gn:admin4_code":"50103381.0",
    "gn:asciiname":"Mahismunda",
    "gn:country_code":"BD",
    "gn:dem":27,
    "gn:feature_class":"P",
    "gn:feature_code":"PPL",
    "gn:name":"Mahismunda",
    "gn:population":0,
    "gn:timezone":"Asia/Dhaka",
    "iso:country":"BD",
    "name:und_x_variant":[
        "Mahishmunda",
        "Mahismunda"
    ],
    "wof:name":"Mahismunda",
    "wof:placetype":"locality"
},
  "geometry": {"coordinates":[89.10898,24.95926],"type":"Point"}
}