{
  "type": "Feature",
  "properties": {
    "gn:admin1_code":"81",
    "gn:admin2_code":"3048",
    "gn:admin3_code":"304849.0",
    "gn:admin4_code":"30484951.0",
    "gn:asciiname":"Kodalatia",
    "gn:country_code":"BD",
    "gn:dem":11,
    "gn:feature_class":"P",
    "gn:feature_code":"PPL",
    "gn:name":"Kod\u0101l\u0101tia",
    "gn:population":0,
    "gn:timezone":"Asia/Dhaka",
    "iso:country":"BD",
    "wof:name":"Kodalatia",
    "wof:placetype":"locality"
},
  "geometry": {"coordinates":[90.80661000000001,24.36691],"type":"Point"}
}