{
  "type": "Feature",
  "properties": {
    "gn:admin1_code":"83",
    "gn:admin2_code":"5081.0",
    "gn:admin3_code":"508185.0",
    "gn:admin4_code":"50818514.0",
    "gn:asciiname":"Rampur Boasla",
    "gn:country_code":"BD",
    "gn:dem":22,
    "gn:feature_class":"P",
    "gn:feature_code":"PPL",
    "gn:name":"Rampur Boasla",
    "gn:population":0,
    "gn:timezone":"Asia/Dhaka",
    "iso:country":"BD",
    "name:ben_x_preferred":[
        "Rampur Boasla"
    ],
    "wof:name":"Rampur Boasla",
    "wof:placetype":"locality"
},
  "geometry": {"coordinates":[88.59945,24.37934],"type":"Point"}
}