{
  "type": "Feature",
  "properties": {
    "gn:admin1_code":"81",
    "gn:admin2_code":"3033.0",
    "gn:admin3_code":"303336.0",
    "gn:admin4_code":"30333608.0",
    "gn:asciiname":"Chheldra",
    "gn:country_code":"BD",
    "gn:dem":17,
    "gn:feature_class":"P",
    "gn:feature_code":"PPL",
    "gn:name":"Chheldra",
    "gn:population":0,
    "gn:timezone":"Asia/Dhaka",
    "iso:country":"BD",
    "name:und_x_variant":[
        "Chheldia"
    ],
    "wof:name":"Chheldra",
    "wof:placetype":"locality"
},
  "geometry": {"coordinates":[90.65275,24.20616],"type":"Point"}
}