{
  "type": "Feature",
  "properties": {
    "gn:admin1_code":"83",
    "gn:asciiname":"Shibpur",
    "gn:country_code":"BD",
    "gn:dem":23,
    "gn:feature_class":"P",
    "gn:feature_code":"PPL",
    "gn:name":"Shibpur",
    "gn:population":0,
    "gn:timezone":"Asia/Dhaka",
    "iso:country":"BD",
    "name:ben_x_preferred":[
        "Shibpur"
    ],
    "wof:name":"Shibpur",
    "wof:placetype":"locality"
},
  "geometry": {"coordinates":[89.44504999999999,25.12806],"type":"Point"}
}