{
  "type": "Feature",
  "properties": {
    "gn:admin1_code":"81",
    "gn:admin2_code":"3048.0",
    "gn:admin3_code":"304892.0",
    "gn:admin4_code":"30489254.0",
    "gn:asciiname":"Chhanati",
    "gn:country_code":"BD",
    "gn:dem":13,
    "gn:feature_class":"P",
    "gn:feature_code":"PPL",
    "gn:name":"Chhan\u0101ti",
    "gn:population":0,
    "gn:timezone":"Asia/Dhaka",
    "iso:country":"BD",
    "wof:name":"Chhanati",
    "wof:placetype":"locality"
},
  "geometry": {"coordinates":[90.91305,24.57002],"type":"Point"}
}