{
  "type": "Feature",
  "properties": {
    "gn:admin1_code":"82",
    "gn:admin2_code":"4057.0",
    "gn:admin3_code":"405747.0",
    "gn:admin4_code":"40574784.0",
    "gn:asciiname":"Rauikandi",
    "gn:country_code":"BD",
    "gn:dem":20,
    "gn:feature_class":"P",
    "gn:feature_code":"PPL",
    "gn:name":"Rauikandi",
    "gn:population":0,
    "gn:timezone":"Asia/Dhaka",
    "iso:country":"BD",
    "name:ben_x_preferred":[
        "Rauikandi"
    ],
    "wof:name":"Rauikandi",
    "wof:placetype":"locality"
},
  "geometry": {"coordinates":[88.8348,23.83593],"type":"Point"}
}