{
  "type": "Feature",
  "properties": {
    "gn:admin1_code":"84",
    "gn:admin2_code":"2046.0",
    "gn:admin3_code":"204661.0",
    "gn:admin4_code":"20466123.0",
    "gn:asciiname":"Muktacharipara",
    "gn:country_code":"BD",
    "gn:dem":77,
    "gn:feature_class":"P",
    "gn:feature_code":"PPL",
    "gn:name":"Mukt\u0101charip\u0101ra",
    "gn:population":0,
    "gn:timezone":"Asia/Dhaka",
    "iso:country":"BD",
    "name:ben_x_preferred":[
        "Mukt\u0101charip\u0101ra"
    ],
    "wof:name":"Muktacharipara",
    "wof:placetype":"locality"
},
  "geometry": {"coordinates":[91.93928,22.72823],"type":"Point"}
}