{
  "type": "Feature",
  "properties": {
    "gn:admin1_code":"87",
    "gn:admin2_code":"5552",
    "gn:admin3_code":"555239.0",
    "gn:admin4_code":"55523995.0",
    "gn:asciiname":"Kanchanswar",
    "gn:country_code":"BD",
    "gn:dem":41,
    "gn:feature_class":"P",
    "gn:feature_code":"PPL",
    "gn:name":"K\u0101nchanswar",
    "gn:population":0,
    "gn:timezone":"Asia/Dhaka",
    "iso:country":"BD",
    "name:ben_x_preferred":[
        "K\u0101nchanswar"
    ],
    "wof:name":"Kanchanswar",
    "wof:placetype":"locality"
},
  "geometry": {"coordinates":[89.24356,25.93908],"type":"Point"}
}