{
  "type": "Feature",
  "properties": {
    "gn:admin1_code":"H",
    "gn:admin2_code":"3072",
    "gn:admin3_code":"307283.0",
    "gn:admin4_code":"30728331.0",
    "gn:asciiname":"Tikarampur",
    "gn:country_code":"BD",
    "gn:dem":12,
    "gn:feature_class":"P",
    "gn:feature_code":"PPL",
    "gn:name":"Tik\u0101r\u0101mpur",
    "gn:population":0,
    "gn:timezone":"Asia/Dhaka",
    "iso:country":"BD",
    "wof:name":"Tikarampur",
    "wof:placetype":"locality"
},
  "geometry": {"coordinates":[90.68114,24.93407],"type":"Point"}
}