{
  "type": "Feature",
  "properties": {
    "gn:admin1_code":"87",
    "gn:admin2_code":"5577.0",
    "gn:admin3_code":"557773.0",
    "gn:admin4_code":"55777335.0",
    "gn:asciiname":"Nidhipara",
    "gn:country_code":"BD",
    "gn:dem":77,
    "gn:feature_class":"P",
    "gn:feature_code":"PPL",
    "gn:name":"Nidh\u012bp\u0101ra",
    "gn:population":0,
    "gn:timezone":"Asia/Dhaka",
    "iso:country":"BD",
    "name:ben_x_preferred":[
        "Nidh\u012bp\u0101ra"
    ],
    "wof:name":"Nidhipara",
    "wof:placetype":"locality"
},
  "geometry": {"coordinates":[88.59926999999998,26.39454000000001],"type":"Point"}
}