{
  "type": "Feature",
  "properties": {
    "gn:admin1_code":"81",
    "gn:admin2_code":"3048.0",
    "gn:admin3_code":"304833.0",
    "gn:admin4_code":"30483394.0",
    "gn:asciiname":"Goara",
    "gn:country_code":"BD",
    "gn:dem":11,
    "gn:feature_class":"P",
    "gn:feature_code":"PPL",
    "gn:name":"Go\u0101ra",
    "gn:population":0,
    "gn:timezone":"Asia/Dhaka",
    "iso:country":"BD",
    "wof:name":"Goara",
    "wof:placetype":"locality"
},
  "geometry": {"coordinates":[90.97776,24.58623],"type":"Point"}
}