{
  "type": "Feature",
  "properties": {
    "gn:admin1_code":"87",
    "gn:admin2_code":"5585",
    "gn:admin3_code":"558576.0",
    "gn:admin4_code":"55857637.0",
    "gn:asciiname":"Jamirbari",
    "gn:country_code":"BD",
    "gn:dem":29,
    "gn:feature_class":"P",
    "gn:feature_code":"PPL",
    "gn:name":"Jamirbari",
    "gn:population":0,
    "gn:timezone":"Asia/Dhaka",
    "iso:country":"BD",
    "name:ben_x_preferred":[
        "Jamirbari"
    ],
    "wof:name":"Jamirbari",
    "wof:placetype":"locality"
},
  "geometry": {"coordinates":[89.30685,25.30987],"type":"Point"}
}