{
  "type": "Feature",
  "properties": {
    "gn:admin1_code":"H",
    "gn:admin2_code":"3072",
    "gn:admin3_code":"307274.0",
    "gn:admin4_code":"30727439.0",
    "gn:asciiname":"Purba Dahar",
    "gn:country_code":"BD",
    "gn:dem":14,
    "gn:feature_class":"P",
    "gn:feature_code":"PPL",
    "gn:name":"Purba Dahar",
    "gn:population":0,
    "gn:timezone":"Asia/Dhaka",
    "iso:country":"BD",
    "name:und_x_variant":[
        "J\u0101m\u0101ti Purbba Dahar"
    ],
    "wof:name":"Purba Dahar",
    "wof:placetype":"locality"
},
  "geometry": {"coordinates":[90.72338999999999,24.96509],"type":"Point"}
}