{
  "type": "Feature",
  "properties": {
    "gn:admin1_code":"84",
    "gn:admin2_code":"2015",
    "gn:admin3_code":"201586.0",
    "gn:admin4_code":"20158647.0",
    "gn:asciiname":"Kumira",
    "gn:country_code":"BD",
    "gn:dem":9,
    "gn:feature_class":"P",
    "gn:feature_code":"PPL",
    "gn:name":"Kum\u012bra",
    "gn:population":0,
    "gn:timezone":"Asia/Dhaka",
    "iso:country":"BD",
    "name:und_x_variant":[
        "Bara Kumira",
        "Kum\u012bra"
    ],
    "wof:name":"Kumira",
    "wof:placetype":"locality"
},
  "geometry": {"coordinates":[91.71057999999999,22.50382],"type":"Point"}
}