{
  "type": "Feature",
  "properties": {
    "gn:admin1_code":"81",
    "gn:admin2_code":"3068.0",
    "gn:admin3_code":"306864.0",
    "gn:admin4_code":"30686444.0",
    "gn:asciiname":"Hairmara",
    "gn:country_code":"BD",
    "gn:dem":8,
    "gn:feature_class":"P",
    "gn:feature_code":"PPL",
    "gn:name":"H\u0101irm\u0101ra",
    "gn:population":0,
    "gn:timezone":"Asia/Dhaka",
    "iso:country":"BD",
    "wof:name":"Hairmara",
    "wof:placetype":"locality"
},
  "geometry": {"coordinates":[90.81312,23.9279],"type":"Point"}
}