{
  "type": "Feature",
  "properties": {
    "gn:admin1_code":"82",
    "gn:admin2_code":"4041",
    "gn:admin3_code":"404109.0",
    "gn:admin4_code":"40410919.0",
    "gn:asciiname":"Mathurapur",
    "gn:country_code":"BD",
    "gn:dem":14,
    "gn:feature_class":"P",
    "gn:feature_code":"PPL",
    "gn:name":"Mathur\u0101pur",
    "gn:population":0,
    "gn:timezone":"Asia/Dhaka",
    "iso:country":"BD",
    "wof:name":"Mathurapur",
    "wof:placetype":"locality"
},
  "geometry": {"coordinates":[89.25905,23.28283],"type":"Point"}
}