{
  "type": "Feature",
  "properties": {
    "gn:admin1_code":"H",
    "gn:admin2_code":"3061.0",
    "gn:admin3_code":"306194.0",
    "gn:admin4_code":"30619476.0",
    "gn:asciiname":"Babupur",
    "gn:country_code":"BD",
    "gn:dem":14,
    "gn:feature_class":"P",
    "gn:feature_code":"PPL",
    "gn:name":"B\u0101bupur",
    "gn:population":0,
    "gn:timezone":"Asia/Dhaka",
    "iso:country":"BD",
    "wof:name":"Babupur",
    "wof:placetype":"locality"
},
  "geometry": {"coordinates":[90.46168,24.52731],"type":"Point"}
}