{
  "type": "Feature",
  "properties": {
    "gn:admin1_code":"85",
    "gn:admin2_code":"1078",
    "gn:admin3_code":"107866.0",
    "gn:admin4_code":"10786659.0",
    "gn:asciiname":"Baliatali",
    "gn:country_code":"BD",
    "gn:dem":7,
    "gn:feature_class":"P",
    "gn:feature_code":"PPL",
    "gn:name":"B\u0101li\u0101tali",
    "gn:population":0,
    "gn:timezone":"Asia/Dhaka",
    "iso:country":"BD",
    "name:ben_x_preferred":[
        "B\u0101li\u0101tali"
    ],
    "wof:name":"Baliatali",
    "wof:placetype":"locality"
},
  "geometry": {"coordinates":[90.27084000000001,21.94849],"type":"Point"}
}