{
  "type": "Feature",
  "properties": {
    "gn:admin1_code":"87",
    "gn:admin2_code":"5552",
    "gn:admin3_code":"555202.0",
    "gn:admin4_code":"55520283.0",
    "gn:asciiname":"Purba Daljure",
    "gn:country_code":"BD",
    "gn:dem":35,
    "gn:feature_class":"P",
    "gn:feature_code":"PPL",
    "gn:name":"Purba Daljure",
    "gn:population":0,
    "gn:timezone":"Asia/Dhaka",
    "iso:country":"BD",
    "name:ben_x_preferred":[
        "Purba Daljure"
    ],
    "wof:name":"Purba Daljure",
    "wof:placetype":"locality"
},
  "geometry": {"coordinates":[89.42976999999998,25.95127],"type":"Point"}
}