{
  "type": "Feature",
  "properties": {
    "gn:admin1_code":"84",
    "gn:admin2_code":"2013.0",
    "gn:admin3_code":"201395.0",
    "gn:admin4_code":"20139520.0",
    "gn:asciiname":"Bagan",
    "gn:country_code":"BD",
    "gn:dem":10,
    "gn:feature_class":"P",
    "gn:feature_code":"PPL",
    "gn:name":"B\u0101gan",
    "gn:population":0,
    "gn:timezone":"Asia/Dhaka",
    "iso:country":"BD",
    "name:und_x_variant":[
        "B\u0101gan",
        "B\u0101gair"
    ],
    "wof:name":"Bagan",
    "wof:placetype":"locality"
},
  "geometry": {"coordinates":[90.96711000000001,23.15174],"type":"Point"}
}