{
  "type": "Feature",
  "properties": {
    "gn:admin1_code":"85",
    "gn:admin2_code":"1006",
    "gn:admin3_code":"100669.0",
    "gn:admin4_code":"10066923.0",
    "gn:asciiname":"West Sholaghar",
    "gn:country_code":"BD",
    "gn:dem":11,
    "gn:feature_class":"P",
    "gn:feature_code":"PPL",
    "gn:name":"West Shol\u0101ghar",
    "gn:population":0,
    "gn:timezone":"Asia/Dhaka",
    "iso:country":"BD",
    "name:und_x_variant":[
        "West Schol\u0101ghar",
        "West Shol\u0101ghar"
    ],
    "wof:name":"West Sholaghar",
    "wof:placetype":"locality"
},
  "geometry": {"coordinates":[90.39612,22.99468],"type":"Point"}
}