{
  "type": "Feature",
  "properties": {
    "gn:admin1_code":"H",
    "gn:admin2_code":"3039",
    "gn:admin3_code":"303929.0",
    "gn:admin4_code":"30392923.0",
    "gn:asciiname":"Shibuttar",
    "gn:country_code":"BD",
    "gn:dem":25,
    "gn:feature_class":"P",
    "gn:feature_code":"PPL",
    "gn:name":"Shibuttar",
    "gn:population":0,
    "gn:timezone":"Asia/Dhaka",
    "iso:country":"BD",
    "name:ben_x_preferred":[
        "Shibuttar"
    ],
    "wof:name":"Shibuttar",
    "wof:placetype":"locality"
},
  "geometry": {"coordinates":[89.91305,25.05695],"type":"Point"}
}