{
  "type": "Feature",
  "properties": {
    "gn:admin1_code":"84",
    "gn:admin2_code":"2015.0",
    "gn:admin3_code":"201570.0",
    "gn:admin4_code":"20157060.0",
    "gn:asciiname":"Mahtir Kheel",
    "gn:country_code":"BD",
    "gn:dem":10,
    "gn:feature_class":"P",
    "gn:feature_code":"PPL",
    "gn:name":"Mahtir Kheel",
    "gn:population":0,
    "gn:timezone":"Asia/Dhaka",
    "iso:country":"BD",
    "name:ben_x_preferred":[
        "Mahtir Kheel"
    ],
    "wof:name":"Mahtir Kheel",
    "wof:placetype":"locality"
},
  "geometry": {"coordinates":[92.01785,22.45228],"type":"Point"}
}