{
  "type": "Feature",
  "properties": {
    "gn:admin1_code":"81",
    "gn:admin2_code":"3033.0",
    "gn:admin3_code":"303386.0",
    "gn:admin4_code":"30338628.0",
    "gn:asciiname":"Berabari",
    "gn:country_code":"BD",
    "gn:dem":15,
    "gn:feature_class":"P",
    "gn:feature_code":"PPL",
    "gn:name":"Ber\u0101b\u0101ri",
    "gn:population":0,
    "gn:timezone":"Asia/Dhaka",
    "iso:country":"BD",
    "wof:name":"Berabari",
    "wof:placetype":"locality"
},
  "geometry": {"coordinates":[90.51953,24.13473],"type":"Point"}
}