{
  "type": "Feature",
  "properties": {
    "gn:admin1_code":"85",
    "gn:admin2_code":"1004.0",
    "gn:admin3_code":"100447.0",
    "gn:admin4_code":"10044711.0",
    "gn:asciiname":"Jhopkhali",
    "gn:country_code":"BD",
    "gn:dem":8,
    "gn:feature_class":"P",
    "gn:feature_code":"PPL",
    "gn:name":"Jhopkh\u0101li",
    "gn:population":0,
    "gn:timezone":"Asia/Dhaka",
    "iso:country":"BD",
    "name:ben_x_preferred":[
        "Jhopkh\u0101li"
    ],
    "wof:name":"Jhopkhali",
    "wof:placetype":"locality"
},
  "geometry": {"coordinates":[90.17623,22.42482],"type":"Point"}
}