{
  "type": "Feature",
  "properties": {
    "gn:admin1_code":"H",
    "gn:admin2_code":"3061",
    "gn:admin3_code":"306131.0",
    "gn:admin4_code":"30613140.0",
    "gn:asciiname":"Naya Simul",
    "gn:country_code":"BD",
    "gn:dem":14,
    "gn:feature_class":"P",
    "gn:feature_code":"PPL",
    "gn:name":"N\u0101ya Simul",
    "gn:population":0,
    "gn:timezone":"Asia/Dhaka",
    "iso:country":"BD",
    "wof:name":"Naya Simul",
    "wof:placetype":"locality"
},
  "geometry": {"coordinates":[90.62103999999999,24.69468],"type":"Point"}
}