{
  "type": "Feature",
  "properties": {
    "gn:admin1_code":"81",
    "gn:admin2_code":"3067.0",
    "gn:admin3_code":"306768.0",
    "gn:admin4_code":"30676831.0",
    "gn:asciiname":"Duara",
    "gn:country_code":"BD",
    "gn:dem":12,
    "gn:feature_class":"P",
    "gn:feature_code":"PPL",
    "gn:name":"Du\u0101ra",
    "gn:population":0,
    "gn:timezone":"Asia/Dhaka",
    "iso:country":"BD",
    "wof:name":"Duara",
    "wof:placetype":"locality"
},
  "geometry": {"coordinates":[90.55969,23.87971],"type":"Point"}
}