{
  "type": "Feature",
  "properties": {
    "gn:admin1_code":"87",
    "gn:admin2_code":"5527",
    "gn:admin3_code":"552730.0",
    "gn:admin4_code":"55273039.0",
    "gn:asciiname":"Surail",
    "gn:country_code":"BD",
    "gn:dem":38,
    "gn:feature_class":"P",
    "gn:feature_code":"PPL",
    "gn:name":"Surail",
    "gn:population":0,
    "gn:timezone":"Asia/Dhaka",
    "iso:country":"BD",
    "wof:name":"Surail",
    "wof:placetype":"locality"
},
  "geometry": {"coordinates":[88.75504000000002,25.58281],"type":"Point"}
}