{
  "type": "Feature",
  "properties": {
    "gn:admin1_code":"83",
    "gn:admin2_code":"5081.0",
    "gn:admin3_code":"508194.0",
    "gn:admin4_code":"50819440.0",
    "gn:asciiname":"Kachua",
    "gn:country_code":"BD",
    "gn:dem":19,
    "gn:feature_class":"P",
    "gn:feature_code":"PPL",
    "gn:name":"Kachua",
    "gn:population":0,
    "gn:timezone":"Asia/Dhaka",
    "iso:country":"BD",
    "name:ben_x_preferred":[
        "Kachua"
    ],
    "wof:name":"Kachua",
    "wof:placetype":"locality"
},
  "geometry": {"coordinates":[88.61494999999999,24.61942],"type":"Point"}
}