{
  "type": "Feature",
  "properties": {
    "gn:admin1_code":"84",
    "gn:admin2_code":"2015.0",
    "gn:admin3_code":"201533.0",
    "gn:admin4_code":"20153319.0",
    "gn:asciiname":"Amtali",
    "gn:country_code":"BD",
    "gn:dem":14,
    "gn:feature_class":"P",
    "gn:feature_code":"PPL",
    "gn:name":"\u0100mtali",
    "gn:population":0,
    "gn:timezone":"Asia/Dhaka",
    "iso:country":"BD",
    "name:ben_x_preferred":[
        "\u0100mtali"
    ],
    "name:ceb_x_preferred":[
        "Amtali"
    ],
    "name:swe_x_preferred":[
        "Amtali"
    ],
    "wof:name":"Amtali",
    "wof:placetype":"locality"
},
  "geometry": {"coordinates":[91.75301,22.75043],"type":"Point"}
}