{
  "type": "Feature",
  "properties": {
    "gn:admin1_code":"81",
    "gn:admin2_code":"3029.0",
    "gn:admin3_code":"302947.0",
    "gn:admin4_code":"30294747.0",
    "gn:asciiname":"Chak Fatepur",
    "gn:country_code":"BD",
    "gn:dem":15,
    "gn:feature_class":"P",
    "gn:feature_code":"PPL",
    "gn:name":"Chak Fatepur",
    "gn:population":0,
    "gn:timezone":"Asia/Dhaka",
    "iso:country":"BD",
    "wof:name":"Chak Fatepur",
    "wof:placetype":"locality"
},
  "geometry": {"coordinates":[89.75804000000002,23.63897],"type":"Point"}
}