{
  "type": "Feature",
  "properties": {
    "gn:admin1_code":"87",
    "gn:admin2_code":"5552",
    "gn:admin3_code":"555255.0",
    "gn:admin4_code":"55525507.0",
    "gn:asciiname":"Budaru",
    "gn:country_code":"BD",
    "gn:dem":33,
    "gn:feature_class":"P",
    "gn:feature_code":"PPL",
    "gn:name":"Bud\u0101ru",
    "gn:population":0,
    "gn:timezone":"Asia/Dhaka",
    "iso:country":"BD",
    "name:ben_x_preferred":[
        "Bud\u0101ru"
    ],
    "wof:name":"Budaru",
    "wof:placetype":"locality"
},
  "geometry": {"coordinates":[89.55575999999998,25.88447],"type":"Point"}
}