{
  "type": "Feature",
  "properties": {
    "gn:admin1_code":"87",
    "gn:admin2_code":"5552.0",
    "gn:admin3_code":"555270.0",
    "gn:admin4_code":"55527067.0",
    "gn:asciiname":"Kuthali",
    "gn:country_code":"BD",
    "gn:dem":63,
    "gn:feature_class":"P",
    "gn:feature_code":"PPL",
    "gn:name":"Kuthali",
    "gn:population":0,
    "gn:timezone":"Asia/Dhaka",
    "iso:country":"BD",
    "name:ben_x_preferred":[
        "Kuthali"
    ],
    "wof:name":"Kuthali",
    "wof:placetype":"locality"
},
  "geometry": {"coordinates":[89.02259000000002,26.34724000000001],"type":"Point"}
}