{
  "type": "Feature",
  "properties": {
    "gn:admin1_code":"84",
    "gn:admin2_code":"2015.0",
    "gn:admin3_code":"201553.0",
    "gn:admin4_code":"20155317.0",
    "gn:asciiname":"Karuya",
    "gn:country_code":"BD",
    "gn:dem":8,
    "gn:feature_class":"P",
    "gn:feature_code":"PPL",
    "gn:name":"Karuya",
    "gn:population":0,
    "gn:timezone":"Asia/Dhaka",
    "iso:country":"BD",
    "wof:name":"Karuya",
    "wof:placetype":"locality"
},
  "geometry": {"coordinates":[91.59999999999999,22.68806],"type":"Point"}
}