{
  "type": "Feature",
  "properties": {
    "gn:admin1_code":"82",
    "gn:admin2_code":"4087",
    "gn:admin3_code":"408747.0",
    "gn:admin4_code":"40874771.0",
    "gn:asciiname":"Jharurkhamar",
    "gn:country_code":"BD",
    "gn:dem":7,
    "gn:feature_class":"P",
    "gn:feature_code":"PPL",
    "gn:name":"Jharurkh\u0101m\u0101r",
    "gn:population":0,
    "gn:timezone":"Asia/Dhaka",
    "iso:country":"BD",
    "wof:name":"Jharurkhamar",
    "wof:placetype":"locality"
},
  "geometry": {"coordinates":[89.0872,22.41413],"type":"Point"}
}