{
  "type": "Feature",
  "properties": {
    "gn:admin1_code":"81",
    "gn:admin2_code":"3093.0",
    "gn:admin3_code":"309347.0",
    "gn:admin4_code":"30934758.0",
    "gn:asciiname":"Baldhi",
    "gn:country_code":"BD",
    "gn:dem":15,
    "gn:feature_class":"P",
    "gn:feature_code":"PPL",
    "gn:name":"Baldhi",
    "gn:population":0,
    "gn:timezone":"Asia/Dhaka",
    "iso:country":"BD",
    "wof:name":"Baldhi",
    "wof:placetype":"locality"
},
  "geometry": {"coordinates":[90.00182,24.34564],"type":"Point"}
}