{
  "type": "Feature",
  "properties": {
    "gn:admin1_code":"85",
    "gn:admin2_code":"1006.0",
    "gn:admin3_code":"100603.0",
    "gn:admin4_code":"10060327.0",
    "gn:asciiname":"Bayelakhal",
    "gn:country_code":"BD",
    "gn:dem":13,
    "gn:feature_class":"P",
    "gn:feature_code":"PPL",
    "gn:name":"B\u0101yel\u0101kh\u0101l",
    "gn:population":0,
    "gn:timezone":"Asia/Dhaka",
    "iso:country":"BD",
    "name:und_x_variant":[
        "Bayelakhali",
        "B\u0101yel\u0101kh\u0101l"
    ],
    "wof:name":"Bayelakhal",
    "wof:placetype":"locality"
},
  "geometry": {"coordinates":[90.35386,22.77192],"type":"Point"}
}