{
  "type": "Feature",
  "properties": {
    "gn:admin1_code":"82",
    "gn:admin2_code":"4050.0",
    "gn:admin3_code":"405094.0",
    "gn:admin4_code":"40509465.0",
    "gn:asciiname":"Magura",
    "gn:country_code":"BD",
    "gn:dem":21,
    "gn:feature_class":"P",
    "gn:feature_code":"PPL",
    "gn:name":"Magura",
    "gn:population":0,
    "gn:timezone":"Asia/Dhaka",
    "iso:country":"BD",
    "name:ben_x_preferred":[
        "Magura"
    ],
    "wof:name":"Magura",
    "wof:placetype":"locality"
},
  "geometry": {"coordinates":[88.90804,23.8546],"type":"Point"}
}