{
  "type": "Feature",
  "properties": {
    "gn:admin1_code":"83",
    "gn:admin2_code":"5064",
    "gn:admin3_code":"506469.0",
    "gn:admin4_code":"50646931.0",
    "gn:asciiname":"Kharhat",
    "gn:country_code":"BD",
    "gn:dem":25,
    "gn:feature_class":"P",
    "gn:feature_code":"PPL",
    "gn:name":"Kharh\u0101t",
    "gn:population":0,
    "gn:timezone":"Asia/Dhaka",
    "iso:country":"BD",
    "name:ben_x_preferred":[
        "Kharh\u0101t"
    ],
    "name:ben_x_variant":[
        "Kh\u0101nrh\u0101t"
    ],
    "wof:name":"Kharhat",
    "wof:placetype":"locality"
},
  "geometry": {"coordinates":[88.63939999999999,24.92964],"type":"Point"}
}