{
  "type": "Feature",
  "properties": {
    "gn:admin1_code":"82",
    "gn:admin2_code":"4055",
    "gn:admin3_code":"405595.0",
    "gn:admin4_code":"40559563.0",
    "gn:asciiname":"Naohatta",
    "gn:country_code":"BD",
    "gn:dem":15,
    "gn:feature_class":"P",
    "gn:feature_code":"PPL",
    "gn:name":"Naoh\u0101tta",
    "gn:population":0,
    "gn:timezone":"Asia/Dhaka",
    "iso:country":"BD",
    "wof:name":"Naohatta",
    "wof:placetype":"locality"
},
  "geometry": {"coordinates":[89.44526,23.57752],"type":"Point"}
}