{
  "type": "Feature",
  "properties": {
    "gn:admin1_code":"84",
    "gn:admin2_code":"2051",
    "gn:admin3_code":"205165.0",
    "gn:admin4_code":"20516538.0",
    "gn:asciiname":"Ichhapur",
    "gn:country_code":"BD",
    "gn:dem":11,
    "gn:feature_class":"P",
    "gn:feature_code":"PPL",
    "gn:name":"Ichh\u0101pur",
    "gn:population":0,
    "gn:timezone":"Asia/Dhaka",
    "iso:country":"BD",
    "wof:name":"Ichhapur",
    "wof:placetype":"locality"
},
  "geometry": {"coordinates":[90.81982000000001,23.10798],"type":"Point"}
}