{
  "type": "Feature",
  "properties": {
    "gn:admin1_code":"85",
    "gn:admin2_code":"1079",
    "gn:admin3_code":"107947.0",
    "gn:admin4_code":"10794779.0",
    "gn:asciiname":"Phalaibania",
    "gn:country_code":"BD",
    "gn:dem":10,
    "gn:feature_class":"P",
    "gn:feature_code":"PPL",
    "gn:name":"Phalaibania",
    "gn:population":0,
    "gn:timezone":"Asia/Dhaka",
    "iso:country":"BD",
    "wof:name":"Phalaibania",
    "wof:placetype":"locality"
},
  "geometry": {"coordinates":[90.05,22.55],"type":"Point"}
}