{
  "type": "Feature",
  "properties": {
    "gn:admin1_code":"85",
    "gn:admin2_code":"1006.0",
    "gn:admin3_code":"100651.0",
    "gn:admin4_code":"10065151.0",
    "gn:asciiname":"Dingamanik",
    "gn:country_code":"BD",
    "gn:dem":9,
    "gn:feature_class":"P",
    "gn:feature_code":"PPL",
    "gn:name":"Ding\u0101m\u0101nik",
    "gn:population":0,
    "gn:timezone":"Asia/Dhaka",
    "iso:country":"BD",
    "name:und_x_variant":[
        "Ding\u0101m\u0101nik"
    ],
    "wof:name":"Dingamanik",
    "wof:placetype":"locality"
},
  "geometry": {"coordinates":[90.45365,22.73335],"type":"Point"}
}