{
  "type": "Feature",
  "properties": {
    "gn:admin1_code":"81",
    "gn:admin2_code":"3035",
    "gn:admin3_code":"303558.0",
    "gn:admin4_code":"30355805.0",
    "gn:asciiname":"Salia",
    "gn:country_code":"BD",
    "gn:dem":6,
    "gn:feature_class":"P",
    "gn:feature_code":"PPL",
    "gn:name":"Salia",
    "gn:population":0,
    "gn:timezone":"Asia/Dhaka",
    "iso:country":"BD",
    "name:ceb_x_preferred":[
        "Salia"
    ],
    "name:deu_x_preferred":[
        "Salia"
    ],
    "wof:name":"Salia",
    "wof:placetype":"locality"
},
  "geometry": {"coordinates":[89.89558000000002,23.29913],"type":"Point"}
}