{
  "type": "Feature",
  "properties": {
    "gn:admin1_code":"87",
    "gn:admin2_code":"5573",
    "gn:admin3_code":"557336.0",
    "gn:admin4_code":"55733629.0",
    "gn:asciiname":"Tilai",
    "gn:country_code":"BD",
    "gn:dem":50,
    "gn:feature_class":"P",
    "gn:feature_code":"PPL",
    "gn:name":"Tilai",
    "gn:population":0,
    "gn:timezone":"Asia/Dhaka",
    "iso:country":"BD",
    "name:ben_x_preferred":[
        "Tilai"
    ],
    "wof:name":"Tilai",
    "wof:placetype":"locality"
},
  "geometry": {"coordinates":[89.05289,26.07086],"type":"Point"}
}