{
  "type": "Feature",
  "properties": {
    "gn:admin1_code":"H",
    "gn:admin2_code":"3072.0",
    "gn:admin3_code":"307218.0",
    "gn:admin4_code":"30721877.0",
    "gn:asciiname":"Bara Batia",
    "gn:country_code":"BD",
    "gn:dem":15,
    "gn:feature_class":"P",
    "gn:feature_code":"PPL",
    "gn:name":"Bara B\u0101tia",
    "gn:population":0,
    "gn:timezone":"Asia/Dhaka",
    "iso:country":"BD",
    "name:und_x_variant":[
        "Bara Batta",
        "Bara B\u0101tia"
    ],
    "wof:name":"Bara Batia",
    "wof:placetype":"locality"
},
  "geometry": {"coordinates":[90.69959,25.00141],"type":"Point"}
}