{
  "type": "Feature",
  "properties": {
    "gn:admin1_code":"85",
    "gn:admin2_code":"1006.0",
    "gn:admin3_code":"100632.0",
    "gn:admin4_code":"10063238.0",
    "gn:asciiname":"Gobardhan",
    "gn:country_code":"BD",
    "gn:dem":8,
    "gn:feature_class":"P",
    "gn:feature_code":"PPL",
    "gn:name":"Gobardhan",
    "gn:population":0,
    "gn:timezone":"Asia/Dhaka",
    "iso:country":"BD",
    "wof:name":"Gobardhan",
    "wof:placetype":"locality"
},
  "geometry": {"coordinates":[90.20811,22.9768],"type":"Point"}
}