{
  "type": "Feature",
  "properties": {
    "gn:admin1_code":"87",
    "gn:admin2_code":"5552",
    "gn:admin3_code":"555255.0",
    "gn:admin4_code":"55525594.0",
    "gn:asciiname":"Khaliaghat",
    "gn:country_code":"BD",
    "gn:dem":33,
    "gn:feature_class":"P",
    "gn:feature_code":"PPL",
    "gn:name":"Khali\u0101gh\u0101t",
    "gn:population":0,
    "gn:timezone":"Asia/Dhaka",
    "iso:country":"BD",
    "name:und_x_variant":[
        "Khalaighat",
        "Khali\u0101gh\u0101t"
    ],
    "wof:name":"Khaliaghat",
    "wof:placetype":"locality"
},
  "geometry": {"coordinates":[89.40000000000001,25.81667],"type":"Point"}
}