{
  "type": "Feature",
  "properties": {
    "gn:admin1_code":"83",
    "gn:admin2_code":"5064.0",
    "gn:admin3_code":"506469.0",
    "gn:admin4_code":"50646973.0",
    "gn:asciiname":"Saorapara",
    "gn:country_code":"BD",
    "gn:dem":41,
    "gn:feature_class":"P",
    "gn:feature_code":"PPL",
    "gn:name":"S\u0101or\u0101p\u0101ra",
    "gn:population":0,
    "gn:timezone":"Asia/Dhaka",
    "iso:country":"BD",
    "name:ben_x_preferred":[
        "S\u0101or\u0101p\u0101ra"
    ],
    "wof:name":"Saorapara",
    "wof:placetype":"locality"
},
  "geometry": {"coordinates":[88.45265000000001,24.82004],"type":"Point"}
}