{
  "type": "Feature",
  "properties": {
    "gn:admin1_code":"81",
    "gn:admin2_code":"3054",
    "gn:admin3_code":"305454.0",
    "gn:admin4_code":"30545435.0",
    "gn:asciiname":"Mobarakdi",
    "gn:country_code":"BD",
    "gn:dem":8,
    "gn:feature_class":"P",
    "gn:feature_code":"PPL",
    "gn:name":"Mob\u0101rakdi",
    "gn:population":0,
    "gn:timezone":"Asia/Dhaka",
    "iso:country":"BD",
    "name:und_x_variant":[
        "Mabarakdi",
        "Mob\u0101rakdi"
    ],
    "wof:name":"Mobarakdi",
    "wof:placetype":"locality"
},
  "geometry": {"coordinates":[90.22129,23.15505],"type":"Point"}
}