{
  "type": "Feature",
  "properties": {
    "gn:admin1_code":"84",
    "gn:admin2_code":"2012",
    "gn:admin3_code":"201263.0",
    "gn:admin4_code":"20126331.0",
    "gn:asciiname":"Sibpur",
    "gn:cc2":"BD",
    "gn:country_code":"BD",
    "gn:dem":11,
    "gn:feature_class":"P",
    "gn:feature_code":"PPL",
    "gn:name":"Sibpur",
    "gn:population":0,
    "gn:timezone":"Asia/Dhaka",
    "iso:country":"BD",
    "name:und_x_variant":[
        "North Shibpur",
        "Sibpur"
    ],
    "wof:name":"Sibpur",
    "wof:placetype":"locality"
},
  "geometry": {"coordinates":[91.16667,23.66667],"type":"Point"}
}