{
  "type": "Feature",
  "properties": {
    "gn:admin1_code":"84",
    "gn:admin2_code":"2015.0",
    "gn:admin3_code":"201533.0",
    "gn:admin4_code":"20153361.0",
    "gn:asciiname":"Gamaritala",
    "gn:country_code":"BD",
    "gn:dem":16,
    "gn:feature_class":"P",
    "gn:feature_code":"PPL",
    "gn:name":"G\u0101m\u0101ritala",
    "gn:population":0,
    "gn:timezone":"Asia/Dhaka",
    "iso:country":"BD",
    "name:ben_x_preferred":[
        "G\u0101m\u0101ritala"
    ],
    "wof:name":"Gamaritala",
    "wof:placetype":"locality"
},
  "geometry": {"coordinates":[91.85492000000001,22.62945],"type":"Point"}
}