{
  "type": "Feature",
  "properties": {
    "gn:admin1_code":"81",
    "gn:admin2_code":"3029.0",
    "gn:admin3_code":"302918.0",
    "gn:admin4_code":"30291875.0",
    "gn:asciiname":"Bandapasa",
    "gn:cc2":"BD",
    "gn:country_code":"BD",
    "gn:dem":5,
    "gn:feature_class":"P",
    "gn:feature_code":"PPL",
    "gn:name":"Bandap\u0101sa",
    "gn:population":0,
    "gn:timezone":"Asia/Dhaka",
    "iso:country":"BD",
    "name:und_x_variant":[
        "Bandapasha",
        "Bandap\u0101sa"
    ],
    "wof:name":"Bandapasa",
    "wof:placetype":"locality"
},
  "geometry": {"coordinates":[89.75,23.33333],"type":"Point"}
}