{
  "type": "Feature",
  "properties": {
    "gn:admin1_code":"83",
    "gn:asciiname":"Kunderpara",
    "gn:country_code":"BD",
    "gn:dem":21,
    "gn:feature_class":"P",
    "gn:feature_code":"PPL",
    "gn:name":"Kunderp\u0101ra",
    "gn:population":0,
    "gn:timezone":"Asia/Dhaka",
    "iso:country":"BD",
    "name:ben_x_preferred":[
        "Kunderp\u0101ra"
    ],
    "wof:name":"Kunderpara",
    "wof:placetype":"locality"
},
  "geometry": {"coordinates":[89.42799000000002,25.15665],"type":"Point"}
}