{
  "type": "Feature",
  "properties": {
    "gn:admin1_code":"81",
    "gn:admin2_code":"3048",
    "gn:admin3_code":"304849.0",
    "gn:admin4_code":"30484917.0",
    "gn:asciiname":"Pataljan",
    "gn:country_code":"BD",
    "gn:dem":14,
    "gn:feature_class":"P",
    "gn:feature_code":"PPL",
    "gn:name":"P\u0101t\u0101lj\u0101n",
    "gn:population":0,
    "gn:timezone":"Asia/Dhaka",
    "iso:country":"BD",
    "wof:name":"Pataljan",
    "wof:placetype":"locality"
},
  "geometry": {"coordinates":[90.85771,24.41809],"type":"Point"}
}