{
  "type": "Feature",
  "properties": {
    "gn:admin1_code":"81",
    "gn:admin2_code":"3068",
    "gn:admin3_code":"306876.0",
    "gn:admin4_code":"30687684.0",
    "gn:asciiname":"Kamargaon",
    "gn:country_code":"BD",
    "gn:dem":15,
    "gn:feature_class":"P",
    "gn:feature_code":"PPL",
    "gn:name":"K\u0101m\u0101rgaon",
    "gn:population":0,
    "gn:timezone":"Asia/Dhaka",
    "iso:country":"BD",
    "name:ceb_x_preferred":[
        "Kamargaon"
    ],
    "name:swe_x_preferred":[
        "Kamargaon"
    ],
    "wof:name":"Kamargaon",
    "wof:placetype":"locality"
},
  "geometry": {"coordinates":[90.72077,23.97339],"type":"Point"}
}