{
  "type": "Feature",
  "properties": {
    "gn:admin1_code":"82",
    "gn:admin2_code":"4044.0",
    "gn:admin3_code":"404471.0",
    "gn:admin4_code":"40447123.0",
    "gn:asciiname":"Dhaldhala Bil",
    "gn:country_code":"BD",
    "gn:dem":13,
    "gn:feature_class":"P",
    "gn:feature_code":"PPL",
    "gn:name":"Dhaldhala Bil",
    "gn:population":0,
    "gn:timezone":"Asia/Dhaka",
    "iso:country":"BD",
    "name:ben_x_preferred":[
        "Dhaldhala Bil"
    ],
    "wof:name":"Dhaldhala Bil",
    "wof:placetype":"locality"
},
  "geometry": {"coordinates":[88.85705,23.27728],"type":"Point"}
}