{
  "type": "Feature",
  "properties": {
    "gn:admin1_code":"83",
    "gn:admin2_code":"5038.0",
    "gn:admin3_code":"503874.0",
    "gn:admin4_code":"50387473.0",
    "gn:asciiname":"Kasiabari",
    "gn:country_code":"BD",
    "gn:dem":26,
    "gn:feature_class":"P",
    "gn:feature_code":"PPL",
    "gn:name":"Kasi\u0101b\u0101ri",
    "gn:population":0,
    "gn:timezone":"Asia/Dhaka",
    "iso:country":"BD",
    "name:ben_x_preferred":[
        "Kasi\u0101b\u0101ri"
    ],
    "wof:name":"Kasiabari",
    "wof:placetype":"locality"
},
  "geometry": {"coordinates":[89.08718,25.20854],"type":"Point"}
}