{
  "type": "Feature",
  "properties": {
    "gn:admin1_code":"82",
    "gn:admin2_code":"4047",
    "gn:admin3_code":"404730.0",
    "gn:admin4_code":"40473047.0",
    "gn:asciiname":"Paschim Andharmanik",
    "gn:country_code":"BD",
    "gn:dem":3,
    "gn:feature_class":"P",
    "gn:feature_code":"PPL",
    "gn:name":"Paschim \u0100ndh\u0101rm\u0101nik",
    "gn:population":0,
    "gn:timezone":"Asia/Dhaka",
    "iso:country":"BD",
    "wof:name":"Paschim Andharmanik",
    "wof:placetype":"locality"
},
  "geometry": {"coordinates":[89.32944999999999,22.74338],"type":"Point"}
}