{
  "type": "Feature",
  "properties": {
    "gn:admin1_code":"87",
    "gn:admin2_code":"5552",
    "gn:admin3_code":"555239.0",
    "gn:admin4_code":"55523953.0",
    "gn:asciiname":"Gopal Ray",
    "gn:country_code":"BD",
    "gn:dem":39,
    "gn:feature_class":"P",
    "gn:feature_code":"PPL",
    "gn:name":"Gopal Ray",
    "gn:population":0,
    "gn:timezone":"Asia/Dhaka",
    "iso:country":"BD",
    "name:ben_x_preferred":[
        "Gopal Ray"
    ],
    "wof:name":"Gopal Ray",
    "wof:placetype":"locality"
},
  "geometry": {"coordinates":[89.27589999999999,25.94914],"type":"Point"}
}