{
  "type": "Feature",
  "properties": {
    "gn:admin1_code":"00",
    "gn:asciiname":"Chhota Nishanbaria Chak",
    "gn:country_code":"BD",
    "gn:dem":-9999,
    "gn:feature_class":"P",
    "gn:feature_code":"PPL",
    "gn:name":"Chhota Nish\u0101nb\u0101ria Chak",
    "gn:population":0,
    "gn:timezone":"Asia/Dhaka",
    "iso:country":"BD",
    "wof:name":"Chhota Nishanbaria Chak",
    "wof:placetype":"locality"
},
  "geometry": {"coordinates":[90.03333000000001,21.96667],"type":"Point"}
}