{
  "type": "Feature",
  "properties": {
    "gn:admin1_code":"81",
    "gn:admin2_code":"3029",
    "gn:admin3_code":"302947.0",
    "gn:admin4_code":"30294771.0",
    "gn:asciiname":"Kachardia",
    "gn:country_code":"BD",
    "gn:dem":11,
    "gn:feature_class":"P",
    "gn:feature_code":"PPL",
    "gn:name":"K\u0101ch\u0101rdia",
    "gn:population":0,
    "gn:timezone":"Asia/Dhaka",
    "iso:country":"BD",
    "name:und_x_variant":[
        "Katchardia",
        "K\u0101ch\u0101rdia"
    ],
    "wof:name":"Kachardia",
    "wof:placetype":"locality"
},
  "geometry": {"coordinates":[89.75218000000002,23.56476],"type":"Point"}
}