{
  "type": "Feature",
  "properties": {
    "gn:admin1_code":"87",
    "gn:admin2_code":"5594.0",
    "gn:admin3_code":"559482.0",
    "gn:admin4_code":"55948251.0",
    "gn:asciiname":"Ranshiha",
    "gn:country_code":"BD",
    "gn:dem":47,
    "gn:feature_class":"P",
    "gn:feature_code":"PPL",
    "gn:name":"Ranshiha",
    "gn:population":0,
    "gn:timezone":"Asia/Dhaka",
    "iso:country":"BD",
    "name:ben_x_preferred":[
        "Ranshiha"
    ],
    "wof:name":"Ranshiha",
    "wof:placetype":"locality"
},
  "geometry": {"coordinates":[88.31925,25.74983],"type":"Point"}
}