{
  "type": "Feature",
  "properties": {
    "gn:admin1_code":"83",
    "gn:admin2_code":"5064.0",
    "gn:admin3_code":"506475.0",
    "gn:admin4_code":"50647525.0",
    "gn:asciiname":"Paschim Chapra",
    "gn:country_code":"BD",
    "gn:dem":29,
    "gn:feature_class":"P",
    "gn:feature_code":"PPL",
    "gn:name":"Paschim Ch\u0101pra",
    "gn:population":0,
    "gn:timezone":"Asia/Dhaka",
    "iso:country":"BD",
    "name:ben_x_preferred":[
        "Paschim Ch\u0101pra"
    ],
    "wof:name":"Paschim Chapra",
    "wof:placetype":"locality"
},
  "geometry": {"coordinates":[88.63502,25.0967],"type":"Point"}
}