{
  "type": "Feature",
  "properties": {
    "gn:admin1_code":"85",
    "gn:admin2_code":"1006.0",
    "gn:admin3_code":"100669.0",
    "gn:admin4_code":"10066911.0",
    "gn:asciiname":"Purba Taika",
    "gn:country_code":"BD",
    "gn:dem":10,
    "gn:feature_class":"P",
    "gn:feature_code":"PPL",
    "gn:name":"Purba Taika",
    "gn:population":0,
    "gn:timezone":"Asia/Dhaka",
    "iso:country":"BD",
    "name:und_x_variant":[
        "East Taika"
    ],
    "wof:name":"Purba Taika",
    "wof:placetype":"locality"
},
  "geometry": {"coordinates":[90.35113,23.04344],"type":"Point"}
}