{
  "type": "Feature",
  "properties": {
    "gn:admin1_code":"83",
    "gn:admin2_code":"5064.0",
    "gn:admin3_code":"506475.0",
    "gn:admin4_code":"50647525.0",
    "gn:asciiname":"Bangram",
    "gn:country_code":"BD",
    "gn:dem":37,
    "gn:feature_class":"P",
    "gn:feature_code":"PPL",
    "gn:name":"Bangr\u0101m",
    "gn:population":0,
    "gn:timezone":"Asia/Dhaka",
    "iso:country":"BD",
    "name:ben_x_preferred":[
        "Bangr\u0101m"
    ],
    "wof:name":"Bangram",
    "wof:placetype":"locality"
},
  "geometry": {"coordinates":[88.61158,25.09472],"type":"Point"}
}