{
  "type": "Feature",
  "properties": {
    "gn:admin1_code":"H",
    "gn:asciiname":"Char Belgachha",
    "gn:country_code":"BD",
    "gn:dem":20,
    "gn:feature_class":"P",
    "gn:feature_code":"PPL",
    "gn:name":"Char Belg\u0101chha",
    "gn:population":0,
    "gn:timezone":"Asia/Dhaka",
    "iso:country":"BD",
    "name:ben_x_preferred":[
        "Char Belg\u0101chha"
    ],
    "wof:name":"Char Belgachha",
    "wof:placetype":"locality"
},
  "geometry": {"coordinates":[89.70810999999998,25.10712],"type":"Point"}
}