{
  "type": "Feature",
  "properties": {
    "gn:admin1_code":"85",
    "gn:admin2_code":"1004.0",
    "gn:admin3_code":"100428.0",
    "gn:admin4_code":"10042809.0",
    "gn:asciiname":"Pakurgachhia",
    "gn:country_code":"BD",
    "gn:dem":5,
    "gn:feature_class":"P",
    "gn:feature_code":"PPL",
    "gn:name":"Pakurgachhia",
    "gn:population":0,
    "gn:timezone":"Asia/Dhaka",
    "iso:country":"BD",
    "name:ben_x_preferred":[
        "Pakurgachhia"
    ],
    "wof:name":"Pakurgachhia",
    "wof:placetype":"locality"
},
  "geometry": {"coordinates":[90.20414,22.19206],"type":"Point"}
}