{
  "type": "Feature",
  "properties": {
    "gn:admin1_code":"83",
    "gn:admin2_code":"5064.0",
    "gn:admin3_code":"506450.0",
    "gn:admin4_code":"50645085.0",
    "gn:asciiname":"Chak Siali",
    "gn:country_code":"BD",
    "gn:dem":19,
    "gn:feature_class":"P",
    "gn:feature_code":"PPL",
    "gn:name":"Chak Siali",
    "gn:population":0,
    "gn:timezone":"Asia/Dhaka",
    "iso:country":"BD",
    "name:ben_x_preferred":[
        "Chak Siali"
    ],
    "wof:name":"Chak Siali",
    "wof:placetype":"locality"
},
  "geometry": {"coordinates":[88.71696999999998,24.84263],"type":"Point"}
}