{
  "type": "Feature",
  "properties": {
    "gn:admin1_code":"83",
    "gn:admin2_code":"5088",
    "gn:admin3_code":"508850.0",
    "gn:admin4_code":"50885034.0",
    "gn:asciiname":"Meghai",
    "gn:country_code":"BD",
    "gn:dem":20,
    "gn:feature_class":"P",
    "gn:feature_code":"PPL",
    "gn:name":"Megh\u0101i",
    "gn:population":0,
    "gn:timezone":"Asia/Dhaka",
    "iso:country":"BD",
    "wof:name":"Meghai",
    "wof:placetype":"locality"
},
  "geometry": {"coordinates":[89.64704999999999,24.66582],"type":"Point"}
}