{
  "type": "Feature",
  "properties": {
    "gn:admin1_code":"81",
    "gn:admin2_code":"3029",
    "gn:admin3_code":"302984.0",
    "gn:admin4_code":"30298447.0",
    "gn:asciiname":"Char Nasirpur",
    "gn:country_code":"BD",
    "gn:dem":1,
    "gn:feature_class":"P",
    "gn:feature_code":"PPL",
    "gn:name":"Char Nasirpur",
    "gn:population":0,
    "gn:timezone":"Asia/Dhaka",
    "iso:country":"BD",
    "name:und_x_variant":[
        "Nashipur",
        "Nasipur",
        "Char Nasirpur",
        "Char N\u0101chhirpur"
    ],
    "wof:name":"Char Nasirpur",
    "wof:placetype":"locality"
},
  "geometry": {"coordinates":[90.09639,23.48052],"type":"Point"}
}