{
  "type": "Feature",
  "properties": {
    "gn:admin1_code":"82",
    "gn:admin2_code":"4050",
    "gn:admin3_code":"405071.0",
    "gn:admin4_code":"40507125.0",
    "gn:asciiname":"Paharpur",
    "gn:country_code":"BD",
    "gn:dem":23,
    "gn:feature_class":"P",
    "gn:feature_code":"PPL",
    "gn:name":"P\u0101h\u0101rpur",
    "gn:population":0,
    "gn:timezone":"Asia/Dhaka",
    "iso:country":"BD",
    "name:ben_x_preferred":[
        "P\u0101h\u0101rpur"
    ],
    "name:ben_x_variant":[
        "\u09aa\u09be\u09b9\u09be\u09a1\u09bc\u09aa\u09c1\u09b0"
    ],
    "name:ceb_x_preferred":[
        "Paharpur"
    ],
    "name:nld_x_preferred":[
        "Paharpur"
    ],
    "wof:name":"Paharpur",
    "wof:placetype":"locality"
},
  "geometry": {"coordinates":[89.15515000000001,23.85438],"type":"Point"}
}