{
  "type": "Feature",
  "properties": {
    "gn:admin1_code":"82",
    "gn:admin2_code":"4041",
    "gn:admin3_code":"404190.0",
    "gn:admin4_code":"40419060.0",
    "gn:asciiname":"Lakshmanpur",
    "gn:country_code":"BD",
    "gn:dem":15,
    "gn:feature_class":"P",
    "gn:feature_code":"PPL",
    "gn:name":"Lakshmanpur",
    "gn:population":0,
    "gn:timezone":"Asia/Dhaka",
    "iso:country":"BD",
    "name:ben_x_preferred":[
        "Lakshmanpur"
    ],
    "wof:name":"Lakshmanpur",
    "wof:placetype":"locality"
},
  "geometry": {"coordinates":[88.95709000000002,23.13324],"type":"Point"}
}