{
  "type": "Feature",
  "properties": {
    "gn:admin1_code":"83",
    "gn:admin2_code":"5088",
    "gn:admin3_code":"508867.0",
    "gn:admin4_code":"50886765.0",
    "gn:asciiname":"Porjana",
    "gn:country_code":"BD",
    "gn:dem":18,
    "gn:feature_class":"P",
    "gn:feature_code":"PPL",
    "gn:name":"Porjana",
    "gn:population":0,
    "gn:timezone":"Asia/Dhaka",
    "iso:country":"BD",
    "wof:name":"Porjana",
    "wof:placetype":"locality"
},
  "geometry": {"coordinates":[89.64811999999998,24.15651],"type":"Point"}
}