{
  "type": "Feature",
  "properties": {
    "gn:admin1_code":"82",
    "gn:admin2_code":"4065.0",
    "gn:admin3_code":"406576.0",
    "gn:admin4_code":"40657647.0",
    "gn:asciiname":"Musuri",
    "gn:country_code":"BD",
    "gn:dem":8,
    "gn:feature_class":"P",
    "gn:feature_code":"PPL",
    "gn:name":"Musuri",
    "gn:population":0,
    "gn:timezone":"Asia/Dhaka",
    "iso:country":"BD",
    "name:ben_x_preferred":[
        "Musuri"
    ],
    "name:ind_x_preferred":[
        "Musuri"
    ],
    "name:kor_x_preferred":[
        "\ubb34\uc218\ub9ac"
    ],
    "wof:name":"Musuri",
    "wof:placetype":"locality"
},
  "geometry": {"coordinates":[89.47615,23.1311],"type":"Point"}
}