{
  "type": "Feature",
  "properties": {
    "gn:admin1_code":"82",
    "gn:admin2_code":"4041.0",
    "gn:admin3_code":"404111.0",
    "gn:admin4_code":"40411186.0",
    "gn:asciiname":"Balidapara",
    "gn:country_code":"BD",
    "gn:dem":16,
    "gn:feature_class":"P",
    "gn:feature_code":"PPL",
    "gn:name":"Balid\u0101p\u0101ra",
    "gn:population":0,
    "gn:timezone":"Asia/Dhaka",
    "iso:country":"BD",
    "name:ben_x_preferred":[
        "Balid\u0101p\u0101ra"
    ],
    "wof:name":"Balidapara",
    "wof:placetype":"locality"
},
  "geometry": {"coordinates":[89.06425,23.24661],"type":"Point"}
}