{
  "type": "Feature",
  "properties": {
    "gn:admin1_code":"81",
    "gn:admin2_code":"3086.0",
    "gn:admin3_code":"308614.0",
    "gn:admin4_code":"30861425.0",
    "gn:asciiname":"Arazi Pom",
    "gn:country_code":"BD",
    "gn:dem":7,
    "gn:feature_class":"P",
    "gn:feature_code":"PPL",
    "gn:name":"\u0100r\u0101zi Pom",
    "gn:population":0,
    "gn:timezone":"Asia/Dhaka",
    "iso:country":"BD",
    "name:und_x_variant":[
        "Arozipom",
        "\u0100r\u0101zi Pom"
    ],
    "wof:name":"Arazi Pom",
    "wof:placetype":"locality"
},
  "geometry": {"coordinates":[90.41101,23.18152000000001],"type":"Point"}
}