{
  "type": "Feature",
  "properties": {
    "gn:admin1_code":"87",
    "gn:admin2_code":"5585.0",
    "gn:admin3_code":"558576.0",
    "gn:admin4_code":"55857656.0",
    "gn:asciiname":"Akbarpur",
    "gn:country_code":"BD",
    "gn:dem":32,
    "gn:feature_class":"P",
    "gn:feature_code":"PPL",
    "gn:name":"Akbarpur",
    "gn:population":0,
    "gn:timezone":"Asia/Dhaka",
    "iso:country":"BD",
    "name:bih_x_preferred":[
        "\u0905\u0915\u092c\u0930\u092a\u0941\u0930"
    ],
    "name:ceb_x_preferred":[
        "Akbarpur"
    ],
    "name:deu_x_preferred":[
        "Akbarpur"
    ],
    "name:ita_x_preferred":[
        "Akbarpur"
    ],
    "name:msa_x_preferred":[
        "Akbarpur"
    ],
    "name:new_x_preferred":[
        "\u0905\u0916\u092c\u0930\u092a\u0941\u0930"
    ],
    "name:nld_x_preferred":[
        "Akbarpur"
    ],
    "name:pol_x_preferred":[
        "Akbarpur"
    ],
    "name:rus_x_preferred":[
        "\u0410\u043a\u0431\u0430\u0440\u043f\u0443\u0440"
    ],
    "name:swe_x_preferred":[
        "Akbarpur"
    ],
    "name:und_x_variant":[
        "Ekbarpur"
    ],
    "name:vie_x_preferred":[
        "Akbarpur"
    ],
    "wof:name":"Akbarpur",
    "wof:placetype":"locality"
},
  "geometry": {"coordinates":[89.36700999999999,25.4358],"type":"Point"}
}