{
  "type": "Feature",
  "properties": {
    "gn:admin1_code":"87",
    "gn:admin2_code":"5585.0",
    "gn:admin3_code":"558576.0",
    "gn:admin4_code":"55857656.0",
    "gn:asciiname":"Akbarpur",
    "gn:country_code":"BD",
    "gn:dem":32,
    "gn:feature_class":"P",
    "gn:feature_code":"PPL",
    "gn:name":"Akbarpur",
    "gn:population":0,
    "gn:timezone":"Asia/Dhaka",
    "iso:country":"BD",
    "name:und_x_variant":[
        "Ekbarpur",
        "Akbarpur"
    ],
    "wof:name":"Akbarpur",
    "wof:placetype":"locality"
},
  "geometry": {"coordinates":[89.36700999999999,25.4358],"type":"Point"}
}