{
  "type": "Feature",
  "properties": {
    "gn:admin1_code":"84",
    "gn:admin2_code":"2084.0",
    "gn:admin3_code":"208487.0",
    "gn:admin4_code":"20848767.0",
    "gn:asciiname":"Maschari",
    "gn:country_code":"BD",
    "gn:dem":63,
    "gn:feature_class":"P",
    "gn:feature_code":"PPL",
    "gn:name":"M\u0101schari",
    "gn:population":0,
    "gn:timezone":"Asia/Dhaka",
    "iso:country":"BD",
    "name:ben_x_preferred":[
        "M\u0101schari"
    ],
    "wof:name":"Maschari",
    "wof:placetype":"locality"
},
  "geometry": {"coordinates":[92.23904,22.57136],"type":"Point"}
}