{
  "type": "Feature",
  "properties": {
    "gn:admin1_code":"81",
    "gn:admin2_code":"3082",
    "gn:admin3_code":"308273.0",
    "gn:admin4_code":"30827365.0",
    "gn:asciiname":"Teliganti",
    "gn:country_code":"BD",
    "gn:dem":15,
    "gn:feature_class":"P",
    "gn:feature_code":"PPL",
    "gn:name":"Telig\u0101nti",
    "gn:population":0,
    "gn:timezone":"Asia/Dhaka",
    "iso:country":"BD",
    "name:und_x_variant":[
        "Teligati",
        "Telig\u0101nti"
    ],
    "wof:name":"Teliganti",
    "wof:placetype":"locality"
},
  "geometry": {"coordinates":[89.41686999999997,23.74942],"type":"Point"}
}