{
  "type": "Feature",
  "properties": {
    "gn:admin1_code":"82",
    "gn:admin2_code":"4047.0",
    "gn:admin3_code":"404753.0",
    "gn:admin4_code":"40475311.0",
    "gn:asciiname":"Fakirpota",
    "gn:country_code":"BD",
    "gn:dem":5,
    "gn:feature_class":"P",
    "gn:feature_code":"PPL",
    "gn:name":"Fakirpota",
    "gn:population":0,
    "gn:timezone":"Asia/Dhaka",
    "iso:country":"BD",
    "name:ben_x_preferred":[
        "Fakirpota"
    ],
    "wof:name":"Fakirpota",
    "wof:placetype":"locality"
},
  "geometry": {"coordinates":[89.26179999999999,22.43425],"type":"Point"}
}