{
  "type": "Feature",
  "properties": {
    "gn:admin1_code":"81",
    "gn:admin2_code":"3026",
    "gn:admin3_code":"302640.0",
    "gn:admin4_code":"30264012.0",
    "gn:asciiname":"Matuail",
    "gn:country_code":"BD",
    "gn:dem":11,
    "gn:feature_class":"P",
    "gn:feature_code":"PPL",
    "gn:name":"M\u0101tuail",
    "gn:population":0,
    "gn:timezone":"Asia/Dhaka",
    "iso:country":"BD",
    "name:und_x_variant":[
        "M\u0101tuail"
    ],
    "wof:name":"Matuail",
    "wof:placetype":"locality"
},
  "geometry": {"coordinates":[90.45983,23.71211],"type":"Point"}
}