{
  "type": "Feature",
  "properties": {
    "gn:admin1_code":"81",
    "gn:admin2_code":"3056",
    "gn:admin3_code":"305670.0",
    "gn:admin4_code":"30567057.0",
    "gn:asciiname":"Paschim Barundi Chak",
    "gn:country_code":"BD",
    "gn:dem":13,
    "gn:feature_class":"P",
    "gn:feature_code":"PPL",
    "gn:name":"Paschim Barundi Chak",
    "gn:population":0,
    "gn:timezone":"Asia/Dhaka",
    "iso:country":"BD",
    "wof:name":"Paschim Barundi Chak",
    "wof:placetype":"locality"
},
  "geometry": {"coordinates":[90.06170999999998,23.89705],"type":"Point"}
}