{
  "type": "Feature",
  "properties": {
    "gn:admin1_code":"84",
    "gn:admin2_code":"2019",
    "gn:admin3_code":"201927.0",
    "gn:admin4_code":"20192787.0",
    "gn:asciiname":"Satgaon",
    "gn:country_code":"BD",
    "gn:dem":11,
    "gn:feature_class":"P",
    "gn:feature_code":"PPL",
    "gn:name":"S\u0101tgaon",
    "gn:population":0,
    "gn:timezone":"Asia/Dhaka",
    "iso:country":"BD",
    "wof:name":"Satgaon",
    "wof:placetype":"locality"
},
  "geometry": {"coordinates":[90.88979999999999,23.48992],"type":"Point"}
}