{
  "type": "Feature",
  "properties": {
    "gn:admin1_code":"85",
    "gn:admin2_code":"1009.0",
    "gn:admin3_code":"100921.0",
    "gn:admin4_code":"10092176.0",
    "gn:asciiname":"Char Gangapur",
    "gn:country_code":"BD",
    "gn:dem":8,
    "gn:feature_class":"P",
    "gn:feature_code":"PPL",
    "gn:name":"Char Gang\u0101pur",
    "gn:population":0,
    "gn:timezone":"Asia/Dhaka",
    "iso:country":"BD",
    "name:ben_x_preferred":[
        "Char Gang\u0101pur"
    ],
    "wof:name":"Char Gangapur",
    "wof:placetype":"locality"
},
  "geometry": {"coordinates":[90.68177,22.47373],"type":"Point"}
}