{
  "type": "Feature",
  "properties": {
    "gn:admin1_code":"82",
    "gn:admin2_code":"4001.0",
    "gn:admin3_code":"400158.0",
    "gn:admin4_code":"40015859.0",
    "gn:asciiname":"Madurpalta",
    "gn:country_code":"BD",
    "gn:dem":6,
    "gn:feature_class":"P",
    "gn:feature_code":"PPL",
    "gn:name":"Madurpalta",
    "gn:population":0,
    "gn:timezone":"Asia/Dhaka",
    "iso:country":"BD",
    "name:ben_x_preferred":[
        "Madurpalta"
    ],
    "wof:name":"Madurpalta",
    "wof:placetype":"locality"
},
  "geometry": {"coordinates":[89.65394000000001,22.46542],"type":"Point"}
}