{
  "type": "Feature",
  "properties": {
    "gn:admin1_code":"82",
    "gn:admin2_code":"4041.0",
    "gn:admin3_code":"404147.0",
    "gn:admin4_code":"40414735.0",
    "gn:asciiname":"Alamnagar",
    "gn:country_code":"BD",
    "gn:dem":13,
    "gn:feature_class":"P",
    "gn:feature_code":"PPL",
    "gn:name":"Alamnagar",
    "gn:population":0,
    "gn:timezone":"Asia/Dhaka",
    "iso:country":"BD",
    "name:ben_x_preferred":[
        "Alamnagar"
    ],
    "name:ceb_x_preferred":[
        "Alamnagar"
    ],
    "name:fas_x_preferred":[
        "\u0639\u0627\u0644\u0645\u200c\u0646\u06af\u0627\u0631"
    ],
    "name:swe_x_preferred":[
        "Alamnagar"
    ],
    "name:urd_x_preferred":[
        "\u0639\u0627\u0644\u0645 \u0646\u06af\u0631"
    ],
    "wof:name":"Alamnagar",
    "wof:placetype":"locality"
},
  "geometry": {"coordinates":[89.1407,23.17307000000001],"type":"Point"}
}