{
  "type": "Feature",
  "properties": {
    "gn:admin1_code":"81",
    "gn:admin2_code":"3093.0",
    "gn:admin3_code":"309309.0",
    "gn:admin4_code":"30930911.0",
    "gn:asciiname":"Barni Kesari",
    "gn:country_code":"BD",
    "gn:dem":14,
    "gn:feature_class":"P",
    "gn:feature_code":"PPL",
    "gn:name":"Barni Kesari",
    "gn:population":0,
    "gn:timezone":"Asia/Dhaka",
    "iso:country":"BD",
    "wof:name":"Barni Kesari",
    "wof:placetype":"locality"
},
  "geometry": {"coordinates":[90.06819,24.2459],"type":"Point"}
}