{
  "type": "Feature",
  "properties": {
    "gn:admin1_code":"81",
    "gn:admin2_code":"3086",
    "gn:admin3_code":"308636.0",
    "gn:admin4_code":"30863635.0",
    "gn:asciiname":"Tar Satmatia",
    "gn:country_code":"BD",
    "gn:dem":9,
    "gn:feature_class":"P",
    "gn:feature_code":"PPL",
    "gn:name":"Tar S\u0101tm\u0101tia",
    "gn:population":0,
    "gn:timezone":"Asia/Dhaka",
    "iso:country":"BD",
    "wof:name":"Tar Satmatia",
    "wof:placetype":"locality"
},
  "geometry": {"coordinates":[90.40916,23.06353],"type":"Point"}
}