{
  "type": "Feature",
  "properties": {
    "gn:admin1_code":"84",
    "gn:admin2_code":"2075.0",
    "gn:admin3_code":"207507.0",
    "gn:admin4_code":"20750704.0",
    "gn:asciiname":"Bara Newazpur",
    "gn:cc2":"BD",
    "gn:country_code":"BD",
    "gn:dem":5,
    "gn:feature_class":"P",
    "gn:feature_code":"PPL",
    "gn:name":"Bara New\u0101zpur",
    "gn:population":0,
    "gn:timezone":"Asia/Dhaka",
    "iso:country":"BD",
    "name:und_x_variant":[
        "Big Newazpur",
        "Bara New\u0101zpur"
    ],
    "wof:name":"Bara Newazpur",
    "wof:placetype":"locality"
},
  "geometry": {"coordinates":[91.01667,22.93333],"type":"Point"}
}