{
  "type": "Feature",
  "properties": {
    "gn:admin1_code":"87",
    "gn:admin2_code":"5573",
    "gn:admin3_code":"557345.0",
    "gn:admin4_code":"55734551.0",
    "gn:asciiname":"Akkelpur",
    "gn:country_code":"BD",
    "gn:dem":44,
    "gn:feature_class":"P",
    "gn:feature_code":"PPL",
    "gn:name":"Akkelpur",
    "gn:population":0,
    "gn:timezone":"Asia/Dhaka",
    "iso:country":"BD",
    "name:ben_x_preferred":[
        "Akkelpur"
    ],
    "wof:name":"Akkelpur",
    "wof:placetype":"locality"
},
  "geometry": {"coordinates":[89.04495,25.87295],"type":"Point"}
}