{
  "type": "Feature",
  "properties": {
    "gn:admin1_code":"84",
    "gn:admin2_code":"2051",
    "gn:admin3_code":"205143.0",
    "gn:admin4_code":"20514345.0",
    "gn:asciiname":"Dakhin Rajapur",
    "gn:country_code":"BD",
    "gn:dem":6,
    "gn:feature_class":"P",
    "gn:feature_code":"PPL",
    "gn:name":"Dakhin R\u0101j\u0101pur",
    "gn:population":0,
    "gn:timezone":"Asia/Dhaka",
    "iso:country":"BD",
    "name:und_x_variant":[
        "Dakhin R\u0101j\u0101pur",
        "South R\u0101j\u0101pur"
    ],
    "wof:name":"Dakhin Rajapur",
    "wof:placetype":"locality"
},
  "geometry": {"coordinates":[90.94891,22.92535],"type":"Point"}
}