{
  "type": "Feature",
  "properties": {
    "gn:admin1_code":"81",
    "gn:admin2_code":"3056",
    "gn:admin3_code":"305628.0",
    "gn:admin4_code":"30562843.0",
    "gn:asciiname":"Panchtara",
    "gn:country_code":"BD",
    "gn:dem":1,
    "gn:feature_class":"P",
    "gn:feature_code":"PPL",
    "gn:name":"P\u0101ncht\u0101ra",
    "gn:population":0,
    "gn:timezone":"Asia/Dhaka",
    "iso:country":"BD",
    "wof:name":"Panchtara",
    "wof:placetype":"locality"
},
  "geometry": {"coordinates":[89.99665999999998,23.68759],"type":"Point"}
}