{
  "type": "Feature",
  "properties": {
    "gn:admin1_code":"84",
    "gn:admin2_code":"2022.0",
    "gn:admin3_code":"202249.0",
    "gn:admin4_code":"20224923.0",
    "gn:asciiname":"Bargonbhunia",
    "gn:country_code":"BD",
    "gn:dem":9,
    "gn:feature_class":"P",
    "gn:feature_code":"PPL",
    "gn:name":"Bargonbhunia",
    "gn:population":0,
    "gn:timezone":"Asia/Dhaka",
    "iso:country":"BD",
    "name:ben_x_preferred":[
        "Bargonbhunia"
    ],
    "wof:name":"Bargonbhunia",
    "wof:placetype":"locality"
},
  "geometry": {"coordinates":[91.86247,21.66888],"type":"Point"}
}