{
  "type": "Feature",
  "properties": {
    "gn:admin1_code":"83",
    "gn:admin2_code":"5081",
    "gn:admin3_code":"508131.0",
    "gn:admin4_code":"50813123.0",
    "gn:asciiname":"Kismat Tekathia",
    "gn:country_code":"BD",
    "gn:dem":18,
    "gn:feature_class":"P",
    "gn:feature_code":"PPL",
    "gn:name":"Kismat Tek\u0101thia",
    "gn:population":0,
    "gn:timezone":"Asia/Dhaka",
    "iso:country":"BD",
    "name:ben_x_preferred":[
        "Kismat Tek\u0101thia"
    ],
    "wof:name":"Kismat Tekathia",
    "wof:placetype":"locality"
},
  "geometry": {"coordinates":[88.81328000000001,24.46536],"type":"Point"}
}