{
  "type": "Feature",
  "properties": {
    "gn:admin1_code":"87",
    "gn:admin2_code":"5527.0",
    "gn:admin3_code":"552738.0",
    "gn:admin4_code":"55273828.0",
    "gn:asciiname":"Kamalpur",
    "gn:country_code":"BD",
    "gn:dem":29,
    "gn:feature_class":"P",
    "gn:feature_code":"PPL",
    "gn:name":"K\u0101m\u0101lpur",
    "gn:population":0,
    "gn:timezone":"Asia/Dhaka",
    "iso:country":"BD",
    "name:ben_x_preferred":[
        "K\u0101m\u0101lpur"
    ],
    "name:cat_x_preferred":[
        "Kamalpur"
    ],
    "name:ceb_x_preferred":[
        "Kamalpur"
    ],
    "name:fra_x_preferred":[
        "Kamalpur"
    ],
    "name:swe_x_preferred":[
        "Kamalpur"
    ],
    "name:tam_x_preferred":[
        "\u0b95\u0bae\u0bb2\u0bcd\u0baa\u0bc2\u0bb0\u0bcd"
    ],
    "wof:name":"Kamalpur",
    "wof:placetype":"locality"
},
  "geometry": {"coordinates":[88.92027,25.4081],"type":"Point"}
}