{
  "type": "Feature",
  "properties": {
    "gn:admin1_code":"87",
    "gn:admin2_code":"5549",
    "gn:admin3_code":"554977.0",
    "gn:admin4_code":"55497784.0",
    "gn:asciiname":"Phul Khan",
    "gn:country_code":"BD",
    "gn:dem":33,
    "gn:feature_class":"P",
    "gn:feature_code":"PPL",
    "gn:name":"Phul Kh\u0101n",
    "gn:population":0,
    "gn:timezone":"Asia/Dhaka",
    "iso:country":"BD",
    "name:ben_x_preferred":[
        "Phul Kh\u0101n"
    ],
    "wof:name":"Phul Khan",
    "wof:placetype":"locality"
},
  "geometry": {"coordinates":[89.56209,25.76109],"type":"Point"}
}