{
  "type": "Feature",
  "properties": {
    "gn:admin1_code":"83",
    "gn:admin2_code":"5064.0",
    "gn:admin3_code":"506447.0",
    "gn:admin4_code":"50644794.0",
    "gn:asciiname":"Gojha",
    "gn:country_code":"BD",
    "gn:dem":21,
    "gn:feature_class":"P",
    "gn:feature_code":"PPL",
    "gn:name":"Gojha",
    "gn:population":0,
    "gn:timezone":"Asia/Dhaka",
    "iso:country":"BD",
    "name:ben_x_preferred":[
        "Gojha"
    ],
    "wof:name":"Gojha",
    "wof:placetype":"locality"
},
  "geometry": {"coordinates":[88.65401,24.64231],"type":"Point"}
}