{
  "type": "Feature",
  "properties": {
    "gn:admin1_code":"84",
    "gn:admin2_code":"2013",
    "gn:admin3_code":"201376.0",
    "gn:admin4_code":"20137634.0",
    "gn:asciiname":"Telimachua",
    "gn:country_code":"BD",
    "gn:dem":8,
    "gn:feature_class":"P",
    "gn:feature_code":"PPL",
    "gn:name":"Telim\u0101chua",
    "gn:population":0,
    "gn:timezone":"Asia/Dhaka",
    "iso:country":"BD",
    "wof:name":"Telimachua",
    "wof:placetype":"locality"
},
  "geometry": {"coordinates":[90.75046,23.37391],"type":"Point"}
}