{
  "type": "Feature",
  "properties": {
    "gn:admin1_code":"84",
    "gn:admin2_code":"2019",
    "gn:admin3_code":"201909.0",
    "gn:admin4_code":"20190918.0",
    "gn:asciiname":"Singha Cho",
    "gn:cc2":"BD",
    "gn:country_code":"BD",
    "gn:dem":11,
    "gn:feature_class":"P",
    "gn:feature_code":"PPL",
    "gn:name":"Singha Cho",
    "gn:population":0,
    "gn:timezone":"Asia/Dhaka",
    "iso:country":"BD",
    "name:und_x_variant":[
        "Singa Cho",
        "Singha Cho"
    ],
    "wof:name":"Singha Cho",
    "wof:placetype":"locality"
},
  "geometry": {"coordinates":[91.06667,23.41667],"type":"Point"}
}