{
  "type": "Feature",
  "properties": {
    "gn:admin1_code":"83",
    "gn:admin2_code":"5064.0",
    "gn:admin3_code":"506469.0",
    "gn:admin4_code":"50646910.0",
    "gn:asciiname":"Bhalanghati",
    "gn:country_code":"BD",
    "gn:dem":27,
    "gn:feature_class":"P",
    "gn:feature_code":"PPL",
    "gn:name":"Bhal\u0101nghati",
    "gn:population":0,
    "gn:timezone":"Asia/Dhaka",
    "iso:country":"BD",
    "name:ben_x_preferred":[
        "Bhal\u0101nghati"
    ],
    "wof:name":"Bhalanghati",
    "wof:placetype":"locality"
},
  "geometry": {"coordinates":[88.57035999999999,24.76734],"type":"Point"}
}