{
  "type": "Feature",
  "properties": {
    "gn:admin1_code":"87",
    "gn:admin2_code":"5532",
    "gn:admin3_code":"553224.0",
    "gn:admin4_code":"55322487.0",
    "gn:asciiname":"Bara Mohanandapur",
    "gn:country_code":"BD",
    "gn:dem":25,
    "gn:feature_class":"P",
    "gn:feature_code":"PPL",
    "gn:name":"Bara Mohanandapur",
    "gn:population":0,
    "gn:timezone":"Asia/Dhaka",
    "iso:country":"BD",
    "name:ben_x_preferred":[
        "Bara Mohanandapur"
    ],
    "wof:name":"Bara Mohanandapur",
    "wof:placetype":"locality"
},
  "geometry": {"coordinates":[89.49337,25.29037000000001],"type":"Point"}
}