{
  "type": "Feature",
  "properties": {
    "gn:admin1_code":"84",
    "gn:admin2_code":"2051",
    "gn:admin3_code":"205165.0",
    "gn:admin4_code":"20516542.0",
    "gn:asciiname":"Shaikpura",
    "gn:country_code":"BD",
    "gn:dem":12,
    "gn:feature_class":"P",
    "gn:feature_code":"PPL",
    "gn:name":"Shaikpura",
    "gn:population":0,
    "gn:timezone":"Asia/Dhaka",
    "iso:country":"BD",
    "name:und_x_variant":[
        "Sekhpura",
        "Shekhpura",
        "Shaikpura"
    ],
    "wof:name":"Shaikpura",
    "wof:placetype":"locality"
},
  "geometry": {"coordinates":[90.85102000000001,23.13715],"type":"Point"}
}