{
  "type": "Feature",
  "properties": {
    "gn:admin1_code":"83",
    "gn:admin2_code":"5064",
    "gn:admin3_code":"506460.0",
    "gn:admin4_code":"50646043.0",
    "gn:asciiname":"Ilsabari",
    "gn:country_code":"BD",
    "gn:dem":21,
    "gn:feature_class":"P",
    "gn:feature_code":"PPL",
    "gn:name":"Ils\u0101b\u0101ri",
    "gn:population":0,
    "gn:timezone":"Asia/Dhaka",
    "iso:country":"BD",
    "name:ben_x_preferred":[
        "Ils\u0101b\u0101ri"
    ],
    "name:und_x_variant":[
        "Ilshabari"
    ],
    "wof:name":"Ilsabari",
    "wof:placetype":"locality"
},
  "geometry": {"coordinates":[88.96095,24.76473],"type":"Point"}
}