{
  "type": "Feature",
  "properties": {
    "gn:admin1_code":"81",
    "gn:admin2_code":"3035.0",
    "gn:admin3_code":"303543.0",
    "gn:admin4_code":"30354374.0",
    "gn:asciiname":"Bhulbaria",
    "gn:country_code":"BD",
    "gn:dem":6,
    "gn:feature_class":"P",
    "gn:feature_code":"PPL",
    "gn:name":"Bhulb\u0101ria",
    "gn:population":0,
    "gn:timezone":"Asia/Dhaka",
    "iso:country":"BD",
    "name:ben_x_preferred":[
        "Bhulb\u0101ria"
    ],
    "wof:name":"Bhulbaria",
    "wof:placetype":"locality"
},
  "geometry": {"coordinates":[89.85614,23.1912],"type":"Point"}
}