{
  "type": "Feature",
  "properties": {
    "gn:admin1_code":"85",
    "gn:admin2_code":"1004.0",
    "gn:admin3_code":"100485.0",
    "gn:admin4_code":"10048535.0",
    "gn:asciiname":"Paschim Kalmegha",
    "gn:country_code":"BD",
    "gn:dem":10,
    "gn:feature_class":"P",
    "gn:feature_code":"PPL",
    "gn:name":"Paschim Kalmegha",
    "gn:population":0,
    "gn:timezone":"Asia/Dhaka",
    "iso:country":"BD",
    "name:ben_x_preferred":[
        "Paschim Kalmegha"
    ],
    "wof:name":"Paschim Kalmegha",
    "wof:placetype":"locality"
},
  "geometry": {"coordinates":[90.00253000000002,22.09266],"type":"Point"}
}