{
  "type": "Feature",
  "properties": {
    "gn:admin1_code":"84",
    "gn:admin2_code":"2019.0",
    "gn:admin3_code":"201972.0",
    "gn:admin4_code":"20197217.0",
    "gn:asciiname":"Asara",
    "gn:country_code":"BD",
    "gn:dem":11,
    "gn:feature_class":"P",
    "gn:feature_code":"PPL",
    "gn:name":"Asara",
    "gn:population":0,
    "gn:timezone":"Asia/Dhaka",
    "iso:country":"BD",
    "name:ara_x_preferred":[
        "\u0623\u0633\u0648\u0631\u0627"
    ],
    "name:aze_x_preferred":[
        "Asara"
    ],
    "name:fas_x_preferred":[
        "\u0622\u0633\u0627\u0631\u0627"
    ],
    "name:ita_x_preferred":[
        "Asara"
    ],
    "name:mlg_x_preferred":[
        "Asara"
    ],
    "name:msa_x_preferred":[
        "Asara"
    ],
    "name:rus_x_preferred":[
        "\u0410\u0441\u0430\u0440\u0430"
    ],
    "name:tur_x_preferred":[
        "Asara"
    ],
    "name:urd_x_preferred":[
        "\u0622\u0633\u0627\u0631\u0627"
    ],
    "name:zho_x_preferred":[
        "\u963f\u8428\u62c9"
    ],
    "wof:name":"Asara",
    "wof:placetype":"locality"
},
  "geometry": {"coordinates":[91.06667,23.28333],"type":"Point"}
}