{
  "type": "Feature",
  "properties": {
    "gn:admin1_code":"83",
    "gn:admin2_code":"5064",
    "gn:admin3_code":"506450.0",
    "gn:admin4_code":"50645066.0",
    "gn:asciiname":"Kusumsahar",
    "gn:country_code":"BD",
    "gn:dem":23,
    "gn:feature_class":"P",
    "gn:feature_code":"PPL",
    "gn:name":"Kusumsahar",
    "gn:population":0,
    "gn:timezone":"Asia/Dhaka",
    "iso:country":"BD",
    "name:ben_x_preferred":[
        "Kusumsahar"
    ],
    "wof:name":"Kusumsahar",
    "wof:placetype":"locality"
},
  "geometry": {"coordinates":[88.79569000000002,24.96272],"type":"Point"}
}