{
  "type": "Feature",
  "properties": {
    "gn:admin1_code":"81",
    "gn:admin2_code":"3029",
    "gn:admin3_code":"302910.0",
    "gn:admin4_code":"30291094.0",
    "gn:asciiname":"Saraibari",
    "gn:country_code":"BD",
    "gn:dem":9,
    "gn:feature_class":"P",
    "gn:feature_code":"PPL",
    "gn:name":"Saraib\u0101ri",
    "gn:population":0,
    "gn:timezone":"Asia/Dhaka",
    "iso:country":"BD",
    "name:und_x_variant":[
        "Sharaibari",
        "Saraib\u0101ri"
    ],
    "wof:name":"Saraibari",
    "wof:placetype":"locality"
},
  "geometry": {"coordinates":[90.00757,23.406],"type":"Point"}
}