{
  "type": "Feature",
  "properties": {
    "gn:admin1_code":"83",
    "gn:admin2_code":"5064.0",
    "gn:admin3_code":"506479.0",
    "gn:admin4_code":"50647955.0",
    "gn:asciiname":"Isnapur",
    "gn:country_code":"BD",
    "gn:dem":33,
    "gn:feature_class":"P",
    "gn:feature_code":"PPL",
    "gn:name":"Isnapur",
    "gn:population":0,
    "gn:timezone":"Asia/Dhaka",
    "iso:country":"BD",
    "name:ben_x_preferred":[
        "Isnapur"
    ],
    "name:bpy_x_preferred":[
        "\u0987\u09b8\u09a8\u09ac\u09aa\u09c1\u09b0"
    ],
    "name:ita_x_preferred":[
        "Isnapur"
    ],
    "name:msa_x_preferred":[
        "Isnapur"
    ],
    "name:new_x_preferred":[
        "\u0907\u0938\u094d\u0928\u093e\u092a\u0941\u0930"
    ],
    "name:nld_x_preferred":[
        "Isnapur"
    ],
    "name:por_x_preferred":[
        "Isnapur"
    ],
    "name:vie_x_preferred":[
        "Isnapur"
    ],
    "name:zho_x_preferred":[
        "\u4f0a\u65af\u7eb3\u666e\u5c14"
    ],
    "wof:name":"Isnapur",
    "wof:placetype":"locality"
},
  "geometry": {"coordinates":[88.46285999999998,25.04149],"type":"Point"}
}