{
  "type": "Feature",
  "properties": {
    "gn:admin1_code":"84",
    "gn:admin2_code":"2046.0",
    "gn:admin3_code":"204665.0",
    "gn:admin4_code":"20466579.0",
    "gn:asciiname":"Dumnighat",
    "gn:country_code":"BD",
    "gn:dem":165,
    "gn:feature_class":"P",
    "gn:feature_code":"PPL",
    "gn:name":"Dumnigh\u0101t",
    "gn:population":0,
    "gn:timezone":"Asia/Dhaka",
    "iso:country":"BD",
    "name:ben_x_preferred":[
        "Dumnigh\u0101t"
    ],
    "wof:name":"Dumnighat",
    "wof:placetype":"locality"
},
  "geometry": {"coordinates":[91.97659,22.92394],"type":"Point"}
}