{
  "type": "Feature",
  "properties": {
    "gn:admin1_code":"84",
    "gn:admin2_code":"2015.0",
    "gn:admin3_code":"201504.0",
    "gn:admin4_code":"20150438.0",
    "gn:asciiname":"Gundwip",
    "gn:country_code":"BD",
    "gn:dem":8,
    "gn:feature_class":"P",
    "gn:feature_code":"PPL",
    "gn:name":"Gundw\u012bp",
    "gn:population":0,
    "gn:timezone":"Asia/Dhaka",
    "iso:country":"BD",
    "name:ben_x_preferred":[
        "Gundw\u012bp"
    ],
    "wof:name":"Gundwip",
    "wof:placetype":"locality"
},
  "geometry": {"coordinates":[91.84826,22.19854],"type":"Point"}
}