{
  "type": "Feature",
  "properties": {
    "gn:admin1_code":"87",
    "gn:admin2_code":"5585",
    "gn:admin3_code":"558527.0",
    "gn:admin4_code":"55852763.0",
    "gn:asciiname":"Sriram",
    "gn:country_code":"BD",
    "gn:dem":39,
    "gn:feature_class":"P",
    "gn:feature_code":"PPL",
    "gn:name":"Srir\u0101m",
    "gn:population":0,
    "gn:timezone":"Asia/Dhaka",
    "iso:country":"BD",
    "name:ben_x_preferred":[
        "Srir\u0101m"
    ],
    "wof:name":"Sriram",
    "wof:placetype":"locality"
},
  "geometry": {"coordinates":[89.21835,25.91167],"type":"Point"}
}