{
  "type": "Feature",
  "properties": {
    "gn:admin1_code":"81",
    "gn:admin2_code":"3067.0",
    "gn:admin3_code":"306758.0",
    "gn:admin4_code":"30675879.0",
    "gn:asciiname":"Fatullah",
    "gn:country_code":"BD",
    "gn:dem":5,
    "gn:feature_class":"P",
    "gn:feature_code":"PPL",
    "gn:name":"Fatullah",
    "gn:population":0,
    "gn:timezone":"Asia/Dhaka",
    "iso:country":"BD",
    "wof:name":"Fatullah",
    "wof:placetype":"locality"
},
  "geometry": {"coordinates":[90.48999999999999,23.65],"type":"Point"}
}