{
  "type": "Feature",
  "properties": {
    "gn:admin1_code":"81",
    "gn:admin2_code":"3067.0",
    "gn:admin3_code":"306758.0",
    "gn:admin4_code":"30675879.0",
    "gn:asciiname":"Fatullah",
    "gn:country_code":"BD",
    "gn:dem":5,
    "gn:feature_class":"P",
    "gn:feature_code":"PPL",
    "gn:name":"Fatullah",
    "gn:population":0,
    "gn:timezone":"Asia/Dhaka",
    "iso:country":"BD",
    "name:ben_x_preferred":[
        "\u09ab\u09a4\u09c1\u09b2\u09cd\u09b2\u09be"
    ],
    "name:urd_x_preferred":[
        "\u0641\u062a\u062d \u0627\u0644\u0644\u06c1"
    ],
    "wof:name":"Fatullah",
    "wof:placetype":"locality"
},
  "geometry": {"coordinates":[90.48999999999999,23.65],"type":"Point"}
}