{
  "type": "Feature",
  "properties": {
    "gn:admin1_code":"87",
    "gn:admin2_code":"5549",
    "gn:admin3_code":"554952.0",
    "gn:admin4_code":"55495238.0",
    "gn:asciiname":"Khalisa Kalua",
    "gn:country_code":"BD",
    "gn:dem":34,
    "gn:feature_class":"P",
    "gn:feature_code":"PPL",
    "gn:name":"Kh\u0101lisa K\u0101lua",
    "gn:population":0,
    "gn:timezone":"Asia/Dhaka",
    "iso:country":"BD",
    "name:ben_x_preferred":[
        "Kh\u0101lisa K\u0101lua"
    ],
    "wof:name":"Khalisa Kalua",
    "wof:placetype":"locality"
},
  "geometry": {"coordinates":[89.61565999999998,25.84904],"type":"Point"}
}