{
  "type": "Feature",
  "properties": {
    "gn:admin1_code":"82",
    "gn:admin2_code":"4087",
    "gn:admin3_code":"408786.0",
    "gn:admin4_code":"40878615.0",
    "gn:asciiname":"Srifaltala",
    "gn:country_code":"BD",
    "gn:dem":6,
    "gn:feature_class":"P",
    "gn:feature_code":"PPL",
    "gn:name":"Srifaltala",
    "gn:population":0,
    "gn:timezone":"Asia/Dhaka",
    "iso:country":"BD",
    "wof:name":"Srifaltala",
    "wof:placetype":"locality"
},
  "geometry": {"coordinates":[89.06938000000002,22.3498],"type":"Point"}
}