{
  "type": "Feature",
  "properties": {
    "gn:admin1_code":"85",
    "gn:admin2_code":"1004.0",
    "gn:admin3_code":"100428.0",
    "gn:admin4_code":"10042838.0",
    "gn:asciiname":"Kalirtabak",
    "gn:country_code":"BD",
    "gn:dem":7,
    "gn:feature_class":"P",
    "gn:feature_code":"PPL",
    "gn:name":"Kalirtabak",
    "gn:population":0,
    "gn:timezone":"Asia/Dhaka",
    "iso:country":"BD",
    "name:ben_x_preferred":[
        "Kalirtabak"
    ],
    "wof:name":"Kalirtabak",
    "wof:placetype":"locality"
},
  "geometry": {"coordinates":[90.12248,22.1101],"type":"Point"}
}