{
  "type": "Feature",
  "properties": {
    "gn:admin1_code":"84",
    "gn:admin2_code":"2015",
    "gn:admin3_code":"201553.0",
    "gn:admin4_code":"20155359.0",
    "gn:asciiname":"Mirsarai",
    "gn:country_code":"BD",
    "gn:dem":10,
    "gn:feature_class":"P",
    "gn:feature_code":"PPL",
    "gn:name":"M\u012brsar\u0101i",
    "gn:population":0,
    "gn:timezone":"Asia/Dhaka",
    "iso:country":"BD",
    "name:und_x_variant":[
        "Minsarai",
        "M\u012brsar\u0101i"
    ],
    "wof:name":"Mirsarai",
    "wof:placetype":"locality"
},
  "geometry": {"coordinates":[91.56999,22.77852],"type":"Point"}
}