{
  "type": "Feature",
  "properties": {
    "gn:admin1_code":"82",
    "gn:admin2_code":"4087.0",
    "gn:admin3_code":"408782.0",
    "gn:admin4_code":"40878240.0",
    "gn:asciiname":"Nabatkati",
    "gn:country_code":"BD",
    "gn:dem":6,
    "gn:feature_class":"P",
    "gn:feature_code":"PPL",
    "gn:name":"Nab\u0101tk\u0101ti",
    "gn:population":0,
    "gn:timezone":"Asia/Dhaka",
    "iso:country":"BD",
    "name:ben_x_preferred":[
        "Nab\u0101tk\u0101ti"
    ],
    "wof:name":"Nabatkati",
    "wof:placetype":"locality"
},
  "geometry": {"coordinates":[88.97644,22.67123],"type":"Point"}
}