{
  "type": "Feature",
  "properties": {
    "gn:admin1_code":"84",
    "gn:admin2_code":"2012.0",
    "gn:admin3_code":"201285.0",
    "gn:admin4_code":"20128518.0",
    "gn:asciiname":"Birgaon",
    "gn:country_code":"BD",
    "gn:dem":11,
    "gn:feature_class":"P",
    "gn:feature_code":"PPL",
    "gn:name":"B\u012brgaon",
    "gn:population":0,
    "gn:timezone":"Asia/Dhaka",
    "iso:country":"BD",
    "name:ben_x_preferred":[
        "\u09ac\u09c0\u09b0\u0997\u09be\u0981\u0993"
    ],
    "name:bpy_x_preferred":[
        "\u09ac\u09c0\u09b0\u0997\u09be\u0981\u0993"
    ],
    "name:deu_x_preferred":[
        "Birgaon"
    ],
    "name:ita_x_preferred":[
        "Birgaon"
    ],
    "name:msa_x_preferred":[
        "Birgaon"
    ],
    "name:new_x_preferred":[
        "\u0935\u0940\u0930\u0917\u093e\u0935\u0902"
    ],
    "name:nld_x_preferred":[
        "Birgaon"
    ],
    "name:por_x_preferred":[
        "Birgaon"
    ],
    "name:spa_x_preferred":[
        "Birgaon"
    ],
    "name:swe_x_preferred":[
        "Birgaon"
    ],
    "name:tgl_x_preferred":[
        "Birgaon"
    ],
    "name:urd_x_preferred":[
        "\u0628\u0631\u06af\u0627\u0624\u06ba"
    ],
    "name:vie_x_preferred":[
        "Birgaon"
    ],
    "name:zho_x_preferred":[
        "\u6bd4\u5c14\u52a0\u5965\u6069"
    ],
    "wof:name":"Birgaon",
    "wof:placetype":"locality"
},
  "geometry": {"coordinates":[90.97435,23.95099],"type":"Point"}
}