{
  "type": "Feature",
  "properties": {
    "gn:admin1_code":"87",
    "gn:admin2_code":"5594.0",
    "gn:admin3_code":"559408.0",
    "gn:admin4_code":"55940842.0",
    "gn:asciiname":"Bahmanbari",
    "gn:country_code":"BD",
    "gn:dem":54,
    "gn:feature_class":"P",
    "gn:feature_code":"PPL",
    "gn:name":"B\u0101hm\u0101nb\u0101ri",
    "gn:population":0,
    "gn:timezone":"Asia/Dhaka",
    "iso:country":"BD",
    "name:ben_x_preferred":[
        "B\u0101hm\u0101nb\u0101ri"
    ],
    "wof:name":"Bahmanbari",
    "wof:placetype":"locality"
},
  "geometry": {"coordinates":[88.25511,26.02117],"type":"Point"}
}