{
  "type": "Feature",
  "properties": {
    "gn:admin1_code":"87",
    "gn:admin2_code":"5573.0",
    "gn:admin3_code":"557336.0",
    "gn:admin4_code":"55733680.0",
    "gn:asciiname":"Mirganj",
    "gn:country_code":"BD",
    "gn:dem":53,
    "gn:feature_class":"P",
    "gn:feature_code":"PPL",
    "gn:name":"Mirganj",
    "gn:population":0,
    "gn:timezone":"Asia/Dhaka",
    "iso:country":"BD",
    "name:ben_x_preferred":[
        "Mirganj"
    ],
    "wof:name":"Mirganj",
    "wof:placetype":"locality"
},
  "geometry": {"coordinates":[88.90489000000002,26.05823],"type":"Point"}
}