{
  "type": "Feature",
  "properties": {
    "gn:admin1_code":"83",
    "gn:admin2_code":"5069",
    "gn:admin3_code":"506944.0",
    "gn:admin4_code":"50694419.0",
    "gn:asciiname":"Malluk Chandpur",
    "gn:cc2":"BD",
    "gn:country_code":"BD",
    "gn:dem":9,
    "gn:feature_class":"P",
    "gn:feature_code":"PPL",
    "gn:name":"Malluk Ch\u0101ndpur",
    "gn:population":0,
    "gn:timezone":"Asia/Dhaka",
    "iso:country":"BD",
    "name:und_x_variant":[
        "Mullukchandpur",
        "Malluk Ch\u0101ndpur"
    ],
    "wof:name":"Malluk Chandpur",
    "wof:placetype":"locality"
},
  "geometry": {"coordinates":[88.90000000000001,24.11667000000001],"type":"Point"}
}