{
  "type": "Feature",
  "properties": {
    "gn:admin1_code":"00",
    "gn:asciiname":"Gokshurdi",
    "gn:cc2":"BD",
    "gn:country_code":"BD",
    "gn:dem":1,
    "gn:feature_class":"P",
    "gn:feature_code":"PPL",
    "gn:name":"Gokshurdi",
    "gn:population":0,
    "gn:timezone":"Asia/Dhaka",
    "iso:country":"BD",
    "name:und_x_variant":[
        "Gokhurdi",
        "Gokshurdi"
    ],
    "wof:name":"Gokshurdi",
    "wof:placetype":"locality"
},
  "geometry": {"coordinates":[90.61667,23.18333],"type":"Point"}
}