{
  "type": "Feature",
  "properties": {
    "gn:admin1_code":"86",
    "gn:admin2_code":"6036",
    "gn:admin3_code":"603677.0",
    "gn:admin4_code":"60367787.0",
    "gn:asciiname":"Kubajpur",
    "gn:cc2":"BD",
    "gn:country_code":"BD",
    "gn:dem":9,
    "gn:feature_class":"P",
    "gn:feature_code":"PPL",
    "gn:name":"Kub\u0101jpur",
    "gn:population":0,
    "gn:timezone":"Asia/Dhaka",
    "iso:country":"BD",
    "name:und_x_variant":[
        "Kubijpur",
        "Kub\u0101jpur"
    ],
    "wof:name":"Kubajpur",
    "wof:placetype":"locality"
},
  "geometry": {"coordinates":[91.55,24.46667],"type":"Point"}
}