{
  "type": "Feature",
  "properties": {
    "gn:admin1_code":"H",
    "gn:admin2_code":"3061.0",
    "gn:admin3_code":"306122.0",
    "gn:admin4_code":"30612218.0",
    "gn:asciiname":"Baraigaon",
    "gn:country_code":"BD",
    "gn:dem":15,
    "gn:feature_class":"P",
    "gn:feature_code":"PPL",
    "gn:name":"B\u0101raigaon",
    "gn:population":0,
    "gn:timezone":"Asia/Dhaka",
    "iso:country":"BD",
    "wof:name":"Baraigaon",
    "wof:placetype":"locality"
},
  "geometry": {"coordinates":[90.61704,24.35095],"type":"Point"}
}