{
  "type": "Feature",
  "properties": {
    "gn:admin1_code":"87",
    "gn:admin2_code":"5577.0",
    "gn:admin3_code":"557773.0",
    "gn:admin4_code":"55777347.0",
    "gn:asciiname":"Baguladangi",
    "gn:country_code":"BD",
    "gn:dem":77,
    "gn:feature_class":"P",
    "gn:feature_code":"PPL",
    "gn:name":"Bagul\u0101d\u0101ngi",
    "gn:population":0,
    "gn:timezone":"Asia/Dhaka",
    "iso:country":"BD",
    "name:ben_x_preferred":[
        "Bagul\u0101d\u0101ngi"
    ],
    "name:und_x_variant":[
        "Baguladanga"
    ],
    "wof:name":"Baguladangi",
    "wof:placetype":"locality"
},
  "geometry": {"coordinates":[88.68518,26.35701],"type":"Point"}
}