{
  "type": "Feature",
  "properties": {
    "gn:admin1_code":"83",
    "gn:admin2_code":"5064.0",
    "gn:admin3_code":"506447.0",
    "gn:admin4_code":"50644754.0",
    "gn:asciiname":"Dhantala",
    "gn:country_code":"BD",
    "gn:dem":20,
    "gn:feature_class":"P",
    "gn:feature_code":"PPL",
    "gn:name":"Dhantala",
    "gn:population":0,
    "gn:timezone":"Asia/Dhaka",
    "iso:country":"BD",
    "name:ben_x_preferred":[
        "Dhantala"
    ],
    "wof:name":"Dhantala",
    "wof:placetype":"locality"
},
  "geometry": {"coordinates":[88.6799,24.75697000000001],"type":"Point"}
}