{
  "type": "Feature",
  "properties": {
    "gn:admin1_code":"81",
    "gn:admin2_code":"3033",
    "gn:admin3_code":"303336.0",
    "gn:admin4_code":"30333651.0",
    "gn:asciiname":"Pakiaba",
    "gn:country_code":"BD",
    "gn:dem":16,
    "gn:feature_class":"P",
    "gn:feature_code":"PPL",
    "gn:name":"P\u0101ki\u0101ba",
    "gn:population":0,
    "gn:timezone":"Asia/Dhaka",
    "iso:country":"BD",
    "wof:name":"Pakiaba",
    "wof:placetype":"locality"
},
  "geometry": {"coordinates":[90.61966,24.17047],"type":"Point"}
}