{
  "type": "Feature",
  "properties": {
    "gn:admin1_code":"81",
    "gn:admin2_code":"3093.0",
    "gn:admin3_code":"309357.0",
    "gn:admin4_code":"30935728.0",
    "gn:asciiname":"Haldia",
    "gn:country_code":"BD",
    "gn:dem":26,
    "gn:feature_class":"P",
    "gn:feature_code":"PPL",
    "gn:name":"H\u0101ldia",
    "gn:population":0,
    "gn:timezone":"Asia/Dhaka",
    "iso:country":"BD",
    "name:ben_x_preferred":[
        "\u09b9\u09b2\u09a6\u09bf\u09af\u09bc\u09be"
    ],
    "name:bih_x_preferred":[
        "\u0939\u0932\u094d\u0926\u093f\u092f\u093e"
    ],
    "name:bpy_x_preferred":[
        "\u09b9\u09b2\u09a6\u09bf\u09af\u09bc\u09be"
    ],
    "name:ceb_x_preferred":[
        "Haldia"
    ],
    "name:deu_x_preferred":[
        "Haldia"
    ],
    "name:fas_x_preferred":[
        "\u0647\u0627\u0644\u062f\u06cc\u0627"
    ],
    "name:fra_x_preferred":[
        "Haldia"
    ],
    "name:hin_x_preferred":[
        "\u0939\u0932\u094d\u0926\u093f\u092f\u093e"
    ],
    "name:ita_x_preferred":[
        "Haldia"
    ],
    "name:jpn_x_preferred":[
        "\u30cf\u30eb\u30c7\u30a3\u30a2"
    ],
    "name:kat_x_preferred":[
        "\u10f0\u10d0\u10da\u10d3\u10d8\u10d0"
    ],
    "name:mlg_x_preferred":[
        "Haldia"
    ],
    "name:msa_x_preferred":[
        "Haldia"
    ],
    "name:new_x_preferred":[
        "\u0939\u0932\u094d\u0926\u093f\u092f\u093e"
    ],
    "name:nno_x_preferred":[
        "Haldia"
    ],
    "name:pam_x_preferred":[
        "Haldia"
    ],
    "name:ron_x_preferred":[
        "Haldia"
    ],
    "name:rus_x_preferred":[
        "\u0425\u0430\u043b\u0434\u0438\u044f"
    ],
    "name:srp_x_preferred":[
        "\u0425\u0430\u043b\u0434\u0438\u0458\u0430"
    ],
    "name:swe_x_preferred":[
        "Haldia"
    ],
    "name:ukr_x_preferred":[
        "\u0425\u0430\u043b\u0434\u0456\u044f"
    ],
    "name:vie_x_preferred":[
        "Haldia"
    ],
    "name:war_x_preferred":[
        "Haldia"
    ],
    "name:zho_x_preferred":[
        "\u970d\u723e\u8fea\u4e9e"
    ],
    "wof:name":"Haldia",
    "wof:placetype":"locality"
},
  "geometry": {"coordinates":[90.09142,24.59753],"type":"Point"}
}