{
  "type": "Feature",
  "properties": {
    "gn:admin1_code":"81",
    "gn:admin2_code":"3056.0",
    "gn:admin3_code":"305610.0",
    "gn:admin4_code":"30561019.0",
    "gn:asciiname":"Ram Narayanpur",
    "gn:country_code":"BD",
    "gn:dem":6,
    "gn:feature_class":"P",
    "gn:feature_code":"PPL",
    "gn:name":"R\u0101m N\u0101r\u0101yanpur",
    "gn:population":0,
    "gn:timezone":"Asia/Dhaka",
    "iso:country":"BD",
    "name:ben_x_preferred":[
        "R\u0101m N\u0101r\u0101yanpur"
    ],
    "wof:name":"Ram Narayanpur",
    "wof:placetype":"locality"
},
  "geometry": {"coordinates":[89.70307,23.94453],"type":"Point"}
}