{
  "type": "Feature",
  "properties": {
    "gn:admin1_code":"84",
    "gn:admin2_code":"2051",
    "gn:admin3_code":"205165.0",
    "gn:admin4_code":"20516514.0",
    "gn:asciiname":"Ramsinghapur",
    "gn:country_code":"BD",
    "gn:dem":14,
    "gn:feature_class":"P",
    "gn:feature_code":"PPL",
    "gn:name":"R\u0101msinghapur",
    "gn:population":0,
    "gn:timezone":"Asia/Dhaka",
    "iso:country":"BD",
    "name:und_x_variant":[
        "R\u0101msinghapur",
        "R\u0101msinhapur"
    ],
    "wof:name":"Ramsinghapur",
    "wof:placetype":"locality"
},
  "geometry": {"coordinates":[90.92877,23.11673],"type":"Point"}
}