{
  "type": "Feature",
  "properties": {
    "gn:admin1_code":"82",
    "gn:admin2_code":"4055",
    "gn:admin3_code":"405585.0",
    "gn:admin4_code":"40558535.0",
    "gn:asciiname":"Masakhali",
    "gn:country_code":"BD",
    "gn:dem":6,
    "gn:feature_class":"P",
    "gn:feature_code":"PPL",
    "gn:name":"Masakh\u0101li",
    "gn:population":0,
    "gn:timezone":"Asia/Dhaka",
    "iso:country":"BD",
    "wof:name":"Masakhali",
    "wof:placetype":"locality"
},
  "geometry": {"coordinates":[89.28333000000001,23.41667],"type":"Point"}
}