{
  "type": "Feature",
  "properties": {
    "gn:admin1_code":"82",
    "gn:admin2_code":"4047.0",
    "gn:admin3_code":"404794.0",
    "gn:admin4_code":"40479467.0",
    "gn:asciiname":"Mandalganti",
    "gn:country_code":"BD",
    "gn:dem":8,
    "gn:feature_class":"P",
    "gn:feature_code":"PPL",
    "gn:name":"Mandalg\u0101nti",
    "gn:population":0,
    "gn:timezone":"Asia/Dhaka",
    "iso:country":"BD",
    "name:ben_x_preferred":[
        "Mandalg\u0101nti"
    ],
    "wof:name":"Mandalganti",
    "wof:placetype":"locality"
},
  "geometry": {"coordinates":[89.67354,22.91151],"type":"Point"}
}