{
  "type": "Feature",
  "properties": {
    "gn:admin1_code":"84",
    "gn:admin2_code":"2015.0",
    "gn:admin3_code":"201508.0",
    "gn:admin4_code":"20150894.0",
    "gn:asciiname":"Jaliakhali",
    "gn:country_code":"BD",
    "gn:dem":3,
    "gn:feature_class":"P",
    "gn:feature_code":"PPL",
    "gn:name":"Jali\u0101kh\u0101li",
    "gn:population":0,
    "gn:timezone":"Asia/Dhaka",
    "iso:country":"BD",
    "name:ben_x_preferred":[
        "Jali\u0101kh\u0101li"
    ],
    "name:ben_x_variant":[
        "Jali\u0101kh\u0101ll"
    ],
    "wof:name":"Jaliakhali",
    "wof:placetype":"locality"
},
  "geometry": {"coordinates":[91.93625,21.97726],"type":"Point"}
}