{
  "type": "Feature",
  "properties": {
    "gn:admin1_code":"83",
    "gn:admin2_code":"5081",
    "gn:admin3_code":"508134.0",
    "gn:admin4_code":"50813447.0",
    "gn:asciiname":"Mollapara",
    "gn:country_code":"BD",
    "gn:dem":35,
    "gn:feature_class":"P",
    "gn:feature_code":"PPL",
    "gn:name":"Moll\u0101p\u0101ra",
    "gn:population":0,
    "gn:timezone":"Asia/Dhaka",
    "iso:country":"BD",
    "name:ben_x_preferred":[
        "Moll\u0101p\u0101ra"
    ],
    "wof:name":"Mollapara",
    "wof:placetype":"locality"
},
  "geometry": {"coordinates":[88.39031999999997,24.46753],"type":"Point"}
}