{
  "type": "Feature",
  "properties": {
    "gn:admin1_code":"81",
    "gn:admin2_code":"3082.0",
    "gn:admin3_code":"308229.0",
    "gn:admin4_code":"30822938.0",
    "gn:asciiname":"Dakshin Daulatdia",
    "gn:country_code":"BD",
    "gn:dem":14,
    "gn:feature_class":"P",
    "gn:feature_code":"PPL",
    "gn:name":"Dakshin Daulatdia",
    "gn:population":0,
    "gn:timezone":"Asia/Dhaka",
    "iso:country":"BD",
    "wof:name":"Dakshin Daulatdia",
    "wof:placetype":"locality"
},
  "geometry": {"coordinates":[89.77072,23.75041],"type":"Point"}
}