{
  "type": "Feature",
  "properties": {
    "gn:admin1_code":"87",
    "gn:admin2_code":"5573",
    "gn:admin3_code":"557345.0",
    "gn:admin4_code":"55734525.0",
    "gn:asciiname":"Uttar Barabhita",
    "gn:country_code":"BD",
    "gn:dem":48,
    "gn:feature_class":"P",
    "gn:feature_code":"PPL",
    "gn:name":"Uttar Barabhita",
    "gn:population":0,
    "gn:timezone":"Asia/Dhaka",
    "iso:country":"BD",
    "name:ben_x_preferred":[
        "Uttar Barabhita"
    ],
    "wof:name":"Uttar Barabhita",
    "wof:placetype":"locality"
},
  "geometry": {"coordinates":[89.02905,25.95373],"type":"Point"}
}