{
  "type": "Feature",
  "properties": {
    "gn:admin1_code":"87",
    "gn:admin2_code":"5527.0",
    "gn:admin3_code":"552710.0",
    "gn:admin4_code":"55271047.0",
    "gn:asciiname":"Achal Kol",
    "gn:country_code":"BD",
    "gn:dem":26,
    "gn:feature_class":"P",
    "gn:feature_code":"PPL",
    "gn:name":"\u0100chal Kol",
    "gn:population":0,
    "gn:timezone":"Asia/Dhaka",
    "iso:country":"BD",
    "name:ben_x_preferred":[
        "\u0100chal Kol"
    ],
    "wof:name":"Achal Kol",
    "wof:placetype":"locality"
},
  "geometry": {"coordinates":[88.91235999999998,25.32827],"type":"Point"}
}