{
  "type": "Feature",
  "properties": {
    "gn:admin1_code":"82",
    "gn:admin2_code":"4065.0",
    "gn:admin3_code":"406552.0",
    "gn:admin4_code":"40655231.0",
    "gn:asciiname":"Palokhali",
    "gn:country_code":"BD",
    "gn:dem":12,
    "gn:feature_class":"P",
    "gn:feature_code":"PPL",
    "gn:name":"P\u0101lokh\u0101li",
    "gn:population":0,
    "gn:timezone":"Asia/Dhaka",
    "iso:country":"BD",
    "name:ben_x_preferred":[
        "P\u0101lokh\u0101li"
    ],
    "wof:name":"Palokhali",
    "wof:placetype":"locality"
},
  "geometry": {"coordinates":[89.59144999999999,23.1916],"type":"Point"}
}