{
  "type": "Feature",
  "properties": {
    "gn:admin1_code":"81",
    "gn:admin2_code":"3082.0",
    "gn:admin3_code":"308229.0",
    "gn:admin4_code":"30822957.0",
    "gn:asciiname":"Sibrampur",
    "gn:country_code":"BD",
    "gn:dem":14,
    "gn:feature_class":"P",
    "gn:feature_code":"PPL",
    "gn:name":"Sibr\u0101mpur",
    "gn:population":0,
    "gn:timezone":"Asia/Dhaka",
    "iso:country":"BD",
    "name:ben_x_preferred":[
        "Sibr\u0101mpur"
    ],
    "wof:name":"Sibrampur",
    "wof:placetype":"locality"
},
  "geometry": {"coordinates":[89.74889,23.77815],"type":"Point"}
}