{
  "type": "Feature",
  "properties": {
    "gn:admin1_code":"83",
    "gn:admin2_code":"5064.0",
    "gn:admin3_code":"506469.0",
    "gn:admin4_code":"50646984.0",
    "gn:asciiname":"Bil Haripur",
    "gn:country_code":"BD",
    "gn:dem":19,
    "gn:feature_class":"P",
    "gn:feature_code":"PPL",
    "gn:name":"Bil Haripur",
    "gn:population":0,
    "gn:timezone":"Asia/Dhaka",
    "iso:country":"BD",
    "name:ben_x_preferred":[
        "Bil Haripur"
    ],
    "wof:name":"Bil Haripur",
    "wof:placetype":"locality"
},
  "geometry": {"coordinates":[88.62584,24.80786],"type":"Point"}
}