{
  "type": "Feature",
  "properties": {
    "gn:admin1_code":"87",
    "gn:admin2_code":"5594",
    "gn:admin3_code":"559494.0",
    "gn:admin4_code":"55949417.0",
    "gn:asciiname":"Kismat Saidpur",
    "gn:country_code":"BD",
    "gn:dem":49,
    "gn:feature_class":"P",
    "gn:feature_code":"PPL",
    "gn:name":"Kismat Saidpur",
    "gn:population":0,
    "gn:timezone":"Asia/Dhaka",
    "iso:country":"BD",
    "name:ben_x_preferred":[
        "Kismat Saidpur"
    ],
    "wof:name":"Kismat Saidpur",
    "wof:placetype":"locality"
},
  "geometry": {"coordinates":[88.47053000000002,25.91643],"type":"Point"}
}