{
  "type": "Feature",
  "properties": {
    "gn:admin1_code":"83",
    "gn:admin2_code":"5076.0",
    "gn:admin3_code":"507616.0",
    "gn:admin4_code":"50761652.0",
    "gn:asciiname":"Mashakhalar Char",
    "gn:country_code":"BD",
    "gn:dem":11,
    "gn:feature_class":"P",
    "gn:feature_code":"PPL",
    "gn:name":"Mashakhal\u0101r Char",
    "gn:population":0,
    "gn:timezone":"Asia/Dhaka",
    "iso:country":"BD",
    "name:ben_x_preferred":[
        "Mashakhal\u0101r Char"
    ],
    "wof:name":"Mashakhalar Char",
    "wof:placetype":"locality"
},
  "geometry": {"coordinates":[89.65076999999999,23.85978],"type":"Point"}
}