{
  "type": "Feature",
  "properties": {
    "gn:admin1_code":"83",
    "gn:admin2_code":"5064",
    "gn:admin3_code":"506486.0",
    "gn:admin4_code":"50648679.0",
    "gn:asciiname":"Kuchinda",
    "gn:country_code":"BD",
    "gn:dem":41,
    "gn:feature_class":"P",
    "gn:feature_code":"PPL",
    "gn:name":"Kuchinda",
    "gn:population":0,
    "gn:timezone":"Asia/Dhaka",
    "iso:country":"BD",
    "name:ben_x_preferred":[
        "Kuchinda"
    ],
    "name:ben_x_variant":[
        "\u0995\u09cb\u099a\u09bf\u09a8\u09a6\u09be"
    ],
    "name:bpy_x_preferred":[
        "\u0995\u09cb\u099a\u09bf\u09a8\u09a6\u09be"
    ],
    "name:ceb_x_preferred":[
        "Kochinda"
    ],
    "name:ita_x_preferred":[
        "Kochinda"
    ],
    "name:lit_x_preferred":[
        "Ko\u010dinda"
    ],
    "name:msa_x_preferred":[
        "Kochinda"
    ],
    "name:nld_x_preferred":[
        "Kochinda"
    ],
    "name:ori_x_preferred":[
        "\u0b15\u0b41\u0b1a\u0b3f\u0b23\u0b4d\u0b21\u0b3e"
    ],
    "name:por_x_preferred":[
        "Kochinda"
    ],
    "name:swe_x_preferred":[
        "Kochinda"
    ],
    "name:vie_x_preferred":[
        "Kochinda"
    ],
    "name:zho_x_preferred":[
        "\u79d1\u94a6\u8fbe"
    ],
    "wof:name":"Kuchinda",
    "wof:placetype":"locality"
},
  "geometry": {"coordinates":[88.59263,25.13277],"type":"Point"}
}