{
  "type": "Feature",
  "properties": {
    "gn:admin1_code":"82",
    "gn:admin2_code":"4050.0",
    "gn:admin3_code":"405094.0",
    "gn:admin4_code":"40509465.0",
    "gn:asciiname":"Parbholadanga",
    "gn:country_code":"BD",
    "gn:dem":22,
    "gn:feature_class":"P",
    "gn:feature_code":"PPL",
    "gn:name":"Parbhol\u0101d\u0101nga",
    "gn:population":0,
    "gn:timezone":"Asia/Dhaka",
    "iso:country":"BD",
    "name:ben_x_preferred":[
        "Parbhol\u0101d\u0101nga"
    ],
    "wof:name":"Parbholadanga",
    "wof:placetype":"locality"
},
  "geometry": {"coordinates":[88.87199,23.85168],"type":"Point"}
}