{
  "type": "Feature",
  "properties": {
    "gn:admin1_code":"83",
    "gn:admin2_code":"5064.0",
    "gn:admin3_code":"506479.0",
    "gn:admin4_code":"50647947.0",
    "gn:asciiname":"Gundail",
    "gn:country_code":"BD",
    "gn:dem":20,
    "gn:feature_class":"P",
    "gn:feature_code":"PPL",
    "gn:name":"Gundail",
    "gn:population":0,
    "gn:timezone":"Asia/Dhaka",
    "iso:country":"BD",
    "name:ben_x_preferred":[
        "Gandul"
    ],
    "name:ben_x_variant":[
        "Gundail"
    ],
    "wof:name":"Gundail",
    "wof:placetype":"locality"
},
  "geometry": {"coordinates":[88.63518000000001,24.96708],"type":"Point"}
}