{
  "type": "Feature",
  "properties": {
    "gn:admin1_code":"84",
    "gn:admin2_code":"2022",
    "gn:admin3_code":"202290.0",
    "gn:admin4_code":"20229031.0",
    "gn:asciiname":"Ledhapara",
    "gn:country_code":"BD",
    "gn:dem":10,
    "gn:feature_class":"P",
    "gn:feature_code":"PPL",
    "gn:name":"Ledh\u0101p\u0101ra",
    "gn:population":0,
    "gn:timezone":"Asia/Dhaka",
    "iso:country":"BD",
    "wof:name":"Ledhapara",
    "wof:placetype":"locality"
},
  "geometry": {"coordinates":[92.25,20.96667],"type":"Point"}
}