{
  "type": "Feature",
  "properties": {
    "gn:admin1_code":"85",
    "gn:admin2_code":"1042.0",
    "gn:admin3_code":"104273.0",
    "gn:admin4_code":"10427310.0",
    "gn:asciiname":"Char Bakrabad",
    "gn:country_code":"BD",
    "gn:dem":13,
    "gn:feature_class":"P",
    "gn:feature_code":"PPL",
    "gn:name":"Char Bakr\u0101b\u0101d",
    "gn:population":0,
    "gn:timezone":"Asia/Dhaka",
    "iso:country":"BD",
    "name:und_x_variant":[
        "Char Bakr\u0101b\u0101d",
        "Bakr\u0101b\u0101d Char"
    ],
    "wof:name":"Char Bakrabad",
    "wof:placetype":"locality"
},
  "geometry": {"coordinates":[90.36985,22.63633],"type":"Point"}
}