{
  "type": "Feature",
  "properties": {
    "gn:admin1_code":"84",
    "gn:admin2_code":"2022.0",
    "gn:admin3_code":"202216.0",
    "gn:admin4_code":"20221639.0",
    "gn:asciiname":"Umkhali",
    "gn:country_code":"BD",
    "gn:dem":7,
    "gn:feature_class":"P",
    "gn:feature_code":"PPL",
    "gn:name":"Umkh\u0101li",
    "gn:population":0,
    "gn:timezone":"Asia/Dhaka",
    "iso:country":"BD",
    "name:ben_x_preferred":[
        "Umkh\u0101li"
    ],
    "wof:name":"Umkhali",
    "wof:placetype":"locality"
},
  "geometry": {"coordinates":[92.03986999999999,21.7464],"type":"Point"}
}