{
  "type": "Feature",
  "properties": {
    "gn:admin1_code":"83",
    "gn:admin2_code":"5081.0",
    "gn:admin3_code":"508172.0",
    "gn:admin4_code":"50817207.0",
    "gn:asciiname":"Baragachhi",
    "gn:country_code":"BD",
    "gn:dem":20,
    "gn:feature_class":"P",
    "gn:feature_code":"PPL",
    "gn:name":"Barag\u0101chhi",
    "gn:population":0,
    "gn:timezone":"Asia/Dhaka",
    "iso:country":"BD",
    "name:ben_x_preferred":[
        "Barag\u0101chhi"
    ],
    "name:ben_x_variant":[
        "Barg\u0101chhi"
    ],
    "wof:name":"Baragachhi",
    "wof:placetype":"locality"
},
  "geometry": {"coordinates":[88.66424000000001,24.47061],"type":"Point"}
}