{
  "type": "Feature",
  "properties": {
    "gn:admin1_code":"H",
    "gn:admin2_code":"3072",
    "gn:admin3_code":"307204.0",
    "gn:admin4_code":"30720447.0",
    "gn:asciiname":"Nasibpur",
    "gn:country_code":"BD",
    "gn:dem":13,
    "gn:feature_class":"P",
    "gn:feature_code":"PPL",
    "gn:name":"Nasibpur",
    "gn:population":0,
    "gn:timezone":"Asia/Dhaka",
    "iso:country":"BD",
    "name:und_x_variant":[
        "Nasibpur Gandharbbapur",
        "Nasibpur"
    ],
    "wof:name":"Nasibpur",
    "wof:placetype":"locality"
},
  "geometry": {"coordinates":[90.79864000000001,24.80999],"type":"Point"}
}