{
  "type": "Feature",
  "properties": {
    "gn:admin1_code":"81",
    "gn:admin2_code":"3054",
    "gn:admin3_code":"305440.0",
    "gn:admin4_code":"30544037.0",
    "gn:asciiname":"Maheraddir Char",
    "gn:country_code":"BD",
    "gn:dem":10,
    "gn:feature_class":"P",
    "gn:feature_code":"PPL",
    "gn:name":"Maheraddir Char",
    "gn:population":0,
    "gn:timezone":"Asia/Dhaka",
    "iso:country":"BD",
    "name:und_x_variant":[
        "Maharaddi Char",
        "Maharaddir Char",
        "Maheraddir Char"
    ],
    "wof:name":"Maheraddir Char",
    "wof:placetype":"locality"
},
  "geometry": {"coordinates":[90.3061,23.09247],"type":"Point"}
}