{
  "type": "Feature",
  "properties": {
    "gn:admin1_code":"83",
    "gn:admin2_code":"5064.0",
    "gn:admin3_code":"506450.0",
    "gn:admin4_code":"50645047.0",
    "gn:asciiname":"Harpur",
    "gn:country_code":"BD",
    "gn:dem":27,
    "gn:feature_class":"P",
    "gn:feature_code":"PPL",
    "gn:name":"H\u0101rpur",
    "gn:population":0,
    "gn:timezone":"Asia/Dhaka",
    "iso:country":"BD",
    "name:ben_x_preferred":[
        "H\u0101rpur"
    ],
    "name:new_x_preferred":[
        "\u0939\u0930\u094d\u092a\u0941\u0930"
    ],
    "wof:name":"Harpur",
    "wof:placetype":"locality"
},
  "geometry": {"coordinates":[88.72466999999997,25.01108],"type":"Point"}
}