{
  "type": "Feature",
  "properties": {
    "gn:admin1_code":"81",
    "gn:admin2_code":"3026",
    "gn:admin3_code":"302662.0",
    "gn:admin4_code":"30266294.0",
    "gn:asciiname":"Ulmanchandra",
    "gn:country_code":"BD",
    "gn:dem":9,
    "gn:feature_class":"P",
    "gn:feature_code":"PPL",
    "gn:name":"Ulm\u0101nch\u0101ndra",
    "gn:population":0,
    "gn:timezone":"Asia/Dhaka",
    "iso:country":"BD",
    "wof:name":"Ulmanchandra",
    "wof:placetype":"locality"
},
  "geometry": {"coordinates":[90.2064,23.68679],"type":"Point"}
}