{
  "type": "Feature",
  "properties": {
    "gn:admin1_code":"82",
    "gn:admin2_code":"4018.0",
    "gn:admin3_code":"401831.0",
    "gn:admin4_code":"40183171.0",
    "gn:asciiname":"Thakurpur",
    "gn:country_code":"BD",
    "gn:dem":16,
    "gn:feature_class":"P",
    "gn:feature_code":"PPL",
    "gn:name":"Thakurpur",
    "gn:population":0,
    "gn:timezone":"Asia/Dhaka",
    "iso:country":"BD",
    "name:ben_x_preferred":[
        "Thakurpur"
    ],
    "wof:name":"Thakurpur",
    "wof:placetype":"locality"
},
  "geometry": {"coordinates":[88.68316,23.5526],"type":"Point"}
}