{
  "type": "Feature",
  "properties": {
    "gn:admin1_code":"84",
    "gn:admin2_code":"2003.0",
    "gn:admin3_code":"200351.0",
    "gn:admin4_code":"20035163.0",
    "gn:asciiname":"Kyauktai",
    "gn:country_code":"BD",
    "gn:dem":23,
    "gn:feature_class":"P",
    "gn:feature_code":"PPL",
    "gn:name":"Kyauktai",
    "gn:population":0,
    "gn:timezone":"Asia/Dhaka",
    "iso:country":"BD",
    "name:ben_x_preferred":[
        "Kyauktai"
    ],
    "wof:name":"Kyauktai",
    "wof:placetype":"locality"
},
  "geometry": {"coordinates":[92.21760999999999,21.76367],"type":"Point"}
}