{
  "type": "Feature",
  "properties": {
    "gn:admin1_code":"82",
    "gn:admin2_code":"4001.0",
    "gn:admin3_code":"400160.0",
    "gn:admin4_code":"40016041.0",
    "gn:asciiname":"Hoglabunia",
    "gn:country_code":"BD",
    "gn:dem":10,
    "gn:feature_class":"P",
    "gn:feature_code":"PPL",
    "gn:name":"Hoglabunia",
    "gn:population":0,
    "gn:timezone":"Asia/Dhaka",
    "iso:country":"BD",
    "name:ben_x_preferred":[
        "Hoglabunia"
    ],
    "wof:name":"Hoglabunia",
    "wof:placetype":"locality"
},
  "geometry": {"coordinates":[89.92933000000002,22.46609],"type":"Point"}
}