{
  "type": "Feature",
  "properties": {
    "gn:admin1_code":"82",
    "gn:asciiname":"Charkhali",
    "gn:country_code":"BD",
    "gn:dem":9,
    "gn:feature_class":"P",
    "gn:feature_code":"PPL",
    "gn:name":"Charkh\u0101li",
    "gn:population":0,
    "gn:timezone":"Asia/Dhaka",
    "iso:country":"BD",
    "name:ben_x_preferred":[
        "Charkh\u0101li"
    ],
    "wof:name":"Charkhali",
    "wof:placetype":"locality"
},
  "geometry": {"coordinates":[90.27574,22.2117],"type":"Point"}
}