{
  "type": "Feature",
  "properties": {
    "gn:admin1_code":"82",
    "gn:admin2_code":"4041.0",
    "gn:admin3_code":"404147.0",
    "gn:admin4_code":"40414765.0",
    "gn:asciiname":"Ghona",
    "gn:country_code":"BD",
    "gn:dem":13,
    "gn:feature_class":"P",
    "gn:feature_code":"PPL",
    "gn:name":"Ghona",
    "gn:population":0,
    "gn:timezone":"Asia/Dhaka",
    "iso:country":"BD",
    "name:ben_x_preferred":[
        "Ghona"
    ],
    "wof:name":"Ghona",
    "wof:placetype":"locality"
},
  "geometry": {"coordinates":[89.18134999999999,23.22697],"type":"Point"}
}