{
  "type": "Feature",
  "properties": {
    "gn:admin1_code":"84",
    "gn:admin2_code":"2019.0",
    "gn:admin3_code":"201968.0",
    "gn:admin4_code":"20196807.0",
    "gn:asciiname":"Baral",
    "gn:country_code":"BD",
    "gn:dem":14,
    "gn:feature_class":"P",
    "gn:feature_code":"PPL",
    "gn:name":"Baral",
    "gn:population":0,
    "gn:timezone":"Asia/Dhaka",
    "iso:country":"BD",
    "wof:name":"Baral",
    "wof:placetype":"locality"
},
  "geometry": {"coordinates":[91.15000000000001,23.31667],"type":"Point"}
}