{
  "type": "Feature",
  "properties": {
    "gn:admin1_code":"H",
    "gn:admin2_code":"3039",
    "gn:admin3_code":"303907.0",
    "gn:admin4_code":"30390723.0",
    "gn:asciiname":"Rajendraganj",
    "gn:country_code":"BD",
    "gn:dem":23,
    "gn:feature_class":"P",
    "gn:feature_code":"PPL",
    "gn:name":"Rajendraganj",
    "gn:population":0,
    "gn:timezone":"Asia/Dhaka",
    "iso:country":"BD",
    "name:und_x_variant":[
        "R\u0101jendraganj"
    ],
    "wof:name":"Rajendraganj",
    "wof:placetype":"locality"
},
  "geometry": {"coordinates":[89.85944000000001,25.19317],"type":"Point"}
}