{
  "type": "Feature",
  "properties": {
    "gn:admin1_code":"87",
    "gn:admin2_code":"5573",
    "gn:admin3_code":"557364.0",
    "gn:admin4_code":"55736450.0",
    "gn:asciiname":"Kundapukur",
    "gn:country_code":"BD",
    "gn:dem":48,
    "gn:feature_class":"P",
    "gn:feature_code":"PPL",
    "gn:name":"Kundapukur",
    "gn:population":0,
    "gn:timezone":"Asia/Dhaka",
    "iso:country":"BD",
    "name:ben_x_preferred":[
        "Kundapukur"
    ],
    "wof:name":"Kundapukur",
    "wof:placetype":"locality"
},
  "geometry": {"coordinates":[88.81491,25.90782],"type":"Point"}
}