{
  "type": "Feature",
  "properties": {
    "gn:admin1_code":"81",
    "gn:admin2_code":"3026",
    "gn:admin3_code":"302672.0",
    "gn:admin4_code":"30267289.0",
    "gn:asciiname":"Rajaghat",
    "gn:country_code":"BD",
    "gn:dem":12,
    "gn:feature_class":"P",
    "gn:feature_code":"PPL",
    "gn:name":"R\u0101j\u0101gh\u0101t",
    "gn:population":0,
    "gn:timezone":"Asia/Dhaka",
    "iso:country":"BD",
    "wof:name":"Rajaghat",
    "wof:placetype":"locality"
},
  "geometry": {"coordinates":[90.26237999999999,23.808],"type":"Point"}
}