{
  "type": "Feature",
  "properties": {
    "gn:admin1_code":"82",
    "gn:admin2_code":"4001.0",
    "gn:admin3_code":"400158.0",
    "gn:admin4_code":"40015829.0",
    "gn:asciiname":"Haldibunia",
    "gn:country_code":"BD",
    "gn:dem":5,
    "gn:feature_class":"P",
    "gn:feature_code":"PPL",
    "gn:name":"Haldibunia",
    "gn:population":0,
    "gn:timezone":"Asia/Dhaka",
    "iso:country":"BD",
    "name:ben_x_preferred":[
        "Haldibunia"
    ],
    "wof:name":"Haldibunia",
    "wof:placetype":"locality"
},
  "geometry": {"coordinates":[89.64538,22.4265],"type":"Point"}
}