{
  "type": "Feature",
  "properties": {
    "gn:admin1_code":"82",
    "gn:admin2_code":"4055",
    "gn:admin3_code":"405566.0",
    "gn:admin4_code":"40556663.0",
    "gn:asciiname":"Khurd Fulbari",
    "gn:country_code":"BD",
    "gn:dem":11,
    "gn:feature_class":"P",
    "gn:feature_code":"PPL",
    "gn:name":"Khurd Fulb\u0101ri",
    "gn:population":0,
    "gn:timezone":"Asia/Dhaka",
    "iso:country":"BD",
    "name:und_x_variant":[
        "Khorda Fulbari",
        "Khord Fulbari",
        "Khurd Fulb\u0101ri"
    ],
    "wof:name":"Khurd Fulbari",
    "wof:placetype":"locality"
},
  "geometry": {"coordinates":[89.54043,23.34931],"type":"Point"}
}