{
  "type": "Feature",
  "properties": {
    "gn:admin1_code":"87",
    "gn:admin2_code":"5552.0",
    "gn:admin3_code":"555270.0",
    "gn:admin4_code":"55527067.0",
    "gn:asciiname":"Tengnamari",
    "gn:country_code":"BD",
    "gn:dem":62,
    "gn:feature_class":"P",
    "gn:feature_code":"PPL",
    "gn:name":"Tengn\u0101m\u0101ri",
    "gn:population":0,
    "gn:timezone":"Asia/Dhaka",
    "iso:country":"BD",
    "name:ben_x_preferred":[
        "Tengn\u0101m\u0101ri"
    ],
    "wof:name":"Tengnamari",
    "wof:placetype":"locality"
},
  "geometry": {"coordinates":[89.02768,26.36694],"type":"Point"}
}