{
  "type": "Feature",
  "properties": {
    "gn:admin1_code":"H",
    "gn:admin2_code":"3061",
    "gn:admin3_code":"306165.0",
    "gn:admin4_code":"30616569.0",
    "gn:asciiname":"Satasia",
    "gn:country_code":"BD",
    "gn:dem":19,
    "gn:feature_class":"P",
    "gn:feature_code":"PPL",
    "gn:name":"S\u0101t\u0101sia",
    "gn:population":0,
    "gn:timezone":"Asia/Dhaka",
    "iso:country":"BD",
    "wof:name":"Satasia",
    "wof:placetype":"locality"
},
  "geometry": {"coordinates":[90.29112000000001,24.76104],"type":"Point"}
}