{
  "type": "Feature",
  "properties": {
    "gn:admin1_code":"81",
    "gn:admin2_code":"3029",
    "gn:admin3_code":"302947.0",
    "gn:admin4_code":"30294755.0",
    "gn:asciiname":"Rasiknagar",
    "gn:country_code":"BD",
    "gn:dem":11,
    "gn:feature_class":"P",
    "gn:feature_code":"PPL",
    "gn:name":"Rasiknagar",
    "gn:population":0,
    "gn:timezone":"Asia/Dhaka",
    "iso:country":"BD",
    "name:und_x_variant":[
        "Rashiknagar",
        "Rasiknagar"
    ],
    "wof:name":"Rasiknagar",
    "wof:placetype":"locality"
},
  "geometry": {"coordinates":[89.79898,23.54518],"type":"Point"}
}