{
  "type": "Feature",
  "properties": {
    "gn:admin1_code":"83",
    "gn:admin2_code":"5064.0",
    "gn:admin3_code":"506428.0",
    "gn:admin4_code":"50642884.0",
    "gn:asciiname":"Malahar",
    "gn:country_code":"BD",
    "gn:dem":26,
    "gn:feature_class":"P",
    "gn:feature_code":"PPL",
    "gn:name":"M\u0101l\u0101h\u0101r",
    "gn:population":0,
    "gn:timezone":"Asia/Dhaka",
    "iso:country":"BD",
    "name:ben_x_preferred":[
        "M\u0101l\u0101h\u0101r"
    ],
    "wof:name":"Malahar",
    "wof:placetype":"locality"
},
  "geometry": {"coordinates":[88.85049000000002,25.15985],"type":"Point"}
}