{
  "type": "Feature",
  "properties": {
    "gn:admin1_code":"82",
    "gn:admin2_code":"4087.0",
    "gn:admin3_code":"408790.0",
    "gn:admin4_code":"40879023.0",
    "gn:asciiname":"Char Kanaidia",
    "gn:country_code":"BD",
    "gn:dem":8,
    "gn:feature_class":"P",
    "gn:feature_code":"PPL",
    "gn:name":"Char K\u0101n\u0101idia",
    "gn:population":0,
    "gn:timezone":"Asia/Dhaka",
    "iso:country":"BD",
    "wof:name":"Char Kanaidia",
    "wof:placetype":"locality"
},
  "geometry": {"coordinates":[89.28479,22.70135],"type":"Point"}
}