{
  "type": "Feature",
  "properties": {
    "gn:admin1_code":"83",
    "gn:admin2_code":"5064.0",
    "gn:admin3_code":"506447.0",
    "gn:admin4_code":"50644774.0",
    "gn:asciiname":"Jodbazar",
    "gn:country_code":"BD",
    "gn:dem":20,
    "gn:feature_class":"P",
    "gn:feature_code":"PPL",
    "gn:name":"Jodb\u0101zar",
    "gn:population":0,
    "gn:timezone":"Asia/Dhaka",
    "iso:country":"BD",
    "name:ben_x_preferred":[
        "Jodb\u0101zar"
    ],
    "wof:name":"Jodbazar",
    "wof:placetype":"locality"
},
  "geometry": {"coordinates":[88.75243,24.7188],"type":"Point"}
}