{
  "type": "Feature",
  "properties": {
    "gn:admin1_code":"81",
    "gn:admin2_code":"3086",
    "gn:admin3_code":"308665.0",
    "gn:admin4_code":"30866575.0",
    "gn:asciiname":"Jogpata",
    "gn:country_code":"BD",
    "gn:dem":11,
    "gn:feature_class":"P",
    "gn:feature_code":"PPL",
    "gn:name":"Jogp\u0101ta",
    "gn:population":0,
    "gn:timezone":"Asia/Dhaka",
    "iso:country":"BD",
    "wof:name":"Jogpata",
    "wof:placetype":"locality"
},
  "geometry": {"coordinates":[90.41070000000001,23.27679],"type":"Point"}
}