{
  "type": "Feature",
  "properties": {
    "gn:admin1_code":"81",
    "gn:admin2_code":"3054",
    "gn:admin3_code":"305440.0",
    "gn:admin4_code":"30544006.0",
    "gn:asciiname":"Phulbari Gazaria",
    "gn:country_code":"BD",
    "gn:dem":8,
    "gn:feature_class":"P",
    "gn:feature_code":"PPL",
    "gn:name":"Phulbari Gaz\u0101ria",
    "gn:population":0,
    "gn:timezone":"Asia/Dhaka",
    "iso:country":"BD",
    "name:und_x_variant":[
        "Phulbari Gajaria",
        "Phulbari Gaz\u0101ria"
    ],
    "wof:name":"Phulbari Gazaria",
    "wof:placetype":"locality"
},
  "geometry": {"coordinates":[90.25957,23.10968],"type":"Point"}
}