{
  "type": "Feature",
  "properties": {
    "gn:admin1_code":"83",
    "gn:admin2_code":"5081",
    "gn:admin3_code":"508172.0",
    "gn:admin4_code":"50817247.0",
    "gn:asciiname":"Kanaidanga",
    "gn:country_code":"BD",
    "gn:dem":23,
    "gn:feature_class":"P",
    "gn:feature_code":"PPL",
    "gn:name":"K\u0101n\u0101id\u0101nga",
    "gn:population":0,
    "gn:timezone":"Asia/Dhaka",
    "iso:country":"BD",
    "name:ben_x_preferred":[
        "K\u0101n\u0101id\u0101nga"
    ],
    "wof:name":"Kanaidanga",
    "wof:placetype":"locality"
},
  "geometry": {"coordinates":[88.48079,24.38254],"type":"Point"}
}