{
  "type": "Feature",
  "properties": {
    "gn:admin1_code":"81",
    "gn:admin2_code":"3048",
    "gn:admin3_code":"304879.0",
    "gn:admin4_code":"30487985.0",
    "gn:asciiname":"Juniail",
    "gn:country_code":"BD",
    "gn:dem":13,
    "gn:feature_class":"P",
    "gn:feature_code":"PPL",
    "gn:name":"Juni\u0101il",
    "gn:population":0,
    "gn:timezone":"Asia/Dhaka",
    "iso:country":"BD",
    "wof:name":"Juniail",
    "wof:placetype":"locality"
},
  "geometry": {"coordinates":[90.75646,24.33844],"type":"Point"}
}