{
  "type": "Feature",
  "properties": {
    "gn:admin1_code":"85",
    "gn:admin2_code":"1078.0",
    "gn:admin3_code":"107866.0",
    "gn:admin4_code":"10786671.0",
    "gn:asciiname":"Amirabad",
    "gn:country_code":"BD",
    "gn:dem":2,
    "gn:feature_class":"P",
    "gn:feature_code":"PPL",
    "gn:name":"Amir\u0101b\u0101d",
    "gn:population":0,
    "gn:timezone":"Asia/Dhaka",
    "iso:country":"BD",
    "name:ben_x_preferred":[
        "Amir\u0101b\u0101d"
    ],
    "wof:name":"Amirabad",
    "wof:placetype":"locality"
},
  "geometry": {"coordinates":[90.18093,21.94375],"type":"Point"}
}