{
  "type": "Feature",
  "properties": {
    "gn:admin1_code":"85",
    "gn:admin2_code":"1078.0",
    "gn:admin3_code":"107866.0",
    "gn:admin4_code":"10786671.0",
    "gn:asciiname":"Amirabad",
    "gn:country_code":"BD",
    "gn:dem":2,
    "gn:feature_class":"P",
    "gn:feature_code":"PPL",
    "gn:name":"Amir\u0101b\u0101d",
    "gn:population":0,
    "gn:timezone":"Asia/Dhaka",
    "iso:country":"BD",
    "name:ara_x_preferred":[
        "\u0623\u0645\u064a\u0631 \u0623\u0628\u0627\u062f"
    ],
    "name:aze_x_preferred":[
        "\u018fmirabad"
    ],
    "name:ben_x_preferred":[
        "Amir\u0101b\u0101d"
    ],
    "name:ceb_x_preferred":[
        "Amirabad"
    ],
    "name:fas_x_preferred":[
        "\u0627\u0645\u06cc\u0631\u0622\u0628\u0627\u062f"
    ],
    "name:mzn_x_preferred":[
        "\u0627\u0645\u06cc\u0631\u0622\u0628\u0627\u062f"
    ],
    "name:swe_x_preferred":[
        "Amirabad"
    ],
    "wof:name":"Amirabad",
    "wof:placetype":"locality"
},
  "geometry": {"coordinates":[90.18093,21.94375],"type":"Point"}
}