{
  "type": "Feature",
  "properties": {
    "gn:admin1_code":"81",
    "gn:admin2_code":"3068",
    "gn:admin3_code":"306860.0",
    "gn:admin4_code":"30686053.0",
    "gn:asciiname":"Par Kasipur",
    "gn:country_code":"BD",
    "gn:dem":11,
    "gn:feature_class":"P",
    "gn:feature_code":"PPL",
    "gn:name":"P\u0101r K\u0101sipur",
    "gn:population":0,
    "gn:timezone":"Asia/Dhaka",
    "iso:country":"BD",
    "wof:name":"Par Kasipur",
    "wof:placetype":"locality"
},
  "geometry": {"coordinates":[90.67561000000001,23.84963],"type":"Point"}
}