{
  "type": "Feature",
  "properties": {
    "gn:admin1_code":"83",
    "gn:admin2_code":"5076",
    "gn:admin3_code":"507672.0",
    "gn:admin4_code":"50767277.0",
    "gn:asciiname":"Nagdemra",
    "gn:country_code":"BD",
    "gn:dem":17,
    "gn:feature_class":"P",
    "gn:feature_code":"PPL",
    "gn:name":"N\u0101gdemra",
    "gn:population":0,
    "gn:timezone":"Asia/Dhaka",
    "iso:country":"BD",
    "wof:name":"Nagdemra",
    "wof:placetype":"locality"
},
  "geometry": {"coordinates":[89.52070000000001,24.13068],"type":"Point"}
}