{
  "type": "Feature",
  "properties": {
    "gn:admin1_code":"81",
    "gn:admin2_code":"3086.0",
    "gn:admin3_code":"308669.0",
    "gn:admin4_code":"30866900.0",
    "gn:asciiname":"Bilaskhan",
    "gn:country_code":"BD",
    "gn:dem":9,
    "gn:feature_class":"P",
    "gn:feature_code":"PPL",
    "gn:name":"Bil\u0101skh\u0101n",
    "gn:population":0,
    "gn:timezone":"Asia/Dhaka",
    "iso:country":"BD",
    "name:und_x_variant":[
        "Khelsi Belaskhan",
        "Bil\u0101skh\u0101n"
    ],
    "wof:name":"Bilaskhan",
    "wof:placetype":"locality"
},
  "geometry": {"coordinates":[90.37229000000001,23.21791],"type":"Point"}
}