{
  "type": "Feature",
  "properties": {
    "gn:admin1_code":"82",
    "gn:admin2_code":"4087.0",
    "gn:admin3_code":"408747.0",
    "gn:admin4_code":"40874787.0",
    "gn:asciiname":"Chakchunakhali",
    "gn:country_code":"BD",
    "gn:dem":5,
    "gn:feature_class":"P",
    "gn:feature_code":"PPL",
    "gn:name":"Chakchunakh\u0101li",
    "gn:population":0,
    "gn:timezone":"Asia/Dhaka",
    "iso:country":"BD",
    "name:ben_x_preferred":[
        "Chakchunakh\u0101li"
    ],
    "wof:name":"Chakchunakhali",
    "wof:placetype":"locality"
},
  "geometry": {"coordinates":[89.03993,22.35614],"type":"Point"}
}