{
  "type": "Feature",
  "properties": {
    "gn:admin1_code":"81",
    "gn:admin2_code":"3035.0",
    "gn:admin3_code":"303558.0",
    "gn:admin4_code":"30355805.0",
    "gn:asciiname":"Baliakandi",
    "gn:country_code":"BD",
    "gn:dem":7,
    "gn:feature_class":"P",
    "gn:feature_code":"PPL",
    "gn:name":"Bali\u0101k\u0101ndi",
    "gn:population":0,
    "gn:timezone":"Asia/Dhaka",
    "iso:country":"BD",
    "name:und_x_variant":[
        "Baakandi",
        "Bali\u0101k\u0101ndi"
    ],
    "wof:name":"Baliakandi",
    "wof:placetype":"locality"
},
  "geometry": {"coordinates":[89.88419,23.26996],"type":"Point"}
}