{
  "type": "Feature",
  "properties": {
    "gn:admin1_code":"87",
    "gn:admin2_code":"5594.0",
    "gn:admin3_code":"559451.0",
    "gn:admin4_code":"55945154.0",
    "gn:asciiname":"Sreepur",
    "gn:country_code":"BD",
    "gn:dem":42,
    "gn:feature_class":"P",
    "gn:feature_code":"PPL",
    "gn:name":"Sreepur",
    "gn:population":0,
    "gn:timezone":"Asia/Dhaka",
    "iso:country":"BD",
    "name:ben_x_preferred":[
        "Sreepur"
    ],
    "name:ceb_x_preferred":[
        "Sreepur"
    ],
    "name:ita_x_preferred":[
        "Sreepur"
    ],
    "name:new_x_preferred":[
        "\u0936\u094d\u0930\u0940\u092a\u0941\u0930"
    ],
    "name:pol_x_preferred":[
        "Sreepur"
    ],
    "name:swe_x_preferred":[
        "Sreepur"
    ],
    "wof:name":"Sreepur",
    "wof:placetype":"locality"
},
  "geometry": {"coordinates":[88.17638000000002,25.86307],"type":"Point"}
}