{
  "type": "Feature",
  "properties": {
    "gn:admin1_code":"81",
    "gn:admin2_code":"3082.0",
    "gn:admin3_code":"308276.0",
    "gn:admin4_code":"30827621.0",
    "gn:asciiname":"Malgala",
    "gn:country_code":"BD",
    "gn:dem":14,
    "gn:feature_class":"P",
    "gn:feature_code":"PPL",
    "gn:name":"Malgala",
    "gn:population":0,
    "gn:timezone":"Asia/Dhaka",
    "iso:country":"BD",
    "name:ben_x_preferred":[
        "Malgala"
    ],
    "wof:name":"Malgala",
    "wof:placetype":"locality"
},
  "geometry": {"coordinates":[89.6863,23.77481],"type":"Point"}
}