{
  "type": "Feature",
  "properties": {
    "gn:admin1_code":"87",
    "gn:admin2_code":"5552",
    "gn:admin3_code":"555239.0",
    "gn:admin4_code":"55523965.0",
    "gn:asciiname":"Khalisa Bichhandai",
    "gn:country_code":"BD",
    "gn:dem":47,
    "gn:feature_class":"P",
    "gn:feature_code":"PPL",
    "gn:name":"Khalisa Bichhandai",
    "gn:population":0,
    "gn:timezone":"Asia/Dhaka",
    "iso:country":"BD",
    "name:ben_x_preferred":[
        "Khalisa Bichhandai"
    ],
    "wof:name":"Khalisa Bichhandai",
    "wof:placetype":"locality"
},
  "geometry": {"coordinates":[89.16555,26.03715],"type":"Point"}
}