{
  "type": "Feature",
  "properties": {
    "gn:admin1_code":"84",
    "gn:admin2_code":"2019.0",
    "gn:admin3_code":"201954.0",
    "gn:admin4_code":"20195476.0",
    "gn:asciiname":"Dwarigaon",
    "gn:country_code":"BD",
    "gn:dem":10,
    "gn:feature_class":"P",
    "gn:feature_code":"PPL",
    "gn:name":"Dw\u0101rigaon",
    "gn:population":0,
    "gn:timezone":"Asia/Dhaka",
    "iso:country":"BD",
    "wof:name":"Dwarigaon",
    "wof:placetype":"locality"
},
  "geometry": {"coordinates":[90.76430000000001,23.66083],"type":"Point"}
}