{
  "type": "Feature",
  "properties": {
    "gn:admin1_code":"83",
    "gn:admin2_code":"5064.0",
    "gn:admin3_code":"506486.0",
    "gn:admin4_code":"50648607.0",
    "gn:asciiname":"Asaranda",
    "gn:country_code":"BD",
    "gn:dem":33,
    "gn:feature_class":"P",
    "gn:feature_code":"PPL",
    "gn:name":"\u0100saranda",
    "gn:population":0,
    "gn:timezone":"Asia/Dhaka",
    "iso:country":"BD",
    "name:ben_x_preferred":[
        "\u0100saranda"
    ],
    "wof:name":"Asaranda",
    "wof:placetype":"locality"
},
  "geometry": {"coordinates":[88.48756,25.17249],"type":"Point"}
}