{
  "type": "Feature",
  "properties": {
    "gn:admin1_code":"H",
    "gn:admin2_code":"3061",
    "gn:admin3_code":"306123.0",
    "gn:admin4_code":"30612331.0",
    "gn:asciiname":"Sahabazpur",
    "gn:country_code":"BD",
    "gn:dem":15,
    "gn:feature_class":"P",
    "gn:feature_code":"PPL",
    "gn:name":"S\u0101h\u0101b\u0101zpur",
    "gn:population":0,
    "gn:timezone":"Asia/Dhaka",
    "iso:country":"BD",
    "name:und_x_variant":[
        "Shahbazpur",
        "Sahabajpur",
        "S\u0101h\u0101b\u0101zpur"
    ],
    "wof:name":"Sahabazpur",
    "wof:placetype":"locality"
},
  "geometry": {"coordinates":[90.55421,24.78082],"type":"Point"}
}