{
  "type": "Feature",
  "properties": {
    "gn:admin1_code":"84",
    "gn:admin2_code":"2013.0",
    "gn:admin3_code":"201395.0",
    "gn:admin4_code":"20139560.0",
    "gn:asciiname":"Debipur",
    "gn:country_code":"BD",
    "gn:dem":13,
    "gn:feature_class":"P",
    "gn:feature_code":"PPL",
    "gn:name":"Debipur",
    "gn:population":0,
    "gn:timezone":"Asia/Dhaka",
    "iso:country":"BD",
    "wof:name":"Debipur",
    "wof:placetype":"locality"
},
  "geometry": {"coordinates":[90.95853,23.25452],"type":"Point"}
}