{
  "type": "Feature",
  "properties": {
    "gn:admin1_code":"H",
    "gn:asciiname":"Char Bahadurabad",
    "gn:country_code":"BD",
    "gn:dem":24,
    "gn:feature_class":"P",
    "gn:feature_code":"PPL",
    "gn:name":"Char B\u0101h\u0101dur\u0101b\u0101d",
    "gn:population":0,
    "gn:timezone":"Asia/Dhaka",
    "iso:country":"BD",
    "name:ben_x_preferred":[
        "Char B\u0101h\u0101dur\u0101b\u0101d"
    ],
    "wof:name":"Char Bahadurabad",
    "wof:placetype":"locality"
},
  "geometry": {"coordinates":[89.74011,25.22652],"type":"Point"}
}