{
  "type": "Feature",
  "properties": {
    "gn:admin1_code":"83",
    "gn:admin2_code":"5010.0",
    "gn:admin3_code":"501094.0",
    "gn:admin4_code":"50109407.0",
    "gn:asciiname":"Alanar",
    "gn:country_code":"BD",
    "gn:dem":25,
    "gn:feature_class":"P",
    "gn:feature_code":"PPL",
    "gn:name":"\u0100lanar",
    "gn:population":0,
    "gn:timezone":"Asia/Dhaka",
    "iso:country":"BD",
    "name:ben_x_preferred":[
        "\u0100lanar"
    ],
    "wof:name":"Alanar",
    "wof:placetype":"locality"
},
  "geometry": {"coordinates":[89.23506999999999,25.0084],"type":"Point"}
}