{
  "type": "Feature",
  "properties": {
    "gn:admin1_code":"83",
    "gn:admin2_code":"5010",
    "gn:admin3_code":"501094.0",
    "gn:admin4_code":"50109439.0",
    "gn:asciiname":"Sirgerpara",
    "gn:country_code":"BD",
    "gn:dem":24,
    "gn:feature_class":"P",
    "gn:feature_code":"PPL",
    "gn:name":"Sirgerp\u0101ra",
    "gn:population":0,
    "gn:timezone":"Asia/Dhaka",
    "iso:country":"BD",
    "name:ben_x_preferred":[
        "Sirgerp\u0101ra"
    ],
    "wof:name":"Sirgerpara",
    "wof:placetype":"locality"
},
  "geometry": {"coordinates":[89.30553,25.06945],"type":"Point"}
}