{
  "type": "Feature",
  "properties": {
    "gn:admin1_code":"87",
    "gn:admin2_code":"5527",
    "gn:admin3_code":"552730.0",
    "gn:admin4_code":"55273094.0",
    "gn:asciiname":"Singanagar",
    "gn:country_code":"BD",
    "gn:dem":42,
    "gn:feature_class":"P",
    "gn:feature_code":"PPL",
    "gn:name":"Sing\u0101nagar",
    "gn:population":0,
    "gn:timezone":"Asia/Dhaka",
    "iso:country":"BD",
    "wof:name":"Singanagar",
    "wof:placetype":"locality"
},
  "geometry": {"coordinates":[88.74306,25.74686],"type":"Point"}
}