{
  "type": "Feature",
  "properties": {
    "gn:admin1_code":"81",
    "gn:admin2_code":"3026.0",
    "gn:admin3_code":"302662.0",
    "gn:admin4_code":"30266233.0",
    "gn:asciiname":"Chhota Barilya",
    "gn:country_code":"BD",
    "gn:dem":11,
    "gn:feature_class":"P",
    "gn:feature_code":"PPL",
    "gn:name":"Chhota B\u0101rilya",
    "gn:population":0,
    "gn:timezone":"Asia/Dhaka",
    "iso:country":"BD",
    "wof:name":"Chhota Barilya",
    "wof:placetype":"locality"
},
  "geometry": {"coordinates":[90.08333,23.66667],"type":"Point"}
}