{
  "type": "Feature",
  "properties": {
    "gn:admin1_code":"87",
    "gn:admin2_code":"5549",
    "gn:admin3_code":"554909.0",
    "gn:admin4_code":"55490983.0",
    "gn:asciiname":"Darikanda",
    "gn:country_code":"BD",
    "gn:dem":26,
    "gn:feature_class":"P",
    "gn:feature_code":"PPL",
    "gn:name":"D\u0101rik\u0101nda",
    "gn:population":0,
    "gn:timezone":"Asia/Dhaka",
    "iso:country":"BD",
    "name:ben_x_preferred":[
        "D\u0101rik\u0101nda"
    ],
    "wof:name":"Darikanda",
    "wof:placetype":"locality"
},
  "geometry": {"coordinates":[89.6571,25.63494],"type":"Point"}
}