{
  "type": "Feature",
  "properties": {
    "gn:admin1_code":"82",
    "gn:admin2_code":"4018",
    "gn:admin3_code":"401823.0",
    "gn:admin4_code":"40182359.0",
    "gn:asciiname":"Sarisadanga",
    "gn:country_code":"BD",
    "gn:dem":19,
    "gn:feature_class":"P",
    "gn:feature_code":"PPL",
    "gn:name":"Saris\u0101d\u0101nga",
    "gn:population":0,
    "gn:timezone":"Asia/Dhaka",
    "iso:country":"BD",
    "name:ben_x_preferred":[
        "Saris\u0101d\u0101nga"
    ],
    "name:und_x_variant":[
        "Sarishadanga"
    ],
    "wof:name":"Sarisadanga",
    "wof:placetype":"locality"
},
  "geometry": {"coordinates":[88.89362,23.68176],"type":"Point"}
}