{
  "type": "Feature",
  "properties": {
    "gn:admin1_code":"81",
    "gn:admin2_code":"3026",
    "gn:admin3_code":"302672.0",
    "gn:admin4_code":"30267294.0",
    "gn:asciiname":"Purba Bagbari",
    "gn:country_code":"BD",
    "gn:dem":21,
    "gn:feature_class":"P",
    "gn:feature_code":"PPL",
    "gn:name":"Purba B\u0101gb\u0101ri",
    "gn:population":0,
    "gn:timezone":"Asia/Dhaka",
    "iso:country":"BD",
    "wof:name":"Purba Bagbari",
    "wof:placetype":"locality"
},
  "geometry": {"coordinates":[90.30791000000001,23.94934],"type":"Point"}
}