{
  "type": "Feature",
  "properties": {
    "gn:admin1_code":"83",
    "gn:admin2_code":"5064",
    "gn:admin3_code":"506469.0",
    "gn:admin4_code":"50646942.0",
    "gn:asciiname":"Patkail",
    "gn:country_code":"BD",
    "gn:dem":26,
    "gn:feature_class":"P",
    "gn:feature_code":"PPL",
    "gn:name":"Patkail",
    "gn:population":0,
    "gn:timezone":"Asia/Dhaka",
    "iso:country":"BD",
    "name:ben_x_preferred":[
        "Patkail"
    ],
    "wof:name":"Patkail",
    "wof:placetype":"locality"
},
  "geometry": {"coordinates":[88.56923,24.87685],"type":"Point"}
}