{
  "type": "Feature",
  "properties": {
    "gn:admin1_code":"83",
    "gn:admin2_code":"5081.0",
    "gn:admin3_code":"508194.0",
    "gn:admin4_code":"50819427.0",
    "gn:asciiname":"Narail",
    "gn:country_code":"BD",
    "gn:dem":26,
    "gn:feature_class":"P",
    "gn:feature_code":"PPL",
    "gn:name":"Nar\u0101il",
    "gn:population":0,
    "gn:timezone":"Asia/Dhaka",
    "iso:country":"BD",
    "name:ben_x_preferred":[
        "Nar\u0101il"
    ],
    "wof:name":"Narail",
    "wof:placetype":"locality"
},
  "geometry": {"coordinates":[88.55934999999999,24.69778],"type":"Point"}
}