{
  "type": "Feature",
  "properties": {
    "gn:admin1_code":"81",
    "gn:admin2_code":"3035",
    "gn:admin3_code":"303532.0",
    "gn:admin4_code":"30353243.0",
    "gn:asciiname":"Pithalari",
    "gn:country_code":"BD",
    "gn:dem":6,
    "gn:feature_class":"P",
    "gn:feature_code":"PPL",
    "gn:name":"Pith\u0101l\u0101ri",
    "gn:population":0,
    "gn:timezone":"Asia/Dhaka",
    "iso:country":"BD",
    "name:ben_x_preferred":[
        "Pith\u0101l\u0101ri"
    ],
    "name:ben_x_variant":[
        "Pith\u0101b\u0101ri"
    ],
    "name:und_x_variant":[
        "Pittabari"
    ],
    "wof:name":"Pithalari",
    "wof:placetype":"locality"
},
  "geometry": {"coordinates":[89.92716,23.06075],"type":"Point"}
}