{
  "type": "Feature",
  "properties": {
    "gn:admin1_code":"82",
    "gn:asciiname":"Mandarhania",
    "gn:country_code":"BD",
    "gn:dem":8,
    "gn:feature_class":"P",
    "gn:feature_code":"PPL",
    "gn:name":"M\u0101nd\u0101rhania",
    "gn:population":0,
    "gn:timezone":"Asia/Dhaka",
    "iso:country":"BD",
    "name:ben_x_preferred":[
        "M\u0101nd\u0101rhania"
    ],
    "wof:name":"Mandarhania",
    "wof:placetype":"locality"
},
  "geometry": {"coordinates":[90.2788,22.3274],"type":"Point"}
}