{
  "type": "Feature",
  "properties": {
    "gn:admin1_code":"83",
    "gn:admin2_code":"5064.0",
    "gn:admin3_code":"506460.0",
    "gn:admin4_code":"50646000.0",
    "gn:asciiname":"Arazi Naogaon",
    "gn:country_code":"BD",
    "gn:dem":21,
    "gn:feature_class":"P",
    "gn:feature_code":"PPL",
    "gn:name":"\u0100razi Naogaon",
    "gn:population":0,
    "gn:timezone":"Asia/Dhaka",
    "iso:country":"BD",
    "name:ben_x_preferred":[
        "\u0100razi Naogaon"
    ],
    "name:und_x_variant":[
        "Arjinoagaon"
    ],
    "wof:name":"Arazi Naogaon",
    "wof:placetype":"locality"
},
  "geometry": {"coordinates":[88.92764,24.78065],"type":"Point"}
}