{
  "type": "Feature",
  "properties": {
    "gn:admin1_code":"87",
    "gn:admin2_code":"5527",
    "gn:admin3_code":"552747.0",
    "gn:admin4_code":"55274754.0",
    "gn:asciiname":"Gohara",
    "gn:country_code":"BD",
    "gn:dem":29,
    "gn:feature_class":"P",
    "gn:feature_code":"PPL",
    "gn:name":"Gohara",
    "gn:population":0,
    "gn:timezone":"Asia/Dhaka",
    "iso:country":"BD",
    "name:ben_x_preferred":[
        "Gohara"
    ],
    "wof:name":"Gohara",
    "wof:placetype":"locality"
},
  "geometry": {"coordinates":[89.04368000000002,25.2721],"type":"Point"}
}