{
  "type": "Feature",
  "properties": {
    "gn:admin1_code":"82",
    "gn:admin2_code":"4041",
    "gn:admin3_code":"404123.0",
    "gn:admin4_code":"40412371.0",
    "gn:asciiname":"Purandarpur",
    "gn:country_code":"BD",
    "gn:dem":11,
    "gn:feature_class":"P",
    "gn:feature_code":"PPL",
    "gn:name":"Purandarpur",
    "gn:population":0,
    "gn:timezone":"Asia/Dhaka",
    "iso:country":"BD",
    "name:ben_x_preferred":[
        "Purandarpur"
    ],
    "wof:name":"Purandarpur",
    "wof:placetype":"locality"
},
  "geometry": {"coordinates":[89.10420000000001,23.0861],"type":"Point"}
}