{
  "type": "Feature",
  "properties": {
    "gn:admin1_code":"87",
    "gn:admin2_code":"5549",
    "gn:admin3_code":"554994.0",
    "gn:admin4_code":"55499433.0",
    "gn:asciiname":"Sarafdi",
    "gn:country_code":"BD",
    "gn:dem":31,
    "gn:feature_class":"P",
    "gn:feature_code":"PPL",
    "gn:name":"Sarafdi",
    "gn:population":0,
    "gn:timezone":"Asia/Dhaka",
    "iso:country":"BD",
    "name:ben_x_preferred":[
        "Sarafdi"
    ],
    "wof:name":"Sarafdi",
    "wof:placetype":"locality"
},
  "geometry": {"coordinates":[89.57167,25.69667],"type":"Point"}
}