{
  "type": "Feature",
  "properties": {
    "gn:admin1_code":"81",
    "gn:admin2_code":"3082",
    "gn:admin3_code":"308276.0",
    "gn:admin4_code":"30827636.0",
    "gn:asciiname":"Ramchandrapur",
    "gn:country_code":"BD",
    "gn:dem":16,
    "gn:feature_class":"P",
    "gn:feature_code":"PPL",
    "gn:name":"R\u0101mchandrapur",
    "gn:population":0,
    "gn:timezone":"Asia/Dhaka",
    "iso:country":"BD",
    "wof:name":"Ramchandrapur",
    "wof:placetype":"locality"
},
  "geometry": {"coordinates":[89.66996,23.75508],"type":"Point"}
}