{
  "type": "Feature",
  "properties": {
    "gn:admin1_code":"84",
    "gn:admin2_code":"2075",
    "gn:admin3_code":"207589.0",
    "gn:admin4_code":"20758920.0",
    "gn:asciiname":"Rameshwarpur",
    "gn:cc2":"BD",
    "gn:country_code":"BD",
    "gn:dem":7,
    "gn:feature_class":"P",
    "gn:feature_code":"PPL",
    "gn:name":"R\u0101meshwarpur",
    "gn:population":0,
    "gn:timezone":"Asia/Dhaka",
    "iso:country":"BD",
    "name:und_x_variant":[
        "Rameswarpur",
        "R\u0101meshwarpur"
    ],
    "wof:name":"Rameshwarpur",
    "wof:placetype":"locality"
},
  "geometry": {"coordinates":[91.23333,22.81667],"type":"Point"}
}