{
  "type": "Feature",
  "properties": {
    "gn:admin1_code":"H",
    "gn:admin2_code":"3072",
    "gn:admin3_code":"307263.0",
    "gn:admin4_code":"30726342.0",
    "gn:asciiname":"Madhupur",
    "gn:country_code":"BD",
    "gn:dem":13,
    "gn:feature_class":"P",
    "gn:feature_code":"PPL",
    "gn:name":"Madhupur",
    "gn:population":0,
    "gn:timezone":"Asia/Dhaka",
    "iso:country":"BD",
    "wof:name":"Madhupur",
    "wof:placetype":"locality"
},
  "geometry": {"coordinates":[90.98396,24.82171],"type":"Point"}
}