{
  "type": "Feature",
  "properties": {
    "gn:admin1_code":"82",
    "gn:admin2_code":"4065.0",
    "gn:admin3_code":"406576.0",
    "gn:admin4_code":"40657606.0",
    "gn:asciiname":"Chaugachha",
    "gn:country_code":"BD",
    "gn:dem":12,
    "gn:feature_class":"P",
    "gn:feature_code":"PPL",
    "gn:name":"Chaug\u0101chha",
    "gn:population":0,
    "gn:timezone":"Asia/Dhaka",
    "iso:country":"BD",
    "name:ben_x_preferred":[
        "Chaug\u0101chha"
    ],
    "wof:name":"Chaugachha",
    "wof:placetype":"locality"
},
  "geometry": {"coordinates":[89.5857,23.17825],"type":"Point"}
}