{
  "type": "Feature",
  "properties": {
    "gn:admin1_code":"82",
    "gn:admin2_code":"4050.0",
    "gn:admin3_code":"405071.0",
    "gn:admin4_code":"40507177.0",
    "gn:asciiname":"Bagbaria",
    "gn:country_code":"BD",
    "gn:dem":12,
    "gn:feature_class":"P",
    "gn:feature_code":"PPL",
    "gn:name":"Bagbaria",
    "gn:population":0,
    "gn:timezone":"Asia/Dhaka",
    "iso:country":"BD",
    "name:ben_x_preferred":[
        "Bagbaria"
    ],
    "wof:name":"Bagbaria",
    "wof:placetype":"locality"
},
  "geometry": {"coordinates":[89.21680000000001,23.7732],"type":"Point"}
}