{
  "type": "Feature",
  "properties": {
    "gn:admin1_code":"H",
    "gn:admin2_code":"3089.0",
    "gn:admin3_code":"308967.0",
    "gn:admin4_code":"30896719.0",
    "gn:asciiname":"Chandrakona",
    "gn:country_code":"BD",
    "gn:dem":18,
    "gn:feature_class":"P",
    "gn:feature_code":"PPL",
    "gn:name":"Chandrakona",
    "gn:population":0,
    "gn:timezone":"Asia/Dhaka",
    "iso:country":"BD",
    "wof:name":"Chandrakona",
    "wof:placetype":"locality"
},
  "geometry": {"coordinates":[90.12989,24.90715],"type":"Point"}
}