{
  "type": "Feature",
  "properties": {
    "gn:admin1_code":"H",
    "gn:admin2_code":"3089.0",
    "gn:admin3_code":"308967.0",
    "gn:admin4_code":"30896719.0",
    "gn:asciiname":"Chandrakona",
    "gn:country_code":"BD",
    "gn:dem":18,
    "gn:feature_class":"P",
    "gn:feature_code":"PPL",
    "gn:name":"Chandrakona",
    "gn:population":0,
    "gn:timezone":"Asia/Dhaka",
    "iso:country":"BD",
    "name:ben_x_preferred":[
        "\u099a\u09a8\u09cd\u09a6\u09cd\u09b0\u0995\u09cb\u09a3\u09be"
    ],
    "name:bpy_x_preferred":[
        "\u099a\u09a8\u09cd\u09a6\u09cd\u09b0\u0995\u09cb\u09a3\u09be"
    ],
    "name:ceb_x_preferred":[
        "Chandrakona"
    ],
    "name:ita_x_preferred":[
        "Chandrakona"
    ],
    "name:msa_x_preferred":[
        "Chandrakona"
    ],
    "name:new_x_preferred":[
        "\u091a\u0928\u094d\u0926\u094d\u0930\u0915\u094b\u0923"
    ],
    "name:pan_x_preferred":[
        "\u0a1a\u0a70\u0a26\u0a30\u0a15\u0a4b\u0a28\u0a3e"
    ],
    "name:por_x_preferred":[
        "Chandrakona"
    ],
    "name:spa_x_preferred":[
        "Chandrakona"
    ],
    "name:swe_x_preferred":[
        "Chandrakona"
    ],
    "name:vie_x_preferred":[
        "Chandrakona"
    ],
    "name:zho_x_preferred":[
        "\u94b1\u5fb7\u62c9\u79d1\u7eb3"
    ],
    "wof:name":"Chandrakona",
    "wof:placetype":"locality"
},
  "geometry": {"coordinates":[90.12989,24.90715],"type":"Point"}
}