{
  "type": "Feature",
  "properties": {
    "gn:admin1_code":"81",
    "gn:admin2_code":"3093.0",
    "gn:admin3_code":"309328.0",
    "gn:admin4_code":"30932851.0",
    "gn:asciiname":"Deonapara",
    "gn:cc2":"BD",
    "gn:country_code":"BD",
    "gn:dem":17,
    "gn:feature_class":"P",
    "gn:feature_code":"PPL",
    "gn:name":"Deon\u0101p\u0101ra",
    "gn:population":0,
    "gn:timezone":"Asia/Dhaka",
    "iso:country":"BD",
    "name:und_x_variant":[
        "Dconapara",
        "Deon\u0101p\u0101ra"
    ],
    "wof:name":"Deonapara",
    "wof:placetype":"locality"
},
  "geometry": {"coordinates":[90.01666999999998,24.41667],"type":"Point"}
}