{
  "type": "Feature",
  "properties": {
    "gn:admin1_code":"83",
    "gn:admin2_code":"5081",
    "gn:admin3_code":"508182.0",
    "gn:admin4_code":"50818281.0",
    "gn:asciiname":"Isabpur",
    "gn:country_code":"BD",
    "gn:dem":19,
    "gn:feature_class":"P",
    "gn:feature_code":"PPL",
    "gn:name":"Isabpur",
    "gn:population":0,
    "gn:timezone":"Asia/Dhaka",
    "iso:country":"BD",
    "name:ben_x_preferred":[
        "Isabpur"
    ],
    "wof:name":"Isabpur",
    "wof:placetype":"locality"
},
  "geometry": {"coordinates":[88.87899999999998,24.50214],"type":"Point"}
}