{
  "type": "Feature",
  "properties": {
    "gn:admin1_code":"83",
    "gn:admin2_code":"5070.0",
    "gn:admin3_code":"507018.0",
    "gn:admin4_code":"50701818.0",
    "gn:asciiname":"Imamnagar",
    "gn:country_code":"BD",
    "gn:dem":30,
    "gn:feature_class":"P",
    "gn:feature_code":"PPL",
    "gn:name":"Imamnagar",
    "gn:population":0,
    "gn:timezone":"Asia/Dhaka",
    "iso:country":"BD",
    "name:ben_x_preferred":[
        "Imamnagar"
    ],
    "wof:name":"Imamnagar",
    "wof:placetype":"locality"
},
  "geometry": {"coordinates":[88.19679000000002,24.94233],"type":"Point"}
}