{
  "type": "Feature",
  "properties": {
    "gn:admin1_code":"87",
    "gn:admin2_code":"5527.0",
    "gn:admin3_code":"552717.0",
    "gn:admin4_code":"55271776.0",
    "gn:asciiname":"Rudrapur",
    "gn:country_code":"BD",
    "gn:dem":45,
    "gn:feature_class":"P",
    "gn:feature_code":"PPL",
    "gn:name":"Rudrapur",
    "gn:population":0,
    "gn:timezone":"Asia/Dhaka",
    "iso:country":"BD",
    "name:ben_x_preferred":[
        "Rudrapur"
    ],
    "name:deu_x_preferred":[
        "Rudrapur"
    ],
    "name:ita_x_preferred":[
        "Rudrapur"
    ],
    "name:nld_x_preferred":[
        "Rudrapur"
    ],
    "name:pol_x_preferred":[
        "Rudrapur"
    ],
    "wof:name":"Rudrapur",
    "wof:placetype":"locality"
},
  "geometry": {"coordinates":[88.5535,25.75562],"type":"Point"}
}