{
  "type": "Feature",
  "properties": {
    "gn:admin1_code":"83",
    "gn:admin2_code":"5064",
    "gn:admin3_code":"506447.0",
    "gn:admin4_code":"50644713.0",
    "gn:asciiname":"Mandakhas",
    "gn:country_code":"BD",
    "gn:dem":24,
    "gn:feature_class":"P",
    "gn:feature_code":"PPL",
    "gn:name":"M\u0101ndakh\u0101s",
    "gn:population":0,
    "gn:timezone":"Asia/Dhaka",
    "iso:country":"BD",
    "name:ben_x_preferred":[
        "M\u0101ndakh\u0101s"
    ],
    "wof:name":"Mandakhas",
    "wof:placetype":"locality"
},
  "geometry": {"coordinates":[88.63759,24.77021],"type":"Point"}
}