{
  "type": "Feature",
  "properties": {
    "gn:admin1_code":"81",
    "gn:admin2_code":"3029",
    "gn:admin3_code":"302918.0",
    "gn:admin4_code":"30291890.0",
    "gn:asciiname":"Patitapara Ramchandrapur",
    "gn:country_code":"BD",
    "gn:dem":11,
    "gn:feature_class":"P",
    "gn:feature_code":"PPL",
    "gn:name":"P\u0101tit\u0101p\u0101ra R\u0101mchandrapur",
    "gn:population":0,
    "gn:timezone":"Asia/Dhaka",
    "iso:country":"BD",
    "name:und_x_variant":[
        "Patipara Ramchandrapur",
        "P\u0101tit\u0101p\u0101ra R\u0101mchandrapur"
    ],
    "wof:name":"Patitapara Ramchandrapur",
    "wof:placetype":"locality"
},
  "geometry": {"coordinates":[89.67495,23.44497],"type":"Point"}
}