{
  "type": "Feature",
  "properties": {
    "gn:admin1_code":"81",
    "gn:admin2_code":"3033.0",
    "gn:admin3_code":"303330.0",
    "gn:admin4_code":"30333081.0",
    "gn:asciiname":"Chamudda",
    "gn:country_code":"BD",
    "gn:dem":12,
    "gn:feature_class":"P",
    "gn:feature_code":"PPL",
    "gn:name":"Ch\u0101mudda",
    "gn:population":0,
    "gn:timezone":"Asia/Dhaka",
    "iso:country":"BD",
    "wof:name":"Chamudda",
    "wof:placetype":"locality"
},
  "geometry": {"coordinates":[90.43519999999999,23.93968],"type":"Point"}
}