{
  "type": "Feature",
  "properties": {
    "gn:admin1_code":"87",
    "gn:admin2_code":"5527",
    "gn:admin3_code":"552764.0",
    "gn:admin4_code":"55276425.0",
    "gn:asciiname":"Karnai",
    "gn:country_code":"BD",
    "gn:dem":39,
    "gn:feature_class":"P",
    "gn:feature_code":"PPL",
    "gn:name":"Karn\u0101i",
    "gn:population":0,
    "gn:timezone":"Asia/Dhaka",
    "iso:country":"BD",
    "name:ben_x_preferred":[
        "Karn\u0101i"
    ],
    "wof:name":"Karnai",
    "wof:placetype":"locality"
},
  "geometry": {"coordinates":[88.65411,25.70643],"type":"Point"}
}