{
  "type": "Feature",
  "properties": {
    "gn:admin1_code":"83",
    "gn:admin2_code":"5081",
    "gn:admin3_code":"508153.0",
    "gn:admin4_code":"50815367.0",
    "gn:asciiname":"Maugachhi",
    "gn:country_code":"BD",
    "gn:dem":21,
    "gn:feature_class":"P",
    "gn:feature_code":"PPL",
    "gn:name":"Maug\u0101chhi",
    "gn:population":0,
    "gn:timezone":"Asia/Dhaka",
    "iso:country":"BD",
    "name:ben_x_preferred":[
        "Maug\u0101chhi"
    ],
    "wof:name":"Maugachhi",
    "wof:placetype":"locality"
},
  "geometry": {"coordinates":[88.62226,24.51211],"type":"Point"}
}