{
  "type": "Feature",
  "properties": {
    "gn:admin1_code":"83",
    "gn:admin2_code":"5038.0",
    "gn:admin3_code":"503861.0",
    "gn:admin4_code":"50386128.0",
    "gn:asciiname":"Sakharanj",
    "gn:country_code":"BD",
    "gn:dem":24,
    "gn:feature_class":"P",
    "gn:feature_code":"PPL",
    "gn:name":"S\u0101kh\u0101ranj",
    "gn:population":0,
    "gn:timezone":"Asia/Dhaka",
    "iso:country":"BD",
    "name:ben_x_preferred":[
        "S\u0101kh\u0101ranj"
    ],
    "wof:name":"Sakharanj",
    "wof:placetype":"locality"
},
  "geometry": {"coordinates":[89.15181,25.01945],"type":"Point"}
}