{
  "type": "Feature",
  "properties": {
    "gn:admin1_code":"87",
    "gn:admin2_code":"5594.0",
    "gn:admin3_code":"559494.0",
    "gn:admin4_code":"55949473.0",
    "gn:asciiname":"Horinda",
    "gn:country_code":"BD",
    "gn:dem":56,
    "gn:feature_class":"P",
    "gn:feature_code":"PPL",
    "gn:name":"Horinda",
    "gn:population":0,
    "gn:timezone":"Asia/Dhaka",
    "iso:country":"BD",
    "name:ben_x_preferred":[
        "Horinda"
    ],
    "wof:name":"Horinda",
    "wof:placetype":"locality"
},
  "geometry": {"coordinates":[88.32399000000002,26.03746],"type":"Point"}
}