{
  "type": "Feature",
  "properties": {
    "gn:admin1_code":"82",
    "gn:admin2_code":"4047.0",
    "gn:admin3_code":"404740.0",
    "gn:admin4_code":"40474066.0",
    "gn:asciiname":"Ketla",
    "gn:country_code":"BD",
    "gn:dem":7,
    "gn:feature_class":"P",
    "gn:feature_code":"PPL",
    "gn:name":"Ketla",
    "gn:population":0,
    "gn:timezone":"Asia/Dhaka",
    "iso:country":"BD",
    "name:ben_x_preferred":[
        "Ketla"
    ],
    "wof:name":"Ketla",
    "wof:placetype":"locality"
},
  "geometry": {"coordinates":[89.57683,22.93129],"type":"Point"}
}