{
  "type": "Feature",
  "properties": {
    "gn:admin1_code":"87",
    "gn:admin2_code":"5577.0",
    "gn:admin3_code":"557773.0",
    "gn:admin4_code":"55777371.0",
    "gn:asciiname":"Puratan Pachagarh",
    "gn:country_code":"BD",
    "gn:dem":79,
    "gn:feature_class":"P",
    "gn:feature_code":"PPL",
    "gn:name":"Pur\u0101tan Pach\u0101garh",
    "gn:population":0,
    "gn:timezone":"Asia/Dhaka",
    "iso:country":"BD",
    "name:ben_x_preferred":[
        "Pur\u0101tan Pach\u0101garh"
    ],
    "wof:name":"Puratan Pachagarh",
    "wof:placetype":"locality"
},
  "geometry": {"coordinates":[88.56423000000002,26.34743],"type":"Point"}
}