{
  "type": "Feature",
  "properties": {
    "gn:admin1_code":"82",
    "gn:admin2_code":"4087",
    "gn:admin3_code":"408704.0",
    "gn:admin4_code":"40870469.0",
    "gn:asciiname":"Kachua",
    "gn:country_code":"BD",
    "gn:dem":5,
    "gn:feature_class":"P",
    "gn:feature_code":"PPL",
    "gn:name":"Kachua",
    "gn:population":0,
    "gn:timezone":"Asia/Dhaka",
    "iso:country":"BD",
    "wof:name":"Kachua",
    "wof:placetype":"locality"
},
  "geometry": {"coordinates":[89.18155,22.61613],"type":"Point"}
}