{
  "type": "Feature",
  "properties": {
    "gn:admin1_code":"85",
    "gn:admin2_code":"1009.0",
    "gn:admin3_code":"100921.0",
    "gn:admin4_code":"10092166.0",
    "gn:asciiname":"Pakshmia",
    "gn:country_code":"BD",
    "gn:dem":5,
    "gn:feature_class":"P",
    "gn:feature_code":"PPL",
    "gn:name":"Pakshmia",
    "gn:population":0,
    "gn:timezone":"Asia/Dhaka",
    "iso:country":"BD",
    "name:ben_x_preferred":[
        "Pakshmia"
    ],
    "wof:name":"Pakshmia",
    "wof:placetype":"locality"
},
  "geometry": {"coordinates":[90.75163000000001,22.49685],"type":"Point"}
}