{
  "type": "Feature",
  "properties": {
    "gn:admin1_code":"84",
    "gn:admin2_code":"2013",
    "gn:admin3_code":"201379.0",
    "gn:admin4_code":"20137925.0",
    "gn:asciiname":"Islamabad",
    "gn:country_code":"BD",
    "gn:dem":9,
    "gn:feature_class":"P",
    "gn:feature_code":"PPL",
    "gn:name":"Isl\u0101m\u0101b\u0101d",
    "gn:population":0,
    "gn:timezone":"Asia/Dhaka",
    "iso:country":"BD",
    "wof:name":"Islamabad",
    "wof:placetype":"locality"
},
  "geometry": {"coordinates":[90.69823,23.41065],"type":"Point"}
}