{
  "type": "Feature",
  "properties": {
    "gn:admin1_code":"83",
    "gn:admin2_code":"5081.0",
    "gn:admin3_code":"508172.0",
    "gn:admin4_code":"50817231.0",
    "gn:asciiname":"Harisardaing",
    "gn:country_code":"BD",
    "gn:dem":25,
    "gn:feature_class":"P",
    "gn:feature_code":"PPL",
    "gn:name":"Haris\u0101rd\u0101ing",
    "gn:population":0,
    "gn:timezone":"Asia/Dhaka",
    "iso:country":"BD",
    "name:ben_x_preferred":[
        "Haris\u0101rd\u0101ing"
    ],
    "wof:name":"Harisardaing",
    "wof:placetype":"locality"
},
  "geometry": {"coordinates":[88.56692,24.41959],"type":"Point"}
}