{
  "type": "Feature",
  "properties": {
    "gn:admin1_code":"82",
    "gn:admin2_code":"4018.0",
    "gn:admin3_code":"401831.0",
    "gn:admin4_code":"40183147.0",
    "gn:asciiname":"Majlishpur",
    "gn:country_code":"BD",
    "gn:dem":18,
    "gn:feature_class":"P",
    "gn:feature_code":"PPL",
    "gn:name":"Majlishpur",
    "gn:population":0,
    "gn:timezone":"Asia/Dhaka",
    "iso:country":"BD",
    "name:ben_x_preferred":[
        "Majlishpur"
    ],
    "wof:name":"Majlishpur",
    "wof:placetype":"locality"
},
  "geometry": {"coordinates":[88.77749,23.69511],"type":"Point"}
}