{
  "type": "Feature",
  "properties": {
    "gn:admin1_code":"84",
    "gn:admin2_code":"2022.0",
    "gn:admin3_code":"202266.0",
    "gn:admin4_code":"20226647.0",
    "gn:asciiname":"Shukmanrapara",
    "gn:country_code":"BD",
    "gn:dem":18,
    "gn:feature_class":"P",
    "gn:feature_code":"PPL",
    "gn:name":"Shukmanr\u0101p\u0101ra",
    "gn:population":0,
    "gn:timezone":"Asia/Dhaka",
    "iso:country":"BD",
    "name:ben_x_preferred":[
        "Shukmanr\u0101p\u0101ra"
    ],
    "wof:name":"Shukmanrapara",
    "wof:placetype":"locality"
},
  "geometry": {"coordinates":[92.21008999999999,21.4372],"type":"Point"}
}