{
  "type": "Feature",
  "properties": {
    "gn:admin1_code":"84",
    "gn:admin2_code":"2013.0",
    "gn:admin3_code":"201345.0",
    "gn:admin4_code":"20134565.0",
    "gn:asciiname":"Asatkuari",
    "gn:country_code":"BD",
    "gn:dem":11,
    "gn:feature_class":"P",
    "gn:feature_code":"PPL",
    "gn:name":"Asatkuari",
    "gn:population":0,
    "gn:timezone":"Asia/Dhaka",
    "iso:country":"BD",
    "name:ita_x_preferred":[
        "Asatkuari"
    ],
    "name:und_x_variant":[
        "\u0100satku\u0101ri"
    ],
    "wof:name":"Asatkuari",
    "wof:placetype":"locality"
},
  "geometry": {"coordinates":[90.77157,23.1683],"type":"Point"}
}