{
  "type": "Feature",
  "properties": {
    "gn:admin1_code":"81",
    "gn:admin2_code":"3093.0",
    "gn:admin3_code":"309376.0",
    "gn:admin4_code":"30937687.0",
    "gn:asciiname":"Danga",
    "gn:country_code":"BD",
    "gn:dem":17,
    "gn:feature_class":"P",
    "gn:feature_code":"PPL",
    "gn:name":"D\u0101nga",
    "gn:population":0,
    "gn:timezone":"Asia/Dhaka",
    "iso:country":"BD",
    "wof:name":"Danga",
    "wof:placetype":"locality"
},
  "geometry": {"coordinates":[89.87715,24.07581],"type":"Point"}
}