{
  "type": "Feature",
  "properties": {
    "gn:admin1_code":"81",
    "gn:admin2_code":"3054",
    "gn:admin3_code":"305487.0",
    "gn:admin4_code":"30548747.0",
    "gn:asciiname":"Dityakhanda",
    "gn:country_code":"BD",
    "gn:dem":12,
    "gn:feature_class":"P",
    "gn:feature_code":"PPL",
    "gn:name":"Dityakhanda",
    "gn:population":0,
    "gn:timezone":"Asia/Dhaka",
    "iso:country":"BD",
    "wof:name":"Dityakhanda",
    "wof:placetype":"locality"
},
  "geometry": {"coordinates":[90.2013,23.35932],"type":"Point"}
}