{
  "type": "Feature",
  "properties": {
    "gn:admin1_code":"87",
    "gn:admin2_code":"5527.0",
    "gn:admin3_code":"552777.0",
    "gn:admin4_code":"55277734.0",
    "gn:asciiname":"Patigram",
    "gn:country_code":"BD",
    "gn:dem":36,
    "gn:feature_class":"P",
    "gn:feature_code":"PPL",
    "gn:name":"Patigram",
    "gn:population":0,
    "gn:timezone":"Asia/Dhaka",
    "iso:country":"BD",
    "name:ben_x_preferred":[
        "Patigram"
    ],
    "wof:name":"Patigram",
    "wof:placetype":"locality"
},
  "geometry": {"coordinates":[88.97558000000002,25.5352],"type":"Point"}
}