{
  "type": "Feature",
  "properties": {
    "gn:admin1_code":"87",
    "gn:admin2_code":"5577.0",
    "gn:admin3_code":"557773.0",
    "gn:admin4_code":"55777371.0",
    "gn:asciiname":"Pradhanpara",
    "gn:country_code":"BD",
    "gn:dem":84,
    "gn:feature_class":"P",
    "gn:feature_code":"PPL",
    "gn:name":"Pradh\u0101np\u0101ra",
    "gn:population":0,
    "gn:timezone":"Asia/Dhaka",
    "iso:country":"BD",
    "name:ben_x_preferred":[
        "Pradh\u0101np\u0101ra"
    ],
    "wof:name":"Pradhanpara",
    "wof:placetype":"locality"
},
  "geometry": {"coordinates":[88.54949999999999,26.38326],"type":"Point"}
}