{
  "type": "Feature",
  "properties": {
    "gn:admin1_code":"84",
    "gn:admin2_code":"2015.0",
    "gn:admin3_code":"201561.0",
    "gn:admin4_code":"20156124.0",
    "gn:asciiname":"Khoajnagar",
    "gn:country_code":"BD",
    "gn:dem":9,
    "gn:feature_class":"P",
    "gn:feature_code":"PPL",
    "gn:name":"Kho\u0101jnagar",
    "gn:population":0,
    "gn:timezone":"Asia/Dhaka",
    "iso:country":"BD",
    "name:ben_x_preferred":[
        "Kho\u0101jnagar"
    ],
    "wof:name":"Khoajnagar",
    "wof:placetype":"locality"
},
  "geometry": {"coordinates":[91.84281,22.30451],"type":"Point"}
}