{
  "type": "Feature",
  "properties": {
    "gn:admin1_code":"83",
    "gn:admin2_code":"5064",
    "gn:admin3_code":"506469.0",
    "gn:admin4_code":"50646973.0",
    "gn:asciiname":"Rasulpur",
    "gn:country_code":"BD",
    "gn:dem":43,
    "gn:feature_class":"P",
    "gn:feature_code":"PPL",
    "gn:name":"Rasulpur",
    "gn:population":0,
    "gn:timezone":"Asia/Dhaka",
    "iso:country":"BD",
    "name:ben_x_preferred":[
        "Rasulpur"
    ],
    "name:fas_x_preferred":[
        "\u0631\u0633\u0648\u0644\u200c\u067e\u0648\u0631"
    ],
    "name:urd_x_preferred":[
        "\u0631\u0633\u0648\u0644\u067e\u0648\u0631"
    ],
    "wof:name":"Rasulpur",
    "wof:placetype":"locality"
},
  "geometry": {"coordinates":[88.45466,24.83979],"type":"Point"}
}