{
  "type": "Feature",
  "properties": {
    "gn:admin1_code":"87",
    "gn:admin2_code":"5552",
    "gn:admin3_code":"555239.0",
    "gn:admin4_code":"55523965.0",
    "gn:asciiname":"Musarat Madati Dakshin",
    "gn:country_code":"BD",
    "gn:dem":44,
    "gn:feature_class":"P",
    "gn:feature_code":"PPL",
    "gn:name":"Musarat Madati Dakshin",
    "gn:population":0,
    "gn:timezone":"Asia/Dhaka",
    "iso:country":"BD",
    "name:und_x_variant":[
        "Musrat Mad\u0101ti Dakshin"
    ],
    "wof:name":"Musarat Madati Dakshin",
    "wof:placetype":"locality"
},
  "geometry": {"coordinates":[89.19683000000001,26.00602],"type":"Point"}
}