{
  "type": "Feature",
  "properties": {
    "gn:admin1_code":"84",
    "gn:admin2_code":"2003.0",
    "gn:admin3_code":"200351.0",
    "gn:admin4_code":"20035115.0",
    "gn:asciiname":"Chathaupara",
    "gn:country_code":"BD",
    "gn:dem":33,
    "gn:feature_class":"P",
    "gn:feature_code":"PPL",
    "gn:name":"Chathaup\u0101ra",
    "gn:population":0,
    "gn:timezone":"Asia/Dhaka",
    "iso:country":"BD",
    "name:ben_x_preferred":[
        "Chathaup\u0101ra"
    ],
    "wof:name":"Chathaupara",
    "wof:placetype":"locality"
},
  "geometry": {"coordinates":[92.10954,21.83402],"type":"Point"}
}