{
  "type": "Feature",
  "properties": {
    "gn:admin1_code":"83",
    "gn:admin2_code":"5038.0",
    "gn:admin3_code":"503847.0",
    "gn:admin4_code":"50384747.0",
    "gn:asciiname":"Billah",
    "gn:country_code":"BD",
    "gn:dem":24,
    "gn:feature_class":"P",
    "gn:feature_code":"PPL",
    "gn:name":"Billah",
    "gn:population":0,
    "gn:timezone":"Asia/Dhaka",
    "iso:country":"BD",
    "name:ben_x_preferred":[
        "Billah"
    ],
    "name:ukr_x_preferred":[
        "\u0411\u0456\u043b\u043b\u0430\u0445"
    ],
    "wof:name":"Billah",
    "wof:placetype":"locality"
},
  "geometry": {"coordinates":[88.96472,25.10078],"type":"Point"}
}