{
  "type": "Feature",
  "properties": {
    "gn:admin1_code":"81",
    "gn:admin2_code":"3029",
    "gn:admin3_code":"302903.0",
    "gn:admin4_code":"30290342.0",
    "gn:asciiname":"Kuldhar",
    "gn:country_code":"BD",
    "gn:dem":9,
    "gn:feature_class":"P",
    "gn:feature_code":"PPL",
    "gn:name":"Kuldhar",
    "gn:population":0,
    "gn:timezone":"Asia/Dhaka",
    "iso:country":"BD",
    "wof:name":"Kuldhar",
    "wof:placetype":"locality"
},
  "geometry": {"coordinates":[89.68146,23.26512],"type":"Point"}
}