{
  "type": "Feature",
  "properties": {
    "gn:admin1_code":"81",
    "gn:admin2_code":"3026",
    "gn:admin3_code":"302614.0",
    "gn:admin4_code":"30261447.0",
    "gn:asciiname":"Delutia",
    "gn:country_code":"BD",
    "gn:dem":11,
    "gn:feature_class":"P",
    "gn:feature_code":"PPL",
    "gn:name":"Delutia",
    "gn:population":0,
    "gn:timezone":"Asia/Dhaka",
    "iso:country":"BD",
    "wof:name":"Delutia",
    "wof:placetype":"locality"
},
  "geometry": {"coordinates":[90.09466999999999,24.01526],"type":"Point"}
}