{
  "type": "Feature",
  "properties": {
    "gn:admin1_code":"87",
    "gn:admin2_code":"5594.0",
    "gn:admin3_code":"559482.0",
    "gn:admin4_code":"55948286.0",
    "gn:asciiname":"Ynua",
    "gn:country_code":"BD",
    "gn:dem":47,
    "gn:feature_class":"P",
    "gn:feature_code":"PPL",
    "gn:name":"Ynua",
    "gn:population":0,
    "gn:timezone":"Asia/Dhaka",
    "iso:country":"BD",
    "name:ben_x_preferred":[
        "Ynua"
    ],
    "wof:name":"Ynua",
    "wof:placetype":"locality"
},
  "geometry": {"coordinates":[88.4552,25.89466],"type":"Point"}
}