{
  "type": "Feature",
  "properties": {
    "gn:admin1_code":"87",
    "gn:admin2_code":"5549",
    "gn:admin3_code":"554994.0",
    "gn:admin4_code":"55499444.0",
    "gn:asciiname":"Madartori",
    "gn:country_code":"BD",
    "gn:dem":30,
    "gn:feature_class":"P",
    "gn:feature_code":"PPL",
    "gn:name":"M\u0101d\u0101rtori",
    "gn:population":0,
    "gn:timezone":"Asia/Dhaka",
    "iso:country":"BD",
    "name:ben_x_preferred":[
        "M\u0101d\u0101rtori"
    ],
    "wof:name":"Madartori",
    "wof:placetype":"locality"
},
  "geometry": {"coordinates":[89.66958000000002,25.68948],"type":"Point"}
}