{
  "type": "Feature",
  "properties": {
    "gn:admin1_code":"81",
    "gn:admin2_code":"3056.0",
    "gn:admin3_code":"305610.0",
    "gn:admin4_code":"30561085.0",
    "gn:asciiname":"Binodpur",
    "gn:country_code":"BD",
    "gn:dem":13,
    "gn:feature_class":"P",
    "gn:feature_code":"PPL",
    "gn:name":"Binodpur",
    "gn:population":0,
    "gn:timezone":"Asia/Dhaka",
    "iso:country":"BD",
    "wof:name":"Binodpur",
    "wof:placetype":"locality"
},
  "geometry": {"coordinates":[89.8351,23.91122],"type":"Point"}
}