{
  "type": "Feature",
  "properties": {
    "gn:admin1_code":"83",
    "gn:admin2_code":"5064.0",
    "gn:admin3_code":"506403.0",
    "gn:admin4_code":"50640352.0",
    "gn:asciiname":"Andharkota",
    "gn:country_code":"BD",
    "gn:dem":17,
    "gn:feature_class":"P",
    "gn:feature_code":"PPL",
    "gn:name":"Andh\u0101rkota",
    "gn:population":0,
    "gn:timezone":"Asia/Dhaka",
    "iso:country":"BD",
    "name:ben_x_preferred":[
        "Andh\u0101rkota"
    ],
    "wof:name":"Andharkota",
    "wof:placetype":"locality"
},
  "geometry": {"coordinates":[88.92498000000001,24.67918],"type":"Point"}
}