{
  "type": "Feature",
  "properties": {
    "gn:admin1_code":"84",
    "gn:admin2_code":"2015.0",
    "gn:admin3_code":"201586.0",
    "gn:admin4_code":"20158628.0",
    "gn:asciiname":"Baraipara",
    "gn:country_code":"BD",
    "gn:dem":17,
    "gn:feature_class":"P",
    "gn:feature_code":"PPL",
    "gn:name":"Baraipara",
    "gn:population":0,
    "gn:timezone":"Asia/Dhaka",
    "iso:country":"BD",
    "wof:name":"Baraipara",
    "wof:placetype":"locality"
},
  "geometry": {"coordinates":[91.63861,22.67222000000001],"type":"Point"}
}