{
  "type": "Feature",
  "properties": {
    "gn:admin1_code":"84",
    "gn:admin2_code":"2019.0",
    "gn:admin3_code":"201909.0",
    "gn:admin4_code":"20190906.0",
    "gn:asciiname":"Adda",
    "gn:country_code":"BD",
    "gn:dem":14,
    "gn:feature_class":"P",
    "gn:feature_code":"PPL",
    "gn:name":"\u0100dda",
    "gn:population":0,
    "gn:timezone":"Asia/Dhaka",
    "iso:country":"BD",
    "name:bre_x_preferred":[
        "Adda"
    ],
    "name:ceb_x_preferred":[
        "Adda"
    ],
    "name:deu_x_preferred":[
        "Adda"
    ],
    "name:fra_x_preferred":[
        "Adda"
    ],
    "name:ita_x_preferred":[
        "Adda"
    ],
    "name:nld_x_preferred":[
        "Adda"
    ],
    "name:pol_x_preferred":[
        "Adda"
    ],
    "name:por_x_preferred":[
        "Adda"
    ],
    "name:ron_x_preferred":[
        "Adda"
    ],
    "name:rus_x_preferred":[
        "\u0410\u0434\u0434\u0430"
    ],
    "name:spa_x_preferred":[
        "Adda"
    ],
    "name:swe_x_preferred":[
        "Adda"
    ],
    "wof:name":"Adda",
    "wof:placetype":"locality"
},
  "geometry": {"coordinates":[90.98277,23.34284],"type":"Point"}
}