{
  "type": "Feature",
  "properties": {
    "gn:admin1_code":"84",
    "gn:admin2_code":"2015.0",
    "gn:admin3_code":"201561.0",
    "gn:admin4_code":"20156164.0",
    "gn:asciiname":"Kashiaish",
    "gn:country_code":"BD",
    "gn:dem":9,
    "gn:feature_class":"P",
    "gn:feature_code":"PPL",
    "gn:name":"Kashiaish",
    "gn:population":0,
    "gn:timezone":"Asia/Dhaka",
    "iso:country":"BD",
    "name:ben_x_preferred":[
        "Kashiaish"
    ],
    "wof:name":"Kashiaish",
    "wof:placetype":"locality"
},
  "geometry": {"coordinates":[91.92538999999999,22.26027],"type":"Point"}
}