{
  "type": "Feature",
  "properties": {
    "gn:admin1_code":"82",
    "gn:admin2_code":"4087.0",
    "gn:admin3_code":"408704.0",
    "gn:admin4_code":"40870486.0",
    "gn:asciiname":"Gondara",
    "gn:country_code":"BD",
    "gn:dem":8,
    "gn:feature_class":"P",
    "gn:feature_code":"PPL",
    "gn:name":"Gond\u0101ra",
    "gn:population":0,
    "gn:timezone":"Asia/Dhaka",
    "iso:country":"BD",
    "name:und_x_variant":[
        "Godanra",
        "Gond\u0101ra"
    ],
    "wof:name":"Gondara",
    "wof:placetype":"locality"
},
  "geometry": {"coordinates":[89.12575,22.53722],"type":"Point"}
}