{
  "type": "Feature",
  "properties": {
    "gn:admin1_code":"82",
    "gn:admin2_code":"4065",
    "gn:admin3_code":"406552.0",
    "gn:admin4_code":"40655207.0",
    "gn:asciiname":"Sarkol",
    "gn:country_code":"BD",
    "gn:dem":10,
    "gn:feature_class":"P",
    "gn:feature_code":"PPL",
    "gn:name":"S\u0101rkol",
    "gn:population":0,
    "gn:timezone":"Asia/Dhaka",
    "iso:country":"BD",
    "name:ben_x_preferred":[
        "S\u0101rkol"
    ],
    "name:ben_x_variant":[
        "S\u0101rol"
    ],
    "wof:name":"Sarkol",
    "wof:placetype":"locality"
},
  "geometry": {"coordinates":[89.61821999999999,23.11987],"type":"Point"}
}