{
  "type": "Feature",
  "properties": {
    "gn:admin1_code":"H",
    "gn:admin2_code":"3072",
    "gn:admin3_code":"307274.0",
    "gn:admin4_code":"30727487.0",
    "gn:asciiname":"Saidpur",
    "gn:country_code":"BD",
    "gn:dem":13,
    "gn:feature_class":"P",
    "gn:feature_code":"PPL",
    "gn:name":"Saidpur",
    "gn:population":0,
    "gn:timezone":"Asia/Dhaka",
    "iso:country":"BD",
    "wof:name":"Saidpur",
    "wof:placetype":"locality"
},
  "geometry": {"coordinates":[90.79715,24.89978],"type":"Point"}
}