{
  "type": "Feature",
  "properties": {
    "gn:admin1_code":"82",
    "gn:admin2_code":"4041.0",
    "gn:admin3_code":"404147.0",
    "gn:admin4_code":"40414735.0",
    "gn:asciiname":"Diara",
    "gn:country_code":"BD",
    "gn:dem":14,
    "gn:feature_class":"P",
    "gn:feature_code":"PPL",
    "gn:name":"Di\u0101ra",
    "gn:population":0,
    "gn:timezone":"Asia/Dhaka",
    "iso:country":"BD",
    "name:ben_x_preferred":[
        "Di\u0101ra"
    ],
    "wof:name":"Diara",
    "wof:placetype":"locality"
},
  "geometry": {"coordinates":[89.12319000000002,23.14308],"type":"Point"}
}