{
  "type": "Feature",
  "properties": {
    "gn:admin1_code":"82",
    "gn:admin2_code":"4087.0",
    "gn:admin3_code":"408786.0",
    "gn:admin4_code":"40878687.0",
    "gn:asciiname":"Golakhali",
    "gn:country_code":"BD",
    "gn:dem":2,
    "gn:feature_class":"P",
    "gn:feature_code":"PPL",
    "gn:name":"Gol\u0101kh\u0101li",
    "gn:population":0,
    "gn:timezone":"Asia/Dhaka",
    "iso:country":"BD",
    "name:ben_x_preferred":[
        "Gol\u0101kh\u0101li"
    ],
    "wof:name":"Golakhali",
    "wof:placetype":"locality"
},
  "geometry": {"coordinates":[89.08766999999997,22.1905],"type":"Point"}
}