{
  "type": "Feature",
  "properties": {
    "gn:admin1_code":"82",
    "gn:admin2_code":"4001.0",
    "gn:admin3_code":"400156.0",
    "gn:admin4_code":"40015685.0",
    "gn:asciiname":"Betbaria",
    "gn:country_code":"BD",
    "gn:dem":8,
    "gn:feature_class":"P",
    "gn:feature_code":"PPL",
    "gn:name":"Betb\u0101ria",
    "gn:population":0,
    "gn:timezone":"Asia/Dhaka",
    "iso:country":"BD",
    "name:ben_x_preferred":[
        "Betb\u0101ria"
    ],
    "wof:name":"Betbaria",
    "wof:placetype":"locality"
},
  "geometry": {"coordinates":[89.75635,22.89802],"type":"Point"}
}