{
  "type": "Feature",
  "properties": {
    "gn:admin1_code":"H",
    "gn:admin2_code":"3089.0",
    "gn:admin3_code":"308967.0",
    "gn:admin4_code":"30896757.0",
    "gn:asciiname":"Dhukuria",
    "gn:country_code":"BD",
    "gn:dem":20,
    "gn:feature_class":"P",
    "gn:feature_code":"PPL",
    "gn:name":"Dhukuria",
    "gn:population":0,
    "gn:timezone":"Asia/Dhaka",
    "iso:country":"BD",
    "wof:name":"Dhukuria",
    "wof:placetype":"locality"
},
  "geometry": {"coordinates":[90.18232999999999,24.98357],"type":"Point"}
}