{
  "type": "Feature",
  "properties": {
    "gn:admin1_code":"83",
    "gn:admin2_code":"5076",
    "gn:admin3_code":"507639.0",
    "gn:admin4_code":"50763952.0",
    "gn:asciiname":"Ruppur",
    "gn:country_code":"BD",
    "gn:dem":21,
    "gn:feature_class":"P",
    "gn:feature_code":"PPL",
    "gn:name":"Ruppur",
    "gn:population":0,
    "gn:timezone":"Asia/Dhaka",
    "iso:country":"BD",
    "name:und_x_variant":[
        "Rooppur",
        "Ropur",
        "Roopur",
        "Ruppur"
    ],
    "wof:name":"Ruppur",
    "wof:placetype":"locality"
},
  "geometry": {"coordinates":[89.06293000000002,24.0696],"type":"Point"}
}