{
  "type": "Feature",
  "properties": {
    "gn:admin1_code":"82",
    "gn:admin2_code":"4087.0",
    "gn:admin3_code":"408747.0",
    "gn:admin4_code":"40874739.0",
    "gn:asciiname":"Sadarkati",
    "gn:country_code":"BD",
    "gn:dem":5,
    "gn:feature_class":"P",
    "gn:feature_code":"PPL",
    "gn:name":"Sadark\u0101ti",
    "gn:population":0,
    "gn:timezone":"Asia/Dhaka",
    "iso:country":"BD",
    "name:ben_x_preferred":[
        "Sadark\u0101ti"
    ],
    "name:urd_x_preferred":[
        "\u0635\u062f\u0627\u0631\u06a9\u0627\u062a\u06cc"
    ],
    "name:zho_x_preferred":[
        "\u6c99\u8fbe\u5c14\u52a0\u7b2c"
    ],
    "wof:name":"Sadarkati",
    "wof:placetype":"locality"
},
  "geometry": {"coordinates":[88.98343,22.40189],"type":"Point"}
}