{
  "type": "Feature",
  "properties": {
    "gn:admin1_code":"85",
    "gn:admin2_code":"1078",
    "gn:admin3_code":"107838.0",
    "gn:admin4_code":"10783871.0",
    "gn:asciiname":"Dakshin Maminpur",
    "gn:country_code":"BD",
    "gn:dem":11,
    "gn:feature_class":"P",
    "gn:feature_code":"PPL",
    "gn:name":"Dakshin Maminpur",
    "gn:population":0,
    "gn:timezone":"Asia/Dhaka",
    "iso:country":"BD",
    "name:und_x_variant":[
        "Maminpore",
        "Maminpur",
        "Dakshin Maminpur"
    ],
    "wof:name":"Dakshin Maminpur",
    "wof:placetype":"locality"
},
  "geometry": {"coordinates":[90.58360999999999,22.51607000000001],"type":"Point"}
}