{
  "type": "Feature",
  "properties": {
    "gn:admin1_code":"81",
    "gn:admin2_code":"3093",
    "gn:admin3_code":"309376.0",
    "gn:admin4_code":"30937621.0",
    "gn:asciiname":"Jalai",
    "gn:country_code":"BD",
    "gn:dem":15,
    "gn:feature_class":"P",
    "gn:feature_code":"PPL",
    "gn:name":"J\u0101l\u0101i",
    "gn:population":0,
    "gn:timezone":"Asia/Dhaka",
    "iso:country":"BD",
    "wof:name":"Jalai",
    "wof:placetype":"locality"
},
  "geometry": {"coordinates":[89.80433000000002,23.99547],"type":"Point"}
}