{
  "type": "Feature",
  "properties": {
    "gn:admin1_code":"85",
    "gn:admin2_code":"1006.0",
    "gn:admin3_code":"100662.0",
    "gn:admin4_code":"10066231.0",
    "gn:asciiname":"Char Madhab Rai",
    "gn:country_code":"BD",
    "gn:dem":12,
    "gn:feature_class":"P",
    "gn:feature_code":"PPL",
    "gn:name":"Char M\u0101dhab R\u0101i",
    "gn:population":0,
    "gn:timezone":"Asia/Dhaka",
    "iso:country":"BD",
    "name:und_x_variant":[
        "Char Madhabray",
        "Char M\u0101dhab R\u0101i"
    ],
    "wof:name":"Char Madhab Rai",
    "wof:placetype":"locality"
},
  "geometry": {"coordinates":[90.43792000000001,22.83279],"type":"Point"}
}