{
  "type": "Feature",
  "properties": {
    "gn:admin1_code":"87",
    "gn:admin2_code":"5527.0",
    "gn:admin3_code":"552710.0",
    "gn:admin4_code":"55271023.0",
    "gn:asciiname":"Ramkrishnapur",
    "gn:country_code":"BD",
    "gn:dem":30,
    "gn:feature_class":"P",
    "gn:feature_code":"PPL",
    "gn:name":"R\u0101mkrishnapur",
    "gn:population":0,
    "gn:timezone":"Asia/Dhaka",
    "iso:country":"BD",
    "name:ben_x_preferred":[
        "R\u0101mkrishnapur"
    ],
    "wof:name":"Ramkrishnapur",
    "wof:placetype":"locality"
},
  "geometry": {"coordinates":[88.95605999999999,25.37448],"type":"Point"}
}