{
  "type": "Feature",
  "properties": {
    "gn:admin1_code":"83",
    "gn:admin2_code":"5064",
    "gn:admin3_code":"506460.0",
    "gn:admin4_code":"50646036.0",
    "gn:asciiname":"Ramraipur",
    "gn:country_code":"BD",
    "gn:dem":18,
    "gn:feature_class":"P",
    "gn:feature_code":"PPL",
    "gn:name":"R\u0101mr\u0101ipur",
    "gn:population":0,
    "gn:timezone":"Asia/Dhaka",
    "iso:country":"BD",
    "name:ben_x_preferred":[
        "R\u0101mr\u0101ipur"
    ],
    "wof:name":"Ramraipur",
    "wof:placetype":"locality"
},
  "geometry": {"coordinates":[88.91330000000001,24.7449],"type":"Point"}
}