{
  "type": "Feature",
  "properties": {
    "gn:admin1_code":"83",
    "gn:admin2_code":"5064.0",
    "gn:admin3_code":"506403.0",
    "gn:admin4_code":"50640352.0",
    "gn:asciiname":"Taranagar",
    "gn:country_code":"BD",
    "gn:dem":17,
    "gn:feature_class":"P",
    "gn:feature_code":"PPL",
    "gn:name":"T\u0101r\u0101nagar",
    "gn:population":0,
    "gn:timezone":"Asia/Dhaka",
    "iso:country":"BD",
    "name:ben_x_preferred":[
        "T\u0101r\u0101nagar"
    ],
    "wof:name":"Taranagar",
    "wof:placetype":"locality"
},
  "geometry": {"coordinates":[88.90018000000001,24.66888],"type":"Point"}
}