{
  "type": "Feature",
  "properties": {
    "gn:admin1_code":"83",
    "gn:admin2_code":"5064.0",
    "gn:admin3_code":"506403.0",
    "gn:admin4_code":"50640352.0",
    "gn:asciiname":"Taranagar",
    "gn:country_code":"BD",
    "gn:dem":17,
    "gn:feature_class":"P",
    "gn:feature_code":"PPL",
    "gn:name":"T\u0101r\u0101nagar",
    "gn:population":0,
    "gn:timezone":"Asia/Dhaka",
    "iso:country":"BD",
    "name:ben_x_preferred":[
        "T\u0101r\u0101nagar"
    ],
    "name:ben_x_variant":[
        "\u09a4\u09be\u09b0\u09be\u09a8\u0997\u09b0"
    ],
    "name:bpy_x_preferred":[
        "\u09a4\u09be\u09b0\u09be\u09a8\u0997\u09b0"
    ],
    "name:ceb_x_preferred":[
        "T\u0101r\u0101nagar"
    ],
    "name:hin_x_preferred":[
        "\u0924\u093e\u0930\u093e\u0928\u0917\u0930"
    ],
    "name:ita_x_preferred":[
        "Taranagar"
    ],
    "name:mlg_x_preferred":[
        "Taranagar"
    ],
    "name:msa_x_preferred":[
        "Taranagar"
    ],
    "name:ori_x_preferred":[
        "\u0b24\u0b3e\u0b30\u0b3e\u0b28\u0b17\u0b30"
    ],
    "name:swe_x_preferred":[
        "T\u0101r\u0101nagar"
    ],
    "name:urd_x_preferred":[
        "\u062a\u0627\u0631\u0627\u0646\u06af\u0631"
    ],
    "name:vie_x_preferred":[
        "Taranagar"
    ],
    "name:zho_x_preferred":[
        "\u5854\u62c9\u7eb3\u52a0\u5c14"
    ],
    "wof:name":"Taranagar",
    "wof:placetype":"locality"
},
  "geometry": {"coordinates":[88.90018000000001,24.66888],"type":"Point"}
}