{
  "type": "Feature",
  "properties": {
    "gn:admin1_code":"81",
    "gn:admin2_code":"3048",
    "gn:admin3_code":"304879.0",
    "gn:admin4_code":"30487957.0",
    "gn:asciiname":"Jangalia",
    "gn:country_code":"BD",
    "gn:dem":15,
    "gn:feature_class":"P",
    "gn:feature_code":"PPL",
    "gn:name":"J\u0101ng\u0101lia",
    "gn:population":0,
    "gn:timezone":"Asia/Dhaka",
    "iso:country":"BD",
    "wof:name":"Jangalia",
    "wof:placetype":"locality"
},
  "geometry": {"coordinates":[90.66784,24.3781],"type":"Point"}
}