{
  "type": "Feature",
  "properties": {
    "gn:admin1_code":"87",
    "gn:admin2_code":"5552.0",
    "gn:admin3_code":"555202.0",
    "gn:admin4_code":"55520211.0",
    "gn:asciiname":"Bhelabari",
    "gn:country_code":"BD",
    "gn:dem":36,
    "gn:feature_class":"P",
    "gn:feature_code":"PPL",
    "gn:name":"Bhel\u0101b\u0101ri",
    "gn:population":0,
    "gn:timezone":"Asia/Dhaka",
    "iso:country":"BD",
    "name:ben_x_preferred":[
        "Bhel\u0101b\u0101ri"
    ],
    "wof:name":"Bhelabari",
    "wof:placetype":"locality"
},
  "geometry": {"coordinates":[89.37751999999998,25.97932],"type":"Point"}
}