{
  "type": "Feature",
  "properties": {
    "gn:admin1_code":"85",
    "gn:admin2_code":"1006",
    "gn:admin3_code":"100662.0",
    "gn:admin4_code":"10066287.0",
    "gn:asciiname":"Sonamukhi",
    "gn:country_code":"BD",
    "gn:dem":8,
    "gn:feature_class":"P",
    "gn:feature_code":"PPL",
    "gn:name":"Son\u0101mukhi",
    "gn:population":0,
    "gn:timezone":"Asia/Dhaka",
    "iso:country":"BD",
    "name:ben_x_preferred":[
        "\u09b8\u09cb\u09a8\u09be\u09ae\u09c1\u0996\u09bf"
    ],
    "name:bpy_x_preferred":[
        "\u09b8\u09cb\u09a8\u09be\u09ae\u09c1\u0996\u09bf"
    ],
    "name:ceb_x_preferred":[
        "Son\u0101mukhi"
    ],
    "name:hif_x_preferred":[
        "Sonamukhi"
    ],
    "name:ita_x_preferred":[
        "Sonamukhi"
    ],
    "name:mlg_x_preferred":[
        "Sonamukhi"
    ],
    "name:msa_x_preferred":[
        "Sonamukhi"
    ],
    "name:ori_x_preferred":[
        "\u0b38\u0b4b\u0b28\u0b3e\u0b2e\u0b41\u0b16\u0b3f"
    ],
    "name:por_x_preferred":[
        "Sonamukhi"
    ],
    "name:spa_x_preferred":[
        "Sonamukhi"
    ],
    "name:swe_x_preferred":[
        "Son\u0101mukhi"
    ],
    "name:urd_x_preferred":[
        "\u0633\u0648\u0646\u0627 \u0645\u06a9\u06be\u06cc"
    ],
    "name:vie_x_preferred":[
        "Sonamukhi"
    ],
    "name:zho_x_preferred":[
        "\u7d22\u7eb3\u7a46\u57fa"
    ],
    "wof:name":"Sonamukhi",
    "wof:placetype":"locality"
},
  "geometry": {"coordinates":[90.51893,22.82233],"type":"Point"}
}