{
  "type": "Feature",
  "properties": {
    "gn:admin1_code":"85",
    "gn:admin2_code":"1006",
    "gn:admin3_code":"100662.0",
    "gn:admin4_code":"10066287.0",
    "gn:asciiname":"Sonamukhi",
    "gn:country_code":"BD",
    "gn:dem":8,
    "gn:feature_class":"P",
    "gn:feature_code":"PPL",
    "gn:name":"Son\u0101mukhi",
    "gn:population":0,
    "gn:timezone":"Asia/Dhaka",
    "iso:country":"BD",
    "wof:name":"Sonamukhi",
    "wof:placetype":"locality"
},
  "geometry": {"coordinates":[90.51893,22.82233],"type":"Point"}
}