{
  "type": "Feature",
  "properties": {
    "gn:admin1_code":"83",
    "gn:admin2_code":"5081",
    "gn:admin3_code":"508134.0",
    "gn:admin4_code":"50813466.0",
    "gn:asciiname":"Jote Gobinda",
    "gn:country_code":"BD",
    "gn:dem":44,
    "gn:feature_class":"P",
    "gn:feature_code":"PPL",
    "gn:name":"Jote Gobinda",
    "gn:population":0,
    "gn:timezone":"Asia/Dhaka",
    "iso:country":"BD",
    "name:ben_x_preferred":[
        "Jote Gobinda"
    ],
    "name:und_x_variant":[
        "Jot Gobinda"
    ],
    "wof:name":"Jote Gobinda",
    "wof:placetype":"locality"
},
  "geometry": {"coordinates":[88.4084,24.56471],"type":"Point"}
}