{
  "type": "Feature",
  "properties": {
    "gn:admin1_code":"84",
    "gn:admin2_code":"2075.0",
    "gn:admin3_code":"207587.0",
    "gn:admin4_code":"20758780.0",
    "gn:asciiname":"Noanni",
    "gn:country_code":"BD",
    "gn:dem":7,
    "gn:feature_class":"P",
    "gn:feature_code":"PPL",
    "gn:name":"Noanni",
    "gn:population":0,
    "gn:timezone":"Asia/Dhaka",
    "iso:country":"BD",
    "wof:name":"Noanni",
    "wof:placetype":"locality"
},
  "geometry": {"coordinates":[91.08389,22.75111],"type":"Point"}
}