{
  "type": "Feature",
  "properties": {
    "gn:admin1_code":"84",
    "gn:admin2_code":"2013.0",
    "gn:admin3_code":"201395.0",
    "gn:admin4_code":"20139595.0",
    "gn:asciiname":"Daulbari",
    "gn:country_code":"BD",
    "gn:dem":11,
    "gn:feature_class":"P",
    "gn:feature_code":"PPL",
    "gn:name":"Daulb\u0101ri",
    "gn:population":0,
    "gn:timezone":"Asia/Dhaka",
    "iso:country":"BD",
    "name:und_x_variant":[
        "Doulbari",
        "Daulb\u0101ri"
    ],
    "wof:name":"Daulbari",
    "wof:placetype":"locality"
},
  "geometry": {"coordinates":[90.9443,23.26015],"type":"Point"}
}