{
  "type": "Feature",
  "properties": {
    "gn:admin1_code":"81",
    "gn:admin2_code":"3056",
    "gn:admin3_code":"305670.0",
    "gn:admin4_code":"30567066.0",
    "gn:asciiname":"Naora Narottampur Dakshin Khanda",
    "gn:country_code":"BD",
    "gn:dem":15,
    "gn:feature_class":"P",
    "gn:feature_code":"PPL",
    "gn:name":"N\u0101ora Narottampur Dakshin Khanda",
    "gn:population":0,
    "gn:timezone":"Asia/Dhaka",
    "iso:country":"BD",
    "wof:name":"Naora Narottampur Dakshin Khanda",
    "wof:placetype":"locality"
},
  "geometry": {"coordinates":[90.02920999999998,23.92789],"type":"Point"}
}