{
  "type": "Feature",
  "properties": {
    "gn:admin1_code":"81",
    "gn:admin2_code":"3026.0",
    "gn:admin3_code":"302638.0",
    "gn:admin4_code":"30263808.0",
    "gn:asciiname":"Dhitpur",
    "gn:country_code":"BD",
    "gn:dem":8,
    "gn:feature_class":"P",
    "gn:feature_code":"PPL",
    "gn:name":"Dhitpur",
    "gn:population":0,
    "gn:timezone":"Asia/Dhaka",
    "iso:country":"BD",
    "wof:name":"Dhitpur",
    "wof:placetype":"locality"
},
  "geometry": {"coordinates":[90.35791999999999,23.68532],"type":"Point"}
}