{
  "type": "Feature",
  "properties": {
    "gn:admin1_code":"83",
    "gn:asciiname":"Beltali",
    "gn:country_code":"BD",
    "gn:dem":23,
    "gn:feature_class":"P",
    "gn:feature_code":"PPL",
    "gn:name":"Beltali",
    "gn:population":0,
    "gn:timezone":"Asia/Dhaka",
    "iso:country":"BD",
    "name:ben_x_preferred":[
        "Beltali"
    ],
    "wof:name":"Beltali",
    "wof:placetype":"locality"
},
  "geometry": {"coordinates":[89.5565,25.17353],"type":"Point"}
}