{
  "type": "Feature",
  "properties": {
    "gn:admin1_code":"87",
    "gn:admin2_code":"5577",
    "gn:admin3_code":"557773.0",
    "gn:admin4_code":"55777335.0",
    "gn:asciiname":"Malani Arazi",
    "gn:country_code":"BD",
    "gn:dem":76,
    "gn:feature_class":"P",
    "gn:feature_code":"PPL",
    "gn:name":"Mal\u0101ni \u0100r\u0101zi",
    "gn:population":0,
    "gn:timezone":"Asia/Dhaka",
    "iso:country":"BD",
    "name:ben_x_preferred":[
        "Mal\u0101ni \u0100r\u0101zi"
    ],
    "name:und_x_variant":[
        "Molaniaraji"
    ],
    "wof:name":"Malani Arazi",
    "wof:placetype":"locality"
},
  "geometry": {"coordinates":[88.61294000000002,26.36658],"type":"Point"}
}