{
  "type": "Feature",
  "properties": {
    "gn:admin1_code":"87",
    "gn:admin2_code":"5552.0",
    "gn:admin3_code":"555270.0",
    "gn:admin4_code":"55527067.0",
    "gn:asciiname":"Beng Kanda",
    "gn:country_code":"BD",
    "gn:dem":64,
    "gn:feature_class":"P",
    "gn:feature_code":"PPL",
    "gn:name":"Beng Kanda",
    "gn:population":0,
    "gn:timezone":"Asia/Dhaka",
    "iso:country":"BD",
    "name:ben_x_preferred":[
        "Beng Kanda"
    ],
    "wof:name":"Beng Kanda",
    "wof:placetype":"locality"
},
  "geometry": {"coordinates":[89.00359,26.36934],"type":"Point"}
}