{
  "type": "Feature",
  "properties": {
    "gn:admin1_code":"87",
    "gn:admin2_code":"5552",
    "gn:admin3_code":"555233.0",
    "gn:admin4_code":"55523338.0",
    "gn:asciiname":"Nij Gaddimari",
    "gn:country_code":"BD",
    "gn:dem":56,
    "gn:feature_class":"P",
    "gn:feature_code":"PPL",
    "gn:name":"Nij Gaddimari",
    "gn:population":0,
    "gn:timezone":"Asia/Dhaka",
    "iso:country":"BD",
    "name:und_x_variant":[
        "Nij Gadm\u0101ri"
    ],
    "wof:name":"Nij Gaddimari",
    "wof:placetype":"locality"
},
  "geometry": {"coordinates":[89.07996999999997,26.1846],"type":"Point"}
}