{
  "type": "Feature",
  "properties": {
    "gn:admin1_code":"84",
    "gn:admin2_code":"2075",
    "gn:admin3_code":"207589.0",
    "gn:admin4_code":"20758995.0",
    "gn:asciiname":"Sandalpur",
    "gn:cc2":"BD",
    "gn:country_code":"BD",
    "gn:dem":10,
    "gn:feature_class":"P",
    "gn:feature_code":"PPL",
    "gn:name":"Sandalpur",
    "gn:population":0,
    "gn:timezone":"Asia/Dhaka",
    "iso:country":"BD",
    "name:hif_x_preferred":[
        "Sandalpur"
    ],
    "name:und_x_variant":[
        "Sondalpur"
    ],
    "wof:name":"Sandalpur",
    "wof:placetype":"locality"
},
  "geometry": {"coordinates":[91.18333,22.83333],"type":"Point"}
}