{
  "type": "Feature",
  "properties": {
    "gn:admin1_code":"81",
    "gn:admin2_code":"3067.0",
    "gn:admin3_code":"306768.0",
    "gn:admin4_code":"30676863.0",
    "gn:asciiname":"Baniadi",
    "gn:country_code":"BD",
    "gn:dem":13,
    "gn:feature_class":"P",
    "gn:feature_code":"PPL",
    "gn:name":"B\u0101ni\u0101di",
    "gn:population":0,
    "gn:timezone":"Asia/Dhaka",
    "iso:country":"BD",
    "wof:name":"Baniadi",
    "wof:placetype":"locality"
},
  "geometry": {"coordinates":[90.52759,23.79455],"type":"Point"}
}