{
  "type": "Feature",
  "properties": {
    "gn:admin1_code":"87",
    "gn:admin2_code":"5527",
    "gn:admin3_code":"552769.0",
    "gn:admin4_code":"55276977.0",
    "gn:asciiname":"Purba Fatehpur",
    "gn:country_code":"BD",
    "gn:dem":32,
    "gn:feature_class":"P",
    "gn:feature_code":"PPL",
    "gn:name":"Purba Fatehpur",
    "gn:population":0,
    "gn:timezone":"Asia/Dhaka",
    "iso:country":"BD",
    "name:ben_x_preferred":[
        "Purba Fatehpur"
    ],
    "wof:name":"Purba Fatehpur",
    "wof:placetype":"locality"
},
  "geometry": {"coordinates":[89.19178000000002,25.37148],"type":"Point"}
}