{
  "type": "Feature",
  "properties": {
    "gn:admin1_code":"H",
    "gn:admin2_code":"3072.0",
    "gn:admin3_code":"307256.0",
    "gn:admin4_code":"30725642.0",
    "gn:asciiname":"Durgasram",
    "gn:country_code":"BD",
    "gn:dem":15,
    "gn:feature_class":"P",
    "gn:feature_code":"PPL",
    "gn:name":"Durg\u0101sram",
    "gn:population":0,
    "gn:timezone":"Asia/Dhaka",
    "iso:country":"BD",
    "wof:name":"Durgasram",
    "wof:placetype":"locality"
},
  "geometry": {"coordinates":[90.90844,24.69271],"type":"Point"}
}