{
  "type": "Feature",
  "properties": {
    "gn:admin1_code":"87",
    "gn:admin2_code":"5594.0",
    "gn:admin3_code":"559451.0",
    "gn:admin4_code":"55945127.0",
    "gn:asciiname":"Dhukuria",
    "gn:country_code":"BD",
    "gn:dem":43,
    "gn:feature_class":"P",
    "gn:feature_code":"PPL",
    "gn:name":"Dhukuria",
    "gn:population":0,
    "gn:timezone":"Asia/Dhaka",
    "iso:country":"BD",
    "name:ben_x_preferred":[
        "Dhukuria"
    ],
    "wof:name":"Dhukuria",
    "wof:placetype":"locality"
},
  "geometry": {"coordinates":[88.1071,25.9103],"type":"Point"}
}