{
  "type": "Feature",
  "properties": {
    "gn:admin1_code":"81",
    "gn:admin2_code":"3068.0",
    "gn:admin3_code":"306863.0",
    "gn:admin4_code":"30686363.0",
    "gn:asciiname":"Gabtali",
    "gn:country_code":"BD",
    "gn:dem":14,
    "gn:feature_class":"P",
    "gn:feature_code":"PPL",
    "gn:name":"G\u0101btali",
    "gn:population":0,
    "gn:timezone":"Asia/Dhaka",
    "iso:country":"BD",
    "wof:name":"Gabtali",
    "wof:placetype":"locality"
},
  "geometry": {"coordinates":[90.65082,23.96399],"type":"Point"}
}