{
  "type": "Feature",
  "properties": {
    "gn:admin1_code":"81",
    "gn:admin2_code":"3093.0",
    "gn:admin3_code":"309328.0",
    "gn:admin4_code":"30932825.0",
    "gn:asciiname":"Chaurasa",
    "gn:country_code":"BD",
    "gn:dem":28,
    "gn:feature_class":"P",
    "gn:feature_code":"PPL",
    "gn:name":"Chaur\u0101sa",
    "gn:population":0,
    "gn:timezone":"Asia/Dhaka",
    "iso:country":"BD",
    "wof:name":"Chaurasa",
    "wof:placetype":"locality"
},
  "geometry": {"coordinates":[90.05422,24.45573],"type":"Point"}
}