{
  "type": "Feature",
  "properties": {
    "gn:admin1_code":"83",
    "gn:admin2_code":"5010",
    "gn:admin3_code":"501020.0",
    "gn:admin4_code":"50102064.0",
    "gn:asciiname":"Phulbari",
    "gn:country_code":"BD",
    "gn:dem":23,
    "gn:feature_class":"P",
    "gn:feature_code":"PPL",
    "gn:name":"Phulb\u0101ri",
    "gn:population":0,
    "gn:timezone":"Asia/Dhaka",
    "iso:country":"BD",
    "wof:name":"Phulbari",
    "wof:placetype":"locality"
},
  "geometry": {"coordinates":[89.37210999999998,24.87259],"type":"Point"}
}