{
  "type": "Feature",
  "properties": {
    "gn:admin1_code":"81",
    "gn:admin2_code":"3068",
    "gn:admin3_code":"306860.0",
    "gn:admin4_code":"30686047.0",
    "gn:asciiname":"Khamardi",
    "gn:country_code":"BD",
    "gn:dem":12,
    "gn:feature_class":"P",
    "gn:feature_code":"PPL",
    "gn:name":"Kh\u0101m\u0101rdi",
    "gn:population":0,
    "gn:timezone":"Asia/Dhaka",
    "iso:country":"BD",
    "wof:name":"Khamardi",
    "wof:placetype":"locality"
},
  "geometry": {"coordinates":[90.66191000000001,23.80803],"type":"Point"}
}