{
  "type": "Feature",
  "properties": {
    "gn:admin1_code":"H",
    "gn:admin2_code":"3061.0",
    "gn:admin3_code":"306123.0",
    "gn:admin4_code":"30612318.0",
    "gn:asciiname":"Bakhripara",
    "gn:country_code":"BD",
    "gn:dem":16,
    "gn:feature_class":"P",
    "gn:feature_code":"PPL",
    "gn:name":"B\u0101khrip\u0101ra",
    "gn:population":0,
    "gn:timezone":"Asia/Dhaka",
    "iso:country":"BD",
    "wof:name":"Bakhripara",
    "wof:placetype":"locality"
},
  "geometry": {"coordinates":[90.48763,24.70633],"type":"Point"}
}