{
  "type": "Feature",
  "properties": {
    "gn:admin1_code":"84",
    "gn:admin2_code":"2019.0",
    "gn:admin3_code":"201918.0",
    "gn:admin4_code":"20191831.0",
    "gn:asciiname":"Paschlim Burichang",
    "gn:country_code":"BD",
    "gn:dem":11,
    "gn:feature_class":"P",
    "gn:feature_code":"PPL",
    "gn:name":"Paschlim Burichang",
    "gn:population":0,
    "gn:timezone":"Asia/Dhaka",
    "iso:country":"BD",
    "wof:name":"Paschlim Burichang",
    "wof:placetype":"locality"
},
  "geometry": {"coordinates":[91.13694,23.56556],"type":"Point"}
}