{
  "type": "Feature",
  "properties": {
    "gn:admin1_code":"84",
    "gn:admin2_code":"2012.0",
    "gn:admin3_code":"201290.0",
    "gn:admin4_code":"20129043.0",
    "gn:asciiname":"Fanda Uk",
    "gn:country_code":"BD",
    "gn:dem":15,
    "gn:feature_class":"P",
    "gn:feature_code":"PPL",
    "gn:name":"Fanda Uk",
    "gn:population":0,
    "gn:timezone":"Asia/Dhaka",
    "iso:country":"BD",
    "wof:name":"Fanda Uk",
    "wof:placetype":"locality"
},
  "geometry": {"coordinates":[91.24276999999999,24.22833],"type":"Point"}
}