{
  "type": "Feature",
  "properties": {
    "gn:admin1_code":"83",
    "gn:admin2_code":"5069.0",
    "gn:admin3_code":"506963.0",
    "gn:admin4_code":"50696373.0",
    "gn:asciiname":"Halti",
    "gn:country_code":"BD",
    "gn:dem":14,
    "gn:feature_class":"P",
    "gn:feature_code":"PPL",
    "gn:name":"H\u0101lti",
    "gn:population":0,
    "gn:timezone":"Asia/Dhaka",
    "iso:country":"BD",
    "name:ara_x_preferred":[
        "\u0647\u0644\u062a\u064a"
    ],
    "name:ben_x_preferred":[
        "H\u0101lti"
    ],
    "name:bul_x_preferred":[
        "\u0425\u0430\u043b\u0442\u0438"
    ],
    "name:cat_x_preferred":[
        "Halti"
    ],
    "name:ceb_x_preferred":[
        "Halti"
    ],
    "name:ces_x_preferred":[
        "Halti"
    ],
    "name:dan_x_preferred":[
        "Halti"
    ],
    "name:deu_x_preferred":[
        "Haltitunturi"
    ],
    "name:est_x_preferred":[
        "Halti"
    ],
    "name:eus_x_preferred":[
        "Halti"
    ],
    "name:fin_x_preferred":[
        "Halti"
    ],
    "name:fra_x_preferred":[
        "Halti"
    ],
    "name:glg_x_preferred":[
        "Haltitunturi"
    ],
    "name:hun_x_preferred":[
        "Haltitunturi"
    ],
    "name:hye_x_preferred":[
        "\u0540\u0561\u056c\u057f\u056b\u0561"
    ],
    "name:ita_x_preferred":[
        "Halti"
    ],
    "name:jpn_x_preferred":[
        "\u30cf\u30eb\u30c6\u30a3"
    ],
    "name:kat_x_preferred":[
        "\u10f0\u10d0\u10da\u10e2\u10d8"
    ],
    "name:kor_x_preferred":[
        "\ud560\ud2f0\uc0b0"
    ],
    "name:lit_x_preferred":[
        "Haltis"
    ],
    "name:lmo_x_preferred":[
        "Halti"
    ],
    "name:nld_x_preferred":[
        "Haltiatunturi"
    ],
    "name:nno_x_preferred":[
        "Halti"
    ],
    "name:nor_x_preferred":[
        "Halti"
    ],
    "name:pol_x_preferred":[
        "Haltiatunturi"
    ],
    "name:por_x_preferred":[
        "Halti"
    ],
    "name:rus_x_preferred":[
        "\u0425\u0430\u043b\u0442\u0438\u0430"
    ],
    "name:slk_x_preferred":[
        "Halti"
    ],
    "name:sme_x_preferred":[
        "H\u00e1ldi"
    ],
    "name:spa_x_preferred":[
        "Monte Halti"
    ],
    "name:swa_x_preferred":[
        "Haltitunturi"
    ],
    "name:swe_x_preferred":[
        "Halde fj\u00e4ll"
    ],
    "name:tur_x_preferred":[
        "Halti Da\u011f\u0131"
    ],
    "name:udm_x_preferred":[
        "\u0425\u0430\u043b\u0442\u0438"
    ],
    "name:ukr_x_preferred":[
        "\u0425\u0430\u043b\u0442\u0456"
    ],
    "name:zho_x_preferred":[
        "\u54c8\u723e\u8482\u4e9e\u5cf0"
    ],
    "wof:name":"Halti",
    "wof:placetype":"locality"
},
  "geometry": {"coordinates":[88.99588,24.52045],"type":"Point"}
}