{
  "type": "Feature",
  "properties": {
    "gn:admin1_code":"87",
    "gn:admin2_code":"5577.0",
    "gn:admin3_code":"557790.0",
    "gn:admin4_code":"55779094.0",
    "gn:asciiname":"Hakimpur",
    "gn:country_code":"BD",
    "gn:dem":98,
    "gn:feature_class":"P",
    "gn:feature_code":"PPL",
    "gn:name":"H\u0101kimpur",
    "gn:population":0,
    "gn:timezone":"Asia/Dhaka",
    "iso:country":"BD",
    "name:ben_x_preferred":[
        "H\u0101kimpur"
    ],
    "wof:name":"Hakimpur",
    "wof:placetype":"locality"
},
  "geometry": {"coordinates":[88.40581999999998,26.5586],"type":"Point"}
}