{
  "type": "Feature",
  "properties": {
    "gn:admin1_code":"81",
    "gn:admin2_code":"3026",
    "gn:admin3_code":"302640.0",
    "gn:admin4_code":"30264086.0",
    "gn:asciiname":"Jatrabari",
    "gn:country_code":"BD",
    "gn:dem":12,
    "gn:feature_class":"P",
    "gn:feature_code":"PPL",
    "gn:name":"J\u0101tr\u0101b\u0101ri",
    "gn:population":0,
    "gn:timezone":"Asia/Dhaka",
    "iso:country":"BD",
    "wof:name":"Jatrabari",
    "wof:placetype":"locality"
},
  "geometry": {"coordinates":[90.43198,23.70748],"type":"Point"}
}