{
  "type": "Feature",
  "properties": {
    "gn:admin1_code":"82",
    "gn:admin2_code":"4065.0",
    "gn:admin3_code":"406528.0",
    "gn:admin4_code":"40652847.0",
    "gn:asciiname":"Loharganti",
    "gn:country_code":"BD",
    "gn:dem":8,
    "gn:feature_class":"P",
    "gn:feature_code":"PPL",
    "gn:name":"Loharganti",
    "gn:population":0,
    "gn:timezone":"Asia/Dhaka",
    "iso:country":"BD",
    "name:ben_x_preferred":[
        "Loharganti"
    ],
    "wof:name":"Loharganti",
    "wof:placetype":"locality"
},
  "geometry": {"coordinates":[89.66978,22.99733],"type":"Point"}
}