{
  "type": "Feature",
  "properties": {
    "gn:admin1_code":"84",
    "gn:admin2_code":"2019.0",
    "gn:admin3_code":"201954.0",
    "gn:admin4_code":"20195447.0",
    "gn:asciiname":"Dulalpur",
    "gn:country_code":"BD",
    "gn:dem":10,
    "gn:feature_class":"P",
    "gn:feature_code":"PPL",
    "gn:name":"Dul\u0101lpur",
    "gn:population":0,
    "gn:timezone":"Asia/Dhaka",
    "iso:country":"BD",
    "wof:name":"Dulalpur",
    "wof:placetype":"locality"
},
  "geometry": {"coordinates":[90.81037000000001,23.72303],"type":"Point"}
}