{
  "type": "Feature",
  "properties": {
    "gn:admin1_code":"83",
    "gn:admin2_code":"5081",
    "gn:admin3_code":"508110.0",
    "gn:admin4_code":"50811015.0",
    "gn:asciiname":"Jot Jayram",
    "gn:country_code":"BD",
    "gn:dem":23,
    "gn:feature_class":"P",
    "gn:feature_code":"PPL",
    "gn:name":"Jot Jayr\u0101m",
    "gn:population":0,
    "gn:timezone":"Asia/Dhaka",
    "iso:country":"BD",
    "name:ben_x_preferred":[
        "Jot Jayr\u0101m"
    ],
    "wof:name":"Jot Jayram",
    "wof:placetype":"locality"
},
  "geometry": {"coordinates":[88.86991,24.18264],"type":"Point"}
}