{
  "type": "Feature",
  "properties": {
    "gn:admin1_code":"83",
    "gn:admin2_code":"5076.0",
    "gn:admin3_code":"507672.0",
    "gn:admin4_code":"50767269.0",
    "gn:asciiname":"Baliakandi",
    "gn:country_code":"BD",
    "gn:dem":17,
    "gn:feature_class":"P",
    "gn:feature_code":"PPL",
    "gn:name":"B\u0101li\u0101k\u0101ndi",
    "gn:population":0,
    "gn:timezone":"Asia/Dhaka",
    "iso:country":"BD",
    "name:ben_x_preferred":[
        "B\u0101li\u0101k\u0101ndi"
    ],
    "wof:name":"Baliakandi",
    "wof:placetype":"locality"
},
  "geometry": {"coordinates":[89.51394999999999,23.98399],"type":"Point"}
}