{
  "type": "Feature",
  "properties": {
    "gn:admin1_code":"H",
    "gn:admin2_code":"3061",
    "gn:admin3_code":"306194.0",
    "gn:admin4_code":"30619447.0",
    "gn:asciiname":"Jilki",
    "gn:country_code":"BD",
    "gn:dem":18,
    "gn:feature_class":"P",
    "gn:feature_code":"PPL",
    "gn:name":"Jilki",
    "gn:population":0,
    "gn:timezone":"Asia/Dhaka",
    "iso:country":"BD",
    "wof:name":"Jilki",
    "wof:placetype":"locality"
},
  "geometry": {"coordinates":[90.48442,24.62124],"type":"Point"}
}