{
  "type": "Feature",
  "properties": {
    "gn:admin1_code":"82",
    "gn:admin2_code":"4041",
    "gn:admin3_code":"404147.0",
    "gn:admin4_code":"40414765.0",
    "gn:asciiname":"Shyamnagar",
    "gn:country_code":"BD",
    "gn:dem":14,
    "gn:feature_class":"P",
    "gn:feature_code":"PPL",
    "gn:name":"Shy\u0101mnagar",
    "gn:population":0,
    "gn:timezone":"Asia/Dhaka",
    "iso:country":"BD",
    "name:ben_x_preferred":[
        "Shy\u0101mnagar"
    ],
    "name:ben_x_variant":[
        "Sy\u0101mnagar"
    ],
    "wof:name":"Shyamnagar",
    "wof:placetype":"locality"
},
  "geometry": {"coordinates":[89.19362,23.2443],"type":"Point"}
}