{
  "type": "Feature",
  "properties": {
    "gn:admin1_code":"H",
    "gn:admin2_code":"3061",
    "gn:admin3_code":"306120.0",
    "gn:admin4_code":"30612059.0",
    "gn:asciiname":"Kusmail Neugi",
    "gn:country_code":"BD",
    "gn:dem":13,
    "gn:feature_class":"P",
    "gn:feature_code":"PPL",
    "gn:name":"Kusm\u0101il Neugi",
    "gn:population":0,
    "gn:timezone":"Asia/Dhaka",
    "iso:country":"BD",
    "wof:name":"Kusmail Neugi",
    "wof:placetype":"locality"
},
  "geometry": {"coordinates":[90.24831,24.66565],"type":"Point"}
}