{
  "type": "Feature",
  "properties": {
    "gn:admin1_code":"84",
    "gn:admin2_code":"2046",
    "gn:admin3_code":"204667.0",
    "gn:admin4_code":"20466763.0",
    "gn:asciiname":"Jugyachola",
    "gn:country_code":"BD",
    "gn:dem":31,
    "gn:feature_class":"P",
    "gn:feature_code":"PPL",
    "gn:name":"Jugy\u0101chola",
    "gn:population":0,
    "gn:timezone":"Asia/Dhaka",
    "iso:country":"BD",
    "name:ben_x_preferred":[
        "Jujkhola"
    ],
    "name:ben_x_variant":[
        "Jugy\u0101chola"
    ],
    "name:und_x_variant":[
        "Jugy\u0101chola"
    ],
    "wof:name":"Jugyachola",
    "wof:placetype":"locality"
},
  "geometry": {"coordinates":[91.76948,22.82564],"type":"Point"}
}