{
  "type": "Feature",
  "properties": {
    "gn:admin1_code":"82",
    "gn:admin2_code":"4055.0",
    "gn:admin3_code":"405557.0",
    "gn:admin4_code":"40555713.0",
    "gn:asciiname":"Gazar Garia Bil",
    "gn:country_code":"BD",
    "gn:dem":8,
    "gn:feature_class":"P",
    "gn:feature_code":"PPL",
    "gn:name":"Gazar Garia Bil",
    "gn:population":0,
    "gn:timezone":"Asia/Dhaka",
    "iso:country":"BD",
    "name:ben_x_preferred":[
        "Gazar Garia Bil"
    ],
    "wof:name":"Gazar Garia Bil",
    "wof:placetype":"locality"
},
  "geometry": {"coordinates":[89.49330999999999,23.37139],"type":"Point"}
}