{
  "type": "Feature",
  "properties": {
    "gn:admin1_code":"85",
    "gn:admin2_code":"1006",
    "gn:admin3_code":"100636.0",
    "gn:admin4_code":"10063681.0",
    "gn:asciiname":"Matiala",
    "gn:country_code":"BD",
    "gn:dem":5,
    "gn:feature_class":"P",
    "gn:feature_code":"PPL",
    "gn:name":"Matiala",
    "gn:population":0,
    "gn:timezone":"Asia/Dhaka",
    "iso:country":"BD",
    "name:und_x_variant":[
        "M\u0101ti\u0101la"
    ],
    "wof:name":"Matiala",
    "wof:placetype":"locality"
},
  "geometry": {"coordinates":[90.57415,22.9296],"type":"Point"}
}