{
  "type": "Feature",
  "properties": {
    "gn:admin1_code":"82",
    "gn:asciiname":"Dariabad",
    "gn:country_code":"BD",
    "gn:dem":9,
    "gn:feature_class":"P",
    "gn:feature_code":"PPL",
    "gn:name":"Dari\u0101bad",
    "gn:population":0,
    "gn:timezone":"Asia/Dhaka",
    "iso:country":"BD",
    "name:ben_x_preferred":[
        "Dari\u0101bad"
    ],
    "name:zho_x_preferred":[
        "\u591a\u91cc\u963f\u5df4\u5fb7"
    ],
    "wof:name":"Dariabad",
    "wof:placetype":"locality"
},
  "geometry": {"coordinates":[90.3901,22.28235],"type":"Point"}
}