{
  "type": "Feature",
  "properties": {
    "gn:admin1_code":"83",
    "gn:admin2_code":"5081.0",
    "gn:admin3_code":"508110.0",
    "gn:admin4_code":"50811023.0",
    "gn:asciiname":"Dhandao",
    "gn:country_code":"BD",
    "gn:dem":19,
    "gn:feature_class":"P",
    "gn:feature_code":"PPL",
    "gn:name":"Dh\u0101nd\u0101o",
    "gn:population":0,
    "gn:timezone":"Asia/Dhaka",
    "iso:country":"BD",
    "name:ben_x_preferred":[
        "Dh\u0101nd\u0101o"
    ],
    "name:ben_x_variant":[
        "Dhandaha"
    ],
    "wof:name":"Dhandao",
    "wof:placetype":"locality"
},
  "geometry": {"coordinates":[88.88925,24.23203],"type":"Point"}
}