{
  "type": "Feature",
  "properties": {
    "gn:admin1_code":"84",
    "gn:admin2_code":"2013",
    "gn:admin3_code":"201379.0",
    "gn:admin4_code":"20137973.0",
    "gn:asciiname":"Lalpur Kalipur",
    "gn:country_code":"BD",
    "gn:dem":8,
    "gn:feature_class":"P",
    "gn:feature_code":"PPL",
    "gn:name":"L\u0101lpur K\u0101lipur",
    "gn:population":0,
    "gn:timezone":"Asia/Dhaka",
    "iso:country":"BD",
    "wof:name":"Lalpur Kalipur",
    "wof:placetype":"locality"
},
  "geometry": {"coordinates":[90.61472000000001,23.47653],"type":"Point"}
}