{
  "type": "Feature",
  "properties": {
    "gn:admin1_code":"81",
    "gn:admin2_code":"3048",
    "gn:admin3_code":"304849.0",
    "gn:admin4_code":"30484934.0",
    "gn:asciiname":"Rayhkola",
    "gn:country_code":"BD",
    "gn:dem":10,
    "gn:feature_class":"P",
    "gn:feature_code":"PPL",
    "gn:name":"R\u0101yhkola",
    "gn:population":0,
    "gn:timezone":"Asia/Dhaka",
    "iso:country":"BD",
    "name:und_x_variant":[
        "R\u0101yhkola",
        "R\u0101ykala"
    ],
    "wof:name":"Rayhkola",
    "wof:placetype":"locality"
},
  "geometry": {"coordinates":[90.84065,24.36012],"type":"Point"}
}