{
  "type": "Feature",
  "properties": {
    "gn:admin1_code":"84",
    "gn:admin2_code":"2015.0",
    "gn:admin3_code":"201553.0",
    "gn:admin4_code":"20155383.0",
    "gn:asciiname":"Mogadia",
    "gn:country_code":"BD",
    "gn:dem":9,
    "gn:feature_class":"P",
    "gn:feature_code":"PPL",
    "gn:name":"Mogadia",
    "gn:population":0,
    "gn:timezone":"Asia/Dhaka",
    "iso:country":"BD",
    "wof:name":"Mogadia",
    "wof:placetype":"locality"
},
  "geometry": {"coordinates":[91.53306000000001,22.72556],"type":"Point"}
}