{
  "type": "Feature",
  "properties": {
    "gn:admin1_code":"83",
    "gn:admin2_code":"5070.0",
    "gn:admin3_code":"507088.0",
    "gn:admin4_code":"50708811.0",
    "gn:asciiname":"Sibnagar",
    "gn:country_code":"BD",
    "gn:dem":26,
    "gn:feature_class":"P",
    "gn:feature_code":"PPL",
    "gn:name":"Sibnagar",
    "gn:population":0,
    "gn:timezone":"Asia/Dhaka",
    "iso:country":"BD",
    "name:ben_x_preferred":[
        "Sibnagar"
    ],
    "wof:name":"Sibnagar",
    "wof:placetype":"locality"
},
  "geometry": {"coordinates":[88.22435,24.73363],"type":"Point"}
}