{
  "type": "Feature",
  "properties": {
    "gn:admin1_code":"81",
    "gn:admin2_code":"3026",
    "gn:admin3_code":"302614.0",
    "gn:admin4_code":"30261417.0",
    "gn:asciiname":"Rabraban",
    "gn:country_code":"BD",
    "gn:dem":14,
    "gn:feature_class":"P",
    "gn:feature_code":"PPL",
    "gn:name":"R\u0101br\u0101ban",
    "gn:population":0,
    "gn:timezone":"Asia/Dhaka",
    "iso:country":"BD",
    "wof:name":"Rabraban",
    "wof:placetype":"locality"
},
  "geometry": {"coordinates":[90.07151999999998,23.96606],"type":"Point"}
}