{
  "type": "Feature",
  "properties": {
    "gn:admin1_code":"87",
    "gn:admin2_code":"5532",
    "gn:admin3_code":"553282.0",
    "gn:admin4_code":"55328243.0",
    "gn:asciiname":"Krisnapur",
    "gn:country_code":"BD",
    "gn:dem":27,
    "gn:feature_class":"P",
    "gn:feature_code":"PPL",
    "gn:name":"Krisnapur",
    "gn:population":0,
    "gn:timezone":"Asia/Dhaka",
    "iso:country":"BD",
    "name:ben_x_preferred":[
        "Krisnapur"
    ],
    "wof:name":"Krisnapur",
    "wof:placetype":"locality"
},
  "geometry": {"coordinates":[89.38391999999997,25.39979],"type":"Point"}
}