{
  "type": "Feature",
  "properties": {
    "gn:admin1_code":"83",
    "gn:admin2_code":"5081.0",
    "gn:admin3_code":"508182.0",
    "gn:admin4_code":"50818213.0",
    "gn:asciiname":"Baneswar",
    "gn:country_code":"BD",
    "gn:dem":24,
    "gn:feature_class":"P",
    "gn:feature_code":"PPL",
    "gn:name":"B\u0101neswar",
    "gn:population":0,
    "gn:timezone":"Asia/Dhaka",
    "iso:country":"BD",
    "name:ben_x_preferred":[
        "B\u0101neswar"
    ],
    "wof:name":"Baneswar",
    "wof:placetype":"locality"
},
  "geometry": {"coordinates":[88.75655,24.36407],"type":"Point"}
}