{
  "type": "Feature",
  "properties": {
    "gn:admin1_code":"83",
    "gn:admin2_code":"5010",
    "gn:admin3_code":"501054.0",
    "gn:admin4_code":"50105476.0",
    "gn:asciiname":"Narhatta",
    "gn:country_code":"BD",
    "gn:dem":22,
    "gn:feature_class":"P",
    "gn:feature_code":"PPL",
    "gn:name":"N\u0101rhatta",
    "gn:population":0,
    "gn:timezone":"Asia/Dhaka",
    "iso:country":"BD",
    "wof:name":"Narhatta",
    "wof:placetype":"locality"
},
  "geometry": {"coordinates":[89.25877,24.86601],"type":"Point"}
}