{
  "type": "Feature",
  "properties": {
    "gn:admin1_code":"84",
    "gn:admin2_code":"2019.0",
    "gn:admin3_code":"201954.0",
    "gn:admin4_code":"20195476.0",
    "gn:asciiname":"Bijoynagar",
    "gn:country_code":"BD",
    "gn:dem":9,
    "gn:feature_class":"P",
    "gn:feature_code":"PPL",
    "gn:name":"Bijoynagar",
    "gn:population":0,
    "gn:timezone":"Asia/Dhaka",
    "iso:country":"BD",
    "name:und_x_variant":[
        "Bejoynagar",
        "Bijoynagar"
    ],
    "wof:name":"Bijoynagar",
    "wof:placetype":"locality"
},
  "geometry": {"coordinates":[90.77323,23.65695],"type":"Point"}
}