{
  "type": "Feature",
  "properties": {
    "gn:admin1_code":"83",
    "gn:admin2_code":"5064",
    "gn:admin3_code":"506447.0",
    "gn:admin4_code":"50644740.0",
    "gn:asciiname":"Nij Kulihar",
    "gn:country_code":"BD",
    "gn:dem":19,
    "gn:feature_class":"P",
    "gn:feature_code":"PPL",
    "gn:name":"Nij Kulih\u0101r",
    "gn:population":0,
    "gn:timezone":"Asia/Dhaka",
    "iso:country":"BD",
    "name:ben_x_preferred":[
        "Nij Kulih\u0101r"
    ],
    "name:und_x_variant":[
        "Nijkutipara"
    ],
    "wof:name":"Nij Kulihar",
    "wof:placetype":"locality"
},
  "geometry": {"coordinates":[88.78534000000001,24.76869],"type":"Point"}
}