{
  "type": "Feature",
  "properties": {
    "gn:admin1_code":"83",
    "gn:admin2_code":"5081.0",
    "gn:admin3_code":"508134.0",
    "gn:admin4_code":"50813485.0",
    "gn:asciiname":"Bilasi",
    "gn:country_code":"BD",
    "gn:dem":26,
    "gn:feature_class":"P",
    "gn:feature_code":"PPL",
    "gn:name":"B\u012bl\u0101si",
    "gn:population":0,
    "gn:timezone":"Asia/Dhaka",
    "iso:country":"BD",
    "name:ben_x_preferred":[
        "B\u012bl\u0101si"
    ],
    "wof:name":"Bilasi",
    "wof:placetype":"locality"
},
  "geometry": {"coordinates":[88.50695999999998,24.5367],"type":"Point"}
}