{
  "type": "Feature",
  "properties": {
    "gn:admin1_code":"87",
    "gn:admin2_code":"5577.0",
    "gn:admin3_code":"557773.0",
    "gn:admin4_code":"55777359.0",
    "gn:asciiname":"Kharuagram",
    "gn:country_code":"BD",
    "gn:dem":70,
    "gn:feature_class":"P",
    "gn:feature_code":"PPL",
    "gn:name":"Kharuagr\u0101m",
    "gn:population":0,
    "gn:timezone":"Asia/Dhaka",
    "iso:country":"BD",
    "name:ben_x_preferred":[
        "Kharuagr\u0101m"
    ],
    "wof:name":"Kharuagram",
    "wof:placetype":"locality"
},
  "geometry": {"coordinates":[88.61865999999998,26.31241],"type":"Point"}
}