{
  "type": "Feature",
  "properties": {
    "gn:admin1_code":"82",
    "gn:admin2_code":"4041",
    "gn:admin3_code":"404111.0",
    "gn:admin4_code":"40411117.0",
    "gn:asciiname":"Kabilpur",
    "gn:country_code":"BD",
    "gn:dem":16,
    "gn:feature_class":"P",
    "gn:feature_code":"PPL",
    "gn:name":"K\u0101bilpur",
    "gn:population":0,
    "gn:timezone":"Asia/Dhaka",
    "iso:country":"BD",
    "name:ben_x_preferred":[
        "K\u0101bilpur"
    ],
    "wof:name":"Kabilpur",
    "wof:placetype":"locality"
},
  "geometry": {"coordinates":[89.01093,23.21257],"type":"Point"}
}