{
  "type": "Feature",
  "properties": {
    "gn:admin1_code":"81",
    "gn:admin2_code":"3048.0",
    "gn:admin3_code":"304827.0",
    "gn:admin4_code":"30482781.0",
    "gn:asciiname":"Char Biswanathpur",
    "gn:country_code":"BD",
    "gn:dem":14,
    "gn:feature_class":"P",
    "gn:feature_code":"PPL",
    "gn:name":"Char Biswan\u0101thpur",
    "gn:population":0,
    "gn:timezone":"Asia/Dhaka",
    "iso:country":"BD",
    "wof:name":"Char Biswanathpur",
    "wof:placetype":"locality"
},
  "geometry": {"coordinates":[90.64831,24.41824],"type":"Point"}
}