{
  "type": "Feature",
  "properties": {
    "gn:admin1_code":"82",
    "gn:admin2_code":"4044.0",
    "gn:admin3_code":"404414.0",
    "gn:admin4_code":"40441431.0",
    "gn:asciiname":"Fatehpur",
    "gn:country_code":"BD",
    "gn:dem":19,
    "gn:feature_class":"P",
    "gn:feature_code":"PPL",
    "gn:name":"Fatehpur",
    "gn:population":0,
    "gn:timezone":"Asia/Dhaka",
    "iso:country":"BD",
    "name:ben_x_preferred":[
        "\u09ab\u09a4\u09c7\u09aa\u09c1\u09b0"
    ],
    "name:ben_x_variant":[
        "\u09ab\u09a4\u09c7\u09b9\u09aa\u09c1\u09b0",
        "Fatehpur"
    ],
    "name:bih_x_preferred":[
        "\u092b\u0924\u0947\u0939\u092a\u0941\u0930"
    ],
    "name:ceb_x_preferred":[
        "Fatehpur"
    ],
    "name:deu_x_preferred":[
        "Fatehpur"
    ],
    "name:ell_x_preferred":[
        "\u03a6\u03b1\u03c4\u03b5\u03c7\u03c0\u03bf\u03cd\u03c1"
    ],
    "name:fas_x_preferred":[
        "\u0641\u0627\u062a\u062d \u067e\u0648\u0631"
    ],
    "name:heb_x_preferred":[
        "\u05e4\u05d8\u05e4\u05d5\u05e8"
    ],
    "name:hun_x_preferred":[
        "Fatehpur"
    ],
    "name:ind_x_preferred":[
        "Fatehpur"
    ],
    "name:kor_x_preferred":[
        "\ud30c\ud14c\ud478\ub974"
    ],
    "name:new_x_preferred":[
        "\u092b\u0924\u0947\u0939\u092a\u0941\u0930"
    ],
    "name:nld_x_preferred":[
        "Fatehpur"
    ],
    "name:pnb_x_preferred":[
        "\u0641\u062a\u062d \u067e\u0648\u0631"
    ],
    "name:pol_x_preferred":[
        "Fatehpur"
    ],
    "name:spa_x_preferred":[
        "Fatehpur"
    ],
    "name:swe_x_preferred":[
        "Fatehpur"
    ],
    "name:tur_x_preferred":[
        "Fatehpur"
    ],
    "name:ukr_x_preferred":[
        "\u0424\u0430\u0442\u0435\u0445\u043f\u0443\u0440"
    ],
    "name:vie_x_preferred":[
        "Fatehpur"
    ],
    "name:zho_cn_x_preferred":[
        "\u6cd5\u5854\u8d6b\u5e03\u5c14"
    ],
    "name:zho_tw_x_preferred":[
        "\u6cd5\u6cf0\u8d6b\u666e\u723e"
    ],
    "wof:name":"Fatehpur",
    "wof:placetype":"locality"
},
  "geometry": {"coordinates":[89.01711,23.64979],"type":"Point"}
}