{
  "type": "Feature",
  "properties": {
    "gn:admin1_code":"87",
    "gn:admin2_code":"5573",
    "gn:admin3_code":"557345.0",
    "gn:admin4_code":"55734543.0",
    "gn:asciiname":"Ganesh",
    "gn:country_code":"BD",
    "gn:dem":46,
    "gn:feature_class":"P",
    "gn:feature_code":"PPL",
    "gn:name":"Ganesh",
    "gn:population":0,
    "gn:timezone":"Asia/Dhaka",
    "iso:country":"BD",
    "name:ben_x_preferred":[
        "Ganesh"
    ],
    "wof:name":"Ganesh",
    "wof:placetype":"locality"
},
  "geometry": {"coordinates":[89.087,25.9198],"type":"Point"}
}