{
  "type": "Feature",
  "properties": {
    "gn:admin1_code":"83",
    "gn:admin2_code":"5010.0",
    "gn:admin3_code":"501020.0",
    "gn:admin4_code":"50102064.0",
    "gn:asciiname":"Chak Brindaban",
    "gn:country_code":"BD",
    "gn:dem":26,
    "gn:feature_class":"P",
    "gn:feature_code":"PPL",
    "gn:name":"Chak Brind\u0101ban",
    "gn:population":0,
    "gn:timezone":"Asia/Dhaka",
    "iso:country":"BD",
    "wof:name":"Chak Brindaban",
    "wof:placetype":"locality"
},
  "geometry": {"coordinates":[89.36043000000002,24.84765],"type":"Point"}
}