{
  "type": "Feature",
  "properties": {
    "gn:admin1_code":"87",
    "gn:admin2_code":"5585",
    "gn:admin3_code":"558503.0",
    "gn:admin4_code":"55850325.0",
    "gn:asciiname":"Mustafapur",
    "gn:country_code":"BD",
    "gn:dem":38,
    "gn:feature_class":"P",
    "gn:feature_code":"PPL",
    "gn:name":"Mustafapur",
    "gn:population":0,
    "gn:timezone":"Asia/Dhaka",
    "iso:country":"BD",
    "name:ben_x_preferred":[
        "Mustafapur"
    ],
    "wof:name":"Mustafapur",
    "wof:placetype":"locality"
},
  "geometry": {"coordinates":[89.04169,25.69373],"type":"Point"}
}