{
  "type": "Feature",
  "properties": {
    "gn:admin1_code":"81",
    "gn:admin2_code":"3048",
    "gn:admin3_code":"304827.0",
    "gn:admin4_code":"30482740.0",
    "gn:asciiname":"Hogla Kandi",
    "gn:country_code":"BD",
    "gn:dem":16,
    "gn:feature_class":"P",
    "gn:feature_code":"PPL",
    "gn:name":"Hogla K\u0101ndi",
    "gn:population":0,
    "gn:timezone":"Asia/Dhaka",
    "iso:country":"BD",
    "wof:name":"Hogla Kandi",
    "wof:placetype":"locality"
},
  "geometry": {"coordinates":[90.61681,24.46034],"type":"Point"}
}