{
  "type": "Feature",
  "properties": {
    "gn:admin1_code":"84",
    "gn:admin2_code":"2012.0",
    "gn:admin3_code":"201213.0",
    "gn:admin4_code":"20121356.0",
    "gn:asciiname":"Harashpur",
    "gn:country_code":"BD",
    "gn:dem":18,
    "gn:feature_class":"P",
    "gn:feature_code":"PPL",
    "gn:name":"Harashpur",
    "gn:population":0,
    "gn:timezone":"Asia/Dhaka",
    "iso:country":"BD",
    "name:und_x_variant":[
        "Haraspur",
        "Harashpur"
    ],
    "wof:name":"Harashpur",
    "wof:placetype":"locality"
},
  "geometry": {"coordinates":[91.29338,24.01724],"type":"Point"}
}