{
  "type": "Feature",
  "properties": {
    "gn:admin1_code":"83",
    "gn:admin2_code":"5076.0",
    "gn:admin3_code":"507616.0",
    "gn:admin4_code":"50761673.0",
    "gn:asciiname":"Deonai",
    "gn:country_code":"BD",
    "gn:dem":10,
    "gn:feature_class":"P",
    "gn:feature_code":"PPL",
    "gn:name":"Deonai",
    "gn:population":0,
    "gn:timezone":"Asia/Dhaka",
    "iso:country":"BD",
    "wof:name":"Deonai",
    "wof:placetype":"locality"
},
  "geometry": {"coordinates":[89.66667,23.93333],"type":"Point"}
}