{
  "type": "Feature",
  "properties": {
    "gn:admin1_code":"81",
    "gn:admin2_code":"3029.0",
    "gn:admin3_code":"302918.0",
    "gn:admin4_code":"30291835.0",
    "gn:asciiname":"Gangi",
    "gn:country_code":"BD",
    "gn:dem":8,
    "gn:feature_class":"P",
    "gn:feature_code":"PPL",
    "gn:name":"G\u0101ngi",
    "gn:population":0,
    "gn:timezone":"Asia/Dhaka",
    "iso:country":"BD",
    "wof:name":"Gangi",
    "wof:placetype":"locality"
},
  "geometry": {"coordinates":[89.62300999999999,23.46186],"type":"Point"}
}