{
  "type": "Feature",
  "properties": {
    "gn:admin1_code":"81",
    "gn:admin2_code":"3059.0",
    "gn:admin3_code":"305956.0",
    "gn:admin4_code":"30595628.0",
    "gn:asciiname":"Char Dumaria",
    "gn:cc2":"BD",
    "gn:country_code":"BD",
    "gn:dem":7,
    "gn:feature_class":"P",
    "gn:feature_code":"PPL",
    "gn:name":"Char Dumaria",
    "gn:population":0,
    "gn:timezone":"Asia/Dhaka",
    "iso:country":"BD",
    "name:und_x_variant":[
        "Char Dumria",
        "Char Dumaria"
    ],
    "wof:name":"Char Dumaria",
    "wof:placetype":"locality"
},
  "geometry": {"coordinates":[90.53333000000001,23.48333],"type":"Point"}
}