{
  "type": "Feature",
  "properties": {
    "gn:admin1_code":"84",
    "gn:admin2_code":"2013",
    "gn:admin3_code":"201395.0",
    "gn:admin4_code":"20139520.0",
    "gn:asciiname":"Koar",
    "gn:country_code":"BD",
    "gn:dem":11,
    "gn:feature_class":"P",
    "gn:feature_code":"PPL",
    "gn:name":"Ko\u0101r",
    "gn:population":0,
    "gn:timezone":"Asia/Dhaka",
    "iso:country":"BD",
    "wof:name":"Koar",
    "wof:placetype":"locality"
},
  "geometry": {"coordinates":[90.97084,23.17028],"type":"Point"}
}