{
  "type": "Feature",
  "properties": {
    "gn:admin1_code":"82",
    "gn:admin2_code":"4001.0",
    "gn:admin3_code":"400160.0",
    "gn:admin4_code":"40016071.0",
    "gn:asciiname":"Tetulbaria",
    "gn:country_code":"BD",
    "gn:dem":8,
    "gn:feature_class":"P",
    "gn:feature_code":"PPL",
    "gn:name":"Tetulbaria",
    "gn:population":0,
    "gn:timezone":"Asia/Dhaka",
    "iso:country":"BD",
    "name:ben_x_preferred":[
        "Tetulbaria"
    ],
    "wof:name":"Tetulbaria",
    "wof:placetype":"locality"
},
  "geometry": {"coordinates":[89.81444,22.43665],"type":"Point"}
}