{
  "type": "Feature",
  "properties": {
    "gn:admin1_code":"84",
    "gn:admin2_code":"2019.0",
    "gn:admin3_code":"201981.0",
    "gn:admin4_code":"20198181.0",
    "gn:asciiname":"Dhair",
    "gn:country_code":"BD",
    "gn:dem":9,
    "gn:feature_class":"P",
    "gn:feature_code":"PPL",
    "gn:name":"Dh\u0101ir",
    "gn:population":0,
    "gn:timezone":"Asia/Dhaka",
    "iso:country":"BD",
    "name:und_x_variant":[
        "East-Dhair",
        "Fast-Dhair",
        "Dh\u0101ir"
    ],
    "wof:name":"Dhair",
    "wof:placetype":"locality"
},
  "geometry": {"coordinates":[91.00354,23.7098],"type":"Point"}
}