{
  "type": "Feature",
  "properties": {
    "gn:admin1_code":"87",
    "gn:admin2_code":"5585.0",
    "gn:admin3_code":"558573.0",
    "gn:admin4_code":"55857347.0",
    "gn:asciiname":"Taiyab",
    "gn:country_code":"BD",
    "gn:dem":35,
    "gn:feature_class":"P",
    "gn:feature_code":"PPL",
    "gn:name":"Taiyab",
    "gn:population":0,
    "gn:timezone":"Asia/Dhaka",
    "iso:country":"BD",
    "name:ben_x_preferred":[
        "Taiyab"
    ],
    "wof:name":"Taiyab",
    "wof:placetype":"locality"
},
  "geometry": {"coordinates":[89.3188,25.70101],"type":"Point"}
}