{
  "type": "Feature",
  "properties": {
    "gn:admin1_code":"85",
    "gn:admin2_code":"1006",
    "gn:admin3_code":"100636.0",
    "gn:admin4_code":"10063654.0",
    "gn:asciiname":"Raghadia",
    "gn:country_code":"BD",
    "gn:dem":5,
    "gn:feature_class":"P",
    "gn:feature_code":"PPL",
    "gn:name":"R\u0101ghadia",
    "gn:population":0,
    "gn:timezone":"Asia/Dhaka",
    "iso:country":"BD",
    "wof:name":"Raghadia",
    "wof:placetype":"locality"
},
  "geometry": {"coordinates":[90.48363999999999,22.92138],"type":"Point"}
}