{
  "type": "Feature",
  "properties": {
    "gn:admin1_code":"82",
    "gn:admin2_code":"4050",
    "gn:admin3_code":"405063.0",
    "gn:admin4_code":"40506371.0",
    "gn:asciiname":"Kismat Phulbari",
    "gn:country_code":"BD",
    "gn:dem":14,
    "gn:feature_class":"P",
    "gn:feature_code":"PPL",
    "gn:name":"Kismat Phulb\u0101ri",
    "gn:population":0,
    "gn:timezone":"Asia/Dhaka",
    "iso:country":"BD",
    "name:und_x_variant":[
        "Kishmat Fulbari",
        "Kismat Phulb\u0101ri"
    ],
    "wof:name":"Kismat Phulbari",
    "wof:placetype":"locality"
},
  "geometry": {"coordinates":[89.34491,23.84261],"type":"Point"}
}