{
  "type": "Feature",
  "properties": {
    "gn:admin1_code":"83",
    "gn:admin2_code":"5081.0",
    "gn:admin3_code":"508125.0",
    "gn:admin4_code":"50812547.0",
    "gn:asciiname":"Kanpail Khati",
    "gn:country_code":"BD",
    "gn:dem":23,
    "gn:feature_class":"P",
    "gn:feature_code":"PPL",
    "gn:name":"Kanpail Khati",
    "gn:population":0,
    "gn:timezone":"Asia/Dhaka",
    "iso:country":"BD",
    "name:ben_x_preferred":[
        "Kanpail Khati"
    ],
    "wof:name":"Kanpail Khati",
    "wof:placetype":"locality"
},
  "geometry": {"coordinates":[88.67995999999999,24.35011],"type":"Point"}
}