{
  "type": "Feature",
  "properties": {
    "gn:admin1_code":"87",
    "gn:admin2_code":"5585.0",
    "gn:admin3_code":"558558.0",
    "gn:admin4_code":"55855816.0",
    "gn:asciiname":"Chithali Madhyapara",
    "gn:country_code":"BD",
    "gn:dem":29,
    "gn:feature_class":"P",
    "gn:feature_code":"PPL",
    "gn:name":"Chithali Madhyap\u0101ra",
    "gn:population":0,
    "gn:timezone":"Asia/Dhaka",
    "iso:country":"BD",
    "name:und_x_variant":[
        "Chetholee Modhopara",
        "Chithali Madhyap\u0101ra"
    ],
    "wof:name":"Chithali Madhyapara",
    "wof:placetype":"locality"
},
  "geometry": {"coordinates":[89.29557,25.57508],"type":"Point"}
}