{
  "type": "Feature",
  "properties": {
    "gn:admin1_code":"81",
    "gn:admin2_code":"3056",
    "gn:admin3_code":"305682.0",
    "gn:admin4_code":"30568260.0",
    "gn:asciiname":"Swalpa Jailla",
    "gn:country_code":"BD",
    "gn:dem":9,
    "gn:feature_class":"P",
    "gn:feature_code":"PPL",
    "gn:name":"Swalpa J\u0101illa",
    "gn:population":0,
    "gn:timezone":"Asia/Dhaka",
    "iso:country":"BD",
    "wof:name":"Swalpa Jailla",
    "wof:placetype":"locality"
},
  "geometry": {"coordinates":[90.22161,23.79602],"type":"Point"}
}