{
  "type": "Feature",
  "properties": {
    "gn:admin1_code":"81",
    "gn:admin2_code":"3029",
    "gn:admin3_code":"302903.0",
    "gn:admin4_code":"30290352.0",
    "gn:asciiname":"Panchuria",
    "gn:country_code":"BD",
    "gn:dem":16,
    "gn:feature_class":"P",
    "gn:feature_code":"PPL",
    "gn:name":"P\u0101nchuria",
    "gn:population":0,
    "gn:timezone":"Asia/Dhaka",
    "iso:country":"BD",
    "wof:name":"Panchuria",
    "wof:placetype":"locality"
},
  "geometry": {"coordinates":[89.61501,23.35914],"type":"Point"}
}