{
  "type": "Feature",
  "properties": {
    "gn:admin1_code":"83",
    "gn:admin2_code":"5081.0",
    "gn:admin3_code":"508112.0",
    "gn:admin4_code":"50811263.0",
    "gn:asciiname":"Naran Bari",
    "gn:country_code":"BD",
    "gn:dem":18,
    "gn:feature_class":"P",
    "gn:feature_code":"PPL",
    "gn:name":"Naran B\u0101ri",
    "gn:population":0,
    "gn:timezone":"Asia/Dhaka",
    "iso:country":"BD",
    "name:ben_x_preferred":[
        "Naran B\u0101ri"
    ],
    "wof:name":"Naran Bari",
    "wof:placetype":"locality"
},
  "geometry": {"coordinates":[88.90668000000002,24.64054],"type":"Point"}
}