{
  "type": "Feature",
  "properties": {
    "gn:admin1_code":"81",
    "gn:admin2_code":"3035.0",
    "gn:admin3_code":"303543.0",
    "gn:admin4_code":"30354313.0",
    "gn:asciiname":"Saphalidanga",
    "gn:country_code":"BD",
    "gn:dem":8,
    "gn:feature_class":"P",
    "gn:feature_code":"PPL",
    "gn:name":"Saphalid\u0101nga",
    "gn:population":0,
    "gn:timezone":"Asia/Dhaka",
    "iso:country":"BD",
    "name:ben_x_preferred":[
        "Saphalid\u0101nga"
    ],
    "wof:name":"Saphalidanga",
    "wof:placetype":"locality"
},
  "geometry": {"coordinates":[89.80735,23.17155],"type":"Point"}
}