{
  "type": "Feature",
  "properties": {
    "gn:admin1_code":"83",
    "gn:admin2_code":"5064.0",
    "gn:admin3_code":"506486.0",
    "gn:admin4_code":"50648663.0",
    "gn:asciiname":"Jaydebpur",
    "gn:country_code":"BD",
    "gn:dem":30,
    "gn:feature_class":"P",
    "gn:feature_code":"PPL",
    "gn:name":"Jaydebpur",
    "gn:population":0,
    "gn:timezone":"Asia/Dhaka",
    "iso:country":"BD",
    "name:ben_x_preferred":[
        "Jaydebpur"
    ],
    "wof:name":"Jaydebpur",
    "wof:placetype":"locality"
},
  "geometry": {"coordinates":[88.49422,25.14435],"type":"Point"}
}