{
  "type": "Feature",
  "properties": {
    "gn:admin1_code":"82",
    "gn:admin2_code":"4055.0",
    "gn:admin3_code":"405557.0",
    "gn:admin4_code":"40555794.0",
    "gn:asciiname":"Sinhadanga",
    "gn:country_code":"BD",
    "gn:dem":11,
    "gn:feature_class":"P",
    "gn:feature_code":"PPL",
    "gn:name":"Sinhadanga",
    "gn:population":0,
    "gn:timezone":"Asia/Dhaka",
    "iso:country":"BD",
    "name:ben_x_preferred":[
        "Sinhadanga"
    ],
    "wof:name":"Sinhadanga",
    "wof:placetype":"locality"
},
  "geometry": {"coordinates":[89.45752,23.39946],"type":"Point"}
}