{
  "type": "Feature",
  "properties": {
    "gn:admin1_code":"82",
    "gn:admin2_code":"4041.0",
    "gn:admin3_code":"404111.0",
    "gn:admin4_code":"40411194.0",
    "gn:asciiname":"Ballabhpur",
    "gn:country_code":"BD",
    "gn:dem":13,
    "gn:feature_class":"P",
    "gn:feature_code":"PPL",
    "gn:name":"Ballabhpur",
    "gn:population":0,
    "gn:timezone":"Asia/Dhaka",
    "iso:country":"BD",
    "name:ben_x_preferred":[
        "Ballabhpur"
    ],
    "wof:name":"Ballabhpur",
    "wof:placetype":"locality"
},
  "geometry": {"coordinates":[88.94153,23.23143],"type":"Point"}
}