{
  "type": "Feature",
  "properties": {
    "gn:admin1_code":"82",
    "gn:admin2_code":"4047.0",
    "gn:admin3_code":"404712.0",
    "gn:admin4_code":"40471283.0",
    "gn:asciiname":"Gajalia",
    "gn:country_code":"BD",
    "gn:dem":7,
    "gn:feature_class":"P",
    "gn:feature_code":"PPL",
    "gn:name":"Gaj\u0101lia",
    "gn:population":0,
    "gn:timezone":"Asia/Dhaka",
    "iso:country":"BD",
    "wof:name":"Gajalia",
    "wof:placetype":"locality"
},
  "geometry": {"coordinates":[89.46584,22.70323],"type":"Point"}
}