{
  "type": "Feature",
  "properties": {
    "gn:admin1_code":"83",
    "gn:admin2_code":"5064.0",
    "gn:admin3_code":"506469.0",
    "gn:admin4_code":"50646921.0",
    "gn:asciiname":"Chapra",
    "gn:country_code":"BD",
    "gn:dem":25,
    "gn:feature_class":"P",
    "gn:feature_code":"PPL",
    "gn:name":"Chapra",
    "gn:population":0,
    "gn:timezone":"Asia/Dhaka",
    "iso:country":"BD",
    "name:ben_x_preferred":[
        "Chapra"
    ],
    "wof:name":"Chapra",
    "wof:placetype":"locality"
},
  "geometry": {"coordinates":[88.61454999999999,24.84939],"type":"Point"}
}