{
  "type": "Feature",
  "properties": {
    "gn:admin1_code":"83",
    "gn:admin2_code":"5070",
    "gn:admin3_code":"507066.0",
    "gn:admin4_code":"50706600.0",
    "gn:asciiname":"Huzrapur",
    "gn:country_code":"BD",
    "gn:dem":28,
    "gn:feature_class":"P",
    "gn:feature_code":"PPL",
    "gn:name":"Huzr\u0101pur",
    "gn:population":0,
    "gn:timezone":"Asia/Dhaka",
    "iso:country":"BD",
    "name:ben_x_preferred":[
        "Huzr\u0101pur"
    ],
    "wof:name":"Huzrapur",
    "wof:placetype":"locality"
},
  "geometry": {"coordinates":[88.28209,24.60191],"type":"Point"}
}