{
  "type": "Feature",
  "properties": {
    "gn:admin1_code":"83",
    "gn:admin2_code":"5076",
    "gn:admin3_code":"507683.0",
    "gn:admin4_code":"50768385.0",
    "gn:asciiname":"Mojaitpur",
    "gn:country_code":"BD",
    "gn:dem":16,
    "gn:feature_class":"P",
    "gn:feature_code":"PPL",
    "gn:name":"Mojaitpur",
    "gn:population":0,
    "gn:timezone":"Asia/Dhaka",
    "iso:country":"BD",
    "wof:name":"Mojaitpur",
    "wof:placetype":"locality"
},
  "geometry": {"coordinates":[89.42945999999998,23.90934],"type":"Point"}
}