{
  "type": "Feature",
  "properties": {
    "gn:admin1_code":"81",
    "gn:admin2_code":"3026.0",
    "gn:admin3_code":"302662.0",
    "gn:admin4_code":"30266261.0",
    "gn:asciiname":"Bataimuri",
    "gn:country_code":"BD",
    "gn:dem":10,
    "gn:feature_class":"P",
    "gn:feature_code":"PPL",
    "gn:name":"B\u0101taimuri",
    "gn:population":0,
    "gn:timezone":"Asia/Dhaka",
    "iso:country":"BD",
    "wof:name":"Bataimuri",
    "wof:placetype":"locality"
},
  "geometry": {"coordinates":[90.03278,23.6654],"type":"Point"}
}