{
  "type": "Feature",
  "properties": {
    "gn:admin1_code":"82",
    "gn:admin2_code":"4087.0",
    "gn:admin3_code":"408786.0",
    "gn:admin4_code":"40878647.0",
    "gn:asciiname":"Shail Khali",
    "gn:country_code":"BD",
    "gn:dem":4,
    "gn:feature_class":"P",
    "gn:feature_code":"PPL",
    "gn:name":"Shail Kh\u0101li",
    "gn:population":0,
    "gn:timezone":"Asia/Dhaka",
    "iso:country":"BD",
    "name:ben_x_preferred":[
        "Shail Kh\u0101li"
    ],
    "wof:name":"Shail Khali",
    "wof:placetype":"locality"
},
  "geometry": {"coordinates":[89.0488,22.24773],"type":"Point"}
}