{
  "type": "Feature",
  "properties": {
    "gn:admin1_code":"84",
    "gn:admin2_code":"2030",
    "gn:admin3_code":"203029.0",
    "gn:admin4_code":"20302986.0",
    "gn:asciiname":"South Khanebari",
    "gn:country_code":"BD",
    "gn:dem":8,
    "gn:feature_class":"P",
    "gn:feature_code":"PPL",
    "gn:name":"South Kh\u0101neb\u0101ri",
    "gn:population":0,
    "gn:timezone":"Asia/Dhaka",
    "iso:country":"BD",
    "wof:name":"South Khanebari",
    "wof:placetype":"locality"
},
  "geometry": {"coordinates":[91.31667,23.05],"type":"Point"}
}