{
  "type": "Feature",
  "properties": {
    "gn:admin1_code":"81",
    "gn:admin2_code":"3056.0",
    "gn:admin3_code":"305610.0",
    "gn:admin4_code":"30561076.0",
    "gn:asciiname":"Baorabari",
    "gn:country_code":"BD",
    "gn:dem":9,
    "gn:feature_class":"P",
    "gn:feature_code":"PPL",
    "gn:name":"Baor\u0101b\u0101ri",
    "gn:population":0,
    "gn:timezone":"Asia/Dhaka",
    "iso:country":"BD",
    "wof:name":"Baorabari",
    "wof:placetype":"locality"
},
  "geometry": {"coordinates":[89.88333,23.95],"type":"Point"}
}