{
  "type": "Feature",
  "properties": {
    "gn:admin1_code":"82",
    "gn:admin2_code":"4047.0",
    "gn:admin3_code":"404769.0",
    "gn:admin4_code":"40476976.0",
    "gn:asciiname":"Uttardihi",
    "gn:country_code":"BD",
    "gn:dem":13,
    "gn:feature_class":"P",
    "gn:feature_code":"PPL",
    "gn:name":"Uttardihi",
    "gn:population":0,
    "gn:timezone":"Asia/Dhaka",
    "iso:country":"BD",
    "name:ben_x_preferred":[
        "Uttardihi"
    ],
    "wof:name":"Uttardihi",
    "wof:placetype":"locality"
},
  "geometry": {"coordinates":[89.43845,23.00606],"type":"Point"}
}