{
  "type": "Feature",
  "properties": {
    "gn:admin1_code":"82",
    "gn:admin2_code":"4018.0",
    "gn:admin3_code":"401823.0",
    "gn:admin4_code":"40182300.0",
    "gn:asciiname":"Belgachi",
    "gn:country_code":"BD",
    "gn:dem":17,
    "gn:feature_class":"P",
    "gn:feature_code":"PPL",
    "gn:name":"Belgachi",
    "gn:population":0,
    "gn:timezone":"Asia/Dhaka",
    "iso:country":"BD",
    "name:ben_x_preferred":[
        "Belgachi"
    ],
    "wof:name":"Belgachi",
    "wof:placetype":"locality"
},
  "geometry": {"coordinates":[88.848,23.62697],"type":"Point"}
}