{
  "type": "Feature",
  "properties": {
    "gn:admin1_code":"82",
    "gn:admin2_code":"4055",
    "gn:admin3_code":"405595.0",
    "gn:admin4_code":"40559510.0",
    "gn:asciiname":"Purba Rajapur",
    "gn:cc2":"BD",
    "gn:country_code":"BD",
    "gn:dem":9,
    "gn:feature_class":"P",
    "gn:feature_code":"PPL",
    "gn:name":"Purba R\u0101j\u0101pur",
    "gn:population":0,
    "gn:timezone":"Asia/Dhaka",
    "iso:country":"BD",
    "name:und_x_variant":[
        "Purba Rajapur Village",
        "Purba R\u0101j\u0101pur"
    ],
    "wof:name":"Purba Rajapur",
    "wof:placetype":"locality"
},
  "geometry": {"coordinates":[89.41667,23.63333],"type":"Point"}
}