{
  "type": "Feature",
  "properties": {
    "gn:admin1_code":"81",
    "gn:admin2_code":"3026.0",
    "gn:admin3_code":"302640.0",
    "gn:admin4_code":"30264048.0",
    "gn:asciiname":"Baraikhali",
    "gn:country_code":"BD",
    "gn:dem":10,
    "gn:feature_class":"P",
    "gn:feature_code":"PPL",
    "gn:name":"B\u0101raikh\u0101li",
    "gn:population":0,
    "gn:timezone":"Asia/Dhaka",
    "iso:country":"BD",
    "wof:name":"Baraikhali",
    "wof:placetype":"locality"
},
  "geometry": {"coordinates":[90.35957000000001,23.74056],"type":"Point"}
}