{
  "type": "Feature",
  "properties": {
    "gn:admin1_code":"83",
    "gn:admin2_code":"5010",
    "gn:admin3_code":"501033.0",
    "gn:admin4_code":"50103327.0",
    "gn:asciiname":"Kamargaon",
    "gn:country_code":"BD",
    "gn:dem":23,
    "gn:feature_class":"P",
    "gn:feature_code":"PPL",
    "gn:name":"K\u0101m\u0101rgaon",
    "gn:population":0,
    "gn:timezone":"Asia/Dhaka",
    "iso:country":"BD",
    "name:ceb_x_preferred":[
        "Kamargaon"
    ],
    "name:swe_x_preferred":[
        "Kamargaon"
    ],
    "wof:name":"Kamargaon",
    "wof:placetype":"locality"
},
  "geometry": {"coordinates":[89.15236,24.86861],"type":"Point"}
}