{
  "type": "Feature",
  "properties": {
    "gn:admin1_code":"84",
    "gn:admin2_code":"2046.0",
    "gn:admin3_code":"204665.0",
    "gn:admin4_code":"20466547.0",
    "gn:asciiname":"Manchandrapara",
    "gn:country_code":"BD",
    "gn:dem":50,
    "gn:feature_class":"P",
    "gn:feature_code":"PPL",
    "gn:name":"Manchandr\u0101p\u0101ra",
    "gn:population":0,
    "gn:timezone":"Asia/Dhaka",
    "iso:country":"BD",
    "name:ben_x_preferred":[
        "Manchandr\u0101p\u0101ra"
    ],
    "wof:name":"Manchandrapara",
    "wof:placetype":"locality"
},
  "geometry": {"coordinates":[91.98936999999999,22.98762],"type":"Point"}
}