{
  "type": "Feature",
  "properties": {
    "gn:admin1_code":"81",
    "gn:admin2_code":"3082.0",
    "gn:admin3_code":"308276.0",
    "gn:admin4_code":"30827600.0",
    "gn:asciiname":"Bhabanipur",
    "gn:country_code":"BD",
    "gn:dem":12,
    "gn:feature_class":"P",
    "gn:feature_code":"PPL",
    "gn:name":"Bhab\u0101nipur",
    "gn:population":0,
    "gn:timezone":"Asia/Dhaka",
    "iso:country":"BD",
    "name:ben_x_preferred":[
        "Bhab\u0101nipur"
    ],
    "name:ben_x_variant":[
        "\u09ad\u09ac\u09be\u09a8\u09c0\u09aa\u09c1\u09b0"
    ],
    "wof:name":"Bhabanipur",
    "wof:placetype":"locality"
},
  "geometry": {"coordinates":[89.63136,23.75835],"type":"Point"}
}