{
  "type": "Feature",
  "properties": {
    "gn:admin1_code":"83",
    "gn:admin2_code":"5069.0",
    "gn:admin3_code":"506909.0",
    "gn:admin4_code":"50690976.0",
    "gn:asciiname":"Munshipara",
    "gn:country_code":"BD",
    "gn:dem":19,
    "gn:feature_class":"P",
    "gn:feature_code":"PPL",
    "gn:name":"Munship\u0101ra",
    "gn:population":0,
    "gn:timezone":"Asia/Dhaka",
    "iso:country":"BD",
    "name:ben_x_preferred":[
        "Munship\u0101ra"
    ],
    "wof:name":"Munshipara",
    "wof:placetype":"locality"
},
  "geometry": {"coordinates":[88.8908,24.32572],"type":"Point"}
}