{
  "type": "Feature",
  "properties": {
    "gn:admin1_code":"87",
    "gn:admin2_code":"5549",
    "gn:admin3_code":"554979.0",
    "gn:admin4_code":"55497971.0",
    "gn:asciiname":"Chaktabari",
    "gn:country_code":"BD",
    "gn:dem":29,
    "gn:feature_class":"P",
    "gn:feature_code":"PPL",
    "gn:name":"Ch\u0101ktab\u0101ri",
    "gn:population":0,
    "gn:timezone":"Asia/Dhaka",
    "iso:country":"BD",
    "name:ben_x_preferred":[
        "Ch\u0101ktab\u0101ri"
    ],
    "wof:name":"Chaktabari",
    "wof:placetype":"locality"
},
  "geometry": {"coordinates":[89.81116,25.54112000000001],"type":"Point"}
}