{
  "type": "Feature",
  "properties": {
    "gn:admin1_code":"83",
    "gn:admin2_code":"5064",
    "gn:admin3_code":"506460.0",
    "gn:admin4_code":"50646065.0",
    "gn:asciiname":"Kaknashi",
    "gn:country_code":"BD",
    "gn:dem":17,
    "gn:feature_class":"P",
    "gn:feature_code":"PPL",
    "gn:name":"K\u0101knashi",
    "gn:population":0,
    "gn:timezone":"Asia/Dhaka",
    "iso:country":"BD",
    "name:ben_x_preferred":[
        "K\u0101knashi"
    ],
    "name:ben_x_variant":[
        "K\u0101knasi"
    ],
    "wof:name":"Kaknashi",
    "wof:placetype":"locality"
},
  "geometry": {"coordinates":[88.80968,24.77098],"type":"Point"}
}