{
  "type": "Feature",
  "properties": {
    "gn:admin1_code":"87",
    "gn:admin2_code":"5594.0",
    "gn:admin3_code":"559451.0",
    "gn:admin4_code":"55945167.0",
    "gn:asciiname":"Chauthala",
    "gn:country_code":"BD",
    "gn:dem":44,
    "gn:feature_class":"P",
    "gn:feature_code":"PPL",
    "gn:name":"Chauth\u0101la",
    "gn:population":0,
    "gn:timezone":"Asia/Dhaka",
    "iso:country":"BD",
    "name:ben_x_preferred":[
        "Chauth\u0101la"
    ],
    "wof:name":"Chauthala",
    "wof:placetype":"locality"
},
  "geometry": {"coordinates":[88.13720000000001,25.9553],"type":"Point"}
}