{
  "type": "Feature",
  "properties": {
    "gn:admin1_code":"82",
    "gn:admin2_code":"4001.0",
    "gn:admin3_code":"400158.0",
    "gn:admin4_code":"40015859.0",
    "gn:asciiname":"Damerkhanda",
    "gn:country_code":"BD",
    "gn:dem":8,
    "gn:feature_class":"P",
    "gn:feature_code":"PPL",
    "gn:name":"Damerkhanda",
    "gn:population":0,
    "gn:timezone":"Asia/Dhaka",
    "iso:country":"BD",
    "name:ben_x_preferred":[
        "Damerkhanda"
    ],
    "wof:name":"Damerkhanda",
    "wof:placetype":"locality"
},
  "geometry": {"coordinates":[89.66778000000002,22.4769],"type":"Point"}
}