{
  "type": "Feature",
  "properties": {
    "gn:admin1_code":"82",
    "gn:asciiname":"Nisanbaria",
    "gn:country_code":"BD",
    "gn:dem":9,
    "gn:feature_class":"P",
    "gn:feature_code":"PPL",
    "gn:name":"Nis\u0101nb\u0101ria",
    "gn:population":0,
    "gn:timezone":"Asia/Dhaka",
    "iso:country":"BD",
    "name:ben_x_preferred":[
        "Nis\u0101nb\u0101ria"
    ],
    "wof:name":"Nisanbaria",
    "wof:placetype":"locality"
},
  "geometry": {"coordinates":[89.99294999999999,22.03354],"type":"Point"}
}