{
  "type": "Feature",
  "properties": {
    "gn:admin1_code":"82",
    "gn:admin2_code":"4044.0",
    "gn:admin3_code":"404419.0",
    "gn:admin4_code":"40441947.0",
    "gn:asciiname":"Dhopabild",
    "gn:country_code":"BD",
    "gn:dem":14,
    "gn:feature_class":"P",
    "gn:feature_code":"PPL",
    "gn:name":"Dhop\u0101bild",
    "gn:population":0,
    "gn:timezone":"Asia/Dhaka",
    "iso:country":"BD",
    "name:ben_x_preferred":[
        "Dhop\u0101bild"
    ],
    "wof:name":"Dhopabild",
    "wof:placetype":"locality"
},
  "geometry": {"coordinates":[89.10043,23.52915],"type":"Point"}
}