{
  "type": "Feature",
  "properties": {
    "gn:admin1_code":"82",
    "gn:admin2_code":"4001.0",
    "gn:admin3_code":"400158.0",
    "gn:admin4_code":"40015829.0",
    "gn:asciiname":"Kalikabari",
    "gn:country_code":"BD",
    "gn:dem":4,
    "gn:feature_class":"P",
    "gn:feature_code":"PPL",
    "gn:name":"Kalikabari",
    "gn:population":0,
    "gn:timezone":"Asia/Dhaka",
    "iso:country":"BD",
    "name:ben_x_preferred":[
        "Kalikabari"
    ],
    "wof:name":"Kalikabari",
    "wof:placetype":"locality"
},
  "geometry": {"coordinates":[89.63664,22.4436],"type":"Point"}
}