{
  "type": "Feature",
  "properties": {
    "gn:admin1_code":"82",
    "gn:admin2_code":"4044",
    "gn:admin3_code":"404419.0",
    "gn:admin4_code":"40441968.0",
    "gn:asciiname":"Kala",
    "gn:country_code":"BD",
    "gn:dem":9,
    "gn:feature_class":"P",
    "gn:feature_code":"PPL",
    "gn:name":"K\u0101la",
    "gn:population":0,
    "gn:timezone":"Asia/Dhaka",
    "iso:country":"BD",
    "wof:name":"Kala",
    "wof:placetype":"locality"
},
  "geometry": {"coordinates":[89.28333000000001,23.53333],"type":"Point"}
}