{
  "type": "Feature",
  "properties": {
    "gn:admin1_code":"82",
    "gn:admin2_code":"4044.0",
    "gn:admin3_code":"404442.0",
    "gn:admin4_code":"40444227.0",
    "gn:asciiname":"Mallikpur",
    "gn:country_code":"BD",
    "gn:dem":15,
    "gn:feature_class":"P",
    "gn:feature_code":"PPL",
    "gn:name":"Mallikpur",
    "gn:population":0,
    "gn:timezone":"Asia/Dhaka",
    "iso:country":"BD",
    "name:ben_x_preferred":[
        "Mallikpur"
    ],
    "wof:name":"Mallikpur",
    "wof:placetype":"locality"
},
  "geometry": {"coordinates":[88.97724000000002,23.5056],"type":"Point"}
}