{
  "type": "Feature",
  "properties": {
    "gn:admin1_code":"84",
    "gn:admin2_code":"2019",
    "gn:admin3_code":"201968.0",
    "gn:admin4_code":"20196880.0",
    "gn:asciiname":"Perul",
    "gn:country_code":"BD",
    "gn:dem":12,
    "gn:feature_class":"P",
    "gn:feature_code":"PPL",
    "gn:name":"Perul",
    "gn:population":0,
    "gn:timezone":"Asia/Dhaka",
    "iso:country":"BD",
    "wof:name":"Perul",
    "wof:placetype":"locality"
},
  "geometry": {"coordinates":[91.13333,23.26667],"type":"Point"}
}