{
  "type": "Feature",
  "properties": {
    "gn:admin1_code":"83",
    "gn:admin2_code":"5069.0",
    "gn:admin3_code":"506963.0",
    "gn:admin4_code":"50696351.0",
    "gn:asciiname":"Birahimpur Arazi",
    "gn:country_code":"BD",
    "gn:dem":15,
    "gn:feature_class":"P",
    "gn:feature_code":"PPL",
    "gn:name":"Bir\u0101himpur \u0100r\u0101zi",
    "gn:population":0,
    "gn:timezone":"Asia/Dhaka",
    "iso:country":"BD",
    "wof:name":"Birahimpur Arazi",
    "wof:placetype":"locality"
},
  "geometry": {"coordinates":[88.93333,24.35],"type":"Point"}
}