{
  "type": "Feature",
  "properties": {
    "gn:admin1_code":"82",
    "gn:admin2_code":"4050.0",
    "gn:admin3_code":"405079.0",
    "gn:admin4_code":"40507950.0",
    "gn:asciiname":"Khajanagar",
    "gn:country_code":"BD",
    "gn:dem":16,
    "gn:feature_class":"P",
    "gn:feature_code":"PPL",
    "gn:name":"Kh\u0101j\u0101nagar",
    "gn:population":0,
    "gn:timezone":"Asia/Dhaka",
    "iso:country":"BD",
    "name:ben_x_preferred":[
        "Kh\u0101j\u0101nagar"
    ],
    "wof:name":"Khajanagar",
    "wof:placetype":"locality"
},
  "geometry": {"coordinates":[89.06308,23.86761],"type":"Point"}
}