{
  "type": "Feature",
  "properties": {
    "gn:admin1_code":"87",
    "gn:admin2_code":"5549",
    "gn:admin3_code":"554961.0",
    "gn:admin4_code":"55496163.0",
    "gn:asciiname":"Kalarchar",
    "gn:country_code":"BD",
    "gn:dem":31,
    "gn:feature_class":"P",
    "gn:feature_code":"PPL",
    "gn:name":"K\u0101l\u0101rchar",
    "gn:population":0,
    "gn:timezone":"Asia/Dhaka",
    "iso:country":"BD",
    "name:ben_x_preferred":[
        "K\u0101l\u0101rchar"
    ],
    "wof:name":"Kalarchar",
    "wof:placetype":"locality"
},
  "geometry": {"coordinates":[89.84138,25.90051],"type":"Point"}
}