{
  "type": "Feature",
  "properties": {
    "gn:admin1_code":"82",
    "gn:admin2_code":"4041.0",
    "gn:admin3_code":"404190.0",
    "gn:admin4_code":"40419008.0",
    "gn:asciiname":"Baghachara",
    "gn:country_code":"BD",
    "gn:dem":9,
    "gn:feature_class":"P",
    "gn:feature_code":"PPL",
    "gn:name":"B\u0101gh\u0101ch\u0101ra",
    "gn:population":0,
    "gn:timezone":"Asia/Dhaka",
    "iso:country":"BD",
    "name:ben_x_preferred":[
        "B\u0101gh\u0101ch\u0101ra"
    ],
    "name:und_x_variant":[
        "Bag Achra"
    ],
    "wof:name":"Baghachara",
    "wof:placetype":"locality"
},
  "geometry": {"coordinates":[88.97013000000003,22.96555],"type":"Point"}
}