{
  "type": "Feature",
  "properties": {
    "gn:admin1_code":"81",
    "gn:admin2_code":"3067.0",
    "gn:admin3_code":"306702.0",
    "gn:admin4_code":"30670215.0",
    "gn:asciiname":"Dayakanda",
    "gn:country_code":"BD",
    "gn:dem":10,
    "gn:feature_class":"P",
    "gn:feature_code":"PPL",
    "gn:name":"Day\u0101k\u0101nda",
    "gn:population":0,
    "gn:timezone":"Asia/Dhaka",
    "iso:country":"BD",
    "wof:name":"Dayakanda",
    "wof:placetype":"locality"
},
  "geometry": {"coordinates":[90.70493,23.73674],"type":"Point"}
}