{
  "type": "Feature",
  "properties": {
    "gn:admin1_code":"H",
    "gn:asciiname":"Hazari oha",
    "gn:country_code":"BD",
    "gn:dem":22,
    "gn:feature_class":"P",
    "gn:feature_code":"PPL",
    "gn:name":"H\u0101z\u0101ri oha",
    "gn:population":0,
    "gn:timezone":"Asia/Dhaka",
    "iso:country":"BD",
    "name:ben_x_preferred":[
        "H\u0101z\u0101ri oha"
    ],
    "wof:name":"Hazari oha",
    "wof:placetype":"locality"
},
  "geometry": {"coordinates":[89.73184000000001,25.05743],"type":"Point"}
}