{
  "type": "Feature",
  "properties": {
    "gn:admin1_code":"83",
    "gn:admin2_code":"5038.0",
    "gn:admin3_code":"503861.0",
    "gn:admin4_code":"50386119.0",
    "gn:asciiname":"Burail",
    "gn:country_code":"BD",
    "gn:dem":25,
    "gn:feature_class":"P",
    "gn:feature_code":"PPL",
    "gn:name":"Bur\u0101il",
    "gn:population":0,
    "gn:timezone":"Asia/Dhaka",
    "iso:country":"BD",
    "name:ben_x_preferred":[
        "Bur\u0101il"
    ],
    "wof:name":"Burail",
    "wof:placetype":"locality"
},
  "geometry": {"coordinates":[89.11601,25.05662],"type":"Point"}
}