{
  "type": "Feature",
  "properties": {
    "gn:admin1_code":"84",
    "gn:admin2_code":"2003.0",
    "gn:admin3_code":"200373.0",
    "gn:admin4_code":"20037357.0",
    "gn:asciiname":"Pransipara",
    "gn:country_code":"BD",
    "gn:dem":27,
    "gn:feature_class":"P",
    "gn:feature_code":"PPL",
    "gn:name":"Pransip\u0101ra",
    "gn:population":0,
    "gn:timezone":"Asia/Dhaka",
    "iso:country":"BD",
    "name:ben_x_preferred":[
        "Pransip\u0101ra"
    ],
    "wof:name":"Pransipara",
    "wof:placetype":"locality"
},
  "geometry": {"coordinates":[92.15029,21.34693],"type":"Point"}
}