{
  "type": "Feature",
  "properties": {
    "gn:admin1_code":"84",
    "gn:admin2_code":"2019",
    "gn:admin3_code":"201968.0",
    "gn:admin4_code":"20196828.0",
    "gn:asciiname":"Tulatali Belghar",
    "gn:country_code":"BD",
    "gn:dem":9,
    "gn:feature_class":"P",
    "gn:feature_code":"PPL",
    "gn:name":"Tul\u0101tali Belghar",
    "gn:population":0,
    "gn:timezone":"Asia/Dhaka",
    "iso:country":"BD",
    "wof:name":"Tulatali Belghar",
    "wof:placetype":"locality"
},
  "geometry": {"coordinates":[91.16667,23.26667],"type":"Point"}
}