{
  "type": "Feature",
  "properties": {
    "gn:admin1_code":"87",
    "gn:admin2_code":"5532",
    "gn:admin3_code":"553230.0",
    "gn:admin4_code":"55323005.0",
    "gn:asciiname":"Darbast",
    "gn:country_code":"BD",
    "gn:dem":27,
    "gn:feature_class":"P",
    "gn:feature_code":"PPL",
    "gn:name":"Darbast",
    "gn:population":0,
    "gn:timezone":"Asia/Dhaka",
    "iso:country":"BD",
    "name:ben_x_preferred":[
        "Darbast"
    ],
    "wof:name":"Darbast",
    "wof:placetype":"locality"
},
  "geometry": {"coordinates":[89.36218000000002,25.22507],"type":"Point"}
}