{
  "type": "Feature",
  "properties": {
    "gn:admin1_code":"87",
    "gn:admin2_code":"5527.0",
    "gn:admin3_code":"552730.0",
    "gn:admin4_code":"55273047.0",
    "gn:asciiname":"Jot Raghu",
    "gn:country_code":"BD",
    "gn:dem":45,
    "gn:feature_class":"P",
    "gn:feature_code":"PPL",
    "gn:name":"Jot Raghu",
    "gn:population":0,
    "gn:timezone":"Asia/Dhaka",
    "iso:country":"BD",
    "name:ben_x_preferred":[
        "Jot Raghu"
    ],
    "wof:name":"Jot Raghu",
    "wof:placetype":"locality"
},
  "geometry": {"coordinates":[88.8366,25.79153],"type":"Point"}
}