{
  "type": "Feature",
  "properties": {
    "gn:admin1_code":"83",
    "gn:admin2_code":"5069.0",
    "gn:admin3_code":"506991.0",
    "gn:admin4_code":"50699187.0",
    "gn:asciiname":"Bhag Nagarkandi",
    "gn:country_code":"BD",
    "gn:dem":11,
    "gn:feature_class":"P",
    "gn:feature_code":"PPL",
    "gn:name":"Bh\u0101g N\u0101gark\u0101ndi",
    "gn:population":0,
    "gn:timezone":"Asia/Dhaka",
    "iso:country":"BD",
    "wof:name":"Bhag Nagarkandi",
    "wof:placetype":"locality"
},
  "geometry": {"coordinates":[89.11667,24.53333],"type":"Point"}
}