{
  "type": "Feature",
  "properties": {
    "gn:admin1_code":"82",
    "gn:admin2_code":"4087",
    "gn:admin3_code":"408747.0",
    "gn:admin4_code":"40874747.0",
    "gn:asciiname":"Nengi",
    "gn:country_code":"BD",
    "gn:dem":7,
    "gn:feature_class":"P",
    "gn:feature_code":"PPL",
    "gn:name":"Nengi",
    "gn:population":0,
    "gn:timezone":"Asia/Dhaka",
    "iso:country":"BD",
    "name:ben_x_preferred":[
        "Nengi"
    ],
    "wof:name":"Nengi",
    "wof:placetype":"locality"
},
  "geometry": {"coordinates":[89.10484,22.40344],"type":"Point"}
}