{
  "type": "Feature",
  "properties": {
    "gn:admin1_code":"H",
    "gn:admin2_code":"3072.0",
    "gn:admin3_code":"307247.0",
    "gn:admin4_code":"30724781.0",
    "gn:asciiname":"Bairati",
    "gn:country_code":"BD",
    "gn:dem":15,
    "gn:feature_class":"P",
    "gn:feature_code":"PPL",
    "gn:name":"Bair\u0101ti",
    "gn:population":0,
    "gn:timezone":"Asia/Dhaka",
    "iso:country":"BD",
    "wof:name":"Bairati",
    "wof:placetype":"locality"
},
  "geometry": {"coordinates":[90.82603,24.628],"type":"Point"}
}