{
  "type": "Feature",
  "properties": {
    "gn:admin1_code":"H",
    "gn:admin2_code":"3061",
    "gn:admin3_code":"306120.0",
    "gn:admin4_code":"30612035.0",
    "gn:asciiname":"Kali Bajail",
    "gn:country_code":"BD",
    "gn:dem":16,
    "gn:feature_class":"P",
    "gn:feature_code":"PPL",
    "gn:name":"K\u0101li B\u0101j\u0101il",
    "gn:population":0,
    "gn:timezone":"Asia/Dhaka",
    "iso:country":"BD",
    "wof:name":"Kali Bajail",
    "wof:placetype":"locality"
},
  "geometry": {"coordinates":[90.32427,24.67772],"type":"Point"}
}