{
  "type": "Feature",
  "properties": {
    "gn:admin1_code":"85",
    "gn:admin2_code":"1006.0",
    "gn:admin3_code":"100602.0",
    "gn:admin4_code":"10060279.0",
    "gn:asciiname":"Bhatra",
    "gn:country_code":"BD",
    "gn:dem":9,
    "gn:feature_class":"P",
    "gn:feature_code":"PPL",
    "gn:name":"Bh\u0101tra",
    "gn:population":0,
    "gn:timezone":"Asia/Dhaka",
    "iso:country":"BD",
    "name:fra_x_preferred":[
        "Bhatra"
    ],
    "wof:name":"Bhatra",
    "wof:placetype":"locality"
},
  "geometry": {"coordinates":[90.13115999999999,23.0186],"type":"Point"}
}