{
  "type": "Feature",
  "properties": {
    "gn:admin1_code":"82",
    "gn:admin2_code":"4044.0",
    "gn:admin3_code":"404471.0",
    "gn:admin4_code":"40447129.0",
    "gn:asciiname":"Chandmari",
    "gn:country_code":"BD",
    "gn:dem":12,
    "gn:feature_class":"P",
    "gn:feature_code":"PPL",
    "gn:name":"Chandm\u0101ri",
    "gn:population":0,
    "gn:timezone":"Asia/Dhaka",
    "iso:country":"BD",
    "name:ben_x_preferred":[
        "Chandm\u0101ri"
    ],
    "wof:name":"Chandmari",
    "wof:placetype":"locality"
},
  "geometry": {"coordinates":[88.8014,23.23593],"type":"Point"}
}