{
  "type": "Feature",
  "properties": {
    "gn:admin1_code":"84",
    "gn:admin2_code":"2019",
    "gn:admin3_code":"201936.0",
    "gn:admin4_code":"20193686.0",
    "gn:asciiname":"Thetalia",
    "gn:country_code":"BD",
    "gn:dem":5,
    "gn:feature_class":"P",
    "gn:feature_code":"PPL",
    "gn:name":"Thet\u0101lia",
    "gn:population":0,
    "gn:timezone":"Asia/Dhaka",
    "iso:country":"BD",
    "wof:name":"Thetalia",
    "wof:placetype":"locality"
},
  "geometry": {"coordinates":[90.71666999999999,23.43333],"type":"Point"}
}