{
  "type": "Feature",
  "properties": {
    "gn:admin1_code":"81",
    "gn:admin2_code":"3035.0",
    "gn:admin3_code":"303558.0",
    "gn:admin4_code":"30355872.0",
    "gn:asciiname":"Banagram",
    "gn:country_code":"BD",
    "gn:dem":5,
    "gn:feature_class":"P",
    "gn:feature_code":"PPL",
    "gn:name":"Banagr\u0101m",
    "gn:population":0,
    "gn:timezone":"Asia/Dhaka",
    "iso:country":"BD",
    "name:ben_x_preferred":[
        "Banagr\u0101m"
    ],
    "wof:name":"Banagram",
    "wof:placetype":"locality"
},
  "geometry": {"coordinates":[89.97084,23.23047],"type":"Point"}
}