{
  "type": "Feature",
  "properties": {
    "gn:admin1_code":"84",
    "gn:admin2_code":"2015",
    "gn:admin3_code":"201533.0",
    "gn:admin4_code":"20153385.0",
    "gn:asciiname":"Udalia TG",
    "gn:country_code":"BD",
    "gn:dem":18,
    "gn:feature_class":"P",
    "gn:feature_code":"PPL",
    "gn:name":"Ud\u0101lia TG",
    "gn:population":0,
    "gn:timezone":"Asia/Dhaka",
    "iso:country":"BD",
    "name:ben_x_preferred":[
        "Ud\u0101lia TG"
    ],
    "name:ben_x_variant":[
        "Ud\u0101lia"
    ],
    "wof:name":"Udalia TG",
    "wof:placetype":"locality"
},
  "geometry": {"coordinates":[91.76331,22.60936],"type":"Point"}
}