{
  "type": "Feature",
  "properties": {
    "gn:admin1_code":"83",
    "gn:admin2_code":"5076.0",
    "gn:admin3_code":"507683.0",
    "gn:admin4_code":"50768347.0",
    "gn:asciiname":"Paipur",
    "gn:country_code":"BD",
    "gn:dem":12,
    "gn:feature_class":"P",
    "gn:feature_code":"PPL",
    "gn:name":"P\u0101ipur",
    "gn:population":0,
    "gn:timezone":"Asia/Dhaka",
    "iso:country":"BD",
    "name:ben_x_preferred":[
        "P\u0101ipur"
    ],
    "wof:name":"Paipur",
    "wof:placetype":"locality"
},
  "geometry": {"coordinates":[89.52131,23.85323],"type":"Point"}
}