{
  "type": "Feature",
  "properties": {
    "gn:admin1_code":"83",
    "gn:admin2_code":"5076.0",
    "gn:admin3_code":"507639.0",
    "gn:admin4_code":"50763931.0",
    "gn:asciiname":"Char Madia",
    "gn:country_code":"BD",
    "gn:dem":7,
    "gn:feature_class":"P",
    "gn:feature_code":"PPL",
    "gn:name":"Char M\u0101dia",
    "gn:population":0,
    "gn:timezone":"Asia/Dhaka",
    "iso:country":"BD",
    "wof:name":"Char Madia",
    "wof:placetype":"locality"
},
  "geometry": {"coordinates":[89.08333,23.98333],"type":"Point"}
}