{
  "type": "Feature",
  "properties": {
    "gn:admin1_code":"81",
    "gn:admin2_code":"3056.0",
    "gn:admin3_code":"305646.0",
    "gn:admin4_code":"30564639.0",
    "gn:asciiname":"Dakshin Gobindapur",
    "gn:country_code":"BD",
    "gn:dem":15,
    "gn:feature_class":"P",
    "gn:feature_code":"PPL",
    "gn:name":"Dakshin Gobindapur",
    "gn:population":0,
    "gn:timezone":"Asia/Dhaka",
    "iso:country":"BD",
    "name:und_x_variant":[
        "Dakshin Gabindapur",
        "Dakshin Gobindapur"
    ],
    "wof:name":"Dakshin Gobindapur",
    "wof:placetype":"locality"
},
  "geometry": {"coordinates":[90.02759,23.74544],"type":"Point"}
}