{
  "type": "Feature",
  "properties": {
    "gn:admin1_code":"87",
    "gn:admin2_code":"5527.0",
    "gn:admin3_code":"552717.0",
    "gn:admin4_code":"55271719.0",
    "gn:asciiname":"Tilain",
    "gn:country_code":"BD",
    "gn:dem":39,
    "gn:feature_class":"P",
    "gn:feature_code":"PPL",
    "gn:name":"Til\u0101in",
    "gn:population":0,
    "gn:timezone":"Asia/Dhaka",
    "iso:country":"BD",
    "name:ben_x_preferred":[
        "Til\u0101in"
    ],
    "wof:name":"Tilain",
    "wof:placetype":"locality"
},
  "geometry": {"coordinates":[88.49250000000001,25.63361],"type":"Point"}
}