{
  "type": "Feature",
  "properties": {
    "gn:admin1_code":"87",
    "gn:admin2_code":"5594.0",
    "gn:admin3_code":"559482.0",
    "gn:admin4_code":"55948260.0",
    "gn:asciiname":"Ujjalkota",
    "gn:country_code":"BD",
    "gn:dem":55,
    "gn:feature_class":"P",
    "gn:feature_code":"PPL",
    "gn:name":"Ujjalkota",
    "gn:population":0,
    "gn:timezone":"Asia/Dhaka",
    "iso:country":"BD",
    "name:ben_x_preferred":[
        "Ujjalkota"
    ],
    "wof:name":"Ujjalkota",
    "wof:placetype":"locality"
},
  "geometry": {"coordinates":[88.38591,25.93774],"type":"Point"}
}