{
  "type": "Feature",
  "properties": {
    "gn:admin1_code":"87",
    "gn:admin2_code":"5585",
    "gn:admin3_code":"558592.0",
    "gn:admin4_code":"55859279.0",
    "gn:asciiname":"Kazipara",
    "gn:country_code":"BD",
    "gn:dem":39,
    "gn:feature_class":"P",
    "gn:feature_code":"PPL",
    "gn:name":"K\u0101z\u012bp\u0101ra",
    "gn:population":0,
    "gn:timezone":"Asia/Dhaka",
    "iso:country":"BD",
    "name:ben_x_preferred":[
        "K\u0101z\u012bp\u0101ra"
    ],
    "name:ben_x_variant":[
        "Q\u0101zip\u0101ra"
    ],
    "wof:name":"Kazipara",
    "wof:placetype":"locality"
},
  "geometry": {"coordinates":[89.02509999999999,25.74623],"type":"Point"}
}