{
  "type": "Feature",
  "properties": {
    "gn:admin1_code":"83",
    "gn:admin2_code":"5081",
    "gn:admin3_code":"508172.0",
    "gn:admin4_code":"50817271.0",
    "gn:asciiname":"Puthia Para",
    "gn:country_code":"BD",
    "gn:dem":20,
    "gn:feature_class":"P",
    "gn:feature_code":"PPL",
    "gn:name":"Puthia Para",
    "gn:population":0,
    "gn:timezone":"Asia/Dhaka",
    "iso:country":"BD",
    "name:ben_x_preferred":[
        "Puthia Para"
    ],
    "wof:name":"Puthia Para",
    "wof:placetype":"locality"
},
  "geometry": {"coordinates":[88.60858,24.46392],"type":"Point"}
}