{
  "type": "Feature",
  "properties": {
    "gn:admin1_code":"82",
    "gn:asciiname":"Ekarbunia",
    "gn:country_code":"BD",
    "gn:dem":9,
    "gn:feature_class":"P",
    "gn:feature_code":"PPL",
    "gn:name":"Ekarbunia",
    "gn:population":0,
    "gn:timezone":"Asia/Dhaka",
    "iso:country":"BD",
    "name:ben_x_preferred":[
        "Ekarbunia"
    ],
    "wof:name":"Ekarbunia",
    "wof:placetype":"locality"
},
  "geometry": {"coordinates":[89.90841,22.0886],"type":"Point"}
}