{
  "type": "Feature",
  "properties": {
    "gn:admin1_code":"83",
    "gn:admin2_code":"5081.0",
    "gn:admin3_code":"508134.0",
    "gn:admin4_code":"50813485.0",
    "gn:asciiname":"Purba Basnail",
    "gn:country_code":"BD",
    "gn:dem":26,
    "gn:feature_class":"P",
    "gn:feature_code":"PPL",
    "gn:name":"Purba B\u0101sn\u0101il",
    "gn:population":0,
    "gn:timezone":"Asia/Dhaka",
    "iso:country":"BD",
    "name:ben_x_preferred":[
        "Purba B\u0101sn\u0101il"
    ],
    "wof:name":"Purba Basnail",
    "wof:placetype":"locality"
},
  "geometry": {"coordinates":[88.48052,24.47085],"type":"Point"}
}