{
  "type": "Feature",
  "properties": {
    "gn:admin1_code":"87",
    "gn:admin2_code":"5585",
    "gn:admin3_code":"558576.0",
    "gn:admin4_code":"55857612.0",
    "gn:asciiname":"Ambari Salagari",
    "gn:country_code":"BD",
    "gn:dem":33,
    "gn:feature_class":"P",
    "gn:feature_code":"PPL",
    "gn:name":"\u0100mb\u0101ri S\u0101l\u0101gari",
    "gn:population":0,
    "gn:timezone":"Asia/Dhaka",
    "iso:country":"BD",
    "wof:name":"Ambari Salagari",
    "wof:placetype":"locality"
},
  "geometry": {"coordinates":[89.26342,25.50296],"type":"Point"}
}