{
  "type": "Feature",
  "properties": {
    "gn:admin1_code":"82",
    "gn:admin2_code":"4065.0",
    "gn:admin3_code":"406576.0",
    "gn:admin4_code":"40657633.0",
    "gn:asciiname":"Rathdanga",
    "gn:country_code":"BD",
    "gn:dem":16,
    "gn:feature_class":"P",
    "gn:feature_code":"PPL",
    "gn:name":"Rathd\u0101nga",
    "gn:population":0,
    "gn:timezone":"Asia/Dhaka",
    "iso:country":"BD",
    "name:ben_x_preferred":[
        "Rathd\u0101nga"
    ],
    "wof:name":"Rathdanga",
    "wof:placetype":"locality"
},
  "geometry": {"coordinates":[89.51336999999999,23.20733],"type":"Point"}
}