{
  "type": "Feature",
  "properties": {
    "gn:admin1_code":"84",
    "gn:asciiname":"Char Madhabpur",
    "gn:country_code":"BD",
    "gn:dem":12,
    "gn:feature_class":"P",
    "gn:feature_code":"PPL",
    "gn:name":"Char M\u0101dhabpur",
    "gn:population":0,
    "gn:timezone":"Asia/Dhaka",
    "iso:country":"BD",
    "name:und_x_variant":[
        "Char M\u0101dhapur",
        "Char M\u0101dhabpur"
    ],
    "wof:name":"Char Madhabpur",
    "wof:placetype":"locality"
},
  "geometry": {"coordinates":[90.81795,23.87866],"type":"Point"}
}