{
  "type": "Feature",
  "properties": {
    "gn:admin1_code":"82",
    "gn:asciiname":"South Aariapur",
    "gn:country_code":"BD",
    "gn:dem":7,
    "gn:feature_class":"P",
    "gn:feature_code":"PPL",
    "gn:name":"South Aariapur",
    "gn:population":0,
    "gn:timezone":"Asia/Dhaka",
    "iso:country":"BD",
    "name:ben_x_preferred":[
        "South Aariapur"
    ],
    "wof:name":"South Aariapur",
    "wof:placetype":"locality"
},
  "geometry": {"coordinates":[90.36221,22.30006],"type":"Point"}
}