{
  "type": "Feature",
  "properties": {
    "gn:admin1_code":"85",
    "gn:admin2_code":"1006.0",
    "gn:admin3_code":"100602.0",
    "gn:admin4_code":"10060279.0",
    "gn:asciiname":"Chhota Basail",
    "gn:country_code":"BD",
    "gn:dem":10,
    "gn:feature_class":"P",
    "gn:feature_code":"PPL",
    "gn:name":"Chhota B\u0101s\u0101il",
    "gn:population":0,
    "gn:timezone":"Asia/Dhaka",
    "iso:country":"BD",
    "name:und_x_variant":[
        "Chhota B\u0101s\u0101il"
    ],
    "wof:name":"Chhota Basail",
    "wof:placetype":"locality"
},
  "geometry": {"coordinates":[90.17010999999999,23.02583],"type":"Point"}
}