{
  "type": "Feature",
  "properties": {
    "gn:admin1_code":"87",
    "gn:admin2_code":"5585.0",
    "gn:admin3_code":"558542.0",
    "gn:admin4_code":"55854281.0",
    "gn:asciiname":"Bhutchhara",
    "gn:country_code":"BD",
    "gn:dem":32,
    "gn:feature_class":"P",
    "gn:feature_code":"PPL",
    "gn:name":"Bhutchh\u0101ra",
    "gn:population":0,
    "gn:timezone":"Asia/Dhaka",
    "iso:country":"BD",
    "wof:name":"Bhutchhara",
    "wof:placetype":"locality"
},
  "geometry": {"coordinates":[89.46666999999999,25.76667],"type":"Point"}
}