{
  "type": "Feature",
  "properties": {
    "gn:admin1_code":"83",
    "gn:admin2_code":"5081.0",
    "gn:admin3_code":"508182.0",
    "gn:admin4_code":"50818267.0",
    "gn:asciiname":"Fatehpur",
    "gn:country_code":"BD",
    "gn:dem":19,
    "gn:feature_class":"P",
    "gn:feature_code":"PPL",
    "gn:name":"Fatehpur",
    "gn:population":0,
    "gn:timezone":"Asia/Dhaka",
    "iso:country":"BD",
    "name:ben_x_preferred":[
        "Fatehpur"
    ],
    "name:ben_x_variant":[
        "Fatepur"
    ],
    "wof:name":"Fatehpur",
    "wof:placetype":"locality"
},
  "geometry": {"coordinates":[88.79531,24.34685],"type":"Point"}
}