{
  "type": "Feature",
  "properties": {
    "gn:admin1_code":"84",
    "gn:admin2_code":"2022.0",
    "gn:admin3_code":"202290.0",
    "gn:admin4_code":"20229047.0",
    "gn:asciiname":"Hadurchara",
    "gn:country_code":"BD",
    "gn:dem":7,
    "gn:feature_class":"P",
    "gn:feature_code":"PPL",
    "gn:name":"H\u0101durchara",
    "gn:population":0,
    "gn:timezone":"Asia/Dhaka",
    "iso:country":"BD",
    "name:ben_x_preferred":[
        "H\u0101durchara"
    ],
    "wof:name":"Hadurchara",
    "wof:placetype":"locality"
},
  "geometry": {"coordinates":[92.28982999999999,20.82745],"type":"Point"}
}