{
  "type": "Feature",
  "properties": {
    "gn:admin1_code":"81",
    "gn:admin2_code":"3086",
    "gn:admin3_code":"308614.0",
    "gn:admin4_code":"30861425.0",
    "gn:asciiname":"Singachura",
    "gn:country_code":"BD",
    "gn:dem":10,
    "gn:feature_class":"P",
    "gn:feature_code":"PPL",
    "gn:name":"Sing\u0101chura",
    "gn:population":0,
    "gn:timezone":"Asia/Dhaka",
    "iso:country":"BD",
    "name:und_x_variant":[
        "Singashura",
        "Sing\u0101chura"
    ],
    "wof:name":"Singachura",
    "wof:placetype":"locality"
},
  "geometry": {"coordinates":[90.3997,23.21438],"type":"Point"}
}