{
  "type": "Feature",
  "properties": {
    "gn:admin1_code":"84",
    "gn:admin2_code":"2022.0",
    "gn:admin3_code":"202295.0",
    "gn:admin4_code":"20229578.0",
    "gn:asciiname":"Narbarpara",
    "gn:country_code":"BD",
    "gn:dem":5,
    "gn:feature_class":"P",
    "gn:feature_code":"PPL",
    "gn:name":"Narbarp\u0101ra",
    "gn:population":0,
    "gn:timezone":"Asia/Dhaka",
    "iso:country":"BD",
    "name:ben_x_preferred":[
        "Narbarp\u0101ra"
    ],
    "wof:name":"Narbarpara",
    "wof:placetype":"locality"
},
  "geometry": {"coordinates":[91.94141,21.77784],"type":"Point"}
}