{
  "type": "Feature",
  "properties": {
    "gn:admin1_code":"81",
    "gn:admin2_code":"3033",
    "gn:admin3_code":"303336.0",
    "gn:admin4_code":"30333643.0",
    "gn:asciiname":"Kardania",
    "gn:country_code":"BD",
    "gn:dem":13,
    "gn:feature_class":"P",
    "gn:feature_code":"PPL",
    "gn:name":"Kardania",
    "gn:population":0,
    "gn:timezone":"Asia/Dhaka",
    "iso:country":"BD",
    "name:und_x_variant":[
        "K\u0101ndania"
    ],
    "wof:name":"Kardania",
    "wof:placetype":"locality"
},
  "geometry": {"coordinates":[90.56740000000001,24.09012],"type":"Point"}
}