{
  "type": "Feature",
  "properties": {
    "gn:admin1_code":"87",
    "gn:admin2_code":"5527",
    "gn:admin3_code":"552747.0",
    "gn:admin4_code":"55274781.0",
    "gn:asciiname":"Debganda Jangla",
    "gn:country_code":"BD",
    "gn:dem":30,
    "gn:feature_class":"P",
    "gn:feature_code":"PPL",
    "gn:name":"Debganda Jangla",
    "gn:population":0,
    "gn:timezone":"Asia/Dhaka",
    "iso:country":"BD",
    "name:ben_x_preferred":[
        "Debganda Jangla"
    ],
    "wof:name":"Debganda Jangla",
    "wof:placetype":"locality"
},
  "geometry": {"coordinates":[88.99851,25.32362],"type":"Point"}
}