{
  "type": "Feature",
  "properties": {
    "gn:admin1_code":"83",
    "gn:admin2_code":"5010",
    "gn:admin3_code":"501054.0",
    "gn:admin4_code":"50105438.0",
    "gn:asciiname":"Jaitul",
    "gn:country_code":"BD",
    "gn:dem":21,
    "gn:feature_class":"P",
    "gn:feature_code":"PPL",
    "gn:name":"Jaitul",
    "gn:population":0,
    "gn:timezone":"Asia/Dhaka",
    "iso:country":"BD",
    "wof:name":"Jaitul",
    "wof:placetype":"locality"
},
  "geometry": {"coordinates":[89.24504,24.84831],"type":"Point"}
}