{
  "type": "Feature",
  "properties": {
    "gn:admin1_code":"87",
    "gn:admin2_code":"5552",
    "gn:admin3_code":"555255.0",
    "gn:admin4_code":"55525583.0",
    "gn:asciiname":"Panchagram Alabaksa",
    "gn:country_code":"BD",
    "gn:dem":36,
    "gn:feature_class":"P",
    "gn:feature_code":"PPL",
    "gn:name":"Panchagr\u0101m \u0100l\u0101baksa",
    "gn:population":0,
    "gn:timezone":"Asia/Dhaka",
    "iso:country":"BD",
    "name:ben_x_preferred":[
        "Panchagr\u0101m \u0100l\u0101baksa"
    ],
    "name:ben_x_variant":[
        "Panchagr\u0101m"
    ],
    "wof:name":"Panchagram Alabaksa",
    "wof:placetype":"locality"
},
  "geometry": {"coordinates":[89.53069000000001,25.84109],"type":"Point"}
}