{
  "type": "Feature",
  "properties": {
    "gn:admin1_code":"82",
    "gn:admin2_code":"4041.0",
    "gn:admin3_code":"404109.0",
    "gn:admin4_code":"40410957.0",
    "gn:asciiname":"Datpur",
    "gn:country_code":"BD",
    "gn:dem":12,
    "gn:feature_class":"P",
    "gn:feature_code":"PPL",
    "gn:name":"D\u0101tpur",
    "gn:population":0,
    "gn:timezone":"Asia/Dhaka",
    "iso:country":"BD",
    "name:ben_x_preferred":[
        "D\u0101tpur"
    ],
    "wof:name":"Datpur",
    "wof:placetype":"locality"
},
  "geometry": {"coordinates":[89.38334999999999,23.1914],"type":"Point"}
}