{
  "type": "Feature",
  "properties": {
    "gn:admin1_code":"87",
    "gn:admin2_code":"5585",
    "gn:admin3_code":"558549.0",
    "gn:admin4_code":"55854931.0",
    "gn:asciiname":"Maheshpur",
    "gn:country_code":"BD",
    "gn:dem":42,
    "gn:feature_class":"P",
    "gn:feature_code":"PPL",
    "gn:name":"Maheshpur",
    "gn:population":0,
    "gn:timezone":"Asia/Dhaka",
    "iso:country":"BD",
    "name:ben_x_preferred":[
        "Maheshpur"
    ],
    "wof:name":"Maheshpur",
    "wof:placetype":"locality"
},
  "geometry": {"coordinates":[89.11994,25.7976],"type":"Point"}
}