{
  "type": "Feature",
  "properties": {
    "gn:admin1_code":"82",
    "gn:admin2_code":"4044.0",
    "gn:admin3_code":"404433.0",
    "gn:admin4_code":"40443333.0",
    "gn:asciiname":"Gunjdnagar",
    "gn:country_code":"BD",
    "gn:dem":10,
    "gn:feature_class":"P",
    "gn:feature_code":"PPL",
    "gn:name":"Gunjdnagar",
    "gn:population":0,
    "gn:timezone":"Asia/Dhaka",
    "iso:country":"BD",
    "name:ben_x_preferred":[
        "Gunjdnagar"
    ],
    "wof:name":"Gunjdnagar",
    "wof:placetype":"locality"
},
  "geometry": {"coordinates":[89.15629,23.42277],"type":"Point"}
}