{
  "type": "Feature",
  "properties": {
    "gn:admin1_code":"85",
    "gn:admin2_code":"1006",
    "gn:admin3_code":"100602.0",
    "gn:admin4_code":"10060287.0",
    "gn:asciiname":"Ratnapur",
    "gn:country_code":"BD",
    "gn:dem":10,
    "gn:feature_class":"P",
    "gn:feature_code":"PPL",
    "gn:name":"Ratnapur",
    "gn:population":0,
    "gn:timezone":"Asia/Dhaka",
    "iso:country":"BD",
    "name:urd_x_preferred":[
        "\u0631\u062a\u0646\u0627\u067e\u0648\u0631"
    ],
    "wof:name":"Ratnapur",
    "wof:placetype":"locality"
},
  "geometry": {"coordinates":[90.20406,22.91638],"type":"Point"}
}