{
  "type": "Feature",
  "properties": {
    "gn:admin1_code":"82",
    "gn:admin2_code":"4044.0",
    "gn:admin3_code":"404471.0",
    "gn:admin4_code":"40447108.0",
    "gn:asciiname":"Jitarpur",
    "gn:country_code":"BD",
    "gn:dem":14,
    "gn:feature_class":"P",
    "gn:feature_code":"PPL",
    "gn:name":"Jit\u0101rpur",
    "gn:population":0,
    "gn:timezone":"Asia/Dhaka",
    "iso:country":"BD",
    "name:ben_x_preferred":[
        "Jit\u0101rpur"
    ],
    "wof:name":"Jitarpur",
    "wof:placetype":"locality"
},
  "geometry": {"coordinates":[89.02266999999998,23.35596],"type":"Point"}
}