{
  "type": "Feature",
  "properties": {
    "gn:admin1_code":"85",
    "gn:admin2_code":"1079.0",
    "gn:admin3_code":"107958.0",
    "gn:admin4_code":"10795886.0",
    "gn:asciiname":"Ghosher Tikikata",
    "gn:country_code":"BD",
    "gn:dem":11,
    "gn:feature_class":"P",
    "gn:feature_code":"PPL",
    "gn:name":"Ghosher Tikik\u0101ta",
    "gn:population":0,
    "gn:timezone":"Asia/Dhaka",
    "iso:country":"BD",
    "name:ben_x_preferred":[
        "Ghosher Tikik\u0101ta"
    ],
    "name:zho_x_preferred":[
        "\u9ad8\u8c22\u5c14\u7b2c\u8482\u52a0\u8fbe"
    ],
    "wof:name":"Ghosher Tikikata",
    "wof:placetype":"locality"
},
  "geometry": {"coordinates":[90.00397,22.27444],"type":"Point"}
}