{
  "type": "Feature",
  "properties": {
    "gn:admin1_code":"83",
    "gn:admin2_code":"5064.0",
    "gn:admin3_code":"506460.0",
    "gn:admin4_code":"50646000.0",
    "gn:asciiname":"Chak Daulat",
    "gn:country_code":"BD",
    "gn:dem":18,
    "gn:feature_class":"P",
    "gn:feature_code":"PPL",
    "gn:name":"Chak Daulat",
    "gn:population":0,
    "gn:timezone":"Asia/Dhaka",
    "iso:country":"BD",
    "wof:name":"Chak Daulat",
    "wof:placetype":"locality"
},
  "geometry": {"coordinates":[88.93333,24.78333],"type":"Point"}
}