{
  "type": "Feature",
  "properties": {
    "gn:admin1_code":"84",
    "gn:admin2_code":"2015.0",
    "gn:admin3_code":"201570.0",
    "gn:admin4_code":"20157069.0",
    "gn:asciiname":"Gabupera",
    "gn:country_code":"BD",
    "gn:dem":22,
    "gn:feature_class":"P",
    "gn:feature_code":"PPL",
    "gn:name":"Gabup\u0113ra",
    "gn:population":0,
    "gn:timezone":"Asia/Dhaka",
    "iso:country":"BD",
    "name:ben_x_preferred":[
        "Gabup\u0101ra"
    ],
    "name:und_x_variant":[
        "Gabup\u0113ra"
    ],
    "wof:name":"Gabupera",
    "wof:placetype":"locality"
},
  "geometry": {"coordinates":[92.04902,22.55497],"type":"Point"}
}