{
  "type": "Feature",
  "properties": {
    "gn:admin1_code":"84",
    "gn:admin2_code":"2013",
    "gn:admin3_code":"201379.0",
    "gn:admin4_code":"20137994.0",
    "gn:asciiname":"Maisadi",
    "gn:country_code":"BD",
    "gn:dem":6,
    "gn:feature_class":"P",
    "gn:feature_code":"PPL",
    "gn:name":"Mais\u0101di",
    "gn:population":0,
    "gn:timezone":"Asia/Dhaka",
    "iso:country":"BD",
    "wof:name":"Maisadi",
    "wof:placetype":"locality"
},
  "geometry": {"coordinates":[90.65000000000001,23.41667],"type":"Point"}
}