{
  "type": "Feature",
  "properties": {
    "gn:admin1_code":"87",
    "gn:admin2_code":"5549",
    "gn:admin3_code":"554918.0",
    "gn:admin4_code":"55491840.0",
    "gn:asciiname":"Nagdaha",
    "gn:country_code":"BD",
    "gn:dem":36,
    "gn:feature_class":"P",
    "gn:feature_code":"PPL",
    "gn:name":"N\u0101gdaha",
    "gn:population":0,
    "gn:timezone":"Asia/Dhaka",
    "iso:country":"BD",
    "name:ben_x_preferred":[
        "N\u0101gdaha"
    ],
    "name:nep_x_preferred":[
        "\u0928\u093e\u0917\u0926\u0939"
    ],
    "wof:name":"Nagdaha",
    "wof:placetype":"locality"
},
  "geometry": {"coordinates":[89.58436,25.93929],"type":"Point"}
}