{
  "type": "Feature",
  "properties": {
    "gn:admin1_code":"87",
    "gn:admin2_code":"5552.0",
    "gn:admin3_code":"555202.0",
    "gn:admin4_code":"55520271.0",
    "gn:asciiname":"Gobardhan",
    "gn:country_code":"BD",
    "gn:dem":34,
    "gn:feature_class":"P",
    "gn:feature_code":"PPL",
    "gn:name":"Gobardhan",
    "gn:population":0,
    "gn:timezone":"Asia/Dhaka",
    "iso:country":"BD",
    "name:ben_x_preferred":[
        "Gobardhan"
    ],
    "wof:name":"Gobardhan",
    "wof:placetype":"locality"
},
  "geometry": {"coordinates":[89.31538,25.88008],"type":"Point"}
}