{
  "type": "Feature",
  "properties": {
    "gn:admin1_code":"87",
    "gn:admin2_code":"5527.0",
    "gn:admin3_code":"552777.0",
    "gn:admin4_code":"55277717.0",
    "gn:asciiname":"Chhota Haripur",
    "gn:country_code":"BD",
    "gn:dem":41,
    "gn:feature_class":"P",
    "gn:feature_code":"PPL",
    "gn:name":"Chhota Haripur",
    "gn:population":0,
    "gn:timezone":"Asia/Dhaka",
    "iso:country":"BD",
    "name:ben_x_preferred":[
        "Chhota Haripur"
    ],
    "wof:name":"Chhota Haripur",
    "wof:placetype":"locality"
},
  "geometry": {"coordinates":[88.88977,25.65675],"type":"Point"}
}