{
  "type": "Feature",
  "properties": {
    "gn:admin1_code":"81",
    "gn:admin2_code":"3054.0",
    "gn:admin3_code":"305440.0",
    "gn:admin4_code":"30544012.0",
    "gn:asciiname":"Atipara",
    "gn:country_code":"BD",
    "gn:dem":8,
    "gn:feature_class":"P",
    "gn:feature_code":"PPL",
    "gn:name":"\u0100tip\u0101ra",
    "gn:population":0,
    "gn:timezone":"Asia/Dhaka",
    "iso:country":"BD",
    "wof:name":"Atipara",
    "wof:placetype":"locality"
},
  "geometry": {"coordinates":[90.15904999999999,23.12901],"type":"Point"}
}