{
  "type": "Feature",
  "properties": {
    "gn:admin1_code":"82",
    "gn:admin2_code":"4087.0",
    "gn:admin3_code":"408786.0",
    "gn:admin4_code":"40878679.0",
    "gn:asciiname":"Banyotala",
    "gn:country_code":"BD",
    "gn:dem":2,
    "gn:feature_class":"P",
    "gn:feature_code":"PPL",
    "gn:name":"Banyotala",
    "gn:population":0,
    "gn:timezone":"Asia/Dhaka",
    "iso:country":"BD",
    "name:ben_x_preferred":[
        "Banyotala"
    ],
    "wof:name":"Banyotala",
    "wof:placetype":"locality"
},
  "geometry": {"coordinates":[89.2272,22.37052000000001],"type":"Point"}
}