{
  "type": "Feature",
  "properties": {
    "gn:admin1_code":"81",
    "gn:admin2_code":"3082.0",
    "gn:admin3_code":"308276.0",
    "gn:admin4_code":"30827636.0",
    "gn:asciiname":"Chhota Nurpur",
    "gn:country_code":"BD",
    "gn:dem":15,
    "gn:feature_class":"P",
    "gn:feature_code":"PPL",
    "gn:name":"Chhota Nurpur",
    "gn:population":0,
    "gn:timezone":"Asia/Dhaka",
    "iso:country":"BD",
    "name:ben_x_preferred":[
        "Chhota Nurpur"
    ],
    "wof:name":"Chhota Nurpur",
    "wof:placetype":"locality"
},
  "geometry": {"coordinates":[89.66825,23.76446],"type":"Point"}
}