{
  "type": "Feature",
  "properties": {
    "gn:admin1_code":"84",
    "gn:admin2_code":"2003.0",
    "gn:admin3_code":"200373.0",
    "gn:admin4_code":"20037338.0",
    "gn:asciiname":"Waiphapara",
    "gn:country_code":"BD",
    "gn:dem":104,
    "gn:feature_class":"P",
    "gn:feature_code":"PPL",
    "gn:name":"Waiphap\u0101ra",
    "gn:population":0,
    "gn:timezone":"Asia/Dhaka",
    "iso:country":"BD",
    "name:ben_x_preferred":[
        "Waiphap\u0101ra"
    ],
    "wof:name":"Waiphapara",
    "wof:placetype":"locality"
},
  "geometry": {"coordinates":[92.23273,21.57176],"type":"Point"}
}