{
  "type": "Feature",
  "properties": {
    "gn:admin1_code":"81",
    "gn:admin2_code":"3035.0",
    "gn:admin3_code":"303558.0",
    "gn:admin4_code":"30355839.0",
    "gn:asciiname":"Acharpara Aruakandi",
    "gn:country_code":"BD",
    "gn:dem":7,
    "gn:feature_class":"P",
    "gn:feature_code":"PPL",
    "gn:name":"Acharp\u0101ra Aru\u0101k\u0101ndi",
    "gn:population":0,
    "gn:timezone":"Asia/Dhaka",
    "iso:country":"BD",
    "name:ben_x_preferred":[
        "Acharp\u0101ra Aru\u0101k\u0101ndi"
    ],
    "wof:name":"Acharpara Aruakandi",
    "wof:placetype":"locality"
},
  "geometry": {"coordinates":[89.97723000000001,23.23646],"type":"Point"}
}