{
  "type": "Feature",
  "properties": {
    "gn:admin1_code":"87",
    "gn:admin2_code":"5577.0",
    "gn:admin3_code":"557704.0",
    "gn:admin4_code":"55770454.0",
    "gn:asciiname":"Badrakali",
    "gn:country_code":"BD",
    "gn:dem":74,
    "gn:feature_class":"P",
    "gn:feature_code":"PPL",
    "gn:name":"Badrakali",
    "gn:population":0,
    "gn:timezone":"Asia/Dhaka",
    "iso:country":"BD",
    "name:ben_x_preferred":[
        "Badrakali"
    ],
    "wof:name":"Badrakali",
    "wof:placetype":"locality"
},
  "geometry": {"coordinates":[88.44414,26.29384000000001],"type":"Point"}
}