{
  "type": "Feature",
  "properties": {
    "gn:admin1_code":"84",
    "gn:admin2_code":"2015.0",
    "gn:admin3_code":"201508.0",
    "gn:admin4_code":"20150844.0",
    "gn:asciiname":"Gunagari",
    "gn:country_code":"BD",
    "gn:dem":6,
    "gn:feature_class":"P",
    "gn:feature_code":"PPL",
    "gn:name":"Gunagari",
    "gn:population":0,
    "gn:timezone":"Asia/Dhaka",
    "iso:country":"BD",
    "name:ben_x_preferred":[
        "Gunagari"
    ],
    "wof:name":"Gunagari",
    "wof:placetype":"locality"
},
  "geometry": {"coordinates":[91.92462,22.09146],"type":"Point"}
}