{
  "type": "Feature",
  "properties": {
    "gn:admin1_code":"81",
    "gn:admin2_code":"3082",
    "gn:admin3_code":"308273.0",
    "gn:admin4_code":"30827395.0",
    "gn:asciiname":"Kauakhola",
    "gn:country_code":"BD",
    "gn:dem":14,
    "gn:feature_class":"P",
    "gn:feature_code":"PPL",
    "gn:name":"K\u0101u\u0101khola",
    "gn:population":0,
    "gn:timezone":"Asia/Dhaka",
    "iso:country":"BD",
    "name:und_x_variant":[
        "Kaoakhola",
        "K\u0101u\u0101khola"
    ],
    "wof:name":"Kauakhola",
    "wof:placetype":"locality"
},
  "geometry": {"coordinates":[89.40432,23.69782],"type":"Point"}
}