{
  "type": "Feature",
  "properties": {
    "gn:admin1_code":"85",
    "gn:admin2_code":"1006",
    "gn:admin3_code":"100694.0",
    "gn:admin4_code":"10069463.0",
    "gn:asciiname":"Masang",
    "gn:country_code":"BD",
    "gn:dem":7,
    "gn:feature_class":"P",
    "gn:feature_code":"PPL",
    "gn:name":"Mas\u0101ng",
    "gn:population":0,
    "gn:timezone":"Asia/Dhaka",
    "iso:country":"BD",
    "wof:name":"Masang",
    "wof:placetype":"locality"
},
  "geometry": {"coordinates":[90.13076,22.87461],"type":"Point"}
}