{
  "type": "Feature",
  "properties": {
    "gn:admin1_code":"82",
    "gn:admin2_code":"4018",
    "gn:admin3_code":"401807.0",
    "gn:admin4_code":"40180715.0",
    "gn:asciiname":"Poltadanga",
    "gn:country_code":"BD",
    "gn:dem":21,
    "gn:feature_class":"P",
    "gn:feature_code":"PPL",
    "gn:name":"Polt\u0101d\u0101nga",
    "gn:population":0,
    "gn:timezone":"Asia/Dhaka",
    "iso:country":"BD",
    "name:ben_x_preferred":[
        "Polt\u0101d\u0101nga"
    ],
    "wof:name":"Poltadanga",
    "wof:placetype":"locality"
},
  "geometry": {"coordinates":[88.8749,23.7731],"type":"Point"}
}