{
  "type": "Feature",
  "properties": {
    "gn:admin1_code":"83",
    "gn:admin2_code":"5064.0",
    "gn:admin3_code":"506450.0",
    "gn:admin4_code":"50645085.0",
    "gn:asciiname":"Tataipur",
    "gn:country_code":"BD",
    "gn:dem":20,
    "gn:feature_class":"P",
    "gn:feature_code":"PPL",
    "gn:name":"Tat\u0101ipur",
    "gn:population":0,
    "gn:timezone":"Asia/Dhaka",
    "iso:country":"BD",
    "name:ben_x_preferred":[
        "Tat\u0101ipur"
    ],
    "wof:name":"Tataipur",
    "wof:placetype":"locality"
},
  "geometry": {"coordinates":[88.7413,24.87141],"type":"Point"}
}