{
  "type": "Feature",
  "properties": {
    "gn:admin1_code":"83",
    "gn:asciiname":"Domgari",
    "gn:country_code":"BD",
    "gn:dem":28,
    "gn:feature_class":"P",
    "gn:feature_code":"PPL",
    "gn:name":"Domgari",
    "gn:population":0,
    "gn:timezone":"Asia/Dhaka",
    "iso:country":"BD",
    "name:ben_x_preferred":[
        "Domgari"
    ],
    "wof:name":"Domgari",
    "wof:placetype":"locality"
},
  "geometry": {"coordinates":[89.26793000000001,25.14572],"type":"Point"}
}