{
  "type": "Feature",
  "properties": {
    "gn:admin1_code":"82",
    "gn:asciiname":"Arazi Durgapur",
    "gn:country_code":"BD",
    "gn:dem":8,
    "gn:feature_class":"P",
    "gn:feature_code":"PPL",
    "gn:name":"\u0100r\u0101zi Durg\u0101pur",
    "gn:population":0,
    "gn:timezone":"Asia/Dhaka",
    "iso:country":"BD",
    "name:ben_x_preferred":[
        "\u0100r\u0101zi Durg\u0101pur"
    ],
    "wof:name":"Arazi Durgapur",
    "wof:placetype":"locality"
},
  "geometry": {"coordinates":[90.29532,22.44957],"type":"Point"}
}