{
  "type": "Feature",
  "properties": {
    "gn:admin1_code":"83",
    "gn:admin2_code":"5069.0",
    "gn:admin3_code":"506909.0",
    "gn:admin4_code":"50690938.0",
    "gn:asciiname":"Mistripara",
    "gn:country_code":"BD",
    "gn:dem":21,
    "gn:feature_class":"P",
    "gn:feature_code":"PPL",
    "gn:name":"Mistrip\u0101ra",
    "gn:population":0,
    "gn:timezone":"Asia/Dhaka",
    "iso:country":"BD",
    "name:ben_x_preferred":[
        "Mistrip\u0101ra"
    ],
    "wof:name":"Mistripara",
    "wof:placetype":"locality"
},
  "geometry": {"coordinates":[88.98858,24.28342],"type":"Point"}
}