{
  "type": "Feature",
  "properties": {
    "gn:admin1_code":"82",
    "gn:admin2_code":"4047.0",
    "gn:admin3_code":"404764.0",
    "gn:admin4_code":"40476461.0",
    "gn:asciiname":"Chak Bagura",
    "gn:country_code":"BD",
    "gn:dem":6,
    "gn:feature_class":"P",
    "gn:feature_code":"PPL",
    "gn:name":"Chak Bagura",
    "gn:population":0,
    "gn:timezone":"Asia/Dhaka",
    "iso:country":"BD",
    "wof:name":"Chak Bagura",
    "wof:placetype":"locality"
},
  "geometry": {"coordinates":[89.29449,22.57808],"type":"Point"}
}