{
  "type": "Feature",
  "properties": {
    "gn:admin1_code":"87",
    "gn:admin2_code":"5585",
    "gn:admin3_code":"558527.0",
    "gn:admin4_code":"55852773.0",
    "gn:asciiname":"Joyramajha",
    "gn:country_code":"BD",
    "gn:dem":33,
    "gn:feature_class":"P",
    "gn:feature_code":"PPL",
    "gn:name":"Joyramajha",
    "gn:population":0,
    "gn:timezone":"Asia/Dhaka",
    "iso:country":"BD",
    "name:ben_x_preferred":[
        "Joyramajha"
    ],
    "wof:name":"Joyramajha",
    "wof:placetype":"locality"
},
  "geometry": {"coordinates":[89.28915000000001,25.88727],"type":"Point"}
}