{
  "type": "Feature",
  "properties": {
    "gn:admin1_code":"82",
    "gn:admin2_code":"4018.0",
    "gn:admin3_code":"401807.0",
    "gn:admin4_code":"40180731.0",
    "gn:asciiname":"Badumajir",
    "gn:country_code":"BD",
    "gn:dem":19,
    "gn:feature_class":"P",
    "gn:feature_code":"PPL",
    "gn:name":"Badumajir",
    "gn:population":0,
    "gn:timezone":"Asia/Dhaka",
    "iso:country":"BD",
    "name:ben_x_preferred":[
        "Badumajir"
    ],
    "wof:name":"Badumajir",
    "wof:placetype":"locality"
},
  "geometry": {"coordinates":[88.97695,23.74577],"type":"Point"}
}