{
  "type": "Feature",
  "properties": {
    "gn:admin1_code":"82",
    "gn:admin2_code":"4050.0",
    "gn:admin3_code":"405039.0",
    "gn:admin4_code":"40503961.0",
    "gn:asciiname":"Gabargaro",
    "gn:country_code":"BD",
    "gn:dem":19,
    "gn:feature_class":"P",
    "gn:feature_code":"PPL",
    "gn:name":"Gabarg\u0101ro",
    "gn:population":0,
    "gn:timezone":"Asia/Dhaka",
    "iso:country":"BD",
    "name:ben_x_preferred":[
        "Gabarg\u0101ro"
    ],
    "name:ben_x_variant":[
        "Gobarg\u0101ra"
    ],
    "wof:name":"Gabargaro",
    "wof:placetype":"locality"
},
  "geometry": {"coordinates":[88.81329000000002,24.01988],"type":"Point"}
}