{
  "type": "Feature",
  "properties": {
    "gn:admin1_code":"84",
    "gn:admin2_code":"2075.0",
    "gn:admin3_code":"207507.0",
    "gn:admin4_code":"20750766.0",
    "gn:asciiname":"Abdullahpur",
    "gn:cc2":"BD",
    "gn:country_code":"BD",
    "gn:dem":8,
    "gn:feature_class":"P",
    "gn:feature_code":"PPL",
    "gn:name":"Abdull\u0101hpur",
    "gn:population":0,
    "gn:timezone":"Asia/Dhaka",
    "iso:country":"BD",
    "name:und_x_variant":[
        "Abdullapur",
        "Abdull\u0101hpur"
    ],
    "wof:name":"Abdullahpur",
    "wof:placetype":"locality"
},
  "geometry": {"coordinates":[91.16667,22.96667],"type":"Point"}
}