{
  "type": "Feature",
  "properties": {
    "gn:admin1_code":"87",
    "gn:admin2_code":"5573.0",
    "gn:admin3_code":"557312.0",
    "gn:admin4_code":"55731266.0",
    "gn:asciiname":"Kakra",
    "gn:country_code":"BD",
    "gn:dem":55,
    "gn:feature_class":"P",
    "gn:feature_code":"PPL",
    "gn:name":"Kakra",
    "gn:population":0,
    "gn:timezone":"Asia/Dhaka",
    "iso:country":"BD",
    "name:ben_x_preferred":[
        "Kakia"
    ],
    "name:fas_x_preferred":[
        "\u06a9\u06a9\u0631\u0627"
    ],
    "wof:name":"Kakra",
    "wof:placetype":"locality"
},
  "geometry": {"coordinates":[88.98541999999998,26.11618],"type":"Point"}
}