{
  "type": "Feature",
  "properties": {
    "gn:admin1_code":"85",
    "gn:admin2_code":"1004.0",
    "gn:admin3_code":"100409.0",
    "gn:admin4_code":"10040979.0",
    "gn:asciiname":"Sharikkhali",
    "gn:country_code":"BD",
    "gn:dem":8,
    "gn:feature_class":"P",
    "gn:feature_code":"PPL",
    "gn:name":"Sharikkhali",
    "gn:population":0,
    "gn:timezone":"Asia/Dhaka",
    "iso:country":"BD",
    "name:ben_x_preferred":[
        "Sharikkhali"
    ],
    "wof:name":"Sharikkhali",
    "wof:placetype":"locality"
},
  "geometry": {"coordinates":[90.17847,22.03582],"type":"Point"}
}