{
  "type": "Feature",
  "properties": {
    "gn:admin1_code":"81",
    "gn:admin2_code":"3056",
    "gn:admin3_code":"305682.0",
    "gn:admin4_code":"30568243.0",
    "gn:asciiname":"Ulail",
    "gn:country_code":"BD",
    "gn:dem":10,
    "gn:feature_class":"P",
    "gn:feature_code":"PPL",
    "gn:name":"Ul\u0101il",
    "gn:population":0,
    "gn:timezone":"Asia/Dhaka",
    "iso:country":"BD",
    "wof:name":"Ulail",
    "wof:placetype":"locality"
},
  "geometry": {"coordinates":[90.22743,23.82269],"type":"Point"}
}