{
  "type": "Feature",
  "properties": {
    "gn:admin1_code":"87",
    "gn:admin2_code":"5594.0",
    "gn:admin3_code":"559408.0",
    "gn:admin4_code":"55940884.0",
    "gn:asciiname":"Uttarparia",
    "gn:country_code":"BD",
    "gn:dem":62,
    "gn:feature_class":"P",
    "gn:feature_code":"PPL",
    "gn:name":"Uttarparia",
    "gn:population":0,
    "gn:timezone":"Asia/Dhaka",
    "iso:country":"BD",
    "name:ben_x_preferred":[
        "Uttarparia"
    ],
    "wof:name":"Uttarparia",
    "wof:placetype":"locality"
},
  "geometry": {"coordinates":[88.26213,26.18455],"type":"Point"}
}