{
  "type": "Feature",
  "properties": {
    "gn:admin1_code":"84",
    "gn:admin2_code":"2013",
    "gn:admin3_code":"201358.0",
    "gn:admin4_code":"20135823.0",
    "gn:asciiname":"Taltali",
    "gn:country_code":"BD",
    "gn:dem":13,
    "gn:feature_class":"P",
    "gn:feature_code":"PPL",
    "gn:name":"T\u0101ltali",
    "gn:population":0,
    "gn:timezone":"Asia/Dhaka",
    "iso:country":"BD",
    "wof:name":"Taltali",
    "wof:placetype":"locality"
},
  "geometry": {"coordinates":[90.94834,23.32869],"type":"Point"}
}