{
  "type": "Feature",
  "properties": {
    "gn:admin1_code":"82",
    "gn:admin2_code":"4047",
    "gn:admin3_code":"404753.0",
    "gn:admin4_code":"40475311.0",
    "gn:asciiname":"Talbaria",
    "gn:country_code":"BD",
    "gn:dem":4,
    "gn:feature_class":"P",
    "gn:feature_code":"PPL",
    "gn:name":"T\u0101lb\u0101ria",
    "gn:population":0,
    "gn:timezone":"Asia/Dhaka",
    "iso:country":"BD",
    "name:ben_x_preferred":[
        "T\u0101lb\u0101ria"
    ],
    "name:ben_x_variant":[
        "T\u0101lberia"
    ],
    "wof:name":"Talbaria",
    "wof:placetype":"locality"
},
  "geometry": {"coordinates":[89.29926999999998,22.42012],"type":"Point"}
}