{
  "type": "Feature",
  "properties": {
    "gn:admin1_code":"83",
    "gn:admin2_code":"5010",
    "gn:admin3_code":"501020.0",
    "gn:admin4_code":"50102077.0",
    "gn:asciiname":"Rabibaria",
    "gn:country_code":"BD",
    "gn:dem":18,
    "gn:feature_class":"P",
    "gn:feature_code":"PPL",
    "gn:name":"Rabib\u0101ria",
    "gn:population":0,
    "gn:timezone":"Asia/Dhaka",
    "iso:country":"BD",
    "wof:name":"Rabibaria",
    "wof:placetype":"locality"
},
  "geometry": {"coordinates":[89.39208000000001,24.84032],"type":"Point"}
}