{
  "type": "Feature",
  "properties": {
    "gn:admin1_code":"82",
    "gn:admin2_code":"4047.0",
    "gn:admin3_code":"404753.0",
    "gn:admin4_code":"40475305.0",
    "gn:asciiname":"Dasbaria",
    "gn:country_code":"BD",
    "gn:dem":5,
    "gn:feature_class":"P",
    "gn:feature_code":"PPL",
    "gn:name":"Dasb\u0101ria",
    "gn:population":0,
    "gn:timezone":"Asia/Dhaka",
    "iso:country":"BD",
    "name:ben_x_preferred":[
        "Dasb\u0101ria"
    ],
    "wof:name":"Dasbaria",
    "wof:placetype":"locality"
},
  "geometry": {"coordinates":[89.30417,22.47757],"type":"Point"}
}