{
  "type": "Feature",
  "properties": {
    "gn:admin1_code":"82",
    "gn:asciiname":"Madhyambati",
    "gn:country_code":"BD",
    "gn:dem":7,
    "gn:feature_class":"P",
    "gn:feature_code":"PPL",
    "gn:name":"Madhyambati",
    "gn:population":0,
    "gn:timezone":"Asia/Dhaka",
    "iso:country":"BD",
    "name:ben_x_preferred":[
        "Madhyambati"
    ],
    "wof:name":"Madhyambati",
    "wof:placetype":"locality"
},
  "geometry": {"coordinates":[90.29691,22.48326],"type":"Point"}
}