{
  "type": "Feature",
  "properties": {
    "gn:admin1_code":"83",
    "gn:admin2_code":"5010",
    "gn:admin3_code":"501094.0",
    "gn:admin4_code":"50109487.0",
    "gn:asciiname":"Kuki ozit",
    "gn:country_code":"BD",
    "gn:dem":24,
    "gn:feature_class":"P",
    "gn:feature_code":"PPL",
    "gn:name":"Kuki ozit",
    "gn:population":0,
    "gn:timezone":"Asia/Dhaka",
    "iso:country":"BD",
    "name:ben_x_preferred":[
        "Kuki ozit"
    ],
    "wof:name":"Kuki ozit",
    "wof:placetype":"locality"
},
  "geometry": {"coordinates":[89.44794,25.05978],"type":"Point"}
}