{
  "type": "Feature",
  "properties": {
    "gn:admin1_code":"82",
    "gn:admin2_code":"4050.0",
    "gn:admin3_code":"405079.0",
    "gn:admin4_code":"40507909.0",
    "gn:asciiname":"Pearpur",
    "gn:country_code":"BD",
    "gn:dem":20,
    "gn:feature_class":"P",
    "gn:feature_code":"PPL",
    "gn:name":"Pearpur",
    "gn:population":0,
    "gn:timezone":"Asia/Dhaka",
    "iso:country":"BD",
    "name:ben_x_preferred":[
        "Pearpur"
    ],
    "wof:name":"Pearpur",
    "wof:placetype":"locality"
},
  "geometry": {"coordinates":[89.11759000000001,23.71173],"type":"Point"}
}