{
  "type": "Feature",
  "properties": {
    "gn:admin1_code":"87",
    "gn:admin2_code":"5594.0",
    "gn:admin3_code":"559486.0",
    "gn:admin4_code":"55948631.0",
    "gn:asciiname":"Pamol",
    "gn:country_code":"BD",
    "gn:dem":47,
    "gn:feature_class":"P",
    "gn:feature_code":"PPL",
    "gn:name":"P\u0101mol",
    "gn:population":0,
    "gn:timezone":"Asia/Dhaka",
    "iso:country":"BD",
    "name:ben_x_preferred":[
        "P\u0101mol"
    ],
    "name:guj_x_preferred":[
        "\u0aaa\u0aae\u0acb\u0ab2"
    ],
    "wof:name":"Pamol",
    "wof:placetype":"locality"
},
  "geometry": {"coordinates":[88.16077,26.00226],"type":"Point"}
}