{
  "type": "Feature",
  "properties": {
    "gn:admin1_code":"82",
    "gn:admin2_code":"4001.0",
    "gn:admin3_code":"400160.0",
    "gn:admin4_code":"40016053.0",
    "gn:asciiname":"Dakshin Phulhata",
    "gn:country_code":"BD",
    "gn:dem":4,
    "gn:feature_class":"P",
    "gn:feature_code":"PPL",
    "gn:name":"Dakshin Phulhata",
    "gn:population":0,
    "gn:timezone":"Asia/Dhaka",
    "iso:country":"BD",
    "name:ben_x_preferred":[
        "Dakshin Phulhata"
    ],
    "wof:name":"Dakshin Phulhata",
    "wof:placetype":"locality"
},
  "geometry": {"coordinates":[89.75247,22.46805],"type":"Point"}
}