{
  "type": "Feature",
  "properties": {
    "gn:admin1_code":"83",
    "gn:admin2_code":"5081.0",
    "gn:admin3_code":"508110.0",
    "gn:admin4_code":"50811055.0",
    "gn:asciiname":"Arazi Chandpur",
    "gn:country_code":"BD",
    "gn:dem":18,
    "gn:feature_class":"P",
    "gn:feature_code":"PPL",
    "gn:name":"\u0100r\u0101zi Ch\u0101ndpur",
    "gn:population":0,
    "gn:timezone":"Asia/Dhaka",
    "iso:country":"BD",
    "name:ben_x_preferred":[
        "\u0100r\u0101zi Ch\u0101ndpur"
    ],
    "wof:name":"Arazi Chandpur",
    "wof:placetype":"locality"
},
  "geometry": {"coordinates":[88.88188000000002,24.16094],"type":"Point"}
}