{
  "type": "Feature",
  "properties": {
    "gn:admin1_code":"82",
    "gn:admin2_code":"4041.0",
    "gn:admin3_code":"404109.0",
    "gn:admin4_code":"40410909.0",
    "gn:asciiname":"Aladipur",
    "gn:country_code":"BD",
    "gn:dem":12,
    "gn:feature_class":"P",
    "gn:feature_code":"PPL",
    "gn:name":"Al\u0101dipur",
    "gn:population":0,
    "gn:timezone":"Asia/Dhaka",
    "iso:country":"BD",
    "name:ben_x_preferred":[
        "Al\u0101dipur"
    ],
    "wof:name":"Aladipur",
    "wof:placetype":"locality"
},
  "geometry": {"coordinates":[89.37158000000002,23.13958],"type":"Point"}
}