{
  "type": "Feature",
  "properties": {
    "gn:admin1_code":"81",
    "gn:admin2_code":"3056",
    "gn:admin3_code":"305628.0",
    "gn:admin4_code":"30562836.0",
    "gn:asciiname":"Lauta",
    "gn:country_code":"BD",
    "gn:dem":10,
    "gn:feature_class":"P",
    "gn:feature_code":"PPL",
    "gn:name":"L\u0101uta",
    "gn:population":0,
    "gn:timezone":"Asia/Dhaka",
    "iso:country":"BD",
    "name:ara_x_preferred":[
        "\u0644\u0627\u0648\u062a\u0627"
    ],
    "name:azb_x_preferred":[
        "\u0644\u0627\u0648\u062a\u0627"
    ],
    "name:bak_x_preferred":[
        "\u041b\u0430\u0443\u0442\u0430"
    ],
    "name:bul_x_preferred":[
        "\u041b\u0430\u0443\u0442\u0430"
    ],
    "name:cat_x_preferred":[
        "Lauta"
    ],
    "name:deu_x_preferred":[
        "Lauta"
    ],
    "name:epo_x_preferred":[
        "Lauta"
    ],
    "name:est_x_preferred":[
        "Lauta"
    ],
    "name:fas_x_preferred":[
        "\u0644\u0627\u0648\u062a\u0627"
    ],
    "name:fra_x_preferred":[
        "Lauta"
    ],
    "name:hsb_x_preferred":[
        "\u0141uty"
    ],
    "name:hun_x_preferred":[
        "Lauta"
    ],
    "name:ita_x_preferred":[
        "Lauta"
    ],
    "name:lav_x_preferred":[
        "Lauta"
    ],
    "name:mkd_x_preferred":[
        "\u041b\u0430\u0443\u0442\u0430"
    ],
    "name:msa_x_preferred":[
        "Lauta"
    ],
    "name:nld_x_preferred":[
        "Lauta"
    ],
    "name:pol_x_preferred":[
        "Lauta"
    ],
    "name:por_x_preferred":[
        "Lauta"
    ],
    "name:ron_x_preferred":[
        "Lauta"
    ],
    "name:rus_x_preferred":[
        "\u041b\u0430\u0443\u0442\u0430"
    ],
    "name:spa_x_preferred":[
        "Lauta"
    ],
    "name:srp_x_preferred":[
        "\u041b\u0430\u0443\u0442\u0430"
    ],
    "name:tur_x_preferred":[
        "Lauta"
    ],
    "name:ukr_x_preferred":[
        "\u041b\u0430\u0443\u0442\u0430"
    ],
    "name:uzb_x_preferred":[
        "Lauta"
    ],
    "name:vol_x_preferred":[
        "Lauta"
    ],
    "name:war_x_preferred":[
        "Lauta"
    ],
    "wof:name":"Lauta",
    "wof:placetype":"locality"
},
  "geometry": {"coordinates":[89.96054000000002,23.76061],"type":"Point"}
}