{
  "type": "Feature",
  "properties": {
    "gn:admin1_code":"82",
    "gn:admin2_code":"4044.0",
    "gn:admin3_code":"404480.0",
    "gn:admin4_code":"40448031.0",
    "gn:asciiname":"Phalia",
    "gn:country_code":"BD",
    "gn:dem":15,
    "gn:feature_class":"P",
    "gn:feature_code":"PPL",
    "gn:name":"Phalia",
    "gn:population":0,
    "gn:timezone":"Asia/Dhaka",
    "iso:country":"BD",
    "name:ben_x_preferred":[
        "Phalia"
    ],
    "name:ceb_x_preferred":[
        "Ph\u0101lia"
    ],
    "name:fas_x_preferred":[
        "\u062a\u062d\u0635\u06cc\u0644 \u067e\u0647\u0627\u0644\u06cc\u0647"
    ],
    "name:fra_x_preferred":[
        "Phalia"
    ],
    "name:pnb_x_preferred":[
        "\u0641\u0627\u0644\u06cc\u0627"
    ],
    "name:por_x_preferred":[
        "Phalia"
    ],
    "name:urd_x_preferred":[
        "\u067e\u06be\u0627\u0644\u06cc\u06c1"
    ],
    "wof:name":"Phalia",
    "wof:placetype":"locality"
},
  "geometry": {"coordinates":[89.22856999999998,23.59061],"type":"Point"}
}