{
  "type": "Feature",
  "properties": {
    "gn:admin1_code":"84",
    "gn:admin2_code":"2015.0",
    "gn:admin3_code":"201547.0",
    "gn:admin4_code":"20154743.0",
    "gn:asciiname":"Gourimandra Hati",
    "gn:country_code":"BD",
    "gn:dem":27,
    "gn:feature_class":"P",
    "gn:feature_code":"PPL",
    "gn:name":"Gourimandra H\u0101ti",
    "gn:population":0,
    "gn:timezone":"Asia/Dhaka",
    "iso:country":"BD",
    "name:ben_x_preferred":[
        "Gourimandra H\u0101ti"
    ],
    "name:ben_x_variant":[
        "Gourimanda H\u0101ti"
    ],
    "wof:name":"Gourimandra Hati",
    "wof:placetype":"locality"
},
  "geometry": {"coordinates":[92.12379,21.99832],"type":"Point"}
}