{
  "type": "Feature",
  "properties": {
    "gn:admin1_code":"82",
    "gn:admin2_code":"4065.0",
    "gn:admin3_code":"406576.0",
    "gn:admin4_code":"40657600.0",
    "gn:asciiname":"Allaypur",
    "gn:country_code":"BD",
    "gn:dem":11,
    "gn:feature_class":"P",
    "gn:feature_code":"PPL",
    "gn:name":"Allaypur",
    "gn:population":0,
    "gn:timezone":"Asia/Dhaka",
    "iso:country":"BD",
    "name:ben_x_preferred":[
        "Allaypur"
    ],
    "wof:name":"Allaypur",
    "wof:placetype":"locality"
},
  "geometry": {"coordinates":[89.50848000000001,23.12678],"type":"Point"}
}