{
  "type": "Feature",
  "properties": {
    "gn:admin1_code":"H",
    "gn:admin2_code":"3039",
    "gn:admin3_code":"303936.0",
    "gn:admin4_code":"30393653.0",
    "gn:asciiname":"Sri Chandabari",
    "gn:country_code":"BD",
    "gn:dem":22,
    "gn:feature_class":"P",
    "gn:feature_code":"PPL",
    "gn:name":"Sri Chandab\u0101ri",
    "gn:population":0,
    "gn:timezone":"Asia/Dhaka",
    "iso:country":"BD",
    "wof:name":"Sri Chandabari",
    "wof:placetype":"locality"
},
  "geometry": {"coordinates":[90.14172000000001,24.86853],"type":"Point"}
}