{
  "type": "Feature",
  "properties": {
    "gn:admin1_code":"83",
    "gn:admin2_code":"5081.0",
    "gn:admin3_code":"508134.0",
    "gn:admin4_code":"50813428.0",
    "gn:asciiname":"Bikarpara",
    "gn:country_code":"BD",
    "gn:dem":26,
    "gn:feature_class":"P",
    "gn:feature_code":"PPL",
    "gn:name":"Bikarpara",
    "gn:population":0,
    "gn:timezone":"Asia/Dhaka",
    "iso:country":"BD",
    "name:ben_x_preferred":[
        "Bikarpara"
    ],
    "wof:name":"Bikarpara",
    "wof:placetype":"locality"
},
  "geometry": {"coordinates":[88.46276999999998,24.40471],"type":"Point"}
}