{
  "type": "Feature",
  "properties": {
    "gn:admin1_code":"87",
    "gn:admin2_code":"5549",
    "gn:admin3_code":"554994.0",
    "gn:admin4_code":"55499455.0",
    "gn:asciiname":"Sadua Damarhat",
    "gn:country_code":"BD",
    "gn:dem":28,
    "gn:feature_class":"P",
    "gn:feature_code":"PPL",
    "gn:name":"Sadua D\u0101m\u0101rh\u0101t",
    "gn:population":0,
    "gn:timezone":"Asia/Dhaka",
    "iso:country":"BD",
    "name:ben_x_preferred":[
        "Sadua D\u0101m\u0101rh\u0101t"
    ],
    "wof:name":"Sadua Damarhat",
    "wof:placetype":"locality"
},
  "geometry": {"coordinates":[89.58383000000001,25.61036],"type":"Point"}
}