{
  "type": "Feature",
  "properties": {
    "gn:admin1_code":"83",
    "gn:admin2_code":"5081.0",
    "gn:admin3_code":"508182.0",
    "gn:admin4_code":"50818213.0",
    "gn:asciiname":"Durgapur",
    "gn:country_code":"BD",
    "gn:dem":20,
    "gn:feature_class":"P",
    "gn:feature_code":"PPL",
    "gn:name":"Durg\u0101pur",
    "gn:population":0,
    "gn:timezone":"Asia/Dhaka",
    "iso:country":"BD",
    "name:ben_x_preferred":[
        "Durg\u0101pur"
    ],
    "wof:name":"Durgapur",
    "wof:placetype":"locality"
},
  "geometry": {"coordinates":[88.78499000000002,24.38862],"type":"Point"}
}