{
  "type": "Feature",
  "properties": {
    "gn:admin1_code":"83",
    "gn:admin2_code":"5070.0",
    "gn:admin3_code":"507088.0",
    "gn:admin4_code":"50708800.0",
    "gn:asciiname":"Dewan Jaygir",
    "gn:country_code":"BD",
    "gn:dem":29,
    "gn:feature_class":"P",
    "gn:feature_code":"PPL",
    "gn:name":"Dewan Jaygir",
    "gn:population":0,
    "gn:timezone":"Asia/Dhaka",
    "iso:country":"BD",
    "name:ben_x_preferred":[
        "Dewan Jaygir"
    ],
    "wof:name":"Dewan Jaygir",
    "wof:placetype":"locality"
},
  "geometry": {"coordinates":[88.16318000000003,24.68767],"type":"Point"}
}