{
  "type": "Feature",
  "properties": {
    "gn:admin1_code":"85",
    "gn:admin2_code":"1042.0",
    "gn:admin3_code":"104284.0",
    "gn:admin4_code":"10428481.0",
    "gn:asciiname":"Bamankhan",
    "gn:country_code":"BD",
    "gn:dem":10,
    "gn:feature_class":"P",
    "gn:feature_code":"PPL",
    "gn:name":"B\u0101mankh\u0101n",
    "gn:population":0,
    "gn:timezone":"Asia/Dhaka",
    "iso:country":"BD",
    "wof:name":"Bamankhan",
    "wof:placetype":"locality"
},
  "geometry": {"coordinates":[90.15554,22.5962],"type":"Point"}
}