{
  "type": "Feature",
  "properties": {
    "gn:admin1_code":"85",
    "gn:admin2_code":"1078.0",
    "gn:admin3_code":"107852.0",
    "gn:admin4_code":"10785252.0",
    "gn:asciiname":"Lakshmipur",
    "gn:country_code":"BD",
    "gn:dem":7,
    "gn:feature_class":"P",
    "gn:feature_code":"PPL",
    "gn:name":"Lakshmipur",
    "gn:population":0,
    "gn:timezone":"Asia/Dhaka",
    "iso:country":"BD",
    "name:ben_x_preferred":[
        "Lakshmipur"
    ],
    "name:ceb_x_preferred":[
        "Lakshmipur"
    ],
    "name:fra_x_preferred":[
        "Lakshmipur"
    ],
    "name:swe_x_preferred":[
        "Lakshmipur"
    ],
    "wof:name":"Lakshmipur",
    "wof:placetype":"locality"
},
  "geometry": {"coordinates":[90.54761999999999,22.27204],"type":"Point"}
}