{
  "type": "Feature",
  "properties": {
    "gn:admin1_code":"87",
    "gn:admin2_code":"5573",
    "gn:admin3_code":"557345.0",
    "gn:admin4_code":"55734594.0",
    "gn:asciiname":"Ronachandi",
    "gn:country_code":"BD",
    "gn:dem":47,
    "gn:feature_class":"P",
    "gn:feature_code":"PPL",
    "gn:name":"Ronachandi",
    "gn:population":0,
    "gn:timezone":"Asia/Dhaka",
    "iso:country":"BD",
    "name:ben_x_preferred":[
        "Ronachandi"
    ],
    "name:ben_x_variant":[
        "R\u0101n\u0101chandi"
    ],
    "wof:name":"Ronachandi",
    "wof:placetype":"locality"
},
  "geometry": {"coordinates":[89.05173000000001,25.92339],"type":"Point"}
}