{
  "type": "Feature",
  "properties": {
    "gn:admin1_code":"87",
    "gn:admin2_code":"5527",
    "gn:admin3_code":"552710.0",
    "gn:admin4_code":"55271071.0",
    "gn:asciiname":"Dighalchand",
    "gn:country_code":"BD",
    "gn:dem":33,
    "gn:feature_class":"P",
    "gn:feature_code":"PPL",
    "gn:name":"Dighalchand",
    "gn:population":0,
    "gn:timezone":"Asia/Dhaka",
    "iso:country":"BD",
    "name:ben_x_preferred":[
        "Dighalchand"
    ],
    "wof:name":"Dighalchand",
    "wof:placetype":"locality"
},
  "geometry": {"coordinates":[89.0155,25.45165],"type":"Point"}
}