{
  "type": "Feature",
  "properties": {
    "gn:admin1_code":"82",
    "gn:asciiname":"Madhyam Sonakhali",
    "gn:country_code":"BD",
    "gn:dem":8,
    "gn:feature_class":"P",
    "gn:feature_code":"PPL",
    "gn:name":"Madhyam Sonakhali",
    "gn:population":0,
    "gn:timezone":"Asia/Dhaka",
    "iso:country":"BD",
    "name:ben_x_preferred":[
        "Madhyam Sonakhali"
    ],
    "wof:name":"Madhyam Sonakhali",
    "wof:placetype":"locality"
},
  "geometry": {"coordinates":[89.94781999999999,22.24405],"type":"Point"}
}