{
  "type": "Feature",
  "properties": {
    "gn:admin1_code":"87",
    "gn:admin2_code":"5532.0",
    "gn:admin3_code":"553230.0",
    "gn:admin4_code":"55323061.0",
    "gn:asciiname":"Baratta",
    "gn:country_code":"BD",
    "gn:dem":25,
    "gn:feature_class":"P",
    "gn:feature_code":"PPL",
    "gn:name":"Baratta",
    "gn:population":0,
    "gn:timezone":"Asia/Dhaka",
    "iso:country":"BD",
    "wof:name":"Baratta",
    "wof:placetype":"locality"
},
  "geometry": {"coordinates":[89.25,25.13333],"type":"Point"}
}