{
  "type": "Feature",
  "properties": {
    "gn:admin1_code":"81",
    "gn:admin2_code":"3026.0",
    "gn:admin3_code":"302662.0",
    "gn:admin4_code":"30266261.0",
    "gn:asciiname":"Bamuahati",
    "gn:country_code":"BD",
    "gn:dem":12,
    "gn:feature_class":"P",
    "gn:feature_code":"PPL",
    "gn:name":"B\u0101mu\u0101h\u0101ti",
    "gn:population":0,
    "gn:timezone":"Asia/Dhaka",
    "iso:country":"BD",
    "wof:name":"Bamuahati",
    "wof:placetype":"locality"
},
  "geometry": {"coordinates":[90.05091,23.674],"type":"Point"}
}