{
  "type": "Feature",
  "properties": {
    "gn:admin1_code":"84",
    "gn:admin2_code":"2015.0",
    "gn:admin3_code":"201561.0",
    "gn:admin4_code":"20156176.0",
    "gn:asciiname":"Binanihara",
    "gn:country_code":"BD",
    "gn:dem":9,
    "gn:feature_class":"P",
    "gn:feature_code":"PPL",
    "gn:name":"Bin\u0101nihara",
    "gn:population":0,
    "gn:timezone":"Asia/Dhaka",
    "iso:country":"BD",
    "name:ben_x_preferred":[
        "Bin\u0101nihara"
    ],
    "wof:name":"Binanihara",
    "wof:placetype":"locality"
},
  "geometry": {"coordinates":[91.89725,22.30636],"type":"Point"}
}