{
  "type": "Feature",
  "properties": {
    "gn:admin1_code":"87",
    "gn:admin2_code":"5527",
    "gn:admin3_code":"552743.0",
    "gn:admin4_code":"55274319.0",
    "gn:asciiname":"Salikaduha",
    "gn:country_code":"BD",
    "gn:dem":32,
    "gn:feature_class":"P",
    "gn:feature_code":"PPL",
    "gn:name":"Salikaduha",
    "gn:population":0,
    "gn:timezone":"Asia/Dhaka",
    "iso:country":"BD",
    "name:und_x_variant":[
        "S\u0101lik\u0101daha"
    ],
    "wof:name":"Salikaduha",
    "wof:placetype":"locality"
},
  "geometry": {"coordinates":[89.21711999999999,25.36571],"type":"Point"}
}