{
  "type": "Feature",
  "properties": {
    "gn:admin1_code":"81",
    "gn:admin2_code":"3093.0",
    "gn:admin3_code":"309366.0",
    "gn:admin4_code":"30936634.0",
    "gn:asciiname":"Bastail",
    "gn:country_code":"BD",
    "gn:dem":21,
    "gn:feature_class":"P",
    "gn:feature_code":"PPL",
    "gn:name":"B\u0101stail",
    "gn:population":0,
    "gn:timezone":"Asia/Dhaka",
    "iso:country":"BD",
    "wof:name":"Bastail",
    "wof:placetype":"locality"
},
  "geometry": {"coordinates":[90.17039,24.16951],"type":"Point"}
}