{
  "type": "Feature",
  "properties": {
    "gn:admin1_code":"87",
    "gn:admin2_code":"5577.0",
    "gn:admin3_code":"557790.0",
    "gn:admin4_code":"55779094.0",
    "gn:asciiname":"Bakshipara",
    "gn:country_code":"BD",
    "gn:dem":101,
    "gn:feature_class":"P",
    "gn:feature_code":"PPL",
    "gn:name":"Bakship\u0101ra",
    "gn:population":0,
    "gn:timezone":"Asia/Dhaka",
    "iso:country":"BD",
    "name:ben_x_preferred":[
        "Bakship\u0101ra"
    ],
    "wof:name":"Bakshipara",
    "wof:placetype":"locality"
},
  "geometry": {"coordinates":[88.40805999999998,26.542],"type":"Point"}
}