{
  "type": "Feature",
  "properties": {
    "gn:admin1_code":"87",
    "gn:admin2_code":"5552.0",
    "gn:admin3_code":"555270.0",
    "gn:admin4_code":"55527019.0",
    "gn:asciiname":"Diabari",
    "gn:country_code":"BD",
    "gn:dem":67,
    "gn:feature_class":"P",
    "gn:feature_code":"PPL",
    "gn:name":"Diabari",
    "gn:population":0,
    "gn:timezone":"Asia/Dhaka",
    "iso:country":"BD",
    "name:ben_x_preferred":[
        "Diabari"
    ],
    "wof:name":"Diabari",
    "wof:placetype":"locality"
},
  "geometry": {"coordinates":[88.92596999999998,26.32402],"type":"Point"}
}