{
  "type": "Feature",
  "properties": {
    "gn:admin1_code":"87",
    "gn:admin2_code":"5577.0",
    "gn:admin3_code":"557773.0",
    "gn:admin4_code":"55777371.0",
    "gn:asciiname":"Dudumari",
    "gn:country_code":"BD",
    "gn:dem":75,
    "gn:feature_class":"P",
    "gn:feature_code":"PPL",
    "gn:name":"Dudum\u0101ri",
    "gn:population":0,
    "gn:timezone":"Asia/Dhaka",
    "iso:country":"BD",
    "name:ben_x_preferred":[
        "Dudum\u0101ri"
    ],
    "wof:name":"Dudumari",
    "wof:placetype":"locality"
},
  "geometry": {"coordinates":[88.58289000000001,26.38604],"type":"Point"}
}