{
  "type": "Feature",
  "properties": {
    "gn:admin1_code":"81",
    "gn:admin2_code":"3093",
    "gn:admin3_code":"309376.0",
    "gn:admin4_code":"30937621.0",
    "gn:asciiname":"Sarutia Gazi",
    "gn:country_code":"BD",
    "gn:dem":14,
    "gn:feature_class":"P",
    "gn:feature_code":"PPL",
    "gn:name":"S\u0101rutia G\u0101zi",
    "gn:population":0,
    "gn:timezone":"Asia/Dhaka",
    "iso:country":"BD",
    "name:und_x_variant":[
        "S\u0101rutia G\u0101zi",
        "S\u0101ratia G\u0101zi"
    ],
    "wof:name":"Sarutia Gazi",
    "wof:placetype":"locality"
},
  "geometry": {"coordinates":[89.83199,23.98194],"type":"Point"}
}