{
  "type": "Feature",
  "properties": {
    "gn:admin1_code":"81",
    "gn:admin2_code":"3082",
    "gn:admin3_code":"308273.0",
    "gn:admin4_code":"30827330.0",
    "gn:asciiname":"Jhaugram",
    "gn:country_code":"BD",
    "gn:dem":15,
    "gn:feature_class":"P",
    "gn:feature_code":"PPL",
    "gn:name":"Jh\u0101ugr\u0101m",
    "gn:population":0,
    "gn:timezone":"Asia/Dhaka",
    "iso:country":"BD",
    "wof:name":"Jhaugram",
    "wof:placetype":"locality"
},
  "geometry": {"coordinates":[89.45489999999999,23.78776],"type":"Point"}
}