{
  "type": "Feature",
  "properties": {
    "gn:admin1_code":"84",
    "gn:admin2_code":"2015.0",
    "gn:admin3_code":"201570.0",
    "gn:admin4_code":"20157043.0",
    "gn:asciiname":"Paschim Khursia",
    "gn:country_code":"BD",
    "gn:dem":38,
    "gn:feature_class":"P",
    "gn:feature_code":"PPL",
    "gn:name":"Paschim Khursia",
    "gn:population":0,
    "gn:timezone":"Asia/Dhaka",
    "iso:country":"BD",
    "name:ben_x_preferred":[
        "Paschim Khursia"
    ],
    "wof:name":"Paschim Khursia",
    "wof:placetype":"locality"
},
  "geometry": {"coordinates":[92.08378,22.34073],"type":"Point"}
}