{
  "type": "Feature",
  "properties": {
    "gn:admin1_code":"83",
    "gn:admin2_code":"5038.0",
    "gn:admin3_code":"503858.0",
    "gn:admin4_code":"50385866.0",
    "gn:asciiname":"Chhatragram",
    "gn:country_code":"BD",
    "gn:dem":27,
    "gn:feature_class":"P",
    "gn:feature_code":"PPL",
    "gn:name":"Chhatragr\u0101m",
    "gn:population":0,
    "gn:timezone":"Asia/Dhaka",
    "iso:country":"BD",
    "name:ben_x_preferred":[
        "Chhatragr\u0101m"
    ],
    "wof:name":"Chhatragram",
    "wof:placetype":"locality"
},
  "geometry": {"coordinates":[89.21548,25.1364],"type":"Point"}
}