{
  "type": "Feature",
  "properties": {
    "gn:admin1_code":"83",
    "gn:admin2_code":"5081.0",
    "gn:admin3_code":"508110.0",
    "gn:admin4_code":"50811015.0",
    "gn:asciiname":"Bara Chhaighati",
    "gn:country_code":"BD",
    "gn:dem":23,
    "gn:feature_class":"P",
    "gn:feature_code":"PPL",
    "gn:name":"Bara Chhaighati",
    "gn:population":0,
    "gn:timezone":"Asia/Dhaka",
    "iso:country":"BD",
    "name:ben_x_preferred":[
        "Bara Chhaighati"
    ],
    "name:und_x_variant":[
        "Bara Chhaighti"
    ],
    "wof:name":"Bara Chhaighati",
    "wof:placetype":"locality"
},
  "geometry": {"coordinates":[88.86554,24.19475],"type":"Point"}
}