{
  "type": "Feature",
  "properties": {
    "gn:admin1_code":"87",
    "gn:admin2_code":"5532",
    "gn:admin3_code":"553230.0",
    "gn:admin4_code":"55323094.0",
    "gn:asciiname":"Chheta Narichagari",
    "gn:country_code":"BD",
    "gn:dem":25,
    "gn:feature_class":"P",
    "gn:feature_code":"PPL",
    "gn:name":"Chheta Narich\u0101g\u0101ri",
    "gn:population":0,
    "gn:timezone":"Asia/Dhaka",
    "iso:country":"BD",
    "name:ben_x_preferred":[
        "Chheta Narich\u0101g\u0101ri"
    ],
    "wof:name":"Chheta Narichagari",
    "wof:placetype":"locality"
},
  "geometry": {"coordinates":[89.38539,25.22471],"type":"Point"}
}