{
  "type": "Feature",
  "properties": {
    "gn:admin1_code":"81",
    "gn:admin2_code":"3067",
    "gn:admin3_code":"306706.0",
    "gn:admin4_code":"30670679.0",
    "gn:asciiname":"Lambadardi",
    "gn:country_code":"BD",
    "gn:dem":8,
    "gn:feature_class":"P",
    "gn:feature_code":"PPL",
    "gn:name":"Lamb\u0101dardi",
    "gn:population":0,
    "gn:timezone":"Asia/Dhaka",
    "iso:country":"BD",
    "wof:name":"Lambadardi",
    "wof:placetype":"locality"
},
  "geometry": {"coordinates":[90.55,23.63333],"type":"Point"}
}