{
  "type": "Feature",
  "properties": {
    "gn:admin1_code":"82",
    "gn:admin2_code":"4041.0",
    "gn:admin3_code":"404111.0",
    "gn:admin4_code":"40411177.0",
    "gn:asciiname":"Arardaha",
    "gn:country_code":"BD",
    "gn:dem":13,
    "gn:feature_class":"P",
    "gn:feature_code":"PPL",
    "gn:name":"\u0100r\u0101rdaha",
    "gn:population":0,
    "gn:timezone":"Asia/Dhaka",
    "iso:country":"BD",
    "name:ben_x_preferred":[
        "\u0100r\u0101rdaha"
    ],
    "name:und_x_variant":[
        "Aradaha"
    ],
    "wof:name":"Arardaha",
    "wof:placetype":"locality"
},
  "geometry": {"coordinates":[89.09647,23.24343],"type":"Point"}
}