{
  "type": "Feature",
  "properties": {
    "gn:admin1_code":"83",
    "gn:admin2_code":"5064.0",
    "gn:admin3_code":"506428.0",
    "gn:admin4_code":"50642810.0",
    "gn:asciiname":"Talandar",
    "gn:country_code":"BD",
    "gn:dem":27,
    "gn:feature_class":"P",
    "gn:feature_code":"PPL",
    "gn:name":"T\u0101l\u0101ndar",
    "gn:population":0,
    "gn:timezone":"Asia/Dhaka",
    "iso:country":"BD",
    "name:ben_x_preferred":[
        "T\u0101l\u0101ndar"
    ],
    "wof:name":"Talandar",
    "wof:placetype":"locality"
},
  "geometry": {"coordinates":[88.70011,25.19798],"type":"Point"}
}