{
  "type": "Feature",
  "properties": {
    "gn:admin1_code":"82",
    "gn:asciiname":"Jamura Kismat",
    "gn:country_code":"BD",
    "gn:dem":9,
    "gn:feature_class":"P",
    "gn:feature_code":"PPL",
    "gn:name":"J\u0101mura Kismat",
    "gn:population":0,
    "gn:timezone":"Asia/Dhaka",
    "iso:country":"BD",
    "name:ben_x_preferred":[
        "J\u0101mura Kismat"
    ],
    "wof:name":"Jamura Kismat",
    "wof:placetype":"locality"
},
  "geometry": {"coordinates":[90.34842999999999,22.39987],"type":"Point"}
}