{
  "type": "Feature",
  "properties": {
    "gn:admin1_code":"85",
    "gn:admin2_code":"1042",
    "gn:admin3_code":"104240.0",
    "gn:admin4_code":"10424038.0",
    "gn:asciiname":"Hosanpur",
    "gn:country_code":"BD",
    "gn:dem":11,
    "gn:feature_class":"P",
    "gn:feature_code":"PPL",
    "gn:name":"Hosanpur",
    "gn:population":0,
    "gn:timezone":"Asia/Dhaka",
    "iso:country":"BD",
    "wof:name":"Hosanpur",
    "wof:placetype":"locality"
},
  "geometry": {"coordinates":[90.22076,22.74779],"type":"Point"}
}