{
  "type": "Feature",
  "properties": {
    "gn:admin1_code":"85",
    "gn:admin2_code":"1078.0",
    "gn:admin3_code":"107838.0",
    "gn:admin4_code":"10783859.0",
    "gn:asciiname":"Bhatsala Char",
    "gn:country_code":"BD",
    "gn:dem":4,
    "gn:feature_class":"P",
    "gn:feature_code":"PPL",
    "gn:name":"Bh\u0101ts\u0101la Char",
    "gn:population":0,
    "gn:timezone":"Asia/Dhaka",
    "iso:country":"BD",
    "wof:name":"Bhatsala Char",
    "wof:placetype":"locality"
},
  "geometry": {"coordinates":[90.51667,22.53333],"type":"Point"}
}