{
  "type": "Feature",
  "properties": {
    "gn:admin1_code":"82",
    "gn:admin2_code":"4041",
    "gn:admin3_code":"404161.0",
    "gn:admin4_code":"40416189.0",
    "gn:asciiname":"Saraskati",
    "gn:country_code":"BD",
    "gn:dem":13,
    "gn:feature_class":"P",
    "gn:feature_code":"PPL",
    "gn:name":"Sarask\u0101ti",
    "gn:population":0,
    "gn:timezone":"Asia/Dhaka",
    "iso:country":"BD",
    "name:ben_x_preferred":[
        "Sarask\u0101ti"
    ],
    "wof:name":"Saraskati",
    "wof:placetype":"locality"
},
  "geometry": {"coordinates":[89.11875000000001,23.06301],"type":"Point"}
}