{
  "type": "Feature",
  "properties": {
    "gn:admin1_code":"85",
    "gn:admin2_code":"1079.0",
    "gn:admin3_code":"107914.0",
    "gn:admin4_code":"10791471.0",
    "gn:asciiname":"Sialkati",
    "gn:country_code":"BD",
    "gn:dem":11,
    "gn:feature_class":"P",
    "gn:feature_code":"PPL",
    "gn:name":"Si\u0101lk\u0101ti",
    "gn:population":0,
    "gn:timezone":"Asia/Dhaka",
    "iso:country":"BD",
    "name:ben_x_preferred":[
        "Si\u0101lk\u0101ti"
    ],
    "wof:name":"Sialkati",
    "wof:placetype":"locality"
},
  "geometry": {"coordinates":[90.05741999999999,22.48771],"type":"Point"}
}