{
  "type": "Feature",
  "properties": {
    "gn:admin1_code":"H",
    "gn:admin2_code":"3061",
    "gn:admin3_code":"306123.0",
    "gn:admin4_code":"30612327.0",
    "gn:asciiname":"Kadim Dowhakhola",
    "gn:country_code":"BD",
    "gn:dem":19,
    "gn:feature_class":"P",
    "gn:feature_code":"PPL",
    "gn:name":"Kadim Dowh\u0101khola",
    "gn:population":0,
    "gn:timezone":"Asia/Dhaka",
    "iso:country":"BD",
    "wof:name":"Kadim Dowhakhola",
    "wof:placetype":"locality"
},
  "geometry": {"coordinates":[90.51528,24.71444],"type":"Point"}
}