{
  "type": "Feature",
  "properties": {
    "gn:admin1_code":"84",
    "gn:admin2_code":"2003.0",
    "gn:admin3_code":"200351.0",
    "gn:admin4_code":"20035147.0",
    "gn:asciiname":"Baishpara",
    "gn:country_code":"BD",
    "gn:dem":40,
    "gn:feature_class":"P",
    "gn:feature_code":"PPL",
    "gn:name":"B\u0101ishp\u0101ra",
    "gn:population":0,
    "gn:timezone":"Asia/Dhaka",
    "iso:country":"BD",
    "name:ben_x_preferred":[
        "B\u0101ishp\u0101ra"
    ],
    "wof:name":"Baishpara",
    "wof:placetype":"locality"
},
  "geometry": {"coordinates":[92.18662,21.86696],"type":"Point"}
}