{
  "type": "Feature",
  "properties": {
    "gn:admin1_code":"81",
    "gn:admin2_code":"3086",
    "gn:admin3_code":"308665.0",
    "gn:admin4_code":"30866518.0",
    "gn:asciiname":"Kandigaon",
    "gn:country_code":"BD",
    "gn:dem":13,
    "gn:feature_class":"P",
    "gn:feature_code":"PPL",
    "gn:name":"K\u0101ndigaon",
    "gn:population":0,
    "gn:timezone":"Asia/Dhaka",
    "iso:country":"BD",
    "wof:name":"Kandigaon",
    "wof:placetype":"locality"
},
  "geometry": {"coordinates":[90.39499000000001,23.22098],"type":"Point"}
}