{
  "type": "Feature",
  "properties": {
    "gn:admin1_code":"84",
    "gn:admin2_code":"2003.0",
    "gn:admin3_code":"200351.0",
    "gn:admin4_code":"20035147.0",
    "gn:asciiname":"Ksheduripara",
    "gn:country_code":"BD",
    "gn:dem":106,
    "gn:feature_class":"P",
    "gn:feature_code":"PPL",
    "gn:name":"Kshedurip\u0101ra",
    "gn:population":0,
    "gn:timezone":"Asia/Dhaka",
    "iso:country":"BD",
    "name:ben_x_preferred":[
        "Kshedurip\u0101ra"
    ],
    "wof:name":"Ksheduripara",
    "wof:placetype":"locality"
},
  "geometry": {"coordinates":[92.14643,21.81462],"type":"Point"}
}