{
  "type": "Feature",
  "properties": {
    "gn:admin1_code":"82",
    "gn:admin2_code":"4050",
    "gn:admin3_code":"405079.0",
    "gn:admin4_code":"40507909.0",
    "gn:asciiname":"Shahanpur",
    "gn:country_code":"BD",
    "gn:dem":15,
    "gn:feature_class":"P",
    "gn:feature_code":"PPL",
    "gn:name":"Sh\u0101h\u0101npur",
    "gn:population":0,
    "gn:timezone":"Asia/Dhaka",
    "iso:country":"BD",
    "name:ben_x_preferred":[
        "Sh\u0101h\u0101npur"
    ],
    "name:ben_x_variant":[
        "Sh\u0101h\u0101pur"
    ],
    "name:und_x_variant":[
        "Sahapur"
    ],
    "wof:name":"Shahanpur",
    "wof:placetype":"locality"
},
  "geometry": {"coordinates":[89.10804,23.75272],"type":"Point"}
}