{
  "type": "Feature",
  "properties": {
    "gn:admin1_code":"82",
    "gn:admin2_code":"4055.0",
    "gn:admin3_code":"405557.0",
    "gn:admin4_code":"40555727.0",
    "gn:asciiname":"Ghoranach",
    "gn:country_code":"BD",
    "gn:dem":12,
    "gn:feature_class":"P",
    "gn:feature_code":"PPL",
    "gn:name":"Ghor\u0101n\u0101ch",
    "gn:population":0,
    "gn:timezone":"Asia/Dhaka",
    "iso:country":"BD",
    "name:ben_x_preferred":[
        "Ghor\u0101n\u0101ch"
    ],
    "wof:name":"Ghoranach",
    "wof:placetype":"locality"
},
  "geometry": {"coordinates":[89.44991999999998,23.42392000000001],"type":"Point"}
}