{
  "type": "Feature",
  "properties": {
    "gn:admin1_code":"85",
    "gn:admin2_code":"1004.0",
    "gn:admin3_code":"100447.0",
    "gn:admin4_code":"10044771.0",
    "gn:asciiname":"Kaialghata",
    "gn:country_code":"BD",
    "gn:dem":8,
    "gn:feature_class":"P",
    "gn:feature_code":"PPL",
    "gn:name":"Kai\u0101lgh\u0101ta",
    "gn:population":0,
    "gn:timezone":"Asia/Dhaka",
    "iso:country":"BD",
    "name:ben_x_preferred":[
        "Kai\u0101lgh\u0101ta"
    ],
    "wof:name":"Kaialghata",
    "wof:placetype":"locality"
},
  "geometry": {"coordinates":[90.1317,22.34569],"type":"Point"}
}