{
  "type": "Feature",
  "properties": {
    "gn:admin1_code":"82",
    "gn:asciiname":"Lohalia Katakhal",
    "gn:country_code":"BD",
    "gn:dem":11,
    "gn:feature_class":"P",
    "gn:feature_code":"PPL",
    "gn:name":"Lohalia Katakh\u0101l",
    "gn:population":0,
    "gn:timezone":"Asia/Dhaka",
    "iso:country":"BD",
    "name:ben_x_preferred":[
        "Lohalia Katakh\u0101l"
    ],
    "wof:name":"Lohalia Katakhal",
    "wof:placetype":"locality"
},
  "geometry": {"coordinates":[90.38341,22.36785],"type":"Point"}
}