{
  "type": "Feature",
  "properties": {
    "gn:admin1_code":"87",
    "gn:admin2_code":"5532",
    "gn:admin3_code":"553267.0",
    "gn:admin4_code":"55326747.0",
    "gn:asciiname":"Bengulia",
    "gn:country_code":"BD",
    "gn:dem":30,
    "gn:feature_class":"P",
    "gn:feature_code":"PPL",
    "gn:name":"Bengulia",
    "gn:population":0,
    "gn:timezone":"Asia/Dhaka",
    "iso:country":"BD",
    "name:ben_x_preferred":[
        "Bengulia"
    ],
    "wof:name":"Bengulia",
    "wof:placetype":"locality"
},
  "geometry": {"coordinates":[89.31497,25.27885],"type":"Point"}
}