{
  "type": "Feature",
  "properties": {
    "gn:admin1_code":"85",
    "gn:admin2_code":"1009.0",
    "gn:admin3_code":"100918.0",
    "gn:admin4_code":"10091887.0",
    "gn:asciiname":"Char Kali",
    "gn:country_code":"BD",
    "gn:dem":7,
    "gn:feature_class":"P",
    "gn:feature_code":"PPL",
    "gn:name":"Char K\u0101li",
    "gn:population":0,
    "gn:timezone":"Asia/Dhaka",
    "iso:country":"BD",
    "wof:name":"Char Kali",
    "wof:placetype":"locality"
},
  "geometry": {"coordinates":[90.60321999999999,22.6612],"type":"Point"}
}