{
  "type": "Feature",
  "properties": {
    "gn:admin1_code":"85",
    "gn:admin2_code":"1079.0",
    "gn:admin3_code":"107988.0",
    "gn:admin4_code":"10798843.0",
    "gn:asciiname":"Togra",
    "gn:country_code":"BD",
    "gn:dem":13,
    "gn:feature_class":"P",
    "gn:feature_code":"PPL",
    "gn:name":"Togra",
    "gn:population":0,
    "gn:timezone":"Asia/Dhaka",
    "iso:country":"BD",
    "name:ben_x_preferred":[
        "Togra"
    ],
    "wof:name":"Togra",
    "wof:placetype":"locality"
},
  "geometry": {"coordinates":[89.97320000000001,22.49365],"type":"Point"}
}