{
  "type": "Feature",
  "properties": {
    "gn:admin1_code":"82",
    "gn:admin2_code":"4047.0",
    "gn:admin3_code":"404794.0",
    "gn:admin4_code":"40479427.0",
    "gn:asciiname":"Kalinagar",
    "gn:country_code":"BD",
    "gn:dem":4,
    "gn:feature_class":"P",
    "gn:feature_code":"PPL",
    "gn:name":"K\u0101linagar",
    "gn:population":0,
    "gn:timezone":"Asia/Dhaka",
    "iso:country":"BD",
    "name:ben_x_preferred":[
        "K\u0101linagar"
    ],
    "wof:name":"Kalinagar",
    "wof:placetype":"locality"
},
  "geometry": {"coordinates":[89.62860000000001,22.89972],"type":"Point"}
}