{
  "type": "Feature",
  "properties": {
    "gn:admin1_code":"82",
    "gn:admin2_code":"4047.0",
    "gn:admin3_code":"404753.0",
    "gn:admin4_code":"40475305.0",
    "gn:asciiname":"Chak Channamara",
    "gn:country_code":"BD",
    "gn:dem":5,
    "gn:feature_class":"P",
    "gn:feature_code":"PPL",
    "gn:name":"Chak Chann\u0101m\u0101ra",
    "gn:population":0,
    "gn:timezone":"Asia/Dhaka",
    "iso:country":"BD",
    "name:ben_x_preferred":[
        "Chak Chann\u0101m\u0101ra"
    ],
    "name:ben_x_variant":[
        "Chak Charn\u0101m\u0101ra"
    ],
    "wof:name":"Chak Channamara",
    "wof:placetype":"locality"
},
  "geometry": {"coordinates":[89.27838,22.49647],"type":"Point"}
}