{
  "type": "Feature",
  "properties": {
    "gn:admin1_code":"85",
    "gn:admin2_code":"1009.0",
    "gn:admin3_code":"100918.0",
    "gn:admin4_code":"10091821.0",
    "gn:asciiname":"Chhota Char Samaia",
    "gn:country_code":"BD",
    "gn:dem":9,
    "gn:feature_class":"P",
    "gn:feature_code":"PPL",
    "gn:name":"Chhota Char Sam\u0101ia",
    "gn:population":0,
    "gn:timezone":"Asia/Dhaka",
    "iso:country":"BD",
    "wof:name":"Chhota Char Samaia",
    "wof:placetype":"locality"
},
  "geometry": {"coordinates":[90.62636000000001,22.6476],"type":"Point"}
}