{
  "type": "Feature",
  "properties": {
    "gn:admin1_code":"83",
    "gn:admin2_code":"5010",
    "gn:admin3_code":"501020.0",
    "gn:admin4_code":"50102069.0",
    "gn:asciiname":"Saralpur",
    "gn:country_code":"BD",
    "gn:dem":23,
    "gn:feature_class":"P",
    "gn:feature_code":"PPL",
    "gn:name":"Saralpur",
    "gn:population":0,
    "gn:timezone":"Asia/Dhaka",
    "iso:country":"BD",
    "wof:name":"Saralpur",
    "wof:placetype":"locality"
},
  "geometry": {"coordinates":[89.31716999999998,24.9425],"type":"Point"}
}