{
  "type": "Feature",
  "properties": {
    "gn:admin1_code":"87",
    "gn:admin2_code":"5573.0",
    "gn:admin3_code":"557315.0",
    "gn:admin4_code":"55731509.0",
    "gn:asciiname":"Bahmania",
    "gn:country_code":"BD",
    "gn:dem":58,
    "gn:feature_class":"P",
    "gn:feature_code":"PPL",
    "gn:name":"B\u0101hmania",
    "gn:population":0,
    "gn:timezone":"Asia/Dhaka",
    "iso:country":"BD",
    "name:ben_x_preferred":[
        "B\u0101hmania"
    ],
    "wof:name":"Bahmania",
    "wof:placetype":"locality"
},
  "geometry": {"coordinates":[88.85927,26.14632000000001],"type":"Point"}
}