{
  "type": "Feature",
  "properties": {
    "gn:admin1_code":"84",
    "gn:admin2_code":"2019.0",
    "gn:admin3_code":"201981.0",
    "gn:admin4_code":"20198176.0",
    "gn:asciiname":"Hirapur",
    "gn:country_code":"BD",
    "gn:dem":11,
    "gn:feature_class":"P",
    "gn:feature_code":"PPL",
    "gn:name":"H\u012br\u0101pur",
    "gn:population":0,
    "gn:timezone":"Asia/Dhaka",
    "iso:country":"BD",
    "wof:name":"Hirapur",
    "wof:placetype":"locality"
},
  "geometry": {"coordinates":[91.04491,23.7186],"type":"Point"}
}