{
  "type": "Feature",
  "properties": {
    "gn:admin1_code":"83",
    "gn:asciiname":"Maklain",
    "gn:country_code":"BD",
    "gn:dem":26,
    "gn:feature_class":"P",
    "gn:feature_code":"PPL",
    "gn:name":"Makl\u0101in",
    "gn:population":0,
    "gn:timezone":"Asia/Dhaka",
    "iso:country":"BD",
    "name:ben_x_preferred":[
        "Makl\u0101in"
    ],
    "wof:name":"Maklain",
    "wof:placetype":"locality"
},
  "geometry": {"coordinates":[89.23983,25.18858],"type":"Point"}
}