{
  "type": "Feature",
  "properties": {
    "gn:admin1_code":"85",
    "gn:admin2_code":"1078.0",
    "gn:admin3_code":"107866.0",
    "gn:admin4_code":"10786635.0",
    "gn:asciiname":"Chhota Panchnambar",
    "gn:country_code":"BD",
    "gn:dem":8,
    "gn:feature_class":"P",
    "gn:feature_code":"PPL",
    "gn:name":"Chhota Panchnambar",
    "gn:population":0,
    "gn:timezone":"Asia/Dhaka",
    "iso:country":"BD",
    "name:ben_x_preferred":[
        "Chhota Panchnambar"
    ],
    "wof:name":"Chhota Panchnambar",
    "wof:placetype":"locality"
},
  "geometry": {"coordinates":[90.27218000000001,21.92779],"type":"Point"}
}