{
  "type": "Feature",
  "properties": {
    "gn:admin1_code":"87",
    "gn:admin2_code":"5594.0",
    "gn:admin3_code":"559494.0",
    "gn:admin4_code":"55949484.0",
    "gn:asciiname":"Kathalgaon",
    "gn:country_code":"BD",
    "gn:dem":65,
    "gn:feature_class":"P",
    "gn:feature_code":"PPL",
    "gn:name":"Kath\u0101lgaon",
    "gn:population":0,
    "gn:timezone":"Asia/Dhaka",
    "iso:country":"BD",
    "name:ben_x_preferred":[
        "Kath\u0101lgaon"
    ],
    "wof:name":"Kathalgaon",
    "wof:placetype":"locality"
},
  "geometry": {"coordinates":[88.38009,26.17531],"type":"Point"}
}