{
  "type": "Feature",
  "properties": {
    "gn:admin1_code":"83",
    "gn:admin2_code":"5038.0",
    "gn:admin3_code":"503858.0",
    "gn:admin4_code":"50385876.0",
    "gn:asciiname":"Garhbalani",
    "gn:country_code":"BD",
    "gn:dem":24,
    "gn:feature_class":"P",
    "gn:feature_code":"PPL",
    "gn:name":"Garhbal\u0101ni",
    "gn:population":0,
    "gn:timezone":"Asia/Dhaka",
    "iso:country":"BD",
    "name:ben_x_preferred":[
        "Garhbal\u0101ni"
    ],
    "wof:name":"Garhbalani",
    "wof:placetype":"locality"
},
  "geometry": {"coordinates":[89.21234,25.05676],"type":"Point"}
}