{
  "type": "Feature",
  "properties": {
    "gn:admin1_code":"81",
    "gn:admin2_code":"3054.0",
    "gn:admin3_code":"305454.0",
    "gn:admin4_code":"30545489.0",
    "gn:asciiname":"Hajrapur",
    "gn:country_code":"BD",
    "gn:dem":11,
    "gn:feature_class":"P",
    "gn:feature_code":"PPL",
    "gn:name":"H\u0101jr\u0101pur",
    "gn:population":0,
    "gn:timezone":"Asia/Dhaka",
    "iso:country":"BD",
    "wof:name":"Hajrapur",
    "wof:placetype":"locality"
},
  "geometry": {"coordinates":[90.17789,23.19106],"type":"Point"}
}