{
  "type": "Feature",
  "properties": {
    "gn:admin1_code":"81",
    "gn:admin2_code":"3068.0",
    "gn:admin3_code":"306860.0",
    "gn:admin4_code":"30686059.0",
    "gn:asciiname":"Balusair",
    "gn:country_code":"BD",
    "gn:dem":10,
    "gn:feature_class":"P",
    "gn:feature_code":"PPL",
    "gn:name":"B\u0101lus\u0101ir",
    "gn:population":0,
    "gn:timezone":"Asia/Dhaka",
    "iso:country":"BD",
    "wof:name":"Balusair",
    "wof:placetype":"locality"
},
  "geometry": {"coordinates":[90.6917,23.87412],"type":"Point"}
}