{
  "type": "Feature",
  "properties": {
    "gn:admin1_code":"81",
    "gn:admin2_code":"3086",
    "gn:admin3_code":"308694.0",
    "gn:admin4_code":"30869429.0",
    "gn:asciiname":"Kabiraj Kandi",
    "gn:country_code":"BD",
    "gn:dem":9,
    "gn:feature_class":"P",
    "gn:feature_code":"PPL",
    "gn:name":"Kabiraj K\u0101ndi",
    "gn:population":0,
    "gn:timezone":"Asia/Dhaka",
    "iso:country":"BD",
    "wof:name":"Kabiraj Kandi",
    "wof:placetype":"locality"
},
  "geometry": {"coordinates":[90.34999999999999,23.33333],"type":"Point"}
}