{
  "type": "Feature",
  "properties": {
    "gn:admin1_code":"84",
    "gn:admin2_code":"2015.0",
    "gn:admin3_code":"201578.0",
    "gn:admin4_code":"20157865.0",
    "gn:asciiname":"Maghdhara Char",
    "gn:country_code":"BD",
    "gn:dem":4,
    "gn:feature_class":"P",
    "gn:feature_code":"PPL",
    "gn:name":"Maghdhara Char",
    "gn:population":0,
    "gn:timezone":"Asia/Dhaka",
    "iso:country":"BD",
    "wof:name":"Maghdhara Char",
    "wof:placetype":"locality"
},
  "geometry": {"coordinates":[91.52833,22.41167],"type":"Point"}
}