{
  "type": "Feature",
  "properties": {
    "gn:admin1_code":"87",
    "gn:admin2_code":"5532",
    "gn:admin3_code":"553221.0",
    "gn:admin4_code":"55322159.0",
    "gn:asciiname":"Chandia",
    "gn:country_code":"BD",
    "gn:dem":25,
    "gn:feature_class":"P",
    "gn:feature_code":"PPL",
    "gn:name":"Chandia",
    "gn:population":0,
    "gn:timezone":"Asia/Dhaka",
    "iso:country":"BD",
    "name:ben_x_preferred":[
        "Chandia"
    ],
    "wof:name":"Chandia",
    "wof:placetype":"locality"
},
  "geometry": {"coordinates":[89.59096,25.3035],"type":"Point"}
}