{
  "type": "Feature",
  "properties": {
    "gn:admin1_code":"84",
    "gn:admin2_code":"2051.0",
    "gn:admin3_code":"205143.0",
    "gn:admin4_code":"20514355.0",
    "gn:asciiname":"Farashganj",
    "gn:country_code":"BD",
    "gn:dem":10,
    "gn:feature_class":"P",
    "gn:feature_code":"PPL",
    "gn:name":"Far\u0101shganj",
    "gn:population":0,
    "gn:timezone":"Asia/Dhaka",
    "iso:country":"BD",
    "name:ara_x_preferred":[
        "\u0641\u0631\u0634\u063a\u0627\u0646\u062c"
    ],
    "name:ben_x_preferred":[
        "\u09ab\u09b0\u09be\u09b6\u0997\u099e\u09cd\u099c"
    ],
    "name:und_x_variant":[
        "Far\u0101shganj"
    ],
    "wof:name":"Farashganj",
    "wof:placetype":"locality"
},
  "geometry": {"coordinates":[90.90589,22.85938],"type":"Point"}
}