{
  "type": "Feature",
  "properties": {
    "gn:admin1_code":"85",
    "gn:admin2_code":"1078.0",
    "gn:admin3_code":"107897.0",
    "gn:admin4_code":"10789783.0",
    "gn:asciiname":"Amlibaria",
    "gn:country_code":"BD",
    "gn:dem":8,
    "gn:feature_class":"P",
    "gn:feature_code":"PPL",
    "gn:name":"Amlib\u0101ria",
    "gn:population":0,
    "gn:timezone":"Asia/Dhaka",
    "iso:country":"BD",
    "name:ben_x_preferred":[
        "Amlib\u0101ria"
    ],
    "wof:name":"Amlibaria",
    "wof:placetype":"locality"
},
  "geometry": {"coordinates":[90.45690999999999,21.9565],"type":"Point"}
}