{
  "type": "Feature",
  "properties": {
    "gn:admin1_code":"82",
    "gn:asciiname":"Badurtala",
    "gn:country_code":"BD",
    "gn:dem":11,
    "gn:feature_class":"P",
    "gn:feature_code":"PPL",
    "gn:name":"Badurtala",
    "gn:population":0,
    "gn:timezone":"Asia/Dhaka",
    "iso:country":"BD",
    "name:ben_x_preferred":[
        "Badurtala"
    ],
    "wof:name":"Badurtala",
    "wof:placetype":"locality"
},
  "geometry": {"coordinates":[89.95211,22.00278],"type":"Point"}
}