{
  "type": "Feature",
  "properties": {
    "gn:admin1_code":"83",
    "gn:admin2_code":"5076.0",
    "gn:admin3_code":"507683.0",
    "gn:admin4_code":"50768347.0",
    "gn:asciiname":"Bar Khanpur",
    "gn:country_code":"BD",
    "gn:dem":17,
    "gn:feature_class":"P",
    "gn:feature_code":"PPL",
    "gn:name":"Bar Kh\u0101npur",
    "gn:population":0,
    "gn:timezone":"Asia/Dhaka",
    "iso:country":"BD",
    "name:ben_x_preferred":[
        "Bar Kh\u0101npur"
    ],
    "wof:name":"Bar Khanpur",
    "wof:placetype":"locality"
},
  "geometry": {"coordinates":[89.53822,23.82712],"type":"Point"}
}