{
  "type": "Feature",
  "properties": {
    "gn:admin1_code":"83",
    "gn:admin2_code":"5064.0",
    "gn:admin3_code":"506475.0",
    "gn:admin4_code":"50647517.0",
    "gn:asciiname":"Arail",
    "gn:country_code":"BD",
    "gn:dem":25,
    "gn:feature_class":"P",
    "gn:feature_code":"PPL",
    "gn:name":"\u0100r\u0101il",
    "gn:population":0,
    "gn:timezone":"Asia/Dhaka",
    "iso:country":"BD",
    "name:ben_x_preferred":[
        "\u0100r\u0101il"
    ],
    "wof:name":"Arail",
    "wof:placetype":"locality"
},
  "geometry": {"coordinates":[88.89865,24.99298],"type":"Point"}
}