{
  "type": "Feature",
  "properties": {
    "gn:admin1_code":"81",
    "gn:admin2_code":"3035.0",
    "gn:admin3_code":"303532.0",
    "gn:admin4_code":"30353230.0",
    "gn:asciiname":"Bara Gopinathpur",
    "gn:country_code":"BD",
    "gn:dem":10,
    "gn:feature_class":"P",
    "gn:feature_code":"PPL",
    "gn:name":"Bara Gopin\u0101thpur",
    "gn:population":0,
    "gn:timezone":"Asia/Dhaka",
    "iso:country":"BD",
    "name:ben_x_preferred":[
        "Bara Gopin\u0101thpur"
    ],
    "wof:name":"Bara Gopinathpur",
    "wof:placetype":"locality"
},
  "geometry": {"coordinates":[89.76940999999999,23.11312],"type":"Point"}
}