{
  "type": "Feature",
  "properties": {
    "gn:admin1_code":"83",
    "gn:admin2_code":"5064.0",
    "gn:admin3_code":"506486.0",
    "gn:admin4_code":"50648694.0",
    "gn:asciiname":"Zinarpur",
    "gn:country_code":"BD",
    "gn:dem":35,
    "gn:feature_class":"P",
    "gn:feature_code":"PPL",
    "gn:name":"Zin\u0101rpur",
    "gn:population":0,
    "gn:timezone":"Asia/Dhaka",
    "iso:country":"BD",
    "name:ben_x_preferred":[
        "Zin\u0101rpur"
    ],
    "wof:name":"Zinarpur",
    "wof:placetype":"locality"
},
  "geometry": {"coordinates":[88.56238,25.02975],"type":"Point"}
}