{
  "type": "Feature",
  "properties": {
    "gn:admin1_code":"85",
    "gn:admin2_code":"1078.0",
    "gn:admin3_code":"107866.0",
    "gn:admin4_code":"10786623.0",
    "gn:asciiname":"Jamalpur",
    "gn:country_code":"BD",
    "gn:dem":8,
    "gn:feature_class":"P",
    "gn:feature_code":"PPL",
    "gn:name":"J\u0101m\u0101lpur",
    "gn:population":0,
    "gn:timezone":"Asia/Dhaka",
    "iso:country":"BD",
    "name:ben_x_preferred":[
        "J\u0101m\u0101lpur"
    ],
    "name:ben_x_variant":[
        "\u099c\u09be\u09ae\u09be\u09b2\u09aa\u09c1\u09b0"
    ],
    "name:bih_x_preferred":[
        "\u091c\u092e\u093e\u0932\u092a\u0941\u0930"
    ],
    "name:bpy_x_preferred":[
        "\u099c\u09be\u09ae\u09be\u09b2\u09aa\u09c1\u09b0"
    ],
    "name:ceb_x_preferred":[
        "Jamalpur"
    ],
    "name:deu_x_preferred":[
        "Jamalpur"
    ],
    "name:fra_x_preferred":[
        "Jamalpur"
    ],
    "name:lit_x_preferred":[
        "D\u017eamalpuras"
    ],
    "name:new_x_preferred":[
        "\u091c\u092e\u0932\u092a\u0941\u0930"
    ],
    "name:nld_x_preferred":[
        "Jamalpur"
    ],
    "name:swe_x_preferred":[
        "Jamalpur"
    ],
    "wof:name":"Jamalpur",
    "wof:placetype":"locality"
},
  "geometry": {"coordinates":[90.17261000000001,21.90411],"type":"Point"}
}