{
  "type": "Feature",
  "properties": {
    "gn:admin1_code":"87",
    "gn:admin2_code":"5527.0",
    "gn:admin3_code":"552712.0",
    "gn:admin4_code":"55271277.0",
    "gn:asciiname":"Lat Dabra",
    "gn:country_code":"BD",
    "gn:dem":54,
    "gn:feature_class":"P",
    "gn:feature_code":"PPL",
    "gn:name":"Lat D\u0101bra",
    "gn:population":0,
    "gn:timezone":"Asia/Dhaka",
    "iso:country":"BD",
    "name:ben_x_preferred":[
        "Lat D\u0101bra"
    ],
    "wof:name":"Lat Dabra",
    "wof:placetype":"locality"
},
  "geometry": {"coordinates":[88.58808000000001,25.95428],"type":"Point"}
}