{
  "type": "Feature",
  "properties": {
    "gn:admin1_code":"83",
    "gn:admin2_code":"5081.0",
    "gn:admin3_code":"508134.0",
    "gn:admin4_code":"50813409.0",
    "gn:asciiname":"Gangabari",
    "gn:country_code":"BD",
    "gn:dem":29,
    "gn:feature_class":"P",
    "gn:feature_code":"PPL",
    "gn:name":"Gang\u0101b\u0101ri",
    "gn:population":0,
    "gn:timezone":"Asia/Dhaka",
    "iso:country":"BD",
    "name:ben_x_preferred":[
        "Gang\u0101b\u0101ri"
    ],
    "name:ben_x_variant":[
        "G\u0101ngob\u0101ri"
    ],
    "wof:name":"Gangabari",
    "wof:placetype":"locality"
},
  "geometry": {"coordinates":[88.31614,24.49966],"type":"Point"}
}