{
  "type": "Feature",
  "properties": {
    "gn:admin1_code":"85",
    "gn:admin2_code":"1006.0",
    "gn:admin3_code":"100607.0",
    "gn:admin4_code":"10060767.0",
    "gn:asciiname":"Bara Hamidpur",
    "gn:country_code":"BD",
    "gn:dem":9,
    "gn:feature_class":"P",
    "gn:feature_code":"PPL",
    "gn:name":"Bara H\u0101midpur",
    "gn:population":0,
    "gn:timezone":"Asia/Dhaka",
    "iso:country":"BD",
    "name:und_x_variant":[
        "Bara H\u0101midpur"
    ],
    "wof:name":"Bara Hamidpur",
    "wof:placetype":"locality"
},
  "geometry": {"coordinates":[90.37569999999999,22.50555],"type":"Point"}
}