{
  "type": "Feature",
  "properties": {
    "gn:admin1_code":"83",
    "gn:admin2_code":"5064.0",
    "gn:admin3_code":"506475.0",
    "gn:admin4_code":"50647525.0",
    "gn:asciiname":"Nakucha",
    "gn:country_code":"BD",
    "gn:dem":27,
    "gn:feature_class":"P",
    "gn:feature_code":"PPL",
    "gn:name":"Nakucha",
    "gn:population":0,
    "gn:timezone":"Asia/Dhaka",
    "iso:country":"BD",
    "name:ben_x_preferred":[
        "Nakucha"
    ],
    "wof:name":"Nakucha",
    "wof:placetype":"locality"
},
  "geometry": {"coordinates":[88.64821999999999,25.09547],"type":"Point"}
}