{
  "type": "Feature",
  "properties": {
    "gn:admin1_code":"84",
    "gn:admin2_code":"2012.0",
    "gn:admin3_code":"201202.0",
    "gn:admin4_code":"20120290.0",
    "gn:asciiname":"Akhaura",
    "gn:country_code":"BD",
    "gn:dem":12,
    "gn:feature_class":"P",
    "gn:feature_code":"PPL",
    "gn:name":"Akhaura",
    "gn:population":0,
    "gn:timezone":"Asia/Dhaka",
    "iso:country":"BD",
    "wof:name":"Akhaura",
    "wof:placetype":"locality"
},
  "geometry": {"coordinates":[91.20768,23.87243],"type":"Point"}
}