{
  "type": "Feature",
  "properties": {
    "gn:admin1_code":"82",
    "gn:asciiname":"Arazi Gerakhali",
    "gn:country_code":"BD",
    "gn:dem":7,
    "gn:feature_class":"P",
    "gn:feature_code":"PPL",
    "gn:name":"Ar\u0101zi Ger\u0101kh\u0101li",
    "gn:population":0,
    "gn:timezone":"Asia/Dhaka",
    "iso:country":"BD",
    "name:ben_x_preferred":[
        "Ar\u0101zi Ger\u0101kh\u0101li"
    ],
    "wof:name":"Arazi Gerakhali",
    "wof:placetype":"locality"
},
  "geometry": {"coordinates":[90.31274999999999,22.2778],"type":"Point"}
}