{
  "type": "Feature",
  "properties": {
    "gn:admin1_code":"87",
    "gn:admin2_code":"5577",
    "gn:admin3_code":"557704.0",
    "gn:admin4_code":"55770427.0",
    "gn:asciiname":"Sathkhamar",
    "gn:country_code":"BD",
    "gn:dem":72,
    "gn:feature_class":"P",
    "gn:feature_code":"PPL",
    "gn:name":"Sathkh\u0101m\u0101r",
    "gn:population":0,
    "gn:timezone":"Asia/Dhaka",
    "iso:country":"BD",
    "name:ben_x_preferred":[
        "Sathkh\u0101m\u0101r"
    ],
    "name:und_x_variant":[
        "Satkhamar"
    ],
    "wof:name":"Sathkhamar",
    "wof:placetype":"locality"
},
  "geometry": {"coordinates":[88.54016,26.20785],"type":"Point"}
}