{
  "type": "Feature",
  "properties": {
    "gn:admin1_code":"83",
    "gn:admin2_code":"5010",
    "gn:admin3_code":"501081.0",
    "gn:admin4_code":"50108175.0",
    "gn:asciiname":"Narchi",
    "gn:country_code":"BD",
    "gn:dem":23,
    "gn:feature_class":"P",
    "gn:feature_code":"PPL",
    "gn:name":"N\u0101rchi",
    "gn:population":0,
    "gn:timezone":"Asia/Dhaka",
    "iso:country":"BD",
    "wof:name":"Narchi",
    "wof:placetype":"locality"
},
  "geometry": {"coordinates":[89.54414,24.91644],"type":"Point"}
}