{
  "type": "Feature",
  "properties": {
    "gn:admin1_code":"82",
    "gn:admin2_code":"4050.0",
    "gn:admin3_code":"405094.0",
    "gn:admin4_code":"40509480.0",
    "gn:asciiname":"Belgachhi",
    "gn:country_code":"BD",
    "gn:dem":22,
    "gn:feature_class":"P",
    "gn:feature_code":"PPL",
    "gn:name":"Belg\u0101chhi",
    "gn:population":0,
    "gn:timezone":"Asia/Dhaka",
    "iso:country":"BD",
    "name:ben_x_preferred":[
        "Belg\u0101chhi"
    ],
    "wof:name":"Belgachhi",
    "wof:placetype":"locality"
},
  "geometry": {"coordinates":[89.05894000000001,23.90254],"type":"Point"}
}