{
  "type": "Feature",
  "properties": {
    "gn:admin1_code":"83",
    "gn:admin2_code":"5081",
    "gn:admin3_code":"508194.0",
    "gn:admin4_code":"50819454.0",
    "gn:asciiname":"Mohanpur",
    "gn:country_code":"BD",
    "gn:dem":30,
    "gn:feature_class":"P",
    "gn:feature_code":"PPL",
    "gn:name":"Mohanpur",
    "gn:population":0,
    "gn:timezone":"Asia/Dhaka",
    "iso:country":"BD",
    "wof:name":"Mohanpur",
    "wof:placetype":"locality"
},
  "geometry": {"coordinates":[88.49370999999999,24.5637],"type":"Point"}
}