{
  "type": "Feature",
  "properties": {
    "gn:admin1_code":"84",
    "gn:admin2_code":"2084",
    "gn:admin3_code":"208429.0",
    "gn:admin4_code":"20842971.0",
    "gn:asciiname":"Belaichari",
    "gn:country_code":"BD",
    "gn:dem":47,
    "gn:feature_class":"P",
    "gn:feature_code":"PPL",
    "gn:name":"Bel\u0101ichari",
    "gn:population":0,
    "gn:timezone":"Asia/Dhaka",
    "iso:country":"BD",
    "name:und_x_variant":[
        "Bel\u0101ichhari",
        "Bilaichhari",
        "Bel\u0101ichari"
    ],
    "wof:name":"Belaichari",
    "wof:placetype":"locality"
},
  "geometry": {"coordinates":[92.34524,22.51083],"type":"Point"}
}