{
  "type": "Feature",
  "properties": {
    "gn:admin1_code":"81",
    "gn:admin2_code":"3082.0",
    "gn:admin3_code":"308276.0",
    "gn:admin4_code":"30827651.0",
    "gn:asciiname":"Chitaliar Bil",
    "gn:country_code":"BD",
    "gn:dem":16,
    "gn:feature_class":"P",
    "gn:feature_code":"PPL",
    "gn:name":"Chit\u0101li\u0101r Bil",
    "gn:population":0,
    "gn:timezone":"Asia/Dhaka",
    "iso:country":"BD",
    "name:ben_x_preferred":[
        "Chit\u0101li\u0101r Bil"
    ],
    "wof:name":"Chitaliar Bil",
    "wof:placetype":"locality"
},
  "geometry": {"coordinates":[89.62424,23.76192],"type":"Point"}
}