{
  "type": "Feature",
  "properties": {
    "gn:admin1_code":"87",
    "gn:admin2_code":"5527.0",
    "gn:admin3_code":"552760.0",
    "gn:admin4_code":"55276047.0",
    "gn:asciiname":"Chak Kanchan",
    "gn:country_code":"BD",
    "gn:dem":46,
    "gn:feature_class":"P",
    "gn:feature_code":"PPL",
    "gn:name":"Chak Kanchan",
    "gn:population":0,
    "gn:timezone":"Asia/Dhaka",
    "iso:country":"BD",
    "name:ben_x_preferred":[
        "Chak Kanchan"
    ],
    "wof:name":"Chak Kanchan",
    "wof:placetype":"locality"
},
  "geometry": {"coordinates":[88.7526,25.81783],"type":"Point"}
}