{
  "type": "Feature",
  "properties": {
    "gn:admin1_code":"81",
    "gn:admin2_code":"3054.0",
    "gn:admin3_code":"305440.0",
    "gn:admin4_code":"30544012.0",
    "gn:asciiname":"Bil Hendia",
    "gn:country_code":"BD",
    "gn:dem":7,
    "gn:feature_class":"P",
    "gn:feature_code":"PPL",
    "gn:name":"B\u012bl Hendia",
    "gn:population":0,
    "gn:timezone":"Asia/Dhaka",
    "iso:country":"BD",
    "name:und_x_variant":[
        "B\u012bl Hendia",
        "B\u012bl Hendala"
    ],
    "wof:name":"Bil Hendia",
    "wof:placetype":"locality"
},
  "geometry": {"coordinates":[90.18886999999999,23.13708],"type":"Point"}
}