{
  "type": "Feature",
  "properties": {
    "gn:admin1_code":"87",
    "gn:admin2_code":"5527",
    "gn:admin3_code":"552769.0",
    "gn:admin4_code":"55276908.0",
    "gn:asciiname":"Palashbari",
    "gn:country_code":"BD",
    "gn:dem":27,
    "gn:feature_class":"P",
    "gn:feature_code":"PPL",
    "gn:name":"Palashbari",
    "gn:population":0,
    "gn:timezone":"Asia/Dhaka",
    "iso:country":"BD",
    "name:ben_x_preferred":[
        "Palashbari"
    ],
    "wof:name":"Palashbari",
    "wof:placetype":"locality"
},
  "geometry": {"coordinates":[89.11004,25.35953],"type":"Point"}
}