{
  "type": "Feature",
  "properties": {
    "gn:admin1_code":"84",
    "gn:admin2_code":"2084.0",
    "gn:admin3_code":"208436.0",
    "gn:admin4_code":"20843676.0",
    "gn:asciiname":"Gancapara",
    "gn:country_code":"BD",
    "gn:dem":70,
    "gn:feature_class":"P",
    "gn:feature_code":"PPL",
    "gn:name":"Gancap\u0101ra",
    "gn:population":0,
    "gn:timezone":"Asia/Dhaka",
    "iso:country":"BD",
    "name:ben_x_preferred":[
        "Gancap\u0101ra"
    ],
    "name:und_x_variant":[
        "Gainda",
        "Gaind\u0101p\u0101ra"
    ],
    "wof:name":"Gancapara",
    "wof:placetype":"locality"
},
  "geometry": {"coordinates":[92.19628,22.36626],"type":"Point"}
}