{
  "type": "Feature",
  "properties": {
    "gn:admin1_code":"81",
    "gn:admin2_code":"3093",
    "gn:admin3_code":"309395.0",
    "gn:admin4_code":"30939541.0",
    "gn:asciiname":"Phanch Bikramhati",
    "gn:country_code":"BD",
    "gn:dem":13,
    "gn:feature_class":"P",
    "gn:feature_code":"PPL",
    "gn:name":"Phanch Bikramhati",
    "gn:population":0,
    "gn:timezone":"Asia/Dhaka",
    "iso:country":"BD",
    "name:und_x_variant":[
        "P\u0101chh Bikramh\u0101ti"
    ],
    "wof:name":"Phanch Bikramhati",
    "wof:placetype":"locality"
},
  "geometry": {"coordinates":[89.92683000000002,24.29313],"type":"Point"}
}