{
  "type": "Feature",
  "properties": {
    "gn:admin1_code":"81",
    "gn:admin2_code":"3067",
    "gn:admin3_code":"306706.0",
    "gn:admin4_code":"30670631.0",
    "gn:asciiname":"Sarail",
    "gn:country_code":"BD",
    "gn:dem":9,
    "gn:feature_class":"P",
    "gn:feature_code":"PPL",
    "gn:name":"S\u0101r\u0101il",
    "gn:population":0,
    "gn:timezone":"Asia/Dhaka",
    "iso:country":"BD",
    "wof:name":"Sarail",
    "wof:placetype":"locality"
},
  "geometry": {"coordinates":[90.54964,23.67843],"type":"Point"}
}