{
  "type": "Feature",
  "properties": {
    "gn:admin1_code":"87",
    "gn:admin2_code":"5527.0",
    "gn:admin3_code":"552747.0",
    "gn:admin4_code":"55274713.0",
    "gn:asciiname":"Baona",
    "gn:country_code":"BD",
    "gn:dem":26,
    "gn:feature_class":"P",
    "gn:feature_code":"PPL",
    "gn:name":"B\u0101ona",
    "gn:population":0,
    "gn:timezone":"Asia/Dhaka",
    "iso:country":"BD",
    "name:ben_x_preferred":[
        "B\u0101ona"
    ],
    "wof:name":"Baona",
    "wof:placetype":"locality"
},
  "geometry": {"coordinates":[89.12745,25.28056],"type":"Point"}
}