{
  "type": "Feature",
  "properties": {
    "gn:admin1_code":"87",
    "gn:admin2_code":"5527.0",
    "gn:admin3_code":"552764.0",
    "gn:admin4_code":"55276486.0",
    "gn:asciiname":"Shibpur",
    "gn:country_code":"BD",
    "gn:dem":45,
    "gn:feature_class":"P",
    "gn:feature_code":"PPL",
    "gn:name":"Shibpur",
    "gn:population":0,
    "gn:timezone":"Asia/Dhaka",
    "iso:country":"BD",
    "name:ben_x_preferred":[
        "Shibpur"
    ],
    "name:urd_x_preferred":[
        "\u0634\u06cc\u0628 \u067e\u0648\u0631"
    ],
    "wof:name":"Shibpur",
    "wof:placetype":"locality"
},
  "geometry": {"coordinates":[88.68469,25.73809],"type":"Point"}
}