{
  "type": "Feature",
  "properties": {
    "gn:admin1_code":"82",
    "gn:admin2_code":"4041.0",
    "gn:admin3_code":"404123.0",
    "gn:admin4_code":"40412359.0",
    "gn:asciiname":"Gunnagar",
    "gn:country_code":"BD",
    "gn:dem":15,
    "gn:feature_class":"P",
    "gn:feature_code":"PPL",
    "gn:name":"Gunnagar",
    "gn:population":0,
    "gn:timezone":"Asia/Dhaka",
    "iso:country":"BD",
    "name:ben_x_preferred":[
        "Gunnagar"
    ],
    "wof:name":"Gunnagar",
    "wof:placetype":"locality"
},
  "geometry": {"coordinates":[89.02616999999999,23.05291],"type":"Point"}
}