{
  "type": "Feature",
  "properties": {
    "gn:admin1_code":"84",
    "gn:admin2_code":"2013.0",
    "gn:admin3_code":"201379.0",
    "gn:admin4_code":"20137932.0",
    "gn:asciiname":"Aithadi",
    "gn:country_code":"BD",
    "gn:dem":9,
    "gn:feature_class":"P",
    "gn:feature_code":"PPL",
    "gn:name":"\u0100ith\u0101di",
    "gn:population":0,
    "gn:timezone":"Asia/Dhaka",
    "iso:country":"BD",
    "name:fas_x_preferred":[
        "\u0627\u06cc\u062a\u0627\u062f\u06cc"
    ],
    "name:und_x_variant":[
        "\u0100ith\u0101di"
    ],
    "wof:name":"Aithadi",
    "wof:placetype":"locality"
},
  "geometry": {"coordinates":[90.63401,23.39264],"type":"Point"}
}