{
  "type": "Feature",
  "properties": {
    "gn:admin1_code":"83",
    "gn:admin2_code":"5081.0",
    "gn:admin3_code":"508153.0",
    "gn:admin4_code":"50815367.0",
    "gn:asciiname":"Bazarpur",
    "gn:country_code":"BD",
    "gn:dem":21,
    "gn:feature_class":"P",
    "gn:feature_code":"PPL",
    "gn:name":"B\u0101z\u0101rpur",
    "gn:population":0,
    "gn:timezone":"Asia/Dhaka",
    "iso:country":"BD",
    "name:ben_x_preferred":[
        "B\u0101z\u0101rpur"
    ],
    "wof:name":"Bazarpur",
    "wof:placetype":"locality"
},
  "geometry": {"coordinates":[88.63710999999998,24.51144],"type":"Point"}
}