{
  "type": "Feature",
  "properties": {
    "gn:admin1_code":"83",
    "gn:admin2_code":"5088",
    "gn:admin3_code":"508894.0",
    "gn:admin4_code":"50889458.0",
    "gn:asciiname":"Parkol",
    "gn:country_code":"BD",
    "gn:dem":17,
    "gn:feature_class":"P",
    "gn:feature_code":"PPL",
    "gn:name":"P\u0101rkol",
    "gn:population":0,
    "gn:timezone":"Asia/Dhaka",
    "iso:country":"BD",
    "name:und_x_variant":[
        "P\u0101rkol",
        "P\u0101rkul"
    ],
    "wof:name":"Parkol",
    "wof:placetype":"locality"
},
  "geometry": {"coordinates":[89.50394,24.32856],"type":"Point"}
}