{
  "type": "Feature",
  "properties": {
    "gn:admin1_code":"82",
    "gn:admin2_code":"4087",
    "gn:admin3_code":"408786.0",
    "gn:admin4_code":"40878647.0",
    "gn:asciiname":"Majerati",
    "gn:country_code":"BD",
    "gn:dem":3,
    "gn:feature_class":"P",
    "gn:feature_code":"PPL",
    "gn:name":"Majer\u0101ti",
    "gn:population":0,
    "gn:timezone":"Asia/Dhaka",
    "iso:country":"BD",
    "name:ben_x_preferred":[
        "Majer\u0101ti"
    ],
    "name:und_x_variant":[
        "M\u0101jher\u0101ti"
    ],
    "wof:name":"Majerati",
    "wof:placetype":"locality"
},
  "geometry": {"coordinates":[89.01482,22.27897],"type":"Point"}
}