{
  "type": "Feature",
  "properties": {
    "gn:admin1_code":"84",
    "gn:admin2_code":"2051.0",
    "gn:admin3_code":"205165.0",
    "gn:admin4_code":"20516514.0",
    "gn:asciiname":"Baurkhara",
    "gn:country_code":"BD",
    "gn:dem":17,
    "gn:feature_class":"P",
    "gn:feature_code":"PPL",
    "gn:name":"B\u0101urkh\u0101ra",
    "gn:population":0,
    "gn:timezone":"Asia/Dhaka",
    "iso:country":"BD",
    "wof:name":"Baurkhara",
    "wof:placetype":"locality"
},
  "geometry": {"coordinates":[90.94443,23.11806],"type":"Point"}
}