{
  "type": "Feature",
  "properties": {
    "gn:admin1_code":"H",
    "gn:admin2_code":"3061",
    "gn:admin3_code":"306194.0",
    "gn:admin4_code":"30619463.0",
    "gn:asciiname":"Sankibanga",
    "gn:country_code":"BD",
    "gn:dem":18,
    "gn:feature_class":"P",
    "gn:feature_code":"PPL",
    "gn:name":"Sankibanga",
    "gn:population":0,
    "gn:timezone":"Asia/Dhaka",
    "iso:country":"BD",
    "name:und_x_variant":[
        "S\u0101nkibh\u0101nga"
    ],
    "wof:name":"Sankibanga",
    "wof:placetype":"locality"
},
  "geometry": {"coordinates":[90.34316,24.49342],"type":"Point"}
}