{
  "type": "Feature",
  "properties": {
    "gn:admin1_code":"H",
    "gn:admin2_code":"3072.0",
    "gn:admin3_code":"307204.0",
    "gn:admin4_code":"30720447.0",
    "gn:asciiname":"Abhaipasa",
    "gn:country_code":"BD",
    "gn:dem":15,
    "gn:feature_class":"P",
    "gn:feature_code":"PPL",
    "gn:name":"Abhaip\u0101sa",
    "gn:population":0,
    "gn:timezone":"Asia/Dhaka",
    "iso:country":"BD",
    "name:und_x_variant":[
        "Abhaip\u0101sa",
        "\u0100bp\u0101sa"
    ],
    "wof:name":"Abhaipasa",
    "wof:placetype":"locality"
},
  "geometry": {"coordinates":[90.81403,24.79669],"type":"Point"}
}