{
  "type": "Feature",
  "properties": {
    "gn:admin1_code":"87",
    "gn:admin2_code":"5573.0",
    "gn:admin3_code":"557315.0",
    "gn:admin4_code":"55731519.0",
    "gn:asciiname":"Sahaparar",
    "gn:country_code":"BD",
    "gn:dem":67,
    "gn:feature_class":"P",
    "gn:feature_code":"PPL",
    "gn:name":"S\u0101h\u0101p\u0101rar",
    "gn:population":0,
    "gn:timezone":"Asia/Dhaka",
    "iso:country":"BD",
    "name:ben_x_preferred":[
        "S\u0101h\u0101p\u0101rar"
    ],
    "wof:name":"Sahaparar",
    "wof:placetype":"locality"
},
  "geometry": {"coordinates":[88.79741,26.2823],"type":"Point"}
}