{
  "type": "Feature",
  "properties": {
    "gn:admin1_code":"83",
    "gn:admin2_code":"5064",
    "gn:admin3_code":"506447.0",
    "gn:admin4_code":"50644747.0",
    "gn:asciiname":"Kasab",
    "gn:country_code":"BD",
    "gn:dem":18,
    "gn:feature_class":"P",
    "gn:feature_code":"PPL",
    "gn:name":"Kasab",
    "gn:population":0,
    "gn:timezone":"Asia/Dhaka",
    "iso:country":"BD",
    "name:ben_x_preferred":[
        "Kasab"
    ],
    "name:cat_x_preferred":[
        "Kasab"
    ],
    "name:deu_x_preferred":[
        "Kasab"
    ],
    "wof:name":"Kasab",
    "wof:placetype":"locality"
},
  "geometry": {"coordinates":[88.81839000000002,24.72359],"type":"Point"}
}