{
  "type": "Feature",
  "properties": {
    "gn:admin1_code":"82",
    "gn:admin2_code":"4047.0",
    "gn:admin3_code":"404712.0",
    "gn:admin4_code":"40471235.0",
    "gn:asciiname":"Aushkhali",
    "gn:country_code":"BD",
    "gn:dem":6,
    "gn:feature_class":"P",
    "gn:feature_code":"PPL",
    "gn:name":"\u0100ushkh\u0101li",
    "gn:population":0,
    "gn:timezone":"Asia/Dhaka",
    "iso:country":"BD",
    "name:und_x_variant":[
        "Auskhali",
        "\u0100ushkh\u0101li"
    ],
    "wof:name":"Aushkhali",
    "wof:placetype":"locality"
},
  "geometry": {"coordinates":[89.47140999999998,22.70717],"type":"Point"}
}