{
  "type": "Feature",
  "properties": {
    "gn:admin1_code":"81",
    "gn:admin2_code":"3048",
    "gn:admin3_code":"304833.0",
    "gn:admin4_code":"30483351.0",
    "gn:asciiname":"Itna",
    "gn:country_code":"BD",
    "gn:dem":11,
    "gn:feature_class":"P",
    "gn:feature_code":"PPL",
    "gn:name":"Itna",
    "gn:population":0,
    "gn:timezone":"Asia/Dhaka",
    "iso:country":"BD",
    "wof:name":"Itna",
    "wof:placetype":"locality"
},
  "geometry": {"coordinates":[91.09595,24.52686],"type":"Point"}
}