{
  "type": "Feature",
  "properties": {
    "gn:admin1_code":"H",
    "gn:admin2_code":"3061",
    "gn:admin3_code":"306131.0",
    "gn:admin4_code":"30613109.0",
    "gn:asciiname":"Sarati",
    "gn:country_code":"BD",
    "gn:dem":16,
    "gn:feature_class":"P",
    "gn:feature_code":"PPL",
    "gn:name":"S\u0101rati",
    "gn:population":0,
    "gn:timezone":"Asia/Dhaka",
    "iso:country":"BD",
    "name:cat_x_preferred":[
        "Sarati"
    ],
    "name:fra_x_preferred":[
        "Sarati"
    ],
    "name:hun_x_preferred":[
        "Sarati \u00e1b\u00e9c\u00e9"
    ],
    "name:ita_x_preferred":[
        "Sarati"
    ],
    "name:jpn_x_preferred":[
        "\u30b5\u30e9\u30c6\u30a3"
    ],
    "name:pol_x_preferred":[
        "Sarati"
    ],
    "name:rus_x_preferred":[
        "\u0421\u0430\u0440\u0430\u0442\u0438"
    ],
    "name:slv_x_preferred":[
        "Sarati"
    ],
    "name:spa_x_preferred":[
        "Sarati"
    ],
    "name:swe_x_preferred":[
        "Sarati"
    ],
    "wof:name":"Sarati",
    "wof:placetype":"locality"
},
  "geometry": {"coordinates":[90.7294,24.6423],"type":"Point"}
}