{
  "type": "Feature",
  "properties": {
    "gn:admin1_code":"84",
    "gn:admin2_code":"2075.0",
    "gn:admin3_code":"207587.0",
    "gn:admin4_code":"20758740.0",
    "gn:asciiname":"Char Matua",
    "gn:country_code":"BD",
    "gn:dem":8,
    "gn:feature_class":"P",
    "gn:feature_code":"PPL",
    "gn:name":"Char Matua",
    "gn:population":0,
    "gn:timezone":"Asia/Dhaka",
    "iso:country":"BD",
    "wof:name":"Char Matua",
    "wof:placetype":"locality"
},
  "geometry": {"coordinates":[90.97499999999999,22.83775],"type":"Point"}
}