{
  "type": "Feature",
  "properties": {
    "gn:admin1_code":"82",
    "gn:admin2_code":"4087.0",
    "gn:admin3_code":"408725.0",
    "gn:admin4_code":"40872531.0",
    "gn:asciiname":"Khas Khamar",
    "gn:country_code":"BD",
    "gn:dem":9,
    "gn:feature_class":"P",
    "gn:feature_code":"PPL",
    "gn:name":"Kh\u0101s Kh\u0101m\u0101r",
    "gn:population":0,
    "gn:timezone":"Asia/Dhaka",
    "iso:country":"BD",
    "name:ben_x_preferred":[
        "Kh\u0101s Kh\u0101m\u0101r"
    ],
    "wof:name":"Khas Khamar",
    "wof:placetype":"locality"
},
  "geometry": {"coordinates":[88.99706,22.65949],"type":"Point"}
}