{
  "type": "Feature",
  "properties": {
    "gn:admin1_code":"81",
    "gn:admin2_code":"3086.0",
    "gn:admin3_code":"308614.0",
    "gn:admin4_code":"30861469.0",
    "gn:asciiname":"Basudebpur",
    "gn:country_code":"BD",
    "gn:dem":14,
    "gn:feature_class":"P",
    "gn:feature_code":"PPL",
    "gn:name":"B\u0101sudebpur",
    "gn:population":0,
    "gn:timezone":"Asia/Dhaka",
    "iso:country":"BD",
    "name:und_x_variant":[
        "Bashudevpur",
        "B\u0101sudebpur"
    ],
    "wof:name":"Basudebpur",
    "wof:placetype":"locality"
},
  "geometry": {"coordinates":[90.46498,23.17597],"type":"Point"}
}