{
  "type": "Feature",
  "properties": {
    "gn:admin1_code":"83",
    "gn:admin2_code":"5070",
    "gn:admin3_code":"507018.0",
    "gn:admin4_code":"50701875.0",
    "gn:asciiname":"Kistapur",
    "gn:country_code":"BD",
    "gn:dem":27,
    "gn:feature_class":"P",
    "gn:feature_code":"PPL",
    "gn:name":"Kist\u0101pur",
    "gn:population":0,
    "gn:timezone":"Asia/Dhaka",
    "iso:country":"BD",
    "name:ben_x_preferred":[
        "Kist\u0101pur"
    ],
    "name:ben_x_variant":[
        "Krishnapur"
    ],
    "wof:name":"Kistapur",
    "wof:placetype":"locality"
},
  "geometry": {"coordinates":[88.22955999999998,24.84035],"type":"Point"}
}