{
  "type": "Feature",
  "properties": {
    "gn:admin1_code":"87",
    "gn:admin2_code":"5527.0",
    "gn:admin3_code":"552712.0",
    "gn:admin4_code":"55271243.0",
    "gn:asciiname":"Rukanpur",
    "gn:country_code":"BD",
    "gn:dem":49,
    "gn:feature_class":"P",
    "gn:feature_code":"PPL",
    "gn:name":"Rukanpur",
    "gn:population":0,
    "gn:timezone":"Asia/Dhaka",
    "iso:country":"BD",
    "name:ben_x_preferred":[
        "Rukanpur"
    ],
    "wof:name":"Rukanpur",
    "wof:placetype":"locality"
},
  "geometry": {"coordinates":[88.69121,25.88676],"type":"Point"}
}