{
  "type": "Feature",
  "properties": {
    "gn:admin1_code":"87",
    "gn:admin2_code":"5594.0",
    "gn:admin3_code":"559482.0",
    "gn:admin4_code":"55948294.0",
    "gn:asciiname":"Danajpur",
    "gn:country_code":"BD",
    "gn:dem":44,
    "gn:feature_class":"P",
    "gn:feature_code":"PPL",
    "gn:name":"D\u0101n\u0101jpur",
    "gn:population":0,
    "gn:timezone":"Asia/Dhaka",
    "iso:country":"BD",
    "name:ben_x_preferred":[
        "D\u0101n\u0101jpur"
    ],
    "wof:name":"Danajpur",
    "wof:placetype":"locality"
},
  "geometry": {"coordinates":[88.31239000000002,25.76542],"type":"Point"}
}