{
  "type": "Feature",
  "properties": {
    "gn:admin1_code":"83",
    "gn:admin2_code":"5064.0",
    "gn:admin3_code":"506486.0",
    "gn:admin4_code":"50648639.0",
    "gn:asciiname":"Bad Saihira",
    "gn:country_code":"BD",
    "gn:dem":34,
    "gn:feature_class":"P",
    "gn:feature_code":"PPL",
    "gn:name":"B\u0101d Saihira",
    "gn:population":0,
    "gn:timezone":"Asia/Dhaka",
    "iso:country":"BD",
    "name:ben_x_preferred":[
        "B\u0101d Saihira"
    ],
    "wof:name":"Bad Saihira",
    "wof:placetype":"locality"
},
  "geometry": {"coordinates":[88.49285,25.07172000000001],"type":"Point"}
}