{
  "type": "Feature",
  "properties": {
    "gn:admin1_code":"82",
    "gn:admin2_code":"4087",
    "gn:admin3_code":"408786.0",
    "gn:admin4_code":"40878671.0",
    "gn:asciiname":"Katakhali",
    "gn:country_code":"BD",
    "gn:dem":3,
    "gn:feature_class":"P",
    "gn:feature_code":"PPL",
    "gn:name":"K\u0101t\u0101kh\u0101li",
    "gn:population":0,
    "gn:timezone":"Asia/Dhaka",
    "iso:country":"BD",
    "name:ben_x_preferred":[
        "K\u0101t\u0101kh\u0101li"
    ],
    "name:und_x_variant":[
        "K\u0101takh\u0101li Chhota"
    ],
    "wof:name":"Katakhali",
    "wof:placetype":"locality"
},
  "geometry": {"coordinates":[89.02977,22.32033],"type":"Point"}
}