{
  "type": "Feature",
  "properties": {
    "gn:admin1_code":"87",
    "gn:admin2_code":"5527.0",
    "gn:admin3_code":"552710.0",
    "gn:admin4_code":"55271059.0",
    "gn:asciiname":"Kheyar Mahmudpur",
    "gn:country_code":"BD",
    "gn:dem":31,
    "gn:feature_class":"P",
    "gn:feature_code":"PPL",
    "gn:name":"Khey\u0101r M\u0101hmudpur",
    "gn:population":0,
    "gn:timezone":"Asia/Dhaka",
    "iso:country":"BD",
    "name:ben_x_preferred":[
        "Khey\u0101r M\u0101hmudpur"
    ],
    "wof:name":"Kheyar Mahmudpur",
    "wof:placetype":"locality"
},
  "geometry": {"coordinates":[88.95851,25.3164],"type":"Point"}
}