{
  "type": "Feature",
  "properties": {
    "gn:admin1_code":"83",
    "gn:asciiname":"Char Chakla",
    "gn:country_code":"BD",
    "gn:dem":8,
    "gn:feature_class":"P",
    "gn:feature_code":"PPL",
    "gn:name":"Char Ch\u0101kla",
    "gn:population":0,
    "gn:timezone":"Asia/Dhaka",
    "iso:country":"BD",
    "name:ben_x_preferred":[
        "Char Ch\u0101kla"
    ],
    "name:ben_x_variant":[
        "Chakla Benodepur"
    ],
    "name:und_x_variant":[
        "Chakla Binodpur"
    ],
    "wof:name":"Char Chakla",
    "wof:placetype":"locality"
},
  "geometry": {"coordinates":[88.91943000000001,24.12758],"type":"Point"}
}