{
  "type": "Feature",
  "properties": {
    "gn:admin1_code":"82",
    "gn:admin2_code":"4047.0",
    "gn:admin3_code":"404775.0",
    "gn:admin4_code":"40477567.0",
    "gn:asciiname":"Srifaltala",
    "gn:country_code":"BD",
    "gn:dem":10,
    "gn:feature_class":"P",
    "gn:feature_code":"PPL",
    "gn:name":"Sr\u012bfaltala",
    "gn:population":0,
    "gn:timezone":"Asia/Dhaka",
    "iso:country":"BD",
    "name:ben_x_preferred":[
        "Sr\u012bfaltala"
    ],
    "wof:name":"Srifaltala",
    "wof:placetype":"locality"
},
  "geometry": {"coordinates":[89.60082,22.83399],"type":"Point"}
}