{
  "type": "Feature",
  "properties": {
    "gn:admin1_code":"84",
    "gn:admin2_code":"2046.0",
    "gn:admin3_code":"204667.0",
    "gn:admin4_code":"20466719.0",
    "gn:asciiname":"Purambil",
    "gn:country_code":"BD",
    "gn:dem":37,
    "gn:feature_class":"P",
    "gn:feature_code":"PPL",
    "gn:name":"Purambil",
    "gn:population":0,
    "gn:timezone":"Asia/Dhaka",
    "iso:country":"BD",
    "name:ben_x_preferred":[
        "Purambil"
    ],
    "wof:name":"Purambil",
    "wof:placetype":"locality"
},
  "geometry": {"coordinates":[91.81891,22.85679],"type":"Point"}
}