{
  "type": "Feature",
  "properties": {
    "gn:admin1_code":"82",
    "gn:admin2_code":"4018.0",
    "gn:admin3_code":"401807.0",
    "gn:admin4_code":"40180755.0",
    "gn:asciiname":"Jamjami",
    "gn:country_code":"BD",
    "gn:dem":17,
    "gn:feature_class":"P",
    "gn:feature_code":"PPL",
    "gn:name":"J\u0101mj\u0101mi",
    "gn:population":0,
    "gn:timezone":"Asia/Dhaka",
    "iso:country":"BD",
    "name:ben_x_preferred":[
        "J\u0101mj\u0101mi"
    ],
    "wof:name":"Jamjami",
    "wof:placetype":"locality"
},
  "geometry": {"coordinates":[89.00591999999997,23.72019],"type":"Point"}
}