{
  "type": "Feature",
  "properties": {
    "gn:admin1_code":"81",
    "gn:admin2_code":"3029",
    "gn:admin3_code":"302918.0",
    "gn:admin4_code":"30291830.0",
    "gn:asciiname":"Kamaleswardi",
    "gn:country_code":"BD",
    "gn:dem":14,
    "gn:feature_class":"P",
    "gn:feature_code":"PPL",
    "gn:name":"Kamaleswardi",
    "gn:population":0,
    "gn:timezone":"Asia/Dhaka",
    "iso:country":"BD",
    "wof:name":"Kamaleswardi",
    "wof:placetype":"locality"
},
  "geometry": {"coordinates":[89.69031,23.47702],"type":"Point"}
}