{
  "type": "Feature",
  "properties": {
    "gn:admin1_code":"83",
    "gn:admin2_code":"5081",
    "gn:admin3_code":"508110.0",
    "gn:admin4_code":"50811063.0",
    "gn:asciiname":"Kalabaria",
    "gn:country_code":"BD",
    "gn:dem":21,
    "gn:feature_class":"P",
    "gn:feature_code":"PPL",
    "gn:name":"Kal\u0101b\u0101ria",
    "gn:population":0,
    "gn:timezone":"Asia/Dhaka",
    "iso:country":"BD",
    "name:ben_x_preferred":[
        "Kal\u0101b\u0101ria"
    ],
    "wof:name":"Kalabaria",
    "wof:placetype":"locality"
},
  "geometry": {"coordinates":[88.76849,24.22354],"type":"Point"}
}