{
  "type": "Feature",
  "properties": {
    "gn:admin1_code":"81",
    "gn:admin2_code":"3056",
    "gn:admin3_code":"305610.0",
    "gn:admin4_code":"30561019.0",
    "gn:asciiname":"Kasi Panchuria",
    "gn:country_code":"BD",
    "gn:dem":9,
    "gn:feature_class":"P",
    "gn:feature_code":"PPL",
    "gn:name":"K\u0101si P\u0101nchuria",
    "gn:population":0,
    "gn:timezone":"Asia/Dhaka",
    "iso:country":"BD",
    "wof:name":"Kasi Panchuria",
    "wof:placetype":"locality"
},
  "geometry": {"coordinates":[89.76666999999998,23.93333],"type":"Point"}
}