{
  "type": "Feature",
  "properties": {
    "gn:admin1_code":"H",
    "gn:admin2_code":"3089.0",
    "gn:admin3_code":"308988.0",
    "gn:admin4_code":"30898813.0",
    "gn:asciiname":"Char Sripur",
    "gn:country_code":"BD",
    "gn:dem":23,
    "gn:feature_class":"P",
    "gn:feature_code":"PPL",
    "gn:name":"Char Sripur",
    "gn:population":0,
    "gn:timezone":"Asia/Dhaka",
    "iso:country":"BD",
    "wof:name":"Char Sripur",
    "wof:placetype":"locality"
},
  "geometry": {"coordinates":[90.00679000000002,24.95381],"type":"Point"}
}