{
  "type": "Feature",
  "properties": {
    "gn:admin1_code":"84",
    "gn:admin2_code":"2013",
    "gn:admin3_code":"201322.0",
    "gn:admin4_code":"20132263.0",
    "gn:asciiname":"Jafrabad",
    "gn:country_code":"BD",
    "gn:dem":11,
    "gn:feature_class":"P",
    "gn:feature_code":"PPL",
    "gn:name":"J\u0101fr\u0101b\u0101d",
    "gn:population":0,
    "gn:timezone":"Asia/Dhaka",
    "iso:country":"BD",
    "name:guj_x_preferred":[
        "\u0a9c\u0abe\u0aab\u0ab0\u0abe\u0aac\u0abe\u0aa6"
    ],
    "name:ita_x_preferred":[
        "Jafrabad"
    ],
    "name:por_x_preferred":[
        "Jafrabad"
    ],
    "name:spa_x_preferred":[
        "Jafrabad"
    ],
    "name:vie_x_preferred":[
        "Jafrabad"
    ],
    "name:zho_x_preferred":[
        "\u8d3e\u592b\u62c9\u5df4\u5fb7"
    ],
    "wof:name":"Jafrabad",
    "wof:placetype":"locality"
},
  "geometry": {"coordinates":[90.64592,23.21424],"type":"Point"}
}