{
  "type": "Feature",
  "properties": {
    "gn:admin1_code":"81",
    "gn:admin2_code":"3054",
    "gn:admin3_code":"305440.0",
    "gn:admin4_code":"30544018.0",
    "gn:asciiname":"South Bansgari",
    "gn:country_code":"BD",
    "gn:dem":13,
    "gn:feature_class":"P",
    "gn:feature_code":"PPL",
    "gn:name":"South B\u0101nsg\u0101ri",
    "gn:population":0,
    "gn:timezone":"Asia/Dhaka",
    "iso:country":"BD",
    "name:und_x_variant":[
        "Dakhin B\u0101nsg\u0101ri",
        "South Banshgari",
        "South B\u0101nsg\u0101ri"
    ],
    "wof:name":"South Bansgari",
    "wof:placetype":"locality"
},
  "geometry": {"coordinates":[90.33671,23.07202],"type":"Point"}
}