{
  "type": "Feature",
  "properties": {
    "gn:admin1_code":"87",
    "gn:admin2_code":"5549",
    "gn:admin3_code":"554961.0",
    "gn:admin4_code":"55496137.0",
    "gn:asciiname":"Mollapara",
    "gn:country_code":"BD",
    "gn:dem":32,
    "gn:feature_class":"P",
    "gn:feature_code":"PPL",
    "gn:name":"Moll\u0101p\u0101ra",
    "gn:population":0,
    "gn:timezone":"Asia/Dhaka",
    "iso:country":"BD",
    "name:ben_x_preferred":[
        "Moll\u0101p\u0101ra"
    ],
    "wof:name":"Mollapara",
    "wof:placetype":"locality"
},
  "geometry": {"coordinates":[89.79867,25.9923],"type":"Point"}
}