{
  "type": "Feature",
  "properties": {
    "gn:admin1_code":"87",
    "gn:admin2_code":"5594.0",
    "gn:admin3_code":"559486.0",
    "gn:admin4_code":"55948679.0",
    "gn:asciiname":"Karnath",
    "gn:country_code":"BD",
    "gn:dem":52,
    "gn:feature_class":"P",
    "gn:feature_code":"PPL",
    "gn:name":"K\u0101rnath",
    "gn:population":0,
    "gn:timezone":"Asia/Dhaka",
    "iso:country":"BD",
    "name:ben_x_preferred":[
        "K\u0101rnath"
    ],
    "wof:name":"Karnath",
    "wof:placetype":"locality"
},
  "geometry": {"coordinates":[88.27304000000002,25.96341],"type":"Point"}
}