{
  "type": "Feature",
  "properties": {
    "gn:admin1_code":"87",
    "gn:admin2_code":"5594.0",
    "gn:admin3_code":"559482.0",
    "gn:admin4_code":"55948269.0",
    "gn:asciiname":"Ghughua",
    "gn:country_code":"BD",
    "gn:dem":48,
    "gn:feature_class":"P",
    "gn:feature_code":"PPL",
    "gn:name":"Ghughua",
    "gn:population":0,
    "gn:timezone":"Asia/Dhaka",
    "iso:country":"BD",
    "name:ben_x_preferred":[
        "Ghughua"
    ],
    "wof:name":"Ghughua",
    "wof:placetype":"locality"
},
  "geometry": {"coordinates":[88.3903,25.89209],"type":"Point"}
}