{
  "type": "Feature",
  "properties": {
    "gn:admin1_code":"H",
    "gn:admin2_code":"3072",
    "gn:admin3_code":"307283.0",
    "gn:admin4_code":"30728331.0",
    "gn:asciiname":"Kona Binna",
    "gn:country_code":"BD",
    "gn:dem":14,
    "gn:feature_class":"P",
    "gn:feature_code":"PPL",
    "gn:name":"Kona Binna",
    "gn:population":0,
    "gn:timezone":"Asia/Dhaka",
    "iso:country":"BD",
    "wof:name":"Kona Binna",
    "wof:placetype":"locality"
},
  "geometry": {"coordinates":[90.66831000000001,24.94435],"type":"Point"}
}