{
  "type": "Feature",
  "properties": {
    "gn:admin1_code":"81",
    "gn:admin2_code":"3068",
    "gn:admin3_code":"306807.0",
    "gn:admin4_code":"30680771.0",
    "gn:asciiname":"Nandarampur",
    "gn:country_code":"BD",
    "gn:dem":18,
    "gn:feature_class":"P",
    "gn:feature_code":"PPL",
    "gn:name":"Nandar\u0101mpur",
    "gn:population":0,
    "gn:timezone":"Asia/Dhaka",
    "iso:country":"BD",
    "wof:name":"Nandarampur",
    "wof:placetype":"locality"
},
  "geometry": {"coordinates":[90.80368,24.13511],"type":"Point"}
}