{
  "type": "Feature",
  "properties": {
    "gn:admin1_code":"84",
    "gn:admin2_code":"2030",
    "gn:admin3_code":"203094.0",
    "gn:admin4_code":"20309466.0",
    "gn:asciiname":"Khichara",
    "gn:country_code":"BD",
    "gn:dem":11,
    "gn:feature_class":"P",
    "gn:feature_code":"PPL",
    "gn:name":"Khichara",
    "gn:population":0,
    "gn:timezone":"Asia/Dhaka",
    "iso:country":"BD",
    "wof:name":"Khichara",
    "wof:placetype":"locality"
},
  "geometry": {"coordinates":[91.38333,22.88333],"type":"Point"}
}