{
  "type": "Feature",
  "properties": {
    "gn:admin1_code":"81",
    "gn:admin2_code":"3067",
    "gn:admin3_code":"306758.0",
    "gn:admin4_code":"30675885.0",
    "gn:asciiname":"Siddhirganj",
    "gn:country_code":"BD",
    "gn:dem":8,
    "gn:feature_class":"P",
    "gn:feature_code":"PPL",
    "gn:name":"Siddhirganj",
    "gn:population":0,
    "gn:timezone":"Asia/Dhaka",
    "iso:country":"BD",
    "name:und_x_variant":[
        "Sidhirganj",
        "Siddhirganj"
    ],
    "wof:name":"Siddhirganj",
    "wof:placetype":"locality"
},
  "geometry": {"coordinates":[90.5149,23.69127000000001],"type":"Point"}
}