{
  "type": "Feature",
  "properties": {
    "gn:admin1_code":"87",
    "gn:admin2_code":"5527",
    "gn:admin3_code":"552710.0",
    "gn:admin4_code":"55271071.0",
    "gn:asciiname":"Khanpur",
    "gn:country_code":"BD",
    "gn:dem":32,
    "gn:feature_class":"P",
    "gn:feature_code":"PPL",
    "gn:name":"Khanpur",
    "gn:population":0,
    "gn:timezone":"Asia/Dhaka",
    "iso:country":"BD",
    "name:ara_x_preferred":[
        "\u062e\u0627\u0646\u0628\u0648\u0631"
    ],
    "name:bel_x_preferred":[
        "\u0425\u0430\u043d\u043f\u0443\u0440"
    ],
    "name:ben_x_preferred":[
        "Khanpur"
    ],
    "name:ces_x_preferred":[
        "Chanp\u00far"
    ],
    "name:fas_x_preferred":[
        "\u062e\u0627\u0646\u067e\u0648\u0631"
    ],
    "name:fra_x_preferred":[
        "Khanpur"
    ],
    "name:ita_x_preferred":[
        "Khanpur"
    ],
    "name:lit_x_preferred":[
        "Chanpuras"
    ],
    "name:mlg_x_preferred":[
        "Khanpur"
    ],
    "name:msa_x_preferred":[
        "Khanpur"
    ],
    "name:nld_x_preferred":[
        "Khanpur"
    ],
    "name:pol_x_preferred":[
        "Khanpur"
    ],
    "name:por_x_preferred":[
        "Khanpur"
    ],
    "name:pus_x_preferred":[
        "\u062e\u0627\u0646\u067e\u0648\u0631"
    ],
    "name:rus_x_preferred":[
        "\u0425\u0430\u043d\u043f\u0443\u0440"
    ],
    "name:srp_x_preferred":[
        "\u0425\u0430\u043d\u043f\u0443\u0440"
    ],
    "name:swe_x_preferred":[
        "Khanpur"
    ],
    "name:urd_x_preferred":[
        "\u062e\u0627\u0646 \u067e\u0648\u0631"
    ],
    "name:war_x_preferred":[
        "Khanpur"
    ],
    "wof:name":"Khanpur",
    "wof:placetype":"locality"
},
  "geometry": {"coordinates":[89.01576,25.41438],"type":"Point"}
}