{
  "type": "Feature",
  "properties": {
    "gn:admin1_code":"83",
    "gn:admin2_code":"5038.0",
    "gn:admin3_code":"503858.0",
    "gn:admin4_code":"50385838.0",
    "gn:asciiname":"Harunja",
    "gn:country_code":"BD",
    "gn:dem":26,
    "gn:feature_class":"P",
    "gn:feature_code":"PPL",
    "gn:name":"H\u0101runja",
    "gn:population":0,
    "gn:timezone":"Asia/Dhaka",
    "iso:country":"BD",
    "wof:name":"Harunja",
    "wof:placetype":"locality"
},
  "geometry": {"coordinates":[89.15089,25.0448],"type":"Point"}
}