{
  "type": "Feature",
  "properties": {
    "gn:admin1_code":"83",
    "gn:admin2_code":"5070.0",
    "gn:admin3_code":"507066.0",
    "gn:admin4_code":"50706622.0",
    "gn:asciiname":"Char Bagdanga",
    "gn:country_code":"BD",
    "gn:dem":25,
    "gn:feature_class":"P",
    "gn:feature_code":"PPL",
    "gn:name":"Char B\u0101gd\u0101nga",
    "gn:population":0,
    "gn:timezone":"Asia/Dhaka",
    "iso:country":"BD",
    "name:ben_x_preferred":[
        "Char B\u0101gd\u0101nga"
    ],
    "name:ben_x_variant":[
        "Char B\u0101ghd\u0101nga"
    ],
    "wof:name":"Char Bagdanga",
    "wof:placetype":"locality"
},
  "geometry": {"coordinates":[88.21218,24.51966],"type":"Point"}
}