{
  "type": "Feature",
  "properties": {
    "gn:admin1_code":"82",
    "gn:admin2_code":"4055.0",
    "gn:admin3_code":"405585.0",
    "gn:admin4_code":"40558535.0",
    "gn:asciiname":"Chhota Amian",
    "gn:country_code":"BD",
    "gn:dem":9,
    "gn:feature_class":"P",
    "gn:feature_code":"PPL",
    "gn:name":"Chhota Amian",
    "gn:population":0,
    "gn:timezone":"Asia/Dhaka",
    "iso:country":"BD",
    "name:ben_x_preferred":[
        "Chhota Amian"
    ],
    "wof:name":"Chhota Amian",
    "wof:placetype":"locality"
},
  "geometry": {"coordinates":[89.26349,23.38636],"type":"Point"}
}