{
  "type": "Feature",
  "properties": {
    "gn:admin1_code":"81",
    "gn:admin2_code":"3056.0",
    "gn:admin3_code":"305670.0",
    "gn:admin4_code":"30567038.0",
    "gn:asciiname":"Bil Taluk",
    "gn:country_code":"BD",
    "gn:dem":10,
    "gn:feature_class":"P",
    "gn:feature_code":"PPL",
    "gn:name":"Bil T\u0101luk",
    "gn:population":0,
    "gn:timezone":"Asia/Dhaka",
    "iso:country":"BD",
    "wof:name":"Bil Taluk",
    "wof:placetype":"locality"
},
  "geometry": {"coordinates":[89.98073000000002,23.9745],"type":"Point"}
}