{
  "type": "Feature",
  "properties": {
    "gn:admin1_code":"H",
    "gn:admin2_code":"3072",
    "gn:admin3_code":"307274.0",
    "gn:admin4_code":"30727407.0",
    "gn:asciiname":"Ramkrishnapur",
    "gn:country_code":"BD",
    "gn:dem":14,
    "gn:feature_class":"P",
    "gn:feature_code":"PPL",
    "gn:name":"R\u0101mkrishnapur",
    "gn:population":0,
    "gn:timezone":"Asia/Dhaka",
    "iso:country":"BD",
    "wof:name":"Ramkrishnapur",
    "wof:placetype":"locality"
},
  "geometry": {"coordinates":[90.76694999999999,24.86113],"type":"Point"}
}