{
  "type": "Feature",
  "properties": {
    "gn:admin1_code":"81",
    "gn:admin2_code":"3054.0",
    "gn:admin3_code":"305454.0",
    "gn:admin4_code":"30545435.0",
    "gn:asciiname":"Banikerpara",
    "gn:country_code":"BD",
    "gn:dem":7,
    "gn:feature_class":"P",
    "gn:feature_code":"PPL",
    "gn:name":"Banikerp\u0101ra",
    "gn:population":0,
    "gn:timezone":"Asia/Dhaka",
    "iso:country":"BD",
    "wof:name":"Banikerpara",
    "wof:placetype":"locality"
},
  "geometry": {"coordinates":[90.21106,23.13687],"type":"Point"}
}