{
  "type": "Feature",
  "properties": {
    "gn:admin1_code":"84",
    "gn:admin2_code":"2075.0",
    "gn:admin3_code":"207536.0",
    "gn:admin4_code":"20753638.0",
    "gn:asciiname":"Dasher Hat",
    "gn:country_code":"BD",
    "gn:dem":13,
    "gn:feature_class":"P",
    "gn:feature_code":"PPL",
    "gn:name":"Dasher H\u0101t",
    "gn:population":0,
    "gn:timezone":"Asia/Dhaka",
    "iso:country":"BD",
    "name:und_x_variant":[
        "Dasharhat",
        "Dasher H\u0101t"
    ],
    "wof:name":"Dasher Hat",
    "wof:placetype":"locality"
},
  "geometry": {"coordinates":[91.08987999999999,22.36392],"type":"Point"}
}