{
  "type": "Feature",
  "properties": {
    "gn:admin1_code":"86",
    "gn:admin2_code":"6036",
    "gn:admin3_code":"603626.0",
    "gn:admin4_code":"60362647.0",
    "gn:asciiname":"Rakhi",
    "gn:country_code":"BD",
    "gn:dem":26,
    "gn:feature_class":"P",
    "gn:feature_code":"PPL",
    "gn:name":"R\u0101khi",
    "gn:population":0,
    "gn:timezone":"Asia/Dhaka",
    "iso:country":"BD",
    "name:ben_x_preferred":[
        "\u09b0\u09be\u0996\u09c0"
    ],
    "name:hin_x_preferred":[
        "\u0930\u093e\u0916\u0940"
    ],
    "name:mar_x_preferred":[
        "\u0930\u093e\u0916\u0940"
    ],
    "name:und_x_variant":[
        "Raki",
        "R\u0101khi"
    ],
    "wof:name":"Rakhi",
    "wof:placetype":"locality"
},
  "geometry": {"coordinates":[91.55986,24.1464],"type":"Point"}
}