{
  "type": "Feature",
  "properties": {
    "gn:admin1_code":"84",
    "gn:admin2_code":"2012.0",
    "gn:admin3_code":"201204.0",
    "gn:admin4_code":"20120459.0",
    "gn:asciiname":"Darikandi",
    "gn:country_code":"BD",
    "gn:dem":13,
    "gn:feature_class":"P",
    "gn:feature_code":"PPL",
    "gn:name":"Darik\u0101ndi",
    "gn:population":0,
    "gn:timezone":"Asia/Dhaka",
    "iso:country":"BD",
    "wof:name":"Darikandi",
    "wof:placetype":"locality"
},
  "geometry": {"coordinates":[90.87642,23.79622],"type":"Point"}
}