{
  "type": "Feature",
  "properties": {
    "gn:admin1_code":"00",
    "gn:asciiname":"Mithuar Char",
    "gn:country_code":"BD",
    "gn:dem":0,
    "gn:feature_class":"P",
    "gn:feature_code":"PPL",
    "gn:name":"Mithu\u0101r Char",
    "gn:population":0,
    "gn:timezone":"Asia/Dhaka",
    "iso:country":"BD",
    "wof:name":"Mithuar Char",
    "wof:placetype":"locality"
},
  "geometry": {"coordinates":[90.53333000000001,22.78333],"type":"Point"}
}