{
  "type": "Feature",
  "properties": {
    "gn:admin1_code":"82",
    "gn:admin2_code":"4057.0",
    "gn:admin3_code":"405787.0",
    "gn:admin4_code":"40578795.0",
    "gn:asciiname":"Tangi",
    "gn:country_code":"BD",
    "gn:dem":22,
    "gn:feature_class":"P",
    "gn:feature_code":"PPL",
    "gn:name":"Tangi",
    "gn:population":0,
    "gn:timezone":"Asia/Dhaka",
    "iso:country":"BD",
    "name:ben_x_preferred":[
        "Tangi"
    ],
    "name:bre_x_preferred":[
        "Tangi"
    ],
    "name:ceb_x_preferred":[
        "Tangi"
    ],
    "name:fra_x_preferred":[
        "Tangi"
    ],
    "name:ita_x_preferred":[
        "Tangi"
    ],
    "name:swe_x_preferred":[
        "Tangi"
    ],
    "name:tgl_x_preferred":[
        "Tangi"
    ],
    "wof:name":"Tangi",
    "wof:placetype":"locality"
},
  "geometry": {"coordinates":[88.70553000000002,23.69253],"type":"Point"}
}