{
  "type": "Feature",
  "properties": {
    "gn:admin1_code":"82",
    "gn:admin2_code":"4041.0",
    "gn:admin3_code":"404147.0",
    "gn:admin4_code":"40414789.0",
    "gn:asciiname":"Bara Gopalpur",
    "gn:country_code":"BD",
    "gn:dem":12,
    "gn:feature_class":"P",
    "gn:feature_code":"PPL",
    "gn:name":"Bara Gop\u0101lpur",
    "gn:population":0,
    "gn:timezone":"Asia/Dhaka",
    "iso:country":"BD",
    "name:ben_x_preferred":[
        "Bara Gop\u0101lpur"
    ],
    "wof:name":"Bara Gopalpur",
    "wof:placetype":"locality"
},
  "geometry": {"coordinates":[89.25717,23.1883],"type":"Point"}
}