{
  "type": "Feature",
  "properties": {
    "gn:admin1_code":"84",
    "gn:admin2_code":"2022.0",
    "gn:admin3_code":"202249.0",
    "gn:admin4_code":"20224935.0",
    "gn:asciiname":"Amuddiaghata",
    "gn:country_code":"BD",
    "gn:dem":27,
    "gn:feature_class":"P",
    "gn:feature_code":"PPL",
    "gn:name":"Amuddiagh\u0101ta",
    "gn:population":0,
    "gn:timezone":"Asia/Dhaka",
    "iso:country":"BD",
    "name:ben_x_preferred":[
        "Amuddiagh\u0101ta"
    ],
    "wof:name":"Amuddiaghata",
    "wof:placetype":"locality"
},
  "geometry": {"coordinates":[91.97861,21.53964],"type":"Point"}
}