{
  "type": "Feature",
  "properties": {
    "gn:admin1_code":"81",
    "gn:admin2_code":"3056",
    "gn:admin3_code":"305622.0",
    "gn:admin4_code":"30562283.0",
    "gn:asciiname":"Nindapara",
    "gn:country_code":"BD",
    "gn:dem":13,
    "gn:feature_class":"P",
    "gn:feature_code":"PPL",
    "gn:name":"Nind\u0101p\u0101ra",
    "gn:population":0,
    "gn:timezone":"Asia/Dhaka",
    "iso:country":"BD",
    "wof:name":"Nindapara",
    "wof:placetype":"locality"
},
  "geometry": {"coordinates":[89.93848,23.91014],"type":"Point"}
}