{
  "type": "Feature",
  "properties": {
    "gn:admin1_code":"82",
    "gn:admin2_code":"4087.0",
    "gn:admin3_code":"408725.0",
    "gn:admin4_code":"40872515.0",
    "gn:asciiname":"Kuraldanga",
    "gn:country_code":"BD",
    "gn:dem":8,
    "gn:feature_class":"P",
    "gn:feature_code":"PPL",
    "gn:name":"Kurald\u0101nga",
    "gn:population":0,
    "gn:timezone":"Asia/Dhaka",
    "iso:country":"BD",
    "name:ben_x_preferred":[
        "Kurald\u0101nga"
    ],
    "wof:name":"Kuraldanga",
    "wof:placetype":"locality"
},
  "geometry": {"coordinates":[88.96807,22.60357],"type":"Point"}
}