{
  "type": "Feature",
  "properties": {
    "gn:admin1_code":"82",
    "gn:admin2_code":"4050.0",
    "gn:admin3_code":"405079.0",
    "gn:admin4_code":"40507982.0",
    "gn:asciiname":"Manikdia",
    "gn:country_code":"BD",
    "gn:dem":16,
    "gn:feature_class":"P",
    "gn:feature_code":"PPL",
    "gn:name":"M\u0101nikdia",
    "gn:population":0,
    "gn:timezone":"Asia/Dhaka",
    "iso:country":"BD",
    "name:ben_x_preferred":[
        "M\u0101nikdia"
    ],
    "wof:name":"Manikdia",
    "wof:placetype":"locality"
},
  "geometry": {"coordinates":[89.04983,23.72909],"type":"Point"}
}