{
  "type": "Feature",
  "properties": {
    "gn:admin1_code":"83",
    "gn:admin2_code":"5070.0",
    "gn:admin3_code":"507066.0",
    "gn:admin4_code":"50706633.0",
    "gn:asciiname":"Nadhai Krishnapur",
    "gn:country_code":"BD",
    "gn:dem":35,
    "gn:feature_class":"P",
    "gn:feature_code":"PPL",
    "gn:name":"N\u0101dhai Krishnapur",
    "gn:population":0,
    "gn:timezone":"Asia/Dhaka",
    "iso:country":"BD",
    "name:ben_x_preferred":[
        "N\u0101dhai Krishnapur"
    ],
    "wof:name":"Nadhai Krishnapur",
    "wof:placetype":"locality"
},
  "geometry": {"coordinates":[88.31919000000001,24.68587],"type":"Point"}
}