{
  "type": "Feature",
  "properties": {
    "gn:admin1_code":"82",
    "gn:admin2_code":"4041.0",
    "gn:admin3_code":"404111.0",
    "gn:admin4_code":"40411194.0",
    "gn:asciiname":"Bara Barni",
    "gn:country_code":"BD",
    "gn:dem":15,
    "gn:feature_class":"P",
    "gn:feature_code":"PPL",
    "gn:name":"Bara Barni",
    "gn:population":0,
    "gn:timezone":"Asia/Dhaka",
    "iso:country":"BD",
    "name:ben_x_preferred":[
        "Bara Barni"
    ],
    "wof:name":"Bara Barni",
    "wof:placetype":"locality"
},
  "geometry": {"coordinates":[88.92099,23.26479],"type":"Point"}
}