{
  "type": "Feature",
  "properties": {
    "gn:admin1_code":"H",
    "gn:admin2_code":"3061",
    "gn:admin3_code":"306122.0",
    "gn:admin4_code":"30612282.0",
    "gn:asciiname":"Rauha",
    "gn:country_code":"BD",
    "gn:dem":16,
    "gn:feature_class":"P",
    "gn:feature_code":"PPL",
    "gn:name":"Rauha",
    "gn:population":0,
    "gn:timezone":"Asia/Dhaka",
    "iso:country":"BD",
    "name:und_x_variant":[
        "Rouha",
        "Rauha"
    ],
    "wof:name":"Rauha",
    "wof:placetype":"locality"
},
  "geometry": {"coordinates":[90.52052999999999,24.48344],"type":"Point"}
}