{
  "type": "Feature",
  "properties": {
    "gn:admin1_code":"81",
    "gn:admin2_code":"3093.0",
    "gn:admin3_code":"309366.0",
    "gn:admin4_code":"30936679.0",
    "gn:asciiname":"Baor Kumarjani",
    "gn:country_code":"BD",
    "gn:dem":13,
    "gn:feature_class":"P",
    "gn:feature_code":"PPL",
    "gn:name":"B\u0101or Kum\u0101rj\u0101ni",
    "gn:population":0,
    "gn:timezone":"Asia/Dhaka",
    "iso:country":"BD",
    "wof:name":"Baor Kumarjani",
    "wof:placetype":"locality"
},
  "geometry": {"coordinates":[90.10695,24.10656],"type":"Point"}
}