{
  "type": "Feature",
  "properties": {
    "gn:admin1_code":"84",
    "gn:admin2_code":"2013",
    "gn:admin3_code":"201376.0",
    "gn:admin4_code":"20137643.0",
    "gn:asciiname":"Sarpar",
    "gn:country_code":"BD",
    "gn:dem":10,
    "gn:feature_class":"P",
    "gn:feature_code":"PPL",
    "gn:name":"S\u0101rp\u0101r",
    "gn:population":0,
    "gn:timezone":"Asia/Dhaka",
    "iso:country":"BD",
    "wof:name":"Sarpar",
    "wof:placetype":"locality"
},
  "geometry": {"coordinates":[90.77795999999999,23.36622],"type":"Point"}
}