{
  "type": "Feature",
  "properties": {
    "gn:admin1_code":"83",
    "gn:asciiname":"Pacharia",
    "gn:country_code":"BD",
    "gn:dem":25,
    "gn:feature_class":"P",
    "gn:feature_code":"PPL",
    "gn:name":"Pach\u0101ria",
    "gn:population":0,
    "gn:timezone":"Asia/Dhaka",
    "iso:country":"BD",
    "name:ben_x_preferred":[
        "Pach\u0101ria"
    ],
    "wof:name":"Pacharia",
    "wof:placetype":"locality"
},
  "geometry": {"coordinates":[89.46015,25.09585],"type":"Point"}
}