{
  "type": "Feature",
  "properties": {
    "gn:admin1_code":"83",
    "gn:asciiname":"Chhayghatia",
    "gn:country_code":"BD",
    "gn:dem":26,
    "gn:feature_class":"P",
    "gn:feature_code":"PPL",
    "gn:name":"Chhayghatia",
    "gn:population":0,
    "gn:timezone":"Asia/Dhaka",
    "iso:country":"BD",
    "name:ben_x_preferred":[
        "Chhayghatia"
    ],
    "wof:name":"Chhayghatia",
    "wof:placetype":"locality"
},
  "geometry": {"coordinates":[89.35688,25.10834],"type":"Point"}
}