{
  "type": "Feature",
  "properties": {
    "gn:admin1_code":"84",
    "gn:admin2_code":"2013",
    "gn:admin3_code":"201345.0",
    "gn:admin4_code":"20134559.0",
    "gn:asciiname":"Mandartail",
    "gn:country_code":"BD",
    "gn:dem":11,
    "gn:feature_class":"P",
    "gn:feature_code":"PPL",
    "gn:name":"M\u0101nd\u0101rtail",
    "gn:population":0,
    "gn:timezone":"Asia/Dhaka",
    "iso:country":"BD",
    "name:und_x_variant":[
        "Mandartali",
        "M\u0101nd\u0101rtail"
    ],
    "wof:name":"Mandartail",
    "wof:placetype":"locality"
},
  "geometry": {"coordinates":[90.81514,23.12507],"type":"Point"}
}