{
  "type": "Feature",
  "properties": {
    "gn:admin1_code":"87",
    "gn:admin2_code":"5532",
    "gn:admin3_code":"553224.0",
    "gn:admin4_code":"55322473.0",
    "gn:asciiname":"Uzirdharanibari",
    "gn:country_code":"BD",
    "gn:dem":25,
    "gn:feature_class":"P",
    "gn:feature_code":"PPL",
    "gn:name":"Uzirdharanibari",
    "gn:population":0,
    "gn:timezone":"Asia/Dhaka",
    "iso:country":"BD",
    "name:ben_x_preferred":[
        "Uzirdharanibari"
    ],
    "wof:name":"Uzirdharanibari",
    "wof:placetype":"locality"
},
  "geometry": {"coordinates":[89.52144,25.41283],"type":"Point"}
}