{
  "type": "Feature",
  "properties": {
    "gn:admin1_code":"82",
    "gn:admin2_code":"4050.0",
    "gn:admin3_code":"405071.0",
    "gn:admin4_code":"40507125.0",
    "gn:asciiname":"Bahula Gobindapur",
    "gn:country_code":"BD",
    "gn:dem":16,
    "gn:feature_class":"P",
    "gn:feature_code":"PPL",
    "gn:name":"Bahula Gobindapur",
    "gn:population":0,
    "gn:timezone":"Asia/Dhaka",
    "iso:country":"BD",
    "name:ben_x_preferred":[
        "Bahula Gobindapur"
    ],
    "name:ben_x_variant":[
        "Bahala Gobindapur"
    ],
    "wof:name":"Bahula Gobindapur",
    "wof:placetype":"locality"
},
  "geometry": {"coordinates":[89.18069,23.85196],"type":"Point"}
}