{
  "type": "Feature",
  "properties": {
    "gn:admin1_code":"81",
    "gn:admin2_code":"3082.0",
    "gn:admin3_code":"308276.0",
    "gn:admin4_code":"30827680.0",
    "gn:asciiname":"Bethulia",
    "gn:country_code":"BD",
    "gn:dem":16,
    "gn:feature_class":"P",
    "gn:feature_code":"PPL",
    "gn:name":"Bethulia",
    "gn:population":0,
    "gn:timezone":"Asia/Dhaka",
    "iso:country":"BD",
    "name:bre_x_preferred":[
        "Baituloua"
    ],
    "name:pol_x_preferred":[
        "Betulia"
    ],
    "name:swe_x_preferred":[
        "Betylua"
    ],
    "wof:name":"Bethulia",
    "wof:placetype":"locality"
},
  "geometry": {"coordinates":[89.61425,23.73851],"type":"Point"}
}