{
  "type": "Feature",
  "properties": {
    "gn:admin1_code":"81",
    "gn:admin2_code":"3093.0",
    "gn:admin3_code":"309385.0",
    "gn:admin4_code":"30938513.0",
    "gn:asciiname":"Baga",
    "gn:country_code":"BD",
    "gn:dem":25,
    "gn:feature_class":"P",
    "gn:feature_code":"PPL",
    "gn:name":"Baga",
    "gn:population":0,
    "gn:timezone":"Asia/Dhaka",
    "iso:country":"BD",
    "wof:name":"Baga",
    "wof:placetype":"locality"
},
  "geometry": {"coordinates":[90.14781000000001,24.34114],"type":"Point"}
}