{
  "type": "Feature",
  "properties": {
    "gn:admin1_code":"81",
    "gn:admin2_code":"3059",
    "gn:admin3_code":"305984.0",
    "gn:admin4_code":"30598488.0",
    "gn:asciiname":"Mattagaon",
    "gn:country_code":"BD",
    "gn:dem":8,
    "gn:feature_class":"P",
    "gn:feature_code":"PPL",
    "gn:name":"Matt\u0101gaon",
    "gn:population":0,
    "gn:timezone":"Asia/Dhaka",
    "iso:country":"BD",
    "wof:name":"Mattagaon",
    "wof:placetype":"locality"
},
  "geometry": {"coordinates":[90.24821,23.53883],"type":"Point"}
}