{
  "type": "Feature",
  "properties": {
    "gn:admin1_code":"84",
    "gn:admin2_code":"2013",
    "gn:admin3_code":"201349.0",
    "gn:admin4_code":"20134970.0",
    "gn:asciiname":"Menapur",
    "gn:country_code":"BD",
    "gn:dem":9,
    "gn:feature_class":"P",
    "gn:feature_code":"PPL",
    "gn:name":"Men\u0101pur",
    "gn:population":0,
    "gn:timezone":"Asia/Dhaka",
    "iso:country":"BD",
    "wof:name":"Menapur",
    "wof:placetype":"locality"
},
  "geometry": {"coordinates":[90.76045999999999,23.31149],"type":"Point"}
}