{
  "type": "Feature",
  "properties": {
    "gn:admin1_code":"87",
    "gn:admin2_code":"5585.0",
    "gn:admin3_code":"558573.0",
    "gn:admin4_code":"55857376.0",
    "gn:asciiname":"Majpara",
    "gn:country_code":"BD",
    "gn:dem":30,
    "gn:feature_class":"P",
    "gn:feature_code":"PPL",
    "gn:name":"M\u0101jp\u0101ra",
    "gn:population":0,
    "gn:timezone":"Asia/Dhaka",
    "iso:country":"BD",
    "name:ben_x_preferred":[
        "M\u0101jp\u0101ra"
    ],
    "wof:name":"Majpara",
    "wof:placetype":"locality"
},
  "geometry": {"coordinates":[89.39333000000001,25.64056],"type":"Point"}
}