{
  "type": "Feature",
  "properties": {
    "gn:admin1_code":"87",
    "gn:admin2_code":"5527.0",
    "gn:admin3_code":"552712.0",
    "gn:admin4_code":"55271269.0",
    "gn:asciiname":"Nagaripara",
    "gn:country_code":"BD",
    "gn:dem":53,
    "gn:feature_class":"P",
    "gn:feature_code":"PPL",
    "gn:name":"N\u0101g\u0101rip\u0101ra",
    "gn:population":0,
    "gn:timezone":"Asia/Dhaka",
    "iso:country":"BD",
    "name:ben_x_preferred":[
        "N\u0101g\u0101rip\u0101ra"
    ],
    "wof:name":"Nagaripara",
    "wof:placetype":"locality"
},
  "geometry": {"coordinates":[88.68074,25.9827],"type":"Point"}
}