{
  "type": "Feature",
  "properties": {
    "gn:admin1_code":"87",
    "gn:admin2_code":"5585.0",
    "gn:admin3_code":"558573.0",
    "gn:admin4_code":"55857385.0",
    "gn:asciiname":"Salmara",
    "gn:country_code":"BD",
    "gn:dem":31,
    "gn:feature_class":"P",
    "gn:feature_code":"PPL",
    "gn:name":"S\u0101lm\u0101ra",
    "gn:population":0,
    "gn:timezone":"Asia/Dhaka",
    "iso:country":"BD",
    "name:ben_x_preferred":[
        "S\u0101lm\u0101ra"
    ],
    "wof:name":"Salmara",
    "wof:placetype":"locality"
},
  "geometry": {"coordinates":[89.45044,25.67696],"type":"Point"}
}