{
  "type": "Feature",
  "properties": {
    "gn:admin1_code":"87",
    "gn:admin2_code":"5585.0",
    "gn:admin3_code":"558592.0",
    "gn:admin4_code":"55859247.0",
    "gn:asciiname":"Hajipur",
    "gn:country_code":"BD",
    "gn:dem":41,
    "gn:feature_class":"P",
    "gn:feature_code":"PPL",
    "gn:name":"H\u0101j\u012bpur",
    "gn:population":0,
    "gn:timezone":"Asia/Dhaka",
    "iso:country":"BD",
    "name:ben_x_preferred":[
        "H\u0101j\u012bpur"
    ],
    "name:ben_x_variant":[
        "Hazipur"
    ],
    "name:und_x_variant":[
        "Hazipur",
        "H\u0101j\u012bpur"
    ],
    "wof:name":"Hajipur",
    "wof:placetype":"locality"
},
  "geometry": {"coordinates":[89.10423,25.80111],"type":"Point"}
}