{
  "type": "Feature",
  "properties": {
    "gn:admin1_code":"82",
    "gn:admin2_code":"4047.0",
    "gn:admin3_code":"404748.0",
    "gn:admin4_code":"40474800.0",
    "gn:asciiname":"Jugipot",
    "gn:country_code":"BD",
    "gn:dem":8,
    "gn:feature_class":"P",
    "gn:feature_code":"PPL",
    "gn:name":"Jugipot",
    "gn:population":0,
    "gn:timezone":"Asia/Dhaka",
    "iso:country":"BD",
    "name:ben_x_preferred":[
        "Jugipot"
    ],
    "wof:name":"Jugipot",
    "wof:placetype":"locality"
},
  "geometry": {"coordinates":[89.49839,22.90675],"type":"Point"}
}