{
  "type": "Feature",
  "properties": {
    "gn:admin1_code":"83",
    "gn:admin2_code":"5076.0",
    "gn:admin3_code":"507683.0",
    "gn:admin4_code":"50768347.0",
    "gn:asciiname":"Nawagram",
    "gn:country_code":"BD",
    "gn:dem":13,
    "gn:feature_class":"P",
    "gn:feature_code":"PPL",
    "gn:name":"Naw\u0101gr\u0101m",
    "gn:population":0,
    "gn:timezone":"Asia/Dhaka",
    "iso:country":"BD",
    "name:ben_x_preferred":[
        "Naw\u0101gr\u0101m"
    ],
    "wof:name":"Nawagram",
    "wof:placetype":"locality"
},
  "geometry": {"coordinates":[89.51288000000002,23.85133],"type":"Point"}
}