{
  "type": "Feature",
  "properties": {
    "gn:admin1_code":"84",
    "gn:admin2_code":"2019",
    "gn:admin3_code":"201918.0",
    "gn:admin4_code":"20191806.0",
    "gn:asciiname":"Kanchanpur",
    "gn:country_code":"BD",
    "gn:dem":14,
    "gn:feature_class":"P",
    "gn:feature_code":"PPL",
    "gn:name":"K\u0101nchanpur",
    "gn:population":0,
    "gn:timezone":"Asia/Dhaka",
    "iso:country":"BD",
    "wof:name":"Kanchanpur",
    "wof:placetype":"locality"
},
  "geometry": {"coordinates":[91.18333,23.53333],"type":"Point"}
}