{
  "type": "Feature",
  "properties": {
    "gn:admin1_code":"82",
    "gn:admin2_code":"4044.0",
    "gn:admin3_code":"404471.0",
    "gn:admin4_code":"40447159.0",
    "gn:asciiname":"Nanchanpur",
    "gn:country_code":"BD",
    "gn:dem":13,
    "gn:feature_class":"P",
    "gn:feature_code":"PPL",
    "gn:name":"N\u0101nchanpur",
    "gn:population":0,
    "gn:timezone":"Asia/Dhaka",
    "iso:country":"BD",
    "name:ben_x_preferred":[
        "N\u0101nchanpur"
    ],
    "wof:name":"Nanchanpur",
    "wof:placetype":"locality"
},
  "geometry": {"coordinates":[88.72111,23.27971],"type":"Point"}
}