{
  "type": "Feature",
  "properties": {
    "gn:admin1_code":"87",
    "gn:admin2_code":"5594.0",
    "gn:admin3_code":"559486.0",
    "gn:admin4_code":"55948663.0",
    "gn:asciiname":"Lehempa",
    "gn:country_code":"BD",
    "gn:dem":42,
    "gn:feature_class":"P",
    "gn:feature_code":"PPL",
    "gn:name":"Lehempa",
    "gn:population":0,
    "gn:timezone":"Asia/Dhaka",
    "iso:country":"BD",
    "name:ben_x_preferred":[
        "Lehempa"
    ],
    "wof:name":"Lehempa",
    "wof:placetype":"locality"
},
  "geometry": {"coordinates":[88.24625999999998,25.83183],"type":"Point"}
}