{
  "type": "Feature",
  "properties": {
    "gn:admin1_code":"87",
    "gn:admin2_code":"5594.0",
    "gn:admin3_code":"559486.0",
    "gn:admin4_code":"55948679.0",
    "gn:asciiname":"Bhedail",
    "gn:country_code":"BD",
    "gn:dem":51,
    "gn:feature_class":"P",
    "gn:feature_code":"PPL",
    "gn:name":"Bhed\u0101il",
    "gn:population":0,
    "gn:timezone":"Asia/Dhaka",
    "iso:country":"BD",
    "name:ben_x_preferred":[
        "Bhed\u0101il"
    ],
    "wof:name":"Bhedail",
    "wof:placetype":"locality"
},
  "geometry": {"coordinates":[88.30371,25.98016],"type":"Point"}
}