{
  "type": "Feature",
  "properties": {
    "gn:admin1_code":"84",
    "gn:admin2_code":"2015.0",
    "gn:admin3_code":"201561.0",
    "gn:admin4_code":"20156188.0",
    "gn:asciiname":"Kaliais",
    "gn:country_code":"BD",
    "gn:dem":10,
    "gn:feature_class":"P",
    "gn:feature_code":"PPL",
    "gn:name":"K\u0101li\u0101is",
    "gn:population":0,
    "gn:timezone":"Asia/Dhaka",
    "iso:country":"BD",
    "name:ben_x_preferred":[
        "K\u0101li\u0101is"
    ],
    "wof:name":"Kaliais",
    "wof:placetype":"locality"
},
  "geometry": {"coordinates":[91.98134,22.24498],"type":"Point"}
}