{
  "type": "Feature",
  "properties": {
    "gn:admin1_code":"H",
    "gn:admin2_code":"3072",
    "gn:admin3_code":"307247.0",
    "gn:admin4_code":"30724747.0",
    "gn:asciiname":"Jalalpur",
    "gn:country_code":"BD",
    "gn:dem":7,
    "gn:feature_class":"P",
    "gn:feature_code":"PPL",
    "gn:name":"J\u0101l\u0101lpur",
    "gn:population":0,
    "gn:timezone":"Asia/Dhaka",
    "iso:country":"BD",
    "wof:name":"Jalalpur",
    "wof:placetype":"locality"
},
  "geometry": {"coordinates":[90.88088999999999,24.67828],"type":"Point"}
}