{
  "type": "Feature",
  "properties": {
    "gn:admin1_code":"82",
    "gn:admin2_code":"4065.0",
    "gn:admin3_code":"406552.0",
    "gn:admin4_code":"40655239.0",
    "gn:asciiname":"Barpa",
    "gn:country_code":"BD",
    "gn:dem":8,
    "gn:feature_class":"P",
    "gn:feature_code":"PPL",
    "gn:name":"Barpa",
    "gn:population":0,
    "gn:timezone":"Asia/Dhaka",
    "iso:country":"BD",
    "name:ben_x_preferred":[
        "Barpa"
    ],
    "wof:name":"Barpa",
    "wof:placetype":"locality"
},
  "geometry": {"coordinates":[89.71693,23.08024],"type":"Point"}
}