{
  "type": "Feature",
  "properties": {
    "gn:admin1_code":"82",
    "gn:admin2_code":"4065.0",
    "gn:admin3_code":"406552.0",
    "gn:admin4_code":"40655223.0",
    "gn:asciiname":"Babra",
    "gn:country_code":"BD",
    "gn:dem":11,
    "gn:feature_class":"P",
    "gn:feature_code":"PPL",
    "gn:name":"B\u0101bra",
    "gn:population":0,
    "gn:timezone":"Asia/Dhaka",
    "iso:country":"BD",
    "name:ben_x_preferred":[
        "B\u0101bra"
    ],
    "wof:name":"Babra",
    "wof:placetype":"locality"
},
  "geometry": {"coordinates":[89.63453,23.23479],"type":"Point"}
}