{
  "type": "Feature",
  "properties": {
    "gn:admin1_code":"83",
    "gn:admin2_code":"5076",
    "gn:admin3_code":"507655.0",
    "gn:admin4_code":"50765543.0",
    "gn:asciiname":"Jorarpur",
    "gn:country_code":"BD",
    "gn:dem":2,
    "gn:feature_class":"P",
    "gn:feature_code":"PPL",
    "gn:name":"Jor\u0101rpur",
    "gn:population":0,
    "gn:timezone":"Asia/Dhaka",
    "iso:country":"BD",
    "wof:name":"Jorarpur",
    "wof:placetype":"locality"
},
  "geometry": {"coordinates":[89.23333000000002,23.95],"type":"Point"}
}