{
  "type": "Feature",
  "properties": {
    "gn:admin1_code":"84",
    "gn:admin2_code":"2013.0",
    "gn:admin3_code":"201349.0",
    "gn:admin4_code":"20134945.0",
    "gn:asciiname":"Gauriswar",
    "gn:country_code":"BD",
    "gn:dem":11,
    "gn:feature_class":"P",
    "gn:feature_code":"PPL",
    "gn:name":"Gauriswar",
    "gn:population":0,
    "gn:timezone":"Asia/Dhaka",
    "iso:country":"BD",
    "name:und_x_variant":[
        "Goriswar",
        "Gauriswar"
    ],
    "wof:name":"Gauriswar",
    "wof:placetype":"locality"
},
  "geometry": {"coordinates":[90.84874000000001,23.30817],"type":"Point"}
}