{
  "type": "Feature",
  "properties": {
    "gn:admin1_code":"87",
    "gn:admin2_code":"5577.0",
    "gn:admin3_code":"557704.0",
    "gn:admin4_code":"55770440.0",
    "gn:asciiname":"Panishali",
    "gn:country_code":"BD",
    "gn:dem":77,
    "gn:feature_class":"P",
    "gn:feature_code":"PPL",
    "gn:name":"P\u0101nish\u0101li",
    "gn:population":0,
    "gn:timezone":"Asia/Dhaka",
    "iso:country":"BD",
    "name:ben_x_preferred":[
        "P\u0101nish\u0101li"
    ],
    "wof:name":"Panishali",
    "wof:placetype":"locality"
},
  "geometry": {"coordinates":[88.4196,26.29933],"type":"Point"}
}