{
  "type": "Feature",
  "properties": {
    "gn:admin1_code":"82",
    "gn:admin2_code":"4047.0",
    "gn:admin3_code":"404775.0",
    "gn:admin4_code":"40477581.0",
    "gn:asciiname":"Gilatala",
    "gn:country_code":"BD",
    "gn:dem":11,
    "gn:feature_class":"P",
    "gn:feature_code":"PPL",
    "gn:name":"Gil\u0101tala",
    "gn:population":0,
    "gn:timezone":"Asia/Dhaka",
    "iso:country":"BD",
    "name:ben_x_preferred":[
        "Gil\u0101tala"
    ],
    "wof:name":"Gilatala",
    "wof:placetype":"locality"
},
  "geometry": {"coordinates":[89.66370000000001,22.79802],"type":"Point"}
}