{
  "type": "Feature",
  "properties": {
    "gn:admin1_code":"81",
    "gn:admin2_code":"3054",
    "gn:admin3_code":"305487.0",
    "gn:admin4_code":"30548752.0",
    "gn:asciiname":"Kathalbari",
    "gn:country_code":"BD",
    "gn:dem":9,
    "gn:feature_class":"P",
    "gn:feature_code":"PPL",
    "gn:name":"K\u0101th\u0101lb\u0101ri",
    "gn:population":0,
    "gn:timezone":"Asia/Dhaka",
    "iso:country":"BD",
    "name:und_x_variant":[
        "Khathal Baria",
        "K\u0101th\u0101lb\u0101ri"
    ],
    "wof:name":"Kathalbari",
    "wof:placetype":"locality"
},
  "geometry": {"coordinates":[90.19343000000001,23.42249],"type":"Point"}
}