{
  "type": "Feature",
  "properties": {
    "gn:admin1_code":"83",
    "gn:admin2_code":"5081.0",
    "gn:admin3_code":"508194.0",
    "gn:admin4_code":"50819427.0",
    "gn:asciiname":"Amritapur",
    "gn:country_code":"BD",
    "gn:dem":27,
    "gn:feature_class":"P",
    "gn:feature_code":"PPL",
    "gn:name":"Amritapur",
    "gn:population":0,
    "gn:timezone":"Asia/Dhaka",
    "iso:country":"BD",
    "name:ben_x_preferred":[
        "Amritapur"
    ],
    "wof:name":"Amritapur",
    "wof:placetype":"locality"
},
  "geometry": {"coordinates":[88.55521,24.66757],"type":"Point"}
}