{
  "type": "Feature",
  "properties": {
    "gn:admin1_code":"84",
    "gn:admin2_code":"2012",
    "gn:admin3_code":"201285.0",
    "gn:admin4_code":"20128560.0",
    "gn:asciiname":"Napang",
    "gn:country_code":"BD",
    "gn:dem":10,
    "gn:feature_class":"P",
    "gn:feature_code":"PPL",
    "gn:name":"N\u0101p\u0101ng",
    "gn:population":0,
    "gn:timezone":"Asia/Dhaka",
    "iso:country":"BD",
    "name:und_x_variant":[
        "Lapang",
        "N\u0101p\u0101ng"
    ],
    "wof:name":"Napang",
    "wof:placetype":"locality"
},
  "geometry": {"coordinates":[90.95287,23.91598],"type":"Point"}
}