{
  "type": "Feature",
  "properties": {
    "gn:admin1_code":"81",
    "gn:admin2_code":"3048",
    "gn:admin3_code":"304849.0",
    "gn:admin4_code":"30484943.0",
    "gn:asciiname":"Salpa Jasodal",
    "gn:country_code":"BD",
    "gn:dem":12,
    "gn:feature_class":"P",
    "gn:feature_code":"PPL",
    "gn:name":"Salpa Jasodal",
    "gn:population":0,
    "gn:timezone":"Asia/Dhaka",
    "iso:country":"BD",
    "wof:name":"Salpa Jasodal",
    "wof:placetype":"locality"
},
  "geometry": {"coordinates":[90.78913,24.40382],"type":"Point"}
}