{
  "type": "Feature",
  "properties": {
    "gn:admin1_code":"84",
    "gn:admin2_code":"2015.0",
    "gn:admin3_code":"201504.0",
    "gn:admin4_code":"20150409.0",
    "gn:asciiname":"Anwara",
    "gn:country_code":"BD",
    "gn:dem":8,
    "gn:feature_class":"P",
    "gn:feature_code":"PPL",
    "gn:name":"Anw\u0101ra",
    "gn:population":0,
    "gn:timezone":"Asia/Dhaka",
    "iso:country":"BD",
    "name:ben_x_preferred":[
        "Anw\u0101ra"
    ],
    "name:ben_x_variant":[
        "\u0986\u09a8\u09cb\u09af\u09bc\u09be\u09b0\u09be"
    ],
    "wof:name":"Anwara",
    "wof:placetype":"locality"
},
  "geometry": {"coordinates":[91.90742,22.2204],"type":"Point"}
}