{
  "type": "Feature",
  "properties": {
    "gn:admin1_code":"83",
    "gn:admin2_code":"5069.0",
    "gn:admin3_code":"506963.0",
    "gn:admin4_code":"50696343.0",
    "gn:asciiname":"Arjunpur",
    "gn:country_code":"BD",
    "gn:dem":17,
    "gn:feature_class":"P",
    "gn:feature_code":"PPL",
    "gn:name":"Arjunpur",
    "gn:population":0,
    "gn:timezone":"Asia/Dhaka",
    "iso:country":"BD",
    "wof:name":"Arjunpur",
    "wof:placetype":"locality"
},
  "geometry": {"coordinates":[89.05830999999998,24.3843],"type":"Point"}
}