{
  "type": "Feature",
  "properties": {
    "gn:admin1_code":"83",
    "gn:admin2_code":"5081.0",
    "gn:admin3_code":"508112.0",
    "gn:admin4_code":"50811288.0",
    "gn:asciiname":"Qazipara",
    "gn:country_code":"BD",
    "gn:dem":19,
    "gn:feature_class":"P",
    "gn:feature_code":"PPL",
    "gn:name":"Q\u0101zip\u0101ra",
    "gn:population":0,
    "gn:timezone":"Asia/Dhaka",
    "iso:country":"BD",
    "name:ben_x_preferred":[
        "Q\u0101zip\u0101ra"
    ],
    "wof:name":"Qazipara",
    "wof:placetype":"locality"
},
  "geometry": {"coordinates":[88.77656999999998,24.53227],"type":"Point"}
}