{
  "type": "Feature",
  "properties": {
    "gn:admin1_code":"87",
    "gn:admin2_code":"5527.0",
    "gn:admin3_code":"552743.0",
    "gn:admin4_code":"55274319.0",
    "gn:asciiname":"Damodarpur",
    "gn:country_code":"BD",
    "gn:dem":30,
    "gn:feature_class":"P",
    "gn:feature_code":"PPL",
    "gn:name":"D\u0101modarpur",
    "gn:population":0,
    "gn:timezone":"Asia/Dhaka",
    "iso:country":"BD",
    "name:ben_x_preferred":[
        "D\u0101modarpur"
    ],
    "wof:name":"Damodarpur",
    "wof:placetype":"locality"
},
  "geometry": {"coordinates":[89.17074000000002,25.31904],"type":"Point"}
}