{
  "type": "Feature",
  "properties": {
    "gn:admin1_code":"82",
    "gn:admin2_code":"4041.0",
    "gn:admin3_code":"404109.0",
    "gn:admin4_code":"40410928.0",
    "gn:asciiname":"Parkul",
    "gn:country_code":"BD",
    "gn:dem":16,
    "gn:feature_class":"P",
    "gn:feature_code":"PPL",
    "gn:name":"P\u0101rkul",
    "gn:population":0,
    "gn:timezone":"Asia/Dhaka",
    "iso:country":"BD",
    "name:ben_x_preferred":[
        "P\u0101rkul"
    ],
    "wof:name":"Parkul",
    "wof:placetype":"locality"
},
  "geometry": {"coordinates":[89.31950000000001,23.19124],"type":"Point"}
}