{
  "type": "Feature",
  "properties": {
    "gn:admin1_code":"83",
    "gn:admin2_code":"5064.0",
    "gn:admin3_code":"506403.0",
    "gn:admin4_code":"50640352.0",
    "gn:asciiname":"Gandagohali",
    "gn:country_code":"BD",
    "gn:dem":18,
    "gn:feature_class":"P",
    "gn:feature_code":"PPL",
    "gn:name":"Gandagoh\u0101li",
    "gn:population":0,
    "gn:timezone":"Asia/Dhaka",
    "iso:country":"BD",
    "name:ben_x_preferred":[
        "Gandagoh\u0101li"
    ],
    "name:und_x_variant":[
        "Gandagonali"
    ],
    "wof:name":"Gandagohali",
    "wof:placetype":"locality"
},
  "geometry": {"coordinates":[88.91247,24.64906],"type":"Point"}
}