{
  "type": "Feature",
  "properties": {
    "gn:admin1_code":"81",
    "gn:admin2_code":"3068",
    "gn:admin3_code":"306876.0",
    "gn:admin4_code":"30687673.0",
    "gn:asciiname":"Miargaon",
    "gn:country_code":"BD",
    "gn:dem":12,
    "gn:feature_class":"P",
    "gn:feature_code":"PPL",
    "gn:name":"Mi\u0101rgaon",
    "gn:population":0,
    "gn:timezone":"Asia/Dhaka",
    "iso:country":"BD",
    "wof:name":"Miargaon",
    "wof:placetype":"locality"
},
  "geometry": {"coordinates":[90.69485,24.03431],"type":"Point"}
}