{
  "type": "Feature",
  "properties": {
    "gn:admin1_code":"85",
    "gn:admin2_code":"1006",
    "gn:admin3_code":"100636.0",
    "gn:admin4_code":"10063667.0",
    "gn:asciiname":"Krishnapura",
    "gn:country_code":"BD",
    "gn:dem":-9999,
    "gn:feature_class":"P",
    "gn:feature_code":"PPL",
    "gn:name":"Krishnapura",
    "gn:population":0,
    "gn:timezone":"Asia/Dhaka",
    "iso:country":"BD",
    "wof:name":"Krishnapura",
    "wof:placetype":"locality"
},
  "geometry": {"coordinates":[90.44131,22.98946],"type":"Point"}
}