{
  "type": "Feature",
  "properties": {
    "gn:admin1_code":"82",
    "gn:admin2_code":"4087.0",
    "gn:admin3_code":"408704.0",
    "gn:admin4_code":"40870477.0",
    "gn:asciiname":"Shanatan Kati",
    "gn:country_code":"BD",
    "gn:dem":3,
    "gn:feature_class":"P",
    "gn:feature_code":"PPL",
    "gn:name":"Shan\u0101tan K\u0101ti",
    "gn:population":0,
    "gn:timezone":"Asia/Dhaka",
    "iso:country":"BD",
    "name:ben_x_preferred":[
        "Shan\u0101tan K\u0101ti"
    ],
    "wof:name":"Shanatan Kati",
    "wof:placetype":"locality"
},
  "geometry": {"coordinates":[89.2308,22.3831],"type":"Point"}
}