{
  "type": "Feature",
  "properties": {
    "gn:admin1_code":"83",
    "gn:admin2_code":"5010",
    "gn:admin3_code":"501054.0",
    "gn:admin4_code":"50105466.0",
    "gn:asciiname":"Malancha",
    "gn:country_code":"BD",
    "gn:dem":25,
    "gn:feature_class":"P",
    "gn:feature_code":"PPL",
    "gn:name":"Malancha",
    "gn:population":0,
    "gn:timezone":"Asia/Dhaka",
    "iso:country":"BD",
    "wof:name":"Malancha",
    "wof:placetype":"locality"
},
  "geometry": {"coordinates":[89.29771,24.80438],"type":"Point"}
}