{
  "type": "Feature",
  "properties": {
    "gn:admin1_code":"87",
    "gn:admin2_code":"5527.0",
    "gn:admin3_code":"552717.0",
    "gn:admin4_code":"55271728.0",
    "gn:asciiname":"Bhatpara",
    "gn:country_code":"BD",
    "gn:dem":39,
    "gn:feature_class":"P",
    "gn:feature_code":"PPL",
    "gn:name":"Bh\u0101tp\u0101ra",
    "gn:population":0,
    "gn:timezone":"Asia/Dhaka",
    "iso:country":"BD",
    "name:ben_x_preferred":[
        "Bh\u0101tp\u0101ra"
    ],
    "wof:name":"Bhatpara",
    "wof:placetype":"locality"
},
  "geometry": {"coordinates":[88.56134,25.6565],"type":"Point"}
}