{
  "type": "Feature",
  "properties": {
    "gn:admin1_code":"84",
    "gn:admin2_code":"2015.0",
    "gn:admin3_code":"201570.0",
    "gn:admin4_code":"20157043.0",
    "gn:asciiname":"Pekua",
    "gn:country_code":"BD",
    "gn:dem":42,
    "gn:feature_class":"P",
    "gn:feature_code":"PPL",
    "gn:name":"Pekua",
    "gn:population":0,
    "gn:timezone":"Asia/Dhaka",
    "iso:country":"BD",
    "name:ben_x_preferred":[
        "Pekua"
    ],
    "wof:name":"Pekua",
    "wof:placetype":"locality"
},
  "geometry": {"coordinates":[92.08046,22.3561],"type":"Point"}
}