{
  "type": "Feature",
  "properties": {
    "gn:admin1_code":"84",
    "gn:admin2_code":"2019",
    "gn:admin3_code":"201909.0",
    "gn:admin4_code":"20190994.0",
    "gn:asciiname":"Laghnasar",
    "gn:cc2":"BD",
    "gn:country_code":"BD",
    "gn:dem":13,
    "gn:feature_class":"P",
    "gn:feature_code":"PPL",
    "gn:name":"Laghnas\u0101r",
    "gn:population":0,
    "gn:timezone":"Asia/Dhaka",
    "iso:country":"BD",
    "name:und_x_variant":[
        "Lagnasar",
        "Laghnas\u0101r"
    ],
    "wof:name":"Laghnasar",
    "wof:placetype":"locality"
},
  "geometry": {"coordinates":[91.11667,23.35],"type":"Point"}
}