{
  "type": "Feature",
  "properties": {
    "gn:admin1_code":"87",
    "gn:admin2_code":"5527.0",
    "gn:admin3_code":"552730.0",
    "gn:admin4_code":"55273007.0",
    "gn:asciiname":"Dakshin Sukdebpur",
    "gn:country_code":"BD",
    "gn:dem":38,
    "gn:feature_class":"P",
    "gn:feature_code":"PPL",
    "gn:name":"Dakshin Sukdebpur",
    "gn:population":0,
    "gn:timezone":"Asia/Dhaka",
    "iso:country":"BD",
    "name:ben_x_preferred":[
        "Dakshin Sukdebpur"
    ],
    "wof:name":"Dakshin Sukdebpur",
    "wof:placetype":"locality"
},
  "geometry": {"coordinates":[88.75991999999999,25.67222000000001],"type":"Point"}
}