{
  "type": "Feature",
  "properties": {
    "gn:admin1_code":"83",
    "gn:admin2_code":"5010",
    "gn:admin3_code":"501094.0",
    "gn:admin4_code":"50109494.0",
    "gn:asciiname":"Enayetpur",
    "gn:country_code":"BD",
    "gn:dem":26,
    "gn:feature_class":"P",
    "gn:feature_code":"PPL",
    "gn:name":"En\u0101yetpur",
    "gn:population":0,
    "gn:timezone":"Asia/Dhaka",
    "iso:country":"BD",
    "name:ben_x_preferred":[
        "En\u0101yetpur"
    ],
    "wof:name":"Enayetpur",
    "wof:placetype":"locality"
},
  "geometry": {"coordinates":[89.33,25.04677],"type":"Point"}
}