{
  "type": "Feature",
  "properties": {
    "gn:admin1_code":"83",
    "gn:admin2_code":"5069.0",
    "gn:admin3_code":"506944.0",
    "gn:admin4_code":"50694485.0",
    "gn:asciiname":"Bandobasti Gobindapur",
    "gn:cc2":"BD",
    "gn:country_code":"BD",
    "gn:dem":16,
    "gn:feature_class":"P",
    "gn:feature_code":"PPL",
    "gn:name":"Bandobasti Gobindapur",
    "gn:population":0,
    "gn:timezone":"Asia/Dhaka",
    "iso:country":"BD",
    "name:und_x_variant":[
        "Bondobasti Gobindapur",
        "Bandobasti Gobindapur"
    ],
    "wof:name":"Bandobasti Gobindapur",
    "wof:placetype":"locality"
},
  "geometry": {"coordinates":[88.95,24.16667],"type":"Point"}
}