{
  "type": "Feature",
  "properties": {
    "gn:admin1_code":"84",
    "gn:admin2_code":"2015",
    "gn:admin3_code":"201533.0",
    "gn:admin4_code":"20153371.0",
    "gn:asciiname":"Bara Thali",
    "gn:country_code":"BD",
    "gn:dem":38,
    "gn:feature_class":"P",
    "gn:feature_code":"PPL",
    "gn:name":"Bara Thali",
    "gn:population":0,
    "gn:timezone":"Asia/Dhaka",
    "iso:country":"BD",
    "name:ben_x_preferred":[
        "Bara Thali"
    ],
    "wof:name":"Bara Thali",
    "wof:placetype":"locality"
},
  "geometry": {"coordinates":[91.82038,22.78192],"type":"Point"}
}