{
  "type": "Feature",
  "properties": {
    "gn:admin1_code":"82",
    "gn:admin2_code":"4087",
    "gn:admin3_code":"408747.0",
    "gn:admin4_code":"40874779.0",
    "gn:asciiname":"Indranagar",
    "gn:country_code":"BD",
    "gn:dem":9,
    "gn:feature_class":"P",
    "gn:feature_code":"PPL",
    "gn:name":"Indranagar",
    "gn:population":0,
    "gn:timezone":"Asia/Dhaka",
    "iso:country":"BD",
    "name:ben_x_preferred":[
        "\u0987\u09a8\u09cd\u09a6\u09cd\u09b0\u09a8\u0997\u09b0"
    ],
    "name:bpy_x_preferred":[
        "\u0987\u09a8\u09cd\u09a6\u09cd\u09b0\u09a8\u0997\u09b0"
    ],
    "name:ita_x_preferred":[
        "Indranagar"
    ],
    "name:mlg_x_preferred":[
        "Indranagar"
    ],
    "name:msa_x_preferred":[
        "Indranagar"
    ],
    "name:new_x_preferred":[
        "\u0907\u0928\u094d\u0926\u094d\u0930\u0928\u0917\u0930"
    ],
    "name:nld_x_preferred":[
        "Indranagar"
    ],
    "name:por_x_preferred":[
        "Indranagar"
    ],
    "name:vie_x_preferred":[
        "Indranagar"
    ],
    "name:zho_x_preferred":[
        "\u4f0a\u6069\u5fb7\u62c9\u7eb3\u52a0\u5c14"
    ],
    "wof:name":"Indranagar",
    "wof:placetype":"locality"
},
  "geometry": {"coordinates":[89.03416,22.52863],"type":"Point"}
}