{
  "type": "Feature",
  "properties": {
    "gn:admin1_code":"81",
    "gn:admin2_code":"3035.0",
    "gn:admin3_code":"303543.0",
    "gn:admin4_code":"30354333.0",
    "gn:asciiname":"Satasia",
    "gn:country_code":"BD",
    "gn:dem":10,
    "gn:feature_class":"P",
    "gn:feature_code":"PPL",
    "gn:name":"S\u0101tasia",
    "gn:population":0,
    "gn:timezone":"Asia/Dhaka",
    "iso:country":"BD",
    "name:ben_x_preferred":[
        "S\u0101tasia"
    ],
    "wof:name":"Satasia",
    "wof:placetype":"locality"
},
  "geometry": {"coordinates":[89.83528000000003,23.1977],"type":"Point"}
}