{
  "type": "Feature",
  "properties": {
    "gn:admin1_code":"83",
    "gn:admin2_code":"5070.0",
    "gn:admin3_code":"507088.0",
    "gn:admin4_code":"50708877.0",
    "gn:asciiname":"Bagichapara",
    "gn:country_code":"BD",
    "gn:dem":27,
    "gn:feature_class":"P",
    "gn:feature_code":"PPL",
    "gn:name":"B\u0101gich\u0101p\u0101ra",
    "gn:population":0,
    "gn:timezone":"Asia/Dhaka",
    "iso:country":"BD",
    "name:ben_x_preferred":[
        "B\u0101gich\u0101p\u0101ra"
    ],
    "wof:name":"Bagichapara",
    "wof:placetype":"locality"
},
  "geometry": {"coordinates":[88.1079,24.80079],"type":"Point"}
}