{
  "type": "Feature",
  "properties": {
    "gn:admin1_code":"82",
    "gn:admin2_code":"4041.0",
    "gn:admin3_code":"404123.0",
    "gn:admin4_code":"40412329.0",
    "gn:asciiname":"Gulbakpur",
    "gn:country_code":"BD",
    "gn:dem":13,
    "gn:feature_class":"P",
    "gn:feature_code":"PPL",
    "gn:name":"Gulb\u0101kpur",
    "gn:population":0,
    "gn:timezone":"Asia/Dhaka",
    "iso:country":"BD",
    "name:ben_x_preferred":[
        "Gulb\u0101kpur"
    ],
    "wof:name":"Gulbakpur",
    "wof:placetype":"locality"
},
  "geometry": {"coordinates":[89.02608000000002,23.19521],"type":"Point"}
}