{
  "type": "Feature",
  "properties": {
    "gn:admin1_code":"87",
    "gn:admin2_code":"5527.0",
    "gn:admin3_code":"552712.0",
    "gn:admin4_code":"55271277.0",
    "gn:asciiname":"Dalua",
    "gn:country_code":"BD",
    "gn:dem":48,
    "gn:feature_class":"P",
    "gn:feature_code":"PPL",
    "gn:name":"Dalua",
    "gn:population":0,
    "gn:timezone":"Asia/Dhaka",
    "iso:country":"BD",
    "name:ben_x_preferred":[
        "Dalua"
    ],
    "wof:name":"Dalua",
    "wof:placetype":"locality"
},
  "geometry": {"coordinates":[88.55233,25.93868],"type":"Point"}
}