{
  "type": "Feature",
  "properties": {
    "gn:admin1_code":"82",
    "gn:admin2_code":"4055",
    "gn:admin3_code":"405566.0",
    "gn:admin4_code":"40556621.0",
    "gn:asciiname":"Maijpara",
    "gn:country_code":"BD",
    "gn:dem":13,
    "gn:feature_class":"P",
    "gn:feature_code":"PPL",
    "gn:name":"M\u0101ijp\u0101ra",
    "gn:population":0,
    "gn:timezone":"Asia/Dhaka",
    "iso:country":"BD",
    "wof:name":"Maijpara",
    "wof:placetype":"locality"
},
  "geometry": {"coordinates":[89.55537,23.4169],"type":"Point"}
}