{
  "type": "Feature",
  "properties": {
    "gn:admin1_code":"87",
    "gn:admin2_code":"5585.0",
    "gn:admin3_code":"558576.0",
    "gn:admin4_code":"55857656.0",
    "gn:asciiname":"Bara Ramnathpur",
    "gn:country_code":"BD",
    "gn:dem":32,
    "gn:feature_class":"P",
    "gn:feature_code":"PPL",
    "gn:name":"Bara Ramnathpur",
    "gn:population":0,
    "gn:timezone":"Asia/Dhaka",
    "iso:country":"BD",
    "name:und_x_variant":[
        "Bara R\u0101mn\u0101thpur"
    ],
    "wof:name":"Bara Ramnathpur",
    "wof:placetype":"locality"
},
  "geometry": {"coordinates":[89.33400999999998,25.40603],"type":"Point"}
}