{
  "type": "Feature",
  "properties": {
    "gn:admin1_code":"87",
    "gn:admin2_code":"5549",
    "gn:admin3_code":"554977.0",
    "gn:admin4_code":"55497752.0",
    "gn:asciiname":"Nazim Khan",
    "gn:country_code":"BD",
    "gn:dem":29,
    "gn:feature_class":"P",
    "gn:feature_code":"PPL",
    "gn:name":"Nazim Khan",
    "gn:population":0,
    "gn:timezone":"Asia/Dhaka",
    "iso:country":"BD",
    "name:ben_x_preferred":[
        "Nazim Khan"
    ],
    "wof:name":"Nazim Khan",
    "wof:placetype":"locality"
},
  "geometry": {"coordinates":[89.55294000000001,25.73158],"type":"Point"}
}