{
  "type": "Feature",
  "properties": {
    "gn:admin1_code":"84",
    "gn:admin2_code":"2019",
    "gn:admin3_code":"201940.0",
    "gn:admin4_code":"20194083.0",
    "gn:asciiname":"Shaitala",
    "gn:country_code":"BD",
    "gn:dem":12,
    "gn:feature_class":"P",
    "gn:feature_code":"PPL",
    "gn:name":"Sh\u0101itala",
    "gn:population":0,
    "gn:timezone":"Asia/Dhaka",
    "iso:country":"BD",
    "wof:name":"Shaitala",
    "wof:placetype":"locality"
},
  "geometry": {"coordinates":[90.92816999999999,23.52732],"type":"Point"}
}