{
  "type": "Feature",
  "properties": {
    "gn:admin1_code":"83",
    "gn:asciiname":"Atiotola",
    "gn:country_code":"BD",
    "gn:dem":26,
    "gn:feature_class":"P",
    "gn:feature_code":"PPL",
    "gn:name":"\u0100tiotola",
    "gn:population":0,
    "gn:timezone":"Asia/Dhaka",
    "iso:country":"BD",
    "name:ben_x_preferred":[
        "\u0100tiotola"
    ],
    "wof:name":"Atiotola",
    "wof:placetype":"locality"
},
  "geometry": {"coordinates":[89.34235,25.10391],"type":"Point"}
}