{
  "type": "Feature",
  "properties": {
    "gn:admin1_code":"81",
    "gn:admin2_code":"3067",
    "gn:admin3_code":"306704.0",
    "gn:admin4_code":"30670460.0",
    "gn:asciiname":"Naogaon",
    "gn:country_code":"BD",
    "gn:dem":11,
    "gn:feature_class":"P",
    "gn:feature_code":"PPL",
    "gn:name":"Naogaon",
    "gn:population":0,
    "gn:timezone":"Asia/Dhaka",
    "iso:country":"BD",
    "name:ben_x_preferred":[
        "\u09a8\u0993\u0997\u09be\u0981"
    ],
    "name:epo_x_preferred":[
        "Naogaon"
    ],
    "name:ron_x_preferred":[
        "Naogaon"
    ],
    "name:rus_x_preferred":[
        "\u041d\u0430\u043e\u0433\u0430\u043e\u043d"
    ],
    "name:swe_x_preferred":[
        "Naogaon"
    ],
    "name:urd_x_preferred":[
        "\u0646\u0627\u0648 \u06af\u0627\u0624\u06ba"
    ],
    "wof:name":"Naogaon",
    "wof:placetype":"locality"
},
  "geometry": {"coordinates":[90.63023,23.73269],"type":"Point"}
}