{
  "type": "Feature",
  "properties": {
    "gn:admin1_code":"82",
    "gn:admin2_code":"4087.0",
    "gn:admin3_code":"408704.0",
    "gn:admin4_code":"40870494.0",
    "gn:asciiname":"Dakshin Puijala",
    "gn:country_code":"BD",
    "gn:dem":0,
    "gn:feature_class":"P",
    "gn:feature_code":"PPL",
    "gn:name":"Dakshin Puij\u0101la",
    "gn:population":0,
    "gn:timezone":"Asia/Dhaka",
    "iso:country":"BD",
    "name:ben_x_preferred":[
        "Dakshin Puij\u0101la"
    ],
    "wof:name":"Dakshin Puijala",
    "wof:placetype":"locality"
},
  "geometry": {"coordinates":[89.19880000000001,22.45385],"type":"Point"}
}