{
  "type": "Feature",
  "properties": {
    "gn:admin1_code":"84",
    "gn:admin2_code":"2075",
    "gn:admin3_code":"207507.0",
    "gn:admin4_code":"20750745.0",
    "gn:asciiname":"Madhupur",
    "gn:country_code":"BD",
    "gn:dem":9,
    "gn:feature_class":"P",
    "gn:feature_code":"PPL",
    "gn:name":"Madhupur",
    "gn:population":0,
    "gn:timezone":"Asia/Dhaka",
    "iso:country":"BD",
    "name:ita_x_preferred":[
        "Madhupur"
    ],
    "name:msa_x_preferred":[
        "Madhupur"
    ],
    "wof:name":"Madhupur",
    "wof:placetype":"locality"
},
  "geometry": {"coordinates":[91.06667,22.96667],"type":"Point"}
}