{
  "type": "Feature",
  "properties": {
    "gn:admin1_code":"81",
    "gn:admin2_code":"3059",
    "gn:admin3_code":"305956.0",
    "gn:admin4_code":"30595685.0",
    "gn:asciiname":"Kazi Kasba",
    "gn:country_code":"BD",
    "gn:dem":9,
    "gn:feature_class":"P",
    "gn:feature_code":"PPL",
    "gn:name":"K\u0101zi Kasba",
    "gn:population":0,
    "gn:timezone":"Asia/Dhaka",
    "iso:country":"BD",
    "wof:name":"Kazi Kasba",
    "wof:placetype":"locality"
},
  "geometry": {"coordinates":[90.48632000000001,23.55044],"type":"Point"}
}