{
  "type": "Feature",
  "properties": {
    "gn:admin1_code":"84",
    "gn:admin2_code":"2012.0",
    "gn:admin3_code":"201204.0",
    "gn:admin4_code":"20120454.0",
    "gn:asciiname":"Baher Char",
    "gn:country_code":"BD",
    "gn:dem":9,
    "gn:feature_class":"P",
    "gn:feature_code":"PPL",
    "gn:name":"B\u0101her Char",
    "gn:population":0,
    "gn:timezone":"Asia/Dhaka",
    "iso:country":"BD",
    "wof:name":"Baher Char",
    "wof:placetype":"locality"
},
  "geometry": {"coordinates":[90.72928,23.73544],"type":"Point"}
}