{
  "type": "Feature",
  "properties": {
    "gn:admin1_code":"H",
    "gn:admin2_code":"3089",
    "gn:admin3_code":"308990.0",
    "gn:admin4_code":"30899055.0",
    "gn:asciiname":"Puthia",
    "gn:country_code":"BD",
    "gn:dem":24,
    "gn:feature_class":"P",
    "gn:feature_code":"PPL",
    "gn:name":"Puthia",
    "gn:population":0,
    "gn:timezone":"Asia/Dhaka",
    "iso:country":"BD",
    "name:ben_x_preferred":[
        "Puthia"
    ],
    "wof:name":"Puthia",
    "wof:placetype":"locality"
},
  "geometry": {"coordinates":[89.98164,25.08926],"type":"Point"}
}