{
  "type": "Feature",
  "properties": {
    "gn:admin1_code":"H",
    "gn:admin2_code":"3072",
    "gn:admin3_code":"307247.0",
    "gn:admin4_code":"30724733.0",
    "gn:asciiname":"Sibpur",
    "gn:country_code":"BD",
    "gn:dem":14,
    "gn:feature_class":"P",
    "gn:feature_code":"PPL",
    "gn:name":"Sibpur",
    "gn:population":0,
    "gn:timezone":"Asia/Dhaka",
    "iso:country":"BD",
    "wof:name":"Sibpur",
    "wof:placetype":"locality"
},
  "geometry": {"coordinates":[90.71545999999999,24.70552],"type":"Point"}
}