{
  "type": "Feature",
  "properties": {
    "gn:admin1_code":"87",
    "gn:admin2_code":"5585",
    "gn:admin3_code":"558542.0",
    "gn:admin4_code":"55854281.0",
    "gn:asciiname":"Rajib",
    "gn:country_code":"BD",
    "gn:dem":33,
    "gn:feature_class":"P",
    "gn:feature_code":"PPL",
    "gn:name":"R\u0101jib",
    "gn:population":0,
    "gn:timezone":"Asia/Dhaka",
    "iso:country":"BD",
    "wof:name":"Rajib",
    "wof:placetype":"locality"
},
  "geometry": {"coordinates":[89.44703,25.72727],"type":"Point"}
}