{
  "type": "Feature",
  "properties": {
    "gn:admin1_code":"83",
    "gn:admin2_code":"5076.0",
    "gn:admin3_code":"507616.0",
    "gn:admin4_code":"50761663.0",
    "gn:asciiname":"Srikantadia",
    "gn:country_code":"BD",
    "gn:dem":13,
    "gn:feature_class":"P",
    "gn:feature_code":"PPL",
    "gn:name":"Srik\u0101ntadia",
    "gn:population":0,
    "gn:timezone":"Asia/Dhaka",
    "iso:country":"BD",
    "name:ben_x_preferred":[
        "Srik\u0101ntadia"
    ],
    "wof:name":"Srikantadia",
    "wof:placetype":"locality"
},
  "geometry": {"coordinates":[89.68963000000002,23.98091],"type":"Point"}
}