{
  "type": "Feature",
  "properties": {
    "gn:admin1_code":"81",
    "gn:admin2_code":"3056.0",
    "gn:admin3_code":"305628.0",
    "gn:admin4_code":"30562814.0",
    "gn:asciiname":"Bankipur",
    "gn:country_code":"BD",
    "gn:dem":16,
    "gn:feature_class":"P",
    "gn:feature_code":"PPL",
    "gn:name":"B\u0101nkipur",
    "gn:population":0,
    "gn:timezone":"Asia/Dhaka",
    "iso:country":"BD",
    "wof:name":"Bankipur",
    "wof:placetype":"locality"
},
  "geometry": {"coordinates":[89.85101999999998,23.78089],"type":"Point"}
}