{
  "type": "Feature",
  "properties": {
    "gn:admin1_code":"H",
    "gn:admin2_code":"3072.0",
    "gn:admin3_code":"307274.0",
    "gn:admin4_code":"30727479.0",
    "gn:asciiname":"Bhattapara",
    "gn:country_code":"BD",
    "gn:dem":12,
    "gn:feature_class":"P",
    "gn:feature_code":"PPL",
    "gn:name":"Bhattap\u0101ra",
    "gn:population":0,
    "gn:timezone":"Asia/Dhaka",
    "iso:country":"BD",
    "name:und_x_variant":[
        "Bhattap\u0101ra",
        "Bhattap\u0101ra Sripur"
    ],
    "wof:name":"Bhattapara",
    "wof:placetype":"locality"
},
  "geometry": {"coordinates":[90.66518000000001,24.9189],"type":"Point"}
}