{
  "type": "Feature",
  "properties": {
    "gn:admin1_code":"87",
    "gn:asciiname":"Tista Nadir Payasti",
    "gn:country_code":"BD",
    "gn:dem":58,
    "gn:feature_class":"P",
    "gn:feature_code":"PPL",
    "gn:name":"T\u012bsta N\u0101dir Payasti",
    "gn:population":0,
    "gn:timezone":"Asia/Dhaka",
    "iso:country":"BD",
    "name:ben_x_preferred":[
        "T\u012bsta N\u0101dir Payasti"
    ],
    "wof:name":"Tista Nadir Payasti",
    "wof:placetype":"locality"
},
  "geometry": {"coordinates":[89.00225,26.25531],"type":"Point"}
}