{
  "type": "Feature",
  "properties": {
    "gn:admin1_code":"87",
    "gn:admin2_code":"5573.0",
    "gn:admin3_code":"557385.0",
    "gn:admin4_code":"55738527.0",
    "gn:asciiname":"Khord Botlagari",
    "gn:country_code":"BD",
    "gn:dem":44,
    "gn:feature_class":"P",
    "gn:feature_code":"PPL",
    "gn:name":"Khord Botlagari",
    "gn:population":0,
    "gn:timezone":"Asia/Dhaka",
    "iso:country":"BD",
    "name:ben_x_preferred":[
        "Khord Botlagari"
    ],
    "wof:name":"Khord Botlagari",
    "wof:placetype":"locality"
},
  "geometry": {"coordinates":[88.87106999999997,25.80945],"type":"Point"}
}