{
  "type": "Feature",
  "properties": {
    "gn:admin1_code":"84",
    "gn:admin2_code":"2013.0",
    "gn:admin3_code":"201349.0",
    "gn:admin4_code":"20134945.0",
    "gn:asciiname":"Hanriain",
    "gn:country_code":"BD",
    "gn:dem":12,
    "gn:feature_class":"P",
    "gn:feature_code":"PPL",
    "gn:name":"H\u0101nri\u0101in",
    "gn:population":0,
    "gn:timezone":"Asia/Dhaka",
    "iso:country":"BD",
    "wof:name":"Hanriain",
    "wof:placetype":"locality"
},
  "geometry": {"coordinates":[90.88735,23.26957],"type":"Point"}
}