{
  "type": "Feature",
  "properties": {
    "gn:admin1_code":"82",
    "gn:admin2_code":"4044.0",
    "gn:admin3_code":"404471.0",
    "gn:admin4_code":"40447159.0",
    "gn:asciiname":"Razirber",
    "gn:country_code":"BD",
    "gn:dem":11,
    "gn:feature_class":"P",
    "gn:feature_code":"PPL",
    "gn:name":"Razirber",
    "gn:population":0,
    "gn:timezone":"Asia/Dhaka",
    "iso:country":"BD",
    "name:ben_x_preferred":[
        "Razirber"
    ],
    "wof:name":"Razirber",
    "wof:placetype":"locality"
},
  "geometry": {"coordinates":[88.75648000000002,23.27407],"type":"Point"}
}