{
  "type": "Feature",
  "properties": {
    "gn:admin1_code":"H",
    "gn:admin2_code":"3061.0",
    "gn:admin3_code":"306123.0",
    "gn:admin4_code":"30612358.0",
    "gn:asciiname":"Bhutiarkona",
    "gn:country_code":"BD",
    "gn:dem":16,
    "gn:feature_class":"P",
    "gn:feature_code":"PPL",
    "gn:name":"Bhuti\u0101rkona",
    "gn:population":0,
    "gn:timezone":"Asia/Dhaka",
    "iso:country":"BD",
    "wof:name":"Bhutiarkona",
    "wof:placetype":"locality"
},
  "geometry": {"coordinates":[90.67243000000001,24.76251],"type":"Point"}
}