{
  "type": "Feature",
  "properties": {
    "gn:admin1_code":"85",
    "gn:admin2_code":"1042",
    "gn:admin3_code":"104273.0",
    "gn:admin4_code":"10427394.0",
    "gn:asciiname":"Ichhapasa",
    "gn:country_code":"BD",
    "gn:dem":8,
    "gn:feature_class":"P",
    "gn:feature_code":"PPL",
    "gn:name":"Ichh\u0101p\u0101sa",
    "gn:population":0,
    "gn:timezone":"Asia/Dhaka",
    "iso:country":"BD",
    "wof:name":"Ichhapasa",
    "wof:placetype":"locality"
},
  "geometry": {"coordinates":[90.24585999999999,22.56875],"type":"Point"}
}