{
  "type": "Feature",
  "properties": {
    "gn:admin1_code":"87",
    "gn:admin2_code":"5577.0",
    "gn:admin3_code":"557725.0",
    "gn:admin4_code":"55772580.0",
    "gn:asciiname":"Ghagrapara",
    "gn:country_code":"BD",
    "gn:dem":72,
    "gn:feature_class":"P",
    "gn:feature_code":"PPL",
    "gn:name":"Gh\u0101grap\u0101ra",
    "gn:population":0,
    "gn:timezone":"Asia/Dhaka",
    "iso:country":"BD",
    "name:ben_x_preferred":[
        "Gh\u0101grap\u0101ra"
    ],
    "wof:name":"Ghagrapara",
    "wof:placetype":"locality"
},
  "geometry": {"coordinates":[88.60819000000002,26.24345],"type":"Point"}
}