{
  "type": "Feature",
  "properties": {
    "gn:admin1_code":"87",
    "gn:admin2_code":"5527.0",
    "gn:admin3_code":"552756.0",
    "gn:admin4_code":"55275647.0",
    "gn:asciiname":"Sultanpur",
    "gn:country_code":"BD",
    "gn:dem":45,
    "gn:feature_class":"P",
    "gn:feature_code":"PPL",
    "gn:name":"Sult\u0101npur",
    "gn:population":0,
    "gn:timezone":"Asia/Dhaka",
    "iso:country":"BD",
    "name:ben_x_preferred":[
        "Sult\u0101npur"
    ],
    "name:ben_x_variant":[
        "\u09b8\u09c1\u09b2\u09a4\u09be\u09a8\u09aa\u09c1\u09b0"
    ],
    "name:bih_x_preferred":[
        "\u0938\u0941\u0932\u094d\u0924\u093e\u0928\u092a\u0941\u0930"
    ],
    "name:bpy_x_preferred":[
        "\u09b8\u09c1\u09b2\u09a4\u09be\u09a8\u09aa\u09c1\u09b0"
    ],
    "name:ceb_x_preferred":[
        "Sultanpur"
    ],
    "name:deu_x_preferred":[
        "Sultanpur"
    ],
    "name:ita_x_preferred":[
        "Sultanpur"
    ],
    "name:jpn_x_preferred":[
        "\u30b9\u30eb\u30bf\u30fc\u30f3\u30d7\u30eb"
    ],
    "name:nld_x_preferred":[
        "Sultanpur"
    ],
    "name:pol_x_preferred":[
        "Sultanpur"
    ],
    "name:rus_x_preferred":[
        "\u0421\u0443\u043b\u0442\u0430\u043d\u043f\u0443\u0440"
    ],
    "name:swe_x_preferred":[
        "Sultanpur"
    ],
    "wof:name":"Sultanpur",
    "wof:placetype":"locality"
},
  "geometry": {"coordinates":[88.59815999999999,25.75922000000001],"type":"Point"}
}