{
  "type": "Feature",
  "properties": {
    "gn:admin1_code":"85",
    "gn:admin2_code":"1078",
    "gn:admin3_code":"107876.0",
    "gn:admin4_code":"10787640.0",
    "gn:asciiname":"Mahakuma",
    "gn:country_code":"BD",
    "gn:dem":10,
    "gn:feature_class":"P",
    "gn:feature_code":"PPL",
    "gn:name":"Mahakuma",
    "gn:population":0,
    "gn:timezone":"Asia/Dhaka",
    "iso:country":"BD",
    "name:ben_x_preferred":[
        "Mahakuma"
    ],
    "name:ben_x_variant":[
        "\u09ae\u09b9\u0995\u09c1\u09ae\u09be"
    ],
    "name:ell_x_preferred":[
        "\u039c\u03b1\u03c7\u03b1\u03ba\u03bf\u03cd\u03bc\u03b1"
    ],
    "wof:name":"Mahakuma",
    "wof:placetype":"locality"
},
  "geometry": {"coordinates":[90.17424,22.30755],"type":"Point"}
}