{
  "type": "Feature",
  "properties": {
    "gn:admin1_code":"84",
    "gn:admin2_code":"2084.0",
    "gn:admin3_code":"208425.0",
    "gn:admin4_code":"20842557.0",
    "gn:asciiname":"Karbaripara",
    "gn:country_code":"BD",
    "gn:dem":58,
    "gn:feature_class":"P",
    "gn:feature_code":"PPL",
    "gn:name":"K\u0101rb\u0101rip\u0101ra",
    "gn:population":0,
    "gn:timezone":"Asia/Dhaka",
    "iso:country":"BD",
    "name:ben_x_preferred":[
        "K\u0101rb\u0101rip\u0101ra"
    ],
    "name:ben_x_variant":[
        "K\u0101r\u0101rip\u0101ra"
    ],
    "wof:name":"Karbaripara",
    "wof:placetype":"locality"
},
  "geometry": {"coordinates":[92.05965999999999,22.65671],"type":"Point"}
}