{
  "type": "Feature",
  "properties": {
    "gn:admin1_code":"85",
    "gn:admin2_code":"1078.0",
    "gn:admin3_code":"107897.0",
    "gn:admin4_code":"10789783.0",
    "gn:asciiname":"Kataban",
    "gn:country_code":"BD",
    "gn:dem":8,
    "gn:feature_class":"P",
    "gn:feature_code":"PPL",
    "gn:name":"Kat\u0101ban",
    "gn:population":0,
    "gn:timezone":"Asia/Dhaka",
    "iso:country":"BD",
    "name:ben_x_preferred":[
        "Kat\u0101ban"
    ],
    "wof:name":"Kataban",
    "wof:placetype":"locality"
},
  "geometry": {"coordinates":[90.41952000000001,21.91443],"type":"Point"}
}