{
  "type": "Feature",
  "properties": {
    "gn:admin1_code":"83",
    "gn:admin2_code":"5038.0",
    "gn:admin3_code":"503874.0",
    "gn:admin4_code":"50387410.0",
    "gn:asciiname":"Santodigar",
    "gn:country_code":"BD",
    "gn:dem":29,
    "gn:feature_class":"P",
    "gn:feature_code":"PPL",
    "gn:name":"Sant\u014ddigar",
    "gn:population":0,
    "gn:timezone":"Asia/Dhaka",
    "iso:country":"BD",
    "name:ben_x_preferred":[
        "Sant\u014ddigar"
    ],
    "wof:name":"Santodigar",
    "wof:placetype":"locality"
},
  "geometry": {"coordinates":[89.16123,25.15732],"type":"Point"}
}