{
  "type": "Feature",
  "properties": {
    "gn:admin1_code":"87",
    "gn:admin2_code":"5594",
    "gn:admin3_code":"559494.0",
    "gn:admin4_code":"55949431.0",
    "gn:asciiname":"Paharbhanga",
    "gn:country_code":"BD",
    "gn:dem":61,
    "gn:feature_class":"P",
    "gn:feature_code":"PPL",
    "gn:name":"Pah\u0101rbh\u0101nga",
    "gn:population":0,
    "gn:timezone":"Asia/Dhaka",
    "iso:country":"BD",
    "name:ben_x_preferred":[
        "Pah\u0101rbh\u0101nga"
    ],
    "wof:name":"Paharbhanga",
    "wof:placetype":"locality"
},
  "geometry": {"coordinates":[88.36819,26.06583],"type":"Point"}
}