{
  "type": "Feature",
  "properties": {
    "gn:admin1_code":"87",
    "gn:admin2_code":"5577.0",
    "gn:admin3_code":"557704.0",
    "gn:admin4_code":"55770413.0",
    "gn:asciiname":"Bahmankumar",
    "gn:country_code":"BD",
    "gn:dem":69,
    "gn:feature_class":"P",
    "gn:feature_code":"PPL",
    "gn:name":"B\u0101hmankumar",
    "gn:population":0,
    "gn:timezone":"Asia/Dhaka",
    "iso:country":"BD",
    "name:ben_x_preferred":[
        "B\u0101hmankumar"
    ],
    "wof:name":"Bahmankumar",
    "wof:placetype":"locality"
},
  "geometry": {"coordinates":[88.37293000000003,26.19312],"type":"Point"}
}