{
  "type": "Feature",
  "properties": {
    "gn:admin1_code":"84",
    "gn:admin2_code":"2022.0",
    "gn:admin3_code":"202216.0",
    "gn:admin4_code":"20221639.0",
    "gn:asciiname":"Betar Hat",
    "gn:country_code":"BD",
    "gn:dem":9,
    "gn:feature_class":"P",
    "gn:feature_code":"PPL",
    "gn:name":"Betar Hat",
    "gn:population":0,
    "gn:timezone":"Asia/Dhaka",
    "iso:country":"BD",
    "name:ben_x_preferred":[
        "Betar Hat"
    ],
    "wof:name":"Betar Hat",
    "wof:placetype":"locality"
},
  "geometry": {"coordinates":[92.04313,21.7724],"type":"Point"}
}