{
  "type": "Feature",
  "properties": {
    "gn:admin1_code":"85",
    "gn:admin2_code":"1078.0",
    "gn:admin3_code":"107838.0",
    "gn:admin4_code":"10783853.0",
    "gn:asciiname":"Dakshin Shaula",
    "gn:country_code":"BD",
    "gn:dem":9,
    "gn:feature_class":"P",
    "gn:feature_code":"PPL",
    "gn:name":"D\u0101kshin Shaula",
    "gn:population":0,
    "gn:timezone":"Asia/Dhaka",
    "iso:country":"BD",
    "name:ben_x_preferred":[
        "D\u0101kshin Shaula"
    ],
    "wof:name":"Dakshin Shaula",
    "wof:placetype":"locality"
},
  "geometry": {"coordinates":[90.61353,22.33685],"type":"Point"}
}