{
  "type": "Feature",
  "properties": {
    "gn:admin1_code":"87",
    "gn:admin2_code":"5585",
    "gn:admin3_code":"558549.0",
    "gn:admin4_code":"55854910.0",
    "gn:asciiname":"Nunipukur",
    "gn:country_code":"BD",
    "gn:dem":40,
    "gn:feature_class":"P",
    "gn:feature_code":"PPL",
    "gn:name":"Nunipukur",
    "gn:population":0,
    "gn:timezone":"Asia/Dhaka",
    "iso:country":"BD",
    "name:ben_x_preferred":[
        "Nunipukur"
    ],
    "wof:name":"Nunipukur",
    "wof:placetype":"locality"
},
  "geometry": {"coordinates":[89.14868,25.75283],"type":"Point"}
}