{
  "type": "Feature",
  "properties": {
    "gn:admin1_code":"82",
    "gn:admin2_code":"4055.0",
    "gn:admin3_code":"405557.0",
    "gn:admin4_code":"40555794.0",
    "gn:asciiname":"Baraikhali",
    "gn:country_code":"BD",
    "gn:dem":10,
    "gn:feature_class":"P",
    "gn:feature_code":"PPL",
    "gn:name":"B\u0101raikh\u0101li",
    "gn:population":0,
    "gn:timezone":"Asia/Dhaka",
    "iso:country":"BD",
    "name:ben_x_preferred":[
        "B\u0101raikh\u0101li"
    ],
    "wof:name":"Baraikhali",
    "wof:placetype":"locality"
},
  "geometry": {"coordinates":[89.48445,23.43629],"type":"Point"}
}