{
  "type": "Feature",
  "properties": {
    "gn:admin1_code":"83",
    "gn:admin2_code":"5069",
    "gn:admin3_code":"506991.0",
    "gn:admin4_code":"50699171.0",
    "gn:asciiname":"Soair",
    "gn:country_code":"BD",
    "gn:dem":16,
    "gn:feature_class":"P",
    "gn:feature_code":"PPL",
    "gn:name":"So\u0101ir",
    "gn:population":0,
    "gn:timezone":"Asia/Dhaka",
    "iso:country":"BD",
    "wof:name":"Soair",
    "wof:placetype":"locality"
},
  "geometry": {"coordinates":[89.16631,24.57613],"type":"Point"}
}