{
  "type": "Feature",
  "properties": {
    "gn:admin1_code":"81",
    "gn:admin2_code":"3086",
    "gn:admin3_code":"308625.0",
    "gn:admin4_code":"30862511.0",
    "gn:asciiname":"Dakshin Damadya",
    "gn:country_code":"BD",
    "gn:dem":12,
    "gn:feature_class":"P",
    "gn:feature_code":"PPL",
    "gn:name":"Dakshin D\u0101madya",
    "gn:population":0,
    "gn:timezone":"Asia/Dhaka",
    "iso:country":"BD",
    "name:und_x_variant":[
        "South Damuddya",
        "South Damudya",
        "South D\u0101madya",
        "Dakshin D\u0101madya"
    ],
    "wof:name":"Dakshin Damadya",
    "wof:placetype":"locality"
},
  "geometry": {"coordinates":[90.44394,23.14601],"type":"Point"}
}