{
  "type": "Feature",
  "properties": {
    "gn:admin1_code":"83",
    "gn:admin2_code":"5064.0",
    "gn:admin3_code":"506469.0",
    "gn:admin4_code":"50646963.0",
    "gn:asciiname":"Jharuapara",
    "gn:country_code":"BD",
    "gn:dem":31,
    "gn:feature_class":"P",
    "gn:feature_code":"PPL",
    "gn:name":"Jh\u0101ruap\u0101ra",
    "gn:population":0,
    "gn:timezone":"Asia/Dhaka",
    "iso:country":"BD",
    "name:ben_x_preferred":[
        "Jh\u0101ruap\u0101ra"
    ],
    "wof:name":"Jharuapara",
    "wof:placetype":"locality"
},
  "geometry": {"coordinates":[88.52206,24.79588],"type":"Point"}
}