{
  "type": "Feature",
  "properties": {
    "gn:admin1_code":"H",
    "gn:admin2_code":"3072.0",
    "gn:admin3_code":"307204.0",
    "gn:admin4_code":"30720435.0",
    "gn:asciiname":"Bamandi",
    "gn:country_code":"BD",
    "gn:dem":15,
    "gn:feature_class":"P",
    "gn:feature_code":"PPL",
    "gn:name":"B\u0101mandi",
    "gn:population":0,
    "gn:timezone":"Asia/Dhaka",
    "iso:country":"BD",
    "wof:name":"Bamandi",
    "wof:placetype":"locality"
},
  "geometry": {"coordinates":[90.9217,24.83261],"type":"Point"}
}