{
  "type": "Feature",
  "properties": {
    "gn:admin1_code":"82",
    "gn:admin2_code":"4047.0",
    "gn:admin3_code":"404717.0",
    "gn:admin4_code":"40471731.0",
    "gn:asciiname":"Chalna",
    "gn:country_code":"BD",
    "gn:dem":7,
    "gn:feature_class":"P",
    "gn:feature_code":"PPL",
    "gn:name":"Ch\u0101lna",
    "gn:population":0,
    "gn:timezone":"Asia/Dhaka",
    "iso:country":"BD",
    "name:und_x_variant":[
        "Chala",
        "Ch\u0101lna"
    ],
    "wof:name":"Chalna",
    "wof:placetype":"locality"
},
  "geometry": {"coordinates":[89.51806999999999,22.60242],"type":"Point"}
}