{
  "type": "Feature",
  "properties": {
    "gn:admin1_code":"83",
    "gn:admin2_code":"5081",
    "gn:admin3_code":"508172.0",
    "gn:admin4_code":"50817231.0",
    "gn:asciiname":"Pukuria",
    "gn:country_code":"BD",
    "gn:dem":21,
    "gn:feature_class":"P",
    "gn:feature_code":"PPL",
    "gn:name":"Pukuria",
    "gn:population":0,
    "gn:timezone":"Asia/Dhaka",
    "iso:country":"BD",
    "name:ben_x_preferred":[
        "Pukuria"
    ],
    "wof:name":"Pukuria",
    "wof:placetype":"locality"
},
  "geometry": {"coordinates":[88.54911,24.39818],"type":"Point"}
}