{
  "type": "Feature",
  "properties": {
    "gn:admin1_code":"82",
    "gn:admin2_code":"4087.0",
    "gn:admin3_code":"408782.0",
    "gn:admin4_code":"40878240.0",
    "gn:asciiname":"Sankhra",
    "gn:country_code":"BD",
    "gn:dem":9,
    "gn:feature_class":"P",
    "gn:feature_code":"PPL",
    "gn:name":"S\u0101nkhra",
    "gn:population":0,
    "gn:timezone":"Asia/Dhaka",
    "iso:country":"BD",
    "name:ben_x_preferred":[
        "S\u0101nkhra"
    ],
    "wof:name":"Sankhra",
    "wof:placetype":"locality"
},
  "geometry": {"coordinates":[88.95079,22.64318],"type":"Point"}
}