{
  "type": "Feature",
  "properties": {
    "gn:admin1_code":"87",
    "gn:admin2_code":"5527.0",
    "gn:admin3_code":"552738.0",
    "gn:admin4_code":"55273847.0",
    "gn:asciiname":"Ushahar",
    "gn:country_code":"BD",
    "gn:dem":34,
    "gn:feature_class":"P",
    "gn:feature_code":"PPL",
    "gn:name":"Ushah\u0101r",
    "gn:population":0,
    "gn:timezone":"Asia/Dhaka",
    "iso:country":"BD",
    "name:ben_x_preferred":[
        "Ushah\u0101r"
    ],
    "wof:name":"Ushahar",
    "wof:placetype":"locality"
},
  "geometry": {"coordinates":[88.82980000000001,25.4987],"type":"Point"}
}