{
  "type": "Feature",
  "properties": {
    "gn:admin1_code":"87",
    "gn:admin2_code":"5527",
    "gn:admin3_code":"552769.0",
    "gn:admin4_code":"55276925.0",
    "gn:asciiname":"Laoogari",
    "gn:country_code":"BD",
    "gn:dem":28,
    "gn:feature_class":"P",
    "gn:feature_code":"PPL",
    "gn:name":"Laoogari",
    "gn:population":0,
    "gn:timezone":"Asia/Dhaka",
    "iso:country":"BD",
    "name:ben_x_preferred":[
        "L\u0101ug\u0101ri"
    ],
    "name:und_x_variant":[
        "L\u0101ug\u0101ri"
    ],
    "wof:name":"Laoogari",
    "wof:placetype":"locality"
},
  "geometry": {"coordinates":[89.11596,25.38884],"type":"Point"}
}