{
  "type": "Feature",
  "properties": {
    "gn:admin1_code":"83",
    "gn:admin2_code":"5064.0",
    "gn:admin3_code":"506475.0",
    "gn:admin4_code":"50647577.0",
    "gn:asciiname":"Patichara",
    "gn:country_code":"BD",
    "gn:dem":26,
    "gn:feature_class":"P",
    "gn:feature_code":"PPL",
    "gn:name":"Patich\u0101ra",
    "gn:population":0,
    "gn:timezone":"Asia/Dhaka",
    "iso:country":"BD",
    "name:ben_x_preferred":[
        "Patich\u0101ra"
    ],
    "wof:name":"Patichara",
    "wof:placetype":"locality"
},
  "geometry": {"coordinates":[88.76347,25.06643],"type":"Point"}
}