{
  "type": "Feature",
  "properties": {
    "gn:admin1_code":"81",
    "gn:admin2_code":"3059",
    "gn:admin3_code":"305924.0",
    "gn:admin4_code":"30592442.0",
    "gn:asciiname":"Pradhaner Char",
    "gn:country_code":"BD",
    "gn:dem":10,
    "gn:feature_class":"P",
    "gn:feature_code":"PPL",
    "gn:name":"Pradh\u0101ner Char",
    "gn:population":0,
    "gn:timezone":"Asia/Dhaka",
    "iso:country":"BD",
    "wof:name":"Pradhaner Char",
    "wof:placetype":"locality"
},
  "geometry": {"coordinates":[90.6112,23.55325],"type":"Point"}
}