{
  "type": "Feature",
  "properties": {
    "gn:admin1_code":"83",
    "gn:admin2_code":"5076.0",
    "gn:admin3_code":"507683.0",
    "gn:admin4_code":"50768309.0",
    "gn:asciiname":"Birahimpur",
    "gn:country_code":"BD",
    "gn:dem":17,
    "gn:feature_class":"P",
    "gn:feature_code":"PPL",
    "gn:name":"Bir\u0101himpur",
    "gn:population":0,
    "gn:timezone":"Asia/Dhaka",
    "iso:country":"BD",
    "name:ben_x_preferred":[
        "Bir\u0101himpur"
    ],
    "wof:name":"Birahimpur",
    "wof:placetype":"locality"
},
  "geometry": {"coordinates":[89.56588000000001,23.95844],"type":"Point"}
}