{
  "type": "Feature",
  "properties": {
    "gn:admin1_code":"81",
    "gn:admin2_code":"3029",
    "gn:admin3_code":"302962.0",
    "gn:admin4_code":"30296294.0",
    "gn:asciiname":"Santoshi",
    "gn:country_code":"BD",
    "gn:dem":8,
    "gn:feature_class":"P",
    "gn:feature_code":"PPL",
    "gn:name":"Santoshi",
    "gn:population":0,
    "gn:timezone":"Asia/Dhaka",
    "iso:country":"BD",
    "wof:name":"Santoshi",
    "wof:placetype":"locality"
},
  "geometry": {"coordinates":[89.87380999999998,23.52078],"type":"Point"}
}