{
  "type": "Feature",
  "properties": {
    "gn:admin1_code":"83",
    "gn:admin2_code":"5064.0",
    "gn:admin3_code":"506406.0",
    "gn:admin4_code":"50640673.0",
    "gn:asciiname":"Faizabad",
    "gn:country_code":"BD",
    "gn:dem":22,
    "gn:feature_class":"P",
    "gn:feature_code":"PPL",
    "gn:name":"Faiz\u0101b\u0101d",
    "gn:population":0,
    "gn:timezone":"Asia/Dhaka",
    "iso:country":"BD",
    "name:ben_x_preferred":[
        "Faiz\u0101b\u0101d"
    ],
    "wof:name":"Faizabad",
    "wof:placetype":"locality"
},
  "geometry": {"coordinates":[88.93025,24.99303],"type":"Point"}
}