{
  "type": "Feature",
  "properties": {
    "gn:admin1_code":"81",
    "gn:admin2_code":"3059",
    "gn:admin3_code":"305944.0",
    "gn:admin4_code":"30594407.0",
    "gn:asciiname":"Kurigaon",
    "gn:country_code":"BD",
    "gn:dem":9,
    "gn:feature_class":"P",
    "gn:feature_code":"PPL",
    "gn:name":"Kurigaon",
    "gn:population":0,
    "gn:timezone":"Asia/Dhaka",
    "iso:country":"BD",
    "wof:name":"Kurigaon",
    "wof:placetype":"locality"
},
  "geometry": {"coordinates":[90.3475,23.48827],"type":"Point"}
}