{
  "type": "Feature",
  "properties": {
    "gn:admin1_code":"85",
    "gn:admin2_code":"1078",
    "gn:admin3_code":"107897.0",
    "gn:admin4_code":"10789783.0",
    "gn:asciiname":"Jugir Haola",
    "gn:country_code":"BD",
    "gn:dem":7,
    "gn:feature_class":"P",
    "gn:feature_code":"PPL",
    "gn:name":"Jugir Haola",
    "gn:population":0,
    "gn:timezone":"Asia/Dhaka",
    "iso:country":"BD",
    "name:ben_x_preferred":[
        "Jugir Haola"
    ],
    "name:und_x_variant":[
        "Jugirhowla",
        "Jugir Haola"
    ],
    "wof:name":"Jugir Haola",
    "wof:placetype":"locality"
},
  "geometry": {"coordinates":[90.45246,21.92861],"type":"Point"}
}