{
  "type": "Feature",
  "properties": {
    "gn:admin1_code":"81",
    "gn:admin2_code":"3086.0",
    "gn:admin3_code":"308669.0",
    "gn:admin4_code":"30866995.0",
    "gn:asciiname":"Arigaon",
    "gn:country_code":"BD",
    "gn:dem":10,
    "gn:feature_class":"P",
    "gn:feature_code":"PPL",
    "gn:name":"\u0100rigaon",
    "gn:population":0,
    "gn:timezone":"Asia/Dhaka",
    "iso:country":"BD",
    "wof:name":"Arigaon",
    "wof:placetype":"locality"
},
  "geometry": {"coordinates":[90.32467,23.21909],"type":"Point"}
}