{
  "type": "Feature",
  "properties": {
    "gn:admin1_code":"83",
    "gn:admin2_code":"5064.0",
    "gn:admin3_code":"506447.0",
    "gn:admin4_code":"50644727.0",
    "gn:asciiname":"Bhadrasona",
    "gn:country_code":"BD",
    "gn:dem":18,
    "gn:feature_class":"P",
    "gn:feature_code":"PPL",
    "gn:name":"Bhadrasona",
    "gn:population":0,
    "gn:timezone":"Asia/Dhaka",
    "iso:country":"BD",
    "name:ben_x_preferred":[
        "Bhadrasona"
    ],
    "name:ben_x_variant":[
        "Bhadrasana"
    ],
    "wof:name":"Bhadrasona",
    "wof:placetype":"locality"
},
  "geometry": {"coordinates":[88.76098,24.79311],"type":"Point"}
}