{
  "type": "Feature",
  "properties": {
    "gn:admin1_code":"82",
    "gn:admin2_code":"4087.0",
    "gn:admin3_code":"408786.0",
    "gn:admin4_code":"40878615.0",
    "gn:asciiname":"Ballavpur",
    "gn:country_code":"BD",
    "gn:dem":5,
    "gn:feature_class":"P",
    "gn:feature_code":"PPL",
    "gn:name":"Ballavpur",
    "gn:population":0,
    "gn:timezone":"Asia/Dhaka",
    "iso:country":"BD",
    "name:ben_x_preferred":[
        "Ballavpur"
    ],
    "name:ben_x_variant":[
        "\u09ac\u09b2\u09cd\u09b2\u09ad\u09aa\u09c1\u09b0"
    ],
    "name:bpy_x_preferred":[
        "\u09ac\u09b2\u09cd\u09b2\u09ad\u09aa\u09c1\u09b0"
    ],
    "name:ita_x_preferred":[
        "Ballavpur"
    ],
    "name:mlg_x_preferred":[
        "Ballavpur"
    ],
    "name:msa_x_preferred":[
        "Ballavpur"
    ],
    "name:new_x_preferred":[
        "\u092c\u0932\u094d\u0932\u092d\u092a\u0941\u0930"
    ],
    "name:nld_x_preferred":[
        "Ballavpur"
    ],
    "name:por_x_preferred":[
        "Ballavpur"
    ],
    "name:und_x_variant":[
        "Ballabhpur"
    ],
    "name:vie_x_preferred":[
        "Ballavpur"
    ],
    "name:zho_x_preferred":[
        "\u5df4\u62c9\u6c83\u666e\u5c14"
    ],
    "wof:name":"Ballavpur",
    "wof:placetype":"locality"
},
  "geometry": {"coordinates":[89.09147,22.34858],"type":"Point"}
}