{
  "type": "Feature",
  "properties": {
    "gn:admin1_code":"83",
    "gn:admin2_code":"5076.0",
    "gn:admin3_code":"507672.0",
    "gn:admin4_code":"50767243.0",
    "gn:asciiname":"Ghugudaha",
    "gn:country_code":"BD",
    "gn:dem":14,
    "gn:feature_class":"P",
    "gn:feature_code":"PPL",
    "gn:name":"Ghugud\u0101ha",
    "gn:population":0,
    "gn:timezone":"Asia/Dhaka",
    "iso:country":"BD",
    "name:ben_x_preferred":[
        "Ghugud\u0101ha"
    ],
    "wof:name":"Ghugudaha",
    "wof:placetype":"locality"
},
  "geometry": {"coordinates":[89.5356,23.99608],"type":"Point"}
}