{
  "type": "Feature",
  "properties": {
    "gn:admin1_code":"H",
    "gn:admin2_code":"3061",
    "gn:admin3_code":"306120.0",
    "gn:admin4_code":"30612083.0",
    "gn:asciiname":"Patuli",
    "gn:country_code":"BD",
    "gn:dem":17,
    "gn:feature_class":"P",
    "gn:feature_code":"PPL",
    "gn:name":"P\u0101tuli",
    "gn:population":0,
    "gn:timezone":"Asia/Dhaka",
    "iso:country":"BD",
    "name:ben_x_preferred":[
        "\u09aa\u09be\u099f\u09c1\u09b2\u09c0"
    ],
    "name:bpy_x_preferred":[
        "\u09aa\u09be\u09a4\u09c1\u09b2\u09bf"
    ],
    "name:ceb_x_preferred":[
        "P\u0101tuli"
    ],
    "name:ita_x_preferred":[
        "Patuli"
    ],
    "name:mlg_x_preferred":[
        "Patuli"
    ],
    "name:msa_x_preferred":[
        "Patuli"
    ],
    "name:nld_x_preferred":[
        "Patuli"
    ],
    "name:por_x_preferred":[
        "Patuli"
    ],
    "name:swe_x_preferred":[
        "P\u0101tuli"
    ],
    "name:vie_x_preferred":[
        "Patuli"
    ],
    "name:zho_x_preferred":[
        "\u5e15\u56fe\u5229"
    ],
    "wof:name":"Patuli",
    "wof:placetype":"locality"
},
  "geometry": {"coordinates":[90.20565000000001,24.61871],"type":"Point"}
}