{
  "type": "Feature",
  "properties": {
    "gn:admin1_code":"84",
    "gn:admin2_code":"2019.0",
    "gn:admin3_code":"201972.0",
    "gn:admin4_code":"20197277.0",
    "gn:asciiname":"Chhota Chandpur",
    "gn:country_code":"BD",
    "gn:dem":11,
    "gn:feature_class":"P",
    "gn:feature_code":"PPL",
    "gn:name":"Chhota Ch\u0101ndpur",
    "gn:population":0,
    "gn:timezone":"Asia/Dhaka",
    "iso:country":"BD",
    "wof:name":"Chhota Chandpur",
    "wof:placetype":"locality"
},
  "geometry": {"coordinates":[91.09999999999999,23.25],"type":"Point"}
}