{
  "type": "Feature",
  "properties": {
    "gn:admin1_code":"84",
    "gn:admin2_code":"2015.0",
    "gn:admin3_code":"201504.0",
    "gn:admin4_code":"20150485.0",
    "gn:asciiname":"Deotala",
    "gn:country_code":"BD",
    "gn:dem":8,
    "gn:feature_class":"P",
    "gn:feature_code":"PPL",
    "gn:name":"Deotala",
    "gn:population":0,
    "gn:timezone":"Asia/Dhaka",
    "iso:country":"BD",
    "name:ben_x_preferred":[
        "Deotala"
    ],
    "wof:name":"Deotala",
    "wof:placetype":"locality"
},
  "geometry": {"coordinates":[91.9308,22.23541],"type":"Point"}
}