{
  "type": "Feature",
  "properties": {
    "gn:admin1_code":"82",
    "gn:admin2_code":"4041.0",
    "gn:admin3_code":"404111.0",
    "gn:admin4_code":"40411125.0",
    "gn:asciiname":"Jatrapur",
    "gn:country_code":"BD",
    "gn:dem":16,
    "gn:feature_class":"P",
    "gn:feature_code":"PPL",
    "gn:name":"Jatrapur",
    "gn:population":0,
    "gn:timezone":"Asia/Dhaka",
    "iso:country":"BD",
    "name:ben_x_preferred":[
        "Jatrapur"
    ],
    "wof:name":"Jatrapur",
    "wof:placetype":"locality"
},
  "geometry": {"coordinates":[89.05752,23.32694],"type":"Point"}
}