{
  "type": "Feature",
  "properties": {
    "gn:admin1_code":"81",
    "gn:admin2_code":"3056",
    "gn:admin3_code":"305610.0",
    "gn:admin4_code":"30561076.0",
    "gn:asciiname":"Mir Hatail",
    "gn:country_code":"BD",
    "gn:dem":16,
    "gn:feature_class":"P",
    "gn:feature_code":"PPL",
    "gn:name":"Mir H\u0101t\u0101il",
    "gn:population":0,
    "gn:timezone":"Asia/Dhaka",
    "iso:country":"BD",
    "wof:name":"Mir Hatail",
    "wof:placetype":"locality"
},
  "geometry": {"coordinates":[89.90985000000001,23.99241],"type":"Point"}
}