{
  "type": "Feature",
  "properties": {
    "gn:admin1_code":"83",
    "gn:admin2_code":"5064.0",
    "gn:admin3_code":"506486.0",
    "gn:admin4_code":"50648694.0",
    "gn:asciiname":"Damdama",
    "gn:country_code":"BD",
    "gn:dem":32,
    "gn:feature_class":"P",
    "gn:feature_code":"PPL",
    "gn:name":"Damdama",
    "gn:population":0,
    "gn:timezone":"Asia/Dhaka",
    "iso:country":"BD",
    "name:ara_x_preferred":[
        "\u062f\u0627\u0645\u062f\u0627\u0645\u0627"
    ],
    "name:aze_x_preferred":[
        "Damdama"
    ],
    "name:ben_x_preferred":[
        "Damdama"
    ],
    "name:ceb_x_preferred":[
        "D\u0101md\u0101m\u0101"
    ],
    "name:fas_x_preferred":[
        "\u062f\u0627\u0645\u062f\u0627\u0645\u0627"
    ],
    "name:msa_x_preferred":[
        "Damdama"
    ],
    "name:swe_x_preferred":[
        "D\u0101md\u0101m\u0101"
    ],
    "wof:name":"Damdama",
    "wof:placetype":"locality"
},
  "geometry": {"coordinates":[88.59820000000001,25.0801],"type":"Point"}
}