{
  "type": "Feature",
  "properties": {
    "gn:admin1_code":"83",
    "gn:admin2_code":"5081",
    "gn:admin3_code":"508122.0",
    "gn:admin4_code":"50812224.0",
    "gn:asciiname":"Sirail",
    "gn:country_code":"BD",
    "gn:dem":20,
    "gn:feature_class":"P",
    "gn:feature_code":"PPL",
    "gn:name":"Sir\u0101il",
    "gn:population":0,
    "gn:timezone":"Asia/Dhaka",
    "iso:country":"BD",
    "wof:name":"Sirail",
    "wof:placetype":"locality"
},
  "geometry": {"coordinates":[88.61667,24.36667000000001],"type":"Point"}
}