{
  "type": "Feature",
  "properties": {
    "gn:admin1_code":"85",
    "gn:admin2_code":"1079.0",
    "gn:admin3_code":"107988.0",
    "gn:admin4_code":"10798851.0",
    "gn:asciiname":"Kalaia",
    "gn:country_code":"BD",
    "gn:dem":10,
    "gn:feature_class":"P",
    "gn:feature_code":"PPL",
    "gn:name":"Kalaia",
    "gn:population":0,
    "gn:timezone":"Asia/Dhaka",
    "iso:country":"BD",
    "name:ben_x_preferred":[
        "Kalaia"
    ],
    "wof:name":"Kalaia",
    "wof:placetype":"locality"
},
  "geometry": {"coordinates":[89.97198,22.46882],"type":"Point"}
}