{
  "type": "Feature",
  "properties": {
    "gn:admin1_code":"84",
    "gn:admin2_code":"2015.0",
    "gn:admin3_code":"201504.0",
    "gn:admin4_code":"20150495.0",
    "gn:asciiname":"Chunnapara",
    "gn:country_code":"BD",
    "gn:dem":7,
    "gn:feature_class":"P",
    "gn:feature_code":"PPL",
    "gn:name":"Chunn\u0101p\u0101ra",
    "gn:population":0,
    "gn:timezone":"Asia/Dhaka",
    "iso:country":"BD",
    "name:ben_x_preferred":[
        "Chunn\u0101p\u0101ra"
    ],
    "name:ben_x_variant":[
        "Chunaupara"
    ],
    "wof:name":"Chunnapara",
    "wof:placetype":"locality"
},
  "geometry": {"coordinates":[91.83136,22.17139],"type":"Point"}
}