{
  "type": "Feature",
  "properties": {
    "gn:admin1_code":"82",
    "gn:admin2_code":"4050",
    "gn:admin3_code":"405079.0",
    "gn:admin4_code":"40507918.0",
    "gn:asciiname":"Noapara",
    "gn:country_code":"BD",
    "gn:dem":15,
    "gn:feature_class":"P",
    "gn:feature_code":"PPL",
    "gn:name":"Noap\u0101ra",
    "gn:population":0,
    "gn:timezone":"Asia/Dhaka",
    "iso:country":"BD",
    "name:ben_x_preferred":[
        "Noap\u0101ra"
    ],
    "name:ben_x_variant":[
        "Naw\u0101p\u0101ra"
    ],
    "wof:name":"Noapara",
    "wof:placetype":"locality"
},
  "geometry": {"coordinates":[89.08235000000001,23.83332],"type":"Point"}
}