{
  "type": "Feature",
  "properties": {
    "gn:admin1_code":"83",
    "gn:admin2_code":"5070.0",
    "gn:admin3_code":"507018.0",
    "gn:admin4_code":"50701818.0",
    "gn:asciiname":"Joyrampur",
    "gn:country_code":"BD",
    "gn:dem":28,
    "gn:feature_class":"P",
    "gn:feature_code":"PPL",
    "gn:name":"Joyr\u0101mpur",
    "gn:population":0,
    "gn:timezone":"Asia/Dhaka",
    "iso:country":"BD",
    "name:ben_x_preferred":[
        "Joyr\u0101mpur"
    ],
    "wof:name":"Joyrampur",
    "wof:placetype":"locality"
},
  "geometry": {"coordinates":[88.21739000000002,24.95314],"type":"Point"}
}