{
  "type": "Feature",
  "properties": {
    "gn:admin1_code":"83",
    "gn:admin2_code":"5081",
    "gn:admin3_code":"508125.0",
    "gn:admin4_code":"50812531.0",
    "gn:asciiname":"Raypur",
    "gn:country_code":"BD",
    "gn:dem":19,
    "gn:feature_class":"P",
    "gn:feature_code":"PPL",
    "gn:name":"R\u0101ypur",
    "gn:population":0,
    "gn:timezone":"Asia/Dhaka",
    "iso:country":"BD",
    "name:ben_x_preferred":[
        "R\u0101ypur"
    ],
    "wof:name":"Raypur",
    "wof:placetype":"locality"
},
  "geometry": {"coordinates":[88.81924000000002,24.24145],"type":"Point"}
}