{
  "type": "Feature",
  "properties": {
    "gn:admin1_code":"81",
    "gn:admin2_code":"3068",
    "gn:admin3_code":"306863.0",
    "gn:admin4_code":"30686347.0",
    "gn:asciiname":"Ramanandi",
    "gn:country_code":"BD",
    "gn:dem":14,
    "gn:feature_class":"P",
    "gn:feature_code":"PPL",
    "gn:name":"R\u0101m\u0101nandi",
    "gn:population":0,
    "gn:timezone":"Asia/Dhaka",
    "iso:country":"BD",
    "wof:name":"Ramanandi",
    "wof:placetype":"locality"
},
  "geometry": {"coordinates":[90.68608999999999,23.9663],"type":"Point"}
}