{
  "type": "Feature",
  "properties": {
    "gn:admin1_code":"87",
    "gn:admin2_code":"5577",
    "gn:admin3_code":"557734.0",
    "gn:admin4_code":"55773466.0",
    "gn:asciiname":"Shikarpur",
    "gn:country_code":"BD",
    "gn:dem":62,
    "gn:feature_class":"P",
    "gn:feature_code":"PPL",
    "gn:name":"Sh\u012bk\u0101rpur",
    "gn:population":0,
    "gn:timezone":"Asia/Dhaka",
    "iso:country":"BD",
    "name:ben_x_preferred":[
        "Sh\u012bk\u0101rpur"
    ],
    "name:ceb_x_preferred":[
        "Shikarpur"
    ],
    "name:pol_x_preferred":[
        "Shikarpur"
    ],
    "name:pus_x_preferred":[
        "\u0634\u06a9\u0627\u0631\u067e\u0648\u0631"
    ],
    "name:swe_x_preferred":[
        "Shikarpur"
    ],
    "name:und_x_variant":[
        "Sikarpur"
    ],
    "name:urd_x_preferred":[
        "\u0634\u06a9\u0627\u0631\u067e\u0648\u0631"
    ],
    "name:vie_x_preferred":[
        "Shikarpur"
    ],
    "wof:name":"Shikarpur",
    "wof:placetype":"locality"
},
  "geometry": {"coordinates":[88.68046,26.17798],"type":"Point"}
}