{
  "type": "Feature",
  "properties": {
    "gn:admin1_code":"85",
    "gn:admin2_code":"1078",
    "gn:admin3_code":"107876.0",
    "gn:admin4_code":"10787681.0",
    "gn:asciiname":"Piprakhali",
    "gn:country_code":"BD",
    "gn:dem":0,
    "gn:feature_class":"P",
    "gn:feature_code":"PPL",
    "gn:name":"Pipr\u0101kh\u0101li",
    "gn:population":0,
    "gn:timezone":"Asia/Dhaka",
    "iso:country":"BD",
    "wof:name":"Piprakhali",
    "wof:placetype":"locality"
},
  "geometry": {"coordinates":[90.25875000000001,22.39171],"type":"Point"}
}