{
  "type": "Feature",
  "properties": {
    "gn:admin1_code":"86",
    "gn:admin2_code":"6090",
    "gn:admin3_code":"609050.0",
    "gn:admin4_code":"60905067.0",
    "gn:asciiname":"Sachna",
    "gn:country_code":"BD",
    "gn:dem":13,
    "gn:feature_class":"P",
    "gn:feature_code":"PPL",
    "gn:name":"Sachna",
    "gn:population":0,
    "gn:timezone":"Asia/Dhaka",
    "iso:country":"BD",
    "wof:name":"Sachna",
    "wof:placetype":"locality"
},
  "geometry": {"coordinates":[91.23560000000001,25.0097],"type":"Point"}
}