{
  "type": "Feature",
  "properties": {
    "gn:admin1_code":"83",
    "gn:admin2_code":"5010.0",
    "gn:admin3_code":"501021.0",
    "gn:admin4_code":"50102138.0",
    "gn:asciiname":"Bhadaikandi",
    "gn:country_code":"BD",
    "gn:dem":26,
    "gn:feature_class":"P",
    "gn:feature_code":"PPL",
    "gn:name":"Bh\u0101d\u0101ik\u0101ndi",
    "gn:population":0,
    "gn:timezone":"Asia/Dhaka",
    "iso:country":"BD",
    "name:und_x_variant":[
        "Bh\u0101d\u0101i Kh\u0101nda",
        "Bh\u0101d\u0101ik\u0101ndi"
    ],
    "wof:name":"Bhadaikandi",
    "wof:placetype":"locality"
},
  "geometry": {"coordinates":[89.31862,24.74806],"type":"Point"}
}