{
  "type": "Feature",
  "properties": {
    "gn:admin1_code":"87",
    "gn:admin2_code":"5532",
    "gn:admin3_code":"553291.0",
    "gn:admin4_code":"55329175.0",
    "gn:asciiname":"Rambhadra",
    "gn:country_code":"BD",
    "gn:dem":28,
    "gn:feature_class":"P",
    "gn:feature_code":"PPL",
    "gn:name":"R\u0101mbhadra",
    "gn:population":0,
    "gn:timezone":"Asia/Dhaka",
    "iso:country":"BD",
    "name:und_x_variant":[
        "R\u0101mbhadra",
        "T\u0101luk R\u0101mbhadra"
    ],
    "wof:name":"Rambhadra",
    "wof:placetype":"locality"
},
  "geometry": {"coordinates":[89.46825,25.5287],"type":"Point"}
}