{
  "type": "Feature",
  "properties": {
    "gn:admin1_code":"83",
    "gn:admin2_code":"5076.0",
    "gn:admin3_code":"507683.0",
    "gn:admin4_code":"50768328.0",
    "gn:asciiname":"Bhadarbhag",
    "gn:country_code":"BD",
    "gn:dem":12,
    "gn:feature_class":"P",
    "gn:feature_code":"PPL",
    "gn:name":"Bh\u0101darbh\u0101g",
    "gn:population":0,
    "gn:timezone":"Asia/Dhaka",
    "iso:country":"BD",
    "name:ben_x_preferred":[
        "Bh\u0101darbh\u0101g"
    ],
    "wof:name":"Bhadarbhag",
    "wof:placetype":"locality"
},
  "geometry": {"coordinates":[89.53796,23.86821],"type":"Point"}
}