{
  "type": "Feature",
  "properties": {
    "gn:admin1_code":"81",
    "gn:admin2_code":"3048.0",
    "gn:admin3_code":"304892.0",
    "gn:admin4_code":"30489227.0",
    "gn:asciiname":"Bheiarkona",
    "gn:country_code":"BD",
    "gn:dem":14,
    "gn:feature_class":"P",
    "gn:feature_code":"PPL",
    "gn:name":"Bhei\u0101rkona",
    "gn:population":0,
    "gn:timezone":"Asia/Dhaka",
    "iso:country":"BD",
    "wof:name":"Bheiarkona",
    "wof:placetype":"locality"
},
  "geometry": {"coordinates":[90.90609000000001,24.59469],"type":"Point"}
}