{
  "type": "Feature",
  "properties": {
    "gn:admin1_code":"81",
    "gn:admin2_code":"3048",
    "gn:admin3_code":"304879.0",
    "gn:admin4_code":"30487995.0",
    "gn:asciiname":"Jay Bishnapur",
    "gn:country_code":"BD",
    "gn:dem":15,
    "gn:feature_class":"P",
    "gn:feature_code":"PPL",
    "gn:name":"Jay Bishnapur",
    "gn:population":0,
    "gn:timezone":"Asia/Dhaka",
    "iso:country":"BD",
    "name:und_x_variant":[
        "Jay Bishnupur"
    ],
    "wof:name":"Jay Bishnapur",
    "wof:placetype":"locality"
},
  "geometry": {"coordinates":[90.68934,24.36331],"type":"Point"}
}