{
  "type": "Feature",
  "properties": {
    "gn:admin1_code":"81",
    "gn:admin2_code":"3067.0",
    "gn:admin3_code":"306706.0",
    "gn:admin4_code":"30670679.0",
    "gn:asciiname":"Gobindakul",
    "gn:country_code":"BD",
    "gn:dem":9,
    "gn:feature_class":"P",
    "gn:feature_code":"PPL",
    "gn:name":"Gobindakul",
    "gn:population":0,
    "gn:timezone":"Asia/Dhaka",
    "iso:country":"BD",
    "wof:name":"Gobindakul",
    "wof:placetype":"locality"
},
  "geometry": {"coordinates":[90.54234,23.64341],"type":"Point"}
}