{
  "type": "Feature",
  "properties": {
    "gn:admin1_code":"84",
    "gn:admin2_code":"2013",
    "gn:admin3_code":"201322.0",
    "gn:admin4_code":"20132263.0",
    "gn:asciiname":"Ibrahimpur",
    "gn:country_code":"BD",
    "gn:dem":8,
    "gn:feature_class":"P",
    "gn:feature_code":"PPL",
    "gn:name":"Ibr\u0101himpur",
    "gn:population":0,
    "gn:timezone":"Asia/Dhaka",
    "iso:country":"BD",
    "wof:name":"Ibrahimpur",
    "wof:placetype":"locality"
},
  "geometry": {"coordinates":[90.57308999999999,23.16192],"type":"Point"}
}