{
  "type": "Feature",
  "properties": {
    "gn:admin1_code":"81",
    "gn:admin2_code":"3033.0",
    "gn:admin3_code":"303336.0",
    "gn:admin4_code":"30333669.0",
    "gn:asciiname":"Char Nilakhi",
    "gn:country_code":"BD",
    "gn:dem":15,
    "gn:feature_class":"P",
    "gn:feature_code":"PPL",
    "gn:name":"Char Nil\u0101khi",
    "gn:population":0,
    "gn:timezone":"Asia/Dhaka",
    "iso:country":"BD",
    "wof:name":"Char Nilakhi",
    "wof:placetype":"locality"
},
  "geometry": {"coordinates":[90.67531,24.12947],"type":"Point"}
}