{
  "type": "Feature",
  "properties": {
    "gn:admin1_code":"H",
    "gn:admin2_code":"3072.0",
    "gn:admin3_code":"307263.0",
    "gn:admin4_code":"30726310.0",
    "gn:asciiname":"Bharera Baniagati",
    "gn:country_code":"BD",
    "gn:dem":7,
    "gn:feature_class":"P",
    "gn:feature_code":"PPL",
    "gn:name":"Bh\u0101rera B\u0101ni\u0101g\u0101ti",
    "gn:population":0,
    "gn:timezone":"Asia/Dhaka",
    "iso:country":"BD",
    "wof:name":"Bharera Baniagati",
    "wof:placetype":"locality"
},
  "geometry": {"coordinates":[90.96571,24.84712],"type":"Point"}
}