{
  "type": "Feature",
  "properties": {
    "gn:admin1_code":"81",
    "gn:admin2_code":"3067",
    "gn:admin3_code":"306704.0",
    "gn:admin4_code":"30670486.0",
    "gn:asciiname":"Shambhupura",
    "gn:country_code":"BD",
    "gn:dem":8,
    "gn:feature_class":"P",
    "gn:feature_code":"PPL",
    "gn:name":"Shambhupura",
    "gn:population":0,
    "gn:timezone":"Asia/Dhaka",
    "iso:country":"BD",
    "name:und_x_variant":[
        "Sambhupura"
    ],
    "wof:name":"Shambhupura",
    "wof:placetype":"locality"
},
  "geometry": {"coordinates":[90.55051,23.58138],"type":"Point"}
}