{
  "type": "Feature",
  "properties": {
    "gn:admin1_code":"87",
    "gn:admin2_code":"5549",
    "gn:admin3_code":"554977.0",
    "gn:admin4_code":"55497731.0",
    "gn:asciiname":"Ramkajji",
    "gn:country_code":"BD",
    "gn:dem":36,
    "gn:feature_class":"P",
    "gn:feature_code":"PPL",
    "gn:name":"R\u0101mk\u0101jji",
    "gn:population":0,
    "gn:timezone":"Asia/Dhaka",
    "iso:country":"BD",
    "name:ben_x_preferred":[
        "R\u0101mk\u0101jji"
    ],
    "wof:name":"Ramkajji",
    "wof:placetype":"locality"
},
  "geometry": {"coordinates":[89.55341,25.83034],"type":"Point"}
}