{
  "type": "Feature",
  "properties": {
    "gn:admin1_code":"82",
    "gn:admin2_code":"4087",
    "gn:admin3_code":"408704.0",
    "gn:admin4_code":"40870443.0",
    "gn:asciiname":"Sriramkati",
    "gn:country_code":"BD",
    "gn:dem":5,
    "gn:feature_class":"P",
    "gn:feature_code":"PPL",
    "gn:name":"Sr\u012br\u0101mk\u0101ti",
    "gn:population":0,
    "gn:timezone":"Asia/Dhaka",
    "iso:country":"BD",
    "name:fas_x_preferred":[
        "\u0633\u0631\u06cc\u0631\u0645\u06a9\u0627\u062a\u06cc"
    ],
    "wof:name":"Sriramkati",
    "wof:placetype":"locality"
},
  "geometry": {"coordinates":[89.18888000000003,22.57495],"type":"Point"}
}