{
  "type": "Feature",
  "properties": {
    "gn:admin1_code":"83",
    "gn:asciiname":"Saroi",
    "gn:country_code":"BD",
    "gn:dem":29,
    "gn:feature_class":"P",
    "gn:feature_code":"PPL",
    "gn:name":"S\u0101r\u014di",
    "gn:population":0,
    "gn:timezone":"Asia/Dhaka",
    "iso:country":"BD",
    "name:ben_x_preferred":[
        "S\u0101r\u014di"
    ],
    "name:fas_x_preferred":[
        "\u0633\u0627\u0631\u0648\u06cc"
    ],
    "name:urd_x_preferred":[
        "\u0633\u0627\u0631\u0648\u06cc"
    ],
    "wof:name":"Saroi",
    "wof:placetype":"locality"
},
  "geometry": {"coordinates":[89.29942,25.14725],"type":"Point"}
}