{
  "type": "Feature",
  "properties": {
    "gn:admin1_code":"87",
    "gn:admin2_code":"5585",
    "gn:admin3_code":"558558.0",
    "gn:admin4_code":"55855883.0",
    "gn:asciiname":"Batan",
    "gn:country_code":"BD",
    "gn:dem":31,
    "gn:feature_class":"P",
    "gn:feature_code":"PPL",
    "gn:name":"Batan",
    "gn:population":0,
    "gn:timezone":"Asia/Dhaka",
    "iso:country":"BD",
    "name:ben_x_preferred":[
        "Batan"
    ],
    "name:ceb_x_preferred":[
        "Batan"
    ],
    "name:deu_x_preferred":[
        "Batan"
    ],
    "name:fra_x_preferred":[
        "Batan"
    ],
    "name:ilo_x_preferred":[
        "Batan"
    ],
    "name:ita_x_preferred":[
        "Batan"
    ],
    "name:nld_x_preferred":[
        "Batan"
    ],
    "name:pol_x_preferred":[
        "Batan"
    ],
    "name:rus_x_preferred":[
        "\u0411\u0430\u0442\u0430\u043d"
    ],
    "name:spa_x_preferred":[
        "Bat\u00e1n"
    ],
    "name:swe_x_preferred":[
        "Batan"
    ],
    "name:ukr_x_preferred":[
        "\u0411\u0430\u0442\u0430\u043d"
    ],
    "wof:name":"Batan",
    "wof:placetype":"locality"
},
  "geometry": {"coordinates":[89.20958,25.59638],"type":"Point"}
}