{
  "type": "Feature",
  "properties": {
    "gn:admin1_code":"83",
    "gn:admin2_code":"5081.0",
    "gn:admin3_code":"508131.0",
    "gn:admin4_code":"50813111.0",
    "gn:asciiname":"Bakhtiarpur",
    "gn:country_code":"BD",
    "gn:dem":20,
    "gn:feature_class":"P",
    "gn:feature_code":"PPL",
    "gn:name":"Bakhtiarpur",
    "gn:population":0,
    "gn:timezone":"Asia/Dhaka",
    "iso:country":"BD",
    "name:ben_x_preferred":[
        "Bakhtiarpur"
    ],
    "name:ben_x_variant":[
        "\u09ac\u0996\u09a4\u09bf\u09af\u09bc\u09be\u09b0\u09aa\u09c1\u09b0"
    ],
    "name:bih_x_preferred":[
        "\u092c\u0916\u094d\u0924\u093f\u092f\u093e\u0930\u092a\u0941\u0930"
    ],
    "name:bpy_x_preferred":[
        "\u09ac\u0996\u09a4\u09bf\u09af\u09bc\u09be\u09b0\u09aa\u09c1\u09b0"
    ],
    "name:ceb_x_preferred":[
        "Bakhtiarpur"
    ],
    "name:deu_x_preferred":[
        "Bakhtiarpur"
    ],
    "name:hif_x_preferred":[
        "Bakhtiarpur"
    ],
    "name:hin_x_preferred":[
        "\u092c\u0916\u094d\u0924\u093f\u092f\u093e\u0930\u092a\u0941\u0930"
    ],
    "name:ita_x_preferred":[
        "Bakhtiarpur"
    ],
    "name:mar_x_preferred":[
        "\u092c\u0916\u094d\u0924\u093f\u092f\u093e\u0930\u092a\u0942\u0930"
    ],
    "name:msa_x_preferred":[
        "Bakhtiarpur"
    ],
    "name:new_x_preferred":[
        "\u092c\u0915\u0924\u0930\u093e\u0930\u092a\u0941\u0930"
    ],
    "name:nld_x_preferred":[
        "Bakhtiarpur"
    ],
    "name:por_x_preferred":[
        "Bakhtiarpur"
    ],
    "name:spa_x_preferred":[
        "Bakhtiarpur"
    ],
    "name:swe_x_preferred":[
        "Bakhtiarpur"
    ],
    "name:urd_x_preferred":[
        "\u0628\u062e\u062a\u06cc\u0627\u0631 \u067e\u0648\u0631"
    ],
    "name:vie_x_preferred":[
        "Bakhtiarpur"
    ],
    "name:zho_x_preferred":[
        "\u5df4\u514b\u8482\u4e9a\u5c14\u666e\u5c14"
    ],
    "wof:name":"Bakhtiarpur",
    "wof:placetype":"locality"
},
  "geometry": {"coordinates":[88.71966,24.47169],"type":"Point"}
}