{
  "type": "Feature",
  "properties": {
    "gn:admin1_code":"81",
    "gn:admin2_code":"3054",
    "gn:admin3_code":"305454.0",
    "gn:admin4_code":"30545435.0",
    "gn:asciiname":"West Madra",
    "gn:country_code":"BD",
    "gn:dem":6,
    "gn:feature_class":"P",
    "gn:feature_code":"PPL",
    "gn:name":"West M\u0101dra",
    "gn:population":0,
    "gn:timezone":"Asia/Dhaka",
    "iso:country":"BD",
    "name:und_x_variant":[
        "Paschim Madra",
        "West M\u0101dra"
    ],
    "wof:name":"West Madra",
    "wof:placetype":"locality"
},
  "geometry": {"coordinates":[90.21749,23.1269],"type":"Point"}
}