{
  "type": "Feature",
  "properties": {
    "gn:admin1_code":"H",
    "gn:admin2_code":"3061.0",
    "gn:admin3_code":"306122.0",
    "gn:admin4_code":"30612225.0",
    "gn:asciiname":"Hati Khola",
    "gn:country_code":"BD",
    "gn:dem":13,
    "gn:feature_class":"P",
    "gn:feature_code":"PPL",
    "gn:name":"H\u0101ti Khola",
    "gn:population":0,
    "gn:timezone":"Asia/Dhaka",
    "iso:country":"BD",
    "wof:name":"Hati Khola",
    "wof:placetype":"locality"
},
  "geometry": {"coordinates":[90.54439000000001,24.42115],"type":"Point"}
}