{
  "type": "Feature",
  "properties": {
    "gn:admin1_code":"82",
    "gn:admin2_code":"4050.0",
    "gn:admin3_code":"405079.0",
    "gn:admin4_code":"40507909.0",
    "gn:asciiname":"Sukkurpur",
    "gn:country_code":"BD",
    "gn:dem":17,
    "gn:feature_class":"P",
    "gn:feature_code":"PPL",
    "gn:name":"Sukkurpur",
    "gn:population":0,
    "gn:timezone":"Asia/Dhaka",
    "iso:country":"BD",
    "name:ben_x_preferred":[
        "Sukkurpur"
    ],
    "wof:name":"Sukkurpur",
    "wof:placetype":"locality"
},
  "geometry": {"coordinates":[89.13240999999999,23.72999],"type":"Point"}
}