{
  "type": "Feature",
  "properties": {
    "gn:admin1_code":"87",
    "gn:admin2_code":"5527.0",
    "gn:admin3_code":"552738.0",
    "gn:admin4_code":"55273809.0",
    "gn:asciiname":"Chandrapur",
    "gn:country_code":"BD",
    "gn:dem":36,
    "gn:feature_class":"P",
    "gn:feature_code":"PPL",
    "gn:name":"Chandrapur",
    "gn:population":0,
    "gn:timezone":"Asia/Dhaka",
    "iso:country":"BD",
    "name:ben_x_preferred":[
        "Chandrapur"
    ],
    "wof:name":"Chandrapur",
    "wof:placetype":"locality"
},
  "geometry": {"coordinates":[88.91847,25.49166],"type":"Point"}
}