{
  "type": "Feature",
  "properties": {
    "gn:admin1_code":"81",
    "gn:admin2_code":"3067.0",
    "gn:admin3_code":"306768.0",
    "gn:admin4_code":"30676831.0",
    "gn:asciiname":"Bir Hataba",
    "gn:country_code":"BD",
    "gn:dem":19,
    "gn:feature_class":"P",
    "gn:feature_code":"PPL",
    "gn:name":"Bir H\u0101t\u0101ba",
    "gn:population":0,
    "gn:timezone":"Asia/Dhaka",
    "iso:country":"BD",
    "wof:name":"Bir Hataba",
    "wof:placetype":"locality"
},
  "geometry": {"coordinates":[90.5408,23.86319],"type":"Point"}
}