{
  "type": "Feature",
  "properties": {
    "gn:admin1_code":"86",
    "gn:admin2_code":"6091",
    "gn:admin3_code":"609159.0",
    "gn:admin4_code":"60915985.0",
    "gn:asciiname":"Rajaganj",
    "gn:country_code":"BD",
    "gn:dem":12,
    "gn:feature_class":"P",
    "gn:feature_code":"PPL",
    "gn:name":"R\u0101j\u0101ganj",
    "gn:population":0,
    "gn:timezone":"Asia/Dhaka",
    "iso:country":"BD",
    "wof:name":"Rajaganj",
    "wof:placetype":"locality"
},
  "geometry": {"coordinates":[92.06667,24.91667],"type":"Point"}
}