{
  "type": "Feature",
  "properties": {
    "gn:admin1_code":"83",
    "gn:admin2_code":"5081",
    "gn:admin3_code":"508134.0",
    "gn:admin4_code":"50813466.0",
    "gn:asciiname":"Kanaipur",
    "gn:country_code":"BD",
    "gn:dem":37,
    "gn:feature_class":"P",
    "gn:feature_code":"PPL",
    "gn:name":"K\u0101n\u0101ipur",
    "gn:population":0,
    "gn:timezone":"Asia/Dhaka",
    "iso:country":"BD",
    "name:ben_x_preferred":[
        "K\u0101n\u0101ipur"
    ],
    "wof:name":"Kanaipur",
    "wof:placetype":"locality"
},
  "geometry": {"coordinates":[88.36117,24.54713],"type":"Point"}
}