{
  "type": "Feature",
  "properties": {
    "gn:admin1_code":"83",
    "gn:admin2_code":"5070.0",
    "gn:admin3_code":"507066.0",
    "gn:admin4_code":"50706611.0",
    "gn:asciiname":"Dinnathpur",
    "gn:country_code":"BD",
    "gn:dem":28,
    "gn:feature_class":"P",
    "gn:feature_code":"PPL",
    "gn:name":"Dinn\u0101thpur",
    "gn:population":0,
    "gn:timezone":"Asia/Dhaka",
    "iso:country":"BD",
    "name:ben_x_preferred":[
        "Dinn\u0101thpur"
    ],
    "name:ben_x_variant":[
        "Dinan\u0101thpur"
    ],
    "name:und_x_variant":[
        "Naud\u0101p\u0101ra"
    ],
    "wof:name":"Dinnathpur",
    "wof:placetype":"locality"
},
  "geometry": {"coordinates":[88.26465999999998,24.63588],"type":"Point"}
}