{
  "type": "Feature",
  "properties": {
    "gn:admin1_code":"H",
    "gn:admin2_code":"3061",
    "gn:admin3_code":"306165.0",
    "gn:admin4_code":"30616534.0",
    "gn:asciiname":"Kansabar Chechua",
    "gn:country_code":"BD",
    "gn:dem":21,
    "gn:feature_class":"P",
    "gn:feature_code":"PPL",
    "gn:name":"Kansab\u0101r Chechua",
    "gn:population":0,
    "gn:timezone":"Asia/Dhaka",
    "iso:country":"BD",
    "name:und_x_variant":[
        "Kansabarichechua",
        "Kansab\u0101r Chechua"
    ],
    "wof:name":"Kansabar Chechua",
    "wof:placetype":"locality"
},
  "geometry": {"coordinates":[90.15385000000001,24.77066],"type":"Point"}
}