{
  "type": "Feature",
  "properties": {
    "gn:admin1_code":"82",
    "gn:admin2_code":"4050.0",
    "gn:admin3_code":"405071.0",
    "gn:admin4_code":"40507100.0",
    "gn:asciiname":"Agrakuada",
    "gn:country_code":"BD",
    "gn:dem":12,
    "gn:feature_class":"P",
    "gn:feature_code":"PPL",
    "gn:name":"Agrakuada",
    "gn:population":0,
    "gn:timezone":"Asia/Dhaka",
    "iso:country":"BD",
    "name:ben_x_preferred":[
        "Agrakuada"
    ],
    "wof:name":"Agrakuada",
    "wof:placetype":"locality"
},
  "geometry": {"coordinates":[89.24890000000001,23.84576],"type":"Point"}
}