{
  "type": "Feature",
  "properties": {
    "gn:admin1_code":"85",
    "gn:admin2_code":"1078",
    "gn:admin3_code":"107838.0",
    "gn:admin4_code":"10783853.0",
    "gn:asciiname":"Kalaiya",
    "gn:country_code":"BD",
    "gn:dem":12,
    "gn:feature_class":"P",
    "gn:feature_code":"PPL",
    "gn:name":"K\u0101l\u0101iya",
    "gn:population":0,
    "gn:timezone":"Asia/Dhaka",
    "iso:country":"BD",
    "name:ben_x_preferred":[
        "K\u0101l\u0101iya"
    ],
    "name:ben_x_variant":[
        "K\u0101laia"
    ],
    "name:bih_x_preferred":[
        "\u0915\u0932\u0948\u092f\u093e"
    ],
    "name:deu_x_preferred":[
        "Kalaiya"
    ],
    "name:fra_x_preferred":[
        "Kalaiya"
    ],
    "name:mai_x_preferred":[
        "\u0915\u0932\u0948\u092f\u093e \u0928\u0917\u0930\u092a\u093e\u0932\u093f\u0915\u093e"
    ],
    "name:nep_x_preferred":[
        "\u0915\u0932\u0948\u092f\u093e \u0928\u0917\u0930\u092a\u093e\u0932\u093f\u0915\u093e"
    ],
    "name:new_x_preferred":[
        "\u0915\u0932\u0948\u092f\u093e \u0928\u0917\u0930\u092a\u093e\u0932\u093f\u0915\u093e"
    ],
    "name:nld_x_preferred":[
        "Kalaiya"
    ],
    "name:pol_x_preferred":[
        "Kalaiya"
    ],
    "name:por_x_preferred":[
        "Kalaiya"
    ],
    "name:rus_x_preferred":[
        "\u041a\u0430\u043b\u0430\u0439\u044f"
    ],
    "name:tam_x_preferred":[
        "\u0b95\u0bb2\u0bc8\u0baf\u0bbe"
    ],
    "name:urd_x_preferred":[
        "\u06a9\u0644\u0626\u06cc\u0627"
    ],
    "name:zho_x_preferred":[
        "\u5361\u840a\u4e9e"
    ],
    "wof:name":"Kalaiya",
    "wof:placetype":"locality"
},
  "geometry": {"coordinates":[90.60118,22.38882000000001],"type":"Point"}
}