{
  "type": "Feature",
  "properties": {
    "gn:admin1_code":"85",
    "gn:admin2_code":"1078",
    "gn:admin3_code":"107838.0",
    "gn:admin4_code":"10783853.0",
    "gn:asciiname":"Kalaiya",
    "gn:country_code":"BD",
    "gn:dem":12,
    "gn:feature_class":"P",
    "gn:feature_code":"PPL",
    "gn:name":"K\u0101l\u0101iya",
    "gn:population":0,
    "gn:timezone":"Asia/Dhaka",
    "iso:country":"BD",
    "name:ben_x_preferred":[
        "K\u0101l\u0101iya"
    ],
    "name:ben_x_variant":[
        "K\u0101laia"
    ],
    "wof:name":"Kalaiya",
    "wof:placetype":"locality"
},
  "geometry": {"coordinates":[90.60118,22.38882000000001],"type":"Point"}
}