{
  "type": "Feature",
  "properties": {
    "gn:admin1_code":"82",
    "gn:admin2_code":"4050",
    "gn:admin3_code":"405079.0",
    "gn:admin4_code":"40507975.0",
    "gn:asciiname":"Jaganathpur",
    "gn:country_code":"BD",
    "gn:dem":14,
    "gn:feature_class":"P",
    "gn:feature_code":"PPL",
    "gn:name":"Jagan\u0101thpur",
    "gn:population":0,
    "gn:timezone":"Asia/Dhaka",
    "iso:country":"BD",
    "name:ben_x_preferred":[
        "Jagan\u0101thpur"
    ],
    "name:ben_x_variant":[
        "Jagann\u0101thpur"
    ],
    "wof:name":"Jaganathpur",
    "wof:placetype":"locality"
},
  "geometry": {"coordinates":[89.14303000000002,23.86618],"type":"Point"}
}