{
  "type": "Feature",
  "properties": {
    "gn:admin1_code":"81",
    "gn:admin2_code":"3056",
    "gn:admin3_code":"305646.0",
    "gn:admin4_code":"30564694.0",
    "gn:asciiname":"Nulandi",
    "gn:country_code":"BD",
    "gn:dem":13,
    "gn:feature_class":"P",
    "gn:feature_code":"PPL",
    "gn:name":"Nulandi",
    "gn:population":0,
    "gn:timezone":"Asia/Dhaka",
    "iso:country":"BD",
    "wof:name":"Nulandi",
    "wof:placetype":"locality"
},
  "geometry": {"coordinates":[90.00785999999999,23.81902],"type":"Point"}
}