{
  "type": "Feature",
  "properties": {
    "gn:admin1_code":"H",
    "gn:admin2_code":"3072",
    "gn:admin3_code":"307283.0",
    "gn:admin4_code":"30728363.0",
    "gn:asciiname":"Sehala",
    "gn:country_code":"BD",
    "gn:dem":16,
    "gn:feature_class":"P",
    "gn:feature_code":"PPL",
    "gn:name":"Sehala",
    "gn:population":0,
    "gn:timezone":"Asia/Dhaka",
    "iso:country":"BD",
    "name:und_x_variant":[
        "Schala",
        "Sehala"
    ],
    "wof:name":"Sehala",
    "wof:placetype":"locality"
},
  "geometry": {"coordinates":[90.51952,24.99839],"type":"Point"}
}