{
  "type": "Feature",
  "properties": {
    "gn:admin1_code":"81",
    "gn:admin2_code":"3068.0",
    "gn:admin3_code":"306876.0",
    "gn:admin4_code":"30687652.0",
    "gn:asciiname":"Agarpur",
    "gn:country_code":"BD",
    "gn:dem":20,
    "gn:feature_class":"P",
    "gn:feature_code":"PPL",
    "gn:name":"\u0100garpur",
    "gn:population":0,
    "gn:timezone":"Asia/Dhaka",
    "iso:country":"BD",
    "wof:name":"Agarpur",
    "wof:placetype":"locality"
},
  "geometry": {"coordinates":[90.80264,23.9947],"type":"Point"}
}