{
  "type": "Feature",
  "properties": {
    "gn:admin1_code":"87",
    "gn:admin2_code":"5585.0",
    "gn:admin3_code":"558576.0",
    "gn:admin4_code":"55857631.0",
    "gn:asciiname":"Chatra",
    "gn:country_code":"BD",
    "gn:dem":31,
    "gn:feature_class":"P",
    "gn:feature_code":"PPL",
    "gn:name":"Chatra",
    "gn:population":0,
    "gn:timezone":"Asia/Dhaka",
    "iso:country":"BD",
    "wof:name":"Chatra",
    "wof:placetype":"locality"
},
  "geometry": {"coordinates":[89.29501999999999,25.34042],"type":"Point"}
}