{
  "type": "Feature",
  "properties": {
    "gn:admin1_code":"81",
    "gn:admin2_code":"3067.0",
    "gn:admin3_code":"306768.0",
    "gn:admin4_code":"30676863.0",
    "gn:asciiname":"Chhota Baniadi",
    "gn:country_code":"BD",
    "gn:dem":9,
    "gn:feature_class":"P",
    "gn:feature_code":"PPL",
    "gn:name":"Chhota B\u0101ni\u0101di",
    "gn:population":0,
    "gn:timezone":"Asia/Dhaka",
    "iso:country":"BD",
    "name:und_x_variant":[
        "Chhotta Baniadi",
        "Chhota B\u0101ni\u0101di"
    ],
    "wof:name":"Chhota Baniadi",
    "wof:placetype":"locality"
},
  "geometry": {"coordinates":[90.53196,23.7889],"type":"Point"}
}