{
  "type": "Feature",
  "properties": {
    "gn:admin1_code":"83",
    "gn:admin2_code":"5038.0",
    "gn:admin3_code":"503847.0",
    "gn:admin4_code":"50384728.0",
    "gn:asciiname":"Chhota Majhipara",
    "gn:country_code":"BD",
    "gn:dem":24,
    "gn:feature_class":"P",
    "gn:feature_code":"PPL",
    "gn:name":"Chhota M\u0101jhip\u0101ra",
    "gn:population":0,
    "gn:timezone":"Asia/Dhaka",
    "iso:country":"BD",
    "name:ben_x_preferred":[
        "Chhota M\u0101jhip\u0101ra"
    ],
    "wof:name":"Chhota Majhipara",
    "wof:placetype":"locality"
},
  "geometry": {"coordinates":[88.96306,25.08477],"type":"Point"}
}