{
  "type": "Feature",
  "properties": {
    "gn:admin1_code":"H",
    "gn:admin2_code":"3061.0",
    "gn:admin3_code":"306120.0",
    "gn:admin4_code":"30612083.0",
    "gn:asciiname":"Ghorsail",
    "gn:country_code":"BD",
    "gn:dem":18,
    "gn:feature_class":"P",
    "gn:feature_code":"PPL",
    "gn:name":"Ghors\u0101il",
    "gn:population":0,
    "gn:timezone":"Asia/Dhaka",
    "iso:country":"BD",
    "wof:name":"Ghorsail",
    "wof:placetype":"locality"
},
  "geometry": {"coordinates":[90.20287,24.67314],"type":"Point"}
}