{
  "type": "Feature",
  "properties": {
    "gn:admin1_code":"83",
    "gn:admin2_code":"5064.0",
    "gn:admin3_code":"506428.0",
    "gn:admin4_code":"50642884.0",
    "gn:asciiname":"Pagai Dewan",
    "gn:country_code":"BD",
    "gn:dem":25,
    "gn:feature_class":"P",
    "gn:feature_code":"PPL",
    "gn:name":"Pagai Dewan",
    "gn:population":0,
    "gn:timezone":"Asia/Dhaka",
    "iso:country":"BD",
    "name:ben_x_preferred":[
        "Pagai Dewan"
    ],
    "wof:name":"Pagai Dewan",
    "wof:placetype":"locality"
},
  "geometry": {"coordinates":[88.8369,25.13301],"type":"Point"}
}