{
  "type": "Feature",
  "properties": {
    "gn:admin1_code":"82",
    "gn:admin2_code":"4055",
    "gn:admin3_code":"405557.0",
    "gn:admin4_code":"40555706.0",
    "gn:asciiname":"West Bariala",
    "gn:country_code":"BD",
    "gn:dem":13,
    "gn:feature_class":"P",
    "gn:feature_code":"PPL",
    "gn:name":"West B\u0101ri\u0101la",
    "gn:population":0,
    "gn:timezone":"Asia/Dhaka",
    "iso:country":"BD",
    "name:und_x_variant":[
        "Paschim Bariala",
        "West B\u0101ri\u0101la"
    ],
    "wof:name":"West Bariala",
    "wof:placetype":"locality"
},
  "geometry": {"coordinates":[89.38382,23.5335],"type":"Point"}
}