{
  "type": "Feature",
  "properties": {
    "gn:admin1_code":"83",
    "gn:admin2_code":"5081",
    "gn:admin3_code":"508125.0",
    "gn:admin4_code":"50812539.0",
    "gn:asciiname":"Jhikra",
    "gn:country_code":"BD",
    "gn:dem":21,
    "gn:feature_class":"P",
    "gn:feature_code":"PPL",
    "gn:name":"Jhikra",
    "gn:population":0,
    "gn:timezone":"Asia/Dhaka",
    "iso:country":"BD",
    "name:ben_x_preferred":[
        "Jhikra"
    ],
    "wof:name":"Jhikra",
    "wof:placetype":"locality"
},
  "geometry": {"coordinates":[88.75714000000001,24.26737],"type":"Point"}
}