{
  "type": "Feature",
  "properties": {
    "gn:admin1_code":"H",
    "gn:admin2_code":"3039.0",
    "gn:admin3_code":"303936.0",
    "gn:admin4_code":"30393659.0",
    "gn:asciiname":"Banarerpar",
    "gn:country_code":"BD",
    "gn:dem":21,
    "gn:feature_class":"P",
    "gn:feature_code":"PPL",
    "gn:name":"B\u0101n\u0101rerp\u0101r",
    "gn:population":0,
    "gn:timezone":"Asia/Dhaka",
    "iso:country":"BD",
    "wof:name":"Banarerpar",
    "wof:placetype":"locality"
},
  "geometry": {"coordinates":[90.05027,24.83041],"type":"Point"}
}