{
  "type": "Feature",
  "properties": {
    "gn:admin1_code":"81",
    "gn:admin2_code":"3035.0",
    "gn:admin3_code":"303558.0",
    "gn:admin4_code":"30355844.0",
    "gn:asciiname":"North Kaligram",
    "gn:country_code":"BD",
    "gn:dem":8,
    "gn:feature_class":"P",
    "gn:feature_code":"PPL",
    "gn:name":"North Kaligr\u0101m",
    "gn:population":0,
    "gn:timezone":"Asia/Dhaka",
    "iso:country":"BD",
    "name:ben_x_preferred":[
        "North Kaligr\u0101m"
    ],
    "wof:name":"North Kaligram",
    "wof:placetype":"locality"
},
  "geometry": {"coordinates":[89.97237,23.19237],"type":"Point"}
}