{
  "type": "Feature",
  "properties": {
    "gn:admin1_code":"H",
    "gn:admin2_code":"3089",
    "gn:admin3_code":"308967.0",
    "gn:admin4_code":"30896766.0",
    "gn:asciiname":"Salua",
    "gn:country_code":"BD",
    "gn:dem":20,
    "gn:feature_class":"P",
    "gn:feature_code":"PPL",
    "gn:name":"S\u0101lua",
    "gn:population":0,
    "gn:timezone":"Asia/Dhaka",
    "iso:country":"BD",
    "name:ell_x_preferred":[
        "\u03a3\u03ac\u03bb\u03bf\u03c5\u03b1"
    ],
    "name:slk_x_preferred":[
        "Salua"
    ],
    "wof:name":"Salua",
    "wof:placetype":"locality"
},
  "geometry": {"coordinates":[90.21028,24.93129],"type":"Point"}
}