{
  "type": "Feature",
  "properties": {
    "gn:admin1_code":"83",
    "gn:admin2_code":"5081.0",
    "gn:admin3_code":"508134.0",
    "gn:admin4_code":"50813409.0",
    "gn:asciiname":"Avora",
    "gn:country_code":"BD",
    "gn:dem":23,
    "gn:feature_class":"P",
    "gn:feature_code":"PPL",
    "gn:name":"Avora",
    "gn:population":0,
    "gn:timezone":"Asia/Dhaka",
    "iso:country":"BD",
    "name:ben_x_preferred":[
        "Avora"
    ],
    "wof:name":"Avora",
    "wof:placetype":"locality"
},
  "geometry": {"coordinates":[88.31525000000001,24.51031],"type":"Point"}
}