{
  "type": "Feature",
  "properties": {
    "gn:admin1_code":"87",
    "gn:admin2_code":"5527.0",
    "gn:admin3_code":"552738.0",
    "gn:admin4_code":"55273838.0",
    "gn:asciiname":"Baraipara",
    "gn:country_code":"BD",
    "gn:dem":34,
    "gn:feature_class":"P",
    "gn:feature_code":"PPL",
    "gn:name":"Baraip\u0101ra",
    "gn:population":0,
    "gn:timezone":"Asia/Dhaka",
    "iso:country":"BD",
    "name:ben_x_preferred":[
        "Baraip\u0101ra"
    ],
    "wof:name":"Baraipara",
    "wof:placetype":"locality"
},
  "geometry": {"coordinates":[88.96292,25.44824],"type":"Point"}
}