{
  "type": "Feature",
  "properties": {
    "gn:admin1_code":"83",
    "gn:admin2_code":"5081",
    "gn:admin3_code":"508134.0",
    "gn:admin4_code":"50813409.0",
    "gn:asciiname":"Kabeitarpara",
    "gn:country_code":"BD",
    "gn:dem":26,
    "gn:feature_class":"P",
    "gn:feature_code":"PPL",
    "gn:name":"Kabeitarp\u0101ra",
    "gn:population":0,
    "gn:timezone":"Asia/Dhaka",
    "iso:country":"BD",
    "name:ben_x_preferred":[
        "Kabeitarp\u0101ra"
    ],
    "name:ben_x_variant":[
        "Kabutarp\u0101ra"
    ],
    "wof:name":"Kabeitarpara",
    "wof:placetype":"locality"
},
  "geometry": {"coordinates":[88.31408,24.50645],"type":"Point"}
}