{
  "type": "Feature",
  "properties": {
    "gn:admin1_code":"H",
    "gn:admin2_code":"3061.0",
    "gn:admin3_code":"306152.0",
    "gn:admin4_code":"30615227.0",
    "gn:asciiname":"Borar Char",
    "gn:country_code":"BD",
    "gn:dem":20,
    "gn:feature_class":"P",
    "gn:feature_code":"PPL",
    "gn:name":"Borar Char",
    "gn:population":0,
    "gn:timezone":"Asia/Dhaka",
    "iso:country":"BD",
    "wof:name":"Borar Char",
    "wof:placetype":"locality"
},
  "geometry": {"coordinates":[90.28943,24.87035],"type":"Point"}
}