{
  "type": "Feature",
  "properties": {
    "gn:admin1_code":"85",
    "gn:admin2_code":"1009.0",
    "gn:admin3_code":"100954.0",
    "gn:admin4_code":"10095485.0",
    "gn:asciiname":"Madhya Char Umed",
    "gn:country_code":"BD",
    "gn:dem":10,
    "gn:feature_class":"P",
    "gn:feature_code":"PPL",
    "gn:name":"Madhya Char Umed",
    "gn:population":0,
    "gn:timezone":"Asia/Dhaka",
    "iso:country":"BD",
    "name:ben_x_preferred":[
        "Madhya Char Umed"
    ],
    "wof:name":"Madhya Char Umed",
    "wof:placetype":"locality"
},
  "geometry": {"coordinates":[90.72112,22.27317],"type":"Point"}
}