{
  "type": "Feature",
  "properties": {
    "gn:admin1_code":"82",
    "gn:admin2_code":"4001.0",
    "gn:admin3_code":"400160.0",
    "gn:admin4_code":"40016059.0",
    "gn:asciiname":"Chalitabunia",
    "gn:country_code":"BD",
    "gn:dem":10,
    "gn:feature_class":"P",
    "gn:feature_code":"PPL",
    "gn:name":"Chalitabunia",
    "gn:population":0,
    "gn:timezone":"Asia/Dhaka",
    "iso:country":"BD",
    "name:ben_x_preferred":[
        "Chalitabunia"
    ],
    "wof:name":"Chalitabunia",
    "wof:placetype":"locality"
},
  "geometry": {"coordinates":[89.85465000000001,22.40926],"type":"Point"}
}