{
  "type": "Feature",
  "properties": {
    "gn:admin1_code":"83",
    "gn:admin2_code":"5081.0",
    "gn:admin3_code":"508172.0",
    "gn:admin4_code":"50817271.0",
    "gn:asciiname":"Choubaria",
    "gn:country_code":"BD",
    "gn:dem":21,
    "gn:feature_class":"P",
    "gn:feature_code":"PPL",
    "gn:name":"Choub\u0101ria",
    "gn:population":0,
    "gn:timezone":"Asia/Dhaka",
    "iso:country":"BD",
    "name:ben_x_preferred":[
        "Choub\u0101ria"
    ],
    "name:ben_x_variant":[
        "Chaub\u0101ria"
    ],
    "name:und_x_variant":[
        "Chubaria"
    ],
    "wof:name":"Choubaria",
    "wof:placetype":"locality"
},
  "geometry": {"coordinates":[88.58637,24.44654],"type":"Point"}
}