{
  "type": "Feature",
  "properties": {
    "gn:admin1_code":"83",
    "gn:admin2_code":"5010",
    "gn:admin3_code":"501033.0",
    "gn:admin4_code":"50103354.0",
    "gn:asciiname":"Jarai",
    "gn:country_code":"BD",
    "gn:dem":22,
    "gn:feature_class":"P",
    "gn:feature_code":"PPL",
    "gn:name":"J\u0101rai",
    "gn:population":0,
    "gn:timezone":"Asia/Dhaka",
    "iso:country":"BD",
    "wof:name":"Jarai",
    "wof:placetype":"locality"
},
  "geometry": {"coordinates":[89.12264,24.91819],"type":"Point"}
}