{
  "type": "Feature",
  "properties": {
    "gn:admin1_code":"H",
    "gn:admin2_code":"3072.0",
    "gn:admin3_code":"307247.0",
    "gn:admin4_code":"30724747.0",
    "gn:asciiname":"Chaumuria",
    "gn:country_code":"BD",
    "gn:dem":12,
    "gn:feature_class":"P",
    "gn:feature_code":"PPL",
    "gn:name":"Chaumuria",
    "gn:population":0,
    "gn:timezone":"Asia/Dhaka",
    "iso:country":"BD",
    "wof:name":"Chaumuria",
    "wof:placetype":"locality"
},
  "geometry": {"coordinates":[90.8627,24.6625],"type":"Point"}
}