{
  "type": "Feature",
  "properties": {
    "gn:admin1_code":"83",
    "gn:asciiname":"Mahimaganj",
    "gn:country_code":"BD",
    "gn:dem":25,
    "gn:feature_class":"P",
    "gn:feature_code":"PPL",
    "gn:name":"Mahim\u0101ganj",
    "gn:population":0,
    "gn:timezone":"Asia/Dhaka",
    "iso:country":"BD",
    "name:ben_x_preferred":[
        "Mahim\u0101ganj"
    ],
    "wof:name":"Mahimaganj",
    "wof:placetype":"locality"
},
  "geometry": {"coordinates":[89.48953,25.10814],"type":"Point"}
}