{
  "type": "Feature",
  "properties": {
    "gn:admin1_code":"82",
    "gn:admin2_code":"4041.0",
    "gn:admin3_code":"404111.0",
    "gn:admin4_code":"40411177.0",
    "gn:asciiname":"Muhammadpur",
    "gn:country_code":"BD",
    "gn:dem":15,
    "gn:feature_class":"P",
    "gn:feature_code":"PPL",
    "gn:name":"Muhammadpur",
    "gn:population":0,
    "gn:timezone":"Asia/Dhaka",
    "iso:country":"BD",
    "name:ben_x_preferred":[
        "Muhammadpur"
    ],
    "wof:name":"Muhammadpur",
    "wof:placetype":"locality"
},
  "geometry": {"coordinates":[89.08022,23.26539],"type":"Point"}
}