{
  "type": "Feature",
  "properties": {
    "gn:admin1_code":"83",
    "gn:admin2_code":"5076",
    "gn:admin3_code":"507672.0",
    "gn:admin4_code":"50767251.0",
    "gn:asciiname":"Talat",
    "gn:country_code":"BD",
    "gn:dem":17,
    "gn:feature_class":"P",
    "gn:feature_code":"PPL",
    "gn:name":"Talat",
    "gn:population":0,
    "gn:timezone":"Asia/Dhaka",
    "iso:country":"BD",
    "name:ceb_x_preferred":[
        "Talat"
    ],
    "name:deu_x_preferred":[
        "Talat"
    ],
    "name:rus_x_preferred":[
        "\u0422\u0430\u043b\u0430\u0442"
    ],
    "wof:name":"Talat",
    "wof:placetype":"locality"
},
  "geometry": {"coordinates":[89.58646,24.07802],"type":"Point"}
}