{
  "type": "Feature",
  "properties": {
    "gn:admin1_code":"83",
    "gn:admin2_code":"5010",
    "gn:admin3_code":"501095.0",
    "gn:admin4_code":"50109552.0",
    "gn:asciiname":"Phulbaria",
    "gn:country_code":"BD",
    "gn:dem":23,
    "gn:feature_class":"P",
    "gn:feature_code":"PPL",
    "gn:name":"Phulb\u0101ria",
    "gn:population":0,
    "gn:timezone":"Asia/Dhaka",
    "iso:country":"BD",
    "name:ben_x_preferred":[
        "Phulb\u0101ria"
    ],
    "wof:name":"Phulbaria",
    "wof:placetype":"locality"
},
  "geometry": {"coordinates":[89.55509000000001,25.03635],"type":"Point"}
}