{
  "type": "Feature",
  "properties": {
    "gn:admin1_code":"H",
    "gn:admin2_code":"3061.0",
    "gn:admin3_code":"306194.0",
    "gn:admin4_code":"30619485.0",
    "gn:asciiname":"Aultia Golabhita",
    "gn:country_code":"BD",
    "gn:dem":17,
    "gn:feature_class":"P",
    "gn:feature_code":"PPL",
    "gn:name":"Aultia Gol\u0101bhita",
    "gn:population":0,
    "gn:timezone":"Asia/Dhaka",
    "iso:country":"BD",
    "wof:name":"Aultia Golabhita",
    "wof:placetype":"locality"
},
  "geometry": {"coordinates":[90.38751999999999,24.54929],"type":"Point"}
}