{
  "type": "Feature",
  "properties": {
    "gn:admin1_code":"87",
    "gn:admin2_code":"5527.0",
    "gn:admin3_code":"552738.0",
    "gn:admin4_code":"55273828.0",
    "gn:asciiname":"Chintaman",
    "gn:country_code":"BD",
    "gn:dem":32,
    "gn:feature_class":"P",
    "gn:feature_code":"PPL",
    "gn:name":"Chint\u0101m\u0101n",
    "gn:population":0,
    "gn:timezone":"Asia/Dhaka",
    "iso:country":"BD",
    "name:ben_x_preferred":[
        "Chint\u0101m\u0101n"
    ],
    "name:und_x_variant":[
        "Chintainan",
        "Chmtaman",
        "Chint\u0101nian"
    ],
    "wof:name":"Chintaman",
    "wof:placetype":"locality"
},
  "geometry": {"coordinates":[88.91266,25.43501],"type":"Point"}
}