{
  "type": "Feature",
  "properties": {
    "gn:admin1_code":"84",
    "gn:admin2_code":"2015.0",
    "gn:admin3_code":"201570.0",
    "gn:admin4_code":"20157051.0",
    "gn:asciiname":"Sahabinagar",
    "gn:country_code":"BD",
    "gn:dem":12,
    "gn:feature_class":"P",
    "gn:feature_code":"PPL",
    "gn:name":"Sahabinagar",
    "gn:population":0,
    "gn:timezone":"Asia/Dhaka",
    "iso:country":"BD",
    "name:ben_x_preferred":[
        "Sahabinagar"
    ],
    "wof:name":"Sahabinagar",
    "wof:placetype":"locality"
},
  "geometry": {"coordinates":[92.06408999999999,22.48646],"type":"Point"}
}