{
  "type": "Feature",
  "properties": {
    "gn:admin1_code":"83",
    "gn:admin2_code":"5069.0",
    "gn:admin3_code":"506991.0",
    "gn:admin4_code":"50699139.0",
    "gn:asciiname":"Dharail",
    "gn:country_code":"BD",
    "gn:dem":19,
    "gn:feature_class":"P",
    "gn:feature_code":"PPL",
    "gn:name":"Dhar\u0101il",
    "gn:population":0,
    "gn:timezone":"Asia/Dhaka",
    "iso:country":"BD",
    "wof:name":"Dharail",
    "wof:placetype":"locality"
},
  "geometry": {"coordinates":[89.07311,24.41313],"type":"Point"}
}