{
  "type": "Feature",
  "properties": {
    "gn:admin1_code":"83",
    "gn:admin2_code":"5081.0",
    "gn:admin3_code":"508110.0",
    "gn:admin4_code":"50811023.0",
    "gn:asciiname":"Tetulia",
    "gn:country_code":"BD",
    "gn:dem":19,
    "gn:feature_class":"P",
    "gn:feature_code":"PPL",
    "gn:name":"Tetulia",
    "gn:population":0,
    "gn:timezone":"Asia/Dhaka",
    "iso:country":"BD",
    "name:ben_x_preferred":[
        "Tetulia"
    ],
    "wof:name":"Tetulia",
    "wof:placetype":"locality"
},
  "geometry": {"coordinates":[88.85488000000002,24.24512],"type":"Point"}
}