{
  "type": "Feature",
  "properties": {
    "gn:admin1_code":"87",
    "gn:admin2_code":"5573.0",
    "gn:admin3_code":"557315.0",
    "gn:admin4_code":"55731557.0",
    "gn:asciiname":"Harinchara",
    "gn:country_code":"BD",
    "gn:dem":57,
    "gn:feature_class":"P",
    "gn:feature_code":"PPL",
    "gn:name":"Harinchara",
    "gn:population":0,
    "gn:timezone":"Asia/Dhaka",
    "iso:country":"BD",
    "name:ben_x_preferred":[
        "Harinchara"
    ],
    "wof:name":"Harinchara",
    "wof:placetype":"locality"
},
  "geometry": {"coordinates":[88.85469000000001,26.09304],"type":"Point"}
}