{
  "type": "Feature",
  "properties": {
    "gn:admin1_code":"83",
    "gn:admin2_code":"5064",
    "gn:admin3_code":"506450.0",
    "gn:admin4_code":"50645057.0",
    "gn:asciiname":"Murtazapur",
    "gn:country_code":"BD",
    "gn:dem":25,
    "gn:feature_class":"P",
    "gn:feature_code":"PPL",
    "gn:name":"Murtaz\u0101pur",
    "gn:population":0,
    "gn:timezone":"Asia/Dhaka",
    "iso:country":"BD",
    "name:ben_x_preferred":[
        "Murtaz\u0101pur"
    ],
    "name:und_x_variant":[
        "Martuzapur"
    ],
    "wof:name":"Murtazapur",
    "wof:placetype":"locality"
},
  "geometry": {"coordinates":[88.67586999999997,24.91799],"type":"Point"}
}