{
  "type": "Feature",
  "properties": {
    "gn:admin1_code":"85",
    "gn:admin2_code":"1006",
    "gn:admin3_code":"100603.0",
    "gn:admin4_code":"10060381.0",
    "gn:asciiname":"Kumariarpit",
    "gn:country_code":"BD",
    "gn:dem":11,
    "gn:feature_class":"P",
    "gn:feature_code":"PPL",
    "gn:name":"Kumari\u0101rpit",
    "gn:population":0,
    "gn:timezone":"Asia/Dhaka",
    "iso:country":"BD",
    "wof:name":"Kumariarpit",
    "wof:placetype":"locality"
},
  "geometry": {"coordinates":[90.34444000000001,22.80736],"type":"Point"}
}