{
  "type": "Feature",
  "properties": {
    "gn:admin1_code":"85",
    "gn:admin2_code":"1042.0",
    "gn:admin3_code":"104273.0",
    "gn:admin4_code":"10427363.0",
    "gn:asciiname":"Bhairabpasa",
    "gn:country_code":"BD",
    "gn:dem":9,
    "gn:feature_class":"P",
    "gn:feature_code":"PPL",
    "gn:name":"Bhairabp\u0101sa",
    "gn:population":0,
    "gn:timezone":"Asia/Dhaka",
    "iso:country":"BD",
    "wof:name":"Bhairabpasa",
    "wof:placetype":"locality"
},
  "geometry": {"coordinates":[90.24254999999999,22.64847],"type":"Point"}
}