{
  "type": "Feature",
  "properties": {
    "gn:admin1_code":"H",
    "gn:admin2_code":"3072",
    "gn:admin3_code":"307247.0",
    "gn:admin4_code":"30724747.0",
    "gn:asciiname":"Jafarpur",
    "gn:country_code":"BD",
    "gn:dem":13,
    "gn:feature_class":"P",
    "gn:feature_code":"PPL",
    "gn:name":"Jafarpur",
    "gn:population":0,
    "gn:timezone":"Asia/Dhaka",
    "iso:country":"BD",
    "wof:name":"Jafarpur",
    "wof:placetype":"locality"
},
  "geometry": {"coordinates":[90.86997,24.67199],"type":"Point"}
}