{
  "type": "Feature",
  "properties": {
    "gn:admin1_code":"84",
    "gn:admin2_code":"2019",
    "gn:admin3_code":"201954.0",
    "gn:admin4_code":"20195409.0",
    "gn:asciiname":"South Akalia",
    "gn:country_code":"BD",
    "gn:dem":11,
    "gn:feature_class":"P",
    "gn:feature_code":"PPL",
    "gn:name":"South Ak\u0101lia",
    "gn:population":0,
    "gn:timezone":"Asia/Dhaka",
    "iso:country":"BD",
    "name:und_x_variant":[
        "South Ak\u0101lia",
        "South \u0100k\u0101lia"
    ],
    "wof:name":"South Akalia",
    "wof:placetype":"locality"
},
  "geometry": {"coordinates":[90.81471000000001,23.6315],"type":"Point"}
}