{
  "type": "Feature",
  "properties": {
    "gn:admin1_code":"83",
    "gn:admin2_code":"5076",
    "gn:admin3_code":"507605.0",
    "gn:admin4_code":"50760547.0",
    "gn:asciiname":"Nagar Chachkia",
    "gn:country_code":"BD",
    "gn:dem":18,
    "gn:feature_class":"P",
    "gn:feature_code":"PPL",
    "gn:name":"Nagar Ch\u0101chkia",
    "gn:population":0,
    "gn:timezone":"Asia/Dhaka",
    "iso:country":"BD",
    "name:und_x_variant":[
        "Nagar",
        "Nagar Ch\u0101chkia"
    ],
    "wof:name":"Nagar Chachkia",
    "wof:placetype":"locality"
},
  "geometry": {"coordinates":[89.34040999999998,24.09326],"type":"Point"}
}