{
  "type": "Feature",
  "properties": {
    "gn:admin1_code":"84",
    "gn:admin2_code":"2019.0",
    "gn:admin3_code":"201936.0",
    "gn:admin4_code":"20193634.0",
    "gn:asciiname":"Elliotganj",
    "gn:country_code":"BD",
    "gn:dem":11,
    "gn:feature_class":"P",
    "gn:feature_code":"PPL",
    "gn:name":"Elliotganj",
    "gn:population":0,
    "gn:timezone":"Asia/Dhaka",
    "iso:country":"BD",
    "wof:name":"Elliotganj",
    "wof:placetype":"locality"
},
  "geometry": {"coordinates":[90.86281,23.51146],"type":"Point"}
}