{
  "type": "Feature",
  "properties": {
    "gn:admin1_code":"85",
    "gn:admin2_code":"1004.0",
    "gn:admin3_code":"100447.0",
    "gn:admin4_code":"10044783.0",
    "gn:asciiname":"Mainkhali",
    "gn:country_code":"BD",
    "gn:dem":10,
    "gn:feature_class":"P",
    "gn:feature_code":"PPL",
    "gn:name":"Mainkh\u0101li",
    "gn:population":0,
    "gn:timezone":"Asia/Dhaka",
    "iso:country":"BD",
    "name:ben_x_preferred":[
        "Mainkh\u0101li"
    ],
    "wof:name":"Mainkhali",
    "wof:placetype":"locality"
},
  "geometry": {"coordinates":[90.11872,22.27771],"type":"Point"}
}