{
  "type": "Feature",
  "properties": {
    "gn:admin1_code":"84",
    "gn:admin2_code":"2003.0",
    "gn:admin3_code":"200373.0",
    "gn:admin4_code":"20037319.0",
    "gn:asciiname":"Thuiripara",
    "gn:country_code":"BD",
    "gn:dem":67,
    "gn:feature_class":"P",
    "gn:feature_code":"PPL",
    "gn:name":"Thuirip\u0101ra",
    "gn:population":0,
    "gn:timezone":"Asia/Dhaka",
    "iso:country":"BD",
    "name:ben_x_preferred":[
        "Thuirip\u0101ra"
    ],
    "wof:name":"Thuiripara",
    "wof:placetype":"locality"
},
  "geometry": {"coordinates":[92.19628,21.64241],"type":"Point"}
}