{
  "type": "Feature",
  "properties": {
    "gn:admin1_code":"85",
    "gn:admin2_code":"1009.0",
    "gn:admin3_code":"100918.0",
    "gn:admin4_code":"10091836.0",
    "gn:asciiname":"Chhota Algi",
    "gn:country_code":"BD",
    "gn:dem":10,
    "gn:feature_class":"P",
    "gn:feature_code":"PPL",
    "gn:name":"Chhota Algi",
    "gn:population":0,
    "gn:timezone":"Asia/Dhaka",
    "iso:country":"BD",
    "wof:name":"Chhota Algi",
    "wof:placetype":"locality"
},
  "geometry": {"coordinates":[90.66018,22.68745],"type":"Point"}
}