{
  "type": "Feature",
  "properties": {
    "gn:admin1_code":"84",
    "gn:admin2_code":"2046.0",
    "gn:admin3_code":"204661.0",
    "gn:admin4_code":"20466147.0",
    "gn:asciiname":"Banarkatapara",
    "gn:country_code":"BD",
    "gn:dem":59,
    "gn:feature_class":"P",
    "gn:feature_code":"PPL",
    "gn:name":"B\u0101nark\u0101t\u0101p\u0101ra",
    "gn:population":0,
    "gn:timezone":"Asia/Dhaka",
    "iso:country":"BD",
    "name:ben_x_preferred":[
        "B\u0101nark\u0101t\u0101p\u0101ra"
    ],
    "wof:name":"Banarkatapara",
    "wof:placetype":"locality"
},
  "geometry": {"coordinates":[91.92117,22.8114],"type":"Point"}
}