{
  "type": "Feature",
  "properties": {
    "gn:admin1_code":"83",
    "gn:admin2_code":"5064.0",
    "gn:admin3_code":"506447.0",
    "gn:admin4_code":"50644713.0",
    "gn:asciiname":"Dhooyapara",
    "gn:country_code":"BD",
    "gn:dem":22,
    "gn:feature_class":"P",
    "gn:feature_code":"PPL",
    "gn:name":"Dhooyap\u0101ra",
    "gn:population":0,
    "gn:timezone":"Asia/Dhaka",
    "iso:country":"BD",
    "name:ben_x_preferred":[
        "Dhooyap\u0101ra"
    ],
    "wof:name":"Dhooyapara",
    "wof:placetype":"locality"
},
  "geometry": {"coordinates":[88.65902,24.73546],"type":"Point"}
}