{
  "type": "Feature",
  "properties": {
    "gn:admin1_code":"83",
    "gn:admin2_code":"5064",
    "gn:admin3_code":"506469.0",
    "gn:admin4_code":"50646952.0",
    "gn:asciiname":"Telihar",
    "gn:country_code":"BD",
    "gn:dem":30,
    "gn:feature_class":"P",
    "gn:feature_code":"PPL",
    "gn:name":"Telihar",
    "gn:population":0,
    "gn:timezone":"Asia/Dhaka",
    "iso:country":"BD",
    "name:ben_x_preferred":[
        "Telihar"
    ],
    "name:ben_x_variant":[
        "Telih\u0101ri"
    ],
    "name:und_x_variant":[
        "Telehari"
    ],
    "wof:name":"Telihar",
    "wof:placetype":"locality"
},
  "geometry": {"coordinates":[88.56962,24.8426],"type":"Point"}
}