{
  "type": "Feature",
  "properties": {
    "gn:admin1_code":"81",
    "gn:admin2_code":"3082",
    "gn:admin3_code":"308273.0",
    "gn:admin4_code":"30827350.0",
    "gn:asciiname":"Nibha Enayetpur",
    "gn:country_code":"BD",
    "gn:dem":15,
    "gn:feature_class":"P",
    "gn:feature_code":"PPL",
    "gn:name":"Nibha En\u0101yetpur",
    "gn:population":0,
    "gn:timezone":"Asia/Dhaka",
    "iso:country":"BD",
    "name:und_x_variant":[
        "Nibha Enayitpur",
        "Nibha En\u0101yetpur"
    ],
    "wof:name":"Nibha Enayetpur",
    "wof:placetype":"locality"
},
  "geometry": {"coordinates":[89.36609,23.81356],"type":"Point"}
}