{
  "type": "Feature",
  "properties": {
    "gn:admin1_code":"84",
    "gn:admin2_code":"2030.0",
    "gn:admin3_code":"203029.0",
    "gn:admin4_code":"20302982.0",
    "gn:asciiname":"Chhanua",
    "gn:country_code":"BD",
    "gn:dem":13,
    "gn:feature_class":"P",
    "gn:feature_code":"PPL",
    "gn:name":"Chhanua",
    "gn:population":0,
    "gn:timezone":"Asia/Dhaka",
    "iso:country":"BD",
    "wof:name":"Chhanua",
    "wof:placetype":"locality"
},
  "geometry": {"coordinates":[91.46666999999999,22.96667],"type":"Point"}
}