{
  "type": "Feature",
  "properties": {
    "gn:admin1_code":"83",
    "gn:admin2_code":"5064.0",
    "gn:admin3_code":"506475.0",
    "gn:admin4_code":"50647560.0",
    "gn:asciiname":"Fahimpur",
    "gn:country_code":"BD",
    "gn:dem":25,
    "gn:feature_class":"P",
    "gn:feature_code":"PPL",
    "gn:name":"Fahimpur",
    "gn:population":0,
    "gn:timezone":"Asia/Dhaka",
    "iso:country":"BD",
    "wof:name":"Fahimpur",
    "wof:placetype":"locality"
},
  "geometry": {"coordinates":[88.74551,25.01123],"type":"Point"}
}