{
  "type": "Feature",
  "properties": {
    "gn:admin1_code":"83",
    "gn:admin2_code":"5070.0",
    "gn:admin3_code":"507088.0",
    "gn:admin4_code":"50708847.0",
    "gn:asciiname":"Goabari Chandpur",
    "gn:country_code":"BD",
    "gn:dem":28,
    "gn:feature_class":"P",
    "gn:feature_code":"PPL",
    "gn:name":"Go\u0101b\u0101ri Chandpur",
    "gn:population":0,
    "gn:timezone":"Asia/Dhaka",
    "iso:country":"BD",
    "name:ben_x_preferred":[
        "Go\u0101b\u0101ri Chandpur"
    ],
    "wof:name":"Goabari Chandpur",
    "wof:placetype":"locality"
},
  "geometry": {"coordinates":[88.20295,24.74583],"type":"Point"}
}