{
  "type": "Feature",
  "properties": {
    "gn:admin1_code":"87",
    "gn:admin2_code":"5527.0",
    "gn:admin3_code":"552717.0",
    "gn:admin4_code":"55271747.0",
    "gn:asciiname":"Khailtair",
    "gn:country_code":"BD",
    "gn:dem":42,
    "gn:feature_class":"P",
    "gn:feature_code":"PPL",
    "gn:name":"Khailtair",
    "gn:population":0,
    "gn:timezone":"Asia/Dhaka",
    "iso:country":"BD",
    "name:ben_x_preferred":[
        "Khailtair"
    ],
    "wof:name":"Khailtair",
    "wof:placetype":"locality"
},
  "geometry": {"coordinates":[88.55813000000001,25.66418],"type":"Point"}
}