{
  "type": "Feature",
  "properties": {
    "gn:admin1_code":"87",
    "gn:admin2_code":"5527.0",
    "gn:admin3_code":"552712.0",
    "gn:admin4_code":"55271208.0",
    "gn:asciiname":"Singara",
    "gn:country_code":"BD",
    "gn:dem":51,
    "gn:feature_class":"P",
    "gn:feature_code":"PPL",
    "gn:name":"Sing\u0101ra",
    "gn:population":0,
    "gn:timezone":"Asia/Dhaka",
    "iso:country":"BD",
    "name:ben_x_preferred":[
        "Sing\u0101ra"
    ],
    "name:deu_x_preferred":[
        "Singara"
    ],
    "name:ell_x_preferred":[
        "\u03a3\u03af\u03bd\u03b3\u03ba\u03b1\u03c1\u03b1"
    ],
    "name:fra_x_preferred":[
        "Singara"
    ],
    "name:ita_x_preferred":[
        "Singara"
    ],
    "name:nld_x_preferred":[
        "Singara"
    ],
    "name:nor_x_preferred":[
        "Singara"
    ],
    "name:por_x_preferred":[
        "Singara"
    ],
    "name:rus_x_preferred":[
        "\u0421\u0438\u043d\u0433\u0430\u0440\u0430"
    ],
    "name:spa_x_preferred":[
        "Singara"
    ],
    "name:ukr_x_preferred":[
        "\u0421\u0438\u043d\u0433\u0430\u0440\u0430"
    ],
    "wof:name":"Singara",
    "wof:placetype":"locality"
},
  "geometry": {"coordinates":[88.55233,25.88829],"type":"Point"}
}