{
  "type": "Feature",
  "properties": {
    "gn:admin1_code":"87",
    "gn:admin2_code":"5549",
    "gn:admin3_code":"554961.0",
    "gn:admin4_code":"55496175.0",
    "gn:asciiname":"Bhagabatipur",
    "gn:country_code":"BD",
    "gn:dem":29,
    "gn:feature_class":"P",
    "gn:feature_code":"PPL",
    "gn:name":"Bhagabatipur",
    "gn:population":0,
    "gn:timezone":"Asia/Dhaka",
    "iso:country":"BD",
    "name:ben_x_preferred":[
        "Bhagabatipur"
    ],
    "wof:name":"Bhagabatipur",
    "wof:placetype":"locality"
},
  "geometry": {"coordinates":[89.77384000000001,25.85318],"type":"Point"}
}