{
  "type": "Feature",
  "properties": {
    "gn:admin1_code":"87",
    "gn:admin2_code":"5527",
    "gn:admin3_code":"552769.0",
    "gn:admin4_code":"55276943.0",
    "gn:asciiname":"Nutan Bamannagar",
    "gn:country_code":"BD",
    "gn:dem":34,
    "gn:feature_class":"P",
    "gn:feature_code":"PPL",
    "gn:name":"Nutan Bamannagar",
    "gn:population":0,
    "gn:timezone":"Asia/Dhaka",
    "iso:country":"BD",
    "name:ben_x_preferred":[
        "Nutan Bamannagar"
    ],
    "wof:name":"Nutan Bamannagar",
    "wof:placetype":"locality"
},
  "geometry": {"coordinates":[89.04120999999998,25.47584],"type":"Point"}
}