{
  "type": "Feature",
  "properties": {
    "gn:admin1_code":"84",
    "gn:admin2_code":"2022.0",
    "gn:admin3_code":"202216.0",
    "gn:admin4_code":"20221605.0",
    "gn:asciiname":"Chhanuapara",
    "gn:country_code":"BD",
    "gn:dem":3,
    "gn:feature_class":"P",
    "gn:feature_code":"PPL",
    "gn:name":"Chhanuap\u0101ra",
    "gn:population":0,
    "gn:timezone":"Asia/Dhaka",
    "iso:country":"BD",
    "name:ben_x_preferred":[
        "Chhanuap\u0101ra"
    ],
    "wof:name":"Chhanuapara",
    "wof:placetype":"locality"
},
  "geometry": {"coordinates":[91.97154,21.70777],"type":"Point"}
}