{
  "type": "Feature",
  "properties": {
    "gn:admin1_code":"84",
    "gn:admin2_code":"2015.0",
    "gn:admin3_code":"201504.0",
    "gn:admin4_code":"20150447.0",
    "gn:asciiname":"Burumchara",
    "gn:country_code":"BD",
    "gn:dem":8,
    "gn:feature_class":"P",
    "gn:feature_code":"PPL",
    "gn:name":"Burumchara",
    "gn:population":0,
    "gn:timezone":"Asia/Dhaka",
    "iso:country":"BD",
    "name:ben_x_preferred":[
        "Burumchhara"
    ],
    "name:ben_x_variant":[
        "Burumchara"
    ],
    "wof:name":"Burumchara",
    "wof:placetype":"locality"
},
  "geometry": {"coordinates":[91.89233,22.18029],"type":"Point"}
}