{
  "type": "Feature",
  "properties": {
    "gn:admin1_code":"81",
    "gn:admin2_code":"3054",
    "gn:admin3_code":"305454.0",
    "gn:admin4_code":"30545435.0",
    "gn:asciiname":"Jay Narayan Char",
    "gn:country_code":"BD",
    "gn:dem":6,
    "gn:feature_class":"P",
    "gn:feature_code":"PPL",
    "gn:name":"Jay Narayan Char",
    "gn:population":0,
    "gn:timezone":"Asia/Dhaka",
    "iso:country":"BD",
    "name:und_x_variant":[
        "Jayn\u0101r\u0101yans\u0101r H\u0101uli"
    ],
    "wof:name":"Jay Narayan Char",
    "wof:placetype":"locality"
},
  "geometry": {"coordinates":[90.20972999999999,23.13284],"type":"Point"}
}