{
  "type": "Feature",
  "properties": {
    "gn:admin1_code":"84",
    "gn:admin2_code":"2022.0",
    "gn:admin3_code":"202290.0",
    "gn:admin4_code":"20229063.0",
    "gn:asciiname":"Dailpara",
    "gn:country_code":"BD",
    "gn:dem":10,
    "gn:feature_class":"P",
    "gn:feature_code":"PPL",
    "gn:name":"Dailp\u0101ra",
    "gn:population":0,
    "gn:timezone":"Asia/Dhaka",
    "iso:country":"BD",
    "name:ben_x_preferred":[
        "Dailp\u0101ra"
    ],
    "wof:name":"Dailpara",
    "wof:placetype":"locality"
},
  "geometry": {"coordinates":[92.29294,20.85616],"type":"Point"}
}