{
  "type": "Feature",
  "properties": {
    "gn:admin1_code":"81",
    "gn:admin2_code":"3026.0",
    "gn:admin3_code":"302638.0",
    "gn:admin4_code":"30263860.0",
    "gn:asciiname":"Bhararia",
    "gn:country_code":"BD",
    "gn:dem":13,
    "gn:feature_class":"P",
    "gn:feature_code":"PPL",
    "gn:name":"Bh\u0101r\u0101ria",
    "gn:population":0,
    "gn:timezone":"Asia/Dhaka",
    "iso:country":"BD",
    "name:und_x_variant":[
        "\u0100ti Bh\u0101r\u0101ria",
        "Bh\u0101r\u0101ria"
    ],
    "wof:name":"Bhararia",
    "wof:placetype":"locality"
},
  "geometry": {"coordinates":[90.35023,23.71617],"type":"Point"}
}