{
  "type": "Feature",
  "properties": {
    "gn:admin1_code":"87",
    "gn:admin2_code":"5594.0",
    "gn:admin3_code":"559482.0",
    "gn:admin4_code":"55948243.0",
    "gn:asciiname":"Kismat",
    "gn:country_code":"BD",
    "gn:dem":48,
    "gn:feature_class":"P",
    "gn:feature_code":"PPL",
    "gn:name":"Kismat",
    "gn:population":0,
    "gn:timezone":"Asia/Dhaka",
    "iso:country":"BD",
    "name:ben_x_preferred":[
        "Kismat"
    ],
    "name:hin_x_preferred":[
        "\u0915\u093f\u0938\u094d\u092e\u0924"
    ],
    "wof:name":"Kismat",
    "wof:placetype":"locality"
},
  "geometry": {"coordinates":[88.2744,25.83025],"type":"Point"}
}