{
  "type": "Feature",
  "properties": {
    "gn:admin1_code":"82",
    "gn:admin2_code":"4041.0",
    "gn:admin3_code":"404161.0",
    "gn:admin4_code":"40416155.0",
    "gn:asciiname":"Ghugharali",
    "gn:country_code":"BD",
    "gn:dem":9,
    "gn:feature_class":"P",
    "gn:feature_code":"PPL",
    "gn:name":"Ghughar\u0101li",
    "gn:population":0,
    "gn:timezone":"Asia/Dhaka",
    "iso:country":"BD",
    "name:ben_x_preferred":[
        "Ghughar\u0101li"
    ],
    "wof:name":"Ghugharali",
    "wof:placetype":"locality"
},
  "geometry": {"coordinates":[89.19937,23.00316],"type":"Point"}
}