{
  "type": "Feature",
  "properties": {
    "gn:admin1_code":"87",
    "gn:admin2_code":"5573.0",
    "gn:admin3_code":"557364.0",
    "gn:admin4_code":"55736453.0",
    "gn:asciiname":"Kachua",
    "gn:country_code":"BD",
    "gn:dem":54,
    "gn:feature_class":"P",
    "gn:feature_code":"PPL",
    "gn:name":"Kachua",
    "gn:population":0,
    "gn:timezone":"Asia/Dhaka",
    "iso:country":"BD",
    "name:ben_x_preferred":[
        "Kachua"
    ],
    "wof:name":"Kachua",
    "wof:placetype":"locality"
},
  "geometry": {"coordinates":[88.83292,26.02237],"type":"Point"}
}