{
  "type": "Feature",
  "properties": {
    "gn:admin1_code":"82",
    "gn:admin2_code":"4041",
    "gn:admin3_code":"404123.0",
    "gn:admin4_code":"40412347.0",
    "gn:asciiname":"Mobarakpur",
    "gn:country_code":"BD",
    "gn:dem":13,
    "gn:feature_class":"P",
    "gn:feature_code":"PPL",
    "gn:name":"Mob\u0101rakpur",
    "gn:population":0,
    "gn:timezone":"Asia/Dhaka",
    "iso:country":"BD",
    "name:ben_x_preferred":[
        "Mob\u0101rakpur"
    ],
    "wof:name":"Mobarakpur",
    "wof:placetype":"locality"
},
  "geometry": {"coordinates":[89.10512,23.09894],"type":"Point"}
}