{
  "type": "Feature",
  "properties": {
    "gn:admin1_code":"82",
    "gn:admin2_code":"4087.0",
    "gn:admin3_code":"408782.0",
    "gn:admin4_code":"40878213.0",
    "gn:asciiname":"Agardari",
    "gn:country_code":"BD",
    "gn:dem":8,
    "gn:feature_class":"P",
    "gn:feature_code":"PPL",
    "gn:name":"\u0100gard\u0101ri",
    "gn:population":0,
    "gn:timezone":"Asia/Dhaka",
    "iso:country":"BD",
    "wof:name":"Agardari",
    "wof:placetype":"locality"
},
  "geometry": {"coordinates":[89.01326,22.76038],"type":"Point"}
}