{
  "type": "Feature",
  "properties": {
    "gn:admin1_code":"87",
    "gn:admin2_code":"5527.0",
    "gn:admin3_code":"552756.0",
    "gn:admin4_code":"55275679.0",
    "gn:asciiname":"Dwipnagar",
    "gn:country_code":"BD",
    "gn:dem":42,
    "gn:feature_class":"P",
    "gn:feature_code":"PPL",
    "gn:name":"Dwipnagar",
    "gn:population":0,
    "gn:timezone":"Asia/Dhaka",
    "iso:country":"BD",
    "name:ben_x_preferred":[
        "Dwipnagar"
    ],
    "wof:name":"Dwipnagar",
    "wof:placetype":"locality"
},
  "geometry": {"coordinates":[88.69121,25.79573],"type":"Point"}
}