{
  "type": "Feature",
  "properties": {
    "gn:admin1_code":"87",
    "gn:admin2_code":"5585",
    "gn:admin3_code":"558558.0",
    "gn:admin4_code":"55855867.0",
    "gn:asciiname":"Baluchar Kashinathpur",
    "gn:country_code":"BD",
    "gn:dem":33,
    "gn:feature_class":"P",
    "gn:feature_code":"PPL",
    "gn:name":"B\u0101luchar K\u0101shin\u0101thpur",
    "gn:population":0,
    "gn:timezone":"Asia/Dhaka",
    "iso:country":"BD",
    "wof:name":"Baluchar Kashinathpur",
    "wof:placetype":"locality"
},
  "geometry": {"coordinates":[89.24975999999999,25.57416],"type":"Point"}
}