{
  "type": "Feature",
  "properties": {
    "gn:admin1_code":"84",
    "gn:admin2_code":"2015.0",
    "gn:admin3_code":"201561.0",
    "gn:admin4_code":"20156173.0",
    "gn:asciiname":"Chapra",
    "gn:country_code":"BD",
    "gn:dem":9,
    "gn:feature_class":"P",
    "gn:feature_code":"PPL",
    "gn:name":"Ch\u0101pra",
    "gn:population":0,
    "gn:timezone":"Asia/Dhaka",
    "iso:country":"BD",
    "name:ben_x_preferred":[
        "Ch\u0101pra"
    ],
    "name:ceb_x_preferred":[
        "Chapra"
    ],
    "name:fra_x_preferred":[
        "Chapra"
    ],
    "name:swe_x_preferred":[
        "Chapra"
    ],
    "wof:name":"Chapra",
    "wof:placetype":"locality"
},
  "geometry": {"coordinates":[91.88527000000001,22.31745],"type":"Point"}
}