{
  "type": "Feature",
  "properties": {
    "gn:admin1_code":"H",
    "gn:admin2_code":"3061",
    "gn:admin3_code":"306113.0",
    "gn:admin4_code":"30611351.0",
    "gn:asciiname":"Jamirdia",
    "gn:country_code":"BD",
    "gn:dem":24,
    "gn:feature_class":"P",
    "gn:feature_code":"PPL",
    "gn:name":"J\u0101mirdia",
    "gn:population":0,
    "gn:timezone":"Asia/Dhaka",
    "iso:country":"BD",
    "wof:name":"Jamirdia",
    "wof:placetype":"locality"
},
  "geometry": {"coordinates":[90.39534999999999,24.29429],"type":"Point"}
}