{
  "type": "Feature",
  "properties": {
    "gn:admin1_code":"87",
    "gn:admin2_code":"5552",
    "gn:admin3_code":"555233.0",
    "gn:admin4_code":"55523395.0",
    "gn:asciiname":"Baroipara",
    "gn:country_code":"BD",
    "gn:dem":50,
    "gn:feature_class":"P",
    "gn:feature_code":"PPL",
    "gn:name":"Baroipara",
    "gn:population":0,
    "gn:timezone":"Asia/Dhaka",
    "iso:country":"BD",
    "name:ben_x_preferred":[
        "Baroipara"
    ],
    "wof:name":"Baroipara",
    "wof:placetype":"locality"
},
  "geometry": {"coordinates":[89.17694,26.1178],"type":"Point"}
}