{
  "type": "Feature",
  "properties": {
    "gn:admin1_code":"81",
    "gn:admin2_code":"3068.0",
    "gn:admin3_code":"306852.0",
    "gn:admin4_code":"30685254.0",
    "gn:asciiname":"Dhulandi",
    "gn:country_code":"BD",
    "gn:dem":12,
    "gn:feature_class":"P",
    "gn:feature_code":"PPL",
    "gn:name":"Dhulandi",
    "gn:population":0,
    "gn:timezone":"Asia/Dhaka",
    "iso:country":"BD",
    "wof:name":"Dhulandi",
    "wof:placetype":"locality"
},
  "geometry": {"coordinates":[90.73456,24.11915],"type":"Point"}
}