{
  "type": "Feature",
  "properties": {
    "gn:admin1_code":"86",
    "gn:admin2_code":"6091",
    "gn:admin3_code":"609108.0",
    "gn:admin4_code":"60910888.0",
    "gn:asciiname":"Rangia",
    "gn:country_code":"BD",
    "gn:dem":23,
    "gn:feature_class":"P",
    "gn:feature_code":"PPL",
    "gn:name":"Rangia",
    "gn:population":0,
    "gn:timezone":"Asia/Dhaka",
    "iso:country":"BD",
    "wof:name":"Rangia",
    "wof:placetype":"locality"
},
  "geometry": {"coordinates":[91.76217,24.744],"type":"Point"}
}