{
  "type": "Feature",
  "properties": {
    "gn:admin1_code":"81",
    "gn:admin2_code":"3056.0",
    "gn:admin3_code":"305610.0",
    "gn:admin4_code":"30561009.0",
    "gn:asciiname":"Bachamara",
    "gn:country_code":"BD",
    "gn:dem":13,
    "gn:feature_class":"P",
    "gn:feature_code":"PPL",
    "gn:name":"B\u0101ch\u0101m\u0101ra",
    "gn:population":0,
    "gn:timezone":"Asia/Dhaka",
    "iso:country":"BD",
    "wof:name":"Bachamara",
    "wof:placetype":"locality"
},
  "geometry": {"coordinates":[89.75350999999998,23.97462],"type":"Point"}
}