{
  "type": "Feature",
  "properties": {
    "gn:admin1_code":"85",
    "gn:admin2_code":"1004.0",
    "gn:admin3_code":"100409.0",
    "gn:admin4_code":"10040979.0",
    "gn:asciiname":"Behala",
    "gn:country_code":"BD",
    "gn:dem":7,
    "gn:feature_class":"P",
    "gn:feature_code":"PPL",
    "gn:name":"Behala",
    "gn:population":0,
    "gn:timezone":"Asia/Dhaka",
    "iso:country":"BD",
    "name:ben_x_preferred":[
        "Behala"
    ],
    "name:ben_x_variant":[
        "\u09ac\u09c7\u09b9\u09be\u09b2\u09be"
    ],
    "wof:name":"Behala",
    "wof:placetype":"locality"
},
  "geometry": {"coordinates":[90.12505,22.01604],"type":"Point"}
}