{
  "type": "Feature",
  "properties": {
    "gn:admin1_code":"83",
    "gn:admin2_code":"5070.0",
    "gn:admin3_code":"507037.0",
    "gn:admin4_code":"50703752.0",
    "gn:asciiname":"Rajarampur",
    "gn:country_code":"BD",
    "gn:dem":27,
    "gn:feature_class":"P",
    "gn:feature_code":"PPL",
    "gn:name":"Rajarampur",
    "gn:population":0,
    "gn:timezone":"Asia/Dhaka",
    "iso:country":"BD",
    "name:ben_x_preferred":[
        "Rajarampur"
    ],
    "wof:name":"Rajarampur",
    "wof:placetype":"locality"
},
  "geometry": {"coordinates":[88.27334999999999,24.76435],"type":"Point"}
}