{
  "type": "Feature",
  "properties": {
    "gn:admin1_code":"H",
    "gn:admin2_code":"3089",
    "gn:admin3_code":"308990.0",
    "gn:admin4_code":"30899039.0",
    "gn:asciiname":"Akbarkhila",
    "gn:country_code":"BD",
    "gn:dem":22,
    "gn:feature_class":"P",
    "gn:feature_code":"PPL",
    "gn:name":"Akbarkhila",
    "gn:population":0,
    "gn:timezone":"Asia/Dhaka",
    "iso:country":"BD",
    "name:ben_x_preferred":[
        "Akbarkhila"
    ],
    "wof:name":"Akbarkhila",
    "wof:placetype":"locality"
},
  "geometry": {"coordinates":[89.97091999999998,25.14905],"type":"Point"}
}