{
  "type": "Feature",
  "properties": {
    "gn:admin1_code":"83",
    "gn:admin2_code":"5070.0",
    "gn:admin3_code":"507066.0",
    "gn:admin4_code":"50706600.0",
    "gn:asciiname":"Alinagar",
    "gn:country_code":"BD",
    "gn:dem":28,
    "gn:feature_class":"P",
    "gn:feature_code":"PPL",
    "gn:name":"Alinagar",
    "gn:population":0,
    "gn:timezone":"Asia/Dhaka",
    "iso:country":"BD",
    "name:ben_x_preferred":[
        "Alinagar"
    ],
    "wof:name":"Alinagar",
    "wof:placetype":"locality"
},
  "geometry": {"coordinates":[88.29255999999999,24.59222],"type":"Point"}
}