{
  "type": "Feature",
  "properties": {
    "gn:admin1_code":"83",
    "gn:admin2_code":"5070.0",
    "gn:admin3_code":"507088.0",
    "gn:admin4_code":"50708847.0",
    "gn:asciiname":"Kantinagar",
    "gn:country_code":"BD",
    "gn:dem":22,
    "gn:feature_class":"P",
    "gn:feature_code":"PPL",
    "gn:name":"K\u0101ntinagar",
    "gn:population":0,
    "gn:timezone":"Asia/Dhaka",
    "iso:country":"BD",
    "name:ben_x_preferred":[
        "K\u0101ntinagar"
    ],
    "wof:name":"Kantinagar",
    "wof:placetype":"locality"
},
  "geometry": {"coordinates":[88.20059999999999,24.7604],"type":"Point"}
}