{
  "type": "Feature",
  "properties": {
    "gn:admin1_code":"82",
    "gn:admin2_code":"4050",
    "gn:admin3_code":"405071.0",
    "gn:admin4_code":"40507151.0",
    "gn:asciiname":"Radhagram",
    "gn:country_code":"BD",
    "gn:dem":18,
    "gn:feature_class":"P",
    "gn:feature_code":"PPL",
    "gn:name":"Radhagram",
    "gn:population":0,
    "gn:timezone":"Asia/Dhaka",
    "iso:country":"BD",
    "name:ben_x_preferred":[
        "Radhagram"
    ],
    "wof:name":"Radhagram",
    "wof:placetype":"locality"
},
  "geometry": {"coordinates":[89.1883,23.9134],"type":"Point"}
}