{
  "type": "Feature",
  "properties": {
    "gn:admin1_code":"82",
    "gn:admin2_code":"4065.0",
    "gn:admin3_code":"406552.0",
    "gn:admin4_code":"40655231.0",
    "gn:asciiname":"Ishangati",
    "gn:country_code":"BD",
    "gn:dem":6,
    "gn:feature_class":"P",
    "gn:feature_code":"PPL",
    "gn:name":"Ish\u0101ng\u0101ti",
    "gn:population":0,
    "gn:timezone":"Asia/Dhaka",
    "iso:country":"BD",
    "name:ben_x_preferred":[
        "Ish\u0101ng\u0101ti"
    ],
    "wof:name":"Ishangati",
    "wof:placetype":"locality"
},
  "geometry": {"coordinates":[89.60420000000001,23.17684],"type":"Point"}
}