{
  "type": "Feature",
  "properties": {
    "gn:admin1_code":"84",
    "gn:admin2_code":"2051.0",
    "gn:admin3_code":"205143.0",
    "gn:admin4_code":"20514310.0",
    "gn:asciiname":"Fateh Dharmmapur",
    "gn:country_code":"BD",
    "gn:dem":13,
    "gn:feature_class":"P",
    "gn:feature_code":"PPL",
    "gn:name":"Fateh Dharmmapur",
    "gn:population":0,
    "gn:timezone":"Asia/Dhaka",
    "iso:country":"BD",
    "name:und_x_variant":[
        "Fatehdharmapur",
        "Fateh Dharmmapur"
    ],
    "wof:name":"Fateh Dharmmapur",
    "wof:placetype":"locality"
},
  "geometry": {"coordinates":[90.88394,22.99484],"type":"Point"}
}