{
  "type": "Feature",
  "properties": {
    "gn:admin1_code":"81",
    "gn:admin2_code":"3093",
    "gn:admin3_code":"309357.0",
    "gn:admin4_code":"30935709.0",
    "gn:asciiname":"Pandura",
    "gn:country_code":"BD",
    "gn:dem":22,
    "gn:feature_class":"P",
    "gn:feature_code":"PPL",
    "gn:name":"Pandura",
    "gn:population":0,
    "gn:timezone":"Asia/Dhaka",
    "iso:country":"BD",
    "name:als_x_preferred":[
        "Pandura"
    ],
    "name:ell_x_preferred":[
        "\u03a0\u03b1\u03bd\u03b4\u03bf\u03cd\u03c1\u03b1"
    ],
    "name:hun_x_preferred":[
        "Pandura"
    ],
    "name:lat_x_preferred":[
        "Pandura"
    ],
    "name:por_x_preferred":[
        "Pandura"
    ],
    "name:spa_x_preferred":[
        "Pandura"
    ],
    "wof:name":"Pandura",
    "wof:placetype":"locality"
},
  "geometry": {"coordinates":[90.03825000000001,24.60252],"type":"Point"}
}