{
  "type": "Feature",
  "properties": {
    "gn:admin1_code":"83",
    "gn:admin2_code":"5070.0",
    "gn:admin3_code":"507088.0",
    "gn:admin4_code":"50708895.0",
    "gn:asciiname":"Chhoto Lampat",
    "gn:country_code":"BD",
    "gn:dem":18,
    "gn:feature_class":"P",
    "gn:feature_code":"PPL",
    "gn:name":"Chhoto Lampat",
    "gn:population":0,
    "gn:timezone":"Asia/Dhaka",
    "iso:country":"BD",
    "name:ben_x_preferred":[
        "Chhoto Lampat"
    ],
    "wof:name":"Chhoto Lampat",
    "wof:placetype":"locality"
},
  "geometry": {"coordinates":[88.14969000000001,24.60718],"type":"Point"}
}