{
  "type": "Feature",
  "properties": {
    "gn:admin1_code":"83",
    "gn:admin2_code":"5070.0",
    "gn:admin3_code":"507056.0",
    "gn:admin4_code":"50705657.0",
    "gn:asciiname":"Bhojail",
    "gn:country_code":"BD",
    "gn:dem":34,
    "gn:feature_class":"P",
    "gn:feature_code":"PPL",
    "gn:name":"Bhoj\u0101il",
    "gn:population":0,
    "gn:timezone":"Asia/Dhaka",
    "iso:country":"BD",
    "name:ben_x_preferred":[
        "Bhoj\u0101il"
    ],
    "name:ben_x_variant":[
        "Bhujail"
    ],
    "wof:name":"Bhojail",
    "wof:placetype":"locality"
},
  "geometry": {"coordinates":[88.47419000000002,24.73231],"type":"Point"}
}