{
  "type": "Feature",
  "properties": {
    "gn:admin1_code":"83",
    "gn:admin2_code":"5064",
    "gn:admin3_code":"506460.0",
    "gn:admin4_code":"50646094.0",
    "gn:asciiname":"Tepagari",
    "gn:country_code":"BD",
    "gn:dem":21,
    "gn:feature_class":"P",
    "gn:feature_code":"PPL",
    "gn:name":"Tep\u0101g\u0101ri",
    "gn:population":0,
    "gn:timezone":"Asia/Dhaka",
    "iso:country":"BD",
    "name:ben_x_preferred":[
        "Tep\u0101g\u0101ri"
    ],
    "name:und_x_variant":[
        "Tehgari"
    ],
    "wof:name":"Tepagari",
    "wof:placetype":"locality"
},
  "geometry": {"coordinates":[88.93779000000001,24.84651],"type":"Point"}
}