{
  "type": "Feature",
  "properties": {
    "gn:admin1_code":"82",
    "gn:admin2_code":"4087.0",
    "gn:admin3_code":"408704.0",
    "gn:admin4_code":"40870443.0",
    "gn:asciiname":"Bairampur",
    "gn:country_code":"BD",
    "gn:dem":4,
    "gn:feature_class":"P",
    "gn:feature_code":"PPL",
    "gn:name":"Bair\u0101mpur",
    "gn:population":0,
    "gn:timezone":"Asia/Dhaka",
    "iso:country":"BD",
    "wof:name":"Bairampur",
    "wof:placetype":"locality"
},
  "geometry": {"coordinates":[89.19296999999997,22.56955],"type":"Point"}
}