{
  "type": "Feature",
  "properties": {
    "gn:admin1_code":"82",
    "gn:admin2_code":"4018.0",
    "gn:admin3_code":"401807.0",
    "gn:admin4_code":"40180747.0",
    "gn:asciiname":"Matpara",
    "gn:country_code":"BD",
    "gn:dem":18,
    "gn:feature_class":"P",
    "gn:feature_code":"PPL",
    "gn:name":"Matp\u0101ra",
    "gn:population":0,
    "gn:timezone":"Asia/Dhaka",
    "iso:country":"BD",
    "name:ben_x_preferred":[
        "Matp\u0101ra"
    ],
    "wof:name":"Matpara",
    "wof:placetype":"locality"
},
  "geometry": {"coordinates":[88.90193000000002,23.81753],"type":"Point"}
}