{
  "type": "Feature",
  "properties": {
    "gn:admin1_code":"83",
    "gn:admin2_code":"5064.0",
    "gn:admin3_code":"506479.0",
    "gn:admin4_code":"50647923.0",
    "gn:asciiname":"Suranda",
    "gn:country_code":"BD",
    "gn:dem":34,
    "gn:feature_class":"P",
    "gn:feature_code":"PPL",
    "gn:name":"Sur\u0101nda",
    "gn:population":0,
    "gn:timezone":"Asia/Dhaka",
    "iso:country":"BD",
    "name:ben_x_preferred":[
        "Sur\u0101nda"
    ],
    "wof:name":"Suranda",
    "wof:placetype":"locality"
},
  "geometry": {"coordinates":[88.50805,25.0588],"type":"Point"}
}