{
  "type": "Feature",
  "properties": {
    "gn:admin1_code":"83",
    "gn:admin2_code":"5010",
    "gn:admin3_code":"501020.0",
    "gn:admin4_code":"50102077.0",
    "gn:asciiname":"Natai",
    "gn:country_code":"BD",
    "gn:dem":22,
    "gn:feature_class":"P",
    "gn:feature_code":"PPL",
    "gn:name":"N\u0101t\u0101i",
    "gn:population":0,
    "gn:timezone":"Asia/Dhaka",
    "iso:country":"BD",
    "wof:name":"Natai",
    "wof:placetype":"locality"
},
  "geometry": {"coordinates":[89.38616,24.84885],"type":"Point"}
}