{
  "type": "Feature",
  "properties": {
    "gn:admin1_code":"84",
    "gn:admin2_code":"2003.0",
    "gn:admin3_code":"200395.0",
    "gn:admin4_code":"20039538.0",
    "gn:asciiname":"Ramkari",
    "gn:country_code":"BD",
    "gn:dem":217,
    "gn:feature_class":"P",
    "gn:feature_code":"PPL",
    "gn:name":"R\u0101mkari",
    "gn:population":0,
    "gn:timezone":"Asia/Dhaka",
    "iso:country":"BD",
    "name:ben_x_preferred":[
        "R\u0101mkari"
    ],
    "wof:name":"Ramkari",
    "wof:placetype":"locality"
},
  "geometry": {"coordinates":[92.54736,21.63861],"type":"Point"}
}