{
  "type": "Feature",
  "properties": {
    "gn:admin1_code":"81",
    "gn:admin2_code":"3054.0",
    "gn:admin3_code":"305454.0",
    "gn:admin4_code":"30545435.0",
    "gn:asciiname":"Guharpara",
    "gn:country_code":"BD",
    "gn:dem":7,
    "gn:feature_class":"P",
    "gn:feature_code":"PPL",
    "gn:name":"Guharp\u0101ra",
    "gn:population":0,
    "gn:timezone":"Asia/Dhaka",
    "iso:country":"BD",
    "name:und_x_variant":[
        "Guharparo",
        "Guharp\u0101ra"
    ],
    "wof:name":"Guharpara",
    "wof:placetype":"locality"
},
  "geometry": {"coordinates":[90.21393,23.14677],"type":"Point"}
}