{
  "type": "Feature",
  "properties": {
    "gn:admin1_code":"82",
    "gn:admin2_code":"4047.0",
    "gn:admin3_code":"404764.0",
    "gn:admin4_code":"40476439.0",
    "gn:asciiname":"Uttar Kumkhali",
    "gn:country_code":"BD",
    "gn:dem":5,
    "gn:feature_class":"P",
    "gn:feature_code":"PPL",
    "gn:name":"Uttar Kumkh\u0101li",
    "gn:population":0,
    "gn:timezone":"Asia/Dhaka",
    "iso:country":"BD",
    "name:ben_x_preferred":[
        "Uttar Kumkh\u0101li"
    ],
    "wof:name":"Uttar Kumkhali",
    "wof:placetype":"locality"
},
  "geometry": {"coordinates":[89.40451,22.49984],"type":"Point"}
}