{
  "type": "Feature",
  "properties": {
    "gn:admin1_code":"83",
    "gn:admin2_code":"5038.0",
    "gn:admin3_code":"503847.0",
    "gn:admin4_code":"50384738.0",
    "gn:asciiname":"Chak Pahunanda",
    "gn:country_code":"BD",
    "gn:dem":24,
    "gn:feature_class":"P",
    "gn:feature_code":"PPL",
    "gn:name":"Chak P\u0101hunanda",
    "gn:population":0,
    "gn:timezone":"Asia/Dhaka",
    "iso:country":"BD",
    "name:ben_x_preferred":[
        "Chak P\u0101hunanda"
    ],
    "wof:name":"Chak Pahunanda",
    "wof:placetype":"locality"
},
  "geometry": {"coordinates":[88.9337,25.14537],"type":"Point"}
}