{
  "type": "Feature",
  "properties": {
    "gn:admin1_code":"87",
    "gn:admin2_code":"5532",
    "gn:admin3_code":"553230.0",
    "gn:admin4_code":"55323078.0",
    "gn:asciiname":"Madarpur",
    "gn:country_code":"BD",
    "gn:dem":28,
    "gn:feature_class":"P",
    "gn:feature_code":"PPL",
    "gn:name":"M\u0101d\u0101rpur",
    "gn:population":0,
    "gn:timezone":"Asia/Dhaka",
    "iso:country":"BD",
    "name:fra_x_preferred":[
        "Madarpur"
    ],
    "name:hif_x_preferred":[
        "Madarpur"
    ],
    "wof:name":"Madarpur",
    "wof:placetype":"locality"
},
  "geometry": {"coordinates":[89.31848000000002,25.16248],"type":"Point"}
}