{
  "type": "Feature",
  "properties": {
    "gn:admin1_code":"85",
    "gn:admin2_code":"1042",
    "gn:admin3_code":"104240.0",
    "gn:admin4_code":"10424019.0",
    "gn:asciiname":"Dakshin Kalyankati",
    "gn:country_code":"BD",
    "gn:dem":8,
    "gn:feature_class":"P",
    "gn:feature_code":"PPL",
    "gn:name":"Dakshin Kaly\u0101nk\u0101ti",
    "gn:population":0,
    "gn:timezone":"Asia/Dhaka",
    "iso:country":"BD",
    "name:und_x_variant":[
        "Dakshin Kaly\u0101nk\u0101ti",
        "South Kaly\u0101nk\u0101ti"
    ],
    "wof:name":"Dakshin Kalyankati",
    "wof:placetype":"locality"
},
  "geometry": {"coordinates":[90.26733,22.71535],"type":"Point"}
}