{
  "type": "Feature",
  "properties": {
    "gn:admin1_code":"82",
    "gn:admin2_code":"4050.0",
    "gn:admin3_code":"405039.0",
    "gn:admin4_code":"40503981.0",
    "gn:asciiname":"Madapur",
    "gn:country_code":"BD",
    "gn:dem":22,
    "gn:feature_class":"P",
    "gn:feature_code":"PPL",
    "gn:name":"Madapur",
    "gn:population":0,
    "gn:timezone":"Asia/Dhaka",
    "iso:country":"BD",
    "name:ben_x_preferred":[
        "Madapur"
    ],
    "wof:name":"Madapur",
    "wof:placetype":"locality"
},
  "geometry": {"coordinates":[88.78763000000002,24.03935],"type":"Point"}
}