{
  "type": "Feature",
  "properties": {
    "gn:admin1_code":"81",
    "gn:admin2_code":"3082.0",
    "gn:admin3_code":"308273.0",
    "gn:admin4_code":"30827385.0",
    "gn:asciiname":"Arpari",
    "gn:country_code":"BD",
    "gn:dem":16,
    "gn:feature_class":"P",
    "gn:feature_code":"PPL",
    "gn:name":"Arp\u0101ri",
    "gn:population":0,
    "gn:timezone":"Asia/Dhaka",
    "iso:country":"BD",
    "name:ben_x_preferred":[
        "Arp\u0101ri"
    ],
    "wof:name":"Arpari",
    "wof:placetype":"locality"
},
  "geometry": {"coordinates":[89.51921999999998,23.77584],"type":"Point"}
}