{
  "type": "Feature",
  "properties": {
    "gn:admin1_code":"84",
    "gn:admin2_code":"2019",
    "gn:admin3_code":"201981.0",
    "gn:admin4_code":"20198158.0",
    "gn:asciiname":"Nagarpar",
    "gn:country_code":"BD",
    "gn:dem":10,
    "gn:feature_class":"P",
    "gn:feature_code":"PPL",
    "gn:name":"Nagarp\u0101r",
    "gn:population":0,
    "gn:timezone":"Asia/Dhaka",
    "iso:country":"BD",
    "wof:name":"Nagarpar",
    "wof:placetype":"locality"
},
  "geometry": {"coordinates":[90.967,23.64512],"type":"Point"}
}