{
  "type": "Feature",
  "properties": {
    "gn:admin1_code":"81",
    "gn:admin2_code":"3068.0",
    "gn:admin3_code":"306863.0",
    "gn:admin4_code":"30686379.0",
    "gn:asciiname":"Chhota Lakshmipur",
    "gn:country_code":"BD",
    "gn:dem":14,
    "gn:feature_class":"P",
    "gn:feature_code":"PPL",
    "gn:name":"Chhota Lakshmipur",
    "gn:population":0,
    "gn:timezone":"Asia/Dhaka",
    "iso:country":"BD",
    "wof:name":"Chhota Lakshmipur",
    "wof:placetype":"locality"
},
  "geometry": {"coordinates":[90.6814,23.93564],"type":"Point"}
}