{
  "type": "Feature",
  "properties": {
    "gn:admin1_code":"87",
    "gn:admin2_code":"5577.0",
    "gn:admin3_code":"557734.0",
    "gn:admin4_code":"55773428.0",
    "gn:asciiname":"Muslim Paikan",
    "gn:country_code":"BD",
    "gn:dem":60,
    "gn:feature_class":"P",
    "gn:feature_code":"PPL",
    "gn:name":"Muslim Paikan",
    "gn:population":0,
    "gn:timezone":"Asia/Dhaka",
    "iso:country":"BD",
    "name:ben_x_preferred":[
        "Muslim Paikan"
    ],
    "wof:name":"Muslim Paikan",
    "wof:placetype":"locality"
},
  "geometry": {"coordinates":[88.66953000000002,26.09341],"type":"Point"}
}