{
  "type": "Feature",
  "properties": {
    "gn:admin1_code":"83",
    "gn:admin2_code":"5064.0",
    "gn:admin3_code":"506475.0",
    "gn:admin4_code":"50647569.0",
    "gn:asciiname":"Kanupara",
    "gn:country_code":"BD",
    "gn:dem":43,
    "gn:feature_class":"P",
    "gn:feature_code":"PPL",
    "gn:name":"K\u0101nup\u0101ra",
    "gn:population":0,
    "gn:timezone":"Asia/Dhaka",
    "iso:country":"BD",
    "name:ben_x_preferred":[
        "K\u0101nup\u0101ra"
    ],
    "wof:name":"Kanupara",
    "wof:placetype":"locality"
},
  "geometry": {"coordinates":[88.59322,25.16416],"type":"Point"}
}