{
  "type": "Feature",
  "properties": {
    "gn:admin1_code":"82",
    "gn:admin2_code":"4041.0",
    "gn:admin3_code":"404147.0",
    "gn:admin4_code":"40414789.0",
    "gn:asciiname":"Maliat",
    "gn:country_code":"BD",
    "gn:dem":11,
    "gn:feature_class":"P",
    "gn:feature_code":"PPL",
    "gn:name":"M\u0101liat",
    "gn:population":0,
    "gn:timezone":"Asia/Dhaka",
    "iso:country":"BD",
    "name:ben_x_preferred":[
        "M\u0101liat"
    ],
    "wof:name":"Maliat",
    "wof:placetype":"locality"
},
  "geometry": {"coordinates":[89.26413000000002,23.20747],"type":"Point"}
}