{
  "type": "Feature",
  "properties": {
    "gn:admin1_code":"81",
    "gn:admin2_code":"3035.0",
    "gn:admin3_code":"303543.0",
    "gn:admin4_code":"30354340.0",
    "gn:asciiname":"Chak Bandadoa",
    "gn:country_code":"BD",
    "gn:dem":8,
    "gn:feature_class":"P",
    "gn:feature_code":"PPL",
    "gn:name":"Chak Bandadoa",
    "gn:population":0,
    "gn:timezone":"Asia/Dhaka",
    "iso:country":"BD",
    "name:und_x_variant":[
        "Chak Bandal",
        "Chakbandola",
        "Chak Bandadoa"
    ],
    "wof:name":"Chak Bandadoa",
    "wof:placetype":"locality"
},
  "geometry": {"coordinates":[89.78534000000001,23.2887],"type":"Point"}
}