{
  "type": "Feature",
  "properties": {
    "gn:admin1_code":"H",
    "gn:admin2_code":"3089",
    "gn:admin3_code":"308988.0",
    "gn:admin4_code":"30898820.0",
    "gn:asciiname":"Pakuria",
    "gn:country_code":"BD",
    "gn:dem":21,
    "gn:feature_class":"P",
    "gn:feature_code":"PPL",
    "gn:name":"P\u0101kuria",
    "gn:population":0,
    "gn:timezone":"Asia/Dhaka",
    "iso:country":"BD",
    "wof:name":"Pakuria",
    "wof:placetype":"locality"
},
  "geometry": {"coordinates":[90.06667,24.98333],"type":"Point"}
}