{
  "type": "Feature",
  "properties": {
    "gn:admin1_code":"87",
    "gn:admin2_code":"5527",
    "gn:admin3_code":"552743.0",
    "gn:admin4_code":"55274357.0",
    "gn:asciiname":"Sonarpara",
    "gn:country_code":"BD",
    "gn:dem":31,
    "gn:feature_class":"P",
    "gn:feature_code":"PPL",
    "gn:name":"Sonarpara",
    "gn:population":0,
    "gn:timezone":"Asia/Dhaka",
    "iso:country":"BD",
    "name:ben_x_preferred":[
        "Sonarpara"
    ],
    "wof:name":"Sonarpara",
    "wof:placetype":"locality"
},
  "geometry": {"coordinates":[89.15938,25.3048],"type":"Point"}
}