{
  "type": "Feature",
  "properties": {
    "gn:admin1_code":"82",
    "gn:admin2_code":"4055.0",
    "gn:admin3_code":"405566.0",
    "gn:admin4_code":"40556631.0",
    "gn:asciiname":"Dakshinpara",
    "gn:country_code":"BD",
    "gn:dem":11,
    "gn:feature_class":"P",
    "gn:feature_code":"PPL",
    "gn:name":"Dakshinp\u0101ra",
    "gn:population":0,
    "gn:timezone":"Asia/Dhaka",
    "iso:country":"BD",
    "wof:name":"Dakshinpara",
    "wof:placetype":"locality"
},
  "geometry": {"coordinates":[89.49993000000001,23.45915],"type":"Point"}
}