{
  "type": "Feature",
  "properties": {
    "gn:admin1_code":"81",
    "gn:admin2_code":"3093",
    "gn:admin3_code":"309328.0",
    "gn:admin4_code":"30932834.0",
    "gn:asciiname":"Safakat",
    "gn:country_code":"BD",
    "gn:dem":18,
    "gn:feature_class":"P",
    "gn:feature_code":"PPL",
    "gn:name":"Safak\u0101t",
    "gn:population":0,
    "gn:timezone":"Asia/Dhaka",
    "iso:country":"BD",
    "name:und_x_variant":[
        "Safak\u0101t",
        "Saf\u0101kot"
    ],
    "wof:name":"Safakat",
    "wof:placetype":"locality"
},
  "geometry": {"coordinates":[90.08431,24.4762],"type":"Point"}
}