{
  "type": "Feature",
  "properties": {
    "gn:admin1_code":"87",
    "gn:admin2_code":"5532",
    "gn:admin3_code":"553267.0",
    "gn:admin4_code":"55326709.0",
    "gn:asciiname":"Cholitadaha",
    "gn:country_code":"BD",
    "gn:dem":27,
    "gn:feature_class":"P",
    "gn:feature_code":"PPL",
    "gn:name":"Cholitadaha",
    "gn:population":0,
    "gn:timezone":"Asia/Dhaka",
    "iso:country":"BD",
    "name:ben_x_preferred":[
        "Cholitadaha"
    ],
    "wof:name":"Cholitadaha",
    "wof:placetype":"locality"
},
  "geometry": {"coordinates":[89.37251999999999,25.25643],"type":"Point"}
}