{
  "type": "Feature",
  "properties": {
    "gn:admin1_code":"84",
    "gn:admin2_code":"2084.0",
    "gn:admin3_code":"208487.0",
    "gn:admin4_code":"20848781.0",
    "gn:asciiname":"Toniapara",
    "gn:country_code":"BD",
    "gn:dem":47,
    "gn:feature_class":"P",
    "gn:feature_code":"PPL",
    "gn:name":"Toni\u0101p\u0101ra",
    "gn:population":0,
    "gn:timezone":"Asia/Dhaka",
    "iso:country":"BD",
    "name:ben_x_preferred":[
        "Toni\u0101p\u0101ra"
    ],
    "wof:name":"Toniapara",
    "wof:placetype":"locality"
},
  "geometry": {"coordinates":[92.08378999999999,22.65967],"type":"Point"}
}