{
  "type": "Feature",
  "properties": {
    "gn:admin1_code":"85",
    "gn:admin2_code":"1042",
    "gn:admin3_code":"104240.0",
    "gn:admin4_code":"10424066.0",
    "gn:asciiname":"Sankardhabal",
    "gn:country_code":"BD",
    "gn:dem":10,
    "gn:feature_class":"P",
    "gn:feature_code":"PPL",
    "gn:name":"Sankardhabal",
    "gn:population":0,
    "gn:timezone":"Asia/Dhaka",
    "iso:country":"BD",
    "wof:name":"Sankardhabal",
    "wof:placetype":"locality"
},
  "geometry": {"coordinates":[90.14547,22.67923],"type":"Point"}
}