{
  "type": "Feature",
  "properties": {
    "gn:admin1_code":"H",
    "gn:admin2_code":"3061.0",
    "gn:admin3_code":"306120.0",
    "gn:admin4_code":"30612047.0",
    "gn:asciiname":"Chouduar",
    "gn:country_code":"BD",
    "gn:dem":19,
    "gn:feature_class":"P",
    "gn:feature_code":"PPL",
    "gn:name":"Choudu\u0101r",
    "gn:population":0,
    "gn:timezone":"Asia/Dhaka",
    "iso:country":"BD",
    "name:und_x_variant":[
        "Chowduar",
        "Choudu\u0101r"
    ],
    "wof:name":"Chouduar",
    "wof:placetype":"locality"
},
  "geometry": {"coordinates":[90.29367000000001,24.61498],"type":"Point"}
}