{
  "type": "Feature",
  "properties": {
    "gn:admin1_code":"81",
    "gn:admin2_code":"3067",
    "gn:admin3_code":"306758.0",
    "gn:admin4_code":"30675845.0",
    "gn:asciiname":"Jalkundi",
    "gn:country_code":"BD",
    "gn:dem":9,
    "gn:feature_class":"P",
    "gn:feature_code":"PPL",
    "gn:name":"J\u0101lkundi",
    "gn:population":0,
    "gn:timezone":"Asia/Dhaka",
    "iso:country":"BD",
    "wof:name":"Jalkundi",
    "wof:placetype":"locality"
},
  "geometry": {"coordinates":[90.49471,23.66473],"type":"Point"}
}