{
  "type": "Feature",
  "properties": {
    "gn:admin1_code":"87",
    "gn:admin2_code":"5577",
    "gn:admin3_code":"557704.0",
    "gn:admin4_code":"55770481.0",
    "gn:asciiname":"Taria",
    "gn:country_code":"BD",
    "gn:dem":71,
    "gn:feature_class":"P",
    "gn:feature_code":"PPL",
    "gn:name":"Taria",
    "gn:population":0,
    "gn:timezone":"Asia/Dhaka",
    "iso:country":"BD",
    "name:ben_x_preferred":[
        "Taria Bhaw\u0101ni"
    ],
    "name:ben_x_variant":[
        "Taria"
    ],
    "wof:name":"Taria",
    "wof:placetype":"locality"
},
  "geometry": {"coordinates":[88.38800999999999,26.24879],"type":"Point"}
}