{
  "type": "Feature",
  "properties": {
    "gn:admin1_code":"83",
    "gn:admin2_code":"5010",
    "gn:admin3_code":"501095.0",
    "gn:admin4_code":"50109510.0",
    "gn:asciiname":"Gandai",
    "gn:country_code":"BD",
    "gn:dem":22,
    "gn:feature_class":"P",
    "gn:feature_code":"PPL",
    "gn:name":"Gandai",
    "gn:population":0,
    "gn:timezone":"Asia/Dhaka",
    "iso:country":"BD",
    "name:ben_x_preferred":[
        "Gandai"
    ],
    "wof:name":"Gandai",
    "wof:placetype":"locality"
},
  "geometry": {"coordinates":[89.46653000000001,25.00756],"type":"Point"}
}