{
  "type": "Feature",
  "properties": {
    "gn:admin1_code":"83",
    "gn:admin2_code":"5010",
    "gn:admin3_code":"501095.0",
    "gn:admin4_code":"50109510.0",
    "gn:asciiname":"Gandai",
    "gn:country_code":"BD",
    "gn:dem":22,
    "gn:feature_class":"P",
    "gn:feature_code":"PPL",
    "gn:name":"Gandai",
    "gn:population":0,
    "gn:timezone":"Asia/Dhaka",
    "iso:country":"BD",
    "name:ben_x_preferred":[
        "Gandai"
    ],
    "name:ben_x_variant":[
        "\u0997\u09be\u09a8\u09a6\u09be\u0987"
    ],
    "name:bpy_x_preferred":[
        "\u0997\u09be\u09a8\u09a6\u09be\u0987"
    ],
    "name:cat_x_preferred":[
        "Gandai"
    ],
    "name:ceb_x_preferred":[
        "Gandai"
    ],
    "name:ita_x_preferred":[
        "Gandai"
    ],
    "name:msa_x_preferred":[
        "Gandai"
    ],
    "name:new_x_preferred":[
        "\u0917\u0902\u0926\u0948"
    ],
    "name:nld_x_preferred":[
        "Gandai"
    ],
    "name:por_x_preferred":[
        "Gandai"
    ],
    "name:spa_x_preferred":[
        "Gandai"
    ],
    "name:swe_x_preferred":[
        "Gandai"
    ],
    "name:tgl_x_preferred":[
        "Gandai"
    ],
    "name:urd_x_preferred":[
        "\u06af\u0646\u0688\u0626\u06cc"
    ],
    "name:vie_x_preferred":[
        "Gandai"
    ],
    "name:zho_x_preferred":[
        "\u52a0\u6069\u4ee3"
    ],
    "wof:name":"Gandai",
    "wof:placetype":"locality"
},
  "geometry": {"coordinates":[89.46653000000001,25.00756],"type":"Point"}
}