{
  "type": "Feature",
  "properties": {
    "gn:admin1_code":"87",
    "gn:admin2_code":"5594",
    "gn:admin3_code":"559494.0",
    "gn:admin4_code":"55949417.0",
    "gn:asciiname":"Saidpur",
    "gn:country_code":"BD",
    "gn:dem":50,
    "gn:feature_class":"P",
    "gn:feature_code":"PPL",
    "gn:name":"Saidpur",
    "gn:population":0,
    "gn:timezone":"Asia/Dhaka",
    "iso:country":"BD",
    "name:ben_x_preferred":[
        "Saidpur"
    ],
    "name:ben_x_variant":[
        "\u09b8\u09c8\u09af\u09bc\u09a6\u09aa\u09c1\u09b0"
    ],
    "name:bpy_x_preferred":[
        "\u09b8\u09be\u09af\u09bc\u09bf\u09a6\u09aa\u09c1\u09b0"
    ],
    "name:ceb_x_preferred":[
        "Saidpur"
    ],
    "name:ita_x_preferred":[
        "Saidpur"
    ],
    "name:pol_x_preferred":[
        "Saidpur"
    ],
    "name:sun_x_preferred":[
        "Saidpur"
    ],
    "name:swe_x_preferred":[
        "Saidpur"
    ],
    "wof:name":"Saidpur",
    "wof:placetype":"locality"
},
  "geometry": {"coordinates":[88.45384,25.91328],"type":"Point"}
}