{
  "type": "Feature",
  "properties": {
    "gn:admin1_code":"81",
    "gn:admin2_code":"3056",
    "gn:admin3_code":"305670.0",
    "gn:admin4_code":"30567028.0",
    "gn:asciiname":"Makorkol",
    "gn:country_code":"BD",
    "gn:dem":14,
    "gn:feature_class":"P",
    "gn:feature_code":"PPL",
    "gn:name":"M\u0101korkol",
    "gn:population":0,
    "gn:timezone":"Asia/Dhaka",
    "iso:country":"BD",
    "name:und_x_variant":[
        "M\u0101korkol",
        "M\u0101karkol"
    ],
    "wof:name":"Makorkol",
    "wof:placetype":"locality"
},
  "geometry": {"coordinates":[89.92183,23.98706],"type":"Point"}
}