{
  "type": "Feature",
  "properties": {
    "gn:admin1_code":"82",
    "gn:admin2_code":"4001.0",
    "gn:admin3_code":"400177.0",
    "gn:admin4_code":"40017738.0",
    "gn:asciiname":"Moreabad",
    "gn:country_code":"BD",
    "gn:dem":12,
    "gn:feature_class":"P",
    "gn:feature_code":"PPL",
    "gn:name":"Moreabad",
    "gn:population":0,
    "gn:timezone":"Asia/Dhaka",
    "iso:country":"BD",
    "name:ben_x_preferred":[
        "Moreabad"
    ],
    "wof:name":"Moreabad",
    "wof:placetype":"locality"
},
  "geometry": {"coordinates":[89.87515,22.35968],"type":"Point"}
}