{
  "type": "Feature",
  "properties": {
    "gn:admin1_code":"81",
    "gn:admin2_code":"3068.0",
    "gn:admin3_code":"306864.0",
    "gn:admin4_code":"30686457.0",
    "gn:asciiname":"Chhota Lakshmipura",
    "gn:country_code":"BD",
    "gn:dem":14,
    "gn:feature_class":"P",
    "gn:feature_code":"PPL",
    "gn:name":"Chhota Lakshmipura",
    "gn:population":0,
    "gn:timezone":"Asia/Dhaka",
    "iso:country":"BD",
    "wof:name":"Chhota Lakshmipura",
    "wof:placetype":"locality"
},
  "geometry": {"coordinates":[90.93433,24.03818],"type":"Point"}
}