{
  "type": "Feature",
  "properties": {
    "gn:admin1_code":"86",
    "gn:admin2_code":"6058.0",
    "gn:admin3_code":"605874.0",
    "gn:admin4_code":"60587429.0",
    "gn:asciiname":"Barabari",
    "gn:country_code":"BD",
    "gn:dem":14,
    "gn:feature_class":"P",
    "gn:feature_code":"PPL",
    "gn:name":"Barab\u0101ri",
    "gn:population":0,
    "gn:timezone":"Asia/Dhaka",
    "iso:country":"BD",
    "wof:name":"Barabari",
    "wof:placetype":"locality"
},
  "geometry": {"coordinates":[91.79816,24.52668],"type":"Point"}
}