{
  "type": "Feature",
  "properties": {
    "gn:admin1_code":"82",
    "gn:admin2_code":"4057",
    "gn:admin3_code":"405747.0",
    "gn:admin4_code":"40574763.0",
    "gn:asciiname":"Muhammadpur",
    "gn:country_code":"BD",
    "gn:dem":22,
    "gn:feature_class":"P",
    "gn:feature_code":"PPL",
    "gn:name":"Muhammadpur",
    "gn:population":0,
    "gn:timezone":"Asia/Dhaka",
    "iso:country":"BD",
    "name:ben_x_preferred":[
        "Muhammadpur"
    ],
    "name:und_x_variant":[
        "Mamudpur"
    ],
    "wof:name":"Muhammadpur",
    "wof:placetype":"locality"
},
  "geometry": {"coordinates":[88.85019,23.91895],"type":"Point"}
}