{
  "type": "Feature",
  "properties": {
    "gn:admin1_code":"83",
    "gn:admin2_code":"5069",
    "gn:admin3_code":"506963.0",
    "gn:admin4_code":"50696307.0",
    "gn:asciiname":"Tegharia",
    "gn:country_code":"BD",
    "gn:dem":18,
    "gn:feature_class":"P",
    "gn:feature_code":"PPL",
    "gn:name":"Tegharia",
    "gn:population":0,
    "gn:timezone":"Asia/Dhaka",
    "iso:country":"BD",
    "name:ben_x_preferred":[
        "Tegharia"
    ],
    "wof:name":"Tegharia",
    "wof:placetype":"locality"
},
  "geometry": {"coordinates":[88.98725999999998,24.3606],"type":"Point"}
}