{
  "type": "Feature",
  "properties": {
    "gn:admin1_code":"82",
    "gn:admin2_code":"4050",
    "gn:admin3_code":"405079.0",
    "gn:admin4_code":"40507931.0",
    "gn:asciiname":"Maju",
    "gn:country_code":"BD",
    "gn:dem":13,
    "gn:feature_class":"P",
    "gn:feature_code":"PPL",
    "gn:name":"M\u0101ju",
    "gn:population":0,
    "gn:timezone":"Asia/Dhaka",
    "iso:country":"BD",
    "wof:name":"Maju",
    "wof:placetype":"locality"
},
  "geometry": {"coordinates":[89.01666999999998,23.76667],"type":"Point"}
}