{
  "type": "Feature",
  "properties": {
    "gn:admin1_code":"81",
    "gn:admin2_code":"3059.0",
    "gn:admin3_code":"305924.0",
    "gn:admin4_code":"30592463.0",
    "gn:asciiname":"Dhuni Chak",
    "gn:country_code":"BD",
    "gn:dem":4,
    "gn:feature_class":"P",
    "gn:feature_code":"PPL",
    "gn:name":"Dhuni Chak",
    "gn:population":0,
    "gn:timezone":"Asia/Dhaka",
    "iso:country":"BD",
    "wof:name":"Dhuni Chak",
    "wof:placetype":"locality"
},
  "geometry": {"coordinates":[90.56667,23.58333],"type":"Point"}
}