{
  "type": "Feature",
  "properties": {
    "gn:admin1_code":"87",
    "gn:admin2_code":"5527.0",
    "gn:admin3_code":"552764.0",
    "gn:admin4_code":"55276408.0",
    "gn:asciiname":"Kusumbi",
    "gn:country_code":"BD",
    "gn:dem":35,
    "gn:feature_class":"P",
    "gn:feature_code":"PPL",
    "gn:name":"Kusumbi",
    "gn:population":0,
    "gn:timezone":"Asia/Dhaka",
    "iso:country":"BD",
    "name:ben_x_preferred":[
        "Kusumbi"
    ],
    "wof:name":"Kusumbi",
    "wof:placetype":"locality"
},
  "geometry": {"coordinates":[88.63346999999997,25.52279],"type":"Point"}
}