{
  "type": "Feature",
  "properties": {
    "gn:admin1_code":"84",
    "gn:admin2_code":"2015.0",
    "gn:admin3_code":"201582.0",
    "gn:admin4_code":"20158251.0",
    "gn:asciiname":"Boisikil",
    "gn:country_code":"BD",
    "gn:dem":7,
    "gn:feature_class":"P",
    "gn:feature_code":"PPL",
    "gn:name":"Boisikil",
    "gn:population":0,
    "gn:timezone":"Asia/Dhaka",
    "iso:country":"BD",
    "name:ben_x_preferred":[
        "Boisikil"
    ],
    "wof:name":"Boisikil",
    "wof:placetype":"locality"
},
  "geometry": {"coordinates":[92.01286,22.09842],"type":"Point"}
}