{
  "type": "Feature",
  "properties": {
    "gn:admin1_code":"82",
    "gn:admin2_code":"4055.0",
    "gn:admin3_code":"405595.0",
    "gn:admin4_code":"40559542.0",
    "gn:asciiname":"Ghasiara",
    "gn:country_code":"BD",
    "gn:dem":16,
    "gn:feature_class":"P",
    "gn:feature_code":"PPL",
    "gn:name":"Gh\u0101si\u0101ra",
    "gn:population":0,
    "gn:timezone":"Asia/Dhaka",
    "iso:country":"BD",
    "wof:name":"Ghasiara",
    "wof:placetype":"locality"
},
  "geometry": {"coordinates":[89.49741,23.56892],"type":"Point"}
}