{
  "type": "Feature",
  "properties": {
    "gn:admin1_code":"82",
    "gn:admin2_code":"4044",
    "gn:admin3_code":"404480.0",
    "gn:admin4_code":"40448075.0",
    "gn:asciiname":"Maukuri",
    "gn:country_code":"BD",
    "gn:dem":15,
    "gn:feature_class":"P",
    "gn:feature_code":"PPL",
    "gn:name":"Maukuri",
    "gn:population":0,
    "gn:timezone":"Asia/Dhaka",
    "iso:country":"BD",
    "name:und_x_variant":[
        "Moukuri",
        "Maukuri"
    ],
    "wof:name":"Maukuri",
    "wof:placetype":"locality"
},
  "geometry": {"coordinates":[89.23878000000001,23.71918],"type":"Point"}
}