{
  "type": "Feature",
  "properties": {
    "gn:admin1_code":"84",
    "gn:admin2_code":"2084.0",
    "gn:admin3_code":"208436.0",
    "gn:admin4_code":"20843657.0",
    "gn:asciiname":"Headman Para",
    "gn:country_code":"BD",
    "gn:dem":15,
    "gn:feature_class":"P",
    "gn:feature_code":"PPLL",
    "gn:name":"Headman Para",
    "gn:population":0,
    "gn:timezone":"Asia/Dhaka",
    "iso:country":"BD",
    "name:ben_x_preferred":[
        "Headman Para"
    ],
    "wof:name":"Headman Para",
    "wof:placetype":"locality"
},
  "geometry": {"coordinates":[92.17982000000001,22.49336],"type":"Point"}
}