{
  "type": "Feature",
  "properties": {
    "gn:admin1_code":"81",
    "gn:admin2_code":"3048.0",
    "gn:admin3_code":"304845.0",
    "gn:admin4_code":"30484528.0",
    "gn:asciiname":"Charia",
    "gn:country_code":"BD",
    "gn:dem":15,
    "gn:feature_class":"P",
    "gn:feature_code":"PPL",
    "gn:name":"Ch\u0101ria",
    "gn:population":0,
    "gn:timezone":"Asia/Dhaka",
    "iso:country":"BD",
    "name:ell_x_preferred":[
        "\u03a7\u03b1\u03c1\u03b9\u03ac \u0397\u03bb\u03b5\u03af\u03b1\u03c2"
    ],
    "wof:name":"Charia",
    "wof:placetype":"locality"
},
  "geometry": {"coordinates":[90.85477,24.27011],"type":"Point"}
}