{
  "type": "Feature",
  "properties": {
    "gn:admin1_code":"82",
    "gn:admin2_code":"4047",
    "gn:admin3_code":"404753.0",
    "gn:admin4_code":"40475378.0",
    "gn:asciiname":"Modhya Moheswaripur",
    "gn:country_code":"BD",
    "gn:dem":4,
    "gn:feature_class":"P",
    "gn:feature_code":"PPL",
    "gn:name":"Modhya Mohesw\u0101ripur",
    "gn:population":0,
    "gn:timezone":"Asia/Dhaka",
    "iso:country":"BD",
    "name:ben_x_preferred":[
        "Modhya Mohesw\u0101ripur"
    ],
    "name:ben_x_variant":[
        "Maheswaripur"
    ],
    "wof:name":"Modhya Moheswaripur",
    "wof:placetype":"locality"
},
  "geometry": {"coordinates":[89.35963000000002,22.42547],"type":"Point"}
}