{
  "type": "Feature",
  "properties": {
    "gn:admin1_code":"83",
    "gn:admin2_code":"5081",
    "gn:admin3_code":"508131.0",
    "gn:admin4_code":"50813147.0",
    "gn:asciiname":"Kapashmail",
    "gn:country_code":"BD",
    "gn:dem":20,
    "gn:feature_class":"P",
    "gn:feature_code":"PPL",
    "gn:name":"K\u0101p\u0101shm\u0101il",
    "gn:population":0,
    "gn:timezone":"Asia/Dhaka",
    "iso:country":"BD",
    "name:ben_x_preferred":[
        "K\u0101p\u0101shm\u0101il"
    ],
    "name:ben_x_variant":[
        "K\u0101p\u0101sman"
    ],
    "wof:name":"Kapashmail",
    "wof:placetype":"locality"
},
  "geometry": {"coordinates":[88.69919,24.45841],"type":"Point"}
}