{
  "type": "Feature",
  "properties": {
    "gn:admin1_code":"87",
    "gn:admin2_code":"5585",
    "gn:admin3_code":"558558.0",
    "gn:admin4_code":"55855872.0",
    "gn:asciiname":"Chak Gopal",
    "gn:country_code":"BD",
    "gn:dem":32,
    "gn:feature_class":"P",
    "gn:feature_code":"PPL",
    "gn:name":"Chak Gopal",
    "gn:population":0,
    "gn:timezone":"Asia/Dhaka",
    "iso:country":"BD",
    "name:ben_x_preferred":[
        "Chak Gopal"
    ],
    "wof:name":"Chak Gopal",
    "wof:placetype":"locality"
},
  "geometry": {"coordinates":[89.12694,25.45825],"type":"Point"}
}