{
  "type": "Feature",
  "properties": {
    "gn:admin1_code":"82",
    "gn:admin2_code":"4057.0",
    "gn:admin3_code":"405787.0",
    "gn:admin4_code":"40578738.0",
    "gn:asciiname":"Buriponta",
    "gn:country_code":"BD",
    "gn:dem":20,
    "gn:feature_class":"P",
    "gn:feature_code":"PPL",
    "gn:name":"Buriponta",
    "gn:population":0,
    "gn:timezone":"Asia/Dhaka",
    "iso:country":"BD",
    "name:ben_x_preferred":[
        "Buriponta"
    ],
    "wof:name":"Buriponta",
    "wof:placetype":"locality"
},
  "geometry": {"coordinates":[88.58221999999998,23.76535],"type":"Point"}
}