{
  "type": "Feature",
  "properties": {
    "gn:admin1_code":"83",
    "gn:admin2_code":"5069.0",
    "gn:admin3_code":"506944.0",
    "gn:admin4_code":"50694466.0",
    "gn:asciiname":"Badhpara",
    "gn:country_code":"BD",
    "gn:dem":19,
    "gn:feature_class":"P",
    "gn:feature_code":"PPL",
    "gn:name":"B\u0101dhp\u0101ra",
    "gn:population":0,
    "gn:timezone":"Asia/Dhaka",
    "iso:country":"BD",
    "name:ben_x_preferred":[
        "B\u0101dhp\u0101ra"
    ],
    "name:ben_x_variant":[
        "Budhp\u0101ra"
    ],
    "wof:name":"Badhpara",
    "wof:placetype":"locality"
},
  "geometry": {"coordinates":[88.99503,24.18245],"type":"Point"}
}