{
  "type": "Feature",
  "properties": {
    "gn:admin1_code":"85",
    "gn:admin2_code":"1009.0",
    "gn:admin3_code":"100965.0",
    "gn:admin4_code":"10096547.0",
    "gn:asciiname":"Kacharir Dagi",
    "gn:country_code":"BD",
    "gn:dem":5,
    "gn:feature_class":"P",
    "gn:feature_code":"PPL",
    "gn:name":"K\u0101ch\u0101rir D\u0101gi",
    "gn:population":0,
    "gn:timezone":"Asia/Dhaka",
    "iso:country":"BD",
    "name:ben_x_preferred":[
        "K\u0101ch\u0101rir D\u0101gi"
    ],
    "wof:name":"Kacharir Dagi",
    "wof:placetype":"locality"
},
  "geometry": {"coordinates":[90.97234,22.34027],"type":"Point"}
}