{
  "type": "Feature",
  "properties": {
    "gn:admin1_code":"82",
    "gn:admin2_code":"4065.0",
    "gn:admin3_code":"406552.0",
    "gn:admin4_code":"40655223.0",
    "gn:asciiname":"Marichpasa",
    "gn:country_code":"BD",
    "gn:dem":11,
    "gn:feature_class":"P",
    "gn:feature_code":"PPL",
    "gn:name":"Marichp\u0101sa",
    "gn:population":0,
    "gn:timezone":"Asia/Dhaka",
    "iso:country":"BD",
    "name:ben_x_preferred":[
        "Marichp\u0101sa"
    ],
    "wof:name":"Marichpasa",
    "wof:placetype":"locality"
},
  "geometry": {"coordinates":[89.62913,23.22896],"type":"Point"}
}