{
  "type": "Feature",
  "properties": {
    "gn:admin1_code":"83",
    "gn:admin2_code":"5038.0",
    "gn:admin3_code":"503847.0",
    "gn:admin4_code":"50384776.0",
    "gn:asciiname":"Teghar Bisha",
    "gn:country_code":"BD",
    "gn:dem":27,
    "gn:feature_class":"P",
    "gn:feature_code":"PPL",
    "gn:name":"Teghar Bisha",
    "gn:population":0,
    "gn:timezone":"Asia/Dhaka",
    "iso:country":"BD",
    "name:ben_x_preferred":[
        "Teghar Bisha"
    ],
    "wof:name":"Teghar Bisha",
    "wof:placetype":"locality"
},
  "geometry": {"coordinates":[89.02341,25.07924],"type":"Point"}
}