{
  "type": "Feature",
  "properties": {
    "gn:admin1_code":"83",
    "gn:admin2_code":"5070.0",
    "gn:admin3_code":"507088.0",
    "gn:admin4_code":"50708823.0",
    "gn:asciiname":"Raninagar",
    "gn:country_code":"BD",
    "gn:dem":27,
    "gn:feature_class":"P",
    "gn:feature_code":"PPL",
    "gn:name":"R\u0101ninagar",
    "gn:population":0,
    "gn:timezone":"Asia/Dhaka",
    "iso:country":"BD",
    "name:ben_x_preferred":[
        "R\u0101ninagar"
    ],
    "wof:name":"Raninagar",
    "wof:placetype":"locality"
},
  "geometry": {"coordinates":[88.24327,24.69149],"type":"Point"}
}