{
  "type": "Feature",
  "properties": {
    "gn:admin1_code":"87",
    "gn:admin2_code":"5594.0",
    "gn:admin3_code":"559408.0",
    "gn:admin4_code":"55940884.0",
    "gn:asciiname":"Sauia Dogach",
    "gn:country_code":"BD",
    "gn:dem":64,
    "gn:feature_class":"P",
    "gn:feature_code":"PPL",
    "gn:name":"Sauia Dog\u0101ch",
    "gn:population":0,
    "gn:timezone":"Asia/Dhaka",
    "iso:country":"BD",
    "name:ben_x_preferred":[
        "Sauia Dog\u0101ch"
    ],
    "wof:name":"Sauia Dogach",
    "wof:placetype":"locality"
},
  "geometry": {"coordinates":[88.28100999999999,26.16661],"type":"Point"}
}