{
  "type": "Feature",
  "properties": {
    "gn:admin1_code":"83",
    "gn:admin2_code":"5081",
    "gn:admin3_code":"508112.0",
    "gn:admin4_code":"50811263.0",
    "gn:asciiname":"Piruli",
    "gn:country_code":"BD",
    "gn:dem":19,
    "gn:feature_class":"P",
    "gn:feature_code":"PPL",
    "gn:name":"Piruli",
    "gn:population":0,
    "gn:timezone":"Asia/Dhaka",
    "iso:country":"BD",
    "name:ben_x_preferred":[
        "Piruli"
    ],
    "name:ben_x_variant":[
        "Piruli Senp\u0101ra"
    ],
    "wof:name":"Piruli",
    "wof:placetype":"locality"
},
  "geometry": {"coordinates":[88.88625,24.60559],"type":"Point"}
}