{
  "type": "Feature",
  "properties": {
    "gn:admin1_code":"H",
    "gn:admin2_code":"3039",
    "gn:admin3_code":"303907.0",
    "gn:admin4_code":"30390747.0",
    "gn:asciiname":"Satanipara",
    "gn:country_code":"BD",
    "gn:dem":26,
    "gn:feature_class":"P",
    "gn:feature_code":"PPL",
    "gn:name":"Satanipara",
    "gn:population":0,
    "gn:timezone":"Asia/Dhaka",
    "iso:country":"BD",
    "name:ben_x_preferred":[
        "Satanipara"
    ],
    "wof:name":"Satanipara",
    "wof:placetype":"locality"
},
  "geometry": {"coordinates":[89.90092,25.28536],"type":"Point"}
}