{
  "type": "Feature",
  "properties": {
    "gn:admin1_code":"H",
    "gn:admin2_code":"3072",
    "gn:admin3_code":"307263.0",
    "gn:admin4_code":"30726363.0",
    "gn:asciiname":"Niharajaypur",
    "gn:country_code":"BD",
    "gn:dem":14,
    "gn:feature_class":"P",
    "gn:feature_code":"PPL",
    "gn:name":"Nih\u0101r\u0101jaypur",
    "gn:population":0,
    "gn:timezone":"Asia/Dhaka",
    "iso:country":"BD",
    "name:und_x_variant":[
        "Niharagaypur",
        "Nih\u0101r\u0101jaypur"
    ],
    "wof:name":"Niharajaypur",
    "wof:placetype":"locality"
},
  "geometry": {"coordinates":[90.94956000000001,24.78515],"type":"Point"}
}