{
  "type": "Feature",
  "properties": {
    "gn:admin1_code":"H",
    "gn:admin2_code":"3061.0",
    "gn:admin3_code":"306172.0",
    "gn:admin4_code":"30617215.0",
    "gn:asciiname":"Char Bhelamari",
    "gn:country_code":"BD",
    "gn:dem":17,
    "gn:feature_class":"P",
    "gn:feature_code":"PPL",
    "gn:name":"Char Bhel\u0101m\u0101ri",
    "gn:population":0,
    "gn:timezone":"Asia/Dhaka",
    "iso:country":"BD",
    "wof:name":"Char Bhelamari",
    "wof:placetype":"locality"
},
  "geometry": {"coordinates":[90.52713,24.54824],"type":"Point"}
}