{
  "type": "Feature",
  "properties": {
    "gn:admin1_code":"81",
    "gn:admin2_code":"3029",
    "gn:admin3_code":"302947.0",
    "gn:admin4_code":"30294763.0",
    "gn:asciiname":"Solakunda",
    "gn:country_code":"BD",
    "gn:dem":12,
    "gn:feature_class":"P",
    "gn:feature_code":"PPL",
    "gn:name":"Sol\u0101kunda",
    "gn:population":0,
    "gn:timezone":"Asia/Dhaka",
    "iso:country":"BD",
    "name:und_x_variant":[
        "Shalakundu",
        "Solakanda",
        "Sol\u0101kunda"
    ],
    "wof:name":"Solakunda",
    "wof:placetype":"locality"
},
  "geometry": {"coordinates":[89.7945,23.53576],"type":"Point"}
}