{
  "type": "Feature",
  "properties": {
    "gn:admin1_code":"87",
    "gn:admin2_code":"5549",
    "gn:admin3_code":"554994.0",
    "gn:admin4_code":"55499461.0",
    "gn:asciiname":"Digal Hailla",
    "gn:country_code":"BD",
    "gn:dem":28,
    "gn:feature_class":"P",
    "gn:feature_code":"PPL",
    "gn:name":"Digal Haill\u0101",
    "gn:population":0,
    "gn:timezone":"Asia/Dhaka",
    "iso:country":"BD",
    "name:ben_x_preferred":[
        "Digal Haill\u0101"
    ],
    "wof:name":"Digal Hailla",
    "wof:placetype":"locality"
},
  "geometry": {"coordinates":[89.67653,25.69465],"type":"Point"}
}