{
  "type": "Feature",
  "properties": {
    "gn:admin1_code":"83",
    "gn:admin2_code":"5064.0",
    "gn:admin3_code":"506479.0",
    "gn:admin4_code":"50647987.0",
    "gn:asciiname":"Kashitara",
    "gn:country_code":"BD",
    "gn:dem":35,
    "gn:feature_class":"P",
    "gn:feature_code":"PPL",
    "gn:name":"K\u0101shit\u0101ra",
    "gn:population":0,
    "gn:timezone":"Asia/Dhaka",
    "iso:country":"BD",
    "name:ben_x_preferred":[
        "K\u0101shit\u0101ra"
    ],
    "wof:name":"Kashitara",
    "wof:placetype":"locality"
},
  "geometry": {"coordinates":[88.48935,24.99338],"type":"Point"}
}