{
  "type": "Feature",
  "properties": {
    "gn:admin1_code":"83",
    "gn:admin2_code":"5081",
    "gn:admin3_code":"508112.0",
    "gn:admin4_code":"50811237.0",
    "gn:asciiname":"Jotjoyram",
    "gn:country_code":"BD",
    "gn:dem":19,
    "gn:feature_class":"P",
    "gn:feature_code":"PPL",
    "gn:name":"Jotjoyr\u0101m",
    "gn:population":0,
    "gn:timezone":"Asia/Dhaka",
    "iso:country":"BD",
    "name:ben_x_preferred":[
        "Jotjoyr\u0101m"
    ],
    "name:ben_x_variant":[
        "Jot Jayr\u0101m"
    ],
    "wof:name":"Jotjoyram",
    "wof:placetype":"locality"
},
  "geometry": {"coordinates":[88.84643,24.54921],"type":"Point"}
}