{
  "type": "Feature",
  "properties": {
    "gn:admin1_code":"81",
    "gn:admin2_code":"3048.0",
    "gn:admin3_code":"304876.0",
    "gn:admin4_code":"30487647.0",
    "gn:asciiname":"Dhariswar",
    "gn:country_code":"BD",
    "gn:dem":13,
    "gn:feature_class":"P",
    "gn:feature_code":"PPL",
    "gn:name":"Dh\u0101riswar",
    "gn:population":0,
    "gn:timezone":"Asia/Dhaka",
    "iso:country":"BD",
    "wof:name":"Dhariswar",
    "wof:placetype":"locality"
},
  "geometry": {"coordinates":[90.90832,24.30963],"type":"Point"}
}