{
  "type": "Feature",
  "properties": {
    "gn:admin1_code":"83",
    "gn:admin2_code":"5064.0",
    "gn:admin3_code":"506450.0",
    "gn:admin4_code":"50645066.0",
    "gn:asciiname":"Bhim Sagar",
    "gn:country_code":"BD",
    "gn:dem":22,
    "gn:feature_class":"P",
    "gn:feature_code":"PPL",
    "gn:name":"Bhim S\u0101gar",
    "gn:population":0,
    "gn:timezone":"Asia/Dhaka",
    "iso:country":"BD",
    "name:ben_x_preferred":[
        "Bhim S\u0101gar"
    ],
    "wof:name":"Bhim Sagar",
    "wof:placetype":"locality"
},
  "geometry": {"coordinates":[88.76921,24.90818],"type":"Point"}
}