{
  "type": "Feature",
  "properties": {
    "gn:admin1_code":"87",
    "gn:admin2_code":"5552",
    "gn:admin3_code":"555233.0",
    "gn:admin4_code":"55523328.0",
    "gn:asciiname":"Paschim Bichhandai",
    "gn:country_code":"BD",
    "gn:dem":46,
    "gn:feature_class":"P",
    "gn:feature_code":"PPL",
    "gn:name":"Paschim Bichhandai",
    "gn:population":0,
    "gn:timezone":"Asia/Dhaka",
    "iso:country":"BD",
    "name:ben_x_preferred":[
        "Paschim Bichhandai"
    ],
    "wof:name":"Paschim Bichhandai",
    "wof:placetype":"locality"
},
  "geometry": {"coordinates":[89.15394000000001,26.05447],"type":"Point"}
}