{
  "type": "Feature",
  "properties": {
    "gn:admin1_code":"81",
    "gn:admin2_code":"3048.0",
    "gn:admin3_code":"304876.0",
    "gn:admin4_code":"30487647.0",
    "gn:asciiname":"Chairgati",
    "gn:country_code":"BD",
    "gn:dem":8,
    "gn:feature_class":"P",
    "gn:feature_code":"PPL",
    "gn:name":"Ch\u0101irg\u0101ti",
    "gn:population":0,
    "gn:timezone":"Asia/Dhaka",
    "iso:country":"BD",
    "wof:name":"Chairgati",
    "wof:placetype":"locality"
},
  "geometry": {"coordinates":[90.90000000000001,24.26667],"type":"Point"}
}