{
  "type": "Feature",
  "properties": {
    "gn:admin1_code":"81",
    "gn:admin2_code":"3033",
    "gn:admin3_code":"303330.0",
    "gn:admin4_code":"30333081.0",
    "gn:asciiname":"Narankul",
    "gn:country_code":"BD",
    "gn:dem":14,
    "gn:feature_class":"P",
    "gn:feature_code":"PPL",
    "gn:name":"N\u0101r\u0101nkul",
    "gn:population":0,
    "gn:timezone":"Asia/Dhaka",
    "iso:country":"BD",
    "wof:name":"Narankul",
    "wof:placetype":"locality"
},
  "geometry": {"coordinates":[90.46635000000001,23.92187],"type":"Point"}
}