{
  "type": "Feature",
  "properties": {
    "gn:admin1_code":"H",
    "gn:admin2_code":"3061",
    "gn:admin3_code":"306172.0",
    "gn:admin4_code":"30617231.0",
    "gn:asciiname":"Surasram",
    "gn:country_code":"BD",
    "gn:dem":14,
    "gn:feature_class":"P",
    "gn:feature_code":"PPL",
    "gn:name":"Sur\u0101sram",
    "gn:population":0,
    "gn:timezone":"Asia/Dhaka",
    "iso:country":"BD",
    "wof:name":"Surasram",
    "wof:placetype":"locality"
},
  "geometry": {"coordinates":[90.77064,24.59273],"type":"Point"}
}