{
  "type": "Feature",
  "properties": {
    "gn:admin1_code":"87",
    "gn:admin2_code":"5527",
    "gn:admin3_code":"552777.0",
    "gn:admin4_code":"55277708.0",
    "gn:asciiname":"Bagha Chara",
    "gn:country_code":"BD",
    "gn:dem":43,
    "gn:feature_class":"P",
    "gn:feature_code":"PPL",
    "gn:name":"B\u0101gh\u0101 Ch\u0101ra",
    "gn:population":0,
    "gn:timezone":"Asia/Dhaka",
    "iso:country":"BD",
    "name:ben_x_preferred":[
        "B\u0101gh\u0101 Ch\u0101ra"
    ],
    "wof:name":"Bagha Chara",
    "wof:placetype":"locality"
},
  "geometry": {"coordinates":[88.88539,25.74636],"type":"Point"}
}