{
  "type": "Feature",
  "properties": {
    "gn:admin1_code":"84",
    "gn:admin2_code":"2003.0",
    "gn:admin3_code":"200351.0",
    "gn:admin4_code":"20035147.0",
    "gn:asciiname":"Headmanpara",
    "gn:country_code":"BD",
    "gn:dem":28,
    "gn:feature_class":"P",
    "gn:feature_code":"PPL",
    "gn:name":"Headmanp\u0101ra",
    "gn:population":0,
    "gn:timezone":"Asia/Dhaka",
    "iso:country":"BD",
    "name:ben_x_preferred":[
        "Headmanp\u0101ra"
    ],
    "name:ben_x_variant":[
        "Gajalia"
    ],
    "wof:name":"Headmanpara",
    "wof:placetype":"locality"
},
  "geometry": {"coordinates":[92.18214,21.84998],"type":"Point"}
}