{
  "type": "Feature",
  "properties": {
    "gn:admin1_code":"82",
    "gn:admin2_code":"4041.0",
    "gn:admin3_code":"404190.0",
    "gn:admin4_code":"40419094.0",
    "gn:asciiname":"Barberia",
    "gn:country_code":"BD",
    "gn:dem":11,
    "gn:feature_class":"P",
    "gn:feature_code":"PPL",
    "gn:name":"B\u0101rberia",
    "gn:population":0,
    "gn:timezone":"Asia/Dhaka",
    "iso:country":"BD",
    "name:ben_x_preferred":[
        "B\u0101rberia"
    ],
    "name:ceb_x_preferred":[
        "Barberia affinitella"
    ],
    "name:nld_x_preferred":[
        "Barberia affinitella"
    ],
    "name:swe_x_preferred":[
        "Barberia affinitella"
    ],
    "name:war_x_preferred":[
        "Barberia affinitella"
    ],
    "wof:name":"Barberia",
    "wof:placetype":"locality"
},
  "geometry": {"coordinates":[88.9766,23.01792],"type":"Point"}
}