{
  "type": "Feature",
  "properties": {
    "gn:admin1_code":"84",
    "gn:admin2_code":"2015.0",
    "gn:admin3_code":"201537.0",
    "gn:admin4_code":"20153735.0",
    "gn:asciiname":"Mitha Chhara",
    "gn:country_code":"BD",
    "gn:dem":32,
    "gn:feature_class":"P",
    "gn:feature_code":"PPL",
    "gn:name":"Mitha Chhara",
    "gn:population":0,
    "gn:timezone":"Asia/Dhaka",
    "iso:country":"BD",
    "name:ben_x_preferred":[
        "Mitha Chhara"
    ],
    "wof:name":"Mitha Chhara",
    "wof:placetype":"locality"
},
  "geometry": {"coordinates":[91.77075000000001,22.47958],"type":"Point"}
}