{
  "type": "Feature",
  "properties": {
    "gn:admin1_code":"85",
    "gn:admin2_code":"1078.0",
    "gn:admin3_code":"107852.0",
    "gn:admin4_code":"10785252.0",
    "gn:asciiname":"Golkhali",
    "gn:country_code":"BD",
    "gn:dem":9,
    "gn:feature_class":"P",
    "gn:feature_code":"PPL",
    "gn:name":"Golkh\u0101li",
    "gn:population":0,
    "gn:timezone":"Asia/Dhaka",
    "iso:country":"BD",
    "name:ben_x_preferred":[
        "Golkh\u0101li"
    ],
    "wof:name":"Golkhali",
    "wof:placetype":"locality"
},
  "geometry": {"coordinates":[90.58347000000001,22.26428],"type":"Point"}
}