{
  "type": "Feature",
  "properties": {
    "gn:admin1_code":"81",
    "gn:admin2_code":"3093.0",
    "gn:admin3_code":"309357.0",
    "gn:admin4_code":"30935766.0",
    "gn:asciiname":"Golabari",
    "gn:country_code":"BD",
    "gn:dem":19,
    "gn:feature_class":"P",
    "gn:feature_code":"PPL",
    "gn:name":"Gol\u0101b\u0101ri",
    "gn:population":0,
    "gn:timezone":"Asia/Dhaka",
    "iso:country":"BD",
    "wof:name":"Golabari",
    "wof:placetype":"locality"
},
  "geometry": {"coordinates":[89.98328000000002,24.61668],"type":"Point"}
}