{
  "type": "Feature",
  "properties": {
    "gn:admin1_code":"82",
    "gn:admin2_code":"4044.0",
    "gn:admin3_code":"404419.0",
    "gn:admin4_code":"40441931.0",
    "gn:asciiname":"Alia Bakri",
    "gn:country_code":"BD",
    "gn:dem":12,
    "gn:feature_class":"P",
    "gn:feature_code":"PPL",
    "gn:name":"\u0100lia B\u0101kri",
    "gn:population":0,
    "gn:timezone":"Asia/Dhaka",
    "iso:country":"BD",
    "wof:name":"Alia Bakri",
    "wof:placetype":"locality"
},
  "geometry": {"coordinates":[89.27608000000002,23.58005],"type":"Point"}
}