{
  "type": "Feature",
  "properties": {
    "gn:admin1_code":"81",
    "gn:admin2_code":"3026.0",
    "gn:admin3_code":"302618.0",
    "gn:admin4_code":"30261831.0",
    "gn:asciiname":"Chhota Ramnathpur",
    "gn:country_code":"BD",
    "gn:dem":12,
    "gn:feature_class":"P",
    "gn:feature_code":"PPL",
    "gn:name":"Chhota R\u0101mn\u0101thpur",
    "gn:population":0,
    "gn:timezone":"Asia/Dhaka",
    "iso:country":"BD",
    "wof:name":"Chhota Ramnathpur",
    "wof:placetype":"locality"
},
  "geometry": {"coordinates":[90.10481,23.61139],"type":"Point"}
}