{
  "type": "Feature",
  "properties": {
    "gn:admin1_code":"H",
    "gn:admin2_code":"3061",
    "gn:admin3_code":"306172.0",
    "gn:admin4_code":"30617231.0",
    "gn:asciiname":"Purbakanda",
    "gn:country_code":"BD",
    "gn:dem":14,
    "gn:feature_class":"P",
    "gn:feature_code":"PPL",
    "gn:name":"Purbak\u0101nda",
    "gn:population":0,
    "gn:timezone":"Asia/Dhaka",
    "iso:country":"BD",
    "name:und_x_variant":[
        "Purbak\u0101nda",
        "Purbbak\u0101nda"
    ],
    "wof:name":"Purbakanda",
    "wof:placetype":"locality"
},
  "geometry": {"coordinates":[90.76827,24.60458],"type":"Point"}
}