{
  "type": "Feature",
  "properties": {
    "gn:admin1_code":"87",
    "gn:admin2_code":"5527.0",
    "gn:admin3_code":"552730.0",
    "gn:admin4_code":"55273071.0",
    "gn:asciiname":"Krishnapur Khamar",
    "gn:country_code":"BD",
    "gn:dem":37,
    "gn:feature_class":"P",
    "gn:feature_code":"PPL",
    "gn:name":"Krishnapur Khamar",
    "gn:population":0,
    "gn:timezone":"Asia/Dhaka",
    "iso:country":"BD",
    "name:ben_x_preferred":[
        "Krishnapur Khamar"
    ],
    "wof:name":"Krishnapur Khamar",
    "wof:placetype":"locality"
},
  "geometry": {"coordinates":[88.76388,25.53528],"type":"Point"}
}