{
  "type": "Feature",
  "properties": {
    "gn:admin1_code":"84",
    "gn:admin2_code":"2013",
    "gn:admin3_code":"201376.0",
    "gn:admin4_code":"20137682.0",
    "gn:asciiname":"Qaziara",
    "gn:country_code":"BD",
    "gn:dem":11,
    "gn:feature_class":"P",
    "gn:feature_code":"PPL",
    "gn:name":"Q\u0101zi\u0101ra",
    "gn:population":0,
    "gn:timezone":"Asia/Dhaka",
    "iso:country":"BD",
    "name:und_x_variant":[
        "K\u0101ji\u0101r\u0101",
        "K\u0101zi\u0101ra",
        "Q\u0101zi\u0101ra"
    ],
    "wof:name":"Qaziara",
    "wof:placetype":"locality"
},
  "geometry": {"coordinates":[90.78198,23.38186],"type":"Point"}
}