{
  "type": "Feature",
  "properties": {
    "gn:admin1_code":"81",
    "gn:admin2_code":"3059",
    "gn:admin3_code":"305924.0",
    "gn:admin4_code":"30592463.0",
    "gn:asciiname":"Husaindi",
    "gn:country_code":"BD",
    "gn:dem":4,
    "gn:feature_class":"P",
    "gn:feature_code":"PPL",
    "gn:name":"Husaindi",
    "gn:population":0,
    "gn:timezone":"Asia/Dhaka",
    "iso:country":"BD",
    "name:und_x_variant":[
        "Hosendi",
        "Husaindi"
    ],
    "wof:name":"Husaindi",
    "wof:placetype":"locality"
},
  "geometry": {"coordinates":[90.60382,23.58103],"type":"Point"}
}