{
  "type": "Feature",
  "properties": {
    "gn:admin1_code":"84",
    "gn:admin2_code":"2013",
    "gn:admin3_code":"201322.0",
    "gn:admin4_code":"20132209.0",
    "gn:asciiname":"Kalyandi",
    "gn:country_code":"BD",
    "gn:dem":13,
    "gn:feature_class":"P",
    "gn:feature_code":"PPL",
    "gn:name":"Kaly\u0101ndi",
    "gn:population":0,
    "gn:timezone":"Asia/Dhaka",
    "iso:country":"BD",
    "wof:name":"Kalyandi",
    "wof:placetype":"locality"
},
  "geometry": {"coordinates":[90.66833,23.27964],"type":"Point"}
}