{
  "type": "Feature",
  "properties": {
    "gn:admin1_code":"82",
    "gn:admin2_code":"4041",
    "gn:admin3_code":"404161.0",
    "gn:admin4_code":"40416167.0",
    "gn:asciiname":"Thate Kamalpur",
    "gn:country_code":"BD",
    "gn:dem":9,
    "gn:feature_class":"P",
    "gn:feature_code":"PPL",
    "gn:name":"Thate Kam\u0101lpur",
    "gn:population":0,
    "gn:timezone":"Asia/Dhaka",
    "iso:country":"BD",
    "wof:name":"Thate Kamalpur",
    "wof:placetype":"locality"
},
  "geometry": {"coordinates":[89.23989,23.01037],"type":"Point"}
}