{
  "type": "Feature",
  "properties": {
    "gn:admin1_code":"81",
    "gn:admin2_code":"3026",
    "gn:admin3_code":"302672.0",
    "gn:admin4_code":"30267233.0",
    "gn:asciiname":"Pipulia",
    "gn:country_code":"BD",
    "gn:dem":11,
    "gn:feature_class":"P",
    "gn:feature_code":"PPL",
    "gn:name":"Pipulia",
    "gn:population":0,
    "gn:timezone":"Asia/Dhaka",
    "iso:country":"BD",
    "wof:name":"Pipulia",
    "wof:placetype":"locality"
},
  "geometry": {"coordinates":[90.33463999999999,23.84918],"type":"Point"}
}