{
  "type": "Feature",
  "properties": {
    "gn:admin1_code":"H",
    "gn:admin2_code":"3061.0",
    "gn:admin3_code":"306131.0",
    "gn:admin4_code":"30613167.0",
    "gn:asciiname":"Charakona",
    "gn:country_code":"BD",
    "gn:dem":17,
    "gn:feature_class":"P",
    "gn:feature_code":"PPL",
    "gn:name":"Char\u0101kona",
    "gn:population":0,
    "gn:timezone":"Asia/Dhaka",
    "iso:country":"BD",
    "wof:name":"Charakona",
    "wof:placetype":"locality"
},
  "geometry": {"coordinates":[90.54828999999999,24.62421],"type":"Point"}
}