{
  "type": "Feature",
  "properties": {
    "gn:admin1_code":"82",
    "gn:admin2_code":"4001.0",
    "gn:admin3_code":"400160.0",
    "gn:admin4_code":"40016071.0",
    "gn:asciiname":"Gabtali",
    "gn:country_code":"BD",
    "gn:dem":4,
    "gn:feature_class":"P",
    "gn:feature_code":"PPL",
    "gn:name":"Gabtali",
    "gn:population":0,
    "gn:timezone":"Asia/Dhaka",
    "iso:country":"BD",
    "name:ben_x_preferred":[
        "Gabtali"
    ],
    "wof:name":"Gabtali",
    "wof:placetype":"locality"
},
  "geometry": {"coordinates":[89.78433000000003,22.42747],"type":"Point"}
}