{
  "type": "Feature",
  "properties": {
    "gn:admin1_code":"81",
    "gn:admin2_code":"3059.0",
    "gn:admin3_code":"305956.0",
    "gn:admin4_code":"30595619.0",
    "gn:asciiname":"Churain",
    "gn:country_code":"BD",
    "gn:dem":11,
    "gn:feature_class":"P",
    "gn:feature_code":"PPL",
    "gn:name":"Chur\u0101in",
    "gn:population":0,
    "gn:timezone":"Asia/Dhaka",
    "iso:country":"BD",
    "wof:name":"Churain",
    "wof:placetype":"locality"
},
  "geometry": {"coordinates":[90.49328,23.50994],"type":"Point"}
}