{
  "type": "Feature",
  "properties": {
    "gn:admin1_code":"83",
    "gn:admin2_code":"5010",
    "gn:admin3_code":"501020.0",
    "gn:admin4_code":"50102047.0",
    "gn:asciiname":"Rokangari",
    "gn:country_code":"BD",
    "gn:dem":20,
    "gn:feature_class":"P",
    "gn:feature_code":"PPL",
    "gn:name":"Rokang\u0101ri",
    "gn:population":0,
    "gn:timezone":"Asia/Dhaka",
    "iso:country":"BD",
    "wof:name":"Rokangari",
    "wof:placetype":"locality"
},
  "geometry": {"coordinates":[89.36667,24.96667],"type":"Point"}
}