{
  "type": "Feature",
  "properties": {
    "gn:admin1_code":"82",
    "gn:admin2_code":"4087.0",
    "gn:admin3_code":"408704.0",
    "gn:admin4_code":"40870477.0",
    "gn:asciiname":"Gokulnagar",
    "gn:country_code":"BD",
    "gn:dem":5,
    "gn:feature_class":"P",
    "gn:feature_code":"PPL",
    "gn:name":"Gokulnagar",
    "gn:population":0,
    "gn:timezone":"Asia/Dhaka",
    "iso:country":"BD",
    "name:vie_x_preferred":[
        "Gokulnagar"
    ],
    "wof:name":"Gokulnagar",
    "wof:placetype":"locality"
},
  "geometry": {"coordinates":[89.24879,22.3964],"type":"Point"}
}