{
  "type": "Feature",
  "properties": {
    "gn:admin1_code":"H",
    "gn:admin2_code":"3039.0",
    "gn:admin3_code":"303936.0",
    "gn:admin4_code":"30393677.0",
    "gn:asciiname":"Bera Pathalia",
    "gn:country_code":"BD",
    "gn:dem":23,
    "gn:feature_class":"P",
    "gn:feature_code":"PPL",
    "gn:name":"Bera P\u0101th\u0101lia",
    "gn:population":0,
    "gn:timezone":"Asia/Dhaka",
    "iso:country":"BD",
    "wof:name":"Bera Pathalia",
    "wof:placetype":"locality"
},
  "geometry": {"coordinates":[89.99280999999998,24.85455],"type":"Point"}
}