{
  "type": "Feature",
  "properties": {
    "gn:admin1_code":"84",
    "gn:admin2_code":"2022.0",
    "gn:admin3_code":"202216.0",
    "gn:admin4_code":"20221650.0",
    "gn:asciiname":"Rosaingapara",
    "gn:country_code":"BD",
    "gn:dem":10,
    "gn:feature_class":"P",
    "gn:feature_code":"PPL",
    "gn:name":"Ros\u0101ing\u0101p\u0101ra",
    "gn:population":0,
    "gn:timezone":"Asia/Dhaka",
    "iso:country":"BD",
    "name:ben_x_preferred":[
        "Ros\u0101ing\u0101p\u0101ra"
    ],
    "wof:name":"Rosaingapara",
    "wof:placetype":"locality"
},
  "geometry": {"coordinates":[92.05112,21.84918],"type":"Point"}
}