{
  "type": "Feature",
  "properties": {
    "gn:admin1_code":"83",
    "gn:asciiname":"Bhelamari",
    "gn:country_code":"BD",
    "gn:dem":27,
    "gn:feature_class":"P",
    "gn:feature_code":"PPL",
    "gn:name":"Bhel\u0101m\u0101ri",
    "gn:population":0,
    "gn:timezone":"Asia/Dhaka",
    "iso:country":"BD",
    "name:ben_x_preferred":[
        "Bhel\u0101m\u0101ri"
    ],
    "wof:name":"Bhelamari",
    "wof:placetype":"locality"
},
  "geometry": {"coordinates":[89.31298000000002,25.18056],"type":"Point"}
}