{
  "type": "Feature",
  "properties": {
    "gn:admin1_code":"84",
    "gn:admin2_code":"2046.0",
    "gn:admin3_code":"204665.0",
    "gn:admin4_code":"20466531.0",
    "gn:asciiname":"Nagongpara",
    "gn:country_code":"BD",
    "gn:dem":50,
    "gn:feature_class":"P",
    "gn:feature_code":"PPL",
    "gn:name":"Nagongp\u0101ra",
    "gn:population":0,
    "gn:timezone":"Asia/Dhaka",
    "iso:country":"BD",
    "name:ben_x_preferred":[
        "Nagongp\u0101ra"
    ],
    "wof:name":"Nagongpara",
    "wof:placetype":"locality"
},
  "geometry": {"coordinates":[92.01526,22.90507],"type":"Point"}
}