{
  "type": "Feature",
  "properties": {
    "gn:admin1_code":"85",
    "gn:admin2_code":"1006",
    "gn:admin3_code":"100607.0",
    "gn:admin4_code":"10060713.0",
    "gn:asciiname":"Pashchim Charadi",
    "gn:country_code":"BD",
    "gn:dem":8,
    "gn:feature_class":"P",
    "gn:feature_code":"PPL",
    "gn:name":"Pashchim Char\u0101di",
    "gn:population":0,
    "gn:timezone":"Asia/Dhaka",
    "iso:country":"BD",
    "name:und_x_variant":[
        "Pashchim Char\u0101di",
        "West Char\u0101di"
    ],
    "wof:name":"Pashchim Charadi",
    "wof:placetype":"locality"
},
  "geometry": {"coordinates":[90.35678,22.6295],"type":"Point"}
}