{
  "type": "Feature",
  "properties": {
    "gn:admin1_code":"85",
    "gn:admin2_code":"1006.0",
    "gn:admin3_code":"100632.0",
    "gn:admin4_code":"10063231.0",
    "gn:asciiname":"Batajor",
    "gn:country_code":"BD",
    "gn:dem":9,
    "gn:feature_class":"P",
    "gn:feature_code":"PPL",
    "gn:name":"B\u0101t\u0101jor",
    "gn:population":0,
    "gn:timezone":"Asia/Dhaka",
    "iso:country":"BD",
    "name:und_x_variant":[
        "Batajar",
        "B\u0101t\u0101jor"
    ],
    "wof:name":"Batajor",
    "wof:placetype":"locality"
},
  "geometry": {"coordinates":[90.25421,22.89745],"type":"Point"}
}