{
  "type": "Feature",
  "properties": {
    "gn:admin1_code":"84",
    "gn:admin2_code":"2003.0",
    "gn:admin3_code":"200351.0",
    "gn:admin4_code":"20035163.0",
    "gn:asciiname":"Aunglapara",
    "gn:country_code":"BD",
    "gn:dem":19,
    "gn:feature_class":"P",
    "gn:feature_code":"PPL",
    "gn:name":"Aungl\u0101p\u0101ra",
    "gn:population":0,
    "gn:timezone":"Asia/Dhaka",
    "iso:country":"BD",
    "name:ben_x_preferred":[
        "Aungl\u0101p\u0101ra"
    ],
    "name:ben_x_variant":[
        "Aung\u0101p\u0101ra"
    ],
    "wof:name":"Aunglapara",
    "wof:placetype":"locality"
},
  "geometry": {"coordinates":[92.23027999999999,21.76511],"type":"Point"}
}