{
  "type": "Feature",
  "properties": {
    "gn:admin1_code":"87",
    "gn:admin2_code":"5527.0",
    "gn:admin3_code":"552712.0",
    "gn:admin4_code":"55271286.0",
    "gn:asciiname":"Deoli",
    "gn:country_code":"BD",
    "gn:dem":56,
    "gn:feature_class":"P",
    "gn:feature_code":"PPL",
    "gn:name":"Deoli",
    "gn:population":0,
    "gn:timezone":"Asia/Dhaka",
    "iso:country":"BD",
    "name:ben_x_preferred":[
        "Deoli"
    ],
    "name:ben_x_variant":[
        "\u09a6\u09c7\u0993\u09b2\u09bf"
    ],
    "name:bih_x_preferred":[
        "\u0926\u0947\u0935\u0932\u0940"
    ],
    "name:ceb_x_preferred":[
        "Deoli"
    ],
    "name:nld_x_preferred":[
        "Deoli"
    ],
    "name:swe_x_preferred":[
        "Deoli"
    ],
    "wof:name":"Deoli",
    "wof:placetype":"locality"
},
  "geometry": {"coordinates":[88.54809,26.00612000000001],"type":"Point"}
}