{
  "type": "Feature",
  "properties": {
    "gn:admin1_code":"82",
    "gn:admin2_code":"4050.0",
    "gn:admin3_code":"405039.0",
    "gn:admin4_code":"40503994.0",
    "gn:asciiname":"Haringachho",
    "gn:country_code":"BD",
    "gn:dem":22,
    "gn:feature_class":"P",
    "gn:feature_code":"PPL",
    "gn:name":"Haring\u0101chho",
    "gn:population":0,
    "gn:timezone":"Asia/Dhaka",
    "iso:country":"BD",
    "name:ben_x_preferred":[
        "Haring\u0101chho"
    ],
    "wof:name":"Haringachho",
    "wof:placetype":"locality"
},
  "geometry": {"coordinates":[88.90779000000001,24.00267],"type":"Point"}
}