{
  "type": "Feature",
  "properties": {
    "gn:admin1_code":"84",
    "gn:admin2_code":"2084",
    "gn:admin3_code":"208447.0",
    "gn:admin4_code":"20844719.0",
    "gn:asciiname":"Khagrachari",
    "gn:country_code":"BD",
    "gn:dem":45,
    "gn:feature_class":"P",
    "gn:feature_code":"PPL",
    "gn:name":"Khagr\u0101chari",
    "gn:population":0,
    "gn:timezone":"Asia/Dhaka",
    "iso:country":"BD",
    "name:und_x_variant":[
        "Khagracheri",
        "Khagr\u0101chhari",
        "Khagr\u0101chari"
    ],
    "wof:name":"Khagrachari",
    "wof:placetype":"locality"
},
  "geometry": {"coordinates":[92.38406999999999,22.66881],"type":"Point"}
}