{
  "type": "Feature",
  "properties": {
    "gn:admin1_code":"83",
    "gn:admin2_code":"5070.0",
    "gn:admin3_code":"507056.0",
    "gn:admin4_code":"50705657.0",
    "gn:asciiname":"Bhatsa",
    "gn:country_code":"BD",
    "gn:dem":33,
    "gn:feature_class":"P",
    "gn:feature_code":"PPL",
    "gn:name":"Bh\u0101tsa",
    "gn:population":0,
    "gn:timezone":"Asia/Dhaka",
    "iso:country":"BD",
    "name:ben_x_preferred":[
        "Bh\u0101tsa"
    ],
    "wof:name":"Bhatsa",
    "wof:placetype":"locality"
},
  "geometry": {"coordinates":[88.48023000000001,24.72215],"type":"Point"}
}