{
  "type": "Feature",
  "properties": {
    "gn:admin1_code":"87",
    "gn:admin2_code":"5552",
    "gn:admin3_code":"555202.0",
    "gn:admin4_code":"55520211.0",
    "gn:asciiname":"Taluk Dulali",
    "gn:country_code":"BD",
    "gn:dem":39,
    "gn:feature_class":"P",
    "gn:feature_code":"PPL",
    "gn:name":"T\u0101luk Dul\u0101li",
    "gn:population":0,
    "gn:timezone":"Asia/Dhaka",
    "iso:country":"BD",
    "wof:name":"Taluk Dulali",
    "wof:placetype":"locality"
},
  "geometry": {"coordinates":[89.37567,26.00267],"type":"Point"}
}