{
  "type": "Feature",
  "properties": {
    "gn:admin1_code":"87",
    "gn:admin2_code":"5549",
    "gn:admin3_code":"554977.0",
    "gn:admin4_code":"55497773.0",
    "gn:asciiname":"Dakshin Pranpati",
    "gn:country_code":"BD",
    "gn:dem":34,
    "gn:feature_class":"P",
    "gn:feature_code":"PPL",
    "gn:name":"Dakshin Pr\u0101npati",
    "gn:population":0,
    "gn:timezone":"Asia/Dhaka",
    "iso:country":"BD",
    "name:ben_x_preferred":[
        "Dakshin Pr\u0101npati"
    ],
    "wof:name":"Dakshin Pranpati",
    "wof:placetype":"locality"
},
  "geometry": {"coordinates":[89.52023,25.78636],"type":"Point"}
}