{
  "type": "Feature",
  "properties": {
    "gn:country":"BD",
    "gn:fcode":"PPL",
    "gn:pop":45670,
    "iso:country":"BD",
    "name:ben_x_preferred":[
        "Burh\u0101nuddin"
    ],
    "name:ben_x_variant":[
        "Barah\u0101nuddin"
    ],
    "name:dut_x_preferred":[
        "Barahanuddin"
    ],
    "name:eng_x_preferred":[
        "Barahanuddin"
    ],
    "name:swe_x_preferred":[
        "Burh\u0101nuddin"
    ],
    "qs:name":"Burh\u0101nuddin",
    "qs:photos_9r":0,
    "qs:photos_sr":0,
    "qs:pop_sr":"7",
    "wof:name":"Burh\u0101nuddin",
    "wof:placetype":"locality",
    "wof:population":45670
},
  "geometry": {"coordinates":[90.7239,22.49518],"type":"Point"}
}