{
  "type": "Feature",
  "properties": {
    "gn:country":"BD",
    "gn:fcode":"PPL",
    "gn:population":45670,
    "iso:country":"BD",
    "name:ben_x_preferred":[
        "Burh\u0101nuddin"
    ],
    "name:ben_x_variant":[
        "Barah\u0101nuddin"
    ],
    "name:ceb_x_preferred":[
        "Burh\u0101nuddin"
    ],
    "name:eng_x_preferred":[
        "Barahanuddin"
    ],
    "name:fas_x_preferred":[
        "\u0628\u0631\u0627\u0647\u0646\u200c\u0627\u0644\u062f\u06cc\u0646"
    ],
    "name:msa_x_preferred":[
        "Barahanuddin"
    ],
    "name:nld_x_preferred":[
        "Barahanuddin"
    ],
    "name:swe_x_preferred":[
        "Burh\u0101nuddin"
    ],
    "qs:name":"Burh\u0101nuddin",
    "qs:photos_9r":0,
    "qs:photos_sr":0,
    "qs:pop_sr":"7",
    "wof:name":"Burh\u0101nuddin",
    "wof:placetype":"locality",
    "wof:population":45670
},
  "geometry": {"coordinates":[90.7239,22.49518],"type":"Point"}
}