{
  "type": "Feature",
  "properties": {
    "gn:admin1_code":"81",
    "gn:admin2_code":"3068.0",
    "gn:admin3_code":"306807.0",
    "gn:admin4_code":"30680713.0",
    "gn:asciiname":"Dakshin Dhuru",
    "gn:country_code":"BD",
    "gn:dem":16,
    "gn:feature_class":"P",
    "gn:feature_code":"PPL",
    "gn:name":"Dakshin Dhuru",
    "gn:population":0,
    "gn:timezone":"Asia/Dhaka",
    "iso:country":"BD",
    "wof:name":"Dakshin Dhuru",
    "wof:placetype":"locality"
},
  "geometry": {"coordinates":[90.82041,24.10869],"type":"Point"}
}