{
  "type": "Feature",
  "properties": {
    "gn:admin1_code":"82",
    "gn:admin2_code":"4044.0",
    "gn:admin3_code":"404442.0",
    "gn:admin4_code":"40444240.0",
    "gn:asciiname":"Bagdanga",
    "gn:country_code":"BD",
    "gn:dem":15,
    "gn:feature_class":"P",
    "gn:feature_code":"PPL",
    "gn:name":"B\u0101gd\u0101nga",
    "gn:population":0,
    "gn:timezone":"Asia/Dhaka",
    "iso:country":"BD",
    "name:ben_x_preferred":[
        "B\u0101gd\u0101nga"
    ],
    "wof:name":"Bagdanga",
    "wof:placetype":"locality"
},
  "geometry": {"coordinates":[89.0269,23.37462],"type":"Point"}
}