{
  "type": "Feature",
  "properties": {
    "gn:admin1_code":"82",
    "gn:admin2_code":"4065.0",
    "gn:admin3_code":"406576.0",
    "gn:admin4_code":"40657613.0",
    "gn:asciiname":"Sambhudanga",
    "gn:country_code":"BD",
    "gn:dem":11,
    "gn:feature_class":"P",
    "gn:feature_code":"PPL",
    "gn:name":"Sambhud\u0101nga",
    "gn:population":0,
    "gn:timezone":"Asia/Dhaka",
    "iso:country":"BD",
    "name:ben_x_preferred":[
        "Sambhud\u0101nga"
    ],
    "wof:name":"Sambhudanga",
    "wof:placetype":"locality"
},
  "geometry": {"coordinates":[89.55311,23.16026],"type":"Point"}
}