{
  "type": "Feature",
  "properties": {
    "gn:admin1_code":"82",
    "gn:asciiname":"Nilkamal",
    "gn:country_code":"BD",
    "gn:dem":7,
    "gn:feature_class":"P",
    "gn:feature_code":"PPL",
    "gn:name":"Nilkamal",
    "gn:population":0,
    "gn:timezone":"Asia/Dhaka",
    "iso:country":"BD",
    "name:ben_x_preferred":[
        "Nilkamal"
    ],
    "name:und_x_variant":[
        "Char Nilkamal"
    ],
    "wof:name":"Nilkamal",
    "wof:placetype":"locality"
},
  "geometry": {"coordinates":[90.65796,22.21514],"type":"Point"}
}