{
  "type": "Feature",
  "properties": {
    "gn:admin1_code":"82",
    "gn:admin2_code":"4044.0",
    "gn:admin3_code":"404414.0",
    "gn:admin4_code":"40441473.0",
    "gn:asciiname":"Kalaparia",
    "gn:country_code":"BD",
    "gn:dem":16,
    "gn:feature_class":"P",
    "gn:feature_code":"PPL",
    "gn:name":"K\u0101l\u0101p\u0101ria",
    "gn:population":0,
    "gn:timezone":"Asia/Dhaka",
    "iso:country":"BD",
    "name:ben_x_preferred":[
        "K\u0101l\u0101p\u0101ria"
    ],
    "wof:name":"Kalaparia",
    "wof:placetype":"locality"
},
  "geometry": {"coordinates":[89.09093,23.67329],"type":"Point"}
}