{
  "type": "Feature",
  "properties": {
    "gn:admin1_code":"82",
    "gn:admin2_code":"4018.0",
    "gn:admin3_code":"401855.0",
    "gn:admin4_code":"40185538.0",
    "gn:asciiname":"Ninkundu",
    "gn:country_code":"BD",
    "gn:dem":17,
    "gn:feature_class":"P",
    "gn:feature_code":"PPL",
    "gn:name":"Ninkundu",
    "gn:population":0,
    "gn:timezone":"Asia/Dhaka",
    "iso:country":"BD",
    "name:ben_x_preferred":[
        "Ninkundu"
    ],
    "wof:name":"Ninkundu",
    "wof:placetype":"locality"
},
  "geometry": {"coordinates":[88.91627,23.45099],"type":"Point"}
}