{
  "type": "Feature",
  "properties": {
    "gn:admin1_code":"82",
    "gn:admin2_code":"4050.0",
    "gn:admin3_code":"405063.0",
    "gn:admin4_code":"40506371.0",
    "gn:asciiname":"Gopgram",
    "gn:country_code":"BD",
    "gn:dem":16,
    "gn:feature_class":"P",
    "gn:feature_code":"PPL",
    "gn:name":"Gopgr\u0101m",
    "gn:population":0,
    "gn:timezone":"Asia/Dhaka",
    "iso:country":"BD",
    "name:und_x_variant":[
        "Gopagram",
        "Gopgr\u0101m"
    ],
    "wof:name":"Gopgram",
    "wof:placetype":"locality"
},
  "geometry": {"coordinates":[89.30483000000002,23.86748],"type":"Point"}
}