{
  "type": "Feature",
  "properties": {
    "gn:admin1_code":"81",
    "gn:admin2_code":"3082.0",
    "gn:admin3_code":"308273.0",
    "gn:admin4_code":"30827360.0",
    "gn:asciiname":"Bil Manushmari",
    "gn:country_code":"BD",
    "gn:dem":14,
    "gn:feature_class":"P",
    "gn:feature_code":"PPL",
    "gn:name":"B\u012bl M\u0101nushm\u0101ri",
    "gn:population":0,
    "gn:timezone":"Asia/Dhaka",
    "iso:country":"BD",
    "name:und_x_variant":[
        "Bil Manusmari",
        "B\u012bl M\u0101nushm\u0101ri"
    ],
    "wof:name":"Bil Manushmari",
    "wof:placetype":"locality"
},
  "geometry": {"coordinates":[89.54349000000001,23.738],"type":"Point"}
}