{
  "type": "Feature",
  "properties": {
    "gn:admin1_code":"82",
    "gn:admin2_code":"4050.0",
    "gn:admin3_code":"405063.0",
    "gn:admin4_code":"40506371.0",
    "gn:asciiname":"Baraipara",
    "gn:country_code":"BD",
    "gn:dem":14,
    "gn:feature_class":"P",
    "gn:feature_code":"PPL",
    "gn:name":"B\u0101raip\u0101ra",
    "gn:population":0,
    "gn:timezone":"Asia/Dhaka",
    "iso:country":"BD",
    "wof:name":"Baraipara",
    "wof:placetype":"locality"
},
  "geometry": {"coordinates":[89.34999999999999,23.86667000000001],"type":"Point"}
}