{
  "type": "Feature",
  "properties": {
    "gn:admin1_code":"85",
    "gn:admin2_code":"1078.0",
    "gn:admin3_code":"107866.0",
    "gn:admin4_code":"10786623.0",
    "gn:asciiname":"Sadarpur",
    "gn:country_code":"BD",
    "gn:dem":7,
    "gn:feature_class":"P",
    "gn:feature_code":"PPL",
    "gn:name":"Sadarpur",
    "gn:population":0,
    "gn:timezone":"Asia/Dhaka",
    "iso:country":"BD",
    "name:ben_x_preferred":[
        "Sadarpur"
    ],
    "wof:name":"Sadarpur",
    "wof:placetype":"locality"
},
  "geometry": {"coordinates":[90.13315,21.90033],"type":"Point"}
}