{
  "type": "Feature",
  "properties": {
    "gn:admin1_code":"H",
    "gn:admin2_code":"3072.0",
    "gn:admin3_code":"307204.0",
    "gn:admin4_code":"30720459.0",
    "gn:asciiname":"Gopalasram Madhuakhali",
    "gn:country_code":"BD",
    "gn:dem":12,
    "gn:feature_class":"P",
    "gn:feature_code":"PPL",
    "gn:name":"Gop\u0101l\u0101sram Madhu\u0101kh\u0101li",
    "gn:population":0,
    "gn:timezone":"Asia/Dhaka",
    "iso:country":"BD",
    "wof:name":"Gopalasram Madhuakhali",
    "wof:placetype":"locality"
},
  "geometry": {"coordinates":[90.93546000000001,24.74458],"type":"Point"}
}