{
  "type": "Feature",
  "properties": {
    "gn:admin1_code":"81",
    "gn:admin2_code":"3054.0",
    "gn:admin3_code":"305440.0",
    "gn:admin4_code":"30544012.0",
    "gn:asciiname":"Bahir Dhulgram",
    "gn:country_code":"BD",
    "gn:dem":8,
    "gn:feature_class":"P",
    "gn:feature_code":"PPL",
    "gn:name":"B\u0101hir Dhulgr\u0101m",
    "gn:population":0,
    "gn:timezone":"Asia/Dhaka",
    "iso:country":"BD",
    "name:und_x_variant":[
        "Baher Dhulgram",
        "B\u0101hir Dhulgr\u0101m"
    ],
    "wof:name":"Bahir Dhulgram",
    "wof:placetype":"locality"
},
  "geometry": {"coordinates":[90.19363,23.11634],"type":"Point"}
}