{
  "type": "Feature",
  "properties": {
    "gn:admin1_code":"87",
    "gn:admin2_code":"5585",
    "gn:admin3_code":"558549.0",
    "gn:admin4_code":"55854931.0",
    "gn:asciiname":"Ramnathpur",
    "gn:country_code":"BD",
    "gn:dem":40,
    "gn:feature_class":"P",
    "gn:feature_code":"PPL",
    "gn:name":"R\u0101mn\u0101thpur",
    "gn:population":0,
    "gn:timezone":"Asia/Dhaka",
    "iso:country":"BD",
    "name:ben_x_preferred":[
        "R\u0101mn\u0101thpur"
    ],
    "wof:name":"Ramnathpur",
    "wof:placetype":"locality"
},
  "geometry": {"coordinates":[89.12974,25.78937],"type":"Point"}
}