{
  "type": "Feature",
  "properties": {
    "gn:admin1_code":"82",
    "gn:admin2_code":"4050.0",
    "gn:admin3_code":"405063.0",
    "gn:admin4_code":"40506347.0",
    "gn:asciiname":"Hijlakar",
    "gn:country_code":"BD",
    "gn:dem":19,
    "gn:feature_class":"P",
    "gn:feature_code":"PPL",
    "gn:name":"Hijl\u0101kar",
    "gn:population":0,
    "gn:timezone":"Asia/Dhaka",
    "iso:country":"BD",
    "name:und_x_variant":[
        "Hizlakar",
        "Hijl\u0101kar"
    ],
    "wof:name":"Hijlakar",
    "wof:placetype":"locality"
},
  "geometry": {"coordinates":[89.26130000000001,23.82299],"type":"Point"}
}