{
  "type": "Feature",
  "properties": {
    "gn:admin1_code":"83",
    "gn:admin2_code":"5010",
    "gn:admin3_code":"501054.0",
    "gn:admin4_code":"50105466.0",
    "gn:asciiname":"Naihati",
    "gn:country_code":"BD",
    "gn:dem":18,
    "gn:feature_class":"P",
    "gn:feature_code":"PPL",
    "gn:name":"Naih\u0101ti",
    "gn:population":0,
    "gn:timezone":"Asia/Dhaka",
    "iso:country":"BD",
    "name:ben_x_preferred":[
        "\u09a8\u09c8\u09b9\u09be\u099f\u09bf"
    ],
    "name:bih_x_preferred":[
        "\u0928\u0948\u0939\u093e\u091f\u0940"
    ],
    "name:bpy_x_preferred":[
        "\u09a8\u09c8\u09b9\u09be\u09a4\u09bf"
    ],
    "name:ceb_x_preferred":[
        "Naih\u0101ti"
    ],
    "name:fas_x_preferred":[
        "\u0646\u06cc\u0627\u062a\u06cc"
    ],
    "name:fra_x_preferred":[
        "Naihati"
    ],
    "name:hin_x_preferred":[
        "\u0928\u0948\u0939\u093e\u091f\u0940"
    ],
    "name:ita_x_preferred":[
        "Naihati"
    ],
    "name:mlg_x_preferred":[
        "Naihati"
    ],
    "name:msa_x_preferred":[
        "Naihati"
    ],
    "name:new_x_preferred":[
        "\u0928\u0948\u0939\u0924\u0940"
    ],
    "name:ori_x_preferred":[
        "\u0b28\u0b3e\u0b07\u0b39\u0b3e\u0b24\u0b3f"
    ],
    "name:pnb_x_preferred":[
        "\u0646\u0627\u0626\u06c1\u062a\u06cc"
    ],
    "name:spa_x_preferred":[
        "Naihati"
    ],
    "name:srp_x_preferred":[
        "\u041d\u0430\u0458\u0445\u0430\u0442\u0438"
    ],
    "name:swe_x_preferred":[
        "Naihati"
    ],
    "name:szl_x_preferred":[
        "Naihati"
    ],
    "name:tgl_x_preferred":[
        "Naihati"
    ],
    "name:urd_x_preferred":[
        "\u0646\u06cc\u06c1\u0627\u0679\u06cc"
    ],
    "name:vie_x_preferred":[
        "Naihati"
    ],
    "name:war_x_preferred":[
        "Naihati"
    ],
    "name:zho_x_preferred":[
        "\u5948\u54c8\u8482"
    ],
    "wof:name":"Naihati",
    "wof:placetype":"locality"
},
  "geometry": {"coordinates":[89.30065999999999,24.86876],"type":"Point"}
}