{
  "type": "Feature",
  "properties": {
    "gn:admin1_code":"85",
    "gn:admin2_code":"1009.0",
    "gn:admin3_code":"100918.0",
    "gn:admin4_code":"10091821.0",
    "gn:asciiname":"Char Sifali",
    "gn:country_code":"BD",
    "gn:dem":8,
    "gn:feature_class":"P",
    "gn:feature_code":"PPL",
    "gn:name":"Char Sifali",
    "gn:population":0,
    "gn:timezone":"Asia/Dhaka",
    "iso:country":"BD",
    "wof:name":"Char Sifali",
    "wof:placetype":"locality"
},
  "geometry": {"coordinates":[90.62130000000001,22.67505],"type":"Point"}
}