{
  "type": "Feature",
  "properties": {
    "gn:admin1_code":"81",
    "gn:admin2_code":"3026",
    "gn:admin3_code":"302672.0",
    "gn:admin4_code":"30267200.0",
    "gn:asciiname":"Sutar Noadda",
    "gn:country_code":"BD",
    "gn:dem":14,
    "gn:feature_class":"P",
    "gn:feature_code":"PPL",
    "gn:name":"Sut\u0101r No\u0101dda",
    "gn:population":0,
    "gn:timezone":"Asia/Dhaka",
    "iso:country":"BD",
    "wof:name":"Sutar Noadda",
    "wof:placetype":"locality"
},
  "geometry": {"coordinates":[90.24977,23.85071],"type":"Point"}
}