{
  "type": "Feature",
  "properties": {
    "gn:admin1_code":"83",
    "gn:admin2_code":"5038.0",
    "gn:admin3_code":"503813.0",
    "gn:admin4_code":"50381347.0",
    "gn:asciiname":"Rukindipur",
    "gn:country_code":"BD",
    "gn:dem":24,
    "gn:feature_class":"P",
    "gn:feature_code":"PPL",
    "gn:name":"Rukindipur",
    "gn:population":0,
    "gn:timezone":"Asia/Dhaka",
    "iso:country":"BD",
    "name:fil_x_preferred":[
        "Rukindipur"
    ],
    "wof:name":"Rukindipur",
    "wof:placetype":"locality"
},
  "geometry": {"coordinates":[89.01111999999998,25.03276],"type":"Point"}
}