{
  "type": "Feature",
  "properties": {
    "gn:admin1_code":"87",
    "gn:admin2_code":"5527",
    "gn:admin3_code":"552769.0",
    "gn:admin4_code":"55276943.0",
    "gn:asciiname":"Kotal Duba",
    "gn:country_code":"BD",
    "gn:dem":35,
    "gn:feature_class":"P",
    "gn:feature_code":"PPL",
    "gn:name":"Kotal Duba",
    "gn:population":0,
    "gn:timezone":"Asia/Dhaka",
    "iso:country":"BD",
    "name:ben_x_preferred":[
        "Kotal Duba"
    ],
    "wof:name":"Kotal Duba",
    "wof:placetype":"locality"
},
  "geometry": {"coordinates":[89.03984,25.48206],"type":"Point"}
}