{
  "type": "Feature",
  "properties": {
    "gn:admin1_code":"81",
    "gn:admin2_code":"3059",
    "gn:admin3_code":"305974.0",
    "gn:admin4_code":"30597454.0",
    "gn:asciiname":"Thairgaon",
    "gn:country_code":"BD",
    "gn:dem":8,
    "gn:feature_class":"P",
    "gn:feature_code":"PPL",
    "gn:name":"Thairgaon",
    "gn:population":0,
    "gn:timezone":"Asia/Dhaka",
    "iso:country":"BD",
    "wof:name":"Thairgaon",
    "wof:placetype":"locality"
},
  "geometry": {"coordinates":[90.34916,23.56798],"type":"Point"}
}