{
  "type": "Feature",
  "properties": {
    "gn:admin1_code":"81",
    "gn:admin2_code":"3029.0",
    "gn:admin3_code":"302918.0",
    "gn:admin4_code":"30291815.0",
    "gn:asciiname":"Barkhadia",
    "gn:country_code":"BD",
    "gn:dem":11,
    "gn:feature_class":"P",
    "gn:feature_code":"PPL",
    "gn:name":"B\u0101rkh\u0101dia",
    "gn:population":0,
    "gn:timezone":"Asia/Dhaka",
    "iso:country":"BD",
    "wof:name":"Barkhadia",
    "wof:placetype":"locality"
},
  "geometry": {"coordinates":[89.69880999999999,23.39898],"type":"Point"}
}