{
  "type": "Feature",
  "properties": {
    "gn:admin1_code":"81",
    "gn:admin2_code":"3068",
    "gn:admin3_code":"306807.0",
    "gn:admin4_code":"30680711.0",
    "gn:asciiname":"Ujilaba",
    "gn:country_code":"BD",
    "gn:dem":16,
    "gn:feature_class":"P",
    "gn:feature_code":"PPL",
    "gn:name":"Ujil\u0101ba",
    "gn:population":0,
    "gn:timezone":"Asia/Dhaka",
    "iso:country":"BD",
    "wof:name":"Ujilaba",
    "wof:placetype":"locality"
},
  "geometry": {"coordinates":[90.84717000000001,24.0607],"type":"Point"}
}