{
  "type": "Feature",
  "properties": {
    "gn:admin1_code":"H",
    "gn:admin2_code":"3039",
    "gn:admin3_code":"303915.0",
    "gn:admin4_code":"30391529.0",
    "gn:asciiname":"Maulavir Char",
    "gn:country_code":"BD",
    "gn:dem":27,
    "gn:feature_class":"P",
    "gn:feature_code":"PPL",
    "gn:name":"Maulavir Char",
    "gn:population":0,
    "gn:timezone":"Asia/Dhaka",
    "iso:country":"BD",
    "name:ben_x_preferred":[
        "Maulavir Char"
    ],
    "wof:name":"Maulavir Char",
    "wof:placetype":"locality"
},
  "geometry": {"coordinates":[89.75558000000002,25.33011],"type":"Point"}
}