{
  "type": "Feature",
  "properties": {
    "gn:admin1_code":"85",
    "gn:admin2_code":"1042",
    "gn:admin3_code":"104240.0",
    "gn:admin4_code":"10424000.0",
    "gn:asciiname":"Kifaitnagar",
    "gn:country_code":"BD",
    "gn:dem":12,
    "gn:feature_class":"P",
    "gn:feature_code":"PPL",
    "gn:name":"Kif\u0101itnagar",
    "gn:population":0,
    "gn:timezone":"Asia/Dhaka",
    "iso:country":"BD",
    "wof:name":"Kifaitnagar",
    "wof:placetype":"locality"
},
  "geometry": {"coordinates":[90.18384,22.64159],"type":"Point"}
}