{
  "type": "Feature",
  "properties": {
    "gn:admin1_code":"82",
    "gn:admin2_code":"4050.0",
    "gn:admin3_code":"405039.0",
    "gn:admin4_code":"40503988.0",
    "gn:asciiname":"Char Ikuri",
    "gn:country_code":"BD",
    "gn:dem":10,
    "gn:feature_class":"P",
    "gn:feature_code":"PPL",
    "gn:name":"Char Ik\u016bri",
    "gn:population":0,
    "gn:timezone":"Asia/Dhaka",
    "iso:country":"BD",
    "name:ben_x_preferred":[
        "Char Ik\u016bri"
    ],
    "wof:name":"Char Ikuri",
    "wof:placetype":"locality"
},
  "geometry": {"coordinates":[88.70432,24.10008],"type":"Point"}
}