{
  "type": "Feature",
  "properties": {
    "gn:admin1_code":"82",
    "gn:admin2_code":"4087.0",
    "gn:admin3_code":"408747.0",
    "gn:admin4_code":"40874707.0",
    "gn:asciiname":"Chaubaria",
    "gn:country_code":"BD",
    "gn:dem":7,
    "gn:feature_class":"P",
    "gn:feature_code":"PPL",
    "gn:name":"Chaub\u0101ria",
    "gn:population":0,
    "gn:timezone":"Asia/Dhaka",
    "iso:country":"BD",
    "name:ben_x_preferred":[
        "Chaub\u0101ria"
    ],
    "wof:name":"Chaubaria",
    "wof:placetype":"locality"
},
  "geometry": {"coordinates":[89.00119000000002,22.50663],"type":"Point"}
}