{
  "type": "Feature",
  "properties": {
    "gn:admin1_code":"82",
    "gn:admin2_code":"4047",
    "gn:admin3_code":"404764.0",
    "gn:admin4_code":"40476489.0",
    "gn:asciiname":"Bethbunia",
    "gn:country_code":"BD",
    "gn:dem":5,
    "gn:feature_class":"P",
    "gn:feature_code":"PPL",
    "gn:name":"Bethbunia",
    "gn:population":0,
    "gn:timezone":"Asia/Dhaka",
    "iso:country":"BD",
    "name:und_x_variant":[
        "Betbunia",
        "Bethbunia"
    ],
    "wof:name":"Bethbunia",
    "wof:placetype":"locality"
},
  "geometry": {"coordinates":[89.39357,22.52708],"type":"Point"}
}