{
  "type": "Feature",
  "properties": {
    "gn:admin1_code":"81",
    "gn:admin2_code":"3033",
    "gn:admin3_code":"303330.0",
    "gn:admin4_code":"30333081.0",
    "gn:asciiname":"Kot Bhadum",
    "gn:country_code":"BD",
    "gn:dem":13,
    "gn:feature_class":"P",
    "gn:feature_code":"PPL",
    "gn:name":"Kot Bh\u0101dum",
    "gn:population":0,
    "gn:timezone":"Asia/Dhaka",
    "iso:country":"BD",
    "name:und_x_variant":[
        "Kot Bhadun",
        "Kot Bh\u0101dum"
    ],
    "wof:name":"Kot Bhadum",
    "wof:placetype":"locality"
},
  "geometry": {"coordinates":[90.45086999999999,23.93829],"type":"Point"}
}