{
  "type": "Feature",
  "properties": {
    "gn:admin1_code":"81",
    "gn:admin2_code":"3033.0",
    "gn:admin3_code":"303330.0",
    "gn:admin4_code":"30333047.0",
    "gn:asciiname":"Gobindabari",
    "gn:country_code":"BD",
    "gn:dem":19,
    "gn:feature_class":"P",
    "gn:feature_code":"PPL",
    "gn:name":"Gobindab\u0101ri",
    "gn:population":0,
    "gn:timezone":"Asia/Dhaka",
    "iso:country":"BD",
    "wof:name":"Gobindabari",
    "wof:placetype":"locality"
},
  "geometry": {"coordinates":[90.29029,23.99085],"type":"Point"}
}