{
  "type": "Feature",
  "properties": {
    "gn:admin1_code":"H",
    "gn:admin2_code":"3072.0",
    "gn:admin3_code":"307247.0",
    "gn:admin4_code":"30724720.0",
    "gn:asciiname":"Batta",
    "gn:country_code":"BD",
    "gn:dem":14,
    "gn:feature_class":"P",
    "gn:feature_code":"PPL",
    "gn:name":"B\u0101tta",
    "gn:population":0,
    "gn:timezone":"Asia/Dhaka",
    "iso:country":"BD",
    "name:spa_x_preferred":[
        "Batta"
    ],
    "wof:name":"Batta",
    "wof:placetype":"locality"
},
  "geometry": {"coordinates":[90.84909,24.63689],"type":"Point"}
}