{
  "type": "Feature",
  "properties": {
    "gn:admin1_code":"83",
    "gn:admin2_code":"5081.0",
    "gn:admin3_code":"508134.0",
    "gn:admin4_code":"50813466.0",
    "gn:asciiname":"Chokarpani",
    "gn:country_code":"BD",
    "gn:dem":40,
    "gn:feature_class":"P",
    "gn:feature_code":"PPL",
    "gn:name":"Chok\u0101rp\u0101ni",
    "gn:population":0,
    "gn:timezone":"Asia/Dhaka",
    "iso:country":"BD",
    "name:ben_x_preferred":[
        "Chok\u0101rp\u0101ni"
    ],
    "wof:name":"Chokarpani",
    "wof:placetype":"locality"
},
  "geometry": {"coordinates":[88.35542,24.59151],"type":"Point"}
}