{
  "type": "Feature",
  "properties": {
    "gn:admin1_code":"87",
    "gn:admin2_code":"5549",
    "gn:admin3_code":"554979.0",
    "gn:admin4_code":"55497911.0",
    "gn:asciiname":"Tangaripara",
    "gn:country_code":"BD",
    "gn:dem":30,
    "gn:feature_class":"P",
    "gn:feature_code":"PPL",
    "gn:name":"T\u0101ng\u0101ripara",
    "gn:population":0,
    "gn:timezone":"Asia/Dhaka",
    "iso:country":"BD",
    "name:ben_x_preferred":[
        "T\u0101ng\u0101ripara"
    ],
    "wof:name":"Tangaripara",
    "wof:placetype":"locality"
},
  "geometry": {"coordinates":[89.84016,25.62661],"type":"Point"}
}