{
  "type": "Feature",
  "properties": {
    "gn:admin1_code":"85",
    "gn:admin2_code":"1078.0",
    "gn:admin3_code":"107866.0",
    "gn:admin4_code":"10786671.0",
    "gn:asciiname":"Lashkarpur",
    "gn:country_code":"BD",
    "gn:dem":11,
    "gn:feature_class":"P",
    "gn:feature_code":"PPL",
    "gn:name":"Lashkarpur",
    "gn:population":0,
    "gn:timezone":"Asia/Dhaka",
    "iso:country":"BD",
    "name:ben_x_preferred":[
        "Lashkarpur"
    ],
    "wof:name":"Lashkarpur",
    "wof:placetype":"locality"
},
  "geometry": {"coordinates":[90.15312,21.92142],"type":"Point"}
}