{
  "type": "Feature",
  "properties": {
    "gn:admin1_code":"H",
    "gn:admin2_code":"3089",
    "gn:admin3_code":"308937.0",
    "gn:admin4_code":"30893725.0",
    "gn:asciiname":"Bangla Kanda",
    "gn:country_code":"BD",
    "gn:dem":25,
    "gn:feature_class":"P",
    "gn:feature_code":"PPL",
    "gn:name":"Bangla Kanda",
    "gn:population":0,
    "gn:timezone":"Asia/Dhaka",
    "iso:country":"BD",
    "name:ben_x_preferred":[
        "Bangla Kanda"
    ],
    "wof:name":"Bangla Kanda",
    "wof:placetype":"locality"
},
  "geometry": {"coordinates":[90.00632,25.14397],"type":"Point"}
}