{
  "type": "Feature",
  "properties": {
    "gn:admin1_code":"81",
    "gn:admin2_code":"3054.0",
    "gn:admin3_code":"305440.0",
    "gn:admin4_code":"30544069.0",
    "gn:asciiname":"Dadpur",
    "gn:country_code":"BD",
    "gn:dem":11,
    "gn:feature_class":"P",
    "gn:feature_code":"PPL",
    "gn:name":"D\u0101dpur",
    "gn:population":0,
    "gn:timezone":"Asia/Dhaka",
    "iso:country":"BD",
    "wof:name":"Dadpur",
    "wof:placetype":"locality"
},
  "geometry": {"coordinates":[90.30828,23.1453],"type":"Point"}
}