{
  "type": "Feature",
  "properties": {
    "gn:admin1_code":"84",
    "gn:admin2_code":"2013",
    "gn:admin3_code":"201358.0",
    "gn:admin4_code":"20135823.0",
    "gn:asciiname":"Kalamian",
    "gn:country_code":"BD",
    "gn:dem":11,
    "gn:feature_class":"P",
    "gn:feature_code":"PPL",
    "gn:name":"Kal\u0101mi\u0101n",
    "gn:population":0,
    "gn:timezone":"Asia/Dhaka",
    "iso:country":"BD",
    "name:und_x_variant":[
        "Kalamia",
        "Kal\u0101mi\u0101n"
    ],
    "wof:name":"Kalamian",
    "wof:placetype":"locality"
},
  "geometry": {"coordinates":[90.94828,23.31368],"type":"Point"}
}