{
  "type": "Feature",
  "properties": {
    "gn:admin1_code":"81",
    "gn:admin2_code":"3029.0",
    "gn:admin3_code":"302947.0",
    "gn:admin4_code":"30294715.0",
    "gn:asciiname":"Dhuldi Gobindapur",
    "gn:country_code":"BD",
    "gn:dem":13,
    "gn:feature_class":"P",
    "gn:feature_code":"PPL",
    "gn:name":"Dhuldi Gobindapur",
    "gn:population":0,
    "gn:timezone":"Asia/Dhaka",
    "iso:country":"BD",
    "wof:name":"Dhuldi Gobindapur",
    "wof:placetype":"locality"
},
  "geometry": {"coordinates":[89.80861999999998,23.61743],"type":"Point"}
}