{
  "type": "Feature",
  "properties": {
    "gn:admin1_code":"82",
    "gn:admin2_code":"4041.0",
    "gn:admin3_code":"404111.0",
    "gn:admin4_code":"40411134.0",
    "gn:asciiname":"Dakshin Sagar",
    "gn:country_code":"BD",
    "gn:dem":16,
    "gn:feature_class":"P",
    "gn:feature_code":"PPL",
    "gn:name":"Dakshin S\u0101gar",
    "gn:population":0,
    "gn:timezone":"Asia/Dhaka",
    "iso:country":"BD",
    "name:ben_x_preferred":[
        "Dakshin S\u0101gar"
    ],
    "wof:name":"Dakshin Sagar",
    "wof:placetype":"locality"
},
  "geometry": {"coordinates":[89.09269,23.27602000000001],"type":"Point"}
}