{
  "type": "Feature",
  "properties": {
    "gn:admin1_code":"83",
    "gn:admin2_code":"5038.0",
    "gn:admin3_code":"503847.0",
    "gn:admin4_code":"50384785.0",
    "gn:asciiname":"Par Batto",
    "gn:country_code":"BD",
    "gn:dem":28,
    "gn:feature_class":"P",
    "gn:feature_code":"PPL",
    "gn:name":"P\u0101r B\u0101tto",
    "gn:population":0,
    "gn:timezone":"Asia/Dhaka",
    "iso:country":"BD",
    "name:ben_x_preferred":[
        "P\u0101r B\u0101tto"
    ],
    "wof:name":"Par Batto",
    "wof:placetype":"locality"
},
  "geometry": {"coordinates":[89.03166999999998,25.15725],"type":"Point"}
}