{
  "type": "Feature",
  "properties": {
    "gn:admin1_code":"82",
    "gn:admin2_code":"4087",
    "gn:admin3_code":"408782.0",
    "gn:admin4_code":"40878240.0",
    "gn:asciiname":"Srirampur",
    "gn:country_code":"BD",
    "gn:dem":8,
    "gn:feature_class":"P",
    "gn:feature_code":"PPL",
    "gn:name":"Srir\u0101mpur",
    "gn:population":0,
    "gn:timezone":"Asia/Dhaka",
    "iso:country":"BD",
    "name:ben_x_preferred":[
        "Srir\u0101mpur"
    ],
    "wof:name":"Srirampur",
    "wof:placetype":"locality"
},
  "geometry": {"coordinates":[88.98191,22.64974],"type":"Point"}
}