{
  "type": "Feature",
  "properties": {
    "gn:admin1_code":"82",
    "gn:admin2_code":"4047.0",
    "gn:admin3_code":"404740.0",
    "gn:admin4_code":"40474017.0",
    "gn:asciiname":"Paschim Ambaria",
    "gn:country_code":"BD",
    "gn:dem":6,
    "gn:feature_class":"P",
    "gn:feature_code":"PPL",
    "gn:name":"Paschim \u0100mb\u0101ria",
    "gn:population":0,
    "gn:timezone":"Asia/Dhaka",
    "iso:country":"BD",
    "name:ben_x_preferred":[
        "Paschim \u0100mb\u0101ria"
    ],
    "wof:name":"Paschim Ambaria",
    "wof:placetype":"locality"
},
  "geometry": {"coordinates":[89.57011,22.95376],"type":"Point"}
}