{
  "type": "Feature",
  "properties": {
    "gn:admin1_code":"81",
    "gn:admin2_code":"3035",
    "gn:admin3_code":"303558.0",
    "gn:admin4_code":"30355805.0",
    "gn:asciiname":"Tungibari",
    "gn:country_code":"BD",
    "gn:dem":9,
    "gn:feature_class":"P",
    "gn:feature_code":"PPL",
    "gn:name":"Tungib\u0101ri",
    "gn:population":0,
    "gn:timezone":"Asia/Dhaka",
    "iso:country":"BD",
    "wof:name":"Tungibari",
    "wof:placetype":"locality"
},
  "geometry": {"coordinates":[89.91341,23.28137000000001],"type":"Point"}
}