{
  "type": "Feature",
  "properties": {
    "gn:admin1_code":"87",
    "gn:admin2_code":"5594",
    "gn:admin3_code":"559451.0",
    "gn:admin4_code":"55945113.0",
    "gn:asciiname":"Jamun",
    "gn:country_code":"BD",
    "gn:dem":50,
    "gn:feature_class":"P",
    "gn:feature_code":"PPL",
    "gn:name":"J\u0101mun",
    "gn:population":0,
    "gn:timezone":"Asia/Dhaka",
    "iso:country":"BD",
    "name:ben_x_preferred":[
        "J\u0101mun"
    ],
    "wof:name":"Jamun",
    "wof:placetype":"locality"
},
  "geometry": {"coordinates":[88.15279,25.92969],"type":"Point"}
}