{
  "type": "Feature",
  "properties": {
    "gn:admin1_code":"87",
    "gn:admin2_code":"5549",
    "gn:admin3_code":"554952.0",
    "gn:admin4_code":"55495285.0",
    "gn:asciiname":"Noebas",
    "gn:country_code":"BD",
    "gn:dem":31,
    "gn:feature_class":"P",
    "gn:feature_code":"PPL",
    "gn:name":"Noeb\u0101s",
    "gn:population":0,
    "gn:timezone":"Asia/Dhaka",
    "iso:country":"BD",
    "name:ben_x_preferred":[
        "Noeb\u0101s"
    ],
    "wof:name":"Noebas",
    "wof:placetype":"locality"
},
  "geometry": {"coordinates":[89.68906,25.80378],"type":"Point"}
}