{
  "type": "Feature",
  "properties": {
    "gn:admin1_code":"83",
    "gn:admin2_code":"5088",
    "gn:admin3_code":"508811.0",
    "gn:admin4_code":"50881127.0",
    "gn:asciiname":"Belkuchi",
    "gn:country_code":"BD",
    "gn:dem":19,
    "gn:feature_class":"P",
    "gn:feature_code":"PPL",
    "gn:name":"Belkuchi",
    "gn:population":0,
    "gn:timezone":"Asia/Dhaka",
    "iso:country":"BD",
    "name:und_x_variant":[
        "Belkoochee",
        "Belkuchi"
    ],
    "wof:name":"Belkuchi",
    "wof:placetype":"locality"
},
  "geometry": {"coordinates":[89.70406,24.29808],"type":"Point"}
}