{
  "type": "Feature",
  "properties": {
    "gn:admin1_code":"87",
    "gn:admin2_code":"5527.0",
    "gn:admin3_code":"552730.0",
    "gn:admin4_code":"55273071.0",
    "gn:asciiname":"Saraswarpur",
    "gn:country_code":"BD",
    "gn:dem":35,
    "gn:feature_class":"P",
    "gn:feature_code":"PPL",
    "gn:name":"S\u0101raswarpur",
    "gn:population":0,
    "gn:timezone":"Asia/Dhaka",
    "iso:country":"BD",
    "name:ben_x_preferred":[
        "S\u0101raswarpur"
    ],
    "wof:name":"Saraswarpur",
    "wof:placetype":"locality"
},
  "geometry": {"coordinates":[88.7731,25.52652],"type":"Point"}
}