{
  "type": "Feature",
  "properties": {
    "gn:admin1_code":"85",
    "gn:admin2_code":"1004.0",
    "gn:admin3_code":"100485.0",
    "gn:admin4_code":"10048583.0",
    "gn:asciiname":"Raynanpur",
    "gn:country_code":"BD",
    "gn:dem":9,
    "gn:feature_class":"P",
    "gn:feature_code":"PPL",
    "gn:name":"Raynanpur",
    "gn:population":0,
    "gn:timezone":"Asia/Dhaka",
    "iso:country":"BD",
    "name:ben_x_preferred":[
        "Raynanpur"
    ],
    "wof:name":"Raynanpur",
    "wof:placetype":"locality"
},
  "geometry": {"coordinates":[90.00516999999998,22.18955],"type":"Point"}
}