{
  "type": "Feature",
  "properties": {
    "gn:admin1_code":"84",
    "gn:admin2_code":"2015.0",
    "gn:admin3_code":"201574.0",
    "gn:admin4_code":"20157437.0",
    "gn:asciiname":"Dalainagar",
    "gn:country_code":"BD",
    "gn:dem":8,
    "gn:feature_class":"P",
    "gn:feature_code":"PPL",
    "gn:name":"Dal\u0101inagar",
    "gn:population":0,
    "gn:timezone":"Asia/Dhaka",
    "iso:country":"BD",
    "name:ben_x_preferred":[
        "Dal\u0101inagar"
    ],
    "wof:name":"Dalainagar",
    "wof:placetype":"locality"
},
  "geometry": {"coordinates":[91.86232,22.52926],"type":"Point"}
}