{
  "type": "Feature",
  "properties": {
    "gn:admin1_code":"83",
    "gn:admin2_code":"5076.0",
    "gn:admin3_code":"507633.0",
    "gn:admin4_code":"50763384.0",
    "gn:asciiname":"Bri Dapania",
    "gn:country_code":"BD",
    "gn:dem":17,
    "gn:feature_class":"P",
    "gn:feature_code":"PPL",
    "gn:name":"Bri D\u0101p\u0101nia",
    "gn:population":0,
    "gn:timezone":"Asia/Dhaka",
    "iso:country":"BD",
    "wof:name":"Bri Dapania",
    "wof:placetype":"locality"
},
  "geometry": {"coordinates":[89.50159000000002,24.21518],"type":"Point"}
}