{
  "type": "Feature",
  "properties": {
    "gn:admin1_code":"83",
    "gn:admin2_code":"5064",
    "gn:admin3_code":"506460.0",
    "gn:admin4_code":"50646007.0",
    "gn:asciiname":"Komaigari",
    "gn:country_code":"BD",
    "gn:dem":18,
    "gn:feature_class":"P",
    "gn:feature_code":"PPL",
    "gn:name":"Komaig\u0101ri",
    "gn:population":0,
    "gn:timezone":"Asia/Dhaka",
    "iso:country":"BD",
    "name:ben_x_preferred":[
        "Komaig\u0101ri"
    ],
    "name:ben_x_variant":[
        "Kam\u0101ig\u0101ri"
    ],
    "wof:name":"Komaigari",
    "wof:placetype":"locality"
},
  "geometry": {"coordinates":[88.92683000000002,24.83294],"type":"Point"}
}