{
  "type": "Feature",
  "properties": {
    "gn:admin1_code":"H",
    "gn:admin2_code":"3061",
    "gn:admin3_code":"306172.0",
    "gn:admin4_code":"30617294.0",
    "gn:asciiname":"Udang",
    "gn:country_code":"BD",
    "gn:dem":13,
    "gn:feature_class":"P",
    "gn:feature_code":"PPL",
    "gn:name":"Udang",
    "gn:population":0,
    "gn:timezone":"Asia/Dhaka",
    "iso:country":"BD",
    "wof:name":"Udang",
    "wof:placetype":"locality"
},
  "geometry": {"coordinates":[90.70179,24.51842000000001],"type":"Point"}
}