{
  "type": "Feature",
  "properties": {
    "gn:admin1_code":"82",
    "gn:admin2_code":"4050",
    "gn:admin3_code":"405071.0",
    "gn:admin4_code":"40507177.0",
    "gn:asciiname":"Ramdia",
    "gn:country_code":"BD",
    "gn:dem":15,
    "gn:feature_class":"P",
    "gn:feature_code":"PPL",
    "gn:name":"Ramdia",
    "gn:population":0,
    "gn:timezone":"Asia/Dhaka",
    "iso:country":"BD",
    "name:ben_x_preferred":[
        "Ramdia"
    ],
    "wof:name":"Ramdia",
    "wof:placetype":"locality"
},
  "geometry": {"coordinates":[89.20248000000002,23.7843],"type":"Point"}
}