{
  "type": "Feature",
  "properties": {
    "gn:admin1_code":"84",
    "gn:admin2_code":"2084.0",
    "gn:admin3_code":"208425.0",
    "gn:admin4_code":"20842557.0",
    "gn:asciiname":"Rakaipara",
    "gn:country_code":"BD",
    "gn:dem":41,
    "gn:feature_class":"P",
    "gn:feature_code":"PPL",
    "gn:name":"Rak\u0101ip\u0101ra",
    "gn:population":0,
    "gn:timezone":"Asia/Dhaka",
    "iso:country":"BD",
    "name:ben_x_preferred":[
        "Rak\u0101ip\u0101ra"
    ],
    "wof:name":"Rakaipara",
    "wof:placetype":"locality"
},
  "geometry": {"coordinates":[92.10374,22.59926],"type":"Point"}
}