{
  "type": "Feature",
  "properties": {
    "gn:admin1_code":"82",
    "gn:admin2_code":"4050",
    "gn:admin3_code":"405079.0",
    "gn:admin4_code":"40507975.0",
    "gn:asciiname":"Nagar Mohamadpur",
    "gn:country_code":"BD",
    "gn:dem":17,
    "gn:feature_class":"P",
    "gn:feature_code":"PPL",
    "gn:name":"Nagar Mohamadpur",
    "gn:population":0,
    "gn:timezone":"Asia/Dhaka",
    "iso:country":"BD",
    "name:ben_x_preferred":[
        "Nagar Mohamadpur"
    ],
    "name:ben_x_variant":[
        "Nagar Muhammadpur"
    ],
    "name:und_x_variant":[
        "Nagar Mahammadpur"
    ],
    "wof:name":"Nagar Mohamadpur",
    "wof:placetype":"locality"
},
  "geometry": {"coordinates":[89.14093000000003,23.88039],"type":"Point"}
}