{
  "type": "Feature",
  "properties": {
    "gn:admin1_code":"81",
    "gn:admin2_code":"3033",
    "gn:admin3_code":"303330.0",
    "gn:admin4_code":"30333081.0",
    "gn:asciiname":"Sorul",
    "gn:country_code":"BD",
    "gn:dem":14,
    "gn:feature_class":"P",
    "gn:feature_code":"PPL",
    "gn:name":"Sorul",
    "gn:population":0,
    "gn:timezone":"Asia/Dhaka",
    "iso:country":"BD",
    "wof:name":"Sorul",
    "wof:placetype":"locality"
},
  "geometry": {"coordinates":[90.47429,23.95478],"type":"Point"}
}