{
  "type": "Feature",
  "properties": {
    "gn:admin1_code":"81",
    "gn:admin2_code":"3093",
    "gn:admin3_code":"309328.0",
    "gn:admin4_code":"30932869.0",
    "gn:asciiname":"Pungli",
    "gn:country_code":"BD",
    "gn:dem":17,
    "gn:feature_class":"P",
    "gn:feature_code":"PPL",
    "gn:name":"Pungli",
    "gn:population":0,
    "gn:timezone":"Asia/Dhaka",
    "iso:country":"BD",
    "wof:name":"Pungli",
    "wof:placetype":"locality"
},
  "geometry": {"coordinates":[89.94023,24.48285],"type":"Point"}
}