{
  "type": "Feature",
  "properties": {
    "gn:admin1_code":"81",
    "gn:admin2_code":"3035.0",
    "gn:admin3_code":"303551.0",
    "gn:admin4_code":"30355107.0",
    "gn:asciiname":"Gachapara",
    "gn:country_code":"BD",
    "gn:dem":7,
    "gn:feature_class":"P",
    "gn:feature_code":"PPL",
    "gn:name":"Gach\u0101p\u0101ra",
    "gn:population":0,
    "gn:timezone":"Asia/Dhaka",
    "iso:country":"BD",
    "wof:name":"Gachapara",
    "wof:placetype":"locality"
},
  "geometry": {"coordinates":[90.03579000000001,22.98982],"type":"Point"}
}