{
  "type": "Feature",
  "properties": {
    "gn:admin1_code":"87",
    "gn:admin2_code":"5585.0",
    "gn:admin3_code":"558573.0",
    "gn:admin4_code":"55857385.0",
    "gn:asciiname":"Bholanathpur",
    "gn:country_code":"BD",
    "gn:dem":29,
    "gn:feature_class":"P",
    "gn:feature_code":"PPL",
    "gn:name":"Bhol\u0101n\u0101thpur",
    "gn:population":0,
    "gn:timezone":"Asia/Dhaka",
    "iso:country":"BD",
    "name:ben_x_preferred":[
        "Bhol\u0101n\u0101thpur"
    ],
    "wof:name":"Bholanathpur",
    "wof:placetype":"locality"
},
  "geometry": {"coordinates":[89.4937,25.64991],"type":"Point"}
}