{
  "type": "Feature",
  "properties": {
    "gn:admin1_code":"H",
    "gn:admin2_code":"3072",
    "gn:admin3_code":"307209.0",
    "gn:admin4_code":"30720947.0",
    "gn:asciiname":"Putkia",
    "gn:country_code":"BD",
    "gn:dem":8,
    "gn:feature_class":"P",
    "gn:feature_code":"PPL",
    "gn:name":"Putkia",
    "gn:population":0,
    "gn:timezone":"Asia/Dhaka",
    "iso:country":"BD",
    "wof:name":"Putkia",
    "wof:placetype":"locality"
},
  "geometry": {"coordinates":[90.9278,24.97275],"type":"Point"}
}