{
  "type": "Feature",
  "properties": {
    "gn:admin1_code":"86",
    "gn:admin2_code":"6091",
    "gn:admin3_code":"609159.0",
    "gn:admin4_code":"60915970.0",
    "gn:asciiname":"Jaipur",
    "gn:country_code":"BD",
    "gn:dem":23,
    "gn:feature_class":"P",
    "gn:feature_code":"PPL",
    "gn:name":"Jaipur",
    "gn:population":0,
    "gn:timezone":"Asia/Dhaka",
    "iso:country":"BD",
    "name:und_x_variant":[
        "Joypur",
        "Jaipur"
    ],
    "wof:name":"Jaipur",
    "wof:placetype":"locality"
},
  "geometry": {"coordinates":[92.30052999999999,25.01294],"type":"Point"}
}