{
  "type": "Feature",
  "properties": {
    "gn:admin1_code":"81",
    "gn:admin2_code":"3056",
    "gn:admin3_code":"305646.0",
    "gn:admin4_code":"30564615.0",
    "gn:asciiname":"Kaimtara",
    "gn:country_code":"BD",
    "gn:dem":4,
    "gn:feature_class":"P",
    "gn:feature_code":"PPL",
    "gn:name":"K\u0101imt\u0101ra",
    "gn:population":0,
    "gn:timezone":"Asia/Dhaka",
    "iso:country":"BD",
    "wof:name":"Kaimtara",
    "wof:placetype":"locality"
},
  "geometry": {"coordinates":[90.03333000000001,23.76667],"type":"Point"}
}