{
  "type": "Feature",
  "properties": {
    "gn:admin1_code":"82",
    "gn:admin2_code":"4044.0",
    "gn:admin3_code":"404419.0",
    "gn:admin4_code":"40441926.0",
    "gn:asciiname":"Ramchandrapur",
    "gn:country_code":"BD",
    "gn:dem":15,
    "gn:feature_class":"P",
    "gn:feature_code":"PPL",
    "gn:name":"R\u0101mchandrapur",
    "gn:population":0,
    "gn:timezone":"Asia/Dhaka",
    "iso:country":"BD",
    "name:ben_x_preferred":[
        "R\u0101mchandrapur"
    ],
    "wof:name":"Ramchandrapur",
    "wof:placetype":"locality"
},
  "geometry": {"coordinates":[89.07366999999998,23.5433],"type":"Point"}
}