{
  "type": "Feature",
  "properties": {
    "gn:admin1_code":"85",
    "gn:admin2_code":"1004.0",
    "gn:admin3_code":"100409.0",
    "gn:admin4_code":"10040907.0",
    "gn:asciiname":"Chalabhanga",
    "gn:country_code":"BD",
    "gn:dem":8,
    "gn:feature_class":"P",
    "gn:feature_code":"PPL",
    "gn:name":"Chalabhanga",
    "gn:population":0,
    "gn:timezone":"Asia/Dhaka",
    "iso:country":"BD",
    "name:ben_x_preferred":[
        "Chalabhanga"
    ],
    "wof:name":"Chalabhanga",
    "wof:placetype":"locality"
},
  "geometry": {"coordinates":[90.24027,22.087],"type":"Point"}
}