{
  "type": "Feature",
  "properties": {
    "gn:admin1_code":"83",
    "gn:admin2_code":"5010",
    "gn:admin3_code":"501033.0",
    "gn:admin4_code":"50103327.0",
    "gn:asciiname":"Sanjaipur",
    "gn:country_code":"BD",
    "gn:dem":22,
    "gn:feature_class":"P",
    "gn:feature_code":"PPL",
    "gn:name":"Sanjaipur",
    "gn:population":0,
    "gn:timezone":"Asia/Dhaka",
    "iso:country":"BD",
    "name:und_x_variant":[
        "Sanjaypur",
        "Sanjaipur"
    ],
    "wof:name":"Sanjaipur",
    "wof:placetype":"locality"
},
  "geometry": {"coordinates":[89.1904,24.86412],"type":"Point"}
}