{
  "type": "Feature",
  "properties": {
    "gn:admin1_code":"87",
    "gn:admin2_code":"5527.0",
    "gn:admin3_code":"552769.0",
    "gn:admin4_code":"55276951.0",
    "gn:asciiname":"Shimulbati",
    "gn:country_code":"BD",
    "gn:dem":36,
    "gn:feature_class":"P",
    "gn:feature_code":"PPL",
    "gn:name":"Shimulb\u0101ti",
    "gn:population":0,
    "gn:timezone":"Asia/Dhaka",
    "iso:country":"BD",
    "name:ben_x_preferred":[
        "Shimulb\u0101ti"
    ],
    "wof:name":"Shimulbati",
    "wof:placetype":"locality"
},
  "geometry": {"coordinates":[88.99462,25.53151],"type":"Point"}
}