{
  "type": "Feature",
  "properties": {
    "gn:admin1_code":"H",
    "gn:admin2_code":"3061",
    "gn:admin3_code":"306152.0",
    "gn:admin4_code":"30615267.0",
    "gn:asciiname":"Kismat",
    "gn:country_code":"BD",
    "gn:dem":19,
    "gn:feature_class":"P",
    "gn:feature_code":"PPL",
    "gn:name":"Kismat",
    "gn:population":0,
    "gn:timezone":"Asia/Dhaka",
    "iso:country":"BD",
    "name:hin_x_preferred":[
        "\u0915\u093f\u0938\u094d\u092e\u0924"
    ],
    "wof:name":"Kismat",
    "wof:placetype":"locality"
},
  "geometry": {"coordinates":[90.33848999999999,24.78964],"type":"Point"}
}