{
  "type": "Feature",
  "properties": {
    "gn:admin1_code":"87",
    "gn:admin2_code":"5532",
    "gn:admin3_code":"553267.0",
    "gn:admin4_code":"55326766.0",
    "gn:asciiname":"Nakkato Kumargari",
    "gn:country_code":"BD",
    "gn:dem":26,
    "gn:feature_class":"P",
    "gn:feature_code":"PPL",
    "gn:name":"Nakkato Kum\u0101rgari",
    "gn:population":0,
    "gn:timezone":"Asia/Dhaka",
    "iso:country":"BD",
    "name:ben_x_preferred":[
        "Nakkato Kum\u0101rgari"
    ],
    "wof:name":"Nakkato Kumargari",
    "wof:placetype":"locality"
},
  "geometry": {"coordinates":[89.47669999999999,25.24594],"type":"Point"}
}