{
  "type": "Feature",
  "properties": {
    "gn:admin1_code":"84",
    "gn:admin2_code":"2022.0",
    "gn:admin3_code":"202266.0",
    "gn:admin4_code":"20226685.0",
    "gn:asciiname":"Dakhin Mithachari",
    "gn:country_code":"BD",
    "gn:dem":8,
    "gn:feature_class":"P",
    "gn:feature_code":"PPL",
    "gn:name":"Dakhin Mith\u0101chari",
    "gn:population":0,
    "gn:timezone":"Asia/Dhaka",
    "iso:country":"BD",
    "name:ben_x_preferred":[
        "Dakhin Mith\u0101chari"
    ],
    "wof:name":"Dakhin Mithachari",
    "wof:placetype":"locality"
},
  "geometry": {"coordinates":[92.05029,21.41108],"type":"Point"}
}