{
  "type": "Feature",
  "properties": {
    "gn:admin1_code":"85",
    "gn:admin2_code":"1006.0",
    "gn:admin3_code":"100607.0",
    "gn:admin4_code":"10060754.0",
    "gn:asciiname":"Baragharia",
    "gn:country_code":"BD",
    "gn:dem":7,
    "gn:feature_class":"P",
    "gn:feature_code":"PPL",
    "gn:name":"Bar\u0101gharia",
    "gn:population":0,
    "gn:timezone":"Asia/Dhaka",
    "iso:country":"BD",
    "name:und_x_variant":[
        "Bar\u0101gharia"
    ],
    "wof:name":"Baragharia",
    "wof:placetype":"locality"
},
  "geometry": {"coordinates":[90.40165,22.559],"type":"Point"}
}