{
  "type": "Feature",
  "properties": {
    "gn:admin1_code":"83",
    "gn:admin2_code":"5069.0",
    "gn:admin3_code":"506963.0",
    "gn:admin4_code":"50696300.0",
    "gn:asciiname":"Baragachha",
    "gn:country_code":"BD",
    "gn:dem":20,
    "gn:feature_class":"P",
    "gn:feature_code":"PPL",
    "gn:name":"Barag\u0101chha",
    "gn:population":0,
    "gn:timezone":"Asia/Dhaka",
    "iso:country":"BD",
    "name:ben_x_preferred":[
        "Barag\u0101chha"
    ],
    "name:ben_x_variant":[
        "Barg\u0101chha"
    ],
    "wof:name":"Baragachha",
    "wof:placetype":"locality"
},
  "geometry": {"coordinates":[88.97733000000002,24.41555],"type":"Point"}
}