{
  "type": "Feature",
  "properties": {
    "gn:admin1_code":"81",
    "gn:admin2_code":"3056.0",
    "gn:admin3_code":"305682.0",
    "gn:admin4_code":"30568294.0",
    "gn:asciiname":"Char Dighalia",
    "gn:country_code":"BD",
    "gn:dem":15,
    "gn:feature_class":"P",
    "gn:feature_code":"PPL",
    "gn:name":"Char Dighalia",
    "gn:population":0,
    "gn:timezone":"Asia/Dhaka",
    "iso:country":"BD",
    "wof:name":"Char Dighalia",
    "wof:placetype":"locality"
},
  "geometry": {"coordinates":[90.11713,23.8469],"type":"Point"}
}