{
  "type": "Feature",
  "properties": {
    "gn:admin1_code":"83",
    "gn:admin2_code":"5064.0",
    "gn:admin3_code":"506475.0",
    "gn:admin4_code":"50647508.0",
    "gn:asciiname":"Bad Ayapur",
    "gn:country_code":"BD",
    "gn:dem":25,
    "gn:feature_class":"P",
    "gn:feature_code":"PPL",
    "gn:name":"B\u0101d \u0100y\u0101pur",
    "gn:population":0,
    "gn:timezone":"Asia/Dhaka",
    "iso:country":"BD",
    "name:ben_x_preferred":[
        "B\u0101d \u0100y\u0101pur"
    ],
    "name:ben_x_variant":[
        "\u0100y\u0101pur"
    ],
    "wof:name":"Bad Ayapur",
    "wof:placetype":"locality"
},
  "geometry": {"coordinates":[88.64601999999999,25.04817],"type":"Point"}
}