{
  "type": "Feature",
  "properties": {
    "gn:admin1_code":"82",
    "gn:admin2_code":"4041.0",
    "gn:admin3_code":"404104.0",
    "gn:admin4_code":"40410421.0",
    "gn:asciiname":"Sibanandapur",
    "gn:country_code":"BD",
    "gn:dem":12,
    "gn:feature_class":"P",
    "gn:feature_code":"PPL",
    "gn:name":"Sibanandapur",
    "gn:population":0,
    "gn:timezone":"Asia/Dhaka",
    "iso:country":"BD",
    "name:ben_x_preferred":[
        "Sibanandapur"
    ],
    "wof:name":"Sibanandapur",
    "wof:placetype":"locality"
},
  "geometry": {"coordinates":[89.37402,23.09005],"type":"Point"}
}