{
  "type": "Feature",
  "properties": {
    "gn:admin1_code":"87",
    "gn:admin2_code":"5549",
    "gn:admin3_code":"554994.0",
    "gn:admin4_code":"55499489.0",
    "gn:asciiname":"Hayatkhan",
    "gn:country_code":"BD",
    "gn:dem":31,
    "gn:feature_class":"P",
    "gn:feature_code":"PPL",
    "gn:name":"H\u0101y\u0101tkh\u0101n",
    "gn:population":0,
    "gn:timezone":"Asia/Dhaka",
    "iso:country":"BD",
    "name:ben_x_preferred":[
        "H\u0101y\u0101tkh\u0101n"
    ],
    "wof:name":"Hayatkhan",
    "wof:placetype":"locality"
},
  "geometry": {"coordinates":[89.60899999999999,25.67277],"type":"Point"}
}