{
  "type": "Feature",
  "properties": {
    "gn:admin1_code":"82",
    "gn:asciiname":"Kalichar",
    "gn:country_code":"BD",
    "gn:dem":9,
    "gn:feature_class":"P",
    "gn:feature_code":"PPL",
    "gn:name":"Kalichar",
    "gn:population":0,
    "gn:timezone":"Asia/Dhaka",
    "iso:country":"BD",
    "name:ben_x_preferred":[
        "Kalichar"
    ],
    "wof:name":"Kalichar",
    "wof:placetype":"locality"
},
  "geometry": {"coordinates":[90.28151,22.37748],"type":"Point"}
}