{
  "type": "Feature",
  "properties": {
    "gn:admin1_code":"87",
    "gn:admin2_code":"5527.0",
    "gn:admin3_code":"552730.0",
    "gn:admin4_code":"55273023.0",
    "gn:asciiname":"Amarpur",
    "gn:country_code":"BD",
    "gn:dem":40,
    "gn:feature_class":"P",
    "gn:feature_code":"PPL",
    "gn:name":"Amarpur",
    "gn:population":0,
    "gn:timezone":"Asia/Dhaka",
    "iso:country":"BD",
    "name:ben_x_preferred":[
        "Amarpur"
    ],
    "name:ceb_x_preferred":[
        "Amarpur"
    ],
    "name:fra_x_preferred":[
        "Amarpur"
    ],
    "name:new_x_preferred":[
        "\u0905\u092e\u0930\u092a\u0941\u0930 \u0917\u093e\u0935\u093f\u0938"
    ],
    "name:nld_x_preferred":[
        "Amarpur"
    ],
    "name:pol_x_preferred":[
        "Amarpur"
    ],
    "name:swe_x_preferred":[
        "Amarpur"
    ],
    "wof:name":"Amarpur",
    "wof:placetype":"locality"
},
  "geometry": {"coordinates":[88.77943,25.63784],"type":"Point"}
}