{
  "type": "Feature",
  "properties": {
    "gn:admin1_code":"83",
    "gn:admin2_code":"5081.0",
    "gn:admin3_code":"508182.0",
    "gn:admin4_code":"50818267.0",
    "gn:asciiname":"Joaddarpara",
    "gn:country_code":"BD",
    "gn:dem":19,
    "gn:feature_class":"P",
    "gn:feature_code":"PPL",
    "gn:name":"Joadd\u0101rp\u0101ra",
    "gn:population":0,
    "gn:timezone":"Asia/Dhaka",
    "iso:country":"BD",
    "name:ben_x_preferred":[
        "Joadd\u0101rp\u0101ra"
    ],
    "wof:name":"Joaddarpara",
    "wof:placetype":"locality"
},
  "geometry": {"coordinates":[88.80062,24.3674],"type":"Point"}
}