{
  "type": "Feature",
  "properties": {
    "gn:admin1_code":"83",
    "gn:admin2_code":"5010",
    "gn:admin3_code":"501094.0",
    "gn:admin4_code":"50109494.0",
    "gn:asciiname":"Purba Jahangirabad",
    "gn:country_code":"BD",
    "gn:dem":24,
    "gn:feature_class":"P",
    "gn:feature_code":"PPL",
    "gn:name":"Purba J\u0101h\u0101ngir\u0101b\u0101d",
    "gn:population":0,
    "gn:timezone":"Asia/Dhaka",
    "iso:country":"BD",
    "name:ben_x_preferred":[
        "Purba J\u0101h\u0101ngir\u0101b\u0101d"
    ],
    "wof:name":"Purba Jahangirabad",
    "wof:placetype":"locality"
},
  "geometry": {"coordinates":[89.31174,25.01932],"type":"Point"}
}