{
  "type": "Feature",
  "properties": {
    "gn:admin1_code":"H",
    "gn:admin2_code":"3039",
    "gn:admin3_code":"303961.0",
    "gn:admin4_code":"30396166.0",
    "gn:asciiname":"Megharbari",
    "gn:country_code":"BD",
    "gn:dem":24,
    "gn:feature_class":"P",
    "gn:feature_code":"PPL",
    "gn:name":"Megharbari",
    "gn:population":0,
    "gn:timezone":"Asia/Dhaka",
    "iso:country":"BD",
    "name:ben_x_preferred":[
        "Megharbari"
    ],
    "wof:name":"Megharbari",
    "wof:placetype":"locality"
},
  "geometry": {"coordinates":[89.83603000000002,25.01478],"type":"Point"}
}