{
  "type": "Feature",
  "properties": {
    "gn:admin1_code":"87",
    "gn:admin2_code":"5577.0",
    "gn:admin3_code":"557773.0",
    "gn:admin4_code":"55777365.0",
    "gn:asciiname":"Khorija Jhalai",
    "gn:country_code":"BD",
    "gn:dem":71,
    "gn:feature_class":"P",
    "gn:feature_code":"PPL",
    "gn:name":"Khorija Jhalai",
    "gn:population":0,
    "gn:timezone":"Asia/Dhaka",
    "iso:country":"BD",
    "name:ben_x_preferred":[
        "Khorija Jhalai"
    ],
    "wof:name":"Khorija Jhalai",
    "wof:placetype":"locality"
},
  "geometry": {"coordinates":[88.47691,26.27811],"type":"Point"}
}