{
  "type": "Feature",
  "properties": {
    "gn:admin1_code":"81",
    "gn:admin2_code":"3048",
    "gn:admin3_code":"304892.0",
    "gn:admin4_code":"30489294.0",
    "gn:asciiname":"Pang Pachiha",
    "gn:country_code":"BD",
    "gn:dem":13,
    "gn:feature_class":"P",
    "gn:feature_code":"PPL",
    "gn:name":"Pang P\u0101chiha",
    "gn:population":0,
    "gn:timezone":"Asia/Dhaka",
    "iso:country":"BD",
    "wof:name":"Pang Pachiha",
    "wof:placetype":"locality"
},
  "geometry": {"coordinates":[90.87226,24.54158],"type":"Point"}
}