{
  "type": "Feature",
  "properties": {
    "gn:admin1_code":"81",
    "gn:admin2_code":"3029.0",
    "gn:admin3_code":"302956.0",
    "gn:admin4_code":"30295684.0",
    "gn:asciiname":"Boalia",
    "gn:country_code":"BD",
    "gn:dem":10,
    "gn:feature_class":"P",
    "gn:feature_code":"PPL",
    "gn:name":"Bo\u0101lia",
    "gn:population":0,
    "gn:timezone":"Asia/Dhaka",
    "iso:country":"BD",
    "wof:name":"Boalia",
    "wof:placetype":"locality"
},
  "geometry": {"coordinates":[89.70469,23.53082],"type":"Point"}
}