{
  "type": "Feature",
  "properties": {
    "gn:admin1_code":"87",
    "gn:admin2_code":"5552.0",
    "gn:admin3_code":"555255.0",
    "gn:admin4_code":"55525507.0",
    "gn:asciiname":"Baraibari",
    "gn:country_code":"BD",
    "gn:dem":36,
    "gn:feature_class":"P",
    "gn:feature_code":"PPL",
    "gn:name":"Bar\u0101ib\u0101ri",
    "gn:population":0,
    "gn:timezone":"Asia/Dhaka",
    "iso:country":"BD",
    "name:ben_x_preferred":[
        "Bar\u0101ib\u0101ri"
    ],
    "name:ben_x_variant":[
        "Barabari"
    ],
    "wof:name":"Baraibari",
    "wof:placetype":"locality"
},
  "geometry": {"coordinates":[89.50315999999999,25.87619],"type":"Point"}
}