{
  "type": "Feature",
  "properties": {
    "gn:admin1_code":"H",
    "gn:admin2_code":"3061.0",
    "gn:admin3_code":"306181.0",
    "gn:admin4_code":"30618154.0",
    "gn:asciiname":"Asi Panchkahania",
    "gn:country_code":"BD",
    "gn:dem":19,
    "gn:feature_class":"P",
    "gn:feature_code":"PPL",
    "gn:name":"Asi P\u0101nchk\u0101hania",
    "gn:population":0,
    "gn:timezone":"Asia/Dhaka",
    "iso:country":"BD",
    "wof:name":"Asi Panchkahania",
    "wof:placetype":"locality"
},
  "geometry": {"coordinates":[90.35739,24.93776],"type":"Point"}
}