{
  "type": "Feature",
  "properties": {
    "gn:admin1_code":"83",
    "gn:admin2_code":"5070",
    "gn:admin3_code":"507088.0",
    "gn:admin4_code":"50708841.0",
    "gn:asciiname":"Shib Narayanpur",
    "gn:country_code":"BD",
    "gn:dem":28,
    "gn:feature_class":"P",
    "gn:feature_code":"PPL",
    "gn:name":"Shib N\u0101r\u0101yanpur",
    "gn:population":0,
    "gn:timezone":"Asia/Dhaka",
    "iso:country":"BD",
    "name:und_x_variant":[
        "Shib N\u0101r\u0101yanpur",
        "Sibn\u0101r\u0101yanpur"
    ],
    "wof:name":"Shib Narayanpur",
    "wof:placetype":"locality"
},
  "geometry": {"coordinates":[88.20045999999998,24.72319],"type":"Point"}
}