{
  "type": "Feature",
  "properties": {
    "gn:admin1_code":"81",
    "gn:admin2_code":"3068.0",
    "gn:admin3_code":"306864.0",
    "gn:admin4_code":"30686484.0",
    "gn:asciiname":"Bakharnagar",
    "gn:country_code":"BD",
    "gn:dem":8,
    "gn:feature_class":"P",
    "gn:feature_code":"PPL",
    "gn:name":"B\u0101kharnagar",
    "gn:population":0,
    "gn:timezone":"Asia/Dhaka",
    "iso:country":"BD",
    "wof:name":"Bakharnagar",
    "wof:placetype":"locality"
},
  "geometry": {"coordinates":[90.93528000000001,23.98936],"type":"Point"}
}