{
  "type": "Feature",
  "properties": {
    "gn:admin1_code":"81",
    "gn:admin2_code":"3054",
    "gn:admin3_code":"305480.0",
    "gn:admin4_code":"30548095.0",
    "gn:asciiname":"Peragram",
    "gn:country_code":"BD",
    "gn:dem":8,
    "gn:feature_class":"P",
    "gn:feature_code":"PPL",
    "gn:name":"Per\u0101gr\u0101m",
    "gn:population":0,
    "gn:timezone":"Asia/Dhaka",
    "iso:country":"BD",
    "wof:name":"Peragram",
    "wof:placetype":"locality"
},
  "geometry": {"coordinates":[90.04949999999999,23.19681],"type":"Point"}
}