{
  "type": "Feature",
  "properties": {
    "gn:admin1_code":"82",
    "gn:admin2_code":"4065",
    "gn:admin3_code":"406552.0",
    "gn:admin4_code":"40655287.0",
    "gn:asciiname":"Madhabhati",
    "gn:country_code":"BD",
    "gn:dem":11,
    "gn:feature_class":"P",
    "gn:feature_code":"PPL",
    "gn:name":"Madhabh\u0101ti",
    "gn:population":0,
    "gn:timezone":"Asia/Dhaka",
    "iso:country":"BD",
    "name:ben_x_preferred":[
        "Madhabh\u0101ti"
    ],
    "wof:name":"Madhabhati",
    "wof:placetype":"locality"
},
  "geometry": {"coordinates":[89.60833000000002,23.25318],"type":"Point"}
}