{
  "type": "Feature",
  "properties": {
    "gn:admin1_code":"83",
    "gn:admin2_code":"5070.0",
    "gn:admin3_code":"507037.0",
    "gn:admin4_code":"50703763.0",
    "gn:asciiname":"Bhatkhair",
    "gn:country_code":"BD",
    "gn:dem":49,
    "gn:feature_class":"P",
    "gn:feature_code":"PPL",
    "gn:name":"Bhatkhair",
    "gn:population":0,
    "gn:timezone":"Asia/Dhaka",
    "iso:country":"BD",
    "name:ben_x_preferred":[
        "Bhatkhair"
    ],
    "wof:name":"Bhatkhair",
    "wof:placetype":"locality"
},
  "geometry": {"coordinates":[88.45971999999998,24.86966],"type":"Point"}
}