{
  "type": "Feature",
  "properties": {
    "gn:admin1_code":"81",
    "gn:admin2_code":"3035.0",
    "gn:admin3_code":"303543.0",
    "gn:admin4_code":"30354313.0",
    "gn:asciiname":"Kuralia",
    "gn:country_code":"BD",
    "gn:dem":9,
    "gn:feature_class":"P",
    "gn:feature_code":"PPL",
    "gn:name":"Kur\u0101lia",
    "gn:population":0,
    "gn:timezone":"Asia/Dhaka",
    "iso:country":"BD",
    "name:ben_x_preferred":[
        "Kur\u0101lia"
    ],
    "wof:name":"Kuralia",
    "wof:placetype":"locality"
},
  "geometry": {"coordinates":[89.75752,23.13533],"type":"Point"}
}