{
  "type": "Feature",
  "properties": {
    "gn:admin1_code":"82",
    "gn:admin2_code":"4050.0",
    "gn:admin3_code":"405039.0",
    "gn:admin4_code":"40503913.0",
    "gn:asciiname":"Isafpur",
    "gn:country_code":"BD",
    "gn:dem":19,
    "gn:feature_class":"P",
    "gn:feature_code":"PPL",
    "gn:name":"Isafpur",
    "gn:population":0,
    "gn:timezone":"Asia/Dhaka",
    "iso:country":"BD",
    "name:ben_x_preferred":[
        "Isafpur"
    ],
    "wof:name":"Isafpur",
    "wof:placetype":"locality"
},
  "geometry": {"coordinates":[88.91201,23.93397],"type":"Point"}
}