{
  "type": "Feature",
  "properties": {
    "gn:admin1_code":"84",
    "gn:admin2_code":"2003.0",
    "gn:admin3_code":"200314.0",
    "gn:admin4_code":"20031415.0",
    "gn:asciiname":"Reichapara",
    "gn:country_code":"BD",
    "gn:dem":144,
    "gn:feature_class":"P",
    "gn:feature_code":"PPL",
    "gn:name":"Reich\u0101p\u0101ra",
    "gn:population":0,
    "gn:timezone":"Asia/Dhaka",
    "iso:country":"BD",
    "name:ben_x_preferred":[
        "Reich\u0101p\u0101ra"
    ],
    "wof:name":"Reichapara",
    "wof:placetype":"locality"
},
  "geometry": {"coordinates":[92.19114999999999,22.17637],"type":"Point"}
}