{
  "type": "Feature",
  "properties": {
    "gn:admin1_code":"83",
    "gn:admin2_code":"5064.0",
    "gn:admin3_code":"506469.0",
    "gn:admin4_code":"50646984.0",
    "gn:asciiname":"Chuniapara",
    "gn:country_code":"BD",
    "gn:dem":27,
    "gn:feature_class":"P",
    "gn:feature_code":"PPL",
    "gn:name":"Chuniapara",
    "gn:population":0,
    "gn:timezone":"Asia/Dhaka",
    "iso:country":"BD",
    "name:ben_x_preferred":[
        "Chuniapara"
    ],
    "wof:name":"Chuniapara",
    "wof:placetype":"locality"
},
  "geometry": {"coordinates":[88.55264,24.77172],"type":"Point"}
}