{
  "type": "Feature",
  "properties": {
    "gn:admin1_code":"81",
    "gn:admin2_code":"3093",
    "gn:admin3_code":"309328.0",
    "gn:admin4_code":"30932834.0",
    "gn:asciiname":"Pechar Ata",
    "gn:country_code":"BD",
    "gn:dem":18,
    "gn:feature_class":"P",
    "gn:feature_code":"PPL",
    "gn:name":"Pech\u0101r \u0100ta",
    "gn:population":0,
    "gn:timezone":"Asia/Dhaka",
    "iso:country":"BD",
    "wof:name":"Pechar Ata",
    "wof:placetype":"locality"
},
  "geometry": {"coordinates":[90.08923,24.4851],"type":"Point"}
}