{
  "type": "Feature",
  "properties": {
    "gn:admin1_code":"83",
    "gn:admin2_code":"5064.0",
    "gn:admin3_code":"506479.0",
    "gn:admin4_code":"50647923.0",
    "gn:asciiname":"Saraigachhi",
    "gn:country_code":"BD",
    "gn:dem":44,
    "gn:feature_class":"P",
    "gn:feature_code":"PPL",
    "gn:name":"S\u0101r\u0101ig\u0101chhi",
    "gn:population":0,
    "gn:timezone":"Asia/Dhaka",
    "iso:country":"BD",
    "name:ben_x_preferred":[
        "S\u0101r\u0101ig\u0101chhi"
    ],
    "wof:name":"Saraigachhi",
    "wof:placetype":"locality"
},
  "geometry": {"coordinates":[88.53675,25.0199],"type":"Point"}
}