{
  "type": "Feature",
  "properties": {
    "gn:admin1_code":"82",
    "gn:admin2_code":"4047",
    "gn:admin3_code":"404730.0",
    "gn:admin4_code":"40473081.0",
    "gn:asciiname":"Kagjipara",
    "gn:country_code":"BD",
    "gn:dem":5,
    "gn:feature_class":"P",
    "gn:feature_code":"PPL",
    "gn:name":"K\u0101gjip\u0101ra",
    "gn:population":0,
    "gn:timezone":"Asia/Dhaka",
    "iso:country":"BD",
    "name:und_x_variant":[
        "Kagazipara",
        "K\u0101gjip\u0101ra"
    ],
    "wof:name":"Kagjipara",
    "wof:placetype":"locality"
},
  "geometry": {"coordinates":[89.41741999999998,22.72395],"type":"Point"}
}