{
  "type": "Feature",
  "properties": {
    "gn:admin1_code":"83",
    "gn:admin2_code":"5070.0",
    "gn:admin3_code":"507088.0",
    "gn:admin4_code":"50708871.0",
    "gn:asciiname":"Jukta Radhakamtapur",
    "gn:country_code":"BD",
    "gn:dem":26,
    "gn:feature_class":"P",
    "gn:feature_code":"PPL",
    "gn:name":"Jukt\u0101 R\u0101dh\u0101kamt\u0101pur",
    "gn:population":0,
    "gn:timezone":"Asia/Dhaka",
    "iso:country":"BD",
    "name:ben_x_preferred":[
        "Jukt\u0101 R\u0101dh\u0101kamt\u0101pur"
    ],
    "wof:name":"Jukta Radhakamtapur",
    "wof:placetype":"locality"
},
  "geometry": {"coordinates":[88.17785000000001,24.63891],"type":"Point"}
}