{
  "type": "Feature",
  "properties": {
    "gn:admin1_code":"84",
    "gn:admin2_code":"2084.0",
    "gn:admin3_code":"208487.0",
    "gn:admin4_code":"20848740.0",
    "gn:asciiname":"Prankhiang",
    "gn:country_code":"BD",
    "gn:dem":24,
    "gn:feature_class":"P",
    "gn:feature_code":"PPL",
    "gn:name":"Prankhiang",
    "gn:population":0,
    "gn:timezone":"Asia/Dhaka",
    "iso:country":"BD",
    "wof:name":"Prankhiang",
    "wof:placetype":"locality"
},
  "geometry": {"coordinates":[92.18694000000001,22.52056],"type":"Point"}
}