{
  "type": "Feature",
  "properties": {
    "gn:admin1_code":"84",
    "gn:admin2_code":"2015.0",
    "gn:admin3_code":"201533.0",
    "gn:admin4_code":"20153342.0",
    "gn:asciiname":"Harwalchari",
    "gn:country_code":"BD",
    "gn:dem":16,
    "gn:feature_class":"P",
    "gn:feature_code":"PPL",
    "gn:name":"H\u0101rwalch\u0101ri",
    "gn:population":0,
    "gn:timezone":"Asia/Dhaka",
    "iso:country":"BD",
    "name:ben_x_preferred":[
        "H\u0101rwalch\u0101ri"
    ],
    "wof:name":"Harwalchari",
    "wof:placetype":"locality"
},
  "geometry": {"coordinates":[91.75235000000001,22.69435],"type":"Point"}
}