{
  "type": "Feature",
  "properties": {
    "gn:admin1_code":"82",
    "gn:admin2_code":"4018.0",
    "gn:admin3_code":"401807.0",
    "gn:admin4_code":"40180787.0",
    "gn:asciiname":"Digaldanga",
    "gn:country_code":"BD",
    "gn:dem":20,
    "gn:feature_class":"P",
    "gn:feature_code":"PPL",
    "gn:name":"Digald\u0101nga",
    "gn:population":0,
    "gn:timezone":"Asia/Dhaka",
    "iso:country":"BD",
    "name:ben_x_preferred":[
        "Digald\u0101nga"
    ],
    "wof:name":"Digaldanga",
    "wof:placetype":"locality"
},
  "geometry": {"coordinates":[88.89919999999999,23.75688],"type":"Point"}
}