{
  "type": "Feature",
  "properties": {
    "gn:admin1_code":"84",
    "gn:admin2_code":"2019",
    "gn:admin3_code":"201954.0",
    "gn:admin4_code":"20195485.0",
    "gn:asciiname":"North Akalia",
    "gn:country_code":"BD",
    "gn:dem":7,
    "gn:feature_class":"P",
    "gn:feature_code":"PPL",
    "gn:name":"North \u0100k\u0101lia",
    "gn:population":0,
    "gn:timezone":"Asia/Dhaka",
    "iso:country":"BD",
    "wof:name":"North Akalia",
    "wof:placetype":"locality"
},
  "geometry": {"coordinates":[90.79485,23.64287],"type":"Point"}
}