{
  "type": "Feature",
  "properties": {
    "gn:admin1_code":"82",
    "gn:admin2_code":"4041.0",
    "gn:admin3_code":"404147.0",
    "gn:admin4_code":"40414792.0",
    "gn:asciiname":"Pantiapara",
    "gn:country_code":"BD",
    "gn:dem":11,
    "gn:feature_class":"P",
    "gn:feature_code":"PPL",
    "gn:name":"Pantiapara",
    "gn:population":0,
    "gn:timezone":"Asia/Dhaka",
    "iso:country":"BD",
    "name:ben_x_preferred":[
        "Pantiapara"
    ],
    "wof:name":"Pantiapara",
    "wof:placetype":"locality"
},
  "geometry": {"coordinates":[89.2436,23.1066],"type":"Point"}
}