{
  "type": "Feature",
  "properties": {
    "gn:admin1_code":"81",
    "gn:admin2_code":"3067.0",
    "gn:admin3_code":"306758.0",
    "gn:admin4_code":"30675831.0",
    "gn:asciiname":"Hariharpara",
    "gn:country_code":"BD",
    "gn:dem":10,
    "gn:feature_class":"P",
    "gn:feature_code":"PPL",
    "gn:name":"Hariharp\u0101ra",
    "gn:population":0,
    "gn:timezone":"Asia/Dhaka",
    "iso:country":"BD",
    "name:ben_x_preferred":[
        "\u09b9\u09b0\u09bf\u09b9\u09b0\u09aa\u09be\u09a1\u09bc\u09be"
    ],
    "wof:name":"Hariharpara",
    "wof:placetype":"locality"
},
  "geometry": {"coordinates":[90.47254,23.62999],"type":"Point"}
}