{
  "type": "Feature",
  "properties": {
    "gn:admin1_code":"87",
    "gn:asciiname":"Chhit Jagatber",
    "gn:country_code":"BD",
    "gn:dem":62,
    "gn:feature_class":"P",
    "gn:feature_code":"PPL",
    "gn:name":"Chhit Jagatber",
    "gn:population":0,
    "gn:timezone":"Asia/Dhaka",
    "iso:country":"BD",
    "name:ben_x_preferred":[
        "Chhit Jagatber"
    ],
    "wof:name":"Chhit Jagatber",
    "wof:placetype":"locality"
},
  "geometry": {"coordinates":[89.07401,26.41569],"type":"Point"}
}