{
  "type": "Feature",
  "properties": {
    "gn:admin1_code":"83",
    "gn:admin2_code":"5038.0",
    "gn:admin3_code":"503847.0",
    "gn:admin4_code":"50384738.0",
    "gn:asciiname":"Chak Barkat",
    "gn:country_code":"BD",
    "gn:dem":27,
    "gn:feature_class":"P",
    "gn:feature_code":"PPL",
    "gn:name":"Chak Barkat",
    "gn:population":0,
    "gn:timezone":"Asia/Dhaka",
    "iso:country":"BD",
    "name:ben_x_preferred":[
        "Chak Barkat"
    ],
    "wof:name":"Chak Barkat",
    "wof:placetype":"locality"
},
  "geometry": {"coordinates":[88.93574,25.15018],"type":"Point"}
}