{
  "type": "Feature",
  "properties": {
    "gn:admin1_code":"H",
    "gn:admin2_code":"3089",
    "gn:admin3_code":"308970.0",
    "gn:admin4_code":"30897086.0",
    "gn:asciiname":"Manakura",
    "gn:country_code":"BD",
    "gn:dem":25,
    "gn:feature_class":"P",
    "gn:feature_code":"PPL",
    "gn:name":"Manakura",
    "gn:population":0,
    "gn:timezone":"Asia/Dhaka",
    "iso:country":"BD",
    "wof:name":"Manakura",
    "wof:placetype":"locality"
},
  "geometry": {"coordinates":[90.17247,25.13604],"type":"Point"}
}