{
  "type": "Feature",
  "properties": {
    "gn:admin1_code":"84",
    "gn:admin2_code":"2030.0",
    "gn:admin3_code":"203014.0",
    "gn:admin4_code":"20301495.0",
    "gn:asciiname":"Gopal",
    "gn:country_code":"BD",
    "gn:dem":13,
    "gn:feature_class":"P",
    "gn:feature_code":"PPL",
    "gn:name":"Gopal",
    "gn:population":0,
    "gn:timezone":"Asia/Dhaka",
    "iso:country":"BD",
    "name:deu_x_preferred":[
        "Gopal"
    ],
    "name:fra_x_preferred":[
        "Gopal"
    ],
    "wof:name":"Gopal",
    "wof:placetype":"locality"
},
  "geometry": {"coordinates":[91.55028,22.99139],"type":"Point"}
}