{
  "type": "Feature",
  "properties": {
    "gn:admin1_code":"83",
    "gn:admin2_code":"5064.0",
    "gn:admin3_code":"506450.0",
    "gn:admin4_code":"50645009.0",
    "gn:asciiname":"Chak Raja",
    "gn:country_code":"BD",
    "gn:dem":21,
    "gn:feature_class":"P",
    "gn:feature_code":"PPL",
    "gn:name":"Chak R\u0101ja",
    "gn:population":0,
    "gn:timezone":"Asia/Dhaka",
    "iso:country":"BD",
    "name:ben_x_preferred":[
        "Chak R\u0101ja"
    ],
    "wof:name":"Chak Raja",
    "wof:placetype":"locality"
},
  "geometry": {"coordinates":[88.81341999999999,24.87132],"type":"Point"}
}