{
  "type": "Feature",
  "properties": {
    "gn:admin1_code":"87",
    "gn:admin2_code":"5585",
    "gn:admin3_code":"558573.0",
    "gn:admin4_code":"55857338.0",
    "gn:asciiname":"Koikuri",
    "gn:country_code":"BD",
    "gn:dem":29,
    "gn:feature_class":"P",
    "gn:feature_code":"PPL",
    "gn:name":"Koikuri",
    "gn:population":0,
    "gn:timezone":"Asia/Dhaka",
    "iso:country":"BD",
    "wof:name":"Koikuri",
    "wof:placetype":"locality"
},
  "geometry": {"coordinates":[89.39276,25.56437],"type":"Point"}
}