{
  "type": "Feature",
  "properties": {
    "gn:admin1_code":"83",
    "gn:admin2_code":"5064.0",
    "gn:admin3_code":"506428.0",
    "gn:admin4_code":"50642831.0",
    "gn:asciiname":"Singarul",
    "gn:country_code":"BD",
    "gn:dem":25,
    "gn:feature_class":"P",
    "gn:feature_code":"PPL",
    "gn:name":"Sing\u0101rul",
    "gn:population":0,
    "gn:timezone":"Asia/Dhaka",
    "iso:country":"BD",
    "name:ben_x_preferred":[
        "Sing\u0101rul"
    ],
    "wof:name":"Singarul",
    "wof:placetype":"locality"
},
  "geometry": {"coordinates":[88.85491999999998,25.10028],"type":"Point"}
}