{
  "type": "Feature",
  "properties": {
    "gn:admin1_code":"83",
    "gn:admin2_code":"5064",
    "gn:admin3_code":"506460.0",
    "gn:admin4_code":"50646000.0",
    "gn:asciiname":"Serpur",
    "gn:country_code":"BD",
    "gn:dem":19,
    "gn:feature_class":"P",
    "gn:feature_code":"PPL",
    "gn:name":"Serpur",
    "gn:population":0,
    "gn:timezone":"Asia/Dhaka",
    "iso:country":"BD",
    "name:ben_x_preferred":[
        "Serpur"
    ],
    "name:ben_x_variant":[
        "\u09b6\u09c7\u09b0\u09aa\u09c1\u09b0"
    ],
    "name:bpy_x_preferred":[
        "\u09b6\u09c7\u09b0\u09aa\u09c1\u09b0"
    ],
    "name:ceb_x_preferred":[
        "Serpur"
    ],
    "name:ita_x_preferred":[
        "Serpur"
    ],
    "name:msa_x_preferred":[
        "Serpur"
    ],
    "name:nld_x_preferred":[
        "Serpur"
    ],
    "name:por_x_preferred":[
        "Serpur"
    ],
    "name:swe_x_preferred":[
        "Serpur"
    ],
    "name:vie_x_preferred":[
        "Serpur"
    ],
    "name:zho_x_preferred":[
        "\u585e\u5c14\u666e\u5c14"
    ],
    "wof:name":"Serpur",
    "wof:placetype":"locality"
},
  "geometry": {"coordinates":[88.941,24.7908],"type":"Point"}
}