{
  "type": "Feature",
  "properties": {
    "gn:admin1_code":"87",
    "gn:admin2_code":"5527.0",
    "gn:admin3_code":"552764.0",
    "gn:admin4_code":"55276434.0",
    "gn:asciiname":"Uttargaon",
    "gn:country_code":"BD",
    "gn:dem":40,
    "gn:feature_class":"P",
    "gn:feature_code":"PPL",
    "gn:name":"Uttargaon",
    "gn:population":0,
    "gn:timezone":"Asia/Dhaka",
    "iso:country":"BD",
    "name:ben_x_preferred":[
        "Uttargaon"
    ],
    "wof:name":"Uttargaon",
    "wof:placetype":"locality"
},
  "geometry": {"coordinates":[88.71228000000001,25.66916],"type":"Point"}
}