{
  "type": "Feature",
  "properties": {
    "gn:admin1_code":"81",
    "gn:admin2_code":"3035.0",
    "gn:admin3_code":"303543.0",
    "gn:admin4_code":"30354306.0",
    "gn:asciiname":"Sadhuhati",
    "gn:country_code":"BD",
    "gn:dem":8,
    "gn:feature_class":"P",
    "gn:feature_code":"PPL",
    "gn:name":"S\u0101dhuh\u0101ti",
    "gn:population":0,
    "gn:timezone":"Asia/Dhaka",
    "iso:country":"BD",
    "name:ben_x_preferred":[
        "S\u0101dhuh\u0101ti"
    ],
    "wof:name":"Sadhuhati",
    "wof:placetype":"locality"
},
  "geometry": {"coordinates":[89.79659000000002,23.13622],"type":"Point"}
}