{
  "type": "Feature",
  "properties": {
    "gn:admin1_code":"87",
    "gn:admin2_code":"5594.0",
    "gn:admin3_code":"559486.0",
    "gn:admin4_code":"55948647.0",
    "gn:asciiname":"Nantol",
    "gn:country_code":"BD",
    "gn:dem":47,
    "gn:feature_class":"P",
    "gn:feature_code":"PPL",
    "gn:name":"Nantol",
    "gn:population":0,
    "gn:timezone":"Asia/Dhaka",
    "iso:country":"BD",
    "name:ben_x_preferred":[
        "Nantol"
    ],
    "wof:name":"Nantol",
    "wof:placetype":"locality"
},
  "geometry": {"coordinates":[88.19651,25.94901],"type":"Point"}
}