{
  "type": "Feature",
  "properties": {
    "gn:admin1_code":"82",
    "gn:asciiname":"Char Anandaprasad",
    "gn:country_code":"BD",
    "gn:dem":7,
    "gn:feature_class":"P",
    "gn:feature_code":"PPL",
    "gn:name":"Char Anandapras\u0101d",
    "gn:population":0,
    "gn:timezone":"Asia/Dhaka",
    "iso:country":"BD",
    "name:ben_x_preferred":[
        "Char Anandapras\u0101d"
    ],
    "wof:name":"Char Anandaprasad",
    "wof:placetype":"locality"
},
  "geometry": {"coordinates":[90.80531000000001,22.23514],"type":"Point"}
}