{
  "type": "Feature",
  "properties": {
    "gn:admin1_code":"82",
    "gn:admin2_code":"4044.0",
    "gn:admin3_code":"404433.0",
    "gn:admin4_code":"40443340.0",
    "gn:asciiname":"Gaurinathpur",
    "gn:country_code":"BD",
    "gn:dem":12,
    "gn:feature_class":"P",
    "gn:feature_code":"PPL",
    "gn:name":"Gaurin\u0101thpur",
    "gn:population":0,
    "gn:timezone":"Asia/Dhaka",
    "iso:country":"BD",
    "name:ben_x_preferred":[
        "Gaurin\u0101thpur"
    ],
    "wof:name":"Gaurinathpur",
    "wof:placetype":"locality"
},
  "geometry": {"coordinates":[89.12708000000001,23.2902],"type":"Point"}
}