{
  "type": "Feature",
  "properties": {
    "gn:admin1_code":"H",
    "gn:admin2_code":"3089",
    "gn:admin3_code":"308988.0",
    "gn:admin4_code":"30898861.0",
    "gn:asciiname":"Number Six Char",
    "gn:country_code":"BD",
    "gn:dem":21,
    "gn:feature_class":"P",
    "gn:feature_code":"PPL",
    "gn:name":"Number Six Char",
    "gn:population":0,
    "gn:timezone":"Asia/Dhaka",
    "iso:country":"BD",
    "name:ben_x_preferred":[
        "Number Six Char"
    ],
    "name:und_x_variant":[
        "No. 6 Char"
    ],
    "wof:name":"Number Six Char",
    "wof:placetype":"locality"
},
  "geometry": {"coordinates":[89.8969,25.01539],"type":"Point"}
}