{
  "type": "Feature",
  "properties": {
    "gn:admin1_code":"H",
    "gn:admin2_code":"3061",
    "gn:admin3_code":"306122.0",
    "gn:admin4_code":"30612231.0",
    "gn:asciiname":"Kursapur",
    "gn:country_code":"BD",
    "gn:dem":14,
    "gn:feature_class":"P",
    "gn:feature_code":"PPL",
    "gn:name":"Kurs\u0101pur",
    "gn:population":0,
    "gn:timezone":"Asia/Dhaka",
    "iso:country":"BD",
    "wof:name":"Kursapur",
    "wof:placetype":"locality"
},
  "geometry": {"coordinates":[90.44274,24.48231],"type":"Point"}
}