{
  "type": "Feature",
  "properties": {
    "gn:admin1_code":"82",
    "gn:admin2_code":"4041.0",
    "gn:admin3_code":"404161.0",
    "gn:admin4_code":"40416127.0",
    "gn:asciiname":"Haridaskati",
    "gn:country_code":"BD",
    "gn:dem":11,
    "gn:feature_class":"P",
    "gn:feature_code":"PPL",
    "gn:name":"Harid\u0101sk\u0101ti",
    "gn:population":0,
    "gn:timezone":"Asia/Dhaka",
    "iso:country":"BD",
    "name:ben_x_preferred":[
        "Harid\u0101sk\u0101ti"
    ],
    "wof:name":"Haridaskati",
    "wof:placetype":"locality"
},
  "geometry": {"coordinates":[89.31882,23.04857],"type":"Point"}
}