{
  "type": "Feature",
  "properties": {
    "gn:admin1_code":"81",
    "gn:admin2_code":"3056.0",
    "gn:admin3_code":"305682.0",
    "gn:admin4_code":"30568217.0",
    "gn:asciiname":"Bri Kaliakair",
    "gn:country_code":"BD",
    "gn:dem":14,
    "gn:feature_class":"P",
    "gn:feature_code":"PPL",
    "gn:name":"Bri K\u0101li\u0101kair",
    "gn:population":0,
    "gn:timezone":"Asia/Dhaka",
    "iso:country":"BD",
    "wof:name":"Bri Kaliakair",
    "wof:placetype":"locality"
},
  "geometry": {"coordinates":[90.06173000000003,23.79098],"type":"Point"}
}