{
  "type": "Feature",
  "properties": {
    "gn:admin1_code":"81",
    "gn:admin2_code":"3059",
    "gn:admin3_code":"305944.0",
    "gn:admin4_code":"30594463.0",
    "gn:asciiname":"Malni",
    "gn:country_code":"BD",
    "gn:dem":8,
    "gn:feature_class":"P",
    "gn:feature_code":"PPL",
    "gn:name":"M\u0101lni",
    "gn:population":0,
    "gn:timezone":"Asia/Dhaka",
    "iso:country":"BD",
    "name:bos_x_preferred":[
        "Malni"
    ],
    "name:hrv_x_preferred":[
        "Malni"
    ],
    "name:nld_x_preferred":[
        "Malni"
    ],
    "name:pol_x_preferred":[
        "Malni"
    ],
    "name:ron_x_preferred":[
        "Malni"
    ],
    "name:slv_x_preferred":[
        "Malni"
    ],
    "name:ukr_x_preferred":[
        "\u041c\u0430\u043b\u043d\u0456"
    ],
    "wof:name":"Malni",
    "wof:placetype":"locality"
},
  "geometry": {"coordinates":[90.40101,23.51102],"type":"Point"}
}