{
  "type": "Feature",
  "properties": {
    "gn:admin1_code":"81",
    "gn:admin2_code":"3086",
    "gn:admin3_code":"308669.0",
    "gn:admin4_code":"30866938.0",
    "gn:asciiname":"Saula",
    "gn:country_code":"BD",
    "gn:dem":10,
    "gn:feature_class":"P",
    "gn:feature_code":"PPL",
    "gn:name":"Saula",
    "gn:population":0,
    "gn:timezone":"Asia/Dhaka",
    "iso:country":"BD",
    "name:ceb_x_preferred":[
        "Saula"
    ],
    "name:swe_x_preferred":[
        "Saula"
    ],
    "wof:name":"Saula",
    "wof:placetype":"locality"
},
  "geometry": {"coordinates":[90.30494,23.25508],"type":"Point"}
}