{
  "type": "Feature",
  "properties": {
    "gn:admin1_code":"83",
    "gn:admin2_code":"5081",
    "gn:admin3_code":"508172.0",
    "gn:admin4_code":"50817223.0",
    "gn:asciiname":"Sundalpur",
    "gn:country_code":"BD",
    "gn:dem":20,
    "gn:feature_class":"P",
    "gn:feature_code":"PPL",
    "gn:name":"Sundalpur",
    "gn:population":0,
    "gn:timezone":"Asia/Dhaka",
    "iso:country":"BD",
    "name:ben_x_preferred":[
        "Sundalpur"
    ],
    "name:ben_x_variant":[
        "Sandalpur"
    ],
    "wof:name":"Sundalpur",
    "wof:placetype":"locality"
},
  "geometry": {"coordinates":[88.55741,24.49151],"type":"Point"}
}