{
  "type": "Feature",
  "properties": {
    "gn:admin1_code":"84",
    "gn:admin2_code":"2013",
    "gn:admin3_code":"201395.0",
    "gn:admin4_code":"20139590.0",
    "gn:asciiname":"Lotra",
    "gn:country_code":"BD",
    "gn:dem":9,
    "gn:feature_class":"P",
    "gn:feature_code":"PPL",
    "gn:name":"Lotra",
    "gn:population":0,
    "gn:timezone":"Asia/Dhaka",
    "iso:country":"BD",
    "wof:name":"Lotra",
    "wof:placetype":"locality"
},
  "geometry": {"coordinates":[90.91667,23.15],"type":"Point"}
}