{
  "type": "Feature",
  "properties": {
    "gn:admin1_code":"87",
    "gn:admin2_code":"5585",
    "gn:admin3_code":"558576.0",
    "gn:admin4_code":"55857612.0",
    "gn:asciiname":"Bara Dargah Bhagawanpur",
    "gn:country_code":"BD",
    "gn:dem":30,
    "gn:feature_class":"P",
    "gn:feature_code":"PPL",
    "gn:name":"Bara Dargah Bhagawanpur",
    "gn:population":0,
    "gn:timezone":"Asia/Dhaka",
    "iso:country":"BD",
    "name:ben_x_preferred":[
        "Bara Dargah Bhagawanpur"
    ],
    "wof:name":"Bara Dargah Bhagawanpur",
    "wof:placetype":"locality"
},
  "geometry": {"coordinates":[89.29598,25.49596],"type":"Point"}
}