{
  "type": "Feature",
  "properties": {
    "gn:admin1_code":"87",
    "gn:admin2_code":"5552",
    "gn:admin3_code":"555233.0",
    "gn:admin4_code":"55523385.0",
    "gn:asciiname":"Hatibandha",
    "gn:country_code":"BD",
    "gn:dem":53,
    "gn:feature_class":"P",
    "gn:feature_code":"PPL",
    "gn:name":"H\u0101tib\u0101ndha",
    "gn:population":0,
    "gn:timezone":"Asia/Dhaka",
    "iso:country":"BD",
    "name:ben_x_preferred":[
        "H\u0101tib\u0101ndha"
    ],
    "name:ben_x_variant":[
        "\u09b9\u09be\u09a4\u09bf\u09ac\u09be\u09a8\u09cd\u09a7\u09be"
    ],
    "name:ita_x_preferred":[
        "Hatibandha"
    ],
    "name:msa_x_preferred":[
        "Hatibandha"
    ],
    "name:nld_x_preferred":[
        "Hatibandha"
    ],
    "name:por_x_preferred":[
        "Hatibandha"
    ],
    "name:vie_x_preferred":[
        "Hatibandha"
    ],
    "name:zho_x_preferred":[
        "\u54c8\u8482\u73ed\u8fbe"
    ],
    "wof:name":"Hatibandha",
    "wof:placetype":"locality"
},
  "geometry": {"coordinates":[89.14081,26.12494],"type":"Point"}
}