{
  "type": "Feature",
  "properties": {
    "gn:admin1_code":"87",
    "gn:admin2_code":"5527.0",
    "gn:admin3_code":"552760.0",
    "gn:admin4_code":"55276047.0",
    "gn:asciiname":"Uttampara",
    "gn:country_code":"BD",
    "gn:dem":47,
    "gn:feature_class":"P",
    "gn:feature_code":"PPL",
    "gn:name":"Uttamp\u0101ra",
    "gn:population":0,
    "gn:timezone":"Asia/Dhaka",
    "iso:country":"BD",
    "name:ben_x_preferred":[
        "Uttamp\u0101ra"
    ],
    "wof:name":"Uttampara",
    "wof:placetype":"locality"
},
  "geometry": {"coordinates":[88.77246,25.81738],"type":"Point"}
}