{
  "type": "Feature",
  "properties": {
    "gn:admin1_code":"82",
    "gn:asciiname":"Purba Ghutabachha",
    "gn:country_code":"BD",
    "gn:dem":9,
    "gn:feature_class":"P",
    "gn:feature_code":"PPL",
    "gn:name":"Purba Ghut\u0101b\u0101chha",
    "gn:population":0,
    "gn:timezone":"Asia/Dhaka",
    "iso:country":"BD",
    "name:ben_x_preferred":[
        "Purba Ghut\u0101b\u0101chha"
    ],
    "wof:name":"Purba Ghutabachha",
    "wof:placetype":"locality"
},
  "geometry": {"coordinates":[89.98836999999997,22.06566],"type":"Point"}
}