{
  "type": "Feature",
  "properties": {
    "gn:admin1_code":"H",
    "gn:admin2_code":"3072.0",
    "gn:admin3_code":"307274.0",
    "gn:admin4_code":"30727447.0",
    "gn:asciiname":"Darun Hasanpur",
    "gn:country_code":"BD",
    "gn:dem":14,
    "gn:feature_class":"P",
    "gn:feature_code":"PPL",
    "gn:name":"Darun Has\u0101npur",
    "gn:population":0,
    "gn:timezone":"Asia/Dhaka",
    "iso:country":"BD",
    "name:und_x_variant":[
        "Darun Has\u0101npur",
        "Darun H\u0101s\u0101mpur"
    ],
    "wof:name":"Darun Hasanpur",
    "wof:placetype":"locality"
},
  "geometry": {"coordinates":[90.78388,24.81171],"type":"Point"}
}