{
  "type": "Feature",
  "properties": {
    "gn:admin1_code":"81",
    "gn:admin2_code":"3086",
    "gn:admin3_code":"308636.0",
    "gn:admin4_code":"30863635.0",
    "gn:asciiname":"Tar Goalkua",
    "gn:country_code":"BD",
    "gn:dem":10,
    "gn:feature_class":"P",
    "gn:feature_code":"PPL",
    "gn:name":"Tar Go\u0101lkua",
    "gn:population":0,
    "gn:timezone":"Asia/Dhaka",
    "iso:country":"BD",
    "name:und_x_variant":[
        "Tar Jualkua",
        "Tar Go\u0101lkua"
    ],
    "wof:name":"Tar Goalkua",
    "wof:placetype":"locality"
},
  "geometry": {"coordinates":[90.41656999999999,23.06883],"type":"Point"}
}