{
  "type": "Feature",
  "properties": {
    "gn:admin1_code":"81",
    "gn:admin2_code":"3029.0",
    "gn:admin3_code":"302956.0",
    "gn:admin4_code":"30295684.0",
    "gn:asciiname":"Amurdi",
    "gn:country_code":"BD",
    "gn:dem":12,
    "gn:feature_class":"P",
    "gn:feature_code":"PPL",
    "gn:name":"\u0100murdi",
    "gn:population":0,
    "gn:timezone":"Asia/Dhaka",
    "iso:country":"BD",
    "wof:name":"Amurdi",
    "wof:placetype":"locality"
},
  "geometry": {"coordinates":[89.69209000000002,23.54183],"type":"Point"}
}