{
  "type": "Feature",
  "properties": {
    "gn:admin1_code":"82",
    "gn:admin2_code":"4041.0",
    "gn:admin3_code":"404190.0",
    "gn:admin4_code":"40419094.0",
    "gn:asciiname":"Benipara",
    "gn:country_code":"BD",
    "gn:dem":11,
    "gn:feature_class":"P",
    "gn:feature_code":"PPL",
    "gn:name":"Benip\u0101ra",
    "gn:population":0,
    "gn:timezone":"Asia/Dhaka",
    "iso:country":"BD",
    "name:ben_x_preferred":[
        "Benip\u0101ra"
    ],
    "wof:name":"Benipara",
    "wof:placetype":"locality"
},
  "geometry": {"coordinates":[88.97407,23.00637],"type":"Point"}
}