{
  "type": "Feature",
  "properties": {
    "gn:admin1_code":"81",
    "gn:admin2_code":"3033.0",
    "gn:admin3_code":"303330.0",
    "gn:admin4_code":"30333081.0",
    "gn:asciiname":"Boran",
    "gn:country_code":"BD",
    "gn:dem":11,
    "gn:feature_class":"P",
    "gn:feature_code":"PPL",
    "gn:name":"Bor\u0101n",
    "gn:population":0,
    "gn:timezone":"Asia/Dhaka",
    "iso:country":"BD",
    "wof:name":"Boran",
    "wof:placetype":"locality"
},
  "geometry": {"coordinates":[90.46975999999999,23.90003],"type":"Point"}
}