{
  "type": "Feature",
  "properties": {
    "gn:admin1_code":"81",
    "gn:admin2_code":"3033.0",
    "gn:admin3_code":"303330.0",
    "gn:admin4_code":"30333081.0",
    "gn:asciiname":"Boran",
    "gn:country_code":"BD",
    "gn:dem":11,
    "gn:feature_class":"P",
    "gn:feature_code":"PPL",
    "gn:name":"Bor\u0101n",
    "gn:population":0,
    "gn:timezone":"Asia/Dhaka",
    "iso:country":"BD",
    "name:ara_x_preferred":[
        "\u0628\u0648\u0631\u0627\u0646\u062f\u062e\u062a"
    ],
    "name:ast_x_preferred":[
        "Boran"
    ],
    "name:azb_x_preferred":[
        "\u0628\u0648\u0631\u0627\u0646\u062f\u062e\u062a"
    ],
    "name:bel_x_preferred":[
        "\u0411\u0430\u0440\u0430\u043d\u0434\u043e\u0445\u0442"
    ],
    "name:ben_x_preferred":[
        "\u09ac\u09c1\u09b0\u09be\u09a8\u09a6\u09be\u0996\u09a4"
    ],
    "name:bul_x_preferred":[
        "\u0411\u043e\u0440\u0430\u043d\u0434\u043e\u0445\u0442"
    ],
    "name:cat_x_preferred":[
        "Boran"
    ],
    "name:ces_x_preferred":[
        "B\u00f3r\u00e1n"
    ],
    "name:dan_x_preferred":[
        "Purandokht"
    ],
    "name:diq_x_preferred":[
        "Burandoxt"
    ],
    "name:fas_x_preferred":[
        "\u0628\u0648\u0631\u0627\u0646\u062f\u062e\u062a"
    ],
    "name:fra_x_preferred":[
        "B\u00fbr\u00e2nd\u00fbkht"
    ],
    "name:hrv_x_preferred":[
        "Boran Perzijska"
    ],
    "name:kor_x_preferred":[
        "\ud478\ub780\ub3c4\ud750\ud2b8"
    ],
    "name:lit_x_preferred":[
        "Purandokta"
    ],
    "name:nor_x_preferred":[
        "Purandohkt"
    ],
    "name:por_x_preferred":[
        "Borana"
    ],
    "name:rus_x_preferred":[
        "\u0411\u043e\u0440\u0430\u043d\u0434\u043e\u0445\u0442"
    ],
    "name:slk_x_preferred":[
        "B\u00f3r\u00e1n"
    ],
    "name:spa_x_preferred":[
        "Boran"
    ],
    "name:swe_x_preferred":[
        "Purandokht"
    ],
    "name:tur_x_preferred":[
        "Purandoht"
    ],
    "name:ukr_x_preferred":[
        "\u0411\u043e\u0440\u0430\u043d\u0434\u043e\u0445\u0442"
    ],
    "name:urd_x_preferred":[
        "\u0628\u0648\u0631\u0627\u0646 \u062f\u062e\u062a"
    ],
    "name:vie_x_preferred":[
        "Borandukht"
    ],
    "wof:name":"Boran",
    "wof:placetype":"locality"
},
  "geometry": {"coordinates":[90.46975999999999,23.90003],"type":"Point"}
}