{
  "type": "Feature",
  "properties": {
    "gn:admin1_code":"87",
    "gn:admin2_code":"5532",
    "gn:admin3_code":"553224.0",
    "gn:admin4_code":"55322414.0",
    "gn:asciiname":"Kajal Dhop",
    "gn:country_code":"BD",
    "gn:dem":26,
    "gn:feature_class":"P",
    "gn:feature_code":"PPL",
    "gn:name":"Kajal Dhop",
    "gn:population":0,
    "gn:timezone":"Asia/Dhaka",
    "iso:country":"BD",
    "name:ben_x_preferred":[
        "Kajal Dhop"
    ],
    "wof:name":"Kajal Dhop",
    "wof:placetype":"locality"
},
  "geometry": {"coordinates":[89.49923000000003,25.3498],"type":"Point"}
}