{
  "type": "Feature",
  "properties": {
    "gn:admin1_code":"83",
    "gn:admin2_code":"5081.0",
    "gn:admin3_code":"508125.0",
    "gn:admin4_code":"50812539.0",
    "gn:asciiname":"Ferozpur",
    "gn:country_code":"BD",
    "gn:dem":22,
    "gn:feature_class":"P",
    "gn:feature_code":"PPL",
    "gn:name":"Ferozpur",
    "gn:population":0,
    "gn:timezone":"Asia/Dhaka",
    "iso:country":"BD",
    "name:ben_x_preferred":[
        "Ferozpur"
    ],
    "wof:name":"Ferozpur",
    "wof:placetype":"locality"
},
  "geometry": {"coordinates":[88.76108000000001,24.27824],"type":"Point"}
}