{
  "type": "Feature",
  "properties": {
    "gn:admin1_code":"81",
    "gn:admin2_code":"3026.0",
    "gn:admin3_code":"302614.0",
    "gn:admin4_code":"30261494.0",
    "gn:asciiname":"Dakshin Naogaon",
    "gn:country_code":"BD",
    "gn:dem":14,
    "gn:feature_class":"P",
    "gn:feature_code":"PPL",
    "gn:name":"Dakshin Naogaon",
    "gn:population":0,
    "gn:timezone":"Asia/Dhaka",
    "iso:country":"BD",
    "wof:name":"Dakshin Naogaon",
    "wof:placetype":"locality"
},
  "geometry": {"coordinates":[90.10827999999999,23.90225],"type":"Point"}
}