{
  "type": "Feature",
  "properties": {
    "gn:admin1_code":"83",
    "gn:admin2_code":"5010",
    "gn:admin3_code":"501054.0",
    "gn:admin4_code":"50105466.0",
    "gn:asciiname":"Isabpur",
    "gn:country_code":"BD",
    "gn:dem":22,
    "gn:feature_class":"P",
    "gn:feature_code":"PPL",
    "gn:name":"Isabpur",
    "gn:population":0,
    "gn:timezone":"Asia/Dhaka",
    "iso:country":"BD",
    "wof:name":"Isabpur",
    "wof:placetype":"locality"
},
  "geometry": {"coordinates":[89.30265,24.83165],"type":"Point"}
}