{
  "type": "Feature",
  "properties": {
    "gn:admin1_code":"87",
    "gn:admin2_code":"5527.0",
    "gn:admin3_code":"552777.0",
    "gn:admin4_code":"55277760.0",
    "gn:asciiname":"Tera Ani",
    "gn:country_code":"BD",
    "gn:dem":40,
    "gn:feature_class":"P",
    "gn:feature_code":"PPL",
    "gn:name":"Ter\u0101 Ani",
    "gn:population":0,
    "gn:timezone":"Asia/Dhaka",
    "iso:country":"BD",
    "name:ben_x_preferred":[
        "Ter\u0101 Ani"
    ],
    "wof:name":"Tera Ani",
    "wof:placetype":"locality"
},
  "geometry": {"coordinates":[88.84454000000002,25.6195],"type":"Point"}
}