{
  "type": "Feature",
  "properties": {
    "gn:admin1_code":"H",
    "gn:admin2_code":"3072.0",
    "gn:admin3_code":"307283.0",
    "gn:admin4_code":"30728323.0",
    "gn:asciiname":"Charbahuli Dadrapara",
    "gn:country_code":"BD",
    "gn:dem":18,
    "gn:feature_class":"P",
    "gn:feature_code":"PPL",
    "gn:name":"Charbahuli D\u0101dr\u0101p\u0101ra",
    "gn:population":0,
    "gn:timezone":"Asia/Dhaka",
    "iso:country":"BD",
    "name:und_x_variant":[
        "Charbahuli D\u0101dr\u0101p\u0101ra",
        "Chorbahuli D\u0101dr\u0101p\u0101ra"
    ],
    "wof:name":"Charbahuli Dadrapara",
    "wof:placetype":"locality"
},
  "geometry": {"coordinates":[90.55174,24.91682],"type":"Point"}
}