{
  "type": "Feature",
  "properties": {
    "gn:admin1_code":"84",
    "gn:admin2_code":"2051.0",
    "gn:admin3_code":"205165.0",
    "gn:admin4_code":"20516566.0",
    "gn:asciiname":"Bigha",
    "gn:country_code":"BD",
    "gn:dem":13,
    "gn:feature_class":"P",
    "gn:feature_code":"PPL",
    "gn:name":"Bigha",
    "gn:population":0,
    "gn:timezone":"Asia/Dhaka",
    "iso:country":"BD",
    "wof:name":"Bigha",
    "wof:placetype":"locality"
},
  "geometry": {"coordinates":[90.88182,23.148],"type":"Point"}
}