{
  "type": "Feature",
  "properties": {
    "gn:admin1_code":"85",
    "gn:admin2_code":"1006",
    "gn:admin3_code":"100694.0",
    "gn:admin4_code":"10069410.0",
    "gn:asciiname":"Uttar Morakati",
    "gn:country_code":"BD",
    "gn:dem":12,
    "gn:feature_class":"P",
    "gn:feature_code":"PPL",
    "gn:name":"Uttar Mor\u0101k\u0101ti",
    "gn:population":0,
    "gn:timezone":"Asia/Dhaka",
    "iso:country":"BD",
    "name:und_x_variant":[
        "Uttar Mor\u0101k\u0101ti",
        "North Mor\u0101k\u0101ti"
    ],
    "wof:name":"Uttar Morakati",
    "wof:placetype":"locality"
},
  "geometry": {"coordinates":[90.24851,22.89161],"type":"Point"}
}