{
  "type": "Feature",
  "properties": {
    "gn:admin1_code":"85",
    "gn:admin2_code":"1078",
    "gn:admin3_code":"107866.0",
    "gn:admin4_code":"10786683.0",
    "gn:asciiname":"Dakshin Tiakhali",
    "gn:country_code":"BD",
    "gn:dem":7,
    "gn:feature_class":"P",
    "gn:feature_code":"PPL",
    "gn:name":"Dakshin Ti\u0101kh\u0101li",
    "gn:population":0,
    "gn:timezone":"Asia/Dhaka",
    "iso:country":"BD",
    "name:und_x_variant":[
        "Dakshin Ti\u0101kh\u0101li",
        "South Ti\u0101kh\u0101li"
    ],
    "wof:name":"Dakshin Tiakhali",
    "wof:placetype":"locality"
},
  "geometry": {"coordinates":[90.24567999999999,22.00275],"type":"Point"}
}