{
  "type": "Feature",
  "properties": {
    "gn:admin1_code":"82",
    "gn:admin2_code":"4001.0",
    "gn:admin3_code":"400173.0",
    "gn:admin4_code":"40017377.0",
    "gn:asciiname":"Gonabelai",
    "gn:country_code":"BD",
    "gn:dem":7,
    "gn:feature_class":"P",
    "gn:feature_code":"PPL",
    "gn:name":"Gon\u0101bel\u0101i",
    "gn:population":0,
    "gn:timezone":"Asia/Dhaka",
    "iso:country":"BD",
    "wof:name":"Gonabelai",
    "wof:placetype":"locality"
},
  "geometry": {"coordinates":[89.587,22.57565],"type":"Point"}
}