{
  "type": "Feature",
  "properties": {
    "gn:admin1_code":"82",
    "gn:admin2_code":"4044.0",
    "gn:admin3_code":"404414.0",
    "gn:admin4_code":"40441431.0",
    "gn:asciiname":"Ahadnagar",
    "gn:country_code":"BD",
    "gn:dem":15,
    "gn:feature_class":"P",
    "gn:feature_code":"PPL",
    "gn:name":"Ahadnagar",
    "gn:population":0,
    "gn:timezone":"Asia/Dhaka",
    "iso:country":"BD",
    "name:ben_x_preferred":[
        "Ahadnagar"
    ],
    "wof:name":"Ahadnagar",
    "wof:placetype":"locality"
},
  "geometry": {"coordinates":[89.0411,23.63126],"type":"Point"}
}