{
  "type": "Feature",
  "properties": {
    "gn:admin1_code":"82",
    "gn:admin2_code":"4041.0",
    "gn:admin3_code":"404111.0",
    "gn:admin4_code":"40411151.0",
    "gn:asciiname":"Batkhnari",
    "gn:country_code":"BD",
    "gn:dem":15,
    "gn:feature_class":"P",
    "gn:feature_code":"PPL",
    "gn:name":"Batkhnari",
    "gn:population":0,
    "gn:timezone":"Asia/Dhaka",
    "iso:country":"BD",
    "name:ben_x_preferred":[
        "Batkhnari"
    ],
    "wof:name":"Batkhnari",
    "wof:placetype":"locality"
},
  "geometry": {"coordinates":[88.98649,23.29441],"type":"Point"}
}