{
  "type": "Feature",
  "properties": {
    "gn:admin1_code":"84",
    "gn:admin2_code":"2015.0",
    "gn:admin3_code":"201561.0",
    "gn:admin4_code":"20156130.0",
    "gn:asciiname":"Dhalghat",
    "gn:country_code":"BD",
    "gn:dem":7,
    "gn:feature_class":"P",
    "gn:feature_code":"PPL",
    "gn:name":"Dhalgh\u0101t",
    "gn:population":0,
    "gn:timezone":"Asia/Dhaka",
    "iso:country":"BD",
    "name:ben_x_preferred":[
        "Dhalgh\u0101t"
    ],
    "name:und_x_variant":[
        "Dhalg Gh\u0101t"
    ],
    "wof:name":"Dhalghat",
    "wof:placetype":"locality"
},
  "geometry": {"coordinates":[91.96545999999999,22.33692000000001],"type":"Point"}
}