{
  "type": "Feature",
  "properties": {
    "gn:admin1_code":"81",
    "gn:admin2_code":"3068.0",
    "gn:admin3_code":"306852.0",
    "gn:admin4_code":"30685254.0",
    "gn:asciiname":"Basubhanda",
    "gn:country_code":"BD",
    "gn:dem":14,
    "gn:feature_class":"P",
    "gn:feature_code":"PPL",
    "gn:name":"Basubh\u0101nda",
    "gn:population":0,
    "gn:timezone":"Asia/Dhaka",
    "iso:country":"BD",
    "wof:name":"Basubhanda",
    "wof:placetype":"locality"
},
  "geometry": {"coordinates":[90.72192,24.09695],"type":"Point"}
}