{
  "type": "Feature",
  "properties": {
    "gn:admin1_code":"83",
    "gn:admin2_code":"5038.0",
    "gn:admin3_code":"503847.0",
    "gn:admin4_code":"50384738.0",
    "gn:asciiname":"Majaidpur",
    "gn:country_code":"BD",
    "gn:dem":21,
    "gn:feature_class":"P",
    "gn:feature_code":"PPL",
    "gn:name":"Majaidpur",
    "gn:population":0,
    "gn:timezone":"Asia/Dhaka",
    "iso:country":"BD",
    "name:ben_x_preferred":[
        "Majaidpur"
    ],
    "wof:name":"Majaidpur",
    "wof:placetype":"locality"
},
  "geometry": {"coordinates":[88.92795,25.13787],"type":"Point"}
}