{
  "type": "Feature",
  "properties": {
    "gn:admin1_code":"82",
    "gn:admin2_code":"4087.0",
    "gn:admin3_code":"408790.0",
    "gn:admin4_code":"40879047.0",
    "gn:asciiname":"Hariharnagar",
    "gn:country_code":"BD",
    "gn:dem":6,
    "gn:feature_class":"P",
    "gn:feature_code":"PPL",
    "gn:name":"Hariharnagar",
    "gn:population":0,
    "gn:timezone":"Asia/Dhaka",
    "iso:country":"BD",
    "wof:name":"Hariharnagar",
    "wof:placetype":"locality"
},
  "geometry": {"coordinates":[89.23596999999999,22.64755],"type":"Point"}
}