{
  "type": "Feature",
  "properties": {
    "gn:admin1_code":"81",
    "gn:admin2_code":"3029.0",
    "gn:admin3_code":"302956.0",
    "gn:admin4_code":"30295652.0",
    "gn:asciiname":"Datter Kapashati",
    "gn:country_code":"BD",
    "gn:dem":10,
    "gn:feature_class":"P",
    "gn:feature_code":"PPL",
    "gn:name":"Datter K\u0101p\u0101sh\u0101ti",
    "gn:population":0,
    "gn:timezone":"Asia/Dhaka",
    "iso:country":"BD",
    "wof:name":"Datter Kapashati",
    "wof:placetype":"locality"
},
  "geometry": {"coordinates":[89.64585,23.51739],"type":"Point"}
}