{
  "type": "Feature",
  "properties": {
    "gn:admin1_code":"84",
    "gn:admin2_code":"2015.0",
    "gn:admin3_code":"201561.0",
    "gn:admin4_code":"20156127.0",
    "gn:asciiname":"Ismal Imanihir Hat",
    "gn:country_code":"BD",
    "gn:dem":8,
    "gn:feature_class":"P",
    "gn:feature_code":"PPL",
    "gn:name":"Ism\u0101l Imanihir H\u0101t",
    "gn:population":0,
    "gn:timezone":"Asia/Dhaka",
    "iso:country":"BD",
    "name:ben_x_preferred":[
        "Ism\u0101l Imanihir H\u0101t"
    ],
    "wof:name":"Ismal Imanihir Hat",
    "wof:placetype":"locality"
},
  "geometry": {"coordinates":[91.83432999999999,22.31723],"type":"Point"}
}