{
  "type": "Feature",
  "properties": {
    "gn:admin1_code":"84",
    "gn:admin2_code":"2084.0",
    "gn:admin3_code":"208429.0",
    "gn:admin4_code":"20842923.0",
    "gn:asciiname":"Bharjyatali",
    "gn:country_code":"BD",
    "gn:dem":106,
    "gn:feature_class":"P",
    "gn:feature_code":"PPL",
    "gn:name":"Bharjyatali",
    "gn:population":0,
    "gn:timezone":"Asia/Dhaka",
    "iso:country":"BD",
    "wof:name":"Bharjyatali",
    "wof:placetype":"locality"
},
  "geometry": {"coordinates":[92.29584,22.46321],"type":"Point"}
}