{
  "type": "Feature",
  "properties": {
    "gn:admin1_code":"83",
    "gn:asciiname":"Hapania",
    "gn:country_code":"BD",
    "gn:dem":23,
    "gn:feature_class":"P",
    "gn:feature_code":"PPL",
    "gn:name":"Hap\u0101nia",
    "gn:population":0,
    "gn:timezone":"Asia/Dhaka",
    "iso:country":"BD",
    "name:ben_x_preferred":[
        "Hap\u0101nia"
    ],
    "wof:name":"Hapania",
    "wof:placetype":"locality"
},
  "geometry": {"coordinates":[89.53388000000002,25.09769],"type":"Point"}
}