{
  "type": "Feature",
  "properties": {
    "gn:admin1_code":"87",
    "gn:admin2_code":"5573.0",
    "gn:admin3_code":"557364.0",
    "gn:admin4_code":"55736450.0",
    "gn:asciiname":"Musrat Kukhapara",
    "gn:country_code":"BD",
    "gn:dem":49,
    "gn:feature_class":"P",
    "gn:feature_code":"PPL",
    "gn:name":"Musrat Kukhapara",
    "gn:population":0,
    "gn:timezone":"Asia/Dhaka",
    "iso:country":"BD",
    "name:ben_x_preferred":[
        "Musrat Kukhapara"
    ],
    "wof:name":"Musrat Kukhapara",
    "wof:placetype":"locality"
},
  "geometry": {"coordinates":[88.84936999999999,25.88531],"type":"Point"}
}