{
  "type": "Feature",
  "properties": {
    "gn:admin1_code":"82",
    "gn:admin2_code":"4001.0",
    "gn:admin3_code":"400156.0",
    "gn:admin4_code":"40015609.0",
    "gn:asciiname":"Bhandarkhola",
    "gn:country_code":"BD",
    "gn:dem":9,
    "gn:feature_class":"P",
    "gn:feature_code":"PPL",
    "gn:name":"Bh\u0101nd\u0101rkhola",
    "gn:population":0,
    "gn:timezone":"Asia/Dhaka",
    "iso:country":"BD",
    "wof:name":"Bhandarkhola",
    "wof:placetype":"locality"
},
  "geometry": {"coordinates":[89.81511999999999,22.90641],"type":"Point"}
}