{
  "type": "Feature",
  "properties": {
    "gn:admin1_code":"87",
    "gn:admin2_code":"5532.0",
    "gn:admin3_code":"553282.0",
    "gn:admin4_code":"55328243.0",
    "gn:asciiname":"Chak Gobindapur",
    "gn:country_code":"BD",
    "gn:dem":27,
    "gn:feature_class":"P",
    "gn:feature_code":"PPL",
    "gn:name":"Chak Gobindapur",
    "gn:population":0,
    "gn:timezone":"Asia/Dhaka",
    "iso:country":"BD",
    "name:und_x_variant":[
        "Chak Gobind\u0101pur"
    ],
    "wof:name":"Chak Gobindapur",
    "wof:placetype":"locality"
},
  "geometry": {"coordinates":[89.38455999999999,25.38315],"type":"Point"}
}