{
  "type": "Feature",
  "properties": {
    "gn:admin1_code":"82",
    "gn:admin2_code":"4050",
    "gn:admin3_code":"405094.0",
    "gn:admin4_code":"40509473.0",
    "gn:asciiname":"Simulia Phulbaria",
    "gn:country_code":"BD",
    "gn:dem":15,
    "gn:feature_class":"P",
    "gn:feature_code":"PPL",
    "gn:name":"Simulia Phulb\u0101ria",
    "gn:population":0,
    "gn:timezone":"Asia/Dhaka",
    "iso:country":"BD",
    "name:ben_x_preferred":[
        "Simulia Phulb\u0101ria"
    ],
    "name:ben_x_variant":[
        "Simulia Phulb\u0101ri"
    ],
    "name:und_x_variant":[
        "Simulia Fulbari"
    ],
    "wof:name":"Simulia Phulbaria",
    "wof:placetype":"locality"
},
  "geometry": {"coordinates":[89.00535000000001,23.91693],"type":"Point"}
}