{
  "type": "Feature",
  "properties": {
    "gn:admin1_code":"82",
    "gn:admin2_code":"4041.0",
    "gn:admin3_code":"404147.0",
    "gn:admin4_code":"40414735.0",
    "gn:asciiname":"Dattapara",
    "gn:country_code":"BD",
    "gn:dem":14,
    "gn:feature_class":"P",
    "gn:feature_code":"PPL",
    "gn:name":"Dattap\u0101ra",
    "gn:population":0,
    "gn:timezone":"Asia/Dhaka",
    "iso:country":"BD",
    "name:ben_x_preferred":[
        "Dattap\u0101ra"
    ],
    "wof:name":"Dattapara",
    "wof:placetype":"locality"
},
  "geometry": {"coordinates":[89.13866,23.14742],"type":"Point"}
}