{
  "type": "Feature",
  "properties": {
    "gn:admin1_code":"81",
    "gn:admin2_code":"3056",
    "gn:admin3_code":"305646.0",
    "gn:admin4_code":"30564600.0",
    "gn:asciiname":"Manara",
    "gn:country_code":"BD",
    "gn:dem":10,
    "gn:feature_class":"P",
    "gn:feature_code":"PPL",
    "gn:name":"M\u0101nara",
    "gn:population":0,
    "gn:timezone":"Asia/Dhaka",
    "iso:country":"BD",
    "name:ceb_x_preferred":[
        "Manara"
    ],
    "name:ces_x_preferred":[
        "Manara"
    ],
    "name:deu_x_preferred":[
        "Manara"
    ],
    "name:fra_x_preferred":[
        "Manara"
    ],
    "name:heb_x_preferred":[
        "\u05de\u05e0\u05e8\u05d4"
    ],
    "name:ita_x_preferred":[
        "Manara"
    ],
    "name:kor_x_preferred":[
        "\ub9c8\ub098\ub77c"
    ],
    "name:new_x_preferred":[
        "\u092e\u0928\u0947\u0930\u093e"
    ],
    "name:por_x_preferred":[
        "Manara"
    ],
    "name:rus_x_preferred":[
        "\u041c\u0430\u043d\u0430\u0440\u0430"
    ],
    "name:swe_x_preferred":[
        "Manara"
    ],
    "wof:name":"Manara",
    "wof:placetype":"locality"
},
  "geometry": {"coordinates":[89.98333000000002,23.86667000000001],"type":"Point"}
}