{
  "type": "Feature",
  "properties": {
    "gn:admin1_code":"82",
    "gn:admin2_code":"4057.0",
    "gn:admin3_code":"405747.0",
    "gn:admin4_code":"40574742.0",
    "gn:asciiname":"Nayapara",
    "gn:country_code":"BD",
    "gn:dem":20,
    "gn:feature_class":"P",
    "gn:feature_code":"PPL",
    "gn:name":"Nayap\u0101ra",
    "gn:population":0,
    "gn:timezone":"Asia/Dhaka",
    "iso:country":"BD",
    "name:ben_x_preferred":[
        "Nayap\u0101ra"
    ],
    "wof:name":"Nayapara",
    "wof:placetype":"locality"
},
  "geometry": {"coordinates":[88.69807,23.85182],"type":"Point"}
}