{
  "type": "Feature",
  "properties": {
    "gn:admin1_code":"82",
    "gn:asciiname":"Golbunia",
    "gn:country_code":"BD",
    "gn:dem":9,
    "gn:feature_class":"P",
    "gn:feature_code":"PPL",
    "gn:name":"Golbunia",
    "gn:population":0,
    "gn:timezone":"Asia/Dhaka",
    "iso:country":"BD",
    "name:ben_x_preferred":[
        "Golbunia"
    ],
    "wof:name":"Golbunia",
    "wof:placetype":"locality"
},
  "geometry": {"coordinates":[89.88229,22.24365],"type":"Point"}
}