{
  "type": "Feature",
  "properties": {
    "gn:admin1_code":"82",
    "gn:admin2_code":"4065.0",
    "gn:admin3_code":"406576.0",
    "gn:admin4_code":"40657633.0",
    "gn:asciiname":"Kuralia",
    "gn:country_code":"BD",
    "gn:dem":12,
    "gn:feature_class":"P",
    "gn:feature_code":"PPL",
    "gn:name":"Kur\u0101lia",
    "gn:population":0,
    "gn:timezone":"Asia/Dhaka",
    "iso:country":"BD",
    "name:ben_x_preferred":[
        "Kur\u0101lia"
    ],
    "wof:name":"Kuralia",
    "wof:placetype":"locality"
},
  "geometry": {"coordinates":[89.55535,23.22334],"type":"Point"}
}