{
  "type": "Feature",
  "properties": {
    "gn:admin1_code":"87",
    "gn:admin2_code":"5527.0",
    "gn:admin3_code":"552764.0",
    "gn:admin4_code":"55276469.0",
    "gn:asciiname":"Ashkarpur",
    "gn:country_code":"BD",
    "gn:dem":36,
    "gn:feature_class":"P",
    "gn:feature_code":"PPL",
    "gn:name":"Ashk\u0101rpur",
    "gn:population":0,
    "gn:timezone":"Asia/Dhaka",
    "iso:country":"BD",
    "name:ben_x_preferred":[
        "Ashk\u0101rpur"
    ],
    "wof:name":"Ashkarpur",
    "wof:placetype":"locality"
},
  "geometry": {"coordinates":[88.66858000000001,25.57013],"type":"Point"}
}