{
  "type": "Feature",
  "properties": {
    "gn:admin1_code":"85",
    "gn:admin2_code":"1006.0",
    "gn:admin3_code":"100607.0",
    "gn:admin4_code":"10060754.0",
    "gn:asciiname":"Gabhikhola",
    "gn:country_code":"BD",
    "gn:dem":8,
    "gn:feature_class":"P",
    "gn:feature_code":"PPL",
    "gn:name":"G\u0101bhikhola",
    "gn:population":0,
    "gn:timezone":"Asia/Dhaka",
    "iso:country":"BD",
    "wof:name":"Gabhikhola",
    "wof:placetype":"locality"
},
  "geometry": {"coordinates":[90.38342,22.56003],"type":"Point"}
}