{
  "type": "Feature",
  "properties": {
    "gn:admin1_code":"84",
    "gn:admin2_code":"2015.0",
    "gn:admin3_code":"201533.0",
    "gn:admin4_code":"20153371.0",
    "gn:asciiname":"Barajali",
    "gn:country_code":"BD",
    "gn:dem":21,
    "gn:feature_class":"P",
    "gn:feature_code":"PPL",
    "gn:name":"Baraj\u0101li",
    "gn:population":0,
    "gn:timezone":"Asia/Dhaka",
    "iso:country":"BD",
    "name:ben_x_preferred":[
        "Baraj\u0101li"
    ],
    "wof:name":"Barajali",
    "wof:placetype":"locality"
},
  "geometry": {"coordinates":[91.80664,22.73352],"type":"Point"}
}