{
  "type": "Feature",
  "properties": {
    "gn:admin1_code":"83",
    "gn:admin2_code":"5088",
    "gn:admin3_code":"508850.0",
    "gn:admin4_code":"50885017.0",
    "gn:asciiname":"Kabihar",
    "gn:country_code":"BD",
    "gn:dem":20,
    "gn:feature_class":"P",
    "gn:feature_code":"PPL",
    "gn:name":"Kabih\u0101r",
    "gn:population":0,
    "gn:timezone":"Asia/Dhaka",
    "iso:country":"BD",
    "wof:name":"Kabihar",
    "wof:placetype":"locality"
},
  "geometry": {"coordinates":[89.62987,24.66012000000001],"type":"Point"}
}