{
  "type": "Feature",
  "properties": {
    "gn:admin1_code":"85",
    "gn:admin2_code":"1009.0",
    "gn:admin3_code":"100921.0",
    "gn:admin4_code":"10092109.0",
    "gn:asciiname":"Bara Manika",
    "gn:country_code":"BD",
    "gn:dem":10,
    "gn:feature_class":"P",
    "gn:feature_code":"PPL",
    "gn:name":"Bara M\u0101nika",
    "gn:population":0,
    "gn:timezone":"Asia/Dhaka",
    "iso:country":"BD",
    "name:und_x_variant":[
        "Bara M\u0101nika"
    ],
    "wof:name":"Bara Manika",
    "wof:placetype":"locality"
},
  "geometry": {"coordinates":[90.72609,22.55753],"type":"Point"}
}