{
  "type": "Feature",
  "properties": {
    "gn:admin1_code":"87",
    "gn:admin2_code":"5527.0",
    "gn:admin3_code":"552764.0",
    "gn:admin4_code":"55276417.0",
    "gn:asciiname":"Balaiapukur",
    "gn:country_code":"BD",
    "gn:dem":36,
    "gn:feature_class":"P",
    "gn:feature_code":"PPL",
    "gn:name":"Balaiapukur",
    "gn:population":0,
    "gn:timezone":"Asia/Dhaka",
    "iso:country":"BD",
    "name:ben_x_preferred":[
        "Balaiapukur"
    ],
    "wof:name":"Balaiapukur",
    "wof:placetype":"locality"
},
  "geometry": {"coordinates":[88.60805999999999,25.54604],"type":"Point"}
}