{
  "type": "Feature",
  "properties": {
    "gn:admin1_code":"81",
    "gn:admin2_code":"3048.0",
    "gn:admin3_code":"304806.0",
    "gn:admin4_code":"30480686.0",
    "gn:asciiname":"Chhota Gajara",
    "gn:country_code":"BD",
    "gn:dem":16,
    "gn:feature_class":"P",
    "gn:feature_code":"PPL",
    "gn:name":"Chhota Gaj\u0101ra",
    "gn:population":0,
    "gn:timezone":"Asia/Dhaka",
    "iso:country":"BD",
    "wof:name":"Chhota Gajara",
    "wof:placetype":"locality"
},
  "geometry": {"coordinates":[90.83278,24.22925],"type":"Point"}
}