{
  "type": "Feature",
  "properties": {
    "gn:admin1_code":"83",
    "gn:admin2_code":"5069.0",
    "gn:admin3_code":"506963.0",
    "gn:admin4_code":"50696314.0",
    "gn:asciiname":"Basudebpur",
    "gn:country_code":"BD",
    "gn:dem":17,
    "gn:feature_class":"P",
    "gn:feature_code":"PPL",
    "gn:name":"B\u0101sudebpur",
    "gn:population":0,
    "gn:timezone":"Asia/Dhaka",
    "iso:country":"BD",
    "name:ben_x_preferred":[
        "B\u0101sudebpur"
    ],
    "name:und_x_variant":[
        "Basudepur"
    ],
    "wof:name":"Basudebpur",
    "wof:placetype":"locality"
},
  "geometry": {"coordinates":[88.96456999999999,24.47471],"type":"Point"}
}