{
  "type": "Feature",
  "properties": {
    "gn:admin1_code":"82",
    "gn:admin2_code":"4050",
    "gn:admin3_code":"405079.0",
    "gn:admin4_code":"40507918.0",
    "gn:asciiname":"Swastipur",
    "gn:country_code":"BD",
    "gn:dem":18,
    "gn:feature_class":"P",
    "gn:feature_code":"PPL",
    "gn:name":"Swastipur",
    "gn:population":0,
    "gn:timezone":"Asia/Dhaka",
    "iso:country":"BD",
    "name:ben_x_preferred":[
        "Swastipur"
    ],
    "wof:name":"Swastipur",
    "wof:placetype":"locality"
},
  "geometry": {"coordinates":[89.09966999999997,23.83856],"type":"Point"}
}