{
  "type": "Feature",
  "properties": {
    "gn:admin1_code":"84",
    "gn:admin2_code":"2019.0",
    "gn:admin3_code":"201918.0",
    "gn:admin4_code":"20191872.0",
    "gn:asciiname":"Baher Char",
    "gn:country_code":"BD",
    "gn:dem":15,
    "gn:feature_class":"P",
    "gn:feature_code":"PPL",
    "gn:name":"B\u0101her Char",
    "gn:population":0,
    "gn:timezone":"Asia/Dhaka",
    "iso:country":"BD",
    "wof:name":"Baher Char",
    "wof:placetype":"locality"
},
  "geometry": {"coordinates":[91.09999999999999,23.53333],"type":"Point"}
}