{
  "type": "Feature",
  "properties": {
    "gn:admin1_code":"82",
    "gn:admin2_code":"4047.0",
    "gn:admin3_code":"404764.0",
    "gn:admin4_code":"40476427.0",
    "gn:asciiname":"Bigardana",
    "gn:country_code":"BD",
    "gn:dem":5,
    "gn:feature_class":"P",
    "gn:feature_code":"PPL",
    "gn:name":"Bigard\u0101na",
    "gn:population":0,
    "gn:timezone":"Asia/Dhaka",
    "iso:country":"BD",
    "wof:name":"Bigardana",
    "wof:placetype":"locality"
},
  "geometry": {"coordinates":[89.42325,22.62719],"type":"Point"}
}