{
  "type": "Feature",
  "properties": {
    "gn:admin1_code":"81",
    "gn:admin2_code":"3029.0",
    "gn:admin3_code":"302903.0",
    "gn:admin4_code":"30290331.0",
    "gn:asciiname":"Barankula",
    "gn:country_code":"BD",
    "gn:dem":14,
    "gn:feature_class":"P",
    "gn:feature_code":"PPL",
    "gn:name":"B\u0101r\u0101nkula",
    "gn:population":0,
    "gn:timezone":"Asia/Dhaka",
    "iso:country":"BD",
    "wof:name":"Barankula",
    "wof:placetype":"locality"
},
  "geometry": {"coordinates":[89.68925,23.32839],"type":"Point"}
}