{
  "type": "Feature",
  "properties": {
    "gn:admin1_code":"83",
    "gn:admin2_code":"5081.0",
    "gn:admin3_code":"508194.0",
    "gn:admin4_code":"50819427.0",
    "gn:asciiname":"Diara",
    "gn:country_code":"BD",
    "gn:dem":35,
    "gn:feature_class":"P",
    "gn:feature_code":"PPL",
    "gn:name":"Di\u0101ra",
    "gn:population":0,
    "gn:timezone":"Asia/Dhaka",
    "iso:country":"BD",
    "name:ben_x_preferred":[
        "Di\u0101ra"
    ],
    "wof:name":"Diara",
    "wof:placetype":"locality"
},
  "geometry": {"coordinates":[88.49644000000001,24.66807],"type":"Point"}
}