{
  "type": "Feature",
  "properties": {
    "gn:admin1_code":"81",
    "gn:admin2_code":"3033.0",
    "gn:admin3_code":"303336.0",
    "gn:admin4_code":"30333608.0",
    "gn:asciiname":"Bhikartek",
    "gn:country_code":"BD",
    "gn:dem":9,
    "gn:feature_class":"P",
    "gn:feature_code":"PPL",
    "gn:name":"Bhik\u0101rtek",
    "gn:population":0,
    "gn:timezone":"Asia/Dhaka",
    "iso:country":"BD",
    "wof:name":"Bhikartek",
    "wof:placetype":"locality"
},
  "geometry": {"coordinates":[90.65742,24.20293],"type":"Point"}
}