{
  "type": "Feature",
  "properties": {
    "gn:admin1_code":"82",
    "gn:admin2_code":"4065.0",
    "gn:admin3_code":"406528.0",
    "gn:admin4_code":"40652800.0",
    "gn:asciiname":"Uthali",
    "gn:country_code":"BD",
    "gn:dem":9,
    "gn:feature_class":"P",
    "gn:feature_code":"PPL",
    "gn:name":"Uthali",
    "gn:population":0,
    "gn:timezone":"Asia/Dhaka",
    "iso:country":"BD",
    "name:ben_x_preferred":[
        "Uthali"
    ],
    "wof:name":"Uthali",
    "wof:placetype":"locality"
},
  "geometry": {"coordinates":[89.62045999999999,23.03838],"type":"Point"}
}