{
  "type": "Feature",
  "properties": {
    "gn:admin1_code":"81",
    "gn:admin2_code":"3059.0",
    "gn:admin3_code":"305984.0",
    "gn:admin4_code":"30598433.0",
    "gn:asciiname":"Charigaon",
    "gn:country_code":"BD",
    "gn:dem":10,
    "gn:feature_class":"P",
    "gn:feature_code":"PPL",
    "gn:name":"Ch\u0101rigaon",
    "gn:population":0,
    "gn:timezone":"Asia/Dhaka",
    "iso:country":"BD",
    "wof:name":"Charigaon",
    "wof:placetype":"locality"
},
  "geometry": {"coordinates":[90.33805,23.59058],"type":"Point"}
}