{
  "type": "Feature",
  "properties": {
    "gn:admin1_code":"81",
    "gn:admin2_code":"3068",
    "gn:admin3_code":"306864.0",
    "gn:admin4_code":"30686457.0",
    "gn:asciiname":"Kukurmara",
    "gn:country_code":"BD",
    "gn:dem":14,
    "gn:feature_class":"P",
    "gn:feature_code":"PPL",
    "gn:name":"Kukurm\u0101ra",
    "gn:population":0,
    "gn:timezone":"Asia/Dhaka",
    "iso:country":"BD",
    "wof:name":"Kukurmara",
    "wof:placetype":"locality"
},
  "geometry": {"coordinates":[90.92233,24.04931],"type":"Point"}
}