{
  "type": "Feature",
  "properties": {
    "gn:admin1_code":"81",
    "gn:admin2_code":"3082",
    "gn:admin3_code":"308207.0",
    "gn:admin4_code":"30820766.0",
    "gn:asciiname":"Jangal",
    "gn:country_code":"BD",
    "gn:dem":15,
    "gn:feature_class":"P",
    "gn:feature_code":"PPL",
    "gn:name":"Jangal",
    "gn:population":0,
    "gn:timezone":"Asia/Dhaka",
    "iso:country":"BD",
    "name:ara_x_preferred":[
        "\u062c\u0646\u063a\u0644"
    ],
    "name:aze_x_preferred":[
        "C\u0259ng\u0259l"
    ],
    "name:ceb_x_preferred":[
        "Jangal"
    ],
    "name:fas_x_preferred":[
        "\u062c\u0646\u06af\u0644"
    ],
    "name:ita_x_preferred":[
        "Jangal"
    ],
    "name:mlg_x_preferred":[
        "Jangal"
    ],
    "name:swe_x_preferred":[
        "Jangal"
    ],
    "name:tur_x_preferred":[
        "Cengel"
    ],
    "wof:name":"Jangal",
    "wof:placetype":"locality"
},
  "geometry": {"coordinates":[89.51326999999998,23.61662],"type":"Point"}
}