{
  "type": "Feature",
  "properties": {
    "gn:admin1_code":"82",
    "gn:admin2_code":"4050.0",
    "gn:admin3_code":"405071.0",
    "gn:admin4_code":"40507108.0",
    "gn:asciiname":"Dudkumra",
    "gn:country_code":"BD",
    "gn:dem":15,
    "gn:feature_class":"P",
    "gn:feature_code":"PPL",
    "gn:name":"Dudkumra",
    "gn:population":0,
    "gn:timezone":"Asia/Dhaka",
    "iso:country":"BD",
    "name:ben_x_preferred":[
        "Dudkumra"
    ],
    "wof:name":"Dudkumra",
    "wof:placetype":"locality"
},
  "geometry": {"coordinates":[89.16435,23.84218],"type":"Point"}
}