{
  "type": "Feature",
  "properties": {
    "gn:admin1_code":"83",
    "gn:admin2_code":"5081.0",
    "gn:admin3_code":"508194.0",
    "gn:admin4_code":"50819467.0",
    "gn:asciiname":"Buruz",
    "gn:country_code":"BD",
    "gn:dem":22,
    "gn:feature_class":"P",
    "gn:feature_code":"PPL",
    "gn:name":"Buruz",
    "gn:population":0,
    "gn:timezone":"Asia/Dhaka",
    "iso:country":"BD",
    "name:ben_x_preferred":[
        "Buruz"
    ],
    "wof:name":"Buruz",
    "wof:placetype":"locality"
},
  "geometry": {"coordinates":[88.58150000000001,24.5484],"type":"Point"}
}