{
  "type": "Feature",
  "properties": {
    "gn:admin1_code":"87",
    "gn:admin2_code":"5549",
    "gn:admin3_code":"554952.0",
    "gn:admin4_code":"55495209.0",
    "gn:asciiname":"Muitarani",
    "gn:country_code":"BD",
    "gn:dem":33,
    "gn:feature_class":"P",
    "gn:feature_code":"PPL",
    "gn:name":"Muitarani",
    "gn:population":0,
    "gn:timezone":"Asia/Dhaka",
    "iso:country":"BD",
    "name:ben_x_preferred":[
        "Muitarani"
    ],
    "wof:name":"Muitarani",
    "wof:placetype":"locality"
},
  "geometry": {"coordinates":[89.61386999999998,25.81194],"type":"Point"}
}