{
  "type": "Feature",
  "properties": {
    "gn:admin1_code":"82",
    "gn:admin2_code":"4047",
    "gn:admin3_code":"404712.0",
    "gn:admin4_code":"40471283.0",
    "gn:asciiname":"Ruhitmara",
    "gn:country_code":"BD",
    "gn:dem":5,
    "gn:feature_class":"P",
    "gn:feature_code":"PPL",
    "gn:name":"Ruhitm\u0101ra",
    "gn:population":0,
    "gn:timezone":"Asia/Dhaka",
    "iso:country":"BD",
    "wof:name":"Ruhitmara",
    "wof:placetype":"locality"
},
  "geometry": {"coordinates":[89.41667,22.65],"type":"Point"}
}