{
  "type": "Feature",
  "properties": {
    "gn:admin1_code":"82",
    "gn:admin2_code":"4050.0",
    "gn:admin3_code":"405063.0",
    "gn:admin4_code":"40506323.0",
    "gn:asciiname":"Beyara",
    "gn:country_code":"BD",
    "gn:dem":17,
    "gn:feature_class":"P",
    "gn:feature_code":"PPL",
    "gn:name":"Bey\u0101ra",
    "gn:population":0,
    "gn:timezone":"Asia/Dhaka",
    "iso:country":"BD",
    "name:und_x_variant":[
        "Beara",
        "Bey\u0101ra"
    ],
    "wof:name":"Beyara",
    "wof:placetype":"locality"
},
  "geometry": {"coordinates":[89.31605,23.75952],"type":"Point"}
}