{
  "type": "Feature",
  "properties": {
    "gn:admin1_code":"81",
    "gn:admin2_code":"3093",
    "gn:admin3_code":"309319.0",
    "gn:admin4_code":"30931954.0",
    "gn:asciiname":"Rayer Basalia",
    "gn:country_code":"BD",
    "gn:dem":21,
    "gn:feature_class":"P",
    "gn:feature_code":"PPL",
    "gn:name":"R\u0101yer B\u0101s\u0101lia",
    "gn:population":0,
    "gn:timezone":"Asia/Dhaka",
    "iso:country":"BD",
    "wof:name":"Rayer Basalia",
    "wof:placetype":"locality"
},
  "geometry": {"coordinates":[89.8484,24.48707000000001],"type":"Point"}
}