{
  "type": "Feature",
  "properties": {
    "gn:admin1_code":"84",
    "gn:admin2_code":"2019",
    "gn:admin3_code":"201936.0",
    "gn:admin4_code":"20193673.0",
    "gn:asciiname":"Lakhaitali",
    "gn:country_code":"BD",
    "gn:dem":10,
    "gn:feature_class":"P",
    "gn:feature_code":"PPL",
    "gn:name":"Lakh\u0101itali",
    "gn:population":0,
    "gn:timezone":"Asia/Dhaka",
    "iso:country":"BD",
    "wof:name":"Lakhaitali",
    "wof:placetype":"locality"
},
  "geometry": {"coordinates":[90.84867,23.49798],"type":"Point"}
}