{
  "type": "Feature",
  "properties": {
    "gn:admin1_code":"84",
    "gn:admin2_code":"2015.0",
    "gn:admin3_code":"201561.0",
    "gn:admin4_code":"20156164.0",
    "gn:asciiname":"Budhupara",
    "gn:country_code":"BD",
    "gn:dem":5,
    "gn:feature_class":"P",
    "gn:feature_code":"PPL",
    "gn:name":"Budhup\u0101ra",
    "gn:population":0,
    "gn:timezone":"Asia/Dhaka",
    "iso:country":"BD",
    "name:ben_x_preferred":[
        "Budhup\u0101ra"
    ],
    "name:und_x_variant":[
        "Budhpara",
        "Budhpura"
    ],
    "wof:name":"Budhupara",
    "wof:placetype":"locality"
},
  "geometry": {"coordinates":[91.91453,22.27366],"type":"Point"}
}