{
  "type": "Feature",
  "properties": {
    "gn:admin1_code":"87",
    "gn:admin2_code":"5532",
    "gn:admin3_code":"553230.0",
    "gn:admin4_code":"55323022.0",
    "gn:asciiname":"Kroragachha",
    "gn:country_code":"BD",
    "gn:dem":22,
    "gn:feature_class":"P",
    "gn:feature_code":"PPL",
    "gn:name":"Kror\u0101g\u0101chha",
    "gn:population":0,
    "gn:timezone":"Asia/Dhaka",
    "iso:country":"BD",
    "name:und_x_variant":[
        "Kror\u0101g\u0101chha",
        "Krorg\u0101chha"
    ],
    "wof:name":"Kroragachha",
    "wof:placetype":"locality"
},
  "geometry": {"coordinates":[89.48053,25.19613],"type":"Point"}
}