{
  "type": "Feature",
  "properties": {
    "gn:admin1_code":"87",
    "gn:admin2_code":"5577.0",
    "gn:admin3_code":"557790.0",
    "gn:admin4_code":"55779040.0",
    "gn:asciiname":"Sukani",
    "gn:country_code":"BD",
    "gn:dem":93,
    "gn:feature_class":"P",
    "gn:feature_code":"PPL",
    "gn:name":"Suk\u0101ni",
    "gn:population":0,
    "gn:timezone":"Asia/Dhaka",
    "iso:country":"BD",
    "name:ben_x_preferred":[
        "Suk\u0101ni"
    ],
    "wof:name":"Sukani",
    "wof:placetype":"locality"
},
  "geometry": {"coordinates":[88.51524000000001,26.50671],"type":"Point"}
}