{
  "type": "Feature",
  "properties": {
    "gn:admin1_code":"H",
    "gn:admin2_code":"3039.0",
    "gn:admin3_code":"303936.0",
    "gn:admin4_code":"30393641.0",
    "gn:asciiname":"Baruamari",
    "gn:country_code":"BD",
    "gn:dem":23,
    "gn:feature_class":"P",
    "gn:feature_code":"PPL",
    "gn:name":"Baru\u0101m\u0101ri",
    "gn:population":0,
    "gn:timezone":"Asia/Dhaka",
    "iso:country":"BD",
    "wof:name":"Baruamari",
    "wof:placetype":"locality"
},
  "geometry": {"coordinates":[90.02374,24.8996],"type":"Point"}
}