{
  "type": "Feature",
  "properties": {
    "gn:admin1_code":"H",
    "gn:admin2_code":"3072",
    "gn:admin3_code":"307209.0",
    "gn:admin4_code":"30720911.0",
    "gn:asciiname":"Ujangaon",
    "gn:country_code":"BD",
    "gn:dem":13,
    "gn:feature_class":"P",
    "gn:feature_code":"PPL",
    "gn:name":"Uj\u0101ngaon",
    "gn:population":0,
    "gn:timezone":"Asia/Dhaka",
    "iso:country":"BD",
    "name:und_x_variant":[
        "Ujangaon Bahirkanda",
        "Uj\u0101ngaon"
    ],
    "wof:name":"Ujangaon",
    "wof:placetype":"locality"
},
  "geometry": {"coordinates":[90.9119,24.96386],"type":"Point"}
}