{
  "type": "Feature",
  "properties": {
    "gn:admin1_code":"84",
    "gn:admin2_code":"2015.0",
    "gn:admin3_code":"201582.0",
    "gn:admin4_code":"20158254.0",
    "gn:asciiname":"Temohini",
    "gn:country_code":"BD",
    "gn:dem":8,
    "gn:feature_class":"P",
    "gn:feature_code":"PPL",
    "gn:name":"Temohini",
    "gn:population":0,
    "gn:timezone":"Asia/Dhaka",
    "iso:country":"BD",
    "name:ben_x_preferred":[
        "Temohini"
    ],
    "wof:name":"Temohini",
    "wof:placetype":"locality"
},
  "geometry": {"coordinates":[92.07980000000001,22.12428],"type":"Point"}
}