{
  "type": "Feature",
  "properties": {
    "gn:admin1_code":"81",
    "gn:admin2_code":"3068.0",
    "gn:admin3_code":"306807.0",
    "gn:admin4_code":"30680771.0",
    "gn:asciiname":"Galgalia",
    "gn:country_code":"BD",
    "gn:dem":17,
    "gn:feature_class":"P",
    "gn:feature_code":"PPL",
    "gn:name":"Galgalia",
    "gn:population":0,
    "gn:timezone":"Asia/Dhaka",
    "iso:country":"BD",
    "wof:name":"Galgalia",
    "wof:placetype":"locality"
},
  "geometry": {"coordinates":[90.79445,24.16078],"type":"Point"}
}