{
  "type": "Feature",
  "properties": {
    "gn:admin1_code":"84",
    "gn:admin2_code":"2019.0",
    "gn:admin3_code":"201940.0",
    "gn:admin4_code":"20194071.0",
    "gn:asciiname":"Dhalkarpara",
    "gn:country_code":"BD",
    "gn:dem":9,
    "gn:feature_class":"P",
    "gn:feature_code":"PPL",
    "gn:name":"Dh\u0101lkarp\u0101ra",
    "gn:population":0,
    "gn:timezone":"Asia/Dhaka",
    "iso:country":"BD",
    "wof:name":"Dhalkarpara",
    "wof:placetype":"locality"
},
  "geometry": {"coordinates":[91.05,23.56667],"type":"Point"}
}