{
  "type": "Feature",
  "properties": {
    "gn:admin1_code":"87",
    "gn:admin2_code":"5549",
    "gn:admin3_code":"554977.0",
    "gn:admin4_code":"55497742.0",
    "gn:asciiname":"Khitab Khan",
    "gn:country_code":"BD",
    "gn:dem":36,
    "gn:feature_class":"P",
    "gn:feature_code":"PPL",
    "gn:name":"Khitab Kh\u0101n",
    "gn:population":0,
    "gn:timezone":"Asia/Dhaka",
    "iso:country":"BD",
    "name:ben_x_preferred":[
        "Khitab Kh\u0101n"
    ],
    "wof:name":"Khitab Khan",
    "wof:placetype":"locality"
},
  "geometry": {"coordinates":[89.50291999999997,25.77742000000001],"type":"Point"}
}