{
  "type": "Feature",
  "properties": {
    "gn:admin1_code":"85",
    "gn:admin2_code":"1006.0",
    "gn:admin3_code":"100651.0",
    "gn:admin4_code":"10065117.0",
    "gn:asciiname":"Durgapur",
    "gn:country_code":"BD",
    "gn:dem":11,
    "gn:feature_class":"P",
    "gn:feature_code":"PPL",
    "gn:name":"Durg\u0101pur",
    "gn:population":0,
    "gn:timezone":"Asia/Dhaka",
    "iso:country":"BD",
    "wof:name":"Durgapur",
    "wof:placetype":"locality"
},
  "geometry": {"coordinates":[90.42099,22.69178],"type":"Point"}
}