{
  "type": "Feature",
  "properties": {
    "gn:admin1_code":"82",
    "gn:admin2_code":"4018.0",
    "gn:admin3_code":"401823.0",
    "gn:admin4_code":"40182323.0",
    "gn:asciiname":"Kotali",
    "gn:country_code":"BD",
    "gn:dem":17,
    "gn:feature_class":"P",
    "gn:feature_code":"PPL",
    "gn:name":"Kot\u0101li",
    "gn:population":0,
    "gn:timezone":"Asia/Dhaka",
    "iso:country":"BD",
    "name:ben_x_preferred":[
        "Kot\u0101li"
    ],
    "wof:name":"Kotali",
    "wof:placetype":"locality"
},
  "geometry": {"coordinates":[88.85544,23.53352000000001],"type":"Point"}
}