{
  "type": "Feature",
  "properties": {
    "gn:admin1_code":"84",
    "gn:admin2_code":"2003.0",
    "gn:admin3_code":"200314.0",
    "gn:admin4_code":"20031431.0",
    "gn:asciiname":"Bakioharapara",
    "gn:country_code":"BD",
    "gn:dem":35,
    "gn:feature_class":"P",
    "gn:feature_code":"PPL",
    "gn:name":"Bakioharap\u0101ra",
    "gn:population":0,
    "gn:timezone":"Asia/Dhaka",
    "iso:country":"BD",
    "name:ben_x_preferred":[
        "Bakioharap\u0101ra"
    ],
    "wof:name":"Bakioharapara",
    "wof:placetype":"locality"
},
  "geometry": {"coordinates":[92.18028,22.25768],"type":"Point"}
}