{
  "type": "Feature",
  "properties": {
    "gn:admin1_code":"81",
    "gn:admin2_code":"3056.0",
    "gn:admin3_code":"305622.0",
    "gn:admin4_code":"30562283.0",
    "gn:asciiname":"Char Garpara",
    "gn:country_code":"BD",
    "gn:dem":12,
    "gn:feature_class":"P",
    "gn:feature_code":"PPL",
    "gn:name":"Char Garp\u0101ra",
    "gn:population":0,
    "gn:timezone":"Asia/Dhaka",
    "iso:country":"BD",
    "wof:name":"Char Garpara",
    "wof:placetype":"locality"
},
  "geometry": {"coordinates":[89.95161999999998,23.89076],"type":"Point"}
}