{
  "type": "Feature",
  "properties": {
    "gn:admin1_code":"81",
    "gn:admin2_code":"3068.0",
    "gn:admin3_code":"306852.0",
    "gn:admin4_code":"30685254.0",
    "gn:asciiname":"Bilagi",
    "gn:country_code":"BD",
    "gn:dem":14,
    "gn:feature_class":"P",
    "gn:feature_code":"PPL",
    "gn:name":"Bil\u0101gi",
    "gn:population":0,
    "gn:timezone":"Asia/Dhaka",
    "iso:country":"BD",
    "name:ceb_x_preferred":[
        "Bilgi"
    ],
    "name:ita_x_preferred":[
        "Bilgi"
    ],
    "name:kan_x_preferred":[
        "\u0cac\u0cc0\u0cb3\u0c97\u0cbf"
    ],
    "name:msa_x_preferred":[
        "Bilgi"
    ],
    "name:nld_x_preferred":[
        "Bilgi"
    ],
    "name:vie_x_preferred":[
        "Bilgi"
    ],
    "name:zho_x_preferred":[
        "\u6bd4\u5c14\u5409"
    ],
    "wof:name":"Bilagi",
    "wof:placetype":"locality"
},
  "geometry": {"coordinates":[90.71259999999999,24.0926],"type":"Point"}
}