{
  "type": "Feature",
  "properties": {
    "gn:admin1_code":"83",
    "gn:admin2_code":"5081.0",
    "gn:admin3_code":"508112.0",
    "gn:admin4_code":"50811275.0",
    "gn:asciiname":"Daspara",
    "gn:country_code":"BD",
    "gn:dem":18,
    "gn:feature_class":"P",
    "gn:feature_code":"PPL",
    "gn:name":"D\u0101spara",
    "gn:population":0,
    "gn:timezone":"Asia/Dhaka",
    "iso:country":"BD",
    "name:ben_x_preferred":[
        "D\u0101spara"
    ],
    "wof:name":"Daspara",
    "wof:placetype":"locality"
},
  "geometry": {"coordinates":[88.83598000000001,24.58713],"type":"Point"}
}