{
  "type": "Feature",
  "properties": {
    "gn:admin1_code":"84",
    "gn:admin2_code":"2013.0",
    "gn:admin3_code":"201395.0",
    "gn:admin4_code":"20139585.0",
    "gn:asciiname":"Ghoramaydan",
    "gn:country_code":"BD",
    "gn:dem":10,
    "gn:feature_class":"P",
    "gn:feature_code":"PPL",
    "gn:name":"Ghor\u0101mayd\u0101n",
    "gn:population":0,
    "gn:timezone":"Asia/Dhaka",
    "iso:country":"BD",
    "name:und_x_variant":[
        "Ghoramaidan",
        "Ghor\u0101mayd\u0101n"
    ],
    "wof:name":"Ghoramaydan",
    "wof:placetype":"locality"
},
  "geometry": {"coordinates":[90.95225000000001,23.19013],"type":"Point"}
}