{
  "type": "Feature",
  "properties": {
    "gn:admin1_code":"82",
    "gn:admin2_code":"4050.0",
    "gn:admin3_code":"405071.0",
    "gn:admin4_code":"40507151.0",
    "gn:asciiname":"Baniapara",
    "gn:country_code":"BD",
    "gn:dem":19,
    "gn:feature_class":"P",
    "gn:feature_code":"PPL",
    "gn:name":"Baniapara",
    "gn:population":0,
    "gn:timezone":"Asia/Dhaka",
    "iso:country":"BD",
    "name:ben_x_preferred":[
        "Baniapara"
    ],
    "wof:name":"Baniapara",
    "wof:placetype":"locality"
},
  "geometry": {"coordinates":[89.15468,23.91568],"type":"Point"}
}