{
  "type": "Feature",
  "properties": {
    "gn:admin1_code":"84",
    "gn:admin2_code":"2022.0",
    "gn:admin3_code":"202224.0",
    "gn:admin4_code":"20222405.0",
    "gn:asciiname":"Khuizapara",
    "gn:country_code":"BD",
    "gn:dem":7,
    "gn:feature_class":"P",
    "gn:feature_code":"PPL",
    "gn:name":"Khuiz\u0101p\u0101ra",
    "gn:population":0,
    "gn:timezone":"Asia/Dhaka",
    "iso:country":"BD",
    "name:ben_x_preferred":[
        "Khuiz\u0101p\u0101ra"
    ],
    "wof:name":"Khuizapara",
    "wof:placetype":"locality"
},
  "geometry": {"coordinates":[92.05155000000001,21.49505],"type":"Point"}
}