{
  "type": "Feature",
  "properties": {
    "gn:admin1_code":"83",
    "gn:admin2_code":"5010",
    "gn:admin3_code":"501094.0",
    "gn:admin4_code":"50109447.0",
    "gn:asciiname":"Mahabbat Nandipur",
    "gn:country_code":"BD",
    "gn:dem":27,
    "gn:feature_class":"P",
    "gn:feature_code":"PPL",
    "gn:name":"Mahabbat Nandipur",
    "gn:population":0,
    "gn:timezone":"Asia/Dhaka",
    "iso:country":"BD",
    "name:ben_x_preferred":[
        "Mahabbat Nandipur"
    ],
    "wof:name":"Mahabbat Nandipur",
    "wof:placetype":"locality"
},
  "geometry": {"coordinates":[89.3399,25.08531],"type":"Point"}
}