{
  "type": "Feature",
  "properties": {
    "gn:admin1_code":"82",
    "gn:admin2_code":"4041.0",
    "gn:admin3_code":"404111.0",
    "gn:admin4_code":"40411160.0",
    "gn:asciiname":"Banurhuda",
    "gn:country_code":"BD",
    "gn:dem":15,
    "gn:feature_class":"P",
    "gn:feature_code":"PPL",
    "gn:name":"B\u0101nurhuda",
    "gn:population":0,
    "gn:timezone":"Asia/Dhaka",
    "iso:country":"BD",
    "name:ben_x_preferred":[
        "B\u0101nurhuda"
    ],
    "name:und_x_variant":[
        "Banurahuda"
    ],
    "wof:name":"Banurhuda",
    "wof:placetype":"locality"
},
  "geometry": {"coordinates":[89.0535,23.20452],"type":"Point"}
}