{
  "type": "Feature",
  "properties": {
    "gn:admin1_code":"82",
    "gn:admin2_code":"4055.0",
    "gn:admin3_code":"405585.0",
    "gn:admin4_code":"40558571.0",
    "gn:asciiname":"Deadanga",
    "gn:country_code":"BD",
    "gn:dem":10,
    "gn:feature_class":"P",
    "gn:feature_code":"PPL",
    "gn:name":"De\u0101d\u0101nga",
    "gn:population":0,
    "gn:timezone":"Asia/Dhaka",
    "iso:country":"BD",
    "name:ben_x_preferred":[
        "De\u0101d\u0101nga"
    ],
    "wof:name":"Deadanga",
    "wof:placetype":"locality"
},
  "geometry": {"coordinates":[89.35625,23.30802000000001],"type":"Point"}
}