{
  "type": "Feature",
  "properties": {
    "gn:admin1_code":"87",
    "gn:admin2_code":"5527.0",
    "gn:admin3_code":"552764.0",
    "gn:admin4_code":"55276434.0",
    "gn:asciiname":"Ramjibanpur",
    "gn:country_code":"BD",
    "gn:dem":41,
    "gn:feature_class":"P",
    "gn:feature_code":"PPL",
    "gn:name":"R\u0101mjibanpur",
    "gn:population":0,
    "gn:timezone":"Asia/Dhaka",
    "iso:country":"BD",
    "name:ben_x_preferred":[
        "R\u0101mjibanpur"
    ],
    "wof:name":"Ramjibanpur",
    "wof:placetype":"locality"
},
  "geometry": {"coordinates":[88.67577,25.68413],"type":"Point"}
}