{
  "type": "Feature",
  "properties": {
    "gn:admin1_code":"87",
    "gn:admin2_code":"5527.0",
    "gn:admin3_code":"552764.0",
    "gn:admin4_code":"55276434.0",
    "gn:asciiname":"Ramjibanpur",
    "gn:country_code":"BD",
    "gn:dem":41,
    "gn:feature_class":"P",
    "gn:feature_code":"PPL",
    "gn:name":"R\u0101mjibanpur",
    "gn:population":0,
    "gn:timezone":"Asia/Dhaka",
    "iso:country":"BD",
    "name:ben_x_preferred":[
        "R\u0101mjibanpur"
    ],
    "name:ben_x_variant":[
        "\u09b0\u09be\u09ae\u099c\u09c0\u09ac\u09a8\u09aa\u09c1\u09b0"
    ],
    "name:bpy_x_preferred":[
        "\u09b0\u09be\u09ae\u099c\u09bf\u09ac\u09a8\u09aa\u09c1\u09b0"
    ],
    "name:ceb_x_preferred":[
        "R\u0101mj\u012bbanpur"
    ],
    "name:ita_x_preferred":[
        "Ramjibanpur"
    ],
    "name:msa_x_preferred":[
        "Ramjibanpur"
    ],
    "name:por_x_preferred":[
        "Ramjibanpur"
    ],
    "name:swe_x_preferred":[
        "R\u0101mj\u012bbanpur"
    ],
    "name:vie_x_preferred":[
        "Ramjibanpur"
    ],
    "name:zho_x_preferred":[
        "\u62c9\u59c6\u5409\u73ed\u666e\u5c14"
    ],
    "wof:name":"Ramjibanpur",
    "wof:placetype":"locality"
},
  "geometry": {"coordinates":[88.67577,25.68413],"type":"Point"}
}