{
  "type": "Feature",
  "properties": {
    "gn:admin1_code":"87",
    "gn:admin2_code":"5527.0",
    "gn:admin3_code":"552717.0",
    "gn:admin4_code":"55271728.0",
    "gn:asciiname":"Kamarpara",
    "gn:country_code":"BD",
    "gn:dem":36,
    "gn:feature_class":"P",
    "gn:feature_code":"PPL",
    "gn:name":"K\u0101m\u0101rp\u0101ra",
    "gn:population":0,
    "gn:timezone":"Asia/Dhaka",
    "iso:country":"BD",
    "name:ben_x_preferred":[
        "K\u0101m\u0101rp\u0101ra"
    ],
    "wof:name":"Kamarpara",
    "wof:placetype":"locality"
},
  "geometry": {"coordinates":[88.55945,25.62867],"type":"Point"}
}