{
  "type": "Feature",
  "properties": {
    "gn:admin1_code":"83",
    "gn:admin2_code":"5064",
    "gn:admin3_code":"506403.0",
    "gn:admin4_code":"50640342.0",
    "gn:asciiname":"Khord Bandaikhara",
    "gn:cc2":"BD",
    "gn:country_code":"BD",
    "gn:dem":17,
    "gn:feature_class":"P",
    "gn:feature_code":"PPL",
    "gn:name":"Khord B\u0101nd\u0101ikh\u0101ra",
    "gn:population":0,
    "gn:timezone":"Asia/Dhaka",
    "iso:country":"BD",
    "name:und_x_variant":[
        "Khordabandaikhara",
        "Khord B\u0101nd\u0101ikh\u0101ra"
    ],
    "wof:name":"Khord Bandaikhara",
    "wof:placetype":"locality"
},
  "geometry": {"coordinates":[88.84999999999999,24.68333],"type":"Point"}
}