{
  "type": "Feature",
  "properties": {
    "gn:admin1_code":"81",
    "gn:admin2_code":"3035",
    "gn:admin3_code":"303558.0",
    "gn:admin4_code":"30355861.0",
    "gn:asciiname":"Lohair",
    "gn:country_code":"BD",
    "gn:dem":9,
    "gn:feature_class":"P",
    "gn:feature_code":"PPL",
    "gn:name":"Loh\u0101ir",
    "gn:population":0,
    "gn:timezone":"Asia/Dhaka",
    "iso:country":"BD",
    "wof:name":"Lohair",
    "wof:placetype":"locality"
},
  "geometry": {"coordinates":[89.94841,23.30408],"type":"Point"}
}