{
  "type": "Feature",
  "properties": {
    "gn:admin1_code":"84",
    "gn:admin2_code":"2075",
    "gn:admin3_code":"207587.0",
    "gn:admin4_code":"20758740.0",
    "gn:asciiname":"Manarkhil",
    "gn:country_code":"BD",
    "gn:dem":11,
    "gn:feature_class":"P",
    "gn:feature_code":"PPL",
    "gn:name":"Man\u0101rkhil",
    "gn:population":0,
    "gn:timezone":"Asia/Dhaka",
    "iso:country":"BD",
    "wof:name":"Manarkhil",
    "wof:placetype":"locality"
},
  "geometry": {"coordinates":[90.96798,22.85584],"type":"Point"}
}