{
  "type": "Feature",
  "properties": {
    "gn:admin1_code":"84",
    "gn:admin2_code":"2075",
    "gn:admin3_code":"207508.0",
    "gn:admin4_code":"20750891.0",
    "gn:asciiname":"Sonaimuri",
    "gn:country_code":"BD",
    "gn:dem":11,
    "gn:feature_class":"P",
    "gn:feature_code":"PPL",
    "gn:name":"Son\u0101imuri",
    "gn:population":0,
    "gn:timezone":"Asia/Dhaka",
    "iso:country":"BD",
    "wof:name":"Sonaimuri",
    "wof:placetype":"locality"
},
  "geometry": {"coordinates":[91.10048999999999,23.03317],"type":"Point"}
}