{
  "type": "Feature",
  "properties": {
    "gn:admin1_code":"87",
    "gn:admin2_code":"5573.0",
    "gn:admin3_code":"557336.0",
    "gn:admin4_code":"55733621.0",
    "gn:asciiname":"Khachimada",
    "gn:country_code":"BD",
    "gn:dem":52,
    "gn:feature_class":"P",
    "gn:feature_code":"PPL",
    "gn:name":"Khachim\u0101da",
    "gn:population":0,
    "gn:timezone":"Asia/Dhaka",
    "iso:country":"BD",
    "name:ben_x_preferred":[
        "Khachim\u0101da"
    ],
    "wof:name":"Khachimada",
    "wof:placetype":"locality"
},
  "geometry": {"coordinates":[88.92594,26.06855],"type":"Point"}
}