{
  "type": "Feature",
  "properties": {
    "gn:admin1_code":"85",
    "gn:admin2_code":"1004.0",
    "gn:admin3_code":"100485.0",
    "gn:admin4_code":"10048571.0",
    "gn:asciiname":"Harinbaria",
    "gn:country_code":"BD",
    "gn:dem":8,
    "gn:feature_class":"P",
    "gn:feature_code":"PPL",
    "gn:name":"Harinbaria",
    "gn:population":0,
    "gn:timezone":"Asia/Dhaka",
    "iso:country":"BD",
    "name:ben_x_preferred":[
        "Harinbaria"
    ],
    "wof:name":"Harinbaria",
    "wof:placetype":"locality"
},
  "geometry": {"coordinates":[89.96410999999998,21.97991],"type":"Point"}
}