{
  "type": "Feature",
  "properties": {
    "gn:admin1_code":"81",
    "gn:admin2_code":"3067",
    "gn:admin3_code":"306702.0",
    "gn:admin4_code":"30670279.0",
    "gn:asciiname":"Nagar Daukadi",
    "gn:country_code":"BD",
    "gn:dem":11,
    "gn:feature_class":"P",
    "gn:feature_code":"PPL",
    "gn:name":"Nagar Dauk\u0101di",
    "gn:population":0,
    "gn:timezone":"Asia/Dhaka",
    "iso:country":"BD",
    "wof:name":"Nagar Daukadi",
    "wof:placetype":"locality"
},
  "geometry": {"coordinates":[90.68487,23.82829],"type":"Point"}
}