{
  "type": "Feature",
  "properties": {
    "gn:admin1_code":"H",
    "gn:admin2_code":"3072",
    "gn:admin3_code":"307204.0",
    "gn:admin4_code":"30720459.0",
    "gn:asciiname":"Ponarakahania Badeura",
    "gn:country_code":"BD",
    "gn:dem":15,
    "gn:feature_class":"P",
    "gn:feature_code":"PPL",
    "gn:name":"Ponarak\u0101hania B\u0101deura",
    "gn:population":0,
    "gn:timezone":"Asia/Dhaka",
    "iso:country":"BD",
    "wof:name":"Ponarakahania Badeura",
    "wof:placetype":"locality"
},
  "geometry": {"coordinates":[90.96953999999999,24.7721],"type":"Point"}
}