{
  "type": "Feature",
  "properties": {
    "gn:admin1_code":"87",
    "gn:admin2_code":"5585",
    "gn:admin3_code":"558558.0",
    "gn:admin4_code":"55855833.0",
    "gn:asciiname":"Tahirpur",
    "gn:country_code":"BD",
    "gn:dem":33,
    "gn:feature_class":"P",
    "gn:feature_code":"PPL",
    "gn:name":"Tahirpur",
    "gn:population":0,
    "gn:timezone":"Asia/Dhaka",
    "iso:country":"BD",
    "name:ben_x_preferred":[
        "Tahirpur"
    ],
    "wof:name":"Tahirpur",
    "wof:placetype":"locality"
},
  "geometry": {"coordinates":[89.2448,25.56434],"type":"Point"}
}