{
  "type": "Feature",
  "properties": {
    "gn:admin1_code":"84",
    "gn:admin2_code":"2046.0",
    "gn:admin3_code":"204680.0",
    "gn:admin4_code":"20468057.0",
    "gn:asciiname":"Nandarampara",
    "gn:country_code":"BD",
    "gn:dem":52,
    "gn:feature_class":"P",
    "gn:feature_code":"PPL",
    "gn:name":"Nandar\u0101mp\u0101ra",
    "gn:population":0,
    "gn:timezone":"Asia/Dhaka",
    "iso:country":"BD",
    "name:ben_x_preferred":[
        "Nandar\u0101mp\u0101ra"
    ],
    "wof:name":"Nandarampara",
    "wof:placetype":"locality"
},
  "geometry": {"coordinates":[91.75082999999999,22.88836],"type":"Point"}
}