{
  "type": "Feature",
  "properties": {
    "gn:admin1_code":"87",
    "gn:admin2_code":"5532",
    "gn:admin3_code":"553230.0",
    "gn:admin4_code":"55323033.0",
    "gn:asciiname":"Teghara",
    "gn:country_code":"BD",
    "gn:dem":28,
    "gn:feature_class":"P",
    "gn:feature_code":"PPL",
    "gn:name":"Teghara",
    "gn:population":0,
    "gn:timezone":"Asia/Dhaka",
    "iso:country":"BD",
    "name:ben_x_preferred":[
        "Teghara"
    ],
    "wof:name":"Teghara",
    "wof:placetype":"locality"
},
  "geometry": {"coordinates":[89.26902,25.20734],"type":"Point"}
}