{
  "type": "Feature",
  "properties": {
    "gn:admin1_code":"82",
    "gn:admin2_code":"4018.0",
    "gn:admin3_code":"401855.0",
    "gn:admin4_code":"40185576.0",
    "gn:asciiname":"Dehat",
    "gn:country_code":"BD",
    "gn:dem":18,
    "gn:feature_class":"P",
    "gn:feature_code":"PPL",
    "gn:name":"Deh\u0101t",
    "gn:population":0,
    "gn:timezone":"Asia/Dhaka",
    "iso:country":"BD",
    "name:ben_x_preferred":[
        "Deh\u0101t"
    ],
    "wof:name":"Dehat",
    "wof:placetype":"locality"
},
  "geometry": {"coordinates":[88.8793,23.47729],"type":"Point"}
}