{
  "type": "Feature",
  "properties": {
    "gn:admin1_code":"83",
    "gn:admin2_code":"5064.0",
    "gn:admin3_code":"506406.0",
    "gn:admin4_code":"50640652.0",
    "gn:asciiname":"Dwarishan",
    "gn:country_code":"BD",
    "gn:dem":24,
    "gn:feature_class":"P",
    "gn:feature_code":"PPL",
    "gn:name":"Dwarishan",
    "gn:population":0,
    "gn:timezone":"Asia/Dhaka",
    "iso:country":"BD",
    "name:ben_x_preferred":[
        "Dwarishan"
    ],
    "name:ben_x_variant":[
        "Dwarisun"
    ],
    "wof:name":"Dwarishan",
    "wof:placetype":"locality"
},
  "geometry": {"coordinates":[88.96681,25.03955],"type":"Point"}
}