{
  "type": "Feature",
  "properties": {
    "gn:admin1_code":"83",
    "gn:admin2_code":"5064",
    "gn:admin3_code":"506450.0",
    "gn:admin4_code":"50645047.0",
    "gn:asciiname":"Jeuli",
    "gn:country_code":"BD",
    "gn:dem":25,
    "gn:feature_class":"P",
    "gn:feature_code":"PPL",
    "gn:name":"Jeuli",
    "gn:population":0,
    "gn:timezone":"Asia/Dhaka",
    "iso:country":"BD",
    "name:ben_x_preferred":[
        "Jeuli"
    ],
    "wof:name":"Jeuli",
    "wof:placetype":"locality"
},
  "geometry": {"coordinates":[88.65326999999998,24.97032],"type":"Point"}
}