{
  "type": "Feature",
  "properties": {
    "gn:admin1_code":"85",
    "gn:admin2_code":"1006",
    "gn:admin3_code":"100602.0",
    "gn:admin4_code":"10060279.0",
    "gn:asciiname":"Ramanander Ak",
    "gn:country_code":"BD",
    "gn:dem":9,
    "gn:feature_class":"P",
    "gn:feature_code":"PPL",
    "gn:name":"R\u0101m\u0101nander \u0100k",
    "gn:population":0,
    "gn:timezone":"Asia/Dhaka",
    "iso:country":"BD",
    "wof:name":"Ramanander Ak",
    "wof:placetype":"locality"
},
  "geometry": {"coordinates":[90.13997000000001,23.00642],"type":"Point"}
}