{
  "type": "Feature",
  "properties": {
    "gn:admin1_code":"H",
    "gn:admin2_code":"3072",
    "gn:admin3_code":"307263.0",
    "gn:admin4_code":"30726342.0",
    "gn:asciiname":"Maijhati",
    "gn:country_code":"BD",
    "gn:dem":15,
    "gn:feature_class":"P",
    "gn:feature_code":"PPL",
    "gn:name":"M\u0101ijh\u0101ti",
    "gn:population":0,
    "gn:timezone":"Asia/Dhaka",
    "iso:country":"BD",
    "name:und_x_variant":[
        "Maijha",
        "M\u0101ijh\u0101ti"
    ],
    "wof:name":"Maijhati",
    "wof:placetype":"locality"
},
  "geometry": {"coordinates":[90.97666,24.83846],"type":"Point"}
}