{
  "type": "Feature",
  "properties": {
    "gn:admin1_code":"82",
    "gn:admin2_code":"4087",
    "gn:admin3_code":"408786.0",
    "gn:admin4_code":"40878647.0",
    "gn:asciiname":"Nidaya",
    "gn:country_code":"BD",
    "gn:dem":3,
    "gn:feature_class":"P",
    "gn:feature_code":"PPL",
    "gn:name":"Nidaya",
    "gn:population":0,
    "gn:timezone":"Asia/Dhaka",
    "iso:country":"BD",
    "wof:name":"Nidaya",
    "wof:placetype":"locality"
},
  "geometry": {"coordinates":[89.01666999999998,22.28333],"type":"Point"}
}