{
  "type": "Feature",
  "properties": {
    "gn:admin1_code":"84",
    "gn:admin2_code":"2075",
    "gn:admin3_code":"207510.0",
    "gn:admin4_code":"20751057.0",
    "gn:asciiname":"Ulupara",
    "gn:country_code":"BD",
    "gn:dem":15,
    "gn:feature_class":"P",
    "gn:feature_code":"PPL",
    "gn:name":"Ulup\u0101ra",
    "gn:population":0,
    "gn:timezone":"Asia/Dhaka",
    "iso:country":"BD",
    "wof:name":"Ulupara",
    "wof:placetype":"locality"
},
  "geometry": {"coordinates":[90.99307,23.05395],"type":"Point"}
}