{
  "type": "Feature",
  "properties": {
    "gn:admin1_code":"81",
    "gn:admin2_code":"3029",
    "gn:admin3_code":"302918.0",
    "gn:admin4_code":"30291860.0",
    "gn:asciiname":"Kandakul",
    "gn:country_code":"BD",
    "gn:dem":13,
    "gn:feature_class":"P",
    "gn:feature_code":"PPL",
    "gn:name":"K\u0101nd\u0101kul",
    "gn:population":0,
    "gn:timezone":"Asia/Dhaka",
    "iso:country":"BD",
    "wof:name":"Kandakul",
    "wof:placetype":"locality"
},
  "geometry": {"coordinates":[89.65772,23.43696],"type":"Point"}
}