{
  "type": "Feature",
  "properties": {
    "gn:admin1_code":"85",
    "gn:admin2_code":"1006",
    "gn:admin3_code":"100694.0",
    "gn:admin4_code":"10069484.0",
    "gn:asciiname":"Madarsi",
    "gn:country_code":"BD",
    "gn:dem":12,
    "gn:feature_class":"P",
    "gn:feature_code":"PPL",
    "gn:name":"M\u0101d\u0101rsi",
    "gn:population":0,
    "gn:timezone":"Asia/Dhaka",
    "iso:country":"BD",
    "wof:name":"Madarsi",
    "wof:placetype":"locality"
},
  "geometry": {"coordinates":[90.24415999999999,22.83796],"type":"Point"}
}