{
  "type": "Feature",
  "properties": {
    "gn:admin1_code":"82",
    "gn:admin2_code":"4057.0",
    "gn:admin3_code":"405747.0",
    "gn:admin4_code":"40574794.0",
    "gn:asciiname":"Hinde",
    "gn:country_code":"BD",
    "gn:dem":19,
    "gn:feature_class":"P",
    "gn:feature_code":"PPL",
    "gn:name":"Hinde",
    "gn:population":0,
    "gn:timezone":"Asia/Dhaka",
    "iso:country":"BD",
    "name:ben_x_preferred":[
        "Hinde"
    ],
    "name:slv_x_preferred":[
        "Hinde"
    ],
    "wof:name":"Hinde",
    "wof:placetype":"locality"
},
  "geometry": {"coordinates":[88.73603,23.86501],"type":"Point"}
}