{
  "type": "Feature",
  "properties": {
    "iso:country":"BD",
    "name:ben_x_preferred":[
        "K\u0101lia"
    ],
    "name:ceb_x_preferred":[
        "Kalia"
    ],
    "name:fra_x_preferred":[
        "Kalia"
    ],
    "name:ind_x_preferred":[
        "Kalia"
    ],
    "name:nld_x_preferred":[
        "Kalia"
    ],
    "name:rus_x_preferred":[
        "\u041a\u0430\u043b\u0438\u044f"
    ],
    "name:swe_x_preferred":[
        "Kalia"
    ],
    "name:unk_x_variant":[
        "Bara K\u0101lia"
    ],
    "qs:gn_country":"BD",
    "qs:gn_fcode":"PPL",
    "qs:gn_pop":40492,
    "qs:name":"Kalia",
    "qs:name_adm0":"Bangladesh",
    "qs:name_adm1":"Khulna",
    "qs:photos":0,
    "qs:photos_1k":0,
    "qs:photos_9k":1,
    "qs:photos_9r":1,
    "qs:photos_all":1,
    "qs:photos_sr":0,
    "qs:placetype":"Town",
    "qs:pop_sr":"7",
    "qs:woe_adm0":23424759,
    "wd:wordcount":78,
    "wof:name":"Kalia",
    "wof:placetype":"locality",
    "wof:population":40492
},
  "geometry": {"coordinates":[89.63094,23.043],"type":"Point"}
}