{
  "type": "Feature",
  "properties": {
    "gn:admin1_code":"H",
    "gn:admin2_code":"3039",
    "gn:admin3_code":"303936.0",
    "gn:admin4_code":"30393623.0",
    "gn:asciiname":"Mulaghata",
    "gn:country_code":"BD",
    "gn:dem":18,
    "gn:feature_class":"P",
    "gn:feature_code":"PPL",
    "gn:name":"Mul\u0101gh\u0101ta",
    "gn:population":0,
    "gn:timezone":"Asia/Dhaka",
    "iso:country":"BD",
    "wof:name":"Mulaghata",
    "wof:placetype":"locality"
},
  "geometry": {"coordinates":[90.18333,24.86667000000001],"type":"Point"}
}