{
  "type": "Feature",
  "properties": {
    "gn:admin1_code":"82",
    "gn:admin2_code":"4018.0",
    "gn:admin3_code":"401823.0",
    "gn:admin4_code":"40182347.0",
    "gn:asciiname":"Bhultia",
    "gn:country_code":"BD",
    "gn:dem":14,
    "gn:feature_class":"P",
    "gn:feature_code":"PPL",
    "gn:name":"Bh\u016bltia",
    "gn:population":0,
    "gn:timezone":"Asia/Dhaka",
    "iso:country":"BD",
    "name:ben_x_preferred":[
        "Bh\u016bltia"
    ],
    "wof:name":"Bhultia",
    "wof:placetype":"locality"
},
  "geometry": {"coordinates":[88.95403,23.56279],"type":"Point"}
}