{
  "type": "Feature",
  "properties": {
    "gn:admin1_code":"83",
    "gn:admin2_code":"5070.0",
    "gn:admin3_code":"507056.0",
    "gn:admin4_code":"50705676.0",
    "gn:asciiname":"Basugram",
    "gn:cc2":"BD",
    "gn:country_code":"BD",
    "gn:dem":27,
    "gn:feature_class":"P",
    "gn:feature_code":"PPL",
    "gn:name":"Basugr\u0101m",
    "gn:population":0,
    "gn:timezone":"Asia/Dhaka",
    "iso:country":"BD",
    "name:und_x_variant":[
        "Dhasol",
        "Basugr\u0101m"
    ],
    "wof:name":"Basugram",
    "wof:placetype":"locality"
},
  "geometry": {"coordinates":[88.34999999999999,24.65],"type":"Point"}
}