{
  "type": "Feature",
  "properties": {
    "gn:admin1_code":"87",
    "gn:admin2_code":"5585",
    "gn:admin3_code":"558576.0",
    "gn:admin4_code":"55857625.0",
    "gn:asciiname":"Uttar Durgapur",
    "gn:country_code":"BD",
    "gn:dem":31,
    "gn:feature_class":"P",
    "gn:feature_code":"PPL",
    "gn:name":"Uttar Durgapur",
    "gn:population":0,
    "gn:timezone":"Asia/Dhaka",
    "iso:country":"BD",
    "name:ben_x_preferred":[
        "Uttar Durgapur"
    ],
    "name:ben_x_variant":[
        "\u0989\u09a4\u09cd\u09a4\u09b0 \u09a6\u09c1\u09b0\u09cd\u0997\u09be\u09aa\u09c1\u09b0"
    ],
    "name:bpy_x_preferred":[
        "\u0989\u09a4\u09cd\u09a4\u09b0 \u09a6\u09c1\u09b0\u09cd\u0997\u09be\u09aa\u09c1\u09b0"
    ],
    "name:ita_x_preferred":[
        "Uttar Durgapur"
    ],
    "name:msa_x_preferred":[
        "Uttar Durgapur"
    ],
    "name:nld_x_preferred":[
        "Uttar Durgapur"
    ],
    "name:por_x_preferred":[
        "Uttar Durgapur"
    ],
    "name:vie_x_preferred":[
        "Uttar Durgapur"
    ],
    "name:zho_x_preferred":[
        "\u5317\u675c\u5c14\u52a0\u666e\u5c14"
    ],
    "wof:name":"Uttar Durgapur",
    "wof:placetype":"locality"
},
  "geometry": {"coordinates":[89.17007,25.44568],"type":"Point"}
}