{
  "type": "Feature",
  "properties": {
    "gn:admin1_code":"81",
    "gn:admin2_code":"3082.0",
    "gn:admin3_code":"308229.0",
    "gn:admin4_code":"30822938.0",
    "gn:asciiname":"Char Daulatdia",
    "gn:country_code":"BD",
    "gn:dem":12,
    "gn:feature_class":"P",
    "gn:feature_code":"PPL",
    "gn:name":"Char Daulatdia",
    "gn:population":0,
    "gn:timezone":"Asia/Dhaka",
    "iso:country":"BD",
    "wof:name":"Char Daulatdia",
    "wof:placetype":"locality"
},
  "geometry": {"coordinates":[89.79555000000001,23.73981],"type":"Point"}
}