{
  "type": "Feature",
  "properties": {
    "gn:admin1_code":"87",
    "gn:admin2_code":"5527.0",
    "gn:admin3_code":"552721.0",
    "gn:admin4_code":"55272154.0",
    "gn:asciiname":"Ratonda",
    "gn:country_code":"BD",
    "gn:dem":47,
    "gn:feature_class":"P",
    "gn:feature_code":"PPL",
    "gn:name":"Ratonda",
    "gn:population":0,
    "gn:timezone":"Asia/Dhaka",
    "iso:country":"BD",
    "name:ben_x_preferred":[
        "Ratonda"
    ],
    "wof:name":"Ratonda",
    "wof:placetype":"locality"
},
  "geometry": {"coordinates":[88.45238000000001,25.81932],"type":"Point"}
}