{
  "type": "Feature",
  "properties": {
    "gn:admin1_code":"84",
    "gn:admin2_code":"2019",
    "gn:admin3_code":"201927.0",
    "gn:admin4_code":"20192787.0",
    "gn:asciiname":"North Padua",
    "gn:country_code":"BD",
    "gn:dem":13,
    "gn:feature_class":"P",
    "gn:feature_code":"PPL",
    "gn:name":"North Padua",
    "gn:population":0,
    "gn:timezone":"Asia/Dhaka",
    "iso:country":"BD",
    "name:und_x_variant":[
        "Padu\u0101",
        "North Padua"
    ],
    "wof:name":"North Padua",
    "wof:placetype":"locality"
},
  "geometry": {"coordinates":[90.90491,23.4643],"type":"Point"}
}