{
  "type": "Feature",
  "properties": {
    "gn:admin1_code":"87",
    "gn:admin2_code":"5549",
    "gn:admin3_code":"554961.0",
    "gn:admin4_code":"55496137.0",
    "gn:asciiname":"Indragarh",
    "gn:country_code":"BD",
    "gn:dem":33,
    "gn:feature_class":"P",
    "gn:feature_code":"PPL",
    "gn:name":"Indr\u0101garh",
    "gn:population":0,
    "gn:timezone":"Asia/Dhaka",
    "iso:country":"BD",
    "name:ben_x_preferred":[
        "Indr\u0101garh"
    ],
    "wof:name":"Indragarh",
    "wof:placetype":"locality"
},
  "geometry": {"coordinates":[89.80768,25.99848],"type":"Point"}
}