{
  "type": "Feature",
  "properties": {
    "gn:admin1_code":"87",
    "gn:admin2_code":"5549",
    "gn:admin3_code":"554961.0",
    "gn:admin4_code":"55496137.0",
    "gn:asciiname":"Indragarh",
    "gn:country_code":"BD",
    "gn:dem":33,
    "gn:feature_class":"P",
    "gn:feature_code":"PPL",
    "gn:name":"Indr\u0101garh",
    "gn:population":0,
    "gn:timezone":"Asia/Dhaka",
    "iso:country":"BD",
    "name:ben_x_preferred":[
        "Indr\u0101garh"
    ],
    "name:ben_x_variant":[
        "\u0987\u09a8\u09cd\u09a6\u09cd\u09b0\u0997\u09a1\u09bc"
    ],
    "name:bpy_x_preferred":[
        "\u0987\u09a8\u09cd\u09a6\u09cd\u09b0\u0997\u09a1\u09bc"
    ],
    "name:hin_x_preferred":[
        "\u0907\u0928\u094d\u0926\u094d\u0930\u0917\u0922\u093c"
    ],
    "name:ita_x_preferred":[
        "Indragarh"
    ],
    "name:msa_x_preferred":[
        "Indragarh"
    ],
    "name:new_x_preferred":[
        "\u0907\u0928\u094d\u0926\u094d\u0930\u0917\u0922"
    ],
    "name:nor_x_preferred":[
        "Indragarh"
    ],
    "name:por_x_preferred":[
        "Indragarh"
    ],
    "name:vie_x_preferred":[
        "Indragarh"
    ],
    "name:zho_x_preferred":[
        "\u4f0a\u6069\u5fb7\u62c9\u52a0\u5c14"
    ],
    "wof:name":"Indragarh",
    "wof:placetype":"locality"
},
  "geometry": {"coordinates":[89.80768,25.99848],"type":"Point"}
}