{
  "type": "Feature",
  "properties": {
    "gn:admin1_code":"82",
    "gn:admin2_code":"4001.0",
    "gn:admin3_code":"400134.0",
    "gn:admin4_code":"40013463.0",
    "gn:asciiname":"Karnta",
    "gn:country_code":"BD",
    "gn:dem":5,
    "gn:feature_class":"P",
    "gn:feature_code":"PPL",
    "gn:name":"K\u0101rnta",
    "gn:population":0,
    "gn:timezone":"Asia/Dhaka",
    "iso:country":"BD",
    "name:ben_x_preferred":[
        "K\u0101rnta"
    ],
    "wof:name":"Karnta",
    "wof:placetype":"locality"
},
  "geometry": {"coordinates":[89.69295,22.79943],"type":"Point"}
}