{
  "type": "Feature",
  "properties": {
    "gn:admin1_code":"81",
    "gn:admin2_code":"3035.0",
    "gn:admin3_code":"303543.0",
    "gn:admin4_code":"30354394.0",
    "gn:asciiname":"Kalibhita",
    "gn:country_code":"BD",
    "gn:dem":5,
    "gn:feature_class":"P",
    "gn:feature_code":"PPL",
    "gn:name":"K\u0101libhita",
    "gn:population":0,
    "gn:timezone":"Asia/Dhaka",
    "iso:country":"BD",
    "name:ben_x_preferred":[
        "K\u0101libhita"
    ],
    "wof:name":"Kalibhita",
    "wof:placetype":"locality"
},
  "geometry": {"coordinates":[89.90289,23.14199],"type":"Point"}
}