{
  "type": "Feature",
  "properties": {
    "gn:admin1_code":"81",
    "gn:admin2_code":"3082.0",
    "gn:admin3_code":"308273.0",
    "gn:admin4_code":"30827310.0",
    "gn:asciiname":"Char Narayanpur",
    "gn:country_code":"BD",
    "gn:dem":14,
    "gn:feature_class":"P",
    "gn:feature_code":"PPL",
    "gn:name":"Char N\u0101r\u0101yanpur",
    "gn:population":0,
    "gn:timezone":"Asia/Dhaka",
    "iso:country":"BD",
    "wof:name":"Char Narayanpur",
    "wof:placetype":"locality"
},
  "geometry": {"coordinates":[89.48496999999998,23.75437],"type":"Point"}
}