{
  "type": "Feature",
  "properties": {
    "gn:admin1_code":"81",
    "gn:admin2_code":"3082",
    "gn:admin3_code":"308273.0",
    "gn:admin4_code":"30827360.0",
    "gn:asciiname":"Sangrampur",
    "gn:country_code":"BD",
    "gn:dem":15,
    "gn:feature_class":"P",
    "gn:feature_code":"PPL",
    "gn:name":"Sangr\u0101mpur",
    "gn:population":0,
    "gn:timezone":"Asia/Dhaka",
    "iso:country":"BD",
    "name:fra_x_preferred":[
        "Sangrampur"
    ],
    "name:new_x_preferred":[
        "\u0938\u0902\u0917\u094d\u0930\u093e\u092e\u092a\u0941\u0930 \u0917\u093e\u0935\u093f\u0938"
    ],
    "name:pol_x_preferred":[
        "Sangrampur"
    ],
    "wof:name":"Sangrampur",
    "wof:placetype":"locality"
},
  "geometry": {"coordinates":[89.54718000000003,23.73815],"type":"Point"}
}