{
  "type": "Feature",
  "properties": {
    "gn:admin1_code":"87",
    "gn:admin2_code":"5573.0",
    "gn:admin3_code":"557364.0",
    "gn:admin4_code":"55736418.0",
    "gn:asciiname":"Chhota Dalua",
    "gn:country_code":"BD",
    "gn:dem":56,
    "gn:feature_class":"P",
    "gn:feature_code":"PPL",
    "gn:name":"Chhota Dalua",
    "gn:population":0,
    "gn:timezone":"Asia/Dhaka",
    "iso:country":"BD",
    "name:ben_x_preferred":[
        "Chhota Dalua"
    ],
    "wof:name":"Chhota Dalua",
    "wof:placetype":"locality"
},
  "geometry": {"coordinates":[88.78278,26.05254],"type":"Point"}
}