{
  "type": "Feature",
  "properties": {
    "gn:admin1_code":"81",
    "gn:admin2_code":"3093",
    "gn:admin3_code":"309366.0",
    "gn:admin4_code":"30936634.0",
    "gn:asciiname":"Uttar Pekua",
    "gn:country_code":"BD",
    "gn:dem":22,
    "gn:feature_class":"P",
    "gn:feature_code":"PPL",
    "gn:name":"Uttar Pekua",
    "gn:population":0,
    "gn:timezone":"Asia/Dhaka",
    "iso:country":"BD",
    "name:und_x_variant":[
        "Pekua"
    ],
    "wof:name":"Uttar Pekua",
    "wof:placetype":"locality"
},
  "geometry": {"coordinates":[90.17022,24.20168],"type":"Point"}
}