{
  "type": "Feature",
  "properties": {
    "gn:admin1_code":"83",
    "gn:admin2_code":"5064",
    "gn:admin3_code":"506479.0",
    "gn:admin4_code":"50647915.0",
    "gn:asciiname":"Jantidal",
    "gn:country_code":"BD",
    "gn:dem":48,
    "gn:feature_class":"P",
    "gn:feature_code":"PPL",
    "gn:name":"Jantid\u0101l",
    "gn:population":0,
    "gn:timezone":"Asia/Dhaka",
    "iso:country":"BD",
    "name:und_x_variant":[
        "Jantijal",
        "Jantid\u0101l"
    ],
    "wof:name":"Jantidal",
    "wof:placetype":"locality"
},
  "geometry": {"coordinates":[88.49677,24.94576],"type":"Point"}
}