{
  "type": "Feature",
  "properties": {
    "gn:admin1_code":"87",
    "gn:admin2_code":"5549",
    "gn:admin3_code":"554977.0",
    "gn:admin4_code":"55497721.0",
    "gn:asciiname":"Kendra",
    "gn:country_code":"BD",
    "gn:dem":33,
    "gn:feature_class":"P",
    "gn:feature_code":"PPL",
    "gn:name":"Kendra",
    "gn:population":0,
    "gn:timezone":"Asia/Dhaka",
    "iso:country":"BD",
    "name:ben_x_preferred":[
        "Kendra"
    ],
    "name:deu_x_preferred":[
        "Kendra"
    ],
    "name:fra_x_preferred":[
        "Kendra"
    ],
    "name:hun_x_preferred":[
        "Kendra"
    ],
    "name:isl_x_preferred":[
        "Kendra"
    ],
    "name:ita_x_preferred":[
        "Kendra"
    ],
    "name:spa_x_preferred":[
        "Kendra"
    ],
    "wof:name":"Kendra",
    "wof:placetype":"locality"
},
  "geometry": {"coordinates":[89.57673,25.79937],"type":"Point"}
}