{
  "type": "Feature",
  "properties": {
    "gn:admin1_code":"87",
    "gn:admin2_code":"5585",
    "gn:admin3_code":"558527.0",
    "gn:admin4_code":"55852752.0",
    "gn:asciiname":"Penuladaha",
    "gn:country_code":"BD",
    "gn:dem":41,
    "gn:feature_class":"P",
    "gn:feature_code":"PPL",
    "gn:name":"Penul\u0101daha",
    "gn:population":0,
    "gn:timezone":"Asia/Dhaka",
    "iso:country":"BD",
    "name:ben_x_preferred":[
        "Penul\u0101daha"
    ],
    "wof:name":"Penuladaha",
    "wof:placetype":"locality"
},
  "geometry": {"coordinates":[89.13588,25.85076],"type":"Point"}
}