{
  "type": "Feature",
  "properties": {
    "gn:admin1_code":"87",
    "gn:admin2_code":"5532",
    "gn:admin3_code":"553267.0",
    "gn:admin4_code":"55326757.0",
    "gn:asciiname":"Mahadipur",
    "gn:country_code":"BD",
    "gn:dem":27,
    "gn:feature_class":"P",
    "gn:feature_code":"PPL",
    "gn:name":"Mahadipur",
    "gn:population":0,
    "gn:timezone":"Asia/Dhaka",
    "iso:country":"BD",
    "name:ben_x_preferred":[
        "Mahadipur"
    ],
    "name:ben_x_variant":[
        "\u09ae\u09b9\u09a6\u09c0\u09aa\u09c1\u09b0"
    ],
    "wof:name":"Mahadipur",
    "wof:placetype":"locality"
},
  "geometry": {"coordinates":[89.38715000000001,25.2876],"type":"Point"}
}