{
  "type": "Feature",
  "properties": {
    "gn:admin1_code":"81",
    "gn:admin2_code":"3056",
    "gn:admin3_code":"305682.0",
    "gn:admin4_code":"30568277.0",
    "gn:asciiname":"Ikrabari",
    "gn:country_code":"BD",
    "gn:dem":13,
    "gn:feature_class":"P",
    "gn:feature_code":"PPL",
    "gn:name":"Ikr\u0101b\u0101ri",
    "gn:population":0,
    "gn:timezone":"Asia/Dhaka",
    "iso:country":"BD",
    "wof:name":"Ikrabari",
    "wof:placetype":"locality"
},
  "geometry": {"coordinates":[90.15248,23.76362],"type":"Point"}
}