{
  "type": "Feature",
  "properties": {
    "gn:admin1_code":"81",
    "gn:admin2_code":"3048",
    "gn:admin3_code":"304842.0",
    "gn:admin4_code":"30484269.0",
    "gn:asciiname":"Lakhpur",
    "gn:country_code":"BD",
    "gn:dem":12,
    "gn:feature_class":"P",
    "gn:feature_code":"PPL",
    "gn:name":"L\u0101khpur",
    "gn:population":0,
    "gn:timezone":"Asia/Dhaka",
    "iso:country":"BD",
    "wof:name":"Lakhpur",
    "wof:placetype":"locality"
},
  "geometry": {"coordinates":[90.89145000000001,24.47816],"type":"Point"}
}