{
  "type": "Feature",
  "properties": {
    "gn:admin1_code":"85",
    "gn:admin2_code":"1009.0",
    "gn:admin3_code":"100921.0",
    "gn:admin4_code":"10092195.0",
    "gn:asciiname":"Dalalpur",
    "gn:country_code":"BD",
    "gn:dem":8,
    "gn:feature_class":"P",
    "gn:feature_code":"PPL",
    "gn:name":"D\u0101l\u0101lpur",
    "gn:population":0,
    "gn:timezone":"Asia/Dhaka",
    "iso:country":"BD",
    "name:ben_x_preferred":[
        "D\u0101l\u0101lpur"
    ],
    "wof:name":"Dalalpur",
    "wof:placetype":"locality"
},
  "geometry": {"coordinates":[90.79114,22.46906],"type":"Point"}
}