{
  "type": "Feature",
  "properties": {
    "gn:admin1_code":"87",
    "gn:admin2_code":"5549",
    "gn:admin3_code":"554961.0",
    "gn:admin4_code":"55496194.0",
    "gn:asciiname":"Santoshpur",
    "gn:country_code":"BD",
    "gn:dem":34,
    "gn:feature_class":"P",
    "gn:feature_code":"PPL",
    "gn:name":"Santoshpur",
    "gn:population":0,
    "gn:timezone":"Asia/Dhaka",
    "iso:country":"BD",
    "wof:name":"Santoshpur",
    "wof:placetype":"locality"
},
  "geometry": {"coordinates":[89.682,26.01421],"type":"Point"}
}