{
  "type": "Feature",
  "properties": {
    "gn:admin1_code":"81",
    "gn:admin2_code":"3056",
    "gn:admin3_code":"305646.0",
    "gn:admin4_code":"30564609.0",
    "gn:asciiname":"Tatalpur",
    "gn:country_code":"BD",
    "gn:dem":15,
    "gn:feature_class":"P",
    "gn:feature_code":"PPL",
    "gn:name":"T\u0101t\u0101lpur",
    "gn:population":0,
    "gn:timezone":"Asia/Dhaka",
    "iso:country":"BD",
    "wof:name":"Tatalpur",
    "wof:placetype":"locality"
},
  "geometry": {"coordinates":[90.07808,23.88528],"type":"Point"}
}