{
  "type": "Feature",
  "properties": {
    "gn:admin1_code":"81",
    "gn:admin2_code":"3029",
    "gn:admin3_code":"302918.0",
    "gn:admin4_code":"30291825.0",
    "gn:asciiname":"Loknath",
    "gn:country_code":"BD",
    "gn:dem":11,
    "gn:feature_class":"P",
    "gn:feature_code":"PPL",
    "gn:name":"Lokn\u0101th",
    "gn:population":0,
    "gn:timezone":"Asia/Dhaka",
    "iso:country":"BD",
    "name:kan_x_preferred":[
        "\u0cb2\u0ccb\u0c95\u0ca8\u0cbe\u0ca5\u0ccd"
    ],
    "name:rus_x_preferred":[
        "\u041b\u043e\u043a\u043d\u0430\u0442"
    ],
    "wof:name":"Loknath",
    "wof:placetype":"locality"
},
  "geometry": {"coordinates":[89.69679000000002,23.38052],"type":"Point"}
}