{
  "type": "Feature",
  "properties": {
    "gn:admin1_code":"84",
    "gn:admin2_code":"2084.0",
    "gn:admin3_code":"208487.0",
    "gn:admin4_code":"20848727.0",
    "gn:asciiname":"Hanumanpahar",
    "gn:country_code":"BD",
    "gn:dem":38,
    "gn:feature_class":"P",
    "gn:feature_code":"PPL",
    "gn:name":"Hanum\u0101np\u0101h\u0101r",
    "gn:population":0,
    "gn:timezone":"Asia/Dhaka",
    "iso:country":"BD",
    "name:ben_x_preferred":[
        "Hanum\u0101np\u0101h\u0101r"
    ],
    "wof:name":"Hanumanpahar",
    "wof:placetype":"locality"
},
  "geometry": {"coordinates":[92.1874,22.66518],"type":"Point"}
}