{
  "type": "Feature",
  "properties": {
    "gn:admin1_code":"85",
    "gn:admin2_code":"1006",
    "gn:admin3_code":"100651.0",
    "gn:admin4_code":"10065151.0",
    "gn:asciiname":"Pharphariatala",
    "gn:country_code":"BD",
    "gn:dem":8,
    "gn:feature_class":"P",
    "gn:feature_code":"PPL",
    "gn:name":"Pharphariat\u0101la",
    "gn:population":0,
    "gn:timezone":"Asia/Dhaka",
    "iso:country":"BD",
    "wof:name":"Pharphariatala",
    "wof:placetype":"locality"
},
  "geometry": {"coordinates":[90.46315,22.73143],"type":"Point"}
}