{
  "type": "Feature",
  "properties": {
    "gn:admin1_code":"H",
    "gn:admin2_code":"3061",
    "gn:admin3_code":"306152.0",
    "gn:admin4_code":"30615213.0",
    "gn:asciiname":"Nimtala",
    "gn:country_code":"BD",
    "gn:dem":20,
    "gn:feature_class":"P",
    "gn:feature_code":"PPL",
    "gn:name":"Nimtala",
    "gn:population":0,
    "gn:timezone":"Asia/Dhaka",
    "iso:country":"BD",
    "wof:name":"Nimtala",
    "wof:placetype":"locality"
},
  "geometry": {"coordinates":[90.22591,24.83544],"type":"Point"}
}