{
  "type": "Feature",
  "properties": {
    "gn:admin1_code":"H",
    "gn:admin2_code":"3061",
    "gn:admin3_code":"306122.0",
    "gn:admin4_code":"30612294.0",
    "gn:asciiname":"Terasri",
    "gn:country_code":"BD",
    "gn:dem":15,
    "gn:feature_class":"P",
    "gn:feature_code":"PPL",
    "gn:name":"Terasri",
    "gn:population":0,
    "gn:timezone":"Asia/Dhaka",
    "iso:country":"BD",
    "wof:name":"Terasri",
    "wof:placetype":"locality"
},
  "geometry": {"coordinates":[90.59032999999999,24.38007],"type":"Point"}
}