{
  "type": "Feature",
  "properties": {
    "gn:admin1_code":"84",
    "gn:admin2_code":"2003",
    "gn:admin3_code":"200351.0",
    "gn:admin4_code":"20035131.0",
    "gn:asciiname":"Suimaunpara",
    "gn:country_code":"BD",
    "gn:dem":23,
    "gn:feature_class":"P",
    "gn:feature_code":"PPL",
    "gn:name":"Suim\u0101unp\u0101ra",
    "gn:population":0,
    "gn:timezone":"Asia/Dhaka",
    "iso:country":"BD",
    "name:ben_x_preferred":[
        "Suim\u0101unp\u0101ra"
    ],
    "name:und_x_variant":[
        "Sangu",
        "Sang\u016bmukh"
    ],
    "wof:name":"Suimaunpara",
    "wof:placetype":"locality"
},
  "geometry": {"coordinates":[92.17277,21.68387],"type":"Point"}
}