{
  "type": "Feature",
  "properties": {
    "gn:admin1_code":"H",
    "gn:admin2_code":"3089",
    "gn:admin3_code":"308988.0",
    "gn:admin4_code":"30898881.0",
    "gn:asciiname":"Bade Tegharia",
    "gn:country_code":"BD",
    "gn:dem":21,
    "gn:feature_class":"P",
    "gn:feature_code":"PPL",
    "gn:name":"B\u0101de Tegh\u0101ria",
    "gn:population":0,
    "gn:timezone":"Asia/Dhaka",
    "iso:country":"BD",
    "name:ben_x_preferred":[
        "B\u0101de Tegh\u0101ria"
    ],
    "wof:name":"Bade Tegharia",
    "wof:placetype":"locality"
},
  "geometry": {"coordinates":[90.06793,25.02195],"type":"Point"}
}