{
  "type": "Feature",
  "properties": {
    "gn:admin1_code":"84",
    "gn:admin2_code":"2012",
    "gn:admin3_code":"201263.0",
    "gn:admin4_code":"20126369.0",
    "gn:asciiname":"Kuti",
    "gn:country_code":"BD",
    "gn:dem":8,
    "gn:feature_class":"P",
    "gn:feature_code":"PPL",
    "gn:name":"Kuti",
    "gn:population":0,
    "gn:timezone":"Asia/Dhaka",
    "iso:country":"BD",
    "name:bos_x_preferred":[
        "Kuti"
    ],
    "name:ceb_x_preferred":[
        "Kuti"
    ],
    "name:deu_x_preferred":[
        "Kuti"
    ],
    "name:fra_x_preferred":[
        "Kuti"
    ],
    "name:hrv_x_preferred":[
        "Kuti"
    ],
    "name:pol_x_preferred":[
        "Kuti"
    ],
    "name:rus_x_preferred":[
        "\u041a\u0443\u0442\u0438"
    ],
    "name:slv_x_preferred":[
        "Kuti"
    ],
    "name:srp_x_preferred":[
        "\u041a\u0443\u0442\u0438"
    ],
    "name:swe_x_preferred":[
        "Kuti"
    ],
    "wof:name":"Kuti",
    "wof:placetype":"locality"
},
  "geometry": {"coordinates":[91.08595,23.742],"type":"Point"}
}