{
  "type": "Feature",
  "properties": {
    "gn:admin1_code":"82",
    "gn:admin2_code":"4087.0",
    "gn:admin3_code":"408704.0",
    "gn:admin4_code":"40870494.0",
    "gn:asciiname":"Urkhar Ati",
    "gn:country_code":"BD",
    "gn:dem":5,
    "gn:feature_class":"P",
    "gn:feature_code":"PPL",
    "gn:name":"Urkh\u0101r Ati",
    "gn:population":0,
    "gn:timezone":"Asia/Dhaka",
    "iso:country":"BD",
    "name:ben_x_preferred":[
        "Urkh\u0101r Ati"
    ],
    "wof:name":"Urkhar Ati",
    "wof:placetype":"locality"
},
  "geometry": {"coordinates":[89.16121,22.4434],"type":"Point"}
}