{
  "type": "Feature",
  "properties": {
    "gn:admin1_code":"81",
    "gn:admin2_code":"3029.0",
    "gn:admin3_code":"302962.0",
    "gn:admin4_code":"30296283.0",
    "gn:asciiname":"Bil Gobindapur",
    "gn:country_code":"BD",
    "gn:dem":10,
    "gn:feature_class":"P",
    "gn:feature_code":"PPL",
    "gn:name":"B\u012bl Gobind\u0101pur",
    "gn:population":0,
    "gn:timezone":"Asia/Dhaka",
    "iso:country":"BD",
    "wof:name":"Bil Gobindapur",
    "wof:placetype":"locality"
},
  "geometry": {"coordinates":[89.89832,23.50823],"type":"Point"}
}