{
  "type": "Feature",
  "properties": {
    "gn:admin1_code":"84",
    "gn:admin2_code":"2075",
    "gn:admin3_code":"207587.0",
    "gn:admin4_code":"20758785.0",
    "gn:asciiname":"Shahazadpur",
    "gn:cc2":"BD",
    "gn:country_code":"BD",
    "gn:dem":8,
    "gn:feature_class":"P",
    "gn:feature_code":"PPL",
    "gn:name":"Sh\u0101h\u0101z\u0101dpur",
    "gn:population":0,
    "gn:timezone":"Asia/Dhaka",
    "iso:country":"BD",
    "name:und_x_variant":[
        "Sahazadapur",
        "Sh\u0101h\u0101z\u0101dpur"
    ],
    "wof:name":"Shahazadpur",
    "wof:placetype":"locality"
},
  "geometry": {"coordinates":[91.05,22.86667000000001],"type":"Point"}
}