{
  "type": "Feature",
  "properties": {
    "gn:admin1_code":"82",
    "gn:admin2_code":"4047",
    "gn:admin3_code":"404712.0",
    "gn:admin4_code":"40471283.0",
    "gn:asciiname":"Jaliakhali",
    "gn:country_code":"BD",
    "gn:dem":8,
    "gn:feature_class":"P",
    "gn:feature_code":"PPL",
    "gn:name":"J\u0101li\u0101kh\u0101li",
    "gn:population":0,
    "gn:timezone":"Asia/Dhaka",
    "iso:country":"BD",
    "wof:name":"Jaliakhali",
    "wof:placetype":"locality"
},
  "geometry": {"coordinates":[89.42428000000002,22.66436],"type":"Point"}
}