{
  "type": "Feature",
  "properties": {
    "gn:admin1_code":"H",
    "gn:admin2_code":"3089",
    "gn:admin3_code":"308937.0",
    "gn:admin4_code":"30893725.0",
    "gn:asciiname":"Nayapara",
    "gn:country_code":"BD",
    "gn:dem":25,
    "gn:feature_class":"P",
    "gn:feature_code":"PPL",
    "gn:name":"Nayap\u0101ra",
    "gn:population":0,
    "gn:timezone":"Asia/Dhaka",
    "iso:country":"BD",
    "wof:name":"Nayapara",
    "wof:placetype":"locality"
},
  "geometry": {"coordinates":[90.05069,25.1757],"type":"Point"}
}