{
  "type": "Feature",
  "properties": {
    "gn:admin1_code":"87",
    "gn:admin2_code":"5577",
    "gn:admin3_code":"557725.0",
    "gn:admin4_code":"55772580.0",
    "gn:asciiname":"Saldanga",
    "gn:country_code":"BD",
    "gn:dem":66,
    "gn:feature_class":"P",
    "gn:feature_code":"PPL",
    "gn:name":"S\u0101ld\u0101nga",
    "gn:population":0,
    "gn:timezone":"Asia/Dhaka",
    "iso:country":"BD",
    "name:ben_x_preferred":[
        "S\u0101ld\u0101nga"
    ],
    "wof:name":"Saldanga",
    "wof:placetype":"locality"
},
  "geometry": {"coordinates":[88.68799999999997,26.20874],"type":"Point"}
}