{
  "type": "Feature",
  "properties": {
    "gn:admin1_code":"82",
    "gn:admin2_code":"4087",
    "gn:admin3_code":"408782.0",
    "gn:admin4_code":"40878251.0",
    "gn:asciiname":"Mirzapur",
    "gn:country_code":"BD",
    "gn:dem":6,
    "gn:feature_class":"P",
    "gn:feature_code":"PPL",
    "gn:name":"Mirz\u0101pur",
    "gn:population":0,
    "gn:timezone":"Asia/Dhaka",
    "iso:country":"BD",
    "name:und_x_variant":[
        "Mrizapur",
        "Mirz\u0101pur"
    ],
    "wof:name":"Mirzapur",
    "wof:placetype":"locality"
},
  "geometry": {"coordinates":[89.11459000000001,22.63468],"type":"Point"}
}