{
  "type": "Feature",
  "properties": {
    "gn:admin1_code":"85",
    "gn:admin2_code":"1042",
    "gn:admin3_code":"104284.0",
    "gn:admin4_code":"10428454.0",
    "gn:asciiname":"Rola",
    "gn:country_code":"BD",
    "gn:dem":7,
    "gn:feature_class":"P",
    "gn:feature_code":"PPL",
    "gn:name":"Rola",
    "gn:population":0,
    "gn:timezone":"Asia/Dhaka",
    "iso:country":"BD",
    "wof:name":"Rola",
    "wof:placetype":"locality"
},
  "geometry": {"coordinates":[90.09878,22.5515],"type":"Point"}
}