{
  "type": "Feature",
  "properties": {
    "gn:admin1_code":"87",
    "gn:admin2_code":"5552",
    "gn:admin3_code":"555202.0",
    "gn:admin4_code":"55520205.0",
    "gn:asciiname":"Kalamati",
    "gn:country_code":"BD",
    "gn:dem":36,
    "gn:feature_class":"P",
    "gn:feature_code":"PPL",
    "gn:name":"K\u0101l\u0101m\u0101ti",
    "gn:population":0,
    "gn:timezone":"Asia/Dhaka",
    "iso:country":"BD",
    "name:ben_x_preferred":[
        "K\u0101l\u0101m\u0101ti"
    ],
    "wof:name":"Kalamati",
    "wof:placetype":"locality"
},
  "geometry": {"coordinates":[89.35568000000001,25.87909],"type":"Point"}
}