{
  "type": "Feature",
  "properties": {
    "gn:admin1_code":"81",
    "gn:admin2_code":"3068.0",
    "gn:admin3_code":"306876.0",
    "gn:admin4_code":"30687684.0",
    "gn:asciiname":"Barai Algi",
    "gn:country_code":"BD",
    "gn:dem":14,
    "gn:feature_class":"P",
    "gn:feature_code":"PPL",
    "gn:name":"B\u0101rai \u0100lgi",
    "gn:population":0,
    "gn:timezone":"Asia/Dhaka",
    "iso:country":"BD",
    "wof:name":"Barai Algi",
    "wof:placetype":"locality"
},
  "geometry": {"coordinates":[90.73614000000001,24.00378],"type":"Point"}
}