{
  "type": "Feature",
  "properties": {
    "gn:admin1_code":"87",
    "gn:admin2_code":"5594.0",
    "gn:admin3_code":"559486.0",
    "gn:admin4_code":"55948647.0",
    "gn:asciiname":"Bhandara",
    "gn:country_code":"BD",
    "gn:dem":51,
    "gn:feature_class":"P",
    "gn:feature_code":"PPL",
    "gn:name":"Bh\u0101nd\u0101ra",
    "gn:population":0,
    "gn:timezone":"Asia/Dhaka",
    "iso:country":"BD",
    "name:ben_x_preferred":[
        "Bh\u0101nd\u0101ra"
    ],
    "name:ben_x_variant":[
        "\u09ad\u09be\u09a8\u09cd\u09a6\u09cd\u09b0\u09be"
    ],
    "name:cat_x_preferred":[
        "Bhandara"
    ],
    "name:ces_x_preferred":[
        "Bhand\u00e1ra"
    ],
    "name:deu_x_preferred":[
        "Bhandara"
    ],
    "name:guj_x_preferred":[
        "\u0aad\u0a82\u0aa1\u0abe\u0ab0\u0abe"
    ],
    "name:hin_x_preferred":[
        "\u092d\u0902\u0921\u093e\u0930\u093e"
    ],
    "name:ita_x_preferred":[
        "Bhandara"
    ],
    "name:mar_x_preferred":[
        "\u092d\u0902\u0921\u093e\u0930\u093e"
    ],
    "name:mlg_x_preferred":[
        "Bhandara"
    ],
    "name:msa_x_preferred":[
        "Bhandara"
    ],
    "name:nep_x_preferred":[
        "\u092d\u0902\u0921\u093e\u0930\u093e"
    ],
    "name:new_x_preferred":[
        "\u092d\u0923\u094d\u0921\u093e\u0930\u093e"
    ],
    "name:nld_x_preferred":[
        "Bhandara"
    ],
    "name:pam_x_preferred":[
        "Bhandara"
    ],
    "name:rus_x_preferred":[
        "\u0411\u0445\u0430\u043d\u0434\u0430\u0440\u0430"
    ],
    "name:san_x_preferred":[
        "\u092d\u0923\u094d\u0921\u093e\u0930\u093e"
    ],
    "name:swe_x_preferred":[
        "Bhandara"
    ],
    "name:tam_x_preferred":[
        "\u0baa\u0ba3\u0bcd\u0b9f\u0bbe\u0bb0\u0bbe"
    ],
    "name:tel_x_preferred":[
        "\u0c2d\u0c02\u0c21\u0c3e\u0c30\u0c3e"
    ],
    "name:urd_x_preferred":[
        "\u0628\u06be\u0646\u0688\u0627\u0631\u0627"
    ],
    "name:vie_x_preferred":[
        "Bhandara"
    ],
    "name:zho_x_preferred":[
        "\u73ed\u8fbe\u62c9"
    ],
    "wof:name":"Bhandara",
    "wof:placetype":"locality"
},
  "geometry": {"coordinates":[88.24831,25.89861],"type":"Point"}
}