{
  "type": "Feature",
  "properties": {
    "gn:admin1_code":"84",
    "gn:admin2_code":"2015.0",
    "gn:admin3_code":"201504.0",
    "gn:admin4_code":"20150447.0",
    "gn:asciiname":"Naldia",
    "gn:country_code":"BD",
    "gn:dem":7,
    "gn:feature_class":"P",
    "gn:feature_code":"PPL",
    "gn:name":"Naldia",
    "gn:population":0,
    "gn:timezone":"Asia/Dhaka",
    "iso:country":"BD",
    "name:ben_x_preferred":[
        "Naldia"
    ],
    "wof:name":"Naldia",
    "wof:placetype":"locality"
},
  "geometry": {"coordinates":[91.87873,22.18435],"type":"Point"}
}