{
  "type": "Feature",
  "properties": {
    "gn:admin1_code":"82",
    "gn:admin2_code":"4041.0",
    "gn:admin3_code":"404190.0",
    "gn:admin4_code":"40419077.0",
    "gn:asciiname":"Barpota",
    "gn:country_code":"BD",
    "gn:dem":9,
    "gn:feature_class":"P",
    "gn:feature_code":"PPL",
    "gn:name":"Barpota",
    "gn:population":0,
    "gn:timezone":"Asia/Dhaka",
    "iso:country":"BD",
    "name:ben_x_preferred":[
        "Barpota"
    ],
    "wof:name":"Barpota",
    "wof:placetype":"locality"
},
  "geometry": {"coordinates":[88.88760000000001,22.99846],"type":"Point"}
}