{
  "type": "Feature",
  "properties": {
    "gn:admin1_code":"83",
    "gn:admin2_code":"5081.0",
    "gn:admin3_code":"508134.0",
    "gn:admin4_code":"50813476.0",
    "gn:asciiname":"Bahadurpara",
    "gn:country_code":"BD",
    "gn:dem":37,
    "gn:feature_class":"P",
    "gn:feature_code":"PPL",
    "gn:name":"B\u0101h\u0101durp\u0101ra",
    "gn:population":0,
    "gn:timezone":"Asia/Dhaka",
    "iso:country":"BD",
    "name:ben_x_preferred":[
        "B\u0101h\u0101durp\u0101ra"
    ],
    "wof:name":"Bahadurpara",
    "wof:placetype":"locality"
},
  "geometry": {"coordinates":[88.44555,24.56071],"type":"Point"}
}