{
  "type": "Feature",
  "properties": {
    "gn:admin1_code":"87",
    "gn:admin2_code":"5527.0",
    "gn:admin3_code":"552717.0",
    "gn:admin4_code":"55271795.0",
    "gn:asciiname":"Sahargram",
    "gn:country_code":"BD",
    "gn:dem":38,
    "gn:feature_class":"P",
    "gn:feature_code":"PPL",
    "gn:name":"S\u0101h\u0101rgr\u0101m",
    "gn:population":0,
    "gn:timezone":"Asia/Dhaka",
    "iso:country":"BD",
    "name:ben_x_preferred":[
        "S\u0101h\u0101rgr\u0101m"
    ],
    "wof:name":"Sahargram",
    "wof:placetype":"locality"
},
  "geometry": {"coordinates":[88.52308000000002,25.68863],"type":"Point"}
}