{
  "type": "Feature",
  "properties": {
    "gn:admin1_code":"82",
    "gn:admin2_code":"4018.0",
    "gn:admin3_code":"401807.0",
    "gn:admin4_code":"40180779.0",
    "gn:asciiname":"Kabilnagar",
    "gn:country_code":"BD",
    "gn:dem":14,
    "gn:feature_class":"P",
    "gn:feature_code":"PPL",
    "gn:name":"K\u0101bilnagar",
    "gn:population":0,
    "gn:timezone":"Asia/Dhaka",
    "iso:country":"BD",
    "name:ben_x_preferred":[
        "K\u0101bilnagar"
    ],
    "wof:name":"Kabilnagar",
    "wof:placetype":"locality"
},
  "geometry": {"coordinates":[88.98425,23.6434],"type":"Point"}
}