{
  "type": "Feature",
  "properties": {
    "gn:admin1_code":"82",
    "gn:admin2_code":"4057.0",
    "gn:admin3_code":"405747.0",
    "gn:admin4_code":"40574731.0",
    "gn:asciiname":"Bamundia",
    "gn:country_code":"BD",
    "gn:dem":20,
    "gn:feature_class":"P",
    "gn:feature_code":"PPL",
    "gn:name":"B\u0101mundia",
    "gn:population":0,
    "gn:timezone":"Asia/Dhaka",
    "iso:country":"BD",
    "name:ben_x_preferred":[
        "B\u0101mundia"
    ],
    "wof:name":"Bamundia",
    "wof:placetype":"locality"
},
  "geometry": {"coordinates":[88.78532,23.79883],"type":"Point"}
}