{
  "type": "Feature",
  "properties": {
    "gn:admin1_code":"83",
    "gn:asciiname":"Pantair Panchpara",
    "gn:country_code":"BD",
    "gn:dem":23,
    "gn:feature_class":"P",
    "gn:feature_code":"PPL",
    "gn:name":"Pant\u0101ir P\u0101nchp\u0101ra",
    "gn:population":0,
    "gn:timezone":"Asia/Dhaka",
    "iso:country":"BD",
    "name:ben_x_preferred":[
        "Pant\u0101ir P\u0101nchp\u0101ra"
    ],
    "wof:name":"Pantair Panchpara",
    "wof:placetype":"locality"
},
  "geometry": {"coordinates":[89.46585999999998,25.13274],"type":"Point"}
}