{
  "type": "Feature",
  "properties": {
    "gn:admin1_code":"84",
    "gn:admin2_code":"2015.0",
    "gn:admin3_code":"201512.0",
    "gn:admin4_code":"20151276.0",
    "gn:asciiname":"Golakmunshir Hat",
    "gn:country_code":"BD",
    "gn:dem":9,
    "gn:feature_class":"P",
    "gn:feature_code":"PPL",
    "gn:name":"Golakmunshir H\u0101t",
    "gn:population":0,
    "gn:timezone":"Asia/Dhaka",
    "iso:country":"BD",
    "name:ben_x_preferred":[
        "Golakmunshir H\u0101t"
    ],
    "wof:name":"Golakmunshir Hat",
    "wof:placetype":"locality"
},
  "geometry": {"coordinates":[91.89978000000001,22.35306],"type":"Point"}
}