{
  "type": "Feature",
  "properties": {
    "gn:admin1_code":"81",
    "gn:admin2_code":"3026",
    "gn:admin3_code":"302662.0",
    "gn:admin4_code":"30266261.0",
    "gn:asciiname":"Kedarpur",
    "gn:country_code":"BD",
    "gn:dem":12,
    "gn:feature_class":"P",
    "gn:feature_code":"PPL",
    "gn:name":"Ked\u0101rpur",
    "gn:population":0,
    "gn:timezone":"Asia/Dhaka",
    "iso:country":"BD",
    "wof:name":"Kedarpur",
    "wof:placetype":"locality"
},
  "geometry": {"coordinates":[90.03319999999999,23.67487],"type":"Point"}
}