{
  "type": "Feature",
  "properties": {
    "gn:admin1_code":"84",
    "gn:admin2_code":"2015.0",
    "gn:admin3_code":"201504.0",
    "gn:admin4_code":"20150495.0",
    "gn:asciiname":"Purba Raipur",
    "gn:country_code":"BD",
    "gn:dem":7,
    "gn:feature_class":"P",
    "gn:feature_code":"PPL",
    "gn:name":"Purba R\u0101ipur",
    "gn:population":0,
    "gn:timezone":"Asia/Dhaka",
    "iso:country":"BD",
    "name:ben_x_preferred":[
        "Purba R\u0101ipur"
    ],
    "name:ben_x_variant":[
        "Raipur"
    ],
    "wof:name":"Purba Raipur",
    "wof:placetype":"locality"
},
  "geometry": {"coordinates":[91.83823,22.15543],"type":"Point"}
}