{
  "type": "Feature",
  "properties": {
    "gn:admin1_code":"83",
    "gn:admin2_code":"5064.0",
    "gn:admin3_code":"506406.0",
    "gn:admin4_code":"50640631.0",
    "gn:asciiname":"Bharatta",
    "gn:country_code":"BD",
    "gn:dem":21,
    "gn:feature_class":"P",
    "gn:feature_code":"PPL",
    "gn:name":"Bh\u0101r\u0101tta",
    "gn:population":0,
    "gn:timezone":"Asia/Dhaka",
    "iso:country":"BD",
    "name:ben_x_preferred":[
        "Bh\u0101r\u0101tta"
    ],
    "wof:name":"Bharatta",
    "wof:placetype":"locality"
},
  "geometry": {"coordinates":[88.87061,24.91755],"type":"Point"}
}