{
  "type": "Feature",
  "properties": {
    "gn:admin1_code":"82",
    "gn:admin2_code":"4057.0",
    "gn:admin3_code":"405787.0",
    "gn:admin4_code":"40578714.0",
    "gn:asciiname":"Malopara",
    "gn:country_code":"BD",
    "gn:dem":20,
    "gn:feature_class":"P",
    "gn:feature_code":"PPL",
    "gn:name":"M\u0101lop\u0101ra",
    "gn:population":0,
    "gn:timezone":"Asia/Dhaka",
    "iso:country":"BD",
    "name:ben_x_preferred":[
        "M\u0101lop\u0101ra"
    ],
    "wof:name":"Malopara",
    "wof:placetype":"locality"
},
  "geometry": {"coordinates":[88.64706,23.70557],"type":"Point"}
}