{
  "type": "Feature",
  "properties": {
    "gn:admin1_code":"81",
    "gn:admin2_code":"3033.0",
    "gn:admin3_code":"303336.0",
    "gn:admin4_code":"30333643.0",
    "gn:asciiname":"Banar Haola",
    "gn:country_code":"BD",
    "gn:dem":17,
    "gn:feature_class":"P",
    "gn:feature_code":"PPL",
    "gn:name":"B\u0101n\u0101r H\u0101ola",
    "gn:population":0,
    "gn:timezone":"Asia/Dhaka",
    "iso:country":"BD",
    "wof:name":"Banar Haola",
    "wof:placetype":"locality"
},
  "geometry": {"coordinates":[90.56487,24.1104],"type":"Point"}
}