{
  "type": "Feature",
  "properties": {
    "gn:admin1_code":"85",
    "gn:admin2_code":"1006.0",
    "gn:admin3_code":"100632.0",
    "gn:admin4_code":"10063223.0",
    "gn:asciiname":"Ghanirapi",
    "gn:country_code":"BD",
    "gn:dem":8,
    "gn:feature_class":"P",
    "gn:feature_code":"PPL",
    "gn:name":"Ghanirapi",
    "gn:population":0,
    "gn:timezone":"Asia/Dhaka",
    "iso:country":"BD",
    "name:und_x_variant":[
        "Ganirapi"
    ],
    "wof:name":"Ghanirapi",
    "wof:placetype":"locality"
},
  "geometry": {"coordinates":[90.21553,23.02314],"type":"Point"}
}