{
  "type": "Feature",
  "properties": {
    "gn:admin1_code":"86",
    "gn:admin2_code":"6091.0",
    "gn:admin3_code":"609138.0",
    "gn:admin4_code":"60913825.0",
    "gn:asciiname":"Dhakadakshin",
    "gn:country_code":"BD",
    "gn:dem":20,
    "gn:feature_class":"P",
    "gn:feature_code":"PPL",
    "gn:name":"Dh\u0101kadakshin",
    "gn:population":0,
    "gn:timezone":"Asia/Dhaka",
    "iso:country":"BD",
    "wof:name":"Dhakadakshin",
    "wof:placetype":"locality"
},
  "geometry": {"coordinates":[92.04086,24.80879],"type":"Point"}
}