{
  "type": "Feature",
  "properties": {
    "gn:admin1_code":"82",
    "gn:admin2_code":"4001",
    "gn:admin3_code":"400173.0",
    "gn:admin4_code":"40017347.0",
    "gn:asciiname":"Hurka",
    "gn:country_code":"BD",
    "gn:dem":6,
    "gn:feature_class":"P",
    "gn:feature_code":"PPL",
    "gn:name":"Hurka",
    "gn:population":0,
    "gn:timezone":"Asia/Dhaka",
    "iso:country":"BD",
    "wof:name":"Hurka",
    "wof:placetype":"locality"
},
  "geometry": {"coordinates":[89.60961,22.55331],"type":"Point"}
}