{
  "type": "Feature",
  "properties": {
    "gn:admin1_code":"85",
    "gn:admin2_code":"1004.0",
    "gn:admin3_code":"100447.0",
    "gn:admin4_code":"10044783.0",
    "gn:asciiname":"Gabtali",
    "gn:country_code":"BD",
    "gn:dem":11,
    "gn:feature_class":"P",
    "gn:feature_code":"PPL",
    "gn:name":"Gabtali",
    "gn:population":0,
    "gn:timezone":"Asia/Dhaka",
    "iso:country":"BD",
    "name:ben_x_preferred":[
        "Gabtali"
    ],
    "wof:name":"Gabtali",
    "wof:placetype":"locality"
},
  "geometry": {"coordinates":[90.08580000000001,22.2314],"type":"Point"}
}