{
  "type": "Feature",
  "properties": {
    "gn:admin1_code":"82",
    "gn:admin2_code":"4057.0",
    "gn:admin3_code":"405747.0",
    "gn:admin4_code":"40574742.0",
    "gn:asciiname":"Tengramari",
    "gn:country_code":"BD",
    "gn:dem":21,
    "gn:feature_class":"P",
    "gn:feature_code":"PPL",
    "gn:name":"Tengr\u0101m\u0101ri",
    "gn:population":0,
    "gn:timezone":"Asia/Dhaka",
    "iso:country":"BD",
    "name:ben_x_preferred":[
        "Tengr\u0101m\u0101ri"
    ],
    "wof:name":"Tengramari",
    "wof:placetype":"locality"
},
  "geometry": {"coordinates":[88.72945,23.86076],"type":"Point"}
}