{
  "type": "Feature",
  "properties": {
    "gn:admin1_code":"87",
    "gn:admin2_code":"5532",
    "gn:admin3_code":"553291.0",
    "gn:admin4_code":"55329106.0",
    "gn:asciiname":"Hatibanda",
    "gn:country_code":"BD",
    "gn:dem":29,
    "gn:feature_class":"P",
    "gn:feature_code":"PPL",
    "gn:name":"H\u0101tib\u0101nda",
    "gn:population":0,
    "gn:timezone":"Asia/Dhaka",
    "iso:country":"BD",
    "name:ben_x_preferred":[
        "H\u0101tib\u0101nda"
    ],
    "wof:name":"Hatibanda",
    "wof:placetype":"locality"
},
  "geometry": {"coordinates":[89.41537,25.5786],"type":"Point"}
}