{
  "type": "Feature",
  "properties": {
    "gn:admin1_code":"84",
    "gn:admin2_code":"2012.0",
    "gn:admin3_code":"201290.0",
    "gn:admin4_code":"20129029.0",
    "gn:asciiname":"Chatalpar",
    "gn:country_code":"BD",
    "gn:dem":12,
    "gn:feature_class":"P",
    "gn:feature_code":"PPL",
    "gn:name":"Ch\u0101t\u0101lp\u0101r",
    "gn:population":0,
    "gn:timezone":"Asia/Dhaka",
    "iso:country":"BD",
    "wof:name":"Chatalpar",
    "wof:placetype":"locality"
},
  "geometry": {"coordinates":[91.08351999999999,24.20988],"type":"Point"}
}