{
  "type": "Feature",
  "properties": {
    "gn:admin1_code":"84",
    "gn:admin2_code":"2015.0",
    "gn:admin3_code":"201512.0",
    "gn:admin4_code":"20151266.0",
    "gn:asciiname":"Char Imamullah",
    "gn:country_code":"BD",
    "gn:dem":9,
    "gn:feature_class":"P",
    "gn:feature_code":"PPL",
    "gn:name":"Char Imamullah",
    "gn:population":0,
    "gn:timezone":"Asia/Dhaka",
    "iso:country":"BD",
    "name:ben_x_preferred":[
        "Char Imamullah"
    ],
    "wof:name":"Char Imamullah",
    "wof:placetype":"locality"
},
  "geometry": {"coordinates":[91.95489999999999,22.35131],"type":"Point"}
}