{
  "type": "Feature",
  "properties": {
    "gn:admin1_code":"87",
    "gn:admin2_code":"5552",
    "gn:admin3_code":"555202.0",
    "gn:admin4_code":"55520283.0",
    "gn:asciiname":"Saptibari",
    "gn:country_code":"BD",
    "gn:dem":35,
    "gn:feature_class":"P",
    "gn:feature_code":"PPL",
    "gn:name":"S\u0101ptib\u0101ri",
    "gn:population":0,
    "gn:timezone":"Asia/Dhaka",
    "iso:country":"BD",
    "name:ben_x_preferred":[
        "S\u0101ptib\u0101ri"
    ],
    "wof:name":"Saptibari",
    "wof:placetype":"locality"
},
  "geometry": {"coordinates":[89.40784000000002,25.90496],"type":"Point"}
}