{
  "type": "Feature",
  "properties": {
    "gn:admin1_code":"83",
    "gn:admin2_code":"5010.0",
    "gn:admin3_code":"501020.0",
    "gn:admin4_code":"50102069.0",
    "gn:asciiname":"Dashtika",
    "gn:country_code":"BD",
    "gn:dem":24,
    "gn:feature_class":"P",
    "gn:feature_code":"PPL",
    "gn:name":"Dashtika",
    "gn:population":0,
    "gn:timezone":"Asia/Dhaka",
    "iso:country":"BD",
    "name:und_x_variant":[
        "Dastika",
        "Dashtika"
    ],
    "wof:name":"Dashtika",
    "wof:placetype":"locality"
},
  "geometry": {"coordinates":[89.33798,24.89447],"type":"Point"}
}