{
  "type": "Feature",
  "properties": {
    "gn:admin1_code":"83",
    "gn:admin2_code":"5081.0",
    "gn:admin3_code":"508134.0",
    "gn:admin4_code":"50813457.0",
    "gn:asciiname":"Baje Tirinda",
    "gn:cc2":"BD",
    "gn:country_code":"BD",
    "gn:dem":35,
    "gn:feature_class":"P",
    "gn:feature_code":"PPL",
    "gn:name":"B\u0101je Tirinda",
    "gn:population":0,
    "gn:timezone":"Asia/Dhaka",
    "iso:country":"BD",
    "name:und_x_variant":[
        "Baze Tirinda",
        "B\u0101je Tirinda"
    ],
    "wof:name":"Baje Tirinda",
    "wof:placetype":"locality"
},
  "geometry": {"coordinates":[88.38333,24.45],"type":"Point"}
}