{
  "type": "Feature",
  "properties": {
    "gn:admin1_code":"82",
    "gn:admin2_code":"4041",
    "gn:admin3_code":"404161.0",
    "gn:admin4_code":"40416167.0",
    "gn:asciiname":"Sonadanga",
    "gn:country_code":"BD",
    "gn:dem":11,
    "gn:feature_class":"P",
    "gn:feature_code":"PPL",
    "gn:name":"Sonadanga",
    "gn:population":0,
    "gn:timezone":"Asia/Dhaka",
    "iso:country":"BD",
    "name:ben_x_preferred":[
        "Sonadanga"
    ],
    "wof:name":"Sonadanga",
    "wof:placetype":"locality"
},
  "geometry": {"coordinates":[89.20146,23.03312],"type":"Point"}
}