{
  "type": "Feature",
  "properties": {
    "gn:admin1_code":"83",
    "gn:admin2_code":"5064.0",
    "gn:admin3_code":"506403.0",
    "gn:admin4_code":"50640352.0",
    "gn:asciiname":"Bazedhanesawar",
    "gn:country_code":"BD",
    "gn:dem":17,
    "gn:feature_class":"P",
    "gn:feature_code":"PPL",
    "gn:name":"B\u0101zedhanesawar",
    "gn:population":0,
    "gn:timezone":"Asia/Dhaka",
    "iso:country":"BD",
    "name:ben_x_preferred":[
        "B\u0101zedhanesawar"
    ],
    "name:ben_x_variant":[
        "B\u0101ze Dhaneswar"
    ],
    "name:und_x_variant":[
        "Baji Dhaneshwar"
    ],
    "wof:name":"Bazedhanesawar",
    "wof:placetype":"locality"
},
  "geometry": {"coordinates":[88.88795,24.65946],"type":"Point"}
}