{
  "type": "Feature",
  "properties": {
    "gn:admin1_code":"87",
    "gn:admin2_code":"5577.0",
    "gn:admin3_code":"557734.0",
    "gn:admin4_code":"55773457.0",
    "gn:asciiname":"Muslim Paikan",
    "gn:country_code":"BD",
    "gn:dem":61,
    "gn:feature_class":"P",
    "gn:feature_code":"PPL",
    "gn:name":"Muslim P\u0101ikan",
    "gn:population":0,
    "gn:timezone":"Asia/Dhaka",
    "iso:country":"BD",
    "name:ben_x_preferred":[
        "Muslim P\u0101ikan"
    ],
    "wof:name":"Muslim Paikan",
    "wof:placetype":"locality"
},
  "geometry": {"coordinates":[88.66511,26.11694],"type":"Point"}
}