{
  "type": "Feature",
  "properties": {
    "gn:admin1_code":"H",
    "gn:admin2_code":"3072.0",
    "gn:admin3_code":"307218.0",
    "gn:admin4_code":"30721808.0",
    "gn:asciiname":"Bakaljhora",
    "gn:country_code":"BD",
    "gn:dem":16,
    "gn:feature_class":"P",
    "gn:feature_code":"PPL",
    "gn:name":"B\u0101kaljhora",
    "gn:population":0,
    "gn:timezone":"Asia/Dhaka",
    "iso:country":"BD",
    "name:und_x_variant":[
        "Bakajora",
        "B\u0101kaljhora",
        "B\u0101kalihora"
    ],
    "wof:name":"Bakaljhora",
    "wof:placetype":"locality"
},
  "geometry": {"coordinates":[90.73259,25.0252],"type":"Point"}
}