{
  "type": "Feature",
  "properties": {
    "gn:admin1_code":"85",
    "gn:admin2_code":"1006",
    "gn:admin3_code":"100662.0",
    "gn:admin4_code":"10066294.0",
    "gn:asciiname":"Purbba Swarta",
    "gn:country_code":"BD",
    "gn:dem":8,
    "gn:feature_class":"P",
    "gn:feature_code":"PPL",
    "gn:name":"Purbba Swarta",
    "gn:population":0,
    "gn:timezone":"Asia/Dhaka",
    "iso:country":"BD",
    "name:und_x_variant":[
        "Purba Swatwa",
        "Purbba Swatwa",
        "Purbba Swarta"
    ],
    "wof:name":"Purbba Swarta",
    "wof:placetype":"locality"
},
  "geometry": {"coordinates":[90.59005999999999,22.86255],"type":"Point"}
}