{
  "type": "Feature",
  "properties": {
    "gn:admin1_code":"81",
    "gn:admin2_code":"3029",
    "gn:admin3_code":"302947.0",
    "gn:admin4_code":"30294763.0",
    "gn:asciiname":"Karimpur",
    "gn:country_code":"BD",
    "gn:dem":14,
    "gn:feature_class":"P",
    "gn:feature_code":"PPL",
    "gn:name":"Karimpur",
    "gn:population":0,
    "gn:timezone":"Asia/Dhaka",
    "iso:country":"BD",
    "name:ben_x_preferred":[
        "\u0995\u09b0\u09bf\u09ae\u09aa\u09c1\u09b0"
    ],
    "name:bpy_x_preferred":[
        "\u0995\u09b0\u09bf\u09ae\u09aa\u09c1\u09b0"
    ],
    "name:ceb_x_preferred":[
        "Kar\u012bmpur"
    ],
    "name:ita_x_preferred":[
        "Karimpur"
    ],
    "name:msa_x_preferred":[
        "Karimpur"
    ],
    "name:new_x_preferred":[
        "\u0915\u0930\u093f\u092e\u092a\u0941\u0930"
    ],
    "name:nld_x_preferred":[
        "Karimpur"
    ],
    "name:por_x_preferred":[
        "Karimpur"
    ],
    "name:rus_x_preferred":[
        "\u041a\u0430\u0440\u0438\u043c\u043f\u0443\u0440"
    ],
    "name:swe_x_preferred":[
        "Kar\u012bmpur"
    ],
    "name:tam_x_preferred":[
        "\u0b95\u0bb0\u0bc0\u0bae\u0bcd\u0baa\u0bc2\u0bb0\u0bcd"
    ],
    "name:vie_x_preferred":[
        "Karimpur"
    ],
    "name:zho_x_preferred":[
        "\u5361\u91cc\u59c6\u666e\u5c14"
    ],
    "wof:name":"Karimpur",
    "wof:placetype":"locality"
},
  "geometry": {"coordinates":[89.75116,23.53841],"type":"Point"}
}