{
  "type": "Feature",
  "properties": {
    "gn:admin1_code":"H",
    "gn:admin2_code":"3072",
    "gn:admin3_code":"307247.0",
    "gn:admin4_code":"30724781.0",
    "gn:asciiname":"Naopara",
    "gn:country_code":"BD",
    "gn:dem":13,
    "gn:feature_class":"P",
    "gn:feature_code":"PPL",
    "gn:name":"Naop\u0101ra",
    "gn:population":0,
    "gn:timezone":"Asia/Dhaka",
    "iso:country":"BD",
    "wof:name":"Naopara",
    "wof:placetype":"locality"
},
  "geometry": {"coordinates":[90.8219,24.6117],"type":"Point"}
}