{
  "type": "Feature",
  "properties": {
    "gn:admin1_code":"82",
    "gn:admin2_code":"4018.0",
    "gn:admin3_code":"401823.0",
    "gn:admin4_code":"40182383.0",
    "gn:asciiname":"Bara Aria",
    "gn:country_code":"BD",
    "gn:dem":15,
    "gn:feature_class":"P",
    "gn:feature_code":"PPL",
    "gn:name":"Bara \u0100ria",
    "gn:population":0,
    "gn:timezone":"Asia/Dhaka",
    "iso:country":"BD",
    "name:ben_x_preferred":[
        "Bara \u0100ria"
    ],
    "wof:name":"Bara Aria",
    "wof:placetype":"locality"
},
  "geometry": {"coordinates":[88.88500999999999,23.53696],"type":"Point"}
}