{
  "type": "Feature",
  "properties": {
    "gn:admin1_code":"82",
    "gn:admin2_code":"4044.0",
    "gn:admin3_code":"404471.0",
    "gn:admin4_code":"40447177.0",
    "gn:asciiname":"Anantapur",
    "gn:country_code":"BD",
    "gn:dem":15,
    "gn:feature_class":"P",
    "gn:feature_code":"PPL",
    "gn:name":"Anantapur",
    "gn:population":0,
    "gn:timezone":"Asia/Dhaka",
    "iso:country":"BD",
    "name:ben_x_preferred":[
        "Anantapur"
    ],
    "wof:name":"Anantapur",
    "wof:placetype":"locality"
},
  "geometry": {"coordinates":[88.78431999999999,23.34297],"type":"Point"}
}