{
  "type": "Feature",
  "properties": {
    "gn:admin1_code":"81",
    "gn:admin2_code":"3086.0",
    "gn:admin3_code":"308669.0",
    "gn:admin4_code":"30866957.0",
    "gn:asciiname":"Domsar",
    "gn:country_code":"BD",
    "gn:dem":12,
    "gn:feature_class":"P",
    "gn:feature_code":"PPL",
    "gn:name":"Doms\u0101r",
    "gn:population":0,
    "gn:timezone":"Asia/Dhaka",
    "iso:country":"BD",
    "wof:name":"Domsar",
    "wof:placetype":"locality"
},
  "geometry": {"coordinates":[90.34017,23.24445],"type":"Point"}
}