{
  "type": "Feature",
  "properties": {
    "gn:admin1_code":"84",
    "gn:admin2_code":"2051.0",
    "gn:admin3_code":"205143.0",
    "gn:admin4_code":"20514395.0",
    "gn:asciiname":"Chandra Prabhabag",
    "gn:country_code":"BD",
    "gn:dem":13,
    "gn:feature_class":"P",
    "gn:feature_code":"PPL",
    "gn:name":"Chandra Prabh\u0101b\u0101g",
    "gn:population":0,
    "gn:timezone":"Asia/Dhaka",
    "iso:country":"BD",
    "wof:name":"Chandra Prabhabag",
    "wof:placetype":"locality"
},
  "geometry": {"coordinates":[90.96281999999999,22.96614],"type":"Point"}
}