{
  "type": "Feature",
  "properties": {
    "gn:admin1_code":"87",
    "gn:admin2_code":"5552",
    "gn:admin3_code":"555233.0",
    "gn:admin4_code":"55523328.0",
    "gn:asciiname":"Dauabari",
    "gn:country_code":"BD",
    "gn:dem":48,
    "gn:feature_class":"P",
    "gn:feature_code":"PPL",
    "gn:name":"D\u0101uab\u0101ri",
    "gn:population":0,
    "gn:timezone":"Asia/Dhaka",
    "iso:country":"BD",
    "name:und_x_variant":[
        "Purba Daobari",
        "Purba Dewab\u0101ri",
        "D\u0101uab\u0101ri"
    ],
    "wof:name":"Dauabari",
    "wof:placetype":"locality"
},
  "geometry": {"coordinates":[89.15179000000001,26.05017],"type":"Point"}
}