{
  "type": "Feature",
  "properties": {
    "gn:admin1_code":"84",
    "gn:admin2_code":"2019",
    "gn:admin3_code":"201937.0",
    "gn:admin4_code":"20193708.0",
    "gn:asciiname":"Manairkandi",
    "gn:country_code":"BD",
    "gn:dem":10,
    "gn:feature_class":"P",
    "gn:feature_code":"PPL",
    "gn:name":"Man\u0101irk\u0101ndi",
    "gn:population":0,
    "gn:timezone":"Asia/Dhaka",
    "iso:country":"BD",
    "wof:name":"Manairkandi",
    "wof:placetype":"locality"
},
  "geometry": {"coordinates":[90.80047999999999,23.59621],"type":"Point"}
}