{
  "type": "Feature",
  "properties": {
    "gn:admin1_code":"85",
    "gn:admin2_code":"1079",
    "gn:admin3_code":"107958.0",
    "gn:admin4_code":"10795860.0",
    "gn:asciiname":"Patakata",
    "gn:country_code":"BD",
    "gn:dem":15,
    "gn:feature_class":"P",
    "gn:feature_code":"PPL",
    "gn:name":"Patakata",
    "gn:population":0,
    "gn:timezone":"Asia/Dhaka",
    "iso:country":"BD",
    "name:ben_x_preferred":[
        "Patakata"
    ],
    "name:und_x_variant":[
        "Pathakata"
    ],
    "wof:name":"Patakata",
    "wof:placetype":"locality"
},
  "geometry": {"coordinates":[89.97649,22.3066],"type":"Point"}
}