{
  "type": "Feature",
  "properties": {
    "gn:admin1_code":"87",
    "gn:admin2_code":"5594.0",
    "gn:admin3_code":"559494.0",
    "gn:admin4_code":"55949452.0",
    "gn:asciiname":"Parphubi",
    "gn:country_code":"BD",
    "gn:dem":56,
    "gn:feature_class":"P",
    "gn:feature_code":"PPL",
    "gn:name":"P\u0101rphubi",
    "gn:population":0,
    "gn:timezone":"Asia/Dhaka",
    "iso:country":"BD",
    "name:ben_x_preferred":[
        "P\u0101rphubi"
    ],
    "wof:name":"Parphubi",
    "wof:placetype":"locality"
},
  "geometry": {"coordinates":[88.39015000000001,26.00205],"type":"Point"}
}