{
  "type": "Feature",
  "properties": {
    "gn:admin1_code":"82",
    "gn:admin2_code":"4087.0",
    "gn:admin3_code":"408786.0",
    "gn:admin4_code":"40878655.0",
    "gn:asciiname":"Godara",
    "gn:country_code":"BD",
    "gn:dem":5,
    "gn:feature_class":"P",
    "gn:feature_code":"PPL",
    "gn:name":"God\u0101ra",
    "gn:population":0,
    "gn:timezone":"Asia/Dhaka",
    "iso:country":"BD",
    "name:ben_x_preferred":[
        "God\u0101ra"
    ],
    "wof:name":"Godara",
    "wof:placetype":"locality"
},
  "geometry": {"coordinates":[89.18668000000002,22.35798],"type":"Point"}
}