{
  "type": "Feature",
  "properties": {
    "gn:admin1_code":"83",
    "gn:admin2_code":"5010",
    "gn:admin3_code":"501081.0",
    "gn:admin4_code":"50108181.0",
    "gn:asciiname":"Pakulla",
    "gn:country_code":"BD",
    "gn:dem":23,
    "gn:feature_class":"P",
    "gn:feature_code":"PPL",
    "gn:name":"P\u0101kulla",
    "gn:population":0,
    "gn:timezone":"Asia/Dhaka",
    "iso:country":"BD",
    "wof:name":"Pakulla",
    "wof:placetype":"locality"
},
  "geometry": {"coordinates":[89.55580999999999,24.98536],"type":"Point"}
}