{
  "type": "Feature",
  "properties": {
    "gn:admin1_code":"H",
    "gn:admin2_code":"3061",
    "gn:admin3_code":"306165.0",
    "gn:admin4_code":"30616551.0",
    "gn:asciiname":"Rajabari",
    "gn:country_code":"BD",
    "gn:dem":19,
    "gn:feature_class":"P",
    "gn:feature_code":"PPL",
    "gn:name":"R\u0101j\u0101b\u0101ri",
    "gn:population":0,
    "gn:timezone":"Asia/Dhaka",
    "iso:country":"BD",
    "wof:name":"Rajabari",
    "wof:placetype":"locality"
},
  "geometry": {"coordinates":[90.17188,24.69684],"type":"Point"}
}