{
  "type": "Feature",
  "properties": {
    "gn:admin1_code":"83",
    "gn:admin2_code":"5081.0",
    "gn:admin3_code":"508112.0",
    "gn:admin4_code":"50811275.0",
    "gn:asciiname":"Anantopara",
    "gn:country_code":"BD",
    "gn:dem":20,
    "gn:feature_class":"P",
    "gn:feature_code":"PPL",
    "gn:name":"Anantop\u0101ra",
    "gn:population":0,
    "gn:timezone":"Asia/Dhaka",
    "iso:country":"BD",
    "name:ben_x_preferred":[
        "Anantop\u0101ra"
    ],
    "name:ben_x_variant":[
        "Anantap\u0101ra"
    ],
    "wof:name":"Anantopara",
    "wof:placetype":"locality"
},
  "geometry": {"coordinates":[88.84723000000002,24.58831],"type":"Point"}
}