{
  "type": "Feature",
  "properties": {
    "gn:admin1_code":"85",
    "gn:admin2_code":"1078.0",
    "gn:admin3_code":"107866.0",
    "gn:admin4_code":"10786683.0",
    "gn:asciiname":"Badurtali",
    "gn:country_code":"BD",
    "gn:dem":6,
    "gn:feature_class":"P",
    "gn:feature_code":"PPL",
    "gn:name":"B\u0101durtali",
    "gn:population":0,
    "gn:timezone":"Asia/Dhaka",
    "iso:country":"BD",
    "name:ben_x_preferred":[
        "B\u0101durtali"
    ],
    "wof:name":"Badurtali",
    "wof:placetype":"locality"
},
  "geometry": {"coordinates":[90.23726000000001,21.97611],"type":"Point"}
}