{
  "type": "Feature",
  "properties": {
    "gn:admin1_code":"82",
    "gn:admin2_code":"4001.0",
    "gn:admin3_code":"400160.0",
    "gn:admin4_code":"40016065.0",
    "gn:asciiname":"Paschim Saralia",
    "gn:country_code":"BD",
    "gn:dem":9,
    "gn:feature_class":"P",
    "gn:feature_code":"PPL",
    "gn:name":"Paschim Saralia",
    "gn:population":0,
    "gn:timezone":"Asia/Dhaka",
    "iso:country":"BD",
    "name:ben_x_preferred":[
        "Paschim Saralia"
    ],
    "wof:name":"Paschim Saralia",
    "wof:placetype":"locality"
},
  "geometry": {"coordinates":[89.82965,22.44998],"type":"Point"}
}