{
  "type": "Feature",
  "properties": {
    "gn:admin1_code":"83",
    "gn:admin2_code":"5070.0",
    "gn:admin3_code":"507088.0",
    "gn:admin4_code":"50708817.0",
    "gn:asciiname":"Kamaipur",
    "gn:country_code":"BD",
    "gn:dem":30,
    "gn:feature_class":"P",
    "gn:feature_code":"PPL",
    "gn:name":"Kamaipur",
    "gn:population":0,
    "gn:timezone":"Asia/Dhaka",
    "iso:country":"BD",
    "name:ben_x_preferred":[
        "Kamaipur"
    ],
    "wof:name":"Kamaipur",
    "wof:placetype":"locality"
},
  "geometry": {"coordinates":[88.17144,24.84965],"type":"Point"}
}