{
  "type": "Feature",
  "properties": {
    "gn:admin1_code":"81",
    "gn:admin2_code":"3029",
    "gn:admin3_code":"302918.0",
    "gn:admin4_code":"30291815.0",
    "gn:asciiname":"Sibpur",
    "gn:country_code":"BD",
    "gn:dem":10,
    "gn:feature_class":"P",
    "gn:feature_code":"PPL",
    "gn:name":"Sibpur",
    "gn:population":0,
    "gn:timezone":"Asia/Dhaka",
    "iso:country":"BD",
    "wof:name":"Sibpur",
    "wof:placetype":"locality"
},
  "geometry": {"coordinates":[89.68902,23.39927],"type":"Point"}
}