{
  "type": "Feature",
  "properties": {
    "gn:admin1_code":"84",
    "gn:admin2_code":"2030.0",
    "gn:admin3_code":"203029.0",
    "gn:admin4_code":"20302917.0",
    "gn:asciiname":"Dhalia",
    "gn:cc2":"BD",
    "gn:country_code":"BD",
    "gn:dem":14,
    "gn:feature_class":"P",
    "gn:feature_code":"PPL",
    "gn:name":"Dhalia",
    "gn:population":0,
    "gn:timezone":"Asia/Dhaka",
    "iso:country":"BD",
    "name:ind_x_preferred":[
        "Dhalia"
    ],
    "name:msa_x_preferred":[
        "Dhalia"
    ],
    "name:und_x_variant":[
        "Big Dhalia",
        "Dhalia"
    ],
    "wof:name":"Dhalia",
    "wof:placetype":"locality"
},
  "geometry": {"coordinates":[91.40000000000001,22.96667],"type":"Point"}
}