{
  "type": "Feature",
  "properties": {
    "gn:admin1_code":"82",
    "gn:admin2_code":"4041.0",
    "gn:admin3_code":"404190.0",
    "gn:admin4_code":"40419077.0",
    "gn:asciiname":"Britti Achra",
    "gn:country_code":"BD",
    "gn:dem":12,
    "gn:feature_class":"P",
    "gn:feature_code":"PPL",
    "gn:name":"Britti \u0100chra",
    "gn:population":0,
    "gn:timezone":"Asia/Dhaka",
    "iso:country":"BD",
    "name:ben_x_preferred":[
        "Britti \u0100chra"
    ],
    "wof:name":"Britti Achra",
    "wof:placetype":"locality"
},
  "geometry": {"coordinates":[88.9153,23.01515],"type":"Point"}
}