{
  "type": "Feature",
  "properties": {
    "gn:admin1_code":"85",
    "gn:admin2_code":"1006.0",
    "gn:admin3_code":"100602.0",
    "gn:admin4_code":"10060279.0",
    "gn:asciiname":"Purba Basunda",
    "gn:country_code":"BD",
    "gn:dem":9,
    "gn:feature_class":"P",
    "gn:feature_code":"PPL",
    "gn:name":"Purba Basunda",
    "gn:population":0,
    "gn:timezone":"Asia/Dhaka",
    "iso:country":"BD",
    "name:und_x_variant":[
        "East Basunda"
    ],
    "wof:name":"Purba Basunda",
    "wof:placetype":"locality"
},
  "geometry": {"coordinates":[90.16354,22.98976],"type":"Point"}
}