{
  "type": "Feature",
  "properties": {
    "gn:admin1_code":"83",
    "gn:admin2_code":"5064.0",
    "gn:admin3_code":"506428.0",
    "gn:admin4_code":"50642852.0",
    "gn:asciiname":"Chak Chaitanya",
    "gn:country_code":"BD",
    "gn:dem":24,
    "gn:feature_class":"P",
    "gn:feature_code":"PPL",
    "gn:name":"Chak Chaitanya",
    "gn:population":0,
    "gn:timezone":"Asia/Dhaka",
    "iso:country":"BD",
    "name:ben_x_preferred":[
        "Chak Chaitanya"
    ],
    "wof:name":"Chak Chaitanya",
    "wof:placetype":"locality"
},
  "geometry": {"coordinates":[88.92435,25.05933],"type":"Point"}
}