{
  "type": "Feature",
  "properties": {
    "gn:admin1_code":"81",
    "gn:admin2_code":"3026.0",
    "gn:admin3_code":"302672.0",
    "gn:admin4_code":"30267239.0",
    "gn:asciiname":"Dhalpur",
    "gn:country_code":"BD",
    "gn:dem":17,
    "gn:feature_class":"P",
    "gn:feature_code":"PPL",
    "gn:name":"Dhalpur",
    "gn:population":0,
    "gn:timezone":"Asia/Dhaka",
    "iso:country":"BD",
    "wof:name":"Dhalpur",
    "wof:placetype":"locality"
},
  "geometry": {"coordinates":[90.28463000000001,23.92799],"type":"Point"}
}