{
  "type": "Feature",
  "properties": {
    "gn:admin1_code":"84",
    "gn:admin2_code":"2019",
    "gn:admin3_code":"201909.0",
    "gn:admin4_code":"20190906.0",
    "gn:asciiname":"West Baghmara",
    "gn:country_code":"BD",
    "gn:dem":15,
    "gn:feature_class":"P",
    "gn:feature_code":"PPL",
    "gn:name":"West B\u0101ghm\u0101ra",
    "gn:population":0,
    "gn:timezone":"Asia/Dhaka",
    "iso:country":"BD",
    "name:und_x_variant":[
        "B\u0101ghm\u0101r\u0101",
        "West Bagmara",
        "West B\u0101ghm\u0101ra"
    ],
    "wof:name":"West Baghmara",
    "wof:placetype":"locality"
},
  "geometry": {"coordinates":[90.98075,23.3287],"type":"Point"}
}