{
  "type": "Feature",
  "properties": {
    "gn:admin1_code":"84",
    "gn:admin2_code":"2030",
    "gn:admin3_code":"203029.0",
    "gn:admin4_code":"20302943.0",
    "gn:asciiname":"Kalidaha",
    "gn:country_code":"BD",
    "gn:dem":9,
    "gn:feature_class":"P",
    "gn:feature_code":"PPL",
    "gn:name":"K\u0101l\u012bd\u0101ha",
    "gn:population":0,
    "gn:timezone":"Asia/Dhaka",
    "iso:country":"BD",
    "wof:name":"Kalidaha",
    "wof:placetype":"locality"
},
  "geometry": {"coordinates":[91.43333,22.98333],"type":"Point"}
}