{
  "type": "Feature",
  "properties": {
    "gn:admin1_code":"83",
    "gn:admin2_code":"5070.0",
    "gn:admin3_code":"507066.0",
    "gn:admin4_code":"50706613.0",
    "gn:asciiname":"Ranihat",
    "gn:country_code":"BD",
    "gn:dem":26,
    "gn:feature_class":"P",
    "gn:feature_code":"PPL",
    "gn:name":"Ranih\u0101t",
    "gn:population":0,
    "gn:timezone":"Asia/Dhaka",
    "iso:country":"BD",
    "name:ben_x_preferred":[
        "Ranih\u0101t"
    ],
    "wof:name":"Ranihat",
    "wof:placetype":"locality"
},
  "geometry": {"coordinates":[88.26339,24.60428],"type":"Point"}
}