{
  "type": "Feature",
  "properties": {
    "gn:admin1_code":"83",
    "gn:admin2_code":"5076.0",
    "gn:admin3_code":"507683.0",
    "gn:admin4_code":"50768366.0",
    "gn:asciiname":"Hogladangi",
    "gn:country_code":"BD",
    "gn:dem":15,
    "gn:feature_class":"P",
    "gn:feature_code":"PPL",
    "gn:name":"Hogladangi",
    "gn:population":0,
    "gn:timezone":"Asia/Dhaka",
    "iso:country":"BD",
    "name:ben_x_preferred":[
        "Hogladangi"
    ],
    "wof:name":"Hogladangi",
    "wof:placetype":"locality"
},
  "geometry": {"coordinates":[89.59363,23.84418],"type":"Point"}
}