{
  "type": "Feature",
  "properties": {
    "gn:admin1_code":"87",
    "gn:admin2_code":"5527",
    "gn:admin3_code":"552769.0",
    "gn:admin4_code":"55276917.0",
    "gn:asciiname":"Kanchdaha",
    "gn:country_code":"BD",
    "gn:dem":33,
    "gn:feature_class":"P",
    "gn:feature_code":"PPL",
    "gn:name":"Kanchdaha",
    "gn:population":0,
    "gn:timezone":"Asia/Dhaka",
    "iso:country":"BD",
    "name:ben_x_preferred":[
        "Kanchdaha"
    ],
    "wof:name":"Kanchdaha",
    "wof:placetype":"locality"
},
  "geometry": {"coordinates":[89.14560999999998,25.42964],"type":"Point"}
}