{
  "type": "Feature",
  "properties": {
    "gn:admin1_code":"82",
    "gn:admin2_code":"4087.0",
    "gn:admin3_code":"408704.0",
    "gn:admin4_code":"40870425.0",
    "gn:asciiname":"Bardal",
    "gn:country_code":"BD",
    "gn:dem":7,
    "gn:feature_class":"P",
    "gn:feature_code":"PPL",
    "gn:name":"Bardal",
    "gn:population":0,
    "gn:timezone":"Asia/Dhaka",
    "iso:country":"BD",
    "name:und_x_variant":[
        "Baradal",
        "Bardal"
    ],
    "wof:name":"Bardal",
    "wof:placetype":"locality"
},
  "geometry": {"coordinates":[89.24551,22.52265],"type":"Point"}
}