{
  "type": "Feature",
  "properties": {
    "gn:admin1_code":"81",
    "gn:admin2_code":"3093.0",
    "gn:admin3_code":"309328.0",
    "gn:admin4_code":"30932886.0",
    "gn:asciiname":"Beila",
    "gn:country_code":"BD",
    "gn:dem":21,
    "gn:feature_class":"P",
    "gn:feature_code":"PPL",
    "gn:name":"Beila",
    "gn:population":0,
    "gn:timezone":"Asia/Dhaka",
    "iso:country":"BD",
    "wof:name":"Beila",
    "wof:placetype":"locality"
},
  "geometry": {"coordinates":[90.18944999999999,24.47806],"type":"Point"}
}