{
  "type": "Feature",
  "properties": {
    "gn:admin1_code":"87",
    "gn:admin2_code":"5585",
    "gn:admin3_code":"558576.0",
    "gn:admin4_code":"55857618.0",
    "gn:asciiname":"Milki",
    "gn:country_code":"BD",
    "gn:dem":33,
    "gn:feature_class":"P",
    "gn:feature_code":"PPL",
    "gn:name":"Milki",
    "gn:population":0,
    "gn:timezone":"Asia/Dhaka",
    "iso:country":"BD",
    "name:ben_x_preferred":[
        "Milki"
    ],
    "wof:name":"Milki",
    "wof:placetype":"locality"
},
  "geometry": {"coordinates":[89.21916,25.49293],"type":"Point"}
}