{
  "type": "Feature",
  "properties": {
    "gn:admin1_code":"83",
    "gn:admin2_code":"5081.0",
    "gn:admin3_code":"508112.0",
    "gn:admin4_code":"50811282.0",
    "gn:asciiname":"Bharatta",
    "gn:country_code":"BD",
    "gn:dem":17,
    "gn:feature_class":"P",
    "gn:feature_code":"PPL",
    "gn:name":"Bharatta",
    "gn:population":0,
    "gn:timezone":"Asia/Dhaka",
    "iso:country":"BD",
    "name:ben_x_preferred":[
        "Bharatta"
    ],
    "wof:name":"Bharatta",
    "wof:placetype":"locality"
},
  "geometry": {"coordinates":[88.79951,24.67234],"type":"Point"}
}