{
  "type": "Feature",
  "properties": {
    "gn:admin1_code":"83",
    "gn:admin2_code":"5010.0",
    "gn:admin3_code":"501020.0",
    "gn:admin4_code":"50102047.0",
    "gn:asciiname":"Chandihara",
    "gn:country_code":"BD",
    "gn:dem":21,
    "gn:feature_class":"P",
    "gn:feature_code":"PPL",
    "gn:name":"Chandih\u0101ra",
    "gn:population":0,
    "gn:timezone":"Asia/Dhaka",
    "iso:country":"BD",
    "wof:name":"Chandihara",
    "wof:placetype":"locality"
},
  "geometry": {"coordinates":[89.36315999999999,24.96918],"type":"Point"}
}