{
  "type": "Feature",
  "properties": {
    "gn:admin1_code":"82",
    "gn:admin2_code":"4055.0",
    "gn:admin3_code":"405595.0",
    "gn:admin4_code":"40559510.0",
    "gn:asciiname":"Chhota Udas",
    "gn:country_code":"BD",
    "gn:dem":14,
    "gn:feature_class":"P",
    "gn:feature_code":"PPL",
    "gn:name":"Chhota Ud\u0101s",
    "gn:population":0,
    "gn:timezone":"Asia/Dhaka",
    "iso:country":"BD",
    "wof:name":"Chhota Udas",
    "wof:placetype":"locality"
},
  "geometry": {"coordinates":[89.40425999999999,23.64059],"type":"Point"}
}