{
  "type": "Feature",
  "properties": {
    "gn:admin1_code":"86",
    "gn:admin2_code":"6058",
    "gn:admin3_code":"605865.0",
    "gn:admin4_code":"60586535.0",
    "gn:asciiname":"Manu",
    "gn:country_code":"BD",
    "gn:dem":24,
    "gn:feature_class":"P",
    "gn:feature_code":"PPL",
    "gn:name":"Manu",
    "gn:population":0,
    "gn:timezone":"Asia/Dhaka",
    "iso:country":"BD",
    "wof:name":"Manu",
    "wof:placetype":"locality"
},
  "geometry": {"coordinates":[91.93519999999999,24.4279],"type":"Point"}
}