{
  "type": "Feature",
  "properties": {
    "gn:admin1_code":"86",
    "gn:admin2_code":"6058",
    "gn:admin3_code":"605865.0",
    "gn:admin4_code":"60586535.0",
    "gn:asciiname":"Manu",
    "gn:country_code":"BD",
    "gn:dem":24,
    "gn:feature_class":"P",
    "gn:feature_code":"PPL",
    "gn:name":"Manu",
    "gn:population":0,
    "gn:timezone":"Asia/Dhaka",
    "iso:country":"BD",
    "name:ben_x_preferred":[
        "\u09ae\u09a8\u09c1"
    ],
    "name:bre_x_preferred":[
        "Manu"
    ],
    "name:bul_x_preferred":[
        "\u041c\u0430\u043d\u0443"
    ],
    "name:cat_x_preferred":[
        "Manu"
    ],
    "name:ceb_x_preferred":[
        "Manu"
    ],
    "name:deu_x_preferred":[
        "Manu"
    ],
    "name:fin_x_preferred":[
        "Manu"
    ],
    "name:fra_x_preferred":[
        "Manu"
    ],
    "name:heb_x_preferred":[
        "\u05de\u05e0\u05d5"
    ],
    "name:ita_x_preferred":[
        "Manu"
    ],
    "name:nld_x_preferred":[
        "Manu"
    ],
    "name:nor_x_preferred":[
        "Manu"
    ],
    "name:por_x_preferred":[
        "Manu"
    ],
    "name:ron_x_preferred":[
        "Manu"
    ],
    "name:rus_x_preferred":[
        "\u041c\u0430\u043d\u0443"
    ],
    "name:spa_x_preferred":[
        "Manu"
    ],
    "name:ukr_x_preferred":[
        "\u041c\u0430\u043d\u0443"
    ],
    "wof:name":"Manu",
    "wof:placetype":"locality"
},
  "geometry": {"coordinates":[91.93519999999999,24.4279],"type":"Point"}
}