{
  "type": "Feature",
  "properties": {
    "gn:admin1_code":"84",
    "gn:admin2_code":"2013",
    "gn:admin3_code":"201345.0",
    "gn:admin4_code":"20134571.0",
    "gn:asciiname":"Sahapur",
    "gn:country_code":"BD",
    "gn:dem":15,
    "gn:feature_class":"P",
    "gn:feature_code":"PPL",
    "gn:name":"S\u0101h\u0101pur",
    "gn:population":0,
    "gn:timezone":"Asia/Dhaka",
    "iso:country":"BD",
    "name:ben_x_preferred":[
        "\u09b8\u09be\u09b9\u09be\u09aa\u09c1\u09b0"
    ],
    "name:bpy_x_preferred":[
        "\u09b8\u09be\u09b9\u09be\u09aa\u09c1\u09b0"
    ],
    "name:ceb_x_preferred":[
        "S\u0101h\u0101pur"
    ],
    "name:hif_x_preferred":[
        "Sahapur"
    ],
    "name:ita_x_preferred":[
        "Sahapur"
    ],
    "name:msa_x_preferred":[
        "Sahapur"
    ],
    "name:nld_x_preferred":[
        "Sahapur"
    ],
    "name:por_x_preferred":[
        "Sahapur"
    ],
    "name:swe_x_preferred":[
        "S\u0101h\u0101pur"
    ],
    "name:urd_x_preferred":[
        "\u0633\u06c1\u067e\u0631"
    ],
    "name:vie_x_preferred":[
        "Sahapur"
    ],
    "name:zho_x_preferred":[
        "\u8428\u54c8\u666e\u5c14"
    ],
    "wof:name":"Sahapur",
    "wof:placetype":"locality"
},
  "geometry": {"coordinates":[90.76482,23.15306],"type":"Point"}
}