{
  "type": "Feature",
  "properties": {
    "gn:admin1_code":"87",
    "gn:admin2_code":"5527.0",
    "gn:admin3_code":"552717.0",
    "gn:admin4_code":"55271785.0",
    "gn:asciiname":"Rangaon",
    "gn:country_code":"BD",
    "gn:dem":34,
    "gn:feature_class":"P",
    "gn:feature_code":"PPL",
    "gn:name":"Rangaon",
    "gn:population":0,
    "gn:timezone":"Asia/Dhaka",
    "iso:country":"BD",
    "name:ben_x_preferred":[
        "Rangaon"
    ],
    "wof:name":"Rangaon",
    "wof:placetype":"locality"
},
  "geometry": {"coordinates":[88.5029,25.57821],"type":"Point"}
}