{
  "type": "Feature",
  "properties": {
    "gn:admin1_code":"H",
    "gn:admin2_code":"3039",
    "gn:admin3_code":"303907.0",
    "gn:admin4_code":"30390711.0",
    "gn:asciiname":"Sarmara",
    "gn:country_code":"BD",
    "gn:dem":27,
    "gn:feature_class":"P",
    "gn:feature_code":"PPL",
    "gn:name":"Sarmara",
    "gn:population":0,
    "gn:timezone":"Asia/Dhaka",
    "iso:country":"BD",
    "name:ben_x_preferred":[
        "Sarmara"
    ],
    "wof:name":"Sarmara",
    "wof:placetype":"locality"
},
  "geometry": {"coordinates":[89.83389,25.27733],"type":"Point"}
}