{
  "type": "Feature",
  "properties": {
    "gn:admin1_code":"83",
    "gn:admin2_code":"5070",
    "gn:admin3_code":"507088.0",
    "gn:admin4_code":"50708847.0",
    "gn:asciiname":"Sikarpur",
    "gn:country_code":"BD",
    "gn:dem":28,
    "gn:feature_class":"P",
    "gn:feature_code":"PPL",
    "gn:name":"Sik\u0101rpur",
    "gn:population":0,
    "gn:timezone":"Asia/Dhaka",
    "iso:country":"BD",
    "name:ben_x_preferred":[
        "Sik\u0101rpur"
    ],
    "wof:name":"Sikarpur",
    "wof:placetype":"locality"
},
  "geometry": {"coordinates":[88.19055999999998,24.78337],"type":"Point"}
}