{
  "type": "Feature",
  "properties": {
    "gn:admin1_code":"H",
    "gn:admin2_code":"3061",
    "gn:admin3_code":"306123.0",
    "gn:admin4_code":"30612372.0",
    "gn:asciiname":"Paik Baroki",
    "gn:country_code":"BD",
    "gn:dem":15,
    "gn:feature_class":"P",
    "gn:feature_code":"PPL",
    "gn:name":"P\u0101ik B\u0101roki",
    "gn:population":0,
    "gn:timezone":"Asia/Dhaka",
    "iso:country":"BD",
    "wof:name":"Paik Baroki",
    "wof:placetype":"locality"
},
  "geometry": {"coordinates":[90.57303,24.73905],"type":"Point"}
}