{
  "type": "Feature",
  "properties": {
    "gn:admin1_code":"82",
    "gn:admin2_code":"4044.0",
    "gn:admin3_code":"404442.0",
    "gn:admin4_code":"40444240.0",
    "gn:asciiname":"Balabaria",
    "gn:country_code":"BD",
    "gn:dem":16,
    "gn:feature_class":"P",
    "gn:feature_code":"PPL",
    "gn:name":"Bal\u0101b\u0101ria",
    "gn:population":0,
    "gn:timezone":"Asia/Dhaka",
    "iso:country":"BD",
    "name:ben_x_preferred":[
        "Bal\u0101b\u0101ria"
    ],
    "wof:name":"Balabaria",
    "wof:placetype":"locality"
},
  "geometry": {"coordinates":[89.03475,23.38596],"type":"Point"}
}