{
  "type": "Feature",
  "properties": {
    "gn:admin1_code":"H",
    "gn:admin2_code":"3089",
    "gn:admin3_code":"308970.0",
    "gn:admin4_code":"30897086.0",
    "gn:asciiname":"Ratkuchi",
    "gn:country_code":"BD",
    "gn:dem":27,
    "gn:feature_class":"P",
    "gn:feature_code":"PPL",
    "gn:name":"Ratkuchi",
    "gn:population":0,
    "gn:timezone":"Asia/Dhaka",
    "iso:country":"BD",
    "name:ben_x_preferred":[
        "Ratkuchi"
    ],
    "wof:name":"Ratkuchi",
    "wof:placetype":"locality"
},
  "geometry": {"coordinates":[90.17796,25.14625],"type":"Point"}
}