{
  "type": "Feature",
  "properties": {
    "gn:admin1_code":"84",
    "gn:admin2_code":"2015.0",
    "gn:admin3_code":"201553.0",
    "gn:admin4_code":"20155371.0",
    "gn:asciiname":"Jafarabad",
    "gn:country_code":"BD",
    "gn:dem":11,
    "gn:feature_class":"P",
    "gn:feature_code":"PPL",
    "gn:name":"Jafar\u0101b\u0101d",
    "gn:population":0,
    "gn:timezone":"Asia/Dhaka",
    "iso:country":"BD",
    "name:ara_x_preferred":[
        "\u062c\u0639\u0641\u0631 \u0622\u0628\u0627\u062f"
    ],
    "name:azb_x_preferred":[
        "\u062c\u0639\u0641\u0631\u0622\u0628\u0627\u062f"
    ],
    "name:fas_x_preferred":[
        "\u062c\u0639\u0641\u0631\u0622\u0628\u0627\u062f"
    ],
    "name:mzn_x_preferred":[
        "\u062c\u0639\u0641\u0631\u0622\u0628\u0627\u062f"
    ],
    "name:pol_x_preferred":[
        "Jafarabad"
    ],
    "name:rus_x_preferred":[
        "\u0414\u0436\u0430\u0444\u0430\u0440\u0430\u0431\u0430\u0434"
    ],
    "wof:name":"Jafarabad",
    "wof:placetype":"locality"
},
  "geometry": {"coordinates":[91.53055999999999,22.74139],"type":"Point"}
}