{
  "type": "Feature",
  "properties": {
    "gn:admin1_code":"84",
    "gn:admin2_code":"2015.0",
    "gn:admin3_code":"201553.0",
    "gn:admin4_code":"20155371.0",
    "gn:asciiname":"Jafarabad",
    "gn:country_code":"BD",
    "gn:dem":11,
    "gn:feature_class":"P",
    "gn:feature_code":"PPL",
    "gn:name":"Jafar\u0101b\u0101d",
    "gn:population":0,
    "gn:timezone":"Asia/Dhaka",
    "iso:country":"BD",
    "wof:name":"Jafarabad",
    "wof:placetype":"locality"
},
  "geometry": {"coordinates":[91.53055999999999,22.74139],"type":"Point"}
}