{
  "type": "Feature",
  "properties": {
    "gn:admin1_code":"84",
    "gn:admin2_code":"2003.0",
    "gn:admin3_code":"200351.0",
    "gn:admin4_code":"20035163.0",
    "gn:asciiname":"May Aungpara",
    "gn:country_code":"BD",
    "gn:dem":181,
    "gn:feature_class":"P",
    "gn:feature_code":"PPL",
    "gn:name":"May Aungp\u0101ra",
    "gn:population":0,
    "gn:timezone":"Asia/Dhaka",
    "iso:country":"BD",
    "name:ben_x_preferred":[
        "May Aungp\u0101ra"
    ],
    "wof:name":"May Aungpara",
    "wof:placetype":"locality"
},
  "geometry": {"coordinates":[92.19217,21.74338],"type":"Point"}
}