{
  "type": "Feature",
  "properties": {
    "gn:admin1_code":"84",
    "gn:admin2_code":"2003.0",
    "gn:admin3_code":"200314.0",
    "gn:admin4_code":"20031447.0",
    "gn:asciiname":"Chaopara",
    "gn:country_code":"BD",
    "gn:dem":43,
    "gn:feature_class":"P",
    "gn:feature_code":"PPL",
    "gn:name":"Chaop\u0101ra",
    "gn:population":0,
    "gn:timezone":"Asia/Dhaka",
    "iso:country":"BD",
    "name:ben_x_preferred":[
        "Chaop\u0101ra"
    ],
    "wof:name":"Chaopara",
    "wof:placetype":"locality"
},
  "geometry": {"coordinates":[92.18147999999999,22.30461],"type":"Point"}
}