{
  "type": "Feature",
  "properties": {
    "gn:admin1_code":"H",
    "gn:admin2_code":"3039",
    "gn:admin3_code":"303907.0",
    "gn:admin4_code":"30390759.0",
    "gn:asciiname":"Madarer Char",
    "gn:country_code":"BD",
    "gn:dem":22,
    "gn:feature_class":"P",
    "gn:feature_code":"PPL",
    "gn:name":"Madarer Char",
    "gn:population":0,
    "gn:timezone":"Asia/Dhaka",
    "iso:country":"BD",
    "name:und_x_variant":[
        "M\u0101d\u0101rer Char"
    ],
    "wof:name":"Madarer Char",
    "wof:placetype":"locality"
},
  "geometry": {"coordinates":[89.79516,25.18234],"type":"Point"}
}