{
  "type": "Feature",
  "properties": {
    "gn:admin1_code":"85",
    "gn:admin2_code":"1079.0",
    "gn:admin3_code":"107958.0",
    "gn:admin4_code":"10795869.0",
    "gn:asciiname":"Bara Saula",
    "gn:country_code":"BD",
    "gn:dem":8,
    "gn:feature_class":"P",
    "gn:feature_code":"PPL",
    "gn:name":"Bara S\u0101ula",
    "gn:population":0,
    "gn:timezone":"Asia/Dhaka",
    "iso:country":"BD",
    "name:ben_x_preferred":[
        "Bara S\u0101ula"
    ],
    "wof:name":"Bara Saula",
    "wof:placetype":"locality"
},
  "geometry": {"coordinates":[90.00197,22.36381],"type":"Point"}
}