{
  "type": "Feature",
  "properties": {
    "gn:admin1_code":"82",
    "gn:admin2_code":"4018.0",
    "gn:admin3_code":"401855.0",
    "gn:admin4_code":"40185576.0",
    "gn:asciiname":"Singnagar",
    "gn:country_code":"BD",
    "gn:dem":16,
    "gn:feature_class":"P",
    "gn:feature_code":"PPL",
    "gn:name":"Singnagar",
    "gn:population":0,
    "gn:timezone":"Asia/Dhaka",
    "iso:country":"BD",
    "name:ben_x_preferred":[
        "Singnagar"
    ],
    "wof:name":"Singnagar",
    "wof:placetype":"locality"
},
  "geometry": {"coordinates":[88.80951,23.48732],"type":"Point"}
}