{
  "type": "Feature",
  "properties": {
    "gn:admin1_code":"83",
    "gn:admin2_code":"5010",
    "gn:admin3_code":"501067.0",
    "gn:admin4_code":"50106784.0",
    "gn:asciiname":"Thalta Majhgram",
    "gn:country_code":"BD",
    "gn:dem":21,
    "gn:feature_class":"P",
    "gn:feature_code":"PPL",
    "gn:name":"Th\u0101lta M\u0101jhgr\u0101m",
    "gn:population":0,
    "gn:timezone":"Asia/Dhaka",
    "iso:country":"BD",
    "wof:name":"Thalta Majhgram",
    "wof:placetype":"locality"
},
  "geometry": {"coordinates":[89.19529,24.77245],"type":"Point"}
}