{
  "type": "Feature",
  "properties": {
    "gn:admin1_code":"82",
    "gn:admin2_code":"4044.0",
    "gn:admin3_code":"404471.0",
    "gn:admin4_code":"40447100.0",
    "gn:asciiname":"Boalia",
    "gn:country_code":"BD",
    "gn:dem":16,
    "gn:feature_class":"P",
    "gn:feature_code":"PPL",
    "gn:name":"Bo\u0101lia",
    "gn:population":0,
    "gn:timezone":"Asia/Dhaka",
    "iso:country":"BD",
    "name:ben_x_preferred":[
        "Bo\u0101lia"
    ],
    "wof:name":"Boalia",
    "wof:placetype":"locality"
},
  "geometry": {"coordinates":[88.88961,23.34748],"type":"Point"}
}