{
  "type": "Feature",
  "properties": {
    "gn:admin1_code":"82",
    "gn:admin2_code":"4041.0",
    "gn:admin3_code":"404111.0",
    "gn:admin4_code":"40411143.0",
    "gn:asciiname":"Digri",
    "gn:country_code":"BD",
    "gn:dem":15,
    "gn:feature_class":"P",
    "gn:feature_code":"PPL",
    "gn:name":"Digri",
    "gn:population":0,
    "gn:timezone":"Asia/Dhaka",
    "iso:country":"BD",
    "name:ben_x_preferred":[
        "Digri"
    ],
    "name:ceb_x_preferred":[
        "Digri"
    ],
    "name:fas_x_preferred":[
        "\u062f\u0647\u06af\u0631\u06cc"
    ],
    "name:pnb_x_preferred":[
        "\u0688\u06af\u0631\u06cc"
    ],
    "name:snd_x_preferred":[
        "\u068a\u06af\u06be\u0699\u064a"
    ],
    "name:urd_x_preferred":[
        "\u0688\u06be\u06af\u0691\u06cc"
    ],
    "wof:name":"Digri",
    "wof:placetype":"locality"
},
  "geometry": {"coordinates":[88.9726,23.24671],"type":"Point"}
}