{
  "type": "Feature",
  "properties": {
    "gn:admin1_code":"83",
    "gn:admin2_code":"5081",
    "gn:admin3_code":"508134.0",
    "gn:admin4_code":"50813457.0",
    "gn:asciiname":"Ujanpara",
    "gn:country_code":"BD",
    "gn:dem":25,
    "gn:feature_class":"P",
    "gn:feature_code":"PPL",
    "gn:name":"Uj\u0101np\u0101ra",
    "gn:population":0,
    "gn:timezone":"Asia/Dhaka",
    "iso:country":"BD",
    "name:ben_x_preferred":[
        "Uj\u0101np\u0101ra"
    ],
    "wof:name":"Ujanpara",
    "wof:placetype":"locality"
},
  "geometry": {"coordinates":[88.34782,24.44759],"type":"Point"}
}