{
  "type": "Feature",
  "properties": {
    "gn:admin1_code":"81",
    "gn:admin2_code":"3056.0",
    "gn:admin3_code":"305678.0",
    "gn:admin4_code":"30567823.0",
    "gn:asciiname":"Dakshin Banagram",
    "gn:country_code":"BD",
    "gn:dem":16,
    "gn:feature_class":"P",
    "gn:feature_code":"PPL",
    "gn:name":"Dakshin Banagr\u0101m",
    "gn:population":0,
    "gn:timezone":"Asia/Dhaka",
    "iso:country":"BD",
    "wof:name":"Dakshin Banagram",
    "wof:placetype":"locality"
},
  "geometry": {"coordinates":[89.87824000000001,23.83236],"type":"Point"}
}