{
  "type": "Feature",
  "properties": {
    "gn:admin1_code":"87",
    "gn:admin2_code":"5585",
    "gn:admin3_code":"558592.0",
    "gn:admin4_code":"55859271.0",
    "gn:asciiname":"Taraganj Hat",
    "gn:country_code":"BD",
    "gn:dem":44,
    "gn:feature_class":"P",
    "gn:feature_code":"PPL",
    "gn:name":"T\u0101raganj H\u0101t",
    "gn:population":0,
    "gn:timezone":"Asia/Dhaka",
    "iso:country":"BD",
    "name:ben_x_preferred":[
        "T\u0101raganj H\u0101t"
    ],
    "wof:name":"Taraganj Hat",
    "wof:placetype":"locality"
},
  "geometry": {"coordinates":[89.00917,25.81493],"type":"Point"}
}