{
  "type": "Feature",
  "properties": {
    "gn:admin1_code":"87",
    "gn:admin2_code":"5573",
    "gn:admin3_code":"557312.0",
    "gn:admin4_code":"55731238.0",
    "gn:asciiname":"Dakhin Sonakhali",
    "gn:country_code":"BD",
    "gn:dem":50,
    "gn:feature_class":"P",
    "gn:feature_code":"PPL",
    "gn:name":"Dakhin Son\u0101kh\u0101li",
    "gn:population":0,
    "gn:timezone":"Asia/Dhaka",
    "iso:country":"BD",
    "name:ben_x_preferred":[
        "Dakhin Son\u0101kh\u0101li"
    ],
    "wof:name":"Dakhin Sonakhali",
    "wof:placetype":"locality"
},
  "geometry": {"coordinates":[89.0594,26.10085],"type":"Point"}
}