{
  "type": "Feature",
  "properties": {
    "gn:admin1_code":"81",
    "gn:admin2_code":"3054.0",
    "gn:admin3_code":"305480.0",
    "gn:admin4_code":"30548066.0",
    "gn:asciiname":"Chamta",
    "gn:country_code":"BD",
    "gn:dem":10,
    "gn:feature_class":"P",
    "gn:feature_code":"PPL",
    "gn:name":"Chamta",
    "gn:population":0,
    "gn:timezone":"Asia/Dhaka",
    "iso:country":"BD",
    "name:ben_x_preferred":[
        "Chamta"
    ],
    "wof:name":"Chamta",
    "wof:placetype":"locality"
},
  "geometry": {"coordinates":[89.94698000000002,23.17116],"type":"Point"}
}