{
  "type": "Feature",
  "properties": {
    "gn:admin1_code":"81",
    "gn:admin2_code":"3029",
    "gn:admin3_code":"302903.0",
    "gn:admin4_code":"30290321.0",
    "gn:asciiname":"North Sirgram",
    "gn:cc2":"BD",
    "gn:country_code":"BD",
    "gn:dem":9,
    "gn:feature_class":"P",
    "gn:feature_code":"PPL",
    "gn:name":"North Sirgr\u0101m",
    "gn:population":0,
    "gn:timezone":"Asia/Dhaka",
    "iso:country":"BD",
    "name:und_x_variant":[
        "Uttarsirgram",
        "North Sirgr\u0101m"
    ],
    "wof:name":"North Sirgram",
    "wof:placetype":"locality"
},
  "geometry": {"coordinates":[89.66667,23.35],"type":"Point"}
}