{
  "type": "Feature",
  "properties": {
    "gn:admin1_code":"83",
    "gn:admin2_code":"5081.0",
    "gn:admin3_code":"508172.0",
    "gn:admin4_code":"50817231.0",
    "gn:asciiname":"Thakurmara",
    "gn:country_code":"BD",
    "gn:dem":18,
    "gn:feature_class":"P",
    "gn:feature_code":"PPL",
    "gn:name":"Th\u0101kurm\u0101ra",
    "gn:population":0,
    "gn:timezone":"Asia/Dhaka",
    "iso:country":"BD",
    "name:ben_x_preferred":[
        "Th\u0101kurm\u0101ra"
    ],
    "wof:name":"Thakurmara",
    "wof:placetype":"locality"
},
  "geometry": {"coordinates":[88.57391,24.39124],"type":"Point"}
}