{
  "type": "Feature",
  "properties": {
    "gn:admin1_code":"84",
    "gn:admin2_code":"2015.0",
    "gn:admin3_code":"201541.0",
    "gn:admin4_code":"20154104.0",
    "gn:asciiname":"Chandgaon",
    "gn:country_code":"BD",
    "gn:dem":6,
    "gn:feature_class":"P",
    "gn:feature_code":"PPL",
    "gn:name":"Ch\u0101ndgaon",
    "gn:population":0,
    "gn:timezone":"Asia/Dhaka",
    "iso:country":"BD",
    "name:ben_x_preferred":[
        "Ch\u0101ndgaon"
    ],
    "wof:name":"Chandgaon",
    "wof:placetype":"locality"
},
  "geometry": {"coordinates":[91.86042999999999,22.39914],"type":"Point"}
}