{
  "type": "Feature",
  "properties": {
    "gn:admin1_code":"83",
    "gn:admin2_code":"5064",
    "gn:admin3_code":"506406.0",
    "gn:admin4_code":"50640621.0",
    "gn:asciiname":"Kalna",
    "gn:country_code":"BD",
    "gn:dem":22,
    "gn:feature_class":"P",
    "gn:feature_code":"PPL",
    "gn:name":"K\u0101lna",
    "gn:population":0,
    "gn:timezone":"Asia/Dhaka",
    "iso:country":"BD",
    "name:ben_x_preferred":[
        "K\u0101lna"
    ],
    "wof:name":"Kalna",
    "wof:placetype":"locality"
},
  "geometry": {"coordinates":[88.86757,24.9905],"type":"Point"}
}