{
  "type": "Feature",
  "properties": {
    "gn:admin1_code":"86",
    "gn:admin2_code":"6091.0",
    "gn:admin3_code":"609117.0",
    "gn:admin4_code":"60911786.0",
    "gn:asciiname":"Balinga",
    "gn:country_code":"BD",
    "gn:dem":19,
    "gn:feature_class":"P",
    "gn:feature_code":"PPL",
    "gn:name":"B\u0101linga",
    "gn:population":0,
    "gn:timezone":"Asia/Dhaka",
    "iso:country":"BD",
    "wof:name":"Balinga",
    "wof:placetype":"locality"
},
  "geometry": {"coordinates":[92.16667,24.86667000000001],"type":"Point"}
}