{
  "type": "Feature",
  "properties": {
    "gn:admin1_code":"87",
    "gn:admin2_code":"5594.0",
    "gn:admin3_code":"559451.0",
    "gn:admin4_code":"55945140.0",
    "gn:asciiname":"Tehgaria",
    "gn:country_code":"BD",
    "gn:dem":40,
    "gn:feature_class":"P",
    "gn:feature_code":"PPL",
    "gn:name":"Tehgaria",
    "gn:population":0,
    "gn:timezone":"Asia/Dhaka",
    "iso:country":"BD",
    "name:ben_x_preferred":[
        "Tehgaria"
    ],
    "wof:name":"Tehgaria",
    "wof:placetype":"locality"
},
  "geometry": {"coordinates":[88.22062,25.81233],"type":"Point"}
}