{
  "type": "Feature",
  "properties": {
    "gn:admin1_code":"83",
    "gn:admin2_code":"5064",
    "gn:admin3_code":"506447.0",
    "gn:admin4_code":"50644767.0",
    "gn:asciiname":"Nalghair",
    "gn:country_code":"BD",
    "gn:dem":22,
    "gn:feature_class":"P",
    "gn:feature_code":"PPL",
    "gn:name":"Nalghair",
    "gn:population":0,
    "gn:timezone":"Asia/Dhaka",
    "iso:country":"BD",
    "name:ben_x_preferred":[
        "Nalghair"
    ],
    "wof:name":"Nalghair",
    "wof:placetype":"locality"
},
  "geometry": {"coordinates":[88.67685,24.7809],"type":"Point"}
}