{
  "type": "Feature",
  "properties": {
    "gn:admin1_code":"82",
    "gn:admin2_code":"4044",
    "gn:admin3_code":"404480.0",
    "gn:admin4_code":"40448075.0",
    "gn:asciiname":"North Krishnanagar",
    "gn:country_code":"BD",
    "gn:dem":14,
    "gn:feature_class":"P",
    "gn:feature_code":"PPL",
    "gn:name":"North Krishnanagar",
    "gn:population":0,
    "gn:timezone":"Asia/Dhaka",
    "iso:country":"BD",
    "name:und_x_variant":[
        "Uttar Krishnanagar",
        "North Krishnanagar"
    ],
    "wof:name":"North Krishnanagar",
    "wof:placetype":"locality"
},
  "geometry": {"coordinates":[89.25528,23.75272],"type":"Point"}
}