{
  "type": "Feature",
  "properties": {
    "gn:admin1_code":"84",
    "gn:admin2_code":"2019.0",
    "gn:admin3_code":"201937.0",
    "gn:admin4_code":"20193704.0",
    "gn:asciiname":"Aichar Char",
    "gn:country_code":"BD",
    "gn:dem":10,
    "gn:feature_class":"P",
    "gn:feature_code":"PPL",
    "gn:name":"\u0100ich\u0101r Char",
    "gn:population":0,
    "gn:timezone":"Asia/Dhaka",
    "iso:country":"BD",
    "wof:name":"Aichar Char",
    "wof:placetype":"locality"
},
  "geometry": {"coordinates":[90.81050999999999,23.62457],"type":"Point"}
}