{
  "type": "Feature",
  "properties": {
    "gn:admin1_code":"81",
    "gn:admin2_code":"3048",
    "gn:admin3_code":"304827.0",
    "gn:admin4_code":"30482767.0",
    "gn:asciiname":"Rahimpur",
    "gn:country_code":"BD",
    "gn:dem":16,
    "gn:feature_class":"P",
    "gn:feature_code":"PPL",
    "gn:name":"Rahimpur",
    "gn:population":0,
    "gn:timezone":"Asia/Dhaka",
    "iso:country":"BD",
    "wof:name":"Rahimpur",
    "wof:placetype":"locality"
},
  "geometry": {"coordinates":[90.71823000000001,24.399],"type":"Point"}
}