{
  "type": "Feature",
  "properties": {
    "gn:admin1_code":"83",
    "gn:admin2_code":"5070.0",
    "gn:admin3_code":"507066.0",
    "gn:admin4_code":"50706600.0",
    "gn:asciiname":"Kaligaoi",
    "gn:country_code":"BD",
    "gn:dem":26,
    "gn:feature_class":"P",
    "gn:feature_code":"PPL",
    "gn:name":"K\u0101ligaoi",
    "gn:population":0,
    "gn:timezone":"Asia/Dhaka",
    "iso:country":"BD",
    "name:ben_x_preferred":[
        "K\u0101ligaoi"
    ],
    "wof:name":"Kaligaoi",
    "wof:placetype":"locality"
},
  "geometry": {"coordinates":[88.27079000000001,24.58242000000001],"type":"Point"}
}