{
  "type": "Feature",
  "properties": {
    "gn:admin1_code":"81",
    "gn:admin2_code":"3033",
    "gn:admin3_code":"303336.0",
    "gn:admin4_code":"30333608.0",
    "gn:asciiname":"Narottampur",
    "gn:country_code":"BD",
    "gn:dem":18,
    "gn:feature_class":"P",
    "gn:feature_code":"PPL",
    "gn:name":"Narottampur",
    "gn:population":0,
    "gn:timezone":"Asia/Dhaka",
    "iso:country":"BD",
    "wof:name":"Narottampur",
    "wof:placetype":"locality"
},
  "geometry": {"coordinates":[90.66081,24.17122],"type":"Point"}
}