{
  "type": "Feature",
  "properties": {
    "gn:admin1_code":"83",
    "gn:admin2_code":"5038.0",
    "gn:admin3_code":"503861.0",
    "gn:admin4_code":"50386147.0",
    "gn:asciiname":"Kazipur",
    "gn:country_code":"BD",
    "gn:dem":23,
    "gn:feature_class":"P",
    "gn:feature_code":"PPL",
    "gn:name":"K\u0101zipur",
    "gn:population":0,
    "gn:timezone":"Asia/Dhaka",
    "iso:country":"BD",
    "name:ben_x_preferred":[
        "K\u0101zipur"
    ],
    "wof:name":"Kazipur",
    "wof:placetype":"locality"
},
  "geometry": {"coordinates":[89.13639000000001,25.02768],"type":"Point"}
}