{
  "type": "Feature",
  "properties": {
    "gn:admin1_code":"85",
    "gn:admin2_code":"1009.0",
    "gn:admin3_code":"100991.0",
    "gn:admin4_code":"10099157.0",
    "gn:asciiname":"Baliakandi",
    "gn:country_code":"BD",
    "gn:dem":9,
    "gn:feature_class":"P",
    "gn:feature_code":"PPL",
    "gn:name":"B\u0101liakandi",
    "gn:population":0,
    "gn:timezone":"Asia/Dhaka",
    "iso:country":"BD",
    "name:ben_x_preferred":[
        "B\u0101liakandi"
    ],
    "wof:name":"Baliakandi",
    "wof:placetype":"locality"
},
  "geometry": {"coordinates":[90.83573,22.44139],"type":"Point"}
}