{
  "type": "Feature",
  "properties": {
    "gn:admin1_code":"83",
    "gn:admin2_code":"5038.0",
    "gn:admin3_code":"503847.0",
    "gn:admin4_code":"50384728.0",
    "gn:asciiname":"Maloypur",
    "gn:country_code":"BD",
    "gn:dem":25,
    "gn:feature_class":"P",
    "gn:feature_code":"PPL",
    "gn:name":"M\u0101loypur",
    "gn:population":0,
    "gn:timezone":"Asia/Dhaka",
    "iso:country":"BD",
    "name:ben_x_preferred":[
        "M\u0101loypur"
    ],
    "wof:name":"Maloypur",
    "wof:placetype":"locality"
},
  "geometry": {"coordinates":[88.94256,25.06791],"type":"Point"}
}