{
  "type": "Feature",
  "properties": {
    "gn:admin1_code":"87",
    "gn:admin2_code":"5552",
    "gn:admin3_code":"555255.0",
    "gn:admin4_code":"55525536.0",
    "gn:asciiname":"Auditmari",
    "gn:country_code":"BD",
    "gn:dem":36,
    "gn:feature_class":"P",
    "gn:feature_code":"PPL",
    "gn:name":"Auditmari",
    "gn:population":0,
    "gn:timezone":"Asia/Dhaka",
    "iso:country":"BD",
    "name:ben_x_preferred":[
        "Auditmari"
    ],
    "wof:name":"Auditmari",
    "wof:placetype":"locality"
},
  "geometry": {"coordinates":[89.40000999999999,25.88221],"type":"Point"}
}