{
  "type": "Feature",
  "properties": {
    "gn:admin1_code":"87",
    "gn:admin2_code":"5594.0",
    "gn:admin3_code":"559408.0",
    "gn:admin4_code":"55940831.0",
    "gn:asciiname":"Kismat Palashbari",
    "gn:country_code":"BD",
    "gn:dem":55,
    "gn:feature_class":"P",
    "gn:feature_code":"PPL",
    "gn:name":"Kismat Pal\u0101shb\u0101ri",
    "gn:population":0,
    "gn:timezone":"Asia/Dhaka",
    "iso:country":"BD",
    "name:ben_x_preferred":[
        "Kismat Pal\u0101shb\u0101ri"
    ],
    "wof:name":"Kismat Palashbari",
    "wof:placetype":"locality"
},
  "geometry": {"coordinates":[88.24049000000002,26.07546],"type":"Point"}
}