{
  "type": "Feature",
  "properties": {
    "gn:admin1_code":"82",
    "gn:admin2_code":"4044",
    "gn:admin3_code":"404480.0",
    "gn:admin4_code":"40448012.0",
    "gn:asciiname":"Tentulia",
    "gn:country_code":"BD",
    "gn:dem":14,
    "gn:feature_class":"P",
    "gn:feature_code":"PPL",
    "gn:name":"Tentulia",
    "gn:population":0,
    "gn:timezone":"Asia/Dhaka",
    "iso:country":"BD",
    "wof:name":"Tentulia",
    "wof:placetype":"locality"
},
  "geometry": {"coordinates":[89.31215,23.6389],"type":"Point"}
}