{
  "type": "Feature",
  "properties": {
    "gn:admin1_code":"84",
    "gn:admin2_code":"2084",
    "gn:admin3_code":"208475.0",
    "gn:admin4_code":"20847557.0",
    "gn:asciiname":"Nanyarchar",
    "gn:country_code":"BD",
    "gn:dem":37,
    "gn:feature_class":"P",
    "gn:feature_code":"PPL",
    "gn:name":"N\u0101ny\u0101rchar",
    "gn:population":0,
    "gn:timezone":"Asia/Dhaka",
    "iso:country":"BD",
    "name:ben_x_preferred":[
        "N\u0101ny\u0101rchar"
    ],
    "name:und_x_variant":[
        "N\u0101ny\u0101rchar",
        "N\u0101ny\u0101rchar B\u0101z\u0101r"
    ],
    "wof:name":"Nanyarchar",
    "wof:placetype":"locality"
},
  "geometry": {"coordinates":[92.09596999999999,22.84073],"type":"Point"}
}