{
  "type": "Feature",
  "properties": {
    "gn:admin1_code":"86",
    "gn:admin2_code":"6036",
    "gn:admin3_code":"603677.0",
    "gn:admin4_code":"60367758.0",
    "gn:asciiname":"Kaliarbhanga",
    "gn:country_code":"BD",
    "gn:dem":9,
    "gn:feature_class":"P",
    "gn:feature_code":"PPL",
    "gn:name":"Kali\u0101rbh\u0101nga",
    "gn:population":0,
    "gn:timezone":"Asia/Dhaka",
    "iso:country":"BD",
    "wof:name":"Kaliarbhanga",
    "wof:placetype":"locality"
},
  "geometry": {"coordinates":[91.48333,24.48333],"type":"Point"}
}