{
  "type": "Feature",
  "properties": {
    "gn:admin1_code":"82",
    "gn:admin2_code":"4018.0",
    "gn:admin3_code":"401807.0",
    "gn:admin4_code":"40180763.0",
    "gn:asciiname":"Sirajkandi",
    "gn:country_code":"BD",
    "gn:dem":22,
    "gn:feature_class":"P",
    "gn:feature_code":"PPL",
    "gn:name":"Sir\u0101jk\u0101ndi",
    "gn:population":0,
    "gn:timezone":"Asia/Dhaka",
    "iso:country":"BD",
    "name:ben_x_preferred":[
        "Sir\u0101jk\u0101ndi"
    ],
    "wof:name":"Sirajkandi",
    "wof:placetype":"locality"
},
  "geometry": {"coordinates":[88.87294,23.68722],"type":"Point"}
}