{
  "type": "Feature",
  "properties": {
    "gn:admin1_code":"84",
    "gn:admin2_code":"2030",
    "gn:admin3_code":"203029.0",
    "gn:admin4_code":"20302947.0",
    "gn:asciiname":"Ruhitia",
    "gn:country_code":"BD",
    "gn:dem":10,
    "gn:feature_class":"P",
    "gn:feature_code":"PPL",
    "gn:name":"Ruhitia",
    "gn:population":0,
    "gn:timezone":"Asia/Dhaka",
    "iso:country":"BD",
    "wof:name":"Ruhitia",
    "wof:placetype":"locality"
},
  "geometry": {"coordinates":[91.42082000000001,23.0213],"type":"Point"}
}