{
  "type": "Feature",
  "properties": {
    "gn:admin1_code":"83",
    "gn:admin2_code":"5081",
    "gn:admin3_code":"508134.0",
    "gn:admin4_code":"50813466.0",
    "gn:asciiname":"Sidhna",
    "gn:country_code":"BD",
    "gn:dem":33,
    "gn:feature_class":"P",
    "gn:feature_code":"PPL",
    "gn:name":"Sidhna",
    "gn:population":0,
    "gn:timezone":"Asia/Dhaka",
    "iso:country":"BD",
    "name:ben_x_preferred":[
        "Sidhna"
    ],
    "name:ben_x_variant":[
        "Sidna"
    ],
    "wof:name":"Sidhna",
    "wof:placetype":"locality"
},
  "geometry": {"coordinates":[88.33424000000002,24.55501],"type":"Point"}
}