{
  "type": "Feature",
  "properties": {
    "gn:admin1_code":"81",
    "gn:admin2_code":"3093.0",
    "gn:admin3_code":"309357.0",
    "gn:admin4_code":"30935709.0",
    "gn:asciiname":"Habibpur",
    "gn:country_code":"BD",
    "gn:dem":20,
    "gn:feature_class":"P",
    "gn:feature_code":"PPL",
    "gn:name":"Habibpur",
    "gn:population":0,
    "gn:timezone":"Asia/Dhaka",
    "iso:country":"BD",
    "wof:name":"Habibpur",
    "wof:placetype":"locality"
},
  "geometry": {"coordinates":[90.01605000000001,24.58953],"type":"Point"}
}