{
  "type": "Feature",
  "properties": {
    "gn:admin1_code":"87",
    "gn:admin2_code":"5573.0",
    "gn:admin3_code":"557315.0",
    "gn:admin4_code":"55731595.0",
    "gn:asciiname":"Jamirbari",
    "gn:country_code":"BD",
    "gn:dem":59,
    "gn:feature_class":"P",
    "gn:feature_code":"PPL",
    "gn:name":"J\u0101mirb\u0101ri",
    "gn:population":0,
    "gn:timezone":"Asia/Dhaka",
    "iso:country":"BD",
    "name:ben_x_preferred":[
        "J\u0101mirb\u0101ri"
    ],
    "wof:name":"Jamirbari",
    "wof:placetype":"locality"
},
  "geometry": {"coordinates":[88.79335999999998,26.05883],"type":"Point"}
}