{
  "type": "Feature",
  "properties": {
    "gn:admin1_code":"83",
    "gn:admin2_code":"5010.0",
    "gn:admin3_code":"501033.0",
    "gn:admin4_code":"50103354.0",
    "gn:asciiname":"Chhota Beragaon",
    "gn:country_code":"BD",
    "gn:dem":20,
    "gn:feature_class":"P",
    "gn:feature_code":"PPL",
    "gn:name":"Chhota Ber\u0101gaon",
    "gn:population":0,
    "gn:timezone":"Asia/Dhaka",
    "iso:country":"BD",
    "wof:name":"Chhota Beragaon",
    "wof:placetype":"locality"
},
  "geometry": {"coordinates":[89.08333,24.88333],"type":"Point"}
}