{
  "type": "Feature",
  "properties": {
    "gn:admin1_code":"82",
    "gn:admin2_code":"4001",
    "gn:admin3_code":"400138.0",
    "gn:admin4_code":"40013847.0",
    "gn:asciiname":"Phultala",
    "gn:country_code":"BD",
    "gn:dem":11,
    "gn:feature_class":"P",
    "gn:feature_code":"PPL",
    "gn:name":"Phultala",
    "gn:population":0,
    "gn:timezone":"Asia/Dhaka",
    "iso:country":"BD",
    "wof:name":"Phultala",
    "wof:placetype":"locality"
},
  "geometry": {"coordinates":[89.90564999999999,22.63041],"type":"Point"}
}