{
  "type": "Feature",
  "properties": {
    "gn:admin1_code":"84",
    "gn:admin2_code":"2015",
    "gn:admin3_code":"201582.0",
    "gn:admin4_code":"20158294.0",
    "gn:asciiname":"Ichamati",
    "gn:country_code":"BD",
    "gn:dem":10,
    "gn:feature_class":"P",
    "gn:feature_code":"PPL",
    "gn:name":"Ich\u0101mati",
    "gn:population":0,
    "gn:timezone":"Asia/Dhaka",
    "iso:country":"BD",
    "name:ben_x_preferred":[
        "Ich\u0101mati"
    ],
    "name:und_x_variant":[
        "Ichhamati"
    ],
    "wof:name":"Ichamati",
    "wof:placetype":"locality"
},
  "geometry": {"coordinates":[92.04722,22.09262],"type":"Point"}
}