{
  "type": "Feature",
  "properties": {
    "gn:admin1_code":"82",
    "gn:asciiname":"Jatabunia",
    "gn:country_code":"BD",
    "gn:dem":11,
    "gn:feature_class":"P",
    "gn:feature_code":"PPL",
    "gn:name":"Jatabunia",
    "gn:population":0,
    "gn:timezone":"Asia/Dhaka",
    "iso:country":"BD",
    "name:ben_x_preferred":[
        "Jatabunia"
    ],
    "wof:name":"Jatabunia",
    "wof:placetype":"locality"
},
  "geometry": {"coordinates":[89.93575,22.20408],"type":"Point"}
}