{
  "type": "Feature",
  "properties": {
    "gn:admin1_code":"82",
    "gn:admin2_code":"4087",
    "gn:admin3_code":"408790.0",
    "gn:admin4_code":"40879063.0",
    "gn:asciiname":"Mandra",
    "gn:country_code":"BD",
    "gn:dem":6,
    "gn:feature_class":"P",
    "gn:feature_code":"PPL",
    "gn:name":"M\u0101ndra",
    "gn:population":0,
    "gn:timezone":"Asia/Dhaka",
    "iso:country":"BD",
    "wof:name":"Mandra",
    "wof:placetype":"locality"
},
  "geometry": {"coordinates":[89.21403000000002,22.69478],"type":"Point"}
}