{
  "type": "Feature",
  "properties": {
    "gn:admin1_code":"83",
    "gn:admin2_code":"5064.0",
    "gn:admin3_code":"506460.0",
    "gn:admin4_code":"50646000.0",
    "gn:asciiname":"Chak Bara",
    "gn:country_code":"BD",
    "gn:dem":19,
    "gn:feature_class":"P",
    "gn:feature_code":"PPL",
    "gn:name":"Chak Bara",
    "gn:population":0,
    "gn:timezone":"Asia/Dhaka",
    "iso:country":"BD",
    "name:ben_x_preferred":[
        "Chak Bara"
    ],
    "wof:name":"Chak Bara",
    "wof:placetype":"locality"
},
  "geometry": {"coordinates":[88.92625,24.82794],"type":"Point"}
}