{
  "type": "Feature",
  "properties": {
    "gn:admin1_code":"85",
    "gn:admin2_code":"1042.0",
    "gn:admin3_code":"104240.0",
    "gn:admin4_code":"10424066.0",
    "gn:asciiname":"Gobindadhabal",
    "gn:country_code":"BD",
    "gn:dem":8,
    "gn:feature_class":"P",
    "gn:feature_code":"PPL",
    "gn:name":"Gobindadhabal",
    "gn:population":0,
    "gn:timezone":"Asia/Dhaka",
    "iso:country":"BD",
    "wof:name":"Gobindadhabal",
    "wof:placetype":"locality"
},
  "geometry": {"coordinates":[90.17943,22.6773],"type":"Point"}
}