{
  "type": "Feature",
  "properties": {
    "gn:admin1_code":"81",
    "gn:admin2_code":"3093",
    "gn:admin3_code":"309385.0",
    "gn:admin4_code":"30938554.0",
    "gn:asciiname":"Sola Pratinia",
    "gn:country_code":"BD",
    "gn:dem":24,
    "gn:feature_class":"P",
    "gn:feature_code":"PPL",
    "gn:name":"Sola Pratinia",
    "gn:population":0,
    "gn:timezone":"Asia/Dhaka",
    "iso:country":"BD",
    "name:und_x_variant":[
        "Sola Pratima"
    ],
    "wof:name":"Sola Pratinia",
    "wof:placetype":"locality"
},
  "geometry": {"coordinates":[90.17551,24.28319],"type":"Point"}
}