{
  "type": "Feature",
  "properties": {
    "gn:admin1_code":"87",
    "gn:admin2_code":"5594.0",
    "gn:admin3_code":"559482.0",
    "gn:admin4_code":"55948208.0",
    "gn:asciiname":"Gilabari",
    "gn:country_code":"BD",
    "gn:dem":45,
    "gn:feature_class":"P",
    "gn:feature_code":"PPL",
    "gn:name":"Gil\u0101b\u0101ri",
    "gn:population":0,
    "gn:timezone":"Asia/Dhaka",
    "iso:country":"BD",
    "name:ben_x_preferred":[
        "Gil\u0101b\u0101ri"
    ],
    "wof:name":"Gilabari",
    "wof:placetype":"locality"
},
  "geometry": {"coordinates":[88.36998,25.73912],"type":"Point"}
}