{
  "type": "Feature",
  "properties": {
    "gn:admin1_code":"84",
    "gn:admin2_code":"2003.0",
    "gn:admin3_code":"200314.0",
    "gn:admin4_code":"20031431.0",
    "gn:asciiname":"Baripara",
    "gn:country_code":"BD",
    "gn:dem":121,
    "gn:feature_class":"P",
    "gn:feature_code":"PPL",
    "gn:name":"Barip\u0101ra",
    "gn:population":0,
    "gn:timezone":"Asia/Dhaka",
    "iso:country":"BD",
    "name:ben_x_preferred":[
        "Barip\u0101ra"
    ],
    "wof:name":"Baripara",
    "wof:placetype":"locality"
},
  "geometry": {"coordinates":[92.22309,22.26568],"type":"Point"}
}