{
  "type": "Feature",
  "properties": {
    "gn:admin1_code":"84",
    "gn:admin2_code":"2015.0",
    "gn:admin3_code":"201570.0",
    "gn:admin4_code":"20157043.0",
    "gn:asciiname":"Falaharia",
    "gn:country_code":"BD",
    "gn:dem":24,
    "gn:feature_class":"P",
    "gn:feature_code":"PPL",
    "gn:name":"Falaharia",
    "gn:population":0,
    "gn:timezone":"Asia/Dhaka",
    "iso:country":"BD",
    "name:ben_x_preferred":[
        "Falaharia"
    ],
    "wof:name":"Falaharia",
    "wof:placetype":"locality"
},
  "geometry": {"coordinates":[92.12578999999999,22.35141],"type":"Point"}
}