{
  "type": "Feature",
  "properties": {
    "gn:admin1_code":"83",
    "gn:admin2_code":"5081.0",
    "gn:admin3_code":"508134.0",
    "gn:admin4_code":"50813476.0",
    "gn:asciiname":"Boshna",
    "gn:country_code":"BD",
    "gn:dem":40,
    "gn:feature_class":"P",
    "gn:feature_code":"PPL",
    "gn:name":"Boshna",
    "gn:population":0,
    "gn:timezone":"Asia/Dhaka",
    "iso:country":"BD",
    "name:ben_x_preferred":[
        "Boshna"
    ],
    "wof:name":"Boshna",
    "wof:placetype":"locality"
},
  "geometry": {"coordinates":[88.44394,24.5403],"type":"Point"}
}