{
  "type": "Feature",
  "properties": {
    "gn:admin1_code":"81",
    "gn:admin2_code":"3029",
    "gn:admin3_code":"302956.0",
    "gn:admin4_code":"30295684.0",
    "gn:asciiname":"Sabek Ramdia",
    "gn:country_code":"BD",
    "gn:dem":13,
    "gn:feature_class":"P",
    "gn:feature_code":"PPL",
    "gn:name":"S\u0101bek R\u0101mdia",
    "gn:population":0,
    "gn:timezone":"Asia/Dhaka",
    "iso:country":"BD",
    "wof:name":"Sabek Ramdia",
    "wof:placetype":"locality"
},
  "geometry": {"coordinates":[89.68745,23.53405],"type":"Point"}
}