{
  "type": "Feature",
  "properties": {
    "gn:admin1_code":"84",
    "gn:admin2_code":"2012.0",
    "gn:admin3_code":"201202.0",
    "gn:admin4_code":"20120257.0",
    "gn:asciiname":"Mulagram",
    "gn:country_code":"BD",
    "gn:dem":8,
    "gn:feature_class":"P",
    "gn:feature_code":"PPL",
    "gn:name":"Mulagram",
    "gn:population":0,
    "gn:timezone":"Asia/Dhaka",
    "iso:country":"BD",
    "wof:name":"Mulagram",
    "wof:placetype":"locality"
},
  "geometry": {"coordinates":[91.13916999999999,23.84833],"type":"Point"}
}