{
  "type": "Feature",
  "properties": {
    "gn:admin1_code":"81",
    "gn:admin2_code":"3067",
    "gn:admin3_code":"306704.0",
    "gn:admin4_code":"30670417.0",
    "gn:asciiname":"Nakati Bhanga",
    "gn:country_code":"BD",
    "gn:dem":7,
    "gn:feature_class":"P",
    "gn:feature_code":"PPL",
    "gn:name":"N\u0101k\u0101ti Bh\u0101nga",
    "gn:population":0,
    "gn:timezone":"Asia/Dhaka",
    "iso:country":"BD",
    "wof:name":"Nakati Bhanga",
    "wof:placetype":"locality"
},
  "geometry": {"coordinates":[90.61667,23.66667],"type":"Point"}
}