{
  "type": "Feature",
  "properties": {
    "gn:admin1_code":"85",
    "gn:admin2_code":"1042",
    "gn:admin3_code":"104273.0",
    "gn:admin4_code":"10427352.0",
    "gn:asciiname":"Nachanmahal",
    "gn:country_code":"BD",
    "gn:dem":7,
    "gn:feature_class":"P",
    "gn:feature_code":"PPL",
    "gn:name":"N\u0101chanmahal",
    "gn:population":0,
    "gn:timezone":"Asia/Dhaka",
    "iso:country":"BD",
    "wof:name":"Nachanmahal",
    "wof:placetype":"locality"
},
  "geometry": {"coordinates":[90.22821,22.57041],"type":"Point"}
}