{
  "type": "Feature",
  "properties": {
    "gn:admin1_code":"82",
    "gn:admin2_code":"4041.0",
    "gn:admin3_code":"404109.0",
    "gn:admin4_code":"40410966.0",
    "gn:asciiname":"Bagharpara",
    "gn:country_code":"BD",
    "gn:dem":13,
    "gn:feature_class":"P",
    "gn:feature_code":"PPL",
    "gn:name":"Bagharpara",
    "gn:population":0,
    "gn:timezone":"Asia/Dhaka",
    "iso:country":"BD",
    "name:ben_x_preferred":[
        "Bagharpara"
    ],
    "wof:name":"Bagharpara",
    "wof:placetype":"locality"
},
  "geometry": {"coordinates":[89.23888000000002,23.32069],"type":"Point"}
}