{
  "type": "Feature",
  "properties": {
    "gn:admin1_code":"81",
    "gn:admin2_code":"3056",
    "gn:admin3_code":"305622.0",
    "gn:admin4_code":"30562223.0",
    "gn:asciiname":"Kundurabari",
    "gn:country_code":"BD",
    "gn:dem":15,
    "gn:feature_class":"P",
    "gn:feature_code":"PPL",
    "gn:name":"Kundurabari",
    "gn:population":0,
    "gn:timezone":"Asia/Dhaka",
    "iso:country":"BD",
    "wof:name":"Kundurabari",
    "wof:placetype":"locality"
},
  "geometry": {"coordinates":[89.94041999999997,23.84877],"type":"Point"}
}