{
  "type": "Feature",
  "properties": {
    "gn:admin1_code":"83",
    "gn:admin2_code":"5010.0",
    "gn:admin3_code":"501054.0",
    "gn:admin4_code":"50105438.0",
    "gn:asciiname":"Aolak",
    "gn:country_code":"BD",
    "gn:dem":22,
    "gn:feature_class":"P",
    "gn:feature_code":"PPL",
    "gn:name":"\u0100ol\u0101k",
    "gn:population":0,
    "gn:timezone":"Asia/Dhaka",
    "iso:country":"BD",
    "name:und_x_variant":[
        "Aolakhayer",
        "\u0100ol\u0101khair",
        "\u0100ol\u0101k"
    ],
    "wof:name":"Aolak",
    "wof:placetype":"locality"
},
  "geometry": {"coordinates":[89.24762,24.80676],"type":"Point"}
}