{
  "type": "Feature",
  "properties": {
    "gn:admin1_code":"81",
    "gn:admin2_code":"3086.0",
    "gn:admin3_code":"308614.0",
    "gn:admin4_code":"30861443.0",
    "gn:asciiname":"Digal Mohish khali",
    "gn:country_code":"BD",
    "gn:dem":12,
    "gn:feature_class":"P",
    "gn:feature_code":"PPL",
    "gn:name":"Digal Mohish kh\u0101li",
    "gn:population":0,
    "gn:timezone":"Asia/Dhaka",
    "iso:country":"BD",
    "name:und_x_variant":[
        "Digal Mohish kh\u0101li",
        "Digar Mahishkh\u0101li"
    ],
    "wof:name":"Digal Mohish khali",
    "wof:placetype":"locality"
},
  "geometry": {"coordinates":[90.50779,23.20836],"type":"Point"}
}