{
  "type": "Feature",
  "properties": {
    "gn:admin1_code":"83",
    "gn:admin2_code":"5081.0",
    "gn:admin3_code":"508182.0",
    "gn:admin4_code":"50818227.0",
    "gn:asciiname":"Chak Bhangirpara",
    "gn:country_code":"BD",
    "gn:dem":17,
    "gn:feature_class":"P",
    "gn:feature_code":"PPL",
    "gn:name":"Chak Bhangirp\u0101ra",
    "gn:population":0,
    "gn:timezone":"Asia/Dhaka",
    "iso:country":"BD",
    "name:ben_x_preferred":[
        "Chak Bhangirp\u0101ra"
    ],
    "wof:name":"Chak Bhangirpara",
    "wof:placetype":"locality"
},
  "geometry": {"coordinates":[88.72355999999998,24.38015],"type":"Point"}
}