{
  "type": "Feature",
  "properties": {
    "gn:admin1_code":"82",
    "gn:admin2_code":"4018.0",
    "gn:admin3_code":"401807.0",
    "gn:admin4_code":"40180715.0",
    "gn:asciiname":"Kaohikata",
    "gn:country_code":"BD",
    "gn:dem":19,
    "gn:feature_class":"P",
    "gn:feature_code":"PPL",
    "gn:name":"Kaohik\u0101ta",
    "gn:population":0,
    "gn:timezone":"Asia/Dhaka",
    "iso:country":"BD",
    "name:ben_x_preferred":[
        "Kaohik\u0101ta"
    ],
    "wof:name":"Kaohikata",
    "wof:placetype":"locality"
},
  "geometry": {"coordinates":[88.86883,23.72908],"type":"Point"}
}