{
  "type": "Feature",
  "properties": {
    "gn:admin1_code":"85",
    "gn:admin2_code":"1079.0",
    "gn:admin3_code":"107958.0",
    "gn:admin4_code":"10795843.0",
    "gn:asciiname":"Phaljhuri",
    "gn:country_code":"BD",
    "gn:dem":8,
    "gn:feature_class":"P",
    "gn:feature_code":"PPL",
    "gn:name":"Phaljhuri",
    "gn:population":0,
    "gn:timezone":"Asia/Dhaka",
    "iso:country":"BD",
    "name:ben_x_preferred":[
        "Phaljhuri"
    ],
    "wof:name":"Phaljhuri",
    "wof:placetype":"locality"
},
  "geometry": {"coordinates":[89.95079,22.34205],"type":"Point"}
}