{
  "type": "Feature",
  "properties": {
    "gn:admin1_code":"81",
    "gn:admin2_code":"3029",
    "gn:admin3_code":"302956.0",
    "gn:admin4_code":"30295663.0",
    "gn:asciiname":"Narkona",
    "gn:country_code":"BD",
    "gn:dem":10,
    "gn:feature_class":"P",
    "gn:feature_code":"PPL",
    "gn:name":"Narkona",
    "gn:population":0,
    "gn:timezone":"Asia/Dhaka",
    "iso:country":"BD",
    "wof:name":"Narkona",
    "wof:placetype":"locality"
},
  "geometry": {"coordinates":[89.5592,23.57602],"type":"Point"}
}