{
  "type": "Feature",
  "properties": {
    "gn:admin1_code":"H",
    "gn:admin2_code":"3061.0",
    "gn:admin3_code":"306152.0",
    "gn:admin4_code":"30615227.0",
    "gn:asciiname":"Char Srikaldi",
    "gn:country_code":"BD",
    "gn:dem":16,
    "gn:feature_class":"P",
    "gn:feature_code":"PPL",
    "gn:name":"Char Srikaldi",
    "gn:population":0,
    "gn:timezone":"Asia/Dhaka",
    "iso:country":"BD",
    "name:und_x_variant":[
        "Fadiar Char",
        "Char Srikaldi"
    ],
    "wof:name":"Char Srikaldi",
    "wof:placetype":"locality"
},
  "geometry": {"coordinates":[90.28507999999999,24.84754],"type":"Point"}
}