{
  "type": "Feature",
  "properties": {
    "gn:admin1_code":"81",
    "gn:admin2_code":"3035",
    "gn:admin3_code":"303532.0",
    "gn:admin4_code":"30353269.0",
    "gn:asciiname":"Paikandi",
    "gn:country_code":"BD",
    "gn:dem":8,
    "gn:feature_class":"P",
    "gn:feature_code":"PPL",
    "gn:name":"P\u0101ik\u0101ndi",
    "gn:population":0,
    "gn:timezone":"Asia/Dhaka",
    "iso:country":"BD",
    "name:ben_x_preferred":[
        "P\u0101ik\u0101ndi"
    ],
    "name:ben_x_variant":[
        "P\u0101ikk\u0101ndi"
    ],
    "wof:name":"Paikandi",
    "wof:placetype":"locality"
},
  "geometry": {"coordinates":[89.77584,23.0376],"type":"Point"}
}