{
  "type": "Feature",
  "properties": {
    "gn:admin1_code":"81",
    "gn:admin2_code":"3029",
    "gn:admin3_code":"302910.0",
    "gn:admin4_code":"30291031.0",
    "gn:asciiname":"Maligao",
    "gn:country_code":"BD",
    "gn:dem":11,
    "gn:feature_class":"P",
    "gn:feature_code":"PPL",
    "gn:name":"M\u0101lig\u0101o",
    "gn:population":0,
    "gn:timezone":"Asia/Dhaka",
    "iso:country":"BD",
    "name:und_x_variant":[
        "Maligram",
        "M\u0101lig\u0101o"
    ],
    "wof:name":"Maligao",
    "wof:placetype":"locality"
},
  "geometry": {"coordinates":[90.03756,23.37318],"type":"Point"}
}