{
  "type": "Feature",
  "properties": {
    "gn:admin1_code":"83",
    "gn:asciiname":"Burikandi",
    "gn:country_code":"BD",
    "gn:dem":25,
    "gn:feature_class":"P",
    "gn:feature_code":"PPL",
    "gn:name":"Burik\u0101ndi",
    "gn:population":0,
    "gn:timezone":"Asia/Dhaka",
    "iso:country":"BD",
    "name:ben_x_preferred":[
        "Burik\u0101ndi"
    ],
    "wof:name":"Burikandi",
    "wof:placetype":"locality"
},
  "geometry": {"coordinates":[89.52918000000003,25.10602],"type":"Point"}
}