{
  "type": "Feature",
  "properties": {
    "gn:admin1_code":"87",
    "gn:admin2_code":"5585",
    "gn:admin3_code":"558527.0",
    "gn:admin4_code":"55852763.0",
    "gn:asciiname":"Mahishamuri",
    "gn:country_code":"BD",
    "gn:dem":38,
    "gn:feature_class":"P",
    "gn:feature_code":"PPL",
    "gn:name":"Mahish\u0101muri",
    "gn:population":0,
    "gn:timezone":"Asia/Dhaka",
    "iso:country":"BD",
    "name:ben_x_preferred":[
        "Mahish\u0101muri"
    ],
    "wof:name":"Mahishamuri",
    "wof:placetype":"locality"
},
  "geometry": {"coordinates":[89.22931,25.90797],"type":"Point"}
}