{
  "type": "Feature",
  "properties": {
    "gn:admin1_code":"81",
    "gn:admin2_code":"3059.0",
    "gn:admin3_code":"305974.0",
    "gn:admin4_code":"30597406.0",
    "gn:asciiname":"Char Khaskandi",
    "gn:country_code":"BD",
    "gn:dem":8,
    "gn:feature_class":"P",
    "gn:feature_code":"PPL",
    "gn:name":"Char Kh\u0101sk\u0101ndi",
    "gn:population":0,
    "gn:timezone":"Asia/Dhaka",
    "iso:country":"BD",
    "name:und_x_variant":[
        "Char Khashkandi",
        "Char Kh\u0101sk\u0101ndi"
    ],
    "wof:name":"Char Khaskandi",
    "wof:placetype":"locality"
},
  "geometry": {"coordinates":[90.38318,23.63856],"type":"Point"}
}