{
  "type": "Feature",
  "properties": {
    "gn:admin1_code":"82",
    "gn:admin2_code":"4044.0",
    "gn:admin3_code":"404414.0",
    "gn:admin4_code":"40441431.0",
    "gn:asciiname":"Harinakunda",
    "gn:country_code":"BD",
    "gn:dem":15,
    "gn:feature_class":"P",
    "gn:feature_code":"PPL",
    "gn:name":"Harin\u0101kunda",
    "gn:population":0,
    "gn:timezone":"Asia/Dhaka",
    "iso:country":"BD",
    "name:ben_x_preferred":[
        "Harin\u0101kunda"
    ],
    "wof:name":"Harinakunda",
    "wof:placetype":"locality"
},
  "geometry": {"coordinates":[89.02725,23.63527],"type":"Point"}
}