{
  "type": "Feature",
  "properties": {
    "gn:admin1_code":"85",
    "gn:admin2_code":"1009.0",
    "gn:admin3_code":"100991.0",
    "gn:admin4_code":"10099157.0",
    "gn:asciiname":"Dewanpur",
    "gn:country_code":"BD",
    "gn:dem":9,
    "gn:feature_class":"P",
    "gn:feature_code":"PPL",
    "gn:name":"Dewanpur",
    "gn:population":0,
    "gn:timezone":"Asia/Dhaka",
    "iso:country":"BD",
    "name:ben_x_preferred":[
        "Dewanpur"
    ],
    "wof:name":"Dewanpur",
    "wof:placetype":"locality"
},
  "geometry": {"coordinates":[90.84251,22.42105],"type":"Point"}
}