{
  "type": "Feature",
  "properties": {
    "gn:admin1_code":"84",
    "gn:admin2_code":"2013",
    "gn:admin3_code":"201395.0",
    "gn:admin4_code":"20139595.0",
    "gn:asciiname":"Khordda",
    "gn:country_code":"BD",
    "gn:dem":10,
    "gn:feature_class":"P",
    "gn:feature_code":"PPL",
    "gn:name":"Khordda",
    "gn:population":0,
    "gn:timezone":"Asia/Dhaka",
    "iso:country":"BD",
    "name:und_x_variant":[
        "Khordha",
        "Khordda"
    ],
    "wof:name":"Khordda",
    "wof:placetype":"locality"
},
  "geometry": {"coordinates":[90.91088999999999,23.22146],"type":"Point"}
}