{
  "type": "Feature",
  "properties": {
    "gn:admin1_code":"81",
    "gn:admin2_code":"3093.0",
    "gn:admin3_code":"309347.0",
    "gn:admin4_code":"30934794.0",
    "gn:asciiname":"Bhabanipur",
    "gn:country_code":"BD",
    "gn:dem":11,
    "gn:feature_class":"P",
    "gn:feature_code":"PPL",
    "gn:name":"Bhab\u0101n\u012bpur",
    "gn:population":0,
    "gn:timezone":"Asia/Dhaka",
    "iso:country":"BD",
    "name:ben_x_preferred":[
        "\u09ad\u09ac\u09be\u09a8\u09c0\u09aa\u09c1\u09b0"
    ],
    "wof:name":"Bhabanipur",
    "wof:placetype":"locality"
},
  "geometry": {"coordinates":[89.95,24.33333],"type":"Point"}
}