{
  "type": "Feature",
  "properties": {
    "gn:admin1_code":"87",
    "gn:admin2_code":"5594.0",
    "gn:admin3_code":"559408.0",
    "gn:admin4_code":"55940831.0",
    "gn:asciiname":"Karwa",
    "gn:country_code":"BD",
    "gn:dem":54,
    "gn:feature_class":"P",
    "gn:feature_code":"PPL",
    "gn:name":"Karwa",
    "gn:population":0,
    "gn:timezone":"Asia/Dhaka",
    "iso:country":"BD",
    "name:ben_x_preferred":[
        "Karwa"
    ],
    "wof:name":"Karwa",
    "wof:placetype":"locality"
},
  "geometry": {"coordinates":[88.21821,26.1017],"type":"Point"}
}