{
  "type": "Feature",
  "properties": {
    "gn:admin1_code":"87",
    "gn:admin2_code":"5527.0",
    "gn:admin3_code":"552756.0",
    "gn:admin4_code":"55275663.0",
    "gn:asciiname":"Chak Iswar",
    "gn:country_code":"BD",
    "gn:dem":48,
    "gn:feature_class":"P",
    "gn:feature_code":"PPL",
    "gn:name":"Chak Isw\u0101r",
    "gn:population":0,
    "gn:timezone":"Asia/Dhaka",
    "iso:country":"BD",
    "name:ben_x_preferred":[
        "Chak Isw\u0101r"
    ],
    "wof:name":"Chak Iswar",
    "wof:placetype":"locality"
},
  "geometry": {"coordinates":[88.5763,25.83106],"type":"Point"}
}