{
  "type": "Feature",
  "properties": {
    "gn:admin1_code":"85",
    "gn:admin2_code":"1006.0",
    "gn:admin3_code":"100662.0",
    "gn:admin4_code":"10066279.0",
    "gn:asciiname":"Sonapur",
    "gn:country_code":"BD",
    "gn:dem":4,
    "gn:feature_class":"P",
    "gn:feature_code":"PPL",
    "gn:name":"Son\u0101pur",
    "gn:population":0,
    "gn:timezone":"Asia/Dhaka",
    "iso:country":"BD",
    "name:und_x_variant":[
        "Tar Son\u0101pur",
        "Char Son\u0101pur",
        "Son\u0101pur"
    ],
    "wof:name":"Sonapur",
    "wof:placetype":"locality"
},
  "geometry": {"coordinates":[90.44755000000001,22.88163],"type":"Point"}
}