{
  "type": "Feature",
  "properties": {
    "gn:admin1_code":"84",
    "gn:admin2_code":"2013",
    "gn:admin3_code":"201349.0",
    "gn:admin4_code":"20134935.0",
    "gn:asciiname":"Satbaria",
    "gn:country_code":"BD",
    "gn:dem":12,
    "gn:feature_class":"P",
    "gn:feature_code":"PPL",
    "gn:name":"S\u0101tb\u0101ria",
    "gn:population":0,
    "gn:timezone":"Asia/Dhaka",
    "iso:country":"BD",
    "wof:name":"Satbaria",
    "wof:placetype":"locality"
},
  "geometry": {"coordinates":[90.79554,23.25573],"type":"Point"}
}