{
  "type": "Feature",
  "properties": {
    "gn:admin1_code":"87",
    "gn:admin2_code":"5594.0",
    "gn:admin3_code":"559482.0",
    "gn:admin4_code":"55948234.0",
    "gn:asciiname":"Bonuapara",
    "gn:country_code":"BD",
    "gn:dem":46,
    "gn:feature_class":"P",
    "gn:feature_code":"PPL",
    "gn:name":"Bonuapara",
    "gn:population":0,
    "gn:timezone":"Asia/Dhaka",
    "iso:country":"BD",
    "name:ben_x_preferred":[
        "Bonuapara"
    ],
    "wof:name":"Bonuapara",
    "wof:placetype":"locality"
},
  "geometry": {"coordinates":[88.38421,25.80566],"type":"Point"}
}