{
  "type": "Feature",
  "properties": {
    "gn:admin1_code":"82",
    "gn:asciiname":"Khantakhali",
    "gn:country_code":"BD",
    "gn:dem":6,
    "gn:feature_class":"P",
    "gn:feature_code":"PPL",
    "gn:name":"Khant\u0101kh\u0101li",
    "gn:population":0,
    "gn:timezone":"Asia/Dhaka",
    "iso:country":"BD",
    "name:ben_x_preferred":[
        "Khant\u0101kh\u0101li"
    ],
    "wof:name":"Khantakhali",
    "wof:placetype":"locality"
},
  "geometry": {"coordinates":[90.3668,22.19702],"type":"Point"}
}