{
  "type": "Feature",
  "properties": {
    "gn:admin1_code":"87",
    "gn:admin2_code":"5549",
    "gn:admin3_code":"554918.0",
    "gn:admin4_code":"55491840.0",
    "gn:asciiname":"Qismat Prankrishna",
    "gn:country_code":"BD",
    "gn:dem":33,
    "gn:feature_class":"P",
    "gn:feature_code":"PPL",
    "gn:name":"Qismat Pr\u0101nkrishna",
    "gn:population":0,
    "gn:timezone":"Asia/Dhaka",
    "iso:country":"BD",
    "name:ben_x_preferred":[
        "Qismat Pr\u0101nkrishna"
    ],
    "wof:name":"Qismat Prankrishna",
    "wof:placetype":"locality"
},
  "geometry": {"coordinates":[89.54738,25.92956],"type":"Point"}
}