{
  "type": "Feature",
  "properties": {
    "gn:admin1_code":"84",
    "gn:admin2_code":"2019",
    "gn:admin3_code":"201909.0",
    "gn:admin4_code":"20190982.0",
    "gn:asciiname":"Sanandakara",
    "gn:country_code":"BD",
    "gn:dem":8,
    "gn:feature_class":"P",
    "gn:feature_code":"PPL",
    "gn:name":"S\u0101nand\u0101k\u0101ra",
    "gn:population":0,
    "gn:timezone":"Asia/Dhaka",
    "iso:country":"BD",
    "wof:name":"Sanandakara",
    "wof:placetype":"locality"
},
  "geometry": {"coordinates":[91.01667,23.25],"type":"Point"}
}