{
  "type": "Feature",
  "properties": {
    "gn:admin1_code":"H",
    "gn:admin2_code":"3072.0",
    "gn:admin3_code":"307247.0",
    "gn:admin4_code":"30724740.0",
    "gn:asciiname":"Bhatlara",
    "gn:country_code":"BD",
    "gn:dem":15,
    "gn:feature_class":"P",
    "gn:feature_code":"PPL",
    "gn:name":"Bh\u0101tl\u0101ra",
    "gn:population":0,
    "gn:timezone":"Asia/Dhaka",
    "iso:country":"BD",
    "wof:name":"Bhatlara",
    "wof:placetype":"locality"
},
  "geometry": {"coordinates":[90.73813,24.68523],"type":"Point"}
}