{
  "type": "Feature",
  "properties": {
    "gn:admin1_code":"83",
    "gn:admin2_code":"5081.0",
    "gn:admin3_code":"508153.0",
    "gn:admin4_code":"50815367.0",
    "gn:asciiname":"Akbarpur",
    "gn:country_code":"BD",
    "gn:dem":22,
    "gn:feature_class":"P",
    "gn:feature_code":"PPL",
    "gn:name":"Akb\u0101rpur",
    "gn:population":0,
    "gn:timezone":"Asia/Dhaka",
    "iso:country":"BD",
    "name:ben_x_preferred":[
        "Akb\u0101rpur"
    ],
    "name:bih_x_preferred":[
        "\u0905\u0915\u092c\u0930\u092a\u0941\u0930"
    ],
    "name:ceb_x_preferred":[
        "Akbarpur"
    ],
    "name:deu_x_preferred":[
        "Akbarpur"
    ],
    "name:ita_x_preferred":[
        "Akbarpur"
    ],
    "name:msa_x_preferred":[
        "Akbarpur"
    ],
    "name:new_x_preferred":[
        "\u0905\u0916\u092c\u0930\u092a\u0941\u0930"
    ],
    "name:nld_x_preferred":[
        "Akbarpur"
    ],
    "name:pol_x_preferred":[
        "Akbarpur"
    ],
    "name:rus_x_preferred":[
        "\u0410\u043a\u0431\u0430\u0440\u043f\u0443\u0440"
    ],
    "name:swe_x_preferred":[
        "Akbarpur"
    ],
    "name:vie_x_preferred":[
        "Akbarpur"
    ],
    "wof:name":"Akbarpur",
    "wof:placetype":"locality"
},
  "geometry": {"coordinates":[88.62445,24.50425],"type":"Point"}
}