{
  "type": "Feature",
  "properties": {
    "gn:admin1_code":"82",
    "gn:admin2_code":"4018.0",
    "gn:admin3_code":"401831.0",
    "gn:admin4_code":"40183159.0",
    "gn:asciiname":"Nichinpur",
    "gn:country_code":"BD",
    "gn:dem":19,
    "gn:feature_class":"P",
    "gn:feature_code":"PPL",
    "gn:name":"Nichinpur",
    "gn:population":0,
    "gn:timezone":"Asia/Dhaka",
    "iso:country":"BD",
    "name:ben_x_preferred":[
        "Nichinpur"
    ],
    "wof:name":"Nichinpur",
    "wof:placetype":"locality"
},
  "geometry": {"coordinates":[88.70820000000001,23.57546],"type":"Point"}
}