{
  "type": "Feature",
  "properties": {
    "gn:admin1_code":"83",
    "gn:admin2_code":"5088.0",
    "gn:admin3_code":"508811.0",
    "gn:admin4_code":"50881140.0",
    "gn:asciiname":"Biswaspara",
    "gn:country_code":"BD",
    "gn:dem":16,
    "gn:feature_class":"P",
    "gn:feature_code":"PPL",
    "gn:name":"Biswasp\u0101ra",
    "gn:population":0,
    "gn:timezone":"Asia/Dhaka",
    "iso:country":"BD",
    "name:und_x_variant":[
        "Biswasp\u0101ra",
        "Bisw\u0101sb\u0101ri"
    ],
    "wof:name":"Biswaspara",
    "wof:placetype":"locality"
},
  "geometry": {"coordinates":[89.65679,24.30359],"type":"Point"}
}