{
  "type": "Feature",
  "properties": {
    "gn:admin1_code":"81",
    "gn:admin2_code":"3033.0",
    "gn:admin3_code":"303386.0",
    "gn:admin4_code":"30338666.0",
    "gn:asciiname":"Doaibari",
    "gn:country_code":"BD",
    "gn:dem":16,
    "gn:feature_class":"P",
    "gn:feature_code":"PPL",
    "gn:name":"Do\u0101ib\u0101ri",
    "gn:population":0,
    "gn:timezone":"Asia/Dhaka",
    "iso:country":"BD",
    "wof:name":"Doaibari",
    "wof:placetype":"locality"
},
  "geometry": {"coordinates":[90.48095000000001,24.1483],"type":"Point"}
}