{
  "type": "Feature",
  "properties": {
    "gn:admin1_code":"87",
    "gn:admin2_code":"5585",
    "gn:admin3_code":"558549.0",
    "gn:admin4_code":"55854963.0",
    "gn:asciiname":"Madhabpur",
    "gn:country_code":"BD",
    "gn:dem":35,
    "gn:feature_class":"P",
    "gn:feature_code":"PPL",
    "gn:name":"Madhabpur",
    "gn:population":0,
    "gn:timezone":"Asia/Dhaka",
    "iso:country":"BD",
    "name:ben_x_preferred":[
        "Madhabpur"
    ],
    "wof:name":"Madhabpur",
    "wof:placetype":"locality"
},
  "geometry": {"coordinates":[89.19933,25.69761],"type":"Point"}
}