{
  "type": "Feature",
  "properties": {
    "gn:admin1_code":"84",
    "gn:admin2_code":"2075.0",
    "gn:admin3_code":"207510.0",
    "gn:admin4_code":"20751019.0",
    "gn:asciiname":"Baktarpur",
    "gn:country_code":"BD",
    "gn:dem":13,
    "gn:feature_class":"P",
    "gn:feature_code":"PPL",
    "gn:name":"Bakt\u0101rpur",
    "gn:population":0,
    "gn:timezone":"Asia/Dhaka",
    "iso:country":"BD",
    "wof:name":"Baktarpur",
    "wof:placetype":"locality"
},
  "geometry": {"coordinates":[90.95698,23.04202],"type":"Point"}
}