{
  "type": "Feature",
  "properties": {
    "gn:admin1_code":"83",
    "gn:admin2_code":"5064",
    "gn:admin3_code":"506406.0",
    "gn:admin4_code":"50640610.0",
    "gn:asciiname":"Sripur",
    "gn:country_code":"BD",
    "gn:dem":21,
    "gn:feature_class":"P",
    "gn:feature_code":"PPL",
    "gn:name":"Sr\u012bpur",
    "gn:population":0,
    "gn:timezone":"Asia/Dhaka",
    "iso:country":"BD",
    "name:bih_x_preferred":[
        "\u0936\u094d\u0930\u0940\u092a\u0941\u0930"
    ],
    "name:und_x_variant":[
        "Sreepur",
        "Sr\u012bpur"
    ],
    "wof:name":"Sripur",
    "wof:placetype":"locality"
},
  "geometry": {"coordinates":[88.95,24.96667],"type":"Point"}
}