{
  "type": "Feature",
  "properties": {
    "gn:admin1_code":"87",
    "gn:admin2_code":"5532",
    "gn:admin3_code":"553282.0",
    "gn:admin4_code":"55328234.0",
    "gn:asciiname":"Tantipara",
    "gn:country_code":"BD",
    "gn:dem":27,
    "gn:feature_class":"P",
    "gn:feature_code":"PPL",
    "gn:name":"Tantipara",
    "gn:population":0,
    "gn:timezone":"Asia/Dhaka",
    "iso:country":"BD",
    "name:ben_x_preferred":[
        "Tantipara"
    ],
    "wof:name":"Tantipara",
    "wof:placetype":"locality"
},
  "geometry": {"coordinates":[89.37909999999999,25.37326],"type":"Point"}
}