{
  "type": "Feature",
  "properties": {
    "gn:admin1_code":"81",
    "gn:admin2_code":"3048.0",
    "gn:admin3_code":"304827.0",
    "gn:admin4_code":"30482740.0",
    "gn:asciiname":"Char Jinari",
    "gn:country_code":"BD",
    "gn:dem":16,
    "gn:feature_class":"P",
    "gn:feature_code":"PPL",
    "gn:name":"Char Jin\u0101ri",
    "gn:population":0,
    "gn:timezone":"Asia/Dhaka",
    "iso:country":"BD",
    "wof:name":"Char Jinari",
    "wof:placetype":"locality"
},
  "geometry": {"coordinates":[90.58955,24.47593],"type":"Point"}
}