{
  "type": "Feature",
  "properties": {
    "gn:admin1_code":"83",
    "gn:admin2_code":"5010.0",
    "gn:admin3_code":"501020.0",
    "gn:admin4_code":"50102047.0",
    "gn:asciiname":"Dakhin Bhag",
    "gn:country_code":"BD",
    "gn:dem":22,
    "gn:feature_class":"P",
    "gn:feature_code":"PPL",
    "gn:name":"Dakhin Bh\u0101g",
    "gn:population":0,
    "gn:timezone":"Asia/Dhaka",
    "iso:country":"BD",
    "name:und_x_variant":[
        "Dakshinbhag",
        "Dakhin Bh\u0101g"
    ],
    "wof:name":"Dakhin Bhag",
    "wof:placetype":"locality"
},
  "geometry": {"coordinates":[89.37826,24.93825],"type":"Point"}
}