{
  "type": "Feature",
  "properties": {
    "gn:admin1_code":"84",
    "gn:admin2_code":"2003.0",
    "gn:admin3_code":"200351.0",
    "gn:admin4_code":"20035163.0",
    "gn:asciiname":"Kaunglagyawpara",
    "gn:country_code":"BD",
    "gn:dem":20,
    "gn:feature_class":"P",
    "gn:feature_code":"PPL",
    "gn:name":"Kaungl\u0101gyawp\u0101ra",
    "gn:population":0,
    "gn:timezone":"Asia/Dhaka",
    "iso:country":"BD",
    "name:ben_x_preferred":[
        "Kaungl\u0101gyawp\u0101ra"
    ],
    "wof:name":"Kaunglagyawpara",
    "wof:placetype":"locality"
},
  "geometry": {"coordinates":[92.21905,21.77179],"type":"Point"}
}