{
  "type": "Feature",
  "properties": {
    "gn:admin1_code":"H",
    "gn:admin2_code":"3072.0",
    "gn:admin3_code":"307274.0",
    "gn:admin4_code":"30727439.0",
    "gn:asciiname":"Gabraganti",
    "gn:country_code":"BD",
    "gn:dem":15,
    "gn:feature_class":"P",
    "gn:feature_code":"PPL",
    "gn:name":"G\u0101br\u0101g\u0101nti",
    "gn:population":0,
    "gn:timezone":"Asia/Dhaka",
    "iso:country":"BD",
    "name:und_x_variant":[
        "Gabragati",
        "G\u0101br\u0101g\u0101nti"
    ],
    "wof:name":"Gabraganti",
    "wof:placetype":"locality"
},
  "geometry": {"coordinates":[90.73658,24.96992],"type":"Point"}
}