{
  "type": "Feature",
  "properties": {
    "gn:admin1_code":"82",
    "gn:admin2_code":"4041.0",
    "gn:admin3_code":"404190.0",
    "gn:admin4_code":"40419069.0",
    "gn:asciiname":"Akjhala",
    "gn:country_code":"BD",
    "gn:dem":14,
    "gn:feature_class":"P",
    "gn:feature_code":"PPL",
    "gn:name":"\u0100kjh\u0101la",
    "gn:population":0,
    "gn:timezone":"Asia/Dhaka",
    "iso:country":"BD",
    "name:ben_x_preferred":[
        "\u0100kjh\u0101la"
    ],
    "wof:name":"Akjhala",
    "wof:placetype":"locality"
},
  "geometry": {"coordinates":[88.97114999999999,23.10763],"type":"Point"}
}