{
  "type": "Feature",
  "properties": {
    "gn:admin1_code":"82",
    "gn:admin2_code":"4047.0",
    "gn:admin3_code":"404794.0",
    "gn:admin4_code":"40479440.0",
    "gn:asciiname":"Balarampur",
    "gn:country_code":"BD",
    "gn:dem":3,
    "gn:feature_class":"P",
    "gn:feature_code":"PPL",
    "gn:name":"Bal\u0101r\u0101mpur",
    "gn:population":0,
    "gn:timezone":"Asia/Dhaka",
    "iso:country":"BD",
    "name:ben_x_preferred":[
        "Bal\u0101r\u0101mpur"
    ],
    "wof:name":"Balarampur",
    "wof:placetype":"locality"
},
  "geometry": {"coordinates":[89.61779,22.91292],"type":"Point"}
}