{
  "type": "Feature",
  "properties": {
    "gn:admin1_code":"85",
    "gn:admin2_code":"1006.0",
    "gn:admin3_code":"100694.0",
    "gn:admin4_code":"10069463.0",
    "gn:asciiname":"Bamankati",
    "gn:country_code":"BD",
    "gn:dem":8,
    "gn:feature_class":"P",
    "gn:feature_code":"PPL",
    "gn:name":"B\u0101mank\u0101ti",
    "gn:population":0,
    "gn:timezone":"Asia/Dhaka",
    "iso:country":"BD",
    "name:und_x_variant":[
        "B\u0101mank\u0101ti"
    ],
    "wof:name":"Bamankati",
    "wof:placetype":"locality"
},
  "geometry": {"coordinates":[90.13621999999999,22.8783],"type":"Point"}
}