{
  "type": "Feature",
  "properties": {
    "gn:admin1_code":"H",
    "gn:admin2_code":"3039",
    "gn:admin3_code":"303907.0",
    "gn:admin4_code":"30390759.0",
    "gn:asciiname":"Rabiar Char",
    "gn:country_code":"BD",
    "gn:dem":25,
    "gn:feature_class":"P",
    "gn:feature_code":"PPL",
    "gn:name":"Rabiar Char",
    "gn:population":0,
    "gn:timezone":"Asia/Dhaka",
    "iso:country":"BD",
    "wof:name":"Rabiar Char",
    "wof:placetype":"locality"
},
  "geometry": {"coordinates":[89.85204,25.16947],"type":"Point"}
}