{
  "type": "Feature",
  "properties": {
    "gn:admin1_code":"81",
    "gn:admin2_code":"3093",
    "gn:admin3_code":"309376.0",
    "gn:admin4_code":"30937621.0",
    "gn:asciiname":"Kadim Kagna",
    "gn:country_code":"BD",
    "gn:dem":14,
    "gn:feature_class":"P",
    "gn:feature_code":"PPL",
    "gn:name":"Kadim K\u0101gna",
    "gn:population":0,
    "gn:timezone":"Asia/Dhaka",
    "iso:country":"BD",
    "wof:name":"Kadim Kagna",
    "wof:placetype":"locality"
},
  "geometry": {"coordinates":[89.80306999999998,24.01391],"type":"Point"}
}