{
  "type": "Feature",
  "properties": {
    "gn:admin1_code":"82",
    "gn:admin2_code":"4044",
    "gn:admin3_code":"404419.0",
    "gn:admin4_code":"40441908.0",
    "gn:asciiname":"Panditpur",
    "gn:country_code":"BD",
    "gn:dem":11,
    "gn:feature_class":"P",
    "gn:feature_code":"PPL",
    "gn:name":"Panditpur",
    "gn:population":0,
    "gn:timezone":"Asia/Dhaka",
    "iso:country":"BD",
    "wof:name":"Panditpur",
    "wof:placetype":"locality"
},
  "geometry": {"coordinates":[89.24865,23.50981],"type":"Point"}
}