{
  "type": "Feature",
  "properties": {
    "gn:admin1_code":"84",
    "gn:admin2_code":"2075.0",
    "gn:admin3_code":"207521.0",
    "gn:admin4_code":"20752183.0",
    "gn:asciiname":"Chhota Rajapur",
    "gn:cc2":"BD",
    "gn:country_code":"BD",
    "gn:dem":10,
    "gn:feature_class":"P",
    "gn:feature_code":"PPL",
    "gn:name":"Chhota R\u0101j\u0101pur",
    "gn:population":0,
    "gn:timezone":"Asia/Dhaka",
    "iso:country":"BD",
    "name:und_x_variant":[
        "Little Rajapur",
        "Chhota R\u0101j\u0101pur"
    ],
    "wof:name":"Chhota Rajapur",
    "wof:placetype":"locality"
},
  "geometry": {"coordinates":[91.25,22.86667000000001],"type":"Point"}
}