{
  "type": "Feature",
  "properties": {
    "gn:admin1_code":"81",
    "gn:admin2_code":"3067",
    "gn:admin3_code":"306704.0",
    "gn:admin4_code":"30670425.0",
    "gn:asciiname":"Paikpara",
    "gn:country_code":"BD",
    "gn:dem":11,
    "gn:feature_class":"P",
    "gn:feature_code":"PPL",
    "gn:name":"P\u0101ikp\u0101ra",
    "gn:population":0,
    "gn:timezone":"Asia/Dhaka",
    "iso:country":"BD",
    "wof:name":"Paikpara",
    "wof:placetype":"locality"
},
  "geometry": {"coordinates":[90.67153,23.70068],"type":"Point"}
}