{
  "type": "Feature",
  "properties": {
    "gn:admin1_code":"87",
    "gn:admin2_code":"5573.0",
    "gn:admin3_code":"557364.0",
    "gn:admin4_code":"55736482.0",
    "gn:asciiname":"Subarnakhuli",
    "gn:country_code":"BD",
    "gn:dem":46,
    "gn:feature_class":"P",
    "gn:feature_code":"PPL",
    "gn:name":"Subarnakhuli",
    "gn:population":0,
    "gn:timezone":"Asia/Dhaka",
    "iso:country":"BD",
    "name:ben_x_preferred":[
        "Subarnakhuli"
    ],
    "wof:name":"Subarnakhuli",
    "wof:placetype":"locality"
},
  "geometry": {"coordinates":[88.86946999999998,25.83886],"type":"Point"}
}