{
  "type": "Feature",
  "properties": {
    "gn:admin1_code":"83",
    "gn:admin2_code":"5064.0",
    "gn:admin3_code":"506475.0",
    "gn:admin4_code":"50647551.0",
    "gn:asciiname":"Khanpur",
    "gn:country_code":"BD",
    "gn:dem":24,
    "gn:feature_class":"P",
    "gn:feature_code":"PPL",
    "gn:name":"Kh\u0101npur",
    "gn:population":0,
    "gn:timezone":"Asia/Dhaka",
    "iso:country":"BD",
    "name:ben_x_preferred":[
        "Kh\u0101npur"
    ],
    "wof:name":"Khanpur",
    "wof:placetype":"locality"
},
  "geometry": {"coordinates":[88.66008000000002,25.03161],"type":"Point"}
}