{
  "type": "Feature",
  "properties": {
    "gn:admin1_code":"87",
    "gn:admin2_code":"5532",
    "gn:admin3_code":"553282.0",
    "gn:admin4_code":"55328243.0",
    "gn:asciiname":"Mirpur",
    "gn:country_code":"BD",
    "gn:dem":29,
    "gn:feature_class":"P",
    "gn:feature_code":"PPL",
    "gn:name":"Mirpur",
    "gn:population":0,
    "gn:timezone":"Asia/Dhaka",
    "iso:country":"BD",
    "name:ben_x_preferred":[
        "Mirpur"
    ],
    "wof:name":"Mirpur",
    "wof:placetype":"locality"
},
  "geometry": {"coordinates":[89.38386,25.42526],"type":"Point"}
}