{
  "type": "Feature",
  "properties": {
    "gn:admin1_code":"87",
    "gn:admin2_code":"5532",
    "gn:admin3_code":"553282.0",
    "gn:admin4_code":"55328243.0",
    "gn:asciiname":"Mirpur",
    "gn:country_code":"BD",
    "gn:dem":29,
    "gn:feature_class":"P",
    "gn:feature_code":"PPL",
    "gn:name":"Mirpur",
    "gn:population":0,
    "gn:timezone":"Asia/Dhaka",
    "iso:country":"BD",
    "name:ben_x_preferred":[
        "Mirpur"
    ],
    "name:ben_x_variant":[
        "\u09ae\u09bf\u09b0\u09aa\u09c1\u09b0"
    ],
    "name:ita_x_preferred":[
        "Mirpur"
    ],
    "name:sco_x_preferred":[
        "Mirpur"
    ],
    "name:snd_x_preferred":[
        "\u0645\u064a\u0631\u067e\u0648\u0631"
    ],
    "wof:name":"Mirpur",
    "wof:placetype":"locality"
},
  "geometry": {"coordinates":[89.38386,25.42526],"type":"Point"}
}