{
  "type": "Feature",
  "properties": {
    "gn:admin1_code":"83",
    "gn:admin2_code":"5070",
    "gn:admin3_code":"507056.0",
    "gn:admin4_code":"50705619.0",
    "gn:asciiname":"Paitali",
    "gn:country_code":"BD",
    "gn:dem":35,
    "gn:feature_class":"P",
    "gn:feature_code":"PPL",
    "gn:name":"P\u0101itali",
    "gn:population":0,
    "gn:timezone":"Asia/Dhaka",
    "iso:country":"BD",
    "name:ben_x_preferred":[
        "P\u0101itali"
    ],
    "name:ben_x_variant":[
        "P\u0101nitali"
    ],
    "name:und_x_variant":[
        "Paintali"
    ],
    "wof:name":"Paitali",
    "wof:placetype":"locality"
},
  "geometry": {"coordinates":[88.36589000000002,24.72593],"type":"Point"}
}