{
  "type": "Feature",
  "properties": {
    "gn:admin1_code":"81",
    "gn:admin2_code":"3093",
    "gn:admin3_code":"309376.0",
    "gn:admin4_code":"30937607.0",
    "gn:asciiname":"Seolai",
    "gn:country_code":"BD",
    "gn:dem":14,
    "gn:feature_class":"P",
    "gn:feature_code":"PPL",
    "gn:name":"Seol\u0101i",
    "gn:population":0,
    "gn:timezone":"Asia/Dhaka",
    "iso:country":"BD",
    "name:und_x_variant":[
        "Seolaid",
        "Seol\u0101i"
    ],
    "wof:name":"Seolai",
    "wof:placetype":"locality"
},
  "geometry": {"coordinates":[89.85136999999997,23.9823],"type":"Point"}
}