{
  "type": "Feature",
  "properties": {
    "gn:admin1_code":"81",
    "gn:admin2_code":"3035",
    "gn:admin3_code":"303558.0",
    "gn:admin4_code":"30355889.0",
    "gn:asciiname":"Mobarakkandi",
    "gn:country_code":"BD",
    "gn:dem":7,
    "gn:feature_class":"P",
    "gn:feature_code":"PPL",
    "gn:name":"Mob\u0101rakk\u0101ndi",
    "gn:population":0,
    "gn:timezone":"Asia/Dhaka",
    "iso:country":"BD",
    "name:und_x_variant":[
        "Mobarek Kandi",
        "Mob\u0101rakk\u0101ndi"
    ],
    "wof:name":"Mobarakkandi",
    "wof:placetype":"locality"
},
  "geometry": {"coordinates":[89.87635,23.30831],"type":"Point"}
}