{
  "type": "Feature",
  "properties": {
    "gn:admin1_code":"H",
    "gn:admin2_code":"3061",
    "gn:admin3_code":"306165.0",
    "gn:admin4_code":"30616508.0",
    "gn:asciiname":"Kathalsar",
    "gn:country_code":"BD",
    "gn:dem":19,
    "gn:feature_class":"P",
    "gn:feature_code":"PPL",
    "gn:name":"K\u0101th\u0101lsar",
    "gn:population":0,
    "gn:timezone":"Asia/Dhaka",
    "iso:country":"BD",
    "wof:name":"Kathalsar",
    "wof:placetype":"locality"
},
  "geometry": {"coordinates":[90.17668,24.78599],"type":"Point"}
}