{
  "type": "Feature",
  "properties": {
    "gn:admin1_code":"85",
    "gn:admin2_code":"1079.0",
    "gn:admin3_code":"107958.0",
    "gn:admin4_code":"10795834.0",
    "gn:asciiname":"West Chalitabunia",
    "gn:country_code":"BD",
    "gn:dem":9,
    "gn:feature_class":"P",
    "gn:feature_code":"PPL",
    "gn:name":"West Ch\u0101lit\u0101bunia",
    "gn:population":0,
    "gn:timezone":"Asia/Dhaka",
    "iso:country":"BD",
    "name:ben_x_preferred":[
        "West Ch\u0101lit\u0101bunia"
    ],
    "wof:name":"West Chalitabunia",
    "wof:placetype":"locality"
},
  "geometry": {"coordinates":[90.02871,22.3317],"type":"Point"}
}