{
  "type": "Feature",
  "properties": {
    "gn:admin1_code":"87",
    "gn:admin2_code":"5594.0",
    "gn:admin3_code":"559451.0",
    "gn:admin4_code":"55945167.0",
    "gn:asciiname":"Dhardharia",
    "gn:country_code":"BD",
    "gn:dem":45,
    "gn:feature_class":"P",
    "gn:feature_code":"PPL",
    "gn:name":"Dhardharia",
    "gn:population":0,
    "gn:timezone":"Asia/Dhaka",
    "iso:country":"BD",
    "name:ben_x_preferred":[
        "Dhardharia"
    ],
    "wof:name":"Dhardharia",
    "wof:placetype":"locality"
},
  "geometry": {"coordinates":[88.13265,25.94585],"type":"Point"}
}