{
  "type": "Feature",
  "properties": {
    "gn:admin1_code":"87",
    "gn:admin2_code":"5549",
    "gn:admin3_code":"554979.0",
    "gn:admin4_code":"55497911.0",
    "gn:asciiname":"Tintali",
    "gn:country_code":"BD",
    "gn:dem":26,
    "gn:feature_class":"P",
    "gn:feature_code":"PPL",
    "gn:name":"Tintali",
    "gn:population":0,
    "gn:timezone":"Asia/Dhaka",
    "iso:country":"BD",
    "name:ben_x_preferred":[
        "Tintali"
    ],
    "wof:name":"Tintali",
    "wof:placetype":"locality"
},
  "geometry": {"coordinates":[89.82501999999999,25.607],"type":"Point"}
}