{
  "type": "Feature",
  "properties": {
    "gn:admin1_code":"84",
    "gn:admin2_code":"2051.0",
    "gn:admin3_code":"205173.0",
    "gn:admin4_code":"20517331.0",
    "gn:asciiname":"Char Algi",
    "gn:country_code":"BD",
    "gn:dem":10,
    "gn:feature_class":"P",
    "gn:feature_code":"PPL",
    "gn:name":"Char \u0100lgi",
    "gn:population":0,
    "gn:timezone":"Asia/Dhaka",
    "iso:country":"BD",
    "wof:name":"Char Algi",
    "wof:placetype":"locality"
},
  "geometry": {"coordinates":[90.94969,22.62517],"type":"Point"}
}