{
  "type": "Feature",
  "properties": {
    "gn:admin1_code":"84",
    "gn:admin2_code":"2075.0",
    "gn:admin3_code":"207580.0",
    "gn:admin4_code":"20758076.0",
    "gn:asciiname":"Bijaibag",
    "gn:cc2":"BD",
    "gn:country_code":"BD",
    "gn:dem":8,
    "gn:feature_class":"P",
    "gn:feature_code":"PPL",
    "gn:name":"Bijaib\u0101g",
    "gn:population":0,
    "gn:timezone":"Asia/Dhaka",
    "iso:country":"BD",
    "name:und_x_variant":[
        "Bijoybagh",
        "Bijaib\u0101g"
    ],
    "wof:name":"Bijaibag",
    "wof:placetype":"locality"
},
  "geometry": {"coordinates":[91.23444000000001,22.94167],"type":"Point"}
}