{
  "type": "Feature",
  "properties": {
    "iso:country":"BD",
    "name:eng_x_colloquial":[
        "Sadar Ghaat",
        "Sadar Ghat"
    ],
    "name:eng_x_preferred":[
        "Sadar Gh\u00e5t"
    ],
    "qs:gn_adm0_cc":"BD",
    "qs:gn_local":1205733,
    "qs:gn_nam_loc":"Chittagong, Chittagong, Chittagong, BD",
    "qs:gn_namadm1":"84",
    "qs:local_max":310,
    "qs:local_sum":310,
    "qs:localhoods":1,
    "qs:name":"Sadar Gh\u00e5t",
    "qs:name_adm0":"Bangladesh",
    "qs:name_adm1":"Chittagong",
    "qs:name_adm2":"Chittagong",
    "qs:name_local":"Chittagong",
    "qs:photo_max":102,
    "qs:photo_sum":310,
    "qs:placetype":"Suburb",
    "qs:quad_count":30,
    "qs:woe_adm0":23424759,
    "qs:woe_adm1":2344790,
    "qs:woe_adm2":23706416,
    "qs:woe_lau":0,
    "qs:woe_local":1915031,
    "qs:woe_ver":"7.10.0",
    "wof:lang":[
        "eng"
    ],
    "wof:name":"Sadar Gh\u00e5t",
    "wof:placetype":"neighbourhood"
},
  "geometry": {"coordinates":[91.824299,22.332965],"type":"Point"}
}