{
  "type": "Feature",
  "properties": {
    "gn:admin1_code":"87",
    "gn:admin2_code":"5527.0",
    "gn:admin3_code":"552756.0",
    "gn:admin4_code":"55275647.0",
    "gn:asciiname":"Nayabad",
    "gn:country_code":"BD",
    "gn:dem":43,
    "gn:feature_class":"P",
    "gn:feature_code":"PPL",
    "gn:name":"Nay\u0101b\u0101d",
    "gn:population":0,
    "gn:timezone":"Asia/Dhaka",
    "iso:country":"BD",
    "name:ben_x_preferred":[
        "Nay\u0101b\u0101d"
    ],
    "wof:name":"Nayabad",
    "wof:placetype":"locality"
},
  "geometry": {"coordinates":[88.64596999999998,25.78817],"type":"Point"}
}