{
  "type": "Feature",
  "properties": {
    "gn:admin1_code":"84",
    "gn:admin2_code":"2022.0",
    "gn:admin3_code":"202249.0",
    "gn:admin4_code":"20224983.0",
    "gn:asciiname":"Kussarpara",
    "gn:country_code":"BD",
    "gn:dem":12,
    "gn:feature_class":"P",
    "gn:feature_code":"PPL",
    "gn:name":"Kuss\u0101rp\u0101ra",
    "gn:population":0,
    "gn:timezone":"Asia/Dhaka",
    "iso:country":"BD",
    "name:ben_x_preferred":[
        "Kuss\u0101rp\u0101ra"
    ],
    "wof:name":"Kussarpara",
    "wof:placetype":"locality"
},
  "geometry": {"coordinates":[91.9782,21.6276],"type":"Point"}
}