{
  "type": "Feature",
  "properties": {
    "gn:admin1_code":"82",
    "gn:admin2_code":"4055.0",
    "gn:admin3_code":"405585.0",
    "gn:admin4_code":"40558535.0",
    "gn:asciiname":"Debila",
    "gn:country_code":"BD",
    "gn:dem":13,
    "gn:feature_class":"P",
    "gn:feature_code":"PPL",
    "gn:name":"Debila",
    "gn:population":0,
    "gn:timezone":"Asia/Dhaka",
    "iso:country":"BD",
    "name:ara_x_preferred":[
        "\u0627\u0644\u062f\u0628\u064a\u0644\u0629"
    ],
    "name:azb_x_preferred":[
        "\u062f\u0628\u06cc\u0644\u0647"
    ],
    "name:ben_x_preferred":[
        "Debila"
    ],
    "name:ceb_x_preferred":[
        "Debila"
    ],
    "name:fas_x_preferred":[
        "\u062f\u0628\u06cc\u0644\u0647"
    ],
    "name:fra_x_preferred":[
        "Debila"
    ],
    "name:ita_x_preferred":[
        "Debila"
    ],
    "name:msa_x_preferred":[
        "Debila"
    ],
    "name:por_x_preferred":[
        "Debila"
    ],
    "name:ron_x_preferred":[
        "Debila"
    ],
    "name:spa_x_preferred":[
        "Debila"
    ],
    "name:swe_x_preferred":[
        "Debila"
    ],
    "name:vie_x_preferred":[
        "Debila"
    ],
    "wof:name":"Debila",
    "wof:placetype":"locality"
},
  "geometry": {"coordinates":[89.27173000000001,23.40342],"type":"Point"}
}