{
  "type": "Feature",
  "properties": {
    "gn:admin1_code":"82",
    "gn:admin2_code":"4055.0",
    "gn:admin3_code":"405585.0",
    "gn:admin4_code":"40558535.0",
    "gn:asciiname":"Debila",
    "gn:country_code":"BD",
    "gn:dem":13,
    "gn:feature_class":"P",
    "gn:feature_code":"PPL",
    "gn:name":"Debila",
    "gn:population":0,
    "gn:timezone":"Asia/Dhaka",
    "iso:country":"BD",
    "name:ben_x_preferred":[
        "Debila"
    ],
    "wof:name":"Debila",
    "wof:placetype":"locality"
},
  "geometry": {"coordinates":[89.27173000000001,23.40342],"type":"Point"}
}