{
  "type": "Feature",
  "properties": {
    "gn:admin1_code":"H",
    "gn:admin2_code":"3039",
    "gn:admin3_code":"303915.0",
    "gn:admin4_code":"30391587.0",
    "gn:asciiname":"Purabhita",
    "gn:country_code":"BD",
    "gn:dem":26,
    "gn:feature_class":"P",
    "gn:feature_code":"PPL",
    "gn:name":"Purabhita",
    "gn:population":0,
    "gn:timezone":"Asia/Dhaka",
    "iso:country":"BD",
    "name:ben_x_preferred":[
        "Purabhita"
    ],
    "wof:name":"Purabhita",
    "wof:placetype":"locality"
},
  "geometry": {"coordinates":[89.78206999999998,25.3182],"type":"Point"}
}