{
  "type": "Feature",
  "properties": {
    "gn:admin1_code":"84",
    "gn:admin2_code":"2013",
    "gn:admin3_code":"201376.0",
    "gn:admin4_code":"20137634.0",
    "gn:asciiname":"Khas Char",
    "gn:country_code":"BD",
    "gn:dem":6,
    "gn:feature_class":"P",
    "gn:feature_code":"PPL",
    "gn:name":"Kh\u0101s Char",
    "gn:population":0,
    "gn:timezone":"Asia/Dhaka",
    "iso:country":"BD",
    "wof:name":"Khas Char",
    "wof:placetype":"locality"
},
  "geometry": {"coordinates":[90.73333,23.36667000000001],"type":"Point"}
}