{
  "type": "Feature",
  "properties": {
    "gn:admin1_code":"H",
    "gn:admin2_code":"3061.0",
    "gn:admin3_code":"306152.0",
    "gn:admin4_code":"30615220.0",
    "gn:asciiname":"Dari Bhabakhali",
    "gn:country_code":"BD",
    "gn:dem":20,
    "gn:feature_class":"P",
    "gn:feature_code":"PPL",
    "gn:name":"Dari Bh\u0101bakh\u0101li",
    "gn:population":0,
    "gn:timezone":"Asia/Dhaka",
    "iso:country":"BD",
    "wof:name":"Dari Bhabakhali",
    "wof:placetype":"locality"
},
  "geometry": {"coordinates":[90.45871,24.68025],"type":"Point"}
}