{
  "type": "Feature",
  "properties": {
    "gn:admin1_code":"H",
    "gn:admin2_code":"3089",
    "gn:admin3_code":"308990.0",
    "gn:admin4_code":"30899071.0",
    "gn:asciiname":"Rangadhan",
    "gn:country_code":"BD",
    "gn:dem":43,
    "gn:feature_class":"P",
    "gn:feature_code":"PPL",
    "gn:name":"R\u0101ng\u0101dhan",
    "gn:population":0,
    "gn:timezone":"Asia/Dhaka",
    "iso:country":"BD",
    "name:ben_x_preferred":[
        "R\u0101ng\u0101dhan"
    ],
    "wof:name":"Rangadhan",
    "wof:placetype":"locality"
},
  "geometry": {"coordinates":[89.98779999999999,25.27753],"type":"Point"}
}