{
  "type": "Feature",
  "properties": {
    "gn:admin1_code":"82",
    "gn:admin2_code":"4044.0",
    "gn:admin3_code":"404471.0",
    "gn:admin4_code":"40447159.0",
    "gn:asciiname":"Bagadanga",
    "gn:country_code":"BD",
    "gn:dem":14,
    "gn:feature_class":"P",
    "gn:feature_code":"PPL",
    "gn:name":"B\u0101g\u0101d\u0101nga",
    "gn:population":0,
    "gn:timezone":"Asia/Dhaka",
    "iso:country":"BD",
    "name:ben_x_preferred":[
        "B\u0101g\u0101d\u0101nga"
    ],
    "name:und_x_variant":[
        "Baghadanga"
    ],
    "wof:name":"Bagadanga",
    "wof:placetype":"locality"
},
  "geometry": {"coordinates":[88.71338,23.29093],"type":"Point"}
}