{
  "type": "Feature",
  "properties": {
    "gn:admin1_code":"83",
    "gn:admin2_code":"5010",
    "gn:admin3_code":"501094.0",
    "gn:admin4_code":"50109479.0",
    "gn:asciiname":"Rangomati",
    "gn:country_code":"BD",
    "gn:dem":23,
    "gn:feature_class":"P",
    "gn:feature_code":"PPL",
    "gn:name":"Rangomati",
    "gn:population":0,
    "gn:timezone":"Asia/Dhaka",
    "iso:country":"BD",
    "name:ben_x_preferred":[
        "Rangomati"
    ],
    "wof:name":"Rangomati",
    "wof:placetype":"locality"
},
  "geometry": {"coordinates":[89.32859999999999,25.0049],"type":"Point"}
}