{
  "type": "Feature",
  "properties": {
    "gn:admin1_code":"87",
    "gn:admin2_code":"5527.0",
    "gn:admin3_code":"552769.0",
    "gn:admin4_code":"55276951.0",
    "gn:asciiname":"Uttar Belpukur",
    "gn:country_code":"BD",
    "gn:dem":34,
    "gn:feature_class":"P",
    "gn:feature_code":"PPL",
    "gn:name":"Uttar Belpukur",
    "gn:population":0,
    "gn:timezone":"Asia/Dhaka",
    "iso:country":"BD",
    "name:ben_x_preferred":[
        "Uttar Belpukur"
    ],
    "wof:name":"Uttar Belpukur",
    "wof:placetype":"locality"
},
  "geometry": {"coordinates":[88.98706,25.49361],"type":"Point"}
}