{
  "type": "Feature",
  "properties": {
    "gn:admin1_code":"81",
    "gn:admin2_code":"3093.0",
    "gn:admin3_code":"309328.0",
    "gn:admin4_code":"30932825.0",
    "gn:asciiname":"Deopara",
    "gn:country_code":"BD",
    "gn:dem":26,
    "gn:feature_class":"P",
    "gn:feature_code":"PPL",
    "gn:name":"Deop\u0101ra",
    "gn:population":0,
    "gn:timezone":"Asia/Dhaka",
    "iso:country":"BD",
    "wof:name":"Deopara",
    "wof:placetype":"locality"
},
  "geometry": {"coordinates":[90.06439,24.40934],"type":"Point"}
}