{
  "type": "Feature",
  "properties": {
    "gn:admin1_code":"87",
    "gn:admin2_code":"5527",
    "gn:admin3_code":"552769.0",
    "gn:admin4_code":"55276986.0",
    "gn:asciiname":"Sonakani",
    "gn:country_code":"BD",
    "gn:dem":31,
    "gn:feature_class":"P",
    "gn:feature_code":"PPL",
    "gn:name":"Sonakani",
    "gn:population":0,
    "gn:timezone":"Asia/Dhaka",
    "iso:country":"BD",
    "name:ben_x_preferred":[
        "Sonakani"
    ],
    "wof:name":"Sonakani",
    "wof:placetype":"locality"
},
  "geometry": {"coordinates":[89.04859999999999,25.35566],"type":"Point"}
}