{
  "type": "Feature",
  "properties": {
    "gn:admin1_code":"84",
    "gn:admin2_code":"2013",
    "gn:admin3_code":"201345.0",
    "gn:admin4_code":"20134577.0",
    "gn:asciiname":"Kutubpur",
    "gn:country_code":"BD",
    "gn:dem":13,
    "gn:feature_class":"P",
    "gn:feature_code":"PPL",
    "gn:name":"Kutubpur",
    "gn:population":0,
    "gn:timezone":"Asia/Dhaka",
    "iso:country":"BD",
    "wof:name":"Kutubpur",
    "wof:placetype":"locality"
},
  "geometry": {"coordinates":[90.78498,23.11706],"type":"Point"}
}