{
  "type": "Feature",
  "properties": {
    "gn:admin1_code":"83",
    "gn:admin2_code":"5064.0",
    "gn:admin3_code":"506447.0",
    "gn:admin4_code":"50644754.0",
    "gn:asciiname":"Chhota Belaldaha",
    "gn:country_code":"BD",
    "gn:dem":22,
    "gn:feature_class":"P",
    "gn:feature_code":"PPL",
    "gn:name":"Chhota Bel\u0101ld\u0101ha",
    "gn:population":0,
    "gn:timezone":"Asia/Dhaka",
    "iso:country":"BD",
    "name:ben_x_preferred":[
        "Chhota Bel\u0101ld\u0101ha"
    ],
    "name:und_x_variant":[
        "Chottobelaldah"
    ],
    "wof:name":"Chhota Belaldaha",
    "wof:placetype":"locality"
},
  "geometry": {"coordinates":[88.70348,24.74678],"type":"Point"}
}