{
  "type": "Feature",
  "properties": {
    "gn:admin1_code":"82",
    "gn:admin2_code":"4047.0",
    "gn:admin3_code":"404764.0",
    "gn:admin4_code":"40476450.0",
    "gn:asciiname":"Birasi",
    "gn:country_code":"BD",
    "gn:dem":7,
    "gn:feature_class":"P",
    "gn:feature_code":"PPL",
    "gn:name":"Bir\u0101si",
    "gn:population":0,
    "gn:timezone":"Asia/Dhaka",
    "iso:country":"BD",
    "wof:name":"Birasi",
    "wof:placetype":"locality"
},
  "geometry": {"coordinates":[89.31289,22.64792000000001],"type":"Point"}
}