{
  "type": "Feature",
  "properties": {
    "gn:admin1_code":"83",
    "gn:admin2_code":"5064.0",
    "gn:admin3_code":"506475.0",
    "gn:admin4_code":"50647534.0",
    "gn:asciiname":"Khurd Barail",
    "gn:country_code":"BD",
    "gn:dem":27,
    "gn:feature_class":"P",
    "gn:feature_code":"PPL",
    "gn:name":"Khurd Bar\u0101il",
    "gn:population":0,
    "gn:timezone":"Asia/Dhaka",
    "iso:country":"BD",
    "name:ben_x_preferred":[
        "Khurd Bar\u0101il"
    ],
    "wof:name":"Khurd Barail",
    "wof:placetype":"locality"
},
  "geometry": {"coordinates":[88.80275999999998,25.04588],"type":"Point"}
}