{
  "type": "Feature",
  "properties": {
    "gn:admin1_code":"87",
    "gn:admin2_code":"5585",
    "gn:admin3_code":"558576.0",
    "gn:admin4_code":"55857650.0",
    "gn:asciiname":"Khetaberpara",
    "gn:country_code":"BD",
    "gn:dem":32,
    "gn:feature_class":"P",
    "gn:feature_code":"PPL",
    "gn:name":"Khetaberpara",
    "gn:population":0,
    "gn:timezone":"Asia/Dhaka",
    "iso:country":"BD",
    "name:ben_x_preferred":[
        "Khetaberpara"
    ],
    "wof:name":"Khetaberpara",
    "wof:placetype":"locality"
},
  "geometry": {"coordinates":[89.19988000000002,25.44915],"type":"Point"}
}