{
  "type": "Feature",
  "properties": {
    "gn:admin1_code":"84",
    "gn:admin2_code":"2019",
    "gn:admin3_code":"201940.0",
    "gn:admin4_code":"20194041.0",
    "gn:asciiname":"Kurchap",
    "gn:country_code":"BD",
    "gn:dem":13,
    "gn:feature_class":"P",
    "gn:feature_code":"PPL",
    "gn:name":"Kurch\u0101p",
    "gn:population":0,
    "gn:timezone":"Asia/Dhaka",
    "iso:country":"BD",
    "wof:name":"Kurchap",
    "wof:placetype":"locality"
},
  "geometry": {"coordinates":[90.97918,23.49819],"type":"Point"}
}