{
  "type": "Feature",
  "properties": {
    "gn:admin1_code":"81",
    "gn:admin2_code":"3086",
    "gn:admin3_code":"308636.0",
    "gn:admin4_code":"30863635.0",
    "gn:asciiname":"Puber Char",
    "gn:cc2":"BD",
    "gn:country_code":"BD",
    "gn:dem":6,
    "gn:feature_class":"P",
    "gn:feature_code":"PPL",
    "gn:name":"Puber Char",
    "gn:population":0,
    "gn:timezone":"Asia/Dhaka",
    "iso:country":"BD",
    "name:und_x_variant":[
        "Pubberchar",
        "Puber Char"
    ],
    "wof:name":"Puber Char",
    "wof:placetype":"locality"
},
  "geometry": {"coordinates":[90.38333,23.06667],"type":"Point"}
}