{
  "type": "Feature",
  "properties": {
    "gn:admin1_code":"81",
    "gn:admin2_code":"3033.0",
    "gn:admin3_code":"303332.0",
    "gn:admin4_code":"30333247.0",
    "gn:asciiname":"Basakair",
    "gn:country_code":"BD",
    "gn:dem":20,
    "gn:feature_class":"P",
    "gn:feature_code":"PPL",
    "gn:name":"B\u0101s\u0101kair",
    "gn:population":0,
    "gn:timezone":"Asia/Dhaka",
    "iso:country":"BD",
    "wof:name":"Basakair",
    "wof:placetype":"locality"
},
  "geometry": {"coordinates":[90.29131,24.19566],"type":"Point"}
}