{
  "type": "Feature",
  "properties": {
    "gn:admin1_code":"86",
    "gn:admin2_code":"6036",
    "gn:admin3_code":"603602.0",
    "gn:admin4_code":"60360267.0",
    "gn:asciiname":"Kamalpur",
    "gn:country_code":"BD",
    "gn:dem":11,
    "gn:feature_class":"P",
    "gn:feature_code":"PPL",
    "gn:name":"K\u0101m\u0101lpur",
    "gn:population":0,
    "gn:timezone":"Asia/Dhaka",
    "iso:country":"BD",
    "name:cat_x_preferred":[
        "Kamalpur"
    ],
    "name:ceb_x_preferred":[
        "Kamalpur"
    ],
    "name:fra_x_preferred":[
        "Kamalpur"
    ],
    "name:swe_x_preferred":[
        "Kamalpur"
    ],
    "name:tam_x_preferred":[
        "\u0b95\u0bae\u0bb2\u0bcd\u0baa\u0bc2\u0bb0\u0bcd"
    ],
    "wof:name":"Kamalpur",
    "wof:placetype":"locality"
},
  "geometry": {"coordinates":[91.16907,24.49491],"type":"Point"}
}