{
  "type": "Feature",
  "properties": {
    "gn:admin1_code":"82",
    "gn:admin2_code":"4065.0",
    "gn:admin3_code":"406528.0",
    "gn:admin4_code":"40652871.0",
    "gn:asciiname":"Kalagachhi",
    "gn:country_code":"BD",
    "gn:dem":12,
    "gn:feature_class":"P",
    "gn:feature_code":"PPL",
    "gn:name":"Kal\u0101g\u0101chhi",
    "gn:population":0,
    "gn:timezone":"Asia/Dhaka",
    "iso:country":"BD",
    "name:ben_x_preferred":[
        "Kal\u0101g\u0101chhi"
    ],
    "wof:name":"Kalagachhi",
    "wof:placetype":"locality"
},
  "geometry": {"coordinates":[89.66632,23.08604],"type":"Point"}
}