{
  "type": "Feature",
  "properties": {
    "gn:admin1_code":"84",
    "gn:admin2_code":"2022.0",
    "gn:admin3_code":"202245.0",
    "gn:admin4_code":"20224581.0",
    "gn:asciiname":"Sahanamdia",
    "gn:country_code":"BD",
    "gn:dem":7,
    "gn:feature_class":"P",
    "gn:feature_code":"PPL",
    "gn:name":"S\u0101h\u0101n\u0101mdia",
    "gn:population":0,
    "gn:timezone":"Asia/Dhaka",
    "iso:country":"BD",
    "name:ben_x_preferred":[
        "S\u0101h\u0101n\u0101mdia"
    ],
    "wof:name":"Sahanamdia",
    "wof:placetype":"locality"
},
  "geometry": {"coordinates":[91.87358999999999,21.87917],"type":"Point"}
}