{
  "type": "Feature",
  "properties": {
    "gn:admin1_code":"83",
    "gn:admin2_code":"5064.0",
    "gn:admin3_code":"506475.0",
    "gn:admin4_code":"50647508.0",
    "gn:asciiname":"Kutura",
    "gn:country_code":"BD",
    "gn:dem":25,
    "gn:feature_class":"P",
    "gn:feature_code":"PPL",
    "gn:name":"Kutura",
    "gn:population":0,
    "gn:timezone":"Asia/Dhaka",
    "iso:country":"BD",
    "name:ben_x_preferred":[
        "Kutura"
    ],
    "wof:name":"Kutura",
    "wof:placetype":"locality"
},
  "geometry": {"coordinates":[88.66113,25.0563],"type":"Point"}
}