{
  "type": "Feature",
  "properties": {
    "gn:admin1_code":"84",
    "gn:admin2_code":"2012.0",
    "gn:admin3_code":"201204.0",
    "gn:admin4_code":"20120488.0",
    "gn:asciiname":"Hasannagar",
    "gn:country_code":"BD",
    "gn:dem":12,
    "gn:feature_class":"P",
    "gn:feature_code":"PPL",
    "gn:name":"H\u0101sannagar",
    "gn:population":0,
    "gn:timezone":"Asia/Dhaka",
    "iso:country":"BD",
    "wof:name":"Hasannagar",
    "wof:placetype":"locality"
},
  "geometry": {"coordinates":[90.87739999999999,23.80953],"type":"Point"}
}