{
  "type": "Feature",
  "properties": {
    "gn:admin1_code":"H",
    "gn:admin2_code":"3089",
    "gn:admin3_code":"308967.0",
    "gn:admin4_code":"30896719.0",
    "gn:asciiname":"Rauha",
    "gn:country_code":"BD",
    "gn:dem":19,
    "gn:feature_class":"P",
    "gn:feature_code":"PPL",
    "gn:name":"Rauha",
    "gn:population":0,
    "gn:timezone":"Asia/Dhaka",
    "iso:country":"BD",
    "wof:name":"Rauha",
    "wof:placetype":"locality"
},
  "geometry": {"coordinates":[90.13333,24.91667],"type":"Point"}
}