{
  "type": "Feature",
  "properties": {
    "gn:admin1_code":"84",
    "gn:admin2_code":"2015.0",
    "gn:admin3_code":"201547.0",
    "gn:admin4_code":"20154762.0",
    "gn:asciiname":"Lobagara",
    "gn:country_code":"BD",
    "gn:dem":19,
    "gn:feature_class":"P",
    "gn:feature_code":"PPL",
    "gn:name":"Lob\u0101gara",
    "gn:population":0,
    "gn:timezone":"Asia/Dhaka",
    "iso:country":"BD",
    "name:ben_x_preferred":[
        "Lob\u0101gara"
    ],
    "wof:name":"Lobagara",
    "wof:placetype":"locality"
},
  "geometry": {"coordinates":[92.11099,21.99438],"type":"Point"}
}