{
  "type": "Feature",
  "properties": {
    "gn:admin1_code":"85",
    "gn:admin2_code":"1078.0",
    "gn:admin3_code":"107866.0",
    "gn:admin4_code":"10786671.0",
    "gn:asciiname":"Chandpara",
    "gn:country_code":"BD",
    "gn:dem":10,
    "gn:feature_class":"P",
    "gn:feature_code":"PPL",
    "gn:name":"Ch\u0101ndp\u0101ra",
    "gn:population":0,
    "gn:timezone":"Asia/Dhaka",
    "iso:country":"BD",
    "name:ben_x_preferred":[
        "Ch\u0101ndp\u0101ra"
    ],
    "name:ben_x_variant":[
        "\u099a\u09be\u0981\u09a6\u09aa\u09be\u09a1\u09bc\u09be"
    ],
    "wof:name":"Chandpara",
    "wof:placetype":"locality"
},
  "geometry": {"coordinates":[90.16622,21.9511],"type":"Point"}
}