{
  "type": "Feature",
  "properties": {
    "gn:admin1_code":"81",
    "gn:admin2_code":"3033.0",
    "gn:admin3_code":"303334.0",
    "gn:admin4_code":"30333469.0",
    "gn:asciiname":"Bariadi",
    "gn:country_code":"BD",
    "gn:dem":12,
    "gn:feature_class":"P",
    "gn:feature_code":"PPL",
    "gn:name":"B\u0101ri\u0101di",
    "gn:population":0,
    "gn:timezone":"Asia/Dhaka",
    "iso:country":"BD",
    "name:ceb_x_preferred":[
        "Bariadi"
    ],
    "name:fin_x_preferred":[
        "Bariadi"
    ],
    "name:fra_x_preferred":[
        "Bariadi"
    ],
    "name:ita_x_preferred":[
        "Bariadi"
    ],
    "name:swa_x_preferred":[
        "Bariadi"
    ],
    "wof:name":"Bariadi",
    "wof:placetype":"locality"
},
  "geometry": {"coordinates":[90.511,24.01296],"type":"Point"}
}