{
  "type": "Feature",
  "properties": {
    "gn:admin1_code":"H",
    "gn:admin2_code":"3061.0",
    "gn:admin3_code":"306181.0",
    "gn:admin4_code":"30618167.0",
    "gn:asciiname":"Char Satfa",
    "gn:country_code":"BD",
    "gn:dem":19,
    "gn:feature_class":"P",
    "gn:feature_code":"PPL",
    "gn:name":"Char S\u0101tfa",
    "gn:population":0,
    "gn:timezone":"Asia/Dhaka",
    "iso:country":"BD",
    "name:und_x_variant":[
        "Char S\u0101tfa",
        "Char S\u0101lfa"
    ],
    "wof:name":"Char Satfa",
    "wof:placetype":"locality"
},
  "geometry": {"coordinates":[90.28642000000001,24.89564],"type":"Point"}
}