{
  "type": "Feature",
  "properties": {
    "gn:admin1_code":"83",
    "gn:admin2_code":"5064.0",
    "gn:admin3_code":"506469.0",
    "gn:admin4_code":"50646973.0",
    "gn:asciiname":"Jamurhat",
    "gn:country_code":"BD",
    "gn:dem":42,
    "gn:feature_class":"P",
    "gn:feature_code":"PPL",
    "gn:name":"J\u0101murhat",
    "gn:population":0,
    "gn:timezone":"Asia/Dhaka",
    "iso:country":"BD",
    "name:ben_x_preferred":[
        "J\u0101murhat"
    ],
    "wof:name":"Jamurhat",
    "wof:placetype":"locality"
},
  "geometry": {"coordinates":[88.48045,24.81358],"type":"Point"}
}