{
  "type": "Feature",
  "properties": {
    "gn:admin1_code":"81",
    "gn:admin2_code":"3067",
    "gn:admin3_code":"306768.0",
    "gn:admin4_code":"30676871.0",
    "gn:asciiname":"Mathbari",
    "gn:country_code":"BD",
    "gn:dem":16,
    "gn:feature_class":"P",
    "gn:feature_code":"PPL",
    "gn:name":"Mathb\u0101ri",
    "gn:population":0,
    "gn:timezone":"Asia/Dhaka",
    "iso:country":"BD",
    "wof:name":"Mathbari",
    "wof:placetype":"locality"
},
  "geometry": {"coordinates":[90.48048,23.87286],"type":"Point"}
}