{
  "type": "Feature",
  "properties": {
    "gn:admin1_code":"84",
    "gn:admin2_code":"2003.0",
    "gn:admin3_code":"200314.0",
    "gn:admin4_code":"20031431.0",
    "gn:asciiname":"Barathali",
    "gn:country_code":"BD",
    "gn:dem":24,
    "gn:feature_class":"P",
    "gn:feature_code":"PPL",
    "gn:name":"Bar\u0101thali",
    "gn:population":0,
    "gn:timezone":"Asia/Dhaka",
    "iso:country":"BD",
    "name:ben_x_preferred":[
        "Bar\u0101thali"
    ],
    "wof:name":"Barathali",
    "wof:placetype":"locality"
},
  "geometry": {"coordinates":[92.14315000000001,22.234],"type":"Point"}
}