{
  "type": "Feature",
  "properties": {
    "gn:admin1_code":"83",
    "gn:admin2_code":"5088",
    "gn:admin3_code":"508861.0",
    "gn:admin4_code":"50886138.0",
    "gn:asciiname":"Raiganj",
    "gn:country_code":"BD",
    "gn:dem":19,
    "gn:feature_class":"P",
    "gn:feature_code":"PPL",
    "gn:name":"Raiganj",
    "gn:population":0,
    "gn:timezone":"Asia/Dhaka",
    "iso:country":"BD",
    "name:ben_x_preferred":[
        "\u09b0\u09be\u09af\u09bc\u0997\u099e\u09cd\u099c"
    ],
    "name:bih_x_preferred":[
        "\u0930\u093e\u092f\u0917\u0902\u091c"
    ],
    "name:cat_x_preferred":[
        "Raiganj"
    ],
    "name:ceb_x_preferred":[
        "R\u0101iganj"
    ],
    "name:fra_x_preferred":[
        "Raiganj"
    ],
    "name:guj_x_preferred":[
        "\u0ab0\u0abe\u0aaf\u0a97\u0a82\u0a9c"
    ],
    "name:hif_x_preferred":[
        "Raiganj"
    ],
    "name:hin_x_preferred":[
        "\u0930\u093e\u092f\u0917\u0902\u091c"
    ],
    "name:ita_x_preferred":[
        "Raiganj"
    ],
    "name:mar_x_preferred":[
        "\u0930\u093e\u092f\u0917\u0902\u091c"
    ],
    "name:mlg_x_preferred":[
        "Raiganj"
    ],
    "name:msa_x_preferred":[
        "Raiganj"
    ],
    "name:ori_x_preferred":[
        "\u0b30\u0b3e\u0b07\u0b17\u0b1e\u0b4d\u0b1c"
    ],
    "name:rus_x_preferred":[
        "\u0420\u0430\u0439\u0433\u0430\u043d\u0434\u0436"
    ],
    "name:spa_x_preferred":[
        "Raiganj"
    ],
    "name:swe_x_preferred":[
        "Raiganj"
    ],
    "name:tam_x_preferred":[
        "\u0bb0\u0bbe\u0baf\u0bcd\u0b95\u0bbe\u0b9e\u0bcd\u0b9a\u0bcd"
    ],
    "name:und_x_variant":[
        "Rayganj",
        "Raiganj"
    ],
    "name:urd_x_preferred":[
        "\u0631\u0627\u0626\u06d2 \u06af\u0646\u062c"
    ],
    "name:vie_x_preferred":[
        "Raiganj"
    ],
    "name:war_x_preferred":[
        "Raiganj"
    ],
    "name:zho_x_preferred":[
        "\u8d56\u7518\u6770"
    ],
    "wof:name":"Raiganj",
    "wof:placetype":"locality"
},
  "geometry": {"coordinates":[89.52738000000002,24.50735],"type":"Point"}
}