{
  "type": "Feature",
  "properties": {
    "gn:admin1_code":"83",
    "gn:admin2_code":"5088",
    "gn:admin3_code":"508861.0",
    "gn:admin4_code":"50886138.0",
    "gn:asciiname":"Raiganj",
    "gn:country_code":"BD",
    "gn:dem":19,
    "gn:feature_class":"P",
    "gn:feature_code":"PPL",
    "gn:name":"Raiganj",
    "gn:population":0,
    "gn:timezone":"Asia/Dhaka",
    "iso:country":"BD",
    "name:und_x_variant":[
        "Rayganj",
        "Raiganj"
    ],
    "wof:name":"Raiganj",
    "wof:placetype":"locality"
},
  "geometry": {"coordinates":[89.52738000000002,24.50735],"type":"Point"}
}