{
  "type": "Feature",
  "properties": {
    "gn:admin1_code":"87",
    "gn:admin2_code":"5549",
    "gn:admin3_code":"554952.0",
    "gn:admin4_code":"55495228.0",
    "gn:asciiname":"Ghogadaha",
    "gn:country_code":"BD",
    "gn:dem":32,
    "gn:feature_class":"P",
    "gn:feature_code":"PPL",
    "gn:name":"Ghog\u0101daha",
    "gn:population":0,
    "gn:timezone":"Asia/Dhaka",
    "iso:country":"BD",
    "name:ben_x_preferred":[
        "Ghog\u0101daha"
    ],
    "wof:name":"Ghogadaha",
    "wof:placetype":"locality"
},
  "geometry": {"coordinates":[89.71653000000001,25.84639],"type":"Point"}
}