{
  "type": "Feature",
  "properties": {
    "gn:admin1_code":"81",
    "gn:admin2_code":"3067.0",
    "gn:admin3_code":"306704.0",
    "gn:admin4_code":"30670486.0",
    "gn:asciiname":"Ghoshair Chak",
    "gn:country_code":"BD",
    "gn:dem":7,
    "gn:feature_class":"P",
    "gn:feature_code":"PPL",
    "gn:name":"Ghosh\u0101ir Chak",
    "gn:population":0,
    "gn:timezone":"Asia/Dhaka",
    "iso:country":"BD",
    "name:und_x_variant":[
        "Ghosh\u0101ir Chak",
        "Ghosher Chak"
    ],
    "wof:name":"Ghoshair Chak",
    "wof:placetype":"locality"
},
  "geometry": {"coordinates":[90.57177,23.62291],"type":"Point"}
}