{
  "type": "Feature",
  "properties": {
    "gn:admin1_code":"85",
    "gn:admin2_code":"1042",
    "gn:admin3_code":"104240.0",
    "gn:admin4_code":"10424095.0",
    "gn:asciiname":"Kansa",
    "gn:country_code":"BD",
    "gn:dem":13,
    "gn:feature_class":"P",
    "gn:feature_code":"PPL",
    "gn:name":"K\u0101nsa",
    "gn:population":0,
    "gn:timezone":"Asia/Dhaka",
    "iso:country":"BD",
    "wof:name":"Kansa",
    "wof:placetype":"locality"
},
  "geometry": {"coordinates":[90.12958,22.66192],"type":"Point"}
}