{
  "type": "Feature",
  "properties": {
    "gn:admin1_code":"87",
    "gn:admin2_code":"5527.0",
    "gn:admin3_code":"552764.0",
    "gn:admin4_code":"55276408.0",
    "gn:asciiname":"Sundara",
    "gn:country_code":"BD",
    "gn:dem":36,
    "gn:feature_class":"P",
    "gn:feature_code":"PPL",
    "gn:name":"Sundara",
    "gn:population":0,
    "gn:timezone":"Asia/Dhaka",
    "iso:country":"BD",
    "name:ben_x_preferred":[
        "Sundara"
    ],
    "wof:name":"Sundara",
    "wof:placetype":"locality"
},
  "geometry": {"coordinates":[88.59933000000002,25.51986],"type":"Point"}
}