{
  "type": "Feature",
  "properties": {
    "gn:admin1_code":"84",
    "gn:admin2_code":"2019.0",
    "gn:admin3_code":"201918.0",
    "gn:admin4_code":"20191806.0",
    "gn:asciiname":"Balarampur",
    "gn:cc2":"BD",
    "gn:country_code":"BD",
    "gn:dem":12,
    "gn:feature_class":"P",
    "gn:feature_code":"PPL",
    "gn:name":"Balar\u0101mpur",
    "gn:population":0,
    "gn:timezone":"Asia/Dhaka",
    "iso:country":"BD",
    "name:und_x_variant":[
        "North Balarampur",
        "Balar\u0101mpur"
    ],
    "wof:name":"Balarampur",
    "wof:placetype":"locality"
},
  "geometry": {"coordinates":[91.16667,23.53333],"type":"Point"}
}