{
  "type": "Feature",
  "properties": {
    "gn:admin1_code":"83",
    "gn:admin2_code":"5064.0",
    "gn:admin3_code":"506447.0",
    "gn:admin4_code":"50644747.0",
    "gn:asciiname":"Bharat Sibnagar",
    "gn:cc2":"BD",
    "gn:country_code":"BD",
    "gn:dem":15,
    "gn:feature_class":"P",
    "gn:feature_code":"PPL",
    "gn:name":"Bharat Sibnagar",
    "gn:population":0,
    "gn:timezone":"Asia/Dhaka",
    "iso:country":"BD",
    "name:und_x_variant":[
        "Bharatshibnagar",
        "Bharat Sibnagar"
    ],
    "wof:name":"Bharat Sibnagar",
    "wof:placetype":"locality"
},
  "geometry": {"coordinates":[88.78333000000001,24.71667],"type":"Point"}
}