{
  "type": "Feature",
  "properties": {
    "gn:admin1_code":"87",
    "gn:admin2_code":"5549",
    "gn:admin3_code":"554961.0",
    "gn:admin4_code":"55496163.0",
    "gn:asciiname":"Char Phakiura",
    "gn:country_code":"BD",
    "gn:dem":33,
    "gn:feature_class":"P",
    "gn:feature_code":"PPL",
    "gn:name":"Char Ph\u0101kiura",
    "gn:population":0,
    "gn:timezone":"Asia/Dhaka",
    "iso:country":"BD",
    "name:ben_x_preferred":[
        "Char Ph\u0101kiura"
    ],
    "wof:name":"Char Phakiura",
    "wof:placetype":"locality"
},
  "geometry": {"coordinates":[89.86349,25.92268],"type":"Point"}
}