{
  "type": "Feature",
  "properties": {
    "gn:admin1_code":"83",
    "gn:admin2_code":"5081",
    "gn:admin3_code":"508134.0",
    "gn:admin4_code":"50813447.0",
    "gn:asciiname":"Paranpur",
    "gn:country_code":"BD",
    "gn:dem":17,
    "gn:feature_class":"P",
    "gn:feature_code":"PPL",
    "gn:name":"Paranpur",
    "gn:population":0,
    "gn:timezone":"Asia/Dhaka",
    "iso:country":"BD",
    "name:ben_x_preferred":[
        "Paranpur"
    ],
    "name:ben_x_variant":[
        "Pr\u0101npur"
    ],
    "wof:name":"Paranpur",
    "wof:placetype":"locality"
},
  "geometry": {"coordinates":[88.46593,24.44881],"type":"Point"}
}