{
  "type": "Feature",
  "properties": {
    "gn:admin1_code":"83",
    "gn:admin2_code":"5064.0",
    "gn:admin3_code":"506406.0",
    "gn:admin4_code":"50640673.0",
    "gn:asciiname":"Morla",
    "gn:country_code":"BD",
    "gn:dem":21,
    "gn:feature_class":"P",
    "gn:feature_code":"PPL",
    "gn:name":"Morla",
    "gn:population":0,
    "gn:timezone":"Asia/Dhaka",
    "iso:country":"BD",
    "name:ben_x_preferred":[
        "Morla"
    ],
    "name:deu_x_preferred":[
        "Morla"
    ],
    "name:ita_x_preferred":[
        "Morla"
    ],
    "name:lmo_x_preferred":[
        "M\u00f3rla"
    ],
    "wof:name":"Morla",
    "wof:placetype":"locality"
},
  "geometry": {"coordinates":[88.93078,25.01985],"type":"Point"}
}