{
  "type": "Feature",
  "properties": {
    "gn:admin1_code":"H",
    "gn:admin2_code":"3061.0",
    "gn:admin3_code":"306123.0",
    "gn:admin4_code":"30612327.0",
    "gn:asciiname":"Churali",
    "gn:country_code":"BD",
    "gn:dem":17,
    "gn:feature_class":"P",
    "gn:feature_code":"PPL",
    "gn:name":"Chur\u0101li",
    "gn:population":0,
    "gn:timezone":"Asia/Dhaka",
    "iso:country":"BD",
    "wof:name":"Churali",
    "wof:placetype":"locality"
},
  "geometry": {"coordinates":[90.5283,24.74423],"type":"Point"}
}