{
  "type": "Feature",
  "properties": {
    "gn:admin1_code":"83",
    "gn:admin2_code":"5064",
    "gn:admin3_code":"506447.0",
    "gn:admin4_code":"50644767.0",
    "gn:asciiname":"Kalachita",
    "gn:country_code":"BD",
    "gn:dem":24,
    "gn:feature_class":"P",
    "gn:feature_code":"PPL",
    "gn:name":"Kal\u0101chita",
    "gn:population":0,
    "gn:timezone":"Asia/Dhaka",
    "iso:country":"BD",
    "name:ben_x_preferred":[
        "Kal\u0101chita"
    ],
    "wof:name":"Kalachita",
    "wof:placetype":"locality"
},
  "geometry": {"coordinates":[88.68234,24.80749],"type":"Point"}
}