{
  "type": "Feature",
  "properties": {
    "gn:admin1_code":"87",
    "gn:admin2_code":"5594.0",
    "gn:admin3_code":"559486.0",
    "gn:admin4_code":"55948615.0",
    "gn:asciiname":"Doshia",
    "gn:country_code":"BD",
    "gn:dem":52,
    "gn:feature_class":"P",
    "gn:feature_code":"PPL",
    "gn:name":"Doshia",
    "gn:population":0,
    "gn:timezone":"Asia/Dhaka",
    "iso:country":"BD",
    "name:ben_x_preferred":[
        "Doshia"
    ],
    "wof:name":"Doshia",
    "wof:placetype":"locality"
},
  "geometry": {"coordinates":[88.29938,25.89296],"type":"Point"}
}