{
  "type": "Feature",
  "properties": {
    "gn:admin1_code":"86",
    "gn:admin2_code":"6090",
    "gn:admin3_code":"609092.0",
    "gn:admin4_code":"60909292.0",
    "gn:asciiname":"Tekerghat",
    "gn:country_code":"BD",
    "gn:dem":14,
    "gn:feature_class":"P",
    "gn:feature_code":"PPL",
    "gn:name":"Tekerghat",
    "gn:population":0,
    "gn:timezone":"Asia/Dhaka",
    "iso:country":"BD",
    "name:und_x_variant":[
        "Takerhat"
    ],
    "wof:name":"Tekerghat",
    "wof:placetype":"locality"
},
  "geometry": {"coordinates":[91.1604,25.19397],"type":"Point"}
}