{
  "type": "Feature",
  "properties": {
    "gn:admin1_code":"82",
    "gn:admin2_code":"4047",
    "gn:admin3_code":"404764.0",
    "gn:admin4_code":"40476416.0",
    "gn:asciiname":"Shahapara",
    "gn:country_code":"BD",
    "gn:dem":7,
    "gn:feature_class":"P",
    "gn:feature_code":"PPL",
    "gn:name":"Sh\u0101h\u0101p\u0101ra",
    "gn:population":0,
    "gn:timezone":"Asia/Dhaka",
    "iso:country":"BD",
    "name:und_x_variant":[
        "Sahapara",
        "Sh\u0101h\u0101p\u0101ra"
    ],
    "wof:name":"Shahapara",
    "wof:placetype":"locality"
},
  "geometry": {"coordinates":[89.24216,22.54454],"type":"Point"}
}