{
  "type": "Feature",
  "properties": {
    "gn:admin1_code":"83",
    "gn:admin2_code":"5069",
    "gn:admin3_code":"506909.0",
    "gn:admin4_code":"50690919.0",
    "gn:asciiname":"Khondakar Malanchi",
    "gn:country_code":"BD",
    "gn:dem":20,
    "gn:feature_class":"P",
    "gn:feature_code":"PPL",
    "gn:name":"Khondakar M\u0101lanchi",
    "gn:population":0,
    "gn:timezone":"Asia/Dhaka",
    "iso:country":"BD",
    "name:ben_x_preferred":[
        "Khondakar M\u0101lanchi"
    ],
    "wof:name":"Khondakar Malanchi",
    "wof:placetype":"locality"
},
  "geometry": {"coordinates":[88.9299,24.31732],"type":"Point"}
}