{
  "type": "Feature",
  "properties": {
    "gn:admin1_code":"87",
    "gn:admin2_code":"5552.0",
    "gn:admin3_code":"555202.0",
    "gn:admin4_code":"55520241.0",
    "gn:asciiname":"Dakshin Gobdha",
    "gn:country_code":"BD",
    "gn:dem":38,
    "gn:feature_class":"P",
    "gn:feature_code":"PPL",
    "gn:name":"Dakshin Gobdha",
    "gn:population":0,
    "gn:timezone":"Asia/Dhaka",
    "iso:country":"BD",
    "name:ben_x_preferred":[
        "Dakshin Gobdha"
    ],
    "wof:name":"Dakshin Gobdha",
    "wof:placetype":"locality"
},
  "geometry": {"coordinates":[89.39533,25.99041],"type":"Point"}
}