{
  "type": "Feature",
  "properties": {
    "gn:admin1_code":"H",
    "gn:admin2_code":"3072",
    "gn:admin3_code":"307263.0",
    "gn:admin4_code":"30726373.0",
    "gn:asciiname":"Ranahijal",
    "gn:country_code":"BD",
    "gn:dem":13,
    "gn:feature_class":"P",
    "gn:feature_code":"PPL",
    "gn:name":"R\u0101n\u0101hijal",
    "gn:population":0,
    "gn:timezone":"Asia/Dhaka",
    "iso:country":"BD",
    "wof:name":"Ranahijal",
    "wof:placetype":"locality"
},
  "geometry": {"coordinates":[90.98884,24.79243],"type":"Point"}
}