{
  "type": "Feature",
  "properties": {
    "gn:admin1_code":"84",
    "gn:admin2_code":"2075.0",
    "gn:admin3_code":"207536.0",
    "gn:admin4_code":"20753619.0",
    "gn:asciiname":"Harni",
    "gn:country_code":"BD",
    "gn:dem":4,
    "gn:feature_class":"P",
    "gn:feature_code":"PPL",
    "gn:name":"Harni",
    "gn:population":0,
    "gn:timezone":"Asia/Dhaka",
    "iso:country":"BD",
    "wof:name":"Harni",
    "wof:placetype":"locality"
},
  "geometry": {"coordinates":[91.09999999999999,22.48333],"type":"Point"}
}