{
  "type": "Feature",
  "properties": {
    "gn:admin1_code":"82",
    "gn:admin2_code":"4001.0",
    "gn:admin3_code":"400177.0",
    "gn:admin4_code":"40017719.0",
    "gn:asciiname":"Sailabunia",
    "gn:country_code":"BD",
    "gn:dem":9,
    "gn:feature_class":"P",
    "gn:feature_code":"PPL",
    "gn:name":"Sailabunia",
    "gn:population":0,
    "gn:timezone":"Asia/Dhaka",
    "iso:country":"BD",
    "name:ben_x_preferred":[
        "Sailabunia"
    ],
    "wof:name":"Sailabunia",
    "wof:placetype":"locality"
},
  "geometry": {"coordinates":[89.80512,22.33729],"type":"Point"}
}