{
  "type": "Feature",
  "properties": {
    "gn:admin1_code":"81",
    "gn:admin2_code":"3067",
    "gn:admin3_code":"306706.0",
    "gn:admin4_code":"30670647.0",
    "gn:asciiname":"Nisang",
    "gn:country_code":"BD",
    "gn:dem":8,
    "gn:feature_class":"P",
    "gn:feature_code":"PPL",
    "gn:name":"Nisang",
    "gn:population":0,
    "gn:timezone":"Asia/Dhaka",
    "iso:country":"BD",
    "wof:name":"Nisang",
    "wof:placetype":"locality"
},
  "geometry": {"coordinates":[90.54196,23.58459],"type":"Point"}
}