{
  "type": "Feature",
  "properties": {
    "gn:admin1_code":"84",
    "gn:admin2_code":"2013.0",
    "gn:admin3_code":"201376.0",
    "gn:admin4_code":"20137643.0",
    "gn:asciiname":"Gabua",
    "gn:country_code":"BD",
    "gn:dem":11,
    "gn:feature_class":"P",
    "gn:feature_code":"PPL",
    "gn:name":"G\u0101bua",
    "gn:population":0,
    "gn:timezone":"Asia/Dhaka",
    "iso:country":"BD",
    "wof:name":"Gabua",
    "wof:placetype":"locality"
},
  "geometry": {"coordinates":[90.76875,23.33234],"type":"Point"}
}