{
  "type": "Feature",
  "properties": {
    "gn:admin1_code":"83",
    "gn:admin2_code":"5064.0",
    "gn:admin3_code":"506406.0",
    "gn:admin4_code":"50640610.0",
    "gn:asciiname":"Byaspur",
    "gn:country_code":"BD",
    "gn:dem":23,
    "gn:feature_class":"P",
    "gn:feature_code":"PPL",
    "gn:name":"By\u0101spur",
    "gn:population":0,
    "gn:timezone":"Asia/Dhaka",
    "iso:country":"BD",
    "name:ben_x_preferred":[
        "By\u0101spur"
    ],
    "name:und_x_variant":[
        "Byashpur"
    ],
    "wof:name":"Byaspur",
    "wof:placetype":"locality"
},
  "geometry": {"coordinates":[88.94193,24.95785],"type":"Point"}
}