{
  "type": "Feature",
  "properties": {
    "gn:admin1_code":"83",
    "gn:admin2_code":"5010",
    "gn:admin3_code":"501040.0",
    "gn:admin4_code":"50104067.0",
    "gn:asciiname":"Nashipur",
    "gn:country_code":"BD",
    "gn:dem":23,
    "gn:feature_class":"P",
    "gn:feature_code":"PPL",
    "gn:name":"Nashipur",
    "gn:population":0,
    "gn:timezone":"Asia/Dhaka",
    "iso:country":"BD",
    "name:hin_x_preferred":[
        "\u0928\u0938\u0940\u092a\u0941\u0930"
    ],
    "name:und_x_variant":[
        "Nasipur",
        "Nashipur"
    ],
    "wof:name":"Nashipur",
    "wof:placetype":"locality"
},
  "geometry": {"coordinates":[89.46013000000001,24.78719],"type":"Point"}
}