{
  "type": "Feature",
  "properties": {
    "gn:admin1_code":"87",
    "gn:admin2_code":"5527",
    "gn:admin3_code":"552717.0",
    "gn:admin4_code":"55271757.0",
    "gn:asciiname":"Jagatpur",
    "gn:country_code":"BD",
    "gn:dem":36,
    "gn:feature_class":"P",
    "gn:feature_code":"PPL",
    "gn:name":"Jagatpur",
    "gn:population":0,
    "gn:timezone":"Asia/Dhaka",
    "iso:country":"BD",
    "name:ben_x_preferred":[
        "Jagatpur"
    ],
    "wof:name":"Jagatpur",
    "wof:placetype":"locality"
},
  "geometry": {"coordinates":[88.53107,25.57675],"type":"Point"}
}