{
  "type": "Feature",
  "properties": {
    "gn:admin1_code":"H",
    "gn:admin2_code":"3089",
    "gn:admin3_code":"308970.0",
    "gn:admin4_code":"30897051.0",
    "gn:asciiname":"Dhubakura",
    "gn:country_code":"BD",
    "gn:dem":26,
    "gn:feature_class":"P",
    "gn:feature_code":"PPL",
    "gn:name":"Dhubakura",
    "gn:population":0,
    "gn:timezone":"Asia/Dhaka",
    "iso:country":"BD",
    "name:ben_x_preferred":[
        "Dhubakura"
    ],
    "wof:name":"Dhubakura",
    "wof:placetype":"locality"
},
  "geometry": {"coordinates":[90.24284,25.15415],"type":"Point"}
}