{
  "type": "Feature",
  "properties": {
    "gn:admin1_code":"81",
    "gn:admin2_code":"3056",
    "gn:admin3_code":"305610.0",
    "gn:admin4_code":"30561066.0",
    "gn:asciiname":"Pantircha",
    "gn:country_code":"BD",
    "gn:dem":14,
    "gn:feature_class":"P",
    "gn:feature_code":"PPL",
    "gn:name":"Pantircha",
    "gn:population":0,
    "gn:timezone":"Asia/Dhaka",
    "iso:country":"BD",
    "wof:name":"Pantircha",
    "wof:placetype":"locality"
},
  "geometry": {"coordinates":[89.81222,23.96909],"type":"Point"}
}