{
  "type": "Feature",
  "properties": {
    "gn:admin1_code":"81",
    "gn:admin2_code":"3029.0",
    "gn:admin3_code":"302918.0",
    "gn:admin4_code":"30291840.0",
    "gn:asciiname":"Chandani",
    "gn:country_code":"BD",
    "gn:dem":13,
    "gn:feature_class":"P",
    "gn:feature_code":"PPL",
    "gn:name":"Chandani",
    "gn:population":0,
    "gn:timezone":"Asia/Dhaka",
    "iso:country":"BD",
    "name:ceb_x_preferred":[
        "Chandani"
    ],
    "name:dty_x_preferred":[
        "\u091a\u093e\u0901\u0926\u0928\u0940"
    ],
    "name:msa_x_preferred":[
        "Chandani"
    ],
    "name:nep_x_preferred":[
        "\u091a\u093e\u0901\u0926\u0928\u0940"
    ],
    "name:new_x_preferred":[
        "\u091a\u093e\u0901\u0926\u0928\u0940"
    ],
    "name:pol_x_preferred":[
        "Chandani"
    ],
    "wof:name":"Chandani",
    "wof:placetype":"locality"
},
  "geometry": {"coordinates":[89.64838,23.3883],"type":"Point"}
}