{
  "type": "Feature",
  "properties": {
    "gn:admin1_code":"87",
    "gn:admin2_code":"5573.0",
    "gn:admin3_code":"557312.0",
    "gn:admin4_code":"55731209.0",
    "gn:asciiname":"Majhiali",
    "gn:country_code":"BD",
    "gn:dem":57,
    "gn:feature_class":"P",
    "gn:feature_code":"PPL",
    "gn:name":"Majhi\u0101li",
    "gn:population":0,
    "gn:timezone":"Asia/Dhaka",
    "iso:country":"BD",
    "name:ben_x_preferred":[
        "Majhi\u0101li"
    ],
    "wof:name":"Majhiali",
    "wof:placetype":"locality"
},
  "geometry": {"coordinates":[88.89634000000002,26.17142],"type":"Point"}
}