{
  "type": "Feature",
  "properties": {
    "gn:admin1_code":"82",
    "gn:asciiname":"Sri Hari",
    "gn:country_code":"BD",
    "gn:dem":9,
    "gn:feature_class":"P",
    "gn:feature_code":"PPL",
    "gn:name":"Sri Hari",
    "gn:population":0,
    "gn:timezone":"Asia/Dhaka",
    "iso:country":"BD",
    "name:ben_x_preferred":[
        "Sri Hari"
    ],
    "wof:name":"Sri Hari",
    "wof:placetype":"locality"
},
  "geometry": {"coordinates":[90.34404000000001,22.15341],"type":"Point"}
}