{
  "type": "Feature",
  "properties": {
    "gn:admin1_code":"82",
    "gn:admin2_code":"4018.0",
    "gn:admin3_code":"401855.0",
    "gn:admin4_code":"40185519.0",
    "gn:asciiname":"Shahpur",
    "gn:country_code":"BD",
    "gn:dem":18,
    "gn:feature_class":"P",
    "gn:feature_code":"PPL",
    "gn:name":"Sh\u0101hpur",
    "gn:population":0,
    "gn:timezone":"Asia/Dhaka",
    "iso:country":"BD",
    "name:ben_x_preferred":[
        "Sh\u0101hpur"
    ],
    "name:ben_x_variant":[
        "\u09b6\u09be\u09b9\u09aa\u09c1\u09b0"
    ],
    "name:cat_x_preferred":[
        "Shapur"
    ],
    "name:nld_x_preferred":[
        "Shahpur"
    ],
    "name:pol_x_preferred":[
        "Shahpur"
    ],
    "name:por_x_preferred":[
        "Shahpur"
    ],
    "wof:name":"Shahpur",
    "wof:placetype":"locality"
},
  "geometry": {"coordinates":[88.92639,23.46761],"type":"Point"}
}