{
  "type": "Feature",
  "properties": {
    "gn:admin1_code":"87",
    "gn:admin2_code":"5594",
    "gn:admin3_code":"559494.0",
    "gn:admin4_code":"55949463.0",
    "gn:asciiname":"Kaharpara",
    "gn:country_code":"BD",
    "gn:dem":57,
    "gn:feature_class":"P",
    "gn:feature_code":"PPL",
    "gn:name":"Kaharp\u0101ra",
    "gn:population":0,
    "gn:timezone":"Asia/Dhaka",
    "iso:country":"BD",
    "name:ben_x_preferred":[
        "Kaharp\u0101ra"
    ],
    "wof:name":"Kaharpara",
    "wof:placetype":"locality"
},
  "geometry": {"coordinates":[88.46176,25.99682],"type":"Point"}
}