{
  "type": "Feature",
  "properties": {
    "gn:admin1_code":"82",
    "gn:admin2_code":"4050",
    "gn:admin3_code":"405039.0",
    "gn:admin4_code":"40503940.0",
    "gn:asciiname":"Kalyanpur",
    "gn:country_code":"BD",
    "gn:dem":21,
    "gn:feature_class":"P",
    "gn:feature_code":"PPL",
    "gn:name":"Kaly\u0101npur",
    "gn:population":0,
    "gn:timezone":"Asia/Dhaka",
    "iso:country":"BD",
    "name:ben_x_preferred":[
        "Kaly\u0101npur"
    ],
    "wof:name":"Kalyanpur",
    "wof:placetype":"locality"
},
  "geometry": {"coordinates":[88.89296,24.03787],"type":"Point"}
}