{
  "type": "Feature",
  "properties": {
    "gn:admin1_code":"87",
    "gn:admin2_code":"5527.0",
    "gn:admin3_code":"552721.0",
    "gn:admin4_code":"55272113.0",
    "gn:asciiname":"Deor",
    "gn:country_code":"BD",
    "gn:dem":42,
    "gn:feature_class":"P",
    "gn:feature_code":"PPL",
    "gn:name":"Deor",
    "gn:population":0,
    "gn:timezone":"Asia/Dhaka",
    "iso:country":"BD",
    "name:ben_x_preferred":[
        "Deor"
    ],
    "wof:name":"Deor",
    "wof:placetype":"locality"
},
  "geometry": {"coordinates":[88.45589,25.7504],"type":"Point"}
}