{
  "type": "Feature",
  "properties": {
    "gn:admin1_code":"82",
    "gn:admin2_code":"4001",
    "gn:admin3_code":"400160.0",
    "gn:admin4_code":"40016071.0",
    "gn:asciiname":"Paschim Chiparai Khali",
    "gn:country_code":"BD",
    "gn:dem":9,
    "gn:feature_class":"P",
    "gn:feature_code":"PPL",
    "gn:name":"Paschim Chiparai Kh\u0101li",
    "gn:population":0,
    "gn:timezone":"Asia/Dhaka",
    "iso:country":"BD",
    "name:ben_x_preferred":[
        "Paschim Chiparai Kh\u0101li"
    ],
    "name:ben_x_variant":[
        "Paschim Chip\u0101b\u0101raikh\u0101li"
    ],
    "wof:name":"Paschim Chiparai Khali",
    "wof:placetype":"locality"
},
  "geometry": {"coordinates":[89.79937,22.38976],"type":"Point"}
}