{
  "type": "Feature",
  "properties": {
    "gn:admin1_code":"83",
    "gn:admin2_code":"5064",
    "gn:admin3_code":"506469.0",
    "gn:admin4_code":"50646931.0",
    "gn:asciiname":"Joypur",
    "gn:country_code":"BD",
    "gn:dem":27,
    "gn:feature_class":"P",
    "gn:feature_code":"PPL",
    "gn:name":"Joypur",
    "gn:population":0,
    "gn:timezone":"Asia/Dhaka",
    "iso:country":"BD",
    "name:ben_x_preferred":[
        "Joypur"
    ],
    "name:ben_x_variant":[
        "Jaypur"
    ],
    "wof:name":"Joypur",
    "wof:placetype":"locality"
},
  "geometry": {"coordinates":[88.60119,24.95363],"type":"Point"}
}