{
  "type": "Feature",
  "properties": {
    "gn:admin1_code":"87",
    "gn:admin2_code":"5549",
    "gn:admin3_code":"554906.0",
    "gn:admin4_code":"55490638.0",
    "gn:asciiname":"Banar Khuli",
    "gn:country_code":"BD",
    "gn:dem":32,
    "gn:feature_class":"P",
    "gn:feature_code":"PPL",
    "gn:name":"Banar Khuli",
    "gn:population":0,
    "gn:timezone":"Asia/Dhaka",
    "iso:country":"BD",
    "name:ben_x_preferred":[
        "Banar Khuli"
    ],
    "wof:name":"Banar Khuli",
    "wof:placetype":"locality"
},
  "geometry": {"coordinates":[89.77161,26.09691],"type":"Point"}
}