{
  "type": "Feature",
  "properties": {
    "gn:admin1_code":"83",
    "gn:admin2_code":"5070.0",
    "gn:admin3_code":"507037.0",
    "gn:admin4_code":"50703784.0",
    "gn:asciiname":"Pirashan",
    "gn:country_code":"BD",
    "gn:dem":26,
    "gn:feature_class":"P",
    "gn:feature_code":"PPL",
    "gn:name":"Pirashan",
    "gn:population":0,
    "gn:timezone":"Asia/Dhaka",
    "iso:country":"BD",
    "name:ben_x_preferred":[
        "Pirashan"
    ],
    "wof:name":"Pirashan",
    "wof:placetype":"locality"
},
  "geometry": {"coordinates":[88.31744999999999,24.78929],"type":"Point"}
}