{
  "type": "Feature",
  "properties": {
    "gn:admin1_code":"87",
    "gn:admin2_code":"5577.0",
    "gn:admin3_code":"557773.0",
    "gn:admin4_code":"55777335.0",
    "gn:asciiname":"Fakirpara",
    "gn:country_code":"BD",
    "gn:dem":76,
    "gn:feature_class":"P",
    "gn:feature_code":"PPL",
    "gn:name":"Fakirp\u0101ra",
    "gn:population":0,
    "gn:timezone":"Asia/Dhaka",
    "iso:country":"BD",
    "name:ben_x_preferred":[
        "Fakirp\u0101ra"
    ],
    "wof:name":"Fakirpara",
    "wof:placetype":"locality"
},
  "geometry": {"coordinates":[88.59322,26.35988],"type":"Point"}
}