{
  "type": "Feature",
  "properties": {
    "gn:admin1_code":"81",
    "gn:admin2_code":"3035.0",
    "gn:admin3_code":"303558.0",
    "gn:admin4_code":"30355844.0",
    "gn:asciiname":"Baniar Char",
    "gn:country_code":"BD",
    "gn:dem":9,
    "gn:feature_class":"P",
    "gn:feature_code":"PPL",
    "gn:name":"Bani\u0101r Char",
    "gn:population":0,
    "gn:timezone":"Asia/Dhaka",
    "iso:country":"BD",
    "name:ben_x_preferred":[
        "Bani\u0101r Char"
    ],
    "wof:name":"Baniar Char",
    "wof:placetype":"locality"
},
  "geometry": {"coordinates":[89.97329000000001,23.20515],"type":"Point"}
}