{
  "type": "Feature",
  "properties": {
    "gn:admin1_code":"H",
    "gn:admin2_code":"3061.0",
    "gn:admin3_code":"306165.0",
    "gn:admin4_code":"30616525.0",
    "gn:asciiname":"Balughat",
    "gn:country_code":"BD",
    "gn:dem":21,
    "gn:feature_class":"P",
    "gn:feature_code":"PPL",
    "gn:name":"B\u0101lugh\u0101t",
    "gn:population":0,
    "gn:timezone":"Asia/Dhaka",
    "iso:country":"BD",
    "wof:name":"Balughat",
    "wof:placetype":"locality"
},
  "geometry": {"coordinates":[90.16315,24.60171],"type":"Point"}
}