{
  "type": "Feature",
  "properties": {
    "gn:admin1_code":"87",
    "gn:admin2_code":"5577.0",
    "gn:admin3_code":"557725.0",
    "gn:admin4_code":"55772573.0",
    "gn:asciiname":"Sardarpara",
    "gn:country_code":"BD",
    "gn:dem":76,
    "gn:feature_class":"P",
    "gn:feature_code":"PPL",
    "gn:name":"Sard\u0101rp\u0101ra",
    "gn:population":0,
    "gn:timezone":"Asia/Dhaka",
    "iso:country":"BD",
    "name:ben_x_preferred":[
        "Sard\u0101rp\u0101ra"
    ],
    "wof:name":"Sardarpara",
    "wof:placetype":"locality"
},
  "geometry": {"coordinates":[88.54021999999998,26.26555],"type":"Point"}
}