{
  "type": "Feature",
  "properties": {
    "gn:admin1_code":"87",
    "gn:admin2_code":"5527.0",
    "gn:admin3_code":"552710.0",
    "gn:admin4_code":"55271023.0",
    "gn:asciiname":"Krishnachandpur",
    "gn:country_code":"BD",
    "gn:dem":32,
    "gn:feature_class":"P",
    "gn:feature_code":"PPL",
    "gn:name":"Krishnach\u0101ndpur",
    "gn:population":0,
    "gn:timezone":"Asia/Dhaka",
    "iso:country":"BD",
    "name:ben_x_preferred":[
        "Krishnach\u0101ndpur"
    ],
    "wof:name":"Krishnachandpur",
    "wof:placetype":"locality"
},
  "geometry": {"coordinates":[88.97326,25.39101],"type":"Point"}
}