{
  "type": "Feature",
  "properties": {
    "gn:admin1_code":"81",
    "gn:admin2_code":"3059",
    "gn:admin3_code":"305994.0",
    "gn:admin4_code":"30599423.0",
    "gn:asciiname":"Uttar Sunarong",
    "gn:country_code":"BD",
    "gn:dem":8,
    "gn:feature_class":"P",
    "gn:feature_code":"PPL",
    "gn:name":"Uttar Sunarong",
    "gn:population":0,
    "gn:timezone":"Asia/Dhaka",
    "iso:country":"BD",
    "wof:name":"Uttar Sunarong",
    "wof:placetype":"locality"
},
  "geometry": {"coordinates":[90.45068999999999,23.52645],"type":"Point"}
}