{
  "type": "Feature",
  "properties": {
    "gn:admin1_code":"82",
    "gn:admin2_code":"4018.0",
    "gn:admin3_code":"401807.0",
    "gn:admin4_code":"40180771.0",
    "gn:asciiname":"Gopalnagar",
    "gn:country_code":"BD",
    "gn:dem":18,
    "gn:feature_class":"P",
    "gn:feature_code":"PPL",
    "gn:name":"Gop\u0101lnagar",
    "gn:population":0,
    "gn:timezone":"Asia/Dhaka",
    "iso:country":"BD",
    "name:ben_x_preferred":[
        "Gop\u0101lnagar"
    ],
    "name:hif_x_preferred":[
        "Gopalnagar"
    ],
    "wof:name":"Gopalnagar",
    "wof:placetype":"locality"
},
  "geometry": {"coordinates":[88.83723000000001,23.71841],"type":"Point"}
}