{
  "type": "Feature",
  "properties": {
    "gn:admin1_code":"84",
    "gn:admin2_code":"2015",
    "gn:admin3_code":"201561.0",
    "gn:admin4_code":"20156188.0",
    "gn:asciiname":"Sosang",
    "gn:country_code":"BD",
    "gn:dem":3,
    "gn:feature_class":"P",
    "gn:feature_code":"PPL",
    "gn:name":"Sos\u0101ng",
    "gn:population":0,
    "gn:timezone":"Asia/Dhaka",
    "iso:country":"BD",
    "wof:name":"Sosang",
    "wof:placetype":"locality"
},
  "geometry": {"coordinates":[91.98333,22.23333],"type":"Point"}
}