{
  "type": "Feature",
  "properties": {
    "gn:admin1_code":"83",
    "gn:admin2_code":"5081",
    "gn:admin3_code":"508110.0",
    "gn:admin4_code":"50811023.0",
    "gn:asciiname":"Khurd Bausa",
    "gn:cc2":"BD",
    "gn:country_code":"BD",
    "gn:dem":22,
    "gn:feature_class":"P",
    "gn:feature_code":"PPL",
    "gn:name":"Khurd B\u0101usa",
    "gn:population":0,
    "gn:timezone":"Asia/Dhaka",
    "iso:country":"BD",
    "name:und_x_variant":[
        "Khorda Bausa",
        "Khurd B\u0101usa"
    ],
    "wof:name":"Khurd Bausa",
    "wof:placetype":"locality"
},
  "geometry": {"coordinates":[88.86667,24.26667],"type":"Point"}
}