{
  "type": "Feature",
  "properties": {
    "gn:admin1_code":"82",
    "gn:admin2_code":"4018.0",
    "gn:admin3_code":"401807.0",
    "gn:admin4_code":"40180794.0",
    "gn:asciiname":"Sanatanpur",
    "gn:country_code":"BD",
    "gn:dem":16,
    "gn:feature_class":"P",
    "gn:feature_code":"PPL",
    "gn:name":"Sanatanpur",
    "gn:population":0,
    "gn:timezone":"Asia/Dhaka",
    "iso:country":"BD",
    "name:ben_x_preferred":[
        "Sanatanpur"
    ],
    "wof:name":"Sanatanpur",
    "wof:placetype":"locality"
},
  "geometry": {"coordinates":[88.91405,23.65462],"type":"Point"}
}