{
  "type": "Feature",
  "properties": {
    "gn:admin1_code":"83",
    "gn:admin2_code":"5070.0",
    "gn:admin3_code":"507018.0",
    "gn:admin4_code":"50701818.0",
    "gn:asciiname":"Tantipara",
    "gn:country_code":"BD",
    "gn:dem":29,
    "gn:feature_class":"P",
    "gn:feature_code":"PPL",
    "gn:name":"T\u0101ntip\u0101ra",
    "gn:population":0,
    "gn:timezone":"Asia/Dhaka",
    "iso:country":"BD",
    "name:ben_x_preferred":[
        "T\u0101ntip\u0101ra"
    ],
    "wof:name":"Tantipara",
    "wof:placetype":"locality"
},
  "geometry": {"coordinates":[88.2209,24.94718],"type":"Point"}
}