{
  "type": "Feature",
  "properties": {
    "gn:admin1_code":"82",
    "gn:admin2_code":"4044.0",
    "gn:admin3_code":"404480.0",
    "gn:admin4_code":"40448044.0",
    "gn:asciiname":"Asannagar",
    "gn:country_code":"BD",
    "gn:dem":15,
    "gn:feature_class":"P",
    "gn:feature_code":"PPL",
    "gn:name":"As\u0101nnagar",
    "gn:population":0,
    "gn:timezone":"Asia/Dhaka",
    "iso:country":"BD",
    "name:ben_x_preferred":[
        "As\u0101nnagar"
    ],
    "wof:name":"Asannagar",
    "wof:placetype":"locality"
},
  "geometry": {"coordinates":[89.18505999999999,23.62145],"type":"Point"}
}