{
  "type": "Feature",
  "properties": {
    "gn:admin1_code":"81",
    "gn:admin2_code":"3082.0",
    "gn:admin3_code":"308276.0",
    "gn:admin4_code":"30827645.0",
    "gn:asciiname":"Belgachi Raghunathpur",
    "gn:country_code":"BD",
    "gn:dem":15,
    "gn:feature_class":"P",
    "gn:feature_code":"PPL",
    "gn:name":"Belg\u0101chi Raghun\u0101thpur",
    "gn:population":0,
    "gn:timezone":"Asia/Dhaka",
    "iso:country":"BD",
    "name:ben_x_preferred":[
        "Belg\u0101chi Raghun\u0101thpur"
    ],
    "wof:name":"Belgachi Raghunathpur",
    "wof:placetype":"locality"
},
  "geometry": {"coordinates":[89.54146,23.77845],"type":"Point"}
}