{
  "type": "Feature",
  "properties": {
    "gn:admin1_code":"84",
    "gn:admin2_code":"2022.0",
    "gn:admin3_code":"202290.0",
    "gn:admin4_code":"20229031.0",
    "gn:asciiname":"Nayapara",
    "gn:country_code":"BD",
    "gn:dem":13,
    "gn:feature_class":"P",
    "gn:feature_code":"PPL",
    "gn:name":"Nayap\u0101ra",
    "gn:population":0,
    "gn:timezone":"Asia/Dhaka",
    "iso:country":"BD",
    "name:ben_x_preferred":[
        "Nayap\u0101ra"
    ],
    "wof:name":"Nayapara",
    "wof:placetype":"locality"
},
  "geometry": {"coordinates":[92.25445000000001,20.95409],"type":"Point"}
}