{
  "type": "Feature",
  "properties": {
    "gn:admin1_code":"85",
    "gn:admin2_code":"1006.0",
    "gn:admin3_code":"100603.0",
    "gn:admin4_code":"10060313.0",
    "gn:asciiname":"Char Algi",
    "gn:country_code":"BD",
    "gn:dem":11,
    "gn:feature_class":"P",
    "gn:feature_code":"PPL",
    "gn:name":"Char \u0100lgi",
    "gn:population":0,
    "gn:timezone":"Asia/Dhaka",
    "iso:country":"BD",
    "wof:name":"Char Algi",
    "wof:placetype":"locality"
},
  "geometry": {"coordinates":[90.30051,22.86468],"type":"Point"}
}