{
  "type": "Feature",
  "properties": {
    "gn:admin1_code":"82",
    "gn:admin2_code":"4041",
    "gn:admin3_code":"404111.0",
    "gn:admin4_code":"40411108.0",
    "gn:asciiname":"Lashkarpur",
    "gn:country_code":"BD",
    "gn:dem":14,
    "gn:feature_class":"P",
    "gn:feature_code":"PPL",
    "gn:name":"Lashkarpur",
    "gn:population":0,
    "gn:timezone":"Asia/Dhaka",
    "iso:country":"BD",
    "name:ben_x_preferred":[
        "Lashkarpur"
    ],
    "name:und_x_variant":[
        "Laskarpur"
    ],
    "wof:name":"Lashkarpur",
    "wof:placetype":"locality"
},
  "geometry": {"coordinates":[89.04183,23.24398],"type":"Point"}
}