{
  "type": "Feature",
  "properties": {
    "gn:admin1_code":"84",
    "gn:admin2_code":"2013",
    "gn:admin3_code":"201379.0",
    "gn:admin4_code":"20137904.0",
    "gn:asciiname":"Santoshpur",
    "gn:country_code":"BD",
    "gn:dem":8,
    "gn:feature_class":"P",
    "gn:feature_code":"PPL",
    "gn:name":"Santoshpur",
    "gn:population":0,
    "gn:timezone":"Asia/Dhaka",
    "iso:country":"BD",
    "name:und_x_variant":[
        "Santospur",
        "Santoshpur"
    ],
    "wof:name":"Santoshpur",
    "wof:placetype":"locality"
},
  "geometry": {"coordinates":[90.69112,23.45477],"type":"Point"}
}