{
  "type": "Feature",
  "properties": {
    "gn:admin1_code":"82",
    "gn:admin2_code":"4018.0",
    "gn:admin3_code":"401807.0",
    "gn:admin4_code":"40180755.0",
    "gn:asciiname":"Sahagpur",
    "gn:country_code":"BD",
    "gn:dem":19,
    "gn:feature_class":"P",
    "gn:feature_code":"PPL",
    "gn:name":"Sah\u0101gpur",
    "gn:population":0,
    "gn:timezone":"Asia/Dhaka",
    "iso:country":"BD",
    "name:ben_x_preferred":[
        "Sah\u0101gpur"
    ],
    "wof:name":"Sahagpur",
    "wof:placetype":"locality"
},
  "geometry": {"coordinates":[89.00605,23.73025],"type":"Point"}
}