{
  "type": "Feature",
  "properties": {
    "gn:admin1_code":"84",
    "gn:admin2_code":"2013.0",
    "gn:admin3_code":"201358.0",
    "gn:admin4_code":"20135879.0",
    "gn:asciiname":"Atiswar",
    "gn:country_code":"BD",
    "gn:dem":9,
    "gn:feature_class":"P",
    "gn:feature_code":"PPL",
    "gn:name":"Atiswar",
    "gn:population":0,
    "gn:timezone":"Asia/Dhaka",
    "iso:country":"BD",
    "wof:name":"Atiswar",
    "wof:placetype":"locality"
},
  "geometry": {"coordinates":[90.81059999999999,23.43378],"type":"Point"}
}