{
  "type": "Feature",
  "properties": {
    "gn:admin1_code":"82",
    "gn:admin2_code":"4044.0",
    "gn:admin3_code":"404419.0",
    "gn:admin4_code":"40441952.0",
    "gn:asciiname":"Atlia",
    "gn:country_code":"BD",
    "gn:dem":15,
    "gn:feature_class":"P",
    "gn:feature_code":"PPL",
    "gn:name":"Atlia",
    "gn:population":0,
    "gn:timezone":"Asia/Dhaka",
    "iso:country":"BD",
    "name:ben_x_preferred":[
        "Atlia"
    ],
    "wof:name":"Atlia",
    "wof:placetype":"locality"
},
  "geometry": {"coordinates":[89.03986999999999,23.48691],"type":"Point"}
}