{
  "type": "Feature",
  "properties": {
    "gn:admin1_code":"87",
    "gn:admin2_code":"5573.0",
    "gn:admin3_code":"557315.0",
    "gn:admin4_code":"55731576.0",
    "gn:asciiname":"Khetkibari",
    "gn:country_code":"BD",
    "gn:dem":65,
    "gn:feature_class":"P",
    "gn:feature_code":"PPL",
    "gn:name":"Khetkib\u0101ri",
    "gn:population":0,
    "gn:timezone":"Asia/Dhaka",
    "iso:country":"BD",
    "name:ben_x_preferred":[
        "Khetkib\u0101ri"
    ],
    "wof:name":"Khetkibari",
    "wof:placetype":"locality"
},
  "geometry": {"coordinates":[88.82025,26.24947],"type":"Point"}
}