{
  "type": "Feature",
  "properties": {
    "gn:admin1_code":"81",
    "gn:admin2_code":"3093",
    "gn:admin3_code":"309395.0",
    "gn:admin4_code":"30939541.0",
    "gn:asciiname":"Sarkarbari",
    "gn:country_code":"BD",
    "gn:dem":17,
    "gn:feature_class":"P",
    "gn:feature_code":"PPL",
    "gn:name":"Sarkarbari",
    "gn:population":0,
    "gn:timezone":"Asia/Dhaka",
    "iso:country":"BD",
    "wof:name":"Sarkarbari",
    "wof:placetype":"locality"
},
  "geometry": {"coordinates":[89.90101,24.29929],"type":"Point"}
}