{
  "type": "Feature",
  "properties": {
    "gn:admin1_code":"83",
    "gn:admin2_code":"5064",
    "gn:admin3_code":"506406.0",
    "gn:admin4_code":"50640610.0",
    "gn:asciiname":"Sadishpur",
    "gn:country_code":"BD",
    "gn:dem":25,
    "gn:feature_class":"P",
    "gn:feature_code":"PPL",
    "gn:name":"S\u0101dishpur",
    "gn:population":0,
    "gn:timezone":"Asia/Dhaka",
    "iso:country":"BD",
    "name:ben_x_preferred":[
        "S\u0101dishpur"
    ],
    "name:ben_x_variant":[
        "S\u0101dispur"
    ],
    "wof:name":"Sadishpur",
    "wof:placetype":"locality"
},
  "geometry": {"coordinates":[88.93930999999998,24.98534],"type":"Point"}
}