{
  "type": "Feature",
  "properties": {
    "gn:admin1_code":"82",
    "gn:admin2_code":"4044.0",
    "gn:admin3_code":"404419.0",
    "gn:admin4_code":"40441926.0",
    "gn:asciiname":"Pratappur",
    "gn:country_code":"BD",
    "gn:dem":15,
    "gn:feature_class":"P",
    "gn:feature_code":"PPL",
    "gn:name":"Prat\u0101ppur",
    "gn:population":0,
    "gn:timezone":"Asia/Dhaka",
    "iso:country":"BD",
    "name:ben_x_preferred":[
        "Prat\u0101ppur"
    ],
    "wof:name":"Pratappur",
    "wof:placetype":"locality"
},
  "geometry": {"coordinates":[89.09010000000001,23.55103],"type":"Point"}
}