{
  "type": "Feature",
  "properties": {
    "gn:admin1_code":"H",
    "gn:admin2_code":"3061.0",
    "gn:admin3_code":"306131.0",
    "gn:admin4_code":"30613140.0",
    "gn:asciiname":"Asrabpur",
    "gn:country_code":"BD",
    "gn:dem":17,
    "gn:feature_class":"P",
    "gn:feature_code":"PPL",
    "gn:name":"\u0100srabpur",
    "gn:population":0,
    "gn:timezone":"Asia/Dhaka",
    "iso:country":"BD",
    "wof:name":"Asrabpur",
    "wof:placetype":"locality"
},
  "geometry": {"coordinates":[90.59712,24.65499],"type":"Point"}
}