{
  "type": "Feature",
  "properties": {
    "gn:admin1_code":"00",
    "gn:asciiname":"Gazipur Manipur",
    "gn:cc2":"BD",
    "gn:country_code":"BD",
    "gn:dem":1,
    "gn:feature_class":"P",
    "gn:feature_code":"PPL",
    "gn:name":"G\u0101z\u012bpur Manipur",
    "gn:population":0,
    "gn:timezone":"Asia/Dhaka",
    "iso:country":"BD",
    "name:und_x_variant":[
        "Gazipur Monipur",
        "G\u0101z\u012bpur Manipur"
    ],
    "wof:name":"Gazipur Manipur",
    "wof:placetype":"locality"
},
  "geometry": {"coordinates":[90.61667,23.11667000000001],"type":"Point"}
}