{
  "type": "Feature",
  "properties": {
    "gn:admin1_code":"H",
    "gn:admin2_code":"3039",
    "gn:admin3_code":"303929.0",
    "gn:admin4_code":"30392979.0",
    "gn:asciiname":"Polabandha",
    "gn:country_code":"BD",
    "gn:dem":25,
    "gn:feature_class":"P",
    "gn:feature_code":"PPL",
    "gn:name":"Polabandha",
    "gn:population":0,
    "gn:timezone":"Asia/Dhaka",
    "iso:country":"BD",
    "name:ben_x_preferred":[
        "Polabandha"
    ],
    "wof:name":"Polabandha",
    "wof:placetype":"locality"
},
  "geometry": {"coordinates":[89.77750999999998,25.09601],"type":"Point"}
}