{
  "type": "Feature",
  "properties": {
    "gn:admin1_code":"83",
    "gn:admin2_code":"5081",
    "gn:admin3_code":"508112.0",
    "gn:admin4_code":"50811269.0",
    "gn:asciiname":"Jugipara",
    "gn:country_code":"BD",
    "gn:dem":18,
    "gn:feature_class":"P",
    "gn:feature_code":"PPL",
    "gn:name":"Jugip\u0101ra",
    "gn:population":0,
    "gn:timezone":"Asia/Dhaka",
    "iso:country":"BD",
    "name:ben_x_preferred":[
        "Jugip\u0101ra"
    ],
    "wof:name":"Jugipara",
    "wof:placetype":"locality"
},
  "geometry": {"coordinates":[88.91198,24.58394],"type":"Point"}
}