{
  "type": "Feature",
  "properties": {
    "gn:admin1_code":"87",
    "gn:admin2_code":"5577.0",
    "gn:admin3_code":"557790.0",
    "gn:admin4_code":"55779067.0",
    "gn:asciiname":"Kekidangi",
    "gn:country_code":"BD",
    "gn:dem":93,
    "gn:feature_class":"P",
    "gn:feature_code":"PPL",
    "gn:name":"Kekid\u0101ngi",
    "gn:population":0,
    "gn:timezone":"Asia/Dhaka",
    "iso:country":"BD",
    "name:ben_x_preferred":[
        "Kekid\u0101ngi"
    ],
    "wof:name":"Kekidangi",
    "wof:placetype":"locality"
},
  "geometry": {"coordinates":[88.38108000000003,26.49489],"type":"Point"}
}