{
  "type": "Feature",
  "properties": {
    "gn:admin1_code":"82",
    "gn:admin2_code":"4050.0",
    "gn:admin3_code":"405071.0",
    "gn:admin4_code":"40507143.0",
    "gn:asciiname":"Betbaria",
    "gn:country_code":"BD",
    "gn:dem":16,
    "gn:feature_class":"P",
    "gn:feature_code":"PPL",
    "gn:name":"Betb\u0101ria",
    "gn:population":0,
    "gn:timezone":"Asia/Dhaka",
    "iso:country":"BD",
    "wof:name":"Betbaria",
    "wof:placetype":"locality"
},
  "geometry": {"coordinates":[89.25839999999999,23.88471],"type":"Point"}
}