{
  "type": "Feature",
  "properties": {
    "gn:admin1_code":"87",
    "gn:admin2_code":"5549",
    "gn:admin3_code":"554977.0",
    "gn:admin4_code":"55497710.0",
    "gn:asciiname":"Sukdeb",
    "gn:country_code":"BD",
    "gn:dem":32,
    "gn:feature_class":"P",
    "gn:feature_code":"PPL",
    "gn:name":"Sukdeb",
    "gn:population":0,
    "gn:timezone":"Asia/Dhaka",
    "iso:country":"BD",
    "name:ben_x_preferred":[
        "Sukdeb"
    ],
    "wof:name":"Sukdeb",
    "wof:placetype":"locality"
},
  "geometry": {"coordinates":[89.53199000000002,25.76351],"type":"Point"}
}