{
  "type": "Feature",
  "properties": {
    "gn:admin1_code":"81",
    "gn:admin2_code":"3093.0",
    "gn:admin3_code":"309357.0",
    "gn:admin4_code":"30935766.0",
    "gn:asciiname":"Bagua",
    "gn:country_code":"BD",
    "gn:dem":19,
    "gn:feature_class":"P",
    "gn:feature_code":"PPL",
    "gn:name":"B\u0101gua",
    "gn:population":0,
    "gn:timezone":"Asia/Dhaka",
    "iso:country":"BD",
    "wof:name":"Bagua",
    "wof:placetype":"locality"
},
  "geometry": {"coordinates":[90.00360000000001,24.63082],"type":"Point"}
}