{
  "type": "Feature",
  "properties": {
    "gn:admin1_code":"81",
    "gn:admin2_code":"3068.0",
    "gn:admin3_code":"306860.0",
    "gn:admin4_code":"30686029.0",
    "gn:asciiname":"Char Hajipur",
    "gn:country_code":"BD",
    "gn:dem":10,
    "gn:feature_class":"P",
    "gn:feature_code":"PPL",
    "gn:name":"Char H\u0101jipur",
    "gn:population":0,
    "gn:timezone":"Asia/Dhaka",
    "iso:country":"BD",
    "name:und_x_variant":[
        "Char Hazipur",
        "Char H\u0101jipur"
    ],
    "wof:name":"Char Hajipur",
    "wof:placetype":"locality"
},
  "geometry": {"coordinates":[90.74556,23.92048],"type":"Point"}
}