{
  "type": "Feature",
  "properties": {
    "gn:admin1_code":"82",
    "gn:admin2_code":"4055.0",
    "gn:admin3_code":"405566.0",
    "gn:admin4_code":"40556652.0",
    "gn:asciiname":"Char Chhatiani Paschimkhanda",
    "gn:country_code":"BD",
    "gn:dem":15,
    "gn:feature_class":"P",
    "gn:feature_code":"PPL",
    "gn:name":"Char Chh\u0101ti\u0101ni Paschimkhanda",
    "gn:population":0,
    "gn:timezone":"Asia/Dhaka",
    "iso:country":"BD",
    "wof:name":"Char Chhatiani Paschimkhanda",
    "wof:placetype":"locality"
},
  "geometry": {"coordinates":[89.59578,23.43058],"type":"Point"}
}