{
  "type": "Feature",
  "properties": {
    "gn:admin1_code":"87",
    "gn:admin2_code":"5532.0",
    "gn:admin3_code":"553230.0",
    "gn:admin4_code":"55323033.0",
    "gn:asciiname":"Chiargram",
    "gn:country_code":"BD",
    "gn:dem":28,
    "gn:feature_class":"P",
    "gn:feature_code":"PPL",
    "gn:name":"Chi\u0101rgr\u0101m",
    "gn:population":0,
    "gn:timezone":"Asia/Dhaka",
    "iso:country":"BD",
    "name:und_x_variant":[
        "Chi\u0101rgr\u0101m",
        "Chi\u0101rgaon"
    ],
    "wof:name":"Chiargram",
    "wof:placetype":"locality"
},
  "geometry": {"coordinates":[89.26061,25.19927],"type":"Point"}
}