{
  "type": "Feature",
  "properties": {
    "gn:admin1_code":"84",
    "gn:admin2_code":"2013.0",
    "gn:admin3_code":"201358.0",
    "gn:admin4_code":"20135863.0",
    "gn:asciiname":"Dari Hayatpur",
    "gn:country_code":"BD",
    "gn:dem":11,
    "gn:feature_class":"P",
    "gn:feature_code":"PPL",
    "gn:name":"Dari Hay\u0101tpur",
    "gn:population":0,
    "gn:timezone":"Asia/Dhaka",
    "iso:country":"BD",
    "wof:name":"Dari Hayatpur",
    "wof:placetype":"locality"
},
  "geometry": {"coordinates":[90.88543,23.32478],"type":"Point"}
}