{
  "type": "Feature",
  "properties": {
    "gn:admin1_code":"87",
    "gn:admin2_code":"5527.0",
    "gn:admin3_code":"552710.0",
    "gn:admin4_code":"55271083.0",
    "gn:asciiname":"Chak Basanta",
    "gn:country_code":"BD",
    "gn:dem":30,
    "gn:feature_class":"P",
    "gn:feature_code":"PPL",
    "gn:name":"Chak Basanta",
    "gn:population":0,
    "gn:timezone":"Asia/Dhaka",
    "iso:country":"BD",
    "name:ben_x_preferred":[
        "Chak Basanta"
    ],
    "wof:name":"Chak Basanta",
    "wof:placetype":"locality"
},
  "geometry": {"coordinates":[88.96581999999999,25.39459],"type":"Point"}
}