{
  "type": "Feature",
  "properties": {
    "gn:admin1_code":"83",
    "gn:admin2_code":"5064",
    "gn:admin3_code":"506479.0",
    "gn:admin4_code":"50647931.0",
    "gn:asciiname":"Satali",
    "gn:country_code":"BD",
    "gn:dem":34,
    "gn:feature_class":"P",
    "gn:feature_code":"PPL",
    "gn:name":"Satali",
    "gn:population":0,
    "gn:timezone":"Asia/Dhaka",
    "iso:country":"BD",
    "name:ben_x_preferred":[
        "Satali"
    ],
    "name:und_x_variant":[
        "Sutali"
    ],
    "wof:name":"Satali",
    "wof:placetype":"locality"
},
  "geometry": {"coordinates":[88.56393,24.98812],"type":"Point"}
}