{
  "type": "Feature",
  "properties": {
    "gn:admin1_code":"83",
    "gn:admin2_code":"5064",
    "gn:admin3_code":"506428.0",
    "gn:admin4_code":"50642852.0",
    "gn:asciiname":"Isabpur",
    "gn:country_code":"BD",
    "gn:dem":26,
    "gn:feature_class":"P",
    "gn:feature_code":"PPL",
    "gn:name":"Isabpur",
    "gn:population":0,
    "gn:timezone":"Asia/Dhaka",
    "iso:country":"BD",
    "name:ben_x_preferred":[
        "Isabpur"
    ],
    "wof:name":"Isabpur",
    "wof:placetype":"locality"
},
  "geometry": {"coordinates":[88.92464,25.05407],"type":"Point"}
}