{
  "type": "Feature",
  "properties": {
    "gn:admin1_code":"82",
    "gn:admin2_code":"4055.0",
    "gn:admin3_code":"405566.0",
    "gn:admin4_code":"40556642.0",
    "gn:asciiname":"Aunara",
    "gn:country_code":"BD",
    "gn:dem":15,
    "gn:feature_class":"P",
    "gn:feature_code":"PPL",
    "gn:name":"\u0100un\u0101ra",
    "gn:population":0,
    "gn:timezone":"Asia/Dhaka",
    "iso:country":"BD",
    "wof:name":"Aunara",
    "wof:placetype":"locality"
},
  "geometry": {"coordinates":[89.56816999999999,23.4319],"type":"Point"}
}