{
  "type": "Feature",
  "properties": {
    "gn:admin1_code":"87",
    "gn:admin2_code":"5527",
    "gn:admin3_code":"552743.0",
    "gn:admin4_code":"55274376.0",
    "gn:asciiname":"Tekam",
    "gn:country_code":"BD",
    "gn:dem":25,
    "gn:feature_class":"P",
    "gn:feature_code":"PPL",
    "gn:name":"Tekam",
    "gn:population":0,
    "gn:timezone":"Asia/Dhaka",
    "iso:country":"BD",
    "name:ben_x_preferred":[
        "Tekam"
    ],
    "wof:name":"Tekam",
    "wof:placetype":"locality"
},
  "geometry": {"coordinates":[89.25933000000001,25.28768],"type":"Point"}
}