{
  "type": "Feature",
  "properties": {
    "gn:admin1_code":"83",
    "gn:admin2_code":"5070.0",
    "gn:admin3_code":"507088.0",
    "gn:admin4_code":"50708811.0",
    "gn:asciiname":"Diar Kansi",
    "gn:country_code":"BD",
    "gn:dem":28,
    "gn:feature_class":"P",
    "gn:feature_code":"PPL",
    "gn:name":"Di\u0101r K\u0101nsi",
    "gn:population":0,
    "gn:timezone":"Asia/Dhaka",
    "iso:country":"BD",
    "name:ben_x_preferred":[
        "Di\u0101r K\u0101nsi"
    ],
    "wof:name":"Diar Kansi",
    "wof:placetype":"locality"
},
  "geometry": {"coordinates":[88.26886999999998,24.7467],"type":"Point"}
}