{
  "type": "Feature",
  "properties": {
    "gn:admin1_code":"84",
    "gn:admin2_code":"2075",
    "gn:admin3_code":"207507.0",
    "gn:admin4_code":"20750728.0",
    "gn:asciiname":"Tahirpur",
    "gn:country_code":"BD",
    "gn:dem":8,
    "gn:feature_class":"P",
    "gn:feature_code":"PPL",
    "gn:name":"T\u0101hirpur",
    "gn:population":0,
    "gn:timezone":"Asia/Dhaka",
    "iso:country":"BD",
    "wof:name":"Tahirpur",
    "wof:placetype":"locality"
},
  "geometry": {"coordinates":[90.995,22.90691],"type":"Point"}
}