{
  "type": "Feature",
  "properties": {
    "gn:admin1_code":"87",
    "gn:admin2_code":"5585",
    "gn:admin3_code":"558503.0",
    "gn:admin4_code":"55850325.0",
    "gn:asciiname":"Taluk Damodarpur",
    "gn:country_code":"BD",
    "gn:dem":39,
    "gn:feature_class":"P",
    "gn:feature_code":"PPL",
    "gn:name":"T\u0101luk D\u0101modarpur",
    "gn:population":0,
    "gn:timezone":"Asia/Dhaka",
    "iso:country":"BD",
    "name:und_x_variant":[
        "Talook Damoodurp",
        "T\u0101luk D\u0101modarpur"
    ],
    "wof:name":"Taluk Damodarpur",
    "wof:placetype":"locality"
},
  "geometry": {"coordinates":[89.0382,25.72236],"type":"Point"}
}