{
  "type": "Feature",
  "properties": {
    "gn:admin1_code":"83",
    "gn:admin2_code":"5064",
    "gn:admin3_code":"506447.0",
    "gn:admin4_code":"50644706.0",
    "gn:asciiname":"Jamdai",
    "gn:country_code":"BD",
    "gn:dem":18,
    "gn:feature_class":"P",
    "gn:feature_code":"PPL",
    "gn:name":"Jamdai",
    "gn:population":0,
    "gn:timezone":"Asia/Dhaka",
    "iso:country":"BD",
    "name:ben_x_preferred":[
        "Jamdai"
    ],
    "wof:name":"Jamdai",
    "wof:placetype":"locality"
},
  "geometry": {"coordinates":[88.70577,24.85362000000001],"type":"Point"}
}