{
  "type": "Feature",
  "properties": {
    "gn:admin1_code":"82",
    "gn:admin2_code":"4018.0",
    "gn:admin3_code":"401823.0",
    "gn:admin4_code":"40182359.0",
    "gn:asciiname":"Hogaldanga",
    "gn:country_code":"BD",
    "gn:dem":17,
    "gn:feature_class":"P",
    "gn:feature_code":"PPL",
    "gn:name":"Hogald\u0101nga",
    "gn:population":0,
    "gn:timezone":"Asia/Dhaka",
    "iso:country":"BD",
    "name:ben_x_preferred":[
        "Hogald\u0101nga"
    ],
    "wof:name":"Hogaldanga",
    "wof:placetype":"locality"
},
  "geometry": {"coordinates":[88.90449,23.619],"type":"Point"}
}