{
  "type": "Feature",
  "properties": {
    "gn:admin1_code":"00",
    "gn:asciiname":"Syedpur",
    "gn:country_code":"BD",
    "gn:dem":2,
    "gn:feature_class":"P",
    "gn:feature_code":"PPL",
    "gn:name":"Syedpur",
    "gn:population":0,
    "gn:timezone":"Asia/Dhaka",
    "iso:country":"BD",
    "name:und_x_variant":[
        "Saidpur"
    ],
    "wof:name":"Syedpur",
    "wof:placetype":"locality"
},
  "geometry": {"coordinates":[90.77240999999999,22.55975],"type":"Point"}
}