{
  "type": "Feature",
  "properties": {
    "gn:admin1_code":"H",
    "gn:admin2_code":"3061",
    "gn:admin3_code":"306131.0",
    "gn:admin4_code":"30613190.0",
    "gn:asciiname":"Mirzapur",
    "gn:country_code":"BD",
    "gn:dem":18,
    "gn:feature_class":"P",
    "gn:feature_code":"PPL",
    "gn:name":"Mirz\u0101pur",
    "gn:population":0,
    "gn:timezone":"Asia/Dhaka",
    "iso:country":"BD",
    "wof:name":"Mirzapur",
    "wof:placetype":"locality"
},
  "geometry": {"coordinates":[90.52421,24.66136],"type":"Point"}
}