{
  "type": "Feature",
  "properties": {
    "gn:admin1_code":"87",
    "gn:admin2_code":"5573.0",
    "gn:admin3_code":"557364.0",
    "gn:admin4_code":"55736450.0",
    "gn:asciiname":"Uttar Balapara",
    "gn:country_code":"BD",
    "gn:dem":51,
    "gn:feature_class":"P",
    "gn:feature_code":"PPL",
    "gn:name":"Uttar B\u0101l\u0101p\u0101ra",
    "gn:population":0,
    "gn:timezone":"Asia/Dhaka",
    "iso:country":"BD",
    "name:ben_x_preferred":[
        "Uttar B\u0101l\u0101p\u0101ra"
    ],
    "wof:name":"Uttar Balapara",
    "wof:placetype":"locality"
},
  "geometry": {"coordinates":[88.80372,25.91241],"type":"Point"}
}