{
  "type": "Feature",
  "properties": {
    "gn:admin1_code":"87",
    "gn:admin2_code":"5527.0",
    "gn:admin3_code":"552717.0",
    "gn:admin4_code":"55271747.0",
    "gn:asciiname":"Keshabpur",
    "gn:country_code":"BD",
    "gn:dem":44,
    "gn:feature_class":"P",
    "gn:feature_code":"PPL",
    "gn:name":"Keshabpur",
    "gn:population":0,
    "gn:timezone":"Asia/Dhaka",
    "iso:country":"BD",
    "name:ben_x_preferred":[
        "Keshabpur"
    ],
    "name:hif_x_preferred":[
        "Keshabpur"
    ],
    "wof:name":"Keshabpur",
    "wof:placetype":"locality"
},
  "geometry": {"coordinates":[88.57504,25.68008],"type":"Point"}
}