{
  "type": "Feature",
  "properties": {
    "gn:admin1_code":"87",
    "gn:admin2_code":"5594.0",
    "gn:admin3_code":"559408.0",
    "gn:admin4_code":"55940852.0",
    "gn:asciiname":"Bhotpara",
    "gn:country_code":"BD",
    "gn:dem":62,
    "gn:feature_class":"P",
    "gn:feature_code":"PPL",
    "gn:name":"Bhotp\u0101ra",
    "gn:population":0,
    "gn:timezone":"Asia/Dhaka",
    "iso:country":"BD",
    "name:ben_x_preferred":[
        "Bhotp\u0101ra"
    ],
    "wof:name":"Bhotpara",
    "wof:placetype":"locality"
},
  "geometry": {"coordinates":[88.31298000000002,26.13924],"type":"Point"}
}