{
  "type": "Feature",
  "properties": {
    "gn:admin1_code":"84",
    "gn:admin2_code":"2075.0",
    "gn:admin3_code":"207536.0",
    "gn:admin4_code":"20753628.0",
    "gn:asciiname":"Char Ishwar",
    "gn:cc2":"BD",
    "gn:country_code":"BD",
    "gn:dem":5,
    "gn:feature_class":"P",
    "gn:feature_code":"PPL",
    "gn:name":"Char Ishwar",
    "gn:population":0,
    "gn:timezone":"Asia/Dhaka",
    "iso:country":"BD",
    "name:und_x_variant":[
        "Char Ishwar Ray",
        "Char Iswar Ray",
        "Char Ishwar"
    ],
    "wof:name":"Char Ishwar",
    "wof:placetype":"locality"
},
  "geometry": {"coordinates":[91.18805999999999,22.27333],"type":"Point"}
}