{
  "type": "Feature",
  "properties": {
    "gn:admin1_code":"83",
    "gn:admin2_code":"5010",
    "gn:admin3_code":"501095.0",
    "gn:admin4_code":"50109531.0",
    "gn:asciiname":"Lohagara",
    "gn:country_code":"BD",
    "gn:dem":23,
    "gn:feature_class":"P",
    "gn:feature_code":"PPL",
    "gn:name":"Loh\u0101gara",
    "gn:population":0,
    "gn:timezone":"Asia/Dhaka",
    "iso:country":"BD",
    "wof:name":"Lohagara",
    "wof:placetype":"locality"
},
  "geometry": {"coordinates":[89.49186,24.97805],"type":"Point"}
}