{
  "type": "Feature",
  "properties": {
    "gn:admin1_code":"83",
    "gn:admin2_code":"5064.0",
    "gn:admin3_code":"506447.0",
    "gn:admin4_code":"50644767.0",
    "gn:asciiname":"Ghatkair",
    "gn:country_code":"BD",
    "gn:dem":19,
    "gn:feature_class":"P",
    "gn:feature_code":"PPL",
    "gn:name":"Gh\u0101tkair",
    "gn:population":0,
    "gn:timezone":"Asia/Dhaka",
    "iso:country":"BD",
    "name:ben_x_preferred":[
        "Gh\u0101tkair"
    ],
    "wof:name":"Ghatkair",
    "wof:placetype":"locality"
},
  "geometry": {"coordinates":[88.68526999999997,24.80829],"type":"Point"}
}