{
  "type": "Feature",
  "properties": {
    "gn:admin1_code":"87",
    "gn:admin2_code":"5573.0",
    "gn:admin3_code":"557312.0",
    "gn:admin4_code":"55731257.0",
    "gn:asciiname":"Uttar Girdo",
    "gn:country_code":"BD",
    "gn:dem":58,
    "gn:feature_class":"P",
    "gn:feature_code":"PPL",
    "gn:name":"Uttar Girdo",
    "gn:population":0,
    "gn:timezone":"Asia/Dhaka",
    "iso:country":"BD",
    "name:ben_x_preferred":[
        "Uttar Girdo"
    ],
    "wof:name":"Uttar Girdo",
    "wof:placetype":"locality"
},
  "geometry": {"coordinates":[88.94583,26.20613],"type":"Point"}
}