{
  "type": "Feature",
  "properties": {
    "gn:admin1_code":"85",
    "gn:admin2_code":"1006",
    "gn:admin3_code":"100607.0",
    "gn:admin4_code":"10060733.0",
    "gn:asciiname":"Sundarkati",
    "gn:country_code":"BD",
    "gn:dem":9,
    "gn:feature_class":"P",
    "gn:feature_code":"PPL",
    "gn:name":"Sundark\u0101ti",
    "gn:population":0,
    "gn:timezone":"Asia/Dhaka",
    "iso:country":"BD",
    "wof:name":"Sundarkati",
    "wof:placetype":"locality"
},
  "geometry": {"coordinates":[90.41381,22.56258],"type":"Point"}
}