{
  "type": "Feature",
  "properties": {
    "gn:admin1_code":"81",
    "gn:admin2_code":"3054",
    "gn:admin3_code":"305440.0",
    "gn:admin4_code":"30544012.0",
    "gn:asciiname":"Pathuriapar",
    "gn:country_code":"BD",
    "gn:dem":9,
    "gn:feature_class":"P",
    "gn:feature_code":"PPL",
    "gn:name":"P\u0101thuriap\u0101r",
    "gn:population":0,
    "gn:timezone":"Asia/Dhaka",
    "iso:country":"BD",
    "name:und_x_variant":[
        "Pathurairpara",
        "P\u0101thuriap\u0101r"
    ],
    "wof:name":"Pathuriapar",
    "wof:placetype":"locality"
},
  "geometry": {"coordinates":[90.19714999999999,23.10281],"type":"Point"}
}