{
  "type": "Feature",
  "properties": {
    "gn:admin1_code":"87",
    "gn:admin2_code":"5594.0",
    "gn:admin3_code":"559494.0",
    "gn:admin4_code":"55949442.0",
    "gn:asciiname":"Milanpur",
    "gn:country_code":"BD",
    "gn:dem":61,
    "gn:feature_class":"P",
    "gn:feature_code":"PPL",
    "gn:name":"Mil\u0101npur",
    "gn:population":0,
    "gn:timezone":"Asia/Dhaka",
    "iso:country":"BD",
    "name:ben_x_preferred":[
        "Mil\u0101npur"
    ],
    "wof:name":"Milanpur",
    "wof:placetype":"locality"
},
  "geometry": {"coordinates":[88.55663,26.03197],"type":"Point"}
}