{
  "type": "Feature",
  "properties": {
    "gn:admin1_code":"87",
    "gn:admin2_code":"5527.0",
    "gn:admin3_code":"552712.0",
    "gn:admin4_code":"55271269.0",
    "gn:asciiname":"Kharikadam Khas",
    "gn:country_code":"BD",
    "gn:dem":54,
    "gn:feature_class":"P",
    "gn:feature_code":"PPL",
    "gn:name":"Kharik\u0101d\u0101m Kh\u0101s",
    "gn:population":0,
    "gn:timezone":"Asia/Dhaka",
    "iso:country":"BD",
    "name:ben_x_preferred":[
        "Kharik\u0101d\u0101m Kh\u0101s"
    ],
    "wof:name":"Kharikadam Khas",
    "wof:placetype":"locality"
},
  "geometry": {"coordinates":[88.67169,25.97227],"type":"Point"}
}