{
  "type": "Feature",
  "properties": {
    "gn:admin1_code":"84",
    "gn:admin2_code":"2022",
    "gn:admin3_code":"202216.0",
    "gn:admin4_code":"20221644.0",
    "gn:asciiname":"Rajarbil",
    "gn:country_code":"BD",
    "gn:dem":10,
    "gn:feature_class":"P",
    "gn:feature_code":"PPL",
    "gn:name":"R\u0101jarbil",
    "gn:population":0,
    "gn:timezone":"Asia/Dhaka",
    "iso:country":"BD",
    "name:ben_x_preferred":[
        "R\u0101jarbil"
    ],
    "wof:name":"Rajarbil",
    "wof:placetype":"locality"
},
  "geometry": {"coordinates":[92.10257,21.73489],"type":"Point"}
}