{
  "type": "Feature",
  "properties": {
    "gn:admin1_code":"81",
    "gn:admin2_code":"3056",
    "gn:admin3_code":"305646.0",
    "gn:admin4_code":"30564609.0",
    "gn:asciiname":"Mrijapur",
    "gn:country_code":"BD",
    "gn:dem":14,
    "gn:feature_class":"P",
    "gn:feature_code":"PPL",
    "gn:name":"Mrij\u0101pur",
    "gn:population":0,
    "gn:timezone":"Asia/Dhaka",
    "iso:country":"BD",
    "wof:name":"Mrijapur",
    "wof:placetype":"locality"
},
  "geometry": {"coordinates":[90.10248,23.87284],"type":"Point"}
}