{
  "type": "Feature",
  "properties": {
    "gn:admin1_code":"81",
    "gn:admin2_code":"3048",
    "gn:admin3_code":"304879.0",
    "gn:admin4_code":"30487947.0",
    "gn:asciiname":"Uttarpara",
    "gn:country_code":"BD",
    "gn:dem":18,
    "gn:feature_class":"P",
    "gn:feature_code":"PPL",
    "gn:name":"Uttarp\u0101ra",
    "gn:population":0,
    "gn:timezone":"Asia/Dhaka",
    "iso:country":"BD",
    "name:ben_x_preferred":[
        "\u0989\u09a4\u09cd\u09a4\u09b0\u09aa\u09be\u09a1\u09bc\u09be \u0995\u09cb\u09a4\u09b0\u0982"
    ],
    "name:bih_x_preferred":[
        "\u0909\u0924\u094d\u0924\u0930\u092a\u093e\u0921\u093c\u093e"
    ],
    "name:bpy_x_preferred":[
        "\u0989\u09a4\u09cd\u09a4\u09b0\u09aa\u09be\u09a1\u09bc\u09be \u0995\u09cb\u099f\u09b0\u09be\u0982"
    ],
    "name:ceb_x_preferred":[
        "Uttarp\u0101ra"
    ],
    "name:fas_x_preferred":[
        "\u0627\u0648\u062a\u0627\u0631\u067e\u0627\u0631\u0627"
    ],
    "name:hif_x_preferred":[
        "Uttarpara"
    ],
    "name:ind_x_preferred":[
        "Uttarpara Kotrung"
    ],
    "name:ita_x_preferred":[
        "Uttarpara Kotrung"
    ],
    "name:msa_x_preferred":[
        "Uttarpara Kotrung"
    ],
    "name:pol_x_preferred":[
        "Uttarpara"
    ],
    "name:por_x_preferred":[
        "Uttarpara Kotrung"
    ],
    "name:spa_x_preferred":[
        "Uttarpara"
    ],
    "name:swe_x_preferred":[
        "Uttarpara Kotrung"
    ],
    "name:vie_x_preferred":[
        "Uttarpara Kotrung"
    ],
    "name:zho_x_preferred":[
        "\u4e4c\u5854\u5c14\u5e15\u62c9\u79d1\u7279\u9f99\u683c"
    ],
    "wof:name":"Uttarpara",
    "wof:placetype":"locality"
},
  "geometry": {"coordinates":[90.70083,24.32056],"type":"Point"}
}