{
  "type": "Feature",
  "properties": {
    "gn:admin1_code":"81",
    "gn:admin2_code":"3048",
    "gn:admin3_code":"304879.0",
    "gn:admin4_code":"30487947.0",
    "gn:asciiname":"Uttarpara",
    "gn:country_code":"BD",
    "gn:dem":18,
    "gn:feature_class":"P",
    "gn:feature_code":"PPL",
    "gn:name":"Uttarp\u0101ra",
    "gn:population":0,
    "gn:timezone":"Asia/Dhaka",
    "iso:country":"BD",
    "wof:name":"Uttarpara",
    "wof:placetype":"locality"
},
  "geometry": {"coordinates":[90.70083,24.32056],"type":"Point"}
}