{
  "type": "Feature",
  "properties": {
    "gn:admin1_code":"87",
    "gn:admin2_code":"5577.0",
    "gn:admin3_code":"557773.0",
    "gn:admin4_code":"55777335.0",
    "gn:asciiname":"Garati",
    "gn:country_code":"BD",
    "gn:dem":80,
    "gn:feature_class":"P",
    "gn:feature_code":"PPL",
    "gn:name":"Gar\u0101ti",
    "gn:population":0,
    "gn:timezone":"Asia/Dhaka",
    "iso:country":"BD",
    "name:ara_x_preferred":[
        "\u063a\u0631\u0627\u062a\u064a"
    ],
    "name:ben_x_preferred":[
        "Gar\u0101ti"
    ],
    "name:ceb_x_preferred":[
        "Gar\u0101t\u012b"
    ],
    "name:fas_x_preferred":[
        "\u06af\u0631\u0627\u062a\u06cc"
    ],
    "name:swe_x_preferred":[
        "Gar\u0101t\u012b"
    ],
    "wof:name":"Garati",
    "wof:placetype":"locality"
},
  "geometry": {"coordinates":[88.62104000000002,26.3936],"type":"Point"}
}