{
  "type": "Feature",
  "properties": {
    "gn:admin1_code":"85",
    "gn:admin2_code":"1006",
    "gn:admin3_code":"100632.0",
    "gn:admin4_code":"10063271.0",
    "gn:asciiname":"Labutali",
    "gn:country_code":"BD",
    "gn:dem":10,
    "gn:feature_class":"P",
    "gn:feature_code":"PPL",
    "gn:name":"Labutali",
    "gn:population":0,
    "gn:timezone":"Asia/Dhaka",
    "iso:country":"BD",
    "name:und_x_variant":[
        "Lebutali",
        "Labutali"
    ],
    "wof:name":"Labutali",
    "wof:placetype":"locality"
},
  "geometry": {"coordinates":[90.24692,22.95081],"type":"Point"}
}