{
  "type": "Feature",
  "properties": {
    "gn:admin1_code":"H",
    "gn:admin2_code":"3061",
    "gn:admin3_code":"306194.0",
    "gn:admin4_code":"30619419.0",
    "gn:asciiname":"Kalsiddhaya",
    "gn:country_code":"BD",
    "gn:dem":15,
    "gn:feature_class":"P",
    "gn:feature_code":"PPL",
    "gn:name":"K\u0101lsiddhaya",
    "gn:population":0,
    "gn:timezone":"Asia/Dhaka",
    "iso:country":"BD",
    "name:und_x_variant":[
        "K\u0101lsiddhaya",
        "K\u0101lsiddhya"
    ],
    "wof:name":"Kalsiddhaya",
    "wof:placetype":"locality"
},
  "geometry": {"coordinates":[90.50497,24.58625],"type":"Point"}
}