{
  "type": "Feature",
  "properties": {
    "gn:admin1_code":"83",
    "gn:admin2_code":"5038.0",
    "gn:admin3_code":"503874.0",
    "gn:admin4_code":"50387452.0",
    "gn:asciiname":"Goneshpur",
    "gn:country_code":"BD",
    "gn:dem":26,
    "gn:feature_class":"P",
    "gn:feature_code":"PPL",
    "gn:name":"Goneshpur",
    "gn:population":0,
    "gn:timezone":"Asia/Dhaka",
    "iso:country":"BD",
    "name:ben_x_preferred":[
        "Goneshpur"
    ],
    "wof:name":"Goneshpur",
    "wof:placetype":"locality"
},
  "geometry": {"coordinates":[89.03529,25.19412],"type":"Point"}
}