{
  "type": "Feature",
  "properties": {
    "gn:admin1_code":"83",
    "gn:admin2_code":"5064.0",
    "gn:admin3_code":"506428.0",
    "gn:admin4_code":"50642863.0",
    "gn:asciiname":"Kokil",
    "gn:country_code":"BD",
    "gn:dem":22,
    "gn:feature_class":"P",
    "gn:feature_code":"PPL",
    "gn:name":"Kokil",
    "gn:population":0,
    "gn:timezone":"Asia/Dhaka",
    "iso:country":"BD",
    "name:ben_x_preferred":[
        "Kokil"
    ],
    "wof:name":"Kokil",
    "wof:placetype":"locality"
},
  "geometry": {"coordinates":[88.89830000000001,25.11696],"type":"Point"}
}