{
  "type": "Feature",
  "properties": {
    "gn:admin1_code":"82",
    "gn:admin2_code":"4087",
    "gn:admin3_code":"408704.0",
    "gn:admin4_code":"40870408.0",
    "gn:asciiname":"Rajapur",
    "gn:country_code":"BD",
    "gn:dem":7,
    "gn:feature_class":"P",
    "gn:feature_code":"PPL",
    "gn:name":"R\u0101j\u0101pur",
    "gn:population":0,
    "gn:timezone":"Asia/Dhaka",
    "iso:country":"BD",
    "name:ben_x_preferred":[
        "R\u0101j\u0101pur"
    ],
    "name:ceb_x_preferred":[
        "Rajapur"
    ],
    "name:fra_x_preferred":[
        "Rajapur"
    ],
    "name:ita_x_preferred":[
        "Rajapur"
    ],
    "name:pol_x_preferred":[
        "Rajapur"
    ],
    "name:swe_x_preferred":[
        "Rajapur"
    ],
    "wof:name":"Rajapur",
    "wof:placetype":"locality"
},
  "geometry": {"coordinates":[89.22031,22.41588],"type":"Point"}
}