{
  "type": "Feature",
  "properties": {
    "gn:admin1_code":"87",
    "gn:admin2_code":"5594.0",
    "gn:admin3_code":"559494.0",
    "gn:admin4_code":"55949494.0",
    "gn:asciiname":"Lauthuti",
    "gn:country_code":"BD",
    "gn:dem":60,
    "gn:feature_class":"P",
    "gn:feature_code":"PPL",
    "gn:name":"L\u0101uthuti",
    "gn:population":0,
    "gn:timezone":"Asia/Dhaka",
    "iso:country":"BD",
    "name:ben_x_preferred":[
        "L\u0101uthuti"
    ],
    "wof:name":"Lauthuti",
    "wof:placetype":"locality"
},
  "geometry": {"coordinates":[88.5907,26.10134],"type":"Point"}
}