{
  "type": "Feature",
  "properties": {
    "gn:admin1_code":"81",
    "gn:admin2_code":"3059.0",
    "gn:admin3_code":"305924.0",
    "gn:admin4_code":"30592421.0",
    "gn:asciiname":"Chanda Kahania",
    "gn:country_code":"BD",
    "gn:dem":8,
    "gn:feature_class":"P",
    "gn:feature_code":"PPL",
    "gn:name":"Chanda K\u0101h\u0101nia",
    "gn:population":0,
    "gn:timezone":"Asia/Dhaka",
    "iso:country":"BD",
    "name:und_x_variant":[
        "Chaudda Kahania",
        "Chanda K\u0101h\u0101nia"
    ],
    "wof:name":"Chanda Kahania",
    "wof:placetype":"locality"
},
  "geometry": {"coordinates":[90.64534,23.51915],"type":"Point"}
}