{
  "type": "Feature",
  "properties": {
    "gn:admin1_code":"87",
    "gn:admin2_code":"5577.0",
    "gn:admin3_code":"557773.0",
    "gn:admin4_code":"55777311.0",
    "gn:asciiname":"Baniyapara",
    "gn:country_code":"BD",
    "gn:dem":84,
    "gn:feature_class":"P",
    "gn:feature_code":"PPL",
    "gn:name":"Baniyap\u0101ra",
    "gn:population":0,
    "gn:timezone":"Asia/Dhaka",
    "iso:country":"BD",
    "name:ben_x_preferred":[
        "Baniyap\u0101ra"
    ],
    "wof:name":"Baniyapara",
    "wof:placetype":"locality"
},
  "geometry": {"coordinates":[88.56754000000002,26.41277],"type":"Point"}
}