{
  "type": "Feature",
  "properties": {
    "gn:admin1_code":"81",
    "gn:admin2_code":"3035",
    "gn:admin3_code":"303532.0",
    "gn:admin4_code":"30353286.0",
    "gn:asciiname":"Sutail",
    "gn:country_code":"BD",
    "gn:dem":9,
    "gn:feature_class":"P",
    "gn:feature_code":"PPL",
    "gn:name":"Sut\u0101il",
    "gn:population":0,
    "gn:timezone":"Asia/Dhaka",
    "iso:country":"BD",
    "name:ben_x_preferred":[
        "Sut\u0101il"
    ],
    "name:und_x_variant":[
        "Suktail"
    ],
    "wof:name":"Sutail",
    "wof:placetype":"locality"
},
  "geometry": {"coordinates":[89.72976,23.09979],"type":"Point"}
}