{
  "type": "Feature",
  "properties": {
    "gn:admin1_code":"87",
    "gn:admin2_code":"5527.0",
    "gn:admin3_code":"552730.0",
    "gn:admin4_code":"55273031.0",
    "gn:asciiname":"Chhota Kaul",
    "gn:country_code":"BD",
    "gn:dem":40,
    "gn:feature_class":"P",
    "gn:feature_code":"PPL",
    "gn:name":"Chhota K\u0101ul",
    "gn:population":0,
    "gn:timezone":"Asia/Dhaka",
    "iso:country":"BD",
    "name:ben_x_preferred":[
        "Chhota K\u0101ul"
    ],
    "wof:name":"Chhota Kaul",
    "wof:placetype":"locality"
},
  "geometry": {"coordinates":[88.75884000000001,25.63761],"type":"Point"}
}