{
  "type": "Feature",
  "properties": {
    "gn:admin1_code":"83",
    "gn:admin2_code":"5081",
    "gn:admin3_code":"508131.0",
    "gn:admin4_code":"50813123.0",
    "gn:asciiname":"Kachupara",
    "gn:country_code":"BD",
    "gn:dem":20,
    "gn:feature_class":"P",
    "gn:feature_code":"PPL",
    "gn:name":"K\u0101chup\u0101ra",
    "gn:population":0,
    "gn:timezone":"Asia/Dhaka",
    "iso:country":"BD",
    "name:ben_x_preferred":[
        "K\u0101chup\u0101ra"
    ],
    "wof:name":"Kachupara",
    "wof:placetype":"locality"
},
  "geometry": {"coordinates":[88.77589,24.44926],"type":"Point"}
}