{
  "type": "Feature",
  "properties": {
    "gn:admin1_code":"81",
    "gn:admin2_code":"3082.0",
    "gn:admin3_code":"308276.0",
    "gn:admin4_code":"30827651.0",
    "gn:asciiname":"Ambaria",
    "gn:country_code":"BD",
    "gn:dem":1,
    "gn:feature_class":"P",
    "gn:feature_code":"PPL",
    "gn:name":"\u0100mb\u0101ria",
    "gn:population":0,
    "gn:timezone":"Asia/Dhaka",
    "iso:country":"BD",
    "name:ben_x_preferred":[
        "\u0100mb\u0101ria"
    ],
    "wof:name":"Ambaria",
    "wof:placetype":"locality"
},
  "geometry": {"coordinates":[89.69198,23.79485],"type":"Point"}
}