{
  "type": "Feature",
  "properties": {
    "gn:admin1_code":"87",
    "gn:admin2_code":"5527.0",
    "gn:admin3_code":"552712.0",
    "gn:admin4_code":"55271234.0",
    "gn:asciiname":"Bhagirpara",
    "gn:country_code":"BD",
    "gn:dem":52,
    "gn:feature_class":"P",
    "gn:feature_code":"PPL",
    "gn:name":"Bhagirp\u0101ra",
    "gn:population":0,
    "gn:timezone":"Asia/Dhaka",
    "iso:country":"BD",
    "name:ben_x_preferred":[
        "Bhagirp\u0101ra"
    ],
    "wof:name":"Bhagirpara",
    "wof:placetype":"locality"
},
  "geometry": {"coordinates":[88.70368000000001,25.9604],"type":"Point"}
}