{
  "type": "Feature",
  "properties": {
    "gn:admin1_code":"87",
    "gn:admin2_code":"5549",
    "gn:admin3_code":"554979.0",
    "gn:admin4_code":"55497983.0",
    "gn:asciiname":"Bausmari",
    "gn:country_code":"BD",
    "gn:dem":28,
    "gn:feature_class":"P",
    "gn:feature_code":"PPL",
    "gn:name":"Bausm\u0101ri",
    "gn:population":0,
    "gn:timezone":"Asia/Dhaka",
    "iso:country":"BD",
    "name:ben_x_preferred":[
        "Bausm\u0101ri"
    ],
    "name:und_x_variant":[
        "Gird Bausm\u0101ri"
    ],
    "wof:name":"Bausmari",
    "wof:placetype":"locality"
},
  "geometry": {"coordinates":[89.84432,25.58448],"type":"Point"}
}