{
  "type": "Feature",
  "properties": {
    "gn:admin1_code":"82",
    "gn:admin2_code":"4018.0",
    "gn:admin3_code":"401807.0",
    "gn:admin4_code":"40180779.0",
    "gn:asciiname":"Hakimpur",
    "gn:country_code":"BD",
    "gn:dem":15,
    "gn:feature_class":"P",
    "gn:feature_code":"PPL",
    "gn:name":"Hakimpur",
    "gn:population":0,
    "gn:timezone":"Asia/Dhaka",
    "iso:country":"BD",
    "name:ben_x_preferred":[
        "Hakimpur"
    ],
    "wof:name":"Hakimpur",
    "wof:placetype":"locality"
},
  "geometry": {"coordinates":[88.97629000000001,23.62465],"type":"Point"}
}