{
  "type": "Feature",
  "properties": {
    "gn:admin1_code":"H",
    "gn:admin2_code":"3039",
    "gn:admin3_code":"303915.0",
    "gn:admin4_code":"30391558.0",
    "gn:asciiname":"Cazokanda",
    "gn:country_code":"BD",
    "gn:dem":20,
    "gn:feature_class":"P",
    "gn:feature_code":"PPL",
    "gn:name":"Cazokanda",
    "gn:population":0,
    "gn:timezone":"Asia/Dhaka",
    "iso:country":"BD",
    "name:ben_x_preferred":[
        "Cazokanda"
    ],
    "wof:name":"Cazokanda",
    "wof:placetype":"locality"
},
  "geometry": {"coordinates":[89.78505,25.12541],"type":"Point"}
}