{
  "type": "Feature",
  "properties": {
    "gn:admin1_code":"81",
    "gn:admin2_code":"3048",
    "gn:admin3_code":"304806.0",
    "gn:admin4_code":"30480643.0",
    "gn:asciiname":"Khonkarkandi",
    "gn:country_code":"BD",
    "gn:dem":13,
    "gn:feature_class":"P",
    "gn:feature_code":"PPL",
    "gn:name":"Khonk\u0101rk\u0101ndi",
    "gn:population":0,
    "gn:timezone":"Asia/Dhaka",
    "iso:country":"BD",
    "wof:name":"Khonkarkandi",
    "wof:placetype":"locality"
},
  "geometry": {"coordinates":[90.94280000000001,24.19731],"type":"Point"}
}