{
  "type": "Feature",
  "properties": {
    "gn:admin1_code":"82",
    "gn:admin2_code":"4050",
    "gn:admin3_code":"405039.0",
    "gn:admin4_code":"40503974.0",
    "gn:asciiname":"Thotarpara",
    "gn:country_code":"BD",
    "gn:dem":8,
    "gn:feature_class":"P",
    "gn:feature_code":"PPL",
    "gn:name":"Thot\u0101rp\u0101ra",
    "gn:population":0,
    "gn:timezone":"Asia/Dhaka",
    "iso:country":"BD",
    "wof:name":"Thotarpara",
    "wof:placetype":"locality"
},
  "geometry": {"coordinates":[88.84999999999999,24.08333],"type":"Point"}
}