{
  "type": "Feature",
  "properties": {
    "gn:admin1_code":"82",
    "gn:admin2_code":"4065.0",
    "gn:admin3_code":"406528.0",
    "gn:admin4_code":"40652807.0",
    "gn:asciiname":"Baratola",
    "gn:country_code":"BD",
    "gn:dem":11,
    "gn:feature_class":"P",
    "gn:feature_code":"PPL",
    "gn:name":"Baratola",
    "gn:population":0,
    "gn:timezone":"Asia/Dhaka",
    "iso:country":"BD",
    "name:ben_x_preferred":[
        "Baratola"
    ],
    "wof:name":"Baratola",
    "wof:placetype":"locality"
},
  "geometry": {"coordinates":[89.61587,23.07678],"type":"Point"}
}