{
  "type": "Feature",
  "properties": {
    "gn:admin1_code":"87",
    "gn:admin2_code":"5527.0",
    "gn:admin3_code":"552760.0",
    "gn:admin4_code":"55276063.0",
    "gn:asciiname":"Chak Rampur",
    "gn:country_code":"BD",
    "gn:dem":50,
    "gn:feature_class":"P",
    "gn:feature_code":"PPL",
    "gn:name":"Chak R\u0101mpur",
    "gn:population":0,
    "gn:timezone":"Asia/Dhaka",
    "iso:country":"BD",
    "name:ben_x_preferred":[
        "Chak R\u0101mpur"
    ],
    "wof:name":"Chak Rampur",
    "wof:placetype":"locality"
},
  "geometry": {"coordinates":[88.76918000000001,25.89471],"type":"Point"}
}