{
  "type": "Feature",
  "properties": {
    "gn:admin1_code":"82",
    "gn:admin2_code":"4050.0",
    "gn:admin3_code":"405079.0",
    "gn:admin4_code":"40507963.0",
    "gn:asciiname":"Alinagar",
    "gn:country_code":"BD",
    "gn:dem":17,
    "gn:feature_class":"P",
    "gn:feature_code":"PPL",
    "gn:name":"Alinagar",
    "gn:population":0,
    "gn:timezone":"Asia/Dhaka",
    "iso:country":"BD",
    "name:ben_x_preferred":[
        "Alinagar"
    ],
    "wof:name":"Alinagar",
    "wof:placetype":"locality"
},
  "geometry": {"coordinates":[89.07043,23.80265],"type":"Point"}
}