{
  "type": "Feature",
  "properties": {
    "gn:admin1_code":"83",
    "gn:admin2_code":"5064.0",
    "gn:admin3_code":"506450.0",
    "gn:admin4_code":"50645095.0",
    "gn:asciiname":"Mollarhat",
    "gn:country_code":"BD",
    "gn:dem":18,
    "gn:feature_class":"P",
    "gn:feature_code":"PPL",
    "gn:name":"Moll\u0101rh\u0101t",
    "gn:population":0,
    "gn:timezone":"Asia/Dhaka",
    "iso:country":"BD",
    "name:ben_x_preferred":[
        "Moll\u0101rh\u0101t"
    ],
    "wof:name":"Mollarhat",
    "wof:placetype":"locality"
},
  "geometry": {"coordinates":[88.7959,24.89035],"type":"Point"}
}