{
  "type": "Feature",
  "properties": {
    "gn:admin1_code":"82",
    "gn:admin2_code":"4047",
    "gn:admin3_code":"404730.0",
    "gn:admin4_code":"40473081.0",
    "gn:asciiname":"Sahas",
    "gn:country_code":"BD",
    "gn:dem":7,
    "gn:feature_class":"P",
    "gn:feature_code":"PPL",
    "gn:name":"S\u0101has",
    "gn:population":0,
    "gn:timezone":"Asia/Dhaka",
    "iso:country":"BD",
    "wof:name":"Sahas",
    "wof:placetype":"locality"
},
  "geometry": {"coordinates":[89.40978,22.76683],"type":"Point"}
}