{
  "type": "Feature",
  "properties": {
    "gn:admin1_code":"H",
    "gn:admin2_code":"3089",
    "gn:admin3_code":"308937.0",
    "gn:admin4_code":"30893760.0",
    "gn:asciiname":"Barwa",
    "gn:country_code":"BD",
    "gn:dem":29,
    "gn:feature_class":"P",
    "gn:feature_code":"PPL",
    "gn:name":"Barwa",
    "gn:population":0,
    "gn:timezone":"Asia/Dhaka",
    "iso:country":"BD",
    "name:deu_x_preferred":[
        "Barwa"
    ],
    "name:slv_x_preferred":[
        "Barwa"
    ],
    "wof:name":"Barwa",
    "wof:placetype":"locality"
},
  "geometry": {"coordinates":[90.10307,25.18991],"type":"Point"}
}