{
  "type": "Feature",
  "properties": {
    "gn:admin1_code":"81",
    "gn:admin2_code":"3056.0",
    "gn:admin3_code":"305646.0",
    "gn:admin4_code":"30564609.0",
    "gn:asciiname":"Bartha",
    "gn:country_code":"BD",
    "gn:dem":13,
    "gn:feature_class":"P",
    "gn:feature_code":"PPL",
    "gn:name":"B\u0101rtha",
    "gn:population":0,
    "gn:timezone":"Asia/Dhaka",
    "iso:country":"BD",
    "wof:name":"Bartha",
    "wof:placetype":"locality"
},
  "geometry": {"coordinates":[90.12226,23.85866],"type":"Point"}
}