{
  "type": "Feature",
  "properties": {
    "gn:admin1_code":"82",
    "gn:admin2_code":"4055",
    "gn:admin3_code":"405595.0",
    "gn:admin4_code":"40559552.0",
    "gn:asciiname":"Sapalgacha",
    "gn:country_code":"BD",
    "gn:dem":14,
    "gn:feature_class":"P",
    "gn:feature_code":"PPL",
    "gn:name":"Sapalg\u0101cha",
    "gn:population":0,
    "gn:timezone":"Asia/Dhaka",
    "iso:country":"BD",
    "name:und_x_variant":[
        "Saphalgacha",
        "Sapalg\u0101cha"
    ],
    "wof:name":"Sapalgacha",
    "wof:placetype":"locality"
},
  "geometry": {"coordinates":[89.51045999999999,23.53933],"type":"Point"}
}