{
  "type": "Feature",
  "properties": {
    "gn:admin1_code":"87",
    "gn:admin2_code":"5585",
    "gn:admin3_code":"558592.0",
    "gn:admin4_code":"55859263.0",
    "gn:asciiname":"Dologach",
    "gn:country_code":"BD",
    "gn:dem":38,
    "gn:feature_class":"P",
    "gn:feature_code":"PPL",
    "gn:name":"Dolog\u0101ch",
    "gn:population":0,
    "gn:timezone":"Asia/Dhaka",
    "iso:country":"BD",
    "name:ben_x_preferred":[
        "Dolog\u0101ch"
    ],
    "wof:name":"Dologach",
    "wof:placetype":"locality"
},
  "geometry": {"coordinates":[89.10526,25.7624],"type":"Point"}
}