{
  "type": "Feature",
  "properties": {
    "gn:admin1_code":"87",
    "gn:admin2_code":"5577.0",
    "gn:admin3_code":"557704.0",
    "gn:admin4_code":"55770454.0",
    "gn:asciiname":"Majgaon",
    "gn:country_code":"BD",
    "gn:dem":70,
    "gn:feature_class":"P",
    "gn:feature_code":"PPL",
    "gn:name":"M\u0101jgaon",
    "gn:population":0,
    "gn:timezone":"Asia/Dhaka",
    "iso:country":"BD",
    "name:ben_x_preferred":[
        "M\u0101jgaon"
    ],
    "name:bpy_x_preferred":[
        "\u09ae\u09be\u099d\u0997\u09be\u0981\u0993"
    ],
    "name:ita_x_preferred":[
        "Majgaon"
    ],
    "name:msa_x_preferred":[
        "Majgaon"
    ],
    "name:nld_x_preferred":[
        "Majgaon"
    ],
    "name:por_x_preferred":[
        "Majgaon"
    ],
    "name:vie_x_preferred":[
        "Majgaon"
    ],
    "name:zho_x_preferred":[
        "\u9a6c\u6770\u52a0\u5965\u6069"
    ],
    "wof:name":"Majgaon",
    "wof:placetype":"locality"
},
  "geometry": {"coordinates":[88.43353,26.25599],"type":"Point"}
}