{
  "type": "Feature",
  "properties": {
    "gn:admin1_code":"87",
    "gn:admin2_code":"5573.0",
    "gn:admin3_code":"557315.0",
    "gn:admin4_code":"55731519.0",
    "gn:asciiname":"Kaulapara",
    "gn:country_code":"BD",
    "gn:dem":68,
    "gn:feature_class":"P",
    "gn:feature_code":"PPL",
    "gn:name":"Kaulap\u0101ra",
    "gn:population":0,
    "gn:timezone":"Asia/Dhaka",
    "iso:country":"BD",
    "name:ben_x_preferred":[
        "Kaulap\u0101ra"
    ],
    "wof:name":"Kaulapara",
    "wof:placetype":"locality"
},
  "geometry": {"coordinates":[88.77896,26.26166],"type":"Point"}
}