{
  "type": "Feature",
  "properties": {
    "gn:admin1_code":"81",
    "gn:admin2_code":"3059",
    "gn:admin3_code":"305984.0",
    "gn:admin4_code":"30598454.0",
    "gn:asciiname":"Paschim Naopara",
    "gn:country_code":"BD",
    "gn:dem":10,
    "gn:feature_class":"P",
    "gn:feature_code":"PPL",
    "gn:name":"Paschim Naop\u0101ra",
    "gn:population":0,
    "gn:timezone":"Asia/Dhaka",
    "iso:country":"BD",
    "wof:name":"Paschim Naopara",
    "wof:placetype":"locality"
},
  "geometry": {"coordinates":[90.32429999999999,23.52],"type":"Point"}
}