{
  "type": "Feature",
  "properties": {
    "gn:admin1_code":"83",
    "gn:admin2_code":"5081.0",
    "gn:admin3_code":"508131.0",
    "gn:admin4_code":"50813183.0",
    "gn:asciiname":"Noapara",
    "gn:country_code":"BD",
    "gn:dem":19,
    "gn:feature_class":"P",
    "gn:feature_code":"PPL",
    "gn:name":"Noap\u0101ra",
    "gn:population":0,
    "gn:timezone":"Asia/Dhaka",
    "iso:country":"BD",
    "name:ben_x_preferred":[
        "Noap\u0101ra"
    ],
    "wof:name":"Noapara",
    "wof:placetype":"locality"
},
  "geometry": {"coordinates":[88.76509,24.50103],"type":"Point"}
}