{
  "type": "Feature",
  "properties": {
    "gn:admin1_code":"85",
    "gn:admin2_code":"1006.0",
    "gn:admin3_code":"100632.0",
    "gn:admin4_code":"10063255.0",
    "gn:asciiname":"Bagiser Par",
    "gn:country_code":"BD",
    "gn:dem":8,
    "gn:feature_class":"P",
    "gn:feature_code":"PPL",
    "gn:name":"B\u0101giser P\u0101r",
    "gn:population":0,
    "gn:timezone":"Asia/Dhaka",
    "iso:country":"BD",
    "name:und_x_variant":[
        "Bagiserpur",
        "Bagisherpur",
        "B\u0101giser P\u0101r"
    ],
    "wof:name":"Bagiser Par",
    "wof:placetype":"locality"
},
  "geometry": {"coordinates":[90.20107,23.04558],"type":"Point"}
}