{
  "type": "Feature",
  "properties": {
    "gn:admin1_code":"83",
    "gn:admin2_code":"5064.0",
    "gn:admin3_code":"506428.0",
    "gn:admin4_code":"50642810.0",
    "gn:asciiname":"Kalipur",
    "gn:country_code":"BD",
    "gn:dem":26,
    "gn:feature_class":"P",
    "gn:feature_code":"PPL",
    "gn:name":"Kalipur",
    "gn:population":0,
    "gn:timezone":"Asia/Dhaka",
    "iso:country":"BD",
    "name:ben_x_preferred":[
        "Kalipur"
    ],
    "wof:name":"Kalipur",
    "wof:placetype":"locality"
},
  "geometry": {"coordinates":[88.70028000000001,25.17919],"type":"Point"}
}