{
  "type": "Feature",
  "properties": {
    "gn:admin1_code":"81",
    "gn:admin2_code":"3026.0",
    "gn:admin3_code":"302618.0",
    "gn:admin4_code":"30261863.0",
    "gn:asciiname":"Hatni",
    "gn:country_code":"BD",
    "gn:dem":10,
    "gn:feature_class":"P",
    "gn:feature_code":"PPL",
    "gn:name":"H\u0101tni",
    "gn:population":0,
    "gn:timezone":"Asia/Dhaka",
    "iso:country":"BD",
    "wof:name":"Hatni",
    "wof:placetype":"locality"
},
  "geometry": {"coordinates":[90.03463000000001,23.65015],"type":"Point"}
}