{
  "type": "Feature",
  "properties": {
    "gn:admin1_code":"87",
    "gn:admin2_code":"5549",
    "gn:admin3_code":"554961.0",
    "gn:admin4_code":"55496163.0",
    "gn:asciiname":"Jhaukuthi",
    "gn:country_code":"BD",
    "gn:dem":28,
    "gn:feature_class":"P",
    "gn:feature_code":"PPL",
    "gn:name":"Jhaukuthi",
    "gn:population":0,
    "gn:timezone":"Asia/Dhaka",
    "iso:country":"BD",
    "name:ben_x_preferred":[
        "Jhaukuthi"
    ],
    "wof:name":"Jhaukuthi",
    "wof:placetype":"locality"
},
  "geometry": {"coordinates":[89.84938000000002,25.92417],"type":"Point"}
}