{
  "type": "Feature",
  "properties": {
    "gn:admin1_code":"87",
    "gn:admin2_code":"5585.0",
    "gn:admin3_code":"558573.0",
    "gn:admin4_code":"55857385.0",
    "gn:asciiname":"Paran",
    "gn:country_code":"BD",
    "gn:dem":31,
    "gn:feature_class":"P",
    "gn:feature_code":"PPL",
    "gn:name":"Paran",
    "gn:population":0,
    "gn:timezone":"Asia/Dhaka",
    "iso:country":"BD",
    "name:ben_x_preferred":[
        "Paran"
    ],
    "wof:name":"Paran",
    "wof:placetype":"locality"
},
  "geometry": {"coordinates":[89.44478000000002,25.66909],"type":"Point"}
}