{
  "type": "Feature",
  "properties": {
    "gn:admin1_code":"81",
    "gn:admin2_code":"3033",
    "gn:admin3_code":"303332.0",
    "gn:admin4_code":"30333257.0",
    "gn:asciiname":"Sakasar",
    "gn:country_code":"BD",
    "gn:dem":18,
    "gn:feature_class":"P",
    "gn:feature_code":"PPL",
    "gn:name":"S\u0101k\u0101s\u0101r",
    "gn:population":0,
    "gn:timezone":"Asia/Dhaka",
    "iso:country":"BD",
    "wof:name":"Sakasar",
    "wof:placetype":"locality"
},
  "geometry": {"coordinates":[90.32599999999999,24.05756],"type":"Point"}
}