{
  "type": "Feature",
  "properties": {
    "gn:admin1_code":"81",
    "gn:admin2_code":"3026",
    "gn:admin3_code":"302640.0",
    "gn:admin4_code":"30264036.0",
    "gn:asciiname":"Paltan",
    "gn:country_code":"BD",
    "gn:dem":18,
    "gn:feature_class":"P",
    "gn:feature_code":"PPL",
    "gn:name":"Paltan",
    "gn:population":184492,
    "gn:timezone":"Asia/Dhaka",
    "iso:country":"BD",
    "name:ceb_x_preferred":[
        "Paltan"
    ],
    "name:swe_x_preferred":[
        "Paltan"
    ],
    "name:und_x_variant":[
        "Paltan, Dhaka, Bangladesh"
    ],
    "wof:name":"Paltan",
    "wof:placetype":"locality",
    "wof:population":184492
},
  "geometry": {"coordinates":[90.41426,23.73625],"type":"Point"}
}