{
  "type": "Feature",
  "properties": {
    "gn:admin1_code":"81",
    "gn:admin2_code":"3093",
    "gn:admin3_code":"309328.0",
    "gn:admin4_code":"30932834.0",
    "gn:asciiname":"Uttar Dhalapara",
    "gn:country_code":"BD",
    "gn:dem":17,
    "gn:feature_class":"P",
    "gn:feature_code":"PPL",
    "gn:name":"Uttar Dhal\u0101p\u0101ra",
    "gn:population":0,
    "gn:timezone":"Asia/Dhaka",
    "iso:country":"BD",
    "wof:name":"Uttar Dhalapara",
    "wof:placetype":"locality"
},
  "geometry": {"coordinates":[90.10008999999999,24.47094],"type":"Point"}
}