{
  "type": "Feature",
  "properties": {
    "gn:admin1_code":"87",
    "gn:admin2_code":"5549",
    "gn:admin3_code":"554994.0",
    "gn:admin4_code":"55499450.0",
    "gn:asciiname":"Sarkerpara",
    "gn:country_code":"BD",
    "gn:dem":28,
    "gn:feature_class":"P",
    "gn:feature_code":"PPL",
    "gn:name":"S\u0101rkerpara",
    "gn:population":0,
    "gn:timezone":"Asia/Dhaka",
    "iso:country":"BD",
    "name:ben_x_preferred":[
        "S\u0101rkerpara"
    ],
    "wof:name":"Sarkerpara",
    "wof:placetype":"locality"
},
  "geometry": {"coordinates":[89.63797,25.74032],"type":"Point"}
}