{
  "type": "Feature",
  "properties": {
    "gn:admin1_code":"83",
    "gn:admin2_code":"5010",
    "gn:admin3_code":"501067.0",
    "gn:admin4_code":"50106710.0",
    "gn:asciiname":"Kalyannagar",
    "gn:country_code":"BD",
    "gn:dem":16,
    "gn:feature_class":"P",
    "gn:feature_code":"PPL",
    "gn:name":"Kaly\u0101nnagar",
    "gn:population":0,
    "gn:timezone":"Asia/Dhaka",
    "iso:country":"BD",
    "wof:name":"Kalyannagar",
    "wof:placetype":"locality"
},
  "geometry": {"coordinates":[89.23333000000002,24.68333],"type":"Point"}
}