{
  "type": "Feature",
  "properties": {
    "gn:admin1_code":"81",
    "gn:admin2_code":"3093",
    "gn:admin3_code":"309385.0",
    "gn:admin4_code":"30938567.0",
    "gn:asciiname":"Kazirampur",
    "gn:country_code":"BD",
    "gn:dem":18,
    "gn:feature_class":"P",
    "gn:feature_code":"PPL",
    "gn:name":"K\u0101zir\u0101mpur",
    "gn:population":0,
    "gn:timezone":"Asia/Dhaka",
    "iso:country":"BD",
    "wof:name":"Kazirampur",
    "wof:placetype":"locality"
},
  "geometry": {"coordinates":[90.12307,24.41136],"type":"Point"}
}