{
  "type": "Feature",
  "properties": {
    "gn:admin1_code":"83",
    "gn:admin2_code":"5064.0",
    "gn:admin3_code":"506428.0",
    "gn:admin4_code":"50642821.0",
    "gn:asciiname":"Chak Noai",
    "gn:country_code":"BD",
    "gn:dem":28,
    "gn:feature_class":"P",
    "gn:feature_code":"PPL",
    "gn:name":"Chak No\u0101i",
    "gn:population":0,
    "gn:timezone":"Asia/Dhaka",
    "iso:country":"BD",
    "name:ben_x_preferred":[
        "Chak No\u0101i"
    ],
    "wof:name":"Chak Noai",
    "wof:placetype":"locality"
},
  "geometry": {"coordinates":[88.82044,25.12308],"type":"Point"}
}