{
  "type": "Feature",
  "properties": {
    "gn:admin1_code":"81",
    "gn:admin2_code":"3059",
    "gn:admin3_code":"305974.0",
    "gn:admin4_code":"30597461.0",
    "gn:asciiname":"Ramananda",
    "gn:country_code":"BD",
    "gn:dem":8,
    "gn:feature_class":"P",
    "gn:feature_code":"PPL",
    "gn:name":"R\u0101m\u0101nanda",
    "gn:population":0,
    "gn:timezone":"Asia/Dhaka",
    "iso:country":"BD",
    "name:ckb_x_preferred":[
        "\u0695\u0627\u0645\u0627\u0646\u0627\u0646\u062f\u0627"
    ],
    "name:fra_x_preferred":[
        "Ramanand"
    ],
    "name:hin_x_preferred":[
        "\u0930\u093e\u092e\u093e\u0928\u0928\u094d\u0926"
    ],
    "name:ita_x_preferred":[
        "R\u0101m\u0101nanda"
    ],
    "name:jpn_x_preferred":[
        "\u30e9\u30fc\u30de\u30fc\u30ca\u30f3\u30c0"
    ],
    "name:nep_x_preferred":[
        "\u0938\u094d\u0935\u093e\u092e\u0940 \u0930\u093e\u092e\u093e\u0928\u0928\u094d\u0926\u093e\u091a\u093e\u0930\u094d\u092f"
    ],
    "name:nno_x_preferred":[
        "Ramananda"
    ],
    "name:pan_x_preferred":[
        "\u0a2d\u0a17\u0a24 \u0a30\u0a3e\u0a2e\u0a3e\u0a28\u0a70\u0a26"
    ],
    "name:pnb_x_preferred":[
        "\u0628\u06be\u06af\u062a \u0631\u0627\u0645\u0627\u0646\u0646\u062f"
    ],
    "name:por_x_preferred":[
        "Ramananda"
    ],
    "name:rus_x_preferred":[
        "\u0420\u0430\u043c\u0430\u043d\u0430\u043d\u0434\u0430"
    ],
    "name:san_x_preferred":[
        "\u0917\u0941\u0930\u0941 \u0930\u093e\u092e\u093e\u0928\u0928\u094d\u0926"
    ],
    "name:swe_x_preferred":[
        "Ramananda"
    ],
    "name:tam_x_preferred":[
        "\u0b87\u0bb0\u0bbe\u0bae\u0bbe\u0ba8\u0ba8\u0bcd\u0ba4\u0bb0\u0bcd"
    ],
    "wof:name":"Ramananda",
    "wof:placetype":"locality"
},
  "geometry": {"coordinates":[90.40237,23.59086],"type":"Point"}
}