{
  "type": "Feature",
  "properties": {
    "gn:admin1_code":"81",
    "gn:admin2_code":"3059",
    "gn:admin3_code":"305974.0",
    "gn:admin4_code":"30597461.0",
    "gn:asciiname":"Ramananda",
    "gn:country_code":"BD",
    "gn:dem":8,
    "gn:feature_class":"P",
    "gn:feature_code":"PPL",
    "gn:name":"R\u0101m\u0101nanda",
    "gn:population":0,
    "gn:timezone":"Asia/Dhaka",
    "iso:country":"BD",
    "wof:name":"Ramananda",
    "wof:placetype":"locality"
},
  "geometry": {"coordinates":[90.40237,23.59086],"type":"Point"}
}