{
  "type": "Feature",
  "properties": {
    "gn:admin1_code":"87",
    "gn:admin2_code":"5549",
    "gn:admin3_code":"554979.0",
    "gn:admin4_code":"55497923.0",
    "gn:asciiname":"Char Kazikata",
    "gn:country_code":"BD",
    "gn:dem":31,
    "gn:feature_class":"P",
    "gn:feature_code":"PPL",
    "gn:name":"Char Kazikata",
    "gn:population":0,
    "gn:timezone":"Asia/Dhaka",
    "iso:country":"BD",
    "name:ben_x_preferred":[
        "Char Kazikata"
    ],
    "wof:name":"Char Kazikata",
    "wof:placetype":"locality"
},
  "geometry": {"coordinates":[89.83439,25.69066],"type":"Point"}
}