{
  "type": "Feature",
  "properties": {
    "gn:admin1_code":"81",
    "gn:admin2_code":"3093",
    "gn:admin3_code":"309347.0",
    "gn:admin4_code":"30934707.0",
    "gn:asciiname":"Kazibari",
    "gn:country_code":"BD",
    "gn:dem":14,
    "gn:feature_class":"P",
    "gn:feature_code":"PPL",
    "gn:name":"K\u0101zib\u0101ri",
    "gn:population":0,
    "gn:timezone":"Asia/Dhaka",
    "iso:country":"BD",
    "wof:name":"Kazibari",
    "wof:placetype":"locality"
},
  "geometry": {"coordinates":[90.01161,24.30702],"type":"Point"}
}