{
  "type": "Feature",
  "properties": {
    "gn:admin1_code":"84",
    "gn:admin2_code":"2019",
    "gn:admin3_code":"201981.0",
    "gn:admin4_code":"20198131.0",
    "gn:asciiname":"South Ampal",
    "gn:country_code":"BD",
    "gn:dem":11,
    "gn:feature_class":"P",
    "gn:feature_code":"PPL",
    "gn:name":"South Amp\u0101l",
    "gn:population":0,
    "gn:timezone":"Asia/Dhaka",
    "iso:country":"BD",
    "name:und_x_variant":[
        "South Amp\u0101l",
        "South \u0100mp\u0101l"
    ],
    "wof:name":"South Ampal",
    "wof:placetype":"locality"
},
  "geometry": {"coordinates":[90.88419,23.582],"type":"Point"}
}