{
  "type": "Feature",
  "properties": {
    "gn:admin1_code":"81",
    "gn:admin2_code":"3035.0",
    "gn:admin3_code":"303558.0",
    "gn:admin4_code":"30355811.0",
    "gn:asciiname":"Banbari",
    "gn:country_code":"BD",
    "gn:dem":4,
    "gn:feature_class":"P",
    "gn:feature_code":"PPL",
    "gn:name":"Banb\u0101ri",
    "gn:population":0,
    "gn:timezone":"Asia/Dhaka",
    "iso:country":"BD",
    "name:ben_x_preferred":[
        "Banb\u0101ri"
    ],
    "name:ben_x_variant":[
        "B\u0101nsbaria"
    ],
    "wof:name":"Banbari",
    "wof:placetype":"locality"
},
  "geometry": {"coordinates":[89.87288000000002,23.21952000000001],"type":"Point"}
}