{
  "type": "Feature",
  "properties": {
    "gn:admin1_code":"82",
    "gn:admin2_code":"4047.0",
    "gn:admin3_code":"404740.0",
    "gn:admin4_code":"40474066.0",
    "gn:asciiname":"Kaibartaganti",
    "gn:country_code":"BD",
    "gn:dem":8,
    "gn:feature_class":"P",
    "gn:feature_code":"PPL",
    "gn:name":"Kaibartag\u0101nti",
    "gn:population":0,
    "gn:timezone":"Asia/Dhaka",
    "iso:country":"BD",
    "name:ben_x_preferred":[
        "Kaibartag\u0101nti"
    ],
    "wof:name":"Kaibartaganti",
    "wof:placetype":"locality"
},
  "geometry": {"coordinates":[89.57671999999999,22.93778],"type":"Point"}
}