{
  "type": "Feature",
  "properties": {
    "gn:admin1_code":"84",
    "gn:admin2_code":"2084.0",
    "gn:admin3_code":"208425.0",
    "gn:admin4_code":"20842538.0",
    "gn:asciiname":"Ulukhala",
    "gn:country_code":"BD",
    "gn:dem":45,
    "gn:feature_class":"P",
    "gn:feature_code":"PPL",
    "gn:name":"Ulukhala",
    "gn:population":0,
    "gn:timezone":"Asia/Dhaka",
    "iso:country":"BD",
    "name:ben_x_preferred":[
        "Ulukhala"
    ],
    "wof:name":"Ulukhala",
    "wof:placetype":"locality"
},
  "geometry": {"coordinates":[91.95475999999999,22.61181],"type":"Point"}
}