{
  "type": "Feature",
  "properties": {
    "gn:admin1_code":"82",
    "gn:admin2_code":"4018",
    "gn:admin3_code":"401831.0",
    "gn:admin4_code":"40183111.0",
    "gn:asciiname":"Moktarpur",
    "gn:country_code":"BD",
    "gn:dem":16,
    "gn:feature_class":"P",
    "gn:feature_code":"PPL",
    "gn:name":"Mokt\u0101rpur",
    "gn:population":0,
    "gn:timezone":"Asia/Dhaka",
    "iso:country":"BD",
    "wof:name":"Moktarpur",
    "wof:placetype":"locality"
},
  "geometry": {"coordinates":[88.72773000000002,23.59945],"type":"Point"}
}