{
  "type": "Feature",
  "properties": {
    "gn:admin1_code":"82",
    "gn:admin2_code":"4041.0",
    "gn:admin3_code":"404147.0",
    "gn:admin4_code":"40414747.0",
    "gn:asciiname":"Uttar Lalitadaha",
    "gn:country_code":"BD",
    "gn:dem":14,
    "gn:feature_class":"P",
    "gn:feature_code":"PPL",
    "gn:name":"Uttar Lalit\u0101daha",
    "gn:population":0,
    "gn:timezone":"Asia/Dhaka",
    "iso:country":"BD",
    "name:ben_x_preferred":[
        "Uttar Lalit\u0101daha"
    ],
    "wof:name":"Uttar Lalitadaha",
    "wof:placetype":"locality"
},
  "geometry": {"coordinates":[89.18709,23.26499],"type":"Point"}
}