{
  "type": "Feature",
  "properties": {
    "gn:admin1_code":"81",
    "gn:admin2_code":"3059",
    "gn:admin3_code":"305984.0",
    "gn:admin4_code":"30598427.0",
    "gn:asciiname":"Jagannathpatti",
    "gn:country_code":"BD",
    "gn:dem":10,
    "gn:feature_class":"P",
    "gn:feature_code":"PPL",
    "gn:name":"Jagann\u0101thpatti",
    "gn:population":0,
    "gn:timezone":"Asia/Dhaka",
    "iso:country":"BD",
    "wof:name":"Jagannathpatti",
    "wof:placetype":"locality"
},
  "geometry": {"coordinates":[90.21028,23.53152],"type":"Point"}
}