{
  "type": "Feature",
  "properties": {
    "gn:admin1_code":"82",
    "gn:admin2_code":"4055",
    "gn:admin3_code":"405557.0",
    "gn:admin4_code":"40555706.0",
    "gn:asciiname":"Naldaha",
    "gn:country_code":"BD",
    "gn:dem":14,
    "gn:feature_class":"P",
    "gn:feature_code":"PPL",
    "gn:name":"Naldaha",
    "gn:population":0,
    "gn:timezone":"Asia/Dhaka",
    "iso:country":"BD",
    "name:und_x_variant":[
        "Nanldaha",
        "Naldaha"
    ],
    "wof:name":"Naldaha",
    "wof:placetype":"locality"
},
  "geometry": {"coordinates":[89.38859000000002,23.52779],"type":"Point"}
}