{
  "type": "Feature",
  "properties": {
    "gn:admin1_code":"82",
    "gn:admin2_code":"4050.0",
    "gn:admin3_code":"405071.0",
    "gn:admin4_code":"40507194.0",
    "gn:asciiname":"Chhota Majgram",
    "gn:cc2":"BD",
    "gn:country_code":"BD",
    "gn:dem":9,
    "gn:feature_class":"P",
    "gn:feature_code":"PPL",
    "gn:name":"Chhota M\u0101jgr\u0101m",
    "gn:population":0,
    "gn:timezone":"Asia/Dhaka",
    "iso:country":"BD",
    "name:und_x_variant":[
        "Chhoto Mazgram",
        "Chhota M\u0101jgr\u0101m"
    ],
    "wof:name":"Chhota Majgram",
    "wof:placetype":"locality"
},
  "geometry": {"coordinates":[89.25,23.91667],"type":"Point"}
}