{
  "type": "Feature",
  "properties": {
    "gn:admin1_code":"83",
    "gn:admin2_code":"5081",
    "gn:admin3_code":"508182.0",
    "gn:admin4_code":"50818240.0",
    "gn:asciiname":"Novapara",
    "gn:country_code":"BD",
    "gn:dem":20,
    "gn:feature_class":"P",
    "gn:feature_code":"PPL",
    "gn:name":"Novap\u0101ra",
    "gn:population":0,
    "gn:timezone":"Asia/Dhaka",
    "iso:country":"BD",
    "name:ben_x_preferred":[
        "Novap\u0101ra"
    ],
    "name:ben_x_variant":[
        "Nay\u0101p\u0101ra"
    ],
    "wof:name":"Novapara",
    "wof:placetype":"locality"
},
  "geometry": {"coordinates":[88.83100999999998,24.42989],"type":"Point"}
}