{
  "type": "Feature",
  "properties": {
    "gn:admin1_code":"H",
    "gn:admin2_code":"3072",
    "gn:admin3_code":"307240.0",
    "gn:admin4_code":"30724083.0",
    "gn:asciiname":"Maijganga",
    "gn:country_code":"BD",
    "gn:dem":9,
    "gn:feature_class":"P",
    "gn:feature_code":"PPL",
    "gn:name":"M\u0101ijg\u0101nga",
    "gn:population":0,
    "gn:timezone":"Asia/Dhaka",
    "iso:country":"BD",
    "name:und_x_variant":[
        "Maijgang",
        "M\u0101ijg\u0101nga"
    ],
    "wof:name":"Maijganga",
    "wof:placetype":"locality"
},
  "geometry": {"coordinates":[90.83959,24.9972],"type":"Point"}
}