{
  "type": "Feature",
  "properties": {
    "gn:admin1_code":"81",
    "gn:admin2_code":"3056",
    "gn:admin3_code":"305670.0",
    "gn:admin4_code":"30567085.0",
    "gn:asciiname":"Uttar Malsi",
    "gn:country_code":"BD",
    "gn:dem":15,
    "gn:feature_class":"P",
    "gn:feature_code":"PPL",
    "gn:name":"Uttar M\u0101lsi",
    "gn:population":0,
    "gn:timezone":"Asia/Dhaka",
    "iso:country":"BD",
    "wof:name":"Uttar Malsi",
    "wof:placetype":"locality"
},
  "geometry": {"coordinates":[90.05020999999998,23.93914],"type":"Point"}
}