{
  "type": "Feature",
  "properties": {
    "gn:admin1_code":"84",
    "gn:admin2_code":"2019",
    "gn:admin3_code":"201936.0",
    "gn:admin4_code":"20193690.0",
    "gn:asciiname":"Itakhola",
    "gn:country_code":"BD",
    "gn:dem":11,
    "gn:feature_class":"P",
    "gn:feature_code":"PPL",
    "gn:name":"It\u0101khola",
    "gn:population":0,
    "gn:timezone":"Asia/Dhaka",
    "iso:country":"BD",
    "name:und_x_variant":[
        "Itkhola",
        "It\u0101khola"
    ],
    "wof:name":"Itakhola",
    "wof:placetype":"locality"
},
  "geometry": {"coordinates":[90.79483999999999,23.52142000000001],"type":"Point"}
}