{
  "type": "Feature",
  "properties": {
    "gn:admin1_code":"85",
    "gn:admin2_code":"1078.0",
    "gn:admin3_code":"107866.0",
    "gn:admin4_code":"10786659.0",
    "gn:asciiname":"Golbunia",
    "gn:country_code":"BD",
    "gn:dem":9,
    "gn:feature_class":"P",
    "gn:feature_code":"PPL",
    "gn:name":"Golbunia",
    "gn:population":0,
    "gn:timezone":"Asia/Dhaka",
    "iso:country":"BD",
    "name:ben_x_preferred":[
        "Golbunia"
    ],
    "wof:name":"Golbunia",
    "wof:placetype":"locality"
},
  "geometry": {"coordinates":[90.20148,21.93542],"type":"Point"}
}