{
  "type": "Feature",
  "properties": {
    "gn:admin1_code":"84",
    "gn:admin2_code":"2015.0",
    "gn:admin3_code":"201508.0",
    "gn:admin4_code":"20150837.0",
    "gn:asciiname":"Jaldi",
    "gn:country_code":"BD",
    "gn:dem":9,
    "gn:feature_class":"P",
    "gn:feature_code":"PPL",
    "gn:name":"Jaldi",
    "gn:population":0,
    "gn:timezone":"Asia/Dhaka",
    "iso:country":"BD",
    "name:ben_x_preferred":[
        "Jaldi"
    ],
    "wof:name":"Jaldi",
    "wof:placetype":"locality"
},
  "geometry": {"coordinates":[91.95131000000001,21.99512],"type":"Point"}
}