{
  "type": "Feature",
  "properties": {
    "gn:admin1_code":"84",
    "gn:admin2_code":"2019",
    "gn:admin3_code":"201937.0",
    "gn:admin4_code":"20193756.0",
    "gn:asciiname":"North Krishnapur",
    "gn:country_code":"BD",
    "gn:dem":11,
    "gn:feature_class":"P",
    "gn:feature_code":"PPL",
    "gn:name":"North Krishnapur",
    "gn:population":0,
    "gn:timezone":"Asia/Dhaka",
    "iso:country":"BD",
    "wof:name":"North Krishnapur",
    "wof:placetype":"locality"
},
  "geometry": {"coordinates":[90.74857,23.62008],"type":"Point"}
}