{
  "type": "Feature",
  "properties": {
    "gn:admin1_code":"82",
    "gn:admin2_code":"4047",
    "gn:admin3_code":"404712.0",
    "gn:admin4_code":"40471271.0",
    "gn:asciiname":"Solmari",
    "gn:country_code":"BD",
    "gn:dem":6,
    "gn:feature_class":"P",
    "gn:feature_code":"PPL",
    "gn:name":"Solm\u0101ri",
    "gn:population":0,
    "gn:timezone":"Asia/Dhaka",
    "iso:country":"BD",
    "name:und_x_variant":[
        "Solemari",
        "Solm\u0101ri"
    ],
    "wof:name":"Solmari",
    "wof:placetype":"locality"
},
  "geometry": {"coordinates":[89.48929,22.7727],"type":"Point"}
}