{
  "type": "Feature",
  "properties": {
    "gn:admin1_code":"82",
    "gn:admin2_code":"4001.0",
    "gn:admin3_code":"400158.0",
    "gn:admin4_code":"40015823.0",
    "gn:asciiname":"Araji Makardhone",
    "gn:country_code":"BD",
    "gn:dem":5,
    "gn:feature_class":"P",
    "gn:feature_code":"PPL",
    "gn:name":"Araji Makardhone",
    "gn:population":0,
    "gn:timezone":"Asia/Dhaka",
    "iso:country":"BD",
    "name:ben_x_preferred":[
        "Araji Makardhone"
    ],
    "wof:name":"Araji Makardhone",
    "wof:placetype":"locality"
},
  "geometry": {"coordinates":[89.62732,22.47814],"type":"Point"}
}