{
  "type": "Feature",
  "properties": {
    "gn:admin1_code":"81",
    "gn:admin2_code":"3059",
    "gn:admin3_code":"305944.0",
    "gn:admin4_code":"30594463.0",
    "gn:asciiname":"Mitusar",
    "gn:country_code":"BD",
    "gn:dem":7,
    "gn:feature_class":"P",
    "gn:feature_code":"PPL",
    "gn:name":"Mitus\u0101r",
    "gn:population":0,
    "gn:timezone":"Asia/Dhaka",
    "iso:country":"BD",
    "wof:name":"Mitusar",
    "wof:placetype":"locality"
},
  "geometry": {"coordinates":[90.39458,23.50989],"type":"Point"}
}