{
  "type": "Feature",
  "properties": {
    "gn:admin1_code":"H",
    "gn:admin2_code":"3072.0",
    "gn:admin3_code":"307274.0",
    "gn:admin4_code":"30727494.0",
    "gn:asciiname":"Baghrua",
    "gn:country_code":"BD",
    "gn:dem":16,
    "gn:feature_class":"P",
    "gn:feature_code":"PPL",
    "gn:name":"B\u0101ghrua",
    "gn:population":0,
    "gn:timezone":"Asia/Dhaka",
    "iso:country":"BD",
    "wof:name":"Baghrua",
    "wof:placetype":"locality"
},
  "geometry": {"coordinates":[90.80766,24.93767],"type":"Point"}
}