{
  "type": "Feature",
  "properties": {
    "gn:admin1_code":"83",
    "gn:admin2_code":"5064.0",
    "gn:admin3_code":"506450.0",
    "gn:admin4_code":"50645028.0",
    "gn:asciiname":"Buzruk Baral",
    "gn:country_code":"BD",
    "gn:dem":21,
    "gn:feature_class":"P",
    "gn:feature_code":"PPL",
    "gn:name":"Buzruk Baral",
    "gn:population":0,
    "gn:timezone":"Asia/Dhaka",
    "iso:country":"BD",
    "name:ben_x_preferred":[
        "Buzruk Baral"
    ],
    "name:ben_x_variant":[
        "Buzrug Bar\u0101il"
    ],
    "name:und_x_variant":[
        "Bazrug Barial"
    ],
    "wof:name":"Buzruk Baral",
    "wof:placetype":"locality"
},
  "geometry": {"coordinates":[88.83218000000002,24.89433],"type":"Point"}
}