{
  "type": "Feature",
  "properties": {
    "gn:admin1_code":"82",
    "gn:admin2_code":"4047.0",
    "gn:admin3_code":"404753.0",
    "gn:admin4_code":"40475394.0",
    "gn:asciiname":"Katmar Char",
    "gn:country_code":"BD",
    "gn:dem":4,
    "gn:feature_class":"P",
    "gn:feature_code":"PPL",
    "gn:name":"Katm\u0101r Char",
    "gn:population":0,
    "gn:timezone":"Asia/Dhaka",
    "iso:country":"BD",
    "name:ben_x_preferred":[
        "Katm\u0101r Char"
    ],
    "wof:name":"Katmar Char",
    "wof:placetype":"locality"
},
  "geometry": {"coordinates":[89.28856999999998,22.29015],"type":"Point"}
}