{
  "type": "Feature",
  "properties": {
    "gn:admin1_code":"83",
    "gn:admin2_code":"5076.0",
    "gn:admin3_code":"507616.0",
    "gn:admin4_code":"50761621.0",
    "gn:asciiname":"Khaerkandi",
    "gn:country_code":"BD",
    "gn:dem":14,
    "gn:feature_class":"P",
    "gn:feature_code":"PPL",
    "gn:name":"Kh\u0101erk\u0101ndi",
    "gn:population":0,
    "gn:timezone":"Asia/Dhaka",
    "iso:country":"BD",
    "name:ben_x_preferred":[
        "Kh\u0101erk\u0101ndi"
    ],
    "wof:name":"Khaerkandi",
    "wof:placetype":"locality"
},
  "geometry": {"coordinates":[89.68049000000001,23.85175],"type":"Point"}
}