{
  "type": "Feature",
  "properties": {
    "gn:admin1_code":"81",
    "gn:admin2_code":"3059",
    "gn:admin3_code":"305956.0",
    "gn:admin4_code":"30595685.0",
    "gn:asciiname":"Sukhabaspur",
    "gn:country_code":"BD",
    "gn:dem":10,
    "gn:feature_class":"P",
    "gn:feature_code":"PPL",
    "gn:name":"Sukhab\u0101spur",
    "gn:population":0,
    "gn:timezone":"Asia/Dhaka",
    "iso:country":"BD",
    "wof:name":"Sukhabaspur",
    "wof:placetype":"locality"
},
  "geometry": {"coordinates":[90.48656,23.54023],"type":"Point"}
}