{
  "type": "Feature",
  "properties": {
    "gn:admin1_code":"81",
    "gn:admin2_code":"3056",
    "gn:admin3_code":"305670.0",
    "gn:admin4_code":"30567076.0",
    "gn:asciiname":"Kaonnara",
    "gn:country_code":"BD",
    "gn:dem":10,
    "gn:feature_class":"P",
    "gn:feature_code":"PPL",
    "gn:name":"K\u0101onn\u0101ra",
    "gn:population":0,
    "gn:timezone":"Asia/Dhaka",
    "iso:country":"BD",
    "wof:name":"Kaonnara",
    "wof:placetype":"locality"
},
  "geometry": {"coordinates":[90.01666999999998,23.96667],"type":"Point"}
}