{
  "type": "Feature",
  "properties": {
    "gn:admin1_code":"87",
    "gn:admin2_code":"5577.0",
    "gn:admin3_code":"557725.0",
    "gn:admin4_code":"55772551.0",
    "gn:asciiname":"Bahadi",
    "gn:country_code":"BD",
    "gn:dem":75,
    "gn:feature_class":"P",
    "gn:feature_code":"PPL",
    "gn:name":"B\u0101hadi",
    "gn:population":0,
    "gn:timezone":"Asia/Dhaka",
    "iso:country":"BD",
    "name:ben_x_preferred":[
        "B\u0101hadi"
    ],
    "wof:name":"Bahadi",
    "wof:placetype":"locality"
},
  "geometry": {"coordinates":[88.50886,26.26768],"type":"Point"}
}