{
  "type": "Feature",
  "properties": {
    "gn:admin1_code":"83",
    "gn:admin2_code":"5038.0",
    "gn:admin3_code":"503874.0",
    "gn:admin4_code":"50387452.0",
    "gn:asciiname":"Radhabari",
    "gn:country_code":"BD",
    "gn:dem":28,
    "gn:feature_class":"P",
    "gn:feature_code":"PPL",
    "gn:name":"R\u0101dh\u0101b\u0101ri",
    "gn:population":0,
    "gn:timezone":"Asia/Dhaka",
    "iso:country":"BD",
    "name:ben_x_preferred":[
        "R\u0101dh\u0101b\u0101ri"
    ],
    "wof:name":"Radhabari",
    "wof:placetype":"locality"
},
  "geometry": {"coordinates":[89.02816999999997,25.20113],"type":"Point"}
}