{
  "type": "Feature",
  "properties": {
    "gn:admin1_code":"83",
    "gn:admin2_code":"5064",
    "gn:admin3_code":"506406.0",
    "gn:admin4_code":"50640621.0",
    "gn:asciiname":"Pindira",
    "gn:country_code":"BD",
    "gn:dem":23,
    "gn:feature_class":"P",
    "gn:feature_code":"PPL",
    "gn:name":"Pindira",
    "gn:population":0,
    "gn:timezone":"Asia/Dhaka",
    "iso:country":"BD",
    "name:ben_x_preferred":[
        "Pindira"
    ],
    "name:ben_x_variant":[
        "Pind\u0101ra"
    ],
    "wof:name":"Pindira",
    "wof:placetype":"locality"
},
  "geometry": {"coordinates":[88.90129,24.95598],"type":"Point"}
}