{
  "type": "Feature",
  "properties": {
    "gn:admin1_code":"81",
    "gn:admin2_code":"3054",
    "gn:admin3_code":"305454.0",
    "gn:admin4_code":"30545471.0",
    "gn:asciiname":"Matibhanga",
    "gn:country_code":"BD",
    "gn:dem":6,
    "gn:feature_class":"P",
    "gn:feature_code":"PPL",
    "gn:name":"M\u0101tibh\u0101nga",
    "gn:population":0,
    "gn:timezone":"Asia/Dhaka",
    "iso:country":"BD",
    "wof:name":"Matibhanga",
    "wof:placetype":"locality"
},
  "geometry": {"coordinates":[90.11496,23.14703],"type":"Point"}
}