{
  "type": "Feature",
  "properties": {
    "gn:admin1_code":"83",
    "gn:admin2_code":"5038.0",
    "gn:admin3_code":"503858.0",
    "gn:admin4_code":"50385885.0",
    "gn:asciiname":"Saranjia",
    "gn:country_code":"BD",
    "gn:dem":25,
    "gn:feature_class":"P",
    "gn:feature_code":"PPL",
    "gn:name":"Saranjia",
    "gn:population":0,
    "gn:timezone":"Asia/Dhaka",
    "iso:country":"BD",
    "name:ben_x_preferred":[
        "Saranjia"
    ],
    "wof:name":"Saranjia",
    "wof:placetype":"locality"
},
  "geometry": {"coordinates":[89.23633000000002,25.08815],"type":"Point"}
}