{
  "type": "Feature",
  "properties": {
    "gn:admin1_code":"81",
    "gn:admin2_code":"3029.0",
    "gn:admin3_code":"302962.0",
    "gn:admin4_code":"30296261.0",
    "gn:asciiname":"Harina",
    "gn:country_code":"BD",
    "gn:dem":8,
    "gn:feature_class":"P",
    "gn:feature_code":"PPL",
    "gn:name":"Harina",
    "gn:population":0,
    "gn:timezone":"Asia/Dhaka",
    "iso:country":"BD",
    "wof:name":"Harina",
    "wof:placetype":"locality"
},
  "geometry": {"coordinates":[89.85784,23.41117],"type":"Point"}
}