{
  "type": "Feature",
  "properties": {
    "gn:admin1_code":"85",
    "gn:admin2_code":"1004.0",
    "gn:admin3_code":"100409.0",
    "gn:admin4_code":"10040994.0",
    "gn:asciiname":"Charpara",
    "gn:country_code":"BD",
    "gn:dem":8,
    "gn:feature_class":"P",
    "gn:feature_code":"PPL",
    "gn:name":"Charpara",
    "gn:population":0,
    "gn:timezone":"Asia/Dhaka",
    "iso:country":"BD",
    "name:ben_x_preferred":[
        "Charpara"
    ],
    "wof:name":"Charpara",
    "wof:placetype":"locality"
},
  "geometry": {"coordinates":[90.08709,22.01849],"type":"Point"}
}