{
  "type": "Feature",
  "properties": {
    "gn:admin1_code":"H",
    "gn:admin2_code":"3039.0",
    "gn:admin3_code":"303961.0",
    "gn:admin4_code":"30396109.0",
    "gn:asciiname":"Hazrabari",
    "gn:country_code":"BD",
    "gn:dem":23,
    "gn:feature_class":"P",
    "gn:feature_code":"PPL",
    "gn:name":"H\u0101zr\u0101b\u0101ri",
    "gn:population":0,
    "gn:timezone":"Asia/Dhaka",
    "iso:country":"BD",
    "wof:name":"Hazrabari",
    "wof:placetype":"locality"
},
  "geometry": {"coordinates":[89.82507,24.92392000000001],"type":"Point"}
}