{
  "type": "Feature",
  "properties": {
    "gn:admin1_code":"83",
    "gn:admin2_code":"5081.0",
    "gn:admin3_code":"508172.0",
    "gn:admin4_code":"50817223.0",
    "gn:asciiname":"Baraipata",
    "gn:country_code":"BD",
    "gn:dem":16,
    "gn:feature_class":"P",
    "gn:feature_code":"PPL",
    "gn:name":"B\u0101raip\u0101ta",
    "gn:population":0,
    "gn:timezone":"Asia/Dhaka",
    "iso:country":"BD",
    "wof:name":"Baraipata",
    "wof:placetype":"locality"
},
  "geometry": {"coordinates":[88.51666999999998,24.46667],"type":"Point"}
}