{
  "type": "Feature",
  "properties": {
    "gn:admin1_code":"83",
    "gn:admin2_code":"5081.0",
    "gn:admin3_code":"508194.0",
    "gn:admin4_code":"50819467.0",
    "gn:asciiname":"Arazi Ektarpur",
    "gn:country_code":"BD",
    "gn:dem":26,
    "gn:feature_class":"P",
    "gn:feature_code":"PPL",
    "gn:name":"Ar\u0101zi Ektarpur",
    "gn:population":0,
    "gn:timezone":"Asia/Dhaka",
    "iso:country":"BD",
    "name:ben_x_preferred":[
        "Ar\u0101zi Ektarpur"
    ],
    "wof:name":"Arazi Ektarpur",
    "wof:placetype":"locality"
},
  "geometry": {"coordinates":[88.54075,24.51202],"type":"Point"}
}