{
  "type": "Feature",
  "properties": {
    "gn:admin1_code":"83",
    "gn:admin2_code":"5038.0",
    "gn:admin3_code":"503847.0",
    "gn:admin4_code":"50384719.0",
    "gn:asciiname":"Mohmudpur",
    "gn:country_code":"BD",
    "gn:dem":25,
    "gn:feature_class":"P",
    "gn:feature_code":"PPL",
    "gn:name":"Mohmudpur",
    "gn:population":0,
    "gn:timezone":"Asia/Dhaka",
    "iso:country":"BD",
    "name:ben_x_preferred":[
        "Mohmudpur"
    ],
    "wof:name":"Mohmudpur",
    "wof:placetype":"locality"
},
  "geometry": {"coordinates":[89.0907,25.09672],"type":"Point"}
}