{
  "type": "Feature",
  "properties": {
    "gn:admin1_code":"81",
    "gn:admin2_code":"3056",
    "gn:admin3_code":"305670.0",
    "gn:admin4_code":"30567038.0",
    "gn:asciiname":"Teghari",
    "gn:country_code":"BD",
    "gn:dem":11,
    "gn:feature_class":"P",
    "gn:feature_code":"PPL",
    "gn:name":"Tegh\u0101ri",
    "gn:population":0,
    "gn:timezone":"Asia/Dhaka",
    "iso:country":"BD",
    "name:spa_x_preferred":[
        "Teghari"
    ],
    "name:und_x_variant":[
        "Teghori",
        "Tegh\u0101ri"
    ],
    "wof:name":"Teghari",
    "wof:placetype":"locality"
},
  "geometry": {"coordinates":[90.01208000000003,23.98353],"type":"Point"}
}