{
  "type": "Feature",
  "properties": {
    "gn:admin1_code":"87",
    "gn:admin2_code":"5577.0",
    "gn:admin3_code":"557704.0",
    "gn:admin4_code":"55770440.0",
    "gn:asciiname":"Sabdigachh",
    "gn:country_code":"BD",
    "gn:dem":73,
    "gn:feature_class":"P",
    "gn:feature_code":"PPL",
    "gn:name":"Sabdig\u0101chh",
    "gn:population":0,
    "gn:timezone":"Asia/Dhaka",
    "iso:country":"BD",
    "name:ben_x_preferred":[
        "Sabdig\u0101chh"
    ],
    "wof:name":"Sabdigachh",
    "wof:placetype":"locality"
},
  "geometry": {"coordinates":[88.38113,26.30346],"type":"Point"}
}