{
  "type": "Feature",
  "properties": {
    "gn:admin1_code":"87",
    "gn:admin2_code":"5573.0",
    "gn:admin3_code":"557364.0",
    "gn:admin4_code":"55736475.0",
    "gn:asciiname":"Tennargar",
    "gn:country_code":"BD",
    "gn:dem":50,
    "gn:feature_class":"P",
    "gn:feature_code":"PPL",
    "gn:name":"Tennargar",
    "gn:population":0,
    "gn:timezone":"Asia/Dhaka",
    "iso:country":"BD",
    "name:ben_x_preferred":[
        "Tennargar"
    ],
    "wof:name":"Tennargar",
    "wof:placetype":"locality"
},
  "geometry": {"coordinates":[88.88878000000003,25.9836],"type":"Point"}
}