{
  "type": "Feature",
  "properties": {
    "gn:admin1_code":"87",
    "gn:admin2_code":"5527",
    "gn:admin3_code":"552760.0",
    "gn:admin4_code":"55276079.0",
    "gn:asciiname":"Margaon",
    "gn:country_code":"BD",
    "gn:dem":46,
    "gn:feature_class":"P",
    "gn:feature_code":"PPL",
    "gn:name":"M\u0101rg\u0101on",
    "gn:population":0,
    "gn:timezone":"Asia/Dhaka",
    "iso:country":"BD",
    "name:ben_x_preferred":[
        "M\u0101rg\u0101on"
    ],
    "wof:name":"Margaon",
    "wof:placetype":"locality"
},
  "geometry": {"coordinates":[88.77656,25.80591],"type":"Point"}
}