{
  "type": "Feature",
  "properties": {
    "gn:admin1_code":"81",
    "gn:admin2_code":"3059",
    "gn:admin3_code":"305974.0",
    "gn:admin4_code":"30597440.0",
    "gn:asciiname":"Khilgaon",
    "gn:country_code":"BD",
    "gn:dem":9,
    "gn:feature_class":"P",
    "gn:feature_code":"PPL",
    "gn:name":"Khilgaon",
    "gn:population":0,
    "gn:timezone":"Asia/Dhaka",
    "iso:country":"BD",
    "wof:name":"Khilgaon",
    "wof:placetype":"locality"
},
  "geometry": {"coordinates":[90.36698,23.53609],"type":"Point"}
}