{
  "type": "Feature",
  "properties": {
    "gn:admin1_code":"86",
    "gn:admin2_code":"6036",
    "gn:admin3_code":"603668.0",
    "gn:admin4_code":"60366827.0",
    "gn:asciiname":"Madna",
    "gn:country_code":"BD",
    "gn:dem":10,
    "gn:feature_class":"P",
    "gn:feature_code":"PPL",
    "gn:name":"M\u0101dna",
    "gn:population":0,
    "gn:timezone":"Asia/Dhaka",
    "iso:country":"BD",
    "name:ara_x_preferred":[
        "\u0645\u0627\u062f\u0646\u0629"
    ],
    "name:azb_x_preferred":[
        "\u0645\u0627\u062f\u0646\u0647"
    ],
    "name:fas_x_preferred":[
        "\u0645\u0627\u062f\u0646\u0647"
    ],
    "name:fra_x_preferred":[
        "Madna"
    ],
    "name:ita_x_preferred":[
        "Madna"
    ],
    "name:kab_x_preferred":[
        "Madna"
    ],
    "name:msa_x_preferred":[
        "Madna"
    ],
    "name:por_x_preferred":[
        "Madna"
    ],
    "name:ron_x_preferred":[
        "Madna"
    ],
    "name:spa_x_preferred":[
        "Madna"
    ],
    "name:und_x_variant":[
        "Mudna",
        "M\u0101dna"
    ],
    "name:urd_x_preferred":[
        "\u0645\u06cc\u0688\u0646\u0627"
    ],
    "name:vie_x_preferred":[
        "Madna"
    ],
    "name:zho_x_preferred":[
        "\u99ac\u5fb7\u7d0d"
    ],
    "wof:name":"Madna",
    "wof:placetype":"locality"
},
  "geometry": {"coordinates":[91.23905000000001,24.33727],"type":"Point"}
}