{
  "type": "Feature",
  "properties": {
    "gn:admin1_code":"87",
    "gn:admin2_code":"5573.0",
    "gn:admin3_code":"557312.0",
    "gn:admin4_code":"55731209.0",
    "gn:asciiname":"Dangapara",
    "gn:country_code":"BD",
    "gn:dem":57,
    "gn:feature_class":"P",
    "gn:feature_code":"PPL",
    "gn:name":"Dangap\u0101ra",
    "gn:population":0,
    "gn:timezone":"Asia/Dhaka",
    "iso:country":"BD",
    "name:ben_x_preferred":[
        "Dangap\u0101ra"
    ],
    "wof:name":"Dangapara",
    "wof:placetype":"locality"
},
  "geometry": {"coordinates":[88.90881999999998,26.15221],"type":"Point"}
}