{
  "type": "Feature",
  "properties": {
    "gn:admin1_code":"87",
    "gn:admin2_code":"5585",
    "gn:admin3_code":"558576.0",
    "gn:admin4_code":"55857625.0",
    "gn:asciiname":"Daneshnagar",
    "gn:country_code":"BD",
    "gn:dem":31,
    "gn:feature_class":"P",
    "gn:feature_code":"PPL",
    "gn:name":"Daneshnagar",
    "gn:population":0,
    "gn:timezone":"Asia/Dhaka",
    "iso:country":"BD",
    "name:ben_x_preferred":[
        "Daneshnagar"
    ],
    "name:ben_x_variant":[
        "Danishnagar"
    ],
    "wof:name":"Daneshnagar",
    "wof:placetype":"locality"
},
  "geometry": {"coordinates":[89.1645,25.48394],"type":"Point"}
}