{
  "type": "Feature",
  "properties": {
    "gn:admin1_code":"81",
    "gn:admin2_code":"3082.0",
    "gn:admin3_code":"308207.0",
    "gn:admin4_code":"30820766.0",
    "gn:asciiname":"Bara Jangal",
    "gn:country_code":"BD",
    "gn:dem":14,
    "gn:feature_class":"P",
    "gn:feature_code":"PPL",
    "gn:name":"B\u0101ra Jangal",
    "gn:population":0,
    "gn:timezone":"Asia/Dhaka",
    "iso:country":"BD",
    "wof:name":"Bara Jangal",
    "wof:placetype":"locality"
},
  "geometry": {"coordinates":[89.52616,23.60271],"type":"Point"}
}