{
  "type": "Feature",
  "properties": {
    "gn:admin1_code":"85",
    "gn:admin2_code":"1006",
    "gn:admin3_code":"100607.0",
    "gn:admin4_code":"10060781.0",
    "gn:asciiname":"Tengrakhali Kismat",
    "gn:country_code":"BD",
    "gn:dem":7,
    "gn:feature_class":"P",
    "gn:feature_code":"PPL",
    "gn:name":"Tengr\u0101kh\u0101li Kismat",
    "gn:population":0,
    "gn:timezone":"Asia/Dhaka",
    "iso:country":"BD",
    "wof:name":"Tengrakhali Kismat",
    "wof:placetype":"locality"
},
  "geometry": {"coordinates":[90.25221999999999,22.48916],"type":"Point"}
}