{
  "type": "Feature",
  "properties": {
    "gn:admin1_code":"82",
    "gn:asciiname":"Chhota Raghunathpur",
    "gn:country_code":"BD",
    "gn:dem":7,
    "gn:feature_class":"P",
    "gn:feature_code":"PPL",
    "gn:name":"Chhota Raghun\u0101thpur",
    "gn:population":0,
    "gn:timezone":"Asia/Dhaka",
    "iso:country":"BD",
    "name:ben_x_preferred":[
        "Chhota Raghun\u0101thpur"
    ],
    "wof:name":"Chhota Raghunathpur",
    "wof:placetype":"locality"
},
  "geometry": {"coordinates":[90.28001,22.48276],"type":"Point"}
}