{
  "type": "Feature",
  "properties": {
    "gn:admin1_code":"87",
    "gn:admin2_code":"5527.0",
    "gn:admin3_code":"552764.0",
    "gn:admin4_code":"55276460.0",
    "gn:asciiname":"Kismatshalki",
    "gn:country_code":"BD",
    "gn:dem":38,
    "gn:feature_class":"P",
    "gn:feature_code":"PPL",
    "gn:name":"Kismatsh\u0101lki",
    "gn:population":0,
    "gn:timezone":"Asia/Dhaka",
    "iso:country":"BD",
    "name:ben_x_preferred":[
        "Kismatsh\u0101lki"
    ],
    "wof:name":"Kismatshalki",
    "wof:placetype":"locality"
},
  "geometry": {"coordinates":[88.72168000000001,25.51759],"type":"Point"}
}