{
  "type": "Feature",
  "properties": {
    "gn:admin1_code":"83",
    "gn:admin2_code":"5010.0",
    "gn:admin3_code":"501054.0",
    "gn:admin4_code":"50105428.0",
    "gn:asciiname":"Dakshin Debkhanda",
    "gn:country_code":"BD",
    "gn:dem":23,
    "gn:feature_class":"P",
    "gn:feature_code":"PPL",
    "gn:name":"Dakshin Debkhanda",
    "gn:population":0,
    "gn:timezone":"Asia/Dhaka",
    "iso:country":"BD",
    "wof:name":"Dakshin Debkhanda",
    "wof:placetype":"locality"
},
  "geometry": {"coordinates":[89.26127,24.73469],"type":"Point"}
}