{
  "type": "Feature",
  "properties": {
    "gn:admin1_code":"84",
    "gn:admin2_code":"2019",
    "gn:admin3_code":"201967.0",
    "gn:admin4_code":"20196700.0",
    "gn:asciiname":"Sasangachha",
    "gn:country_code":"BD",
    "gn:dem":16,
    "gn:feature_class":"P",
    "gn:feature_code":"PPL",
    "gn:name":"Sasang\u0101chha",
    "gn:population":0,
    "gn:timezone":"Asia/Dhaka",
    "iso:country":"BD",
    "wof:name":"Sasangachha",
    "wof:placetype":"locality"
},
  "geometry": {"coordinates":[91.16667,23.46667],"type":"Point"}
}