{
  "type": "Feature",
  "properties": {
    "gn:admin1_code":"84",
    "gn:admin2_code":"2019",
    "gn:admin3_code":"201937.0",
    "gn:admin4_code":"20193717.0",
    "gn:asciiname":"Machhimpur",
    "gn:country_code":"BD",
    "gn:dem":11,
    "gn:feature_class":"P",
    "gn:feature_code":"PPL",
    "gn:name":"M\u0101chhimpur",
    "gn:population":0,
    "gn:timezone":"Asia/Dhaka",
    "iso:country":"BD",
    "wof:name":"Machhimpur",
    "wof:placetype":"locality"
},
  "geometry": {"coordinates":[90.82964,23.62235],"type":"Point"}
}