{
  "type": "Feature",
  "properties": {
    "gn:admin1_code":"87",
    "gn:admin2_code":"5577.0",
    "gn:admin3_code":"557773.0",
    "gn:admin4_code":"55777347.0",
    "gn:asciiname":"Dalua Dighi",
    "gn:country_code":"BD",
    "gn:dem":75,
    "gn:feature_class":"P",
    "gn:feature_code":"PPL",
    "gn:name":"Dalu\u0101 D\u012bghi",
    "gn:population":0,
    "gn:timezone":"Asia/Dhaka",
    "iso:country":"BD",
    "name:ben_x_preferred":[
        "Dalu\u0101 D\u012bghi"
    ],
    "wof:name":"Dalua Dighi",
    "wof:placetype":"locality"
},
  "geometry": {"coordinates":[88.66394,26.35292],"type":"Point"}
}