{
  "type": "Feature",
  "properties": {
    "gn:admin1_code":"87",
    "gn:admin2_code":"5585",
    "gn:admin3_code":"558573.0",
    "gn:admin4_code":"55857357.0",
    "gn:asciiname":"Taluk Kandi Kabilpara",
    "gn:country_code":"BD",
    "gn:dem":31,
    "gn:feature_class":"P",
    "gn:feature_code":"PPL",
    "gn:name":"T\u0101luk K\u0101ndi K\u0101bilpara",
    "gn:population":0,
    "gn:timezone":"Asia/Dhaka",
    "iso:country":"BD",
    "name:ben_x_preferred":[
        "T\u0101luk K\u0101ndi K\u0101bilpara"
    ],
    "wof:name":"Taluk Kandi Kabilpara",
    "wof:placetype":"locality"
},
  "geometry": {"coordinates":[89.45303,25.60359],"type":"Point"}
}