{
  "type": "Feature",
  "properties": {
    "gn:admin1_code":"H",
    "gn:admin2_code":"3061",
    "gn:admin3_code":"306120.0",
    "gn:admin4_code":"30612035.0",
    "gn:asciiname":"Lakshmipur",
    "gn:country_code":"BD",
    "gn:dem":19,
    "gn:feature_class":"P",
    "gn:feature_code":"PPL",
    "gn:name":"Lakshmipur",
    "gn:population":0,
    "gn:timezone":"Asia/Dhaka",
    "iso:country":"BD",
    "wof:name":"Lakshmipur",
    "wof:placetype":"locality"
},
  "geometry": {"coordinates":[90.30947,24.68815],"type":"Point"}
}