{
  "type": "Feature",
  "properties": {
    "gn:admin1_code":"H",
    "gn:admin2_code":"3039.0",
    "gn:admin3_code":"303929.0",
    "gn:admin4_code":"30392923.0",
    "gn:asciiname":"Char Putimari",
    "gn:country_code":"BD",
    "gn:dem":23,
    "gn:feature_class":"P",
    "gn:feature_code":"PPL",
    "gn:name":"Char Putimari",
    "gn:population":0,
    "gn:timezone":"Asia/Dhaka",
    "iso:country":"BD",
    "name:und_x_variant":[
        "Char Putim\u0101ri"
    ],
    "wof:name":"Char Putimari",
    "wof:placetype":"locality"
},
  "geometry": {"coordinates":[89.89498,25.0586],"type":"Point"}
}