{
  "type": "Feature",
  "properties": {
    "gn:admin1_code":"82",
    "gn:admin2_code":"4041.0",
    "gn:admin3_code":"404109.0",
    "gn:admin4_code":"40410919.0",
    "gn:asciiname":"Telihanyapara",
    "gn:country_code":"BD",
    "gn:dem":13,
    "gn:feature_class":"P",
    "gn:feature_code":"PPL",
    "gn:name":"Telih\u0101nyapara",
    "gn:population":0,
    "gn:timezone":"Asia/Dhaka",
    "iso:country":"BD",
    "name:ben_x_preferred":[
        "Telih\u0101nyapara"
    ],
    "wof:name":"Telihanyapara",
    "wof:placetype":"locality"
},
  "geometry": {"coordinates":[89.26716999999999,23.27652],"type":"Point"}
}