{
  "type": "Feature",
  "properties": {
    "gn:admin1_code":"82",
    "gn:admin2_code":"4065.0",
    "gn:admin3_code":"406576.0",
    "gn:admin4_code":"40657613.0",
    "gn:asciiname":"Bhatgati",
    "gn:country_code":"BD",
    "gn:dem":9,
    "gn:feature_class":"P",
    "gn:feature_code":"PPL",
    "gn:name":"Bh\u0101tg\u0101ti",
    "gn:population":0,
    "gn:timezone":"Asia/Dhaka",
    "iso:country":"BD",
    "name:ben_x_preferred":[
        "Bh\u0101tg\u0101ti"
    ],
    "wof:name":"Bhatgati",
    "wof:placetype":"locality"
},
  "geometry": {"coordinates":[89.59265000000001,23.17379],"type":"Point"}
}