{
  "type": "Feature",
  "properties": {
    "gn:admin1_code":"81",
    "gn:admin2_code":"3068",
    "gn:admin3_code":"306864.0",
    "gn:admin4_code":"30686450.0",
    "gn:asciiname":"Nandertek",
    "gn:country_code":"BD",
    "gn:dem":18,
    "gn:feature_class":"P",
    "gn:feature_code":"PPL",
    "gn:name":"Nandertek",
    "gn:population":0,
    "gn:timezone":"Asia/Dhaka",
    "iso:country":"BD",
    "wof:name":"Nandertek",
    "wof:placetype":"locality"
},
  "geometry": {"coordinates":[90.83015,24.0222],"type":"Point"}
}