{
  "type": "Feature",
  "properties": {
    "gn:admin1_code":"81",
    "gn:admin2_code":"3035.0",
    "gn:admin3_code":"303543.0",
    "gn:admin4_code":"30354327.0",
    "gn:asciiname":"Jangal Mukundapur",
    "gn:country_code":"BD",
    "gn:dem":7,
    "gn:feature_class":"P",
    "gn:feature_code":"PPL",
    "gn:name":"Jangal Mukundapur",
    "gn:population":0,
    "gn:timezone":"Asia/Dhaka",
    "iso:country":"BD",
    "name:ben_x_preferred":[
        "Jangal Mukundapur"
    ],
    "wof:name":"Jangal Mukundapur",
    "wof:placetype":"locality"
},
  "geometry": {"coordinates":[89.70269999999999,23.20252],"type":"Point"}
}