{
  "type": "Feature",
  "properties": {
    "gn:admin1_code":"83",
    "gn:admin2_code":"5010",
    "gn:admin3_code":"501094.0",
    "gn:admin4_code":"50109431.0",
    "gn:asciiname":"Laskarpur",
    "gn:country_code":"BD",
    "gn:dem":23,
    "gn:feature_class":"P",
    "gn:feature_code":"PPL",
    "gn:name":"Laskarpur",
    "gn:population":0,
    "gn:timezone":"Asia/Dhaka",
    "iso:country":"BD",
    "name:ben_x_preferred":[
        "Laskarpur"
    ],
    "wof:name":"Laskarpur",
    "wof:placetype":"locality"
},
  "geometry": {"coordinates":[89.37453000000002,25.02863],"type":"Point"}
}