{
  "type": "Feature",
  "properties": {
    "gn:admin1_code":"87",
    "gn:admin2_code":"5594.0",
    "gn:admin3_code":"559494.0",
    "gn:admin4_code":"55949489.0",
    "gn:asciiname":"Salandar",
    "gn:country_code":"BD",
    "gn:dem":58,
    "gn:feature_class":"P",
    "gn:feature_code":"PPL",
    "gn:name":"Sal\u0101ndar",
    "gn:population":0,
    "gn:timezone":"Asia/Dhaka",
    "iso:country":"BD",
    "name:ben_x_preferred":[
        "Sal\u0101ndar"
    ],
    "wof:name":"Salandar",
    "wof:placetype":"locality"
},
  "geometry": {"coordinates":[88.50306999999999,26.03871],"type":"Point"}
}