{
  "type": "Feature",
  "properties": {
    "gn:admin1_code":"87",
    "gn:admin2_code":"5585",
    "gn:admin3_code":"558549.0",
    "gn:admin4_code":"55854900.0",
    "gn:asciiname":"Chhota Rangpur",
    "gn:country_code":"BD",
    "gn:dem":35,
    "gn:feature_class":"P",
    "gn:feature_code":"PPL",
    "gn:name":"Chhota Rangpur",
    "gn:population":0,
    "gn:timezone":"Asia/Dhaka",
    "iso:country":"BD",
    "name:ben_x_preferred":[
        "Chhota Rangpur"
    ],
    "wof:name":"Chhota Rangpur",
    "wof:placetype":"locality"
},
  "geometry": {"coordinates":[89.3026,25.71932],"type":"Point"}
}