{
  "type": "Feature",
  "properties": {
    "gn:admin1_code":"83",
    "gn:admin2_code":"5064.0",
    "gn:admin3_code":"506428.0",
    "gn:admin4_code":"50642877.0",
    "gn:asciiname":"Hazranpur",
    "gn:country_code":"BD",
    "gn:dem":27,
    "gn:feature_class":"P",
    "gn:feature_code":"PPL",
    "gn:name":"H\u0101zr\u0101npur",
    "gn:population":0,
    "gn:timezone":"Asia/Dhaka",
    "iso:country":"BD",
    "name:ben_x_preferred":[
        "H\u0101zr\u0101npur"
    ],
    "wof:name":"Hazranpur",
    "wof:placetype":"locality"
},
  "geometry": {"coordinates":[88.71670999999998,25.13848],"type":"Point"}
}