{
  "type": "Feature",
  "properties": {
    "gn:admin1_code":"82",
    "gn:admin2_code":"4087.0",
    "gn:admin3_code":"408747.0",
    "gn:admin4_code":"40874779.0",
    "gn:asciiname":"Bil Digha",
    "gn:country_code":"BD",
    "gn:dem":1,
    "gn:feature_class":"P",
    "gn:feature_code":"PPL",
    "gn:name":"B\u012bl D\u012bgha",
    "gn:population":0,
    "gn:timezone":"Asia/Dhaka",
    "iso:country":"BD",
    "wof:name":"Bil Digha",
    "wof:placetype":"locality"
},
  "geometry": {"coordinates":[89.06667,22.51667],"type":"Point"}
}