{
  "type": "Feature",
  "properties": {
    "gn:admin1_code":"81",
    "gn:admin2_code":"3086.0",
    "gn:admin3_code":"308669.0",
    "gn:admin4_code":"30866995.0",
    "gn:asciiname":"Darihaola",
    "gn:country_code":"BD",
    "gn:dem":11,
    "gn:feature_class":"P",
    "gn:feature_code":"PPL",
    "gn:name":"Darih\u0101ola",
    "gn:population":0,
    "gn:timezone":"Asia/Dhaka",
    "iso:country":"BD",
    "wof:name":"Darihaola",
    "wof:placetype":"locality"
},
  "geometry": {"coordinates":[90.30392000000001,23.21314],"type":"Point"}
}