{
  "type": "Feature",
  "properties": {
    "gn:admin1_code":"84",
    "gn:admin2_code":"2013.0",
    "gn:admin3_code":"201376.0",
    "gn:admin4_code":"20137656.0",
    "gn:asciiname":"Char Silandi",
    "gn:country_code":"BD",
    "gn:dem":10,
    "gn:feature_class":"P",
    "gn:feature_code":"PPL",
    "gn:name":"Char Silandi",
    "gn:population":0,
    "gn:timezone":"Asia/Dhaka",
    "iso:country":"BD",
    "wof:name":"Char Silandi",
    "wof:placetype":"locality"
},
  "geometry": {"coordinates":[90.77466,23.4427],"type":"Point"}
}