{
  "type": "Feature",
  "properties": {
    "gn:admin1_code":"81",
    "gn:admin2_code":"3035.0",
    "gn:admin3_code":"303532.0",
    "gn:admin4_code":"30353286.0",
    "gn:asciiname":"Jogacha",
    "gn:country_code":"BD",
    "gn:dem":11,
    "gn:feature_class":"P",
    "gn:feature_code":"PPL",
    "gn:name":"Jog\u0101cha",
    "gn:population":0,
    "gn:timezone":"Asia/Dhaka",
    "iso:country":"BD",
    "name:ben_x_preferred":[
        "Jog\u0101cha"
    ],
    "wof:name":"Jogacha",
    "wof:placetype":"locality"
},
  "geometry": {"coordinates":[89.75712,23.06258],"type":"Point"}
}