{
  "type": "Feature",
  "properties": {
    "gn:admin1_code":"84",
    "gn:admin2_code":"2019",
    "gn:admin3_code":"201918.0",
    "gn:admin4_code":"20191894.0",
    "gn:asciiname":"Kharatia",
    "gn:country_code":"BD",
    "gn:dem":11,
    "gn:feature_class":"P",
    "gn:feature_code":"PPL",
    "gn:name":"Kh\u0101r\u0101tia",
    "gn:population":0,
    "gn:timezone":"Asia/Dhaka",
    "iso:country":"BD",
    "wof:name":"Kharatia",
    "wof:placetype":"locality"
},
  "geometry": {"coordinates":[91.13333,23.53333],"type":"Point"}
}