{
  "type": "Feature",
  "properties": {
    "gn:admin1_code":"85",
    "gn:admin2_code":"1078.0",
    "gn:admin3_code":"107897.0",
    "gn:admin4_code":"10789783.0",
    "gn:asciiname":"Char Bostin",
    "gn:country_code":"BD",
    "gn:dem":5,
    "gn:feature_class":"P",
    "gn:feature_code":"PPL",
    "gn:name":"Char Bostin",
    "gn:population":0,
    "gn:timezone":"Asia/Dhaka",
    "iso:country":"BD",
    "name:ben_x_preferred":[
        "Char Bostin"
    ],
    "name:und_x_variant":[
        "Char Bastin"
    ],
    "wof:name":"Char Bostin",
    "wof:placetype":"locality"
},
  "geometry": {"coordinates":[90.58297,21.95713],"type":"Point"}
}