{
  "type": "Feature",
  "properties": {
    "gn:admin1_code":"83",
    "gn:admin2_code":"5070.0",
    "gn:admin3_code":"507088.0",
    "gn:admin4_code":"50708889.0",
    "gn:asciiname":"Bajitpur",
    "gn:country_code":"BD",
    "gn:dem":27,
    "gn:feature_class":"P",
    "gn:feature_code":"PPL",
    "gn:name":"Bajitpur",
    "gn:population":0,
    "gn:timezone":"Asia/Dhaka",
    "iso:country":"BD",
    "name:ben_x_preferred":[
        "Bajitpur"
    ],
    "wof:name":"Bajitpur",
    "wof:placetype":"locality"
},
  "geometry": {"coordinates":[88.16135,24.74571],"type":"Point"}
}