{
  "type": "Feature",
  "properties": {
    "gn:admin1_code":"82",
    "gn:admin2_code":"4041.0",
    "gn:admin3_code":"404109.0",
    "gn:admin4_code":"40410928.0",
    "gn:asciiname":"Pukuria",
    "gn:country_code":"BD",
    "gn:dem":10,
    "gn:feature_class":"P",
    "gn:feature_code":"PPL",
    "gn:name":"Pukuria",
    "gn:population":0,
    "gn:timezone":"Asia/Dhaka",
    "iso:country":"BD",
    "name:ben_x_preferred":[
        "Pukuria"
    ],
    "wof:name":"Pukuria",
    "wof:placetype":"locality"
},
  "geometry": {"coordinates":[89.31031999999998,23.20525],"type":"Point"}
}