{
  "type": "Feature",
  "properties": {
    "gn:admin1_code":"82",
    "gn:admin2_code":"4044.0",
    "gn:admin3_code":"404419.0",
    "gn:admin4_code":"40441900.0",
    "gn:asciiname":"Lakshmikal",
    "gn:country_code":"BD",
    "gn:dem":15,
    "gn:feature_class":"P",
    "gn:feature_code":"PPL",
    "gn:name":"Lakshmikal",
    "gn:population":0,
    "gn:timezone":"Asia/Dhaka",
    "iso:country":"BD",
    "name:ben_x_preferred":[
        "Lakshmikal"
    ],
    "wof:name":"Lakshmikal",
    "wof:placetype":"locality"
},
  "geometry": {"coordinates":[89.14864,23.55096],"type":"Point"}
}