{
  "type": "Feature",
  "properties": {
    "gn:admin1_code":"81",
    "gn:admin2_code":"3082",
    "gn:admin3_code":"308276.0",
    "gn:admin4_code":"30827629.0",
    "gn:asciiname":"Sastapur",
    "gn:country_code":"BD",
    "gn:dem":14,
    "gn:feature_class":"P",
    "gn:feature_code":"PPL",
    "gn:name":"S\u0101st\u0101pur",
    "gn:population":0,
    "gn:timezone":"Asia/Dhaka",
    "iso:country":"BD",
    "name:und_x_variant":[
        "Sayestapur",
        "S\u0101st\u0101pur"
    ],
    "wof:name":"Sastapur",
    "wof:placetype":"locality"
},
  "geometry": {"coordinates":[89.68575,23.6262],"type":"Point"}
}