{
  "type": "Feature",
  "properties": {
    "gn:admin1_code":"H",
    "gn:admin2_code":"3089.0",
    "gn:admin3_code":"308967.0",
    "gn:admin4_code":"30896728.0",
    "gn:asciiname":"Char Bhabna",
    "gn:country_code":"BD",
    "gn:dem":22,
    "gn:feature_class":"P",
    "gn:feature_code":"PPL",
    "gn:name":"Char Bh\u0101bna",
    "gn:population":0,
    "gn:timezone":"Asia/Dhaka",
    "iso:country":"BD",
    "wof:name":"Char Bhabna",
    "wof:placetype":"locality"
},
  "geometry": {"coordinates":[90.23877,24.91362],"type":"Point"}
}