{
  "type": "Feature",
  "properties": {
    "gn:admin1_code":"81",
    "gn:admin2_code":"3035.0",
    "gn:admin3_code":"303532.0",
    "gn:admin4_code":"30353286.0",
    "gn:asciiname":"Talajogir Char",
    "gn:country_code":"BD",
    "gn:dem":13,
    "gn:feature_class":"P",
    "gn:feature_code":"PPL",
    "gn:name":"T\u0101lajogir Char",
    "gn:population":0,
    "gn:timezone":"Asia/Dhaka",
    "iso:country":"BD",
    "name:ben_x_preferred":[
        "T\u0101lajogir Char"
    ],
    "wof:name":"Talajogir Char",
    "wof:placetype":"locality"
},
  "geometry": {"coordinates":[89.74891,23.05122],"type":"Point"}
}