{
  "type": "Feature",
  "properties": {
    "gn:admin1_code":"87",
    "gn:admin2_code":"5532",
    "gn:admin3_code":"553291.0",
    "gn:admin4_code":"55329118.0",
    "gn:asciiname":"Sicha",
    "gn:country_code":"BD",
    "gn:dem":27,
    "gn:feature_class":"P",
    "gn:feature_code":"PPL",
    "gn:name":"Sicha",
    "gn:population":0,
    "gn:timezone":"Asia/Dhaka",
    "iso:country":"BD",
    "name:ben_x_preferred":[
        "Sicha"
    ],
    "wof:name":"Sicha",
    "wof:placetype":"locality"
},
  "geometry": {"coordinates":[89.62501999999998,25.48253],"type":"Point"}
}