{
  "type": "Feature",
  "properties": {
    "gn:admin1_code":"83",
    "gn:admin2_code":"5069",
    "gn:admin3_code":"506909.0",
    "gn:admin4_code":"50690957.0",
    "gn:asciiname":"Maligachhi",
    "gn:country_code":"BD",
    "gn:dem":15,
    "gn:feature_class":"P",
    "gn:feature_code":"PPL",
    "gn:name":"M\u0101lig\u0101chhi",
    "gn:population":0,
    "gn:timezone":"Asia/Dhaka",
    "iso:country":"BD",
    "name:ben_x_preferred":[
        "M\u0101lig\u0101chhi"
    ],
    "wof:name":"Maligachhi",
    "wof:placetype":"locality"
},
  "geometry": {"coordinates":[88.91455999999999,24.28301],"type":"Point"}
}