{
  "type": "Feature",
  "properties": {
    "gn:admin1_code":"H",
    "gn:admin2_code":"3072.0",
    "gn:admin3_code":"307256.0",
    "gn:admin4_code":"30725610.0",
    "gn:asciiname":"Biasi",
    "gn:country_code":"BD",
    "gn:dem":13,
    "gn:feature_class":"P",
    "gn:feature_code":"PPL",
    "gn:name":"Bi\u0101si",
    "gn:population":0,
    "gn:timezone":"Asia/Dhaka",
    "iso:country":"BD",
    "wof:name":"Biasi",
    "wof:placetype":"locality"
},
  "geometry": {"coordinates":[90.97729,24.632],"type":"Point"}
}