{
  "type": "Feature",
  "properties": {
    "gn:admin1_code":"87",
    "gn:admin2_code":"5594.0",
    "gn:admin3_code":"559494.0",
    "gn:admin4_code":"55949458.0",
    "gn:asciiname":"Mukhtar Mela",
    "gn:country_code":"BD",
    "gn:dem":59,
    "gn:feature_class":"P",
    "gn:feature_code":"PPL",
    "gn:name":"Mukht\u0101r Mela",
    "gn:population":0,
    "gn:timezone":"Asia/Dhaka",
    "iso:country":"BD",
    "name:ben_x_preferred":[
        "Mukht\u0101r Mela"
    ],
    "wof:name":"Mukhtar Mela",
    "wof:placetype":"locality"
},
  "geometry": {"coordinates":[88.42288000000001,26.03213],"type":"Point"}
}