{
  "type": "Feature",
  "properties": {
    "gn:admin1_code":"85",
    "gn:admin2_code":"1042.0",
    "gn:admin3_code":"104243.0",
    "gn:admin4_code":"10424363.0",
    "gn:asciiname":"Bara Kathalia",
    "gn:country_code":"BD",
    "gn:dem":9,
    "gn:feature_class":"P",
    "gn:feature_code":"PPL",
    "gn:name":"Bara K\u0101th\u0101lia",
    "gn:population":0,
    "gn:timezone":"Asia/Dhaka",
    "iso:country":"BD",
    "name:ben_x_preferred":[
        "Bara K\u0101th\u0101lia"
    ],
    "wof:name":"Bara Kathalia",
    "wof:placetype":"locality"
},
  "geometry": {"coordinates":[90.13625999999999,22.41159],"type":"Point"}
}