{
  "type": "Feature",
  "properties": {
    "gn:admin1_code":"87",
    "gn:admin2_code":"5585",
    "gn:admin3_code":"558576.0",
    "gn:admin4_code":"55857669.0",
    "gn:asciiname":"Hilli",
    "gn:country_code":"BD",
    "gn:dem":32,
    "gn:feature_class":"P",
    "gn:feature_code":"PPL",
    "gn:name":"Hilli",
    "gn:population":0,
    "gn:timezone":"Asia/Dhaka",
    "iso:country":"BD",
    "name:ben_x_preferred":[
        "Hilli"
    ],
    "name:deu_x_preferred":[
        "Hilli"
    ],
    "name:fin_x_preferred":[
        "Hilli"
    ],
    "wof:name":"Hilli",
    "wof:placetype":"locality"
},
  "geometry": {"coordinates":[89.31815999999998,25.45099],"type":"Point"}
}