{
  "type": "Feature",
  "properties": {
    "gn:admin1_code":"83",
    "gn:admin2_code":"5069.0",
    "gn:admin3_code":"506963.0",
    "gn:admin4_code":"50696314.0",
    "gn:asciiname":"Banurbhag",
    "gn:country_code":"BD",
    "gn:dem":18,
    "gn:feature_class":"P",
    "gn:feature_code":"PPL",
    "gn:name":"B\u0101nurbh\u0101g",
    "gn:population":0,
    "gn:timezone":"Asia/Dhaka",
    "iso:country":"BD",
    "name:ben_x_preferred":[
        "B\u0101nurbh\u0101g"
    ],
    "wof:name":"Banurbhag",
    "wof:placetype":"locality"
},
  "geometry": {"coordinates":[88.92537,24.47399],"type":"Point"}
}