{
  "type": "Feature",
  "properties": {
    "gn:admin1_code":"87",
    "gn:admin2_code":"5594.0",
    "gn:admin3_code":"559482.0",
    "gn:admin4_code":"55948294.0",
    "gn:asciiname":"Beldahi",
    "gn:country_code":"BD",
    "gn:dem":43,
    "gn:feature_class":"P",
    "gn:feature_code":"PPL",
    "gn:name":"Beldahi",
    "gn:population":0,
    "gn:timezone":"Asia/Dhaka",
    "iso:country":"BD",
    "name:ben_x_preferred":[
        "Beldahi"
    ],
    "wof:name":"Beldahi",
    "wof:placetype":"locality"
},
  "geometry": {"coordinates":[88.27714,25.78809],"type":"Point"}
}