{
  "type": "Feature",
  "properties": {
    "gn:admin1_code":"82",
    "gn:admin2_code":"4044.0",
    "gn:admin3_code":"404471.0",
    "gn:admin4_code":"40447165.0",
    "gn:asciiname":"Begampur",
    "gn:country_code":"BD",
    "gn:dem":17,
    "gn:feature_class":"P",
    "gn:feature_code":"PPL",
    "gn:name":"Begampur",
    "gn:population":0,
    "gn:timezone":"Asia/Dhaka",
    "iso:country":"BD",
    "name:ben_x_preferred":[
        "Begampur"
    ],
    "wof:name":"Begampur",
    "wof:placetype":"locality"
},
  "geometry": {"coordinates":[88.88013000000002,23.37952],"type":"Point"}
}