{
  "type": "Feature",
  "properties": {
    "gn:admin1_code":"81",
    "gn:admin2_code":"3056",
    "gn:admin3_code":"305622.0",
    "gn:admin4_code":"30562211.0",
    "gn:asciiname":"Sanjuri",
    "gn:country_code":"BD",
    "gn:dem":17,
    "gn:feature_class":"P",
    "gn:feature_code":"PPL",
    "gn:name":"S\u0101njuri",
    "gn:population":0,
    "gn:timezone":"Asia/Dhaka",
    "iso:country":"BD",
    "wof:name":"Sanjuri",
    "wof:placetype":"locality"
},
  "geometry": {"coordinates":[89.92430999999998,23.87836],"type":"Point"}
}