{
  "type": "Feature",
  "properties": {
    "gn:admin1_code":"82",
    "gn:admin2_code":"4041.0",
    "gn:admin3_code":"404123.0",
    "gn:admin4_code":"40412353.0",
    "gn:asciiname":"Chanda",
    "gn:country_code":"BD",
    "gn:dem":14,
    "gn:feature_class":"P",
    "gn:feature_code":"PPL",
    "gn:name":"Chanda",
    "gn:population":0,
    "gn:timezone":"Asia/Dhaka",
    "iso:country":"BD",
    "name:ben_x_preferred":[
        "Chanda"
    ],
    "wof:name":"Chanda",
    "wof:placetype":"locality"
},
  "geometry": {"coordinates":[89.07929,23.16796],"type":"Point"}
}