{
  "type": "Feature",
  "properties": {
    "gn:admin1_code":"85",
    "gn:admin2_code":"1079.0",
    "gn:admin3_code":"107914.0",
    "gn:admin4_code":"10791447.0",
    "gn:asciiname":"Radhanagar",
    "gn:country_code":"BD",
    "gn:dem":10,
    "gn:feature_class":"P",
    "gn:feature_code":"PPL",
    "gn:name":"R\u0101dh\u0101nagar",
    "gn:population":0,
    "gn:timezone":"Asia/Dhaka",
    "iso:country":"BD",
    "name:ben_x_preferred":[
        "R\u0101dh\u0101nagar"
    ],
    "wof:name":"Radhanagar",
    "wof:placetype":"locality"
},
  "geometry": {"coordinates":[90.09689,22.45493],"type":"Point"}
}