{
  "type": "Feature",
  "properties": {
    "gn:admin1_code":"81",
    "gn:admin2_code":"3056.0",
    "gn:admin3_code":"305610.0",
    "gn:admin4_code":"30561028.0",
    "gn:asciiname":"Hatkora Diara",
    "gn:country_code":"BD",
    "gn:dem":9,
    "gn:feature_class":"P",
    "gn:feature_code":"PPL",
    "gn:name":"H\u0101tkora Di\u0101ra",
    "gn:population":0,
    "gn:timezone":"Asia/Dhaka",
    "iso:country":"BD",
    "wof:name":"Hatkora Diara",
    "wof:placetype":"locality"
},
  "geometry": {"coordinates":[89.83333,23.93333],"type":"Point"}
}