{
  "type": "Feature",
  "properties": {
    "gn:admin1_code":"82",
    "gn:admin2_code":"4050.0",
    "gn:admin3_code":"405079.0",
    "gn:admin4_code":"40507975.0",
    "gn:asciiname":"Char Gopalpur",
    "gn:country_code":"BD",
    "gn:dem":17,
    "gn:feature_class":"P",
    "gn:feature_code":"PPL",
    "gn:name":"Char Gop\u0101lpur",
    "gn:population":0,
    "gn:timezone":"Asia/Dhaka",
    "iso:country":"BD",
    "name:ben_x_preferred":[
        "Char Gop\u0101lpur"
    ],
    "wof:name":"Char Gopalpur",
    "wof:placetype":"locality"
},
  "geometry": {"coordinates":[89.14363,23.86153],"type":"Point"}
}