{
  "type": "Feature",
  "properties": {
    "gn:admin1_code":"H",
    "gn:admin2_code":"3061.0",
    "gn:admin3_code":"306120.0",
    "gn:admin4_code":"30612094.0",
    "gn:asciiname":"Haripur",
    "gn:country_code":"BD",
    "gn:dem":16,
    "gn:feature_class":"P",
    "gn:feature_code":"PPL",
    "gn:name":"Haripur",
    "gn:population":0,
    "gn:timezone":"Asia/Dhaka",
    "iso:country":"BD",
    "wof:name":"Haripur",
    "wof:placetype":"locality"
},
  "geometry": {"coordinates":[90.21839,24.53928],"type":"Point"}
}