{
  "type": "Feature",
  "properties": {
    "gn:admin1_code":"82",
    "gn:admin2_code":"4041.0",
    "gn:admin3_code":"404104.0",
    "gn:admin4_code":"40410463.0",
    "gn:asciiname":"Dighaliabad",
    "gn:country_code":"BD",
    "gn:dem":6,
    "gn:feature_class":"P",
    "gn:feature_code":"PPL",
    "gn:name":"Dighali\u0101b\u0101d",
    "gn:population":0,
    "gn:timezone":"Asia/Dhaka",
    "iso:country":"BD",
    "name:ben_x_preferred":[
        "Dighali\u0101b\u0101d"
    ],
    "wof:name":"Dighaliabad",
    "wof:placetype":"locality"
},
  "geometry": {"coordinates":[89.54344,22.95157],"type":"Point"}
}