{
  "type": "Feature",
  "properties": {
    "gn:admin1_code":"84",
    "gn:admin2_code":"2019",
    "gn:admin3_code":"201940.0",
    "gn:admin4_code":"20194077.0",
    "gn:asciiname":"Rajamenhar",
    "gn:country_code":"BD",
    "gn:dem":9,
    "gn:feature_class":"P",
    "gn:feature_code":"PPL",
    "gn:name":"R\u0101j\u0101menhar",
    "gn:population":0,
    "gn:timezone":"Asia/Dhaka",
    "iso:country":"BD",
    "name:und_x_variant":[
        "R\u0101j\u0101menhar",
        "R\u0101j\u0101meh\u0101r"
    ],
    "wof:name":"Rajamenhar",
    "wof:placetype":"locality"
},
  "geometry": {"coordinates":[90.93114,23.55235],"type":"Point"}
}