{
  "type": "Feature",
  "properties": {
    "gn:admin1_code":"H",
    "gn:admin2_code":"3061",
    "gn:admin3_code":"306131.0",
    "gn:admin4_code":"30613154.0",
    "gn:asciiname":"Khordda Saiya",
    "gn:country_code":"BD",
    "gn:dem":14,
    "gn:feature_class":"P",
    "gn:feature_code":"PPL",
    "gn:name":"Khordda S\u0101iya",
    "gn:population":0,
    "gn:timezone":"Asia/Dhaka",
    "iso:country":"BD",
    "wof:name":"Khordda Saiya",
    "wof:placetype":"locality"
},
  "geometry": {"coordinates":[90.60585,24.60596],"type":"Point"}
}