{
  "type": "Feature",
  "properties": {
    "gn:admin1_code":"87",
    "gn:admin2_code":"5527",
    "gn:admin3_code":"552747.0",
    "gn:admin4_code":"55274740.0",
    "gn:asciiname":"Bishapara",
    "gn:country_code":"BD",
    "gn:dem":30,
    "gn:feature_class":"P",
    "gn:feature_code":"PPL",
    "gn:name":"Bishapara",
    "gn:population":0,
    "gn:timezone":"Asia/Dhaka",
    "iso:country":"BD",
    "name:ben_x_preferred":[
        "Bishapara"
    ],
    "wof:name":"Bishapara",
    "wof:placetype":"locality"
},
  "geometry": {"coordinates":[89.02223000000002,25.30344],"type":"Point"}
}