{
  "type": "Feature",
  "properties": {
    "gn:admin1_code":"H",
    "gn:admin2_code":"3061",
    "gn:admin3_code":"306131.0",
    "gn:admin4_code":"30613154.0",
    "gn:asciiname":"Maijbhag",
    "gn:country_code":"BD",
    "gn:dem":14,
    "gn:feature_class":"P",
    "gn:feature_code":"PPL",
    "gn:name":"M\u0101ijbh\u0101g",
    "gn:population":0,
    "gn:timezone":"Asia/Dhaka",
    "iso:country":"BD",
    "name:und_x_variant":[
        "M\u0101ijbh\u0101g",
        "M\u0101ijbhag"
    ],
    "wof:name":"Maijbhag",
    "wof:placetype":"locality"
},
  "geometry": {"coordinates":[90.63215,24.61963],"type":"Point"}
}