{
  "type": "Feature",
  "properties": {
    "gn:admin1_code":"87",
    "gn:admin2_code":"5527.0",
    "gn:admin3_code":"552712.0",
    "gn:admin4_code":"55271234.0",
    "gn:asciiname":"Barahat",
    "gn:country_code":"BD",
    "gn:dem":50,
    "gn:feature_class":"P",
    "gn:feature_code":"PPL",
    "gn:name":"Barah\u0101t",
    "gn:population":0,
    "gn:timezone":"Asia/Dhaka",
    "iso:country":"BD",
    "name:ben_x_preferred":[
        "Barah\u0101t"
    ],
    "wof:name":"Barahat",
    "wof:placetype":"locality"
},
  "geometry": {"coordinates":[88.6784,25.92965],"type":"Point"}
}