{
  "type": "Feature",
  "properties": {
    "gn:admin1_code":"H",
    "gn:admin2_code":"3072.0",
    "gn:admin3_code":"307283.0",
    "gn:admin4_code":"30728355.0",
    "gn:asciiname":"Atharapata",
    "gn:country_code":"BD",
    "gn:dem":16,
    "gn:feature_class":"P",
    "gn:feature_code":"PPL",
    "gn:name":"Athar\u0101p\u0101ta",
    "gn:population":0,
    "gn:timezone":"Asia/Dhaka",
    "iso:country":"BD",
    "name:und_x_variant":[
        "Athar\u0101p\u0101ta",
        "\u0100th\u0101rapota"
    ],
    "wof:name":"Atharapata",
    "wof:placetype":"locality"
},
  "geometry": {"coordinates":[90.59671,24.83295],"type":"Point"}
}