{
  "type": "Feature",
  "properties": {
    "gn:admin1_code":"H",
    "gn:admin2_code":"3089",
    "gn:admin3_code":"308937.0",
    "gn:admin4_code":"30893743.0",
    "gn:asciiname":"Bholuka",
    "gn:country_code":"BD",
    "gn:dem":24,
    "gn:feature_class":"P",
    "gn:feature_code":"PPL",
    "gn:name":"Bholuka",
    "gn:population":0,
    "gn:timezone":"Asia/Dhaka",
    "iso:country":"BD",
    "name:und_x_variant":[
        "Bhaluka",
        "Bholuka"
    ],
    "wof:name":"Bholuka",
    "wof:placetype":"locality"
},
  "geometry": {"coordinates":[90.04782,25.19966],"type":"Point"}
}