{
  "type": "Feature",
  "properties": {
    "gn:admin1_code":"82",
    "gn:admin2_code":"4065.0",
    "gn:admin3_code":"406576.0",
    "gn:admin4_code":"40657606.0",
    "gn:asciiname":"Daoatala",
    "gn:country_code":"BD",
    "gn:dem":11,
    "gn:feature_class":"P",
    "gn:feature_code":"PPL",
    "gn:name":"Dao\u0101tala",
    "gn:population":0,
    "gn:timezone":"Asia/Dhaka",
    "iso:country":"BD",
    "name:ben_x_preferred":[
        "Dao\u0101tala"
    ],
    "wof:name":"Daoatala",
    "wof:placetype":"locality"
},
  "geometry": {"coordinates":[89.56551,23.18782],"type":"Point"}
}