{
  "type": "Feature",
  "properties": {
    "gn:admin1_code":"81",
    "gn:admin2_code":"3048",
    "gn:admin3_code":"304854.0",
    "gn:admin4_code":"30485411.0",
    "gn:asciiname":"Matikata",
    "gn:country_code":"BD",
    "gn:dem":10,
    "gn:feature_class":"P",
    "gn:feature_code":"PPL",
    "gn:name":"M\u0101tik\u0101ta",
    "gn:population":0,
    "gn:timezone":"Asia/Dhaka",
    "iso:country":"BD",
    "wof:name":"Matikata",
    "wof:placetype":"locality"
},
  "geometry": {"coordinates":[90.88697999999999,24.10682000000001],"type":"Point"}
}