{
  "type": "Feature",
  "properties": {
    "gn:admin1_code":"87",
    "gn:admin2_code":"5532",
    "gn:admin3_code":"553291.0",
    "gn:admin4_code":"55329163.0",
    "gn:asciiname":"Bishnatari",
    "gn:country_code":"BD",
    "gn:dem":26,
    "gn:feature_class":"P",
    "gn:feature_code":"PPL",
    "gn:name":"Bishnat\u0101ri",
    "gn:population":0,
    "gn:timezone":"Asia/Dhaka",
    "iso:country":"BD",
    "name:ben_x_preferred":[
        "Bishnat\u0101ri"
    ],
    "wof:name":"Bishnatari",
    "wof:placetype":"locality"
},
  "geometry": {"coordinates":[89.51586999999998,25.50241],"type":"Point"}
}