{
  "type": "Feature",
  "properties": {
    "gn:admin1_code":"83",
    "gn:admin2_code":"5064.0",
    "gn:admin3_code":"506469.0",
    "gn:admin4_code":"50646973.0",
    "gn:asciiname":"Satalpur",
    "gn:country_code":"BD",
    "gn:dem":46,
    "gn:feature_class":"P",
    "gn:feature_code":"PPL",
    "gn:name":"Sat\u0101lpur",
    "gn:population":0,
    "gn:timezone":"Asia/Dhaka",
    "iso:country":"BD",
    "name:ben_x_preferred":[
        "Sat\u0101lpur"
    ],
    "wof:name":"Satalpur",
    "wof:placetype":"locality"
},
  "geometry": {"coordinates":[88.48399000000001,24.85814],"type":"Point"}
}