{
  "type": "Feature",
  "properties": {
    "gn:admin1_code":"83",
    "gn:admin2_code":"5081",
    "gn:admin3_code":"508131.0",
    "gn:admin4_code":"50813171.0",
    "gn:asciiname":"Kismat Maria",
    "gn:country_code":"BD",
    "gn:dem":21,
    "gn:feature_class":"P",
    "gn:feature_code":"PPL",
    "gn:name":"Kismat M\u0101ria",
    "gn:population":0,
    "gn:timezone":"Asia/Dhaka",
    "iso:country":"BD",
    "name:ben_x_preferred":[
        "Kismat M\u0101ria"
    ],
    "name:ben_x_variant":[
        "M\u0101ria Kismat"
    ],
    "wof:name":"Kismat Maria",
    "wof:placetype":"locality"
},
  "geometry": {"coordinates":[88.77821999999998,24.42085],"type":"Point"}
}