{
  "type": "Feature",
  "properties": {
    "gn:admin1_code":"84",
    "gn:admin2_code":"2015.0",
    "gn:admin3_code":"201582.0",
    "gn:admin4_code":"20158258.0",
    "gn:asciiname":"Maisamura",
    "gn:country_code":"BD",
    "gn:dem":12,
    "gn:feature_class":"P",
    "gn:feature_code":"PPL",
    "gn:name":"Mais\u0101mura",
    "gn:population":0,
    "gn:timezone":"Asia/Dhaka",
    "iso:country":"BD",
    "name:ben_x_preferred":[
        "Mais\u0101mura"
    ],
    "wof:name":"Maisamura",
    "wof:placetype":"locality"
},
  "geometry": {"coordinates":[92.05437000000001,22.13927],"type":"Point"}
}