{
  "type": "Feature",
  "properties": {
    "gn:admin1_code":"81",
    "gn:admin2_code":"3033",
    "gn:admin3_code":"303336.0",
    "gn:admin4_code":"30333643.0",
    "gn:asciiname":"Khudadia",
    "gn:country_code":"BD",
    "gn:dem":13,
    "gn:feature_class":"P",
    "gn:feature_code":"PPL",
    "gn:name":"Khud\u0101dia",
    "gn:population":0,
    "gn:timezone":"Asia/Dhaka",
    "iso:country":"BD",
    "name:und_x_variant":[
        "Khud\u0101dia",
        "Khod\u0101dia"
    ],
    "wof:name":"Khudadia",
    "wof:placetype":"locality"
},
  "geometry": {"coordinates":[90.56802999999999,24.09872],"type":"Point"}
}