{
  "type": "Feature",
  "properties": {
    "gn:admin1_code":"87",
    "gn:admin2_code":"5552",
    "gn:admin3_code":"555239.0",
    "gn:admin4_code":"55523923.0",
    "gn:asciiname":"Nithak",
    "gn:country_code":"BD",
    "gn:dem":40,
    "gn:feature_class":"P",
    "gn:feature_code":"PPL",
    "gn:name":"Nithak",
    "gn:population":0,
    "gn:timezone":"Asia/Dhaka",
    "iso:country":"BD",
    "name:ben_x_preferred":[
        "Nithak"
    ],
    "wof:name":"Nithak",
    "wof:placetype":"locality"
},
  "geometry": {"coordinates":[89.31923,25.98171],"type":"Point"}
}