{
  "type": "Feature",
  "properties": {
    "gn:admin1_code":"82",
    "gn:admin2_code":"4044.0",
    "gn:admin3_code":"404419.0",
    "gn:admin4_code":"40441921.0",
    "gn:asciiname":"Munuria",
    "gn:country_code":"BD",
    "gn:dem":13,
    "gn:feature_class":"P",
    "gn:feature_code":"PPL",
    "gn:name":"Munuria",
    "gn:population":0,
    "gn:timezone":"Asia/Dhaka",
    "iso:country":"BD",
    "name:ben_x_preferred":[
        "Munuria"
    ],
    "wof:name":"Munuria",
    "wof:placetype":"locality"
},
  "geometry": {"coordinates":[89.2486,23.4593],"type":"Point"}
}