{
  "type": "Feature",
  "properties": {
    "gn:admin1_code":"82",
    "gn:admin2_code":"4044.0",
    "gn:admin3_code":"404419.0",
    "gn:admin4_code":"40441942.0",
    "gn:asciiname":"Hajratala",
    "gn:country_code":"BD",
    "gn:dem":12,
    "gn:feature_class":"P",
    "gn:feature_code":"PPL",
    "gn:name":"H\u0101jr\u0101tala",
    "gn:population":0,
    "gn:timezone":"Asia/Dhaka",
    "iso:country":"BD",
    "name:ben_x_preferred":[
        "H\u0101jr\u0101tala"
    ],
    "wof:name":"Hajratala",
    "wof:placetype":"locality"
},
  "geometry": {"coordinates":[89.21794,23.52763],"type":"Point"}
}