{
  "type": "Feature",
  "properties": {
    "gn:admin1_code":"82",
    "gn:admin2_code":"4055.0",
    "gn:admin3_code":"405595.0",
    "gn:admin4_code":"40559573.0",
    "gn:asciiname":"Arazi Tupipara",
    "gn:country_code":"BD",
    "gn:dem":10,
    "gn:feature_class":"P",
    "gn:feature_code":"PPL",
    "gn:name":"\u0100r\u0101zi Tupip\u0101ra",
    "gn:population":0,
    "gn:timezone":"Asia/Dhaka",
    "iso:country":"BD",
    "wof:name":"Arazi Tupipara",
    "wof:placetype":"locality"
},
  "geometry": {"coordinates":[89.38333,23.56667],"type":"Point"}
}