{
  "type": "Feature",
  "properties": {
    "gn:admin1_code":"83",
    "gn:admin2_code":"5010",
    "gn:admin3_code":"501094.0",
    "gn:admin4_code":"50109487.0",
    "gn:asciiname":"Gangnagar Majhpara",
    "gn:country_code":"BD",
    "gn:dem":22,
    "gn:feature_class":"P",
    "gn:feature_code":"PPL",
    "gn:name":"Gangnagar M\u0101jhp\u0101ra",
    "gn:population":0,
    "gn:timezone":"Asia/Dhaka",
    "iso:country":"BD",
    "name:ben_x_preferred":[
        "Gangnagar M\u0101jhp\u0101ra"
    ],
    "wof:name":"Gangnagar Majhpara",
    "wof:placetype":"locality"
},
  "geometry": {"coordinates":[89.41259000000002,25.07181],"type":"Point"}
}