{
  "type": "Feature",
  "properties": {
    "gn:admin1_code":"83",
    "gn:admin2_code":"5081.0",
    "gn:admin3_code":"508125.0",
    "gn:admin4_code":"50812587.0",
    "gn:asciiname":"Baliaghati",
    "gn:country_code":"BD",
    "gn:dem":22,
    "gn:feature_class":"P",
    "gn:feature_code":"PPL",
    "gn:name":"B\u0101li\u0101gh\u0101ti",
    "gn:population":0,
    "gn:timezone":"Asia/Dhaka",
    "iso:country":"BD",
    "name:ben_x_preferred":[
        "B\u0101li\u0101gh\u0101ti"
    ],
    "wof:name":"Baliaghati",
    "wof:placetype":"locality"
},
  "geometry": {"coordinates":[88.76356,24.35355],"type":"Point"}
}