{
  "type": "Feature",
  "properties": {
    "gn:admin1_code":"82",
    "gn:admin2_code":"4065.0",
    "gn:admin3_code":"406576.0",
    "gn:admin4_code":"40657633.0",
    "gn:asciiname":"Dhuria Ambaria",
    "gn:country_code":"BD",
    "gn:dem":11,
    "gn:feature_class":"P",
    "gn:feature_code":"PPL",
    "gn:name":"Dhuria Amb\u0101ria",
    "gn:population":0,
    "gn:timezone":"Asia/Dhaka",
    "iso:country":"BD",
    "name:ben_x_preferred":[
        "Dhuria Amb\u0101ria"
    ],
    "wof:name":"Dhuria Ambaria",
    "wof:placetype":"locality"
},
  "geometry": {"coordinates":[89.55453,23.21206],"type":"Point"}
}