{
  "type": "Feature",
  "properties": {
    "gn:admin1_code":"82",
    "gn:admin2_code":"4087.0",
    "gn:admin3_code":"408725.0",
    "gn:admin4_code":"40872547.0",
    "gn:asciiname":"Atapur",
    "gn:country_code":"BD",
    "gn:dem":7,
    "gn:feature_class":"P",
    "gn:feature_code":"PPL",
    "gn:name":"\u0100t\u0101pur",
    "gn:population":0,
    "gn:timezone":"Asia/Dhaka",
    "iso:country":"BD",
    "wof:name":"Atapur",
    "wof:placetype":"locality"
},
  "geometry": {"coordinates":[89.01130000000001,22.5679],"type":"Point"}
}