{
  "type": "Feature",
  "properties": {
    "gn:admin1_code":"84",
    "gn:admin2_code":"2015.0",
    "gn:admin3_code":"201508.0",
    "gn:admin4_code":"20150825.0",
    "gn:asciiname":"Khudukkhali",
    "gn:country_code":"BD",
    "gn:dem":7,
    "gn:feature_class":"P",
    "gn:feature_code":"PPL",
    "gn:name":"Khudukkh\u0101li",
    "gn:population":0,
    "gn:timezone":"Asia/Dhaka",
    "iso:country":"BD",
    "name:ben_x_preferred":[
        "Khudukkh\u0101li"
    ],
    "wof:name":"Khudukkhali",
    "wof:placetype":"locality"
},
  "geometry": {"coordinates":[91.91078,21.91366],"type":"Point"}
}