{
  "type": "Feature",
  "properties": {
    "gn:admin1_code":"86",
    "gn:admin2_code":"6036.0",
    "gn:admin3_code":"603626.0",
    "gn:admin4_code":"60362609.0",
    "gn:asciiname":"Sokhdebpur",
    "gn:country_code":"BD",
    "gn:dem":27,
    "gn:feature_class":"P",
    "gn:feature_code":"PPL",
    "gn:name":"Sokhdebpur",
    "gn:population":0,
    "gn:timezone":"Asia/Dhaka",
    "iso:country":"BD",
    "wof:name":"Sokhdebpur",
    "wof:placetype":"locality"
},
  "geometry": {"coordinates":[91.54441,24.14301],"type":"Point"}
}