{
  "type": "Feature",
  "properties": {
    "gn:admin1_code":"84",
    "gn:admin2_code":"2051.0",
    "gn:admin3_code":"205173.0",
    "gn:admin4_code":"20517331.0",
    "gn:asciiname":"Char Hasan Hossain",
    "gn:country_code":"BD",
    "gn:dem":9,
    "gn:feature_class":"P",
    "gn:feature_code":"PPL",
    "gn:name":"Char Hasan Hossain",
    "gn:population":0,
    "gn:timezone":"Asia/Dhaka",
    "iso:country":"BD",
    "name:und_x_variant":[
        "Char Hassan Hosein",
        "Char H\u0101san Hosein",
        "Char Hasan Hossain"
    ],
    "wof:name":"Char Hasan Hossain",
    "wof:placetype":"locality"
},
  "geometry": {"coordinates":[90.94291,22.66541],"type":"Point"}
}