{
  "type": "Feature",
  "properties": {
    "gn:admin1_code":"85",
    "gn:admin2_code":"1079",
    "gn:admin3_code":"107914.0",
    "gn:admin4_code":"10791459.0",
    "gn:asciiname":"Atar Khali",
    "gn:country_code":"BD",
    "gn:dem":11,
    "gn:feature_class":"P",
    "gn:feature_code":"PPL",
    "gn:name":"Atar Khali",
    "gn:population":0,
    "gn:timezone":"Asia/Dhaka",
    "iso:country":"BD",
    "name:ben_x_preferred":[
        "Atar Khali"
    ],
    "wof:name":"Atar Khali",
    "wof:placetype":"locality"
},
  "geometry": {"coordinates":[89.99266999999998,22.39397],"type":"Point"}
}