{
  "type": "Feature",
  "properties": {
    "gn:admin1_code":"84",
    "gn:admin2_code":"2022.0",
    "gn:admin3_code":"202266.0",
    "gn:admin4_code":"20226609.0",
    "gn:asciiname":"Haitupi",
    "gn:country_code":"BD",
    "gn:dem":9,
    "gn:feature_class":"P",
    "gn:feature_code":"PPL",
    "gn:name":"H\u0101itupi",
    "gn:population":0,
    "gn:timezone":"Asia/Dhaka",
    "iso:country":"BD",
    "name:ben_x_preferred":[
        "H\u0101itupi"
    ],
    "wof:name":"Haitupi",
    "wof:placetype":"locality"
},
  "geometry": {"coordinates":[92.11086,21.43846],"type":"Point"}
}