{
  "type": "Feature",
  "properties": {
    "gn:admin1_code":"85",
    "gn:admin2_code":"1006",
    "gn:admin3_code":"100607.0",
    "gn:admin4_code":"10060781.0",
    "gn:asciiname":"Niamati",
    "gn:country_code":"BD",
    "gn:dem":8,
    "gn:feature_class":"P",
    "gn:feature_code":"PPL",
    "gn:name":"Ni\u0101m\u0101ti",
    "gn:population":0,
    "gn:timezone":"Asia/Dhaka",
    "iso:country":"BD",
    "name:ben_x_preferred":[
        "Ni\u0101m\u0101ti"
    ],
    "name:und_x_variant":[
        "Nyamati"
    ],
    "wof:name":"Niamati",
    "wof:placetype":"locality"
},
  "geometry": {"coordinates":[90.20243000000001,22.48415],"type":"Point"}
}