{
  "type": "Feature",
  "properties": {
    "gn:admin1_code":"81",
    "gn:admin2_code":"3056",
    "gn:admin3_code":"305678.0",
    "gn:admin4_code":"30567823.0",
    "gn:asciiname":"Sahili",
    "gn:country_code":"BD",
    "gn:dem":14,
    "gn:feature_class":"P",
    "gn:feature_code":"PPL",
    "gn:name":"S\u0101hili",
    "gn:population":0,
    "gn:timezone":"Asia/Dhaka",
    "iso:country":"BD",
    "wof:name":"Sahili",
    "wof:placetype":"locality"
},
  "geometry": {"coordinates":[89.87489000000002,23.86433],"type":"Point"}
}