{
  "type": "Feature",
  "properties": {
    "gn:admin1_code":"83",
    "gn:admin2_code":"5064.0",
    "gn:admin3_code":"506428.0",
    "gn:admin4_code":"50642842.0",
    "gn:asciiname":"Purba Raghunathpur",
    "gn:country_code":"BD",
    "gn:dem":24,
    "gn:feature_class":"P",
    "gn:feature_code":"PPL",
    "gn:name":"Purba Raghunathpur",
    "gn:population":0,
    "gn:timezone":"Asia/Dhaka",
    "iso:country":"BD",
    "name:ben_x_preferred":[
        "Purba Raghunathpur"
    ],
    "wof:name":"Purba Raghunathpur",
    "wof:placetype":"locality"
},
  "geometry": {"coordinates":[88.91072,25.14191],"type":"Point"}
}