{
  "type": "Feature",
  "properties": {
    "gn:admin1_code":"87",
    "gn:admin2_code":"5532",
    "gn:admin3_code":"553282.0",
    "gn:admin4_code":"55328234.0",
    "gn:asciiname":"Islampur",
    "gn:country_code":"BD",
    "gn:dem":29,
    "gn:feature_class":"P",
    "gn:feature_code":"PPL",
    "gn:name":"Islampur",
    "gn:population":0,
    "gn:timezone":"Asia/Dhaka",
    "iso:country":"BD",
    "name:ben_x_preferred":[
        "Islampur"
    ],
    "wof:name":"Islampur",
    "wof:placetype":"locality"
},
  "geometry": {"coordinates":[89.35484,25.36745],"type":"Point"}
}