{
  "type": "Feature",
  "properties": {
    "gn:admin1_code":"87",
    "gn:admin2_code":"5594.0",
    "gn:admin3_code":"559494.0",
    "gn:admin4_code":"55949436.0",
    "gn:asciiname":"Darajgaon",
    "gn:country_code":"BD",
    "gn:dem":67,
    "gn:feature_class":"P",
    "gn:feature_code":"PPL",
    "gn:name":"D\u0101r\u0101jgaon",
    "gn:population":0,
    "gn:timezone":"Asia/Dhaka",
    "iso:country":"BD",
    "name:ben_x_preferred":[
        "D\u0101r\u0101jgaon"
    ],
    "wof:name":"Darajgaon",
    "wof:placetype":"locality"
},
  "geometry": {"coordinates":[88.49419,26.17875],"type":"Point"}
}