{
  "type": "Feature",
  "properties": {
    "gn:admin1_code":"81",
    "gn:admin2_code":"3056.0",
    "gn:admin3_code":"305628.0",
    "gn:admin4_code":"30562851.0",
    "gn:asciiname":"Bangala",
    "gn:country_code":"BD",
    "gn:dem":11,
    "gn:feature_class":"P",
    "gn:feature_code":"PPL",
    "gn:name":"B\u0101ng\u0101la",
    "gn:population":0,
    "gn:timezone":"Asia/Dhaka",
    "iso:country":"BD",
    "wof:name":"Bangala",
    "wof:placetype":"locality"
},
  "geometry": {"coordinates":[89.94228000000003,23.78719],"type":"Point"}
}