{
  "type": "Feature",
  "properties": {
    "gn:admin1_code":"87",
    "gn:admin2_code":"5573.0",
    "gn:admin3_code":"557312.0",
    "gn:admin4_code":"55731276.0",
    "gn:asciiname":"ogipara",
    "gn:country_code":"BD",
    "gn:dem":64,
    "gn:feature_class":"P",
    "gn:feature_code":"PPL",
    "gn:name":"ogip\u0101ra",
    "gn:population":0,
    "gn:timezone":"Asia/Dhaka",
    "iso:country":"BD",
    "name:ben_x_preferred":[
        "ogip\u0101ra"
    ],
    "wof:name":"ogipara",
    "wof:placetype":"locality"
},
  "geometry": {"coordinates":[88.88515,26.26966],"type":"Point"}
}