{
  "type": "Feature",
  "properties": {
    "gn:admin1_code":"84",
    "gn:admin2_code":"2046.0",
    "gn:admin3_code":"204680.0",
    "gn:admin4_code":"20468038.0",
    "gn:asciiname":"Lundugyapara",
    "gn:country_code":"BD",
    "gn:dem":89,
    "gn:feature_class":"P",
    "gn:feature_code":"PPL",
    "gn:name":"Lundugy\u0101p\u0101ra",
    "gn:population":0,
    "gn:timezone":"Asia/Dhaka",
    "iso:country":"BD",
    "name:ben_x_preferred":[
        "Lundugy\u0101p\u0101ra"
    ],
    "wof:name":"Lundugyapara",
    "wof:placetype":"locality"
},
  "geometry": {"coordinates":[91.90844,22.90991],"type":"Point"}
}