{
  "type": "Feature",
  "properties": {
    "gn:admin1_code":"83",
    "gn:admin2_code":"5064",
    "gn:admin3_code":"506450.0",
    "gn:admin4_code":"50645057.0",
    "gn:asciiname":"Kurapara",
    "gn:country_code":"BD",
    "gn:dem":22,
    "gn:feature_class":"P",
    "gn:feature_code":"PPL",
    "gn:name":"Kur\u0101p\u0101ra",
    "gn:population":0,
    "gn:timezone":"Asia/Dhaka",
    "iso:country":"BD",
    "name:ben_x_preferred":[
        "Kur\u0101p\u0101ra"
    ],
    "wof:name":"Kurapara",
    "wof:placetype":"locality"
},
  "geometry": {"coordinates":[88.66204999999999,24.9396],"type":"Point"}
}