{
  "type": "Feature",
  "properties": {
    "gn:admin1_code":"87",
    "gn:admin2_code":"5549",
    "gn:admin3_code":"554918.0",
    "gn:admin4_code":"55491827.0",
    "gn:asciiname":"Khachabari",
    "gn:country_code":"BD",
    "gn:dem":30,
    "gn:feature_class":"P",
    "gn:feature_code":"PPL",
    "gn:name":"Khach\u0101bari",
    "gn:population":0,
    "gn:timezone":"Asia/Dhaka",
    "iso:country":"BD",
    "name:ben_x_preferred":[
        "Khach\u0101bari"
    ],
    "wof:name":"Khachabari",
    "wof:placetype":"locality"
},
  "geometry": {"coordinates":[89.6341,25.8883],"type":"Point"}
}