{
  "type": "Feature",
  "properties": {
    "gn:admin1_code":"81",
    "gn:admin2_code":"3086",
    "gn:admin3_code":"308636.0",
    "gn:admin4_code":"30863635.0",
    "gn:asciiname":"Dakshin Halaipatti",
    "gn:country_code":"BD",
    "gn:dem":11,
    "gn:feature_class":"P",
    "gn:feature_code":"PPL",
    "gn:name":"Dakshin Hal\u0101ipatti",
    "gn:population":0,
    "gn:timezone":"Asia/Dhaka",
    "iso:country":"BD",
    "name:und_x_variant":[
        "South Kalaipatti",
        "South Halaipatty",
        "South Halaipatti",
        "Dakshin Hal\u0101ipatti"
    ],
    "wof:name":"Dakshin Halaipatti",
    "wof:placetype":"locality"
},
  "geometry": {"coordinates":[90.40192999999999,23.07336],"type":"Point"}
}