{
  "type": "Feature",
  "properties": {
    "gn:admin1_code":"82",
    "gn:admin2_code":"4041.0",
    "gn:admin3_code":"404109.0",
    "gn:admin4_code":"40410947.0",
    "gn:asciiname":"Arazi Jamdia",
    "gn:country_code":"BD",
    "gn:dem":17,
    "gn:feature_class":"P",
    "gn:feature_code":"PPL",
    "gn:name":"\u0100r\u0101zi J\u0101mdia",
    "gn:population":0,
    "gn:timezone":"Asia/Dhaka",
    "iso:country":"BD",
    "name:ben_x_preferred":[
        "\u0100r\u0101zi J\u0101mdia"
    ],
    "wof:name":"Arazi Jamdia",
    "wof:placetype":"locality"
},
  "geometry": {"coordinates":[89.3835,23.20549],"type":"Point"}
}