{
  "type": "Feature",
  "properties": {
    "gn:admin1_code":"83",
    "gn:admin2_code":"5070",
    "gn:admin3_code":"507066.0",
    "gn:admin4_code":"50706611.0",
    "gn:asciiname":"Manpur",
    "gn:country_code":"BD",
    "gn:dem":34,
    "gn:feature_class":"P",
    "gn:feature_code":"PPL",
    "gn:name":"M\u0101npur",
    "gn:population":0,
    "gn:timezone":"Asia/Dhaka",
    "iso:country":"BD",
    "name:ben_x_preferred":[
        "M\u0101npur"
    ],
    "name:ceb_x_preferred":[
        "Manpur"
    ],
    "name:fra_x_preferred":[
        "Manpur"
    ],
    "name:pol_x_preferred":[
        "Manpur"
    ],
    "name:swe_x_preferred":[
        "Manpur"
    ],
    "wof:name":"Manpur",
    "wof:placetype":"locality"
},
  "geometry": {"coordinates":[88.30686999999998,24.63714],"type":"Point"}
}