{
  "type": "Feature",
  "properties": {
    "gn:admin1_code":"87",
    "gn:admin2_code":"5527",
    "gn:admin3_code":"552769.0",
    "gn:admin4_code":"55276925.0",
    "gn:asciiname":"Paramanandapi",
    "gn:country_code":"BD",
    "gn:dem":29,
    "gn:feature_class":"P",
    "gn:feature_code":"PPL",
    "gn:name":"Paramanandapi",
    "gn:population":0,
    "gn:timezone":"Asia/Dhaka",
    "iso:country":"BD",
    "name:ben_x_preferred":[
        "Paramanandapi"
    ],
    "wof:name":"Paramanandapi",
    "wof:placetype":"locality"
},
  "geometry": {"coordinates":[89.11230999999999,25.39215],"type":"Point"}
}