{
  "type": "Feature",
  "properties": {
    "gn:admin1_code":"83",
    "gn:admin2_code":"5081.0",
    "gn:admin3_code":"508134.0",
    "gn:admin4_code":"50813409.0",
    "gn:asciiname":"Dumkoli",
    "gn:country_code":"BD",
    "gn:dem":25,
    "gn:feature_class":"P",
    "gn:feature_code":"PPL",
    "gn:name":"Dumkoli",
    "gn:population":0,
    "gn:timezone":"Asia/Dhaka",
    "iso:country":"BD",
    "name:ben_x_preferred":[
        "Dumkoli"
    ],
    "name:ben_x_variant":[
        "Domkuli"
    ],
    "wof:name":"Dumkoli",
    "wof:placetype":"locality"
},
  "geometry": {"coordinates":[88.31408,24.51688],"type":"Point"}
}