{
  "type": "Feature",
  "properties": {
    "gn:admin1_code":"87",
    "gn:admin2_code":"5573.0",
    "gn:admin3_code":"557315.0",
    "gn:admin4_code":"55731557.0",
    "gn:asciiname":"Sonaraipara",
    "gn:country_code":"BD",
    "gn:dem":54,
    "gn:feature_class":"P",
    "gn:feature_code":"PPL",
    "gn:name":"Son\u0101r\u0101ip\u0101ra",
    "gn:population":0,
    "gn:timezone":"Asia/Dhaka",
    "iso:country":"BD",
    "name:ben_x_preferred":[
        "Son\u0101r\u0101ip\u0101ra"
    ],
    "wof:name":"Sonaraipara",
    "wof:placetype":"locality"
},
  "geometry": {"coordinates":[88.83969999999999,26.089],"type":"Point"}
}