{
  "type": "Feature",
  "properties": {
    "gn:admin1_code":"H",
    "gn:admin2_code":"3072",
    "gn:admin3_code":"307204.0",
    "gn:admin4_code":"30720471.0",
    "gn:asciiname":"Shyampur",
    "gn:country_code":"BD",
    "gn:dem":13,
    "gn:feature_class":"P",
    "gn:feature_code":"PPL",
    "gn:name":"Shy\u0101mpur",
    "gn:population":0,
    "gn:timezone":"Asia/Dhaka",
    "iso:country":"BD",
    "wof:name":"Shyampur",
    "wof:placetype":"locality"
},
  "geometry": {"coordinates":[90.86678000000001,24.8439],"type":"Point"}
}