{
  "type": "Feature",
  "properties": {
    "gn:admin1_code":"87",
    "gn:admin2_code":"5585",
    "gn:admin3_code":"558592.0",
    "gn:admin4_code":"55859279.0",
    "gn:asciiname":"Pashapara",
    "gn:country_code":"BD",
    "gn:dem":42,
    "gn:feature_class":"P",
    "gn:feature_code":"PPL",
    "gn:name":"Pash\u0101p\u0101ra",
    "gn:population":0,
    "gn:timezone":"Asia/Dhaka",
    "iso:country":"BD",
    "name:ben_x_preferred":[
        "Pash\u0101p\u0101ra"
    ],
    "wof:name":"Pashapara",
    "wof:placetype":"locality"
},
  "geometry": {"coordinates":[89.03618,25.76406],"type":"Point"}
}