{
  "type": "Feature",
  "properties": {
    "gn:admin1_code":"87",
    "gn:admin2_code":"5585",
    "gn:admin3_code":"558503.0",
    "gn:admin4_code":"55850363.0",
    "gn:asciiname":"Kutubpur Khiarpara",
    "gn:country_code":"BD",
    "gn:dem":38,
    "gn:feature_class":"P",
    "gn:feature_code":"PPL",
    "gn:name":"Kutubpur Khiarpara",
    "gn:population":0,
    "gn:timezone":"Asia/Dhaka",
    "iso:country":"BD",
    "name:ben_x_preferred":[
        "Kutubpur Khiarpara"
    ],
    "wof:name":"Kutubpur Khiarpara",
    "wof:placetype":"locality"
},
  "geometry": {"coordinates":[89.12770999999999,25.64466],"type":"Point"}
}