{
  "type": "Feature",
  "properties": {
    "gn:admin1_code":"86",
    "gn:admin2_code":"6090.0",
    "gn:admin3_code":"609023.0",
    "gn:admin4_code":"60902390.0",
    "gn:asciiname":"Bagain",
    "gn:country_code":"BD",
    "gn:dem":18,
    "gn:feature_class":"P",
    "gn:feature_code":"PPL",
    "gn:name":"B\u0101gain",
    "gn:population":0,
    "gn:timezone":"Asia/Dhaka",
    "iso:country":"BD",
    "wof:name":"Bagain",
    "wof:placetype":"locality"
},
  "geometry": {"coordinates":[91.65102,24.88881],"type":"Point"}
}