{
  "type": "Feature",
  "properties": {
    "gn:admin1_code":"87",
    "gn:admin2_code":"5573",
    "gn:admin3_code":"557345.0",
    "gn:admin4_code":"55734534.0",
    "gn:asciiname":"Uttar Chandkhana",
    "gn:country_code":"BD",
    "gn:dem":44,
    "gn:feature_class":"P",
    "gn:feature_code":"PPL",
    "gn:name":"Uttar Ch\u0101ndkh\u0101na",
    "gn:population":0,
    "gn:timezone":"Asia/Dhaka",
    "iso:country":"BD",
    "name:ben_x_preferred":[
        "Uttar Ch\u0101ndkh\u0101na"
    ],
    "wof:name":"Uttar Chandkhana",
    "wof:placetype":"locality"
},
  "geometry": {"coordinates":[89.03740999999999,25.86134],"type":"Point"}
}