{
  "type": "Feature",
  "properties": {
    "gn:admin1_code":"82",
    "gn:asciiname":"Tengrakhali",
    "gn:country_code":"BD",
    "gn:dem":9,
    "gn:feature_class":"P",
    "gn:feature_code":"PPL",
    "gn:name":"Tengr\u0101kh\u0101li",
    "gn:population":0,
    "gn:timezone":"Asia/Dhaka",
    "iso:country":"BD",
    "name:ben_x_preferred":[
        "Tengr\u0101kh\u0101li"
    ],
    "wof:name":"Tengrakhali",
    "wof:placetype":"locality"
},
  "geometry": {"coordinates":[90.31101,22.37311],"type":"Point"}
}