{
  "type": "Feature",
  "properties": {
    "gn:admin1_code":"81",
    "gn:admin2_code":"3054",
    "gn:admin3_code":"305440.0",
    "gn:admin4_code":"30544031.0",
    "gn:asciiname":"Paschim Khanduli",
    "gn:country_code":"BD",
    "gn:dem":7,
    "gn:feature_class":"P",
    "gn:feature_code":"PPL",
    "gn:name":"Paschim Kh\u0101nduli",
    "gn:population":0,
    "gn:timezone":"Asia/Dhaka",
    "iso:country":"BD",
    "name:und_x_variant":[
        "Paschim Kh\u0101nduli",
        "West Kh\u0101nduli"
    ],
    "wof:name":"Paschim Khanduli",
    "wof:placetype":"locality"
},
  "geometry": {"coordinates":[90.15648,23.08244],"type":"Point"}
}