{
  "type": "Feature",
  "properties": {
    "gn:admin1_code":"82",
    "gn:admin2_code":"4047.0",
    "gn:admin3_code":"404794.0",
    "gn:admin4_code":"40479413.0",
    "gn:asciiname":"Shekpura",
    "gn:country_code":"BD",
    "gn:dem":5,
    "gn:feature_class":"P",
    "gn:feature_code":"PPL",
    "gn:name":"Shekpura",
    "gn:population":0,
    "gn:timezone":"Asia/Dhaka",
    "iso:country":"BD",
    "name:ben_x_preferred":[
        "Shekpura"
    ],
    "wof:name":"Shekpura",
    "wof:placetype":"locality"
},
  "geometry": {"coordinates":[89.64872,22.8715],"type":"Point"}
}