{
  "type": "Feature",
  "properties": {
    "gn:admin1_code":"82",
    "gn:admin2_code":"4044.0",
    "gn:admin3_code":"404433.0",
    "gn:admin4_code":"40443320.0",
    "gn:asciiname":"Haradebpur",
    "gn:country_code":"BD",
    "gn:dem":13,
    "gn:feature_class":"P",
    "gn:feature_code":"PPL",
    "gn:name":"Haradebpur",
    "gn:population":0,
    "gn:timezone":"Asia/Dhaka",
    "iso:country":"BD",
    "name:ben_x_preferred":[
        "Haradebpur"
    ],
    "wof:name":"Haradebpur",
    "wof:placetype":"locality"
},
  "geometry": {"coordinates":[89.19468000000001,23.42807],"type":"Point"}
}