{
  "type": "Feature",
  "properties": {
    "gn:admin1_code":"84",
    "gn:admin2_code":"2013.0",
    "gn:admin3_code":"201358.0",
    "gn:admin4_code":"20135894.0",
    "gn:asciiname":"Asharkota",
    "gn:country_code":"BD",
    "gn:dem":10,
    "gn:feature_class":"P",
    "gn:feature_code":"PPL",
    "gn:name":"\u0100sh\u0101rkota",
    "gn:population":0,
    "gn:timezone":"Asia/Dhaka",
    "iso:country":"BD",
    "name:und_x_variant":[
        "Asharkata",
        "\u0100sh\u0101rkota"
    ],
    "wof:name":"Asharkota",
    "wof:placetype":"locality"
},
  "geometry": {"coordinates":[90.83472999999999,23.39714],"type":"Point"}
}