{
  "type": "Feature",
  "properties": {
    "gn:admin1_code":"82",
    "gn:admin2_code":"4050.0",
    "gn:admin3_code":"405079.0",
    "gn:admin4_code":"40507950.0",
    "gn:asciiname":"Dustapara",
    "gn:country_code":"BD",
    "gn:dem":15,
    "gn:feature_class":"P",
    "gn:feature_code":"PPL",
    "gn:name":"Dustap\u0101ra",
    "gn:population":0,
    "gn:timezone":"Asia/Dhaka",
    "iso:country":"BD",
    "name:ben_x_preferred":[
        "Dustap\u0101ra"
    ],
    "wof:name":"Dustapara",
    "wof:placetype":"locality"
},
  "geometry": {"coordinates":[89.06949,23.87395],"type":"Point"}
}