{
  "type": "Feature",
  "properties": {
    "gn:admin1_code":"83",
    "gn:admin2_code":"5064",
    "gn:admin3_code":"506475.0",
    "gn:admin4_code":"50647551.0",
    "gn:asciiname":"Meghdumbar",
    "gn:country_code":"BD",
    "gn:dem":26,
    "gn:feature_class":"P",
    "gn:feature_code":"PPL",
    "gn:name":"Meghdumbar",
    "gn:population":0,
    "gn:timezone":"Asia/Dhaka",
    "iso:country":"BD",
    "name:ben_x_preferred":[
        "Meghdumbar"
    ],
    "name:ben_x_variant":[
        "Megdambar"
    ],
    "name:und_x_variant":[
        "Meghodomber"
    ],
    "wof:name":"Meghdumbar",
    "wof:placetype":"locality"
},
  "geometry": {"coordinates":[88.68748000000002,25.00164],"type":"Point"}
}