{
  "type": "Feature",
  "properties": {
    "gn:admin1_code":"H",
    "gn:admin2_code":"3061",
    "gn:admin3_code":"306181.0",
    "gn:admin4_code":"30618131.0",
    "gn:asciiname":"Kusiadhara",
    "gn:country_code":"BD",
    "gn:dem":21,
    "gn:feature_class":"P",
    "gn:feature_code":"PPL",
    "gn:name":"Kusiadhara",
    "gn:population":0,
    "gn:timezone":"Asia/Dhaka",
    "iso:country":"BD",
    "wof:name":"Kusiadhara",
    "wof:placetype":"locality"
},
  "geometry": {"coordinates":[90.47964,24.90932],"type":"Point"}
}