{
  "type": "Feature",
  "properties": {
    "gn:admin1_code":"81",
    "gn:admin2_code":"3029.0",
    "gn:admin3_code":"302918.0",
    "gn:admin4_code":"30291835.0",
    "gn:asciiname":"Gohailbari",
    "gn:country_code":"BD",
    "gn:dem":12,
    "gn:feature_class":"P",
    "gn:feature_code":"PPL",
    "gn:name":"Goh\u0101ilb\u0101ri",
    "gn:population":0,
    "gn:timezone":"Asia/Dhaka",
    "iso:country":"BD",
    "wof:name":"Gohailbari",
    "wof:placetype":"locality"
},
  "geometry": {"coordinates":[89.61976,23.44429],"type":"Point"}
}