{
  "type": "Feature",
  "properties": {
    "gn:admin1_code":"87",
    "gn:admin2_code":"5532",
    "gn:admin3_code":"553224.0",
    "gn:admin4_code":"55322443.0",
    "gn:asciiname":"Baguria",
    "gn:country_code":"BD",
    "gn:dem":24,
    "gn:feature_class":"P",
    "gn:feature_code":"PPL",
    "gn:name":"Baguria",
    "gn:population":0,
    "gn:timezone":"Asia/Dhaka",
    "iso:country":"BD",
    "name:ben_x_preferred":[
        "Baguria"
    ],
    "wof:name":"Baguria",
    "wof:placetype":"locality"
},
  "geometry": {"coordinates":[89.60258,25.33746],"type":"Point"}
}