{
  "type": "Feature",
  "properties": {
    "gn:admin1_code":"87",
    "gn:admin2_code":"5549",
    "gn:admin3_code":"554961.0",
    "gn:admin4_code":"55496163.0",
    "gn:asciiname":"Char Majiali",
    "gn:country_code":"BD",
    "gn:dem":30,
    "gn:feature_class":"P",
    "gn:feature_code":"PPL",
    "gn:name":"Char M\u0101ji\u0101li",
    "gn:population":0,
    "gn:timezone":"Asia/Dhaka",
    "iso:country":"BD",
    "name:ben_x_preferred":[
        "Char M\u0101ji\u0101li"
    ],
    "wof:name":"Char Majiali",
    "wof:placetype":"locality"
},
  "geometry": {"coordinates":[89.8171,25.91034],"type":"Point"}
}