{
  "type": "Feature",
  "properties": {
    "gn:admin1_code":"82",
    "gn:admin2_code":"4044.0",
    "gn:admin3_code":"404414.0",
    "gn:admin4_code":"40441452.0",
    "gn:asciiname":"Dherakhali",
    "gn:country_code":"BD",
    "gn:dem":18,
    "gn:feature_class":"P",
    "gn:feature_code":"PPL",
    "gn:name":"Dherakh\u0101li",
    "gn:population":0,
    "gn:timezone":"Asia/Dhaka",
    "iso:country":"BD",
    "name:ben_x_preferred":[
        "Dherakh\u0101li"
    ],
    "wof:name":"Dherakhali",
    "wof:placetype":"locality"
},
  "geometry": {"coordinates":[89.06121999999998,23.7118],"type":"Point"}
}