{
  "type": "Feature",
  "properties": {
    "gn:admin1_code":"81",
    "gn:admin2_code":"3054",
    "gn:admin3_code":"305440.0",
    "gn:admin4_code":"30544094.0",
    "gn:asciiname":"Kalaisardarer Char",
    "gn:country_code":"BD",
    "gn:dem":10,
    "gn:feature_class":"P",
    "gn:feature_code":"PPL",
    "gn:name":"K\u0101l\u0101isardarer Char",
    "gn:population":0,
    "gn:timezone":"Asia/Dhaka",
    "iso:country":"BD",
    "name:und_x_variant":[
        "Kalai Sarder Char",
        "K\u0101l\u0101isardarer Char"
    ],
    "wof:name":"Kalaisardarer Char",
    "wof:placetype":"locality"
},
  "geometry": {"coordinates":[90.2933,23.07558],"type":"Point"}
}