{
  "type": "Feature",
  "properties": {
    "gn:admin1_code":"81",
    "gn:admin2_code":"3048",
    "gn:admin3_code":"304849.0",
    "gn:admin4_code":"30484977.0",
    "gn:asciiname":"MahichKandi",
    "gn:country_code":"BD",
    "gn:dem":14,
    "gn:feature_class":"P",
    "gn:feature_code":"PPL",
    "gn:name":"MahichK\u0101ndi",
    "gn:population":0,
    "gn:timezone":"Asia/Dhaka",
    "iso:country":"BD",
    "name:und_x_variant":[
        "MahichK\u0101ndi",
        "Mahish K\u0101ndi"
    ],
    "wof:name":"MahichKandi",
    "wof:placetype":"locality"
},
  "geometry": {"coordinates":[90.80349,24.5073],"type":"Point"}
}