{
  "type": "Feature",
  "properties": {
    "gn:admin1_code":"81",
    "gn:admin2_code":"3026",
    "gn:admin3_code":"302638.0",
    "gn:admin4_code":"30263825.0",
    "gn:asciiname":"Jainpur",
    "gn:country_code":"BD",
    "gn:dem":11,
    "gn:feature_class":"P",
    "gn:feature_code":"PPL",
    "gn:name":"Jainpur",
    "gn:population":0,
    "gn:timezone":"Asia/Dhaka",
    "iso:country":"BD",
    "name:pan_x_preferred":[
        "\u0a1c\u0a48\u0a28\u0a2a\u0a41\u0a30"
    ],
    "wof:name":"Jainpur",
    "wof:placetype":"locality"
},
  "geometry": {"coordinates":[90.29677,23.69781],"type":"Point"}
}