{
  "type": "Feature",
  "properties": {
    "gn:admin1_code":"87",
    "gn:admin2_code":"5552.0",
    "gn:admin3_code":"555270.0",
    "gn:admin4_code":"55527067.0",
    "gn:asciiname":"Mukta Jaldhar",
    "gn:country_code":"BD",
    "gn:dem":62,
    "gn:feature_class":"P",
    "gn:feature_code":"PPL",
    "gn:name":"Mukta Jaldh\u0101r",
    "gn:population":0,
    "gn:timezone":"Asia/Dhaka",
    "iso:country":"BD",
    "name:ben_x_preferred":[
        "Mukta Jaldh\u0101r"
    ],
    "wof:name":"Mukta Jaldhar",
    "wof:placetype":"locality"
},
  "geometry": {"coordinates":[89.01098,26.38019],"type":"Point"}
}