{
  "type": "Feature",
  "properties": {
    "gn:admin1_code":"83",
    "gn:admin2_code":"5070.0",
    "gn:admin3_code":"507088.0",
    "gn:admin4_code":"50708808.0",
    "gn:asciiname":"Madari Moralertola",
    "gn:country_code":"BD",
    "gn:dem":28,
    "gn:feature_class":"P",
    "gn:feature_code":"PPL",
    "gn:name":"Madari Moralertola",
    "gn:population":0,
    "gn:timezone":"Asia/Dhaka",
    "iso:country":"BD",
    "name:ben_x_preferred":[
        "Madari Moralertola"
    ],
    "wof:name":"Madari Moralertola",
    "wof:placetype":"locality"
},
  "geometry": {"coordinates":[88.08591,24.74494],"type":"Point"}
}