{
  "type": "Feature",
  "properties": {
    "gn:admin1_code":"87",
    "gn:admin2_code":"5585",
    "gn:admin3_code":"558558.0",
    "gn:admin4_code":"55855833.0",
    "gn:asciiname":"Bila Hariharpur",
    "gn:country_code":"BD",
    "gn:dem":32,
    "gn:feature_class":"P",
    "gn:feature_code":"PPL",
    "gn:name":"Bila Hariharpur",
    "gn:population":0,
    "gn:timezone":"Asia/Dhaka",
    "iso:country":"BD",
    "name:ben_x_preferred":[
        "Bila Hariharpur"
    ],
    "wof:name":"Bila Hariharpur",
    "wof:placetype":"locality"
},
  "geometry": {"coordinates":[89.22639000000002,25.55895],"type":"Point"}
}