{
  "type": "Feature",
  "properties": {
    "gn:admin1_code":"82",
    "gn:admin2_code":"4087.0",
    "gn:admin3_code":"408782.0",
    "gn:admin4_code":"40878240.0",
    "gn:asciiname":"Hardaha",
    "gn:country_code":"BD",
    "gn:dem":8,
    "gn:feature_class":"P",
    "gn:feature_code":"PPL",
    "gn:name":"Hardaha",
    "gn:population":0,
    "gn:timezone":"Asia/Dhaka",
    "iso:country":"BD",
    "name:ben_x_preferred":[
        "Hardaha"
    ],
    "wof:name":"Hardaha",
    "wof:placetype":"locality"
},
  "geometry": {"coordinates":[88.94071,22.62928],"type":"Point"}
}