{
  "type": "Feature",
  "properties": {
    "gn:admin1_code":"87",
    "gn:admin2_code":"5532",
    "gn:admin3_code":"553282.0",
    "gn:admin4_code":"55328225.0",
    "gn:asciiname":"Jamudanga",
    "gn:country_code":"BD",
    "gn:dem":30,
    "gn:feature_class":"P",
    "gn:feature_code":"PPL",
    "gn:name":"Jamudanga",
    "gn:population":0,
    "gn:timezone":"Asia/Dhaka",
    "iso:country":"BD",
    "name:und_x_variant":[
        "J\u0101mud\u0101nga"
    ],
    "wof:name":"Jamudanga",
    "wof:placetype":"locality"
},
  "geometry": {"coordinates":[89.46562,25.42889],"type":"Point"}
}