{
  "type": "Feature",
  "properties": {
    "gn:admin1_code":"H",
    "gn:admin2_code":"3072",
    "gn:admin3_code":"307240.0",
    "gn:admin4_code":"30724059.0",
    "gn:asciiname":"Lengura",
    "gn:country_code":"BD",
    "gn:dem":19,
    "gn:feature_class":"P",
    "gn:feature_code":"PPL",
    "gn:name":"Lengura",
    "gn:population":0,
    "gn:timezone":"Asia/Dhaka",
    "iso:country":"BD",
    "wof:name":"Lengura",
    "wof:placetype":"locality"
},
  "geometry": {"coordinates":[90.78695,25.15658],"type":"Point"}
}