{
  "type": "Feature",
  "properties": {
    "gn:admin1_code":"82",
    "gn:admin2_code":"4047",
    "gn:admin3_code":"404764.0",
    "gn:admin4_code":"40476450.0",
    "gn:asciiname":"Takia",
    "gn:country_code":"BD",
    "gn:dem":9,
    "gn:feature_class":"P",
    "gn:feature_code":"PPL",
    "gn:name":"Takia",
    "gn:population":0,
    "gn:timezone":"Asia/Dhaka",
    "iso:country":"BD",
    "wof:name":"Takia",
    "wof:placetype":"locality"
},
  "geometry": {"coordinates":[89.31661,22.63416],"type":"Point"}
}