{
  "type": "Feature",
  "properties": {
    "gn:admin1_code":"87",
    "gn:admin2_code":"5527",
    "gn:admin3_code":"552710.0",
    "gn:admin4_code":"55271035.0",
    "gn:asciiname":"Katchgram",
    "gn:country_code":"BD",
    "gn:dem":33,
    "gn:feature_class":"P",
    "gn:feature_code":"PPL",
    "gn:name":"Katchgram",
    "gn:population":0,
    "gn:timezone":"Asia/Dhaka",
    "iso:country":"BD",
    "name:ben_x_preferred":[
        "Katchgram"
    ],
    "wof:name":"Katchgram",
    "wof:placetype":"locality"
},
  "geometry": {"coordinates":[89.04881999999998,25.37217],"type":"Point"}
}