{
  "type": "Feature",
  "properties": {
    "gn:admin1_code":"82",
    "gn:admin2_code":"4047",
    "gn:admin3_code":"404753.0",
    "gn:admin4_code":"40475394.0",
    "gn:asciiname":"Uttar Bedkashi",
    "gn:country_code":"BD",
    "gn:dem":5,
    "gn:feature_class":"P",
    "gn:feature_code":"PPL",
    "gn:name":"Uttar Bedk\u0101shi",
    "gn:population":0,
    "gn:timezone":"Asia/Dhaka",
    "iso:country":"BD",
    "name:ben_x_preferred":[
        "Uttar Bedk\u0101shi"
    ],
    "name:ben_x_variant":[
        "Uttar Bedk\u0101si"
    ],
    "wof:name":"Uttar Bedkashi",
    "wof:placetype":"locality"
},
  "geometry": {"coordinates":[89.30354,22.30385],"type":"Point"}
}