{
  "type": "Feature",
  "properties": {
    "gn:admin1_code":"87",
    "gn:admin2_code":"5527.0",
    "gn:admin3_code":"552760.0",
    "gn:admin4_code":"55276063.0",
    "gn:asciiname":"Randangapara",
    "gn:country_code":"BD",
    "gn:dem":53,
    "gn:feature_class":"P",
    "gn:feature_code":"PPL",
    "gn:name":"R\u0101nd\u0101ngap\u0101ra",
    "gn:population":0,
    "gn:timezone":"Asia/Dhaka",
    "iso:country":"BD",
    "name:ben_x_preferred":[
        "R\u0101nd\u0101ngap\u0101ra"
    ],
    "wof:name":"Randangapara",
    "wof:placetype":"locality"
},
  "geometry": {"coordinates":[88.76314000000001,25.93505],"type":"Point"}
}