{
  "type": "Feature",
  "properties": {
    "gn:admin1_code":"83",
    "gn:admin2_code":"5038.0",
    "gn:admin3_code":"503861.0",
    "gn:admin4_code":"50386119.0",
    "gn:asciiname":"Chhota Tara",
    "gn:country_code":"BD",
    "gn:dem":24,
    "gn:feature_class":"P",
    "gn:feature_code":"PPL",
    "gn:name":"Chhota T\u0101ra",
    "gn:population":0,
    "gn:timezone":"Asia/Dhaka",
    "iso:country":"BD",
    "name:ben_x_preferred":[
        "Chhota T\u0101ra"
    ],
    "wof:name":"Chhota Tara",
    "wof:placetype":"locality"
},
  "geometry": {"coordinates":[89.12703,25.09367],"type":"Point"}
}