{
  "type": "Feature",
  "properties": {
    "gn:admin1_code":"82",
    "gn:admin2_code":"4057.0",
    "gn:admin3_code":"405747.0",
    "gn:admin4_code":"40574794.0",
    "gn:asciiname":"Palashipara",
    "gn:country_code":"BD",
    "gn:dem":23,
    "gn:feature_class":"P",
    "gn:feature_code":"PPL",
    "gn:name":"Pal\u0101ship\u0101ra",
    "gn:population":0,
    "gn:timezone":"Asia/Dhaka",
    "iso:country":"BD",
    "name:ben_x_preferred":[
        "Pal\u0101ship\u0101ra"
    ],
    "name:ben_x_variant":[
        "\u09aa\u09b2\u09be\u09b6\u09c0\u09aa\u09be\u09a1\u09bc\u09be"
    ],
    "wof:name":"Palashipara",
    "wof:placetype":"locality"
},
  "geometry": {"coordinates":[88.73475000000001,23.89595],"type":"Point"}
}