{
  "type": "Feature",
  "properties": {
    "gn:admin1_code":"83",
    "gn:admin2_code":"5064.0",
    "gn:admin3_code":"506486.0",
    "gn:admin4_code":"50648679.0",
    "gn:asciiname":"Laimail",
    "gn:country_code":"BD",
    "gn:dem":42,
    "gn:feature_class":"P",
    "gn:feature_code":"PPL",
    "gn:name":"L\u0101im\u0101il",
    "gn:population":0,
    "gn:timezone":"Asia/Dhaka",
    "iso:country":"BD",
    "name:ben_x_preferred":[
        "L\u0101im\u0101il"
    ],
    "wof:name":"Laimail",
    "wof:placetype":"locality"
},
  "geometry": {"coordinates":[88.54571999999997,25.13609],"type":"Point"}
}