{
  "type": "Feature",
  "properties": {
    "gn:admin1_code":"83",
    "gn:admin2_code":"5088",
    "gn:admin3_code":"508894.0",
    "gn:admin4_code":"50889487.0",
    "gn:asciiname":"Panch Digal",
    "gn:country_code":"BD",
    "gn:dem":15,
    "gn:feature_class":"P",
    "gn:feature_code":"PPL",
    "gn:name":"P\u0101nch Digal",
    "gn:population":0,
    "gn:timezone":"Asia/Dhaka",
    "iso:country":"BD",
    "name:und_x_variant":[
        "P\u0101nch Digal",
        "Pachh Dighalg\u0101n"
    ],
    "wof:name":"Panch Digal",
    "wof:placetype":"locality"
},
  "geometry": {"coordinates":[89.45565000000001,24.31291],"type":"Point"}
}