{
  "type": "Feature",
  "properties": {
    "gn:admin1_code":"82",
    "gn:admin2_code":"4065",
    "gn:admin3_code":"406552.0",
    "gn:admin4_code":"40655247.0",
    "gn:asciiname":"Sarsuna",
    "gn:country_code":"BD",
    "gn:dem":10,
    "gn:feature_class":"P",
    "gn:feature_code":"PPL",
    "gn:name":"Sarsuna",
    "gn:population":0,
    "gn:timezone":"Asia/Dhaka",
    "iso:country":"BD",
    "name:ben_x_preferred":[
        "\u09b8\u09b0\u09b6\u09c1\u09a8\u09be"
    ],
    "wof:name":"Sarsuna",
    "wof:placetype":"locality"
},
  "geometry": {"coordinates":[89.58699,23.25754],"type":"Point"}
}