{
  "type": "Feature",
  "properties": {
    "gn:admin1_code":"81",
    "gn:admin2_code":"3067",
    "gn:admin3_code":"306704.0",
    "gn:admin4_code":"30670417.0",
    "gn:asciiname":"Paschim Damodardi",
    "gn:country_code":"BD",
    "gn:dem":9,
    "gn:feature_class":"P",
    "gn:feature_code":"PPL",
    "gn:name":"Paschim D\u0101modardi",
    "gn:population":0,
    "gn:timezone":"Asia/Dhaka",
    "iso:country":"BD",
    "wof:name":"Paschim Damodardi",
    "wof:placetype":"locality"
},
  "geometry": {"coordinates":[90.63102000000001,23.68036],"type":"Point"}
}