{
  "type": "Feature",
  "properties": {
    "gn:admin1_code":"83",
    "gn:admin2_code":"5064.0",
    "gn:admin3_code":"506486.0",
    "gn:admin4_code":"50648679.0",
    "gn:asciiname":"Banikuri",
    "gn:country_code":"BD",
    "gn:dem":38,
    "gn:feature_class":"P",
    "gn:feature_code":"PPL",
    "gn:name":"B\u0101nikuri",
    "gn:population":0,
    "gn:timezone":"Asia/Dhaka",
    "iso:country":"BD",
    "name:ben_x_preferred":[
        "B\u0101nikuri"
    ],
    "wof:name":"Banikuri",
    "wof:placetype":"locality"
},
  "geometry": {"coordinates":[88.51804,25.13301],"type":"Point"}
}