{
  "type": "Feature",
  "properties": {
    "gn:admin1_code":"81",
    "gn:admin2_code":"3033.0",
    "gn:admin3_code":"303332.0",
    "gn:admin4_code":"30333285.0",
    "gn:asciiname":"Bhauman",
    "gn:country_code":"BD",
    "gn:dem":18,
    "gn:feature_class":"P",
    "gn:feature_code":"PPL",
    "gn:name":"Bh\u0101um\u0101n",
    "gn:population":0,
    "gn:timezone":"Asia/Dhaka",
    "iso:country":"BD",
    "wof:name":"Bhauman",
    "wof:placetype":"locality"
},
  "geometry": {"coordinates":[90.17264,24.06921],"type":"Point"}
}