{
  "type": "Feature",
  "properties": {
    "gn:admin1_code":"84",
    "gn:admin2_code":"2022.0",
    "gn:admin3_code":"202216.0",
    "gn:admin4_code":"20221667.0",
    "gn:asciiname":"Medakarchhapara",
    "gn:country_code":"BD",
    "gn:dem":13,
    "gn:feature_class":"P",
    "gn:feature_code":"PPL",
    "gn:name":"Med\u0101karchh\u0101p\u0101ra",
    "gn:population":0,
    "gn:timezone":"Asia/Dhaka",
    "iso:country":"BD",
    "name:ben_x_preferred":[
        "Med\u0101karchh\u0101p\u0101ra"
    ],
    "wof:name":"Medakarchhapara",
    "wof:placetype":"locality"
},
  "geometry": {"coordinates":[92.06483,21.63567],"type":"Point"}
}