{
  "type": "Feature",
  "properties": {
    "gn:admin1_code":"82",
    "gn:admin2_code":"4087",
    "gn:admin3_code":"408782.0",
    "gn:admin4_code":"40878200.0",
    "gn:asciiname":"Palaspol",
    "gn:country_code":"BD",
    "gn:dem":9,
    "gn:feature_class":"P",
    "gn:feature_code":"PPL",
    "gn:name":"Pal\u0101spol",
    "gn:population":0,
    "gn:timezone":"Asia/Dhaka",
    "iso:country":"BD",
    "wof:name":"Palaspol",
    "wof:placetype":"locality"
},
  "geometry": {"coordinates":[89.07052,22.71252],"type":"Point"}
}