{
  "type": "Feature",
  "properties": {
    "gn:admin1_code":"83",
    "gn:admin2_code":"5010",
    "gn:admin3_code":"501095.0",
    "gn:admin4_code":"50109510.0",
    "gn:asciiname":"Katagara",
    "gn:country_code":"BD",
    "gn:dem":24,
    "gn:feature_class":"P",
    "gn:feature_code":"PPL",
    "gn:name":"K\u0101t\u0101gara",
    "gn:population":0,
    "gn:timezone":"Asia/Dhaka",
    "iso:country":"BD",
    "name:ben_x_preferred":[
        "K\u0101t\u0101gara"
    ],
    "wof:name":"Katagara",
    "wof:placetype":"locality"
},
  "geometry": {"coordinates":[89.47246,25.00213],"type":"Point"}
}