{
  "type": "Feature",
  "properties": {
    "gn:admin1_code":"81",
    "gn:admin2_code":"3026",
    "gn:admin3_code":"302672.0",
    "gn:admin4_code":"30267200.0",
    "gn:asciiname":"Majidpur",
    "gn:country_code":"BD",
    "gn:dem":15,
    "gn:feature_class":"P",
    "gn:feature_code":"PPL",
    "gn:name":"Majidpur",
    "gn:population":0,
    "gn:timezone":"Asia/Dhaka",
    "iso:country":"BD",
    "wof:name":"Majidpur",
    "wof:placetype":"locality"
},
  "geometry": {"coordinates":[90.26248,23.84599],"type":"Point"}
}