{
  "type": "Feature",
  "properties": {
    "gn:admin1_code":"83",
    "gn:admin2_code":"5069.0",
    "gn:admin3_code":"506963.0",
    "gn:admin4_code":"50696314.0",
    "gn:asciiname":"Choudhuripara",
    "gn:country_code":"BD",
    "gn:dem":20,
    "gn:feature_class":"P",
    "gn:feature_code":"PPL",
    "gn:name":"Choudhurip\u0101ra",
    "gn:population":0,
    "gn:timezone":"Asia/Dhaka",
    "iso:country":"BD",
    "name:ben_x_preferred":[
        "Choudhurip\u0101ra"
    ],
    "wof:name":"Choudhuripara",
    "wof:placetype":"locality"
},
  "geometry": {"coordinates":[88.95649,24.45493],"type":"Point"}
}