{
  "type": "Feature",
  "properties": {
    "gn:admin1_code":"81",
    "gn:admin2_code":"3035",
    "gn:admin3_code":"303558.0",
    "gn:admin4_code":"30355889.0",
    "gn:asciiname":"Tengrakhola",
    "gn:country_code":"BD",
    "gn:dem":12,
    "gn:feature_class":"P",
    "gn:feature_code":"PPL",
    "gn:name":"Tengrakhola",
    "gn:population":0,
    "gn:timezone":"Asia/Dhaka",
    "iso:country":"BD",
    "name:und_x_variant":[
        "Tenrkhola",
        "Tengrakhola"
    ],
    "wof:name":"Tengrakhola",
    "wof:placetype":"locality"
},
  "geometry": {"coordinates":[89.87737,23.32179],"type":"Point"}
}