{
  "type": "Feature",
  "properties": {
    "gn:admin1_code":"82",
    "gn:admin2_code":"4041.0",
    "gn:admin3_code":"404190.0",
    "gn:admin4_code":"40419094.0",
    "gn:asciiname":"Ullasi",
    "gn:country_code":"BD",
    "gn:dem":13,
    "gn:feature_class":"P",
    "gn:feature_code":"PPL",
    "gn:name":"Ull\u0101si",
    "gn:population":0,
    "gn:timezone":"Asia/Dhaka",
    "iso:country":"BD",
    "name:ben_x_preferred":[
        "Ull\u0101si"
    ],
    "wof:name":"Ullasi",
    "wof:placetype":"locality"
},
  "geometry": {"coordinates":[88.99621999999999,23.02777],"type":"Point"}
}