{
  "type": "Feature",
  "properties": {
    "gn:admin1_code":"84",
    "gn:admin2_code":"2046.0",
    "gn:admin3_code":"204667.0",
    "gn:admin4_code":"20466763.0",
    "gn:asciiname":"Algapara",
    "gn:country_code":"BD",
    "gn:dem":63,
    "gn:feature_class":"P",
    "gn:feature_code":"PPL",
    "gn:name":"Alg\u0101p\u0101ra",
    "gn:population":0,
    "gn:timezone":"Asia/Dhaka",
    "iso:country":"BD",
    "name:ben_x_preferred":[
        "Alg\u0101p\u0101ra"
    ],
    "wof:name":"Algapara",
    "wof:placetype":"locality"
},
  "geometry": {"coordinates":[91.88326000000001,22.84156],"type":"Point"}
}