{
  "type": "Feature",
  "properties": {
    "gn:admin1_code":"85",
    "gn:admin2_code":"1006.0",
    "gn:admin3_code":"100602.0",
    "gn:admin4_code":"10060287.0",
    "gn:asciiname":"Chapachupa",
    "gn:country_code":"BD",
    "gn:dem":6,
    "gn:feature_class":"P",
    "gn:feature_code":"PPL",
    "gn:name":"Chap\u0101chupa",
    "gn:population":0,
    "gn:timezone":"Asia/Dhaka",
    "iso:country":"BD",
    "name:und_x_variant":[
        "Chap\u0101chupa"
    ],
    "wof:name":"Chapachupa",
    "wof:placetype":"locality"
},
  "geometry": {"coordinates":[90.17934,22.93449],"type":"Point"}
}