{
  "type": "Feature",
  "properties": {
    "gn:admin1_code":"81",
    "gn:admin2_code":"3048",
    "gn:admin3_code":"304854.0",
    "gn:admin4_code":"30485411.0",
    "gn:asciiname":"Samai Kandi",
    "gn:country_code":"BD",
    "gn:dem":11,
    "gn:feature_class":"P",
    "gn:feature_code":"PPL",
    "gn:name":"S\u0101m\u0101i K\u0101ndi",
    "gn:population":0,
    "gn:timezone":"Asia/Dhaka",
    "iso:country":"BD",
    "wof:name":"Samai Kandi",
    "wof:placetype":"locality"
},
  "geometry": {"coordinates":[90.90985000000001,24.13021],"type":"Point"}
}