{
  "type": "Feature",
  "properties": {
    "gn:admin1_code":"83",
    "gn:admin2_code":"5069",
    "gn:admin3_code":"506963.0",
    "gn:admin4_code":"50696394.0",
    "gn:asciiname":"Purbapara",
    "gn:country_code":"BD",
    "gn:dem":15,
    "gn:feature_class":"P",
    "gn:feature_code":"PPL",
    "gn:name":"Purbap\u0101ra",
    "gn:population":0,
    "gn:timezone":"Asia/Dhaka",
    "iso:country":"BD",
    "wof:name":"Purbapara",
    "wof:placetype":"locality"
},
  "geometry": {"coordinates":[88.95,24.38333],"type":"Point"}
}