{
  "type": "Feature",
  "properties": {
    "gn:admin1_code":"82",
    "gn:admin2_code":"4050.0",
    "gn:admin3_code":"405071.0",
    "gn:admin4_code":"40507134.0",
    "gn:asciiname":"Itmampur",
    "gn:country_code":"BD",
    "gn:dem":17,
    "gn:feature_class":"P",
    "gn:feature_code":"PPL",
    "gn:name":"Itmampur",
    "gn:population":0,
    "gn:timezone":"Asia/Dhaka",
    "iso:country":"BD",
    "name:ben_x_preferred":[
        "Itmampur"
    ],
    "name:ben_x_variant":[
        "Etm\u0101mpur"
    ],
    "wof:name":"Itmampur",
    "wof:placetype":"locality"
},
  "geometry": {"coordinates":[89.23328000000002,23.83133],"type":"Point"}
}