{
  "type": "Feature",
  "properties": {
    "gn:admin1_code":"81",
    "gn:admin2_code":"3056.0",
    "gn:admin3_code":"305670.0",
    "gn:admin4_code":"30567095.0",
    "gn:asciiname":"Akasi",
    "gn:country_code":"BD",
    "gn:dem":17,
    "gn:feature_class":"P",
    "gn:feature_code":"PPL",
    "gn:name":"\u0100k\u0101si",
    "gn:population":0,
    "gn:timezone":"Asia/Dhaka",
    "iso:country":"BD",
    "wof:name":"Akasi",
    "wof:placetype":"locality"
},
  "geometry": {"coordinates":[89.95021,23.95163],"type":"Point"}
}