{
  "type": "Feature",
  "properties": {
    "gn:admin1_code":"82",
    "gn:admin2_code":"4065.0",
    "gn:admin3_code":"406552.0",
    "gn:admin4_code":"40655231.0",
    "gn:asciiname":"Basupati",
    "gn:country_code":"BD",
    "gn:dem":11,
    "gn:feature_class":"P",
    "gn:feature_code":"PPL",
    "gn:name":"Basupati",
    "gn:population":0,
    "gn:timezone":"Asia/Dhaka",
    "iso:country":"BD",
    "name:ben_x_preferred":[
        "Basupati"
    ],
    "wof:name":"Basupati",
    "wof:placetype":"locality"
},
  "geometry": {"coordinates":[89.60175,23.18779],"type":"Point"}
}