{
  "type": "Feature",
  "properties": {
    "gn:admin1_code":"87",
    "gn:admin2_code":"5549",
    "gn:admin3_code":"554961.0",
    "gn:admin4_code":"55496194.0",
    "gn:asciiname":"Naodanga Kuthi",
    "gn:country_code":"BD",
    "gn:dem":32,
    "gn:feature_class":"P",
    "gn:feature_code":"PPL",
    "gn:name":"Naodanga Kuthi",
    "gn:population":0,
    "gn:timezone":"Asia/Dhaka",
    "iso:country":"BD",
    "name:ben_x_preferred":[
        "Naodanga Kuthi"
    ],
    "wof:name":"Naodanga Kuthi",
    "wof:placetype":"locality"
},
  "geometry": {"coordinates":[89.65283000000002,26.01329],"type":"Point"}
}