{
  "type": "Feature",
  "properties": {
    "gn:admin1_code":"H",
    "gn:admin2_code":"3061",
    "gn:admin3_code":"306172.0",
    "gn:admin4_code":"30617215.0",
    "gn:asciiname":"Kharia",
    "gn:country_code":"BD",
    "gn:dem":16,
    "gn:feature_class":"P",
    "gn:feature_code":"PPL",
    "gn:name":"Kharia",
    "gn:population":0,
    "gn:timezone":"Asia/Dhaka",
    "iso:country":"BD",
    "name:cat_x_preferred":[
        "Kharia"
    ],
    "name:deu_x_preferred":[
        "Kharia"
    ],
    "wof:name":"Kharia",
    "wof:placetype":"locality"
},
  "geometry": {"coordinates":[90.56892000000001,24.53085],"type":"Point"}
}