{
  "type": "Feature",
  "properties": {
    "gn:admin1_code":"84",
    "gn:admin2_code":"2019.0",
    "gn:admin3_code":"201927.0",
    "gn:admin4_code":"20192723.0",
    "gn:asciiname":"Bhuari",
    "gn:country_code":"BD",
    "gn:dem":12,
    "gn:feature_class":"P",
    "gn:feature_code":"PPL",
    "gn:name":"Bhu\u0101ri",
    "gn:population":0,
    "gn:timezone":"Asia/Dhaka",
    "iso:country":"BD",
    "wof:name":"Bhuari",
    "wof:placetype":"locality"
},
  "geometry": {"coordinates":[90.95681,23.38269],"type":"Point"}
}