{
  "type": "Feature",
  "properties": {
    "gn:admin1_code":"83",
    "gn:admin2_code":"5070.0",
    "gn:admin3_code":"507066.0",
    "gn:admin4_code":"50706616.0",
    "gn:asciiname":"Char Kasimpur",
    "gn:country_code":"BD",
    "gn:dem":24,
    "gn:feature_class":"P",
    "gn:feature_code":"PPL",
    "gn:name":"Char K\u0101simpur",
    "gn:population":0,
    "gn:timezone":"Asia/Dhaka",
    "iso:country":"BD",
    "name:ben_x_preferred":[
        "Char K\u0101simpur"
    ],
    "name:und_x_variant":[
        "Char Kashimpur"
    ],
    "wof:name":"Char Kasimpur",
    "wof:placetype":"locality"
},
  "geometry": {"coordinates":[88.30551,24.53967],"type":"Point"}
}