{
  "type": "Feature",
  "properties": {
    "gn:admin1_code":"81",
    "gn:admin2_code":"3067.0",
    "gn:admin3_code":"306704.0",
    "gn:admin4_code":"30670469.0",
    "gn:asciiname":"Diara Menikhali",
    "gn:country_code":"BD",
    "gn:dem":9,
    "gn:feature_class":"P",
    "gn:feature_code":"PPL",
    "gn:name":"Di\u0101ra Menikh\u0101li",
    "gn:population":0,
    "gn:timezone":"Asia/Dhaka",
    "iso:country":"BD",
    "wof:name":"Diara Menikhali",
    "wof:placetype":"locality"
},
  "geometry": {"coordinates":[90.61667,23.63333],"type":"Point"}
}