{
  "type": "Feature",
  "properties": {
    "gn:admin1_code":"87",
    "gn:admin2_code":"5527.0",
    "gn:admin3_code":"552764.0",
    "gn:admin4_code":"55276460.0",
    "gn:asciiname":"Chak Parbatipur",
    "gn:country_code":"BD",
    "gn:dem":35,
    "gn:feature_class":"P",
    "gn:feature_code":"PPL",
    "gn:name":"Chak P\u0101rbatipur",
    "gn:population":0,
    "gn:timezone":"Asia/Dhaka",
    "iso:country":"BD",
    "name:ben_x_preferred":[
        "Chak P\u0101rbatipur"
    ],
    "wof:name":"Chak Parbatipur",
    "wof:placetype":"locality"
},
  "geometry": {"coordinates":[88.74343,25.558],"type":"Point"}
}