{
  "type": "Feature",
  "properties": {
    "gn:admin1_code":"84",
    "gn:admin2_code":"2046.0",
    "gn:admin3_code":"204661.0",
    "gn:admin4_code":"20466147.0",
    "gn:asciiname":"Majarapara",
    "gn:country_code":"BD",
    "gn:dem":45,
    "gn:feature_class":"P",
    "gn:feature_code":"PPL",
    "gn:name":"M\u0101jar\u0101p\u0101ra",
    "gn:population":0,
    "gn:timezone":"Asia/Dhaka",
    "iso:country":"BD",
    "name:ben_x_preferred":[
        "M\u0101jar\u0101p\u0101ra"
    ],
    "wof:name":"Majarapara",
    "wof:placetype":"locality"
},
  "geometry": {"coordinates":[91.90608,22.84659],"type":"Point"}
}