{
  "type": "Feature",
  "properties": {
    "gn:admin1_code":"83",
    "gn:admin2_code":"5038",
    "gn:admin3_code":"503858.0",
    "gn:admin4_code":"50385885.0",
    "gn:asciiname":"Mandai",
    "gn:country_code":"BD",
    "gn:dem":26,
    "gn:feature_class":"P",
    "gn:feature_code":"PPL",
    "gn:name":"M\u0101nd\u0101i",
    "gn:population":0,
    "gn:timezone":"Asia/Dhaka",
    "iso:country":"BD",
    "wof:name":"Mandai",
    "wof:placetype":"locality"
},
  "geometry": {"coordinates":[89.2268,25.10558],"type":"Point"}
}