{
  "type": "Feature",
  "properties": {
    "gn:admin1_code":"82",
    "gn:admin2_code":"4041.0",
    "gn:admin3_code":"404109.0",
    "gn:admin4_code":"40410976.0",
    "gn:asciiname":"Punihar",
    "gn:country_code":"BD",
    "gn:dem":12,
    "gn:feature_class":"P",
    "gn:feature_code":"PPL",
    "gn:name":"Punihar",
    "gn:population":0,
    "gn:timezone":"Asia/Dhaka",
    "iso:country":"BD",
    "name:ben_x_preferred":[
        "Punihar"
    ],
    "wof:name":"Punihar",
    "wof:placetype":"locality"
},
  "geometry": {"coordinates":[89.35093000000001,23.26371],"type":"Point"}
}