{
  "type": "Feature",
  "properties": {
    "gn:admin1_code":"87",
    "gn:admin2_code":"5552",
    "gn:admin3_code":"555202.0",
    "gn:admin4_code":"55520289.0",
    "gn:asciiname":"Balapara",
    "gn:country_code":"BD",
    "gn:dem":37,
    "gn:feature_class":"P",
    "gn:feature_code":"PPL",
    "gn:name":"Balapara",
    "gn:population":0,
    "gn:timezone":"Asia/Dhaka",
    "iso:country":"BD",
    "name:ben_x_preferred":[
        "Balapara"
    ],
    "wof:name":"Balapara",
    "wof:placetype":"locality"
},
  "geometry": {"coordinates":[89.38528000000002,25.89562],"type":"Point"}
}