{
  "type": "Feature",
  "properties": {
    "gn:admin1_code":"84",
    "gn:admin2_code":"2019.0",
    "gn:admin3_code":"201940.0",
    "gn:admin4_code":"20194041.0",
    "gn:asciiname":"Bakrikandi",
    "gn:country_code":"BD",
    "gn:dem":10,
    "gn:feature_class":"P",
    "gn:feature_code":"PPL",
    "gn:name":"Bakrik\u0101ndi",
    "gn:population":0,
    "gn:timezone":"Asia/Dhaka",
    "iso:country":"BD",
    "wof:name":"Bakrikandi",
    "wof:placetype":"locality"
},
  "geometry": {"coordinates":[90.97022,23.51528],"type":"Point"}
}