{
  "type": "Feature",
  "properties": {
    "gn:admin1_code":"81",
    "gn:admin2_code":"3056.0",
    "gn:admin3_code":"305678.0",
    "gn:admin4_code":"30567847.0",
    "gn:asciiname":"Boalipara",
    "gn:country_code":"BD",
    "gn:dem":10,
    "gn:feature_class":"P",
    "gn:feature_code":"PPL",
    "gn:name":"Bo\u0101lip\u0101ra",
    "gn:population":0,
    "gn:timezone":"Asia/Dhaka",
    "iso:country":"BD",
    "wof:name":"Boalipara",
    "wof:placetype":"locality"
},
  "geometry": {"coordinates":[89.79351,23.83372],"type":"Point"}
}