{
  "type": "Feature",
  "properties": {
    "gn:admin1_code":"83",
    "gn:admin2_code":"5038.0",
    "gn:admin3_code":"503847.0",
    "gn:admin4_code":"50384766.0",
    "gn:asciiname":"Uri",
    "gn:country_code":"BD",
    "gn:dem":25,
    "gn:feature_class":"P",
    "gn:feature_code":"PPL",
    "gn:name":"Uri",
    "gn:population":0,
    "gn:timezone":"Asia/Dhaka",
    "iso:country":"BD",
    "name:ceb_x_preferred":[
        "Uri"
    ],
    "name:chv_x_preferred":[
        "\u0423\u0440\u0438"
    ],
    "name:dan_x_preferred":[
        "Uri"
    ],
    "name:deu_x_preferred":[
        "Uri"
    ],
    "name:epo_x_preferred":[
        "URI"
    ],
    "name:fra_x_preferred":[
        "Uri"
    ],
    "name:heb_x_preferred":[
        "\u05d0\u05d5\u05e8\u05d9"
    ],
    "name:hrv_x_preferred":[
        "Uri"
    ],
    "name:hye_x_preferred":[
        "\u0548\u0582\u057c\u056b"
    ],
    "name:jpn_x_preferred":[
        "\u30a6\u30ea"
    ],
    "name:ltz_x_preferred":[
        "Uri"
    ],
    "name:msa_x_preferred":[
        "Uri"
    ],
    "name:nld_x_preferred":[
        "Uri"
    ],
    "name:pol_x_preferred":[
        "Uri"
    ],
    "name:por_x_preferred":[
        "Uri"
    ],
    "name:rus_x_preferred":[
        "\u0423\u0440\u0438"
    ],
    "name:spa_x_preferred":[
        "Uri"
    ],
    "name:srp_x_preferred":[
        "\u0423\u0440\u0438"
    ],
    "name:swe_x_preferred":[
        "Uri"
    ],
    "name:ukr_x_preferred":[
        "\u0423\u0440\u0456"
    ],
    "name:vie_x_preferred":[
        "Uri"
    ],
    "wof:name":"Uri",
    "wof:placetype":"locality"
},
  "geometry": {"coordinates":[89.03008,25.05276],"type":"Point"}
}