{
  "type": "Feature",
  "properties": {
    "gn:admin1_code":"84",
    "gn:admin2_code":"2046.0",
    "gn:admin3_code":"204661.0",
    "gn:admin4_code":"20466123.0",
    "gn:asciiname":"Baiddapara",
    "gn:country_code":"BD",
    "gn:dem":36,
    "gn:feature_class":"P",
    "gn:feature_code":"PPL",
    "gn:name":"Baiddap\u0101ra",
    "gn:population":0,
    "gn:timezone":"Asia/Dhaka",
    "iso:country":"BD",
    "name:ben_x_preferred":[
        "Baiddap\u0101ra"
    ],
    "wof:name":"Baiddapara",
    "wof:placetype":"locality"
},
  "geometry": {"coordinates":[91.93481,22.70482],"type":"Point"}
}