{
  "type": "Feature",
  "properties": {
    "gn:admin1_code":"85",
    "gn:admin2_code":"1009.0",
    "gn:admin3_code":"100954.0",
    "gn:admin4_code":"10095419.0",
    "gn:asciiname":"Uttar Char Bhuta",
    "gn:country_code":"BD",
    "gn:dem":9,
    "gn:feature_class":"P",
    "gn:feature_code":"PPL",
    "gn:name":"Uttar Char Bhuta",
    "gn:population":0,
    "gn:timezone":"Asia/Dhaka",
    "iso:country":"BD",
    "name:ben_x_preferred":[
        "Uttar Char Bhuta"
    ],
    "wof:name":"Uttar Char Bhuta",
    "wof:placetype":"locality"
},
  "geometry": {"coordinates":[90.76508,22.34356],"type":"Point"}
}