{
  "type": "Feature",
  "properties": {
    "gn:admin1_code":"81",
    "gn:admin2_code":"3033",
    "gn:admin3_code":"303334.0",
    "gn:admin4_code":"30333469.0",
    "gn:asciiname":"Sarusuachhla",
    "gn:country_code":"BD",
    "gn:dem":14,
    "gn:feature_class":"P",
    "gn:feature_code":"PPL",
    "gn:name":"Sarusu\u0101chhla",
    "gn:population":0,
    "gn:timezone":"Asia/Dhaka",
    "iso:country":"BD",
    "wof:name":"Sarusuachhla",
    "wof:placetype":"locality"
},
  "geometry": {"coordinates":[90.5256,24.02695],"type":"Point"}
}