{
  "type": "Feature",
  "properties": {
    "gn:admin1_code":"82",
    "gn:asciiname":"Kachhablar Don",
    "gn:country_code":"BD",
    "gn:dem":4,
    "gn:feature_class":"P",
    "gn:feature_code":"PPL",
    "gn:name":"Kachhabl\u0101r Don",
    "gn:population":0,
    "gn:timezone":"Asia/Dhaka",
    "iso:country":"BD",
    "name:ben_x_preferred":[
        "Kachhabl\u0101r Don"
    ],
    "wof:name":"Kachhablar Don",
    "wof:placetype":"locality"
},
  "geometry": {"coordinates":[90.66677,22.01421],"type":"Point"}
}