{
  "type": "Feature",
  "properties": {
    "gn:admin1_code":"84",
    "gn:admin2_code":"2015.0",
    "gn:admin3_code":"201570.0",
    "gn:admin4_code":"20157008.0",
    "gn:asciiname":"Din Chawdia",
    "gn:country_code":"BD",
    "gn:dem":16,
    "gn:feature_class":"P",
    "gn:feature_code":"PPL",
    "gn:name":"Din Chawdia",
    "gn:population":0,
    "gn:timezone":"Asia/Dhaka",
    "iso:country":"BD",
    "name:ben_x_preferred":[
        "Din Chawdia"
    ],
    "wof:name":"Din Chawdia",
    "wof:placetype":"locality"
},
  "geometry": {"coordinates":[92.00266000000001,22.43151],"type":"Point"}
}