{
  "type": "Feature",
  "properties": {
    "gn:admin1_code":"81",
    "gn:admin2_code":"3048.0",
    "gn:admin3_code":"304827.0",
    "gn:admin4_code":"30482781.0",
    "gn:asciiname":"Bil Bagmara",
    "gn:country_code":"BD",
    "gn:dem":14,
    "gn:feature_class":"P",
    "gn:feature_code":"PPL",
    "gn:name":"Bil B\u0101gm\u0101r\u0101",
    "gn:population":0,
    "gn:timezone":"Asia/Dhaka",
    "iso:country":"BD",
    "name:und_x_variant":[
        "Bilpagmara",
        "Bil B\u0101gm\u0101r\u0101"
    ],
    "wof:name":"Bil Bagmara",
    "wof:placetype":"locality"
},
  "geometry": {"coordinates":[90.6174,24.48418],"type":"Point"}
}