{
  "type": "Feature",
  "properties": {
    "gn:admin1_code":"82",
    "gn:asciiname":"Oasher Hat",
    "gn:country_code":"BD",
    "gn:dem":5,
    "gn:feature_class":"P",
    "gn:feature_code":"PPL",
    "gn:name":"O\u0101sher H\u0101t",
    "gn:population":0,
    "gn:timezone":"Asia/Dhaka",
    "iso:country":"BD",
    "name:ben_x_preferred":[
        "O\u0101sher H\u0101t"
    ],
    "wof:name":"Oasher Hat",
    "wof:placetype":"locality"
},
  "geometry": {"coordinates":[90.95674,22.24089],"type":"Point"}
}