{
  "type": "Feature",
  "properties": {
    "gn:admin1_code":"87",
    "gn:admin2_code":"5594.0",
    "gn:admin3_code":"559494.0",
    "gn:admin4_code":"55949473.0",
    "gn:asciiname":"Chhota Bhengroal",
    "gn:country_code":"BD",
    "gn:dem":59,
    "gn:feature_class":"P",
    "gn:feature_code":"PPL",
    "gn:name":"Chhota Bhengro\u0101l",
    "gn:population":0,
    "gn:timezone":"Asia/Dhaka",
    "iso:country":"BD",
    "name:ben_x_preferred":[
        "Chhota Bhengro\u0101l"
    ],
    "wof:name":"Chhota Bhengroal",
    "wof:placetype":"locality"
},
  "geometry": {"coordinates":[88.33788,26.0379],"type":"Point"}
}