{
  "type": "Feature",
  "properties": {
    "gn:admin1_code":"84",
    "gn:admin2_code":"2015.0",
    "gn:admin3_code":"201533.0",
    "gn:admin4_code":"20153361.0",
    "gn:asciiname":"Purba Andharmanik",
    "gn:country_code":"BD",
    "gn:dem":19,
    "gn:feature_class":"P",
    "gn:feature_code":"PPL",
    "gn:name":"Purba Andh\u0101rmanik",
    "gn:population":0,
    "gn:timezone":"Asia/Dhaka",
    "iso:country":"BD",
    "name:ben_x_preferred":[
        "Purba Andh\u0101rmanik"
    ],
    "wof:name":"Purba Andharmanik",
    "wof:placetype":"locality"
},
  "geometry": {"coordinates":[91.89346,22.62798],"type":"Point"}
}