{
  "type": "Feature",
  "properties": {
    "gn:admin1_code":"85",
    "gn:admin2_code":"1078.0",
    "gn:admin3_code":"107895.0",
    "gn:admin4_code":"10789513.0",
    "gn:asciiname":"Kumarkhali",
    "gn:country_code":"BD",
    "gn:dem":9,
    "gn:feature_class":"P",
    "gn:feature_code":"PPL",
    "gn:name":"Kum\u0101rkh\u0101li",
    "gn:population":0,
    "gn:timezone":"Asia/Dhaka",
    "iso:country":"BD",
    "name:ben_x_preferred":[
        "Kum\u0101rkh\u0101li"
    ],
    "wof:name":"Kumarkhali",
    "wof:placetype":"locality"
},
  "geometry": {"coordinates":[90.22776,22.32096],"type":"Point"}
}