{
  "type": "Feature",
  "properties": {
    "gn:admin1_code":"H",
    "gn:admin2_code":"3072",
    "gn:admin3_code":"307263.0",
    "gn:admin4_code":"30726363.0",
    "gn:asciiname":"Loneswar",
    "gn:country_code":"BD",
    "gn:dem":12,
    "gn:feature_class":"P",
    "gn:feature_code":"PPL",
    "gn:name":"Loneswar",
    "gn:population":0,
    "gn:timezone":"Asia/Dhaka",
    "iso:country":"BD",
    "wof:name":"Loneswar",
    "wof:placetype":"locality"
},
  "geometry": {"coordinates":[90.92189,24.78189],"type":"Point"}
}