{
  "type": "Feature",
  "properties": {
    "gn:admin1_code":"82",
    "gn:admin2_code":"4047.0",
    "gn:admin3_code":"404740.0",
    "gn:admin4_code":"40474066.0",
    "gn:asciiname":"Gazirhat",
    "gn:country_code":"BD",
    "gn:dem":7,
    "gn:feature_class":"P",
    "gn:feature_code":"PPL",
    "gn:name":"G\u0101zirh\u0101t",
    "gn:population":0,
    "gn:timezone":"Asia/Dhaka",
    "iso:country":"BD",
    "name:ben_x_preferred":[
        "G\u0101zirh\u0101t"
    ],
    "name:ben_x_variant":[
        "G\u0101zikh\u0101l"
    ],
    "wof:name":"Gazirhat",
    "wof:placetype":"locality"
},
  "geometry": {"coordinates":[89.56961,22.98991],"type":"Point"}
}