{
  "type": "Feature",
  "properties": {
    "gn:admin1_code":"82",
    "gn:asciiname":"Telimudafat",
    "gn:country_code":"BD",
    "gn:dem":8,
    "gn:feature_class":"P",
    "gn:feature_code":"PPL",
    "gn:name":"Telimud\u0101fat",
    "gn:population":0,
    "gn:timezone":"Asia/Dhaka",
    "iso:country":"BD",
    "name:ben_x_preferred":[
        "Telimud\u0101fat"
    ],
    "wof:name":"Telimudafat",
    "wof:placetype":"locality"
},
  "geometry": {"coordinates":[90.34314999999999,22.20088],"type":"Point"}
}