{
  "type": "Feature",
  "properties": {
    "gn:admin1_code":"81",
    "gn:admin2_code":"3026",
    "gn:admin3_code":"302640.0",
    "gn:admin4_code":"30264005.0",
    "gn:asciiname":"Sekerkalsi",
    "gn:country_code":"BD",
    "gn:dem":15,
    "gn:feature_class":"P",
    "gn:feature_code":"PPL",
    "gn:name":"Sekerkalsi",
    "gn:population":0,
    "gn:timezone":"Asia/Dhaka",
    "iso:country":"BD",
    "wof:name":"Sekerkalsi",
    "wof:placetype":"locality"
},
  "geometry": {"coordinates":[90.37350000000001,23.82108],"type":"Point"}
}