{
  "type": "Feature",
  "properties": {
    "gn:admin1_code":"81",
    "gn:admin2_code":"3056",
    "gn:admin3_code":"305610.0",
    "gn:admin4_code":"30561066.0",
    "gn:asciiname":"Jointa",
    "gn:country_code":"BD",
    "gn:dem":13,
    "gn:feature_class":"P",
    "gn:feature_code":"PPL",
    "gn:name":"Jointa",
    "gn:population":0,
    "gn:timezone":"Asia/Dhaka",
    "iso:country":"BD",
    "name:und_x_variant":[
        "Jainda"
    ],
    "wof:name":"Jointa",
    "wof:placetype":"locality"
},
  "geometry": {"coordinates":[89.80596,23.96885],"type":"Point"}
}