{
  "type": "Feature",
  "properties": {
    "gn:admin1_code":"87",
    "gn:admin2_code":"5585",
    "gn:admin3_code":"558592.0",
    "gn:admin4_code":"55859271.0",
    "gn:asciiname":"Ganirampur",
    "gn:country_code":"BD",
    "gn:dem":43,
    "gn:feature_class":"P",
    "gn:feature_code":"PPL",
    "gn:name":"Ganirampur",
    "gn:population":0,
    "gn:timezone":"Asia/Dhaka",
    "iso:country":"BD",
    "name:ben_x_preferred":[
        "Ganirampur"
    ],
    "wof:name":"Ganirampur",
    "wof:placetype":"locality"
},
  "geometry": {"coordinates":[89.03246999999998,25.81249],"type":"Point"}
}