{
  "type": "Feature",
  "properties": {
    "gn:admin1_code":"82",
    "gn:admin2_code":"4065.0",
    "gn:admin3_code":"406552.0",
    "gn:admin4_code":"40655294.0",
    "gn:asciiname":"Chaksi",
    "gn:country_code":"BD",
    "gn:dem":12,
    "gn:feature_class":"P",
    "gn:feature_code":"PPL",
    "gn:name":"Ch\u0101ksi",
    "gn:population":0,
    "gn:timezone":"Asia/Dhaka",
    "iso:country":"BD",
    "wof:name":"Chaksi",
    "wof:placetype":"locality"
},
  "geometry": {"coordinates":[89.65423,23.28641],"type":"Point"}
}