{
  "type": "Feature",
  "properties": {
    "gn:admin1_code":"87",
    "gn:admin2_code":"5532",
    "gn:admin3_code":"553267.0",
    "gn:admin4_code":"55326757.0",
    "gn:asciiname":"Parbatipur",
    "gn:country_code":"BD",
    "gn:dem":28,
    "gn:feature_class":"P",
    "gn:feature_code":"PPL",
    "gn:name":"Parbatipur",
    "gn:population":0,
    "gn:timezone":"Asia/Dhaka",
    "iso:country":"BD",
    "name:ben_x_preferred":[
        "Parbatipur"
    ],
    "name:ceb_x_preferred":[
        "Parbatipur"
    ],
    "name:swe_x_preferred":[
        "Parbatipur"
    ],
    "wof:name":"Parbatipur",
    "wof:placetype":"locality"
},
  "geometry": {"coordinates":[89.40481,25.2818],"type":"Point"}
}