{
  "type": "Feature",
  "properties": {
    "iso:country":"BD",
    "name:ben_x_preferred":[
        "Rahmatpur"
    ],
    "qs:gn_country":"BD",
    "qs:gn_fcode":"PPL",
    "qs:gn_pop":0,
    "qs:name":"Azmatpur",
    "qs:name_adm0":"India",
    "qs:name_adm1":"Bihar",
    "qs:photos":6,
    "qs:photos_1k":1,
    "qs:photos_9k":1,
    "qs:photos_9r":1,
    "qs:photos_all":6,
    "qs:photos_sr":1,
    "qs:placetype":"Town",
    "qs:pop_sr":"0",
    "qs:woe_adm0":23424848,
    "wof:name":"Azmatpur",
    "wof:placetype":"locality"
},
  "geometry": {"coordinates":[88.12609999999999,25.8498],"type":"Point"}
}