{
  "type": "Feature",
  "properties": {
    "gn:admin1_code":"85",
    "gn:admin2_code":"1006",
    "gn:admin3_code":"100694.0",
    "gn:admin4_code":"10069421.0",
    "gn:asciiname":"Narikel",
    "gn:country_code":"BD",
    "gn:dem":11,
    "gn:feature_class":"P",
    "gn:feature_code":"PPL",
    "gn:name":"N\u0101rikel",
    "gn:population":0,
    "gn:timezone":"Asia/Dhaka",
    "iso:country":"BD",
    "name:und_x_variant":[
        "N\u0101rikel",
        "N\u0101rikeli"
    ],
    "wof:name":"Narikel",
    "wof:placetype":"locality"
},
  "geometry": {"coordinates":[90.21156000000001,22.83847],"type":"Point"}
}