{
  "type": "Feature",
  "properties": {
    "gn:admin1_code":"84",
    "gn:admin2_code":"2015.0",
    "gn:admin3_code":"201582.0",
    "gn:admin4_code":"20158287.0",
    "gn:asciiname":"Karianagar",
    "gn:country_code":"BD",
    "gn:dem":11,
    "gn:feature_class":"P",
    "gn:feature_code":"PPL",
    "gn:name":"Kari\u0101nagar",
    "gn:population":0,
    "gn:timezone":"Asia/Dhaka",
    "iso:country":"BD",
    "name:ben_x_preferred":[
        "Kari\u0101nagar"
    ],
    "wof:name":"Karianagar",
    "wof:placetype":"locality"
},
  "geometry": {"coordinates":[92.09703,22.06498],"type":"Point"}
}