{
  "type": "Feature",
  "properties": {
    "gn:admin1_code":"81",
    "gn:admin2_code":"3056",
    "gn:admin3_code":"305670.0",
    "gn:admin4_code":"30567085.0",
    "gn:asciiname":"Kaijuri",
    "gn:country_code":"BD",
    "gn:dem":15,
    "gn:feature_class":"P",
    "gn:feature_code":"PPL",
    "gn:name":"Kaijuri",
    "gn:population":0,
    "gn:timezone":"Asia/Dhaka",
    "iso:country":"BD",
    "wof:name":"Kaijuri",
    "wof:placetype":"locality"
},
  "geometry": {"coordinates":[90.04680999999999,23.94835],"type":"Point"}
}