{
  "type": "Feature",
  "properties": {
    "gn:admin1_code":"87",
    "gn:admin2_code":"5527.0",
    "gn:admin3_code":"552712.0",
    "gn:admin4_code":"55271234.0",
    "gn:asciiname":"Matiakura",
    "gn:country_code":"BD",
    "gn:dem":52,
    "gn:feature_class":"P",
    "gn:feature_code":"PPL",
    "gn:name":"M\u0101ti\u0101kura",
    "gn:population":0,
    "gn:timezone":"Asia/Dhaka",
    "iso:country":"BD",
    "name:ben_x_preferred":[
        "M\u0101ti\u0101kura"
    ],
    "wof:name":"Matiakura",
    "wof:placetype":"locality"
},
  "geometry": {"coordinates":[88.68819000000001,25.94709],"type":"Point"}
}