{
  "type": "Feature",
  "properties": {
    "gn:admin1_code":"83",
    "gn:asciiname":"Par Sonaidanga",
    "gn:country_code":"BD",
    "gn:dem":22,
    "gn:feature_class":"P",
    "gn:feature_code":"PPL",
    "gn:name":"P\u0101r Son\u0101id\u0101nga",
    "gn:population":0,
    "gn:timezone":"Asia/Dhaka",
    "iso:country":"BD",
    "name:ben_x_preferred":[
        "P\u0101r Son\u0101id\u0101nga"
    ],
    "wof:name":"Par Sonaidanga",
    "wof:placetype":"locality"
},
  "geometry": {"coordinates":[89.48455,25.14553],"type":"Point"}
}