{
  "type": "Feature",
  "properties": {
    "gn:admin1_code":"H",
    "gn:admin2_code":"3089",
    "gn:admin3_code":"308967.0",
    "gn:admin4_code":"30896738.0",
    "gn:asciiname":"Medirpar",
    "gn:country_code":"BD",
    "gn:dem":19,
    "gn:feature_class":"P",
    "gn:feature_code":"PPL",
    "gn:name":"Medirpar",
    "gn:population":0,
    "gn:timezone":"Asia/Dhaka",
    "iso:country":"BD",
    "name:ben_x_preferred":[
        "Medirpar"
    ],
    "wof:name":"Medirpar",
    "wof:placetype":"locality"
},
  "geometry": {"coordinates":[90.13724999999999,25.01311],"type":"Point"}
}