{
  "type": "Feature",
  "properties": {
    "gn:admin1_code":"81",
    "gn:admin2_code":"3033",
    "gn:admin3_code":"303336.0",
    "gn:admin4_code":"30333694.0",
    "gn:asciiname":"Nayan Bazar",
    "gn:country_code":"BD",
    "gn:dem":16,
    "gn:feature_class":"P",
    "gn:feature_code":"PPL",
    "gn:name":"Nay\u0101n B\u0101z\u0101r",
    "gn:population":0,
    "gn:timezone":"Asia/Dhaka",
    "iso:country":"BD",
    "wof:name":"Nayan Bazar",
    "wof:placetype":"locality"
},
  "geometry": {"coordinates":[90.63364,24.26083],"type":"Point"}
}