{
  "type": "Feature",
  "properties": {
    "gn:admin1_code":"81",
    "gn:admin2_code":"3048.0",
    "gn:admin3_code":"304892.0",
    "gn:admin4_code":"30489281.0",
    "gn:asciiname":"Bansati",
    "gn:country_code":"BD",
    "gn:dem":13,
    "gn:feature_class":"P",
    "gn:feature_code":"PPL",
    "gn:name":"B\u0101ns\u0101ti",
    "gn:population":0,
    "gn:timezone":"Asia/Dhaka",
    "iso:country":"BD",
    "wof:name":"Bansati",
    "wof:placetype":"locality"
},
  "geometry": {"coordinates":[90.83789,24.52158],"type":"Point"}
}