{
  "type": "Feature",
  "properties": {
    "gn:admin1_code":"83",
    "gn:admin2_code":"5076.0",
    "gn:admin3_code":"507655.0",
    "gn:admin4_code":"50765508.0",
    "gn:asciiname":"Ataikula",
    "gn:country_code":"BD",
    "gn:dem":19,
    "gn:feature_class":"P",
    "gn:feature_code":"PPL",
    "gn:name":"\u0100t\u0101ikula",
    "gn:population":0,
    "gn:timezone":"Asia/Dhaka",
    "iso:country":"BD",
    "wof:name":"Ataikula",
    "wof:placetype":"locality"
},
  "geometry": {"coordinates":[89.40781,24.03242],"type":"Point"}
}