{
  "type": "Feature",
  "properties": {
    "gn:admin1_code":"81",
    "gn:admin2_code":"3056",
    "gn:admin3_code":"305610.0",
    "gn:admin4_code":"30561076.0",
    "gn:asciiname":"Silimpur",
    "gn:country_code":"BD",
    "gn:dem":9,
    "gn:feature_class":"P",
    "gn:feature_code":"PPL",
    "gn:name":"Silimpur",
    "gn:population":0,
    "gn:timezone":"Asia/Dhaka",
    "iso:country":"BD",
    "wof:name":"Silimpur",
    "wof:placetype":"locality"
},
  "geometry": {"coordinates":[89.89796,23.9685],"type":"Point"}
}