{
  "type": "Feature",
  "properties": {
    "gn:admin1_code":"83",
    "gn:admin2_code":"5081.0",
    "gn:admin3_code":"508134.0",
    "gn:admin4_code":"50813419.0",
    "gn:asciiname":"Char Diar Asharidaha",
    "gn:country_code":"BD",
    "gn:dem":25,
    "gn:feature_class":"P",
    "gn:feature_code":"PPL",
    "gn:name":"Char Diar Ash\u0101ridaha",
    "gn:population":0,
    "gn:timezone":"Asia/Dhaka",
    "iso:country":"BD",
    "name:ben_x_preferred":[
        "Char Diar Ash\u0101ridaha"
    ],
    "wof:name":"Char Diar Asharidaha",
    "wof:placetype":"locality"
},
  "geometry": {"coordinates":[88.33511,24.38847],"type":"Point"}
}