{
  "type": "Feature",
  "properties": {
    "gn:admin1_code":"84",
    "gn:admin2_code":"2051",
    "gn:admin3_code":"205158.0",
    "gn:admin4_code":"20515811.0",
    "gn:asciiname":"Saicha",
    "gn:country_code":"BD",
    "gn:dem":15,
    "gn:feature_class":"P",
    "gn:feature_code":"PPL",
    "gn:name":"S\u0101icha",
    "gn:population":0,
    "gn:timezone":"Asia/Dhaka",
    "iso:country":"BD",
    "wof:name":"Saicha",
    "wof:placetype":"locality"
},
  "geometry": {"coordinates":[90.80582,23.01203],"type":"Point"}
}