{
  "type": "Feature",
  "properties": {
    "gn:admin1_code":"84",
    "gn:admin2_code":"2015.0",
    "gn:admin3_code":"201504.0",
    "gn:admin4_code":"20150428.0",
    "gn:asciiname":"Taitadwip",
    "gn:country_code":"BD",
    "gn:dem":9,
    "gn:feature_class":"P",
    "gn:feature_code":"PPL",
    "gn:name":"Tait\u0101dwip",
    "gn:population":0,
    "gn:timezone":"Asia/Dhaka",
    "iso:country":"BD",
    "name:ben_x_preferred":[
        "Tait\u0101dwip"
    ],
    "wof:name":"Taitadwip",
    "wof:placetype":"locality"
},
  "geometry": {"coordinates":[91.90600999999999,22.17113],"type":"Point"}
}