{
  "type": "Feature",
  "properties": {
    "gn:admin1_code":"87",
    "gn:admin2_code":"5527.0",
    "gn:admin3_code":"552738.0",
    "gn:admin4_code":"55273847.0",
    "gn:asciiname":"Ganipur",
    "gn:country_code":"BD",
    "gn:dem":35,
    "gn:feature_class":"P",
    "gn:feature_code":"PPL",
    "gn:name":"Ganipur",
    "gn:population":0,
    "gn:timezone":"Asia/Dhaka",
    "iso:country":"BD",
    "name:ben_x_preferred":[
        "Ganipur"
    ],
    "wof:name":"Ganipur",
    "wof:placetype":"locality"
},
  "geometry": {"coordinates":[88.83418,25.51722],"type":"Point"}
}