{
  "type": "Feature",
  "properties": {
    "gn:admin1_code":"82",
    "gn:admin2_code":"4044.0",
    "gn:admin3_code":"404442.0",
    "gn:admin4_code":"40444213.0",
    "gn:asciiname":"Balutar",
    "gn:country_code":"BD",
    "gn:dem":18,
    "gn:feature_class":"P",
    "gn:feature_code":"PPL",
    "gn:name":"B\u0101lutar",
    "gn:population":0,
    "gn:timezone":"Asia/Dhaka",
    "iso:country":"BD",
    "name:ben_x_preferred":[
        "B\u0101lutar"
    ],
    "wof:name":"Balutar",
    "wof:placetype":"locality"
},
  "geometry": {"coordinates":[88.99242,23.42397],"type":"Point"}
}