{
  "type": "Feature",
  "properties": {
    "gn:admin1_code":"85",
    "gn:admin2_code":"1006",
    "gn:admin3_code":"100662.0",
    "gn:admin4_code":"10066279.0",
    "gn:asciiname":"Saila",
    "gn:country_code":"BD",
    "gn:dem":5,
    "gn:feature_class":"P",
    "gn:feature_code":"PPL",
    "gn:name":"Saila",
    "gn:population":0,
    "gn:timezone":"Asia/Dhaka",
    "iso:country":"BD",
    "wof:name":"Saila",
    "wof:placetype":"locality"
},
  "geometry": {"coordinates":[90.45,22.86667000000001],"type":"Point"}
}