{
  "type": "Feature",
  "properties": {
    "gn:admin1_code":"87",
    "gn:admin2_code":"5532",
    "gn:admin3_code":"553291.0",
    "gn:admin4_code":"55329169.0",
    "gn:asciiname":"Khamar dhubai",
    "gn:country_code":"BD",
    "gn:dem":29,
    "gn:feature_class":"P",
    "gn:feature_code":"PPL",
    "gn:name":"Khamar dhubai",
    "gn:population":0,
    "gn:timezone":"Asia/Dhaka",
    "iso:country":"BD",
    "name:ben_x_preferred":[
        "Khamar dhubai"
    ],
    "wof:name":"Khamar dhubai",
    "wof:placetype":"locality"
},
  "geometry": {"coordinates":[89.57784000000002,25.46887000000001],"type":"Point"}
}