{
  "type": "Feature",
  "properties": {
    "gn:admin1_code":"82",
    "gn:admin2_code":"4018.0",
    "gn:admin3_code":"401807.0",
    "gn:admin4_code":"40180707.0",
    "gn:asciiname":"Damosh",
    "gn:country_code":"BD",
    "gn:dem":18,
    "gn:feature_class":"P",
    "gn:feature_code":"PPL",
    "gn:name":"D\u0101mosh",
    "gn:population":0,
    "gn:timezone":"Asia/Dhaka",
    "iso:country":"BD",
    "name:ben_x_preferred":[
        "D\u0101mosh"
    ],
    "wof:name":"Damosh",
    "wof:placetype":"locality"
},
  "geometry": {"coordinates":[88.94171,23.7312],"type":"Point"}
}