{
  "type": "Feature",
  "properties": {
    "gn:admin1_code":"H",
    "gn:admin2_code":"3089",
    "gn:admin3_code":"308967.0",
    "gn:admin4_code":"30896709.0",
    "gn:asciiname":"Maminakanda",
    "gn:country_code":"BD",
    "gn:dem":25,
    "gn:feature_class":"P",
    "gn:feature_code":"PPL",
    "gn:name":"M\u0101min\u0101k\u0101nda",
    "gn:population":0,
    "gn:timezone":"Asia/Dhaka",
    "iso:country":"BD",
    "wof:name":"Maminakanda",
    "wof:placetype":"locality"
},
  "geometry": {"coordinates":[90.16597,24.96217],"type":"Point"}
}