{
  "type": "Feature",
  "properties": {
    "gn:admin1_code":"83",
    "gn:admin2_code":"5081.0",
    "gn:admin3_code":"508112.0",
    "gn:admin4_code":"50811282.0",
    "gn:asciiname":"Chandipur",
    "gn:country_code":"BD",
    "gn:dem":17,
    "gn:feature_class":"P",
    "gn:feature_code":"PPL",
    "gn:name":"Chandipur",
    "gn:population":0,
    "gn:timezone":"Asia/Dhaka",
    "iso:country":"BD",
    "name:ben_x_preferred":[
        "Chandipur"
    ],
    "wof:name":"Chandipur",
    "wof:placetype":"locality"
},
  "geometry": {"coordinates":[88.75784,24.63544],"type":"Point"}
}