{
  "type": "Feature",
  "properties": {
    "gn:admin1_code":"84",
    "gn:admin2_code":"2019",
    "gn:admin3_code":"201981.0",
    "gn:admin4_code":"20198194.0",
    "gn:asciiname":"Srikail",
    "gn:country_code":"BD",
    "gn:dem":8,
    "gn:feature_class":"P",
    "gn:feature_code":"PPL",
    "gn:name":"Sr\u012bk\u0101il",
    "gn:population":0,
    "gn:timezone":"Asia/Dhaka",
    "iso:country":"BD",
    "wof:name":"Srikail",
    "wof:placetype":"locality"
},
  "geometry": {"coordinates":[90.94976,23.74781],"type":"Point"}
}