{
  "type": "Feature",
  "properties": {
    "gn:admin1_code":"82",
    "gn:admin2_code":"4055.0",
    "gn:admin3_code":"405585.0",
    "gn:admin4_code":"40558571.0",
    "gn:asciiname":"Harispur",
    "gn:country_code":"BD",
    "gn:dem":11,
    "gn:feature_class":"P",
    "gn:feature_code":"PPL",
    "gn:name":"Harispur",
    "gn:population":0,
    "gn:timezone":"Asia/Dhaka",
    "iso:country":"BD",
    "name:ben_x_preferred":[
        "Harispur"
    ],
    "wof:name":"Harispur",
    "wof:placetype":"locality"
},
  "geometry": {"coordinates":[89.34614000000001,23.30991],"type":"Point"}
}