{
  "type": "Feature",
  "properties": {
    "gn:admin1_code":"H",
    "gn:admin2_code":"3061",
    "gn:admin3_code":"306131.0",
    "gn:admin4_code":"30613167.0",
    "gn:asciiname":"Momrazpur",
    "gn:country_code":"BD",
    "gn:dem":17,
    "gn:feature_class":"P",
    "gn:feature_code":"PPL",
    "gn:name":"Momrazpur",
    "gn:population":0,
    "gn:timezone":"Asia/Dhaka",
    "iso:country":"BD",
    "name:und_x_variant":[
        "Momrezpur"
    ],
    "wof:name":"Momrazpur",
    "wof:placetype":"locality"
},
  "geometry": {"coordinates":[90.54554,24.6157],"type":"Point"}
}