{
  "type": "Feature",
  "properties": {
    "gn:admin1_code":"84",
    "gn:asciiname":"Char Dighaldi",
    "gn:country_code":"BD",
    "gn:dem":12,
    "gn:feature_class":"P",
    "gn:feature_code":"PPL",
    "gn:name":"Char Dighaldi",
    "gn:population":0,
    "gn:timezone":"Asia/Dhaka",
    "iso:country":"BD",
    "wof:name":"Char Dighaldi",
    "wof:placetype":"locality"
},
  "geometry": {"coordinates":[90.75664,23.80817],"type":"Point"}
}