{
  "type": "Feature",
  "properties": {
    "gn:admin1_code":"81",
    "gn:admin2_code":"3033.0",
    "gn:admin3_code":"303330.0",
    "gn:admin4_code":"30333067.0",
    "gn:asciiname":"Baruipara",
    "gn:country_code":"BD",
    "gn:dem":20,
    "gn:feature_class":"P",
    "gn:feature_code":"PPL",
    "gn:name":"B\u0101ruip\u0101ra",
    "gn:population":0,
    "gn:timezone":"Asia/Dhaka",
    "iso:country":"BD",
    "name:hif_x_preferred":[
        "Baruipara"
    ],
    "wof:name":"Baruipara",
    "wof:placetype":"locality"
},
  "geometry": {"coordinates":[90.42837,24.13318],"type":"Point"}
}