{
  "type": "Feature",
  "properties": {
    "gn:admin1_code":"82",
    "gn:admin2_code":"4057",
    "gn:admin3_code":"405787.0",
    "gn:admin4_code":"40578700.0",
    "gn:asciiname":"Meherpur",
    "gn:country_code":"BD",
    "gn:dem":22,
    "gn:feature_class":"P",
    "gn:feature_code":"PPL",
    "gn:name":"Meherpur",
    "gn:population":0,
    "gn:timezone":"Asia/Dhaka",
    "iso:country":"BD",
    "name:ben_x_preferred":[
        "Meherpur"
    ],
    "name:eng_x_preferred":[
        "Meherpur"
    ],
    "wof:name":"Meherpur",
    "wof:placetype":"locality"
},
  "geometry": {"coordinates":[88.63033,23.77687],"type":"Point"}
}