{
  "type": "Feature",
  "properties": {
    "gn:admin1_code":"H",
    "gn:admin2_code":"3089",
    "gn:admin3_code":"308990.0",
    "gn:admin4_code":"30899094.0",
    "gn:asciiname":"Gorak",
    "gn:country_code":"BD",
    "gn:dem":26,
    "gn:feature_class":"P",
    "gn:feature_code":"PPL",
    "gn:name":"Gorak",
    "gn:population":0,
    "gn:timezone":"Asia/Dhaka",
    "iso:country":"BD",
    "name:ben_x_preferred":[
        "Gorak"
    ],
    "wof:name":"Gorak",
    "wof:placetype":"locality"
},
  "geometry": {"coordinates":[89.986,25.17364],"type":"Point"}
}