{
  "type": "Feature",
  "properties": {
    "gn:admin1_code":"85",
    "gn:admin2_code":"1006",
    "gn:admin3_code":"100669.0",
    "gn:admin4_code":"10066935.0",
    "gn:asciiname":"Srimati",
    "gn:country_code":"BD",
    "gn:dem":6,
    "gn:feature_class":"P",
    "gn:feature_code":"PPL",
    "gn:name":"Sr\u012bmati",
    "gn:population":0,
    "gn:timezone":"Asia/Dhaka",
    "iso:country":"BD",
    "wof:name":"Srimati",
    "wof:placetype":"locality"
},
  "geometry": {"coordinates":[90.42113999999999,22.98178],"type":"Point"}
}