{
  "type": "Feature",
  "properties": {
    "gn:admin1_code":"81",
    "gn:admin2_code":"3082.0",
    "gn:admin3_code":"308207.0",
    "gn:admin4_code":"30820747.0",
    "gn:asciiname":"Diara",
    "gn:country_code":"BD",
    "gn:dem":13,
    "gn:feature_class":"P",
    "gn:feature_code":"PPL",
    "gn:name":"Di\u0101ra",
    "gn:population":0,
    "gn:timezone":"Asia/Dhaka",
    "iso:country":"BD",
    "wof:name":"Diara",
    "wof:placetype":"locality"
},
  "geometry": {"coordinates":[89.55769000000002,23.72189],"type":"Point"}
}