{
  "type": "Feature",
  "properties": {
    "gn:admin1_code":"H",
    "gn:admin2_code":"3039",
    "gn:admin3_code":"303915.0",
    "gn:admin4_code":"30391507.0",
    "gn:asciiname":"Kalakanda",
    "gn:country_code":"BD",
    "gn:dem":25,
    "gn:feature_class":"P",
    "gn:feature_code":"PPL",
    "gn:name":"Kalakanda",
    "gn:population":0,
    "gn:timezone":"Asia/Dhaka",
    "iso:country":"BD",
    "wof:name":"Kalakanda",
    "wof:placetype":"locality"
},
  "geometry": {"coordinates":[89.78570000000001,25.24743],"type":"Point"}
}