{
  "type": "Feature",
  "properties": {
    "gn:admin1_code":"83",
    "gn:admin2_code":"5010",
    "gn:admin3_code":"501006.0",
    "gn:admin4_code":"50100600.0",
    "gn:asciiname":"Malshon",
    "gn:country_code":"BD",
    "gn:dem":21,
    "gn:feature_class":"P",
    "gn:feature_code":"PPL",
    "gn:name":"M\u0101lshon",
    "gn:population":0,
    "gn:timezone":"Asia/Dhaka",
    "iso:country":"BD",
    "name:ben_x_preferred":[
        "M\u0101lshon"
    ],
    "name:ben_x_variant":[
        "Malson"
    ],
    "name:und_x_variant":[
        "Mansail"
    ],
    "wof:name":"Malshon",
    "wof:placetype":"locality"
},
  "geometry": {"coordinates":[88.98199,24.78994],"type":"Point"}
}