{
  "type": "Feature",
  "properties": {
    "gn:admin1_code":"82",
    "gn:asciiname":"Tukttakhali",
    "gn:country_code":"BD",
    "gn:dem":5,
    "gn:feature_class":"P",
    "gn:feature_code":"PPL",
    "gn:name":"Tukttakh\u0101li",
    "gn:population":0,
    "gn:timezone":"Asia/Dhaka",
    "iso:country":"BD",
    "name:ben_x_preferred":[
        "Tukttakh\u0101li"
    ],
    "wof:name":"Tukttakhali",
    "wof:placetype":"locality"
},
  "geometry": {"coordinates":[90.31289,22.41631],"type":"Point"}
}