{
  "type": "Feature",
  "properties": {
    "gn:admin1_code":"87",
    "gn:admin2_code":"5552",
    "gn:admin3_code":"555239.0",
    "gn:admin4_code":"55523929.0",
    "gn:asciiname":"Jatripara",
    "gn:country_code":"BD",
    "gn:dem":45,
    "gn:feature_class":"P",
    "gn:feature_code":"PPL",
    "gn:name":"J\u0101trip\u0101ra",
    "gn:population":0,
    "gn:timezone":"Asia/Dhaka",
    "iso:country":"BD",
    "name:ben_x_preferred":[
        "J\u0101trip\u0101ra"
    ],
    "wof:name":"Jatripara",
    "wof:placetype":"locality"
},
  "geometry": {"coordinates":[89.2597,26.0203],"type":"Point"}
}