{
  "type": "Feature",
  "properties": {
    "gn:admin1_code":"87",
    "gn:admin2_code":"5552",
    "gn:admin3_code":"555239.0",
    "gn:admin4_code":"55523935.0",
    "gn:asciiname":"Satipara",
    "gn:country_code":"BD",
    "gn:dem":42,
    "gn:feature_class":"P",
    "gn:feature_code":"PPL",
    "gn:name":"Satip\u0101ra",
    "gn:population":0,
    "gn:timezone":"Asia/Dhaka",
    "iso:country":"BD",
    "name:ben_x_preferred":[
        "Satip\u0101ra"
    ],
    "wof:name":"Satipara",
    "wof:placetype":"locality"
},
  "geometry": {"coordinates":[89.20085999999998,25.99836],"type":"Point"}
}