{
  "type": "Feature",
  "properties": {
    "gn:admin1_code":"87",
    "gn:admin2_code":"5573.0",
    "gn:admin3_code":"557364.0",
    "gn:admin4_code":"55736437.0",
    "gn:asciiname":"Dondari",
    "gn:country_code":"BD",
    "gn:dem":50,
    "gn:feature_class":"P",
    "gn:feature_code":"PPL",
    "gn:name":"Dondari",
    "gn:population":0,
    "gn:timezone":"Asia/Dhaka",
    "iso:country":"BD",
    "name:ben_x_preferred":[
        "Dondari"
    ],
    "wof:name":"Dondari",
    "wof:placetype":"locality"
},
  "geometry": {"coordinates":[88.92936,25.96808],"type":"Point"}
}