{
  "type": "Feature",
  "properties": {
    "gn:admin1_code":"84",
    "gn:admin2_code":"2015.0",
    "gn:admin3_code":"201561.0",
    "gn:admin4_code":"20156139.0",
    "gn:asciiname":"Karankhain",
    "gn:country_code":"BD",
    "gn:dem":8,
    "gn:feature_class":"P",
    "gn:feature_code":"PPL",
    "gn:name":"Kar\u0101nkhain",
    "gn:population":0,
    "gn:timezone":"Asia/Dhaka",
    "iso:country":"BD",
    "name:ben_x_preferred":[
        "Kar\u0101nkhain"
    ],
    "wof:name":"Karankhain",
    "wof:placetype":"locality"
},
  "geometry": {"coordinates":[91.93328,22.33777000000001],"type":"Point"}
}