{
  "type": "Feature",
  "properties": {
    "gn:admin1_code":"87",
    "gn:admin2_code":"5532",
    "gn:admin3_code":"553224.0",
    "gn:admin4_code":"55322414.0",
    "gn:asciiname":"Kholabari",
    "gn:country_code":"BD",
    "gn:dem":25,
    "gn:feature_class":"P",
    "gn:feature_code":"PPL",
    "gn:name":"Kholabari",
    "gn:population":0,
    "gn:timezone":"Asia/Dhaka",
    "iso:country":"BD",
    "name:ben_x_preferred":[
        "Kholabari"
    ],
    "wof:name":"Kholabari",
    "wof:placetype":"locality"
},
  "geometry": {"coordinates":[89.50838,25.34591],"type":"Point"}
}