{
  "type": "Feature",
  "properties": {
    "gn:admin1_code":"86",
    "gn:admin2_code":"6091",
    "gn:admin3_code":"609159.0",
    "gn:admin4_code":"60915985.0",
    "gn:asciiname":"Panichara",
    "gn:cc2":"BD",
    "gn:country_code":"BD",
    "gn:dem":11,
    "gn:feature_class":"P",
    "gn:feature_code":"PPL",
    "gn:name":"Panichara",
    "gn:population":0,
    "gn:timezone":"Asia/Dhaka",
    "iso:country":"BD",
    "name:und_x_variant":[
        "Panichera",
        "Panicharrha",
        "Panichara"
    ],
    "wof:name":"Panichara",
    "wof:placetype":"locality"
},
  "geometry": {"coordinates":[92.03333000000001,24.95],"type":"Point"}
}