{
  "type": "Feature",
  "properties": {
    "gn:admin1_code":"83",
    "gn:admin2_code":"5069.0",
    "gn:admin3_code":"506944.0",
    "gn:admin4_code":"50694409.0",
    "gn:asciiname":"Barabil Khali",
    "gn:country_code":"BD",
    "gn:dem":19,
    "gn:feature_class":"P",
    "gn:feature_code":"PPL",
    "gn:name":"Barabil Kh\u0101li",
    "gn:population":0,
    "gn:timezone":"Asia/Dhaka",
    "iso:country":"BD",
    "name:ben_x_preferred":[
        "Barabil Kh\u0101li"
    ],
    "wof:name":"Barabil Khali",
    "wof:placetype":"locality"
},
  "geometry": {"coordinates":[88.96366,24.21807],"type":"Point"}
}