{
  "type": "Feature",
  "properties": {
    "gn:admin1_code":"81",
    "gn:admin2_code":"3056.0",
    "gn:admin3_code":"305678.0",
    "gn:admin4_code":"30567871.0",
    "gn:asciiname":"Charipara",
    "gn:country_code":"BD",
    "gn:dem":15,
    "gn:feature_class":"P",
    "gn:feature_code":"PPL",
    "gn:name":"Ch\u0101rip\u0101ra",
    "gn:population":0,
    "gn:timezone":"Asia/Dhaka",
    "iso:country":"BD",
    "name:tam_x_preferred":[
        "\u0b9a\u0bbe\u0bb0\u0bbf\u0baa\u0bb0\u0bbe"
    ],
    "wof:name":"Charipara",
    "wof:placetype":"locality"
},
  "geometry": {"coordinates":[89.82545999999998,23.83106],"type":"Point"}
}