{
  "type": "Feature",
  "properties": {
    "gn:admin1_code":"81",
    "gn:admin2_code":"3033",
    "gn:admin3_code":"303332.0",
    "gn:admin4_code":"30333219.0",
    "gn:asciiname":"Sonatala",
    "gn:country_code":"BD",
    "gn:dem":13,
    "gn:feature_class":"P",
    "gn:feature_code":"PPL",
    "gn:name":"Son\u0101tala",
    "gn:population":0,
    "gn:timezone":"Asia/Dhaka",
    "iso:country":"BD",
    "wof:name":"Sonatala",
    "wof:placetype":"locality"
},
  "geometry": {"coordinates":[90.33289000000001,24.1085],"type":"Point"}
}