{
  "type": "Feature",
  "properties": {
    "gn:admin1_code":"81",
    "gn:admin2_code":"3067",
    "gn:admin3_code":"306768.0",
    "gn:admin4_code":"30676847.0",
    "gn:asciiname":"Tarail",
    "gn:country_code":"BD",
    "gn:dem":10,
    "gn:feature_class":"P",
    "gn:feature_code":"PPL",
    "gn:name":"T\u0101r\u0101il",
    "gn:population":0,
    "gn:timezone":"Asia/Dhaka",
    "iso:country":"BD",
    "wof:name":"Tarail",
    "wof:placetype":"locality"
},
  "geometry": {"coordinates":[90.57044,23.86016],"type":"Point"}
}