{
  "type": "Feature",
  "properties": {
    "gn:admin1_code":"82",
    "gn:admin2_code":"4018.0",
    "gn:admin3_code":"401855.0",
    "gn:admin4_code":"40185557.0",
    "gn:asciiname":"Goalpara",
    "gn:country_code":"BD",
    "gn:dem":17,
    "gn:feature_class":"P",
    "gn:feature_code":"PPL",
    "gn:name":"Go\u0101lp\u0101ra",
    "gn:population":0,
    "gn:timezone":"Asia/Dhaka",
    "iso:country":"BD",
    "name:ben_x_preferred":[
        "Go\u0101lp\u0101ra"
    ],
    "wof:name":"Goalpara",
    "wof:placetype":"locality"
},
  "geometry": {"coordinates":[88.77710999999999,23.43239],"type":"Point"}
}