{
  "type": "Feature",
  "properties": {
    "gn:admin1_code":"83",
    "gn:admin2_code":"5081.0",
    "gn:admin3_code":"508153.0",
    "gn:admin4_code":"50815340.0",
    "gn:asciiname":"Ghasigaon",
    "gn:country_code":"BD",
    "gn:dem":22,
    "gn:feature_class":"P",
    "gn:feature_code":"PPL",
    "gn:name":"Gh\u0101sigaon",
    "gn:population":0,
    "gn:timezone":"Asia/Dhaka",
    "iso:country":"BD",
    "name:ben_x_preferred":[
        "Gh\u0101sigaon"
    ],
    "wof:name":"Ghasigaon",
    "wof:placetype":"locality"
},
  "geometry": {"coordinates":[88.61072,24.58921],"type":"Point"}
}