{
  "type": "Feature",
  "properties": {
    "gn:admin1_code":"81",
    "gn:admin2_code":"3035.0",
    "gn:admin3_code":"303558.0",
    "gn:admin4_code":"30355855.0",
    "gn:asciiname":"Bajara",
    "gn:country_code":"BD",
    "gn:dem":8,
    "gn:feature_class":"P",
    "gn:feature_code":"PPL",
    "gn:name":"Bajara",
    "gn:population":0,
    "gn:timezone":"Asia/Dhaka",
    "iso:country":"BD",
    "name:ben_x_preferred":[
        "Bajara"
    ],
    "wof:name":"Bajara",
    "wof:placetype":"locality"
},
  "geometry": {"coordinates":[89.84022,23.24199],"type":"Point"}
}