{
  "type": "Feature",
  "properties": {
    "gn:admin1_code":"H",
    "gn:admin2_code":"3089",
    "gn:admin3_code":"308990.0",
    "gn:admin4_code":"30899071.0",
    "gn:asciiname":"Tengarpara",
    "gn:country_code":"BD",
    "gn:dem":26,
    "gn:feature_class":"P",
    "gn:feature_code":"PPL",
    "gn:name":"Tengarpara",
    "gn:population":0,
    "gn:timezone":"Asia/Dhaka",
    "iso:country":"BD",
    "name:ben_x_preferred":[
        "Tengarpara"
    ],
    "wof:name":"Tengarpara",
    "wof:placetype":"locality"
},
  "geometry": {"coordinates":[89.97095,25.21443],"type":"Point"}
}