{
  "type": "Feature",
  "properties": {
    "gn:admin1_code":"82",
    "gn:admin2_code":"4044.0",
    "gn:admin3_code":"404419.0",
    "gn:admin4_code":"40441958.0",
    "gn:asciiname":"Uttar Bhabanipur",
    "gn:country_code":"BD",
    "gn:dem":16,
    "gn:feature_class":"P",
    "gn:feature_code":"PPL",
    "gn:name":"Uttar Bhab\u0101nipur",
    "gn:population":0,
    "gn:timezone":"Asia/Dhaka",
    "iso:country":"BD",
    "name:ben_x_preferred":[
        "Uttar Bhab\u0101nipur"
    ],
    "wof:name":"Uttar Bhabanipur",
    "wof:placetype":"locality"
},
  "geometry": {"coordinates":[89.12235,23.51706],"type":"Point"}
}