{
  "type": "Feature",
  "properties": {
    "gn:admin1_code":"87",
    "gn:admin2_code":"5527.0",
    "gn:admin3_code":"552712.0",
    "gn:admin4_code":"55271217.0",
    "gn:asciiname":"Durlabhpur",
    "gn:country_code":"BD",
    "gn:dem":52,
    "gn:feature_class":"P",
    "gn:feature_code":"PPL",
    "gn:name":"Durlabhpur",
    "gn:population":0,
    "gn:timezone":"Asia/Dhaka",
    "iso:country":"BD",
    "name:ben_x_preferred":[
        "Durllabhpur"
    ],
    "name:ben_x_variant":[
        "Durlabhpur"
    ],
    "wof:name":"Durlabhpur",
    "wof:placetype":"locality"
},
  "geometry": {"coordinates":[88.61627,25.94462],"type":"Point"}
}