{
  "type": "Feature",
  "properties": {
    "gn:admin1_code":"87",
    "gn:admin2_code":"5527.0",
    "gn:admin3_code":"552721.0",
    "gn:admin4_code":"55272167.0",
    "gn:asciiname":"Bara Sultanpur",
    "gn:country_code":"BD",
    "gn:dem":51,
    "gn:feature_class":"P",
    "gn:feature_code":"PPL",
    "gn:name":"Bara Sult\u0101npur",
    "gn:population":0,
    "gn:timezone":"Asia/Dhaka",
    "iso:country":"BD",
    "name:ben_x_preferred":[
        "Bara Sult\u0101npur"
    ],
    "wof:name":"Bara Sultanpur",
    "wof:placetype":"locality"
},
  "geometry": {"coordinates":[88.41571999999999,25.82742],"type":"Point"}
}