{
  "type": "Feature",
  "properties": {
    "gn:admin1_code":"84",
    "gn:admin2_code":"2022.0",
    "gn:admin3_code":"202290.0",
    "gn:admin4_code":"20229031.0",
    "gn:asciiname":"Jhimongkhalipara",
    "gn:country_code":"BD",
    "gn:dem":13,
    "gn:feature_class":"P",
    "gn:feature_code":"PPL",
    "gn:name":"Jhimongkh\u0101l\u012bp\u0101ra",
    "gn:population":0,
    "gn:timezone":"Asia/Dhaka",
    "iso:country":"BD",
    "name:ben_x_preferred":[
        "Jhimongkh\u0101l\u012bp\u0101ra"
    ],
    "name:ben_x_variant":[
        "Jhimangkh\u0101l\u012bp\u0101ra"
    ],
    "wof:name":"Jhimongkhalipara",
    "wof:placetype":"locality"
},
  "geometry": {"coordinates":[92.22723999999999,21.05763],"type":"Point"}
}