{
  "type": "Feature",
  "properties": {
    "gn:admin1_code":"87",
    "gn:admin2_code":"5577.0",
    "gn:admin3_code":"557773.0",
    "gn:admin4_code":"55777347.0",
    "gn:asciiname":"Nahaliapara",
    "gn:country_code":"BD",
    "gn:dem":82,
    "gn:feature_class":"P",
    "gn:feature_code":"PPL",
    "gn:name":"Nahali\u0101p\u0101ra",
    "gn:population":0,
    "gn:timezone":"Asia/Dhaka",
    "iso:country":"BD",
    "name:ben_x_preferred":[
        "Nahali\u0101p\u0101ra"
    ],
    "wof:name":"Nahaliapara",
    "wof:placetype":"locality"
},
  "geometry": {"coordinates":[88.63276,26.41474],"type":"Point"}
}