{
  "type": "Feature",
  "properties": {
    "gn:admin1_code":"81",
    "gn:admin2_code":"3093",
    "gn:admin3_code":"309347.0",
    "gn:admin4_code":"30934765.0",
    "gn:asciiname":"Paikpara",
    "gn:country_code":"BD",
    "gn:dem":23,
    "gn:feature_class":"P",
    "gn:feature_code":"PPL",
    "gn:name":"P\u0101ikp\u0101ra",
    "gn:population":0,
    "gn:timezone":"Asia/Dhaka",
    "iso:country":"BD",
    "wof:name":"Paikpara",
    "wof:placetype":"locality"
},
  "geometry": {"coordinates":[90.08942,24.36897],"type":"Point"}
}