{
  "type": "Feature",
  "properties": {
    "gn:admin1_code":"82",
    "gn:admin2_code":"4018.0",
    "gn:admin3_code":"401823.0",
    "gn:admin4_code":"40182300.0",
    "gn:asciiname":"Thakurpur",
    "gn:country_code":"BD",
    "gn:dem":19,
    "gn:feature_class":"P",
    "gn:feature_code":"PPL",
    "gn:name":"Th\u0101kurpur",
    "gn:population":0,
    "gn:timezone":"Asia/Dhaka",
    "iso:country":"BD",
    "name:ben_x_preferred":[
        "Th\u0101kurpur"
    ],
    "wof:name":"Thakurpur",
    "wof:placetype":"locality"
},
  "geometry": {"coordinates":[88.85141,23.62241],"type":"Point"}
}