{
  "type": "Feature",
  "properties": {
    "gn:admin1_code":"85",
    "gn:admin2_code":"1042.0",
    "gn:admin3_code":"104240.0",
    "gn:admin4_code":"10424038.0",
    "gn:asciiname":"Balighona",
    "gn:country_code":"BD",
    "gn:dem":10,
    "gn:feature_class":"P",
    "gn:feature_code":"PPL",
    "gn:name":"B\u0101lighona",
    "gn:population":0,
    "gn:timezone":"Asia/Dhaka",
    "iso:country":"BD",
    "wof:name":"Balighona",
    "wof:placetype":"locality"
},
  "geometry": {"coordinates":[90.21680000000001,22.74023],"type":"Point"}
}