{
  "type": "Feature",
  "properties": {
    "gn:admin1_code":"84",
    "gn:admin2_code":"2013.0",
    "gn:admin3_code":"201358.0",
    "gn:admin4_code":"20135823.0",
    "gn:asciiname":"Bargi",
    "gn:country_code":"BD",
    "gn:dem":14,
    "gn:feature_class":"P",
    "gn:feature_code":"PPL",
    "gn:name":"Bargi",
    "gn:population":0,
    "gn:timezone":"Asia/Dhaka",
    "iso:country":"BD",
    "name:ben_x_preferred":[
        "\u09ac\u09b0\u09cd\u0997\u09bf"
    ],
    "name:mar_x_preferred":[
        "\u092c\u093e\u0930\u094d\u0917\u0940"
    ],
    "name:vie_x_preferred":[
        "Bargi"
    ],
    "wof:name":"Bargi",
    "wof:placetype":"locality"
},
  "geometry": {"coordinates":[90.93683,23.33695],"type":"Point"}
}