{
  "type": "Feature",
  "properties": {
    "gn:admin1_code":"87",
    "gn:admin2_code":"5527",
    "gn:admin3_code":"552777.0",
    "gn:admin4_code":"55277777.0",
    "gn:asciiname":"Kholahati",
    "gn:country_code":"BD",
    "gn:dem":36,
    "gn:feature_class":"P",
    "gn:feature_code":"PPL",
    "gn:name":"Kholah\u0101ti",
    "gn:population":0,
    "gn:timezone":"Asia/Dhaka",
    "iso:country":"BD",
    "name:ben_x_preferred":[
        "Kholah\u0101ti"
    ],
    "wof:name":"Kholahati",
    "wof:placetype":"locality"
},
  "geometry": {"coordinates":[88.98658,25.65884],"type":"Point"}
}