{
  "type": "Feature",
  "properties": {
    "gn:admin1_code":"82",
    "gn:admin2_code":"4055.0",
    "gn:admin3_code":"405585.0",
    "gn:admin4_code":"40558547.0",
    "gn:asciiname":"Gangarampur",
    "gn:country_code":"BD",
    "gn:dem":10,
    "gn:feature_class":"P",
    "gn:feature_code":"PPL",
    "gn:name":"Gangarampur",
    "gn:population":0,
    "gn:timezone":"Asia/Dhaka",
    "iso:country":"BD",
    "name:ben_x_preferred":[
        "Gangarampur"
    ],
    "name:ben_x_variant":[
        "\u0997\u0999\u09cd\u0997\u09be\u09b0\u09be\u09ae\u09aa\u09c1\u09b0"
    ],
    "name:bpy_x_preferred":[
        "\u0997\u0999\u09cd\u0997\u09be\u09b0\u09be\u09ae\u09aa\u09c1\u09b0"
    ],
    "name:ceb_x_preferred":[
        "Gang\u0101r\u0101mpur"
    ],
    "name:hif_x_preferred":[
        "Gangarampur"
    ],
    "name:hin_x_preferred":[
        "\u0917\u0902\u0917\u093e\u0930\u093e\u092e\u092a\u0941\u0930"
    ],
    "name:ita_x_preferred":[
        "Gangarampur"
    ],
    "name:msa_x_preferred":[
        "Gangarampur"
    ],
    "name:new_x_preferred":[
        "\u0917\u0902\u0917\u093e\u0930\u093e\u092e\u092a\u0941\u0930"
    ],
    "name:ori_x_preferred":[
        "\u0b17\u0b19\u0b4d\u0b17\u0b3e\u0b30\u0b3e\u0b2e\u0b2a\u0b41\u0b30"
    ],
    "name:por_x_preferred":[
        "Gangarampur"
    ],
    "name:spa_x_preferred":[
        "Gangarampur"
    ],
    "name:swe_x_preferred":[
        "Gang\u0101r\u0101mpur"
    ],
    "name:vie_x_preferred":[
        "Gangarampur"
    ],
    "name:zho_x_preferred":[
        "\u5188\u683c\u963f\u62c9\u59c6\u666e\u5c14"
    ],
    "wof:name":"Gangarampur",
    "wof:placetype":"locality"
},
  "geometry": {"coordinates":[89.45685999999998,23.30519],"type":"Point"}
}