{
  "type": "Feature",
  "properties": {
    "gn:admin1_code":"82",
    "gn:admin2_code":"4055.0",
    "gn:admin3_code":"405585.0",
    "gn:admin4_code":"40558547.0",
    "gn:asciiname":"Gangarampur",
    "gn:country_code":"BD",
    "gn:dem":10,
    "gn:feature_class":"P",
    "gn:feature_code":"PPL",
    "gn:name":"Gangarampur",
    "gn:population":0,
    "gn:timezone":"Asia/Dhaka",
    "iso:country":"BD",
    "name:ben_x_preferred":[
        "Gangarampur"
    ],
    "wof:name":"Gangarampur",
    "wof:placetype":"locality"
},
  "geometry": {"coordinates":[89.45685999999998,23.30519],"type":"Point"}
}