{
  "type": "Feature",
  "properties": {
    "gn:admin1_code":"82",
    "gn:admin2_code":"4044.0",
    "gn:admin3_code":"404419.0",
    "gn:admin4_code":"40441979.0",
    "gn:asciiname":"Chuadanga",
    "gn:country_code":"BD",
    "gn:dem":12,
    "gn:feature_class":"P",
    "gn:feature_code":"PPL",
    "gn:name":"Chu\u0101d\u0101nga",
    "gn:population":0,
    "gn:timezone":"Asia/Dhaka",
    "iso:country":"BD",
    "name:ben_x_preferred":[
        "Chu\u0101d\u0101nga"
    ],
    "wof:name":"Chuadanga",
    "wof:placetype":"locality"
},
  "geometry": {"coordinates":[89.20095999999999,23.53865],"type":"Point"}
}