{
  "type": "Feature",
  "properties": {
    "gn:admin1_code":"82",
    "gn:admin2_code":"4047.0",
    "gn:admin3_code":"404730.0",
    "gn:admin4_code":"40473094.0",
    "gn:asciiname":"Haburia",
    "gn:country_code":"BD",
    "gn:dem":3,
    "gn:feature_class":"P",
    "gn:feature_code":"PPL",
    "gn:name":"H\u0101buria",
    "gn:population":0,
    "gn:timezone":"Asia/Dhaka",
    "iso:country":"BD",
    "wof:name":"Haburia",
    "wof:placetype":"locality"
},
  "geometry": {"coordinates":[89.34349,22.72985],"type":"Point"}
}