{
  "type": "Feature",
  "properties": {
    "gn:admin1_code":"82",
    "gn:admin2_code":"4055",
    "gn:admin3_code":"405595.0",
    "gn:admin4_code":"40559552.0",
    "gn:asciiname":"Majail Madartala",
    "gn:country_code":"BD",
    "gn:dem":13,
    "gn:feature_class":"P",
    "gn:feature_code":"PPL",
    "gn:name":"Majail Madartala",
    "gn:population":0,
    "gn:timezone":"Asia/Dhaka",
    "iso:country":"BD",
    "wof:name":"Majail Madartala",
    "wof:placetype":"locality"
},
  "geometry": {"coordinates":[89.5154,23.53243],"type":"Point"}
}