{
  "type": "Feature",
  "properties": {
    "gn:admin1_code":"83",
    "gn:admin2_code":"5069",
    "gn:admin3_code":"506963.0",
    "gn:admin4_code":"50696373.0",
    "gn:asciiname":"Purba Madhnagar",
    "gn:country_code":"BD",
    "gn:dem":19,
    "gn:feature_class":"P",
    "gn:feature_code":"PPL",
    "gn:name":"Purba M\u0101dhnagar",
    "gn:population":0,
    "gn:timezone":"Asia/Dhaka",
    "iso:country":"BD",
    "name:ben_x_preferred":[
        "Purba M\u0101dhnagar"
    ],
    "wof:name":"Purba Madhnagar",
    "wof:placetype":"locality"
},
  "geometry": {"coordinates":[88.96477,24.5349],"type":"Point"}
}