{
  "type": "Feature",
  "properties": {
    "gn:admin1_code":"87",
    "gn:admin2_code":"5585",
    "gn:admin3_code":"558576.0",
    "gn:admin4_code":"55857695.0",
    "gn:asciiname":"Kashimpur Harina",
    "gn:country_code":"BD",
    "gn:dem":30,
    "gn:feature_class":"P",
    "gn:feature_code":"PPL",
    "gn:name":"Kashimpur Harina",
    "gn:population":0,
    "gn:timezone":"Asia/Dhaka",
    "iso:country":"BD",
    "name:ben_x_preferred":[
        "Kashimpur Harina"
    ],
    "wof:name":"Kashimpur Harina",
    "wof:placetype":"locality"
},
  "geometry": {"coordinates":[89.19289999999999,25.4166],"type":"Point"}
}