{
  "type": "Feature",
  "properties": {
    "gn:admin1_code":"87",
    "gn:admin2_code":"5532",
    "gn:admin3_code":"553267.0",
    "gn:admin4_code":"55326709.0",
    "gn:asciiname":"Purba Ramchandrapur",
    "gn:country_code":"BD",
    "gn:dem":28,
    "gn:feature_class":"P",
    "gn:feature_code":"PPL",
    "gn:name":"Purba Ramchandrapur",
    "gn:population":0,
    "gn:timezone":"Asia/Dhaka",
    "iso:country":"BD",
    "name:ben_x_preferred":[
        "Purba Ramchandrapur"
    ],
    "wof:name":"Purba Ramchandrapur",
    "wof:placetype":"locality"
},
  "geometry": {"coordinates":[89.38004000000002,25.26179],"type":"Point"}
}