{
  "type": "Feature",
  "properties": {
    "gn:admin1_code":"82",
    "gn:admin2_code":"4047",
    "gn:admin3_code":"404730.0",
    "gn:admin4_code":"40473081.0",
    "gn:asciiname":"Latabunia",
    "gn:country_code":"BD",
    "gn:dem":4,
    "gn:feature_class":"P",
    "gn:feature_code":"PPL",
    "gn:name":"Lat\u0101bunia",
    "gn:population":0,
    "gn:timezone":"Asia/Dhaka",
    "iso:country":"BD",
    "wof:name":"Latabunia",
    "wof:placetype":"locality"
},
  "geometry": {"coordinates":[89.38719,22.73615],"type":"Point"}
}