{
  "type": "Feature",
  "properties": {
    "gn:admin1_code":"83",
    "gn:admin2_code":"5081.0",
    "gn:admin3_code":"508194.0",
    "gn:admin4_code":"50819413.0",
    "gn:asciiname":"Gholkandor",
    "gn:country_code":"BD",
    "gn:dem":48,
    "gn:feature_class":"P",
    "gn:feature_code":"PPL",
    "gn:name":"Gholk\u0101ndor",
    "gn:population":0,
    "gn:timezone":"Asia/Dhaka",
    "iso:country":"BD",
    "name:ben_x_preferred":[
        "Gholk\u0101ndor"
    ],
    "name:ben_x_variant":[
        "Gholkandar"
    ],
    "wof:name":"Gholkandor",
    "wof:placetype":"locality"
},
  "geometry": {"coordinates":[88.425,24.64753],"type":"Point"}
}