{
  "type": "Feature",
  "properties": {
    "gn:admin1_code":"84",
    "gn:admin2_code":"2015.0",
    "gn:admin3_code":"201504.0",
    "gn:admin4_code":"20150476.0",
    "gn:asciiname":"Kunirbil",
    "gn:country_code":"BD",
    "gn:dem":8,
    "gn:feature_class":"P",
    "gn:feature_code":"PPL",
    "gn:name":"Kunirbil",
    "gn:population":0,
    "gn:timezone":"Asia/Dhaka",
    "iso:country":"BD",
    "name:ben_x_preferred":[
        "Kunirbil"
    ],
    "wof:name":"Kunirbil",
    "wof:placetype":"locality"
},
  "geometry": {"coordinates":[91.95332999999999,22.21522],"type":"Point"}
}