{
  "type": "Feature",
  "properties": {
    "gn:admin1_code":"84",
    "gn:admin2_code":"2015.0",
    "gn:admin3_code":"201533.0",
    "gn:admin4_code":"20153361.0",
    "gn:asciiname":"Barmacharimukh",
    "gn:country_code":"BD",
    "gn:dem":49,
    "gn:feature_class":"P",
    "gn:feature_code":"PPL",
    "gn:name":"Barmacharimukh",
    "gn:population":0,
    "gn:timezone":"Asia/Dhaka",
    "iso:country":"BD",
    "name:ben_x_preferred":[
        "Barmacharimukh"
    ],
    "wof:name":"Barmacharimukh",
    "wof:placetype":"locality"
},
  "geometry": {"coordinates":[91.92453,22.68965],"type":"Point"}
}