{
  "type": "Feature",
  "properties": {
    "gn:admin1_code":"81",
    "gn:admin2_code":"3067",
    "gn:admin3_code":"306768.0",
    "gn:admin4_code":"30676815.0",
    "gn:asciiname":"Masimabad",
    "gn:country_code":"BD",
    "gn:dem":9,
    "gn:feature_class":"P",
    "gn:feature_code":"PPL",
    "gn:name":"M\u0101sim\u0101b\u0101d",
    "gn:population":0,
    "gn:timezone":"Asia/Dhaka",
    "iso:country":"BD",
    "wof:name":"Masimabad",
    "wof:placetype":"locality"
},
  "geometry": {"coordinates":[90.54940000000001,23.80456],"type":"Point"}
}