{
  "type": "Feature",
  "properties": {
    "gn:admin1_code":"82",
    "gn:admin2_code":"4041.0",
    "gn:admin3_code":"404190.0",
    "gn:admin4_code":"40419034.0",
    "gn:asciiname":"Tebaria",
    "gn:country_code":"BD",
    "gn:dem":12,
    "gn:feature_class":"P",
    "gn:feature_code":"PPL",
    "gn:name":"Teb\u0101ria",
    "gn:population":0,
    "gn:timezone":"Asia/Dhaka",
    "iso:country":"BD",
    "name:ben_x_preferred":[
        "Teb\u0101ria"
    ],
    "wof:name":"Tebaria",
    "wof:placetype":"locality"
},
  "geometry": {"coordinates":[88.97465,23.151],"type":"Point"}
}