{
  "type": "Feature",
  "properties": {
    "gn:admin1_code":"83",
    "gn:asciiname":"Krishtapur",
    "gn:country_code":"BD",
    "gn:dem":24,
    "gn:feature_class":"P",
    "gn:feature_code":"PPL",
    "gn:name":"Krishtapur",
    "gn:population":0,
    "gn:timezone":"Asia/Dhaka",
    "iso:country":"BD",
    "name:ben_x_preferred":[
        "Krishtapur"
    ],
    "wof:name":"Krishtapur",
    "wof:placetype":"locality"
},
  "geometry": {"coordinates":[89.41863000000002,25.159],"type":"Point"}
}