{
  "type": "Feature",
  "properties": {
    "gn:admin1_code":"86",
    "gn:admin2_code":"6036",
    "gn:admin3_code":"603671.0",
    "gn:admin4_code":"60367194.0",
    "gn:asciiname":"Nawagaon",
    "gn:country_code":"BD",
    "gn:dem":12,
    "gn:feature_class":"P",
    "gn:feature_code":"PPL",
    "gn:name":"Nawagaon",
    "gn:population":0,
    "gn:timezone":"Asia/Dhaka",
    "iso:country":"BD",
    "name:und_x_variant":[
        "Noyagaon",
        "Nawagaon"
    ],
    "wof:name":"Nawagaon",
    "wof:placetype":"locality"
},
  "geometry": {"coordinates":[91.36449,24.09456],"type":"Point"}
}