{
  "type": "Feature",
  "properties": {
    "gn:admin1_code":"82",
    "gn:admin2_code":"4087",
    "gn:admin3_code":"408782.0",
    "gn:admin4_code":"40878240.0",
    "gn:asciiname":"Radhanagar",
    "gn:country_code":"BD",
    "gn:dem":6,
    "gn:feature_class":"P",
    "gn:feature_code":"PPL",
    "gn:name":"R\u0101dh\u0101nagar",
    "gn:population":0,
    "gn:timezone":"Asia/Dhaka",
    "iso:country":"BD",
    "name:ben_x_preferred":[
        "R\u0101dh\u0101nagar"
    ],
    "wof:name":"Radhanagar",
    "wof:placetype":"locality"
},
  "geometry": {"coordinates":[88.93278000000002,22.64527],"type":"Point"}
}