{
  "type": "Feature",
  "properties": {
    "gn:admin1_code":"81",
    "gn:admin2_code":"3068.0",
    "gn:admin3_code":"306852.0",
    "gn:admin4_code":"30685261.0",
    "gn:asciiname":"Akanagar",
    "gn:country_code":"BD",
    "gn:dem":16,
    "gn:feature_class":"P",
    "gn:feature_code":"PPL",
    "gn:name":"\u0100k\u0101nagar",
    "gn:population":0,
    "gn:timezone":"Asia/Dhaka",
    "iso:country":"BD",
    "wof:name":"Akanagar",
    "wof:placetype":"locality"
},
  "geometry": {"coordinates":[90.78751,24.10798],"type":"Point"}
}