{
  "type": "Feature",
  "properties": {
    "gn:admin1_code":"81",
    "gn:admin2_code":"3048.0",
    "gn:admin3_code":"304827.0",
    "gn:admin4_code":"30482767.0",
    "gn:asciiname":"Asutia",
    "gn:country_code":"BD",
    "gn:dem":15,
    "gn:feature_class":"P",
    "gn:feature_code":"PPL",
    "gn:name":"\u0100sutia",
    "gn:population":0,
    "gn:timezone":"Asia/Dhaka",
    "iso:country":"BD",
    "wof:name":"Asutia",
    "wof:placetype":"locality"
},
  "geometry": {"coordinates":[90.69605,24.3946],"type":"Point"}
}