{
  "type": "Feature",
  "properties": {
    "gn:admin1_code":"82",
    "gn:admin2_code":"4087",
    "gn:admin3_code":"408747.0",
    "gn:admin4_code":"40874747.0",
    "gn:asciiname":"Kalikapur",
    "gn:country_code":"BD",
    "gn:dem":7,
    "gn:feature_class":"P",
    "gn:feature_code":"PPL",
    "gn:name":"K\u0101lik\u0101pur",
    "gn:population":0,
    "gn:timezone":"Asia/Dhaka",
    "iso:country":"BD",
    "name:ben_x_preferred":[
        "K\u0101lik\u0101pur"
    ],
    "name:und_x_variant":[
        "K\u0101lik\u0101pur Bara"
    ],
    "wof:name":"Kalikapur",
    "wof:placetype":"locality"
},
  "geometry": {"coordinates":[89.14794999999999,22.39811],"type":"Point"}
}