{
  "type": "Feature",
  "properties": {
    "gn:admin1_code":"81",
    "gn:admin2_code":"3059.0",
    "gn:admin3_code":"305944.0",
    "gn:admin4_code":"30594407.0",
    "gn:asciiname":"Bara Bejgaon",
    "gn:country_code":"BD",
    "gn:dem":9,
    "gn:feature_class":"P",
    "gn:feature_code":"PPL",
    "gn:name":"Bara Bejgaon",
    "gn:population":0,
    "gn:timezone":"Asia/Dhaka",
    "iso:country":"BD",
    "name:und_x_variant":[
        "Bejgaon",
        "Bara Bejgaon"
    ],
    "wof:name":"Bara Bejgaon",
    "wof:placetype":"locality"
},
  "geometry": {"coordinates":[90.35348999999999,23.46408],"type":"Point"}
}