{
  "type": "Feature",
  "properties": {
    "gn:admin1_code":"85",
    "gn:admin2_code":"1078",
    "gn:admin3_code":"107895.0",
    "gn:admin4_code":"10789531.0",
    "gn:asciiname":"Patuakhali",
    "gn:country_code":"BD",
    "gn:dem":7,
    "gn:feature_class":"P",
    "gn:feature_code":"PPL",
    "gn:name":"Patu\u0101kh\u0101li",
    "gn:population":0,
    "gn:timezone":"Asia/Dhaka",
    "iso:country":"BD",
    "name:ara_x_preferred":[
        "\u0628\u0627\u062a\u0648\u0627\u062e\u0627\u0644\u064a"
    ],
    "name:ben_x_preferred":[
        "Patu\u0101kh\u0101li"
    ],
    "name:mar_x_preferred":[
        "\u092a\u091f\u0941\u0906\u0916\u093e\u0932\u0940"
    ],
    "name:rus_x_preferred":[
        "\u041f\u0430\u0442\u0443\u0430\u043a\u0445\u0430\u043b\u0438"
    ],
    "name:swe_x_preferred":[
        "Patuakhali"
    ],
    "wof:name":"Patuakhali",
    "wof:placetype":"locality"
},
  "geometry": {"coordinates":[90.22441000000001,22.27147],"type":"Point"}
}