{
  "type": "Feature",
  "properties": {
    "gn:admin1_code":"85",
    "gn:admin2_code":"1078",
    "gn:admin3_code":"107895.0",
    "gn:admin4_code":"10789531.0",
    "gn:asciiname":"Patuakhali",
    "gn:country_code":"BD",
    "gn:dem":7,
    "gn:feature_class":"P",
    "gn:feature_code":"PPL",
    "gn:name":"Patu\u0101kh\u0101li",
    "gn:population":0,
    "gn:timezone":"Asia/Dhaka",
    "iso:country":"BD",
    "name:ben_x_preferred":[
        "Patu\u0101kh\u0101li"
    ],
    "wof:name":"Patuakhali",
    "wof:placetype":"locality"
},
  "geometry": {"coordinates":[90.22441000000001,22.27147],"type":"Point"}
}