{
  "type": "Feature",
  "properties": {
    "gn:admin1_code":"83",
    "gn:admin2_code":"5070.0",
    "gn:admin3_code":"507088.0",
    "gn:admin4_code":"50708823.0",
    "gn:asciiname":"Narendrapur",
    "gn:country_code":"BD",
    "gn:dem":25,
    "gn:feature_class":"P",
    "gn:feature_code":"PPL",
    "gn:name":"Narendrapur",
    "gn:population":0,
    "gn:timezone":"Asia/Dhaka",
    "iso:country":"BD",
    "name:ben_x_preferred":[
        "Narendrapur"
    ],
    "name:epo_x_preferred":[
        "Narendrapur"
    ],
    "wof:name":"Narendrapur",
    "wof:placetype":"locality"
},
  "geometry": {"coordinates":[88.27488000000002,24.72359],"type":"Point"}
}