{
  "type": "Feature",
  "properties": {
    "gn:admin1_code":"82",
    "gn:admin2_code":"4050.0",
    "gn:admin3_code":"405039.0",
    "gn:admin4_code":"40503974.0",
    "gn:asciiname":"Bahirmadi",
    "gn:country_code":"BD",
    "gn:dem":22,
    "gn:feature_class":"P",
    "gn:feature_code":"PPL",
    "gn:name":"B\u0101hirm\u0101di",
    "gn:population":0,
    "gn:timezone":"Asia/Dhaka",
    "iso:country":"BD",
    "name:ben_x_preferred":[
        "B\u0101hirm\u0101di"
    ],
    "wof:name":"Bahirmadi",
    "wof:placetype":"locality"
},
  "geometry": {"coordinates":[88.81626,24.06093],"type":"Point"}
}