{
  "type": "Feature",
  "properties": {
    "gn:admin1_code":"H",
    "gn:admin2_code":"3089",
    "gn:admin3_code":"308937.0",
    "gn:admin4_code":"30893743.0",
    "gn:asciiname":"Mahari",
    "gn:country_code":"BD",
    "gn:dem":25,
    "gn:feature_class":"P",
    "gn:feature_code":"PPL",
    "gn:name":"Mahari",
    "gn:population":0,
    "gn:timezone":"Asia/Dhaka",
    "iso:country":"BD",
    "name:ben_x_preferred":[
        "Mahari"
    ],
    "name:heb_x_preferred":[
        "\u05de\u05d4\u05e8\"\u05d9"
    ],
    "wof:name":"Mahari",
    "wof:placetype":"locality"
},
  "geometry": {"coordinates":[89.995,25.22312],"type":"Point"}
}