{
  "type": "Feature",
  "properties": {
    "gn:admin1_code":"82",
    "gn:admin2_code":"4050",
    "gn:admin3_code":"405039.0",
    "gn:admin4_code":"40503981.0",
    "gn:asciiname":"Pakuria",
    "gn:country_code":"BD",
    "gn:dem":21,
    "gn:feature_class":"P",
    "gn:feature_code":"PPL",
    "gn:name":"P\u0101kuria",
    "gn:population":0,
    "gn:timezone":"Asia/Dhaka",
    "iso:country":"BD",
    "wof:name":"Pakuria",
    "wof:placetype":"locality"
},
  "geometry": {"coordinates":[88.74366999999999,24.04841],"type":"Point"}
}