{
  "type": "Feature",
  "properties": {
    "gn:admin1_code":"83",
    "gn:admin2_code":"5081",
    "gn:admin3_code":"508131.0",
    "gn:admin4_code":"50813111.0",
    "gn:asciiname":"Namudarkhali",
    "gn:country_code":"BD",
    "gn:dem":18,
    "gn:feature_class":"P",
    "gn:feature_code":"PPL",
    "gn:name":"N\u0101mudarkh\u0101li",
    "gn:population":0,
    "gn:timezone":"Asia/Dhaka",
    "iso:country":"BD",
    "name:ben_x_preferred":[
        "N\u0101mudarkh\u0101li"
    ],
    "wof:name":"Namudarkhali",
    "wof:placetype":"locality"
},
  "geometry": {"coordinates":[88.75894,24.47412000000001],"type":"Point"}
}