{
  "type": "Feature",
  "properties": {
    "gn:admin1_code":"82",
    "gn:admin2_code":"4044.0",
    "gn:admin3_code":"404471.0",
    "gn:admin4_code":"40447117.0",
    "gn:asciiname":"Rakhalbhaga",
    "gn:country_code":"BD",
    "gn:dem":16,
    "gn:feature_class":"P",
    "gn:feature_code":"PPL",
    "gn:name":"Rakhalbhaga",
    "gn:population":0,
    "gn:timezone":"Asia/Dhaka",
    "iso:country":"BD",
    "name:ben_x_preferred":[
        "Rakhalbhaga"
    ],
    "wof:name":"Rakhalbhaga",
    "wof:placetype":"locality"
},
  "geometry": {"coordinates":[88.90911,23.40227],"type":"Point"}
}