{
  "type": "Feature",
  "properties": {
    "gn:admin1_code":"87",
    "gn:admin2_code":"5532",
    "gn:admin3_code":"553230.0",
    "gn:admin4_code":"55323094.0",
    "gn:asciiname":"Damadarpur",
    "gn:country_code":"BD",
    "gn:dem":23,
    "gn:feature_class":"P",
    "gn:feature_code":"PPL",
    "gn:name":"D\u0101madarpur",
    "gn:population":0,
    "gn:timezone":"Asia/Dhaka",
    "iso:country":"BD",
    "name:ben_x_preferred":[
        "D\u0101madarpur"
    ],
    "wof:name":"Damadarpur",
    "wof:placetype":"locality"
},
  "geometry": {"coordinates":[89.41154,25.21588],"type":"Point"}
}