{
  "type": "Feature",
  "properties": {
    "gn:admin1_code":"82",
    "gn:admin2_code":"4065.0",
    "gn:admin3_code":"406576.0",
    "gn:admin4_code":"40657613.0",
    "gn:asciiname":"Nandakol",
    "gn:country_code":"BD",
    "gn:dem":7,
    "gn:feature_class":"P",
    "gn:feature_code":"PPL",
    "gn:name":"Nandakol",
    "gn:population":0,
    "gn:timezone":"Asia/Dhaka",
    "iso:country":"BD",
    "name:ben_x_preferred":[
        "Nandakol"
    ],
    "wof:name":"Nandakol",
    "wof:placetype":"locality"
},
  "geometry": {"coordinates":[89.59544,23.13329],"type":"Point"}
}