{
  "type": "Feature",
  "properties": {
    "gn:admin1_code":"82",
    "gn:admin2_code":"4044",
    "gn:admin3_code":"404471.0",
    "gn:admin4_code":"40447183.0",
    "gn:asciiname":"Khalispur",
    "gn:country_code":"BD",
    "gn:dem":12,
    "gn:feature_class":"P",
    "gn:feature_code":"PPL",
    "gn:name":"Kh\u0101lispur",
    "gn:population":0,
    "gn:timezone":"Asia/Dhaka",
    "iso:country":"BD",
    "name:ben_x_preferred":[
        "Kh\u0101lispur"
    ],
    "name:und_x_variant":[
        "Hat Khalispur",
        "Khalishpur"
    ],
    "wof:name":"Khalispur",
    "wof:placetype":"locality"
},
  "geometry": {"coordinates":[88.94353000000002,23.39277],"type":"Point"}
}