{
  "type": "Feature",
  "properties": {
    "gn:admin1_code":"83",
    "gn:admin2_code":"5010.0",
    "gn:admin3_code":"501020.0",
    "gn:admin4_code":"50102021.0",
    "gn:asciiname":"Bagulahar",
    "gn:country_code":"BD",
    "gn:dem":24,
    "gn:feature_class":"P",
    "gn:feature_code":"PPL",
    "gn:name":"Bagul\u0101h\u0101r",
    "gn:population":0,
    "gn:timezone":"Asia/Dhaka",
    "iso:country":"BD",
    "wof:name":"Bagulahar",
    "wof:placetype":"locality"
},
  "geometry": {"coordinates":[89.31683000000002,24.88799],"type":"Point"}
}