{
  "type": "Feature",
  "properties": {
    "gn:admin1_code":"81",
    "gn:admin2_code":"3026.0",
    "gn:admin3_code":"302672.0",
    "gn:admin4_code":"30267222.0",
    "gn:asciiname":"Basutia",
    "gn:country_code":"BD",
    "gn:dem":15,
    "gn:feature_class":"P",
    "gn:feature_code":"PPL",
    "gn:name":"B\u0101sutia",
    "gn:population":0,
    "gn:timezone":"Asia/Dhaka",
    "iso:country":"BD",
    "wof:name":"Basutia",
    "wof:placetype":"locality"
},
  "geometry": {"coordinates":[90.312,23.82594],"type":"Point"}
}