{
  "type": "Feature",
  "properties": {
    "gn:admin1_code":"83",
    "gn:asciiname":"Baliarber",
    "gn:country_code":"BD",
    "gn:dem":19,
    "gn:feature_class":"P",
    "gn:feature_code":"PPL",
    "gn:name":"Baliarber",
    "gn:population":0,
    "gn:timezone":"Asia/Dhaka",
    "iso:country":"BD",
    "name:ben_x_preferred":[
        "Baliarber"
    ],
    "wof:name":"Baliarber",
    "wof:placetype":"locality"
},
  "geometry": {"coordinates":[89.52885000000001,25.04927],"type":"Point"}
}