{
  "type": "Feature",
  "properties": {
    "gn:admin1_code":"87",
    "gn:admin2_code":"5594.0",
    "gn:admin3_code":"559451.0",
    "gn:admin4_code":"55945167.0",
    "gn:asciiname":"Mollatola",
    "gn:country_code":"BD",
    "gn:dem":47,
    "gn:feature_class":"P",
    "gn:feature_code":"PPL",
    "gn:name":"Mollatola",
    "gn:population":0,
    "gn:timezone":"Asia/Dhaka",
    "iso:country":"BD",
    "name:ben_x_preferred":[
        "Mollatola"
    ],
    "wof:name":"Mollatola",
    "wof:placetype":"locality"
},
  "geometry": {"coordinates":[88.19110000000001,25.9461],"type":"Point"}
}