{
  "type": "Feature",
  "properties": {
    "gn:admin1_code":"85",
    "gn:admin2_code":"1042.0",
    "gn:admin3_code":"104240.0",
    "gn:admin4_code":"10424076.0",
    "gn:asciiname":"Dasanakanda",
    "gn:country_code":"BD",
    "gn:dem":7,
    "gn:feature_class":"P",
    "gn:feature_code":"PPL",
    "gn:name":"Dasan\u0101kanda",
    "gn:population":0,
    "gn:timezone":"Asia/Dhaka",
    "iso:country":"BD",
    "wof:name":"Dasanakanda",
    "wof:placetype":"locality"
},
  "geometry": {"coordinates":[90.21339999999999,22.71574],"type":"Point"}
}