{
  "type": "Feature",
  "properties": {
    "gn:admin1_code":"81",
    "gn:admin2_code":"3059.0",
    "gn:admin3_code":"305974.0",
    "gn:admin4_code":"30597494.0",
    "gn:asciiname":"Baram",
    "gn:country_code":"BD",
    "gn:dem":8,
    "gn:feature_class":"P",
    "gn:feature_code":"PPL",
    "gn:name":"Bar\u0101m",
    "gn:population":0,
    "gn:timezone":"Asia/Dhaka",
    "iso:country":"BD",
    "wof:name":"Baram",
    "wof:placetype":"locality"
},
  "geometry": {"coordinates":[90.27606,23.62852],"type":"Point"}
}