{
  "type": "Feature",
  "properties": {
    "gn:admin1_code":"81",
    "gn:admin2_code":"3026",
    "gn:admin3_code":"302672.0",
    "gn:admin4_code":"30267200.0",
    "gn:asciiname":"Karnapara",
    "gn:country_code":"BD",
    "gn:dem":13,
    "gn:feature_class":"P",
    "gn:feature_code":"PPL",
    "gn:name":"Karnap\u0101ra",
    "gn:population":0,
    "gn:timezone":"Asia/Dhaka",
    "iso:country":"BD",
    "wof:name":"Karnapara",
    "wof:placetype":"locality"
},
  "geometry": {"coordinates":[90.25512999999999,23.8267],"type":"Point"}
}