{
  "type": "Feature",
  "properties": {
    "gn:admin1_code":"81",
    "gn:admin2_code":"3059",
    "gn:admin3_code":"305994.0",
    "gn:admin4_code":"30599423.0",
    "gn:asciiname":"Selimpur",
    "gn:country_code":"BD",
    "gn:dem":9,
    "gn:feature_class":"P",
    "gn:feature_code":"PPL",
    "gn:name":"Selimpur",
    "gn:population":0,
    "gn:timezone":"Asia/Dhaka",
    "iso:country":"BD",
    "wof:name":"Selimpur",
    "wof:placetype":"locality"
},
  "geometry": {"coordinates":[90.41773999999999,23.51685],"type":"Point"}
}