{
  "type": "Feature",
  "properties": {
    "gn:admin1_code":"83",
    "gn:admin2_code":"5064.0",
    "gn:admin3_code":"506475.0",
    "gn:admin4_code":"50647560.0",
    "gn:asciiname":"Bad Puia",
    "gn:country_code":"BD",
    "gn:dem":24,
    "gn:feature_class":"P",
    "gn:feature_code":"PPL",
    "gn:name":"B\u0101d Puia",
    "gn:population":0,
    "gn:timezone":"Asia/Dhaka",
    "iso:country":"BD",
    "name:ben_x_preferred":[
        "B\u0101d Puia"
    ],
    "wof:name":"Bad Puia",
    "wof:placetype":"locality"
},
  "geometry": {"coordinates":[88.75612,25.0279],"type":"Point"}
}