{
  "type": "Feature",
  "properties": {
    "gn:admin1_code":"85",
    "gn:admin2_code":"1006",
    "gn:admin3_code":"100607.0",
    "gn:admin4_code":"10060761.0",
    "gn:asciiname":"Sialghuni",
    "gn:country_code":"BD",
    "gn:dem":10,
    "gn:feature_class":"P",
    "gn:feature_code":"PPL",
    "gn:name":"Si\u0101lghuni",
    "gn:population":0,
    "gn:timezone":"Asia/Dhaka",
    "iso:country":"BD",
    "wof:name":"Sialghuni",
    "wof:placetype":"locality"
},
  "geometry": {"coordinates":[90.44484,22.55337],"type":"Point"}
}