{
  "type": "Feature",
  "properties": {
    "gn:admin1_code":"83",
    "gn:admin2_code":"5081.0",
    "gn:admin3_code":"508182.0",
    "gn:admin4_code":"50818213.0",
    "gn:asciiname":"Palashbari",
    "gn:country_code":"BD",
    "gn:dem":20,
    "gn:feature_class":"P",
    "gn:feature_code":"PPL",
    "gn:name":"Pal\u0101shb\u0101ri",
    "gn:population":0,
    "gn:timezone":"Asia/Dhaka",
    "iso:country":"BD",
    "name:ben_x_preferred":[
        "Pal\u0101shb\u0101ri"
    ],
    "wof:name":"Palashbari",
    "wof:placetype":"locality"
},
  "geometry": {"coordinates":[88.80354,24.35328],"type":"Point"}
}