{
  "type": "Feature",
  "properties": {
    "gn:admin1_code":"87",
    "gn:admin2_code":"5585",
    "gn:admin3_code":"558542.0",
    "gn:admin4_code":"55854200.0",
    "gn:asciiname":"Banhilkhuti",
    "gn:country_code":"BD",
    "gn:dem":37,
    "gn:feature_class":"P",
    "gn:feature_code":"PPL",
    "gn:name":"Banhilkhuti",
    "gn:population":0,
    "gn:timezone":"Asia/Dhaka",
    "iso:country":"BD",
    "name:ben_x_preferred":[
        "Banhilkhuti"
    ],
    "wof:name":"Banhilkhuti",
    "wof:placetype":"locality"
},
  "geometry": {"coordinates":[89.32982,25.79178],"type":"Point"}
}