{
  "type": "Feature",
  "properties": {
    "gn:admin1_code":"83",
    "gn:admin2_code":"5070.0",
    "gn:admin3_code":"507088.0",
    "gn:admin4_code":"50708829.0",
    "gn:asciiname":"Chakchama",
    "gn:country_code":"BD",
    "gn:dem":28,
    "gn:feature_class":"P",
    "gn:feature_code":"PPL",
    "gn:name":"Chakch\u0101ma",
    "gn:population":0,
    "gn:timezone":"Asia/Dhaka",
    "iso:country":"BD",
    "name:ben_x_preferred":[
        "Chakch\u0101ma"
    ],
    "wof:name":"Chakchama",
    "wof:placetype":"locality"
},
  "geometry": {"coordinates":[88.13753,24.6994],"type":"Point"}
}