{
  "type": "Feature",
  "properties": {
    "gn:admin1_code":"84",
    "gn:admin2_code":"2022.0",
    "gn:admin3_code":"202266.0",
    "gn:admin4_code":"20226619.0",
    "gn:asciiname":"Jaospara",
    "gn:country_code":"BD",
    "gn:dem":16,
    "gn:feature_class":"P",
    "gn:feature_code":"PPL",
    "gn:name":"Jaosp\u0101ra",
    "gn:population":0,
    "gn:timezone":"Asia/Dhaka",
    "iso:country":"BD",
    "name:ben_x_preferred":[
        "Jaosp\u0101ra"
    ],
    "wof:name":"Jaospara",
    "wof:placetype":"locality"
},
  "geometry": {"coordinates":[92.19687999999999,21.46137],"type":"Point"}
}