{
  "type": "Feature",
  "properties": {
    "gn:admin1_code":"81",
    "gn:asciiname":"Charbila",
    "gn:country_code":"BD",
    "gn:dem":7,
    "gn:feature_class":"P",
    "gn:feature_code":"PPL",
    "gn:name":"Charbila",
    "gn:population":0,
    "gn:timezone":"Asia/Dhaka",
    "iso:country":"BD",
    "name:ben_x_preferred":[
        "Charbila"
    ],
    "wof:name":"Charbila",
    "wof:placetype":"locality"
},
  "geometry": {"coordinates":[89.50700000000001,23.2193],"type":"Point"}
}