{
  "type": "Feature",
  "properties": {
    "gn:admin1_code":"83",
    "gn:admin2_code":"5081",
    "gn:admin3_code":"508134.0",
    "gn:admin4_code":"50813466.0",
    "gn:asciiname":"Kalipur",
    "gn:country_code":"BD",
    "gn:dem":40,
    "gn:feature_class":"P",
    "gn:feature_code":"PPL",
    "gn:name":"Kalipur",
    "gn:population":0,
    "gn:timezone":"Asia/Dhaka",
    "iso:country":"BD",
    "name:ben_x_preferred":[
        "Kalipur"
    ],
    "wof:name":"Kalipur",
    "wof:placetype":"locality"
},
  "geometry": {"coordinates":[88.36423000000001,24.597],"type":"Point"}
}