{
  "type": "Feature",
  "properties": {
    "gn:admin1_code":"81",
    "gn:admin2_code":"3093.0",
    "gn:admin3_code":"309347.0",
    "gn:admin4_code":"30934751.0",
    "gn:asciiname":"Bhadrabari",
    "gn:country_code":"BD",
    "gn:dem":16,
    "gn:feature_class":"P",
    "gn:feature_code":"PPL",
    "gn:name":"Bhadrab\u0101ri",
    "gn:population":0,
    "gn:timezone":"Asia/Dhaka",
    "iso:country":"BD",
    "wof:name":"Bhadrabari",
    "wof:placetype":"locality"
},
  "geometry": {"coordinates":[90.01093,24.39531],"type":"Point"}
}