{
  "type": "Feature",
  "properties": {
    "gn:admin1_code":"82",
    "gn:admin2_code":"4055.0",
    "gn:admin3_code":"405566.0",
    "gn:admin4_code":"40556684.0",
    "gn:asciiname":"Gobarnada",
    "gn:country_code":"BD",
    "gn:dem":10,
    "gn:feature_class":"P",
    "gn:feature_code":"PPL",
    "gn:name":"Gobarn\u0101da",
    "gn:population":0,
    "gn:timezone":"Asia/Dhaka",
    "iso:country":"BD",
    "wof:name":"Gobarnada",
    "wof:placetype":"locality"
},
  "geometry": {"coordinates":[89.54420999999998,23.37342],"type":"Point"}
}