{
  "type": "Feature",
  "properties": {
    "gn:admin1_code":"82",
    "gn:admin2_code":"4050",
    "gn:admin3_code":"405015.0",
    "gn:admin4_code":"40501554.0",
    "gn:asciiname":"Patuakandi",
    "gn:country_code":"BD",
    "gn:dem":21,
    "gn:feature_class":"P",
    "gn:feature_code":"PPL",
    "gn:name":"P\u0101tu\u0101k\u0101ndi",
    "gn:population":0,
    "gn:timezone":"Asia/Dhaka",
    "iso:country":"BD",
    "name:ben_x_preferred":[
        "P\u0101tu\u0101k\u0101ndi"
    ],
    "wof:name":"Patuakandi",
    "wof:placetype":"locality"
},
  "geometry": {"coordinates":[88.92328000000001,24.04300000000001],"type":"Point"}
}