{
  "type": "Feature",
  "properties": {
    "gn:admin1_code":"87",
    "gn:admin2_code":"5532",
    "gn:admin3_code":"553282.0",
    "gn:admin4_code":"55328260.0",
    "gn:asciiname":"Daudpur",
    "gn:country_code":"BD",
    "gn:dem":29,
    "gn:feature_class":"P",
    "gn:feature_code":"PPL",
    "gn:name":"Daudpur",
    "gn:population":0,
    "gn:timezone":"Asia/Dhaka",
    "iso:country":"BD",
    "name:ben_x_preferred":[
        "Daudpur"
    ],
    "wof:name":"Daudpur",
    "wof:placetype":"locality"
},
  "geometry": {"coordinates":[89.44901,25.40691],"type":"Point"}
}