{
  "type": "Feature",
  "properties": {
    "gn:admin1_code":"85",
    "gn:admin2_code":"1009.0",
    "gn:admin3_code":"100965.0",
    "gn:admin4_code":"10096547.0",
    "gn:asciiname":"Sitakunda",
    "gn:country_code":"BD",
    "gn:dem":7,
    "gn:feature_class":"P",
    "gn:feature_code":"PPL",
    "gn:name":"Sitakunda",
    "gn:population":0,
    "gn:timezone":"Asia/Dhaka",
    "iso:country":"BD",
    "name:ben_x_preferred":[
        "Sitakunda"
    ],
    "name:kaz_x_preferred":[
        "\u0421\u0438\u0442\u0430\u043a\u0443\u043d\u0434\u0430"
    ],
    "name:rus_x_preferred":[
        "\u0421\u0438\u0442\u0430\u043a\u0443\u043d\u0434\u0430"
    ],
    "name:zho_x_preferred":[
        "\u5e0c\u5854\u6606\u8fbe"
    ],
    "wof:name":"Sitakunda",
    "wof:placetype":"locality"
},
  "geometry": {"coordinates":[90.98247000000001,22.30746],"type":"Point"}
}