{
  "type": "Feature",
  "properties": {
    "gn:admin1_code":"84",
    "gn:admin2_code":"2013",
    "gn:admin3_code":"201345.0",
    "gn:admin4_code":"20134523.0",
    "gn:asciiname":"Santoshpur",
    "gn:country_code":"BD",
    "gn:dem":14,
    "gn:feature_class":"P",
    "gn:feature_code":"PPL",
    "gn:name":"Santoshpur",
    "gn:population":0,
    "gn:timezone":"Asia/Dhaka",
    "iso:country":"BD",
    "wof:name":"Santoshpur",
    "wof:placetype":"locality"
},
  "geometry": {"coordinates":[90.70386000000001,23.0815],"type":"Point"}
}