{
  "type": "Feature",
  "properties": {
    "gn:admin1_code":"84",
    "gn:admin2_code":"2084.0",
    "gn:admin3_code":"208436.0",
    "gn:admin4_code":"20843619.0",
    "gn:asciiname":"Tipperachari",
    "gn:country_code":"BD",
    "gn:dem":22,
    "gn:feature_class":"P",
    "gn:feature_code":"PPL",
    "gn:name":"Tipper\u0101chari",
    "gn:population":0,
    "gn:timezone":"Asia/Dhaka",
    "iso:country":"BD",
    "name:ben_x_preferred":[
        "Tipper\u0101chari"
    ],
    "wof:name":"Tipperachari",
    "wof:placetype":"locality"
},
  "geometry": {"coordinates":[92.11653,22.55097],"type":"Point"}
}