{
  "type": "Feature",
  "properties": {
    "gn:admin1_code":"82",
    "gn:admin2_code":"4050",
    "gn:admin3_code":"405094.0",
    "gn:admin4_code":"40509480.0",
    "gn:asciiname":"Sudhirajpur",
    "gn:country_code":"BD",
    "gn:dem":19,
    "gn:feature_class":"P",
    "gn:feature_code":"PPL",
    "gn:name":"Sudhirajpur",
    "gn:population":0,
    "gn:timezone":"Asia/Dhaka",
    "iso:country":"BD",
    "name:ben_x_preferred":[
        "Sudhirajpur"
    ],
    "wof:name":"Sudhirajpur",
    "wof:placetype":"locality"
},
  "geometry": {"coordinates":[89.03707,23.88017],"type":"Point"}
}