{
  "type": "Feature",
  "properties": {
    "gn:admin1_code":"87",
    "gn:admin2_code":"5577.0",
    "gn:admin3_code":"557773.0",
    "gn:admin4_code":"55777383.0",
    "gn:asciiname":"Kahapara",
    "gn:country_code":"BD",
    "gn:dem":86,
    "gn:feature_class":"P",
    "gn:feature_code":"PPL",
    "gn:name":"K\u0101h\u0101p\u0101ra",
    "gn:population":0,
    "gn:timezone":"Asia/Dhaka",
    "iso:country":"BD",
    "name:ben_x_preferred":[
        "K\u0101h\u0101p\u0101ra"
    ],
    "wof:name":"Kahapara",
    "wof:placetype":"locality"
},
  "geometry": {"coordinates":[88.54328000000002,26.47845],"type":"Point"}
}