{
  "type": "Feature",
  "properties": {
    "gn:admin1_code":"87",
    "gn:admin2_code":"5527.0",
    "gn:admin3_code":"552764.0",
    "gn:admin4_code":"55276469.0",
    "gn:asciiname":"Darail",
    "gn:country_code":"BD",
    "gn:dem":36,
    "gn:feature_class":"P",
    "gn:feature_code":"PPL",
    "gn:name":"D\u0101r\u0101il",
    "gn:population":0,
    "gn:timezone":"Asia/Dhaka",
    "iso:country":"BD",
    "name:ben_x_preferred":[
        "D\u0101r\u0101il"
    ],
    "wof:name":"Darail",
    "wof:placetype":"locality"
},
  "geometry": {"coordinates":[88.66707,25.56687],"type":"Point"}
}