{
  "type": "Feature",
  "properties": {
    "gn:admin1_code":"87",
    "gn:admin2_code":"5527.0",
    "gn:admin3_code":"552764.0",
    "gn:admin4_code":"55276486.0",
    "gn:asciiname":"Sudarban",
    "gn:country_code":"BD",
    "gn:dem":42,
    "gn:feature_class":"P",
    "gn:feature_code":"PPL",
    "gn:name":"Sudarban",
    "gn:population":0,
    "gn:timezone":"Asia/Dhaka",
    "iso:country":"BD",
    "name:ben_x_preferred":[
        "Sudarban"
    ],
    "wof:name":"Sudarban",
    "wof:placetype":"locality"
},
  "geometry": {"coordinates":[88.72884999999999,25.75845],"type":"Point"}
}