{
  "type": "Feature",
  "properties": {
    "gn:admin1_code":"87",
    "gn:admin2_code":"5577.0",
    "gn:admin3_code":"557790.0",
    "gn:admin4_code":"55779094.0",
    "gn:asciiname":"Monigachh",
    "gn:country_code":"BD",
    "gn:dem":97,
    "gn:feature_class":"P",
    "gn:feature_code":"PPL",
    "gn:name":"Mon\u012bg\u0101chh",
    "gn:population":0,
    "gn:timezone":"Asia/Dhaka",
    "iso:country":"BD",
    "name:ben_x_preferred":[
        "Mon\u012bg\u0101chh"
    ],
    "wof:name":"Monigachh",
    "wof:placetype":"locality"
},
  "geometry": {"coordinates":[88.40733,26.53733],"type":"Point"}
}