{
  "type": "Feature",
  "properties": {
    "gn:admin1_code":"82",
    "gn:asciiname":"Mathbaria",
    "gn:country_code":"BD",
    "gn:dem":6,
    "gn:feature_class":"P",
    "gn:feature_code":"PPL",
    "gn:name":"Mathb\u0101ria",
    "gn:population":0,
    "gn:timezone":"Asia/Dhaka",
    "iso:country":"BD",
    "name:ben_x_preferred":[
        "Mathb\u0101ria"
    ],
    "name:ceb_x_preferred":[
        "Mathba"
    ],
    "name:swe_x_preferred":[
        "Mathba"
    ],
    "wof:name":"Mathbaria",
    "wof:placetype":"locality"
},
  "geometry": {"coordinates":[90.46852,22.25631],"type":"Point"}
}