{
  "type": "Feature",
  "properties": {
    "gn:admin1_code":"84",
    "gn:admin2_code":"2013",
    "gn:admin3_code":"201349.0",
    "gn:admin4_code":"20134935.0",
    "gn:asciiname":"Qazirgaon",
    "gn:country_code":"BD",
    "gn:dem":12,
    "gn:feature_class":"P",
    "gn:feature_code":"PPL",
    "gn:name":"Q\u0101zirgaon",
    "gn:population":0,
    "gn:timezone":"Asia/Dhaka",
    "iso:country":"BD",
    "name:und_x_variant":[
        "Kazigaon",
        "K\u0101zirgaon",
        "Q\u0101zirgaon"
    ],
    "wof:name":"Qazirgaon",
    "wof:placetype":"locality"
},
  "geometry": {"coordinates":[90.85794,23.26567],"type":"Point"}
}