{
  "type": "Feature",
  "properties": {
    "gn:admin1_code":"81",
    "gn:admin2_code":"3048.0",
    "gn:admin3_code":"304879.0",
    "gn:admin4_code":"30487928.0",
    "gn:asciiname":"Char Kursa",
    "gn:country_code":"BD",
    "gn:dem":15,
    "gn:feature_class":"P",
    "gn:feature_code":"PPL",
    "gn:name":"Char Kursa",
    "gn:population":0,
    "gn:timezone":"Asia/Dhaka",
    "iso:country":"BD",
    "wof:name":"Char Kursa",
    "wof:placetype":"locality"
},
  "geometry": {"coordinates":[90.63997999999999,24.32181],"type":"Point"}
}