{
  "type": "Feature",
  "properties": {
    "gn:admin1_code":"82",
    "gn:asciiname":"Gabbaria",
    "gn:country_code":"BD",
    "gn:dem":11,
    "gn:feature_class":"P",
    "gn:feature_code":"PPL",
    "gn:name":"G\u0101bb\u0101ria",
    "gn:population":0,
    "gn:timezone":"Asia/Dhaka",
    "iso:country":"BD",
    "name:ben_x_preferred":[
        "G\u0101bb\u0101ria"
    ],
    "wof:name":"Gabbaria",
    "wof:placetype":"locality"
},
  "geometry": {"coordinates":[89.92245,22.05613],"type":"Point"}
}