{
  "type": "Feature",
  "properties": {
    "gn:admin1_code":"81",
    "gn:admin2_code":"3056",
    "gn:admin3_code":"305622.0",
    "gn:admin4_code":"30562259.0",
    "gn:asciiname":"Kundura",
    "gn:country_code":"BD",
    "gn:dem":11,
    "gn:feature_class":"P",
    "gn:feature_code":"PPL",
    "gn:name":"Kundura",
    "gn:population":0,
    "gn:timezone":"Asia/Dhaka",
    "iso:country":"BD",
    "wof:name":"Kundura",
    "wof:placetype":"locality"
},
  "geometry": {"coordinates":[89.97216999999998,23.8106],"type":"Point"}
}