{
  "type": "Feature",
  "properties": {
    "gn:admin1_code":"81",
    "gn:admin2_code":"3093.0",
    "gn:admin3_code":"309319.0",
    "gn:admin4_code":"30931954.0",
    "gn:asciiname":"Char Gabsara",
    "gn:country_code":"BD",
    "gn:dem":19,
    "gn:feature_class":"P",
    "gn:feature_code":"PPL",
    "gn:name":"Char G\u0101bs\u0101ra",
    "gn:population":0,
    "gn:timezone":"Asia/Dhaka",
    "iso:country":"BD",
    "wof:name":"Char Gabsara",
    "wof:placetype":"locality"
},
  "geometry": {"coordinates":[89.81187,24.49539],"type":"Point"}
}