{
  "type": "Feature",
  "properties": {
    "gn:admin1_code":"82",
    "gn:admin2_code":"4065.0",
    "gn:admin3_code":"406552.0",
    "gn:admin4_code":"40655271.0",
    "gn:asciiname":"Kundasi",
    "gn:country_code":"BD",
    "gn:dem":12,
    "gn:feature_class":"P",
    "gn:feature_code":"PPL",
    "gn:name":"Kundasi",
    "gn:population":0,
    "gn:timezone":"Asia/Dhaka",
    "iso:country":"BD",
    "name:ben_x_preferred":[
        "Kundasi"
    ],
    "wof:name":"Kundasi",
    "wof:placetype":"locality"
},
  "geometry": {"coordinates":[89.65626,23.17932],"type":"Point"}
}