{
  "type": "Feature",
  "properties": {
    "gn:admin1_code":"83",
    "gn:admin2_code":"5064.0",
    "gn:admin3_code":"506486.0",
    "gn:admin4_code":"50648694.0",
    "gn:asciiname":"Chandura",
    "gn:country_code":"BD",
    "gn:dem":27,
    "gn:feature_class":"P",
    "gn:feature_code":"PPL",
    "gn:name":"Chandura",
    "gn:population":0,
    "gn:timezone":"Asia/Dhaka",
    "iso:country":"BD",
    "name:ben_x_preferred":[
        "Chandura"
    ],
    "wof:name":"Chandura",
    "wof:placetype":"locality"
},
  "geometry": {"coordinates":[88.59973000000002,25.06858],"type":"Point"}
}