{
  "type": "Feature",
  "properties": {
    "gn:admin1_code":"81",
    "gn:admin2_code":"3059.0",
    "gn:admin3_code":"305984.0",
    "gn:admin4_code":"30598420.0",
    "gn:asciiname":"Benukhali",
    "gn:country_code":"BD",
    "gn:dem":11,
    "gn:feature_class":"P",
    "gn:feature_code":"PPL",
    "gn:name":"Benukh\u0101li",
    "gn:population":0,
    "gn:timezone":"Asia/Dhaka",
    "iso:country":"BD",
    "wof:name":"Benukhali",
    "wof:placetype":"locality"
},
  "geometry": {"coordinates":[90.24281000000001,23.63315],"type":"Point"}
}