{
  "type": "Feature",
  "properties": {
    "gn:admin1_code":"83",
    "gn:admin2_code":"5064.0",
    "gn:admin3_code":"506479.0",
    "gn:admin4_code":"50647955.0",
    "gn:asciiname":"Balishahi",
    "gn:country_code":"BD",
    "gn:dem":28,
    "gn:feature_class":"P",
    "gn:feature_code":"PPL",
    "gn:name":"B\u0101lish\u0101hi",
    "gn:population":0,
    "gn:timezone":"Asia/Dhaka",
    "iso:country":"BD",
    "name:ben_x_preferred":[
        "B\u0101lish\u0101hi"
    ],
    "wof:name":"Balishahi",
    "wof:placetype":"locality"
},
  "geometry": {"coordinates":[88.45001999999999,25.01426],"type":"Point"}
}