{
  "type": "Feature",
  "properties": {
    "gn:admin1_code":"83",
    "gn:admin2_code":"5010.0",
    "gn:admin3_code":"501006.0",
    "gn:admin4_code":"50100600.0",
    "gn:asciiname":"Chatni",
    "gn:country_code":"BD",
    "gn:dem":19,
    "gn:feature_class":"P",
    "gn:feature_code":"PPL",
    "gn:name":"Ch\u0101tni",
    "gn:population":0,
    "gn:timezone":"Asia/Dhaka",
    "iso:country":"BD",
    "name:ben_x_preferred":[
        "Ch\u0101tni"
    ],
    "name:und_x_variant":[
        "Chhatni"
    ],
    "wof:name":"Chatni",
    "wof:placetype":"locality"
},
  "geometry": {"coordinates":[88.97995999999998,24.76607000000001],"type":"Point"}
}