{
  "type": "Feature",
  "properties": {
    "gn:admin1_code":"84",
    "gn:admin2_code":"2022.0",
    "gn:admin3_code":"202249.0",
    "gn:admin4_code":"20224935.0",
    "gn:asciiname":"Mudir Chara",
    "gn:country_code":"BD",
    "gn:dem":3,
    "gn:feature_class":"P",
    "gn:feature_code":"PPL",
    "gn:name":"Mudir Ch\u0101ra",
    "gn:population":0,
    "gn:timezone":"Asia/Dhaka",
    "iso:country":"BD",
    "name:ben_x_preferred":[
        "Mudir Ch\u0101ra"
    ],
    "name:ben_x_variant":[
        "Mudirchhara"
    ],
    "wof:name":"Mudir Chara",
    "wof:placetype":"locality"
},
  "geometry": {"coordinates":[91.97806,21.54306],"type":"Point"}
}