{
  "type": "Feature",
  "properties": {
    "gn:admin1_code":"84",
    "gn:admin2_code":"2022.0",
    "gn:admin3_code":"202216.0",
    "gn:admin4_code":"20221616.0",
    "gn:asciiname":"Paharchanda",
    "gn:country_code":"BD",
    "gn:dem":8,
    "gn:feature_class":"P",
    "gn:feature_code":"PPL",
    "gn:name":"Pah\u0101rch\u0101nda",
    "gn:population":0,
    "gn:timezone":"Asia/Dhaka",
    "iso:country":"BD",
    "name:ben_x_preferred":[
        "Pah\u0101rch\u0101nda"
    ],
    "wof:name":"Paharchanda",
    "wof:placetype":"locality"
},
  "geometry": {"coordinates":[92.02773999999999,21.81237],"type":"Point"}
}