{
  "type": "Feature",
  "properties": {
    "gn:admin1_code":"83",
    "gn:admin2_code":"5069",
    "gn:admin3_code":"506963.0",
    "gn:admin4_code":"50696387.0",
    "gn:asciiname":"Kholabaria",
    "gn:country_code":"BD",
    "gn:dem":17,
    "gn:feature_class":"P",
    "gn:feature_code":"PPL",
    "gn:name":"Khol\u0101b\u0101ria",
    "gn:population":0,
    "gn:timezone":"Asia/Dhaka",
    "iso:country":"BD",
    "wof:name":"Kholabaria",
    "wof:placetype":"locality"
},
  "geometry": {"coordinates":[89.00923,24.51569],"type":"Point"}
}