{
  "type": "Feature",
  "properties": {
    "gn:admin1_code":"81",
    "gn:admin2_code":"3082.0",
    "gn:admin3_code":"308207.0",
    "gn:admin4_code":"30820757.0",
    "gn:asciiname":"Gupta Lakshmandia",
    "gn:cc2":"BD",
    "gn:country_code":"BD",
    "gn:dem":7,
    "gn:feature_class":"P",
    "gn:feature_code":"PPL",
    "gn:name":"Gupta Lakshmandia",
    "gn:population":0,
    "gn:timezone":"Asia/Dhaka",
    "iso:country":"BD",
    "name:und_x_variant":[
        "Gupta Lakhandia",
        "Gupta Lakshmandia"
    ],
    "wof:name":"Gupta Lakshmandia",
    "wof:placetype":"locality"
},
  "geometry": {"coordinates":[89.63333,23.61667000000001],"type":"Point"}
}