{
  "type": "Feature",
  "properties": {
    "gn:admin1_code":"83",
    "gn:admin2_code":"5064",
    "gn:admin3_code":"506460.0",
    "gn:admin4_code":"50646065.0",
    "gn:asciiname":"Kujagari",
    "gn:country_code":"BD",
    "gn:dem":18,
    "gn:feature_class":"P",
    "gn:feature_code":"PPL",
    "gn:name":"Kuj\u0101g\u0101ri",
    "gn:population":0,
    "gn:timezone":"Asia/Dhaka",
    "iso:country":"BD",
    "name:ben_x_preferred":[
        "Kuj\u0101g\u0101ri"
    ],
    "wof:name":"Kujagari",
    "wof:placetype":"locality"
},
  "geometry": {"coordinates":[88.82987,24.74245],"type":"Point"}
}