{
  "type": "Feature",
  "properties": {
    "gn:admin1_code":"82",
    "gn:admin2_code":"4087",
    "gn:admin3_code":"408747.0",
    "gn:admin4_code":"40874715.0",
    "gn:asciiname":"Mukunda Madhusudanpur",
    "gn:country_code":"BD",
    "gn:dem":4,
    "gn:feature_class":"P",
    "gn:feature_code":"PPL",
    "gn:name":"Mukunda Madhusudanpur",
    "gn:population":0,
    "gn:timezone":"Asia/Dhaka",
    "iso:country":"BD",
    "wof:name":"Mukunda Madhusudanpur",
    "wof:placetype":"locality"
},
  "geometry": {"coordinates":[89.11667,22.43333],"type":"Point"}
}