{
  "type": "Feature",
  "properties": {
    "gn:admin1_code":"82",
    "gn:admin2_code":"4057.0",
    "gn:admin3_code":"405760.0",
    "gn:admin4_code":"40576028.0",
    "gn:asciiname":"Hatishala",
    "gn:country_code":"BD",
    "gn:dem":27,
    "gn:feature_class":"P",
    "gn:feature_code":"PPL",
    "gn:name":"H\u0101tish\u0101la",
    "gn:population":0,
    "gn:timezone":"Asia/Dhaka",
    "iso:country":"BD",
    "name:ben_x_preferred":[
        "H\u0101tish\u0101la"
    ],
    "wof:name":"Hatishala",
    "wof:placetype":"locality"
},
  "geometry": {"coordinates":[88.61492,23.64743],"type":"Point"}
}