{
  "type": "Feature",
  "properties": {
    "gn:admin1_code":"82",
    "gn:admin2_code":"4087",
    "gn:admin3_code":"408786.0",
    "gn:admin4_code":"40878694.0",
    "gn:asciiname":"Kalyan",
    "gn:country_code":"BD",
    "gn:dem":2,
    "gn:feature_class":"P",
    "gn:feature_code":"PPL",
    "gn:name":"Kalyan",
    "gn:population":0,
    "gn:timezone":"Asia/Dhaka",
    "iso:country":"BD",
    "name:ben_x_preferred":[
        "Kalyan"
    ],
    "wof:name":"Kalyan",
    "wof:placetype":"locality"
},
  "geometry": {"coordinates":[89.07529,22.32762],"type":"Point"}
}