{
  "type": "Feature",
  "properties": {
    "gn:admin1_code":"82",
    "gn:admin2_code":"4087",
    "gn:admin3_code":"408786.0",
    "gn:admin4_code":"40878694.0",
    "gn:asciiname":"Kalyan",
    "gn:country_code":"BD",
    "gn:dem":2,
    "gn:feature_class":"P",
    "gn:feature_code":"PPL",
    "gn:name":"Kalyan",
    "gn:population":0,
    "gn:timezone":"Asia/Dhaka",
    "iso:country":"BD",
    "name:bel_x_preferred":[
        "\u041a\u0430\u043b\u044c\u044f\u043d"
    ],
    "name:ben_x_preferred":[
        "Kalyan"
    ],
    "name:ben_x_variant":[
        "\u0995\u09b2\u09cd\u09af\u09be\u09a8-\u09a6\u09cb\u09ae\u09cd\u09ac\u09bf\u0993\u09af\u09bc\u09be\u09b2\u09bf"
    ],
    "name:cat_x_preferred":[
        "Kalyan"
    ],
    "name:ceb_x_preferred":[
        "Kaly\u0101n"
    ],
    "name:che_x_preferred":[
        "\u041a\u0430\u043b\u044c\u044f\u043d"
    ],
    "name:fas_x_preferred":[
        "\u06a9\u0627\u0644\u06cc\u0627\u0646"
    ],
    "name:fin_x_preferred":[
        "Kalyan"
    ],
    "name:fra_x_preferred":[
        "Kalyan"
    ],
    "name:hin_x_preferred":[
        "\u0915\u0932\u094d\u092f\u093e\u0923"
    ],
    "name:ita_x_preferred":[
        "Kalyan"
    ],
    "name:jpn_x_preferred":[
        "\u30ab\u30ea\u30e4\u30fc\u30f3"
    ],
    "name:kan_x_preferred":[
        "\u0c95\u0cb2\u0ccd\u0caf\u0cbe\u0ca3\u0ccd"
    ],
    "name:kir_x_preferred":[
        "\u041a\u0430\u043b\u044c\u044f\u043d"
    ],
    "name:kor_x_preferred":[
        "\uce7c\ub9ac\uc548"
    ],
    "name:lit_x_preferred":[
        "Kaljanas"
    ],
    "name:mal_x_preferred":[
        "\u0d15\u0d32\u0d4d\u0d2f\u0d3e\u0d7a"
    ],
    "name:mar_x_preferred":[
        "\u0915\u0932\u094d\u092f\u093e\u0923"
    ],
    "name:new_x_preferred":[
        "\u0915\u0932\u094d\u092f\u093e\u0928"
    ],
    "name:por_x_preferred":[
        "Kalyan"
    ],
    "name:rus_x_preferred":[
        "\u041a\u0430\u043b\u044c\u044f\u043d"
    ],
    "name:swe_x_preferred":[
        "Kalyan"
    ],
    "name:urd_x_preferred":[
        "\u06a9\u0644\u06cc\u0627\u0646"
    ],
    "name:vie_x_preferred":[
        "Kalyan"
    ],
    "name:war_x_preferred":[
        "Kalyan"
    ],
    "wof:name":"Kalyan",
    "wof:placetype":"locality"
},
  "geometry": {"coordinates":[89.07529,22.32762],"type":"Point"}
}