{
  "type": "Feature",
  "properties": {
    "gn:admin1_code":"81",
    "gn:admin2_code":"3093",
    "gn:admin3_code":"309328.0",
    "gn:admin4_code":"30932851.0",
    "gn:asciiname":"Manaji",
    "gn:country_code":"BD",
    "gn:dem":18,
    "gn:feature_class":"P",
    "gn:feature_code":"PPL",
    "gn:name":"Man\u0101ji",
    "gn:population":0,
    "gn:timezone":"Asia/Dhaka",
    "iso:country":"BD",
    "wof:name":"Manaji",
    "wof:placetype":"locality"
},
  "geometry": {"coordinates":[90.02124999999999,24.44144],"type":"Point"}
}