{
  "type": "Feature",
  "properties": {
    "gn:admin1_code":"83",
    "gn:admin2_code":"5064.0",
    "gn:admin3_code":"506450.0",
    "gn:admin4_code":"50645057.0",
    "gn:asciiname":"Debipur",
    "gn:country_code":"BD",
    "gn:dem":22,
    "gn:feature_class":"P",
    "gn:feature_code":"PPL",
    "gn:name":"Debipur",
    "gn:population":0,
    "gn:timezone":"Asia/Dhaka",
    "iso:country":"BD",
    "name:ben_x_preferred":[
        "Debipur"
    ],
    "wof:name":"Debipur",
    "wof:placetype":"locality"
},
  "geometry": {"coordinates":[88.71715999999998,24.93468],"type":"Point"}
}