{
  "type": "Feature",
  "properties": {
    "gn:admin1_code":"81",
    "gn:admin2_code":"3093",
    "gn:admin3_code":"309385.0",
    "gn:admin4_code":"30938513.0",
    "gn:asciiname":"Salgrampur",
    "gn:country_code":"BD",
    "gn:dem":17,
    "gn:feature_class":"P",
    "gn:feature_code":"PPL",
    "gn:name":"S\u0101lgr\u0101mpur",
    "gn:population":0,
    "gn:timezone":"Asia/Dhaka",
    "iso:country":"BD",
    "wof:name":"Salgrampur",
    "wof:placetype":"locality"
},
  "geometry": {"coordinates":[90.11667,24.31667],"type":"Point"}
}