{
  "type": "Feature",
  "properties": {
    "gn:admin1_code":"H",
    "gn:admin2_code":"3072",
    "gn:admin3_code":"307238.0",
    "gn:admin4_code":"30723867.0",
    "gn:asciiname":"Jagannathpur",
    "gn:country_code":"BD",
    "gn:dem":14,
    "gn:feature_class":"P",
    "gn:feature_code":"PPL",
    "gn:name":"Jagann\u0101thpur",
    "gn:population":0,
    "gn:timezone":"Asia/Dhaka",
    "iso:country":"BD",
    "wof:name":"Jagannathpur",
    "wof:placetype":"locality"
},
  "geometry": {"coordinates":[91.07942,24.70652],"type":"Point"}
}