{
  "type": "Feature",
  "properties": {
    "gn:admin1_code":"87",
    "gn:admin2_code":"5585",
    "gn:admin3_code":"558573.0",
    "gn:admin4_code":"55857328.0",
    "gn:asciiname":"Itakumari",
    "gn:country_code":"BD",
    "gn:dem":31,
    "gn:feature_class":"P",
    "gn:feature_code":"PPL",
    "gn:name":"Itakum\u0101ri",
    "gn:population":0,
    "gn:timezone":"Asia/Dhaka",
    "iso:country":"BD",
    "name:und_x_variant":[
        "Itakum\u0101ri",
        "It\u0101kum\u0101ri"
    ],
    "wof:name":"Itakumari",
    "wof:placetype":"locality"
},
  "geometry": {"coordinates":[89.39493,25.71195],"type":"Point"}
}