{
  "type": "Feature",
  "properties": {
    "gn:admin1_code":"83",
    "gn:admin2_code":"5070.0",
    "gn:admin3_code":"507056.0",
    "gn:admin4_code":"50705657.0",
    "gn:asciiname":"Dulahar",
    "gn:country_code":"BD",
    "gn:dem":44,
    "gn:feature_class":"P",
    "gn:feature_code":"PPL",
    "gn:name":"Dulah\u0101r",
    "gn:population":0,
    "gn:timezone":"Asia/Dhaka",
    "iso:country":"BD",
    "name:ben_x_preferred":[
        "Dulah\u0101r"
    ],
    "wof:name":"Dulahar",
    "wof:placetype":"locality"
},
  "geometry": {"coordinates":[88.45489999999999,24.74778],"type":"Point"}
}