{
  "type": "Feature",
  "properties": {
    "gn:admin1_code":"84",
    "gn:admin2_code":"2015.0",
    "gn:admin3_code":"201537.0",
    "gn:admin4_code":"20153717.0",
    "gn:asciiname":"Nihaipur",
    "gn:country_code":"BD",
    "gn:dem":8,
    "gn:feature_class":"P",
    "gn:feature_code":"PPL",
    "gn:name":"Nih\u0101ipur",
    "gn:population":0,
    "gn:timezone":"Asia/Dhaka",
    "iso:country":"BD",
    "name:ben_x_preferred":[
        "Nih\u0101ipur"
    ],
    "wof:name":"Nihaipur",
    "wof:placetype":"locality"
},
  "geometry": {"coordinates":[91.82590999999999,22.46046],"type":"Point"}
}