{
  "type": "Feature",
  "properties": {
    "gn:admin1_code":"81",
    "gn:admin2_code":"3048.0",
    "gn:admin3_code":"304842.0",
    "gn:admin4_code":"30484243.0",
    "gn:asciiname":"Bade Srirampur",
    "gn:country_code":"BD",
    "gn:dem":14,
    "gn:feature_class":"P",
    "gn:feature_code":"PPL",
    "gn:name":"B\u0101de Sr\u012br\u0101mpur",
    "gn:population":0,
    "gn:timezone":"Asia/Dhaka",
    "iso:country":"BD",
    "wof:name":"Bade Srirampur",
    "wof:placetype":"locality"
},
  "geometry": {"coordinates":[90.84141,24.44417],"type":"Point"}
}