{
  "type": "Feature",
  "properties": {
    "gn:admin1_code":"87",
    "gn:admin2_code":"5585",
    "gn:admin3_code":"558573.0",
    "gn:admin4_code":"55857309.0",
    "gn:asciiname":"Pratap Jaysen",
    "gn:country_code":"BD",
    "gn:dem":31,
    "gn:feature_class":"P",
    "gn:feature_code":"PPL",
    "gn:name":"Prat\u0101p Jaysen",
    "gn:population":0,
    "gn:timezone":"Asia/Dhaka",
    "iso:country":"BD",
    "wof:name":"Pratap Jaysen",
    "wof:placetype":"locality"
},
  "geometry": {"coordinates":[89.45365,25.69998],"type":"Point"}
}