{
  "type": "Feature",
  "properties": {
    "gn:admin1_code":"84",
    "gn:admin2_code":"2022.0",
    "gn:admin3_code":"202224.0",
    "gn:admin4_code":"20222447.0",
    "gn:asciiname":"Matterkul",
    "gn:country_code":"BD",
    "gn:dem":7,
    "gn:feature_class":"P",
    "gn:feature_code":"PPL",
    "gn:name":"Matterkul",
    "gn:population":0,
    "gn:timezone":"Asia/Dhaka",
    "iso:country":"BD",
    "name:ben_x_preferred":[
        "Matterkul"
    ],
    "wof:name":"Matterkul",
    "wof:placetype":"locality"
},
  "geometry": {"coordinates":[92.04785,21.42807],"type":"Point"}
}