{
  "type": "Feature",
  "properties": {
    "gn:admin1_code":"81",
    "gn:admin2_code":"3093",
    "gn:admin3_code":"309366.0",
    "gn:admin4_code":"30936671.0",
    "gn:asciiname":"Mahera",
    "gn:country_code":"BD",
    "gn:dem":15,
    "gn:feature_class":"P",
    "gn:feature_code":"PPL",
    "gn:name":"Mahera",
    "gn:population":0,
    "gn:timezone":"Asia/Dhaka",
    "iso:country":"BD",
    "wof:name":"Mahera",
    "wof:placetype":"locality"
},
  "geometry": {"coordinates":[90.0309,24.1637],"type":"Point"}
}