{
  "type": "Feature",
  "properties": {
    "gn:admin1_code":"84",
    "gn:admin2_code":"2013",
    "gn:admin3_code":"201345.0",
    "gn:admin4_code":"20134571.0",
    "gn:asciiname":"Saichakhali",
    "gn:country_code":"BD",
    "gn:dem":11,
    "gn:feature_class":"P",
    "gn:feature_code":"PPL",
    "gn:name":"S\u0101ich\u0101kh\u0101li",
    "gn:population":0,
    "gn:timezone":"Asia/Dhaka",
    "iso:country":"BD",
    "name:und_x_variant":[
        "S\u0101ich\u0101kh\u0101li",
        "S\u0101chi\u0101kh\u0101li"
    ],
    "wof:name":"Saichakhali",
    "wof:placetype":"locality"
},
  "geometry": {"coordinates":[90.77491999999999,23.15547],"type":"Point"}
}