{
  "type": "Feature",
  "properties": {
    "gn:admin1_code":"H",
    "gn:admin2_code":"3072.0",
    "gn:admin3_code":"307209.0",
    "gn:admin4_code":"30720911.0",
    "gn:asciiname":"Gulia",
    "gn:country_code":"BD",
    "gn:dem":13,
    "gn:feature_class":"P",
    "gn:feature_code":"PPL",
    "gn:name":"Gulia",
    "gn:population":0,
    "gn:timezone":"Asia/Dhaka",
    "iso:country":"BD",
    "name:ceb_x_preferred":[
        "Gulia"
    ],
    "name:deu_x_preferred":[
        "Gulia"
    ],
    "name:hin_x_preferred":[
        "\u0917\u0941\u0932\u093f\u092f\u093e"
    ],
    "name:ron_x_preferred":[
        "Gulia"
    ],
    "name:srp_x_preferred":[
        "\u0413\u0443\u043b\u0438\u0458\u0430"
    ],
    "wof:name":"Gulia",
    "wof:placetype":"locality"
},
  "geometry": {"coordinates":[90.89691000000001,24.91673],"type":"Point"}
}