{
  "type": "Feature",
  "properties": {
    "gn:admin1_code":"82",
    "gn:admin2_code":"4041.0",
    "gn:admin3_code":"404190.0",
    "gn:admin4_code":"40419034.0",
    "gn:asciiname":"Sibbas",
    "gn:country_code":"BD",
    "gn:dem":13,
    "gn:feature_class":"P",
    "gn:feature_code":"PPL",
    "gn:name":"Sibb\u0101s",
    "gn:population":0,
    "gn:timezone":"Asia/Dhaka",
    "iso:country":"BD",
    "name:ben_x_preferred":[
        "Sibb\u0101s"
    ],
    "wof:name":"Sibbas",
    "wof:placetype":"locality"
},
  "geometry": {"coordinates":[88.95352,23.17264],"type":"Point"}
}