{
  "type": "Feature",
  "properties": {
    "gn:admin1_code":"83",
    "gn:admin2_code":"5064.0",
    "gn:admin3_code":"506486.0",
    "gn:admin4_code":"50648607.0",
    "gn:asciiname":"Rasulpur",
    "gn:country_code":"BD",
    "gn:dem":34,
    "gn:feature_class":"P",
    "gn:feature_code":"PPL",
    "gn:name":"Rasulpur",
    "gn:population":0,
    "gn:timezone":"Asia/Dhaka",
    "iso:country":"BD",
    "name:ben_x_preferred":[
        "Rasulpur"
    ],
    "wof:name":"Rasulpur",
    "wof:placetype":"locality"
},
  "geometry": {"coordinates":[88.49218,25.19987],"type":"Point"}
}