{
  "type": "Feature",
  "properties": {
    "gn:admin1_code":"82",
    "gn:admin2_code":"4087.0",
    "gn:admin3_code":"408747.0",
    "gn:admin4_code":"40874755.0",
    "gn:asciiname":"Gobindapur Bara",
    "gn:country_code":"BD",
    "gn:dem":10,
    "gn:feature_class":"P",
    "gn:feature_code":"PPL",
    "gn:name":"Gobindapur Bara",
    "gn:population":0,
    "gn:timezone":"Asia/Dhaka",
    "iso:country":"BD",
    "wof:name":"Gobindapur Bara",
    "wof:placetype":"locality"
},
  "geometry": {"coordinates":[89.07054000000002,22.43078],"type":"Point"}
}