{
  "type": "Feature",
  "properties": {
    "gn:admin1_code":"87",
    "gn:admin2_code":"5527.0",
    "gn:admin3_code":"552717.0",
    "gn:admin4_code":"55271766.0",
    "gn:asciiname":"Dohagram",
    "gn:country_code":"BD",
    "gn:dem":42,
    "gn:feature_class":"P",
    "gn:feature_code":"PPL",
    "gn:name":"Doh\u0101gr\u0101m",
    "gn:population":0,
    "gn:timezone":"Asia/Dhaka",
    "iso:country":"BD",
    "name:ben_x_preferred":[
        "Doh\u0101gr\u0101m"
    ],
    "wof:name":"Dohagram",
    "wof:placetype":"locality"
},
  "geometry": {"coordinates":[88.60814000000001,25.69403],"type":"Point"}
}