{
  "type": "Feature",
  "properties": {
    "gn:admin1_code":"84",
    "gn:admin2_code":"2022.0",
    "gn:admin3_code":"202224.0",
    "gn:admin4_code":"20222483.0",
    "gn:asciiname":"Gomatali",
    "gn:country_code":"BD",
    "gn:dem":3,
    "gn:feature_class":"P",
    "gn:feature_code":"PPL",
    "gn:name":"Gom\u0101tali",
    "gn:population":0,
    "gn:timezone":"Asia/Dhaka",
    "iso:country":"BD",
    "name:ben_x_preferred":[
        "Gom\u0101tali"
    ],
    "wof:name":"Gomatali",
    "wof:placetype":"locality"
},
  "geometry": {"coordinates":[92.01040999999999,21.58239],"type":"Point"}
}