{
  "type": "Feature",
  "properties": {
    "gn:admin1_code":"H",
    "gn:admin2_code":"3072.0",
    "gn:admin3_code":"307209.0",
    "gn:admin4_code":"30720947.0",
    "gn:asciiname":"Bamangaon",
    "gn:country_code":"BD",
    "gn:dem":16,
    "gn:feature_class":"P",
    "gn:feature_code":"PPL",
    "gn:name":"B\u0101mangaon",
    "gn:population":0,
    "gn:timezone":"Asia/Dhaka",
    "iso:country":"BD",
    "wof:name":"Bamangaon",
    "wof:placetype":"locality"
},
  "geometry": {"coordinates":[90.94506,24.94155],"type":"Point"}
}