{
  "type": "Feature",
  "properties": {
    "gn:admin1_code":"81",
    "gn:admin2_code":"3093.0",
    "gn:admin3_code":"309376.0",
    "gn:admin4_code":"30937607.0",
    "gn:asciiname":"Arra Kumed",
    "gn:country_code":"BD",
    "gn:dem":14,
    "gn:feature_class":"P",
    "gn:feature_code":"PPL",
    "gn:name":"\u0100rra Kumed",
    "gn:population":0,
    "gn:timezone":"Asia/Dhaka",
    "iso:country":"BD",
    "wof:name":"Arra Kumed",
    "wof:placetype":"locality"
},
  "geometry": {"coordinates":[89.85183000000001,23.98706],"type":"Point"}
}