{
  "type": "Feature",
  "properties": {
    "gn:admin1_code":"83",
    "gn:admin2_code":"5064.0",
    "gn:admin3_code":"506428.0",
    "gn:admin4_code":"50642821.0",
    "gn:asciiname":"Kajalgram",
    "gn:country_code":"BD",
    "gn:dem":28,
    "gn:feature_class":"P",
    "gn:feature_code":"PPL",
    "gn:name":"K\u0101jalgr\u0101m",
    "gn:population":0,
    "gn:timezone":"Asia/Dhaka",
    "iso:country":"BD",
    "name:ben_x_preferred":[
        "K\u0101jalgr\u0101m"
    ],
    "wof:name":"Kajalgram",
    "wof:placetype":"locality"
},
  "geometry": {"coordinates":[88.77676,25.1549],"type":"Point"}
}