{
  "type": "Feature",
  "properties": {
    "gn:admin1_code":"87",
    "gn:admin2_code":"5527.0",
    "gn:admin3_code":"552756.0",
    "gn:admin4_code":"55275647.0",
    "gn:asciiname":"Joyrampur",
    "gn:country_code":"BD",
    "gn:dem":45,
    "gn:feature_class":"P",
    "gn:feature_code":"PPL",
    "gn:name":"Joyr\u0101mpur",
    "gn:population":0,
    "gn:timezone":"Asia/Dhaka",
    "iso:country":"BD",
    "name:ben_x_preferred":[
        "Joyr\u0101mpur"
    ],
    "wof:name":"Joyrampur",
    "wof:placetype":"locality"
},
  "geometry": {"coordinates":[88.60540999999998,25.78372],"type":"Point"}
}