{
  "type": "Feature",
  "properties": {
    "gn:admin1_code":"82",
    "gn:asciiname":"Bazarkhali",
    "gn:country_code":"BD",
    "gn:dem":8,
    "gn:feature_class":"P",
    "gn:feature_code":"PPL",
    "gn:name":"B\u0101z\u0101rkh\u0101li",
    "gn:population":0,
    "gn:timezone":"Asia/Dhaka",
    "iso:country":"BD",
    "name:ben_x_preferred":[
        "B\u0101z\u0101rkh\u0101li"
    ],
    "wof:name":"Bazarkhali",
    "wof:placetype":"locality"
},
  "geometry": {"coordinates":[90.25505,22.19809],"type":"Point"}
}