{
  "type": "Feature",
  "properties": {
    "gn:admin1_code":"83",
    "gn:admin2_code":"5070.0",
    "gn:admin3_code":"507066.0",
    "gn:admin4_code":"50706639.0",
    "gn:asciiname":"Das Rasia",
    "gn:country_code":"BD",
    "gn:dem":26,
    "gn:feature_class":"P",
    "gn:feature_code":"PPL",
    "gn:name":"Das Rasia",
    "gn:population":0,
    "gn:timezone":"Asia/Dhaka",
    "iso:country":"BD",
    "wof:name":"Das Rasia",
    "wof:placetype":"locality"
},
  "geometry": {"coordinates":[88.25376,24.54368],"type":"Point"}
}