{
  "type": "Feature",
  "properties": {
    "gn:admin1_code":"81",
    "gn:admin2_code":"3086",
    "gn:admin3_code":"308669.0",
    "gn:admin4_code":"30866947.0",
    "gn:asciiname":"Mankala",
    "gn:country_code":"BD",
    "gn:dem":9,
    "gn:feature_class":"P",
    "gn:feature_code":"PPL",
    "gn:name":"Mankala",
    "gn:population":0,
    "gn:timezone":"Asia/Dhaka",
    "iso:country":"BD",
    "name:und_x_variant":[
        "Mankata",
        "Mankala"
    ],
    "wof:name":"Mankala",
    "wof:placetype":"locality"
},
  "geometry": {"coordinates":[90.31034,23.20625],"type":"Point"}
}