{
  "type": "Feature",
  "properties": {
    "gn:admin1_code":"83",
    "gn:admin2_code":"5064.0",
    "gn:admin3_code":"506475.0",
    "gn:admin4_code":"50647534.0",
    "gn:asciiname":"Baghmar",
    "gn:country_code":"BD",
    "gn:dem":26,
    "gn:feature_class":"P",
    "gn:feature_code":"PPL",
    "gn:name":"B\u0101ghm\u0101r",
    "gn:population":0,
    "gn:timezone":"Asia/Dhaka",
    "iso:country":"BD",
    "name:ben_x_preferred":[
        "B\u0101ghm\u0101r"
    ],
    "name:ben_x_variant":[
        "Bagm\u0101r"
    ],
    "wof:name":"Baghmar",
    "wof:placetype":"locality"
},
  "geometry": {"coordinates":[88.78990999999998,25.02678],"type":"Point"}
}