{
  "type": "Feature",
  "properties": {
    "gn:admin1_code":"81",
    "gn:admin2_code":"3048.0",
    "gn:admin3_code":"304879.0",
    "gn:admin4_code":"30487928.0",
    "gn:asciiname":"Char Terateki",
    "gn:country_code":"BD",
    "gn:dem":14,
    "gn:feature_class":"P",
    "gn:feature_code":"PPL",
    "gn:name":"Char Ter\u0101teki",
    "gn:population":0,
    "gn:timezone":"Asia/Dhaka",
    "iso:country":"BD",
    "wof:name":"Char Terateki",
    "wof:placetype":"locality"
},
  "geometry": {"coordinates":[90.64462,24.3345],"type":"Point"}
}