{
  "type": "Feature",
  "properties": {
    "gn:admin1_code":"83",
    "gn:admin2_code":"5010.0",
    "gn:admin3_code":"501020.0",
    "gn:admin4_code":"50102034.0",
    "gn:asciiname":"Barbakpur",
    "gn:country_code":"BD",
    "gn:dem":23,
    "gn:feature_class":"P",
    "gn:feature_code":"PPL",
    "gn:name":"B\u0101rb\u0101kpur",
    "gn:population":0,
    "gn:timezone":"Asia/Dhaka",
    "iso:country":"BD",
    "wof:name":"Barbakpur",
    "wof:placetype":"locality"
},
  "geometry": {"coordinates":[89.35358000000002,24.90718],"type":"Point"}
}