{
  "type": "Feature",
  "properties": {
    "gn:admin1_code":"82",
    "gn:admin2_code":"4087",
    "gn:admin3_code":"408747.0",
    "gn:admin4_code":"40874747.0",
    "gn:asciiname":"Suta",
    "gn:country_code":"BD",
    "gn:dem":6,
    "gn:feature_class":"P",
    "gn:feature_code":"PPL",
    "gn:name":"Suta",
    "gn:population":0,
    "gn:timezone":"Asia/Dhaka",
    "iso:country":"BD",
    "name:ben_x_preferred":[
        "Suta"
    ],
    "name:und_x_variant":[
        "Sota"
    ],
    "wof:name":"Suta",
    "wof:placetype":"locality"
},
  "geometry": {"coordinates":[89.12633000000002,22.37221],"type":"Point"}
}