{
  "type": "Feature",
  "properties": {
    "gn:admin1_code":"87",
    "gn:admin2_code":"5573.0",
    "gn:admin3_code":"557385.0",
    "gn:admin4_code":"55738540.0",
    "gn:asciiname":"Brahmmattar",
    "gn:country_code":"BD",
    "gn:dem":39,
    "gn:feature_class":"P",
    "gn:feature_code":"PPL",
    "gn:name":"Brahmmattar",
    "gn:population":0,
    "gn:timezone":"Asia/Dhaka",
    "iso:country":"BD",
    "name:ben_x_preferred":[
        "Brahmmattar"
    ],
    "name:ben_x_variant":[
        "Brahmottar"
    ],
    "wof:name":"Brahmmattar",
    "wof:placetype":"locality"
},
  "geometry": {"coordinates":[88.93007,25.79395],"type":"Point"}
}