{
  "type": "Feature",
  "properties": {
    "gn:admin1_code":"84",
    "gn:admin2_code":"2015.0",
    "gn:admin3_code":"201504.0",
    "gn:admin4_code":"20150428.0",
    "gn:asciiname":"Barakhain",
    "gn:country_code":"BD",
    "gn:dem":8,
    "gn:feature_class":"P",
    "gn:feature_code":"PPL",
    "gn:name":"B\u0101r\u0101kh\u0101in",
    "gn:population":0,
    "gn:timezone":"Asia/Dhaka",
    "iso:country":"BD",
    "name:ben_x_preferred":[
        "B\u0101r\u0101kh\u0101in"
    ],
    "wof:name":"Barakhain",
    "wof:placetype":"locality"
},
  "geometry": {"coordinates":[91.90937,22.18034],"type":"Point"}
}