{
  "type": "Feature",
  "properties": {
    "gn:admin1_code":"H",
    "gn:admin2_code":"3089",
    "gn:admin3_code":"308970.0",
    "gn:admin4_code":"30897034.0",
    "gn:asciiname":"Baitkamari",
    "gn:country_code":"BD",
    "gn:dem":20,
    "gn:feature_class":"P",
    "gn:feature_code":"PPL",
    "gn:name":"Baitkam\u0101ri",
    "gn:population":0,
    "gn:timezone":"Asia/Dhaka",
    "iso:country":"BD",
    "name:ben_x_preferred":[
        "Baitkam\u0101ri"
    ],
    "wof:name":"Baitkamari",
    "wof:placetype":"locality"
},
  "geometry": {"coordinates":[90.16160000000001,25.03933],"type":"Point"}
}