{
  "type": "Feature",
  "properties": {
    "gn:admin1_code":"87",
    "gn:admin2_code":"5527.0",
    "gn:admin3_code":"552712.0",
    "gn:admin4_code":"55271208.0",
    "gn:asciiname":"Nandagaon",
    "gn:country_code":"BD",
    "gn:dem":50,
    "gn:feature_class":"P",
    "gn:feature_code":"PPL",
    "gn:name":"Nand\u0101gaon",
    "gn:population":0,
    "gn:timezone":"Asia/Dhaka",
    "iso:country":"BD",
    "name:ben_x_preferred":[
        "Nand\u0101gaon"
    ],
    "wof:name":"Nandagaon",
    "wof:placetype":"locality"
},
  "geometry": {"coordinates":[88.57205,25.88963],"type":"Point"}
}