{
  "type": "Feature",
  "properties": {
    "gn:admin1_code":"82",
    "gn:admin2_code":"4041.0",
    "gn:admin3_code":"404147.0",
    "gn:admin4_code":"40414771.0",
    "gn:asciiname":"Nrisinhakati",
    "gn:country_code":"BD",
    "gn:dem":12,
    "gn:feature_class":"P",
    "gn:feature_code":"PPL",
    "gn:name":"Nrisinhak\u0101ti",
    "gn:population":0,
    "gn:timezone":"Asia/Dhaka",
    "iso:country":"BD",
    "name:ben_x_preferred":[
        "Nrisinhak\u0101ti"
    ],
    "wof:name":"Nrisinhakati",
    "wof:placetype":"locality"
},
  "geometry": {"coordinates":[89.30316999999999,23.16784],"type":"Point"}
}