{
  "type": "Feature",
  "properties": {
    "gn:admin1_code":"81",
    "gn:admin2_code":"3026",
    "gn:admin3_code":"302614.0",
    "gn:admin4_code":"30261441.0",
    "gn:asciiname":"Kashtipur",
    "gn:country_code":"BD",
    "gn:dem":16,
    "gn:feature_class":"P",
    "gn:feature_code":"PPL",
    "gn:name":"Kashtipur",
    "gn:population":0,
    "gn:timezone":"Asia/Dhaka",
    "iso:country":"BD",
    "wof:name":"Kashtipur",
    "wof:placetype":"locality"
},
  "geometry": {"coordinates":[90.08767,23.95558],"type":"Point"}
}