{
  "type": "Feature",
  "properties": {
    "gn:admin1_code":"87",
    "gn:admin2_code":"5527",
    "gn:admin3_code":"552769.0",
    "gn:admin4_code":"55276969.0",
    "gn:asciiname":"Khalekpur",
    "gn:country_code":"BD",
    "gn:dem":32,
    "gn:feature_class":"P",
    "gn:feature_code":"PPL",
    "gn:name":"Khalekpur",
    "gn:population":0,
    "gn:timezone":"Asia/Dhaka",
    "iso:country":"BD",
    "name:ben_x_preferred":[
        "Khalekpur"
    ],
    "wof:name":"Khalekpur",
    "wof:placetype":"locality"
},
  "geometry": {"coordinates":[89.07526999999997,25.50711],"type":"Point"}
}