{
  "type": "Feature",
  "properties": {
    "gn:admin1_code":"81",
    "gn:admin2_code":"3067.0",
    "gn:admin3_code":"306702.0",
    "gn:admin4_code":"30670223.0",
    "gn:asciiname":"Bara Manohardi",
    "gn:country_code":"BD",
    "gn:dem":13,
    "gn:feature_class":"P",
    "gn:feature_code":"PPL",
    "gn:name":"Bara Manohardi",
    "gn:population":0,
    "gn:timezone":"Asia/Dhaka",
    "iso:country":"BD",
    "wof:name":"Bara Manohardi",
    "wof:placetype":"locality"
},
  "geometry": {"coordinates":[90.61739,23.78736],"type":"Point"}
}