{
  "type": "Feature",
  "properties": {
    "gn:admin1_code":"83",
    "gn:admin2_code":"5064.0",
    "gn:admin3_code":"506479.0",
    "gn:admin4_code":"50647915.0",
    "gn:asciiname":"Mulukdanga",
    "gn:country_code":"BD",
    "gn:dem":43,
    "gn:feature_class":"P",
    "gn:feature_code":"PPL",
    "gn:name":"Mulukd\u0101nga",
    "gn:population":0,
    "gn:timezone":"Asia/Dhaka",
    "iso:country":"BD",
    "name:ben_x_preferred":[
        "Mulukd\u0101nga"
    ],
    "wof:name":"Mulukdanga",
    "wof:placetype":"locality"
},
  "geometry": {"coordinates":[88.50674000000002,24.93119],"type":"Point"}
}