{
  "type": "Feature",
  "properties": {
    "gn:admin1_code":"87",
    "gn:admin2_code":"5527",
    "gn:admin3_code":"552747.0",
    "gn:admin4_code":"55274713.0",
    "gn:asciiname":"Jot Bashmuri",
    "gn:country_code":"BD",
    "gn:dem":28,
    "gn:feature_class":"P",
    "gn:feature_code":"PPL",
    "gn:name":"Jot Bashmuri",
    "gn:population":0,
    "gn:timezone":"Asia/Dhaka",
    "iso:country":"BD",
    "name:ben_x_preferred":[
        "Jot Bashmuri"
    ],
    "wof:name":"Jot Bashmuri",
    "wof:placetype":"locality"
},
  "geometry": {"coordinates":[89.12584,25.26213],"type":"Point"}
}