{
  "type": "Feature",
  "properties": {
    "gn:admin1_code":"82",
    "gn:admin2_code":"4047.0",
    "gn:admin3_code":"404794.0",
    "gn:admin4_code":"40479467.0",
    "gn:asciiname":"Chagladah",
    "gn:country_code":"BD",
    "gn:dem":6,
    "gn:feature_class":"P",
    "gn:feature_code":"PPL",
    "gn:name":"Chagladah",
    "gn:population":0,
    "gn:timezone":"Asia/Dhaka",
    "iso:country":"BD",
    "name:ben_x_preferred":[
        "Chagladah"
    ],
    "name:ben_x_variant":[
        "Chhagladaha"
    ],
    "wof:name":"Chagladah",
    "wof:placetype":"locality"
},
  "geometry": {"coordinates":[89.68363000000002,22.88668],"type":"Point"}
}