{
  "type": "Feature",
  "properties": {
    "gn:admin1_code":"83",
    "gn:admin2_code":"5070.0",
    "gn:admin3_code":"507066.0",
    "gn:admin4_code":"50706600.0",
    "gn:asciiname":"Balubagan",
    "gn:country_code":"BD",
    "gn:dem":24,
    "gn:feature_class":"P",
    "gn:feature_code":"PPL",
    "gn:name":"B\u0101lub\u0101g\u0101n",
    "gn:population":0,
    "gn:timezone":"Asia/Dhaka",
    "iso:country":"BD",
    "name:ben_x_preferred":[
        "B\u0101lub\u0101g\u0101n"
    ],
    "wof:name":"Balubagan",
    "wof:placetype":"locality"
},
  "geometry": {"coordinates":[88.26694999999999,24.59348],"type":"Point"}
}