{
  "type": "Feature",
  "properties": {
    "gn:admin1_code":"H",
    "gn:admin2_code":"3072",
    "gn:admin3_code":"307204.0",
    "gn:admin4_code":"30720447.0",
    "gn:asciiname":"Nababpur",
    "gn:country_code":"BD",
    "gn:dem":18,
    "gn:feature_class":"P",
    "gn:feature_code":"PPL",
    "gn:name":"Nab\u0101bpur",
    "gn:population":0,
    "gn:timezone":"Asia/Dhaka",
    "iso:country":"BD",
    "wof:name":"Nababpur",
    "wof:placetype":"locality"
},
  "geometry": {"coordinates":[90.82736,24.81186],"type":"Point"}
}