{
  "type": "Feature",
  "properties": {
    "gn:admin1_code":"81",
    "gn:admin2_code":"3056.0",
    "gn:admin3_code":"305670.0",
    "gn:admin4_code":"30567085.0",
    "gn:asciiname":"Gaola",
    "gn:country_code":"BD",
    "gn:dem":14,
    "gn:feature_class":"P",
    "gn:feature_code":"PPL",
    "gn:name":"Gaola",
    "gn:population":0,
    "gn:timezone":"Asia/Dhaka",
    "iso:country":"BD",
    "wof:name":"Gaola",
    "wof:placetype":"locality"
},
  "geometry": {"coordinates":[90.06278,23.94309],"type":"Point"}
}