{
  "type": "Feature",
  "properties": {
    "gn:admin1_code":"81",
    "gn:admin2_code":"3054.0",
    "gn:admin3_code":"305440.0",
    "gn:admin4_code":"30544082.0",
    "gn:asciiname":"Dakhin Takta",
    "gn:country_code":"BD",
    "gn:dem":11,
    "gn:feature_class":"P",
    "gn:feature_code":"PPL",
    "gn:name":"Dakhin Takta",
    "gn:population":0,
    "gn:timezone":"Asia/Dhaka",
    "iso:country":"BD",
    "name:und_x_variant":[
        "Daskhin Takta",
        "Dakshintakta",
        "Dakhin Takta"
    ],
    "wof:name":"Dakhin Takta",
    "wof:placetype":"locality"
},
  "geometry": {"coordinates":[90.26561,23.00263],"type":"Point"}
}