{
  "type": "Feature",
  "properties": {
    "gn:admin1_code":"H",
    "gn:admin2_code":"3061.0",
    "gn:admin3_code":"306181.0",
    "gn:admin4_code":"30618109.0",
    "gn:asciiname":"Dhakirkanda",
    "gn:country_code":"BD",
    "gn:dem":20,
    "gn:feature_class":"P",
    "gn:feature_code":"PPL",
    "gn:name":"Dh\u0101kirk\u0101nda",
    "gn:population":0,
    "gn:timezone":"Asia/Dhaka",
    "iso:country":"BD",
    "name:und_x_variant":[
        "Dhalirkanda",
        "Dh\u0101kirk\u0101nda"
    ],
    "wof:name":"Dhakirkanda",
    "wof:placetype":"locality"
},
  "geometry": {"coordinates":[90.35079,24.85658],"type":"Point"}
}