{
  "type": "Feature",
  "properties": {
    "gn:admin1_code":"83",
    "gn:admin2_code":"5064.0",
    "gn:admin3_code":"506450.0",
    "gn:admin4_code":"50645076.0",
    "gn:asciiname":"Ekdala Gosainpur",
    "gn:country_code":"BD",
    "gn:dem":21,
    "gn:feature_class":"P",
    "gn:feature_code":"PPL",
    "gn:name":"Ekd\u0101la Gos\u0101inpur",
    "gn:population":0,
    "gn:timezone":"Asia/Dhaka",
    "iso:country":"BD",
    "wof:name":"Ekdala Gosainpur",
    "wof:placetype":"locality"
},
  "geometry": {"coordinates":[88.84999999999999,24.95],"type":"Point"}
}