{
  "type": "Feature",
  "properties": {
    "gn:admin1_code":"84",
    "gn:admin2_code":"2075",
    "gn:admin3_code":"207536.0",
    "gn:admin4_code":"20753609.0",
    "gn:asciiname":"Sagaria",
    "gn:country_code":"BD",
    "gn:dem":7,
    "gn:feature_class":"P",
    "gn:feature_code":"PPL",
    "gn:name":"Sagaria",
    "gn:population":0,
    "gn:timezone":"Asia/Dhaka",
    "iso:country":"BD",
    "name:und_x_variant":[
        "Sagardi",
        "Sagaria"
    ],
    "wof:name":"Sagaria",
    "wof:placetype":"locality"
},
  "geometry": {"coordinates":[91.13554000000001,22.19059],"type":"Point"}
}