{
  "type": "Feature",
  "properties": {
    "gn:admin1_code":"82",
    "gn:admin2_code":"4055.0",
    "gn:admin3_code":"405585.0",
    "gn:admin4_code":"40558571.0",
    "gn:asciiname":"Aruakandi",
    "gn:country_code":"BD",
    "gn:dem":14,
    "gn:feature_class":"P",
    "gn:feature_code":"PPL",
    "gn:name":"Aru\u0101k\u0101ndi",
    "gn:population":0,
    "gn:timezone":"Asia/Dhaka",
    "iso:country":"BD",
    "name:ben_x_preferred":[
        "Aru\u0101k\u0101ndi"
    ],
    "wof:name":"Aruakandi",
    "wof:placetype":"locality"
},
  "geometry": {"coordinates":[89.32942,23.31786],"type":"Point"}
}