{
  "type": "Feature",
  "properties": {
    "gn:admin1_code":"83",
    "gn:admin2_code":"5069",
    "gn:admin3_code":"506944.0",
    "gn:admin4_code":"50694466.0",
    "gn:asciiname":"Nurullapur",
    "gn:country_code":"BD",
    "gn:dem":20,
    "gn:feature_class":"P",
    "gn:feature_code":"PPL",
    "gn:name":"Nurull\u0101pur",
    "gn:population":0,
    "gn:timezone":"Asia/Dhaka",
    "iso:country":"BD",
    "name:ben_x_preferred":[
        "Nurull\u0101pur"
    ],
    "wof:name":"Nurullapur",
    "wof:placetype":"locality"
},
  "geometry": {"coordinates":[88.98336999999999,24.17457000000001],"type":"Point"}
}