{
  "type": "Feature",
  "properties": {
    "gn:admin1_code":"82",
    "gn:admin2_code":"4050.0",
    "gn:admin3_code":"405094.0",
    "gn:admin4_code":"40509421.0",
    "gn:asciiname":"Char Khadimpur",
    "gn:country_code":"BD",
    "gn:dem":19,
    "gn:feature_class":"P",
    "gn:feature_code":"PPL",
    "gn:name":"Char Kh\u0101dimpur",
    "gn:population":0,
    "gn:timezone":"Asia/Dhaka",
    "iso:country":"BD",
    "name:ben_x_preferred":[
        "Char Kh\u0101dimpur"
    ],
    "wof:name":"Char Khadimpur",
    "wof:placetype":"locality"
},
  "geometry": {"coordinates":[89.02535,23.98872],"type":"Point"}
}