{
  "type": "Feature",
  "properties": {
    "gn:admin1_code":"85",
    "gn:admin2_code":"1006.0",
    "gn:admin3_code":"100694.0",
    "gn:admin4_code":"10069410.0",
    "gn:asciiname":"Bamrail",
    "gn:country_code":"BD",
    "gn:dem":10,
    "gn:feature_class":"P",
    "gn:feature_code":"PPL",
    "gn:name":"B\u0101mr\u0101il",
    "gn:population":0,
    "gn:timezone":"Asia/Dhaka",
    "iso:country":"BD",
    "name:und_x_variant":[
        "B\u0101mr\u0101il"
    ],
    "wof:name":"Bamrail",
    "wof:placetype":"locality"
},
  "geometry": {"coordinates":[90.2647,22.89425],"type":"Point"}
}