{
  "type": "Feature",
  "properties": {
    "gn:admin1_code":"85",
    "gn:admin2_code":"1078.0",
    "gn:admin3_code":"107838.0",
    "gn:admin4_code":"10783865.0",
    "gn:asciiname":"Birpasha",
    "gn:country_code":"BD",
    "gn:dem":9,
    "gn:feature_class":"P",
    "gn:feature_code":"PPL",
    "gn:name":"Birp\u0101sha",
    "gn:population":0,
    "gn:timezone":"Asia/Dhaka",
    "iso:country":"BD",
    "name:ben_x_preferred":[
        "Birp\u0101sha"
    ],
    "wof:name":"Birpasha",
    "wof:placetype":"locality"
},
  "geometry": {"coordinates":[90.50355,22.45105],"type":"Point"}
}