{
  "type": "Feature",
  "properties": {
    "gn:admin1_code":"82",
    "gn:admin2_code":"4050.0",
    "gn:admin3_code":"405094.0",
    "gn:admin4_code":"40509429.0",
    "gn:asciiname":"Simulia Gaurdaha",
    "gn:country_code":"BD",
    "gn:dem":17,
    "gn:feature_class":"P",
    "gn:feature_code":"PPL",
    "gn:name":"Simulia Gaurdaha",
    "gn:population":0,
    "gn:timezone":"Asia/Dhaka",
    "iso:country":"BD",
    "name:ben_x_preferred":[
        "Simulia Gaurdaha"
    ],
    "name:ben_x_variant":[
        "Gaurdaha"
    ],
    "name:und_x_variant":[
        "Gordaha"
    ],
    "wof:name":"Simulia Gaurdaha",
    "wof:placetype":"locality"
},
  "geometry": {"coordinates":[89.02585999999999,23.91925],"type":"Point"}
}