{
  "type": "Feature",
  "properties": {
    "gn:admin1_code":"81",
    "gn:admin2_code":"3093.0",
    "gn:admin3_code":"309376.0",
    "gn:admin4_code":"30937621.0",
    "gn:asciiname":"Gotabag",
    "gn:country_code":"BD",
    "gn:dem":12,
    "gn:feature_class":"P",
    "gn:feature_code":"PPL",
    "gn:name":"Got\u0101b\u0101g",
    "gn:population":0,
    "gn:timezone":"Asia/Dhaka",
    "iso:country":"BD",
    "wof:name":"Gotabag",
    "wof:placetype":"locality"
},
  "geometry": {"coordinates":[89.8096,23.98072],"type":"Point"}
}