{
  "type": "Feature",
  "properties": {
    "gn:admin1_code":"83",
    "gn:admin2_code":"5064.0",
    "gn:admin3_code":"506469.0",
    "gn:admin4_code":"50646963.0",
    "gn:asciiname":"Kakoil",
    "gn:country_code":"BD",
    "gn:dem":38,
    "gn:feature_class":"P",
    "gn:feature_code":"PPL",
    "gn:name":"Kakoil",
    "gn:population":0,
    "gn:timezone":"Asia/Dhaka",
    "iso:country":"BD",
    "name:ben_x_preferred":[
        "Kakoil"
    ],
    "wof:name":"Kakoil",
    "wof:placetype":"locality"
},
  "geometry": {"coordinates":[88.48279000000002,24.79733],"type":"Point"}
}