{
  "type": "Feature",
  "properties": {
    "gn:admin1_code":"87",
    "gn:admin2_code":"5573.0",
    "gn:admin3_code":"557345.0",
    "gn:admin4_code":"55734517.0",
    "gn:asciiname":"Nayankhal",
    "gn:country_code":"BD",
    "gn:dem":45,
    "gn:feature_class":"P",
    "gn:feature_code":"PPL",
    "gn:name":"Nayankh\u0101l",
    "gn:population":0,
    "gn:timezone":"Asia/Dhaka",
    "iso:country":"BD",
    "name:ben_x_preferred":[
        "Nayankh\u0101l"
    ],
    "wof:name":"Nayankhal",
    "wof:placetype":"locality"
},
  "geometry": {"coordinates":[88.98180000000001,25.86517000000001],"type":"Point"}
}