{
  "type": "Feature",
  "properties": {
    "gn:admin1_code":"84",
    "gn:admin2_code":"2051",
    "gn:admin3_code":"205165.0",
    "gn:admin4_code":"20516566.0",
    "gn:asciiname":"Paniala",
    "gn:country_code":"BD",
    "gn:dem":11,
    "gn:feature_class":"P",
    "gn:feature_code":"PPL",
    "gn:name":"P\u0101ni\u0101la",
    "gn:population":0,
    "gn:timezone":"Asia/Dhaka",
    "iso:country":"BD",
    "name:urd_x_preferred":[
        "\u067e\u0646\u06cc\u0627\u0644\u06c1"
    ],
    "wof:name":"Paniala",
    "wof:placetype":"locality"
},
  "geometry": {"coordinates":[90.90886999999999,23.13407],"type":"Point"}
}