{
  "type": "Feature",
  "properties": {
    "gn:admin1_code":"87",
    "gn:admin2_code":"5552.0",
    "gn:admin3_code":"555270.0",
    "gn:admin4_code":"55527027.0",
    "gn:asciiname":"Nazirgumani",
    "gn:country_code":"BD",
    "gn:dem":62,
    "gn:feature_class":"P",
    "gn:feature_code":"PPL",
    "gn:name":"N\u0101zirgum\u0101ni",
    "gn:population":0,
    "gn:timezone":"Asia/Dhaka",
    "iso:country":"BD",
    "name:ben_x_preferred":[
        "N\u0101zirgum\u0101ni"
    ],
    "wof:name":"Nazirgumani",
    "wof:placetype":"locality"
},
  "geometry": {"coordinates":[89.09166999999999,26.35626],"type":"Point"}
}