{
  "type": "Feature",
  "properties": {
    "gn:admin1_code":"84",
    "gn:admin2_code":"2015.0",
    "gn:admin3_code":"201582.0",
    "gn:admin4_code":"20158229.0",
    "gn:asciiname":"Uttar Bamandanga",
    "gn:country_code":"BD",
    "gn:dem":10,
    "gn:feature_class":"P",
    "gn:feature_code":"PPL",
    "gn:name":"Uttar B\u0101mand\u0101nga",
    "gn:population":0,
    "gn:timezone":"Asia/Dhaka",
    "iso:country":"BD",
    "name:ben_x_preferred":[
        "Uttar B\u0101mand\u0101nga"
    ],
    "wof:name":"Uttar Bamandanga",
    "wof:placetype":"locality"
},
  "geometry": {"coordinates":[91.96702000000001,22.16371],"type":"Point"}
}