{
  "type": "Feature",
  "properties": {
    "gn:admin1_code":"84",
    "gn:admin2_code":"2051.0",
    "gn:admin3_code":"205165.0",
    "gn:admin4_code":"20516547.0",
    "gn:asciiname":"Anandanpur",
    "gn:country_code":"BD",
    "gn:dem":11,
    "gn:feature_class":"P",
    "gn:feature_code":"PPL",
    "gn:name":"\u0100nandanpur",
    "gn:population":0,
    "gn:timezone":"Asia/Dhaka",
    "iso:country":"BD",
    "name:und_x_variant":[
        "\u0100nandanpur",
        "\u0100nandipur"
    ],
    "wof:name":"Anandanpur",
    "wof:placetype":"locality"
},
  "geometry": {"coordinates":[90.88588,23.03272],"type":"Point"}
}