{
  "type": "Feature",
  "properties": {
    "gn:admin1_code":"87",
    "gn:admin2_code":"5527",
    "gn:admin3_code":"552712.0",
    "gn:admin4_code":"55271269.0",
    "gn:asciiname":"Kasimnagar",
    "gn:country_code":"BD",
    "gn:dem":52,
    "gn:feature_class":"P",
    "gn:feature_code":"PPL",
    "gn:name":"K\u0101simnagar",
    "gn:population":0,
    "gn:timezone":"Asia/Dhaka",
    "iso:country":"BD",
    "name:ben_x_preferred":[
        "K\u0101simnagar"
    ],
    "wof:name":"Kasimnagar",
    "wof:placetype":"locality"
},
  "geometry": {"coordinates":[88.71473,25.98225],"type":"Point"}
}