{
  "type": "Feature",
  "properties": {
    "gn:admin1_code":"82",
    "gn:admin2_code":"4041",
    "gn:admin3_code":"404123.0",
    "gn:admin4_code":"40412347.0",
    "gn:asciiname":"Kirtipur",
    "gn:country_code":"BD",
    "gn:dem":12,
    "gn:feature_class":"P",
    "gn:feature_code":"PPL",
    "gn:name":"Kirtipur",
    "gn:population":0,
    "gn:timezone":"Asia/Dhaka",
    "iso:country":"BD",
    "name:ben_x_preferred":[
        "Kirtipur"
    ],
    "name:ceb_x_preferred":[
        "Kirtipur"
    ],
    "name:deu_x_preferred":[
        "Kirtipur"
    ],
    "name:dty_x_preferred":[
        "\u0915\u0940\u0930\u094d\u0924\u093f\u092a\u0941\u0930"
    ],
    "name:fin_x_preferred":[
        "Kirtipur"
    ],
    "name:fra_x_preferred":[
        "Kirtipur"
    ],
    "name:hin_x_preferred":[
        "\u0915\u0940\u0930\u094d\u0924\u093f\u092a\u0941\u0930"
    ],
    "name:jpn_x_preferred":[
        "\u30ad\u30eb\u30c6\u30a3\u30d7\u30eb"
    ],
    "name:lit_x_preferred":[
        "Kyrtipuras"
    ],
    "name:mai_x_preferred":[
        "\u0915\u0940\u0930\u094d\u0924\u093f\u092a\u0941\u0930 \u0928\u0917\u0930\u092a\u093e\u0932\u093f\u0915\u093e"
    ],
    "name:nep_x_preferred":[
        "\u0915\u0940\u0930\u094d\u0924\u093f\u092a\u0941\u0930 \u0928\u0917\u0930\u092a\u093e\u0932\u093f\u0915\u093e"
    ],
    "name:new_x_preferred":[
        "\u0915\u093f\u092a\u0942 \u0928\u0917\u0930\u092a\u093e\u0932\u093f\u0915\u093e"
    ],
    "name:nor_x_preferred":[
        "Kirtipur"
    ],
    "name:pol_x_preferred":[
        "Kirtipur"
    ],
    "name:rus_x_preferred":[
        "\u041a\u0438\u0440\u0442\u0438\u043f\u0443\u0440"
    ],
    "name:spa_x_preferred":[
        "Kirtipur"
    ],
    "name:swe_x_preferred":[
        "Kirtipur"
    ],
    "name:tam_x_preferred":[
        "\u0b95\u0bc0\u0bb0\u0bcd\u0ba4\u0bcd\u0ba4\u0bbf\u0baa\u0bc2\u0bb0\u0bcd"
    ],
    "name:urd_x_preferred":[
        "\u06a9\u0631\u062a\u06cc\u067e\u0648\u0631"
    ],
    "name:zho_x_preferred":[
        "\u5409\u723e\u8482\u5e03\u723e"
    ],
    "wof:name":"Kirtipur",
    "wof:placetype":"locality"
},
  "geometry": {"coordinates":[89.11626,23.1122],"type":"Point"}
}