{
  "type": "Feature",
  "properties": {
    "gn:admin1_code":"84",
    "gn:admin2_code":"2015.0",
    "gn:admin3_code":"201537.0",
    "gn:admin4_code":"20153741.0",
    "gn:asciiname":"Udalia Kalarani",
    "gn:country_code":"BD",
    "gn:dem":29,
    "gn:feature_class":"P",
    "gn:feature_code":"PPL",
    "gn:name":"Udalia Kalarani",
    "gn:population":0,
    "gn:timezone":"Asia/Dhaka",
    "iso:country":"BD",
    "wof:name":"Udalia Kalarani",
    "wof:placetype":"locality"
},
  "geometry": {"coordinates":[91.74527999999999,22.58694],"type":"Point"}
}