{
  "type": "Feature",
  "properties": {
    "gn:admin1_code":"83",
    "gn:admin2_code":"5081.0",
    "gn:admin3_code":"508112.0",
    "gn:admin4_code":"50811282.0",
    "gn:asciiname":"Sayeda",
    "gn:country_code":"BD",
    "gn:dem":19,
    "gn:feature_class":"P",
    "gn:feature_code":"PPL",
    "gn:name":"Sayeda",
    "gn:population":0,
    "gn:timezone":"Asia/Dhaka",
    "iso:country":"BD",
    "name:ben_x_preferred":[
        "Sayeda"
    ],
    "wof:name":"Sayeda",
    "wof:placetype":"locality"
},
  "geometry": {"coordinates":[88.77261999999997,24.65014],"type":"Point"}
}