{
  "type": "Feature",
  "properties": {
    "gn:admin1_code":"84",
    "gn:admin2_code":"2022.0",
    "gn:admin3_code":"202290.0",
    "gn:admin4_code":"20229047.0",
    "gn:asciiname":"Uttar Nowapara",
    "gn:country_code":"BD",
    "gn:dem":6,
    "gn:feature_class":"P",
    "gn:feature_code":"PPL",
    "gn:name":"Uttar Nowapara",
    "gn:population":0,
    "gn:timezone":"Asia/Dhaka",
    "iso:country":"BD",
    "name:ben_x_preferred":[
        "Uttar Nowapara"
    ],
    "wof:name":"Uttar Nowapara",
    "wof:placetype":"locality"
},
  "geometry": {"coordinates":[92.30374999999999,20.8344],"type":"Point"}
}