{
  "type": "Feature",
  "properties": {
    "gn:admin1_code":"H",
    "gn:admin2_code":"3089",
    "gn:admin3_code":"308990.0",
    "gn:admin4_code":"30899015.0",
    "gn:asciiname":"Char Simul Char",
    "gn:country_code":"BD",
    "gn:dem":25,
    "gn:feature_class":"P",
    "gn:feature_code":"PPL",
    "gn:name":"Char Simul Char",
    "gn:population":0,
    "gn:timezone":"Asia/Dhaka",
    "iso:country":"BD",
    "name:ben_x_preferred":[
        "Char Simul Char"
    ],
    "wof:name":"Char Simul Char",
    "wof:placetype":"locality"
},
  "geometry": {"coordinates":[89.90293,25.11278],"type":"Point"}
}