{
  "type": "Feature",
  "properties": {
    "gn:admin1_code":"82",
    "gn:admin2_code":"4001.0",
    "gn:admin3_code":"400173.0",
    "gn:admin4_code":"40017341.0",
    "gn:asciiname":"Chitra",
    "gn:country_code":"BD",
    "gn:dem":6,
    "gn:feature_class":"P",
    "gn:feature_code":"PPL",
    "gn:name":"Chitra",
    "gn:population":0,
    "gn:timezone":"Asia/Dhaka",
    "iso:country":"BD",
    "name:ben_x_preferred":[
        "\u099a\u09bf\u09a4\u09cd\u09b0\u09be"
    ],
    "name:hin_x_preferred":[
        "\u091a\u093f\u0924\u094d\u0930\u093e"
    ],
    "name:ita_x_preferred":[
        "Chitra"
    ],
    "name:nld_x_preferred":[
        "Chitra"
    ],
    "wof:name":"Chitra",
    "wof:placetype":"locality"
},
  "geometry": {"coordinates":[89.59999999999999,22.61821],"type":"Point"}
}