{
  "type": "Feature",
  "properties": {
    "gn:admin1_code":"82",
    "gn:admin2_code":"4044.0",
    "gn:admin3_code":"404480.0",
    "gn:admin4_code":"40448031.0",
    "gn:asciiname":"Tripura",
    "gn:country_code":"BD",
    "gn:dem":9,
    "gn:feature_class":"P",
    "gn:feature_code":"PPL",
    "gn:name":"Tripura",
    "gn:population":0,
    "gn:timezone":"Asia/Dhaka",
    "iso:country":"BD",
    "name:ben_x_preferred":[
        "Tripura"
    ],
    "wof:name":"Tripura",
    "wof:placetype":"locality"
},
  "geometry": {"coordinates":[89.21983,23.62122],"type":"Point"}
}