{
  "type": "Feature",
  "properties": {
    "gn:admin1_code":"H",
    "gn:admin2_code":"3061",
    "gn:admin3_code":"306131.0",
    "gn:admin4_code":"30613185.0",
    "gn:asciiname":"Kanthalia",
    "gn:country_code":"BD",
    "gn:dem":18,
    "gn:feature_class":"P",
    "gn:feature_code":"PPL",
    "gn:name":"K\u0101nth\u0101lia",
    "gn:population":0,
    "gn:timezone":"Asia/Dhaka",
    "iso:country":"BD",
    "wof:name":"Kanthalia",
    "wof:placetype":"locality"
},
  "geometry": {"coordinates":[90.65366,24.69743],"type":"Point"}
}