{
  "type": "Feature",
  "properties": {
    "gn:admin1_code":"87",
    "gn:admin2_code":"5585.0",
    "gn:admin3_code":"558549.0",
    "gn:admin4_code":"55854931.0",
    "gn:asciiname":"Arazi Mominpur",
    "gn:country_code":"BD",
    "gn:dem":40,
    "gn:feature_class":"P",
    "gn:feature_code":"PPL",
    "gn:name":"Ar\u0101zi Mominpur",
    "gn:population":0,
    "gn:timezone":"Asia/Dhaka",
    "iso:country":"BD",
    "name:ben_x_preferred":[
        "Ar\u0101zi Mominpur"
    ],
    "name:ben_x_variant":[
        "Arazi Mominpoor",
        "\u0100r\u0101zi Maminpur"
    ],
    "wof:name":"Arazi Mominpur",
    "wof:placetype":"locality"
},
  "geometry": {"coordinates":[89.11716,25.77243],"type":"Point"}
}