{
  "type": "Feature",
  "properties": {
    "gn:admin1_code":"H",
    "gn:admin2_code":"3089",
    "gn:admin3_code":"308988.0",
    "gn:admin4_code":"30898874.0",
    "gn:asciiname":"Lachhmanpur",
    "gn:country_code":"BD",
    "gn:dem":22,
    "gn:feature_class":"P",
    "gn:feature_code":"PPL",
    "gn:name":"Lachhmanpur",
    "gn:population":0,
    "gn:timezone":"Asia/Dhaka",
    "iso:country":"BD",
    "name:und_x_variant":[
        "Lachmanpur",
        "Lachhmanpur"
    ],
    "wof:name":"Lachhmanpur",
    "wof:placetype":"locality"
},
  "geometry": {"coordinates":[90.01429,24.9775],"type":"Point"}
}