{
  "type": "Feature",
  "properties": {
    "gn:admin1_code":"81",
    "gn:admin2_code":"3026",
    "gn:admin3_code":"302662.0",
    "gn:admin4_code":"30266220.0",
    "gn:asciiname":"Puratan Bandura",
    "gn:country_code":"BD",
    "gn:dem":14,
    "gn:feature_class":"P",
    "gn:feature_code":"PPL",
    "gn:name":"Pur\u0101tan B\u0101ndura",
    "gn:population":0,
    "gn:timezone":"Asia/Dhaka",
    "iso:country":"BD",
    "wof:name":"Puratan Bandura",
    "wof:placetype":"locality"
},
  "geometry": {"coordinates":[90.11529,23.6623],"type":"Point"}
}