{
  "type": "Feature",
  "properties": {
    "gn:admin1_code":"83",
    "gn:admin2_code":"5070.0",
    "gn:admin3_code":"507037.0",
    "gn:admin4_code":"50703784.0",
    "gn:asciiname":"Bhagalpur",
    "gn:country_code":"BD",
    "gn:dem":32,
    "gn:feature_class":"P",
    "gn:feature_code":"PPL",
    "gn:name":"Bhagalpur",
    "gn:population":0,
    "gn:timezone":"Asia/Dhaka",
    "iso:country":"BD",
    "name:ben_x_preferred":[
        "Bhagalpur"
    ],
    "wof:name":"Bhagalpur",
    "wof:placetype":"locality"
},
  "geometry": {"coordinates":[88.35365999999998,24.82135],"type":"Point"}
}