{
  "type": "Feature",
  "properties": {
    "gn:admin1_code":"82",
    "gn:admin2_code":"4087.0",
    "gn:admin3_code":"408790.0",
    "gn:admin4_code":"40879063.0",
    "gn:asciiname":"Charikhada",
    "gn:country_code":"BD",
    "gn:dem":12,
    "gn:feature_class":"P",
    "gn:feature_code":"PPL",
    "gn:name":"Ch\u0101rikh\u0101da",
    "gn:population":0,
    "gn:timezone":"Asia/Dhaka",
    "iso:country":"BD",
    "wof:name":"Charikhada",
    "wof:placetype":"locality"
},
  "geometry": {"coordinates":[89.24165000000001,22.72963],"type":"Point"}
}