{
  "type": "Feature",
  "properties": {
    "gn:admin1_code":"84",
    "gn:admin2_code":"2022.0",
    "gn:admin3_code":"202290.0",
    "gn:admin4_code":"20229063.0",
    "gn:asciiname":"Hatiarghona",
    "gn:country_code":"BD",
    "gn:dem":12,
    "gn:feature_class":"P",
    "gn:feature_code":"PPL",
    "gn:name":"Hati\u0101rghona",
    "gn:population":0,
    "gn:timezone":"Asia/Dhaka",
    "iso:country":"BD",
    "name:ben_x_preferred":[
        "Hati\u0101rghona"
    ],
    "wof:name":"Hatiarghona",
    "wof:placetype":"locality"
},
  "geometry": {"coordinates":[92.26273,20.88073],"type":"Point"}
}