{
  "type": "Feature",
  "properties": {
    "gn:admin1_code":"81",
    "gn:admin2_code":"3093",
    "gn:admin3_code":"309376.0",
    "gn:admin4_code":"30937680.0",
    "gn:asciiname":"Rautara",
    "gn:country_code":"BD",
    "gn:dem":17,
    "gn:feature_class":"P",
    "gn:feature_code":"PPL",
    "gn:name":"R\u0101ut\u0101ra",
    "gn:population":0,
    "gn:timezone":"Asia/Dhaka",
    "iso:country":"BD",
    "wof:name":"Rautara",
    "wof:placetype":"locality"
},
  "geometry": {"coordinates":[90.00598000000002,24.02712],"type":"Point"}
}