{
  "type": "Feature",
  "properties": {
    "gn:admin1_code":"81",
    "gn:admin2_code":"3059.0",
    "gn:admin3_code":"305924.0",
    "gn:admin4_code":"30592463.0",
    "gn:asciiname":"Ashrabdi",
    "gn:country_code":"BD",
    "gn:dem":12,
    "gn:feature_class":"P",
    "gn:feature_code":"PPL",
    "gn:name":"Ashr\u0101bdi",
    "gn:population":0,
    "gn:timezone":"Asia/Dhaka",
    "iso:country":"BD",
    "name:und_x_variant":[
        "Ashr\u0101bdi",
        "\u0100sr\u0101fdi"
    ],
    "wof:name":"Ashrabdi",
    "wof:placetype":"locality"
},
  "geometry": {"coordinates":[90.59426000000001,23.57906],"type":"Point"}
}