{
  "type": "Feature",
  "properties": {
    "gn:admin1_code":"85",
    "gn:admin2_code":"1006.0",
    "gn:admin3_code":"100632.0",
    "gn:admin4_code":"10063255.0",
    "gn:asciiname":"Badurtala",
    "gn:country_code":"BD",
    "gn:dem":11,
    "gn:feature_class":"P",
    "gn:feature_code":"PPL",
    "gn:name":"B\u0101durtala",
    "gn:population":0,
    "gn:timezone":"Asia/Dhaka",
    "iso:country":"BD",
    "name:und_x_variant":[
        "B\u0101durtala"
    ],
    "wof:name":"Badurtala",
    "wof:placetype":"locality"
},
  "geometry": {"coordinates":[90.20236,23.05848],"type":"Point"}
}