{
  "type": "Feature",
  "properties": {
    "gn:admin1_code":"87",
    "gn:admin2_code":"5527.0",
    "gn:admin3_code":"552721.0",
    "gn:admin4_code":"55272113.0",
    "gn:asciiname":"Alampur",
    "gn:country_code":"BD",
    "gn:dem":44,
    "gn:feature_class":"P",
    "gn:feature_code":"PPL",
    "gn:name":"Alampur",
    "gn:population":0,
    "gn:timezone":"Asia/Dhaka",
    "iso:country":"BD",
    "name:ben_x_preferred":[
        "Alampur"
    ],
    "name:ceb_x_preferred":[
        "Alampur"
    ],
    "name:hin_x_preferred":[
        "\u0906\u0932\u092e\u092a\u0941\u0930"
    ],
    "name:swe_x_preferred":[
        "Alampur"
    ],
    "wof:name":"Alampur",
    "wof:placetype":"locality"
},
  "geometry": {"coordinates":[88.48814,25.75544],"type":"Point"}
}