{
  "type": "Feature",
  "properties": {
    "gn:admin1_code":"87",
    "gn:admin2_code":"5573.0",
    "gn:admin3_code":"557315.0",
    "gn:admin4_code":"55731538.0",
    "gn:asciiname":"Dhanpara",
    "gn:country_code":"BD",
    "gn:dem":55,
    "gn:feature_class":"P",
    "gn:feature_code":"PPL",
    "gn:name":"Dh\u0101np\u0101ra",
    "gn:population":0,
    "gn:timezone":"Asia/Dhaka",
    "iso:country":"BD",
    "name:ben_x_preferred":[
        "Dh\u0101np\u0101ra"
    ],
    "wof:name":"Dhanpara",
    "wof:placetype":"locality"
},
  "geometry": {"coordinates":[88.83573,26.09487],"type":"Point"}
}