{
  "type": "Feature",
  "properties": {
    "gn:admin1_code":"83",
    "gn:admin2_code":"5081",
    "gn:admin3_code":"508110.0",
    "gn:admin4_code":"50811023.0",
    "gn:asciiname":"Sadhupara",
    "gn:country_code":"BD",
    "gn:dem":18,
    "gn:feature_class":"P",
    "gn:feature_code":"PPL",
    "gn:name":"S\u0101dhup\u0101ra",
    "gn:population":0,
    "gn:timezone":"Asia/Dhaka",
    "iso:country":"BD",
    "name:ben_x_preferred":[
        "S\u0101dhup\u0101ra"
    ],
    "wof:name":"Sadhupara",
    "wof:placetype":"locality"
},
  "geometry": {"coordinates":[88.90591999999999,24.24143],"type":"Point"}
}