{
  "type": "Feature",
  "properties": {
    "gn:admin1_code":"82",
    "gn:admin2_code":"4050.0",
    "gn:admin3_code":"405094.0",
    "gn:admin4_code":"40509480.0",
    "gn:asciiname":"Bolur Char",
    "gn:country_code":"BD",
    "gn:dem":17,
    "gn:feature_class":"P",
    "gn:feature_code":"PPL",
    "gn:name":"Bolur Char",
    "gn:population":0,
    "gn:timezone":"Asia/Dhaka",
    "iso:country":"BD",
    "name:ben_x_preferred":[
        "Bolur Char"
    ],
    "wof:name":"Bolur Char",
    "wof:placetype":"locality"
},
  "geometry": {"coordinates":[89.0091,23.83802],"type":"Point"}
}