{
  "type": "Feature",
  "properties": {
    "gn:admin1_code":"82",
    "gn:admin2_code":"4087.0",
    "gn:admin3_code":"408747.0",
    "gn:admin4_code":"40874715.0",
    "gn:asciiname":"Chanchai",
    "gn:country_code":"BD",
    "gn:dem":10,
    "gn:feature_class":"P",
    "gn:feature_code":"PPL",
    "gn:name":"Ch\u0101nch\u0101i",
    "gn:population":0,
    "gn:timezone":"Asia/Dhaka",
    "iso:country":"BD",
    "name:ben_x_preferred":[
        "Ch\u0101nch\u0101i"
    ],
    "wof:name":"Chanchai",
    "wof:placetype":"locality"
},
  "geometry": {"coordinates":[89.1028,22.43899],"type":"Point"}
}