{
  "type": "Feature",
  "properties": {
    "gn:admin1_code":"84",
    "gn:admin2_code":"2046.0",
    "gn:admin3_code":"204680.0",
    "gn:admin4_code":"20468038.0",
    "gn:asciiname":"Kristamanipara",
    "gn:country_code":"BD",
    "gn:dem":68,
    "gn:feature_class":"P",
    "gn:feature_code":"PPL",
    "gn:name":"Kristaman\u012bp\u0101ra",
    "gn:population":0,
    "gn:timezone":"Asia/Dhaka",
    "iso:country":"BD",
    "name:ben_x_preferred":[
        "Kristaman\u012bp\u0101ra"
    ],
    "wof:name":"Kristamanipara",
    "wof:placetype":"locality"
},
  "geometry": {"coordinates":[91.94363,22.96636],"type":"Point"}
}