{
  "type": "Feature",
  "properties": {
    "gn:admin1_code":"87",
    "gn:admin2_code":"5549",
    "gn:admin3_code":"554977.0",
    "gn:admin4_code":"55497742.0",
    "gn:asciiname":"Gatiasyam",
    "gn:country_code":"BD",
    "gn:dem":35,
    "gn:feature_class":"P",
    "gn:feature_code":"PPL",
    "gn:name":"Gatiasyam",
    "gn:population":0,
    "gn:timezone":"Asia/Dhaka",
    "iso:country":"BD",
    "name:ben_x_preferred":[
        "Gatiasyam"
    ],
    "wof:name":"Gatiasyam",
    "wof:placetype":"locality"
},
  "geometry": {"coordinates":[89.47166999999997,25.79537],"type":"Point"}
}