{
  "type": "Feature",
  "properties": {
    "gn:admin1_code":"83",
    "gn:admin2_code":"5038.0",
    "gn:admin3_code":"503861.0",
    "gn:admin4_code":"50386147.0",
    "gn:asciiname":"Binsara",
    "gn:country_code":"BD",
    "gn:dem":22,
    "gn:feature_class":"P",
    "gn:feature_code":"PPL",
    "gn:name":"Bins\u0101ra",
    "gn:population":0,
    "gn:timezone":"Asia/Dhaka",
    "iso:country":"BD",
    "name:ben_x_preferred":[
        "Bins\u0101ra"
    ],
    "wof:name":"Binsara",
    "wof:placetype":"locality"
},
  "geometry": {"coordinates":[89.10364,25.05287],"type":"Point"}
}