{
  "type": "Feature",
  "properties": {
    "gn:admin1_code":"83",
    "gn:admin2_code":"5064.0",
    "gn:admin3_code":"506486.0",
    "gn:admin4_code":"50648671.0",
    "gn:asciiname":"Saiyadpur",
    "gn:country_code":"BD",
    "gn:dem":38,
    "gn:feature_class":"P",
    "gn:feature_code":"PPL",
    "gn:name":"Saiyadpur",
    "gn:population":0,
    "gn:timezone":"Asia/Dhaka",
    "iso:country":"BD",
    "name:ben_x_preferred":[
        "Saiyadpur"
    ],
    "wof:name":"Saiyadpur",
    "wof:placetype":"locality"
},
  "geometry": {"coordinates":[88.55629999999999,25.12579],"type":"Point"}
}