{
  "type": "Feature",
  "properties": {
    "gn:admin1_code":"87",
    "gn:admin2_code":"5549",
    "gn:admin3_code":"554906.0",
    "gn:admin4_code":"55490685.0",
    "gn:asciiname":"Dakshin Dhaldanga",
    "gn:country_code":"BD",
    "gn:dem":36,
    "gn:feature_class":"P",
    "gn:feature_code":"PPL",
    "gn:name":"Dakshin Dhaldanga",
    "gn:population":0,
    "gn:timezone":"Asia/Dhaka",
    "iso:country":"BD",
    "name:ben_x_preferred":[
        "Dakshin Dhaldanga"
    ],
    "wof:name":"Dakshin Dhaldanga",
    "wof:placetype":"locality"
},
  "geometry": {"coordinates":[89.66494,26.19159],"type":"Point"}
}