{
  "type": "Feature",
  "properties": {
    "gn:admin1_code":"H",
    "gn:admin2_code":"3061.0",
    "gn:admin3_code":"306123.0",
    "gn:admin4_code":"30612310.0",
    "gn:asciiname":"Dhakura",
    "gn:country_code":"BD",
    "gn:dem":15,
    "gn:feature_class":"P",
    "gn:feature_code":"PPL",
    "gn:name":"Dhakura",
    "gn:population":0,
    "gn:timezone":"Asia/Dhaka",
    "iso:country":"BD",
    "name:und_x_variant":[
        "Dhekura"
    ],
    "wof:name":"Dhakura",
    "wof:placetype":"locality"
},
  "geometry": {"coordinates":[90.61138,24.78974],"type":"Point"}
}