{
  "type": "Feature",
  "properties": {
    "gn:admin1_code":"87",
    "gn:admin2_code":"5577.0",
    "gn:admin3_code":"557773.0",
    "gn:admin4_code":"55777311.0",
    "gn:asciiname":"Baidnar Jot",
    "gn:country_code":"BD",
    "gn:dem":86,
    "gn:feature_class":"P",
    "gn:feature_code":"PPL",
    "gn:name":"Baidn\u0101r Jot",
    "gn:population":0,
    "gn:timezone":"Asia/Dhaka",
    "iso:country":"BD",
    "name:ben_x_preferred":[
        "Baidn\u0101r Jot"
    ],
    "wof:name":"Baidnar Jot",
    "wof:placetype":"locality"
},
  "geometry": {"coordinates":[88.56922,26.44343],"type":"Point"}
}