{
  "type": "Feature",
  "properties": {
    "gn:admin1_code":"82",
    "gn:asciiname":"Pajakhali Hazra",
    "gn:country_code":"BD",
    "gn:dem":7,
    "gn:feature_class":"P",
    "gn:feature_code":"PPL",
    "gn:name":"P\u0101j\u0101khali H\u0101zra",
    "gn:population":0,
    "gn:timezone":"Asia/Dhaka",
    "iso:country":"BD",
    "name:ben_x_preferred":[
        "P\u0101j\u0101khali H\u0101zra"
    ],
    "name:ben_x_variant":[
        "P\u0101z\u0101kh\u0101li H\u0101zra"
    ],
    "name:und_x_variant":[
        "Pajakali Hazra",
        "Rajakhali"
    ],
    "wof:name":"Pajakhali Hazra",
    "wof:placetype":"locality"
},
  "geometry": {"coordinates":[90.40179000000001,22.39551],"type":"Point"}
}