{
  "type": "Feature",
  "properties": {
    "gn:admin1_code":"84",
    "gn:admin2_code":"2022",
    "gn:admin3_code":"202224.0",
    "gn:admin4_code":"20222483.0",
    "gn:asciiname":"Napitkhali",
    "gn:country_code":"BD",
    "gn:dem":3,
    "gn:feature_class":"P",
    "gn:feature_code":"PPL",
    "gn:name":"Napitkh\u0101li",
    "gn:population":0,
    "gn:timezone":"Asia/Dhaka",
    "iso:country":"BD",
    "name:ben_x_preferred":[
        "Napitkh\u0101li"
    ],
    "wof:name":"Napitkhali",
    "wof:placetype":"locality"
},
  "geometry": {"coordinates":[92.05258000000001,21.59645],"type":"Point"}
}