{
  "type": "Feature",
  "properties": {
    "gn:admin1_code":"87",
    "gn:admin2_code":"5527.0",
    "gn:admin3_code":"552730.0",
    "gn:admin4_code":"55273063.0",
    "gn:asciiname":"Nasaratpur",
    "gn:country_code":"BD",
    "gn:dem":44,
    "gn:feature_class":"P",
    "gn:feature_code":"PPL",
    "gn:name":"Nasaratpur",
    "gn:population":0,
    "gn:timezone":"Asia/Dhaka",
    "iso:country":"BD",
    "name:ben_x_preferred":[
        "Nasaratpur"
    ],
    "wof:name":"Nasaratpur",
    "wof:placetype":"locality"
},
  "geometry": {"coordinates":[88.76876999999998,25.73867000000001],"type":"Point"}
}