{
  "type": "Feature",
  "properties": {
    "gn:admin1_code":"87",
    "gn:admin2_code":"5527.0",
    "gn:admin3_code":"552717.0",
    "gn:admin4_code":"55271795.0",
    "gn:asciiname":"Ratanor",
    "gn:country_code":"BD",
    "gn:dem":42,
    "gn:feature_class":"P",
    "gn:feature_code":"PPL",
    "gn:name":"Ratanor",
    "gn:population":0,
    "gn:timezone":"Asia/Dhaka",
    "iso:country":"BD",
    "name:ben_x_preferred":[
        "Ratanor"
    ],
    "wof:name":"Ratanor",
    "wof:placetype":"locality"
},
  "geometry": {"coordinates":[88.48992,25.66517],"type":"Point"}
}