{
  "type": "Feature",
  "properties": {
    "gn:admin1_code":"85",
    "gn:admin2_code":"1006.0",
    "gn:admin3_code":"100607.0",
    "gn:admin4_code":"10060794.0",
    "gn:asciiname":"Daokati",
    "gn:country_code":"BD",
    "gn:dem":11,
    "gn:feature_class":"P",
    "gn:feature_code":"PPL",
    "gn:name":"D\u0101ok\u0101ti",
    "gn:population":0,
    "gn:timezone":"Asia/Dhaka",
    "iso:country":"BD",
    "name:und_x_variant":[
        "D\u0101ok\u0101ti"
    ],
    "wof:name":"Daokati",
    "wof:placetype":"locality"
},
  "geometry": {"coordinates":[90.31507000000001,22.55914],"type":"Point"}
}