{
  "type": "Feature",
  "properties": {
    "gn:admin1_code":"84",
    "gn:admin2_code":"2019",
    "gn:admin3_code":"201927.0",
    "gn:admin4_code":"20192787.0",
    "gn:asciiname":"North Krishnapur",
    "gn:country_code":"BD",
    "gn:dem":10,
    "gn:feature_class":"P",
    "gn:feature_code":"PPL",
    "gn:name":"North Krishnapur",
    "gn:population":0,
    "gn:timezone":"Asia/Dhaka",
    "iso:country":"BD",
    "name:und_x_variant":[
        "Krishnapur",
        "North Krishnapur"
    ],
    "wof:name":"North Krishnapur",
    "wof:placetype":"locality"
},
  "geometry": {"coordinates":[90.88805000000001,23.49455],"type":"Point"}
}