{
  "type": "Feature",
  "properties": {
    "gn:admin1_code":"83",
    "gn:admin2_code":"5081.0",
    "gn:admin3_code":"508134.0",
    "gn:admin4_code":"50813447.0",
    "gn:asciiname":"Laladighi",
    "gn:country_code":"BD",
    "gn:dem":28,
    "gn:feature_class":"P",
    "gn:feature_code":"PPL",
    "gn:name":"L\u0101ladighi",
    "gn:population":0,
    "gn:timezone":"Asia/Dhaka",
    "iso:country":"BD",
    "name:ben_x_preferred":[
        "L\u0101ladighi"
    ],
    "wof:name":"Laladighi",
    "wof:placetype":"locality"
},
  "geometry": {"coordinates":[88.4329,24.40559],"type":"Point"}
}