{
  "type": "Feature",
  "properties": {
    "gn:admin1_code":"86",
    "gn:admin2_code":"6090",
    "gn:admin3_code":"609047.0",
    "gn:admin4_code":"60904719.0",
    "gn:asciiname":"Das Nawagaon",
    "gn:country_code":"BD",
    "gn:dem":12,
    "gn:feature_class":"P",
    "gn:feature_code":"PPL",
    "gn:name":"D\u0101s Naw\u0101gaon",
    "gn:population":0,
    "gn:timezone":"Asia/Dhaka",
    "iso:country":"BD",
    "name:und_x_variant":[
        "Noagaon",
        "Naw\u0101gaon",
        "D\u0101s Naw\u0101gaon"
    ],
    "wof:name":"Das Nawagaon",
    "wof:placetype":"locality"
},
  "geometry": {"coordinates":[91.46608999999999,24.79824],"type":"Point"}
}