{
  "type": "Feature",
  "properties": {
    "gn:admin1_code":"82",
    "gn:admin2_code":"4065.0",
    "gn:admin3_code":"406576.0",
    "gn:admin4_code":"40657694.0",
    "gn:asciiname":"Bamanhat",
    "gn:country_code":"BD",
    "gn:dem":9,
    "gn:feature_class":"P",
    "gn:feature_code":"PPL",
    "gn:name":"B\u0101manh\u0101t",
    "gn:population":0,
    "gn:timezone":"Asia/Dhaka",
    "iso:country":"BD",
    "name:ben_x_preferred":[
        "B\u0101manh\u0101t"
    ],
    "wof:name":"Bamanhat",
    "wof:placetype":"locality"
},
  "geometry": {"coordinates":[89.42350999999999,23.20603],"type":"Point"}
}