{
  "type": "Feature",
  "properties": {
    "gn:admin1_code":"H",
    "gn:admin2_code":"3089.0",
    "gn:admin3_code":"308967.0",
    "gn:admin4_code":"30896757.0",
    "gn:asciiname":"Dhamna",
    "gn:country_code":"BD",
    "gn:dem":19,
    "gn:feature_class":"P",
    "gn:feature_code":"PPL",
    "gn:name":"Dhamna",
    "gn:population":0,
    "gn:timezone":"Asia/Dhaka",
    "iso:country":"BD",
    "name:und_x_variant":[
        "Dh\u0101mna"
    ],
    "wof:name":"Dhamna",
    "wof:placetype":"locality"
},
  "geometry": {"coordinates":[90.19344,25.00289],"type":"Point"}
}