{
  "type": "Feature",
  "properties": {
    "gn:admin1_code":"H",
    "gn:admin2_code":"3072",
    "gn:admin3_code":"307209.0",
    "gn:admin4_code":"30720983.0",
    "gn:asciiname":"Ramer Geria",
    "gn:country_code":"BD",
    "gn:dem":15,
    "gn:feature_class":"P",
    "gn:feature_code":"PPL",
    "gn:name":"R\u0101mer Geria",
    "gn:population":0,
    "gn:timezone":"Asia/Dhaka",
    "iso:country":"BD",
    "wof:name":"Ramer Geria",
    "wof:placetype":"locality"
},
  "geometry": {"coordinates":[90.97754999999999,24.90233],"type":"Point"}
}