{
  "type": "Feature",
  "properties": {
    "gn:admin1_code":"81",
    "gn:admin2_code":"3026.0",
    "gn:admin3_code":"302638.0",
    "gn:admin4_code":"30263825.0",
    "gn:asciiname":"Akchail",
    "gn:country_code":"BD",
    "gn:dem":14,
    "gn:feature_class":"P",
    "gn:feature_code":"PPL",
    "gn:name":"\u0100kch\u0101il",
    "gn:population":0,
    "gn:timezone":"Asia/Dhaka",
    "iso:country":"BD",
    "wof:name":"Akchail",
    "wof:placetype":"locality"
},
  "geometry": {"coordinates":[90.27742000000001,23.71798],"type":"Point"}
}