{
  "type": "Feature",
  "properties": {
    "gn:admin1_code":"84",
    "gn:admin2_code":"2022.0",
    "gn:admin3_code":"202224.0",
    "gn:admin4_code":"20222447.0",
    "gn:asciiname":"Lamuni Para",
    "gn:country_code":"BD",
    "gn:dem":6,
    "gn:feature_class":"P",
    "gn:feature_code":"PPL",
    "gn:name":"Lamuni Para",
    "gn:population":0,
    "gn:timezone":"Asia/Dhaka",
    "iso:country":"BD",
    "name:ben_x_preferred":[
        "Lamuni Para"
    ],
    "wof:name":"Lamuni Para",
    "wof:placetype":"locality"
},
  "geometry": {"coordinates":[91.98226,21.42002],"type":"Point"}
}