{
  "type": "Feature",
  "properties": {
    "gn:admin1_code":"81",
    "gn:admin2_code":"3086",
    "gn:admin3_code":"308694.0",
    "gn:admin4_code":"30869494.0",
    "gn:asciiname":"North Baiksa",
    "gn:country_code":"BD",
    "gn:dem":13,
    "gn:feature_class":"P",
    "gn:feature_code":"PPL",
    "gn:name":"North B\u0101iksa",
    "gn:population":0,
    "gn:timezone":"Asia/Dhaka",
    "iso:country":"BD",
    "name:und_x_variant":[
        "Uttar Baikasa",
        "North Baiksha",
        "Uttar B\u0101iksa",
        "North B\u0101iksa"
    ],
    "wof:name":"North Baiksa",
    "wof:placetype":"locality"
},
  "geometry": {"coordinates":[90.31492,23.33636],"type":"Point"}
}