{
  "type": "Feature",
  "properties": {
    "gn:admin1_code":"83",
    "gn:admin2_code":"5081.0",
    "gn:admin3_code":"508112.0",
    "gn:admin4_code":"50811218.0",
    "gn:asciiname":"Gopalpur",
    "gn:country_code":"BD",
    "gn:dem":18,
    "gn:feature_class":"P",
    "gn:feature_code":"PPL",
    "gn:name":"Gop\u0101lpur",
    "gn:population":0,
    "gn:timezone":"Asia/Dhaka",
    "iso:country":"BD",
    "name:ben_x_preferred":[
        "Gop\u0101lpur"
    ],
    "wof:name":"Gopalpur",
    "wof:placetype":"locality"
},
  "geometry": {"coordinates":[88.80986,24.56997],"type":"Point"}
}