{
  "type": "Feature",
  "properties": {
    "gn:admin1_code":"81",
    "gn:admin2_code":"3068.0",
    "gn:admin3_code":"306864.0",
    "gn:admin4_code":"30686464.0",
    "gn:asciiname":"Char Begamabad",
    "gn:country_code":"BD",
    "gn:dem":11,
    "gn:feature_class":"P",
    "gn:feature_code":"PPL",
    "gn:name":"Char Begam\u0101b\u0101d",
    "gn:population":0,
    "gn:timezone":"Asia/Dhaka",
    "iso:country":"BD",
    "wof:name":"Char Begamabad",
    "wof:placetype":"locality"
},
  "geometry": {"coordinates":[90.96621,24.02309],"type":"Point"}
}