{
  "type": "Feature",
  "properties": {
    "gn:admin1_code":"83",
    "gn:asciiname":"Rahimapur",
    "gn:country_code":"BD",
    "gn:dem":26,
    "gn:feature_class":"P",
    "gn:feature_code":"PPL",
    "gn:name":"Rahim\u0101pur",
    "gn:population":0,
    "gn:timezone":"Asia/Dhaka",
    "iso:country":"BD",
    "name:ben_x_preferred":[
        "Rahim\u0101pur"
    ],
    "wof:name":"Rahimapur",
    "wof:placetype":"locality"
},
  "geometry": {"coordinates":[89.35524000000002,25.15255],"type":"Point"}
}