{
  "type": "Feature",
  "properties": {
    "gn:admin1_code":"82",
    "gn:admin2_code":"4050",
    "gn:admin3_code":"405071.0",
    "gn:admin4_code":"40507177.0",
    "gn:asciiname":"Oasi",
    "gn:country_code":"BD",
    "gn:dem":14,
    "gn:feature_class":"P",
    "gn:feature_code":"PPL",
    "gn:name":"O\u0101si",
    "gn:population":0,
    "gn:timezone":"Asia/Dhaka",
    "iso:country":"BD",
    "name:ben_x_preferred":[
        "O\u0101si"
    ],
    "wof:name":"Oasi",
    "wof:placetype":"locality"
},
  "geometry": {"coordinates":[89.21913000000001,23.77019],"type":"Point"}
}