{
  "type": "Feature",
  "properties": {
    "gn:admin1_code":"82",
    "gn:asciiname":"Bauria Chariana",
    "gn:country_code":"BD",
    "gn:dem":6,
    "gn:feature_class":"P",
    "gn:feature_code":"PPL",
    "gn:name":"B\u0101uria Ch\u0101ri\u0101na",
    "gn:population":0,
    "gn:timezone":"Asia/Dhaka",
    "iso:country":"BD",
    "name:ben_x_preferred":[
        "B\u0101uria Ch\u0101ri\u0101na"
    ],
    "wof:name":"Bauria Chariana",
    "wof:placetype":"locality"
},
  "geometry": {"coordinates":[90.37934,22.20529],"type":"Point"}
}