{
  "type": "Feature",
  "properties": {
    "gn:admin1_code":"H",
    "gn:admin2_code":"3072.0",
    "gn:admin3_code":"307204.0",
    "gn:admin4_code":"30720435.0",
    "gn:asciiname":"Gobindapur",
    "gn:country_code":"BD",
    "gn:dem":17,
    "gn:feature_class":"P",
    "gn:feature_code":"PPL",
    "gn:name":"Gobindapur",
    "gn:population":0,
    "gn:timezone":"Asia/Dhaka",
    "iso:country":"BD",
    "name:und_x_variant":[
        "Deogaon Gabindapur",
        "Deogaon Gobindapur",
        "Gobindapur"
    ],
    "wof:name":"Gobindapur",
    "wof:placetype":"locality"
},
  "geometry": {"coordinates":[90.89797,24.81604],"type":"Point"}
}