{
  "type": "Feature",
  "properties": {
    "gn:admin1_code":"87",
    "gn:admin2_code":"5573.0",
    "gn:admin3_code":"557364.0",
    "gn:admin4_code":"55736400.0",
    "gn:asciiname":"Pora Kukhapara",
    "gn:country_code":"BD",
    "gn:dem":47,
    "gn:feature_class":"P",
    "gn:feature_code":"PPL",
    "gn:name":"Pora Kukh\u0101p\u0101ra",
    "gn:population":0,
    "gn:timezone":"Asia/Dhaka",
    "iso:country":"BD",
    "name:ben_x_preferred":[
        "Pora Kukh\u0101p\u0101ra"
    ],
    "wof:name":"Pora Kukhapara",
    "wof:placetype":"locality"
},
  "geometry": {"coordinates":[88.85285,25.92019],"type":"Point"}
}