{
  "type": "Feature",
  "properties": {
    "gn:admin1_code":"84",
    "gn:admin2_code":"2075.0",
    "gn:admin3_code":"207507.0",
    "gn:admin4_code":"20750728.0",
    "gn:asciiname":"Abdullapur",
    "gn:country_code":"BD",
    "gn:dem":13,
    "gn:feature_class":"P",
    "gn:feature_code":"PPL",
    "gn:name":"\u0100bdull\u0101pur",
    "gn:population":0,
    "gn:timezone":"Asia/Dhaka",
    "iso:country":"BD",
    "name:ben_x_preferred":[
        "\u0986\u09ac\u09cd\u09a6\u09c1\u09b2\u09cd\u09b2\u09be\u09aa\u09c1\u09b0"
    ],
    "name:fas_x_preferred":[
        "\u0639\u0628\u062f\u0627\u0644\u0644\u0647\u200c\u067e\u0648\u0631"
    ],
    "name:tel_x_preferred":[
        "\u0c05\u0c2c\u0c4d\u0c26\u0c41\u0c32\u0c4d\u0c32\u0c3e\u0c2a\u0c42\u0c30\u0c4d"
    ],
    "wof:name":"Abdullapur",
    "wof:placetype":"locality"
},
  "geometry": {"coordinates":[90.99149,22.91206],"type":"Point"}
}