{
  "type": "Feature",
  "properties": {
    "gn:admin1_code":"84",
    "gn:admin2_code":"2075.0",
    "gn:admin3_code":"207507.0",
    "gn:admin4_code":"20750728.0",
    "gn:asciiname":"Abdullapur",
    "gn:country_code":"BD",
    "gn:dem":13,
    "gn:feature_class":"P",
    "gn:feature_code":"PPL",
    "gn:name":"\u0100bdull\u0101pur",
    "gn:population":0,
    "gn:timezone":"Asia/Dhaka",
    "iso:country":"BD",
    "wof:name":"Abdullapur",
    "wof:placetype":"locality"
},
  "geometry": {"coordinates":[90.99149,22.91206],"type":"Point"}
}