{
  "type": "Feature",
  "properties": {
    "gn:admin1_code":"83",
    "gn:admin2_code":"5081",
    "gn:admin3_code":"508134.0",
    "gn:admin4_code":"50813438.0",
    "gn:asciiname":"Kashabpur",
    "gn:country_code":"BD",
    "gn:dem":36,
    "gn:feature_class":"P",
    "gn:feature_code":"PPL",
    "gn:name":"Kashabpur",
    "gn:population":0,
    "gn:timezone":"Asia/Dhaka",
    "iso:country":"BD",
    "name:ben_x_preferred":[
        "Kashabpur"
    ],
    "name:ben_x_variant":[
        "Kesabpur"
    ],
    "wof:name":"Kashabpur",
    "wof:placetype":"locality"
},
  "geometry": {"coordinates":[88.38571,24.4961],"type":"Point"}
}