{
  "type": "Feature",
  "properties": {
    "gn:admin1_code":"85",
    "gn:admin2_code":"1004.0",
    "gn:admin3_code":"100428.0",
    "gn:admin4_code":"10042847.0",
    "gn:asciiname":"Charakgachhia",
    "gn:country_code":"BD",
    "gn:dem":12,
    "gn:feature_class":"P",
    "gn:feature_code":"PPL",
    "gn:name":"Charakgachhia",
    "gn:population":0,
    "gn:timezone":"Asia/Dhaka",
    "iso:country":"BD",
    "name:ben_x_preferred":[
        "Charakgachhia"
    ],
    "wof:name":"Charakgachhia",
    "wof:placetype":"locality"
},
  "geometry": {"coordinates":[90.05259000000002,22.08779],"type":"Point"}
}