{
  "type": "Feature",
  "properties": {
    "gn:admin1_code":"83",
    "gn:admin2_code":"5081",
    "gn:admin3_code":"508131.0",
    "gn:admin4_code":"50813111.0",
    "gn:asciiname":"Krishna Lakshmipur",
    "gn:country_code":"BD",
    "gn:dem":20,
    "gn:feature_class":"P",
    "gn:feature_code":"PPL",
    "gn:name":"Krishna Lakshmipur",
    "gn:population":0,
    "gn:timezone":"Asia/Dhaka",
    "iso:country":"BD",
    "name:ben_x_preferred":[
        "Krishna Lakshmipur"
    ],
    "name:ben_x_variant":[
        "Lakshman Khalsi"
    ],
    "wof:name":"Krishna Lakshmipur",
    "wof:placetype":"locality"
},
  "geometry": {"coordinates":[88.73918,24.46926],"type":"Point"}
}