{
  "type": "Feature",
  "properties": {
    "gn:admin1_code":"81",
    "gn:admin2_code":"3067.0",
    "gn:admin3_code":"306704.0",
    "gn:admin4_code":"30670477.0",
    "gn:asciiname":"Alampur",
    "gn:country_code":"BD",
    "gn:dem":12,
    "gn:feature_class":"P",
    "gn:feature_code":"PPL",
    "gn:name":"\u0100lampur",
    "gn:population":0,
    "gn:timezone":"Asia/Dhaka",
    "iso:country":"BD",
    "name:ceb_x_preferred":[
        "Alampur"
    ],
    "name:hin_x_preferred":[
        "\u0906\u0932\u092e\u092a\u0941\u0930"
    ],
    "name:swe_x_preferred":[
        "Alampur"
    ],
    "wof:name":"Alampur",
    "wof:placetype":"locality"
},
  "geometry": {"coordinates":[90.58418,23.7129],"type":"Point"}
}