{
  "type": "Feature",
  "properties": {
    "gn:admin1_code":"81",
    "gn:admin2_code":"3059.0",
    "gn:admin3_code":"305944.0",
    "gn:admin4_code":"30594447.0",
    "gn:asciiname":"Bankaij",
    "gn:country_code":"BD",
    "gn:dem":9,
    "gn:feature_class":"P",
    "gn:feature_code":"PPL",
    "gn:name":"B\u0101nk\u0101ij",
    "gn:population":0,
    "gn:timezone":"Asia/Dhaka",
    "iso:country":"BD",
    "wof:name":"Bankaij",
    "wof:placetype":"locality"
},
  "geometry": {"coordinates":[90.42774,23.46049],"type":"Point"}
}