{
  "type": "Feature",
  "properties": {
    "gn:admin1_code":"82",
    "gn:admin2_code":"4065.0",
    "gn:admin3_code":"406576.0",
    "gn:admin4_code":"40657627.0",
    "gn:asciiname":"Madhurgati",
    "gn:country_code":"BD",
    "gn:dem":11,
    "gn:feature_class":"P",
    "gn:feature_code":"PPL",
    "gn:name":"Madhurg\u0101ti",
    "gn:population":0,
    "gn:timezone":"Asia/Dhaka",
    "iso:country":"BD",
    "name:ben_x_preferred":[
        "Madhurg\u0101ti"
    ],
    "wof:name":"Madhurgati",
    "wof:placetype":"locality"
},
  "geometry": {"coordinates":[89.46191999999998,23.05593],"type":"Point"}
}