{
  "type": "Feature",
  "properties": {
    "gn:admin1_code":"83",
    "gn:admin2_code":"5064.0",
    "gn:admin3_code":"506428.0",
    "gn:admin4_code":"50642842.0",
    "gn:asciiname":"Haritakidanga",
    "gn:country_code":"BD",
    "gn:dem":29,
    "gn:feature_class":"P",
    "gn:feature_code":"PPL",
    "gn:name":"Haritakid\u0101nga",
    "gn:population":0,
    "gn:timezone":"Asia/Dhaka",
    "iso:country":"BD",
    "name:ben_x_preferred":[
        "Haritakid\u0101nga"
    ],
    "wof:name":"Haritakidanga",
    "wof:placetype":"locality"
},
  "geometry": {"coordinates":[88.88509999999999,25.13814],"type":"Point"}
}