{
  "type": "Feature",
  "properties": {
    "gn:admin1_code":"87",
    "gn:admin2_code":"5527",
    "gn:admin3_code":"552769.0",
    "gn:admin4_code":"55276986.0",
    "gn:asciiname":"Bayra",
    "gn:country_code":"BD",
    "gn:dem":32,
    "gn:feature_class":"P",
    "gn:feature_code":"PPL",
    "gn:name":"Bayra",
    "gn:population":0,
    "gn:timezone":"Asia/Dhaka",
    "iso:country":"BD",
    "name:ben_x_preferred":[
        "Bayra"
    ],
    "wof:name":"Bayra",
    "wof:placetype":"locality"
},
  "geometry": {"coordinates":[89.08255,25.31258],"type":"Point"}
}