{
  "type": "Feature",
  "properties": {
    "gn:admin1_code":"87",
    "gn:admin2_code":"5549",
    "gn:admin3_code":"554918.0",
    "gn:admin4_code":"55491867.0",
    "gn:asciiname":"Krishnananda Boksi",
    "gn:country_code":"BD",
    "gn:dem":33,
    "gn:feature_class":"P",
    "gn:feature_code":"PPL",
    "gn:name":"Krishnananda Boksi",
    "gn:population":0,
    "gn:timezone":"Asia/Dhaka",
    "iso:country":"BD",
    "name:ben_x_preferred":[
        "Krishnananda Boksi"
    ],
    "wof:name":"Krishnananda Boksi",
    "wof:placetype":"locality"
},
  "geometry": {"coordinates":[89.50695999999998,25.99942],"type":"Point"}
}