{
  "type": "Feature",
  "properties": {
    "gn:admin1_code":"82",
    "gn:admin2_code":"4047.0",
    "gn:admin3_code":"404730.0",
    "gn:admin4_code":"40473081.0",
    "gn:asciiname":"Dighulia",
    "gn:country_code":"BD",
    "gn:dem":4,
    "gn:feature_class":"P",
    "gn:feature_code":"PPL",
    "gn:name":"Dighulia",
    "gn:population":0,
    "gn:timezone":"Asia/Dhaka",
    "iso:country":"BD",
    "wof:name":"Dighulia",
    "wof:placetype":"locality"
},
  "geometry": {"coordinates":[89.39548000000001,22.73785],"type":"Point"}
}