{
  "type": "Feature",
  "properties": {
    "gn:admin1_code":"82",
    "gn:admin2_code":"4050",
    "gn:admin3_code":"405079.0",
    "gn:admin4_code":"40507963.0",
    "gn:asciiname":"Jhaudia",
    "gn:country_code":"BD",
    "gn:dem":18,
    "gn:feature_class":"P",
    "gn:feature_code":"PPL",
    "gn:name":"Jh\u0101udia",
    "gn:population":0,
    "gn:timezone":"Asia/Dhaka",
    "iso:country":"BD",
    "name:ben_x_preferred":[
        "Jh\u0101udia"
    ],
    "wof:name":"Jhaudia",
    "wof:placetype":"locality"
},
  "geometry": {"coordinates":[89.05542,23.77445],"type":"Point"}
}