{
  "type": "Feature",
  "properties": {
    "gn:admin1_code":"85",
    "gn:admin2_code":"1078.0",
    "gn:admin3_code":"107866.0",
    "gn:admin4_code":"10786635.0",
    "gn:asciiname":"Masuakhali",
    "gn:country_code":"BD",
    "gn:dem":11,
    "gn:feature_class":"P",
    "gn:feature_code":"PPL",
    "gn:name":"Masuakhali",
    "gn:population":0,
    "gn:timezone":"Asia/Dhaka",
    "iso:country":"BD",
    "name:ben_x_preferred":[
        "Masuakhali"
    ],
    "wof:name":"Masuakhali",
    "wof:placetype":"locality"
},
  "geometry": {"coordinates":[90.28655000000001,22.00192],"type":"Point"}
}