{
  "type": "Feature",
  "properties": {
    "gn:admin1_code":"82",
    "gn:admin2_code":"4087.0",
    "gn:admin3_code":"408782.0",
    "gn:admin4_code":"40878251.0",
    "gn:asciiname":"Byangadaha",
    "gn:country_code":"BD",
    "gn:dem":10,
    "gn:feature_class":"P",
    "gn:feature_code":"PPL",
    "gn:name":"By\u0101ngadaha",
    "gn:population":0,
    "gn:timezone":"Asia/Dhaka",
    "iso:country":"BD",
    "name:und_x_variant":[
        "By\u0101ngdaha",
        "By\u0101ngadaha"
    ],
    "wof:name":"Byangadaha",
    "wof:placetype":"locality"
},
  "geometry": {"coordinates":[89.11320000000001,22.6034],"type":"Point"}
}