{
  "type": "Feature",
  "properties": {
    "gn:admin1_code":"87",
    "gn:admin2_code":"5527",
    "gn:admin3_code":"552717.0",
    "gn:admin4_code":"55271747.0",
    "gn:asciiname":"Pipalla",
    "gn:country_code":"BD",
    "gn:dem":39,
    "gn:feature_class":"P",
    "gn:feature_code":"PPL",
    "gn:name":"Pipalla",
    "gn:population":0,
    "gn:timezone":"Asia/Dhaka",
    "iso:country":"BD",
    "name:ben_x_preferred":[
        "Pipalla"
    ],
    "name:ben_x_variant":[
        "Pipalya"
    ],
    "wof:name":"Pipalla",
    "wof:placetype":"locality"
},
  "geometry": {"coordinates":[88.56461,25.67403],"type":"Point"}
}