{
  "type": "Feature",
  "properties": {
    "gn:admin1_code":"82",
    "gn:admin2_code":"4057.0",
    "gn:admin3_code":"405787.0",
    "gn:admin4_code":"40578795.0",
    "gn:asciiname":"Katalpota",
    "gn:country_code":"BD",
    "gn:dem":16,
    "gn:feature_class":"P",
    "gn:feature_code":"PPL",
    "gn:name":"K\u0101t\u0101lpota",
    "gn:population":0,
    "gn:timezone":"Asia/Dhaka",
    "iso:country":"BD",
    "name:ben_x_preferred":[
        "K\u0101t\u0101lpota"
    ],
    "wof:name":"Katalpota",
    "wof:placetype":"locality"
},
  "geometry": {"coordinates":[88.70723000000002,23.68247],"type":"Point"}
}