{
  "type": "Feature",
  "properties": {
    "gn:admin1_code":"83",
    "gn:admin2_code":"5081.0",
    "gn:admin3_code":"508134.0",
    "gn:admin4_code":"50813447.0",
    "gn:asciiname":"Alipur",
    "gn:country_code":"BD",
    "gn:dem":27,
    "gn:feature_class":"P",
    "gn:feature_code":"PPL",
    "gn:name":"Alipur",
    "gn:population":0,
    "gn:timezone":"Asia/Dhaka",
    "iso:country":"BD",
    "name:ben_x_preferred":[
        "Alipur"
    ],
    "name:cat_x_preferred":[
        "Alipur"
    ],
    "name:ceb_x_preferred":[
        "Alipur"
    ],
    "name:swe_x_preferred":[
        "Alipur"
    ],
    "wof:name":"Alipur",
    "wof:placetype":"locality"
},
  "geometry": {"coordinates":[88.45186,24.46846],"type":"Point"}
}