{
  "type": "Feature",
  "properties": {
    "gn:admin1_code":"82",
    "gn:admin2_code":"4087",
    "gn:admin3_code":"408790.0",
    "gn:admin4_code":"40879094.0",
    "gn:asciiname":"Kalapota",
    "gn:country_code":"BD",
    "gn:dem":6,
    "gn:feature_class":"P",
    "gn:feature_code":"PPL",
    "gn:name":"Kal\u0101pota",
    "gn:population":0,
    "gn:timezone":"Asia/Dhaka",
    "iso:country":"BD",
    "wof:name":"Kalapota",
    "wof:placetype":"locality"
},
  "geometry": {"coordinates":[89.20489999999999,22.79462],"type":"Point"}
}