{
  "type": "Feature",
  "properties": {
    "gn:admin1_code":"84",
    "gn:admin2_code":"2013.0",
    "gn:admin3_code":"201349.0",
    "gn:admin4_code":"20134900.0",
    "gn:asciiname":"Dopalla",
    "gn:country_code":"BD",
    "gn:dem":9,
    "gn:feature_class":"P",
    "gn:feature_code":"PPL",
    "gn:name":"Dopalla",
    "gn:population":0,
    "gn:timezone":"Asia/Dhaka",
    "iso:country":"BD",
    "wof:name":"Dopalla",
    "wof:placetype":"locality"
},
  "geometry": {"coordinates":[90.89033000000001,23.24161],"type":"Point"}
}