{
  "type": "Feature",
  "properties": {
    "gn:admin1_code":"84",
    "gn:admin2_code":"2015.0",
    "gn:admin3_code":"201582.0",
    "gn:admin4_code":"20158269.0",
    "gn:asciiname":"Hindupara",
    "gn:country_code":"BD",
    "gn:dem":10,
    "gn:feature_class":"P",
    "gn:feature_code":"PPL",
    "gn:name":"Hindup\u0101ra",
    "gn:population":0,
    "gn:timezone":"Asia/Dhaka",
    "iso:country":"BD",
    "name:ben_x_preferred":[
        "Hindup\u0101ra"
    ],
    "wof:name":"Hindupara",
    "wof:placetype":"locality"
},
  "geometry": {"coordinates":[92.04642,22.13226],"type":"Point"}
}