{
  "type": "Feature",
  "properties": {
    "gn:admin1_code":"84",
    "gn:admin2_code":"2013",
    "gn:admin3_code":"201395.0",
    "gn:admin4_code":"20139515.0",
    "gn:asciiname":"Musadpur",
    "gn:country_code":"BD",
    "gn:dem":12,
    "gn:feature_class":"P",
    "gn:feature_code":"PPL",
    "gn:name":"Musadpur",
    "gn:population":0,
    "gn:timezone":"Asia/Dhaka",
    "iso:country":"BD",
    "name:und_x_variant":[
        "Mus\u0101dp\u0101ra"
    ],
    "wof:name":"Musadpur",
    "wof:placetype":"locality"
},
  "geometry": {"coordinates":[90.98349,23.15344],"type":"Point"}
}