{
  "type": "Feature",
  "properties": {
    "gn:admin1_code":"83",
    "gn:admin2_code":"5038.0",
    "gn:admin3_code":"503861.0",
    "gn:admin4_code":"50386109.0",
    "gn:asciiname":"Bania Chapar",
    "gn:country_code":"BD",
    "gn:dem":24,
    "gn:feature_class":"P",
    "gn:feature_code":"PPL",
    "gn:name":"B\u0101nia Ch\u0101par",
    "gn:population":0,
    "gn:timezone":"Asia/Dhaka",
    "iso:country":"BD",
    "wof:name":"Bania Chapar",
    "wof:placetype":"locality"
},
  "geometry": {"coordinates":[89.18403000000001,24.9463],"type":"Point"}
}