{
  "type": "Feature",
  "properties": {
    "gn:admin1_code":"82",
    "gn:admin2_code":"4041.0",
    "gn:admin3_code":"404147.0",
    "gn:admin4_code":"40414735.0",
    "gn:asciiname":"Dumdia",
    "gn:country_code":"BD",
    "gn:dem":13,
    "gn:feature_class":"P",
    "gn:feature_code":"PPL",
    "gn:name":"Dumdia",
    "gn:population":0,
    "gn:timezone":"Asia/Dhaka",
    "iso:country":"BD",
    "name:ben_x_preferred":[
        "Dumdia"
    ],
    "wof:name":"Dumdia",
    "wof:placetype":"locality"
},
  "geometry": {"coordinates":[89.1354,23.13222],"type":"Point"}
}