{
  "type": "Feature",
  "properties": {
    "gn:admin1_code":"87",
    "gn:admin2_code":"5594.0",
    "gn:admin3_code":"559494.0",
    "gn:admin4_code":"55949484.0",
    "gn:asciiname":"Kani Kasalcon",
    "gn:country_code":"BD",
    "gn:dem":61,
    "gn:feature_class":"P",
    "gn:feature_code":"PPL",
    "gn:name":"Kani Kasal\u00e7on",
    "gn:population":0,
    "gn:timezone":"Asia/Dhaka",
    "iso:country":"BD",
    "name:ben_x_preferred":[
        "Kani Kasal\u00e7on"
    ],
    "wof:name":"Kani Kasalcon",
    "wof:placetype":"locality"
},
  "geometry": {"coordinates":[88.37149000000002,26.16646],"type":"Point"}
}