{
  "type": "Feature",
  "properties": {
    "gn:admin1_code":"87",
    "gn:admin2_code":"5585.0",
    "gn:admin3_code":"558573.0",
    "gn:admin4_code":"55857366.0",
    "gn:asciiname":"Kismat Kala",
    "gn:country_code":"BD",
    "gn:dem":33,
    "gn:feature_class":"P",
    "gn:feature_code":"PPL",
    "gn:name":"Kismat K\u0101la",
    "gn:population":0,
    "gn:timezone":"Asia/Dhaka",
    "iso:country":"BD",
    "name:ben_x_preferred":[
        "Kismat K\u0101la"
    ],
    "wof:name":"Kismat Kala",
    "wof:placetype":"locality"
},
  "geometry": {"coordinates":[89.37317,25.66769],"type":"Point"}
}