{
  "type": "Feature",
  "properties": {
    "gn:admin1_code":"83",
    "gn:admin2_code":"5081",
    "gn:admin3_code":"508112.0",
    "gn:admin4_code":"50811263.0",
    "gn:asciiname":"Seuzbari",
    "gn:country_code":"BD",
    "gn:dem":18,
    "gn:feature_class":"P",
    "gn:feature_code":"PPL",
    "gn:name":"Seuzb\u0101ri",
    "gn:population":0,
    "gn:timezone":"Asia/Dhaka",
    "iso:country":"BD",
    "name:ben_x_preferred":[
        "Seuzb\u0101ri"
    ],
    "name:ben_x_variant":[
        "Senzb\u0101ri"
    ],
    "name:und_x_variant":[
        "Sewzbari"
    ],
    "wof:name":"Seuzbari",
    "wof:placetype":"locality"
},
  "geometry": {"coordinates":[88.89609,24.60406],"type":"Point"}
}