{
  "type": "Feature",
  "properties": {
    "gn:admin1_code":"82",
    "gn:admin2_code":"4018.0",
    "gn:admin3_code":"401855.0",
    "gn:admin4_code":"40185538.0",
    "gn:asciiname":"Pratappur",
    "gn:country_code":"BD",
    "gn:dem":18,
    "gn:feature_class":"P",
    "gn:feature_code":"PPL",
    "gn:name":"Prat\u0101ppur",
    "gn:population":0,
    "gn:timezone":"Asia/Dhaka",
    "iso:country":"BD",
    "name:ben_x_preferred":[
        "Prat\u0101ppur"
    ],
    "wof:name":"Pratappur",
    "wof:placetype":"locality"
},
  "geometry": {"coordinates":[88.8407,23.42691],"type":"Point"}
}