{
  "type": "Feature",
  "properties": {
    "gn:admin1_code":"87",
    "gn:admin2_code":"5527",
    "gn:admin3_code":"552777.0",
    "gn:admin4_code":"55277743.0",
    "gn:asciiname":"Chancha",
    "gn:country_code":"BD",
    "gn:dem":33,
    "gn:feature_class":"P",
    "gn:feature_code":"PPL",
    "gn:name":"Chancha",
    "gn:population":0,
    "gn:timezone":"Asia/Dhaka",
    "iso:country":"BD",
    "name:ben_x_preferred":[
        "Chancha"
    ],
    "wof:name":"Chancha",
    "wof:placetype":"locality"
},
  "geometry": {"coordinates":[89.02135,25.57153],"type":"Point"}
}