{
  "type": "Feature",
  "properties": {
    "gn:admin1_code":"82",
    "gn:admin2_code":"4044.0",
    "gn:admin3_code":"404419.0",
    "gn:admin4_code":"40441989.0",
    "gn:asciiname":"Borai",
    "gn:country_code":"BD",
    "gn:dem":18,
    "gn:feature_class":"P",
    "gn:feature_code":"PPL",
    "gn:name":"Borai",
    "gn:population":0,
    "gn:timezone":"Asia/Dhaka",
    "iso:country":"BD",
    "name:ara_x_preferred":[
        "\u0628\u0631\u0627\u064a\u064a"
    ],
    "name:ben_x_preferred":[
        "Borai"
    ],
    "name:fas_x_preferred":[
        "\u0628\u0631\u0627\u06cc\u06cc"
    ],
    "wof:name":"Borai",
    "wof:placetype":"locality"
},
  "geometry": {"coordinates":[88.98818,23.57059],"type":"Point"}
}