{
  "type": "Feature",
  "properties": {
    "gn:admin1_code":"81",
    "gn:admin2_code":"3054",
    "gn:admin3_code":"305454.0",
    "gn:admin4_code":"30545447.0",
    "gn:asciiname":"Nij Bajitpur",
    "gn:country_code":"BD",
    "gn:dem":11,
    "gn:feature_class":"P",
    "gn:feature_code":"PPL",
    "gn:name":"Nij B\u0101jitpur",
    "gn:population":0,
    "gn:timezone":"Asia/Dhaka",
    "iso:country":"BD",
    "wof:name":"Nij Bajitpur",
    "wof:placetype":"locality"
},
  "geometry": {"coordinates":[90.09557,23.17784],"type":"Point"}
}