{
  "type": "Feature",
  "properties": {
    "gn:admin1_code":"82",
    "gn:admin2_code":"4050",
    "gn:admin3_code":"405063.0",
    "gn:admin4_code":"40506347.0",
    "gn:asciiname":"Jagal",
    "gn:country_code":"BD",
    "gn:dem":15,
    "gn:feature_class":"P",
    "gn:feature_code":"PPL",
    "gn:name":"J\u0101gal",
    "gn:population":0,
    "gn:timezone":"Asia/Dhaka",
    "iso:country":"BD",
    "name:und_x_variant":[
        "Son\u0101p\u0101til",
        "J\u0101gal"
    ],
    "wof:name":"Jagal",
    "wof:placetype":"locality"
},
  "geometry": {"coordinates":[89.26803000000002,23.76604],"type":"Point"}
}