{
  "type": "Feature",
  "properties": {
    "gn:admin1_code":"84",
    "gn:admin2_code":"2046.0",
    "gn:admin3_code":"204661.0",
    "gn:admin4_code":"20466147.0",
    "gn:asciiname":"Digalcharipara",
    "gn:country_code":"BD",
    "gn:dem":74,
    "gn:feature_class":"P",
    "gn:feature_code":"PPL",
    "gn:name":"Digalchar\u012bp\u0101ra",
    "gn:population":0,
    "gn:timezone":"Asia/Dhaka",
    "iso:country":"BD",
    "name:ben_x_preferred":[
        "Digalchar\u012bp\u0101ra"
    ],
    "wof:name":"Digalcharipara",
    "wof:placetype":"locality"
},
  "geometry": {"coordinates":[91.94652000000001,22.83824],"type":"Point"}
}