{
  "type": "Feature",
  "properties": {
    "gn:admin1_code":"86",
    "gn:admin2_code":"6091.0",
    "gn:admin3_code":"609141.0",
    "gn:admin4_code":"60914162.0",
    "gn:asciiname":"Dakshin Pratappur",
    "gn:country_code":"BD",
    "gn:dem":20,
    "gn:feature_class":"P",
    "gn:feature_code":"PPL",
    "gn:name":"Dakshin Prat\u0101ppur",
    "gn:population":0,
    "gn:timezone":"Asia/Dhaka",
    "iso:country":"BD",
    "wof:name":"Dakshin Pratappur",
    "wof:placetype":"locality"
},
  "geometry": {"coordinates":[91.96321,25.15838],"type":"Point"}
}