{
  "type": "Feature",
  "properties": {
    "gn:admin1_code":"82",
    "gn:admin2_code":"4044.0",
    "gn:admin3_code":"404419.0",
    "gn:admin4_code":"40441942.0",
    "gn:asciiname":"Munshidanga",
    "gn:country_code":"BD",
    "gn:dem":11,
    "gn:feature_class":"P",
    "gn:feature_code":"PPL",
    "gn:name":"Munshidanga",
    "gn:population":0,
    "gn:timezone":"Asia/Dhaka",
    "iso:country":"BD",
    "name:ben_x_preferred":[
        "Munshidanga"
    ],
    "wof:name":"Munshidanga",
    "wof:placetype":"locality"
},
  "geometry": {"coordinates":[89.22565999999998,23.50645],"type":"Point"}
}