{
  "type": "Feature",
  "properties": {
    "gn:admin1_code":"81",
    "gn:admin2_code":"3056",
    "gn:admin3_code":"305610.0",
    "gn:admin4_code":"30561057.0",
    "gn:asciiname":"Purba Raghunathpur",
    "gn:country_code":"BD",
    "gn:dem":12,
    "gn:feature_class":"P",
    "gn:feature_code":"PPL",
    "gn:name":"Purba Raghun\u0101thpur",
    "gn:population":0,
    "gn:timezone":"Asia/Dhaka",
    "iso:country":"BD",
    "wof:name":"Purba Raghunathpur",
    "wof:placetype":"locality"
},
  "geometry": {"coordinates":[89.93333,23.93333],"type":"Point"}
}