{
  "type": "Feature",
  "properties": {
    "gn:admin1_code":"83",
    "gn:asciiname":"Pantabari",
    "gn:country_code":"BD",
    "gn:dem":25,
    "gn:feature_class":"P",
    "gn:feature_code":"PPL",
    "gn:name":"P\u0101ntab\u0101ri",
    "gn:population":0,
    "gn:timezone":"Asia/Dhaka",
    "iso:country":"BD",
    "name:ben_x_preferred":[
        "P\u0101ntab\u0101ri"
    ],
    "wof:name":"Pantabari",
    "wof:placetype":"locality"
},
  "geometry": {"coordinates":[89.49299000000001,25.09891],"type":"Point"}
}