{
  "type": "Feature",
  "properties": {
    "gn:admin1_code":"87",
    "gn:admin2_code":"5527.0",
    "gn:admin3_code":"552764.0",
    "gn:admin4_code":"55276425.0",
    "gn:asciiname":"Mazon",
    "gn:country_code":"BD",
    "gn:dem":39,
    "gn:feature_class":"P",
    "gn:feature_code":"PPL",
    "gn:name":"Mazon",
    "gn:population":0,
    "gn:timezone":"Asia/Dhaka",
    "iso:country":"BD",
    "name:ben_x_preferred":[
        "Mazon"
    ],
    "name:ceb_x_preferred":[
        "Mazon"
    ],
    "name:deu_x_preferred":[
        "Mazon"
    ],
    "name:fra_x_preferred":[
        "Mazon"
    ],
    "name:glg_x_preferred":[
        "Maz\u00f3n"
    ],
    "name:pol_x_preferred":[
        "Mazon"
    ],
    "name:swe_x_preferred":[
        "Mazon"
    ],
    "wof:name":"Mazon",
    "wof:placetype":"locality"
},
  "geometry": {"coordinates":[88.64426,25.66782000000001],"type":"Point"}
}