{
  "type": "Feature",
  "properties": {
    "gn:admin1_code":"83",
    "gn:admin2_code":"5010",
    "gn:admin3_code":"501095.0",
    "gn:admin4_code":"50109584.0",
    "gn:asciiname":"Baliadanga",
    "gn:country_code":"BD",
    "gn:dem":22,
    "gn:feature_class":"P",
    "gn:feature_code":"PPL",
    "gn:name":"B\u0101li\u0101d\u0101nga",
    "gn:population":0,
    "gn:timezone":"Asia/Dhaka",
    "iso:country":"BD",
    "name:ben_x_preferred":[
        "B\u0101li\u0101d\u0101nga"
    ],
    "wof:name":"Baliadanga",
    "wof:placetype":"locality"
},
  "geometry": {"coordinates":[89.57496,25.03979],"type":"Point"}
}