{
  "type": "Feature",
  "properties": {
    "gn:admin1_code":"H",
    "gn:admin2_code":"3039",
    "gn:admin3_code":"303915.0",
    "gn:admin4_code":"30391536.0",
    "gn:asciiname":"Chukaibar",
    "gn:country_code":"BD",
    "gn:dem":25,
    "gn:feature_class":"P",
    "gn:feature_code":"PPL",
    "gn:name":"Chukaibar",
    "gn:population":0,
    "gn:timezone":"Asia/Dhaka",
    "iso:country":"BD",
    "name:ben_x_preferred":[
        "Chukaibar"
    ],
    "wof:name":"Chukaibar",
    "wof:placetype":"locality"
},
  "geometry": {"coordinates":[89.77068,25.1808],"type":"Point"}
}