{
  "type": "Feature",
  "properties": {
    "gn:admin1_code":"82",
    "gn:admin2_code":"4041",
    "gn:admin3_code":"404123.0",
    "gn:admin4_code":"40412347.0",
    "gn:asciiname":"Laujani",
    "gn:country_code":"BD",
    "gn:dem":11,
    "gn:feature_class":"P",
    "gn:feature_code":"PPL",
    "gn:name":"L\u0101uj\u0101ni",
    "gn:population":0,
    "gn:timezone":"Asia/Dhaka",
    "iso:country":"BD",
    "name:ben_x_preferred":[
        "L\u0101uj\u0101ni"
    ],
    "wof:name":"Laujani",
    "wof:placetype":"locality"
},
  "geometry": {"coordinates":[89.12137,23.12396],"type":"Point"}
}