{
  "type": "Feature",
  "properties": {
    "gn:admin1_code":"84",
    "gn:admin2_code":"2051",
    "gn:admin3_code":"205143.0",
    "gn:admin4_code":"20514350.0",
    "gn:asciiname":"Isabpur",
    "gn:country_code":"BD",
    "gn:dem":10,
    "gn:feature_class":"P",
    "gn:feature_code":"PPL",
    "gn:name":"Isabpur",
    "gn:population":0,
    "gn:timezone":"Asia/Dhaka",
    "iso:country":"BD",
    "wof:name":"Isabpur",
    "wof:placetype":"locality"
},
  "geometry": {"coordinates":[90.96007,22.94649],"type":"Point"}
}