{
  "type": "Feature",
  "properties": {
    "gn:admin1_code":"81",
    "gn:admin2_code":"3048",
    "gn:admin3_code":"304879.0",
    "gn:admin4_code":"30487976.0",
    "gn:asciiname":"Paik Lakshmia",
    "gn:country_code":"BD",
    "gn:dem":15,
    "gn:feature_class":"P",
    "gn:feature_code":"PPL",
    "gn:name":"P\u0101ik Lakshmia",
    "gn:population":0,
    "gn:timezone":"Asia/Dhaka",
    "iso:country":"BD",
    "wof:name":"Paik Lakshmia",
    "wof:placetype":"locality"
},
  "geometry": {"coordinates":[90.67357,24.32828],"type":"Point"}
}