{
  "type": "Feature",
  "properties": {
    "gn:admin1_code":"H",
    "gn:admin2_code":"3039.0",
    "gn:admin3_code":"303961.0",
    "gn:admin4_code":"30396195.0",
    "gn:asciiname":"Bani Pakuria",
    "gn:country_code":"BD",
    "gn:dem":22,
    "gn:feature_class":"P",
    "gn:feature_code":"PPL",
    "gn:name":"B\u0101ni P\u0101kuria",
    "gn:population":0,
    "gn:timezone":"Asia/Dhaka",
    "iso:country":"BD",
    "wof:name":"Bani Pakuria",
    "wof:placetype":"locality"
},
  "geometry": {"coordinates":[89.86976999999997,24.96061],"type":"Point"}
}