{
  "type": "Feature",
  "properties": {
    "gn:admin1_code":"84",
    "gn:admin2_code":"2046.0",
    "gn:admin3_code":"204670.0",
    "gn:admin4_code":"20467035.0",
    "gn:asciiname":"Paindoagpara",
    "gn:country_code":"BD",
    "gn:dem":76,
    "gn:feature_class":"P",
    "gn:feature_code":"PPL",
    "gn:name":"P\u0101indoagp\u00e3ra",
    "gn:population":0,
    "gn:timezone":"Asia/Dhaka",
    "iso:country":"BD",
    "name:ben_x_preferred":[
        "P\u0101indoagp\u00e3ra"
    ],
    "wof:name":"Paindoagpara",
    "wof:placetype":"locality"
},
  "geometry": {"coordinates":[91.94419000000001,22.98368],"type":"Point"}
}