{
  "type": "Feature",
  "properties": {
    "gn:admin1_code":"82",
    "gn:admin2_code":"4047.0",
    "gn:admin3_code":"404740.0",
    "gn:admin4_code":"40474085.0",
    "gn:asciiname":"Batibhita",
    "gn:country_code":"BD",
    "gn:dem":9,
    "gn:feature_class":"P",
    "gn:feature_code":"PPL",
    "gn:name":"B\u0101tibhita",
    "gn:population":0,
    "gn:timezone":"Asia/Dhaka",
    "iso:country":"BD",
    "name:ben_x_preferred":[
        "B\u0101tibhita"
    ],
    "wof:name":"Batibhita",
    "wof:placetype":"locality"
},
  "geometry": {"coordinates":[89.56085999999998,22.87813],"type":"Point"}
}