{
  "type": "Feature",
  "properties": {
    "gn:admin1_code":"81",
    "gn:admin2_code":"3033",
    "gn:admin3_code":"303334.0",
    "gn:admin4_code":"30333486.0",
    "gn:asciiname":"Tumlia",
    "gn:country_code":"BD",
    "gn:dem":14,
    "gn:feature_class":"P",
    "gn:feature_code":"PPL",
    "gn:name":"Tumlia",
    "gn:population":0,
    "gn:timezone":"Asia/Dhaka",
    "iso:country":"BD",
    "wof:name":"Tumlia",
    "wof:placetype":"locality"
},
  "geometry": {"coordinates":[90.55029999999999,23.92614],"type":"Point"}
}