{
  "type": "Feature",
  "properties": {
    "gn:admin1_code":"82",
    "gn:admin2_code":"4041.0",
    "gn:admin3_code":"404104.0",
    "gn:admin4_code":"40410431.0",
    "gn:asciiname":"Harishpur",
    "gn:country_code":"BD",
    "gn:dem":8,
    "gn:feature_class":"P",
    "gn:feature_code":"PPL",
    "gn:name":"Harishpur",
    "gn:population":0,
    "gn:timezone":"Asia/Dhaka",
    "iso:country":"BD",
    "name:ben_x_preferred":[
        "Harishpur"
    ],
    "name:ben_x_variant":[
        "\u09b9\u09b0\u09bf\u09b6\u09aa\u09c1\u09b0"
    ],
    "name:bpy_x_preferred":[
        "\u09b9\u09b0\u09bf\u09b6\u09aa\u09c1\u09b0"
    ],
    "name:ita_x_preferred":[
        "Harishpur"
    ],
    "name:mlg_x_preferred":[
        "Harishpur"
    ],
    "name:msa_x_preferred":[
        "Harishpur"
    ],
    "name:new_x_preferred":[
        "\u0939\u0930\u093f\u0936\u092a\u0941\u0930"
    ],
    "name:nld_x_preferred":[
        "Harishpur"
    ],
    "name:por_x_preferred":[
        "Harishpur"
    ],
    "name:vie_x_preferred":[
        "Harishpur"
    ],
    "name:zho_x_preferred":[
        "\u54c8\u91cc\u65af\u8d6b\u666e\u5c14"
    ],
    "wof:name":"Harishpur",
    "wof:placetype":"locality"
},
  "geometry": {"coordinates":[89.34263,23.05196],"type":"Point"}
}