{
  "type": "Feature",
  "properties": {
    "gn:admin1_code":"82",
    "gn:admin2_code":"4041.0",
    "gn:admin3_code":"404104.0",
    "gn:admin4_code":"40410431.0",
    "gn:asciiname":"Harishpur",
    "gn:country_code":"BD",
    "gn:dem":8,
    "gn:feature_class":"P",
    "gn:feature_code":"PPL",
    "gn:name":"Harishpur",
    "gn:population":0,
    "gn:timezone":"Asia/Dhaka",
    "iso:country":"BD",
    "name:ben_x_preferred":[
        "Harishpur"
    ],
    "wof:name":"Harishpur",
    "wof:placetype":"locality"
},
  "geometry": {"coordinates":[89.34263,23.05196],"type":"Point"}
}