{
  "type": "Feature",
  "properties": {
    "gn:admin1_code":"81",
    "gn:admin2_code":"3059",
    "gn:admin3_code":"305924.0",
    "gn:admin4_code":"30592463.0",
    "gn:asciiname":"Raghur Char",
    "gn:country_code":"BD",
    "gn:dem":9,
    "gn:feature_class":"P",
    "gn:feature_code":"PPL",
    "gn:name":"Raghur Char",
    "gn:population":0,
    "gn:timezone":"Asia/Dhaka",
    "iso:country":"BD",
    "wof:name":"Raghur Char",
    "wof:placetype":"locality"
},
  "geometry": {"coordinates":[90.58765,23.58299],"type":"Point"}
}