{
  "type": "Feature",
  "properties": {
    "gn:admin1_code":"81",
    "gn:admin2_code":"3033",
    "gn:admin3_code":"303386.0",
    "gn:admin4_code":"30338638.0",
    "gn:asciiname":"Pathantek",
    "gn:country_code":"BD",
    "gn:dem":16,
    "gn:feature_class":"P",
    "gn:feature_code":"PPL",
    "gn:name":"P\u0101th\u0101ntek",
    "gn:population":0,
    "gn:timezone":"Asia/Dhaka",
    "iso:country":"BD",
    "wof:name":"Pathantek",
    "wof:placetype":"locality"
},
  "geometry": {"coordinates":[90.52315,24.25292],"type":"Point"}
}