{
  "type": "Feature",
  "properties": {
    "gn:admin1_code":"87",
    "gn:admin2_code":"5594.0",
    "gn:admin3_code":"559486.0",
    "gn:admin4_code":"55948679.0",
    "gn:asciiname":"Ghanasyampur",
    "gn:country_code":"BD",
    "gn:dem":51,
    "gn:feature_class":"P",
    "gn:feature_code":"PPL",
    "gn:name":"Ghan\u0101syampur",
    "gn:population":0,
    "gn:timezone":"Asia/Dhaka",
    "iso:country":"BD",
    "name:ben_x_preferred":[
        "Ghan\u0101syampur"
    ],
    "wof:name":"Ghanasyampur",
    "wof:placetype":"locality"
},
  "geometry": {"coordinates":[88.28628,25.96139],"type":"Point"}
}