{
  "type": "Feature",
  "properties": {
    "gn:admin1_code":"87",
    "gn:admin2_code":"5577.0",
    "gn:admin3_code":"557773.0",
    "gn:admin4_code":"55777336.0",
    "gn:asciiname":"Jatanpokhri",
    "gn:country_code":"BD",
    "gn:dem":79,
    "gn:feature_class":"P",
    "gn:feature_code":"PPL",
    "gn:name":"Jatanpokhri",
    "gn:population":0,
    "gn:timezone":"Asia/Dhaka",
    "iso:country":"BD",
    "name:ben_x_preferred":[
        "Jatanpokhri"
    ],
    "wof:name":"Jatanpokhri",
    "wof:placetype":"locality"
},
  "geometry": {"coordinates":[88.52833000000003,26.32594000000001],"type":"Point"}
}