{
  "type": "Feature",
  "properties": {
    "gn:admin1_code":"82",
    "gn:asciiname":"Dakurbania",
    "gn:country_code":"BD",
    "gn:dem":8,
    "gn:feature_class":"P",
    "gn:feature_code":"PPL",
    "gn:name":"D\u0101kurbania",
    "gn:population":0,
    "gn:timezone":"Asia/Dhaka",
    "iso:country":"BD",
    "name:ben_x_preferred":[
        "D\u0101kurbania"
    ],
    "wof:name":"Dakurbania",
    "wof:placetype":"locality"
},
  "geometry": {"coordinates":[90.28371,22.40742],"type":"Point"}
}