{
  "type": "Feature",
  "properties": {
    "gn:admin1_code":"82",
    "gn:admin2_code":"4041.0",
    "gn:admin3_code":"404109.0",
    "gn:admin4_code":"40410909.0",
    "gn:asciiname":"Basuari",
    "gn:country_code":"BD",
    "gn:dem":14,
    "gn:feature_class":"P",
    "gn:feature_code":"PPL",
    "gn:name":"Basu\u0101ri",
    "gn:population":0,
    "gn:timezone":"Asia/Dhaka",
    "iso:country":"BD",
    "name:ben_x_preferred":[
        "Basu\u0101ri"
    ],
    "wof:name":"Basuari",
    "wof:placetype":"locality"
},
  "geometry": {"coordinates":[89.35775,23.15635],"type":"Point"}
}