{
  "type": "Feature",
  "properties": {
    "gn:admin1_code":"H",
    "gn:admin2_code":"3061.0",
    "gn:admin3_code":"306181.0",
    "gn:admin4_code":"30618113.0",
    "gn:asciiname":"Gajiapara",
    "gn:country_code":"BD",
    "gn:dem":19,
    "gn:feature_class":"P",
    "gn:feature_code":"PPL",
    "gn:name":"Gaji\u0101p\u0101ra",
    "gn:population":0,
    "gn:timezone":"Asia/Dhaka",
    "iso:country":"BD",
    "wof:name":"Gajiapara",
    "wof:placetype":"locality"
},
  "geometry": {"coordinates":[90.41901,24.8894],"type":"Point"}
}