{
  "type": "Feature",
  "properties": {
    "gn:admin1_code":"81",
    "gn:admin2_code":"3086.0",
    "gn:admin3_code":"308636.0",
    "gn:admin4_code":"30863659.0",
    "gn:asciiname":"Balikuri",
    "gn:country_code":"BD",
    "gn:dem":14,
    "gn:feature_class":"P",
    "gn:feature_code":"PPL",
    "gn:name":"B\u0101likuri",
    "gn:population":0,
    "gn:timezone":"Asia/Dhaka",
    "iso:country":"BD",
    "name:und_x_variant":[
        "Balikuni",
        "B\u0101likuri"
    ],
    "wof:name":"Balikuri",
    "wof:placetype":"locality"
},
  "geometry": {"coordinates":[90.37899,23.09714],"type":"Point"}
}