{
  "type": "Feature",
  "properties": {
    "gn:admin1_code":"H",
    "gn:admin2_code":"3039",
    "gn:admin3_code":"303961.0",
    "gn:admin4_code":"30396166.0",
    "gn:asciiname":"Dephlapara",
    "gn:country_code":"BD",
    "gn:dem":26,
    "gn:feature_class":"P",
    "gn:feature_code":"PPL",
    "gn:name":"Dephlapara",
    "gn:population":0,
    "gn:timezone":"Asia/Dhaka",
    "iso:country":"BD",
    "name:ben_x_preferred":[
        "Dephlapara"
    ],
    "wof:name":"Dephlapara",
    "wof:placetype":"locality"
},
  "geometry": {"coordinates":[89.83374999999999,25.02062],"type":"Point"}
}