{
  "type": "Feature",
  "properties": {
    "gn:admin1_code":"87",
    "gn:admin2_code":"5532",
    "gn:admin3_code":"553230.0",
    "gn:admin4_code":"55323033.0",
    "gn:asciiname":"Kanatikor",
    "gn:country_code":"BD",
    "gn:dem":27,
    "gn:feature_class":"P",
    "gn:feature_code":"PPL",
    "gn:name":"Kan\u0101tikor",
    "gn:population":0,
    "gn:timezone":"Asia/Dhaka",
    "iso:country":"BD",
    "name:ben_x_preferred":[
        "Kan\u0101tikor"
    ],
    "wof:name":"Kanatikor",
    "wof:placetype":"locality"
},
  "geometry": {"coordinates":[89.27280999999998,25.20509],"type":"Point"}
}