{
  "type": "Feature",
  "properties": {
    "gn:admin1_code":"87",
    "gn:admin2_code":"5577.0",
    "gn:admin3_code":"557773.0",
    "gn:admin4_code":"55777335.0",
    "gn:asciiname":"Pokhridanga",
    "gn:country_code":"BD",
    "gn:dem":81,
    "gn:feature_class":"P",
    "gn:feature_code":"PPL",
    "gn:name":"Pokhrid\u0101nga",
    "gn:population":0,
    "gn:timezone":"Asia/Dhaka",
    "iso:country":"BD",
    "name:ben_x_preferred":[
        "Pokhrid\u0101nga"
    ],
    "wof:name":"Pokhridanga",
    "wof:placetype":"locality"
},
  "geometry": {"coordinates":[88.59867,26.41248],"type":"Point"}
}