{
  "type": "Feature",
  "properties": {
    "gn:admin1_code":"82",
    "gn:admin2_code":"4050.0",
    "gn:admin3_code":"405079.0",
    "gn:admin4_code":"40507994.0",
    "gn:asciiname":"Rajitpur",
    "gn:country_code":"BD",
    "gn:dem":15,
    "gn:feature_class":"P",
    "gn:feature_code":"PPL",
    "gn:name":"Rajitpur",
    "gn:population":0,
    "gn:timezone":"Asia/Dhaka",
    "iso:country":"BD",
    "name:ben_x_preferred":[
        "Rajitpur"
    ],
    "wof:name":"Rajitpur",
    "wof:placetype":"locality"
},
  "geometry": {"coordinates":[89.13704,23.78752],"type":"Point"}
}