{
  "type": "Feature",
  "properties": {
    "gn:admin1_code":"83",
    "gn:admin2_code":"5081.0",
    "gn:admin3_code":"508131.0",
    "gn:admin4_code":"50813111.0",
    "gn:asciiname":"Amgram",
    "gn:country_code":"BD",
    "gn:dem":19,
    "gn:feature_class":"P",
    "gn:feature_code":"PPL",
    "gn:name":"Amgram",
    "gn:population":0,
    "gn:timezone":"Asia/Dhaka",
    "iso:country":"BD",
    "name:ben_x_preferred":[
        "Amgram"
    ],
    "wof:name":"Amgram",
    "wof:placetype":"locality"
},
  "geometry": {"coordinates":[88.72584999999999,24.4521],"type":"Point"}
}