{
  "type": "Feature",
  "properties": {
    "gn:admin1_code":"84",
    "gn:admin2_code":"2084.0",
    "gn:admin3_code":"208447.0",
    "gn:admin4_code":"20844738.0",
    "gn:asciiname":"Thakhara",
    "gn:country_code":"BD",
    "gn:dem":71,
    "gn:feature_class":"P",
    "gn:feature_code":"PPL",
    "gn:name":"Th\u0101khara",
    "gn:population":0,
    "gn:timezone":"Asia/Dhaka",
    "iso:country":"BD",
    "name:ben_x_preferred":[
        "Th\u0101khara"
    ],
    "wof:name":"Thakhara",
    "wof:placetype":"locality"
},
  "geometry": {"coordinates":[92.52379999999999,22.59295],"type":"Point"}
}