{
  "type": "Feature",
  "properties": {
    "gn:admin1_code":"83",
    "gn:admin2_code":"5064.0",
    "gn:admin3_code":"506406.0",
    "gn:admin4_code":"50640652.0",
    "gn:asciiname":"Champadal",
    "gn:country_code":"BD",
    "gn:dem":25,
    "gn:feature_class":"P",
    "gn:feature_code":"PPL",
    "gn:name":"Ch\u0101mp\u0101dal",
    "gn:population":0,
    "gn:timezone":"Asia/Dhaka",
    "iso:country":"BD",
    "name:ben_x_preferred":[
        "Ch\u0101mp\u0101dal"
    ],
    "wof:name":"Champadal",
    "wof:placetype":"locality"
},
  "geometry": {"coordinates":[89.00785999999999,25.02809],"type":"Point"}
}