{
  "type": "Feature",
  "properties": {
    "gn:admin1_code":"81",
    "gn:admin2_code":"3035.0",
    "gn:admin3_code":"303543.0",
    "gn:admin4_code":"30354381.0",
    "gn:asciiname":"Mahishapora",
    "gn:country_code":"BD",
    "gn:dem":14,
    "gn:feature_class":"P",
    "gn:feature_code":"PPL",
    "gn:name":"Mahishapora",
    "gn:population":0,
    "gn:timezone":"Asia/Dhaka",
    "iso:country":"BD",
    "name:ben_x_preferred":[
        "Mahishapora"
    ],
    "wof:name":"Mahishapora",
    "wof:placetype":"locality"
},
  "geometry": {"coordinates":[89.68999000000002,23.18143],"type":"Point"}
}