{
  "type": "Feature",
  "properties": {
    "gn:admin1_code":"H",
    "gn:admin2_code":"3072.0",
    "gn:admin3_code":"307256.0",
    "gn:admin4_code":"30725673.0",
    "gn:asciiname":"Gabar Deotala",
    "gn:country_code":"BD",
    "gn:dem":13,
    "gn:feature_class":"P",
    "gn:feature_code":"PPL",
    "gn:name":"G\u0101bar Deotala",
    "gn:population":0,
    "gn:timezone":"Asia/Dhaka",
    "iso:country":"BD",
    "wof:name":"Gabar Deotala",
    "wof:placetype":"locality"
},
  "geometry": {"coordinates":[90.91235,24.65715],"type":"Point"}
}