{
  "type": "Feature",
  "properties": {
    "gn:admin1_code":"87",
    "gn:admin2_code":"5585",
    "gn:admin3_code":"558576.0",
    "gn:admin4_code":"55857618.0",
    "gn:asciiname":"Pakura",
    "gn:country_code":"BD",
    "gn:dem":31,
    "gn:feature_class":"P",
    "gn:feature_code":"PPL",
    "gn:name":"Pakura",
    "gn:population":0,
    "gn:timezone":"Asia/Dhaka",
    "iso:country":"BD",
    "name:ben_x_preferred":[
        "Pakura"
    ],
    "name:ben_x_variant":[
        "Pakuria"
    ],
    "wof:name":"Pakura",
    "wof:placetype":"locality"
},
  "geometry": {"coordinates":[89.20784,25.48394],"type":"Point"}
}