{
  "type": "Feature",
  "properties": {
    "gn:admin1_code":"83",
    "gn:admin2_code":"5064.0",
    "gn:admin3_code":"506486.0",
    "gn:admin4_code":"50648671.0",
    "gn:asciiname":"Karaldanga",
    "gn:country_code":"BD",
    "gn:dem":45,
    "gn:feature_class":"P",
    "gn:feature_code":"PPL",
    "gn:name":"Karald\u0101nga",
    "gn:population":0,
    "gn:timezone":"Asia/Dhaka",
    "iso:country":"BD",
    "name:ben_x_preferred":[
        "Karald\u0101nga"
    ],
    "wof:name":"Karaldanga",
    "wof:placetype":"locality"
},
  "geometry": {"coordinates":[88.59147,25.11847],"type":"Point"}
}