{
  "type": "Feature",
  "properties": {
    "gn:admin1_code":"83",
    "gn:admin2_code":"5070.0",
    "gn:admin3_code":"507056.0",
    "gn:admin4_code":"50705619.0",
    "gn:asciiname":"Mabaldanga",
    "gn:country_code":"BD",
    "gn:dem":39,
    "gn:feature_class":"P",
    "gn:feature_code":"PPL",
    "gn:name":"Mabald\u0101nga",
    "gn:population":0,
    "gn:timezone":"Asia/Dhaka",
    "iso:country":"BD",
    "name:ben_x_preferred":[
        "Mabald\u0101nga"
    ],
    "wof:name":"Mabaldanga",
    "wof:placetype":"locality"
},
  "geometry": {"coordinates":[88.35343,24.72494],"type":"Point"}
}