{
  "type": "Feature",
  "properties": {
    "gn:admin1_code":"81",
    "gn:admin2_code":"3086",
    "gn:admin3_code":"308665.0",
    "gn:admin4_code":"30866588.0",
    "gn:asciiname":"Hogla Char",
    "gn:country_code":"BD",
    "gn:dem":0,
    "gn:feature_class":"P",
    "gn:feature_code":"PPL",
    "gn:name":"Hogla Char",
    "gn:population":0,
    "gn:timezone":"Asia/Dhaka",
    "iso:country":"BD",
    "wof:name":"Hogla Char",
    "wof:placetype":"locality"
},
  "geometry": {"coordinates":[90.46666999999999,23.38333],"type":"Point"}
}