{
  "type": "Feature",
  "properties": {
    "gn:admin1_code":"84",
    "gn:admin2_code":"2019",
    "gn:admin3_code":"201968.0",
    "gn:admin4_code":"20196814.0",
    "gn:asciiname":"Kalikapur",
    "gn:country_code":"BD",
    "gn:dem":14,
    "gn:feature_class":"P",
    "gn:feature_code":"PPL",
    "gn:name":"Kalikapur",
    "gn:population":0,
    "gn:timezone":"Asia/Dhaka",
    "iso:country":"BD",
    "name:und_x_variant":[
        "Kamalpur",
        "Kaml\u0101pur",
        "Kalikapur"
    ],
    "wof:name":"Kalikapur",
    "wof:placetype":"locality"
},
  "geometry": {"coordinates":[91.20671,23.36619],"type":"Point"}
}