{
  "type": "Feature",
  "properties": {
    "gn:admin1_code":"H",
    "gn:admin2_code":"3039",
    "gn:admin3_code":"303907.0",
    "gn:admin4_code":"30390759.0",
    "gn:asciiname":"Khewar Char",
    "gn:country_code":"BD",
    "gn:dem":24,
    "gn:feature_class":"P",
    "gn:feature_code":"PPL",
    "gn:name":"Khewar Char",
    "gn:population":0,
    "gn:timezone":"Asia/Dhaka",
    "iso:country":"BD",
    "name:ben_x_preferred":[
        "Khewar Char"
    ],
    "wof:name":"Khewar Char",
    "wof:placetype":"locality"
},
  "geometry": {"coordinates":[89.82585999999998,25.18616],"type":"Point"}
}