{
  "type": "Feature",
  "properties": {
    "gn:admin1_code":"84",
    "gn:admin2_code":"2084",
    "gn:admin3_code":"208429.0",
    "gn:admin4_code":"20842947.0",
    "gn:asciiname":"Mashkubha",
    "gn:country_code":"BD",
    "gn:dem":55,
    "gn:feature_class":"P",
    "gn:feature_code":"PPL",
    "gn:name":"Mashkubha",
    "gn:population":0,
    "gn:timezone":"Asia/Dhaka",
    "iso:country":"BD",
    "wof:name":"Mashkubha",
    "wof:placetype":"locality"
},
  "geometry": {"coordinates":[92.38155,22.39117],"type":"Point"}
}