{
  "type": "Feature",
  "properties": {
    "gn:admin1_code":"87",
    "gn:admin2_code":"5577.0",
    "gn:admin3_code":"557734.0",
    "gn:admin4_code":"55773428.0",
    "gn:asciiname":"Maria Kamalapokhri",
    "gn:country_code":"BD",
    "gn:dem":59,
    "gn:feature_class":"P",
    "gn:feature_code":"PPL",
    "gn:name":"Maria Kamalapokhri",
    "gn:population":0,
    "gn:timezone":"Asia/Dhaka",
    "iso:country":"BD",
    "name:ben_x_preferred":[
        "Maria Kamalapokhri"
    ],
    "wof:name":"Maria Kamalapokhri",
    "wof:placetype":"locality"
},
  "geometry": {"coordinates":[88.69389,26.0834],"type":"Point"}
}