{
  "type": "Feature",
  "properties": {
    "gn:admin1_code":"82",
    "gn:admin2_code":"4087.0",
    "gn:admin3_code":"408786.0",
    "gn:admin4_code":"40878631.0",
    "gn:asciiname":"Jeleykhali",
    "gn:country_code":"BD",
    "gn:dem":2,
    "gn:feature_class":"P",
    "gn:feature_code":"PPL",
    "gn:name":"Jeleykh\u0101li",
    "gn:population":0,
    "gn:timezone":"Asia/Dhaka",
    "iso:country":"BD",
    "name:ben_x_preferred":[
        "Jeleykh\u0101li"
    ],
    "wof:name":"Jeleykhali",
    "wof:placetype":"locality"
},
  "geometry": {"coordinates":[89.30946,22.28239],"type":"Point"}
}