{
  "type": "Feature",
  "properties": {
    "gn:admin1_code":"84",
    "gn:admin2_code":"2019.0",
    "gn:admin3_code":"201981.0",
    "gn:admin4_code":"20198140.0",
    "gn:asciiname":"Gangatia",
    "gn:country_code":"BD",
    "gn:dem":12,
    "gn:feature_class":"P",
    "gn:feature_code":"PPL",
    "gn:name":"G\u0101ng\u0101tia",
    "gn:population":0,
    "gn:timezone":"Asia/Dhaka",
    "iso:country":"BD",
    "wof:name":"Gangatia",
    "wof:placetype":"locality"
},
  "geometry": {"coordinates":[90.87257,23.63486],"type":"Point"}
}