{
  "type": "Feature",
  "properties": {
    "gn:admin1_code":"81",
    "gn:admin2_code":"3056.0",
    "gn:admin3_code":"305646.0",
    "gn:admin4_code":"30564655.0",
    "gn:asciiname":"Diara Golara Chandi",
    "gn:country_code":"BD",
    "gn:dem":16,
    "gn:feature_class":"P",
    "gn:feature_code":"PPL",
    "gn:name":"Di\u0101ra Gol\u0101ra Ch\u0101ndi",
    "gn:population":0,
    "gn:timezone":"Asia/Dhaka",
    "iso:country":"BD",
    "wof:name":"Diara Golara Chandi",
    "wof:placetype":"locality"
},
  "geometry": {"coordinates":[90.03230000000001,23.88548],"type":"Point"}
}