{
  "type": "Feature",
  "properties": {
    "gn:admin1_code":"84",
    "gn:admin2_code":"2015.0",
    "gn:admin3_code":"201518.0",
    "gn:admin4_code":"20151838.0",
    "gn:asciiname":"Chem",
    "gn:country_code":"BD",
    "gn:dem":20,
    "gn:feature_class":"P",
    "gn:feature_code":"PPL",
    "gn:name":"Chem",
    "gn:population":0,
    "gn:timezone":"Asia/Dhaka",
    "iso:country":"BD",
    "name:ben_x_preferred":[
        "Chem"
    ],
    "name:und_x_variant":[
        "Chemi"
    ],
    "wof:name":"Chem",
    "wof:placetype":"locality"
},
  "geometry": {"coordinates":[92.14615000000001,22.21385],"type":"Point"}
}