{
  "type": "Feature",
  "properties": {
    "gn:admin1_code":"83",
    "gn:admin2_code":"5064",
    "gn:admin3_code":"506469.0",
    "gn:admin4_code":"50646931.0",
    "gn:asciiname":"Pungi",
    "gn:country_code":"BD",
    "gn:dem":24,
    "gn:feature_class":"P",
    "gn:feature_code":"PPL",
    "gn:name":"Pungi",
    "gn:population":0,
    "gn:timezone":"Asia/Dhaka",
    "iso:country":"BD",
    "name:ben_x_preferred":[
        "Pungi"
    ],
    "wof:name":"Pungi",
    "wof:placetype":"locality"
},
  "geometry": {"coordinates":[88.62836,24.93938],"type":"Point"}
}