{
  "type": "Feature",
  "properties": {
    "gn:admin1_code":"83",
    "gn:admin2_code":"5064",
    "gn:admin3_code":"506469.0",
    "gn:admin4_code":"50646931.0",
    "gn:asciiname":"Pungi",
    "gn:country_code":"BD",
    "gn:dem":24,
    "gn:feature_class":"P",
    "gn:feature_code":"PPL",
    "gn:name":"Pungi",
    "gn:population":0,
    "gn:timezone":"Asia/Dhaka",
    "iso:country":"BD",
    "name:aze_x_preferred":[
        "Pungi"
    ],
    "name:ben_x_preferred":[
        "Pungi"
    ],
    "name:bih_x_preferred":[
        "\u092c\u0940\u0928"
    ],
    "name:deu_x_preferred":[
        "Pungi"
    ],
    "name:fin_x_preferred":[
        "P\u016bngi"
    ],
    "name:fra_x_preferred":[
        "Pungi"
    ],
    "name:hin_x_preferred":[
        "\u092c\u0940\u0928"
    ],
    "name:ita_x_preferred":[
        "Pungi"
    ],
    "name:kaz_x_preferred":[
        "\u041f\u0443\u043d\u0433\u0438"
    ],
    "name:lav_x_preferred":[
        "Pungi"
    ],
    "name:mal_x_preferred":[
        "\u0d2e\u0d15\u0d41\u0d1f\u0d3f"
    ],
    "name:mar_x_preferred":[
        "\u092a\u0941\u0902\u0917\u0940"
    ],
    "name:pan_x_preferred":[
        "\u0a2c\u0a40\u0a28"
    ],
    "name:pol_x_preferred":[
        "Pungi"
    ],
    "name:rus_x_preferred":[
        "\u041f\u0443\u043d\u0433\u0438"
    ],
    "name:spa_x_preferred":[
        "Pungi"
    ],
    "name:swe_x_preferred":[
        "Pungi"
    ],
    "name:tam_x_preferred":[
        "\u0bae\u0b95\u0bc1\u0b9f\u0bbf"
    ],
    "name:tel_x_preferred":[
        "\u0c2a\u0c3e\u0c2e\u0c41\u0c32 \u0c2c\u0c41\u0c30\u0c4d\u0c30"
    ],
    "name:tur_x_preferred":[
        "Pungi"
    ],
    "wof:name":"Pungi",
    "wof:placetype":"locality"
},
  "geometry": {"coordinates":[88.62836,24.93938],"type":"Point"}
}