{
  "type": "Feature",
  "properties": {
    "gn:admin1_code":"H",
    "gn:admin2_code":"3061",
    "gn:admin3_code":"306181.0",
    "gn:admin4_code":"30618190.0",
    "gn:asciiname":"Putia",
    "gn:country_code":"BD",
    "gn:dem":18,
    "gn:feature_class":"P",
    "gn:feature_code":"PPL",
    "gn:name":"Putia",
    "gn:population":0,
    "gn:timezone":"Asia/Dhaka",
    "iso:country":"BD",
    "wof:name":"Putia",
    "wof:placetype":"locality"
},
  "geometry": {"coordinates":[90.30905,24.99537],"type":"Point"}
}