{
  "type": "Feature",
  "properties": {
    "gn:admin1_code":"85",
    "gn:admin2_code":"1009.0",
    "gn:admin3_code":"100921.0",
    "gn:admin4_code":"10092128.0",
    "gn:asciiname":"Dakshin Chhota Manika",
    "gn:country_code":"BD",
    "gn:dem":11,
    "gn:feature_class":"P",
    "gn:feature_code":"PPL",
    "gn:name":"Dakshin Chhota M\u0101nika",
    "gn:population":0,
    "gn:timezone":"Asia/Dhaka",
    "iso:country":"BD",
    "name:und_x_variant":[
        "Dakshin Chhota M\u0101nika",
        "Chhota M\u0101nika"
    ],
    "wof:name":"Dakshin Chhota Manika",
    "wof:placetype":"locality"
},
  "geometry": {"coordinates":[90.68924,22.50677],"type":"Point"}
}