{
  "type": "Feature",
  "properties": {
    "gn:admin1_code":"82",
    "gn:admin2_code":"4050.0",
    "gn:admin3_code":"405079.0",
    "gn:admin4_code":"40507982.0",
    "gn:asciiname":"Gangaparkandi",
    "gn:country_code":"BD",
    "gn:dem":17,
    "gn:feature_class":"P",
    "gn:feature_code":"PPL",
    "gn:name":"Gangapark\u0101ndi",
    "gn:population":0,
    "gn:timezone":"Asia/Dhaka",
    "iso:country":"BD",
    "name:ben_x_preferred":[
        "Gangapark\u0101ndi"
    ],
    "wof:name":"Gangaparkandi",
    "wof:placetype":"locality"
},
  "geometry": {"coordinates":[89.0638,23.72979],"type":"Point"}
}