{
  "type": "Feature",
  "properties": {
    "gn:admin1_code":"81",
    "gn:admin2_code":"3026.0",
    "gn:admin3_code":"302614.0",
    "gn:admin4_code":"30261405.0",
    "gn:asciiname":"Amta",
    "gn:country_code":"BD",
    "gn:dem":14,
    "gn:feature_class":"P",
    "gn:feature_code":"PPL",
    "gn:name":"\u0100mta",
    "gn:population":0,
    "gn:timezone":"Asia/Dhaka",
    "iso:country":"BD",
    "name:ceb_x_preferred":[
        "\u0100mta"
    ],
    "name:swe_x_preferred":[
        "\u0100mta"
    ],
    "wof:name":"Amta",
    "wof:placetype":"locality"
},
  "geometry": {"coordinates":[90.05699,23.99542000000001],"type":"Point"}
}