{
  "type": "Feature",
  "properties": {
    "gn:admin1_code":"87",
    "gn:admin2_code":"5577.0",
    "gn:admin3_code":"557725.0",
    "gn:admin4_code":"55772507.0",
    "gn:asciiname":"Arazi Maria",
    "gn:country_code":"BD",
    "gn:dem":69,
    "gn:feature_class":"P",
    "gn:feature_code":"PPL",
    "gn:name":"Ar\u0101zi Maria",
    "gn:population":0,
    "gn:timezone":"Asia/Dhaka",
    "iso:country":"BD",
    "name:ben_x_preferred":[
        "Ar\u0101zi Maria"
    ],
    "wof:name":"Arazi Maria",
    "wof:placetype":"locality"
},
  "geometry": {"coordinates":[88.69168000000001,26.25775],"type":"Point"}
}