{
  "type": "Feature",
  "properties": {
    "gn:admin1_code":"81",
    "gn:admin2_code":"3048.0",
    "gn:admin3_code":"304892.0",
    "gn:admin4_code":"30489281.0",
    "gn:asciiname":"Hajipur",
    "gn:country_code":"BD",
    "gn:dem":14,
    "gn:feature_class":"P",
    "gn:feature_code":"PPL",
    "gn:name":"H\u0101jipur",
    "gn:population":0,
    "gn:timezone":"Asia/Dhaka",
    "iso:country":"BD",
    "name:und_x_variant":[
        "H\u0101jipur",
        "H\u0101zipur"
    ],
    "wof:name":"Hajipur",
    "wof:placetype":"locality"
},
  "geometry": {"coordinates":[90.84538000000001,24.54411],"type":"Point"}
}