{
  "type": "Feature",
  "properties": {
    "gn:admin1_code":"83",
    "gn:admin2_code":"5064",
    "gn:admin3_code":"506460.0",
    "gn:admin4_code":"50646000.0",
    "gn:asciiname":"Khalishakuri",
    "gn:country_code":"BD",
    "gn:dem":20,
    "gn:feature_class":"P",
    "gn:feature_code":"PPL",
    "gn:name":"Khalish\u0101kuri",
    "gn:population":0,
    "gn:timezone":"Asia/Dhaka",
    "iso:country":"BD",
    "name:ben_x_preferred":[
        "Khalish\u0101kuri"
    ],
    "name:ben_x_variant":[
        "Khalis\u0101kuri"
    ],
    "name:und_x_variant":[
        "Khaliashakuri"
    ],
    "wof:name":"Khalishakuri",
    "wof:placetype":"locality"
},
  "geometry": {"coordinates":[88.93876999999998,24.83216],"type":"Point"}
}