{
  "type": "Feature",
  "properties": {
    "gn:admin1_code":"87",
    "gn:admin2_code":"5585",
    "gn:admin3_code":"558549.0",
    "gn:admin4_code":"55854910.0",
    "gn:asciiname":"Keshabpur",
    "gn:country_code":"BD",
    "gn:dem":37,
    "gn:feature_class":"P",
    "gn:feature_code":"PPL",
    "gn:name":"Keshabpur",
    "gn:population":0,
    "gn:timezone":"Asia/Dhaka",
    "iso:country":"BD",
    "name:ben_x_preferred":[
        "Keshabpur"
    ],
    "name:ben_x_variant":[
        "Kesabpur",
        "Kismut Kesubpoor"
    ],
    "name:hif_x_preferred":[
        "Keshabpur"
    ],
    "wof:name":"Keshabpur",
    "wof:placetype":"locality"
},
  "geometry": {"coordinates":[89.15957,25.69443],"type":"Point"}
}