{
  "type": "Feature",
  "properties": {
    "gn:admin1_code":"H",
    "gn:admin2_code":"3072.0",
    "gn:admin3_code":"307283.0",
    "gn:admin4_code":"30728355.0",
    "gn:asciiname":"Gohalakanda",
    "gn:country_code":"BD",
    "gn:dem":15,
    "gn:feature_class":"P",
    "gn:feature_code":"PPL",
    "gn:name":"Gohalak\u0101nda",
    "gn:population":0,
    "gn:timezone":"Asia/Dhaka",
    "iso:country":"BD",
    "wof:name":"Gohalakanda",
    "wof:placetype":"locality"
},
  "geometry": {"coordinates":[90.58928,24.84881],"type":"Point"}
}