{
  "type": "Feature",
  "properties": {
    "gn:admin1_code":"83",
    "gn:admin2_code":"5010.0",
    "gn:admin3_code":"501054.0",
    "gn:admin4_code":"50105476.0",
    "gn:asciiname":"Binod",
    "gn:country_code":"BD",
    "gn:dem":23,
    "gn:feature_class":"P",
    "gn:feature_code":"PPL",
    "gn:name":"Binod",
    "gn:population":0,
    "gn:timezone":"Asia/Dhaka",
    "iso:country":"BD",
    "name:und_x_variant":[
        "Binode",
        "Binod"
    ],
    "wof:name":"Binod",
    "wof:placetype":"locality"
},
  "geometry": {"coordinates":[89.2597,24.88471],"type":"Point"}
}