{
  "type": "Feature",
  "properties": {
    "gn:admin1_code":"87",
    "gn:admin2_code":"5577.0",
    "gn:admin3_code":"557773.0",
    "gn:admin4_code":"55777359.0",
    "gn:asciiname":"Telipara",
    "gn:country_code":"BD",
    "gn:dem":71,
    "gn:feature_class":"P",
    "gn:feature_code":"PPL",
    "gn:name":"Telip\u0101ra",
    "gn:population":0,
    "gn:timezone":"Asia/Dhaka",
    "iso:country":"BD",
    "name:ben_x_preferred":[
        "Telip\u0101ra"
    ],
    "wof:name":"Telipara",
    "wof:placetype":"locality"
},
  "geometry": {"coordinates":[88.64695,26.33133],"type":"Point"}
}