{
  "type": "Feature",
  "properties": {
    "gn:admin1_code":"87",
    "gn:asciiname":"Chhat Telai",
    "gn:country_code":"BD",
    "gn:dem":36,
    "gn:feature_class":"P",
    "gn:feature_code":"PPL",
    "gn:name":"Chh\u0101t Telai",
    "gn:population":0,
    "gn:timezone":"Asia/Dhaka",
    "iso:country":"BD",
    "name:und_x_variant":[
        "Chhat Tilai",
        "Chh\u0101t Telai"
    ],
    "wof:name":"Chhat Telai",
    "wof:placetype":"locality"
},
  "geometry": {"coordinates":[89.70517,26.17781],"type":"Point"}
}