{
  "type": "Feature",
  "properties": {
    "gn:admin1_code":"83",
    "gn:admin2_code":"5070.0",
    "gn:admin3_code":"507088.0",
    "gn:admin4_code":"50708895.0",
    "gn:asciiname":"Paka Dighaltola",
    "gn:country_code":"BD",
    "gn:dem":23,
    "gn:feature_class":"P",
    "gn:feature_code":"PPL",
    "gn:name":"Paka Dighaltola",
    "gn:population":0,
    "gn:timezone":"Asia/Dhaka",
    "iso:country":"BD",
    "name:ben_x_preferred":[
        "Paka Dighaltola"
    ],
    "wof:name":"Paka Dighaltola",
    "wof:placetype":"locality"
},
  "geometry": {"coordinates":[88.15061999999998,24.59707],"type":"Point"}
}