{
  "type": "Feature",
  "properties": {
    "gn:admin1_code":"87",
    "gn:admin2_code":"5577",
    "gn:admin3_code":"557725.0",
    "gn:admin4_code":"55772587.0",
    "gn:asciiname":"Sukhanpukhari",
    "gn:country_code":"BD",
    "gn:dem":62,
    "gn:feature_class":"P",
    "gn:feature_code":"PPL",
    "gn:name":"Sukhanpukhari",
    "gn:population":0,
    "gn:timezone":"Asia/Dhaka",
    "iso:country":"BD",
    "name:ben_x_preferred":[
        "Sukhanpokhri"
    ],
    "name:ben_x_variant":[
        "Sukhanpukhari"
    ],
    "wof:name":"Sukhanpukhari",
    "wof:placetype":"locality"
},
  "geometry": {"coordinates":[88.62758000000002,26.11207000000001],"type":"Point"}
}