{
  "type": "Feature",
  "properties": {
    "gn:admin1_code":"84",
    "gn:admin2_code":"2003.0",
    "gn:admin3_code":"200395.0",
    "gn:admin4_code":"20039538.0",
    "gn:asciiname":"Ningraipara",
    "gn:country_code":"BD",
    "gn:dem":235,
    "gn:feature_class":"P",
    "gn:feature_code":"PPL",
    "gn:name":"Ningraip\u0101ra",
    "gn:population":0,
    "gn:timezone":"Asia/Dhaka",
    "iso:country":"BD",
    "name:ben_x_preferred":[
        "Ningraip\u0101ra"
    ],
    "wof:name":"Ningraipara",
    "wof:placetype":"locality"
},
  "geometry": {"coordinates":[92.51751,21.71907],"type":"Point"}
}