{
  "type": "Feature",
  "properties": {
    "gn:admin1_code":"82",
    "gn:admin2_code":"4018.0",
    "gn:admin3_code":"401823.0",
    "gn:admin4_code":"40182347.0",
    "gn:asciiname":"Kumriadanga",
    "gn:country_code":"BD",
    "gn:dem":17,
    "gn:feature_class":"P",
    "gn:feature_code":"PPL",
    "gn:name":"Kumri\u0101d\u0101nga",
    "gn:population":0,
    "gn:timezone":"Asia/Dhaka",
    "iso:country":"BD",
    "name:ben_x_preferred":[
        "Kumri\u0101d\u0101nga"
    ],
    "wof:name":"Kumriadanga",
    "wof:placetype":"locality"
},
  "geometry": {"coordinates":[88.94954,23.59825],"type":"Point"}
}