{
  "type": "Feature",
  "properties": {
    "gn:admin1_code":"81",
    "gn:admin2_code":"3082",
    "gn:admin3_code":"308276.0",
    "gn:admin4_code":"30827680.0",
    "gn:asciiname":"Ramkantapur",
    "gn:country_code":"BD",
    "gn:dem":17,
    "gn:feature_class":"P",
    "gn:feature_code":"PPL",
    "gn:name":"R\u0101mk\u0101ntapur",
    "gn:population":0,
    "gn:timezone":"Asia/Dhaka",
    "iso:country":"BD",
    "wof:name":"Ramkantapur",
    "wof:placetype":"locality"
},
  "geometry": {"coordinates":[89.64699,23.73803],"type":"Point"}
}