{
  "type": "Feature",
  "properties": {
    "gn:admin1_code":"81",
    "gn:admin2_code":"3067.0",
    "gn:admin3_code":"306758.0",
    "gn:admin4_code":"30675837.0",
    "gn:asciiname":"Chashara",
    "gn:country_code":"BD",
    "gn:dem":9,
    "gn:feature_class":"P",
    "gn:feature_code":"PPL",
    "gn:name":"Ch\u0101sh\u0101ra",
    "gn:population":0,
    "gn:timezone":"Asia/Dhaka",
    "iso:country":"BD",
    "wof:name":"Chashara",
    "wof:placetype":"locality"
},
  "geometry": {"coordinates":[90.49684000000001,23.62502000000001],"type":"Point"}
}