{
  "type": "Feature",
  "properties": {
    "gn:admin1_code":"81",
    "gn:admin2_code":"3068.0",
    "gn:admin3_code":"306876.0",
    "gn:admin4_code":"30687631.0",
    "gn:asciiname":"Bailaba",
    "gn:country_code":"BD",
    "gn:dem":13,
    "gn:feature_class":"P",
    "gn:feature_code":"PPL",
    "gn:name":"Bail\u0101ba",
    "gn:population":0,
    "gn:timezone":"Asia/Dhaka",
    "iso:country":"BD",
    "wof:name":"Bailaba",
    "wof:placetype":"locality"
},
  "geometry": {"coordinates":[90.73316,24.08617000000001],"type":"Point"}
}