{
  "type": "Feature",
  "properties": {
    "gn:admin1_code":"81",
    "gn:admin2_code":"3026.0",
    "gn:admin3_code":"302614.0",
    "gn:admin4_code":"30261494.0",
    "gn:asciiname":"Chhota Kalampur",
    "gn:country_code":"BD",
    "gn:dem":13,
    "gn:feature_class":"P",
    "gn:feature_code":"PPL",
    "gn:name":"Chhota K\u0101l\u0101mpur",
    "gn:population":0,
    "gn:timezone":"Asia/Dhaka",
    "iso:country":"BD",
    "wof:name":"Chhota Kalampur",
    "wof:placetype":"locality"
},
  "geometry": {"coordinates":[90.15047,23.92187],"type":"Point"}
}