{
  "type": "Feature",
  "properties": {
    "gn:admin1_code":"82",
    "gn:admin2_code":"4044.0",
    "gn:admin3_code":"404419.0",
    "gn:admin4_code":"40441900.0",
    "gn:asciiname":"Gilabaria",
    "gn:country_code":"BD",
    "gn:dem":14,
    "gn:feature_class":"P",
    "gn:feature_code":"PPL",
    "gn:name":"Gil\u0101b\u0101ria",
    "gn:population":0,
    "gn:timezone":"Asia/Dhaka",
    "iso:country":"BD",
    "name:ben_x_preferred":[
        "Gil\u0101b\u0101ria"
    ],
    "wof:name":"Gilabaria",
    "wof:placetype":"locality"
},
  "geometry": {"coordinates":[89.14855,23.56102000000001],"type":"Point"}
}