{
  "type": "Feature",
  "properties": {
    "gn:admin1_code":"81",
    "gn:admin2_code":"3029",
    "gn:admin3_code":"302903.0",
    "gn:admin4_code":"30290331.0",
    "gn:asciiname":"Phalia",
    "gn:country_code":"BD",
    "gn:dem":13,
    "gn:feature_class":"P",
    "gn:feature_code":"PPL",
    "gn:name":"Phalia",
    "gn:population":0,
    "gn:timezone":"Asia/Dhaka",
    "iso:country":"BD",
    "name:ceb_x_preferred":[
        "Ph\u0101lia"
    ],
    "name:fas_x_preferred":[
        "\u062a\u062d\u0635\u06cc\u0644 \u067e\u0647\u0627\u0644\u06cc\u0647"
    ],
    "name:fra_x_preferred":[
        "Phalia"
    ],
    "name:pnb_x_preferred":[
        "\u0641\u0627\u0644\u06cc\u0627"
    ],
    "name:por_x_preferred":[
        "Phalia"
    ],
    "name:urd_x_preferred":[
        "\u067e\u06be\u0627\u0644\u06cc\u06c1"
    ],
    "wof:name":"Phalia",
    "wof:placetype":"locality"
},
  "geometry": {"coordinates":[89.70574999999999,23.31383],"type":"Point"}
}