{
  "type": "Feature",
  "properties": {
    "gn:admin1_code":"84",
    "gn:admin2_code":"2030",
    "gn:admin3_code":"203025.0",
    "gn:admin4_code":"20302577.0",
    "gn:asciiname":"Sikandarpur",
    "gn:cc2":"BD",
    "gn:country_code":"BD",
    "gn:dem":10,
    "gn:feature_class":"P",
    "gn:feature_code":"PPL",
    "gn:name":"Sikandarpur",
    "gn:population":0,
    "gn:timezone":"Asia/Dhaka",
    "iso:country":"BD",
    "name:und_x_variant":[
        "Sekandarpur",
        "Sikandarpur"
    ],
    "wof:name":"Sikandarpur",
    "wof:placetype":"locality"
},
  "geometry": {"coordinates":[91.26667,22.95],"type":"Point"}
}