{
  "type": "Feature",
  "properties": {
    "gn:admin1_code":"87",
    "gn:admin2_code":"5552",
    "gn:admin3_code":"555202.0",
    "gn:admin4_code":"55520205.0",
    "gn:asciiname":"Arazi Deodoba",
    "gn:country_code":"BD",
    "gn:dem":36,
    "gn:feature_class":"P",
    "gn:feature_code":"PPL",
    "gn:name":"Arazi Deodoba",
    "gn:population":0,
    "gn:timezone":"Asia/Dhaka",
    "iso:country":"BD",
    "name:ben_x_preferred":[
        "Arazi Deodoba"
    ],
    "wof:name":"Arazi Deodoba",
    "wof:placetype":"locality"
},
  "geometry": {"coordinates":[89.36043000000002,25.90374],"type":"Point"}
}