{
  "type": "Feature",
  "properties": {
    "gn:country":"BD",
    "gn:fcode":"PPL",
    "gn:pop":31671,
    "iso:country":"BD",
    "qs:name":"Nab\u012bnagar",
    "qs:photos_9r":0,
    "qs:photos_sr":0,
    "qs:pop_sr":"7",
    "wof:name":"Nab\u012bnagar",
    "wof:placetype":"locality",
    "wof:population":31671
},
  "geometry": {"coordinates":[90.96792000000001,23.88791],"type":"Point"}
}