{
  "type": "Feature",
  "properties": {
    "gn:admin1_code":"83",
    "gn:admin2_code":"5081.0",
    "gn:admin3_code":"508153.0",
    "gn:admin4_code":"50815381.0",
    "gn:asciiname":"Barail",
    "gn:country_code":"BD",
    "gn:dem":21,
    "gn:feature_class":"P",
    "gn:feature_code":"PPL",
    "gn:name":"Bar\u0101il",
    "gn:population":0,
    "gn:timezone":"Asia/Dhaka",
    "iso:country":"BD",
    "name:ben_x_preferred":[
        "Bar\u0101il"
    ],
    "wof:name":"Barail",
    "wof:placetype":"locality"
},
  "geometry": {"coordinates":[88.66029,24.62725],"type":"Point"}
}