{
  "type": "Feature",
  "properties": {
    "gn:admin1_code":"87",
    "gn:admin2_code":"5527.0",
    "gn:admin3_code":"552721.0",
    "gn:admin4_code":"55272113.0",
    "gn:asciiname":"Mandalpara",
    "gn:country_code":"BD",
    "gn:dem":45,
    "gn:feature_class":"P",
    "gn:feature_code":"PPL",
    "gn:name":"Mandalp\u0101ra",
    "gn:population":0,
    "gn:timezone":"Asia/Dhaka",
    "iso:country":"BD",
    "name:ben_x_preferred":[
        "Mandalp\u0101ra"
    ],
    "wof:name":"Mandalpara",
    "wof:placetype":"locality"
},
  "geometry": {"coordinates":[88.50121,25.77909],"type":"Point"}
}