{
  "type": "Feature",
  "properties": {
    "gn:admin1_code":"84",
    "gn:admin2_code":"2046.0",
    "gn:admin3_code":"204680.0",
    "gn:admin4_code":"20468038.0",
    "gn:asciiname":"Aungjaphrupara",
    "gn:country_code":"BD",
    "gn:dem":70,
    "gn:feature_class":"P",
    "gn:feature_code":"PPL",
    "gn:name":"Aungjaphrup\u0101ra",
    "gn:population":0,
    "gn:timezone":"Asia/Dhaka",
    "iso:country":"BD",
    "name:ben_x_preferred":[
        "Aungjaphrup\u0101ra"
    ],
    "wof:name":"Aungjaphrupara",
    "wof:placetype":"locality"
},
  "geometry": {"coordinates":[91.93685000000001,22.90808],"type":"Point"}
}