{
  "type": "Feature",
  "properties": {
    "gn:admin1_code":"87",
    "gn:admin2_code":"5594.0",
    "gn:admin3_code":"559408.0",
    "gn:admin4_code":"55940810.0",
    "gn:asciiname":"Harinmari",
    "gn:country_code":"BD",
    "gn:dem":53,
    "gn:feature_class":"P",
    "gn:feature_code":"PPL",
    "gn:name":"Harinm\u0101ri",
    "gn:population":0,
    "gn:timezone":"Asia/Dhaka",
    "iso:country":"BD",
    "name:ben_x_preferred":[
        "Harinm\u0101ri"
    ],
    "wof:name":"Harinmari",
    "wof:placetype":"locality"
},
  "geometry": {"coordinates":[88.21955,26.12303],"type":"Point"}
}