{
  "type": "Feature",
  "properties": {
    "gn:admin1_code":"H",
    "gn:admin2_code":"3061",
    "gn:admin3_code":"306131.0",
    "gn:admin4_code":"30613145.0",
    "gn:asciiname":"Khalbola",
    "gn:country_code":"BD",
    "gn:dem":13,
    "gn:feature_class":"P",
    "gn:feature_code":"PPL",
    "gn:name":"Kh\u0101lbola",
    "gn:population":0,
    "gn:timezone":"Asia/Dhaka",
    "iso:country":"BD",
    "wof:name":"Khalbola",
    "wof:placetype":"locality"
},
  "geometry": {"coordinates":[90.68733,24.63706],"type":"Point"}
}