{
  "type": "Feature",
  "properties": {
    "gn:admin1_code":"87",
    "gn:admin2_code":"5577.0",
    "gn:admin3_code":"557773.0",
    "gn:admin4_code":"55777365.0",
    "gn:asciiname":"Haripara",
    "gn:country_code":"BD",
    "gn:dem":75,
    "gn:feature_class":"P",
    "gn:feature_code":"PPL",
    "gn:name":"Harip\u0101ra",
    "gn:population":0,
    "gn:timezone":"Asia/Dhaka",
    "iso:country":"BD",
    "name:ben_x_preferred":[
        "Harip\u0101ra"
    ],
    "wof:name":"Haripara",
    "wof:placetype":"locality"
},
  "geometry": {"coordinates":[88.49478000000001,26.2817],"type":"Point"}
}