{
  "type": "Feature",
  "properties": {
    "gn:admin1_code":"H",
    "gn:admin2_code":"3061.0",
    "gn:admin3_code":"306165.0",
    "gn:admin4_code":"30616577.0",
    "gn:asciiname":"Gojanga",
    "gn:country_code":"BD",
    "gn:dem":20,
    "gn:feature_class":"P",
    "gn:feature_code":"PPL",
    "gn:name":"Goj\u0101nga",
    "gn:population":0,
    "gn:timezone":"Asia/Dhaka",
    "iso:country":"BD",
    "wof:name":"Gojanga",
    "wof:placetype":"locality"
},
  "geometry": {"coordinates":[90.19884,24.76091],"type":"Point"}
}