{
  "type": "Feature",
  "properties": {
    "gn:admin1_code":"81",
    "gn:admin2_code":"3054",
    "gn:admin3_code":"305480.0",
    "gn:admin4_code":"30548028.0",
    "gn:asciiname":"Sataria",
    "gn:country_code":"BD",
    "gn:dem":9,
    "gn:feature_class":"P",
    "gn:feature_code":"PPL",
    "gn:name":"S\u0101t\u0101ria",
    "gn:population":0,
    "gn:timezone":"Asia/Dhaka",
    "iso:country":"BD",
    "name:nld_x_preferred":[
        "Sataria"
    ],
    "wof:name":"Sataria",
    "wof:placetype":"locality"
},
  "geometry": {"coordinates":[90.08568,23.18249],"type":"Point"}
}