{
  "type": "Feature",
  "properties": {
    "gn:admin1_code":"81",
    "gn:admin2_code":"3068",
    "gn:admin3_code":"306863.0",
    "gn:admin4_code":"30686347.0",
    "gn:asciiname":"Ichhakhali",
    "gn:country_code":"BD",
    "gn:dem":12,
    "gn:feature_class":"P",
    "gn:feature_code":"PPL",
    "gn:name":"Ichh\u0101kh\u0101li",
    "gn:population":0,
    "gn:timezone":"Asia/Dhaka",
    "iso:country":"BD",
    "wof:name":"Ichhakhali",
    "wof:placetype":"locality"
},
  "geometry": {"coordinates":[90.69432999999999,23.97158],"type":"Point"}
}