{
  "type": "Feature",
  "properties": {
    "gn:admin1_code":"87",
    "gn:admin2_code":"5552",
    "gn:admin3_code":"555255.0",
    "gn:admin4_code":"55525536.0",
    "gn:asciiname":"Dakshin Batrish Hazari",
    "gn:country_code":"BD",
    "gn:dem":36,
    "gn:feature_class":"P",
    "gn:feature_code":"PPL",
    "gn:name":"Dakshin Batrish Hazari",
    "gn:population":0,
    "gn:timezone":"Asia/Dhaka",
    "iso:country":"BD",
    "name:ben_x_preferred":[
        "Dakshin Batrish Hazari"
    ],
    "wof:name":"Dakshin Batrish Hazari",
    "wof:placetype":"locality"
},
  "geometry": {"coordinates":[89.39986999999998,25.8914],"type":"Point"}
}