{
  "type": "Feature",
  "properties": {
    "gn:admin1_code":"84",
    "gn:admin2_code":"2022.0",
    "gn:admin3_code":"202290.0",
    "gn:admin4_code":"20229031.0",
    "gn:asciiname":"Fulerdeil",
    "gn:country_code":"BD",
    "gn:dem":15,
    "gn:feature_class":"P",
    "gn:feature_code":"PPL",
    "gn:name":"Fulerdeil",
    "gn:population":0,
    "gn:timezone":"Asia/Dhaka",
    "iso:country":"BD",
    "name:ben_x_preferred":[
        "Fulerdeil"
    ],
    "wof:name":"Fulerdeil",
    "wof:placetype":"locality"
},
  "geometry": {"coordinates":[92.22957,21.0053],"type":"Point"}
}