{
  "type": "Feature",
  "properties": {
    "gn:admin1_code":"83",
    "gn:admin2_code":"5064.0",
    "gn:admin3_code":"506475.0",
    "gn:admin4_code":"50647534.0",
    "gn:asciiname":"Nadhuni",
    "gn:country_code":"BD",
    "gn:dem":22,
    "gn:feature_class":"P",
    "gn:feature_code":"PPL",
    "gn:name":"Nadhuni",
    "gn:population":0,
    "gn:timezone":"Asia/Dhaka",
    "iso:country":"BD",
    "name:ben_x_preferred":[
        "Nadhuni"
    ],
    "wof:name":"Nadhuni",
    "wof:placetype":"locality"
},
  "geometry": {"coordinates":[88.78645,25.01788],"type":"Point"}
}