{
  "type": "Feature",
  "properties": {
    "gn:admin1_code":"82",
    "gn:admin2_code":"4041.0",
    "gn:admin3_code":"404109.0",
    "gn:admin4_code":"40410966.0",
    "gn:asciiname":"Majiali",
    "gn:country_code":"BD",
    "gn:dem":16,
    "gn:feature_class":"P",
    "gn:feature_code":"PPL",
    "gn:name":"M\u0101ji\u0101li",
    "gn:population":0,
    "gn:timezone":"Asia/Dhaka",
    "iso:country":"BD",
    "name:ben_x_preferred":[
        "M\u0101ji\u0101li"
    ],
    "wof:name":"Majiali",
    "wof:placetype":"locality"
},
  "geometry": {"coordinates":[89.24204,23.30578],"type":"Point"}
}