{
  "type": "Feature",
  "properties": {
    "gn:admin1_code":"87",
    "gn:admin2_code":"5594.0",
    "gn:admin3_code":"559408.0",
    "gn:admin4_code":"55940821.0",
    "gn:asciiname":"Barakot",
    "gn:country_code":"BD",
    "gn:dem":52,
    "gn:feature_class":"P",
    "gn:feature_code":"PPL",
    "gn:name":"Barakot",
    "gn:population":0,
    "gn:timezone":"Asia/Dhaka",
    "iso:country":"BD",
    "name:ben_x_preferred":[
        "Barakot"
    ],
    "wof:name":"Barakot",
    "wof:placetype":"locality"
},
  "geometry": {"coordinates":[88.24164,26.10149],"type":"Point"}
}