{
  "type": "Feature",
  "properties": {
    "gn:admin1_code":"85",
    "gn:admin2_code":"1042.0",
    "gn:admin3_code":"104243.0",
    "gn:admin4_code":"10424394.0",
    "gn:asciiname":"Dakshin Charail",
    "gn:country_code":"BD",
    "gn:dem":12,
    "gn:feature_class":"P",
    "gn:feature_code":"PPL",
    "gn:name":"Dakshin Char\u0101il",
    "gn:population":0,
    "gn:timezone":"Asia/Dhaka",
    "iso:country":"BD",
    "name:ben_x_preferred":[
        "Dakshin Char\u0101il"
    ],
    "wof:name":"Dakshin Charail",
    "wof:placetype":"locality"
},
  "geometry": {"coordinates":[90.11711,22.4602],"type":"Point"}
}