{
  "type": "Feature",
  "properties": {
    "gn:admin1_code":"H",
    "gn:admin2_code":"3061",
    "gn:admin3_code":"306165.0",
    "gn:admin4_code":"30616525.0",
    "gn:asciiname":"Sukpatuli",
    "gn:country_code":"BD",
    "gn:dem":18,
    "gn:feature_class":"P",
    "gn:feature_code":"PPL",
    "gn:name":"Sukp\u0101tuli",
    "gn:population":0,
    "gn:timezone":"Asia/Dhaka",
    "iso:country":"BD",
    "wof:name":"Sukpatuli",
    "wof:placetype":"locality"
},
  "geometry": {"coordinates":[90.19893999999999,24.66168],"type":"Point"}
}