{
  "type": "Feature",
  "properties": {
    "gn:admin1_code":"87",
    "gn:admin2_code":"5527.0",
    "gn:admin3_code":"552710.0",
    "gn:admin4_code":"55271023.0",
    "gn:asciiname":"Pali Khanpur",
    "gn:country_code":"BD",
    "gn:dem":31,
    "gn:feature_class":"P",
    "gn:feature_code":"PPL",
    "gn:name":"Pali Kh\u0101npur",
    "gn:population":0,
    "gn:timezone":"Asia/Dhaka",
    "iso:country":"BD",
    "name:ben_x_preferred":[
        "Pali Kh\u0101npur"
    ],
    "wof:name":"Pali Khanpur",
    "wof:placetype":"locality"
},
  "geometry": {"coordinates":[88.95104000000001,25.35131],"type":"Point"}
}