{
  "type": "Feature",
  "properties": {
    "gn:admin1_code":"H",
    "gn:admin2_code":"3072.0",
    "gn:admin3_code":"307274.0",
    "gn:admin4_code":"30727479.0",
    "gn:asciiname":"Baje Amli",
    "gn:country_code":"BD",
    "gn:dem":13,
    "gn:feature_class":"P",
    "gn:feature_code":"PPL",
    "gn:name":"B\u0101je \u0100mli",
    "gn:population":0,
    "gn:timezone":"Asia/Dhaka",
    "iso:country":"BD",
    "wof:name":"Baje Amli",
    "wof:placetype":"locality"
},
  "geometry": {"coordinates":[90.70567,24.9046],"type":"Point"}
}