{
  "type": "Feature",
  "properties": {
    "gn:admin1_code":"83",
    "gn:admin2_code":"5081",
    "gn:admin3_code":"508131.0",
    "gn:admin4_code":"50813123.0",
    "gn:asciiname":"Paikartuli",
    "gn:country_code":"BD",
    "gn:dem":19,
    "gn:feature_class":"P",
    "gn:feature_code":"PPL",
    "gn:name":"P\u0101ik\u0101rtuli",
    "gn:population":0,
    "gn:timezone":"Asia/Dhaka",
    "iso:country":"BD",
    "name:ben_x_preferred":[
        "P\u0101ik\u0101rtuli"
    ],
    "wof:name":"Paikartuli",
    "wof:placetype":"locality"
},
  "geometry": {"coordinates":[88.79819000000001,24.4494],"type":"Point"}
}