{
  "type": "Feature",
  "properties": {
    "gn:admin1_code":"81",
    "gn:admin2_code":"3029.0",
    "gn:admin3_code":"302984.0",
    "gn:admin4_code":"30298476.0",
    "gn:asciiname":"Biswanathpur",
    "gn:country_code":"BD",
    "gn:dem":1,
    "gn:feature_class":"P",
    "gn:feature_code":"PPL",
    "gn:name":"Biswan\u0101thpur",
    "gn:population":0,
    "gn:timezone":"Asia/Dhaka",
    "iso:country":"BD",
    "wof:name":"Biswanathpur",
    "wof:placetype":"locality"
},
  "geometry": {"coordinates":[90.12384,23.5509],"type":"Point"}
}