{
  "type": "Feature",
  "properties": {
    "gn:admin1_code":"86",
    "gn:admin2_code":"6036.0",
    "gn:admin3_code":"603644.0",
    "gn:admin4_code":"60364428.0",
    "gn:asciiname":"Gajariakandi",
    "gn:country_code":"BD",
    "gn:dem":13,
    "gn:feature_class":"P",
    "gn:feature_code":"PPL",
    "gn:name":"Gaj\u0101ri\u0101k\u0101ndi",
    "gn:population":0,
    "gn:timezone":"Asia/Dhaka",
    "iso:country":"BD",
    "name:und_x_variant":[
        "Gazariakandi",
        "Guj\u0101r\u0101k\u0101ndi",
        "Gaj\u0101ri\u0101k\u0101ndi"
    ],
    "wof:name":"Gajariakandi",
    "wof:placetype":"locality"
},
  "geometry": {"coordinates":[91.3623,24.3857],"type":"Point"}
}