{
  "type": "Feature",
  "properties": {
    "gn:admin1_code":"H",
    "gn:admin2_code":"3089",
    "gn:admin3_code":"308970.0",
    "gn:admin4_code":"30897008.0",
    "gn:asciiname":"Gobinda",
    "gn:country_code":"BD",
    "gn:dem":21,
    "gn:feature_class":"P",
    "gn:feature_code":"PPL",
    "gn:name":"Gobinda",
    "gn:population":0,
    "gn:timezone":"Asia/Dhaka",
    "iso:country":"BD",
    "name:ben_x_preferred":[
        "Gobinda"
    ],
    "wof:name":"Gobinda",
    "wof:placetype":"locality"
},
  "geometry": {"coordinates":[90.16482000000001,25.0959],"type":"Point"}
}