{
  "type": "Feature",
  "properties": {
    "gn:admin1_code":"83",
    "gn:admin2_code":"5069.0",
    "gn:admin3_code":"506909.0",
    "gn:admin4_code":"50690938.0",
    "gn:asciiname":"Pakuar Diar",
    "gn:country_code":"BD",
    "gn:dem":21,
    "gn:feature_class":"P",
    "gn:feature_code":"PPL",
    "gn:name":"P\u0101ku\u0101r Di\u0101r",
    "gn:population":0,
    "gn:timezone":"Asia/Dhaka",
    "iso:country":"BD",
    "name:ben_x_preferred":[
        "P\u0101ku\u0101r Di\u0101r"
    ],
    "wof:name":"Pakuar Diar",
    "wof:placetype":"locality"
},
  "geometry": {"coordinates":[88.97235999999999,24.31961],"type":"Point"}
}