{
  "type": "Feature",
  "properties": {
    "gn:admin1_code":"81",
    "gn:admin2_code":"3068",
    "gn:admin3_code":"306852.0",
    "gn:admin4_code":"30685294.0",
    "gn:asciiname":"Sabhardia",
    "gn:country_code":"BD",
    "gn:dem":10,
    "gn:feature_class":"P",
    "gn:feature_code":"PPL",
    "gn:name":"S\u0101bh\u0101rdia",
    "gn:population":0,
    "gn:timezone":"Asia/Dhaka",
    "iso:country":"BD",
    "wof:name":"Sabhardia",
    "wof:placetype":"locality"
},
  "geometry": {"coordinates":[90.74713,24.12871],"type":"Point"}
}