{
  "type": "Feature",
  "properties": {
    "gn:admin1_code":"83",
    "gn:asciiname":"Shikgachh",
    "gn:country_code":"BD",
    "gn:dem":81,
    "gn:feature_class":"P",
    "gn:feature_code":"PPL",
    "gn:name":"Shikg\u0101chh",
    "gn:population":0,
    "gn:timezone":"Asia/Dhaka",
    "iso:country":"BD",
    "name:ben_x_preferred":[
        "Shikg\u0101chh"
    ],
    "wof:name":"Shikgachh",
    "wof:placetype":"locality"
},
  "geometry": {"coordinates":[88.5258,26.3972],"type":"Point"}
}