{
  "type": "Feature",
  "properties": {
    "gn:admin1_code":"85",
    "gn:admin2_code":"1079",
    "gn:admin3_code":"107976.0",
    "gn:admin4_code":"10797652.0",
    "gn:asciiname":"Kumarkhali",
    "gn:country_code":"BD",
    "gn:dem":8,
    "gn:feature_class":"P",
    "gn:feature_code":"PPL",
    "gn:name":"Kum\u0101rkh\u0101li",
    "gn:population":0,
    "gn:timezone":"Asia/Dhaka",
    "iso:country":"BD",
    "name:und_x_variant":[
        "Kum\u0101rkh\u0101li"
    ],
    "wof:name":"Kumarkhali",
    "wof:placetype":"locality"
},
  "geometry": {"coordinates":[89.93659,22.73847],"type":"Point"}
}