{
  "type": "Feature",
  "properties": {
    "gn:admin1_code":"86",
    "gn:admin2_code":"6058",
    "gn:admin3_code":"605814.0",
    "gn:admin4_code":"60581407.0",
    "gn:asciiname":"Barlekha",
    "gn:country_code":"BD",
    "gn:dem":20,
    "gn:feature_class":"P",
    "gn:feature_code":"PPL",
    "gn:name":"Barlekha",
    "gn:population":0,
    "gn:timezone":"Asia/Dhaka",
    "iso:country":"BD",
    "wof:name":"Barlekha",
    "wof:placetype":"locality"
},
  "geometry": {"coordinates":[92.19546,24.71027],"type":"Point"}
}