{
  "type": "Feature",
  "properties": {
    "gn:admin1_code":"82",
    "gn:admin2_code":"4041.0",
    "gn:admin3_code":"404190.0",
    "gn:admin4_code":"40419025.0",
    "gn:asciiname":"Kharidanga",
    "gn:country_code":"BD",
    "gn:dem":10,
    "gn:feature_class":"P",
    "gn:feature_code":"PPL",
    "gn:name":"Kharidanga",
    "gn:population":0,
    "gn:timezone":"Asia/Dhaka",
    "iso:country":"BD",
    "name:ben_x_preferred":[
        "Kharidanga"
    ],
    "wof:name":"Kharidanga",
    "wof:placetype":"locality"
},
  "geometry": {"coordinates":[88.90921,23.01981],"type":"Point"}
}