{
  "type": "Feature",
  "properties": {
    "gn:admin1_code":"87",
    "gn:admin2_code":"5594.0",
    "gn:admin3_code":"559486.0",
    "gn:admin4_code":"55948663.0",
    "gn:asciiname":"Nayanpur",
    "gn:country_code":"BD",
    "gn:dem":50,
    "gn:feature_class":"P",
    "gn:feature_code":"PPL",
    "gn:name":"Nayanpur",
    "gn:population":0,
    "gn:timezone":"Asia/Dhaka",
    "iso:country":"BD",
    "name:ben_x_preferred":[
        "Nayanpur"
    ],
    "wof:name":"Nayanpur",
    "wof:placetype":"locality"
},
  "geometry": {"coordinates":[88.24951999999998,25.87874],"type":"Point"}
}