{
  "type": "Feature",
  "properties": {
    "gn:admin1_code":"84",
    "gn:admin2_code":"2015",
    "gn:admin3_code":"201561.0",
    "gn:admin4_code":"20156118.0",
    "gn:asciiname":"Saha Mirpur",
    "gn:country_code":"BD",
    "gn:dem":10,
    "gn:feature_class":"P",
    "gn:feature_code":"PPL",
    "gn:name":"Saha Mirpur",
    "gn:population":0,
    "gn:timezone":"Asia/Dhaka",
    "iso:country":"BD",
    "name:ben_x_preferred":[
        "Saha Mirpur"
    ],
    "wof:name":"Saha Mirpur",
    "wof:placetype":"locality"
},
  "geometry": {"coordinates":[91.85323,22.27322],"type":"Point"}
}