{
  "type": "Feature",
  "properties": {
    "gn:admin1_code":"83",
    "gn:admin2_code":"5064.0",
    "gn:admin3_code":"506486.0",
    "gn:admin4_code":"50648679.0",
    "gn:asciiname":"Muradangapara",
    "gn:country_code":"BD",
    "gn:dem":38,
    "gn:feature_class":"P",
    "gn:feature_code":"PPL",
    "gn:name":"Mur\u0101d\u0101ng\u0101p\u0101ra",
    "gn:population":0,
    "gn:timezone":"Asia/Dhaka",
    "iso:country":"BD",
    "name:ben_x_preferred":[
        "Mur\u0101d\u0101ng\u0101p\u0101ra"
    ],
    "wof:name":"Muradangapara",
    "wof:placetype":"locality"
},
  "geometry": {"coordinates":[88.56333000000002,25.17242],"type":"Point"}
}