{
  "type": "Feature",
  "properties": {
    "gn:admin1_code":"H",
    "gn:admin2_code":"3039",
    "gn:admin3_code":"303936.0",
    "gn:admin4_code":"30393659.0",
    "gn:asciiname":"Nandina",
    "gn:country_code":"BD",
    "gn:dem":22,
    "gn:feature_class":"P",
    "gn:feature_code":"PPL",
    "gn:name":"N\u0101ndina",
    "gn:population":0,
    "gn:timezone":"Asia/Dhaka",
    "iso:country":"BD",
    "name:ara_x_preferred":[
        "\u0646\u0627\u0646\u062f\u064a\u0646"
    ],
    "name:mal_x_preferred":[
        "\u0d28\u0d28\u0d4d\u0d26\u0d3f\u0d28"
    ],
    "name:nld_x_preferred":[
        "Nandina"
    ],
    "name:por_x_preferred":[
        "Nandina"
    ],
    "name:rus_x_preferred":[
        "\u041d\u0430\u043d\u0434\u0438\u043d\u0430"
    ],
    "name:spa_x_preferred":[
        "Nandina"
    ],
    "wof:name":"Nandina",
    "wof:placetype":"locality"
},
  "geometry": {"coordinates":[90.03323,24.86718],"type":"Point"}
}