{
  "type": "Feature",
  "properties": {
    "gn:admin1_code":"H",
    "gn:admin2_code":"3039",
    "gn:admin3_code":"303936.0",
    "gn:admin4_code":"30393659.0",
    "gn:asciiname":"Nandina",
    "gn:country_code":"BD",
    "gn:dem":22,
    "gn:feature_class":"P",
    "gn:feature_code":"PPL",
    "gn:name":"N\u0101ndina",
    "gn:population":0,
    "gn:timezone":"Asia/Dhaka",
    "iso:country":"BD",
    "wof:name":"Nandina",
    "wof:placetype":"locality"
},
  "geometry": {"coordinates":[90.03323,24.86718],"type":"Point"}
}