{
  "type": "Feature",
  "properties": {
    "gn:admin1_code":"84",
    "gn:admin2_code":"2015.0",
    "gn:admin3_code":"201553.0",
    "gn:admin4_code":"20155383.0",
    "gn:asciiname":"Shaherkhali",
    "gn:country_code":"BD",
    "gn:dem":8,
    "gn:feature_class":"P",
    "gn:feature_code":"PPL",
    "gn:name":"Shaherkh\u0101li",
    "gn:population":0,
    "gn:timezone":"Asia/Dhaka",
    "iso:country":"BD",
    "wof:name":"Shaherkhali",
    "wof:placetype":"locality"
},
  "geometry": {"coordinates":[91.54889,22.71667],"type":"Point"}
}