{
  "type": "Feature",
  "properties": {
    "gn:admin1_code":"81",
    "gn:admin2_code":"3026.0",
    "gn:admin3_code":"302614.0",
    "gn:admin4_code":"30261435.0",
    "gn:asciiname":"Chhota Asulia",
    "gn:country_code":"BD",
    "gn:dem":12,
    "gn:feature_class":"P",
    "gn:feature_code":"PPL",
    "gn:name":"Chhota Asulia",
    "gn:population":0,
    "gn:timezone":"Asia/Dhaka",
    "iso:country":"BD",
    "wof:name":"Chhota Asulia",
    "wof:placetype":"locality"
},
  "geometry": {"coordinates":[90.20019000000001,23.93576],"type":"Point"}
}