{
  "type": "Feature",
  "properties": {
    "gn:admin1_code":"87",
    "gn:admin2_code":"5594.0",
    "gn:admin3_code":"559486.0",
    "gn:admin4_code":"55948631.0",
    "gn:asciiname":"Sialdangi",
    "gn:country_code":"BD",
    "gn:dem":51,
    "gn:feature_class":"P",
    "gn:feature_code":"PPL",
    "gn:name":"Siald\u0101ngi",
    "gn:population":0,
    "gn:timezone":"Asia/Dhaka",
    "iso:country":"BD",
    "name:ben_x_preferred":[
        "Siald\u0101ngi"
    ],
    "wof:name":"Sialdangi",
    "wof:placetype":"locality"
},
  "geometry": {"coordinates":[88.19311,25.97344],"type":"Point"}
}