{
  "type": "Feature",
  "properties": {
    "gn:admin1_code":"81",
    "gn:admin2_code":"3056",
    "gn:admin3_code":"305682.0",
    "gn:admin4_code":"30568243.0",
    "gn:asciiname":"Singair Bridge",
    "gn:country_code":"BD",
    "gn:dem":3,
    "gn:feature_class":"P",
    "gn:feature_code":"PPL",
    "gn:name":"Singair Bridge",
    "gn:population":0,
    "gn:timezone":"Asia/Dhaka",
    "iso:country":"BD",
    "wof:name":"Singair Bridge",
    "wof:placetype":"locality"
},
  "geometry": {"coordinates":[90.24362000000001,23.79869],"type":"Point"}
}