{
  "type": "Feature",
  "properties": {
    "gn:admin1_code":"81",
    "gn:admin2_code":"3086.0",
    "gn:admin3_code":"308614.0",
    "gn:admin4_code":"30861417.0",
    "gn:asciiname":"Gazipur",
    "gn:country_code":"BD",
    "gn:dem":11,
    "gn:feature_class":"P",
    "gn:feature_code":"PPL",
    "gn:name":"G\u0101zipur",
    "gn:population":0,
    "gn:timezone":"Asia/Dhaka",
    "iso:country":"BD",
    "wof:name":"Gazipur",
    "wof:placetype":"locality"
},
  "geometry": {"coordinates":[90.49301,23.16916],"type":"Point"}
}