{
  "type": "Feature",
  "properties": {
    "gn:admin1_code":"83",
    "gn:admin2_code":"5076",
    "gn:admin3_code":"507655.0",
    "gn:admin4_code":"50765577.0",
    "gn:asciiname":"Sankarpur",
    "gn:country_code":"BD",
    "gn:dem":20,
    "gn:feature_class":"P",
    "gn:feature_code":"PPL",
    "gn:name":"Sankarpur",
    "gn:population":0,
    "gn:timezone":"Asia/Dhaka",
    "iso:country":"BD",
    "name:ceb_x_preferred":[
        "Sankarpur"
    ],
    "name:fra_x_preferred":[
        "Sankarpur"
    ],
    "name:pol_x_preferred":[
        "Sankarpur"
    ],
    "name:swe_x_preferred":[
        "Sankarpur"
    ],
    "wof:name":"Sankarpur",
    "wof:placetype":"locality"
},
  "geometry": {"coordinates":[89.19285000000001,24.04713],"type":"Point"}
}