{
  "type": "Feature",
  "properties": {
    "gn:admin1_code":"82",
    "gn:admin2_code":"4050.0",
    "gn:admin3_code":"405015.0",
    "gn:admin4_code":"40501567.0",
    "gn:asciiname":"Hosenpur",
    "gn:country_code":"BD",
    "gn:dem":18,
    "gn:feature_class":"P",
    "gn:feature_code":"PPL",
    "gn:name":"Hosenpur",
    "gn:population":0,
    "gn:timezone":"Asia/Dhaka",
    "iso:country":"BD",
    "name:ben_x_preferred":[
        "Hosenpur"
    ],
    "wof:name":"Hosenpur",
    "wof:placetype":"locality"
},
  "geometry": {"coordinates":[88.93755999999998,24.06293],"type":"Point"}
}