{
  "type": "Feature",
  "properties": {
    "gn:admin1_code":"82",
    "gn:admin2_code":"4055",
    "gn:admin3_code":"405595.0",
    "gn:admin4_code":"40559531.0",
    "gn:asciiname":"Kusai Ichhapur",
    "gn:country_code":"BD",
    "gn:dem":15,
    "gn:feature_class":"P",
    "gn:feature_code":"PPL",
    "gn:name":"Kus\u0101i Ichh\u0101pur",
    "gn:population":0,
    "gn:timezone":"Asia/Dhaka",
    "iso:country":"BD",
    "wof:name":"Kusai Ichhapur",
    "wof:placetype":"locality"
},
  "geometry": {"coordinates":[89.39046999999999,23.64973],"type":"Point"}
}