{
  "type": "Feature",
  "properties": {
    "gn:admin1_code":"82",
    "gn:admin2_code":"4044.0",
    "gn:admin3_code":"404433.0",
    "gn:admin4_code":"40443310.0",
    "gn:asciiname":"Thikdanga",
    "gn:country_code":"BD",
    "gn:dem":15,
    "gn:feature_class":"P",
    "gn:feature_code":"PPL",
    "gn:name":"Thikd\u0101nga",
    "gn:population":0,
    "gn:timezone":"Asia/Dhaka",
    "iso:country":"BD",
    "name:ben_x_preferred":[
        "Thikd\u0101nga"
    ],
    "wof:name":"Thikdanga",
    "wof:placetype":"locality"
},
  "geometry": {"coordinates":[89.15963000000001,23.31699],"type":"Point"}
}