{
  "type": "Feature",
  "properties": {
    "gn:admin1_code":"82",
    "gn:admin2_code":"4041",
    "gn:admin3_code":"404111.0",
    "gn:admin4_code":"40411186.0",
    "gn:asciiname":"Singhajhul",
    "gn:country_code":"BD",
    "gn:dem":14,
    "gn:feature_class":"P",
    "gn:feature_code":"PPL",
    "gn:name":"Singhajhul",
    "gn:population":0,
    "gn:timezone":"Asia/Dhaka",
    "iso:country":"BD",
    "name:ben_x_preferred":[
        "Singhajhul"
    ],
    "name:ben_x_variant":[
        "Singhajhuli"
    ],
    "wof:name":"Singhajhul",
    "wof:placetype":"locality"
},
  "geometry": {"coordinates":[89.05816999999998,23.24853],"type":"Point"}
}