{
  "type": "Feature",
  "properties": {
    "gn:admin1_code":"81",
    "gn:admin2_code":"3082.0",
    "gn:admin3_code":"308273.0",
    "gn:admin4_code":"30827380.0",
    "gn:asciiname":"Asurhat",
    "gn:country_code":"BD",
    "gn:dem":16,
    "gn:feature_class":"P",
    "gn:feature_code":"PPL",
    "gn:name":"\u0100surh\u0101t",
    "gn:population":0,
    "gn:timezone":"Asia/Dhaka",
    "iso:country":"BD",
    "name:und_x_variant":[
        "Assurhat",
        "\u0100surh\u0101t"
    ],
    "wof:name":"Asurhat",
    "wof:placetype":"locality"
},
  "geometry": {"coordinates":[89.42168000000002,23.7051],"type":"Point"}
}