{
  "type": "Feature",
  "properties": {
    "gn:admin1_code":"H",
    "gn:admin2_code":"3061",
    "gn:admin3_code":"306152.0",
    "gn:admin4_code":"30615200.0",
    "gn:asciiname":"Maskanda",
    "gn:country_code":"BD",
    "gn:dem":16,
    "gn:feature_class":"P",
    "gn:feature_code":"PPL",
    "gn:name":"M\u0101sk\u0101nda",
    "gn:population":0,
    "gn:timezone":"Asia/Dhaka",
    "iso:country":"BD",
    "wof:name":"Maskanda",
    "wof:placetype":"locality"
},
  "geometry": {"coordinates":[90.40373,24.73582],"type":"Point"}
}