{
  "type": "Feature",
  "properties": {
    "gn:admin1_code":"82",
    "gn:admin2_code":"4087",
    "gn:admin3_code":"408704.0",
    "gn:admin4_code":"40870460.0",
    "gn:asciiname":"Kapsanta",
    "gn:country_code":"BD",
    "gn:dem":5,
    "gn:feature_class":"P",
    "gn:feature_code":"PPL",
    "gn:name":"K\u0101psanta",
    "gn:population":0,
    "gn:timezone":"Asia/Dhaka",
    "iso:country":"BD",
    "name:ben_x_preferred":[
        "K\u0101psanta"
    ],
    "name:und_x_variant":[
        "K\u0101psanda"
    ],
    "wof:name":"Kapsanta",
    "wof:placetype":"locality"
},
  "geometry": {"coordinates":[89.20357,22.47383],"type":"Point"}
}