{
  "type": "Feature",
  "properties": {
    "gn:admin1_code":"82",
    "gn:admin2_code":"4041.0",
    "gn:admin3_code":"404111.0",
    "gn:admin4_code":"40411194.0",
    "gn:asciiname":"Kulia",
    "gn:country_code":"BD",
    "gn:dem":13,
    "gn:feature_class":"P",
    "gn:feature_code":"PPL",
    "gn:name":"Kulia",
    "gn:population":0,
    "gn:timezone":"Asia/Dhaka",
    "iso:country":"BD",
    "name:ben_x_preferred":[
        "Kulia"
    ],
    "name:deu_x_preferred":[
        "Kulia"
    ],
    "name:nor_x_preferred":[
        "Kulia"
    ],
    "name:pol_x_preferred":[
        "Kulia"
    ],
    "name:spa_x_preferred":[
        "Kulia"
    ],
    "wof:name":"Kulia",
    "wof:placetype":"locality"
},
  "geometry": {"coordinates":[88.89782,23.23547],"type":"Point"}
}