{
  "type": "Feature",
  "properties": {
    "gn:admin1_code":"82",
    "gn:admin2_code":"4047.0",
    "gn:admin3_code":"404753.0",
    "gn:admin4_code":"40475305.0",
    "gn:asciiname":"Baliadanga",
    "gn:country_code":"BD",
    "gn:dem":6,
    "gn:feature_class":"P",
    "gn:feature_code":"PPL",
    "gn:name":"B\u0101li\u0101d\u0101nga",
    "gn:population":0,
    "gn:timezone":"Asia/Dhaka",
    "iso:country":"BD",
    "name:ben_x_preferred":[
        "B\u0101li\u0101d\u0101nga"
    ],
    "wof:name":"Baliadanga",
    "wof:placetype":"locality"
},
  "geometry": {"coordinates":[89.30658000000003,22.46472],"type":"Point"}
}