{
  "type": "Feature",
  "properties": {
    "gn:admin1_code":"82",
    "gn:admin2_code":"4041.0",
    "gn:admin3_code":"404111.0",
    "gn:admin4_code":"40411177.0",
    "gn:asciiname":"Durgabarkati",
    "gn:country_code":"BD",
    "gn:dem":13,
    "gn:feature_class":"P",
    "gn:feature_code":"PPL",
    "gn:name":"Durg\u0101bark\u0101ti",
    "gn:population":0,
    "gn:timezone":"Asia/Dhaka",
    "iso:country":"BD",
    "name:ben_x_preferred":[
        "Durg\u0101bark\u0101ti"
    ],
    "wof:name":"Durgabarkati",
    "wof:placetype":"locality"
},
  "geometry": {"coordinates":[89.10449,23.26073],"type":"Point"}
}