{
  "type": "Feature",
  "properties": {
    "gn:admin1_code":"82",
    "gn:admin2_code":"4065.0",
    "gn:admin3_code":"406528.0",
    "gn:admin4_code":"40652879.0",
    "gn:asciiname":"Gopaldanga",
    "gn:country_code":"BD",
    "gn:dem":12,
    "gn:feature_class":"P",
    "gn:feature_code":"PPL",
    "gn:name":"Gop\u0101ld\u0101nga",
    "gn:population":0,
    "gn:timezone":"Asia/Dhaka",
    "iso:country":"BD",
    "name:ben_x_preferred":[
        "Gop\u0101ld\u0101nga"
    ],
    "wof:name":"Gopaldanga",
    "wof:placetype":"locality"
},
  "geometry": {"coordinates":[89.76546,23.00121],"type":"Point"}
}