{
  "type": "Feature",
  "properties": {
    "gn:admin1_code":"87",
    "gn:admin2_code":"5549",
    "gn:admin3_code":"554918.0",
    "gn:admin4_code":"55491827.0",
    "gn:asciiname":"Sujanerkuthi",
    "gn:country_code":"BD",
    "gn:dem":34,
    "gn:feature_class":"P",
    "gn:feature_code":"PPL",
    "gn:name":"Sujanerkuthi",
    "gn:population":0,
    "gn:timezone":"Asia/Dhaka",
    "iso:country":"BD",
    "name:ben_x_preferred":[
        "Sujanerkuthi"
    ],
    "wof:name":"Sujanerkuthi",
    "wof:placetype":"locality"
},
  "geometry": {"coordinates":[89.60885999999998,25.94276],"type":"Point"}
}