{
  "type": "Feature",
  "properties": {
    "gn:admin1_code":"85",
    "gn:admin2_code":"1042",
    "gn:admin3_code":"104240.0",
    "gn:admin4_code":"10424038.0",
    "gn:asciiname":"Ramzankati",
    "gn:country_code":"BD",
    "gn:dem":11,
    "gn:feature_class":"P",
    "gn:feature_code":"PPL",
    "gn:name":"R\u0101mz\u0101nk\u0101ti",
    "gn:population":0,
    "gn:timezone":"Asia/Dhaka",
    "iso:country":"BD",
    "name:und_x_variant":[
        "Ramjankati",
        "R\u0101mz\u0101nk\u0101ti"
    ],
    "wof:name":"Ramzankati",
    "wof:placetype":"locality"
},
  "geometry": {"coordinates":[90.19412,22.7383],"type":"Point"}
}