{
  "type": "Feature",
  "properties": {
    "gn:admin1_code":"H",
    "gn:admin2_code":"3072.0",
    "gn:admin3_code":"307274.0",
    "gn:admin4_code":"30727479.0",
    "gn:asciiname":"Dumnikona",
    "gn:cc2":"BD",
    "gn:country_code":"BD",
    "gn:dem":14,
    "gn:feature_class":"P",
    "gn:feature_code":"PPL",
    "gn:name":"Dumnikona",
    "gn:population":0,
    "gn:timezone":"Asia/Dhaka",
    "iso:country":"BD",
    "name:und_x_variant":[
        "Domnikona",
        "Dumnikona"
    ],
    "wof:name":"Dumnikona",
    "wof:placetype":"locality"
},
  "geometry": {"coordinates":[90.66667,24.88333],"type":"Point"}
}