{
  "type": "Feature",
  "properties": {
    "gn:admin1_code":"81",
    "gn:admin2_code":"3029.0",
    "gn:admin3_code":"302903.0",
    "gn:admin4_code":"30290384.0",
    "gn:asciiname":"Kumurtia",
    "gn:country_code":"BD",
    "gn:dem":7,
    "gn:feature_class":"P",
    "gn:feature_code":"PPL",
    "gn:name":"Kumurtia",
    "gn:population":0,
    "gn:timezone":"Asia/Dhaka",
    "iso:country":"BD",
    "name:ben_x_preferred":[
        "Kumurtia"
    ],
    "wof:name":"Kumurtia",
    "wof:placetype":"locality"
},
  "geometry": {"coordinates":[89.69078,23.23363],"type":"Point"}
}