{
  "type": "Feature",
  "properties": {
    "gn:admin1_code":"H",
    "gn:admin2_code":"3061.0",
    "gn:admin3_code":"306165.0",
    "gn:admin4_code":"30616543.0",
    "gn:asciiname":"Hatil",
    "gn:country_code":"BD",
    "gn:dem":20,
    "gn:feature_class":"P",
    "gn:feature_code":"PPL",
    "gn:name":"H\u0101til",
    "gn:population":0,
    "gn:timezone":"Asia/Dhaka",
    "iso:country":"BD",
    "wof:name":"Hatil",
    "wof:placetype":"locality"
},
  "geometry": {"coordinates":[90.16768999999999,24.74733],"type":"Point"}
}