{
  "type": "Feature",
  "properties": {
    "gn:admin1_code":"H",
    "gn:admin2_code":"3072",
    "gn:admin3_code":"307240.0",
    "gn:admin4_code":"30724011.0",
    "gn:asciiname":"Shahapur Chak",
    "gn:country_code":"BD",
    "gn:dem":12,
    "gn:feature_class":"P",
    "gn:feature_code":"PPL",
    "gn:name":"Sh\u0101h\u0101pur Chak",
    "gn:population":0,
    "gn:timezone":"Asia/Dhaka",
    "iso:country":"BD",
    "name:und_x_variant":[
        "Shahapur",
        "Sh\u0101h\u0101pur Chak",
        "Sh\u0101h\u0101pur"
    ],
    "wof:name":"Shahapur Chak",
    "wof:placetype":"locality"
},
  "geometry": {"coordinates":[90.92558,25.01027],"type":"Point"}
}