{
  "type": "Feature",
  "properties": {
    "gn:admin1_code":"81",
    "gn:admin2_code":"3082.0",
    "gn:admin3_code":"308273.0",
    "gn:admin4_code":"30827370.0",
    "gn:asciiname":"Bil Nausi",
    "gn:country_code":"BD",
    "gn:dem":10,
    "gn:feature_class":"P",
    "gn:feature_code":"PPL",
    "gn:name":"B\u012bl Nausi",
    "gn:population":0,
    "gn:timezone":"Asia/Dhaka",
    "iso:country":"BD",
    "wof:name":"Bil Nausi",
    "wof:placetype":"locality"
},
  "geometry": {"coordinates":[89.46666999999999,23.68333],"type":"Point"}
}