{
  "type": "Feature",
  "properties": {
    "gn:admin1_code":"87",
    "gn:admin2_code":"5549",
    "gn:admin3_code":"554961.0",
    "gn:admin4_code":"55496188.0",
    "gn:asciiname":"Chander Hat",
    "gn:country_code":"BD",
    "gn:dem":35,
    "gn:feature_class":"P",
    "gn:feature_code":"PPL",
    "gn:name":"Chander Hat",
    "gn:population":0,
    "gn:timezone":"Asia/Dhaka",
    "iso:country":"BD",
    "name:ben_x_preferred":[
        "Chander Hat"
    ],
    "wof:name":"Chander Hat",
    "wof:placetype":"locality"
},
  "geometry": {"coordinates":[89.63565,26.05373],"type":"Point"}
}