{
  "type": "Feature",
  "properties": {
    "gn:admin1_code":"82",
    "gn:admin2_code":"4047",
    "gn:admin3_code":"404764.0",
    "gn:admin4_code":"40476450.0",
    "gn:asciiname":"Malath",
    "gn:country_code":"BD",
    "gn:dem":6,
    "gn:feature_class":"P",
    "gn:feature_code":"PPL",
    "gn:name":"M\u0101lath",
    "gn:population":0,
    "gn:timezone":"Asia/Dhaka",
    "iso:country":"BD",
    "wof:name":"Malath",
    "wof:placetype":"locality"
},
  "geometry": {"coordinates":[89.31200000000003,22.65356],"type":"Point"}
}