{
  "type": "Feature",
  "properties": {
    "gn:admin1_code":"86",
    "gn:admin2_code":"6036",
    "gn:admin3_code":"603611.0",
    "gn:admin4_code":"60361144.0",
    "gn:asciiname":"Makalkandi",
    "gn:country_code":"BD",
    "gn:dem":12,
    "gn:feature_class":"P",
    "gn:feature_code":"PPL",
    "gn:name":"M\u0101k\u0101lk\u0101ndi",
    "gn:population":0,
    "gn:timezone":"Asia/Dhaka",
    "iso:country":"BD",
    "name:und_x_variant":[
        "Makhalkandi",
        "M\u0101k\u0101lk\u0101ndi"
    ],
    "wof:name":"Makalkandi",
    "wof:placetype":"locality"
},
  "geometry": {"coordinates":[91.39281,24.61393],"type":"Point"}
}