{
  "type": "Feature",
  "properties": {
    "gn:admin1_code":"83",
    "gn:asciiname":"Wazirpara",
    "gn:country_code":"BD",
    "gn:dem":23,
    "gn:feature_class":"P",
    "gn:feature_code":"PPL",
    "gn:name":"Wazirp\u0101ra",
    "gn:population":0,
    "gn:timezone":"Asia/Dhaka",
    "iso:country":"BD",
    "name:ben_x_preferred":[
        "Wazirp\u0101ra"
    ],
    "wof:name":"Wazirpara",
    "wof:placetype":"locality"
},
  "geometry": {"coordinates":[89.51366,25.04913],"type":"Point"}
}