{
  "type": "Feature",
  "properties": {
    "gn:admin1_code":"85",
    "gn:admin2_code":"1078.0",
    "gn:admin3_code":"107852.0",
    "gn:admin4_code":"10785242.0",
    "gn:asciiname":"Singarhawla",
    "gn:country_code":"BD",
    "gn:dem":7,
    "gn:feature_class":"P",
    "gn:feature_code":"PPL",
    "gn:name":"Singarh\u0101wla",
    "gn:population":0,
    "gn:timezone":"Asia/Dhaka",
    "iso:country":"BD",
    "name:ben_x_preferred":[
        "Singarh\u0101wla"
    ],
    "wof:name":"Singarhawla",
    "wof:placetype":"locality"
},
  "geometry": {"coordinates":[90.52236000000001,22.2985],"type":"Point"}
}