{
  "type": "Feature",
  "properties": {
    "gn:admin1_code":"83",
    "gn:admin2_code":"5010.0",
    "gn:admin3_code":"501094.0",
    "gn:admin4_code":"50109455.0",
    "gn:asciiname":"Bharahar",
    "gn:country_code":"BD",
    "gn:dem":26,
    "gn:feature_class":"P",
    "gn:feature_code":"PPL",
    "gn:name":"Bh\u0101r\u0101h\u0101r",
    "gn:population":0,
    "gn:timezone":"Asia/Dhaka",
    "iso:country":"BD",
    "wof:name":"Bharahar",
    "wof:placetype":"locality"
},
  "geometry": {"coordinates":[89.19863000000002,24.94661],"type":"Point"}
}