{
  "type": "Feature",
  "properties": {
    "gn:admin1_code":"H",
    "gn:admin2_code":"3061.0",
    "gn:admin3_code":"306124.0",
    "gn:admin4_code":"30612433.0",
    "gn:asciiname":"Dhara",
    "gn:country_code":"BD",
    "gn:dem":20,
    "gn:feature_class":"P",
    "gn:feature_code":"PPL",
    "gn:name":"Dh\u0101ra",
    "gn:population":0,
    "gn:timezone":"Asia/Dhaka",
    "iso:country":"BD",
    "wof:name":"Dhara",
    "wof:placetype":"locality"
},
  "geometry": {"coordinates":[90.33748,25.05809],"type":"Point"}
}