{
  "type": "Feature",
  "properties": {
    "gn:admin1_code":"82",
    "gn:admin2_code":"4050",
    "gn:admin3_code":"405063.0",
    "gn:admin4_code":"40506323.0",
    "gn:asciiname":"Singaria",
    "gn:country_code":"BD",
    "gn:dem":16,
    "gn:feature_class":"P",
    "gn:feature_code":"PPL",
    "gn:name":"Singaria",
    "gn:population":0,
    "gn:timezone":"Asia/Dhaka",
    "iso:country":"BD",
    "wof:name":"Singaria",
    "wof:placetype":"locality"
},
  "geometry": {"coordinates":[89.31349,23.81223],"type":"Point"}
}