{
  "type": "Feature",
  "properties": {
    "gn:admin1_code":"84",
    "gn:admin2_code":"2013.0",
    "gn:admin3_code":"201349.0",
    "gn:admin4_code":"20134930.0",
    "gn:asciiname":"Guataba",
    "gn:country_code":"BD",
    "gn:dem":14,
    "gn:feature_class":"P",
    "gn:feature_code":"PPL",
    "gn:name":"Guat\u0101ba",
    "gn:population":0,
    "gn:timezone":"Asia/Dhaka",
    "iso:country":"BD",
    "name:und_x_variant":[
        "Guat\u0101ba",
        "Gu\u0101toba"
    ],
    "wof:name":"Guataba",
    "wof:placetype":"locality"
},
  "geometry": {"coordinates":[90.86803,23.18785],"type":"Point"}
}