{
  "type": "Feature",
  "properties": {
    "gn:admin1_code":"87",
    "gn:admin2_code":"5532",
    "gn:admin3_code":"553267.0",
    "gn:admin4_code":"55326738.0",
    "gn:asciiname":"Digdari",
    "gn:country_code":"BD",
    "gn:dem":26,
    "gn:feature_class":"P",
    "gn:feature_code":"PPL",
    "gn:name":"Digdari",
    "gn:population":0,
    "gn:timezone":"Asia/Dhaka",
    "iso:country":"BD",
    "name:ben_x_preferred":[
        "Digdari"
    ],
    "wof:name":"Digdari",
    "wof:placetype":"locality"
},
  "geometry": {"coordinates":[89.33372,25.25924],"type":"Point"}
}