{
  "type": "Feature",
  "properties": {
    "gn:admin1_code":"87",
    "gn:admin2_code":"5549",
    "gn:admin3_code":"554994.0",
    "gn:admin4_code":"55499472.0",
    "gn:asciiname":"Apuarkhata",
    "gn:country_code":"BD",
    "gn:dem":31,
    "gn:feature_class":"P",
    "gn:feature_code":"PPL",
    "gn:name":"\u0100pu\u0101rkh\u0101ta",
    "gn:population":0,
    "gn:timezone":"Asia/Dhaka",
    "iso:country":"BD",
    "name:ben_x_preferred":[
        "\u0100pu\u0101rkh\u0101ta"
    ],
    "wof:name":"Apuarkhata",
    "wof:placetype":"locality"
},
  "geometry": {"coordinates":[89.58844999999999,25.71256],"type":"Point"}
}