{
  "type": "Feature",
  "properties": {
    "gn:admin1_code":"81",
    "gn:admin2_code":"3033.0",
    "gn:admin3_code":"303330.0",
    "gn:admin4_code":"30333000.0",
    "gn:asciiname":"Arijpur",
    "gn:country_code":"BD",
    "gn:dem":13,
    "gn:feature_class":"P",
    "gn:feature_code":"PPL",
    "gn:name":"\u0100rijpur",
    "gn:population":0,
    "gn:timezone":"Asia/Dhaka",
    "iso:country":"BD",
    "wof:name":"Arijpur",
    "wof:placetype":"locality"
},
  "geometry": {"coordinates":[90.40900000000001,23.88721],"type":"Point"}
}