{
  "type": "Feature",
  "properties": {
    "gn:admin1_code":"83",
    "gn:admin2_code":"5064",
    "gn:admin3_code":"506469.0",
    "gn:admin4_code":"50646952.0",
    "gn:asciiname":"Rupnarayanpur",
    "gn:country_code":"BD",
    "gn:dem":27,
    "gn:feature_class":"P",
    "gn:feature_code":"PPL",
    "gn:name":"Rupnarayanpur",
    "gn:population":0,
    "gn:timezone":"Asia/Dhaka",
    "iso:country":"BD",
    "name:ben_x_preferred":[
        "Rupnarayanpur"
    ],
    "name:ceb_x_preferred":[
        "Rupn\u0101r\u0101yanpur"
    ],
    "name:swe_x_preferred":[
        "Rupn\u0101r\u0101yanpur"
    ],
    "name:zho_x_preferred":[
        "\u6b23\u675c\u65af\u5766\u6070\u5e03\u83b1\u9547"
    ],
    "wof:name":"Rupnarayanpur",
    "wof:placetype":"locality"
},
  "geometry": {"coordinates":[88.57975,24.86131],"type":"Point"}
}