{
  "type": "Feature",
  "properties": {
    "gn:admin1_code":"87",
    "gn:admin2_code":"5532",
    "gn:admin3_code":"553230.0",
    "gn:admin4_code":"55323005.0",
    "gn:asciiname":"Balua",
    "gn:country_code":"BD",
    "gn:dem":26,
    "gn:feature_class":"P",
    "gn:feature_code":"PPL",
    "gn:name":"B\u0101lua",
    "gn:population":0,
    "gn:timezone":"Asia/Dhaka",
    "iso:country":"BD",
    "name:ben_x_preferred":[
        "B\u0101lua"
    ],
    "wof:name":"Balua",
    "wof:placetype":"locality"
},
  "geometry": {"coordinates":[89.35032,25.18548],"type":"Point"}
}