{
  "type": "Feature",
  "properties": {
    "gn:admin1_code":"81",
    "gn:admin2_code":"3068",
    "gn:admin3_code":"306863.0",
    "gn:admin4_code":"30686379.0",
    "gn:asciiname":"Sanerbari",
    "gn:country_code":"BD",
    "gn:dem":16,
    "gn:feature_class":"P",
    "gn:feature_code":"PPL",
    "gn:name":"S\u0101nerb\u0101ri",
    "gn:population":0,
    "gn:timezone":"Asia/Dhaka",
    "iso:country":"BD",
    "wof:name":"Sanerbari",
    "wof:placetype":"locality"
},
  "geometry": {"coordinates":[90.65747,23.96137],"type":"Point"}
}