{
  "type": "Feature",
  "properties": {
    "gn:admin1_code":"83",
    "gn:admin2_code":"5081.0",
    "gn:admin3_code":"508134.0",
    "gn:admin4_code":"50813457.0",
    "gn:asciiname":"Kumrapara",
    "gn:country_code":"BD",
    "gn:dem":31,
    "gn:feature_class":"P",
    "gn:feature_code":"PPL",
    "gn:name":"Kumr\u0101p\u0101ra",
    "gn:population":0,
    "gn:timezone":"Asia/Dhaka",
    "iso:country":"BD",
    "name:ben_x_preferred":[
        "Kumr\u0101p\u0101ra"
    ],
    "wof:name":"Kumrapara",
    "wof:placetype":"locality"
},
  "geometry": {"coordinates":[88.39418000000001,24.44914],"type":"Point"}
}