{
  "type": "Feature",
  "properties": {
    "gn:admin1_code":"85",
    "gn:admin2_code":"1006",
    "gn:admin3_code":"100662.0",
    "gn:admin4_code":"10066279.0",
    "gn:asciiname":"Kasba",
    "gn:country_code":"BD",
    "gn:dem":5,
    "gn:feature_class":"P",
    "gn:feature_code":"PPL",
    "gn:name":"Kasba",
    "gn:population":0,
    "gn:timezone":"Asia/Dhaka",
    "iso:country":"BD",
    "name:ceb_x_preferred":[
        "Kasba"
    ],
    "name:hin_x_preferred":[
        "\u0915\u0938\u094d\u092c\u093e"
    ],
    "name:new_x_preferred":[
        "\u0915\u0938\u094d\u092c\u093e"
    ],
    "name:nld_x_preferred":[
        "Kasba"
    ],
    "name:por_x_preferred":[
        "Kasba"
    ],
    "name:rus_x_preferred":[
        "\u041a\u0430\u0441\u0431\u0430"
    ],
    "name:swe_x_preferred":[
        "Kasba"
    ],
    "wof:name":"Kasba",
    "wof:placetype":"locality"
},
  "geometry": {"coordinates":[90.45,22.86667000000001],"type":"Point"}
}