{
  "type": "Feature",
  "properties": {
    "gn:admin1_code":"87",
    "gn:admin2_code":"5594.0",
    "gn:admin3_code":"559482.0",
    "gn:admin4_code":"55948269.0",
    "gn:asciiname":"Ramdebpur",
    "gn:country_code":"BD",
    "gn:dem":49,
    "gn:feature_class":"P",
    "gn:feature_code":"PPL",
    "gn:name":"R\u0101mdebpur",
    "gn:population":0,
    "gn:timezone":"Asia/Dhaka",
    "iso:country":"BD",
    "name:ben_x_preferred":[
        "R\u0101mdebpur"
    ],
    "wof:name":"Ramdebpur",
    "wof:placetype":"locality"
},
  "geometry": {"coordinates":[88.40224000000001,25.92326],"type":"Point"}
}