{
  "type": "Feature",
  "properties": {
    "gn:admin1_code":"82",
    "gn:admin2_code":"4047.0",
    "gn:admin3_code":"404764.0",
    "gn:admin4_code":"40476416.0",
    "gn:asciiname":"Garerdanga",
    "gn:country_code":"BD",
    "gn:dem":7,
    "gn:feature_class":"P",
    "gn:feature_code":"PPL",
    "gn:name":"Garerd\u0101nga",
    "gn:population":0,
    "gn:timezone":"Asia/Dhaka",
    "iso:country":"BD",
    "wof:name":"Garerdanga",
    "wof:placetype":"locality"
},
  "geometry": {"coordinates":[89.25393000000003,22.51842000000001],"type":"Point"}
}