{
  "type": "Feature",
  "properties": {
    "gn:admin1_code":"83",
    "gn:admin2_code":"5038",
    "gn:admin3_code":"503813.0",
    "gn:admin4_code":"50381363.0",
    "gn:asciiname":"Santa",
    "gn:country_code":"BD",
    "gn:dem":21,
    "gn:feature_class":"P",
    "gn:feature_code":"PPL",
    "gn:name":"S\u0101nta",
    "gn:population":0,
    "gn:timezone":"Asia/Dhaka",
    "iso:country":"BD",
    "wof:name":"Santa",
    "wof:placetype":"locality"
},
  "geometry": {"coordinates":[89.04315,24.95784],"type":"Point"}
}