{
  "type": "Feature",
  "properties": {
    "gn:admin1_code":"82",
    "gn:admin2_code":"4087.0",
    "gn:admin3_code":"408725.0",
    "gn:admin4_code":"40872579.0",
    "gn:asciiname":"Tilkuri",
    "gn:country_code":"BD",
    "gn:dem":6,
    "gn:feature_class":"P",
    "gn:feature_code":"PPL",
    "gn:name":"Tilkuri",
    "gn:population":0,
    "gn:timezone":"Asia/Dhaka",
    "iso:country":"BD",
    "name:ben_x_preferred":[
        "Tilkuri"
    ],
    "wof:name":"Tilkuri",
    "wof:placetype":"locality"
},
  "geometry": {"coordinates":[88.98814,22.57685],"type":"Point"}
}