{
  "type": "Feature",
  "properties": {
    "gn:admin1_code":"81",
    "gn:admin2_code":"3035",
    "gn:admin3_code":"303558.0",
    "gn:admin4_code":"30355833.0",
    "gn:asciiname":"Kulakona",
    "gn:country_code":"BD",
    "gn:dem":10,
    "gn:feature_class":"P",
    "gn:feature_code":"PPL",
    "gn:name":"Kul\u0101kona",
    "gn:population":0,
    "gn:timezone":"Asia/Dhaka",
    "iso:country":"BD",
    "wof:name":"Kulakona",
    "wof:placetype":"locality"
},
  "geometry": {"coordinates":[89.83408,23.30192000000001],"type":"Point"}
}