{
  "type": "Feature",
  "properties": {
    "gn:admin1_code":"84",
    "gn:admin2_code":"2075.0",
    "gn:admin3_code":"207587.0",
    "gn:admin4_code":"20758700.0",
    "gn:asciiname":"Dadpur",
    "gn:country_code":"BD",
    "gn:dem":11,
    "gn:feature_class":"P",
    "gn:feature_code":"PPL",
    "gn:name":"D\u0101dpur",
    "gn:population":0,
    "gn:timezone":"Asia/Dhaka",
    "iso:country":"BD",
    "wof:name":"Dadpur",
    "wof:placetype":"locality"
},
  "geometry": {"coordinates":[91.10361,22.85528],"type":"Point"}
}