{
  "type": "Feature",
  "properties": {
    "gn:admin1_code":"82",
    "gn:admin2_code":"4047.0",
    "gn:admin3_code":"404745.0",
    "gn:admin4_code":"40474512.0",
    "gn:asciiname":"Khalishpur",
    "gn:country_code":"BD",
    "gn:dem":6,
    "gn:feature_class":"P",
    "gn:feature_code":"PPL",
    "gn:name":"Kh\u0101lishpur",
    "gn:population":0,
    "gn:timezone":"Asia/Dhaka",
    "iso:country":"BD",
    "name:ben_x_preferred":[
        "Kh\u0101lishpur"
    ],
    "wof:name":"Khalishpur",
    "wof:placetype":"locality"
},
  "geometry": {"coordinates":[89.54427,22.85308],"type":"Point"}
}