{
  "type": "Feature",
  "properties": {
    "gn:admin1_code":"H",
    "gn:admin2_code":"3061.0",
    "gn:admin3_code":"306131.0",
    "gn:admin4_code":"30613185.0",
    "gn:asciiname":"Hatulia",
    "gn:country_code":"BD",
    "gn:dem":16,
    "gn:feature_class":"P",
    "gn:feature_code":"PPL",
    "gn:name":"H\u0101tulia",
    "gn:population":0,
    "gn:timezone":"Asia/Dhaka",
    "iso:country":"BD",
    "wof:name":"Hatulia",
    "wof:placetype":"locality"
},
  "geometry": {"coordinates":[90.63894999999999,24.68739],"type":"Point"}
}