{
  "type": "Feature",
  "properties": {
    "gn:admin1_code":"82",
    "gn:asciiname":"Saniaddalkati",
    "gn:country_code":"BD",
    "gn:dem":9,
    "gn:feature_class":"P",
    "gn:feature_code":"PPL",
    "gn:name":"Saniaddalk\u0101ti",
    "gn:population":0,
    "gn:timezone":"Asia/Dhaka",
    "iso:country":"BD",
    "name:ben_x_preferred":[
        "Saniaddalk\u0101ti"
    ],
    "wof:name":"Saniaddalkati",
    "wof:placetype":"locality"
},
  "geometry": {"coordinates":[90.2851,22.46433],"type":"Point"}
}