{
  "type": "Feature",
  "properties": {
    "gn:admin1_code":"84",
    "gn:admin2_code":"2015.0",
    "gn:admin3_code":"201537.0",
    "gn:admin4_code":"20153701.0",
    "gn:asciiname":"Chowdhury Hat",
    "gn:country_code":"BD",
    "gn:dem":9,
    "gn:feature_class":"P",
    "gn:feature_code":"PPL",
    "gn:name":"Chowdhury H\u0101t",
    "gn:population":0,
    "gn:timezone":"Asia/Dhaka",
    "iso:country":"BD",
    "name:ben_x_preferred":[
        "Chowdhury H\u0101t"
    ],
    "wof:name":"Chowdhury Hat",
    "wof:placetype":"locality"
},
  "geometry": {"coordinates":[91.81403,22.44181],"type":"Point"}
}