{
  "type": "Feature",
  "properties": {
    "gn:admin1_code":"82",
    "gn:admin2_code":"4047.0",
    "gn:admin3_code":"404775.0",
    "gn:admin4_code":"40477567.0",
    "gn:asciiname":"Mahishaghuni",
    "gn:country_code":"BD",
    "gn:dem":6,
    "gn:feature_class":"P",
    "gn:feature_code":"PPL",
    "gn:name":"Mahish\u0101ghuni",
    "gn:population":0,
    "gn:timezone":"Asia/Dhaka",
    "iso:country":"BD",
    "name:ben_x_preferred":[
        "Mahish\u0101ghuni"
    ],
    "wof:name":"Mahishaghuni",
    "wof:placetype":"locality"
},
  "geometry": {"coordinates":[89.59123000000002,22.84066],"type":"Point"}
}