{
  "type": "Feature",
  "properties": {
    "gn:admin1_code":"H",
    "gn:admin2_code":"3072",
    "gn:admin3_code":"307247.0",
    "gn:admin4_code":"30724794.0",
    "gn:asciiname":"Ramaigati Pubati",
    "gn:country_code":"BD",
    "gn:dem":14,
    "gn:feature_class":"P",
    "gn:feature_code":"PPL",
    "gn:name":"Ram\u0101ig\u0101ti Pub\u0101ti",
    "gn:population":0,
    "gn:timezone":"Asia/Dhaka",
    "iso:country":"BD",
    "wof:name":"Ramaigati Pubati",
    "wof:placetype":"locality"
},
  "geometry": {"coordinates":[90.76340999999999,24.683],"type":"Point"}
}