{
  "type": "Feature",
  "properties": {
    "gn:admin1_code":"81",
    "gn:admin2_code":"3067",
    "gn:admin3_code":"306768.0",
    "gn:admin4_code":"30676879.0",
    "gn:asciiname":"Solpina",
    "gn:country_code":"BD",
    "gn:dem":19,
    "gn:feature_class":"P",
    "gn:feature_code":"PPL",
    "gn:name":"Solpina",
    "gn:population":0,
    "gn:timezone":"Asia/Dhaka",
    "iso:country":"BD",
    "wof:name":"Solpina",
    "wof:placetype":"locality"
},
  "geometry": {"coordinates":[90.52154,23.84267],"type":"Point"}
}