{
  "type": "Feature",
  "properties": {
    "gn:admin1_code":"82",
    "gn:admin2_code":"4087",
    "gn:admin3_code":"408786.0",
    "gn:admin4_code":"40878694.0",
    "gn:asciiname":"Kanchrahati Nandigram",
    "gn:country_code":"BD",
    "gn:dem":3,
    "gn:feature_class":"P",
    "gn:feature_code":"PPL",
    "gn:name":"K\u0101nchr\u0101h\u0101ti Nandigr\u0101m",
    "gn:population":0,
    "gn:timezone":"Asia/Dhaka",
    "iso:country":"BD",
    "wof:name":"Kanchrahati Nandigram",
    "wof:placetype":"locality"
},
  "geometry": {"coordinates":[89.09999999999999,22.35],"type":"Point"}
}