{
  "type": "Feature",
  "properties": {
    "gn:admin1_code":"H",
    "gn:admin2_code":"3072",
    "gn:admin3_code":"307274.0",
    "gn:admin4_code":"30727494.0",
    "gn:asciiname":"Kagajipara",
    "gn:country_code":"BD",
    "gn:dem":14,
    "gn:feature_class":"P",
    "gn:feature_code":"PPL",
    "gn:name":"K\u0101gajip\u0101ra",
    "gn:population":0,
    "gn:timezone":"Asia/Dhaka",
    "iso:country":"BD",
    "wof:name":"Kagajipara",
    "wof:placetype":"locality"
},
  "geometry": {"coordinates":[90.80887,24.89372],"type":"Point"}
}