{
  "type": "Feature",
  "properties": {
    "iso:country":"BD",
    "name:ben_x_preferred":[
        "\u09ab\u09c7\u09a8\u09c0"
    ],
    "name:ceb_x_preferred":[
        "Feni"
    ],
    "name:ell_x_preferred":[
        "\u03a6\u03ad\u03bd\u03b9"
    ],
    "name:eng_x_preferred":[
        "Feni"
    ],
    "name:fra_x_preferred":[
        "Feni"
    ],
    "name:ita_x_preferred":[
        "Feni"
    ],
    "name:nld_x_preferred":[
        "Feni"
    ],
    "name:pol_x_preferred":[
        "Pheni"
    ],
    "name:pol_x_variant":[
        "Feni"
    ],
    "name:swe_x_preferred":[
        "Feni"
    ],
    "name:unk_x_variant":[
        "Fenny"
    ],
    "name:zho_x_preferred":[
        "Bandarban"
    ],
    "qs:gn_country":"BD",
    "qs:gn_fcode":"PPL",
    "qs:gn_pop":84028,
    "qs:name":"Feni",
    "qs:name_adm0":"Bangladesh",
    "qs:name_adm1":"Chittagong",
    "qs:photos":0,
    "qs:photos_1k":0,
    "qs:photos_9k":1,
    "qs:photos_9r":1,
    "qs:photos_all":8,
    "qs:photos_sr":0,
    "qs:placetype":"Town",
    "qs:pop_sr":"8",
    "qs:woe_adm0":23424759,
    "wd:wordcount":132,
    "wof:name":"Feni",
    "wof:placetype":"locality",
    "wof:population":84028
},
  "geometry": {"coordinates":[91.40130000000001,23.01134],"type":"Point"}
}