{
  "type": "Feature",
  "properties": {
    "gn:admin1_code":"82",
    "gn:admin2_code":"4047.0",
    "gn:admin3_code":"404712.0",
    "gn:admin4_code":"40471283.0",
    "gn:asciiname":"Buna",
    "gn:country_code":"BD",
    "gn:dem":5,
    "gn:feature_class":"P",
    "gn:feature_code":"PPL",
    "gn:name":"Buna",
    "gn:population":0,
    "gn:timezone":"Asia/Dhaka",
    "iso:country":"BD",
    "name:bos_x_preferred":[
        "Buna"
    ],
    "name:bul_x_preferred":[
        "\u0411\u0443\u043d\u0430"
    ],
    "name:ceb_x_preferred":[
        "Buna"
    ],
    "name:deu_x_preferred":[
        "Buna"
    ],
    "name:fra_x_preferred":[
        "Buna"
    ],
    "name:heb_x_preferred":[
        "\u05d1\u05d5\u05e0\u05d4"
    ],
    "name:hrv_x_preferred":[
        "Buna"
    ],
    "name:hun_x_preferred":[
        "Buna"
    ],
    "name:ita_x_preferred":[
        "Buna"
    ],
    "name:jpn_x_preferred":[
        "\u30d6\u30ca"
    ],
    "name:nld_x_preferred":[
        "Buna"
    ],
    "name:pol_x_preferred":[
        "Buna"
    ],
    "name:rus_x_preferred":[
        "\u0411\u0443\u043d\u0430"
    ],
    "name:spa_x_preferred":[
        "Buna"
    ],
    "name:srp_x_preferred":[
        "\u0411\u0443\u043d\u0430"
    ],
    "name:swe_x_preferred":[
        "Buna"
    ],
    "name:ukr_x_preferred":[
        "\u0411\u0443\u043d\u0430"
    ],
    "wof:name":"Buna",
    "wof:placetype":"locality"
},
  "geometry": {"coordinates":[89.48333000000002,22.65],"type":"Point"}
}