{
  "type": "Feature",
  "properties": {
    "gn:admin1_code":"82",
    "gn:admin2_code":"4047.0",
    "gn:admin3_code":"404775.0",
    "gn:admin4_code":"40477527.0",
    "gn:asciiname":"Chandpur",
    "gn:country_code":"BD",
    "gn:dem":4,
    "gn:feature_class":"P",
    "gn:feature_code":"PPL",
    "gn:name":"Ch\u0101ndpur",
    "gn:population":0,
    "gn:timezone":"Asia/Dhaka",
    "iso:country":"BD",
    "name:ben_x_preferred":[
        "Ch\u0101ndpur"
    ],
    "wof:name":"Chandpur",
    "wof:placetype":"locality"
},
  "geometry": {"coordinates":[89.65279,22.8121],"type":"Point"}
}