{
  "type": "Feature",
  "properties": {
    "gn:admin1_code":"83",
    "gn:admin2_code":"5076",
    "gn:admin3_code":"507655.0",
    "gn:admin4_code":"50765560.0",
    "gn:asciiname":"Jayanpur",
    "gn:country_code":"BD",
    "gn:dem":16,
    "gn:feature_class":"P",
    "gn:feature_code":"PPL",
    "gn:name":"Jay\u0101npur",
    "gn:population":0,
    "gn:timezone":"Asia/Dhaka",
    "iso:country":"BD",
    "name:ben_x_preferred":[
        "Jay\u0101npur"
    ],
    "name:und_x_variant":[
        "Joyenpur"
    ],
    "wof:name":"Jayanpur",
    "wof:placetype":"locality"
},
  "geometry": {"coordinates":[89.15057,23.98339],"type":"Point"}
}