{
  "type": "Feature",
  "properties": {
    "gn:admin1_code":"H",
    "gn:asciiname":"Bir Kursa",
    "gn:country_code":"BD",
    "gn:dem":14,
    "gn:feature_class":"P",
    "gn:feature_code":"PPL",
    "gn:name":"Bir Kursa",
    "gn:population":0,
    "gn:timezone":"Asia/Dhaka",
    "iso:country":"BD",
    "name:ben_x_preferred":[
        "Bir Kursa"
    ],
    "wof:name":"Bir Kursa",
    "wof:placetype":"locality"
},
  "geometry": {"coordinates":[89.7141,25.13897],"type":"Point"}
}