{
  "type": "Feature",
  "properties": {
    "gn:admin1_code":"82",
    "gn:admin2_code":"4087",
    "gn:admin3_code":"408747.0",
    "gn:admin4_code":"40874755.0",
    "gn:asciiname":"Tulakati",
    "gn:country_code":"BD",
    "gn:dem":1,
    "gn:feature_class":"P",
    "gn:feature_code":"PPL",
    "gn:name":"Tul\u0101k\u0101ti",
    "gn:population":0,
    "gn:timezone":"Asia/Dhaka",
    "iso:country":"BD",
    "name:ben_x_preferred":[
        "Tul\u0101k\u0101ti"
    ],
    "wof:name":"Tulakati",
    "wof:placetype":"locality"
},
  "geometry": {"coordinates":[89.06169,22.45695],"type":"Point"}
}