{
  "type": "Feature",
  "properties": {
    "gn:admin1_code":"87",
    "gn:admin2_code":"5577.0",
    "gn:admin3_code":"557725.0",
    "gn:admin4_code":"55772521.0",
    "gn:asciiname":"Nazirpara",
    "gn:country_code":"BD",
    "gn:dem":71,
    "gn:feature_class":"P",
    "gn:feature_code":"PPL",
    "gn:name":"N\u0101zirp\u0101ra",
    "gn:population":0,
    "gn:timezone":"Asia/Dhaka",
    "iso:country":"BD",
    "name:ben_x_preferred":[
        "N\u0101zirp\u0101ra"
    ],
    "wof:name":"Nazirpara",
    "wof:placetype":"locality"
},
  "geometry": {"coordinates":[88.55334999999999,26.20866],"type":"Point"}
}