{
  "type": "Feature",
  "properties": {
    "gn:admin1_code":"H",
    "gn:admin2_code":"3061",
    "gn:admin3_code":"306120.0",
    "gn:admin4_code":"30612083.0",
    "gn:asciiname":"Maukatala",
    "gn:country_code":"BD",
    "gn:dem":17,
    "gn:feature_class":"P",
    "gn:feature_code":"PPL",
    "gn:name":"Mauk\u0101tala",
    "gn:population":0,
    "gn:timezone":"Asia/Dhaka",
    "iso:country":"BD",
    "name:und_x_variant":[
        "Mauk\u0101tala",
        "Mauh\u0101tala"
    ],
    "wof:name":"Maukatala",
    "wof:placetype":"locality"
},
  "geometry": {"coordinates":[90.18716000000001,24.63603],"type":"Point"}
}