{
  "type": "Feature",
  "properties": {
    "gn:admin1_code":"83",
    "gn:admin2_code":"5064",
    "gn:admin3_code":"506486.0",
    "gn:admin4_code":"50648607.0",
    "gn:asciiname":"Mirzapur",
    "gn:country_code":"BD",
    "gn:dem":32,
    "gn:feature_class":"P",
    "gn:feature_code":"PPL",
    "gn:name":"Mirz\u0101pur",
    "gn:population":0,
    "gn:timezone":"Asia/Dhaka",
    "iso:country":"BD",
    "name:ara_x_preferred":[
        "\u0645\u064a\u0631\u0632\u0627\u0628\u0648\u0631"
    ],
    "name:azb_x_preferred":[
        "\u0645\u06cc\u0631\u0632\u0627\u067e\u0648\u0631"
    ],
    "name:ben_x_preferred":[
        "Mirz\u0101pur"
    ],
    "name:bih_x_preferred":[
        "\u092e\u093f\u0930\u094d\u091c\u093e\u092a\u0941\u0930"
    ],
    "name:cat_x_preferred":[
        "Mirzapur"
    ],
    "name:ceb_x_preferred":[
        "Mirz\u0101pur"
    ],
    "name:deu_x_preferred":[
        "Mirzapur"
    ],
    "name:fas_x_preferred":[
        "\u0645\u06cc\u0631\u0632\u0627\u067e\u0648\u0631"
    ],
    "name:fra_x_preferred":[
        "Mirzapur"
    ],
    "name:guj_x_preferred":[
        "\u0aae\u0abf\u0ab0\u0acd\u0a9c\u0abe\u0aaa\u0ac1\u0ab0"
    ],
    "name:heb_x_preferred":[
        "\u05de\u05d9\u05e8\u05d6\u05d0\u05e4\u05d5\u05e8"
    ],
    "name:hin_x_preferred":[
        "\u092e\u093f\u0930\u094d\u091c\u093c\u093e\u092a\u0941\u0930"
    ],
    "name:hye_x_preferred":[
        "\u0544\u056b\u0580\u0566\u0561\u057a\u0578\u0582\u0580"
    ],
    "name:ind_x_preferred":[
        "Mirzapur"
    ],
    "name:ita_x_preferred":[
        "Mirzapur"
    ],
    "name:jpn_x_preferred":[
        "\u30df\u30fc\u30eb\u30b6\u30fc\u30d7\u30eb"
    ],
    "name:mai_x_preferred":[
        "\u092e\u093f\u0930\u094d\u091c\u093e\u092a\u0941\u0930"
    ],
    "name:mar_x_preferred":[
        "\u092e\u093f\u0930\u094d\u091d\u093e\u092a\u0942\u0930"
    ],
    "name:mlg_x_preferred":[
        "Mirzapur"
    ],
    "name:new_x_preferred":[
        "\u092e\u093f\u0930\u094d\u091c\u093e\u092a\u0941\u0930"
    ],
    "name:nor_x_preferred":[
        "Mirzapur"
    ],
    "name:pam_x_preferred":[
        "Mirzapur"
    ],
    "name:pnb_x_preferred":[
        "\u0645\u0631\u0632\u0627\u067e\u0648\u0631"
    ],
    "name:pol_x_preferred":[
        "Mirzapur"
    ],
    "name:rus_x_preferred":[
        "\u041c\u0438\u0440\u0437\u0430\u043f\u0443\u0440"
    ],
    "name:san_x_preferred":[
        "\u092e\u093f\u0930\u094d\u091c\u093e\u092a\u0941\u0930\u092e\u094d"
    ],
    "name:srp_x_preferred":[
        "\u041c\u0438\u0440\u0437\u0430\u043f\u0443\u0440-\u0412\u0438\u043d\u0434\u0445\u0458\u0430\u0447\u0430\u043b"
    ],
    "name:swe_x_preferred":[
        "Mirzapur-cum-Vindhy\u0101chal"
    ],
    "name:tam_x_preferred":[
        "\u0bae\u0bbf\u0bb0\u0bcd\u0b9a\u0bbe\u0baa\u0bc2\u0bb0\u0bcd"
    ],
    "name:ukr_x_preferred":[
        "\u041c\u0456\u0440\u0437\u0430\u043f\u0443\u0440"
    ],
    "name:urd_x_preferred":[
        "\u0645\u0631\u0632\u0627\u067e\u0648\u0631"
    ],
    "name:zho_x_preferred":[
        "\u5bc6\u672d\u6d66"
    ],
    "wof:name":"Mirzapur",
    "wof:placetype":"locality"
},
  "geometry": {"coordinates":[88.48851999999999,25.16649],"type":"Point"}
}