{
  "type": "Feature",
  "properties": {
    "gn:admin1_code":"84",
    "gn:admin2_code":"2084.0",
    "gn:admin3_code":"208458.0",
    "gn:admin4_code":"20845867.0",
    "gn:asciiname":"Barbania",
    "gn:country_code":"BD",
    "gn:dem":38,
    "gn:feature_class":"P",
    "gn:feature_code":"PPL",
    "gn:name":"Barbania",
    "gn:population":0,
    "gn:timezone":"Asia/Dhaka",
    "iso:country":"BD",
    "name:azb_x_preferred":[
        "\u0628\u0627\u0631\u0628\u0627\u0646\u06cc\u0627"
    ],
    "name:bel_x_preferred":[
        "\u0411\u0430\u0440\u0431\u0430\u043d\u0456\u044f"
    ],
    "name:ben_x_preferred":[
        "Barbania"
    ],
    "name:bul_x_preferred":[
        "\u0411\u0430\u0440\u0431\u0430\u043d\u0438\u044f"
    ],
    "name:ceb_x_preferred":[
        "Barbania"
    ],
    "name:deu_x_preferred":[
        "Barbania"
    ],
    "name:epo_x_preferred":[
        "Barbania"
    ],
    "name:eus_x_preferred":[
        "Barbania"
    ],
    "name:fas_x_preferred":[
        "\u0628\u0627\u0631\u0628\u0627\u0646\u06cc\u0627"
    ],
    "name:fra_x_preferred":[
        "Barbania"
    ],
    "name:hun_x_preferred":[
        "Barbania"
    ],
    "name:hye_x_preferred":[
        "\u0532\u0561\u0580\u0562\u0561\u0576\u056b\u0561"
    ],
    "name:ind_x_preferred":[
        "Barbania"
    ],
    "name:ita_x_preferred":[
        "Barbania"
    ],
    "name:jpn_x_preferred":[
        "\u30d0\u30eb\u30d0\u30cb\u30fc\u30a2"
    ],
    "name:kaz_x_preferred":[
        "\u0411\u0430\u0440\u0431\u0430\u043d\u0438\u044f"
    ],
    "name:lat_x_preferred":[
        "Barbania"
    ],
    "name:lmo_x_preferred":[
        "Barbania"
    ],
    "name:msa_x_preferred":[
        "Barbania"
    ],
    "name:nap_x_preferred":[
        "Barbania"
    ],
    "name:nld_x_preferred":[
        "Barbania"
    ],
    "name:pms_x_preferred":[
        "Barbani\u00e0"
    ],
    "name:pol_x_preferred":[
        "Barbania"
    ],
    "name:por_x_preferred":[
        "Barbania"
    ],
    "name:ron_x_preferred":[
        "Barbania"
    ],
    "name:rus_x_preferred":[
        "\u0411\u0430\u0440\u0431\u0430\u043d\u0438\u044f"
    ],
    "name:scn_x_preferred":[
        "Barbania"
    ],
    "name:spa_x_preferred":[
        "Barbania"
    ],
    "name:srp_x_preferred":[
        "\u0411\u0430\u0440\u0431\u0430\u043d\u0438\u0458\u0430"
    ],
    "name:swe_x_preferred":[
        "Barbania"
    ],
    "name:tgl_x_preferred":[
        "Barbania"
    ],
    "name:ukr_x_preferred":[
        "\u0411\u0430\u0440\u0431\u0430\u043d\u0456\u044f"
    ],
    "name:uzb_x_preferred":[
        "Barbania"
    ],
    "name:vie_x_preferred":[
        "Barbania"
    ],
    "name:vol_x_preferred":[
        "Barbania"
    ],
    "name:war_x_preferred":[
        "Barbania"
    ],
    "name:zho_x_preferred":[
        "\u5df4\u5c14\u5df4\u5c3c\u4e9a"
    ],
    "wof:name":"Barbania",
    "wof:placetype":"locality"
},
  "geometry": {"coordinates":[92.1878,22.87563],"type":"Point"}
}