{
  "type": "Feature",
  "properties": {
    "gn:admin1_code":"84",
    "gn:admin2_code":"2084.0",
    "gn:admin3_code":"208458.0",
    "gn:admin4_code":"20845867.0",
    "gn:asciiname":"Barbania",
    "gn:country_code":"BD",
    "gn:dem":38,
    "gn:feature_class":"P",
    "gn:feature_code":"PPL",
    "gn:name":"Barbania",
    "gn:population":0,
    "gn:timezone":"Asia/Dhaka",
    "iso:country":"BD",
    "name:ben_x_preferred":[
        "Barbania"
    ],
    "wof:name":"Barbania",
    "wof:placetype":"locality"
},
  "geometry": {"coordinates":[92.1878,22.87563],"type":"Point"}
}