{
  "type": "Feature",
  "properties": {
    "gn:admin1_code":"H",
    "gn:admin2_code":"3061.0",
    "gn:admin3_code":"306181.0",
    "gn:admin4_code":"30618163.0",
    "gn:asciiname":"Dhanta",
    "gn:country_code":"BD",
    "gn:dem":18,
    "gn:feature_class":"P",
    "gn:feature_code":"PPL",
    "gn:name":"Dhanta",
    "gn:population":0,
    "gn:timezone":"Asia/Dhaka",
    "iso:country":"BD",
    "wof:name":"Dhanta",
    "wof:placetype":"locality"
},
  "geometry": {"coordinates":[90.34847000000001,24.89285],"type":"Point"}
}