{
  "type": "Feature",
  "properties": {
    "gn:admin1_code":"81",
    "gn:admin2_code":"3048",
    "gn:admin3_code":"304806.0",
    "gn:admin4_code":"30480686.0",
    "gn:asciiname":"Nilakhi",
    "gn:country_code":"BD",
    "gn:dem":14,
    "gn:feature_class":"P",
    "gn:feature_code":"PPL",
    "gn:name":"Nilakhi",
    "gn:population":0,
    "gn:timezone":"Asia/Dhaka",
    "iso:country":"BD",
    "wof:name":"Nilakhi",
    "wof:placetype":"locality"
},
  "geometry": {"coordinates":[90.86524,24.2246],"type":"Point"}
}