{
  "type": "Feature",
  "properties": {
    "gn:admin1_code":"83",
    "gn:admin2_code":"5064.0",
    "gn:admin3_code":"506475.0",
    "gn:admin4_code":"50647569.0",
    "gn:asciiname":"Moyiakuri",
    "gn:country_code":"BD",
    "gn:dem":45,
    "gn:feature_class":"P",
    "gn:feature_code":"PPL",
    "gn:name":"Moyi\u0101kuri",
    "gn:population":0,
    "gn:timezone":"Asia/Dhaka",
    "iso:country":"BD",
    "name:ben_x_preferred":[
        "Moyi\u0101kuri"
    ],
    "wof:name":"Moyiakuri",
    "wof:placetype":"locality"
},
  "geometry": {"coordinates":[88.63179000000002,25.14589],"type":"Point"}
}