{
  "type": "Feature",
  "properties": {
    "gn:admin1_code":"83",
    "gn:admin2_code":"5010",
    "gn:admin3_code":"501021.0",
    "gn:admin4_code":"50102112.0",
    "gn:asciiname":"Mansurpur",
    "gn:country_code":"BD",
    "gn:dem":23,
    "gn:feature_class":"P",
    "gn:feature_code":"PPL",
    "gn:name":"Mansurpur",
    "gn:population":0,
    "gn:timezone":"Asia/Dhaka",
    "iso:country":"BD",
    "wof:name":"Mansurpur",
    "wof:placetype":"locality"
},
  "geometry": {"coordinates":[89.36060999999999,24.80151],"type":"Point"}
}