{
  "type": "Feature",
  "properties": {
    "gn:admin1_code":"87",
    "gn:admin2_code":"5527.0",
    "gn:admin3_code":"552710.0",
    "gn:admin4_code":"55271059.0",
    "gn:asciiname":"Benipur",
    "gn:country_code":"BD",
    "gn:dem":29,
    "gn:feature_class":"P",
    "gn:feature_code":"PPL",
    "gn:name":"Benipur",
    "gn:population":0,
    "gn:timezone":"Asia/Dhaka",
    "iso:country":"BD",
    "name:ben_x_preferred":[
        "Benipur"
    ],
    "wof:name":"Benipur",
    "wof:placetype":"locality"
},
  "geometry": {"coordinates":[88.94795000000001,25.33219],"type":"Point"}
}