{
  "type": "Feature",
  "properties": {
    "gn:admin1_code":"87",
    "gn:admin2_code":"5552.0",
    "gn:admin3_code":"555270.0",
    "gn:admin4_code":"55527081.0",
    "gn:asciiname":"Panisala",
    "gn:country_code":"BD",
    "gn:dem":73,
    "gn:feature_class":"P",
    "gn:feature_code":"PPL",
    "gn:name":"P\u0101nis\u0101la",
    "gn:population":0,
    "gn:timezone":"Asia/Dhaka",
    "iso:country":"BD",
    "name:ben_x_preferred":[
        "P\u0101nis\u0101la"
    ],
    "name:vie_x_preferred":[
        "Panisala"
    ],
    "wof:name":"Panisala",
    "wof:placetype":"locality"
},
  "geometry": {"coordinates":[88.96498000000003,26.41979000000001],"type":"Point"}
}