{
  "type": "Feature",
  "properties": {
    "gn:admin1_code":"84",
    "gn:admin2_code":"2013.0",
    "gn:admin3_code":"201379.0",
    "gn:admin4_code":"20137969.0",
    "gn:asciiname":"Chhengar Char",
    "gn:cc2":"BD",
    "gn:country_code":"BD",
    "gn:dem":7,
    "gn:feature_class":"P",
    "gn:feature_code":"PPL",
    "gn:name":"Chheng\u0101r Char",
    "gn:population":0,
    "gn:timezone":"Asia/Dhaka",
    "iso:country":"BD",
    "name:und_x_variant":[
        "Changerchar",
        "Chheng\u0101r Char"
    ],
    "wof:name":"Chhengar Char",
    "wof:placetype":"locality"
},
  "geometry": {"coordinates":[90.61667,23.46667],"type":"Point"}
}