{
  "type": "Feature",
  "properties": {
    "gn:admin1_code":"83",
    "gn:admin2_code":"5064.0",
    "gn:admin3_code":"506486.0",
    "gn:admin4_code":"50648639.0",
    "gn:asciiname":"Goala",
    "gn:country_code":"BD",
    "gn:dem":37,
    "gn:feature_class":"P",
    "gn:feature_code":"PPL",
    "gn:name":"Go\u0101la",
    "gn:population":0,
    "gn:timezone":"Asia/Dhaka",
    "iso:country":"BD",
    "name:ben_x_preferred":[
        "Go\u0101la"
    ],
    "name:ceb_x_preferred":[
        "Goala"
    ],
    "name:swe_x_preferred":[
        "Goala"
    ],
    "wof:name":"Goala",
    "wof:placetype":"locality"
},
  "geometry": {"coordinates":[88.50758,25.11275],"type":"Point"}
}