{
  "type": "Feature",
  "properties": {
    "gn:admin1_code":"87",
    "gn:admin2_code":"5573.0",
    "gn:admin3_code":"557312.0",
    "gn:admin4_code":"55731219.0",
    "gn:asciiname":"Salhata",
    "gn:country_code":"BD",
    "gn:dem":54,
    "gn:feature_class":"P",
    "gn:feature_code":"PPL",
    "gn:name":"Salhata",
    "gn:population":0,
    "gn:timezone":"Asia/Dhaka",
    "iso:country":"BD",
    "name:ben_x_preferred":[
        "Salhata"
    ],
    "wof:name":"Salhata",
    "wof:placetype":"locality"
},
  "geometry": {"coordinates":[88.98239000000002,26.11256],"type":"Point"}
}