{
  "type": "Feature",
  "properties": {
    "gn:admin1_code":"81",
    "gn:admin2_code":"3056",
    "gn:admin3_code":"305622.0",
    "gn:admin4_code":"30562271.0",
    "gn:asciiname":"Nandir Bandha",
    "gn:country_code":"BD",
    "gn:dem":11,
    "gn:feature_class":"P",
    "gn:feature_code":"PPL",
    "gn:name":"Nandir B\u0101ndha",
    "gn:population":0,
    "gn:timezone":"Asia/Dhaka",
    "iso:country":"BD",
    "wof:name":"Nandir Bandha",
    "wof:placetype":"locality"
},
  "geometry": {"coordinates":[89.90064,23.92493],"type":"Point"}
}