{
  "type": "Feature",
  "properties": {
    "gn:admin1_code":"85",
    "gn:admin2_code":"1078.0",
    "gn:admin3_code":"107897.0",
    "gn:admin4_code":"10789783.0",
    "gn:asciiname":"Uttaripara",
    "gn:country_code":"BD",
    "gn:dem":9,
    "gn:feature_class":"P",
    "gn:feature_code":"PPL",
    "gn:name":"Uttarip\u0101ra",
    "gn:population":0,
    "gn:timezone":"Asia/Dhaka",
    "iso:country":"BD",
    "name:ben_x_preferred":[
        "Uttarip\u0101ra"
    ],
    "wof:name":"Uttaripara",
    "wof:placetype":"locality"
},
  "geometry": {"coordinates":[90.40807,21.90617],"type":"Point"}
}