{
  "type": "Feature",
  "properties": {
    "gn:admin1_code":"82",
    "gn:asciiname":"Lomobaria",
    "gn:country_code":"BD",
    "gn:dem":7,
    "gn:feature_class":"P",
    "gn:feature_code":"PPL",
    "gn:name":"Lomobaria",
    "gn:population":0,
    "gn:timezone":"Asia/Dhaka",
    "iso:country":"BD",
    "name:ben_x_preferred":[
        "Lomobaria"
    ],
    "wof:name":"Lomobaria",
    "wof:placetype":"locality"
},
  "geometry": {"coordinates":[90.29053999999999,22.32771],"type":"Point"}
}