{
  "type": "Feature",
  "properties": {
    "gn:admin1_code":"82",
    "gn:admin2_code":"4087.0",
    "gn:admin3_code":"408747.0",
    "gn:admin4_code":"40874755.0",
    "gn:asciiname":"Durbadanga",
    "gn:country_code":"BD",
    "gn:dem":1,
    "gn:feature_class":"P",
    "gn:feature_code":"PPL",
    "gn:name":"Durb\u0101d\u0101nga",
    "gn:population":0,
    "gn:timezone":"Asia/Dhaka",
    "iso:country":"BD",
    "name:ben_x_preferred":[
        "Durb\u0101d\u0101nga"
    ],
    "wof:name":"Durbadanga",
    "wof:placetype":"locality"
},
  "geometry": {"coordinates":[89.06175999999998,22.46316],"type":"Point"}
}