{
  "type": "Feature",
  "properties": {
    "gn:admin1_code":"81",
    "gn:admin2_code":"3029",
    "gn:admin3_code":"302956.0",
    "gn:admin4_code":"30295684.0",
    "gn:asciiname":"Raghunathpur",
    "gn:country_code":"BD",
    "gn:dem":16,
    "gn:feature_class":"P",
    "gn:feature_code":"PPL",
    "gn:name":"Raghun\u0101thpur",
    "gn:population":0,
    "gn:timezone":"Asia/Dhaka",
    "iso:country":"BD",
    "wof:name":"Raghunathpur",
    "wof:placetype":"locality"
},
  "geometry": {"coordinates":[89.68895999999999,23.55101],"type":"Point"}
}