{
  "type": "Feature",
  "properties": {
    "gn:admin1_code":"83",
    "gn:admin2_code":"5076.0",
    "gn:admin3_code":"507616.0",
    "gn:admin4_code":"50761642.0",
    "gn:asciiname":"Srinibasdad",
    "gn:country_code":"BD",
    "gn:dem":12,
    "gn:feature_class":"P",
    "gn:feature_code":"PPL",
    "gn:name":"Srinib\u0101sdad",
    "gn:population":0,
    "gn:timezone":"Asia/Dhaka",
    "iso:country":"BD",
    "name:ben_x_preferred":[
        "Srinib\u0101sdad"
    ],
    "wof:name":"Srinibasdad",
    "wof:placetype":"locality"
},
  "geometry": {"coordinates":[89.65314000000002,23.92641],"type":"Point"}
}