{
  "type": "Feature",
  "properties": {
    "gn:admin1_code":"82",
    "gn:admin2_code":"4041.0",
    "gn:admin3_code":"404123.0",
    "gn:admin4_code":"40412383.0",
    "gn:asciiname":"Kulbaria",
    "gn:country_code":"BD",
    "gn:dem":11,
    "gn:feature_class":"P",
    "gn:feature_code":"PPL",
    "gn:name":"Kulb\u0101ria",
    "gn:population":0,
    "gn:timezone":"Asia/Dhaka",
    "iso:country":"BD",
    "name:ben_x_preferred":[
        "Kulb\u0101ria"
    ],
    "wof:name":"Kulbaria",
    "wof:placetype":"locality"
},
  "geometry": {"coordinates":[88.99124999999999,22.94948],"type":"Point"}
}