{
  "type": "Feature",
  "properties": {
    "gn:admin1_code":"82",
    "gn:admin2_code":"4050",
    "gn:admin3_code":"405071.0",
    "gn:admin4_code":"40507143.0",
    "gn:asciiname":"Tarapur",
    "gn:country_code":"BD",
    "gn:dem":17,
    "gn:feature_class":"P",
    "gn:feature_code":"PPL",
    "gn:name":"T\u0101r\u0101pur",
    "gn:population":0,
    "gn:timezone":"Asia/Dhaka",
    "iso:country":"BD",
    "name:deu_x_preferred":[
        "Tarapur"
    ],
    "wof:name":"Tarapur",
    "wof:placetype":"locality"
},
  "geometry": {"coordinates":[89.26093,23.87686],"type":"Point"}
}