{
  "type": "Feature",
  "properties": {
    "gn:admin1_code":"83",
    "gn:admin2_code":"5081",
    "gn:admin3_code":"508112.0",
    "gn:admin4_code":"50811282.0",
    "gn:asciiname":"Kastha",
    "gn:country_code":"BD",
    "gn:dem":19,
    "gn:feature_class":"P",
    "gn:feature_code":"PPL",
    "gn:name":"Kastha",
    "gn:population":0,
    "gn:timezone":"Asia/Dhaka",
    "iso:country":"BD",
    "name:ben_x_preferred":[
        "Kastha"
    ],
    "wof:name":"Kastha",
    "wof:placetype":"locality"
},
  "geometry": {"coordinates":[88.79595,24.63689],"type":"Point"}
}