{
  "type": "Feature",
  "properties": {
    "gn:admin1_code":"81",
    "gn:admin2_code":"3048",
    "gn:admin3_code":"304842.0",
    "gn:admin4_code":"30484294.0",
    "gn:asciiname":"Sutarpara",
    "gn:country_code":"BD",
    "gn:dem":11,
    "gn:feature_class":"P",
    "gn:feature_code":"PPL",
    "gn:name":"Sut\u0101rp\u0101ra",
    "gn:population":0,
    "gn:timezone":"Asia/Dhaka",
    "iso:country":"BD",
    "wof:name":"Sutarpara",
    "wof:placetype":"locality"
},
  "geometry": {"coordinates":[90.96174000000001,24.44203],"type":"Point"}
}