{
  "type": "Feature",
  "properties": {
    "gn:admin1_code":"84",
    "gn:admin2_code":"2015.0",
    "gn:admin3_code":"201508.0",
    "gn:admin4_code":"20150844.0",
    "gn:asciiname":"Bailchari",
    "gn:country_code":"BD",
    "gn:dem":9,
    "gn:feature_class":"P",
    "gn:feature_code":"PPL",
    "gn:name":"Bailchari",
    "gn:population":0,
    "gn:timezone":"Asia/Dhaka",
    "iso:country":"BD",
    "wof:name":"Bailchari",
    "wof:placetype":"locality"
},
  "geometry": {"coordinates":[91.93944,22.05917],"type":"Point"}
}