{
  "type": "Feature",
  "properties": {
    "gn:admin1_code":"81",
    "gn:admin2_code":"3026.0",
    "gn:admin3_code":"302640.0",
    "gn:admin4_code":"30264025.0",
    "gn:asciiname":"Goran",
    "gn:country_code":"BD",
    "gn:dem":13,
    "gn:feature_class":"P",
    "gn:feature_code":"PPL",
    "gn:name":"Gor\u0101n",
    "gn:population":0,
    "gn:timezone":"Asia/Dhaka",
    "iso:country":"BD",
    "wof:name":"Goran",
    "wof:placetype":"locality"
},
  "geometry": {"coordinates":[90.43413,23.75027],"type":"Point"}
}