{
  "type": "Feature",
  "properties": {
    "gn:admin1_code":"85",
    "gn:admin2_code":"1006.0",
    "gn:admin3_code":"100651.0",
    "gn:admin4_code":"10065134.0",
    "gn:asciiname":"Charbaria Lamchari",
    "gn:country_code":"BD",
    "gn:dem":10,
    "gn:feature_class":"P",
    "gn:feature_code":"PPL",
    "gn:name":"Charb\u0101ria Lamchari",
    "gn:population":0,
    "gn:timezone":"Asia/Dhaka",
    "iso:country":"BD",
    "name:und_x_variant":[
        "Charb\u0101ria Lamchari"
    ],
    "name:zho_x_preferred":[
        "\u5dee\u5c14\u5df4\u5229\u4e9a\u62c9\u59c6\u5dee\u91cc"
    ],
    "wof:name":"Charbaria Lamchari",
    "wof:placetype":"locality"
},
  "geometry": {"coordinates":[90.41540999999999,22.73714],"type":"Point"}
}