{
  "type": "Feature",
  "properties": {
    "gn:admin1_code":"82",
    "gn:admin2_code":"4050.0",
    "gn:admin3_code":"405015.0",
    "gn:admin4_code":"40501554.0",
    "gn:asciiname":"Ramchandrapur",
    "gn:country_code":"BD",
    "gn:dem":21,
    "gn:feature_class":"P",
    "gn:feature_code":"PPL",
    "gn:name":"R\u0101mchandrapur",
    "gn:population":0,
    "gn:timezone":"Asia/Dhaka",
    "iso:country":"BD",
    "name:ben_x_preferred":[
        "R\u0101mchandrapur"
    ],
    "wof:name":"Ramchandrapur",
    "wof:placetype":"locality"
},
  "geometry": {"coordinates":[88.95801,24.03737000000001],"type":"Point"}
}