{
  "type": "Feature",
  "properties": {
    "gn:admin1_code":"84",
    "gn:admin2_code":"2015.0",
    "gn:admin3_code":"201512.0",
    "gn:admin4_code":"20151266.0",
    "gn:asciiname":"Chhandandi",
    "gn:country_code":"BD",
    "gn:dem":8,
    "gn:feature_class":"P",
    "gn:feature_code":"PPL",
    "gn:name":"Chhandandi",
    "gn:population":0,
    "gn:timezone":"Asia/Dhaka",
    "iso:country":"BD",
    "name:ben_x_preferred":[
        "Chhandandi"
    ],
    "wof:name":"Chhandandi",
    "wof:placetype":"locality"
},
  "geometry": {"coordinates":[91.94432999999999,22.37612],"type":"Point"}
}