{
  "type": "Feature",
  "properties": {
    "gn:admin1_code":"81",
    "gn:admin2_code":"3056.0",
    "gn:admin3_code":"305682.0",
    "gn:admin4_code":"30568225.0",
    "gn:asciiname":"Char Narayanpur",
    "gn:country_code":"BD",
    "gn:dem":10,
    "gn:feature_class":"P",
    "gn:feature_code":"PPL",
    "gn:name":"Char N\u0101r\u0101yanpur",
    "gn:population":0,
    "gn:timezone":"Asia/Dhaka",
    "iso:country":"BD",
    "wof:name":"Char Narayanpur",
    "wof:placetype":"locality"
},
  "geometry": {"coordinates":[90.22873,23.76632],"type":"Point"}
}