{
  "type": "Feature",
  "properties": {
    "gn:admin1_code":"81",
    "gn:admin2_code":"3054",
    "gn:admin3_code":"305480.0",
    "gn:admin4_code":"30548009.0",
    "gn:asciiname":"Lausar",
    "gn:country_code":"BD",
    "gn:dem":5,
    "gn:feature_class":"P",
    "gn:feature_code":"PPL",
    "gn:name":"L\u0101us\u0101r",
    "gn:population":0,
    "gn:timezone":"Asia/Dhaka",
    "iso:country":"BD",
    "name:und_x_variant":[
        "Lousar",
        "L\u0101us\u0101r"
    ],
    "wof:name":"Lausar",
    "wof:placetype":"locality"
},
  "geometry": {"coordinates":[90.06623,23.13317],"type":"Point"}
}