{
  "type": "Feature",
  "properties": {
    "gn:admin1_code":"87",
    "gn:admin2_code":"5577.0",
    "gn:admin3_code":"557790.0",
    "gn:admin4_code":"55779067.0",
    "gn:asciiname":"Kanchabari",
    "gn:country_code":"BD",
    "gn:dem":94,
    "gn:feature_class":"P",
    "gn:feature_code":"PPL",
    "gn:name":"Kanchab\u0101ri",
    "gn:population":0,
    "gn:timezone":"Asia/Dhaka",
    "iso:country":"BD",
    "name:ben_x_preferred":[
        "Kanchab\u0101ri"
    ],
    "wof:name":"Kanchabari",
    "wof:placetype":"locality"
},
  "geometry": {"coordinates":[88.41673,26.48068],"type":"Point"}
}