{
  "type": "Feature",
  "properties": {
    "gn:admin1_code":"85",
    "gn:admin2_code":"1006",
    "gn:admin3_code":"100651.0",
    "gn:admin4_code":"10065134.0",
    "gn:asciiname":"Puranpara",
    "gn:country_code":"BD",
    "gn:dem":12,
    "gn:feature_class":"P",
    "gn:feature_code":"PPL",
    "gn:name":"Pur\u0101np\u0101ra",
    "gn:population":0,
    "gn:timezone":"Asia/Dhaka",
    "iso:country":"BD",
    "wof:name":"Puranpara",
    "wof:placetype":"locality"
},
  "geometry": {"coordinates":[90.35847,22.72741],"type":"Point"}
}