{
  "type": "Feature",
  "properties": {
    "gn:admin1_code":"83",
    "gn:asciiname":"Gobindanagar",
    "gn:country_code":"BD",
    "gn:dem":24,
    "gn:feature_class":"P",
    "gn:feature_code":"PPL",
    "gn:name":"Gobindanagar",
    "gn:population":0,
    "gn:timezone":"Asia/Dhaka",
    "iso:country":"BD",
    "name:ben_x_preferred":[
        "Gobindanagar"
    ],
    "wof:name":"Gobindanagar",
    "wof:placetype":"locality"
},
  "geometry": {"coordinates":[89.43259999999999,25.16413],"type":"Point"}
}