{
  "type": "Feature",
  "properties": {
    "gn:admin1_code":"82",
    "gn:admin2_code":"4047.0",
    "gn:admin3_code":"404717.0",
    "gn:admin4_code":"40471731.0",
    "gn:asciiname":"Dacope",
    "gn:country_code":"BD",
    "gn:dem":6,
    "gn:feature_class":"P",
    "gn:feature_code":"PPL",
    "gn:name":"Dacope",
    "gn:population":0,
    "gn:timezone":"Asia/Dhaka",
    "iso:country":"BD",
    "name:und_x_variant":[
        "B\u0101ruikh\u0101li",
        "D\u0101kupi",
        "Dacope"
    ],
    "wof:name":"Dacope",
    "wof:placetype":"locality"
},
  "geometry": {"coordinates":[89.48743,22.5816],"type":"Point"}
}