{
  "type": "Feature",
  "properties": {
    "gn:admin1_code":"82",
    "gn:admin2_code":"4050.0",
    "gn:admin3_code":"405071.0",
    "gn:admin4_code":"40507194.0",
    "gn:asciiname":"Gobindapur",
    "gn:country_code":"BD",
    "gn:dem":16,
    "gn:feature_class":"P",
    "gn:feature_code":"PPL",
    "gn:name":"Gobindapur",
    "gn:population":0,
    "gn:timezone":"Asia/Dhaka",
    "iso:country":"BD",
    "name:ben_x_preferred":[
        "Gobindapur"
    ],
    "wof:name":"Gobindapur",
    "wof:placetype":"locality"
},
  "geometry": {"coordinates":[89.22573,23.96739],"type":"Point"}
}