{
  "type": "Feature",
  "properties": {
    "gn:admin1_code":"87",
    "gn:admin2_code":"5527.0",
    "gn:admin3_code":"552710.0",
    "gn:admin4_code":"55271071.0",
    "gn:asciiname":"Ratanpur",
    "gn:country_code":"BD",
    "gn:dem":37,
    "gn:feature_class":"P",
    "gn:feature_code":"PPL",
    "gn:name":"Ratanpur",
    "gn:population":0,
    "gn:timezone":"Asia/Dhaka",
    "iso:country":"BD",
    "name:ben_x_preferred":[
        "Ratanpur"
    ],
    "wof:name":"Ratanpur",
    "wof:placetype":"locality"
},
  "geometry": {"coordinates":[89.0003,25.44175],"type":"Point"}
}