{
  "type": "Feature",
  "properties": {
    "gn:admin1_code":"H",
    "gn:admin2_code":"3089",
    "gn:admin3_code":"308988.0",
    "gn:admin4_code":"30898847.0",
    "gn:asciiname":"Polobhanga",
    "gn:country_code":"BD",
    "gn:dem":24,
    "gn:feature_class":"P",
    "gn:feature_code":"PPL",
    "gn:name":"Polobh\u0101nga",
    "gn:population":0,
    "gn:timezone":"Asia/Dhaka",
    "iso:country":"BD",
    "name:ben_x_preferred":[
        "Polobh\u0101nga"
    ],
    "wof:name":"Polobhanga",
    "wof:placetype":"locality"
},
  "geometry": {"coordinates":[90.11036,25.0274],"type":"Point"}
}