{
  "type": "Feature",
  "properties": {
    "gn:admin1_code":"84",
    "gn:admin2_code":"2019",
    "gn:admin3_code":"201927.0",
    "gn:admin4_code":"20192723.0",
    "gn:asciiname":"Lagaada",
    "gn:country_code":"BD",
    "gn:dem":11,
    "gn:feature_class":"P",
    "gn:feature_code":"PPL",
    "gn:name":"Lagaad\u0101",
    "gn:population":0,
    "gn:timezone":"Asia/Dhaka",
    "iso:country":"BD",
    "name:und_x_variant":[
        "Lagaad\u0101",
        "Lagadda"
    ],
    "wof:name":"Lagaada",
    "wof:placetype":"locality"
},
  "geometry": {"coordinates":[90.94571999999999,23.39938],"type":"Point"}
}