{
  "type": "Feature",
  "properties": {
    "gn:admin1_code":"81",
    "gn:admin2_code":"3056.0",
    "gn:admin3_code":"305622.0",
    "gn:admin4_code":"30562211.0",
    "gn:asciiname":"Banyaprasad",
    "gn:country_code":"BD",
    "gn:dem":14,
    "gn:feature_class":"P",
    "gn:feature_code":"PPL",
    "gn:name":"Bany\u0101pras\u0101d",
    "gn:population":0,
    "gn:timezone":"Asia/Dhaka",
    "iso:country":"BD",
    "wof:name":"Banyaprasad",
    "wof:placetype":"locality"
},
  "geometry": {"coordinates":[89.91364,23.84855],"type":"Point"}
}