{
  "type": "Feature",
  "properties": {
    "gn:admin1_code":"83",
    "gn:admin2_code":"5064.0",
    "gn:admin3_code":"506479.0",
    "gn:admin4_code":"50647955.0",
    "gn:asciiname":"Kalibari",
    "gn:country_code":"BD",
    "gn:dem":31,
    "gn:feature_class":"P",
    "gn:feature_code":"PPL",
    "gn:name":"K\u0101libari",
    "gn:population":0,
    "gn:timezone":"Asia/Dhaka",
    "iso:country":"BD",
    "name:ben_x_preferred":[
        "K\u0101libari"
    ],
    "wof:name":"Kalibari",
    "wof:placetype":"locality"
},
  "geometry": {"coordinates":[88.48149000000002,25.05883],"type":"Point"}
}