{
  "type": "Feature",
  "properties": {
    "gn:admin1_code":"87",
    "gn:admin2_code":"5573.0",
    "gn:admin3_code":"557385.0",
    "gn:admin4_code":"55738527.0",
    "gn:asciiname":"Batlagari",
    "gn:country_code":"BD",
    "gn:dem":43,
    "gn:feature_class":"P",
    "gn:feature_code":"PPL",
    "gn:name":"Batl\u0101g\u0101ri",
    "gn:population":0,
    "gn:timezone":"Asia/Dhaka",
    "iso:country":"BD",
    "name:ben_x_preferred":[
        "Batl\u0101g\u0101ri"
    ],
    "wof:name":"Batlagari",
    "wof:placetype":"locality"
},
  "geometry": {"coordinates":[88.86346999999998,25.7831],"type":"Point"}
}