{
  "type": "Feature",
  "properties": {
    "gn:admin1_code":"81",
    "gn:admin2_code":"3086.0",
    "gn:admin3_code":"308636.0",
    "gn:admin4_code":"30863635.0",
    "gn:asciiname":"Char Satmatia",
    "gn:country_code":"BD",
    "gn:dem":9,
    "gn:feature_class":"P",
    "gn:feature_code":"PPL",
    "gn:name":"Char S\u0101tm\u0101tia",
    "gn:population":0,
    "gn:timezone":"Asia/Dhaka",
    "iso:country":"BD",
    "name:und_x_variant":[
        "Char S\u0101tm\u0101tia"
    ],
    "wof:name":"Char Satmatia",
    "wof:placetype":"locality"
},
  "geometry": {"coordinates":[90.40568,23.05807],"type":"Point"}
}