{
  "type": "Feature",
  "properties": {
    "gn:admin1_code":"83",
    "gn:admin2_code":"5069",
    "gn:admin3_code":"506963.0",
    "gn:admin4_code":"50696351.0",
    "gn:asciiname":"Mohanpur",
    "gn:country_code":"BD",
    "gn:dem":18,
    "gn:feature_class":"P",
    "gn:feature_code":"PPL",
    "gn:name":"Mohanpur",
    "gn:population":0,
    "gn:timezone":"Asia/Dhaka",
    "iso:country":"BD",
    "name:ben_x_preferred":[
        "Mohanpur"
    ],
    "name:ceb_x_preferred":[
        "Mohanpur"
    ],
    "name:fra_x_preferred":[
        "Mohanpur"
    ],
    "name:ita_x_preferred":[
        "Mohanpur"
    ],
    "name:new_x_preferred":[
        "\u092e\u094b\u0939\u0928\u092a\u0941\u0930 \u0917\u093e\u0935\u093f\u0938"
    ],
    "name:pol_x_preferred":[
        "Mohanpur"
    ],
    "name:swe_x_preferred":[
        "Mohanpur"
    ],
    "wof:name":"Mohanpur",
    "wof:placetype":"locality"
},
  "geometry": {"coordinates":[88.93808,24.36412],"type":"Point"}
}