{
  "type": "Feature",
  "properties": {
    "gn:admin1_code":"81",
    "gn:admin2_code":"3067",
    "gn:admin3_code":"306702.0",
    "gn:admin4_code":"30670271.0",
    "gn:asciiname":"Khirdasdi",
    "gn:country_code":"BD",
    "gn:dem":10,
    "gn:feature_class":"P",
    "gn:feature_code":"PPL",
    "gn:name":"Khird\u0101sdi",
    "gn:population":0,
    "gn:timezone":"Asia/Dhaka",
    "iso:country":"BD",
    "wof:name":"Khirdasdi",
    "wof:placetype":"locality"
},
  "geometry": {"coordinates":[90.68863,23.77442000000001],"type":"Point"}
}