{
  "type": "Feature",
  "properties": {
    "gn:admin1_code":"82",
    "gn:admin2_code":"4041.0",
    "gn:admin3_code":"404104.0",
    "gn:admin4_code":"40410473.0",
    "gn:asciiname":"Banagram",
    "gn:country_code":"BD",
    "gn:dem":10,
    "gn:feature_class":"P",
    "gn:feature_code":"PPL",
    "gn:name":"Banagr\u0101m",
    "gn:population":0,
    "gn:timezone":"Asia/Dhaka",
    "iso:country":"BD",
    "name:ben_x_preferred":[
        "Banagr\u0101m"
    ],
    "wof:name":"Banagram",
    "wof:placetype":"locality"
},
  "geometry": {"coordinates":[89.43689999999999,23.08654],"type":"Point"}
}