{
  "type": "Feature",
  "properties": {
    "gn:admin1_code":"83",
    "gn:admin2_code":"5081.0",
    "gn:admin3_code":"508182.0",
    "gn:admin4_code":"50818281.0",
    "gn:asciiname":"Basupara",
    "gn:country_code":"BD",
    "gn:dem":21,
    "gn:feature_class":"P",
    "gn:feature_code":"PPL",
    "gn:name":"B\u0101sup\u0101ra",
    "gn:population":0,
    "gn:timezone":"Asia/Dhaka",
    "iso:country":"BD",
    "name:ben_x_preferred":[
        "B\u0101sup\u0101ra"
    ],
    "wof:name":"Basupara",
    "wof:placetype":"locality"
},
  "geometry": {"coordinates":[88.85666999999999,24.46347],"type":"Point"}
}