{
  "type": "Feature",
  "properties": {
    "gn:admin1_code":"82",
    "gn:admin2_code":"4041",
    "gn:admin3_code":"404138.0",
    "gn:admin4_code":"40413885.0",
    "gn:asciiname":"Satbaria",
    "gn:country_code":"BD",
    "gn:dem":11,
    "gn:feature_class":"P",
    "gn:feature_code":"PPL",
    "gn:name":"S\u0101tb\u0101ria",
    "gn:population":0,
    "gn:timezone":"Asia/Dhaka",
    "iso:country":"BD",
    "wof:name":"Satbaria",
    "wof:placetype":"locality"
},
  "geometry": {"coordinates":[89.15903,22.90668],"type":"Point"}
}