{
  "type": "Feature",
  "properties": {
    "gn:admin1_code":"84",
    "gn:admin2_code":"2019",
    "gn:admin3_code":"201927.0",
    "gn:admin4_code":"20192779.0",
    "gn:asciiname":"North Badarpur",
    "gn:country_code":"BD",
    "gn:dem":10,
    "gn:feature_class":"P",
    "gn:feature_code":"PPL",
    "gn:name":"North Badarpur",
    "gn:population":0,
    "gn:timezone":"Asia/Dhaka",
    "iso:country":"BD",
    "name:und_x_variant":[
        "Badarpur",
        "North Badarpur"
    ],
    "wof:name":"North Badarpur",
    "wof:placetype":"locality"
},
  "geometry": {"coordinates":[90.96775,23.44362000000001],"type":"Point"}
}