{
  "type": "Feature",
  "properties": {
    "gn:admin1_code":"85",
    "gn:admin2_code":"1006.0",
    "gn:admin3_code":"100603.0",
    "gn:admin4_code":"10060367.0",
    "gn:asciiname":"Gajalia",
    "gn:country_code":"BD",
    "gn:dem":9,
    "gn:feature_class":"P",
    "gn:feature_code":"PPL",
    "gn:name":"Gajalia",
    "gn:population":0,
    "gn:timezone":"Asia/Dhaka",
    "iso:country":"BD",
    "wof:name":"Gajalia",
    "wof:placetype":"locality"
},
  "geometry": {"coordinates":[90.30226999999999,22.7597],"type":"Point"}
}