{
  "type": "Feature",
  "properties": {
    "gn:admin1_code":"81",
    "gn:admin2_code":"3054.0",
    "gn:admin3_code":"305454.0",
    "gn:admin4_code":"30545447.0",
    "gn:asciiname":"Chaturpara",
    "gn:country_code":"BD",
    "gn:dem":11,
    "gn:feature_class":"P",
    "gn:feature_code":"PPL",
    "gn:name":"Chaturp\u0101ra",
    "gn:population":0,
    "gn:timezone":"Asia/Dhaka",
    "iso:country":"BD",
    "wof:name":"Chaturpara",
    "wof:placetype":"locality"
},
  "geometry": {"coordinates":[90.12931,23.1595],"type":"Point"}
}