{
  "type": "Feature",
  "properties": {
    "gn:admin1_code":"82",
    "gn:asciiname":"Arazi Baultali",
    "gn:country_code":"BD",
    "gn:dem":9,
    "gn:feature_class":"P",
    "gn:feature_code":"PPL",
    "gn:name":"\u0100r\u0101zi Baultali",
    "gn:population":0,
    "gn:timezone":"Asia/Dhaka",
    "iso:country":"BD",
    "name:ben_x_preferred":[
        "\u0100r\u0101zi Baultali"
    ],
    "wof:name":"Arazi Baultali",
    "wof:placetype":"locality"
},
  "geometry": {"coordinates":[90.46877000000001,22.47418],"type":"Point"}
}