{
  "type": "Feature",
  "properties": {
    "gn:admin1_code":"85",
    "gn:admin2_code":"1078.0",
    "gn:admin3_code":"107897.0",
    "gn:admin4_code":"10789727.0",
    "gn:asciiname":"Taktabunia",
    "gn:country_code":"BD",
    "gn:dem":8,
    "gn:feature_class":"P",
    "gn:feature_code":"PPL",
    "gn:name":"T\u0101kt\u0101bunia",
    "gn:population":0,
    "gn:timezone":"Asia/Dhaka",
    "iso:country":"BD",
    "name:ben_x_preferred":[
        "T\u0101kt\u0101bunia"
    ],
    "wof:name":"Taktabunia",
    "wof:placetype":"locality"
},
  "geometry": {"coordinates":[90.34815,21.94302],"type":"Point"}
}