{
  "type": "Feature",
  "properties": {
    "gn:admin1_code":"82",
    "gn:admin2_code":"4047.0",
    "gn:admin3_code":"404785.0",
    "gn:admin4_code":"40478517.0",
    "gn:asciiname":"Gabarchaka",
    "gn:country_code":"BD",
    "gn:dem":8,
    "gn:feature_class":"P",
    "gn:feature_code":"PPL",
    "gn:name":"Gabarch\u0101ka",
    "gn:population":0,
    "gn:timezone":"Asia/Dhaka",
    "iso:country":"BD",
    "name:ben_x_preferred":[
        "Gabarch\u0101ka"
    ],
    "wof:name":"Gabarchaka",
    "wof:placetype":"locality"
},
  "geometry": {"coordinates":[89.54948,22.82292],"type":"Point"}
}