{
  "type": "Feature",
  "properties": {
    "gn:admin1_code":"82",
    "gn:admin2_code":"4065.0",
    "gn:admin3_code":"406576.0",
    "gn:admin4_code":"40657613.0",
    "gn:asciiname":"Tabra",
    "gn:country_code":"BD",
    "gn:dem":10,
    "gn:feature_class":"P",
    "gn:feature_code":"PPL",
    "gn:name":"T\u0101bra",
    "gn:population":0,
    "gn:timezone":"Asia/Dhaka",
    "iso:country":"BD",
    "name:ben_x_preferred":[
        "T\u0101bra"
    ],
    "wof:name":"Tabra",
    "wof:placetype":"locality"
},
  "geometry": {"coordinates":[89.58238,23.14403],"type":"Point"}
}