{
  "type": "Feature",
  "properties": {
    "gn:admin1_code":"82",
    "gn:admin2_code":"4047.0",
    "gn:admin3_code":"404753.0",
    "gn:admin4_code":"40475372.0",
    "gn:asciiname":"Deara",
    "gn:country_code":"BD",
    "gn:dem":3,
    "gn:feature_class":"P",
    "gn:feature_code":"PPL",
    "gn:name":"De\u0101ra",
    "gn:population":0,
    "gn:timezone":"Asia/Dhaka",
    "iso:country":"BD",
    "name:ben_x_preferred":[
        "De\u0101ra"
    ],
    "name:ben_x_variant":[
        "Dakhin De\u0101ra"
    ],
    "name:und_x_variant":[
        "Dakshin Deara"
    ],
    "wof:name":"Deara",
    "wof:placetype":"locality"
},
  "geometry": {"coordinates":[89.28626,22.3995],"type":"Point"}
}