{
  "type": "Feature",
  "properties": {
    "gn:admin1_code":"81",
    "gn:admin2_code":"3033",
    "gn:admin3_code":"303336.0",
    "gn:admin4_code":"30333686.0",
    "gn:asciiname":"Targaon",
    "gn:country_code":"BD",
    "gn:dem":13,
    "gn:feature_class":"P",
    "gn:feature_code":"PPL",
    "gn:name":"T\u0101rgaon",
    "gn:population":0,
    "gn:timezone":"Asia/Dhaka",
    "iso:country":"BD",
    "name:und_x_variant":[
        "T\u0101r\u0101gaon",
        "T\u0101rgaon"
    ],
    "wof:name":"Targaon",
    "wof:placetype":"locality"
},
  "geometry": {"coordinates":[90.58617,24.11859],"type":"Point"}
}