{
  "type": "Feature",
  "properties": {
    "gn:admin1_code":"84",
    "gn:admin2_code":"2012",
    "gn:admin3_code":"201285.0",
    "gn:admin4_code":"20128536.0",
    "gn:asciiname":"Malai",
    "gn:country_code":"BD",
    "gn:dem":10,
    "gn:feature_class":"P",
    "gn:feature_code":"PPL",
    "gn:name":"M\u0101l\u0101i",
    "gn:population":0,
    "gn:timezone":"Asia/Dhaka",
    "iso:country":"BD",
    "wof:name":"Malai",
    "wof:placetype":"locality"
},
  "geometry": {"coordinates":[90.97766,23.79613],"type":"Point"}
}