{
  "type": "Feature",
  "properties": {
    "gn:admin1_code":"84",
    "gn:admin2_code":"2012",
    "gn:admin3_code":"201285.0",
    "gn:admin4_code":"20128536.0",
    "gn:asciiname":"Malai",
    "gn:country_code":"BD",
    "gn:dem":10,
    "gn:feature_class":"P",
    "gn:feature_code":"PPL",
    "gn:name":"M\u0101l\u0101i",
    "gn:population":0,
    "gn:timezone":"Asia/Dhaka",
    "iso:country":"BD",
    "name:hin_x_preferred":[
        "\u092e\u0932\u093e\u0908"
    ],
    "name:jpn_x_preferred":[
        "\u30de\u30e9\u30a4"
    ],
    "name:kan_x_preferred":[
        "\u0cae\u0cb2\u0cbe\u0caf\u0cbf"
    ],
    "name:kor_x_preferred":[
        "\ub9d0\ub77c\uc774"
    ],
    "name:mal_x_preferred":[
        "\u0d2e\u0d32\u0d3e\u0d2f\u0d4d"
    ],
    "name:nld_x_preferred":[
        "Malai"
    ],
    "name:spa_x_preferred":[
        "Malai"
    ],
    "wof:name":"Malai",
    "wof:placetype":"locality"
},
  "geometry": {"coordinates":[90.97766,23.79613],"type":"Point"}
}