{
  "type": "Feature",
  "properties": {
    "gn:admin1_code":"81",
    "gn:admin2_code":"3048.0",
    "gn:admin3_code":"304845.0",
    "gn:admin4_code":"30484519.0",
    "gn:asciiname":"Banagram",
    "gn:country_code":"BD",
    "gn:dem":12,
    "gn:feature_class":"P",
    "gn:feature_code":"PPL",
    "gn:name":"Banagr\u0101m",
    "gn:population":0,
    "gn:timezone":"Asia/Dhaka",
    "iso:country":"BD",
    "wof:name":"Banagram",
    "wof:placetype":"locality"
},
  "geometry": {"coordinates":[90.80431,24.34339],"type":"Point"}
}