{
  "type": "Feature",
  "properties": {
    "gn:admin1_code":"87",
    "gn:admin2_code":"5585.0",
    "gn:admin3_code":"558558.0",
    "gn:admin4_code":"55855827.0",
    "gn:asciiname":"Baniapara",
    "gn:country_code":"BD",
    "gn:dem":33,
    "gn:feature_class":"P",
    "gn:feature_code":"PPL",
    "gn:name":"B\u0101ni\u0101p\u0101ra",
    "gn:population":0,
    "gn:timezone":"Asia/Dhaka",
    "iso:country":"BD",
    "name:ben_x_preferred":[
        "B\u0101ni\u0101p\u0101ra"
    ],
    "wof:name":"Baniapara",
    "wof:placetype":"locality"
},
  "geometry": {"coordinates":[89.38224,25.62531],"type":"Point"}
}