{
  "type": "Feature",
  "properties": {
    "gn:admin1_code":"84",
    "gn:admin2_code":"2019.0",
    "gn:admin3_code":"201968.0",
    "gn:admin4_code":"20196880.0",
    "gn:asciiname":"East Alokdia",
    "gn:cc2":"BD",
    "gn:country_code":"BD",
    "gn:dem":8,
    "gn:feature_class":"P",
    "gn:feature_code":"PPL",
    "gn:name":"East Alokdia",
    "gn:population":0,
    "gn:timezone":"Asia/Dhaka",
    "iso:country":"BD",
    "name:und_x_variant":[
        "Alokdia",
        "East Alokdia"
    ],
    "wof:name":"East Alokdia",
    "wof:placetype":"locality"
},
  "geometry": {"coordinates":[91.15000000000001,23.25],"type":"Point"}
}