{
  "type": "Feature",
  "properties": {
    "gn:admin1_code":"83",
    "gn:admin2_code":"5064.0",
    "gn:admin3_code":"506475.0",
    "gn:admin4_code":"50647543.0",
    "gn:asciiname":"Barail",
    "gn:country_code":"BD",
    "gn:dem":27,
    "gn:feature_class":"P",
    "gn:feature_code":"PPL",
    "gn:name":"B\u0101r\u0101il",
    "gn:population":0,
    "gn:timezone":"Asia/Dhaka",
    "iso:country":"BD",
    "name:ben_x_preferred":[
        "B\u0101r\u0101il"
    ],
    "wof:name":"Barail",
    "wof:placetype":"locality"
},
  "geometry": {"coordinates":[88.73875,25.11369],"type":"Point"}
}