{
  "type": "Feature",
  "properties": {
    "gn:admin1_code":"H",
    "gn:admin2_code":"3039",
    "gn:admin3_code":"303907.0",
    "gn:admin4_code":"30390771.0",
    "gn:asciiname":"Dakshin",
    "gn:country_code":"BD",
    "gn:dem":25,
    "gn:feature_class":"P",
    "gn:feature_code":"PPL",
    "gn:name":"Dakshin",
    "gn:population":0,
    "gn:timezone":"Asia/Dhaka",
    "iso:country":"BD",
    "name:ben_x_preferred":[
        "Dakshin"
    ],
    "wof:name":"Dakshin",
    "wof:placetype":"locality"
},
  "geometry": {"coordinates":[89.89577,25.11085],"type":"Point"}
}