{
  "type": "Feature",
  "properties": {
    "gn:admin1_code":"82",
    "gn:admin2_code":"4047.0",
    "gn:admin3_code":"404730.0",
    "gn:admin4_code":"40473013.0",
    "gn:asciiname":"Ghona",
    "gn:country_code":"BD",
    "gn:dem":7,
    "gn:feature_class":"P",
    "gn:feature_code":"PPL",
    "gn:name":"Ghona",
    "gn:population":0,
    "gn:timezone":"Asia/Dhaka",
    "iso:country":"BD",
    "wof:name":"Ghona",
    "wof:placetype":"locality"
},
  "geometry": {"coordinates":[89.44216,22.76595],"type":"Point"}
}