{
  "type": "Feature",
  "properties": {
    "gn:admin1_code":"83",
    "gn:admin2_code":"5088.0",
    "gn:admin3_code":"508867.0",
    "gn:admin4_code":"50886743.0",
    "gn:asciiname":"Bri Bangaon",
    "gn:country_code":"BD",
    "gn:dem":15,
    "gn:feature_class":"P",
    "gn:feature_code":"PPL",
    "gn:name":"Bri Bangaon",
    "gn:population":0,
    "gn:timezone":"Asia/Dhaka",
    "iso:country":"BD",
    "name:und_x_variant":[
        "Bari Bangaon",
        "Bri Bangaon"
    ],
    "wof:name":"Bri Bangaon",
    "wof:placetype":"locality"
},
  "geometry": {"coordinates":[89.54815000000001,24.202],"type":"Point"}
}