{
  "type": "Feature",
  "properties": {
    "gn:admin1_code":"81",
    "gn:admin2_code":"3093.0",
    "gn:admin3_code":"309328.0",
    "gn:admin4_code":"30932851.0",
    "gn:asciiname":"Dhaluabari",
    "gn:country_code":"BD",
    "gn:dem":18,
    "gn:feature_class":"P",
    "gn:feature_code":"PPL",
    "gn:name":"Dhalu\u0101b\u0101ri",
    "gn:population":0,
    "gn:timezone":"Asia/Dhaka",
    "iso:country":"BD",
    "wof:name":"Dhaluabari",
    "wof:placetype":"locality"
},
  "geometry": {"coordinates":[90.02471,24.4012],"type":"Point"}
}