{
  "type": "Feature",
  "properties": {
    "gn:admin1_code":"84",
    "gn:admin2_code":"2013",
    "gn:admin3_code":"201345.0",
    "gn:admin4_code":"20134511.0",
    "gn:asciiname":"Krishnapur",
    "gn:country_code":"BD",
    "gn:dem":17,
    "gn:feature_class":"P",
    "gn:feature_code":"PPL",
    "gn:name":"Krishnapur",
    "gn:population":0,
    "gn:timezone":"Asia/Dhaka",
    "iso:country":"BD",
    "wof:name":"Krishnapur",
    "wof:placetype":"locality"
},
  "geometry": {"coordinates":[90.74653000000001,23.20668],"type":"Point"}
}