{
  "type": "Feature",
  "properties": {
    "gn:admin1_code":"83",
    "gn:admin2_code":"5070.0",
    "gn:admin3_code":"507066.0",
    "gn:admin4_code":"50706633.0",
    "gn:asciiname":"Arunbari",
    "gn:country_code":"BD",
    "gn:dem":29,
    "gn:feature_class":"P",
    "gn:feature_code":"PPL",
    "gn:name":"Arunb\u0101ri",
    "gn:population":0,
    "gn:timezone":"Asia/Dhaka",
    "iso:country":"BD",
    "name:ben_x_preferred":[
        "Arunb\u0101ri"
    ],
    "wof:name":"Arunbari",
    "wof:placetype":"locality"
},
  "geometry": {"coordinates":[88.26266,24.68534],"type":"Point"}
}