{
  "type": "Feature",
  "properties": {
    "gn:admin1_code":"81",
    "gn:admin2_code":"3093",
    "gn:admin3_code":"309309.0",
    "gn:admin4_code":"30930935.0",
    "gn:asciiname":"Karatiapara",
    "gn:country_code":"BD",
    "gn:dem":11,
    "gn:feature_class":"P",
    "gn:feature_code":"PPL",
    "gn:name":"Karati\u0101p\u0101ra",
    "gn:population":0,
    "gn:timezone":"Asia/Dhaka",
    "iso:country":"BD",
    "wof:name":"Karatiapara",
    "wof:placetype":"locality"
},
  "geometry": {"coordinates":[90.02244,24.25892],"type":"Point"}
}