{
  "type": "Feature",
  "properties": {
    "gn:admin1_code":"H",
    "gn:admin2_code":"3061.0",
    "gn:admin3_code":"306122.0",
    "gn:admin4_code":"30612250.0",
    "gn:asciiname":"Bil Makhal",
    "gn:country_code":"BD",
    "gn:dem":8,
    "gn:feature_class":"P",
    "gn:feature_code":"PPL",
    "gn:name":"Bil M\u0101khal",
    "gn:population":0,
    "gn:timezone":"Asia/Dhaka",
    "iso:country":"BD",
    "name:und_x_variant":[
        "Bill M\u0101kh\u0101l",
        "Bil M\u0101khal"
    ],
    "wof:name":"Bil Makhal",
    "wof:placetype":"locality"
},
  "geometry": {"coordinates":[90.55414,24.30805],"type":"Point"}
}