{
  "type": "Feature",
  "properties": {
    "gn:admin1_code":"85",
    "gn:admin2_code":"1042.0",
    "gn:admin3_code":"104243.0",
    "gn:admin4_code":"10424394.0",
    "gn:asciiname":"Madhabpura",
    "gn:country_code":"BD",
    "gn:dem":4,
    "gn:feature_class":"P",
    "gn:feature_code":"PPL",
    "gn:name":"M\u0101dhabpura",
    "gn:population":0,
    "gn:timezone":"Asia/Dhaka",
    "iso:country":"BD",
    "name:ben_x_preferred":[
        "M\u0101dhabpura"
    ],
    "wof:name":"Madhabpura",
    "wof:placetype":"locality"
},
  "geometry": {"coordinates":[90.13343999999999,22.47449],"type":"Point"}
}