{
  "type": "Feature",
  "properties": {
    "gn:admin1_code":"84",
    "gn:admin2_code":"2015.0",
    "gn:admin3_code":"201537.0",
    "gn:admin4_code":"20153771.0",
    "gn:asciiname":"Chankhola Bil",
    "gn:country_code":"BD",
    "gn:dem":25,
    "gn:feature_class":"P",
    "gn:feature_code":"PPL",
    "gn:name":"Chankhola Bil",
    "gn:population":0,
    "gn:timezone":"Asia/Dhaka",
    "iso:country":"BD",
    "name:ben_x_preferred":[
        "Chankhola Bil"
    ],
    "wof:name":"Chankhola Bil",
    "wof:placetype":"locality"
},
  "geometry": {"coordinates":[91.77822999999999,22.54699],"type":"Point"}
}