{
  "type": "Feature",
  "properties": {
    "gn:admin1_code":"83",
    "gn:admin2_code":"5064.0",
    "gn:admin3_code":"506486.0",
    "gn:admin4_code":"50648694.0",
    "gn:asciiname":"Babupur",
    "gn:country_code":"BD",
    "gn:dem":27,
    "gn:feature_class":"P",
    "gn:feature_code":"PPL",
    "gn:name":"Babupur",
    "gn:population":0,
    "gn:timezone":"Asia/Dhaka",
    "iso:country":"BD",
    "name:ben_x_preferred":[
        "Babupur"
    ],
    "wof:name":"Babupur",
    "wof:placetype":"locality"
},
  "geometry": {"coordinates":[88.59350000000001,25.06144],"type":"Point"}
}