{
  "type": "Feature",
  "properties": {
    "gn:admin1_code":"82",
    "gn:admin2_code":"4041.0",
    "gn:admin3_code":"404147.0",
    "gn:admin4_code":"40414783.0",
    "gn:asciiname":"Jhat",
    "gn:country_code":"BD",
    "gn:dem":16,
    "gn:feature_class":"P",
    "gn:feature_code":"PPL",
    "gn:name":"Jh\u0101t",
    "gn:population":0,
    "gn:timezone":"Asia/Dhaka",
    "iso:country":"BD",
    "name:ben_x_preferred":[
        "Jh\u0101t"
    ],
    "wof:name":"Jhat",
    "wof:placetype":"locality"
},
  "geometry": {"coordinates":[89.29006,23.12175],"type":"Point"}
}