{
  "type": "Feature",
  "properties": {
    "gn:admin1_code":"86",
    "gn:admin2_code":"6091",
    "gn:admin3_code":"609159.0",
    "gn:admin4_code":"60915947.0",
    "gn:asciiname":"Nandirai",
    "gn:country_code":"BD",
    "gn:dem":22,
    "gn:feature_class":"P",
    "gn:feature_code":"PPL",
    "gn:name":"Nandir\u0101i",
    "gn:population":0,
    "gn:timezone":"Asia/Dhaka",
    "iso:country":"BD",
    "wof:name":"Nandirai",
    "wof:placetype":"locality"
},
  "geometry": {"coordinates":[92.23333,24.98333],"type":"Point"}
}