{
  "type": "Feature",
  "properties": {
    "gn:admin1_code":"87",
    "gn:admin2_code":"5573.0",
    "gn:admin3_code":"557385.0",
    "gn:admin4_code":"55738567.0",
    "gn:asciiname":"Chhail",
    "gn:country_code":"BD",
    "gn:dem":46,
    "gn:feature_class":"P",
    "gn:feature_code":"PPL",
    "gn:name":"Chhail",
    "gn:population":0,
    "gn:timezone":"Asia/Dhaka",
    "iso:country":"BD",
    "name:ben_x_preferred":[
        "Chhail"
    ],
    "wof:name":"Chhail",
    "wof:placetype":"locality"
},
  "geometry": {"coordinates":[88.93930999999998,25.83694],"type":"Point"}
}