{
  "type": "Feature",
  "properties": {
    "gn:admin1_code":"81",
    "gn:admin2_code":"3029.0",
    "gn:admin3_code":"302947.0",
    "gn:admin4_code":"30294755.0",
    "gn:asciiname":"Akain",
    "gn:country_code":"BD",
    "gn:dem":11,
    "gn:feature_class":"P",
    "gn:feature_code":"PPL",
    "gn:name":"\u0100kain",
    "gn:population":0,
    "gn:timezone":"Asia/Dhaka",
    "iso:country":"BD",
    "wof:name":"Akain",
    "wof:placetype":"locality"
},
  "geometry": {"coordinates":[89.83295,23.53479],"type":"Point"}
}