{
  "type": "Feature",
  "properties": {
    "gn:admin1_code":"87",
    "gn:admin2_code":"5573.0",
    "gn:admin3_code":"557336.0",
    "gn:admin4_code":"55733607.0",
    "gn:asciiname":"Kharija Golna",
    "gn:country_code":"BD",
    "gn:dem":54,
    "gn:feature_class":"P",
    "gn:feature_code":"PPL",
    "gn:name":"Kharija Golna",
    "gn:population":0,
    "gn:timezone":"Asia/Dhaka",
    "iso:country":"BD",
    "name:ben_x_preferred":[
        "Kharija Golna"
    ],
    "wof:name":"Kharija Golna",
    "wof:placetype":"locality"
},
  "geometry": {"coordinates":[88.97029999999999,26.06411],"type":"Point"}
}