{
  "type": "Feature",
  "properties": {
    "gn:admin1_code":"82",
    "gn:admin2_code":"4044.0",
    "gn:admin3_code":"404442.0",
    "gn:admin4_code":"40444240.0",
    "gn:asciiname":"Rangiarpota",
    "gn:country_code":"BD",
    "gn:dem":14,
    "gn:feature_class":"P",
    "gn:feature_code":"PPL",
    "gn:name":"R\u0101ngi\u0101rpota",
    "gn:population":0,
    "gn:timezone":"Asia/Dhaka",
    "iso:country":"BD",
    "name:ben_x_preferred":[
        "R\u0101ngi\u0101rpota"
    ],
    "wof:name":"Rangiarpota",
    "wof:placetype":"locality"
},
  "geometry": {"coordinates":[89.0488,23.41215],"type":"Point"}
}