{
  "type": "Feature",
  "properties": {
    "gn:admin1_code":"81",
    "gn:admin2_code":"3026",
    "gn:admin3_code":"302614.0",
    "gn:admin4_code":"30261459.0",
    "gn:asciiname":"Sripur",
    "gn:country_code":"BD",
    "gn:dem":15,
    "gn:feature_class":"P",
    "gn:feature_code":"PPL",
    "gn:name":"Sripur",
    "gn:population":0,
    "gn:timezone":"Asia/Dhaka",
    "iso:country":"BD",
    "name:bih_x_preferred":[
        "\u0936\u094d\u0930\u0940\u092a\u0941\u0930"
    ],
    "wof:name":"Sripur",
    "wof:placetype":"locality"
},
  "geometry": {"coordinates":[90.10894,23.96343],"type":"Point"}
}