{
  "type": "Feature",
  "properties": {
    "gn:admin1_code":"82",
    "gn:admin2_code":"4041.0",
    "gn:admin3_code":"404161.0",
    "gn:admin4_code":"40416116.0",
    "gn:asciiname":"Dhakuria",
    "gn:country_code":"BD",
    "gn:dem":9,
    "gn:feature_class":"P",
    "gn:feature_code":"PPL",
    "gn:name":"Dh\u0101kuria",
    "gn:population":0,
    "gn:timezone":"Asia/Dhaka",
    "iso:country":"BD",
    "name:ben_x_preferred":[
        "Dh\u0101kuria"
    ],
    "wof:name":"Dhakuria",
    "wof:placetype":"locality"
},
  "geometry": {"coordinates":[89.26975999999998,23.06856],"type":"Point"}
}