{
  "type": "Feature",
  "properties": {
    "gn:admin1_code":"82",
    "gn:admin2_code":"4041.0",
    "gn:admin3_code":"404161.0",
    "gn:admin4_code":"40416116.0",
    "gn:asciiname":"Dhakuria",
    "gn:country_code":"BD",
    "gn:dem":9,
    "gn:feature_class":"P",
    "gn:feature_code":"PPL",
    "gn:name":"Dh\u0101kuria",
    "gn:population":0,
    "gn:timezone":"Asia/Dhaka",
    "iso:country":"BD",
    "name:ben_x_preferred":[
        "Dh\u0101kuria"
    ],
    "name:ben_x_variant":[
        "\u09a2\u09be\u0995\u09c1\u09b0\u09bf\u09af\u09bc\u09be"
    ],
    "name:bpy_x_preferred":[
        "\u09a2\u09be\u0995\u09c1\u09b0\u09bf\u09af\u09bc\u09be"
    ],
    "name:hin_x_preferred":[
        "\u0922\u0915\u0941\u0930\u093f\u092f\u093e"
    ],
    "name:ita_x_preferred":[
        "Dhakuria"
    ],
    "name:msa_x_preferred":[
        "Dhakuria"
    ],
    "name:new_x_preferred":[
        "\u0922\u0915\u0941\u0930\u093f\u092f\u093e"
    ],
    "name:nld_x_preferred":[
        "Dhakuria"
    ],
    "name:vie_x_preferred":[
        "Dhakuria"
    ],
    "name:zho_x_preferred":[
        "\u8fbe\u5e93\u91cc\u4e9a"
    ],
    "wof:name":"Dhakuria",
    "wof:placetype":"locality"
},
  "geometry": {"coordinates":[89.26975999999998,23.06856],"type":"Point"}
}