{
  "type": "Feature",
  "properties": {
    "gn:admin1_code":"85",
    "gn:admin2_code":"1006",
    "gn:admin3_code":"100607.0",
    "gn:admin4_code":"10060794.0",
    "gn:asciiname":"Lochanabad",
    "gn:country_code":"BD",
    "gn:dem":10,
    "gn:feature_class":"P",
    "gn:feature_code":"PPL",
    "gn:name":"Lochan\u0101b\u0101d",
    "gn:population":0,
    "gn:timezone":"Asia/Dhaka",
    "iso:country":"BD",
    "wof:name":"Lochanabad",
    "wof:placetype":"locality"
},
  "geometry": {"coordinates":[90.30062,22.54019],"type":"Point"}
}