{
  "type": "Feature",
  "properties": {
    "gn:admin1_code":"81",
    "gn:admin2_code":"3067.0",
    "gn:admin3_code":"306704.0",
    "gn:admin4_code":"30670486.0",
    "gn:asciiname":"Bhaliarcharjya Chak",
    "gn:country_code":"BD",
    "gn:dem":5,
    "gn:feature_class":"P",
    "gn:feature_code":"PPL",
    "gn:name":"Bhaliarcharjya Chak",
    "gn:population":0,
    "gn:timezone":"Asia/Dhaka",
    "iso:country":"BD",
    "name:und_x_variant":[
        "Bhattacharyya Chak",
        "Bhatt\u0101ch\u0101rjya Chak",
        "Bhaliarcharjya Chak"
    ],
    "wof:name":"Bhaliarcharjya Chak",
    "wof:placetype":"locality"
},
  "geometry": {"coordinates":[90.55351,23.59808],"type":"Point"}
}