{
  "type": "Feature",
  "properties": {
    "gn:admin1_code":"81",
    "gn:admin2_code":"3093",
    "gn:admin3_code":"309347.0",
    "gn:admin4_code":"30934765.0",
    "gn:asciiname":"Naliachara",
    "gn:country_code":"BD",
    "gn:dem":24,
    "gn:feature_class":"P",
    "gn:feature_code":"PPL",
    "gn:name":"N\u0101liachara",
    "gn:population":0,
    "gn:timezone":"Asia/Dhaka",
    "iso:country":"BD",
    "name:und_x_variant":[
        "N\u0101liachara",
        "N\u0101lia Ch\u0101la"
    ],
    "wof:name":"Naliachara",
    "wof:placetype":"locality"
},
  "geometry": {"coordinates":[90.09298,24.3611],"type":"Point"}
}