{
  "type": "Feature",
  "properties": {
    "gn:admin1_code":"87",
    "gn:admin2_code":"5585.0",
    "gn:admin3_code":"558573.0",
    "gn:admin4_code":"55857319.0",
    "gn:asciiname":"Balatari",
    "gn:country_code":"BD",
    "gn:dem":31,
    "gn:feature_class":"P",
    "gn:feature_code":"PPL",
    "gn:name":"B\u0101l\u0101t\u0101ri",
    "gn:population":0,
    "gn:timezone":"Asia/Dhaka",
    "iso:country":"BD",
    "name:ben_x_preferred":[
        "B\u0101l\u0101t\u0101ri"
    ],
    "wof:name":"Balatari",
    "wof:placetype":"locality"
},
  "geometry": {"coordinates":[89.47354,25.69025],"type":"Point"}
}