{
  "type": "Feature",
  "properties": {
    "gn:admin1_code":"83",
    "gn:admin2_code":"5010",
    "gn:admin3_code":"501095.0",
    "gn:admin4_code":"50109573.0",
    "gn:asciiname":"Kamalerpara",
    "gn:country_code":"BD",
    "gn:dem":22,
    "gn:feature_class":"P",
    "gn:feature_code":"PPL",
    "gn:name":"Kamalerp\u0101ra",
    "gn:population":0,
    "gn:timezone":"Asia/Dhaka",
    "iso:country":"BD",
    "name:ben_x_preferred":[
        "Kamalerp\u0101ra"
    ],
    "wof:name":"Kamalerpara",
    "wof:placetype":"locality"
},
  "geometry": {"coordinates":[89.51625,25.02288],"type":"Point"}
}