{
  "type": "Feature",
  "properties": {
    "gn:admin1_code":"82",
    "gn:admin2_code":"4044.0",
    "gn:admin3_code":"404414.0",
    "gn:admin4_code":"40441473.0",
    "gn:asciiname":"Madia",
    "gn:country_code":"BD",
    "gn:dem":15,
    "gn:feature_class":"P",
    "gn:feature_code":"PPL",
    "gn:name":"M\u0101dia",
    "gn:population":0,
    "gn:timezone":"Asia/Dhaka",
    "iso:country":"BD",
    "name:ben_x_preferred":[
        "M\u0101dia"
    ],
    "name:ceb_x_preferred":[
        "Madia"
    ],
    "name:ita_x_preferred":[
        "Madia"
    ],
    "name:por_x_preferred":[
        "Madia"
    ],
    "name:rus_x_preferred":[
        "\u041c\u0430\u0434\u0438\u044f"
    ],
    "name:spa_x_preferred":[
        "Madia"
    ],
    "name:swe_x_preferred":[
        "Madia"
    ],
    "name:vie_x_preferred":[
        "Madia"
    ],
    "name:war_x_preferred":[
        "Madia"
    ],
    "wof:name":"Madia",
    "wof:placetype":"locality"
},
  "geometry": {"coordinates":[89.10925,23.66302],"type":"Point"}
}