{
  "type": "Feature",
  "properties": {
    "gn:admin1_code":"87",
    "gn:admin2_code":"5527",
    "gn:admin3_code":"552769.0",
    "gn:admin4_code":"55276986.0",
    "gn:asciiname":"Ahmadnagar",
    "gn:country_code":"BD",
    "gn:dem":32,
    "gn:feature_class":"P",
    "gn:feature_code":"PPL",
    "gn:name":"Ahmadnagar",
    "gn:population":0,
    "gn:timezone":"Asia/Dhaka",
    "iso:country":"BD",
    "name:ben_x_preferred":[
        "Ahmadnagar"
    ],
    "wof:name":"Ahmadnagar",
    "wof:placetype":"locality"
},
  "geometry": {"coordinates":[89.05609,25.33116],"type":"Point"}
}