{
  "type": "Feature",
  "properties": {
    "gn:admin1_code":"87",
    "gn:admin2_code":"5527.0",
    "gn:admin3_code":"552760.0",
    "gn:admin4_code":"55276063.0",
    "gn:asciiname":"Bandaria",
    "gn:country_code":"BD",
    "gn:dem":51,
    "gn:feature_class":"P",
    "gn:feature_code":"PPL",
    "gn:name":"Bandaria",
    "gn:population":0,
    "gn:timezone":"Asia/Dhaka",
    "iso:country":"BD",
    "name:ben_x_preferred":[
        "Bandaria"
    ],
    "wof:name":"Bandaria",
    "wof:placetype":"locality"
},
  "geometry": {"coordinates":[88.76708000000001,25.87727000000001],"type":"Point"}
}