{
  "type": "Feature",
  "properties": {
    "gn:admin1_code":"81",
    "gn:admin2_code":"3082",
    "gn:admin3_code":"308273.0",
    "gn:admin4_code":"30827340.0",
    "gn:asciiname":"Kuthi Maliat",
    "gn:country_code":"BD",
    "gn:dem":15,
    "gn:feature_class":"P",
    "gn:feature_code":"PPL",
    "gn:name":"Kuthi M\u0101li\u0101t",
    "gn:population":0,
    "gn:timezone":"Asia/Dhaka",
    "iso:country":"BD",
    "wof:name":"Kuthi Maliat",
    "wof:placetype":"locality"
},
  "geometry": {"coordinates":[89.33308000000002,23.74571],"type":"Point"}
}