{
  "type": "Feature",
  "properties": {
    "gn:admin1_code":"87",
    "gn:admin2_code":"5552",
    "gn:admin3_code":"555233.0",
    "gn:admin4_code":"55523309.0",
    "gn:asciiname":"Bura Saradabi",
    "gn:country_code":"BD",
    "gn:dem":54,
    "gn:feature_class":"P",
    "gn:feature_code":"PPL",
    "gn:name":"Bura Sarad\u0101bi",
    "gn:population":0,
    "gn:timezone":"Asia/Dhaka",
    "iso:country":"BD",
    "name:ben_x_preferred":[
        "Bura Sarad\u0101bi"
    ],
    "wof:name":"Bura Saradabi",
    "wof:placetype":"locality"
},
  "geometry": {"coordinates":[89.11904,26.23942000000001],"type":"Point"}
}