{
  "type": "Feature",
  "properties": {
    "gn:admin1_code":"87",
    "gn:admin2_code":"5527.0",
    "gn:admin3_code":"552743.0",
    "gn:admin4_code":"55274338.0",
    "gn:asciiname":"Chhaysat",
    "gn:country_code":"BD",
    "gn:dem":28,
    "gn:feature_class":"P",
    "gn:feature_code":"PPL",
    "gn:name":"Chhaysat",
    "gn:population":0,
    "gn:timezone":"Asia/Dhaka",
    "iso:country":"BD",
    "name:ben_x_preferred":[
        "Chhaysat"
    ],
    "wof:name":"Chhaysat",
    "wof:placetype":"locality"
},
  "geometry": {"coordinates":[89.226,25.2446],"type":"Point"}
}