{
  "type": "Feature",
  "properties": {
    "gn:admin1_code":"81",
    "gn:admin2_code":"3059",
    "gn:admin3_code":"305974.0",
    "gn:admin4_code":"30597474.0",
    "gn:asciiname":"Nagar",
    "gn:country_code":"BD",
    "gn:dem":9,
    "gn:feature_class":"P",
    "gn:feature_code":"PPL",
    "gn:name":"Nagar",
    "gn:population":0,
    "gn:timezone":"Asia/Dhaka",
    "iso:country":"BD",
    "name:ben_x_preferred":[
        "\u09a8\u0997\u09b0"
    ],
    "name:bpy_x_preferred":[
        "\u09a8\u0997\u09b0"
    ],
    "name:cat_x_preferred":[
        "Nagar"
    ],
    "name:ceb_x_preferred":[
        "Nagar"
    ],
    "name:deu_x_preferred":[
        "Nagar"
    ],
    "name:heb_x_preferred":[
        "\u05e0\u05d2\u05e8"
    ],
    "name:new_x_preferred":[
        "\u0928\u0917\u0930"
    ],
    "name:nld_x_preferred":[
        "Nagar"
    ],
    "name:swe_x_preferred":[
        "Nagar"
    ],
    "wof:name":"Nagar",
    "wof:placetype":"locality"
},
  "geometry": {"coordinates":[90.43232,23.55691],"type":"Point"}
}