{
  "type": "Feature",
  "properties": {
    "gn:admin1_code":"87",
    "gn:admin2_code":"5527",
    "gn:admin3_code":"552743.0",
    "gn:admin4_code":"55274357.0",
    "gn:asciiname":"Shalgaon",
    "gn:country_code":"BD",
    "gn:dem":27,
    "gn:feature_class":"P",
    "gn:feature_code":"PPL",
    "gn:name":"Shalgaon",
    "gn:population":0,
    "gn:timezone":"Asia/Dhaka",
    "iso:country":"BD",
    "name:ben_x_preferred":[
        "Shalgaon"
    ],
    "wof:name":"Shalgaon",
    "wof:placetype":"locality"
},
  "geometry": {"coordinates":[89.14362,25.27198],"type":"Point"}
}