{
  "type": "Feature",
  "properties": {
    "gn:admin1_code":"83",
    "gn:admin2_code":"5081",
    "gn:admin3_code":"508134.0",
    "gn:admin4_code":"50813438.0",
    "gn:asciiname":"Godagari",
    "gn:country_code":"BD",
    "gn:dem":26,
    "gn:feature_class":"P",
    "gn:feature_code":"PPL",
    "gn:name":"God\u0101g\u0101ri",
    "gn:population":0,
    "gn:timezone":"Asia/Dhaka",
    "iso:country":"BD",
    "name:ben_x_preferred":[
        "God\u0101g\u0101ri"
    ],
    "name:und_x_variant":[
        "Srimantapur",
        "Godaganj"
    ],
    "wof:name":"Godagari",
    "wof:placetype":"locality"
},
  "geometry": {"coordinates":[88.32356999999998,24.46831],"type":"Point"}
}