{
  "type": "Feature",
  "properties": {
    "gn:admin1_code":"83",
    "gn:admin2_code":"5081.0",
    "gn:admin3_code":"508194.0",
    "gn:admin4_code":"50819440.0",
    "gn:asciiname":"Biharail",
    "gn:country_code":"BD",
    "gn:dem":23,
    "gn:feature_class":"P",
    "gn:feature_code":"PPL",
    "gn:name":"Bihar\u0101il",
    "gn:population":0,
    "gn:timezone":"Asia/Dhaka",
    "iso:country":"BD",
    "name:ben_x_preferred":[
        "Bihar\u0101il"
    ],
    "wof:name":"Biharail",
    "wof:placetype":"locality"
},
  "geometry": {"coordinates":[88.61032,24.68551],"type":"Point"}
}