{
  "type": "Feature",
  "properties": {
    "gn:admin1_code":"87",
    "gn:admin2_code":"5594.0",
    "gn:admin3_code":"559494.0",
    "gn:admin4_code":"55949442.0",
    "gn:asciiname":"Gareya",
    "gn:country_code":"BD",
    "gn:dem":56,
    "gn:feature_class":"P",
    "gn:feature_code":"PPL",
    "gn:name":"Gareya",
    "gn:population":0,
    "gn:timezone":"Asia/Dhaka",
    "iso:country":"BD",
    "name:ben_x_preferred":[
        "Gareya"
    ],
    "name:und_x_variant":[
        "Gareyagopalpur"
    ],
    "wof:name":"Gareya",
    "wof:placetype":"locality"
},
  "geometry": {"coordinates":[88.60596,26.04885],"type":"Point"}
}