{
  "type": "Feature",
  "properties": {
    "gn:admin1_code":"81",
    "gn:admin2_code":"3086.0",
    "gn:admin3_code":"308614.0",
    "gn:admin4_code":"30861425.0",
    "gn:asciiname":"Bara Chhaygaon",
    "gn:country_code":"BD",
    "gn:dem":10,
    "gn:feature_class":"P",
    "gn:feature_code":"PPL",
    "gn:name":"Bara Chhaygaon",
    "gn:population":0,
    "gn:timezone":"Asia/Dhaka",
    "iso:country":"BD",
    "name:und_x_variant":[
        "Bara Chhoygaon",
        "Bara Chhaygaon"
    ],
    "wof:name":"Bara Chhaygaon",
    "wof:placetype":"locality"
},
  "geometry": {"coordinates":[90.39536,23.19852],"type":"Point"}
}