{
  "type": "Feature",
  "properties": {
    "gn:admin1_code":"H",
    "gn:admin2_code":"3089",
    "gn:admin3_code":"308937.0",
    "gn:admin4_code":"30893717.0",
    "gn:asciiname":"Dahariapara",
    "gn:country_code":"BD",
    "gn:dem":20,
    "gn:feature_class":"P",
    "gn:feature_code":"PPL",
    "gn:name":"Dahariap\u0101ra",
    "gn:population":0,
    "gn:timezone":"Asia/Dhaka",
    "iso:country":"BD",
    "name:ben_x_preferred":[
        "Dahariap\u0101ra"
    ],
    "wof:name":"Dahariapara",
    "wof:placetype":"locality"
},
  "geometry": {"coordinates":[90.0784,25.0879],"type":"Point"}
}