{
  "type": "Feature",
  "properties": {
    "gn:admin1_code":"87",
    "gn:admin2_code":"5585",
    "gn:admin3_code":"558542.0",
    "gn:admin4_code":"55854227.0",
    "gn:asciiname":"Kaunia",
    "gn:country_code":"BD",
    "gn:dem":34,
    "gn:feature_class":"P",
    "gn:feature_code":"PPL",
    "gn:name":"Kaunia",
    "gn:population":0,
    "gn:timezone":"Asia/Dhaka",
    "iso:country":"BD",
    "name:ben_x_preferred":[
        "Kaunia"
    ],
    "name:ceb_x_preferred":[
        "Kaunia"
    ],
    "name:por_x_preferred":[
        "Kaunia"
    ],
    "name:spa_x_preferred":[
        "Kaunia"
    ],
    "name:swe_x_preferred":[
        "Kaunia"
    ],
    "name:vie_x_preferred":[
        "Kaunia"
    ],
    "name:war_x_preferred":[
        "Kaunia"
    ],
    "wof:name":"Kaunia",
    "wof:placetype":"locality"
},
  "geometry": {"coordinates":[89.42038000000002,25.77423],"type":"Point"}
}