{
  "type": "Feature",
  "properties": {
    "gn:admin1_code":"83",
    "gn:admin2_code":"5076.0",
    "gn:admin3_code":"507655.0",
    "gn:admin4_code":"50765543.0",
    "gn:asciiname":"Ramkrishnapur",
    "gn:country_code":"BD",
    "gn:dem":18,
    "gn:feature_class":"P",
    "gn:feature_code":"PPL",
    "gn:name":"R\u0101mkrishnapur",
    "gn:population":0,
    "gn:timezone":"Asia/Dhaka",
    "iso:country":"BD",
    "name:ben_x_preferred":[
        "R\u0101mkrishnapur"
    ],
    "wof:name":"Ramkrishnapur",
    "wof:placetype":"locality"
},
  "geometry": {"coordinates":[89.23321,23.95658],"type":"Point"}
}