{
  "type": "Feature",
  "properties": {
    "gn:admin1_code":"87",
    "gn:admin2_code":"5585",
    "gn:admin3_code":"558558.0",
    "gn:admin4_code":"55855867.0",
    "gn:asciiname":"Batasan",
    "gn:country_code":"BD",
    "gn:dem":36,
    "gn:feature_class":"P",
    "gn:feature_code":"PPL",
    "gn:name":"B\u0101t\u0101san",
    "gn:population":0,
    "gn:timezone":"Asia/Dhaka",
    "iso:country":"BD",
    "name:ben_x_preferred":[
        "B\u0101t\u0101san"
    ],
    "wof:name":"Batasan",
    "wof:placetype":"locality"
},
  "geometry": {"coordinates":[89.26585,25.61515],"type":"Point"}
}