{
  "type": "Feature",
  "properties": {
    "gn:admin1_code":"81",
    "gn:admin2_code":"3033",
    "gn:admin3_code":"303330.0",
    "gn:admin4_code":"30333025.0",
    "gn:asciiname":"Jamuna",
    "gn:country_code":"BD",
    "gn:dem":13,
    "gn:feature_class":"P",
    "gn:feature_code":"PPL",
    "gn:name":"Jamuna",
    "gn:population":0,
    "gn:timezone":"Asia/Dhaka",
    "iso:country":"BD",
    "name:ben_x_preferred":[
        "\u09af\u09ae\u09c1\u09a8\u09be \u09a8\u09a6\u09c0"
    ],
    "name:bih_x_preferred":[
        "\u091c\u092e\u0941\u0928\u093e"
    ],
    "name:cat_x_preferred":[
        "Jamuna"
    ],
    "name:ceb_x_preferred":[
        "Jamuna"
    ],
    "name:new_x_preferred":[
        "\u091c\u092e\u0941\u0928\u093e"
    ],
    "name:nld_x_preferred":[
        "Jamuna"
    ],
    "name:pol_x_preferred":[
        "Jamuna"
    ],
    "name:swe_x_preferred":[
        "Jamuna"
    ],
    "wof:name":"Jamuna",
    "wof:placetype":"locality"
},
  "geometry": {"coordinates":[90.46118,24.00345],"type":"Point"}
}