{
  "type": "Feature",
  "properties": {
    "gn:admin1_code":"81",
    "gn:admin2_code":"3056",
    "gn:admin3_code":"305678.0",
    "gn:admin4_code":"30567811.0",
    "gn:asciiname":"Kushtia",
    "gn:country_code":"BD",
    "gn:dem":18,
    "gn:feature_class":"P",
    "gn:feature_code":"PPL",
    "gn:name":"Kushtia",
    "gn:population":0,
    "gn:timezone":"Asia/Dhaka",
    "iso:country":"BD",
    "wof:name":"Kushtia",
    "wof:placetype":"locality"
},
  "geometry": {"coordinates":[89.84061,23.76601],"type":"Point"}
}