{
  "type": "Feature",
  "properties": {
    "gn:admin1_code":"84",
    "gn:admin2_code":"2013",
    "gn:admin3_code":"201358.0",
    "gn:admin4_code":"20135815.0",
    "gn:asciiname":"Kundapur",
    "gn:country_code":"BD",
    "gn:dem":12,
    "gn:feature_class":"P",
    "gn:feature_code":"PPL",
    "gn:name":"Kundapur",
    "gn:population":0,
    "gn:timezone":"Asia/Dhaka",
    "iso:country":"BD",
    "name:ben_x_preferred":[
        "\u0995\u09c1\u09a8\u09cd\u09a6\u09aa\u09c1\u09b0"
    ],
    "name:bpy_x_preferred":[
        "\u0995\u09c1\u09a8\u09cd\u09a6\u09aa\u09c1\u09b0"
    ],
    "name:ind_x_preferred":[
        "Kundapur"
    ],
    "name:ita_x_preferred":[
        "Kundapura"
    ],
    "name:kan_x_preferred":[
        "\u0c95\u0cc1\u0c82\u0ca6\u0cbe\u0caa\u0cc1\u0cb0"
    ],
    "name:mal_x_preferred":[
        "\u0d15\u0d41\u0d28\u0d4d\u0d26\u0d3e\u0d2a\u0d41\u0d30"
    ],
    "name:mar_x_preferred":[
        "\u0915\u0941\u0902\u0926\u093e\u092a\u0942\u0930"
    ],
    "name:mlg_x_preferred":[
        "Kundapura"
    ],
    "name:msa_x_preferred":[
        "Kundapura"
    ],
    "name:new_x_preferred":[
        "\u0915\u0941\u0928\u094d\u0926\u092a\u0941\u0930\u093e"
    ],
    "name:nld_x_preferred":[
        "Kundapura"
    ],
    "name:spa_x_preferred":[
        "Kundapura"
    ],
    "name:swe_x_preferred":[
        "Kundapura"
    ],
    "name:tam_x_preferred":[
        "\u0b95\u0bc1\u0ba8\u0bcd\u0ba4\u0bbe\u0baa\u0bc1\u0bb0\u0bbe"
    ],
    "name:urd_x_preferred":[
        "\u06a9\u0646\u0688\u0627\u067e\u0648\u0631"
    ],
    "name:vie_x_preferred":[
        "Kundapur"
    ],
    "name:zho_x_preferred":[
        "\u6606\u8fbe\u666e\u62c9"
    ],
    "wof:name":"Kundapur",
    "wof:placetype":"locality"
},
  "geometry": {"coordinates":[90.79986,23.40475],"type":"Point"}
}