{
  "type": "Feature",
  "properties": {
    "gn:admin1_code":"85",
    "gn:admin2_code":"1079.0",
    "gn:admin3_code":"107914.0",
    "gn:admin4_code":"10791459.0",
    "gn:asciiname":"Bhagirathpur",
    "gn:country_code":"BD",
    "gn:dem":8,
    "gn:feature_class":"P",
    "gn:feature_code":"PPL",
    "gn:name":"Bh\u0101girathpur",
    "gn:population":0,
    "gn:timezone":"Asia/Dhaka",
    "iso:country":"BD",
    "name:ben_x_preferred":[
        "Bh\u0101girathpur"
    ],
    "name:ceb_x_preferred":[
        "Bhagirathpur"
    ],
    "name:swe_x_preferred":[
        "Bhagirathpur"
    ],
    "wof:name":"Bhagirathpur",
    "wof:placetype":"locality"
},
  "geometry": {"coordinates":[90.01978000000003,22.39361],"type":"Point"}
}