{
  "type": "Feature",
  "properties": {
    "gn:admin1_code":"87",
    "gn:admin2_code":"5585.0",
    "gn:admin3_code":"558573.0",
    "gn:admin4_code":"55857366.0",
    "gn:asciiname":"Sayadpur",
    "gn:country_code":"BD",
    "gn:dem":33,
    "gn:feature_class":"P",
    "gn:feature_code":"PPL",
    "gn:name":"Sayadp\u016br",
    "gn:population":0,
    "gn:timezone":"Asia/Dhaka",
    "iso:country":"BD",
    "name:ben_x_preferred":[
        "Sayadp\u016br"
    ],
    "wof:name":"Sayadpur",
    "wof:placetype":"locality"
},
  "geometry": {"coordinates":[89.35449,25.66528],"type":"Point"}
}