{
  "type": "Feature",
  "properties": {
    "gn:admin1_code":"84",
    "gn:admin2_code":"2015.0",
    "gn:admin3_code":"201582.0",
    "gn:admin4_code":"20158276.0",
    "gn:asciiname":"Fakirkil",
    "gn:country_code":"BD",
    "gn:dem":14,
    "gn:feature_class":"P",
    "gn:feature_code":"PPL",
    "gn:name":"Fakirkil",
    "gn:population":0,
    "gn:timezone":"Asia/Dhaka",
    "iso:country":"BD",
    "name:ben_x_preferred":[
        "Fakirkil"
    ],
    "wof:name":"Fakirkil",
    "wof:placetype":"locality"
},
  "geometry": {"coordinates":[92.13375000000001,22.1657],"type":"Point"}
}