{
  "type": "Feature",
  "properties": {
    "gn:admin1_code":"82",
    "gn:admin2_code":"4065.0",
    "gn:admin3_code":"406528.0",
    "gn:admin4_code":"40652823.0",
    "gn:asciiname":"Madhabpasa",
    "gn:country_code":"BD",
    "gn:dem":8,
    "gn:feature_class":"P",
    "gn:feature_code":"PPL",
    "gn:name":"M\u0101dhabpasa",
    "gn:population":0,
    "gn:timezone":"Asia/Dhaka",
    "iso:country":"BD",
    "name:ben_x_preferred":[
        "M\u0101dhabpasa"
    ],
    "wof:name":"Madhabpasa",
    "wof:placetype":"locality"
},
  "geometry": {"coordinates":[89.59989,23.01329],"type":"Point"}
}