{
  "type": "Feature",
  "properties": {
    "gn:admin1_code":"81",
    "gn:admin2_code":"3026.0",
    "gn:admin3_code":"302618.0",
    "gn:admin4_code":"30261831.0",
    "gn:asciiname":"Debinagar",
    "gn:country_code":"BD",
    "gn:dem":10,
    "gn:feature_class":"P",
    "gn:feature_code":"PPL",
    "gn:name":"Debinagar",
    "gn:population":0,
    "gn:timezone":"Asia/Dhaka",
    "iso:country":"BD",
    "wof:name":"Debinagar",
    "wof:placetype":"locality"
},
  "geometry": {"coordinates":[90.11667,23.58333],"type":"Point"}
}