{
  "type": "Feature",
  "properties": {
    "gn:admin1_code":"83",
    "gn:admin2_code":"5076.0",
    "gn:admin3_code":"507616.0",
    "gn:admin4_code":"50761642.0",
    "gn:asciiname":"Kalikapur",
    "gn:country_code":"BD",
    "gn:dem":16,
    "gn:feature_class":"P",
    "gn:feature_code":"PPL",
    "gn:name":"K\u0101lik\u0101pur",
    "gn:population":0,
    "gn:timezone":"Asia/Dhaka",
    "iso:country":"BD",
    "name:ben_x_preferred":[
        "K\u0101lik\u0101pur"
    ],
    "wof:name":"Kalikapur",
    "wof:placetype":"locality"
},
  "geometry": {"coordinates":[89.59398,23.94394],"type":"Point"}
}