{
  "type": "Feature",
  "properties": {
    "gn:admin1_code":"83",
    "gn:admin2_code":"5081.0",
    "gn:admin3_code":"508125.0",
    "gn:admin4_code":"50812571.0",
    "gn:asciiname":"Bhatpara Arazi",
    "gn:country_code":"BD",
    "gn:dem":19,
    "gn:feature_class":"P",
    "gn:feature_code":"PPL",
    "gn:name":"Bh\u0101tp\u0101ra \u0100r\u0101zi",
    "gn:population":0,
    "gn:timezone":"Asia/Dhaka",
    "iso:country":"BD",
    "wof:name":"Bhatpara Arazi",
    "wof:placetype":"locality"
},
  "geometry": {"coordinates":[88.83333,24.31667],"type":"Point"}
}