{
  "type": "Feature",
  "properties": {
    "gn:admin1_code":"83",
    "gn:admin2_code":"5088",
    "gn:admin3_code":"508861.0",
    "gn:admin4_code":"50886128.0",
    "gn:asciiname":"Uttar Faridpur",
    "gn:country_code":"BD",
    "gn:dem":18,
    "gn:feature_class":"P",
    "gn:feature_code":"PPL",
    "gn:name":"Uttar Far\u012bdpur",
    "gn:population":0,
    "gn:timezone":"Asia/Dhaka",
    "iso:country":"BD",
    "wof:name":"Uttar Faridpur",
    "wof:placetype":"locality"
},
  "geometry": {"coordinates":[89.44455000000001,24.51891],"type":"Point"}
}