{
  "type": "Feature",
  "properties": {
    "gn:admin1_code":"84",
    "gn:admin2_code":"2019",
    "gn:admin3_code":"201931.0",
    "gn:admin4_code":"20193195.0",
    "gn:asciiname":"Samuksar",
    "gn:country_code":"BD",
    "gn:dem":12,
    "gn:feature_class":"P",
    "gn:feature_code":"PPL",
    "gn:name":"S\u0101muks\u0101r",
    "gn:population":0,
    "gn:timezone":"Asia/Dhaka",
    "iso:country":"BD",
    "wof:name":"Samuksar",
    "wof:placetype":"locality"
},
  "geometry": {"coordinates":[91.25,23.35],"type":"Point"}
}