{
  "type": "Feature",
  "properties": {
    "gn:admin1_code":"81",
    "gn:admin2_code":"3029",
    "gn:admin3_code":"302918.0",
    "gn:admin4_code":"30291830.0",
    "gn:asciiname":"Krishnanagar",
    "gn:country_code":"BD",
    "gn:dem":15,
    "gn:feature_class":"P",
    "gn:feature_code":"PPL",
    "gn:name":"Krishnanagar",
    "gn:population":0,
    "gn:timezone":"Asia/Dhaka",
    "iso:country":"BD",
    "name:deu_x_preferred":[
        "Krishnanagar"
    ],
    "wof:name":"Krishnanagar",
    "wof:placetype":"locality"
},
  "geometry": {"coordinates":[89.7075,23.41817],"type":"Point"}
}