{
  "type": "Feature",
  "properties": {
    "gn:admin1_code":"83",
    "gn:admin2_code":"5064.0",
    "gn:admin3_code":"506447.0",
    "gn:admin4_code":"50644767.0",
    "gn:asciiname":"Dusati",
    "gn:country_code":"BD",
    "gn:dem":25,
    "gn:feature_class":"P",
    "gn:feature_code":"PPL",
    "gn:name":"Dusati",
    "gn:population":0,
    "gn:timezone":"Asia/Dhaka",
    "iso:country":"BD",
    "name:ben_x_preferred":[
        "Dusati"
    ],
    "wof:name":"Dusati",
    "wof:placetype":"locality"
},
  "geometry": {"coordinates":[88.69965000000001,24.79291],"type":"Point"}
}