{
  "type": "Feature",
  "properties": {
    "gn:admin1_code":"82",
    "gn:admin2_code":"4047.0",
    "gn:admin3_code":"404712.0",
    "gn:admin4_code":"40471271.0",
    "gn:asciiname":"Dakhin Raingamari",
    "gn:country_code":"BD",
    "gn:dem":4,
    "gn:feature_class":"P",
    "gn:feature_code":"PPL",
    "gn:name":"Dakhin R\u0101ing\u0101m\u0101ri",
    "gn:population":0,
    "gn:timezone":"Asia/Dhaka",
    "iso:country":"BD",
    "name:ben_x_preferred":[
        "Dakhin R\u0101ing\u0101m\u0101ri"
    ],
    "wof:name":"Dakhin Raingamari",
    "wof:placetype":"locality"
},
  "geometry": {"coordinates":[89.51719,22.76789],"type":"Point"}
}