{
  "type": "Feature",
  "properties": {
    "gn:admin1_code":"87",
    "gn:admin2_code":"5573.0",
    "gn:admin3_code":"557315.0",
    "gn:admin4_code":"55731509.0",
    "gn:asciiname":"Mistripara",
    "gn:country_code":"BD",
    "gn:dem":57,
    "gn:feature_class":"P",
    "gn:feature_code":"PPL",
    "gn:name":"Mistrip\u0101ra",
    "gn:population":0,
    "gn:timezone":"Asia/Dhaka",
    "iso:country":"BD",
    "name:ben_x_preferred":[
        "Mistrip\u0101ra"
    ],
    "wof:name":"Mistripara",
    "wof:placetype":"locality"
},
  "geometry": {"coordinates":[88.86396999999999,26.16599],"type":"Point"}
}