{
  "type": "Feature",
  "properties": {
    "gn:admin1_code":"82",
    "gn:asciiname":"East Chila",
    "gn:country_code":"BD",
    "gn:dem":8,
    "gn:feature_class":"P",
    "gn:feature_code":"PPL",
    "gn:name":"East Chila",
    "gn:population":0,
    "gn:timezone":"Asia/Dhaka",
    "iso:country":"BD",
    "name:ben_x_preferred":[
        "East Chila"
    ],
    "wof:name":"East Chila",
    "wof:placetype":"locality"
},
  "geometry": {"coordinates":[90.28489999999999,22.08232000000001],"type":"Point"}
}