{
  "type": "Feature",
  "properties": {
    "gn:admin1_code":"81",
    "gn:admin2_code":"3082",
    "gn:admin3_code":"308276.0",
    "gn:admin4_code":"30827651.0",
    "gn:asciiname":"Marjatkol",
    "gn:country_code":"BD",
    "gn:dem":15,
    "gn:feature_class":"P",
    "gn:feature_code":"PPL",
    "gn:name":"Marjatkol",
    "gn:population":0,
    "gn:timezone":"Asia/Dhaka",
    "iso:country":"BD",
    "name:und_x_variant":[
        "Marjotkjola",
        "Marjatkol"
    ],
    "wof:name":"Marjatkol",
    "wof:placetype":"locality"
},
  "geometry": {"coordinates":[89.59548000000002,23.74443],"type":"Point"}
}