{
  "type": "Feature",
  "properties": {
    "gn:admin1_code":"83",
    "gn:admin2_code":"5081.0",
    "gn:admin3_code":"508112.0",
    "gn:admin4_code":"50811294.0",
    "gn:asciiname":"Gongapara",
    "gn:country_code":"BD",
    "gn:dem":20,
    "gn:feature_class":"P",
    "gn:feature_code":"PPL",
    "gn:name":"Gong\u0101p\u0101ra",
    "gn:population":0,
    "gn:timezone":"Asia/Dhaka",
    "iso:country":"BD",
    "name:ben_x_preferred":[
        "Gong\u0101p\u0101ra"
    ],
    "wof:name":"Gongapara",
    "wof:placetype":"locality"
},
  "geometry": {"coordinates":[88.73893000000002,24.61497],"type":"Point"}
}