{
  "type": "Feature",
  "properties": {
    "gn:admin1_code":"84",
    "gn:admin2_code":"2084.0",
    "gn:admin3_code":"208429.0",
    "gn:admin4_code":"20842947.0",
    "gn:asciiname":"Bidyacharanbari",
    "gn:country_code":"BD",
    "gn:dem":173,
    "gn:feature_class":"P",
    "gn:feature_code":"PPL",
    "gn:name":"Bidy\u0101charanb\u0101ri",
    "gn:population":0,
    "gn:timezone":"Asia/Dhaka",
    "iso:country":"BD",
    "name:ben_x_preferred":[
        "Bidy\u0101charanb\u0101ri"
    ],
    "wof:name":"Bidyacharanbari",
    "wof:placetype":"locality"
},
  "geometry": {"coordinates":[92.50081,22.48266],"type":"Point"}
}