{
  "type": "Feature",
  "properties": {
    "gn:admin1_code":"85",
    "gn:admin2_code":"1078.0",
    "gn:admin3_code":"107897.0",
    "gn:admin4_code":"10789727.0",
    "gn:asciiname":"Phelabunia",
    "gn:country_code":"BD",
    "gn:dem":9,
    "gn:feature_class":"P",
    "gn:feature_code":"PPL",
    "gn:name":"Phelabunia",
    "gn:population":0,
    "gn:timezone":"Asia/Dhaka",
    "iso:country":"BD",
    "name:ben_x_preferred":[
        "Phelabunia"
    ],
    "wof:name":"Phelabunia",
    "wof:placetype":"locality"
},
  "geometry": {"coordinates":[90.36763000000001,21.98453],"type":"Point"}
}