{
  "type": "Feature",
  "properties": {
    "gn:admin1_code":"84",
    "gn:admin2_code":"2019",
    "gn:admin3_code":"201927.0",
    "gn:admin4_code":"20192779.0",
    "gn:asciiname":"West Rasulpur",
    "gn:country_code":"BD",
    "gn:dem":13,
    "gn:feature_class":"P",
    "gn:feature_code":"PPL",
    "gn:name":"West Ras\u016blpur",
    "gn:population":0,
    "gn:timezone":"Asia/Dhaka",
    "iso:country":"BD",
    "name:und_x_variant":[
        "Ras\u016blpur",
        "West Ras\u016blpur"
    ],
    "wof:name":"West Rasulpur",
    "wof:placetype":"locality"
},
  "geometry": {"coordinates":[90.94333,23.43382],"type":"Point"}
}