{
  "type": "Feature",
  "properties": {
    "gn:admin1_code":"83",
    "gn:admin2_code":"5038.0",
    "gn:admin3_code":"503813.0",
    "gn:admin4_code":"50381363.0",
    "gn:asciiname":"Chak Bizli",
    "gn:country_code":"BD",
    "gn:dem":23,
    "gn:feature_class":"P",
    "gn:feature_code":"PPL",
    "gn:name":"Chak Bizli",
    "gn:population":0,
    "gn:timezone":"Asia/Dhaka",
    "iso:country":"BD",
    "name:und_x_variant":[
        "Chak Bijli",
        "Chak Bizli"
    ],
    "wof:name":"Chak Bizli",
    "wof:placetype":"locality"
},
  "geometry": {"coordinates":[89.0239,24.94831],"type":"Point"}
}