{
  "type": "Feature",
  "properties": {
    "gn:admin1_code":"87",
    "gn:admin2_code":"5527",
    "gn:admin3_code":"552769.0",
    "gn:admin4_code":"55276951.0",
    "gn:asciiname":"Bhagal Pur Bazar",
    "gn:country_code":"BD",
    "gn:dem":35,
    "gn:feature_class":"P",
    "gn:feature_code":"PPL",
    "gn:name":"Bhagal Pur Bazar",
    "gn:population":0,
    "gn:timezone":"Asia/Dhaka",
    "iso:country":"BD",
    "name:ben_x_preferred":[
        "Bhagal Pur Bazar"
    ],
    "wof:name":"Bhagal Pur Bazar",
    "wof:placetype":"locality"
},
  "geometry": {"coordinates":[89.00803000000001,25.51735],"type":"Point"}
}