{
  "type": "Feature",
  "properties": {
    "gn:admin1_code":"81",
    "gn:admin2_code":"3048.0",
    "gn:admin3_code":"304876.0",
    "gn:admin4_code":"30487638.0",
    "gn:asciiname":"Biatir Char",
    "gn:country_code":"BD",
    "gn:dem":5,
    "gn:feature_class":"P",
    "gn:feature_code":"PPL",
    "gn:name":"Bi\u0101tir Char",
    "gn:population":0,
    "gn:timezone":"Asia/Dhaka",
    "iso:country":"BD",
    "wof:name":"Biatir Char",
    "wof:placetype":"locality"
},
  "geometry": {"coordinates":[90.95619000000001,24.27453],"type":"Point"}
}