{
  "type": "Feature",
  "properties": {
    "gn:admin1_code":"83",
    "gn:admin2_code":"5081.0",
    "gn:admin3_code":"508110.0",
    "gn:admin4_code":"50811015.0",
    "gn:asciiname":"Bag Sayasta",
    "gn:country_code":"BD",
    "gn:dem":26,
    "gn:feature_class":"P",
    "gn:feature_code":"PPL",
    "gn:name":"Bag S\u0101yasta",
    "gn:population":0,
    "gn:timezone":"Asia/Dhaka",
    "iso:country":"BD",
    "name:ben_x_preferred":[
        "Bag S\u0101yasta"
    ],
    "name:ben_x_variant":[
        "B\u0101g S\u0101yesta"
    ],
    "wof:name":"Bag Sayasta",
    "wof:placetype":"locality"
},
  "geometry": {"coordinates":[88.85823000000001,24.18352],"type":"Point"}
}