{
  "type": "Feature",
  "properties": {
    "gn:admin1_code":"85",
    "gn:admin2_code":"1006.0",
    "gn:admin3_code":"100632.0",
    "gn:admin4_code":"10063294.0",
    "gn:asciiname":"East Char Sarikal",
    "gn:country_code":"BD",
    "gn:dem":8,
    "gn:feature_class":"P",
    "gn:feature_code":"PPL",
    "gn:name":"East Char Sarikal",
    "gn:population":0,
    "gn:timezone":"Asia/Dhaka",
    "iso:country":"BD",
    "wof:name":"East Char Sarikal",
    "wof:placetype":"locality"
},
  "geometry": {"coordinates":[90.30972,22.92974],"type":"Point"}
}