{
  "type": "Feature",
  "properties": {
    "gn:admin1_code":"87",
    "gn:admin2_code":"5577.0",
    "gn:admin3_code":"557790.0",
    "gn:admin4_code":"55779067.0",
    "gn:asciiname":"Kumartuli",
    "gn:country_code":"BD",
    "gn:dem":91,
    "gn:feature_class":"P",
    "gn:feature_code":"PPL",
    "gn:name":"Kumartuli",
    "gn:population":0,
    "gn:timezone":"Asia/Dhaka",
    "iso:country":"BD",
    "name:ben_x_preferred":[
        "Kumartuli"
    ],
    "wof:name":"Kumartuli",
    "wof:placetype":"locality"
},
  "geometry": {"coordinates":[88.37651,26.48855],"type":"Point"}
}