{
  "type": "Feature",
  "properties": {
    "gn:admin1_code":"87",
    "gn:admin2_code":"5549",
    "gn:admin3_code":"554979.0",
    "gn:admin4_code":"55497911.0",
    "gn:asciiname":"Bagoar Char",
    "gn:country_code":"BD",
    "gn:dem":26,
    "gn:feature_class":"P",
    "gn:feature_code":"PPL",
    "gn:name":"Bagoar Char",
    "gn:population":0,
    "gn:timezone":"Asia/Dhaka",
    "iso:country":"BD",
    "name:ben_x_preferred":[
        "Bagoar Char"
    ],
    "wof:name":"Bagoar Char",
    "wof:placetype":"locality"
},
  "geometry": {"coordinates":[89.80619,25.59064],"type":"Point"}
}