{
  "type": "Feature",
  "properties": {
    "gn:admin1_code":"81",
    "gn:asciiname":"South Khurd Basa",
    "gn:country_code":"BD",
    "gn:dem":16,
    "gn:feature_class":"P",
    "gn:feature_code":"PPL",
    "gn:name":"South Khurd Basa",
    "gn:population":0,
    "gn:timezone":"Asia/Dhaka",
    "iso:country":"BD",
    "name:und_x_variant":[
        "Dakshin Khordabasa",
        "South Khurd Basa"
    ],
    "wof:name":"South Khurd Basa",
    "wof:placetype":"locality"
},
  "geometry": {"coordinates":[89.32191,23.76356],"type":"Point"}
}