{
  "type": "Feature",
  "properties": {
    "gn:admin1_code":"85",
    "gn:admin2_code":"1006.0",
    "gn:admin3_code":"100694.0",
    "gn:admin4_code":"10069484.0",
    "gn:asciiname":"East Dhamsar",
    "gn:country_code":"BD",
    "gn:dem":9,
    "gn:feature_class":"P",
    "gn:feature_code":"PPL",
    "gn:name":"East Dh\u0101ms\u0101r",
    "gn:population":0,
    "gn:timezone":"Asia/Dhaka",
    "iso:country":"BD",
    "wof:name":"East Dhamsar",
    "wof:placetype":"locality"
},
  "geometry": {"coordinates":[90.25225,22.84452000000001],"type":"Point"}
}