{
  "type": "Feature",
  "properties": {
    "gn:admin1_code":"83",
    "gn:asciiname":"Chalarpar",
    "gn:country_code":"BD",
    "gn:dem":25,
    "gn:feature_class":"P",
    "gn:feature_code":"PPL",
    "gn:name":"Chal\u0101rp\u0101r",
    "gn:population":0,
    "gn:timezone":"Asia/Dhaka",
    "iso:country":"BD",
    "name:ben_x_preferred":[
        "Chal\u0101rp\u0101r"
    ],
    "wof:name":"Chalarpar",
    "wof:placetype":"locality"
},
  "geometry": {"coordinates":[89.38207,25.17276],"type":"Point"}
}