{
  "type": "Feature",
  "properties": {
    "gn:admin1_code":"H",
    "gn:admin2_code":"3072.0",
    "gn:admin3_code":"307209.0",
    "gn:admin4_code":"30720911.0",
    "gn:asciiname":"Dattapara",
    "gn:country_code":"BD",
    "gn:dem":16,
    "gn:feature_class":"P",
    "gn:feature_code":"PPL",
    "gn:name":"Dattap\u0101ra",
    "gn:population":0,
    "gn:timezone":"Asia/Dhaka",
    "iso:country":"BD",
    "wof:name":"Dattapara",
    "wof:placetype":"locality"
},
  "geometry": {"coordinates":[90.88985,24.94179],"type":"Point"}
}