{
  "type": "Feature",
  "properties": {
    "gn:admin1_code":"82",
    "gn:asciiname":"Amragachhia",
    "gn:country_code":"BD",
    "gn:dem":13,
    "gn:feature_class":"P",
    "gn:feature_code":"PPL",
    "gn:name":"Amr\u0101g\u0101chhia",
    "gn:population":0,
    "gn:timezone":"Asia/Dhaka",
    "iso:country":"BD",
    "name:ben_x_preferred":[
        "Amr\u0101g\u0101chhia"
    ],
    "name:ben_x_variant":[
        "\u0100mr\u0101g\u0101chhia Hog\u0101lp\u0101ti"
    ],
    "name:fas_x_preferred":[
        "\u0627\u0645\u0631\u0627\u06af\u0627\u0686\u0647\u06cc\u0627 \u0647\u0648\u06af\u0627\u0644\u067e\u0627\u062a\u06cc"
    ],
    "wof:name":"Amragachhia",
    "wof:placetype":"locality"
},
  "geometry": {"coordinates":[89.91157,22.24015],"type":"Point"}
}