{
  "type": "Feature",
  "properties": {
    "gn:admin1_code":"H",
    "gn:admin2_code":"3089.0",
    "gn:admin3_code":"308988.0",
    "gn:admin4_code":"30898888.0",
    "gn:asciiname":"Charkhar Char",
    "gn:country_code":"BD",
    "gn:dem":22,
    "gn:feature_class":"P",
    "gn:feature_code":"PPL",
    "gn:name":"Charkh\u0101r Char",
    "gn:population":0,
    "gn:timezone":"Asia/Dhaka",
    "iso:country":"BD",
    "wof:name":"Charkhar Char",
    "wof:placetype":"locality"
},
  "geometry": {"coordinates":[90.08801,24.90895],"type":"Point"}
}