{
  "type": "Feature",
  "properties": {
    "gn:admin1_code":"83",
    "gn:admin2_code":"5081.0",
    "gn:admin3_code":"508134.0",
    "gn:admin4_code":"50813447.0",
    "gn:asciiname":"Hazipur",
    "gn:country_code":"BD",
    "gn:dem":36,
    "gn:feature_class":"P",
    "gn:feature_code":"PPL",
    "gn:name":"H\u0101zipur",
    "gn:population":0,
    "gn:timezone":"Asia/Dhaka",
    "iso:country":"BD",
    "name:ben_x_preferred":[
        "H\u0101zipur"
    ],
    "wof:name":"Hazipur",
    "wof:placetype":"locality"
},
  "geometry": {"coordinates":[88.43388,24.42008],"type":"Point"}
}