{
  "type": "Feature",
  "properties": {
    "gn:admin1_code":"87",
    "gn:admin2_code":"5527.0",
    "gn:admin3_code":"552730.0",
    "gn:admin4_code":"55273055.0",
    "gn:asciiname":"Binnakuri",
    "gn:country_code":"BD",
    "gn:dem":45,
    "gn:feature_class":"P",
    "gn:feature_code":"PPL",
    "gn:name":"Binnakuri",
    "gn:population":0,
    "gn:timezone":"Asia/Dhaka",
    "iso:country":"BD",
    "name:ben_x_preferred":[
        "Binnakuri"
    ],
    "wof:name":"Binnakuri",
    "wof:placetype":"locality"
},
  "geometry": {"coordinates":[88.81399999999999,25.70823],"type":"Point"}
}