{
  "type": "Feature",
  "properties": {
    "gn:admin1_code":"82",
    "gn:admin2_code":"4057.0",
    "gn:admin3_code":"405787.0",
    "gn:admin4_code":"40578757.0",
    "gn:asciiname":"Gadi",
    "gn:country_code":"BD",
    "gn:dem":21,
    "gn:feature_class":"P",
    "gn:feature_code":"PPL",
    "gn:name":"Gadi",
    "gn:population":0,
    "gn:timezone":"Asia/Dhaka",
    "iso:country":"BD",
    "name:ben_x_preferred":[
        "Gadi"
    ],
    "name:ceb_x_preferred":[
        "Gadi"
    ],
    "name:swe_x_preferred":[
        "Gadi"
    ],
    "wof:name":"Gadi",
    "wof:placetype":"locality"
},
  "geometry": {"coordinates":[88.65136,23.8213],"type":"Point"}
}