{
  "type": "Feature",
  "properties": {
    "gn:admin1_code":"87",
    "gn:admin2_code":"5549",
    "gn:admin3_code":"554961.0",
    "gn:admin4_code":"55496118.0",
    "gn:asciiname":"Berubari",
    "gn:country_code":"BD",
    "gn:dem":32,
    "gn:feature_class":"P",
    "gn:feature_code":"PPL",
    "gn:name":"Berub\u0101ri",
    "gn:population":0,
    "gn:timezone":"Asia/Dhaka",
    "iso:country":"BD",
    "name:ben_x_preferred":[
        "Berub\u0101ri"
    ],
    "wof:name":"Berubari",
    "wof:placetype":"locality"
},
  "geometry": {"coordinates":[89.72389,25.95791],"type":"Point"}
}