{
  "type": "Feature",
  "properties": {
    "gn:admin1_code":"81",
    "gn:admin2_code":"3067",
    "gn:admin3_code":"306702.0",
    "gn:admin4_code":"30670263.0",
    "gn:asciiname":"Jangalia",
    "gn:country_code":"BD",
    "gn:dem":8,
    "gn:feature_class":"P",
    "gn:feature_code":"PPL",
    "gn:name":"J\u0101ng\u0101lia",
    "gn:population":0,
    "gn:timezone":"Asia/Dhaka",
    "iso:country":"BD",
    "wof:name":"Jangalia",
    "wof:placetype":"locality"
},
  "geometry": {"coordinates":[90.67932,23.73791],"type":"Point"}
}