{
  "type": "Feature",
  "properties": {
    "gn:admin1_code":"82",
    "gn:admin2_code":"4055.0",
    "gn:admin3_code":"405595.0",
    "gn:admin4_code":"40559531.0",
    "gn:asciiname":"Chakdaha",
    "gn:country_code":"BD",
    "gn:dem":16,
    "gn:feature_class":"P",
    "gn:feature_code":"PPL",
    "gn:name":"Ch\u0101kdaha",
    "gn:population":0,
    "gn:timezone":"Asia/Dhaka",
    "iso:country":"BD",
    "name:ben_x_preferred":[
        "\u099a\u09be\u0995\u09a6\u09b9"
    ],
    "name:bpy_x_preferred":[
        "\u099a\u09be\u0995\u09a6\u09b9"
    ],
    "name:ita_x_preferred":[
        "Chakdaha"
    ],
    "name:msa_x_preferred":[
        "Chakdaha"
    ],
    "name:new_x_preferred":[
        "\u091a\u0915\u0926\u0939"
    ],
    "name:por_x_preferred":[
        "Chakdaha"
    ],
    "name:spa_x_preferred":[
        "Chakdaha"
    ],
    "name:swe_x_preferred":[
        "Chakdaha"
    ],
    "name:vie_x_preferred":[
        "Chakdaha"
    ],
    "name:zho_x_preferred":[
        "\u6070\u514b\u8fbe\u54c8"
    ],
    "wof:name":"Chakdaha",
    "wof:placetype":"locality"
},
  "geometry": {"coordinates":[89.38011999999998,23.64898],"type":"Point"}
}