{
  "type": "Feature",
  "properties": {
    "gn:admin1_code":"87",
    "gn:admin2_code":"5573.0",
    "gn:admin3_code":"557312.0",
    "gn:admin4_code":"55731276.0",
    "gn:asciiname":"Bhujaripara",
    "gn:country_code":"BD",
    "gn:dem":66,
    "gn:feature_class":"P",
    "gn:feature_code":"PPL",
    "gn:name":"Bhuj\u0101rip\u0101ra",
    "gn:population":0,
    "gn:timezone":"Asia/Dhaka",
    "iso:country":"BD",
    "name:ben_x_preferred":[
        "Bhuj\u0101rip\u0101ra"
    ],
    "wof:name":"Bhujaripara",
    "wof:placetype":"locality"
},
  "geometry": {"coordinates":[88.87478,26.27566],"type":"Point"}
}