{
  "type": "Feature",
  "properties": {
    "gn:admin1_code":"84",
    "gn:admin2_code":"2019",
    "gn:admin3_code":"201981.0",
    "gn:admin4_code":"20198190.0",
    "gn:asciiname":"Mastafapur",
    "gn:country_code":"BD",
    "gn:dem":9,
    "gn:feature_class":"P",
    "gn:feature_code":"PPL",
    "gn:name":"Mastaf\u0101pur",
    "gn:population":0,
    "gn:timezone":"Asia/Dhaka",
    "iso:country":"BD",
    "wof:name":"Mastafapur",
    "wof:placetype":"locality"
},
  "geometry": {"coordinates":[90.89528,23.69435],"type":"Point"}
}