{
  "type": "Feature",
  "properties": {
    "gn:admin1_code":"82",
    "gn:admin2_code":"4001",
    "gn:admin3_code":"400173.0",
    "gn:admin4_code":"40017377.0",
    "gn:asciiname":"Rajnagar",
    "gn:country_code":"BD",
    "gn:dem":8,
    "gn:feature_class":"P",
    "gn:feature_code":"PPL",
    "gn:name":"R\u0101jnagar",
    "gn:population":0,
    "gn:timezone":"Asia/Dhaka",
    "iso:country":"BD",
    "wof:name":"Rajnagar",
    "wof:placetype":"locality"
},
  "geometry": {"coordinates":[89.5765,22.61364],"type":"Point"}
}