{
  "type": "Feature",
  "properties": {
    "gn:admin1_code":"84",
    "gn:admin2_code":"2003.0",
    "gn:admin3_code":"200314.0",
    "gn:admin4_code":"20031463.0",
    "gn:asciiname":"Basantapara",
    "gn:country_code":"BD",
    "gn:dem":277,
    "gn:feature_class":"P",
    "gn:feature_code":"PPL",
    "gn:name":"Basantap\u0101ra",
    "gn:population":0,
    "gn:timezone":"Asia/Dhaka",
    "iso:country":"BD",
    "name:ben_x_preferred":[
        "Basantap\u0101ra"
    ],
    "wof:name":"Basantapara",
    "wof:placetype":"locality"
},
  "geometry": {"coordinates":[92.22229,22.11967000000001],"type":"Point"}
}