{
  "type": "Feature",
  "properties": {
    "gn:admin1_code":"85",
    "gn:admin2_code":"1009.0",
    "gn:admin3_code":"100954.0",
    "gn:admin4_code":"10095447.0",
    "gn:asciiname":"Char Sakhina",
    "gn:country_code":"BD",
    "gn:dem":9,
    "gn:feature_class":"P",
    "gn:feature_code":"PPL",
    "gn:name":"Char Sakhina",
    "gn:population":0,
    "gn:timezone":"Asia/Dhaka",
    "iso:country":"BD",
    "name:ben_x_preferred":[
        "Char Sakhina"
    ],
    "wof:name":"Char Sakhina",
    "wof:placetype":"locality"
},
  "geometry": {"coordinates":[90.72011999999999,22.35059],"type":"Point"}
}