{
  "type": "Feature",
  "properties": {
    "gn:admin1_code":"82",
    "gn:admin2_code":"4087",
    "gn:admin3_code":"408704.0",
    "gn:admin4_code":"40870417.0",
    "gn:asciiname":"Kamalapur",
    "gn:country_code":"BD",
    "gn:dem":2,
    "gn:feature_class":"P",
    "gn:feature_code":"PPL",
    "gn:name":"Kamal\u0101pur",
    "gn:population":0,
    "gn:timezone":"Asia/Dhaka",
    "iso:country":"BD",
    "name:ben_x_preferred":[
        "Kamal\u0101pur"
    ],
    "wof:name":"Kamalapur",
    "wof:placetype":"locality"
},
  "geometry": {"coordinates":[89.15019000000002,22.48755],"type":"Point"}
}