{
  "type": "Feature",
  "properties": {
    "gn:admin1_code":"81",
    "gn:admin2_code":"3082.0",
    "gn:admin3_code":"308207.0",
    "gn:admin4_code":"30820785.0",
    "gn:asciiname":"Chashabila",
    "gn:country_code":"BD",
    "gn:dem":14,
    "gn:feature_class":"P",
    "gn:feature_code":"PPL",
    "gn:name":"Chash\u0101bila",
    "gn:population":0,
    "gn:timezone":"Asia/Dhaka",
    "iso:country":"BD",
    "name:und_x_variant":[
        "Chasabiha",
        "Chash\u0101bila"
    ],
    "wof:name":"Chashabila",
    "wof:placetype":"locality"
},
  "geometry": {"coordinates":[89.46814999999999,23.67238],"type":"Point"}
}