{
  "type": "Feature",
  "properties": {
    "gn:admin1_code":"81",
    "gn:admin2_code":"3082",
    "gn:admin3_code":"308207.0",
    "gn:admin4_code":"30820785.0",
    "gn:asciiname":"Solabaria",
    "gn:country_code":"BD",
    "gn:dem":12,
    "gn:feature_class":"P",
    "gn:feature_code":"PPL",
    "gn:name":"Sol\u0101b\u0101ria",
    "gn:population":0,
    "gn:timezone":"Asia/Dhaka",
    "iso:country":"BD",
    "name:und_x_variant":[
        "Solabari",
        "Sol\u0101b\u0101ria"
    ],
    "wof:name":"Solabaria",
    "wof:placetype":"locality"
},
  "geometry": {"coordinates":[89.49925999999998,23.6515],"type":"Point"}
}