{
  "type": "Feature",
  "properties": {
    "gn:admin1_code":"85",
    "gn:admin2_code":"1006.0",
    "gn:admin3_code":"100632.0",
    "gn:admin4_code":"10063255.0",
    "gn:asciiname":"Ahmedkati",
    "gn:country_code":"BD",
    "gn:dem":9,
    "gn:feature_class":"P",
    "gn:feature_code":"PPL",
    "gn:name":"Ahmedk\u0101ti",
    "gn:population":0,
    "gn:timezone":"Asia/Dhaka",
    "iso:country":"BD",
    "name:und_x_variant":[
        "Ahammedkati",
        "Ahmadkati",
        "\u0100h\u0101mmadk\u0101ti",
        "Ahmedk\u0101ti"
    ],
    "wof:name":"Ahmedkati",
    "wof:placetype":"locality"
},
  "geometry": {"coordinates":[90.17912,23.05269],"type":"Point"}
}