{
  "type": "Feature",
  "properties": {
    "gn:admin1_code":"83",
    "gn:admin2_code":"5038",
    "gn:admin3_code":"503847.0",
    "gn:admin4_code":"50384738.0",
    "gn:asciiname":"Sheikpara",
    "gn:country_code":"BD",
    "gn:dem":25,
    "gn:feature_class":"P",
    "gn:feature_code":"PPL",
    "gn:name":"Sheikp\u0101ra",
    "gn:population":0,
    "gn:timezone":"Asia/Dhaka",
    "iso:country":"BD",
    "name:ben_x_preferred":[
        "Sheikp\u0101ra"
    ],
    "name:ben_x_variant":[
        "Sekhpara"
    ],
    "wof:name":"Sheikpara",
    "wof:placetype":"locality"
},
  "geometry": {"coordinates":[88.96184000000002,25.16552],"type":"Point"}
}