{
  "type": "Feature",
  "properties": {
    "gn:admin1_code":"85",
    "gn:admin2_code":"1004.0",
    "gn:admin3_code":"100447.0",
    "gn:admin4_code":"10044747.0",
    "gn:asciiname":"Katakhali",
    "gn:country_code":"BD",
    "gn:dem":8,
    "gn:feature_class":"P",
    "gn:feature_code":"PPL",
    "gn:name":"K\u0101t\u0101kh\u0101li",
    "gn:population":0,
    "gn:timezone":"Asia/Dhaka",
    "iso:country":"BD",
    "name:ben_x_preferred":[
        "K\u0101t\u0101kh\u0101li"
    ],
    "wof:name":"Katakhali",
    "wof:placetype":"locality"
},
  "geometry": {"coordinates":[90.18555000000001,22.3965],"type":"Point"}
}