{
  "type": "Feature",
  "properties": {
    "gn:admin1_code":"87",
    "gn:admin2_code":"5585.0",
    "gn:admin3_code":"558549.0",
    "gn:admin4_code":"55854900.0",
    "gn:asciiname":"Dimla",
    "gn:country_code":"BD",
    "gn:dem":34,
    "gn:feature_class":"P",
    "gn:feature_code":"PPL",
    "gn:name":"Dimla",
    "gn:population":0,
    "gn:timezone":"Asia/Dhaka",
    "iso:country":"BD",
    "name:ben_x_preferred":[
        "Dimla"
    ],
    "wof:name":"Dimla",
    "wof:placetype":"locality"
},
  "geometry": {"coordinates":[89.28230000000001,25.71855],"type":"Point"}
}