{
  "type": "Feature",
  "properties": {
    "gn:admin1_code":"87",
    "gn:admin2_code":"5577.0",
    "gn:admin3_code":"557734.0",
    "gn:admin4_code":"55773428.0",
    "gn:asciiname":"Lohagara",
    "gn:country_code":"BD",
    "gn:dem":54,
    "gn:feature_class":"P",
    "gn:feature_code":"PPL",
    "gn:name":"Lohagara",
    "gn:population":0,
    "gn:timezone":"Asia/Dhaka",
    "iso:country":"BD",
    "name:ben_x_preferred":[
        "Lohagara"
    ],
    "wof:name":"Lohagara",
    "wof:placetype":"locality"
},
  "geometry": {"coordinates":[88.6808,26.0812],"type":"Point"}
}