{
  "type": "Feature",
  "properties": {
    "gn:admin1_code":"85",
    "gn:admin2_code":"1006",
    "gn:admin3_code":"100607.0",
    "gn:admin4_code":"10060727.0",
    "gn:asciiname":"Otampur",
    "gn:country_code":"BD",
    "gn:dem":6,
    "gn:feature_class":"P",
    "gn:feature_code":"PPL",
    "gn:name":"Otampur",
    "gn:population":0,
    "gn:timezone":"Asia/Dhaka",
    "iso:country":"BD",
    "wof:name":"Otampur",
    "wof:placetype":"locality"
},
  "geometry": {"coordinates":[90.44542,22.61626],"type":"Point"}
}