{
  "type": "Feature",
  "properties": {
    "gn:admin1_code":"84",
    "gn:admin2_code":"2003.0",
    "gn:admin3_code":"200314.0",
    "gn:admin4_code":"20031463.0",
    "gn:asciiname":"Headmanpara",
    "gn:country_code":"BD",
    "gn:dem":33,
    "gn:feature_class":"P",
    "gn:feature_code":"PPL",
    "gn:name":"Headmanp\u0101ra",
    "gn:population":0,
    "gn:timezone":"Asia/Dhaka",
    "iso:country":"BD",
    "name:ben_x_preferred":[
        "Headmanp\u0101ra"
    ],
    "wof:name":"Headmanpara",
    "wof:placetype":"locality"
},
  "geometry": {"coordinates":[92.19461,22.13485],"type":"Point"}
}