{
  "type": "Feature",
  "properties": {
    "gn:admin1_code":"83",
    "gn:admin2_code":"5010",
    "gn:admin3_code":"501054.0",
    "gn:admin4_code":"50105428.0",
    "gn:asciiname":"Parishes",
    "gn:country_code":"BD",
    "gn:dem":24,
    "gn:feature_class":"P",
    "gn:feature_code":"PPL",
    "gn:name":"Parishes",
    "gn:population":0,
    "gn:timezone":"Asia/Dhaka",
    "iso:country":"BD",
    "name:und_x_variant":[
        "Parisesh",
        "Parishes"
    ],
    "wof:name":"Parishes",
    "wof:placetype":"locality"
},
  "geometry": {"coordinates":[89.25962,24.76927],"type":"Point"}
}