{
  "type": "Feature",
  "properties": {
    "gn:admin1_code":"H",
    "gn:admin2_code":"3072.0",
    "gn:admin3_code":"307263.0",
    "gn:admin4_code":"30726310.0",
    "gn:asciiname":"Daulatpur",
    "gn:country_code":"BD",
    "gn:dem":12,
    "gn:feature_class":"P",
    "gn:feature_code":"PPL",
    "gn:name":"Daulatpur",
    "gn:population":0,
    "gn:timezone":"Asia/Dhaka",
    "iso:country":"BD",
    "name:und_x_variant":[
        "Daulatpur R\u0101mchandrapur",
        "Daulatpur"
    ],
    "wof:name":"Daulatpur",
    "wof:placetype":"locality"
},
  "geometry": {"coordinates":[90.92913,24.86364],"type":"Point"}
}