{
  "type": "Feature",
  "properties": {
    "gn:admin1_code":"81",
    "gn:admin2_code":"3056.0",
    "gn:admin3_code":"305682.0",
    "gn:admin4_code":"30568260.0",
    "gn:asciiname":"Char Madhu Sonatala",
    "gn:country_code":"BD",
    "gn:dem":11,
    "gn:feature_class":"P",
    "gn:feature_code":"PPL",
    "gn:name":"Char Madhu Son\u0101tala",
    "gn:population":0,
    "gn:timezone":"Asia/Dhaka",
    "iso:country":"BD",
    "wof:name":"Char Madhu Sonatala",
    "wof:placetype":"locality"
},
  "geometry": {"coordinates":[90.18282000000001,23.77146],"type":"Point"}
}