{
  "type": "Feature",
  "properties": {
    "gn:admin1_code":"82",
    "gn:admin2_code":"4055.0",
    "gn:admin3_code":"405557.0",
    "gn:admin4_code":"40555774.0",
    "gn:asciiname":"Bhudharpara",
    "gn:country_code":"BD",
    "gn:dem":10,
    "gn:feature_class":"P",
    "gn:feature_code":"PPL",
    "gn:name":"Bhudharp\u0101ra",
    "gn:population":0,
    "gn:timezone":"Asia/Dhaka",
    "iso:country":"BD",
    "name:ben_x_preferred":[
        "Bhudharp\u0101ra"
    ],
    "wof:name":"Bhudharpara",
    "wof:placetype":"locality"
},
  "geometry": {"coordinates":[89.38481999999998,23.41451],"type":"Point"}
}