{
  "type": "Feature",
  "properties": {
    "gn:admin1_code":"81",
    "gn:admin2_code":"3029",
    "gn:admin3_code":"302956.0",
    "gn:admin4_code":"30295684.0",
    "gn:asciiname":"Jaliar Mobarakdia",
    "gn:cc2":"BD",
    "gn:country_code":"BD",
    "gn:dem":14,
    "gn:feature_class":"P",
    "gn:feature_code":"PPL",
    "gn:name":"J\u0101li\u0101r Mob\u0101rakdia",
    "gn:population":0,
    "gn:timezone":"Asia/Dhaka",
    "iso:country":"BD",
    "name:und_x_variant":[
        "Jaliar Mabarakdi",
        "J\u0101li\u0101r Mob\u0101rakdia"
    ],
    "wof:name":"Jaliar Mobarakdia",
    "wof:placetype":"locality"
},
  "geometry": {"coordinates":[89.68333,23.53333],"type":"Point"}
}