{
  "type": "Feature",
  "properties": {
    "gn:admin1_code":"83",
    "gn:admin2_code":"5010.0",
    "gn:admin3_code":"501033.0",
    "gn:admin4_code":"50103354.0",
    "gn:asciiname":"Bhatanda",
    "gn:country_code":"BD",
    "gn:dem":22,
    "gn:feature_class":"P",
    "gn:feature_code":"PPL",
    "gn:name":"Bh\u0101t\u0101nda",
    "gn:population":0,
    "gn:timezone":"Asia/Dhaka",
    "iso:country":"BD",
    "wof:name":"Bhatanda",
    "wof:placetype":"locality"
},
  "geometry": {"coordinates":[89.14168000000002,24.88257],"type":"Point"}
}