{
  "type": "Feature",
  "properties": {
    "gn:admin1_code":"83",
    "gn:admin2_code":"5010.0",
    "gn:admin3_code":"501088.0",
    "gn:admin4_code":"50108847.0",
    "gn:asciiname":"Dari Khaga",
    "gn:country_code":"BD",
    "gn:dem":19,
    "gn:feature_class":"P",
    "gn:feature_code":"PPL",
    "gn:name":"Dari Kh\u0101ga",
    "gn:population":0,
    "gn:timezone":"Asia/Dhaka",
    "iso:country":"BD",
    "wof:name":"Dari Khaga",
    "wof:placetype":"locality"
},
  "geometry": {"coordinates":[89.46791999999998,24.65814],"type":"Point"}
}