{
  "type": "Feature",
  "properties": {
    "gn:admin1_code":"84",
    "gn:admin2_code":"2084.0",
    "gn:admin3_code":"208478.0",
    "gn:admin4_code":"20847871.0",
    "gn:asciiname":"Longadu",
    "gn:country_code":"BD",
    "gn:dem":46,
    "gn:feature_class":"P",
    "gn:feature_code":"PPL",
    "gn:name":"Longadu",
    "gn:population":0,
    "gn:timezone":"Asia/Dhaka",
    "iso:country":"BD",
    "name:ben_x_preferred":[
        "Longadu"
    ],
    "wof:name":"Longadu",
    "wof:placetype":"locality"
},
  "geometry": {"coordinates":[92.21159,22.3511],"type":"Point"}
}