{
  "type": "Feature",
  "properties": {
    "gn:admin1_code":"85",
    "gn:admin2_code":"1004.0",
    "gn:admin3_code":"100485.0",
    "gn:admin4_code":"10048523.0",
    "gn:asciiname":"Kalirchar",
    "gn:country_code":"BD",
    "gn:dem":11,
    "gn:feature_class":"P",
    "gn:feature_code":"PPL",
    "gn:name":"Kalirchar",
    "gn:population":0,
    "gn:timezone":"Asia/Dhaka",
    "iso:country":"BD",
    "name:ben_x_preferred":[
        "Kalirchar"
    ],
    "wof:name":"Kalirchar",
    "wof:placetype":"locality"
},
  "geometry": {"coordinates":[90.04904999999999,22.16059],"type":"Point"}
}