{
  "type": "Feature",
  "properties": {
    "gn:admin1_code":"87",
    "gn:admin2_code":"5532",
    "gn:admin3_code":"553267.0",
    "gn:admin4_code":"55326776.0",
    "gn:asciiname":"Purba Faridpur",
    "gn:country_code":"BD",
    "gn:dem":26,
    "gn:feature_class":"P",
    "gn:feature_code":"PPL",
    "gn:name":"Purba Faridpur",
    "gn:population":0,
    "gn:timezone":"Asia/Dhaka",
    "iso:country":"BD",
    "name:ben_x_preferred":[
        "Purba Faridpur"
    ],
    "wof:name":"Purba Faridpur",
    "wof:placetype":"locality"
},
  "geometry": {"coordinates":[89.41786999999999,25.25165],"type":"Point"}
}