{
  "type": "Feature",
  "properties": {
    "gn:admin1_code":"87",
    "gn:admin2_code":"5527",
    "gn:admin3_code":"552764.0",
    "gn:admin4_code":"55276425.0",
    "gn:asciiname":"Mahabalipur",
    "gn:country_code":"BD",
    "gn:dem":41,
    "gn:feature_class":"P",
    "gn:feature_code":"PPL",
    "gn:name":"Mah\u0101balipur",
    "gn:population":0,
    "gn:timezone":"Asia/Dhaka",
    "iso:country":"BD",
    "name:ben_x_preferred":[
        "Mah\u0101balipur"
    ],
    "wof:name":"Mahabalipur",
    "wof:placetype":"locality"
},
  "geometry": {"coordinates":[88.65586999999999,25.68869],"type":"Point"}
}