{
  "type": "Feature",
  "properties": {
    "gn:admin1_code":"87",
    "gn:admin2_code":"5527.0",
    "gn:admin3_code":"552760.0",
    "gn:admin4_code":"55276094.0",
    "gn:asciiname":"Bhandardana",
    "gn:country_code":"BD",
    "gn:dem":47,
    "gn:feature_class":"P",
    "gn:feature_code":"PPL",
    "gn:name":"Bh\u0101nd\u0101rdana",
    "gn:population":0,
    "gn:timezone":"Asia/Dhaka",
    "iso:country":"BD",
    "name:ben_x_preferred":[
        "Bh\u0101nd\u0101rdana"
    ],
    "wof:name":"Bhandardana",
    "wof:placetype":"locality"
},
  "geometry": {"coordinates":[88.76999000000001,25.86624],"type":"Point"}
}