{
  "type": "Feature",
  "properties": {
    "gn:admin1_code":"83",
    "gn:admin2_code":"5038.0",
    "gn:admin3_code":"503874.0",
    "gn:admin4_code":"50387452.0",
    "gn:asciiname":"Sultonpur",
    "gn:country_code":"BD",
    "gn:dem":28,
    "gn:feature_class":"P",
    "gn:feature_code":"PPL",
    "gn:name":"Sult\u014dnpur",
    "gn:population":0,
    "gn:timezone":"Asia/Dhaka",
    "iso:country":"BD",
    "name:ben_x_preferred":[
        "Sult\u014dnpur"
    ],
    "wof:name":"Sultonpur",
    "wof:placetype":"locality"
},
  "geometry": {"coordinates":[89.03943000000002,25.17249],"type":"Point"}
}