{
  "type": "Feature",
  "properties": {
    "gn:admin1_code":"82",
    "gn:admin2_code":"4001.0",
    "gn:admin3_code":"400160.0",
    "gn:admin4_code":"40016023.0",
    "gn:asciiname":"Dakshin Sutalari",
    "gn:country_code":"BD",
    "gn:dem":8,
    "gn:feature_class":"P",
    "gn:feature_code":"PPL",
    "gn:name":"Dakshin Sutalari",
    "gn:population":0,
    "gn:timezone":"Asia/Dhaka",
    "iso:country":"BD",
    "name:ben_x_preferred":[
        "Dakshin Sutalari"
    ],
    "wof:name":"Dakshin Sutalari",
    "wof:placetype":"locality"
},
  "geometry": {"coordinates":[89.79543000000002,22.44263],"type":"Point"}
}