{
  "type": "Feature",
  "properties": {
    "gn:admin1_code":"83",
    "gn:admin2_code":"5064",
    "gn:admin3_code":"506450.0",
    "gn:admin4_code":"50645019.0",
    "gn:asciiname":"Tanka Sibpur",
    "gn:country_code":"BD",
    "gn:dem":21,
    "gn:feature_class":"P",
    "gn:feature_code":"PPL",
    "gn:name":"Tanka Sibpur",
    "gn:population":0,
    "gn:timezone":"Asia/Dhaka",
    "iso:country":"BD",
    "wof:name":"Tanka Sibpur",
    "wof:placetype":"locality"
},
  "geometry": {"coordinates":[88.71666999999999,24.88333],"type":"Point"}
}