{
  "type": "Feature",
  "properties": {
    "gn:admin1_code":"82",
    "gn:admin2_code":"4047.0",
    "gn:admin3_code":"404712.0",
    "gn:admin4_code":"40471247.0",
    "gn:asciiname":"Bhandarkote",
    "gn:country_code":"BD",
    "gn:dem":9,
    "gn:feature_class":"P",
    "gn:feature_code":"PPL",
    "gn:name":"Bh\u0101nd\u0101rkote",
    "gn:population":0,
    "gn:timezone":"Asia/Dhaka",
    "iso:country":"BD",
    "wof:name":"Bhandarkote",
    "wof:placetype":"locality"
},
  "geometry": {"coordinates":[89.56979,22.68323],"type":"Point"}
}