{
  "type": "Feature",
  "properties": {
    "gn:admin1_code":"84",
    "gn:admin2_code":"2013",
    "gn:admin3_code":"201358.0",
    "gn:admin4_code":"20135839.0",
    "gn:asciiname":"Khidda",
    "gn:country_code":"BD",
    "gn:dem":12,
    "gn:feature_class":"P",
    "gn:feature_code":"PPL",
    "gn:name":"Khidda",
    "gn:population":0,
    "gn:timezone":"Asia/Dhaka",
    "iso:country":"BD",
    "wof:name":"Khidda",
    "wof:placetype":"locality"
},
  "geometry": {"coordinates":[90.90358999999999,23.37822],"type":"Point"}
}