{
  "type": "Feature",
  "properties": {
    "gn:admin1_code":"82",
    "gn:admin2_code":"4001.0",
    "gn:admin3_code":"400156.0",
    "gn:admin4_code":"40015695.0",
    "gn:asciiname":"Garfa",
    "gn:country_code":"BD",
    "gn:dem":10,
    "gn:feature_class":"P",
    "gn:feature_code":"PPL",
    "gn:name":"G\u0101rfa",
    "gn:population":0,
    "gn:timezone":"Asia/Dhaka",
    "iso:country":"BD",
    "wof:name":"Garfa",
    "wof:placetype":"locality"
},
  "geometry": {"coordinates":[89.81576,22.92111],"type":"Point"}
}