{
  "type": "Feature",
  "properties": {
    "gn:admin1_code":"84",
    "gn:admin2_code":"2022.0",
    "gn:admin3_code":"202224.0",
    "gn:admin4_code":"20222411.0",
    "gn:asciiname":"Uttarpara",
    "gn:country_code":"BD",
    "gn:dem":5,
    "gn:feature_class":"P",
    "gn:feature_code":"PPL",
    "gn:name":"Uttarp\u0101ra",
    "gn:population":0,
    "gn:timezone":"Asia/Dhaka",
    "iso:country":"BD",
    "name:ben_x_preferred":[
        "Uttarp\u0101ra"
    ],
    "wof:name":"Uttarpara",
    "wof:placetype":"locality"
},
  "geometry": {"coordinates":[92.03127000000001,21.52336],"type":"Point"}
}