{
  "type": "Feature",
  "properties": {
    "gn:admin1_code":"83",
    "gn:admin2_code":"5038.0",
    "gn:admin3_code":"503861.0",
    "gn:admin4_code":"50386119.0",
    "gn:asciiname":"Konchakul",
    "gn:country_code":"BD",
    "gn:dem":26,
    "gn:feature_class":"P",
    "gn:feature_code":"PPL",
    "gn:name":"K\u014dnch\u0101kul",
    "gn:population":0,
    "gn:timezone":"Asia/Dhaka",
    "iso:country":"BD",
    "name:ben_x_preferred":[
        "K\u014dnch\u0101kul"
    ],
    "wof:name":"Konchakul",
    "wof:placetype":"locality"
},
  "geometry": {"coordinates":[89.1519,25.11557],"type":"Point"}
}