{
  "type": "Feature",
  "properties": {
    "gn:admin1_code":"87",
    "gn:admin2_code":"5585",
    "gn:admin3_code":"558527.0",
    "gn:admin4_code":"55852773.0",
    "gn:asciiname":"Kismat Dukhia",
    "gn:country_code":"BD",
    "gn:dem":36,
    "gn:feature_class":"P",
    "gn:feature_code":"PPL",
    "gn:name":"Kismat Dukhia",
    "gn:population":0,
    "gn:timezone":"Asia/Dhaka",
    "iso:country":"BD",
    "wof:name":"Kismat Dukhia",
    "wof:placetype":"locality"
},
  "geometry": {"coordinates":[89.28333000000001,25.86667000000001],"type":"Point"}
}