{
  "type": "Feature",
  "properties": {
    "gn:admin1_code":"H",
    "gn:admin2_code":"3072",
    "gn:admin3_code":"307247.0",
    "gn:admin4_code":"30724794.0",
    "gn:asciiname":"Salpa Maijhati",
    "gn:country_code":"BD",
    "gn:dem":13,
    "gn:feature_class":"P",
    "gn:feature_code":"PPL",
    "gn:name":"Salpa M\u0101ijh\u0101ti",
    "gn:population":0,
    "gn:timezone":"Asia/Dhaka",
    "iso:country":"BD",
    "wof:name":"Salpa Maijhati",
    "wof:placetype":"locality"
},
  "geometry": {"coordinates":[90.73333,24.66667],"type":"Point"}
}