{
  "type": "Feature",
  "properties": {
    "gn:admin1_code":"82",
    "gn:admin2_code":"4050",
    "gn:admin3_code":"405071.0",
    "gn:admin4_code":"40507186.0",
    "gn:asciiname":"Tebaria",
    "gn:country_code":"BD",
    "gn:dem":18,
    "gn:feature_class":"P",
    "gn:feature_code":"PPL",
    "gn:name":"Teb\u0101ria",
    "gn:population":0,
    "gn:timezone":"Asia/Dhaka",
    "iso:country":"BD",
    "wof:name":"Tebaria",
    "wof:placetype":"locality"
},
  "geometry": {"coordinates":[89.25251999999998,23.84771],"type":"Point"}
}