{
  "type": "Feature",
  "properties": {
    "gn:admin1_code":"81",
    "gn:admin2_code":"3035.0",
    "gn:admin3_code":"303532.0",
    "gn:admin4_code":"30353277.0",
    "gn:asciiname":"Gandiasur",
    "gn:country_code":"BD",
    "gn:dem":11,
    "gn:feature_class":"P",
    "gn:feature_code":"PPL",
    "gn:name":"Gandi\u0101sur",
    "gn:population":0,
    "gn:timezone":"Asia/Dhaka",
    "iso:country":"BD",
    "name:ben_x_preferred":[
        "Gandi\u0101sur"
    ],
    "wof:name":"Gandiasur",
    "wof:placetype":"locality"
},
  "geometry": {"coordinates":[89.91458,23.1074],"type":"Point"}
}