{
  "type": "Feature",
  "properties": {
    "gn:admin1_code":"83",
    "gn:admin2_code":"5064.0",
    "gn:admin3_code":"506479.0",
    "gn:admin4_code":"50647987.0",
    "gn:asciiname":"Madhupur",
    "gn:country_code":"BD",
    "gn:dem":44,
    "gn:feature_class":"P",
    "gn:feature_code":"PPL",
    "gn:name":"Madhupur",
    "gn:population":0,
    "gn:timezone":"Asia/Dhaka",
    "iso:country":"BD",
    "name:ben_x_preferred":[
        "Madhupur"
    ],
    "name:ita_x_preferred":[
        "Madhupur"
    ],
    "name:msa_x_preferred":[
        "Madhupur"
    ],
    "wof:name":"Madhupur",
    "wof:placetype":"locality"
},
  "geometry": {"coordinates":[88.50482,24.98003],"type":"Point"}
}