{
  "type": "Feature",
  "properties": {
    "gn:admin1_code":"83",
    "gn:admin2_code":"5069",
    "gn:admin3_code":"506909.0",
    "gn:admin4_code":"50690938.0",
    "gn:asciiname":"Teghari",
    "gn:country_code":"BD",
    "gn:dem":13,
    "gn:feature_class":"P",
    "gn:feature_code":"PPL",
    "gn:name":"Teghari",
    "gn:population":0,
    "gn:timezone":"Asia/Dhaka",
    "iso:country":"BD",
    "name:spa_x_preferred":[
        "Teghari"
    ],
    "wof:name":"Teghari",
    "wof:placetype":"locality"
},
  "geometry": {"coordinates":[88.98333000000002,24.35],"type":"Point"}
}