{
  "type": "Feature",
  "properties": {
    "gn:admin1_code":"82",
    "gn:admin2_code":"4050.0",
    "gn:admin3_code":"405039.0",
    "gn:admin4_code":"40503961.0",
    "gn:asciiname":"Harisankara",
    "gn:country_code":"BD",
    "gn:dem":25,
    "gn:feature_class":"P",
    "gn:feature_code":"PPL",
    "gn:name":"Harisank\u0101ra",
    "gn:population":0,
    "gn:timezone":"Asia/Dhaka",
    "iso:country":"BD",
    "name:ben_x_preferred":[
        "Harisank\u0101ra"
    ],
    "wof:name":"Harisankara",
    "wof:placetype":"locality"
},
  "geometry": {"coordinates":[88.82064,24.04523],"type":"Point"}
}