{
  "type": "Feature",
  "properties": {
    "gn:admin1_code":"82",
    "gn:admin2_code":"4041",
    "gn:admin3_code":"404111.0",
    "gn:admin4_code":"40411177.0",
    "gn:asciiname":"Khurd Singhajhuli",
    "gn:country_code":"BD",
    "gn:dem":12,
    "gn:feature_class":"P",
    "gn:feature_code":"PPL",
    "gn:name":"Khurd Singhajhuli",
    "gn:population":0,
    "gn:timezone":"Asia/Dhaka",
    "iso:country":"BD",
    "name:ben_x_preferred":[
        "Khurd Singhajhuli"
    ],
    "name:und_x_variant":[
        "Khorda Singhajhuli"
    ],
    "wof:name":"Khurd Singhajhuli",
    "wof:placetype":"locality"
},
  "geometry": {"coordinates":[89.08161,23.23711],"type":"Point"}
}