{
  "type": "Feature",
  "properties": {
    "gn:admin1_code":"85",
    "gn:admin2_code":"1042.0",
    "gn:admin3_code":"104243.0",
    "gn:admin4_code":"10424315.0",
    "gn:asciiname":"Amua",
    "gn:country_code":"BD",
    "gn:dem":10,
    "gn:feature_class":"P",
    "gn:feature_code":"PPL",
    "gn:name":"\u0100mua",
    "gn:population":0,
    "gn:timezone":"Asia/Dhaka",
    "iso:country":"BD",
    "name:ben_x_preferred":[
        "\u0100mua"
    ],
    "wof:name":"Amua",
    "wof:placetype":"locality"
},
  "geometry": {"coordinates":[90.07836,22.36815],"type":"Point"}
}