{
  "type": "Feature",
  "properties": {
    "gn:admin1_code":"84",
    "gn:admin2_code":"2019.0",
    "gn:admin3_code":"201936.0",
    "gn:admin4_code":"20193682.0",
    "gn:asciiname":"Baliardron",
    "gn:country_code":"BD",
    "gn:dem":5,
    "gn:feature_class":"P",
    "gn:feature_code":"PPL",
    "gn:name":"B\u0101li\u0101rdron",
    "gn:population":0,
    "gn:timezone":"Asia/Dhaka",
    "iso:country":"BD",
    "wof:name":"Baliardron",
    "wof:placetype":"locality"
},
  "geometry": {"coordinates":[90.7591,23.4603],"type":"Point"}
}