{
  "type": "Feature",
  "properties": {
    "gn:admin1_code":"87",
    "gn:admin2_code":"5549",
    "gn:admin3_code":"554977.0",
    "gn:admin4_code":"55497731.0",
    "gn:asciiname":"Chaturohuj",
    "gn:country_code":"BD",
    "gn:dem":36,
    "gn:feature_class":"P",
    "gn:feature_code":"PPL",
    "gn:name":"Chaturohuj",
    "gn:population":0,
    "gn:timezone":"Asia/Dhaka",
    "iso:country":"BD",
    "name:ben_x_preferred":[
        "Chaturohuj"
    ],
    "wof:name":"Chaturohuj",
    "wof:placetype":"locality"
},
  "geometry": {"coordinates":[89.56971999999998,25.86707],"type":"Point"}
}