{
  "type": "Feature",
  "properties": {
    "gn:admin1_code":"83",
    "gn:admin2_code":"5081",
    "gn:admin3_code":"508182.0",
    "gn:admin4_code":"50818281.0",
    "gn:asciiname":"Khoksa",
    "gn:country_code":"BD",
    "gn:dem":20,
    "gn:feature_class":"P",
    "gn:feature_code":"PPL",
    "gn:name":"Khoksa",
    "gn:population":0,
    "gn:timezone":"Asia/Dhaka",
    "iso:country":"BD",
    "name:ben_x_preferred":[
        "Khoksa"
    ],
    "name:ceb_x_preferred":[
        "Khoksa"
    ],
    "name:swe_x_preferred":[
        "Khoksa"
    ],
    "wof:name":"Khoksa",
    "wof:placetype":"locality"
},
  "geometry": {"coordinates":[88.87555999999999,24.45223],"type":"Point"}
}