{
  "type": "Feature",
  "properties": {
    "gn:admin1_code":"81",
    "gn:admin2_code":"3029.0",
    "gn:admin3_code":"302903.0",
    "gn:admin4_code":"30290342.0",
    "gn:asciiname":"Char Kharakdia",
    "gn:country_code":"BD",
    "gn:dem":2,
    "gn:feature_class":"P",
    "gn:feature_code":"PPL",
    "gn:name":"Char Kharakdia",
    "gn:population":0,
    "gn:timezone":"Asia/Dhaka",
    "iso:country":"BD",
    "wof:name":"Char Kharakdia",
    "wof:placetype":"locality"
},
  "geometry": {"coordinates":[89.65994000000001,23.28499],"type":"Point"}
}