{
  "type": "Feature",
  "properties": {
    "gn:admin1_code":"82",
    "gn:admin2_code":"4050",
    "gn:admin3_code":"405094.0",
    "gn:admin4_code":"40509473.0",
    "gn:asciiname":"Jogipur",
    "gn:country_code":"BD",
    "gn:dem":19,
    "gn:feature_class":"P",
    "gn:feature_code":"PPL",
    "gn:name":"Jogipur",
    "gn:population":0,
    "gn:timezone":"Asia/Dhaka",
    "iso:country":"BD",
    "name:ben_x_preferred":[
        "Jogipur"
    ],
    "name:ben_x_variant":[
        "Jogipol"
    ],
    "wof:name":"Jogipur",
    "wof:placetype":"locality"
},
  "geometry": {"coordinates":[89.0166,23.93449],"type":"Point"}
}