{
  "type": "Feature",
  "properties": {
    "gn:admin1_code":"83",
    "gn:admin2_code":"5010",
    "gn:admin3_code":"501094.0",
    "gn:admin4_code":"50109455.0",
    "gn:asciiname":"Masimpur Chalunja",
    "gn:country_code":"BD",
    "gn:dem":23,
    "gn:feature_class":"P",
    "gn:feature_code":"PPL",
    "gn:name":"M\u0101simpur Ch\u0101lunja",
    "gn:population":0,
    "gn:timezone":"Asia/Dhaka",
    "iso:country":"BD",
    "wof:name":"Masimpur Chalunja",
    "wof:placetype":"locality"
},
  "geometry": {"coordinates":[89.20753000000001,24.93456],"type":"Point"}
}