{
  "type": "Feature",
  "properties": {
    "gn:admin1_code":"82",
    "gn:admin2_code":"4041",
    "gn:admin3_code":"404111.0",
    "gn:admin4_code":"40411108.0",
    "gn:asciiname":"Gobindapur",
    "gn:country_code":"BD",
    "gn:dem":10,
    "gn:feature_class":"P",
    "gn:feature_code":"PPL",
    "gn:name":"Gobindapur",
    "gn:population":0,
    "gn:timezone":"Asia/Dhaka",
    "iso:country":"BD",
    "name:ben_x_preferred":[
        "Gobindapur"
    ],
    "wof:name":"Gobindapur",
    "wof:placetype":"locality"
},
  "geometry": {"coordinates":[88.99359,23.22864],"type":"Point"}
}