{
  "type": "Feature",
  "properties": {
    "gn:admin1_code":"81",
    "gn:admin2_code":"3029",
    "gn:admin3_code":"302918.0",
    "gn:admin4_code":"30291885.0",
    "gn:asciiname":"Tongrail",
    "gn:country_code":"BD",
    "gn:dem":12,
    "gn:feature_class":"P",
    "gn:feature_code":"PPL",
    "gn:name":"Tongr\u0101il",
    "gn:population":0,
    "gn:timezone":"Asia/Dhaka",
    "iso:country":"BD",
    "wof:name":"Tongrail",
    "wof:placetype":"locality"
},
  "geometry": {"coordinates":[89.74258,23.30209],"type":"Point"}
}