{
  "type": "Feature",
  "properties": {
    "gn:admin1_code":"84",
    "gn:admin2_code":"2019.0",
    "gn:admin3_code":"201975.0",
    "gn:admin4_code":"20197519.0",
    "gn:asciiname":"Baidyer Bazar",
    "gn:country_code":"BD",
    "gn:dem":10,
    "gn:feature_class":"P",
    "gn:feature_code":"PPL",
    "gn:name":"Baidyer B\u0101z\u0101r",
    "gn:population":0,
    "gn:timezone":"Asia/Dhaka",
    "iso:country":"BD",
    "name:und_x_variant":[
        "Chhota Deobhog",
        "Baidya",
        "Chhota Deobbog",
        "Baidya B\u0101z\u0101r",
        "Baidyer B\u0101z\u0101r"
    ],
    "wof:name":"Baidyer Bazar",
    "wof:placetype":"locality"
},
  "geometry": {"coordinates":[90.64287,23.65075],"type":"Point"}
}