{
  "type": "Feature",
  "properties": {
    "gn:admin1_code":"81",
    "gn:admin2_code":"3067",
    "gn:admin3_code":"306706.0",
    "gn:admin4_code":"30670615.0",
    "gn:asciiname":"Nabiganj",
    "gn:country_code":"BD",
    "gn:dem":9,
    "gn:feature_class":"P",
    "gn:feature_code":"PPL",
    "gn:name":"Nabiganj",
    "gn:population":0,
    "gn:timezone":"Asia/Dhaka",
    "iso:country":"BD",
    "wof:name":"Nabiganj",
    "wof:placetype":"locality"
},
  "geometry": {"coordinates":[90.51973,23.6286],"type":"Point"}
}