{
  "type": "Feature",
  "properties": {
    "gn:admin1_code":"81",
    "gn:admin2_code":"3093",
    "gn:admin3_code":"309385.0",
    "gn:admin4_code":"30938513.0",
    "gn:asciiname":"Jogirkopha",
    "gn:country_code":"BD",
    "gn:dem":12,
    "gn:feature_class":"P",
    "gn:feature_code":"PPL",
    "gn:name":"Jogirkopha",
    "gn:population":0,
    "gn:timezone":"Asia/Dhaka",
    "iso:country":"BD",
    "wof:name":"Jogirkopha",
    "wof:placetype":"locality"
},
  "geometry": {"coordinates":[90.08333,24.33333],"type":"Point"}
}