{
  "type": "Feature",
  "properties": {
    "gn:admin1_code":"84",
    "gn:admin2_code":"2022.0",
    "gn:admin3_code":"202294.0",
    "gn:admin4_code":"20229447.0",
    "gn:asciiname":"Chak Boitapalong",
    "gn:country_code":"BD",
    "gn:dem":23,
    "gn:feature_class":"P",
    "gn:feature_code":"PPL",
    "gn:name":"Chak Boit\u0101p\u0101long",
    "gn:population":0,
    "gn:timezone":"Asia/Dhaka",
    "iso:country":"BD",
    "name:ben_x_preferred":[
        "Chak Boit\u0101p\u0101long"
    ],
    "name:ben_x_variant":[
        "Chah Boit\u0101p\u0101long"
    ],
    "wof:name":"Chak Boitapalong",
    "wof:placetype":"locality"
},
  "geometry": {"coordinates":[92.15634,21.26704],"type":"Point"}
}