{
  "type": "Feature",
  "properties": {
    "gn:admin1_code":"84",
    "gn:admin2_code":"2013.0",
    "gn:admin3_code":"201358.0",
    "gn:admin4_code":"20135855.0",
    "gn:asciiname":"Ayma",
    "gn:country_code":"BD",
    "gn:dem":6,
    "gn:feature_class":"P",
    "gn:feature_code":"PPL",
    "gn:name":"\u0100yma",
    "gn:population":0,
    "gn:timezone":"Asia/Dhaka",
    "iso:country":"BD",
    "name:und_x_variant":[
        "\u0100yma"
    ],
    "wof:name":"Ayma",
    "wof:placetype":"locality"
},
  "geometry": {"coordinates":[90.8108,23.33791],"type":"Point"}
}