{
  "type": "Feature",
  "properties": {
    "gn:admin1_code":"83",
    "gn:admin2_code":"5064",
    "gn:admin3_code":"506450.0",
    "gn:admin4_code":"50645028.0",
    "gn:asciiname":"Manoharpur",
    "gn:country_code":"BD",
    "gn:dem":21,
    "gn:feature_class":"P",
    "gn:feature_code":"PPL",
    "gn:name":"Manoharpur",
    "gn:population":0,
    "gn:timezone":"Asia/Dhaka",
    "iso:country":"BD",
    "name:ben_x_preferred":[
        "Manoharpur"
    ],
    "name:und_x_variant":[
        "Manaharpur"
    ],
    "wof:name":"Manoharpur",
    "wof:placetype":"locality"
},
  "geometry": {"coordinates":[88.83223000000002,24.88574],"type":"Point"}
}