{
  "type": "Feature",
  "properties": {
    "gn:admin1_code":"83",
    "gn:admin2_code":"5070.0",
    "gn:admin3_code":"507088.0",
    "gn:admin4_code":"50708865.0",
    "gn:asciiname":"Charpaka",
    "gn:country_code":"BD",
    "gn:dem":18,
    "gn:feature_class":"P",
    "gn:feature_code":"PPL",
    "gn:name":"Charpaka",
    "gn:population":0,
    "gn:timezone":"Asia/Dhaka",
    "iso:country":"BD",
    "name:ben_x_preferred":[
        "Charpaka"
    ],
    "wof:name":"Charpaka",
    "wof:placetype":"locality"
},
  "geometry": {"coordinates":[88.12777,24.61638],"type":"Point"}
}