{
  "type": "Feature",
  "properties": {
    "gn:admin1_code":"84",
    "gn:admin2_code":"2075",
    "gn:admin3_code":"207508.0",
    "gn:admin4_code":"20750877.0",
    "gn:asciiname":"Nateswar",
    "gn:country_code":"BD",
    "gn:dem":8,
    "gn:feature_class":"P",
    "gn:feature_code":"PPL",
    "gn:name":"Nateswar",
    "gn:population":0,
    "gn:timezone":"Asia/Dhaka",
    "iso:country":"BD",
    "wof:name":"Nateswar",
    "wof:placetype":"locality"
},
  "geometry": {"coordinates":[91.15000000000001,22.98333],"type":"Point"}
}