{
  "type": "Feature",
  "properties": {
    "gn:admin1_code":"82",
    "gn:admin2_code":"4044.0",
    "gn:admin3_code":"404433.0",
    "gn:admin4_code":"40443361.0",
    "gn:asciiname":"Chaprail",
    "gn:country_code":"BD",
    "gn:dem":16,
    "gn:feature_class":"P",
    "gn:feature_code":"PPL",
    "gn:name":"Ch\u0101pr\u0101il",
    "gn:population":0,
    "gn:timezone":"Asia/Dhaka",
    "iso:country":"BD",
    "name:ben_x_preferred":[
        "Ch\u0101pr\u0101il"
    ],
    "wof:name":"Chaprail",
    "wof:placetype":"locality"
},
  "geometry": {"coordinates":[89.18257,23.37227],"type":"Point"}
}