{
  "type": "Feature",
  "properties": {
    "gn:admin1_code":"82",
    "gn:admin2_code":"4050",
    "gn:admin3_code":"405071.0",
    "gn:admin4_code":"40507143.0",
    "gn:asciiname":"Jagannathpur",
    "gn:country_code":"BD",
    "gn:dem":17,
    "gn:feature_class":"P",
    "gn:feature_code":"PPL",
    "gn:name":"Jagann\u0101thpur",
    "gn:population":0,
    "gn:timezone":"Asia/Dhaka",
    "iso:country":"BD",
    "wof:name":"Jagannathpur",
    "wof:placetype":"locality"
},
  "geometry": {"coordinates":[89.27818000000001,23.8805],"type":"Point"}
}