{
  "type": "Feature",
  "properties": {
    "gn:admin1_code":"83",
    "gn:admin2_code":"5081.0",
    "gn:admin3_code":"508125.0",
    "gn:admin4_code":"50812571.0",
    "gn:asciiname":"Dhiren",
    "gn:country_code":"BD",
    "gn:dem":22,
    "gn:feature_class":"P",
    "gn:feature_code":"PPL",
    "gn:name":"Dhiren",
    "gn:population":0,
    "gn:timezone":"Asia/Dhaka",
    "iso:country":"BD",
    "name:ben_x_preferred":[
        "Dhiren"
    ],
    "wof:name":"Dhiren",
    "wof:placetype":"locality"
},
  "geometry": {"coordinates":[88.82409,24.30135],"type":"Point"}
}