{
  "type": "Feature",
  "properties": {
    "gn:admin1_code":"87",
    "gn:admin2_code":"5594.0",
    "gn:admin3_code":"559482.0",
    "gn:admin4_code":"55948200.0",
    "gn:asciiname":"Bath Paligaon",
    "gn:country_code":"BD",
    "gn:dem":47,
    "gn:feature_class":"P",
    "gn:feature_code":"PPL",
    "gn:name":"Bath P\u0101ligaon",
    "gn:population":0,
    "gn:timezone":"Asia/Dhaka",
    "iso:country":"BD",
    "name:ben_x_preferred":[
        "Bath P\u0101ligaon"
    ],
    "wof:name":"Bath Paligaon",
    "wof:placetype":"locality"
},
  "geometry": {"coordinates":[88.34161,25.85563],"type":"Point"}
}