{
  "type": "Feature",
  "properties": {
    "gn:admin1_code":"87",
    "gn:admin2_code":"5527.0",
    "gn:admin3_code":"552730.0",
    "gn:admin4_code":"55273047.0",
    "gn:asciiname":"Bangalpara",
    "gn:country_code":"BD",
    "gn:dem":44,
    "gn:feature_class":"P",
    "gn:feature_code":"PPL",
    "gn:name":"B\u0101ng\u0101lp\u0101r\u0101",
    "gn:population":0,
    "gn:timezone":"Asia/Dhaka",
    "iso:country":"BD",
    "name:ben_x_preferred":[
        "B\u0101ng\u0101lp\u0101r\u0101"
    ],
    "wof:name":"Bangalpara",
    "wof:placetype":"locality"
},
  "geometry": {"coordinates":[88.8556,25.74911],"type":"Point"}
}