{
  "type": "Feature",
  "properties": {
    "gn:admin1_code":"84",
    "gn:admin2_code":"2019",
    "gn:admin3_code":"201909.0",
    "gn:admin4_code":"20190918.0",
    "gn:asciiname":"Jaspur",
    "gn:cc2":"BD",
    "gn:country_code":"BD",
    "gn:dem":10,
    "gn:feature_class":"P",
    "gn:feature_code":"PPL",
    "gn:name":"J\u0101spur",
    "gn:population":0,
    "gn:timezone":"Asia/Dhaka",
    "iso:country":"BD",
    "name:bpy_x_preferred":[
        "\u099c\u09b6\u09aa\u09c1\u09b0"
    ],
    "name:ceb_x_preferred":[
        "Jaspur"
    ],
    "name:hin_x_preferred":[
        "\u091c\u0938\u092a\u0941\u0930"
    ],
    "name:ita_x_preferred":[
        "Jaspur"
    ],
    "name:mlg_x_preferred":[
        "Jaspur"
    ],
    "name:msa_x_preferred":[
        "Jaspur"
    ],
    "name:new_x_preferred":[
        "\u091c\u0938\u094d\u092a\u0941\u0930"
    ],
    "name:nld_x_preferred":[
        "Jaspur"
    ],
    "name:pol_x_preferred":[
        "Jaspur"
    ],
    "name:por_x_preferred":[
        "Jaspur"
    ],
    "name:swe_x_preferred":[
        "Jaspur"
    ],
    "name:und_x_variant":[
        "West Jaspur",
        "J\u0101spur"
    ],
    "name:urd_x_preferred":[
        "\u062c\u0633\u067e\u0631"
    ],
    "name:vie_x_preferred":[
        "Jaspur"
    ],
    "name:zho_x_preferred":[
        "\u8d3e\u65af\u666e\u5c14"
    ],
    "wof:name":"Jaspur",
    "wof:placetype":"locality"
},
  "geometry": {"coordinates":[91.08333,23.41667],"type":"Point"}
}