{
  "type": "Feature",
  "properties": {
    "gn:admin1_code":"82",
    "gn:admin2_code":"4055.0",
    "gn:admin3_code":"405585.0",
    "gn:admin4_code":"40558511.0",
    "gn:asciiname":"Uchgram",
    "gn:country_code":"BD",
    "gn:dem":11,
    "gn:feature_class":"P",
    "gn:feature_code":"PPL",
    "gn:name":"Uchgr\u0101m",
    "gn:population":0,
    "gn:timezone":"Asia/Dhaka",
    "iso:country":"BD",
    "name:ben_x_preferred":[
        "Uchgr\u0101m"
    ],
    "wof:name":"Uchgram",
    "wof:placetype":"locality"
},
  "geometry": {"coordinates":[89.36360000000001,23.38598],"type":"Point"}
}