{
  "type": "Feature",
  "properties": {
    "gn:admin1_code":"82",
    "gn:admin2_code":"4041.0",
    "gn:admin3_code":"404109.0",
    "gn:admin4_code":"40410947.0",
    "gn:asciiname":"Mamudanipur",
    "gn:country_code":"BD",
    "gn:dem":10,
    "gn:feature_class":"P",
    "gn:feature_code":"PPL",
    "gn:name":"M\u0101mud\u0101nipur",
    "gn:population":0,
    "gn:timezone":"Asia/Dhaka",
    "iso:country":"BD",
    "name:ben_x_preferred":[
        "M\u0101mud\u0101nipur"
    ],
    "wof:name":"Mamudanipur",
    "wof:placetype":"locality"
},
  "geometry": {"coordinates":[89.41333,23.21908],"type":"Point"}
}