{
  "type": "Feature",
  "properties": {
    "gn:admin1_code":"87",
    "gn:admin2_code":"5577.0",
    "gn:admin3_code":"557773.0",
    "gn:admin4_code":"55777371.0",
    "gn:asciiname":"Kazipara",
    "gn:country_code":"BD",
    "gn:dem":79,
    "gn:feature_class":"P",
    "gn:feature_code":"PPL",
    "gn:name":"K\u0101z\u012bp\u0101ra",
    "gn:population":0,
    "gn:timezone":"Asia/Dhaka",
    "iso:country":"BD",
    "name:ben_x_preferred":[
        "K\u0101z\u012bp\u0101ra"
    ],
    "wof:name":"Kazipara",
    "wof:placetype":"locality"
},
  "geometry": {"coordinates":[88.54212,26.37282],"type":"Point"}
}