{
  "type": "Feature",
  "properties": {
    "gn:admin1_code":"83",
    "gn:admin2_code":"5069",
    "gn:admin3_code":"506991.0",
    "gn:admin4_code":"50699147.0",
    "gn:asciiname":"Kumgram",
    "gn:country_code":"BD",
    "gn:dem":16,
    "gn:feature_class":"P",
    "gn:feature_code":"PPL",
    "gn:name":"Kumgr\u0101m",
    "gn:population":0,
    "gn:timezone":"Asia/Dhaka",
    "iso:country":"BD",
    "name:und_x_variant":[
        "Kumgr\u0101m",
        "Kumgaon"
    ],
    "wof:name":"Kumgram",
    "wof:placetype":"locality"
},
  "geometry": {"coordinates":[89.26841999999998,24.52946],"type":"Point"}
}