{
  "type": "Feature",
  "properties": {
    "gn:admin1_code":"87",
    "gn:admin2_code":"5552",
    "gn:admin3_code":"555233.0",
    "gn:admin4_code":"55523347.0",
    "gn:asciiname":"Paschim Kadma",
    "gn:country_code":"BD",
    "gn:dem":46,
    "gn:feature_class":"P",
    "gn:feature_code":"PPL",
    "gn:name":"Paschim K\u0101dma",
    "gn:population":0,
    "gn:timezone":"Asia/Dhaka",
    "iso:country":"BD",
    "wof:name":"Paschim Kadma",
    "wof:placetype":"locality"
},
  "geometry": {"coordinates":[89.21266,26.06539],"type":"Point"}
}