{
  "type": "Feature",
  "properties": {
    "gn:admin1_code":"87",
    "gn:admin2_code":"5532",
    "gn:admin3_code":"553282.0",
    "gn:admin4_code":"55328286.0",
    "gn:asciiname":"Manduarpara",
    "gn:country_code":"BD",
    "gn:dem":28,
    "gn:feature_class":"P",
    "gn:feature_code":"PPL",
    "gn:name":"Manduarpara",
    "gn:population":0,
    "gn:timezone":"Asia/Dhaka",
    "iso:country":"BD",
    "name:ben_x_preferred":[
        "Manduarpara"
    ],
    "wof:name":"Manduarpara",
    "wof:placetype":"locality"
},
  "geometry": {"coordinates":[89.46616999999998,25.47169],"type":"Point"}
}