{
  "type": "Feature",
  "properties": {
    "gn:admin1_code":"82",
    "gn:admin2_code":"4001.0",
    "gn:admin3_code":"400177.0",
    "gn:admin4_code":"40017797.0",
    "gn:asciiname":"Paschim Sonatala",
    "gn:country_code":"BD",
    "gn:dem":11,
    "gn:feature_class":"P",
    "gn:feature_code":"PPL",
    "gn:name":"Paschim Sonatala",
    "gn:population":0,
    "gn:timezone":"Asia/Dhaka",
    "iso:country":"BD",
    "name:ben_x_preferred":[
        "Paschim Sonatala"
    ],
    "wof:name":"Paschim Sonatala",
    "wof:placetype":"locality"
},
  "geometry": {"coordinates":[89.80244999999999,22.25641],"type":"Point"}
}