{
  "type": "Feature",
  "properties": {
    "gn:admin1_code":"81",
    "gn:admin2_code":"3035.0",
    "gn:admin3_code":"303532.0",
    "gn:admin4_code":"30353290.0",
    "gn:asciiname":"Padmabila",
    "gn:country_code":"BD",
    "gn:dem":7,
    "gn:feature_class":"P",
    "gn:feature_code":"PPL",
    "gn:name":"Padmabila",
    "gn:population":0,
    "gn:timezone":"Asia/Dhaka",
    "iso:country":"BD",
    "name:ben_x_preferred":[
        "Padmabila"
    ],
    "wof:name":"Padmabila",
    "wof:placetype":"locality"
},
  "geometry": {"coordinates":[89.87146,23.09889],"type":"Point"}
}