{
  "type": "Feature",
  "properties": {
    "gn:admin1_code":"83",
    "gn:admin2_code":"5038.0",
    "gn:admin3_code":"503858.0",
    "gn:admin4_code":"50385885.0",
    "gn:asciiname":"Kapanka",
    "gn:country_code":"BD",
    "gn:dem":27,
    "gn:feature_class":"P",
    "gn:feature_code":"PPL",
    "gn:name":"Kapanka",
    "gn:population":0,
    "gn:timezone":"Asia/Dhaka",
    "iso:country":"BD",
    "name:ben_x_preferred":[
        "Kapanka"
    ],
    "wof:name":"Kapanka",
    "wof:placetype":"locality"
},
  "geometry": {"coordinates":[89.24258,25.11163],"type":"Point"}
}