{
  "type": "Feature",
  "properties": {
    "gn:admin1_code":"84",
    "gn:admin2_code":"2022.0",
    "gn:admin3_code":"202249.0",
    "gn:admin4_code":"20224935.0",
    "gn:asciiname":"Thakukala",
    "gn:country_code":"BD",
    "gn:dem":8,
    "gn:feature_class":"P",
    "gn:feature_code":"PPL",
    "gn:name":"Th\u0101kukala",
    "gn:population":0,
    "gn:timezone":"Asia/Dhaka",
    "iso:country":"BD",
    "name:ben_x_preferred":[
        "Th\u0101kukala"
    ],
    "wof:name":"Thakukala",
    "wof:placetype":"locality"
},
  "geometry": {"coordinates":[91.96541000000001,21.52596],"type":"Point"}
}