{
  "type": "Feature",
  "properties": {
    "gn:admin1_code":"81",
    "gn:admin2_code":"3048",
    "gn:admin3_code":"304806.0",
    "gn:admin4_code":"30480634.0",
    "gn:asciiname":"Saserdighi",
    "gn:country_code":"BD",
    "gn:dem":12,
    "gn:feature_class":"P",
    "gn:feature_code":"PPL",
    "gn:name":"Saserdighi",
    "gn:population":0,
    "gn:timezone":"Asia/Dhaka",
    "iso:country":"BD",
    "name:und_x_variant":[
        "Saserdigi",
        "Saserdighi"
    ],
    "wof:name":"Saserdighi",
    "wof:placetype":"locality"
},
  "geometry": {"coordinates":[90.95036,24.18461],"type":"Point"}
}