{
  "type": "Feature",
  "properties": {
    "gn:admin1_code":"82",
    "gn:admin2_code":"4041",
    "gn:admin3_code":"404147.0",
    "gn:admin4_code":"40414753.0",
    "gn:asciiname":"Panchbaria",
    "gn:country_code":"BD",
    "gn:dem":13,
    "gn:feature_class":"P",
    "gn:feature_code":"PPL",
    "gn:name":"Panchb\u0101ria",
    "gn:population":0,
    "gn:timezone":"Asia/Dhaka",
    "iso:country":"BD",
    "wof:name":"Panchbaria",
    "wof:placetype":"locality"
},
  "geometry": {"coordinates":[89.24505000000001,23.23506],"type":"Point"}
}