{
  "type": "Feature",
  "properties": {
    "gn:admin1_code":"86",
    "gn:admin2_code":"6091.0",
    "gn:admin3_code":"609194.0",
    "gn:admin4_code":"60919447.0",
    "gn:asciiname":"Chargram",
    "gn:country_code":"BD",
    "gn:dem":22,
    "gn:feature_class":"P",
    "gn:feature_code":"PPL",
    "gn:name":"Chargr\u0101m",
    "gn:population":0,
    "gn:timezone":"Asia/Dhaka",
    "iso:country":"BD",
    "wof:name":"Chargram",
    "wof:placetype":"locality"
},
  "geometry": {"coordinates":[92.39634,24.98172000000001],"type":"Point"}
}