{
  "type": "Feature",
  "properties": {
    "gn:admin1_code":"83",
    "gn:admin2_code":"5010",
    "gn:admin3_code":"501021.0",
    "gn:admin4_code":"50102151.0",
    "gn:asciiname":"Kazipara",
    "gn:country_code":"BD",
    "gn:dem":23,
    "gn:feature_class":"P",
    "gn:feature_code":"PPL",
    "gn:name":"K\u0101zip\u0101ra",
    "gn:population":0,
    "gn:timezone":"Asia/Dhaka",
    "iso:country":"BD",
    "wof:name":"Kazipara",
    "wof:placetype":"locality"
},
  "geometry": {"coordinates":[89.41454,24.81612],"type":"Point"}
}