{
  "type": "Feature",
  "properties": {
    "gn:admin1_code":"83",
    "gn:admin2_code":"5064.0",
    "gn:admin3_code":"506460.0",
    "gn:admin4_code":"50646073.0",
    "gn:asciiname":"Atitha",
    "gn:country_code":"BD",
    "gn:dem":21,
    "gn:feature_class":"P",
    "gn:feature_code":"PPL",
    "gn:name":"Atitha",
    "gn:population":0,
    "gn:timezone":"Asia/Dhaka",
    "iso:country":"BD",
    "name:ben_x_preferred":[
        "Atitha"
    ],
    "wof:name":"Atitha",
    "wof:placetype":"locality"
},
  "geometry": {"coordinates":[88.9098,24.88639],"type":"Point"}
}