{
  "type": "Feature",
  "properties": {
    "gn:admin1_code":"H",
    "gn:admin2_code":"3061",
    "gn:admin3_code":"306122.0",
    "gn:admin4_code":"30612244.0",
    "gn:asciiname":"Mashakhali",
    "gn:country_code":"BD",
    "gn:dem":14,
    "gn:feature_class":"P",
    "gn:feature_code":"PPL",
    "gn:name":"Mash\u0101kh\u0101li",
    "gn:population":0,
    "gn:timezone":"Asia/Dhaka",
    "iso:country":"BD",
    "name:und_x_variant":[
        "Mash\u0101kh\u0101li",
        "Mas\u0101kh\u0101li"
    ],
    "wof:name":"Mashakhali",
    "wof:placetype":"locality"
},
  "geometry": {"coordinates":[90.52994,24.38924],"type":"Point"}
}