{
  "type": "Feature",
  "properties": {
    "gn:admin1_code":"83",
    "gn:admin2_code":"5064.0",
    "gn:admin3_code":"506475.0",
    "gn:admin4_code":"50647569.0",
    "gn:asciiname":"Fokanda",
    "gn:country_code":"BD",
    "gn:dem":44,
    "gn:feature_class":"P",
    "gn:feature_code":"PPL",
    "gn:name":"Fokanda",
    "gn:population":0,
    "gn:timezone":"Asia/Dhaka",
    "iso:country":"BD",
    "name:ben_x_preferred":[
        "Fokanda"
    ],
    "wof:name":"Fokanda",
    "wof:placetype":"locality"
},
  "geometry": {"coordinates":[88.60606999999997,25.15781],"type":"Point"}
}