{
  "type": "Feature",
  "properties": {
    "gn:admin1_code":"81",
    "gn:admin2_code":"3093.0",
    "gn:admin3_code":"309366.0",
    "gn:admin4_code":"30936607.0",
    "gn:asciiname":"Beltail",
    "gn:country_code":"BD",
    "gn:dem":17,
    "gn:feature_class":"P",
    "gn:feature_code":"PPL",
    "gn:name":"Beltail",
    "gn:population":0,
    "gn:timezone":"Asia/Dhaka",
    "iso:country":"BD",
    "wof:name":"Beltail",
    "wof:placetype":"locality"
},
  "geometry": {"coordinates":[90.16603000000001,24.12935],"type":"Point"}
}