{
  "type": "Feature",
  "properties": {
    "gn:admin1_code":"83",
    "gn:admin2_code":"5064.0",
    "gn:admin3_code":"506486.0",
    "gn:admin4_code":"50648671.0",
    "gn:asciiname":"Bahapur",
    "gn:country_code":"BD",
    "gn:dem":40,
    "gn:feature_class":"P",
    "gn:feature_code":"PPL",
    "gn:name":"B\u0101h\u0101pur",
    "gn:population":0,
    "gn:timezone":"Asia/Dhaka",
    "iso:country":"BD",
    "name:ben_x_preferred":[
        "B\u0101h\u0101pur"
    ],
    "wof:name":"Bahapur",
    "wof:placetype":"locality"
},
  "geometry": {"coordinates":[88.57185,25.08448],"type":"Point"}
}