{
  "type": "Feature",
  "properties": {
    "gn:admin1_code":"81",
    "gn:admin2_code":"3056.0",
    "gn:admin3_code":"305610.0",
    "gn:admin4_code":"30561085.0",
    "gn:asciiname":"Bangram",
    "gn:country_code":"BD",
    "gn:dem":15,
    "gn:feature_class":"P",
    "gn:feature_code":"PPL",
    "gn:name":"Bangr\u0101m",
    "gn:population":0,
    "gn:timezone":"Asia/Dhaka",
    "iso:country":"BD",
    "wof:name":"Bangram",
    "wof:placetype":"locality"
},
  "geometry": {"coordinates":[89.82868000000001,23.9007],"type":"Point"}
}