{
  "type": "Feature",
  "properties": {
    "gn:admin1_code":"81",
    "gn:admin2_code":"3068.0",
    "gn:admin3_code":"306876.0",
    "gn:admin4_code":"30687684.0",
    "gn:asciiname":"Bharatkandi",
    "gn:country_code":"BD",
    "gn:dem":10,
    "gn:feature_class":"P",
    "gn:feature_code":"PPL",
    "gn:name":"Bharatk\u0101ndi",
    "gn:population":0,
    "gn:timezone":"Asia/Dhaka",
    "iso:country":"BD",
    "wof:name":"Bharatkandi",
    "wof:placetype":"locality"
},
  "geometry": {"coordinates":[90.71641,23.94823],"type":"Point"}
}