{
  "type": "Feature",
  "properties": {
    "gn:admin1_code":"87",
    "gn:admin2_code":"5577.0",
    "gn:admin3_code":"557725.0",
    "gn:admin4_code":"55772587.0",
    "gn:asciiname":"Menagram",
    "gn:country_code":"BD",
    "gn:dem":59,
    "gn:feature_class":"P",
    "gn:feature_code":"PPL",
    "gn:name":"Menagr\u0101m",
    "gn:population":0,
    "gn:timezone":"Asia/Dhaka",
    "iso:country":"BD",
    "name:ben_x_preferred":[
        "Menagr\u0101m"
    ],
    "wof:name":"Menagram",
    "wof:placetype":"locality"
},
  "geometry": {"coordinates":[88.62786,26.12499],"type":"Point"}
}