{
  "type": "Feature",
  "properties": {
    "gn:admin1_code":"82",
    "gn:admin2_code":"4044.0",
    "gn:admin3_code":"404471.0",
    "gn:admin4_code":"40447183.0",
    "gn:asciiname":"Kankliadari",
    "gn:country_code":"BD",
    "gn:dem":14,
    "gn:feature_class":"P",
    "gn:feature_code":"PPL",
    "gn:name":"K\u0101nkli\u0101d\u0101ri",
    "gn:population":0,
    "gn:timezone":"Asia/Dhaka",
    "iso:country":"BD",
    "name:ben_x_preferred":[
        "K\u0101nkli\u0101d\u0101ri"
    ],
    "wof:name":"Kankliadari",
    "wof:placetype":"locality"
},
  "geometry": {"coordinates":[88.97929000000001,23.38459],"type":"Point"}
}