{
  "type": "Feature",
  "properties": {
    "gn:admin1_code":"85",
    "gn:admin2_code":"1042.0",
    "gn:admin3_code":"104273.0",
    "gn:admin4_code":"10427352.0",
    "gn:asciiname":"Debra",
    "gn:country_code":"BD",
    "gn:dem":8,
    "gn:feature_class":"P",
    "gn:feature_code":"PPL",
    "gn:name":"Debra",
    "gn:population":0,
    "gn:timezone":"Asia/Dhaka",
    "iso:country":"BD",
    "wof:name":"Debra",
    "wof:placetype":"locality"
},
  "geometry": {"coordinates":[90.21763,22.57434],"type":"Point"}
}