{
  "type": "Feature",
  "properties": {
    "gn:admin1_code":"81",
    "gn:admin2_code":"3026",
    "gn:admin3_code":"302618.0",
    "gn:admin4_code":"30261852.0",
    "gn:asciiname":"Malikanda",
    "gn:country_code":"BD",
    "gn:dem":15,
    "gn:feature_class":"P",
    "gn:feature_code":"PPL",
    "gn:name":"M\u0101lik\u0101nda",
    "gn:population":0,
    "gn:timezone":"Asia/Dhaka",
    "iso:country":"BD",
    "name:und_x_variant":[
        "M\u0101lik\u0101nda"
    ],
    "wof:name":"Malikanda",
    "wof:placetype":"locality"
},
  "geometry": {"coordinates":[90.14512999999999,23.58228],"type":"Point"}
}