{
  "type": "Feature",
  "properties": {
    "gn:admin1_code":"81",
    "gn:admin2_code":"3056",
    "gn:admin3_code":"305628.0",
    "gn:admin4_code":"30562843.0",
    "gn:asciiname":"Jalia",
    "gn:country_code":"BD",
    "gn:dem":1,
    "gn:feature_class":"P",
    "gn:feature_code":"PPL",
    "gn:name":"J\u0101lia",
    "gn:population":0,
    "gn:timezone":"Asia/Dhaka",
    "iso:country":"BD",
    "name:ceb_x_preferred":[
        "Jalia"
    ],
    "name:guj_x_preferred":[
        "\u0a9c\u0abe\u0ab3\u0ac0\u0aaf\u0abe"
    ],
    "name:hin_x_preferred":[
        "\u091c\u093e\u0932\u0940\u092f\u093e"
    ],
    "name:swe_x_preferred":[
        "Jalia"
    ],
    "name:urd_x_preferred":[
        "\u062c\u0644\u0627"
    ],
    "wof:name":"Jalia",
    "wof:placetype":"locality"
},
  "geometry": {"coordinates":[90.0012,23.68964],"type":"Point"}
}