{
  "type": "Feature",
  "properties": {
    "gn:admin1_code":"87",
    "gn:admin2_code":"5552",
    "gn:admin3_code":"555255.0",
    "gn:admin4_code":"55525500.0",
    "gn:asciiname":"Kharda Saptana",
    "gn:country_code":"BD",
    "gn:dem":35,
    "gn:feature_class":"P",
    "gn:feature_code":"PPL",
    "gn:name":"Kharda Saptana",
    "gn:population":0,
    "gn:timezone":"Asia/Dhaka",
    "iso:country":"BD",
    "name:ben_x_preferred":[
        "Kharda Saptana"
    ],
    "name:ben_x_variant":[
        "Khorda S\u0101ptana"
    ],
    "wof:name":"Kharda Saptana",
    "wof:placetype":"locality"
},
  "geometry": {"coordinates":[89.43786999999998,25.91494],"type":"Point"}
}