{
  "type": "Feature",
  "properties": {
    "gn:admin1_code":"83",
    "gn:admin2_code":"5070.0",
    "gn:admin3_code":"507066.0",
    "gn:admin4_code":"50706611.0",
    "gn:asciiname":"Jadupur",
    "gn:country_code":"BD",
    "gn:dem":29,
    "gn:feature_class":"P",
    "gn:feature_code":"PPL",
    "gn:name":"J\u0101dupur",
    "gn:population":0,
    "gn:timezone":"Asia/Dhaka",
    "iso:country":"BD",
    "name:ben_x_preferred":[
        "J\u0101dupur"
    ],
    "wof:name":"Jadupur",
    "wof:placetype":"locality"
},
  "geometry": {"coordinates":[88.28589000000002,24.62244],"type":"Point"}
}