{
  "type": "Feature",
  "properties": {
    "gn:admin1_code":"81",
    "gn:admin2_code":"3067.0",
    "gn:admin3_code":"306706.0",
    "gn:admin4_code":"30670663.0",
    "gn:asciiname":"Fular",
    "gn:country_code":"BD",
    "gn:dem":10,
    "gn:feature_class":"P",
    "gn:feature_code":"PPL",
    "gn:name":"Fular",
    "gn:population":0,
    "gn:timezone":"Asia/Dhaka",
    "iso:country":"BD",
    "wof:name":"Fular",
    "wof:placetype":"locality"
},
  "geometry": {"coordinates":[90.55,23.68333],"type":"Point"}
}