{
  "type": "Feature",
  "properties": {
    "gn:admin1_code":"83",
    "gn:admin2_code":"5064.0",
    "gn:admin3_code":"506486.0",
    "gn:admin4_code":"50648671.0",
    "gn:asciiname":"Unchadanga",
    "gn:country_code":"BD",
    "gn:dem":45,
    "gn:feature_class":"P",
    "gn:feature_code":"PPL",
    "gn:name":"Unch\u0101d\u0101nga",
    "gn:population":0,
    "gn:timezone":"Asia/Dhaka",
    "iso:country":"BD",
    "name:ben_x_preferred":[
        "Unch\u0101d\u0101nga"
    ],
    "wof:name":"Unchadanga",
    "wof:placetype":"locality"
},
  "geometry": {"coordinates":[88.59098,25.10966],"type":"Point"}
}