{
  "type": "Feature",
  "properties": {
    "gn:admin1_code":"83",
    "gn:admin2_code":"5069",
    "gn:admin3_code":"506963.0",
    "gn:admin4_code":"50696321.0",
    "gn:asciiname":"Sekhpara",
    "gn:country_code":"BD",
    "gn:dem":19,
    "gn:feature_class":"P",
    "gn:feature_code":"PPL",
    "gn:name":"Sekhp\u0101ra",
    "gn:population":0,
    "gn:timezone":"Asia/Dhaka",
    "iso:country":"BD",
    "name:ben_x_preferred":[
        "Sekhp\u0101ra"
    ],
    "wof:name":"Sekhpara",
    "wof:placetype":"locality"
},
  "geometry": {"coordinates":[88.9372,24.50746],"type":"Point"}
}