{
  "type": "Feature",
  "properties": {
    "gn:admin1_code":"84",
    "gn:admin2_code":"2051.0",
    "gn:admin3_code":"205143.0",
    "gn:admin4_code":"20514395.0",
    "gn:asciiname":"Gomatali",
    "gn:country_code":"BD",
    "gn:dem":10,
    "gn:feature_class":"P",
    "gn:feature_code":"PPL",
    "gn:name":"Gom\u0101tali",
    "gn:population":0,
    "gn:timezone":"Asia/Dhaka",
    "iso:country":"BD",
    "wof:name":"Gomatali",
    "wof:placetype":"locality"
},
  "geometry": {"coordinates":[90.95350000000001,22.99015],"type":"Point"}
}