{
  "type": "Feature",
  "properties": {
    "gn:admin1_code":"84",
    "gn:admin2_code":"2075.0",
    "gn:admin3_code":"207507.0",
    "gn:admin4_code":"20750704.0",
    "gn:asciiname":"Bhababhadri",
    "gn:country_code":"BD",
    "gn:dem":14,
    "gn:feature_class":"P",
    "gn:feature_code":"PPL",
    "gn:name":"Bhab\u0101bhadri",
    "gn:population":0,
    "gn:timezone":"Asia/Dhaka",
    "iso:country":"BD",
    "wof:name":"Bhababhadri",
    "wof:placetype":"locality"
},
  "geometry": {"coordinates":[90.99419,22.94378],"type":"Point"}
}