{
  "type": "Feature",
  "properties": {
    "gn:admin1_code":"85",
    "gn:admin2_code":"1004.0",
    "gn:admin3_code":"100447.0",
    "gn:admin4_code":"10044771.0",
    "gn:asciiname":"Machhua Khali",
    "gn:country_code":"BD",
    "gn:dem":13,
    "gn:feature_class":"P",
    "gn:feature_code":"PPL",
    "gn:name":"M\u0101chhua Kh\u0101li",
    "gn:population":0,
    "gn:timezone":"Asia/Dhaka",
    "iso:country":"BD",
    "name:ben_x_preferred":[
        "M\u0101chhua Kh\u0101li"
    ],
    "wof:name":"Machhua Khali",
    "wof:placetype":"locality"
},
  "geometry": {"coordinates":[90.13862,22.36417],"type":"Point"}
}