{
  "type": "Feature",
  "properties": {
    "gn:admin1_code":"81",
    "gn:admin2_code":"3026.0",
    "gn:admin3_code":"302662.0",
    "gn:admin4_code":"30266233.0",
    "gn:asciiname":"Bilchari",
    "gn:country_code":"BD",
    "gn:dem":10,
    "gn:feature_class":"P",
    "gn:feature_code":"PPL",
    "gn:name":"Bilchari",
    "gn:population":0,
    "gn:timezone":"Asia/Dhaka",
    "iso:country":"BD",
    "wof:name":"Bilchari",
    "wof:placetype":"locality"
},
  "geometry": {"coordinates":[90.06667,23.68333],"type":"Point"}
}