{
  "type": "Feature",
  "properties": {
    "gn:admin1_code":"84",
    "gn:admin2_code":"2013.0",
    "gn:admin3_code":"201376.0",
    "gn:admin4_code":"20137686.0",
    "gn:asciiname":"Bakra",
    "gn:country_code":"BD",
    "gn:dem":10,
    "gn:feature_class":"P",
    "gn:feature_code":"PPL",
    "gn:name":"B\u0101kra",
    "gn:population":0,
    "gn:timezone":"Asia/Dhaka",
    "iso:country":"BD",
    "name:und_x_variant":[
        "B\u0101kra Gonsaipur",
        "B\u0101kra"
    ],
    "wof:name":"Bakra",
    "wof:placetype":"locality"
},
  "geometry": {"coordinates":[90.72875999999999,23.28479],"type":"Point"}
}