{
  "type": "Feature",
  "properties": {
    "gn:admin1_code":"87",
    "gn:admin2_code":"5527",
    "gn:admin3_code":"552721.0",
    "gn:admin4_code":"55272140.0",
    "gn:asciiname":"Islampur",
    "gn:country_code":"BD",
    "gn:dem":48,
    "gn:feature_class":"P",
    "gn:feature_code":"PPL",
    "gn:name":"Isl\u0101mpur",
    "gn:population":0,
    "gn:timezone":"Asia/Dhaka",
    "iso:country":"BD",
    "name:ben_x_preferred":[
        "Isl\u0101mpur"
    ],
    "name:ben_x_variant":[
        "Ichhl\u0101mpur"
    ],
    "wof:name":"Islampur",
    "wof:placetype":"locality"
},
  "geometry": {"coordinates":[88.48329,25.84607],"type":"Point"}
}