{
  "type": "Feature",
  "properties": {
    "gn:admin1_code":"82",
    "gn:admin2_code":"4044.0",
    "gn:admin3_code":"404480.0",
    "gn:admin4_code":"40448000.0",
    "gn:asciiname":"Baliadangi",
    "gn:country_code":"BD",
    "gn:dem":16,
    "gn:feature_class":"P",
    "gn:feature_code":"PPL",
    "gn:name":"B\u0101li\u0101d\u0101ngi",
    "gn:population":0,
    "gn:timezone":"Asia/Dhaka",
    "iso:country":"BD",
    "name:ben_x_preferred":[
        "B\u0101li\u0101d\u0101ngi"
    ],
    "wof:name":"Baliadangi",
    "wof:placetype":"locality"
},
  "geometry": {"coordinates":[89.22875000000001,23.71118],"type":"Point"}
}