{
  "type": "Feature",
  "properties": {
    "gn:admin1_code":"84",
    "gn:admin2_code":"2012",
    "gn:admin3_code":"201204.0",
    "gn:admin4_code":"20120430.0",
    "gn:asciiname":"Nabipur",
    "gn:country_code":"BD",
    "gn:dem":12,
    "gn:feature_class":"P",
    "gn:feature_code":"PPL",
    "gn:name":"Nab\u012bpur",
    "gn:population":0,
    "gn:timezone":"Asia/Dhaka",
    "iso:country":"BD",
    "wof:name":"Nabipur",
    "wof:placetype":"locality"
},
  "geometry": {"coordinates":[90.81934,23.85322],"type":"Point"}
}