{
  "type": "Feature",
  "properties": {
    "gn:admin1_code":"82",
    "gn:admin2_code":"4041",
    "gn:admin3_code":"404123.0",
    "gn:admin4_code":"40412341.0",
    "gn:asciiname":"Ista",
    "gn:country_code":"BD",
    "gn:dem":13,
    "gn:feature_class":"P",
    "gn:feature_code":"PPL",
    "gn:name":"Ista",
    "gn:population":0,
    "gn:timezone":"Asia/Dhaka",
    "iso:country":"BD",
    "name:ceb_x_preferred":[
        "Ista"
    ],
    "wof:name":"Ista",
    "wof:placetype":"locality"
},
  "geometry": {"coordinates":[89.04959000000002,22.99613],"type":"Point"}
}