{
  "type": "Feature",
  "properties": {
    "gn:admin1_code":"84",
    "gn:admin2_code":"2022.0",
    "gn:admin3_code":"202224.0",
    "gn:admin4_code":"20222447.0",
    "gn:asciiname":"Jolapara",
    "gn:country_code":"BD",
    "gn:dem":11,
    "gn:feature_class":"P",
    "gn:feature_code":"PPL",
    "gn:name":"Jolap\u0101ra",
    "gn:population":0,
    "gn:timezone":"Asia/Dhaka",
    "iso:country":"BD",
    "name:ben_x_preferred":[
        "Jolap\u0101ra"
    ],
    "wof:name":"Jolapara",
    "wof:placetype":"locality"
},
  "geometry": {"coordinates":[92.01157000000001,21.42776],"type":"Point"}
}