{
  "type": "Feature",
  "properties": {
    "gn:admin1_code":"84",
    "gn:admin2_code":"2022.0",
    "gn:admin3_code":"202266.0",
    "gn:admin4_code":"20226657.0",
    "gn:asciiname":"Kaluiakhola",
    "gn:country_code":"BD",
    "gn:dem":15,
    "gn:feature_class":"P",
    "gn:feature_code":"PPL",
    "gn:name":"Kalui\u0101khola",
    "gn:population":0,
    "gn:timezone":"Asia/Dhaka",
    "iso:country":"BD",
    "name:ben_x_preferred":[
        "Kalui\u0101khola"
    ],
    "wof:name":"Kaluiakhola",
    "wof:placetype":"locality"
},
  "geometry": {"coordinates":[92.09554,21.34107],"type":"Point"}
}