{
  "type": "Feature",
  "properties": {
    "gn:admin1_code":"84",
    "gn:admin2_code":"2015.0",
    "gn:admin3_code":"201570.0",
    "gn:admin4_code":"20157086.0",
    "gn:asciiname":"Chinnga",
    "gn:country_code":"BD",
    "gn:dem":14,
    "gn:feature_class":"P",
    "gn:feature_code":"PPLL",
    "gn:name":"Chinnga",
    "gn:population":0,
    "gn:timezone":"Asia/Dhaka",
    "iso:country":"BD",
    "name:ben_x_preferred":[
        "Chinnga"
    ],
    "wof:name":"Chinnga",
    "wof:placetype":"locality"
},
  "geometry": {"coordinates":[92.03135,22.42985],"type":"Point"}
}