{
  "type": "Feature",
  "properties": {
    "gn:admin1_code":"H",
    "gn:admin2_code":"3061",
    "gn:admin3_code":"306122.0",
    "gn:admin4_code":"30612263.0",
    "gn:asciiname":"Raihar",
    "gn:country_code":"BD",
    "gn:dem":15,
    "gn:feature_class":"P",
    "gn:feature_code":"PPL",
    "gn:name":"R\u0101ihar",
    "gn:population":0,
    "gn:timezone":"Asia/Dhaka",
    "iso:country":"BD",
    "wof:name":"Raihar",
    "wof:placetype":"locality"
},
  "geometry": {"coordinates":[90.62594,24.42311],"type":"Point"}
}