{
  "type": "Feature",
  "properties": {
    "gn:admin1_code":"81",
    "gn:admin2_code":"3093.0",
    "gn:admin3_code":"309357.0",
    "gn:admin4_code":"30935719.0",
    "gn:asciiname":"Beribaid",
    "gn:country_code":"BD",
    "gn:dem":21,
    "gn:feature_class":"P",
    "gn:feature_code":"PPL",
    "gn:name":"Berib\u0101id",
    "gn:population":0,
    "gn:timezone":"Asia/Dhaka",
    "iso:country":"BD",
    "wof:name":"Beribaid",
    "wof:placetype":"locality"
},
  "geometry": {"coordinates":[90.1314,24.64163],"type":"Point"}
}