{
  "type": "Feature",
  "properties": {
    "gn:admin1_code":"85",
    "gn:admin2_code":"1078.0",
    "gn:admin3_code":"107866.0",
    "gn:admin4_code":"10786671.0",
    "gn:asciiname":"Paschim Sonatali",
    "gn:country_code":"BD",
    "gn:dem":9,
    "gn:feature_class":"P",
    "gn:feature_code":"PPL",
    "gn:name":"Paschim Son\u0101tali",
    "gn:population":0,
    "gn:timezone":"Asia/Dhaka",
    "iso:country":"BD",
    "name:ben_x_preferred":[
        "Paschim Son\u0101tali"
    ],
    "wof:name":"Paschim Sonatali",
    "wof:placetype":"locality"
},
  "geometry": {"coordinates":[90.16378,21.97134],"type":"Point"}
}