{
  "type": "Feature",
  "properties": {
    "gn:admin1_code":"87",
    "gn:admin2_code":"5549",
    "gn:admin3_code":"554994.0",
    "gn:admin4_code":"55499455.0",
    "gn:asciiname":"Nanda Nefra",
    "gn:country_code":"BD",
    "gn:dem":29,
    "gn:feature_class":"P",
    "gn:feature_code":"PPL",
    "gn:name":"Nanda Nefra",
    "gn:population":0,
    "gn:timezone":"Asia/Dhaka",
    "iso:country":"BD",
    "name:ben_x_preferred":[
        "Nanda Nefra"
    ],
    "name:ben_x_variant":[
        "Nefra Nanda"
    ],
    "name:und_x_variant":[
        "Nefra Nanda"
    ],
    "wof:name":"Nanda Nefra",
    "wof:placetype":"locality"
},
  "geometry": {"coordinates":[89.56814,25.64396],"type":"Point"}
}