{
  "type": "Feature",
  "properties": {
    "gn:admin1_code":"83",
    "gn:admin2_code":"5070.0",
    "gn:admin3_code":"507056.0",
    "gn:admin4_code":"50705676.0",
    "gn:asciiname":"Purba Lakshmanpur",
    "gn:country_code":"BD",
    "gn:dem":31,
    "gn:feature_class":"P",
    "gn:feature_code":"PPL",
    "gn:name":"Purba Lakshmanpur",
    "gn:population":0,
    "gn:timezone":"Asia/Dhaka",
    "iso:country":"BD",
    "name:ben_x_preferred":[
        "Purba Lakshmanpur"
    ],
    "wof:name":"Purba Lakshmanpur",
    "wof:placetype":"locality"
},
  "geometry": {"coordinates":[88.49561,24.71078],"type":"Point"}
}