{
  "type": "Feature",
  "properties": {
    "gn:admin1_code":"85",
    "gn:admin2_code":"1004.0",
    "gn:admin3_code":"100409.0",
    "gn:admin4_code":"10040939.0",
    "gn:asciiname":"Charpara",
    "gn:country_code":"BD",
    "gn:dem":7,
    "gn:feature_class":"P",
    "gn:feature_code":"PPL",
    "gn:name":"Charp\u0101ra",
    "gn:population":0,
    "gn:timezone":"Asia/Dhaka",
    "iso:country":"BD",
    "name:ben_x_preferred":[
        "Charp\u0101ra"
    ],
    "wof:name":"Charpara",
    "wof:placetype":"locality"
},
  "geometry": {"coordinates":[90.13,21.93975],"type":"Point"}
}