{
  "type": "Feature",
  "properties": {
    "gn:admin1_code":"82",
    "gn:asciiname":"Munshipur",
    "gn:country_code":"BD",
    "gn:dem":15,
    "gn:feature_class":"P",
    "gn:feature_code":"PPL",
    "gn:name":"Munshipur",
    "gn:population":0,
    "gn:timezone":"Asia/Dhaka",
    "iso:country":"BD",
    "name:ben_x_preferred":[
        "Munshipur"
    ],
    "wof:name":"Munshipur",
    "wof:placetype":"locality"
},
  "geometry": {"coordinates":[88.65123,23.57535],"type":"Point"}
}