{
  "type": "Feature",
  "properties": {
    "gn:admin1_code":"83",
    "gn:admin2_code":"5070.0",
    "gn:admin3_code":"507066.0",
    "gn:admin4_code":"50706683.0",
    "gn:asciiname":"Akandabari",
    "gn:country_code":"BD",
    "gn:dem":30,
    "gn:feature_class":"P",
    "gn:feature_code":"PPL",
    "gn:name":"Akandab\u0101ri",
    "gn:population":0,
    "gn:timezone":"Asia/Dhaka",
    "iso:country":"BD",
    "name:ben_x_preferred":[
        "Akandab\u0101ri"
    ],
    "wof:name":"Akandabari",
    "wof:placetype":"locality"
},
  "geometry": {"coordinates":[88.23034,24.59722],"type":"Point"}
}