{
  "type": "Feature",
  "properties": {
    "gn:admin1_code":"83",
    "gn:admin2_code":"5081",
    "gn:admin3_code":"508134.0",
    "gn:admin4_code":"50813476.0",
    "gn:asciiname":"Jaykrishnapur",
    "gn:country_code":"BD",
    "gn:dem":37,
    "gn:feature_class":"P",
    "gn:feature_code":"PPL",
    "gn:name":"Jaykrishnapur",
    "gn:population":0,
    "gn:timezone":"Asia/Dhaka",
    "iso:country":"BD",
    "name:ben_x_preferred":[
        "Jaykrishnapur"
    ],
    "wof:name":"Jaykrishnapur",
    "wof:placetype":"locality"
},
  "geometry": {"coordinates":[88.45256999999999,24.51976],"type":"Point"}
}