{
  "type": "Feature",
  "properties": {
    "gn:admin1_code":"83",
    "gn:admin2_code":"5064.0",
    "gn:admin3_code":"506428.0",
    "gn:admin4_code":"50642852.0",
    "gn:asciiname":"Poranagar",
    "gn:country_code":"BD",
    "gn:dem":23,
    "gn:feature_class":"P",
    "gn:feature_code":"PPL",
    "gn:name":"Poranagar",
    "gn:population":0,
    "gn:timezone":"Asia/Dhaka",
    "iso:country":"BD",
    "name:ben_x_preferred":[
        "Poranagar"
    ],
    "wof:name":"Poranagar",
    "wof:placetype":"locality"
},
  "geometry": {"coordinates":[88.92401,25.07578],"type":"Point"}
}