{
  "type": "Feature",
  "properties": {
    "gn:admin1_code":"82",
    "gn:admin2_code":"4047",
    "gn:admin3_code":"404764.0",
    "gn:admin4_code":"40476461.0",
    "gn:asciiname":"Kharia Dhemsakhali",
    "gn:country_code":"BD",
    "gn:dem":4,
    "gn:feature_class":"P",
    "gn:feature_code":"PPL",
    "gn:name":"Kharia Dhems\u0101kh\u0101li",
    "gn:population":0,
    "gn:timezone":"Asia/Dhaka",
    "iso:country":"BD",
    "wof:name":"Kharia Dhemsakhali",
    "wof:placetype":"locality"
},
  "geometry": {"coordinates":[89.33589000000001,22.53346],"type":"Point"}
}