{
  "type": "Feature",
  "properties": {
    "gn:admin1_code":"86",
    "gn:admin2_code":"6058.0",
    "gn:admin3_code":"605874.0",
    "gn:admin4_code":"60587414.0",
    "gn:asciiname":"Alawa",
    "gn:country_code":"BD",
    "gn:dem":19,
    "gn:feature_class":"P",
    "gn:feature_code":"PPL",
    "gn:name":"Al\u0101wa",
    "gn:population":0,
    "gn:timezone":"Asia/Dhaka",
    "iso:country":"BD",
    "name:und_x_variant":[
        "Alaha",
        "Al\u0101wa"
    ],
    "wof:name":"Alawa",
    "wof:placetype":"locality"
},
  "geometry": {"coordinates":[91.71021,24.48445],"type":"Point"}
}