{
  "type": "Feature",
  "properties": {
    "gn:admin1_code":"87",
    "gn:admin2_code":"5573",
    "gn:admin3_code":"557345.0",
    "gn:admin4_code":"55734534.0",
    "gn:asciiname":"Chandkhana",
    "gn:country_code":"BD",
    "gn:dem":40,
    "gn:feature_class":"P",
    "gn:feature_code":"PPL",
    "gn:name":"Ch\u0101ndkhana",
    "gn:population":0,
    "gn:timezone":"Asia/Dhaka",
    "iso:country":"BD",
    "name:ben_x_preferred":[
        "Ch\u0101ndkhana"
    ],
    "wof:name":"Chandkhana",
    "wof:placetype":"locality"
},
  "geometry": {"coordinates":[89.0401,25.84805],"type":"Point"}
}