{
  "type": "Feature",
  "properties": {
    "gn:admin1_code":"87",
    "gn:admin2_code":"5573.0",
    "gn:admin3_code":"557315.0",
    "gn:admin4_code":"55731547.0",
    "gn:asciiname":"Patripara",
    "gn:country_code":"BD",
    "gn:dem":62,
    "gn:feature_class":"P",
    "gn:feature_code":"PPL",
    "gn:name":"Patrip\u0101ra",
    "gn:population":0,
    "gn:timezone":"Asia/Dhaka",
    "iso:country":"BD",
    "name:ben_x_preferred":[
        "Patrip\u0101ra"
    ],
    "wof:name":"Patripara",
    "wof:placetype":"locality"
},
  "geometry": {"coordinates":[88.81811999999999,26.20331],"type":"Point"}
}