{
  "type": "Feature",
  "properties": {
    "gn:admin1_code":"87",
    "gn:admin2_code":"5585",
    "gn:admin3_code":"558576.0",
    "gn:admin4_code":"55857663.0",
    "gn:asciiname":"Asmatpur",
    "gn:country_code":"BD",
    "gn:dem":28,
    "gn:feature_class":"P",
    "gn:feature_code":"PPL",
    "gn:name":"Asmatpur",
    "gn:population":0,
    "gn:timezone":"Asia/Dhaka",
    "iso:country":"BD",
    "name:ben_x_preferred":[
        "Asmatpur"
    ],
    "wof:name":"Asmatpur",
    "wof:placetype":"locality"
},
  "geometry": {"coordinates":[89.37895,25.46021],"type":"Point"}
}