{
  "type": "Feature",
  "properties": {
    "gn:admin1_code":"87",
    "gn:admin2_code":"5527.0",
    "gn:admin3_code":"552764.0",
    "gn:admin4_code":"55276477.0",
    "gn:asciiname":"Sheikhpura",
    "gn:country_code":"BD",
    "gn:dem":39,
    "gn:feature_class":"P",
    "gn:feature_code":"PPL",
    "gn:name":"Sheikhpura",
    "gn:population":0,
    "gn:timezone":"Asia/Dhaka",
    "iso:country":"BD",
    "name:ara_x_preferred":[
        "\u0634\u064a\u062e \u0628\u0648\u0631\u0627"
    ],
    "name:ben_x_preferred":[
        "Sheikhpura"
    ],
    "name:ben_x_variant":[
        "\u09b6\u09c7\u0996\u09aa\u09c1\u09b0\u09be"
    ],
    "name:bih_x_preferred":[
        "\u0936\u0947\u0916\u092a\u0941\u0930\u093e"
    ],
    "name:bpy_x_preferred":[
        "\u09b6\u09c7\u0996\u09aa\u09c1\u09b0"
    ],
    "name:guj_x_preferred":[
        "\u0ab6\u0ac7\u0a96\u0aaa\u0ac1\u0ab0\u0abe"
    ],
    "name:hin_x_preferred":[
        "\u0936\u0947\u0916\u092a\u0941\u0930\u093e"
    ],
    "name:ita_x_preferred":[
        "Sheikhpura"
    ],
    "name:mar_x_preferred":[
        "\u0936\u0947\u0916\u092a\u0941\u0930\u093e"
    ],
    "name:mlg_x_preferred":[
        "Sheikhpura"
    ],
    "name:msa_x_preferred":[
        "Sheikhpura"
    ],
    "name:nep_x_preferred":[
        "\u0936\u0947\u0916\u092a\u0941\u0930\u093e"
    ],
    "name:ori_x_preferred":[
        "\u0b36\u0b47\u0b07\u0b16\u0b2a\u0b41\u0b30\u0b3e"
    ],
    "name:por_x_preferred":[
        "Sheikhpura"
    ],
    "name:rus_x_preferred":[
        "\u0428\u0435\u0439\u0445\u043f\u0443\u0440\u0430"
    ],
    "name:san_x_preferred":[
        "\u0936\u0947\u0916\u092a\u0941\u0930\u093e"
    ],
    "name:spa_x_preferred":[
        "Sheikhpura"
    ],
    "name:urd_x_preferred":[
        "\u0634\u06cc\u062e \u067e\u0648\u0631\u06c1"
    ],
    "name:vie_x_preferred":[
        "Sheikhpura"
    ],
    "name:zho_x_preferred":[
        "\u65af\u8d6b\u4f0a\u514b\u666e\u62c9"
    ],
    "wof:name":"Sheikhpura",
    "wof:placetype":"locality"
},
  "geometry": {"coordinates":[88.65176,25.62038],"type":"Point"}
}