{
  "type": "Feature",
  "properties": {
    "gn:admin1_code":"82",
    "gn:admin2_code":"4065.0",
    "gn:admin3_code":"406576.0",
    "gn:admin4_code":"40657633.0",
    "gn:asciiname":"Chalitatala",
    "gn:country_code":"BD",
    "gn:dem":16,
    "gn:feature_class":"P",
    "gn:feature_code":"PPL",
    "gn:name":"Ch\u0101lit\u0101t\u0101la",
    "gn:population":0,
    "gn:timezone":"Asia/Dhaka",
    "iso:country":"BD",
    "name:ben_x_preferred":[
        "Ch\u0101lit\u0101t\u0101la"
    ],
    "wof:name":"Chalitatala",
    "wof:placetype":"locality"
},
  "geometry": {"coordinates":[89.54912,23.22738],"type":"Point"}
}