{
  "type": "Feature",
  "properties": {
    "gn:admin1_code":"81",
    "gn:admin2_code":"3026",
    "gn:admin3_code":"302672.0",
    "gn:admin4_code":"30267294.0",
    "gn:asciiname":"Ichhar Kandi",
    "gn:country_code":"BD",
    "gn:dem":11,
    "gn:feature_class":"P",
    "gn:feature_code":"PPL",
    "gn:name":"Ichh\u0101r K\u0101ndi",
    "gn:population":0,
    "gn:timezone":"Asia/Dhaka",
    "iso:country":"BD",
    "name:und_x_variant":[
        "Kandi",
        "Ichh\u0101r K\u0101ndi"
    ],
    "wof:name":"Ichhar Kandi",
    "wof:placetype":"locality"
},
  "geometry": {"coordinates":[90.34574000000001,23.94292],"type":"Point"}
}