{
  "type": "Feature",
  "properties": {
    "gn:admin1_code":"85",
    "gn:admin2_code":"1042",
    "gn:admin3_code":"104240.0",
    "gn:admin4_code":"10424028.0",
    "gn:asciiname":"Ostakhan",
    "gn:country_code":"BD",
    "gn:dem":8,
    "gn:feature_class":"P",
    "gn:feature_code":"PPL",
    "gn:name":"Ost\u0101kh\u0101n",
    "gn:population":0,
    "gn:timezone":"Asia/Dhaka",
    "iso:country":"BD",
    "wof:name":"Ostakhan",
    "wof:placetype":"locality"
},
  "geometry": {"coordinates":[90.15722,22.64272],"type":"Point"}
}