{
  "type": "Feature",
  "properties": {
    "gn:admin1_code":"82",
    "gn:asciiname":"Char Faizuddin",
    "gn:country_code":"BD",
    "gn:dem":9,
    "gn:feature_class":"P",
    "gn:feature_code":"PPL",
    "gn:name":"Char Faizuddin",
    "gn:population":0,
    "gn:timezone":"Asia/Dhaka",
    "iso:country":"BD",
    "name:ben_x_preferred":[
        "Char Faizuddin"
    ],
    "name:und_x_variant":[
        "Char Faizaddi",
        "Char Jangalia"
    ],
    "wof:name":"Char Faizuddin",
    "wof:placetype":"locality"
},
  "geometry": {"coordinates":[90.98094,22.21275],"type":"Point"}
}