{
  "type": "Feature",
  "properties": {
    "gn:admin1_code":"87",
    "gn:admin2_code":"5527.0",
    "gn:admin3_code":"552730.0",
    "gn:admin4_code":"55273023.0",
    "gn:asciiname":"Phulpur",
    "gn:country_code":"BD",
    "gn:dem":37,
    "gn:feature_class":"P",
    "gn:feature_code":"PPL",
    "gn:name":"Phulpur",
    "gn:population":0,
    "gn:timezone":"Asia/Dhaka",
    "iso:country":"BD",
    "name:ben_x_preferred":[
        "Phulpur"
    ],
    "name:ita_x_preferred":[
        "Phulpur"
    ],
    "name:pol_x_preferred":[
        "Phulpur"
    ],
    "wof:name":"Phulpur",
    "wof:placetype":"locality"
},
  "geometry": {"coordinates":[88.80798,25.58261],"type":"Point"}
}