{
  "type": "Feature",
  "properties": {
    "gn:admin1_code":"81",
    "gn:admin2_code":"3056",
    "gn:admin3_code":"305646.0",
    "gn:admin4_code":"30564609.0",
    "gn:asciiname":"Madhya Barundi Chak",
    "gn:country_code":"BD",
    "gn:dem":12,
    "gn:feature_class":"P",
    "gn:feature_code":"PPL",
    "gn:name":"Madhya Barundi Chak",
    "gn:population":0,
    "gn:timezone":"Asia/Dhaka",
    "iso:country":"BD",
    "wof:name":"Madhya Barundi Chak",
    "wof:placetype":"locality"
},
  "geometry": {"coordinates":[90.09542,23.90044],"type":"Point"}
}