{
  "type": "Feature",
  "properties": {
    "gn:admin1_code":"84",
    "gn:admin2_code":"2013",
    "gn:admin3_code":"201345.0",
    "gn:admin4_code":"20134595.0",
    "gn:asciiname":"Sajanmagh",
    "gn:country_code":"BD",
    "gn:dem":10,
    "gn:feature_class":"P",
    "gn:feature_code":"PPL",
    "gn:name":"Sajanmagh",
    "gn:population":0,
    "gn:timezone":"Asia/Dhaka",
    "iso:country":"BD",
    "name:und_x_variant":[
        "Sachanmegh",
        "S\u0101janmegh",
        "Sajanmagh"
    ],
    "wof:name":"Sajanmagh",
    "wof:placetype":"locality"
},
  "geometry": {"coordinates":[90.80473000000001,23.19495],"type":"Point"}
}