{
  "type": "Feature",
  "properties": {
    "gn:admin1_code":"83",
    "gn:admin2_code":"5081.0",
    "gn:admin3_code":"508125.0",
    "gn:admin4_code":"50812587.0",
    "gn:asciiname":"Ghaipara",
    "gn:country_code":"BD",
    "gn:dem":19,
    "gn:feature_class":"P",
    "gn:feature_code":"PPL",
    "gn:name":"Gh\u0101ip\u0101ra",
    "gn:population":0,
    "gn:timezone":"Asia/Dhaka",
    "iso:country":"BD",
    "name:ben_x_preferred":[
        "Gh\u0101ip\u0101ra"
    ],
    "wof:name":"Ghaipara",
    "wof:placetype":"locality"
},
  "geometry": {"coordinates":[88.77925,24.34914],"type":"Point"}
}