{
  "type": "Feature",
  "properties": {
    "gn:admin1_code":"H",
    "gn:asciiname":"Pachabahara",
    "gn:country_code":"BD",
    "gn:dem":22,
    "gn:feature_class":"P",
    "gn:feature_code":"PPL",
    "gn:name":"Pach\u0101bahara",
    "gn:population":0,
    "gn:timezone":"Asia/Dhaka",
    "iso:country":"BD",
    "name:ben_x_preferred":[
        "Pach\u0101bahara"
    ],
    "wof:name":"Pachabahara",
    "wof:placetype":"locality"
},
  "geometry": {"coordinates":[89.73436,25.04536],"type":"Point"}
}