{
  "type": "Feature",
  "properties": {
    "gn:admin1_code":"83",
    "gn:admin2_code":"5069.0",
    "gn:admin3_code":"506991.0",
    "gn:admin4_code":"50699163.0",
    "gn:asciiname":"Bara Baraihati",
    "gn:country_code":"BD",
    "gn:dem":19,
    "gn:feature_class":"P",
    "gn:feature_code":"PPL",
    "gn:name":"Bara B\u0101raih\u0101ti",
    "gn:population":0,
    "gn:timezone":"Asia/Dhaka",
    "iso:country":"BD",
    "wof:name":"Bara Baraihati",
    "wof:placetype":"locality"
},
  "geometry": {"coordinates":[89.06028000000001,24.51559],"type":"Point"}
}