{
  "type": "Feature",
  "properties": {
    "gn:admin1_code":"84",
    "gn:admin2_code":"2015.0",
    "gn:admin3_code":"201504.0",
    "gn:admin4_code":"20150457.0",
    "gn:asciiname":"Paschim Baraia",
    "gn:country_code":"BD",
    "gn:dem":8,
    "gn:feature_class":"P",
    "gn:feature_code":"PPL",
    "gn:name":"Paschim B\u0101raia",
    "gn:population":0,
    "gn:timezone":"Asia/Dhaka",
    "iso:country":"BD",
    "name:ben_x_preferred":[
        "Paschim B\u0101raia"
    ],
    "wof:name":"Paschim Baraia",
    "wof:placetype":"locality"
},
  "geometry": {"coordinates":[91.84612,22.17661],"type":"Point"}
}