{
  "type": "Feature",
  "properties": {
    "gn:admin1_code":"82",
    "gn:admin2_code":"4050.0",
    "gn:admin3_code":"405039.0",
    "gn:admin4_code":"40503954.0",
    "gn:asciiname":"Test Damash",
    "gn:country_code":"BD",
    "gn:dem":20,
    "gn:feature_class":"P",
    "gn:feature_code":"PPL",
    "gn:name":"Test D\u0101mash",
    "gn:population":0,
    "gn:timezone":"Asia/Dhaka",
    "iso:country":"BD",
    "name:ben_x_preferred":[
        "Test D\u0101mash"
    ],
    "wof:name":"Test Damash",
    "wof:placetype":"locality"
},
  "geometry": {"coordinates":[88.87279000000002,24.07806],"type":"Point"}
}