{
  "type": "Feature",
  "properties": {
    "gn:admin1_code":"84",
    "gn:admin2_code":"2003.0",
    "gn:admin3_code":"200351.0",
    "gn:admin4_code":"20035163.0",
    "gn:asciiname":"Giaphrubara",
    "gn:country_code":"BD",
    "gn:dem":16,
    "gn:feature_class":"P",
    "gn:feature_code":"PPL",
    "gn:name":"Gi\u0101phrub\u0101ra",
    "gn:population":0,
    "gn:timezone":"Asia/Dhaka",
    "iso:country":"BD",
    "name:ben_x_preferred":[
        "Gi\u0101phrub\u0101ra"
    ],
    "wof:name":"Giaphrubara",
    "wof:placetype":"locality"
},
  "geometry": {"coordinates":[92.20989,21.79783],"type":"Point"}
}