{
  "type": "Feature",
  "properties": {
    "gn:admin1_code":"83",
    "gn:admin2_code":"5010",
    "gn:admin3_code":"501094.0",
    "gn:admin4_code":"50109447.0",
    "gn:asciiname":"Haludbari",
    "gn:country_code":"BD",
    "gn:dem":24,
    "gn:feature_class":"P",
    "gn:feature_code":"PPL",
    "gn:name":"Haludb\u0101ri",
    "gn:population":0,
    "gn:timezone":"Asia/Dhaka",
    "iso:country":"BD",
    "name:ben_x_preferred":[
        "Haludb\u0101ri"
    ],
    "wof:name":"Haludbari",
    "wof:placetype":"locality"
},
  "geometry": {"coordinates":[89.29066999999998,25.07484],"type":"Point"}
}