{
  "type": "Feature",
  "properties": {
    "gn:admin1_code":"82",
    "gn:admin2_code":"4044.0",
    "gn:admin3_code":"404471.0",
    "gn:admin4_code":"40447189.0",
    "gn:asciiname":"Hanifpur",
    "gn:country_code":"BD",
    "gn:dem":14,
    "gn:feature_class":"P",
    "gn:feature_code":"PPL",
    "gn:name":"H\u0101nifpur",
    "gn:population":0,
    "gn:timezone":"Asia/Dhaka",
    "iso:country":"BD",
    "name:ben_x_preferred":[
        "H\u0101nifpur"
    ],
    "wof:name":"Hanifpur",
    "wof:placetype":"locality"
},
  "geometry": {"coordinates":[88.79284,23.35633],"type":"Point"}
}