{
  "type": "Feature",
  "properties": {
    "gn:admin1_code":"83",
    "gn:admin2_code":"5081.0",
    "gn:admin3_code":"508153.0",
    "gn:admin4_code":"50815381.0",
    "gn:asciiname":"Pariladanga",
    "gn:country_code":"BD",
    "gn:dem":20,
    "gn:feature_class":"P",
    "gn:feature_code":"PPL",
    "gn:name":"P\u0101ril\u0101d\u0101nga",
    "gn:population":0,
    "gn:timezone":"Asia/Dhaka",
    "iso:country":"BD",
    "name:ben_x_preferred":[
        "P\u0101ril\u0101d\u0101nga"
    ],
    "wof:name":"Pariladanga",
    "wof:placetype":"locality"
},
  "geometry": {"coordinates":[88.62994999999999,24.61538],"type":"Point"}
}