{
  "type": "Feature",
  "properties": {
    "gn:admin1_code":"81",
    "gn:admin2_code":"3093.0",
    "gn:admin3_code":"309385.0",
    "gn:admin4_code":"30938567.0",
    "gn:asciiname":"Chakchakia Sripur",
    "gn:country_code":"BD",
    "gn:dem":21,
    "gn:feature_class":"P",
    "gn:feature_code":"PPL",
    "gn:name":"Chakchakia Sripur",
    "gn:population":0,
    "gn:timezone":"Asia/Dhaka",
    "iso:country":"BD",
    "wof:name":"Chakchakia Sripur",
    "wof:placetype":"locality"
},
  "geometry": {"coordinates":[90.16746000000001,24.41531],"type":"Point"}
}