{
  "type": "Feature",
  "properties": {
    "gn:admin1_code":"82",
    "gn:admin2_code":"4018.0",
    "gn:admin3_code":"401855.0",
    "gn:admin4_code":"40185538.0",
    "gn:asciiname":"Chakla",
    "gn:country_code":"BD",
    "gn:dem":13,
    "gn:feature_class":"P",
    "gn:feature_code":"PPL",
    "gn:name":"Ch\u0101kla",
    "gn:population":0,
    "gn:timezone":"Asia/Dhaka",
    "iso:country":"BD",
    "name:ben_x_preferred":[
        "Ch\u0101kla"
    ],
    "name:hin_x_preferred":[
        "\u091a\u0915\u0932\u093e"
    ],
    "wof:name":"Chakla",
    "wof:placetype":"locality"
},
  "geometry": {"coordinates":[88.91812,23.41248],"type":"Point"}
}