{
  "type": "Feature",
  "properties": {
    "gn:admin1_code":"83",
    "gn:admin2_code":"5070.0",
    "gn:admin3_code":"507088.0",
    "gn:admin4_code":"50708841.0",
    "gn:asciiname":"Raghabpur",
    "gn:country_code":"BD",
    "gn:dem":28,
    "gn:feature_class":"P",
    "gn:feature_code":"PPL",
    "gn:name":"Raghabpur",
    "gn:population":0,
    "gn:timezone":"Asia/Dhaka",
    "iso:country":"BD",
    "name:ben_x_preferred":[
        "Raghabpur"
    ],
    "wof:name":"Raghabpur",
    "wof:placetype":"locality"
},
  "geometry": {"coordinates":[88.20448,24.71798],"type":"Point"}
}