{
  "type": "Feature",
  "properties": {
    "gn:admin1_code":"82",
    "gn:admin2_code":"4041.0",
    "gn:admin3_code":"404147.0",
    "gn:admin4_code":"40414711.0",
    "gn:asciiname":"Gadgachhi",
    "gn:country_code":"BD",
    "gn:dem":9,
    "gn:feature_class":"P",
    "gn:feature_code":"PPL",
    "gn:name":"G\u0101dg\u0101chhi",
    "gn:population":0,
    "gn:timezone":"Asia/Dhaka",
    "iso:country":"BD",
    "name:ben_x_preferred":[
        "G\u0101dg\u0101chhi"
    ],
    "wof:name":"Gadgachhi",
    "wof:placetype":"locality"
},
  "geometry": {"coordinates":[89.34610000000001,23.10686],"type":"Point"}
}