{
  "type": "Feature",
  "properties": {
    "gn:admin1_code":"81",
    "gn:admin2_code":"3093.0",
    "gn:admin3_code":"309385.0",
    "gn:admin4_code":"30938527.0",
    "gn:asciiname":"Chhota Mausa",
    "gn:country_code":"BD",
    "gn:dem":22,
    "gn:feature_class":"P",
    "gn:feature_code":"PPL",
    "gn:name":"Chhota Mausa",
    "gn:population":0,
    "gn:timezone":"Asia/Dhaka",
    "iso:country":"BD",
    "wof:name":"Chhota Mausa",
    "wof:placetype":"locality"
},
  "geometry": {"coordinates":[90.14547,24.30392],"type":"Point"}
}