{
  "type": "Feature",
  "properties": {
    "gn:admin1_code":"85",
    "gn:admin2_code":"1078.0",
    "gn:admin3_code":"107852.0",
    "gn:admin4_code":"10785242.0",
    "gn:asciiname":"Arejbagi",
    "gn:country_code":"BD",
    "gn:dem":8,
    "gn:feature_class":"P",
    "gn:feature_code":"PPL",
    "gn:name":"Arejbagi",
    "gn:population":0,
    "gn:timezone":"Asia/Dhaka",
    "iso:country":"BD",
    "name:ben_x_preferred":[
        "Arejbagi"
    ],
    "wof:name":"Arejbagi",
    "wof:placetype":"locality"
},
  "geometry": {"coordinates":[90.51091,22.30753],"type":"Point"}
}