{
  "type": "Feature",
  "properties": {
    "gn:admin1_code":"81",
    "gn:admin2_code":"3093",
    "gn:admin3_code":"309357.0",
    "gn:admin4_code":"30935719.0",
    "gn:asciiname":"Radhanagar",
    "gn:country_code":"BD",
    "gn:dem":19,
    "gn:feature_class":"P",
    "gn:feature_code":"PPL",
    "gn:name":"R\u0101dh\u0101nagar",
    "gn:population":0,
    "gn:timezone":"Asia/Dhaka",
    "iso:country":"BD",
    "wof:name":"Radhanagar",
    "wof:placetype":"locality"
},
  "geometry": {"coordinates":[90.03551999999998,24.64874],"type":"Point"}
}