{
  "type": "Feature",
  "properties": {
    "gn:admin1_code":"82",
    "gn:admin2_code":"4041",
    "gn:admin3_code":"404111.0",
    "gn:admin4_code":"40411143.0",
    "gn:asciiname":"Swarupdaha",
    "gn:country_code":"BD",
    "gn:dem":12,
    "gn:feature_class":"P",
    "gn:feature_code":"PPL",
    "gn:name":"Swarupdaha",
    "gn:population":0,
    "gn:timezone":"Asia/Dhaka",
    "iso:country":"BD",
    "wof:name":"Swarupdaha",
    "wof:placetype":"locality"
},
  "geometry": {"coordinates":[89.00497,23.24609],"type":"Point"}
}