{
  "type": "Feature",
  "properties": {
    "gn:admin1_code":"85",
    "gn:admin2_code":"1078.0",
    "gn:admin3_code":"107857.0",
    "gn:admin4_code":"10785739.0",
    "gn:asciiname":"Char Agasti",
    "gn:country_code":"BD",
    "gn:dem":5,
    "gn:feature_class":"P",
    "gn:feature_code":"PPL",
    "gn:name":"Char Agasti",
    "gn:population":0,
    "gn:timezone":"Asia/Dhaka",
    "iso:country":"BD",
    "name:ben_x_preferred":[
        "Char Agasti"
    ],
    "name:und_x_variant":[
        "Burirchar"
    ],
    "wof:name":"Char Agasti",
    "wof:placetype":"locality"
},
  "geometry": {"coordinates":[90.50870999999999,21.99952],"type":"Point"}
}