{
  "type": "Feature",
  "properties": {
    "gn:admin1_code":"84",
    "gn:admin2_code":"2015.0",
    "gn:admin3_code":"201561.0",
    "gn:admin4_code":"20156167.0",
    "gn:asciiname":"Chhatarpetua",
    "gn:country_code":"BD",
    "gn:dem":8,
    "gn:feature_class":"P",
    "gn:feature_code":"PPL",
    "gn:name":"Chhatarpetua",
    "gn:population":0,
    "gn:timezone":"Asia/Dhaka",
    "iso:country":"BD",
    "name:ben_x_preferred":[
        "Chhatarpetua"
    ],
    "name:und_x_variant":[
        "Chhattarpetua"
    ],
    "wof:name":"Chhatarpetua",
    "wof:placetype":"locality"
},
  "geometry": {"coordinates":[92.00427000000001,22.33899],"type":"Point"}
}