{
  "type": "Feature",
  "properties": {
    "gn:admin1_code":"85",
    "gn:admin2_code":"1042",
    "gn:admin3_code":"104240.0",
    "gn:admin4_code":"10424076.0",
    "gn:asciiname":"Kafurkati",
    "gn:country_code":"BD",
    "gn:dem":13,
    "gn:feature_class":"P",
    "gn:feature_code":"PPL",
    "gn:name":"K\u0101furk\u0101ti",
    "gn:population":0,
    "gn:timezone":"Asia/Dhaka",
    "iso:country":"BD",
    "name:und_x_variant":[
        "K\u0101furk\u0101ti"
    ],
    "wof:name":"Kafurkati",
    "wof:placetype":"locality"
},
  "geometry": {"coordinates":[90.17834000000001,22.73095],"type":"Point"}
}