{
  "type": "Feature",
  "properties": {
    "gn:admin1_code":"81",
    "gn:admin2_code":"3048.0",
    "gn:admin3_code":"304806.0",
    "gn:admin4_code":"30480643.0",
    "gn:asciiname":"Chiniar Char",
    "gn:country_code":"BD",
    "gn:dem":13,
    "gn:feature_class":"P",
    "gn:feature_code":"PPL",
    "gn:name":"Chini\u0101r Char",
    "gn:population":0,
    "gn:timezone":"Asia/Dhaka",
    "iso:country":"BD",
    "wof:name":"Chiniar Char",
    "wof:placetype":"locality"
},
  "geometry": {"coordinates":[90.93127,24.18034],"type":"Point"}
}