{
  "type": "Feature",
  "properties": {
    "gn:admin1_code":"83",
    "gn:admin2_code":"5038",
    "gn:admin3_code":"503813.0",
    "gn:admin4_code":"50381363.0",
    "gn:asciiname":"Makimpur",
    "gn:country_code":"BD",
    "gn:dem":23,
    "gn:feature_class":"P",
    "gn:feature_code":"PPL",
    "gn:name":"Makimpur",
    "gn:population":0,
    "gn:timezone":"Asia/Dhaka",
    "iso:country":"BD",
    "wof:name":"Makimpur",
    "wof:placetype":"locality"
},
  "geometry": {"coordinates":[89.04411999999998,24.97285],"type":"Point"}
}