{
  "type": "Feature",
  "properties": {
    "gn:admin1_code":"81",
    "gn:admin2_code":"3059",
    "gn:admin3_code":"305994.0",
    "gn:admin4_code":"30599494.0",
    "gn:asciiname":"Sonarang",
    "gn:country_code":"BD",
    "gn:dem":9,
    "gn:feature_class":"P",
    "gn:feature_code":"PPL",
    "gn:name":"Son\u0101rang",
    "gn:population":0,
    "gn:timezone":"Asia/Dhaka",
    "iso:country":"BD",
    "wof:name":"Sonarang",
    "wof:placetype":"locality"
},
  "geometry": {"coordinates":[90.46638,23.52426],"type":"Point"}
}