{
  "type": "Feature",
  "properties": {
    "gn:admin1_code":"85",
    "gn:admin2_code":"1078.0",
    "gn:admin3_code":"107852.0",
    "gn:admin4_code":"10785221.0",
    "gn:asciiname":"Baharampur",
    "gn:country_code":"BD",
    "gn:dem":7,
    "gn:feature_class":"P",
    "gn:feature_code":"PPL",
    "gn:name":"B\u0101h\u0101r\u0101mpur",
    "gn:population":0,
    "gn:timezone":"Asia/Dhaka",
    "iso:country":"BD",
    "name:ben_x_preferred":[
        "B\u0101h\u0101r\u0101mpur"
    ],
    "wof:name":"Baharampur",
    "wof:placetype":"locality"
},
  "geometry": {"coordinates":[90.57572999999999,22.351],"type":"Point"}
}