{
  "type": "Feature",
  "properties": {
    "gn:admin1_code":"85",
    "gn:admin2_code":"1078.0",
    "gn:admin3_code":"107852.0",
    "gn:admin4_code":"10785221.0",
    "gn:asciiname":"Baharampur",
    "gn:country_code":"BD",
    "gn:dem":7,
    "gn:feature_class":"P",
    "gn:feature_code":"PPL",
    "gn:name":"B\u0101h\u0101r\u0101mpur",
    "gn:population":0,
    "gn:timezone":"Asia/Dhaka",
    "iso:country":"BD",
    "name:ben_x_preferred":[
        "B\u0101h\u0101r\u0101mpur"
    ],
    "name:ben_x_variant":[
        "\u09ac\u09b9\u09b0\u09ae\u09aa\u09c1\u09b0"
    ],
    "name:bih_x_preferred":[
        "\u092c\u0939\u0930\u093e\u092e\u092a\u0941\u0930"
    ],
    "name:bpy_x_preferred":[
        "\u09ac\u09be\u09b9\u09be\u09b0\u09be\u09ae\u09aa\u09c1\u09b0"
    ],
    "name:cat_x_preferred":[
        "Baharampur"
    ],
    "name:ceb_x_preferred":[
        "Baharampur"
    ],
    "name:epo_x_preferred":[
        "Baharampuro"
    ],
    "name:fas_x_preferred":[
        "\u0628\u0647\u0631\u0627\u0645\u200c\u067e\u0648\u0631"
    ],
    "name:fra_x_preferred":[
        "Baharampur"
    ],
    "name:guj_x_preferred":[
        "\u0aac\u0ab9\u0ab0\u0abe\u0aae\u0aaa\u0ac1\u0ab0"
    ],
    "name:ita_x_preferred":[
        "Baharampur"
    ],
    "name:mar_x_preferred":[
        "\u092c\u0939\u0930\u093e\u092e\u092a\u0942\u0930"
    ],
    "name:mlg_x_preferred":[
        "Baharampur"
    ],
    "name:msa_x_preferred":[
        "Baharampur"
    ],
    "name:new_x_preferred":[
        "\u092c\u0939\u0930\u092e\u092a\u0941\u0930"
    ],
    "name:ori_x_preferred":[
        "\u0b2c\u0b39\u0b30\u0b2e\u0b4d\u200c\u0b2a\u0b41\u0b30\u0b4d"
    ],
    "name:pam_x_preferred":[
        "Baharampur"
    ],
    "name:pol_x_preferred":[
        "Baharampur"
    ],
    "name:rus_x_preferred":[
        "\u0411\u0430\u0445\u0430\u0440\u0430\u043c\u043f\u0443\u0440"
    ],
    "name:san_x_preferred":[
        "\u092c\u0939\u0930\u093e\u092e\u092a\u0941\u0930"
    ],
    "name:spa_x_preferred":[
        "Baharampur"
    ],
    "name:swe_x_preferred":[
        "Baharampur"
    ],
    "name:tam_x_preferred":[
        "\u0baa\u0b95\u0bb0\u0bae\u0bcd\u0baa\u0bc2\u0bb0\u0bcd"
    ],
    "name:ukr_x_preferred":[
        "\u0411\u0430\u0445\u0430\u0440\u0430\u043c\u043f\u0443\u0440"
    ],
    "name:urd_x_preferred":[
        "\u0628\u06c1\u0631\u0627\u0645 \u067e\u0648\u0631"
    ],
    "name:vie_x_preferred":[
        "Baharampur"
    ],
    "name:war_x_preferred":[
        "Baharampur"
    ],
    "name:zho_x_preferred":[
        "\u5df4\u54c8\u62c9\u59c6\u666e\u5c14"
    ],
    "wof:name":"Baharampur",
    "wof:placetype":"locality"
},
  "geometry": {"coordinates":[90.57572999999999,22.351],"type":"Point"}
}