{
  "type": "Feature",
  "properties": {
    "gn:admin1_code":"83",
    "gn:admin2_code":"5038.0",
    "gn:admin3_code":"503874.0",
    "gn:admin4_code":"50387473.0",
    "gn:asciiname":"Pukurpar",
    "gn:country_code":"BD",
    "gn:dem":26,
    "gn:feature_class":"P",
    "gn:feature_code":"PPL",
    "gn:name":"Pukurp\u0101r",
    "gn:population":0,
    "gn:timezone":"Asia/Dhaka",
    "iso:country":"BD",
    "name:ben_x_preferred":[
        "Pukurp\u0101r"
    ],
    "wof:name":"Pukurpar",
    "wof:placetype":"locality"
},
  "geometry": {"coordinates":[89.1161,25.19145],"type":"Point"}
}