{
  "type": "Feature",
  "properties": {
    "gn:admin1_code":"82",
    "gn:admin2_code":"4044.0",
    "gn:admin3_code":"404442.0",
    "gn:admin4_code":"40444240.0",
    "gn:asciiname":"Paspatila",
    "gn:country_code":"BD",
    "gn:dem":18,
    "gn:feature_class":"P",
    "gn:feature_code":"PPL",
    "gn:name":"P\u0101spatila",
    "gn:population":0,
    "gn:timezone":"Asia/Dhaka",
    "iso:country":"BD",
    "name:ben_x_preferred":[
        "P\u0101spatila"
    ],
    "wof:name":"Paspatila",
    "wof:placetype":"locality"
},
  "geometry": {"coordinates":[89.01772,23.39076],"type":"Point"}
}