{
  "type": "Feature",
  "properties": {
    "gn:admin1_code":"87",
    "gn:admin2_code":"5577.0",
    "gn:admin3_code":"557773.0",
    "gn:admin4_code":"55777371.0",
    "gn:asciiname":"Sarkarpara",
    "gn:country_code":"BD",
    "gn:dem":82,
    "gn:feature_class":"P",
    "gn:feature_code":"PPL",
    "gn:name":"Sark\u0101rp\u0101ra",
    "gn:population":0,
    "gn:timezone":"Asia/Dhaka",
    "iso:country":"BD",
    "name:ben_x_preferred":[
        "Sark\u0101rp\u0101ra"
    ],
    "wof:name":"Sarkarpara",
    "wof:placetype":"locality"
},
  "geometry": {"coordinates":[88.56073000000001,26.35555],"type":"Point"}
}