{
  "type": "Feature",
  "properties": {
    "gn:admin1_code":"87",
    "gn:admin2_code":"5585.0",
    "gn:admin3_code":"558558.0",
    "gn:admin4_code":"55855811.0",
    "gn:asciiname":"Barabala",
    "gn:country_code":"BD",
    "gn:dem":31,
    "gn:feature_class":"P",
    "gn:feature_code":"PPL",
    "gn:name":"Bar\u0101b\u0101la",
    "gn:population":0,
    "gn:timezone":"Asia/Dhaka",
    "iso:country":"BD",
    "wof:name":"Barabala",
    "wof:placetype":"locality"
},
  "geometry": {"coordinates":[89.13333,25.55],"type":"Point"}
}