{
  "type": "Feature",
  "properties": {
    "iso:country":"BD",
    "name:ben_x_preferred":[
        "Jaldanp\u0101ra"
    ],
    "qs:gn_country":"BD",
    "qs:gn_fcode":"PPL",
    "qs:gn_pop":0,
    "qs:name":"Jaldapara",
    "qs:name_adm0":"India",
    "qs:name_adm1":"West Bengal",
    "qs:photos":60,
    "qs:photos_1k":12,
    "qs:photos_9k":1,
    "qs:photos_9r":2,
    "qs:photos_all":60,
    "qs:photos_sr":2,
    "qs:placetype":"Town",
    "qs:pop_sr":"0",
    "qs:woe_adm0":23424848,
    "wof:name":"Jaldapara",
    "wof:placetype":"locality"
},
  "geometry": {"coordinates":[88.87936000000001,26.17079],"type":"Point"}
}