{
  "type": "Feature",
  "properties": {
    "gn:admin1_code":"84",
    "gn:admin2_code":"2022.0",
    "gn:admin3_code":"202224.0",
    "gn:admin4_code":"20222483.0",
    "gn:asciiname":"Kaharghona",
    "gn:country_code":"BD",
    "gn:dem":4,
    "gn:feature_class":"P",
    "gn:feature_code":"PPL",
    "gn:name":"Kah\u0101rghona",
    "gn:population":0,
    "gn:timezone":"Asia/Dhaka",
    "iso:country":"BD",
    "name:ben_x_preferred":[
        "Kah\u0101rghona"
    ],
    "wof:name":"Kaharghona",
    "wof:placetype":"locality"
},
  "geometry": {"coordinates":[92.03391000000001,21.58082000000001],"type":"Point"}
}