{
  "type": "Feature",
  "properties": {
    "gn:admin1_code":"87",
    "gn:admin2_code":"5573.0",
    "gn:admin3_code":"557336.0",
    "gn:admin4_code":"55733680.0",
    "gn:asciiname":"Pathanpara",
    "gn:country_code":"BD",
    "gn:dem":50,
    "gn:feature_class":"P",
    "gn:feature_code":"PPL",
    "gn:name":"P\u0101th\u0101np\u0101ra",
    "gn:population":0,
    "gn:timezone":"Asia/Dhaka",
    "iso:country":"BD",
    "name:ben_x_preferred":[
        "P\u0101th\u0101np\u0101ra"
    ],
    "wof:name":"Pathanpara",
    "wof:placetype":"locality"
},
  "geometry": {"coordinates":[88.92657,26.01047],"type":"Point"}
}