{
  "type": "Feature",
  "properties": {
    "gn:admin1_code":"H",
    "gn:admin2_code":"3061",
    "gn:admin3_code":"306181.0",
    "gn:admin4_code":"30618113.0",
    "gn:asciiname":"Nalchapra",
    "gn:country_code":"BD",
    "gn:dem":14,
    "gn:feature_class":"P",
    "gn:feature_code":"PPL",
    "gn:name":"Nalch\u0101pra",
    "gn:population":0,
    "gn:timezone":"Asia/Dhaka",
    "iso:country":"BD",
    "wof:name":"Nalchapra",
    "wof:placetype":"locality"
},
  "geometry": {"coordinates":[90.46714,24.91703],"type":"Point"}
}