{
  "type": "Feature",
  "properties": {
    "gn:admin1_code":"87",
    "gn:admin2_code":"5577",
    "gn:admin3_code":"557725.0",
    "gn:admin4_code":"55772551.0",
    "gn:asciiname":"Shikarpur",
    "gn:country_code":"BD",
    "gn:dem":73,
    "gn:feature_class":"P",
    "gn:feature_code":"PPL",
    "gn:name":"Shik\u0101rpur",
    "gn:population":0,
    "gn:timezone":"Asia/Dhaka",
    "iso:country":"BD",
    "name:ben_x_preferred":[
        "Shik\u0101rpur"
    ],
    "name:ceb_x_preferred":[
        "Shikarpur"
    ],
    "name:pol_x_preferred":[
        "Shikarpur"
    ],
    "name:pus_x_preferred":[
        "\u0634\u06a9\u0627\u0631\u067e\u0648\u0631"
    ],
    "name:swe_x_preferred":[
        "Shikarpur"
    ],
    "name:urd_x_preferred":[
        "\u0634\u06a9\u0627\u0631\u067e\u0648\u0631"
    ],
    "name:vie_x_preferred":[
        "Shikarpur"
    ],
    "wof:name":"Shikarpur",
    "wof:placetype":"locality"
},
  "geometry": {"coordinates":[88.48430999999999,26.25213],"type":"Point"}
}