{
  "type": "Feature",
  "properties": {
    "gn:admin1_code":"83",
    "gn:asciiname":"Beurgram",
    "gn:country_code":"BD",
    "gn:dem":26,
    "gn:feature_class":"P",
    "gn:feature_code":"PPL",
    "gn:name":"Beurgram",
    "gn:population":0,
    "gn:timezone":"Asia/Dhaka",
    "iso:country":"BD",
    "name:ben_x_preferred":[
        "Beurgram"
    ],
    "wof:name":"Beurgram",
    "wof:placetype":"locality"
},
  "geometry": {"coordinates":[89.25135999999998,25.11205],"type":"Point"}
}