{
  "type": "Feature",
  "properties": {
    "gn:admin1_code":"81",
    "gn:admin2_code":"3086",
    "gn:admin3_code":"308669.0",
    "gn:admin4_code":"30866995.0",
    "gn:asciiname":"Sundisar",
    "gn:country_code":"BD",
    "gn:dem":8,
    "gn:feature_class":"P",
    "gn:feature_code":"PPL",
    "gn:name":"Sundis\u0101r",
    "gn:population":0,
    "gn:timezone":"Asia/Dhaka",
    "iso:country":"BD",
    "wof:name":"Sundisar",
    "wof:placetype":"locality"
},
  "geometry": {"coordinates":[90.32329,23.22716],"type":"Point"}
}