{
  "type": "Feature",
  "properties": {
    "gn:admin1_code":"83",
    "gn:admin2_code":"5010.0",
    "gn:admin3_code":"501021.0",
    "gn:admin4_code":"50102112.0",
    "gn:asciiname":"Ashekpur",
    "gn:country_code":"BD",
    "gn:dem":22,
    "gn:feature_class":"P",
    "gn:feature_code":"PPL",
    "gn:name":"Ashekpur",
    "gn:population":0,
    "gn:timezone":"Asia/Dhaka",
    "iso:country":"BD",
    "name:und_x_variant":[
        "Asekpur",
        "Ashekpur"
    ],
    "wof:name":"Ashekpur",
    "wof:placetype":"locality"
},
  "geometry": {"coordinates":[89.35472,24.79656],"type":"Point"}
}