{
  "type": "Feature",
  "properties": {
    "gn:admin1_code":"83",
    "gn:admin2_code":"5064.0",
    "gn:admin3_code":"506406.0",
    "gn:admin4_code":"50640663.0",
    "gn:asciiname":"Bhandarpur",
    "gn:country_code":"BD",
    "gn:dem":23,
    "gn:feature_class":"P",
    "gn:feature_code":"PPL",
    "gn:name":"Bh\u0101nd\u0101rpur",
    "gn:population":0,
    "gn:timezone":"Asia/Dhaka",
    "iso:country":"BD",
    "name:ben_x_preferred":[
        "Bh\u0101nd\u0101rpur"
    ],
    "wof:name":"Bhandarpur",
    "wof:placetype":"locality"
},
  "geometry": {"coordinates":[88.96735,24.97224],"type":"Point"}
}