{
  "type": "Feature",
  "properties": {
    "gn:admin1_code":"82",
    "gn:admin2_code":"4041.0",
    "gn:admin3_code":"404147.0",
    "gn:admin4_code":"40414789.0",
    "gn:asciiname":"Baliadanga",
    "gn:country_code":"BD",
    "gn:dem":13,
    "gn:feature_class":"P",
    "gn:feature_code":"PPL",
    "gn:name":"B\u0101li\u0101d\u0101nga",
    "gn:population":0,
    "gn:timezone":"Asia/Dhaka",
    "iso:country":"BD",
    "name:ben_x_preferred":[
        "B\u0101li\u0101d\u0101nga"
    ],
    "name:und_x_variant":[
        "Balidanga"
    ],
    "wof:name":"Baliadanga",
    "wof:placetype":"locality"
},
  "geometry": {"coordinates":[89.22905,23.21232],"type":"Point"}
}