{
  "type": "Feature",
  "properties": {
    "gn:admin1_code":"83",
    "gn:admin2_code":"5081",
    "gn:admin3_code":"508134.0",
    "gn:admin4_code":"50813457.0",
    "gn:asciiname":"Tilibari",
    "gn:country_code":"BD",
    "gn:dem":39,
    "gn:feature_class":"P",
    "gn:feature_code":"PPL",
    "gn:name":"Tilib\u0101ri",
    "gn:population":0,
    "gn:timezone":"Asia/Dhaka",
    "iso:country":"BD",
    "name:ben_x_preferred":[
        "Tilib\u0101ri"
    ],
    "wof:name":"Tilibari",
    "wof:placetype":"locality"
},
  "geometry": {"coordinates":[88.41049,24.42454],"type":"Point"}
}