{
  "type": "Feature",
  "properties": {
    "gn:admin1_code":"83",
    "gn:asciiname":"Bugdair",
    "gn:country_code":"BD",
    "gn:dem":42,
    "gn:feature_class":"P",
    "gn:feature_code":"PPL",
    "gn:name":"Bugda\u012br",
    "gn:population":0,
    "gn:timezone":"Asia/Dhaka",
    "iso:country":"BD",
    "name:ben_x_preferred":[
        "Bugda\u012br"
    ],
    "wof:name":"Bugdair",
    "wof:placetype":"locality"
},
  "geometry": {"coordinates":[88.5802,25.7565],"type":"Point"}
}