{
  "type": "Feature",
  "properties": {
    "gn:admin1_code":"81",
    "gn:admin2_code":"3026",
    "gn:admin3_code":"302638.0",
    "gn:admin4_code":"30263877.0",
    "gn:asciiname":"Totail",
    "gn:country_code":"BD",
    "gn:dem":10,
    "gn:feature_class":"P",
    "gn:feature_code":"PPL",
    "gn:name":"Tot\u0101il",
    "gn:population":0,
    "gn:timezone":"Asia/Dhaka",
    "iso:country":"BD",
    "wof:name":"Totail",
    "wof:placetype":"locality"
},
  "geometry": {"coordinates":[90.32686,23.73292],"type":"Point"}
}