{
  "type": "Feature",
  "properties": {
    "gn:admin1_code":"H",
    "gn:admin2_code":"3061.0",
    "gn:admin3_code":"306131.0",
    "gn:admin4_code":"30613109.0",
    "gn:asciiname":"Dasasia",
    "gn:country_code":"BD",
    "gn:dem":15,
    "gn:feature_class":"P",
    "gn:feature_code":"PPL",
    "gn:name":"D\u0101s\u0101sia",
    "gn:population":0,
    "gn:timezone":"Asia/Dhaka",
    "iso:country":"BD",
    "name:und_x_variant":[
        "Dashasia",
        "D\u0101s\u0101sia"
    ],
    "wof:name":"Dasasia",
    "wof:placetype":"locality"
},
  "geometry": {"coordinates":[90.7461,24.63039],"type":"Point"}
}