{
  "type": "Feature",
  "properties": {
    "gn:admin1_code":"87",
    "gn:admin2_code":"5549",
    "gn:admin3_code":"554994.0",
    "gn:admin4_code":"55499478.0",
    "gn:asciiname":"Purir Patal",
    "gn:country_code":"BD",
    "gn:dem":29,
    "gn:feature_class":"P",
    "gn:feature_code":"PPL",
    "gn:name":"Purir P\u0101t\u0101l",
    "gn:population":0,
    "gn:timezone":"Asia/Dhaka",
    "iso:country":"BD",
    "name:ben_x_preferred":[
        "Purir P\u0101t\u0101l"
    ],
    "wof:name":"Purir Patal",
    "wof:placetype":"locality"
},
  "geometry": {"coordinates":[89.61579,25.61774],"type":"Point"}
}