{
  "type": "Feature",
  "properties": {
    "gn:admin1_code":"82",
    "gn:admin2_code":"4047.0",
    "gn:admin3_code":"404753.0",
    "gn:admin4_code":"40475355.0",
    "gn:asciiname":"Gobrar Tek",
    "gn:country_code":"BD",
    "gn:dem":6,
    "gn:feature_class":"P",
    "gn:feature_code":"PPL",
    "gn:name":"Gobr\u0101r Tek",
    "gn:population":0,
    "gn:timezone":"Asia/Dhaka",
    "iso:country":"BD",
    "name:ben_x_preferred":[
        "Gobr\u0101r Tek"
    ],
    "wof:name":"Gobrar Tek",
    "wof:placetype":"locality"
},
  "geometry": {"coordinates":[89.26289,22.33414],"type":"Point"}
}