{
  "type": "Feature",
  "properties": {
    "gn:admin1_code":"81",
    "gn:admin2_code":"3029.0",
    "gn:admin3_code":"302903.0",
    "gn:admin4_code":"30290352.0",
    "gn:asciiname":"Char Panchuria",
    "gn:country_code":"BD",
    "gn:dem":11,
    "gn:feature_class":"P",
    "gn:feature_code":"PPL",
    "gn:name":"Char P\u0101nchuria",
    "gn:population":0,
    "gn:timezone":"Asia/Dhaka",
    "iso:country":"BD",
    "wof:name":"Char Panchuria",
    "wof:placetype":"locality"
},
  "geometry": {"coordinates":[89.6125,23.37716],"type":"Point"}
}