{
  "type": "Feature",
  "properties": {
    "gn:admin1_code":"87",
    "gn:admin2_code":"5527",
    "gn:admin3_code":"552777.0",
    "gn:admin4_code":"55277743.0",
    "gn:asciiname":"Uttara",
    "gn:country_code":"BD",
    "gn:dem":37,
    "gn:feature_class":"P",
    "gn:feature_code":"PPL",
    "gn:name":"Uttara",
    "gn:population":0,
    "gn:timezone":"Asia/Dhaka",
    "iso:country":"BD",
    "name:ben_x_preferred":[
        "Uttara"
    ],
    "name:ben_x_variant":[
        "\u0989\u09a4\u09cd\u09a4\u09b0\u09be"
    ],
    "name:deu_x_preferred":[
        "Uttara"
    ],
    "name:hin_x_preferred":[
        "\u0909\u0924\u094d\u0924\u0930\u093e"
    ],
    "wof:name":"Uttara",
    "wof:placetype":"locality"
},
  "geometry": {"coordinates":[89.04212,25.5697],"type":"Point"}
}