{
  "type": "Feature",
  "properties": {
    "gn:admin1_code":"81",
    "gn:admin2_code":"3093",
    "gn:admin3_code":"309328.0",
    "gn:admin4_code":"30932851.0",
    "gn:asciiname":"Tegharia",
    "gn:country_code":"BD",
    "gn:dem":27,
    "gn:feature_class":"P",
    "gn:feature_code":"PPL",
    "gn:name":"Tegharia",
    "gn:population":0,
    "gn:timezone":"Asia/Dhaka",
    "iso:country":"BD",
    "name:und_x_variant":[
        "Tagharia",
        "Tegharia"
    ],
    "wof:name":"Tegharia",
    "wof:placetype":"locality"
},
  "geometry": {"coordinates":[90.02905,24.43991],"type":"Point"}
}