{
  "type": "Feature",
  "properties": {
    "gn:admin1_code":"H",
    "gn:admin2_code":"3089.0",
    "gn:admin3_code":"308990.0",
    "gn:admin4_code":"30899031.0",
    "gn:asciiname":"Garh Jaripa",
    "gn:country_code":"BD",
    "gn:dem":23,
    "gn:feature_class":"P",
    "gn:feature_code":"PPL",
    "gn:name":"Garh Jaripa",
    "gn:population":0,
    "gn:timezone":"Asia/Dhaka",
    "iso:country":"BD",
    "name:und_x_variant":[
        "Gar Jaripa",
        "Garh Jaripa"
    ],
    "wof:name":"Garh Jaripa",
    "wof:placetype":"locality"
},
  "geometry": {"coordinates":[90.01006,25.10433],"type":"Point"}
}