{
  "type": "Feature",
  "properties": {
    "gn:admin1_code":"84",
    "gn:admin2_code":"2015.0",
    "gn:admin3_code":"201518.0",
    "gn:admin4_code":"20151885.0",
    "gn:asciiname":"Gachhbaria",
    "gn:country_code":"BD",
    "gn:dem":12,
    "gn:feature_class":"P",
    "gn:feature_code":"PPL",
    "gn:name":"G\u0101chhb\u0101ria",
    "gn:population":0,
    "gn:timezone":"Asia/Dhaka",
    "iso:country":"BD",
    "name:ben_x_preferred":[
        "G\u0101chhb\u0101ria"
    ],
    "wof:name":"Gachhbaria",
    "wof:placetype":"locality"
},
  "geometry": {"coordinates":[92.02705,22.21215],"type":"Point"}
}