{
  "type": "Feature",
  "properties": {
    "gn:admin1_code":"82",
    "gn:admin2_code":"4044",
    "gn:admin3_code":"404480.0",
    "gn:admin4_code":"40448050.0",
    "gn:asciiname":"Sadhuhati",
    "gn:country_code":"BD",
    "gn:dem":14,
    "gn:feature_class":"P",
    "gn:feature_code":"PPL",
    "gn:name":"S\u0101dhuh\u0101ti",
    "gn:population":0,
    "gn:timezone":"Asia/Dhaka",
    "iso:country":"BD",
    "wof:name":"Sadhuhati",
    "wof:placetype":"locality"
},
  "geometry": {"coordinates":[89.30246,23.69215],"type":"Point"}
}