{
  "type": "Feature",
  "properties": {
    "gn:admin1_code":"85",
    "gn:admin2_code":"1004",
    "gn:admin3_code":"100428.0",
    "gn:admin4_code":"10042876.0",
    "gn:asciiname":"Tarabunia",
    "gn:country_code":"BD",
    "gn:dem":9,
    "gn:feature_class":"P",
    "gn:feature_code":"PPL",
    "gn:name":"Tarabunia",
    "gn:population":0,
    "gn:timezone":"Asia/Dhaka",
    "iso:country":"BD",
    "name:ben_x_preferred":[
        "Tarabunia"
    ],
    "name:ben_x_variant":[
        "T\u0101r\u0101bania"
    ],
    "wof:name":"Tarabunia",
    "wof:placetype":"locality"
},
  "geometry": {"coordinates":[90.1743,22.24085],"type":"Point"}
}