{
  "type": "Feature",
  "properties": {
    "gn:admin1_code":"81",
    "gn:admin2_code":"3026",
    "gn:admin3_code":"302672.0",
    "gn:admin4_code":"30267272.0",
    "gn:asciiname":"Kalabari",
    "gn:country_code":"BD",
    "gn:dem":16,
    "gn:feature_class":"P",
    "gn:feature_code":"PPL",
    "gn:name":"Kal\u0101b\u0101ri",
    "gn:population":0,
    "gn:timezone":"Asia/Dhaka",
    "iso:country":"BD",
    "name:deu_x_preferred":[
        "Kalabari"
    ],
    "name:fra_x_preferred":[
        "Kalabari"
    ],
    "wof:name":"Kalabari",
    "wof:placetype":"locality"
},
  "geometry": {"coordinates":[90.23287000000001,23.91743],"type":"Point"}
}