{
  "type": "Feature",
  "properties": {
    "gn:admin1_code":"H",
    "gn:admin2_code":"3072",
    "gn:admin3_code":"307283.0",
    "gn:admin4_code":"30728387.0",
    "gn:asciiname":"Pailati",
    "gn:country_code":"BD",
    "gn:dem":15,
    "gn:feature_class":"P",
    "gn:feature_code":"PPL",
    "gn:name":"P\u0101il\u0101ti",
    "gn:population":0,
    "gn:timezone":"Asia/Dhaka",
    "iso:country":"BD",
    "wof:name":"Pailati",
    "wof:placetype":"locality"
},
  "geometry": {"coordinates":[90.62652,24.86586],"type":"Point"}
}