{
  "type": "Feature",
  "properties": {
    "gn:admin1_code":"83",
    "gn:admin2_code":"5038.0",
    "gn:admin3_code":"503874.0",
    "gn:admin4_code":"50387410.0",
    "gn:asciiname":"Bayro",
    "gn:country_code":"BD",
    "gn:dem":26,
    "gn:feature_class":"P",
    "gn:feature_code":"PPL",
    "gn:name":"Bayro",
    "gn:population":0,
    "gn:timezone":"Asia/Dhaka",
    "iso:country":"BD",
    "name:ben_x_preferred":[
        "Bayro"
    ],
    "wof:name":"Bayro",
    "wof:placetype":"locality"
},
  "geometry": {"coordinates":[89.15971999999999,25.20015],"type":"Point"}
}