{
  "type": "Feature",
  "properties": {
    "gn:admin1_code":"87",
    "gn:admin2_code":"5585",
    "gn:admin3_code":"558576.0",
    "gn:admin4_code":"55857637.0",
    "gn:asciiname":"Junaidpur",
    "gn:country_code":"BD",
    "gn:dem":28,
    "gn:feature_class":"P",
    "gn:feature_code":"PPL",
    "gn:name":"Junaidpur",
    "gn:population":0,
    "gn:timezone":"Asia/Dhaka",
    "iso:country":"BD",
    "name:ben_x_preferred":[
        "Junaidpur"
    ],
    "wof:name":"Junaidpur",
    "wof:placetype":"locality"
},
  "geometry": {"coordinates":[89.30883,25.31988],"type":"Point"}
}