{
  "type": "Feature",
  "properties": {
    "gn:admin1_code":"82",
    "gn:admin2_code":"4044.0",
    "gn:admin3_code":"404471.0",
    "gn:admin4_code":"40447135.0",
    "gn:asciiname":"Bhalpara",
    "gn:country_code":"BD",
    "gn:dem":16,
    "gn:feature_class":"P",
    "gn:feature_code":"PPL",
    "gn:name":"Bh\u0101lp\u0101ra",
    "gn:population":0,
    "gn:timezone":"Asia/Dhaka",
    "iso:country":"BD",
    "name:ben_x_preferred":[
        "Bh\u0101lp\u0101ra"
    ],
    "wof:name":"Bhalpara",
    "wof:placetype":"locality"
},
  "geometry": {"coordinates":[88.95052,23.29668],"type":"Point"}
}