{
  "type": "Feature",
  "properties": {
    "gn:admin1_code":"82",
    "gn:admin2_code":"4044.0",
    "gn:admin3_code":"404433.0",
    "gn:admin4_code":"40443381.0",
    "gn:asciiname":"Naradahi",
    "gn:country_code":"BD",
    "gn:dem":14,
    "gn:feature_class":"P",
    "gn:feature_code":"PPL",
    "gn:name":"Naradahi",
    "gn:population":0,
    "gn:timezone":"Asia/Dhaka",
    "iso:country":"BD",
    "name:ben_x_preferred":[
        "Naradahi"
    ],
    "wof:name":"Naradahi",
    "wof:placetype":"locality"
},
  "geometry": {"coordinates":[89.11433000000002,23.33684],"type":"Point"}
}