{
  "type": "Feature",
  "properties": {
    "gn:admin1_code":"85",
    "gn:admin2_code":"1006",
    "gn:admin3_code":"100651.0",
    "gn:admin4_code":"10065177.0",
    "gn:asciiname":"Raypasa",
    "gn:country_code":"BD",
    "gn:dem":8,
    "gn:feature_class":"P",
    "gn:feature_code":"PPL",
    "gn:name":"R\u0101yp\u0101sa",
    "gn:population":0,
    "gn:timezone":"Asia/Dhaka",
    "iso:country":"BD",
    "wof:name":"Raypasa",
    "wof:placetype":"locality"
},
  "geometry": {"coordinates":[90.30728999999999,22.71744],"type":"Point"}
}