{
  "type": "Feature",
  "properties": {
    "gn:admin1_code":"84",
    "gn:admin2_code":"2015.0",
    "gn:admin3_code":"201582.0",
    "gn:admin4_code":"20158251.0",
    "gn:asciiname":"Kanchana",
    "gn:country_code":"BD",
    "gn:dem":9,
    "gn:feature_class":"P",
    "gn:feature_code":"PPL",
    "gn:name":"K\u0101nchana",
    "gn:population":0,
    "gn:timezone":"Asia/Dhaka",
    "iso:country":"BD",
    "name:ben_x_preferred":[
        "K\u0101nchana"
    ],
    "name:tam_x_preferred":[
        "\u0b95\u0bbe\u0b9e\u0bcd\u0b9a\u0ba9\u0bbe"
    ],
    "wof:name":"Kanchana",
    "wof:placetype":"locality"
},
  "geometry": {"coordinates":[91.99395,22.12221],"type":"Point"}
}