{
  "type": "Feature",
  "properties": {
    "gn:admin1_code":"87",
    "gn:admin2_code":"5527",
    "gn:admin3_code":"552743.0",
    "gn:admin4_code":"55274376.0",
    "gn:asciiname":"Khanil",
    "gn:country_code":"BD",
    "gn:dem":29,
    "gn:feature_class":"P",
    "gn:feature_code":"PPL",
    "gn:name":"Khanil",
    "gn:population":0,
    "gn:timezone":"Asia/Dhaka",
    "iso:country":"BD",
    "name:ben_x_preferred":[
        "Khanil"
    ],
    "wof:name":"Khanil",
    "wof:placetype":"locality"
},
  "geometry": {"coordinates":[89.25083000000002,25.27271],"type":"Point"}
}