{
  "type": "Feature",
  "properties": {
    "gn:admin1_code":"82",
    "gn:admin2_code":"4044.0",
    "gn:admin3_code":"404471.0",
    "gn:admin4_code":"40447183.0",
    "gn:asciiname":"Kamdebpur",
    "gn:country_code":"BD",
    "gn:dem":12,
    "gn:feature_class":"P",
    "gn:feature_code":"PPL",
    "gn:name":"K\u0101mdebpur",
    "gn:population":0,
    "gn:timezone":"Asia/Dhaka",
    "iso:country":"BD",
    "name:ben_x_preferred":[
        "K\u0101mdebpur"
    ],
    "wof:name":"Kamdebpur",
    "wof:placetype":"locality"
},
  "geometry": {"coordinates":[88.9448,23.37552],"type":"Point"}
}