{
  "type": "Feature",
  "properties": {
    "gn:admin1_code":"H",
    "gn:admin2_code":"3089",
    "gn:admin3_code":"308990.0",
    "gn:admin4_code":"30899063.0",
    "gn:asciiname":"Kararpara",
    "gn:country_code":"BD",
    "gn:dem":22,
    "gn:feature_class":"P",
    "gn:feature_code":"PPL",
    "gn:name":"K\u0101r\u0101rp\u0101ra",
    "gn:population":0,
    "gn:timezone":"Asia/Dhaka",
    "iso:country":"BD",
    "name:ben_x_preferred":[
        "K\u0101r\u0101rp\u0101ra"
    ],
    "wof:name":"Kararpara",
    "wof:placetype":"locality"
},
  "geometry": {"coordinates":[90.01828,25.07166],"type":"Point"}
}