{
  "type": "Feature",
  "properties": {
    "gn:admin1_code":"H",
    "gn:admin2_code":"3061.0",
    "gn:admin3_code":"306131.0",
    "gn:admin4_code":"30613194.0",
    "gn:asciiname":"Bri Charakona",
    "gn:cc2":"BD",
    "gn:country_code":"BD",
    "gn:dem":13,
    "gn:feature_class":"P",
    "gn:feature_code":"PPL",
    "gn:name":"Bri Char\u0101kona",
    "gn:population":0,
    "gn:timezone":"Asia/Dhaka",
    "iso:country":"BD",
    "name:und_x_variant":[
        "Bricharkona",
        "Bri Char\u0101kona"
    ],
    "wof:name":"Bri Charakona",
    "wof:placetype":"locality"
},
  "geometry": {"coordinates":[90.55,24.63333],"type":"Point"}
}