{
  "type": "Feature",
  "properties": {
    "gn:admin1_code":"87",
    "gn:admin2_code":"5549",
    "gn:admin3_code":"554952.0",
    "gn:admin4_code":"55495219.0",
    "gn:asciiname":"Joy Saraswati",
    "gn:country_code":"BD",
    "gn:dem":30,
    "gn:feature_class":"P",
    "gn:feature_code":"PPL",
    "gn:name":"Joy Saraswati",
    "gn:population":0,
    "gn:timezone":"Asia/Dhaka",
    "iso:country":"BD",
    "name:ben_x_preferred":[
        "Joy Saraswati"
    ],
    "wof:name":"Joy Saraswati",
    "wof:placetype":"locality"
},
  "geometry": {"coordinates":[89.66781999999998,25.84132],"type":"Point"}
}