{
  "type": "Feature",
  "properties": {
    "gn:admin1_code":"84",
    "gn:admin2_code":"2019.0",
    "gn:admin3_code":"201981.0",
    "gn:admin4_code":"20198140.0",
    "gn:asciiname":"Baraiakuri",
    "gn:country_code":"BD",
    "gn:dem":11,
    "gn:feature_class":"P",
    "gn:feature_code":"PPL",
    "gn:name":"Barai\u0101kuri",
    "gn:population":0,
    "gn:timezone":"Asia/Dhaka",
    "iso:country":"BD",
    "wof:name":"Baraiakuri",
    "wof:placetype":"locality"
},
  "geometry": {"coordinates":[90.8706,23.61438],"type":"Point"}
}