{
  "type": "Feature",
  "properties": {
    "gn:admin1_code":"81",
    "gn:admin2_code":"3035.0",
    "gn:admin3_code":"303543.0",
    "gn:admin4_code":"30354340.0",
    "gn:asciiname":"Buruz Majhigati",
    "gn:country_code":"BD",
    "gn:dem":11,
    "gn:feature_class":"P",
    "gn:feature_code":"PPL",
    "gn:name":"Buruz M\u0101jhig\u0101ti",
    "gn:population":0,
    "gn:timezone":"Asia/Dhaka",
    "iso:country":"BD",
    "name:und_x_variant":[
        "Pachim Majhigati",
        "Buruz M\u0101jhig\u0101ti"
    ],
    "wof:name":"Buruz Majhigati",
    "wof:placetype":"locality"
},
  "geometry": {"coordinates":[89.78631,23.28682],"type":"Point"}
}