{
  "type": "Feature",
  "properties": {
    "gn:admin1_code":"82",
    "gn:admin2_code":"4047.0",
    "gn:admin3_code":"404785.0",
    "gn:admin4_code":"40478525.0",
    "gn:asciiname":"Banarganti",
    "gn:country_code":"BD",
    "gn:dem":7,
    "gn:feature_class":"P",
    "gn:feature_code":"PPL",
    "gn:name":"B\u0101narg\u0101nti",
    "gn:population":0,
    "gn:timezone":"Asia/Dhaka",
    "iso:country":"BD",
    "name:ben_x_preferred":[
        "B\u0101narg\u0101nti"
    ],
    "wof:name":"Banarganti",
    "wof:placetype":"locality"
},
  "geometry": {"coordinates":[89.54706,22.80876],"type":"Point"}
}