{
  "type": "Feature",
  "properties": {
    "gn:admin1_code":"87",
    "gn:admin2_code":"5585",
    "gn:admin3_code":"558576.0",
    "gn:admin4_code":"55857669.0",
    "gn:asciiname":"Tularampur",
    "gn:country_code":"BD",
    "gn:dem":31,
    "gn:feature_class":"P",
    "gn:feature_code":"PPL",
    "gn:name":"Tularampur",
    "gn:population":0,
    "gn:timezone":"Asia/Dhaka",
    "iso:country":"BD",
    "name:ben_x_preferred":[
        "Tularampur"
    ],
    "wof:name":"Tularampur",
    "wof:placetype":"locality"
},
  "geometry": {"coordinates":[89.32281999999999,25.44746],"type":"Point"}
}