{
  "type": "Feature",
  "properties": {
    "gn:admin1_code":"87",
    "gn:admin2_code":"5549",
    "gn:admin3_code":"554918.0",
    "gn:admin4_code":"55491840.0",
    "gn:asciiname":"Ramprasad",
    "gn:country_code":"BD",
    "gn:dem":33,
    "gn:feature_class":"P",
    "gn:feature_code":"PPL",
    "gn:name":"R\u0101mpr\u0101s\u0101d",
    "gn:population":0,
    "gn:timezone":"Asia/Dhaka",
    "iso:country":"BD",
    "name:ben_x_preferred":[
        "R\u0101mpr\u0101s\u0101d"
    ],
    "wof:name":"Ramprasad",
    "wof:placetype":"locality"
},
  "geometry": {"coordinates":[89.54299999999998,25.93706],"type":"Point"}
}