{
  "type": "Feature",
  "properties": {
    "gn:admin1_code":"87",
    "gn:admin2_code":"5549",
    "gn:admin3_code":"554977.0",
    "gn:admin4_code":"55497784.0",
    "gn:asciiname":"Umar Majid",
    "gn:country_code":"BD",
    "gn:dem":33,
    "gn:feature_class":"P",
    "gn:feature_code":"PPL",
    "gn:name":"Umar Majid",
    "gn:population":0,
    "gn:timezone":"Asia/Dhaka",
    "iso:country":"BD",
    "name:ben_x_preferred":[
        "Umar Majid"
    ],
    "wof:name":"Umar Majid",
    "wof:placetype":"locality"
},
  "geometry": {"coordinates":[89.57235,25.75453],"type":"Point"}
}