{
  "type": "Feature",
  "properties": {
    "gn:admin1_code":"82",
    "gn:admin2_code":"4047",
    "gn:admin3_code":"404730.0",
    "gn:admin4_code":"40473094.0",
    "gn:asciiname":"Mandartala",
    "gn:country_code":"BD",
    "gn:dem":3,
    "gn:feature_class":"P",
    "gn:feature_code":"PPL",
    "gn:name":"M\u0101nd\u0101rtala",
    "gn:population":0,
    "gn:timezone":"Asia/Dhaka",
    "iso:country":"BD",
    "wof:name":"Mandartala",
    "wof:placetype":"locality"
},
  "geometry": {"coordinates":[89.36404,22.74884],"type":"Point"}
}