{
  "type": "Feature",
  "properties": {
    "gn:admin1_code":"82",
    "gn:admin2_code":"4087",
    "gn:admin3_code":"408704.0",
    "gn:admin4_code":"40870494.0",
    "gn:asciiname":"Nasimabad",
    "gn:country_code":"BD",
    "gn:dem":3,
    "gn:feature_class":"P",
    "gn:feature_code":"PPL",
    "gn:name":"N\u0101sim\u0101b\u0101d",
    "gn:population":0,
    "gn:timezone":"Asia/Dhaka",
    "iso:country":"BD",
    "name:ben_x_preferred":[
        "N\u0101sim\u0101b\u0101d"
    ],
    "wof:name":"Nasimabad",
    "wof:placetype":"locality"
},
  "geometry": {"coordinates":[89.16511,22.40446],"type":"Point"}
}