{
  "type": "Feature",
  "properties": {
    "gn:admin1_code":"81",
    "gn:admin2_code":"3029.0",
    "gn:admin3_code":"302947.0",
    "gn:admin4_code":"30294700.0",
    "gn:asciiname":"Guha Lakshmipur",
    "gn:country_code":"BD",
    "gn:dem":14,
    "gn:feature_class":"P",
    "gn:feature_code":"PPL",
    "gn:name":"Guha Lakshmipur",
    "gn:population":0,
    "gn:timezone":"Asia/Dhaka",
    "iso:country":"BD",
    "wof:name":"Guha Lakshmipur",
    "wof:placetype":"locality"
},
  "geometry": {"coordinates":[89.83519,23.61064],"type":"Point"}
}