{
  "type": "Feature",
  "properties": {
    "gn:admin1_code":"82",
    "gn:admin2_code":"4018.0",
    "gn:admin3_code":"401807.0",
    "gn:admin4_code":"40180715.0",
    "gn:asciiname":"Atharokhada",
    "gn:country_code":"BD",
    "gn:dem":20,
    "gn:feature_class":"P",
    "gn:feature_code":"PPL",
    "gn:name":"Ath\u0101rokh\u0101da",
    "gn:population":0,
    "gn:timezone":"Asia/Dhaka",
    "iso:country":"BD",
    "name:ben_x_preferred":[
        "Ath\u0101rokh\u0101da"
    ],
    "wof:name":"Atharokhada",
    "wof:placetype":"locality"
},
  "geometry": {"coordinates":[88.86294000000002,23.75595],"type":"Point"}
}