{
  "type": "Feature",
  "properties": {
    "gn:admin1_code":"85",
    "gn:admin2_code":"1006.0",
    "gn:admin3_code":"100662.0",
    "gn:admin4_code":"10066279.0",
    "gn:asciiname":"Gauripur",
    "gn:country_code":"BD",
    "gn:dem":12,
    "gn:feature_class":"P",
    "gn:feature_code":"PPL",
    "gn:name":"Gaur\u012bpur",
    "gn:population":0,
    "gn:timezone":"Asia/Dhaka",
    "iso:country":"BD",
    "name:ceb_x_preferred":[
        "Gauripur"
    ],
    "name:sco_x_preferred":[
        "Gauripur"
    ],
    "name:swe_x_preferred":[
        "Gauripur"
    ],
    "wof:name":"Gauripur",
    "wof:placetype":"locality"
},
  "geometry": {"coordinates":[90.40636000000001,22.88055],"type":"Point"}
}