{
  "type": "Feature",
  "properties": {
    "gn:admin1_code":"87",
    "gn:admin2_code":"5585",
    "gn:admin3_code":"558558.0",
    "gn:admin4_code":"55855816.0",
    "gn:asciiname":"Nanker Hat",
    "gn:country_code":"BD",
    "gn:dem":33,
    "gn:feature_class":"P",
    "gn:feature_code":"PPL",
    "gn:name":"N\u0101nker H\u0101t",
    "gn:population":0,
    "gn:timezone":"Asia/Dhaka",
    "iso:country":"BD",
    "wof:name":"Nanker Hat",
    "wof:placetype":"locality"
},
  "geometry": {"coordinates":[89.32858,25.53336],"type":"Point"}
}