{
  "type": "Feature",
  "properties": {
    "gn:admin1_code":"85",
    "gn:admin2_code":"1006",
    "gn:admin3_code":"100669.0",
    "gn:admin4_code":"10066923.0",
    "gn:asciiname":"South Gachhua",
    "gn:country_code":"BD",
    "gn:dem":11,
    "gn:feature_class":"P",
    "gn:feature_code":"PPL",
    "gn:name":"South G\u0101chhua",
    "gn:population":0,
    "gn:timezone":"Asia/Dhaka",
    "iso:country":"BD",
    "wof:name":"South Gachhua",
    "wof:placetype":"locality"
},
  "geometry": {"coordinates":[90.41193,22.95872],"type":"Point"}
}