{
  "type": "Feature",
  "properties": {
    "gn:admin1_code":"87",
    "gn:admin2_code":"5573.0",
    "gn:admin3_code":"557364.0",
    "gn:admin4_code":"55736418.0",
    "gn:asciiname":"Uttar Choura",
    "gn:country_code":"BD",
    "gn:dem":55,
    "gn:feature_class":"P",
    "gn:feature_code":"PPL",
    "gn:name":"Uttar Choura",
    "gn:population":0,
    "gn:timezone":"Asia/Dhaka",
    "iso:country":"BD",
    "name:ben_x_preferred":[
        "Uttar Choura"
    ],
    "wof:name":"Uttar Choura",
    "wof:placetype":"locality"
},
  "geometry": {"coordinates":[88.79654000000002,26.03795],"type":"Point"}
}