{
  "type": "Feature",
  "properties": {
    "gn:admin1_code":"85",
    "gn:admin2_code":"1006.0",
    "gn:admin3_code":"100669.0",
    "gn:admin4_code":"10066959.0",
    "gn:asciiname":"Bara Patar Char",
    "gn:country_code":"BD",
    "gn:dem":6,
    "gn:feature_class":"P",
    "gn:feature_code":"PPL",
    "gn:name":"Bara P\u0101t\u0101r Char",
    "gn:population":0,
    "gn:timezone":"Asia/Dhaka",
    "iso:country":"BD",
    "name:und_x_variant":[
        "Bara P\u0101t\u0101r Char"
    ],
    "wof:name":"Bara Patar Char",
    "wof:placetype":"locality"
},
  "geometry": {"coordinates":[90.39094,22.9498],"type":"Point"}
}