{
  "type": "Feature",
  "properties": {
    "gn:admin1_code":"83",
    "gn:asciiname":"Matarpara",
    "gn:country_code":"BD",
    "gn:dem":28,
    "gn:feature_class":"P",
    "gn:feature_code":"PPL",
    "gn:name":"Matarp\u0101ra",
    "gn:population":0,
    "gn:timezone":"Asia/Dhaka",
    "iso:country":"BD",
    "name:ben_x_preferred":[
        "Matarp\u0101ra"
    ],
    "wof:name":"Matarpara",
    "wof:placetype":"locality"
},
  "geometry": {"coordinates":[89.54940000000001,25.12833],"type":"Point"}
}