{
  "type": "Feature",
  "properties": {
    "gn:admin1_code":"82",
    "gn:admin2_code":"4050",
    "gn:admin3_code":"405039.0",
    "gn:admin4_code":"40503940.0",
    "gn:asciiname":"Shahapur",
    "gn:country_code":"BD",
    "gn:dem":20,
    "gn:feature_class":"P",
    "gn:feature_code":"PPL",
    "gn:name":"Sh\u0101h\u0101pur",
    "gn:population":0,
    "gn:timezone":"Asia/Dhaka",
    "iso:country":"BD",
    "name:ben_x_preferred":[
        "Sh\u0101h\u0101pur"
    ],
    "name:ben_x_variant":[
        "S\u0101h\u0101pur",
        "\u09b6\u09be\u09b9\u09be\u09aa\u09c1\u09b0"
    ],
    "name:bpy_x_preferred":[
        "\u09b6\u09be\u09b9\u09be\u09aa\u09c1\u09b0"
    ],
    "name:ceb_x_preferred":[
        "Sh\u0101h\u0101pur"
    ],
    "name:hin_x_preferred":[
        "\u0936\u0939\u093e\u092a\u0941\u0930"
    ],
    "name:ita_x_preferred":[
        "Shahapur"
    ],
    "name:mar_x_preferred":[
        "\u0936\u0939\u093e\u092a\u0942\u0930"
    ],
    "name:msa_x_preferred":[
        "Shahapur"
    ],
    "name:nld_x_preferred":[
        "Shahapur"
    ],
    "name:por_x_preferred":[
        "Shahapur"
    ],
    "name:swe_x_preferred":[
        "Sh\u0101h\u0101pur"
    ],
    "name:vie_x_preferred":[
        "Shahapur"
    ],
    "name:zho_x_preferred":[
        "\u65af\u54c8\u54c8\u666e\u5c14"
    ],
    "wof:name":"Shahapur",
    "wof:placetype":"locality"
},
  "geometry": {"coordinates":[88.88655,24.0299],"type":"Point"}
}