{
  "type": "Feature",
  "properties": {
    "gn:admin1_code":"87",
    "gn:admin2_code":"5527.0",
    "gn:admin3_code":"552777.0",
    "gn:admin4_code":"55277743.0",
    "gn:asciiname":"Dakshin Harirampur",
    "gn:country_code":"BD",
    "gn:dem":36,
    "gn:feature_class":"P",
    "gn:feature_code":"PPL",
    "gn:name":"Dakshin Har\u012br\u0101mpur",
    "gn:population":0,
    "gn:timezone":"Asia/Dhaka",
    "iso:country":"BD",
    "wof:name":"Dakshin Harirampur",
    "wof:placetype":"locality"
},
  "geometry": {"coordinates":[89.02790999999998,25.59261],"type":"Point"}
}