{
  "type": "Feature",
  "properties": {
    "gn:admin1_code":"83",
    "gn:admin2_code":"5081",
    "gn:admin3_code":"508172.0",
    "gn:admin4_code":"50817271.0",
    "gn:asciiname":"Mathura",
    "gn:country_code":"BD",
    "gn:dem":19,
    "gn:feature_class":"P",
    "gn:feature_code":"PPL",
    "gn:name":"Mathura",
    "gn:population":0,
    "gn:timezone":"Asia/Dhaka",
    "iso:country":"BD",
    "wof:name":"Mathura",
    "wof:placetype":"locality"
},
  "geometry": {"coordinates":[88.61667,24.45],"type":"Point"}
}