{
  "type": "Feature",
  "properties": {
    "gn:admin1_code":"84",
    "gn:admin2_code":"2019",
    "gn:admin3_code":"201909.0",
    "gn:admin4_code":"20190937.0",
    "gn:asciiname":"Jhaguria",
    "gn:country_code":"BD",
    "gn:dem":9,
    "gn:feature_class":"P",
    "gn:feature_code":"PPL",
    "gn:name":"Jh\u0101guria",
    "gn:population":0,
    "gn:timezone":"Asia/Dhaka",
    "iso:country":"BD",
    "wof:name":"Jhaguria",
    "wof:placetype":"locality"
},
  "geometry": {"coordinates":[91.01667,23.36667000000001],"type":"Point"}
}