{
  "type": "Feature",
  "properties": {
    "gn:admin1_code":"83",
    "gn:admin2_code":"5064",
    "gn:admin3_code":"506469.0",
    "gn:admin4_code":"50646921.0",
    "gn:asciiname":"Santosh",
    "gn:country_code":"BD",
    "gn:dem":23,
    "gn:feature_class":"P",
    "gn:feature_code":"PPL",
    "gn:name":"Santosh",
    "gn:population":0,
    "gn:timezone":"Asia/Dhaka",
    "iso:country":"BD",
    "name:ben_x_preferred":[
        "Santosh"
    ],
    "wof:name":"Santosh",
    "wof:placetype":"locality"
},
  "geometry": {"coordinates":[88.62899,24.82052],"type":"Point"}
}