{
  "type": "Feature",
  "properties": {
    "gn:admin1_code":"87",
    "gn:admin2_code":"5577.0",
    "gn:admin3_code":"557704.0",
    "gn:admin4_code":"55770467.0",
    "gn:asciiname":"Kismat Rusiya",
    "gn:country_code":"BD",
    "gn:dem":71,
    "gn:feature_class":"P",
    "gn:feature_code":"PPL",
    "gn:name":"Kismat Rusiya",
    "gn:population":0,
    "gn:timezone":"Asia/Dhaka",
    "iso:country":"BD",
    "name:ben_x_preferred":[
        "Kismat Rusiya"
    ],
    "wof:name":"Kismat Rusiya",
    "wof:placetype":"locality"
},
  "geometry": {"coordinates":[88.44275999999998,26.2298],"type":"Point"}
}