{
  "type": "Feature",
  "properties": {
    "gn:admin1_code":"83",
    "gn:admin2_code":"5010.0",
    "gn:admin3_code":"501027.0",
    "gn:admin4_code":"50102747.0",
    "gn:asciiname":"Elangi",
    "gn:country_code":"BD",
    "gn:dem":20,
    "gn:feature_class":"P",
    "gn:feature_code":"PPL",
    "gn:name":"Elangi",
    "gn:population":0,
    "gn:timezone":"Asia/Dhaka",
    "iso:country":"BD",
    "wof:name":"Elangi",
    "wof:placetype":"locality"
},
  "geometry": {"coordinates":[89.50024999999999,24.69282],"type":"Point"}
}