{
  "type": "Feature",
  "properties": {
    "gn:admin1_code":"82",
    "gn:admin2_code":"4001.0",
    "gn:admin3_code":"400108.0",
    "gn:admin4_code":"40010851.0",
    "gn:asciiname":"Gotapara",
    "gn:country_code":"BD",
    "gn:dem":7,
    "gn:feature_class":"P",
    "gn:feature_code":"PPL",
    "gn:name":"Got\u0101p\u0101ra",
    "gn:population":0,
    "gn:timezone":"Asia/Dhaka",
    "iso:country":"BD",
    "wof:name":"Gotapara",
    "wof:placetype":"locality"
},
  "geometry": {"coordinates":[89.81667,22.68333],"type":"Point"}
}