{
  "type": "Feature",
  "properties": {
    "gn:admin1_code":"82",
    "gn:admin2_code":"4087.0",
    "gn:admin3_code":"408704.0",
    "gn:admin4_code":"40870469.0",
    "gn:asciiname":"Dadpur",
    "gn:country_code":"BD",
    "gn:dem":6,
    "gn:feature_class":"P",
    "gn:feature_code":"PPL",
    "gn:name":"D\u0101dpur",
    "gn:population":0,
    "gn:timezone":"Asia/Dhaka",
    "iso:country":"BD",
    "wof:name":"Dadpur",
    "wof:placetype":"locality"
},
  "geometry": {"coordinates":[89.17896999999998,22.63885],"type":"Point"}
}