{
  "type": "Feature",
  "properties": {
    "gn:admin1_code":"82",
    "gn:admin2_code":"4047.0",
    "gn:admin3_code":"404775.0",
    "gn:admin4_code":"40477527.0",
    "gn:asciiname":"Tarulia",
    "gn:country_code":"BD",
    "gn:dem":5,
    "gn:feature_class":"P",
    "gn:feature_code":"PPL",
    "gn:name":"T\u0101rulia",
    "gn:population":0,
    "gn:timezone":"Asia/Dhaka",
    "iso:country":"BD",
    "name:ben_x_preferred":[
        "T\u0101rulia"
    ],
    "wof:name":"Tarulia",
    "wof:placetype":"locality"
},
  "geometry": {"coordinates":[89.63476999999997,22.80775],"type":"Point"}
}