{
  "type": "Feature",
  "properties": {
    "gn:admin1_code":"85",
    "gn:admin2_code":"1006",
    "gn:admin3_code":"100669.0",
    "gn:admin4_code":"10066983.0",
    "gn:asciiname":"Uttar Patar Char",
    "gn:country_code":"BD",
    "gn:dem":11,
    "gn:feature_class":"P",
    "gn:feature_code":"PPL",
    "gn:name":"Uttar P\u0101t\u0101r Char",
    "gn:population":0,
    "gn:timezone":"Asia/Dhaka",
    "iso:country":"BD",
    "name:und_x_variant":[
        "Uttar P\u0101t\u0101r Char",
        "North P\u0101t\u0101r Char"
    ],
    "wof:name":"Uttar Patar Char",
    "wof:placetype":"locality"
},
  "geometry": {"coordinates":[90.39259,23.04815],"type":"Point"}
}