{
  "type": "Feature",
  "properties": {
    "gn:admin1_code":"84",
    "gn:admin2_code":"2015.0",
    "gn:admin3_code":"201508.0",
    "gn:admin4_code":"20150875.0",
    "gn:asciiname":"Sadhanpur",
    "gn:country_code":"BD",
    "gn:dem":11,
    "gn:feature_class":"P",
    "gn:feature_code":"PPL",
    "gn:name":"S\u0101dh\u0101npur",
    "gn:population":0,
    "gn:timezone":"Asia/Dhaka",
    "iso:country":"BD",
    "name:ben_x_preferred":[
        "S\u0101dh\u0101npur"
    ],
    "wof:name":"Sadhanpur",
    "wof:placetype":"locality"
},
  "geometry": {"coordinates":[91.9224,22.11178],"type":"Point"}
}