{
  "type": "Feature",
  "properties": {
    "gn:admin1_code":"84",
    "gn:admin2_code":"2019.0",
    "gn:admin3_code":"201981.0",
    "gn:admin4_code":"20198131.0",
    "gn:asciiname":"Borar Char",
    "gn:country_code":"BD",
    "gn:dem":12,
    "gn:feature_class":"P",
    "gn:feature_code":"PPL",
    "gn:name":"Bor\u0101r Char",
    "gn:population":0,
    "gn:timezone":"Asia/Dhaka",
    "iso:country":"BD",
    "name:und_x_variant":[
        "Borachar",
        "Bor\u0101r Char"
    ],
    "wof:name":"Borar Char",
    "wof:placetype":"locality"
},
  "geometry": {"coordinates":[90.87421000000001,23.60411],"type":"Point"}
}