{
  "type": "Feature",
  "properties": {
    "gn:admin1_code":"82",
    "gn:admin2_code":"4041.0",
    "gn:admin3_code":"404147.0",
    "gn:admin4_code":"40414765.0",
    "gn:asciiname":"Bijaynagar",
    "gn:country_code":"BD",
    "gn:dem":12,
    "gn:feature_class":"P",
    "gn:feature_code":"PPL",
    "gn:name":"Bijaynagar",
    "gn:population":0,
    "gn:timezone":"Asia/Dhaka",
    "iso:country":"BD",
    "name:ben_x_preferred":[
        "Bijaynagar"
    ],
    "name:und_x_variant":[
        "Bijoynagar"
    ],
    "wof:name":"Bijaynagar",
    "wof:placetype":"locality"
},
  "geometry": {"coordinates":[89.18075999999998,23.21626],"type":"Point"}
}