{
  "type": "Feature",
  "properties": {
    "gn:admin1_code":"83",
    "gn:admin2_code":"5081.0",
    "gn:admin3_code":"508172.0",
    "gn:admin4_code":"50817255.0",
    "gn:asciiname":"Sairpukur",
    "gn:country_code":"BD",
    "gn:dem":21,
    "gn:feature_class":"P",
    "gn:feature_code":"PPL",
    "gn:name":"Sairpukur",
    "gn:population":0,
    "gn:timezone":"Asia/Dhaka",
    "iso:country":"BD",
    "name:ben_x_preferred":[
        "Sairpukur"
    ],
    "wof:name":"Sairpukur",
    "wof:placetype":"locality"
},
  "geometry": {"coordinates":[88.56177,24.43652],"type":"Point"}
}