{
  "type": "Feature",
  "properties": {
    "gn:admin1_code":"87",
    "gn:admin2_code":"5577.0",
    "gn:admin3_code":"557773.0",
    "gn:admin4_code":"55777323.0",
    "gn:asciiname":"Jaherpara",
    "gn:country_code":"BD",
    "gn:dem":74,
    "gn:feature_class":"P",
    "gn:feature_code":"PPL",
    "gn:name":"J\u0101herp\u0101ra",
    "gn:population":0,
    "gn:timezone":"Asia/Dhaka",
    "iso:country":"BD",
    "name:ben_x_preferred":[
        "J\u0101herp\u0101ra"
    ],
    "wof:name":"Jaherpara",
    "wof:placetype":"locality"
},
  "geometry": {"coordinates":[88.69535,26.34946],"type":"Point"}
}