{
  "type": "Feature",
  "properties": {
    "gn:admin1_code":"81",
    "gn:admin2_code":"3086.0",
    "gn:admin3_code":"308636.0",
    "gn:admin4_code":"30863671.0",
    "gn:asciiname":"Ghatakhan",
    "gn:country_code":"BD",
    "gn:dem":13,
    "gn:feature_class":"P",
    "gn:feature_code":"PPL",
    "gn:name":"Gh\u0101t\u0101kh\u0101n",
    "gn:population":0,
    "gn:timezone":"Asia/Dhaka",
    "iso:country":"BD",
    "wof:name":"Ghatakhan",
    "wof:placetype":"locality"
},
  "geometry": {"coordinates":[90.43607,23.04059],"type":"Point"}
}