{
  "type": "Feature",
  "properties": {
    "gn:admin1_code":"82",
    "gn:admin2_code":"4018.0",
    "gn:admin3_code":"401831.0",
    "gn:admin4_code":"40183147.0",
    "gn:asciiname":"Manjharpota",
    "gn:country_code":"BD",
    "gn:dem":20,
    "gn:feature_class":"P",
    "gn:feature_code":"PPL",
    "gn:name":"Manjharpota",
    "gn:population":0,
    "gn:timezone":"Asia/Dhaka",
    "iso:country":"BD",
    "name:ben_x_preferred":[
        "Manjharpota"
    ],
    "wof:name":"Manjharpota",
    "wof:placetype":"locality"
},
  "geometry": {"coordinates":[88.76436,23.62889],"type":"Point"}
}