{
  "type": "Feature",
  "properties": {
    "gn:admin1_code":"H",
    "gn:admin2_code":"3089",
    "gn:admin3_code":"308990.0",
    "gn:admin4_code":"30899079.0",
    "gn:asciiname":"Joat Meghanat",
    "gn:country_code":"BD",
    "gn:dem":38,
    "gn:feature_class":"P",
    "gn:feature_code":"PPL",
    "gn:name":"Jo\u0101t Megh\u0101nat",
    "gn:population":0,
    "gn:timezone":"Asia/Dhaka",
    "iso:country":"BD",
    "name:ben_x_preferred":[
        "Jo\u0101t Megh\u0101nat"
    ],
    "wof:name":"Joat Meghanat",
    "wof:placetype":"locality"
},
  "geometry": {"coordinates":[89.94495999999999,25.27461],"type":"Point"}
}