{
  "type": "Feature",
  "properties": {
    "gn:admin1_code":"84",
    "gn:admin2_code":"2013.0",
    "gn:admin3_code":"201379.0",
    "gn:admin4_code":"20137904.0",
    "gn:asciiname":"Hapania",
    "gn:country_code":"BD",
    "gn:dem":6,
    "gn:feature_class":"P",
    "gn:feature_code":"PPL",
    "gn:name":"H\u0101p\u0101nia",
    "gn:population":0,
    "gn:timezone":"Asia/Dhaka",
    "iso:country":"BD",
    "wof:name":"Hapania",
    "wof:placetype":"locality"
},
  "geometry": {"coordinates":[90.66667,23.48333],"type":"Point"}
}