{
  "type": "Feature",
  "properties": {
    "gn:admin1_code":"81",
    "gn:admin2_code":"3059.0",
    "gn:admin3_code":"305994.0",
    "gn:admin4_code":"30599431.0",
    "gn:asciiname":"Dwipara",
    "gn:country_code":"BD",
    "gn:dem":5,
    "gn:feature_class":"P",
    "gn:feature_code":"PPL",
    "gn:name":"Dwip\u0101ra",
    "gn:population":0,
    "gn:timezone":"Asia/Dhaka",
    "iso:country":"BD",
    "wof:name":"Dwipara",
    "wof:placetype":"locality"
},
  "geometry": {"coordinates":[90.44419000000001,23.54716],"type":"Point"}
}