{
  "type": "Feature",
  "properties": {
    "gn:admin1_code":"84",
    "gn:admin2_code":"2015.0",
    "gn:admin3_code":"201504.0",
    "gn:admin4_code":"20150447.0",
    "gn:asciiname":"Khuruskhul",
    "gn:country_code":"BD",
    "gn:dem":10,
    "gn:feature_class":"P",
    "gn:feature_code":"PPL",
    "gn:name":"Khuruskhul",
    "gn:population":0,
    "gn:timezone":"Asia/Dhaka",
    "iso:country":"BD",
    "name:ben_x_preferred":[
        "Khuruskhul"
    ],
    "wof:name":"Khuruskhul",
    "wof:placetype":"locality"
},
  "geometry": {"coordinates":[91.86666,22.15863],"type":"Point"}
}