{
  "type": "Feature",
  "properties": {
    "gn:admin1_code":"85",
    "gn:admin2_code":"1006",
    "gn:admin3_code":"100669.0",
    "gn:admin4_code":"10066923.0",
    "gn:asciiname":"South Galaibhanga",
    "gn:country_code":"BD",
    "gn:dem":9,
    "gn:feature_class":"P",
    "gn:feature_code":"PPL",
    "gn:name":"South Gal\u0101ibh\u0101nga",
    "gn:population":0,
    "gn:timezone":"Asia/Dhaka",
    "iso:country":"BD",
    "wof:name":"South Galaibhanga",
    "wof:placetype":"locality"
},
  "geometry": {"coordinates":[90.40810999999999,22.94857],"type":"Point"}
}