{
  "type": "Feature",
  "properties": {
    "gn:admin1_code":"87",
    "gn:admin2_code":"5532",
    "gn:admin3_code":"553282.0",
    "gn:admin4_code":"55328208.0",
    "gn:asciiname":"Yusufpur",
    "gn:country_code":"BD",
    "gn:dem":25,
    "gn:feature_class":"P",
    "gn:feature_code":"PPL",
    "gn:name":"Yusufpur",
    "gn:population":0,
    "gn:timezone":"Asia/Dhaka",
    "iso:country":"BD",
    "name:ben_x_preferred":[
        "Yusufpur"
    ],
    "name:msa_x_preferred":[
        "Yusufpur"
    ],
    "wof:name":"Yusufpur",
    "wof:placetype":"locality"
},
  "geometry": {"coordinates":[89.46425000000001,25.34501],"type":"Point"}
}