{
  "type": "Feature",
  "properties": {
    "gn:admin1_code":"87",
    "gn:admin2_code":"5527.0",
    "gn:admin3_code":"552764.0",
    "gn:admin4_code":"55276443.0",
    "gn:asciiname":"Patalsha",
    "gn:country_code":"BD",
    "gn:dem":30,
    "gn:feature_class":"P",
    "gn:feature_code":"PPL",
    "gn:name":"P\u0101talsha",
    "gn:population":0,
    "gn:timezone":"Asia/Dhaka",
    "iso:country":"BD",
    "name:ben_x_preferred":[
        "P\u0101talsha"
    ],
    "wof:name":"Patalsha",
    "wof:placetype":"locality"
},
  "geometry": {"coordinates":[88.70119,25.49858],"type":"Point"}
}