{
  "type": "Feature",
  "properties": {
    "gn:admin1_code":"82",
    "gn:admin2_code":"4018.0",
    "gn:admin3_code":"401807.0",
    "gn:admin4_code":"40180779.0",
    "gn:asciiname":"Kaitpara",
    "gn:country_code":"BD",
    "gn:dem":17,
    "gn:feature_class":"P",
    "gn:feature_code":"PPL",
    "gn:name":"K\u0101itp\u0101ra",
    "gn:population":0,
    "gn:timezone":"Asia/Dhaka",
    "iso:country":"BD",
    "name:ben_x_preferred":[
        "K\u0101itp\u0101ra"
    ],
    "wof:name":"Kaitpara",
    "wof:placetype":"locality"
},
  "geometry": {"coordinates":[89.01045999999999,23.65681],"type":"Point"}
}