{
  "type": "Feature",
  "properties": {
    "gn:admin1_code":"86",
    "gn:admin2_code":"6090",
    "gn:admin3_code":"609086.0",
    "gn:admin4_code":"60908695.0",
    "gn:asciiname":"Salla",
    "gn:country_code":"BD",
    "gn:dem":8,
    "gn:feature_class":"P",
    "gn:feature_code":"PPL",
    "gn:name":"Salla",
    "gn:population":0,
    "gn:timezone":"Asia/Dhaka",
    "iso:country":"BD",
    "name:bak_x_preferred":[
        "\u0421\u0430\u043b\u043b\u0430"
    ],
    "name:cat_x_preferred":[
        "Salla"
    ],
    "name:ceb_x_preferred":[
        "Salla"
    ],
    "name:ces_x_preferred":[
        "Salla"
    ],
    "name:dan_x_preferred":[
        "Salla"
    ],
    "name:deu_x_preferred":[
        "Salla"
    ],
    "name:epo_x_preferred":[
        "Salla"
    ],
    "name:est_x_preferred":[
        "Salla vald"
    ],
    "name:eus_x_preferred":[
        "Salla"
    ],
    "name:fin_x_preferred":[
        "Salla"
    ],
    "name:fra_x_preferred":[
        "Salla"
    ],
    "name:glg_x_preferred":[
        "Salla"
    ],
    "name:ita_x_preferred":[
        "Salla"
    ],
    "name:lat_x_preferred":[
        "Salla"
    ],
    "name:ltz_x_preferred":[
        "Salla"
    ],
    "name:nld_x_preferred":[
        "Salla"
    ],
    "name:nor_x_preferred":[
        "Salla"
    ],
    "name:oci_x_preferred":[
        "Salla"
    ],
    "name:pol_x_preferred":[
        "Salla"
    ],
    "name:por_x_preferred":[
        "Salla"
    ],
    "name:ron_x_preferred":[
        "Salla"
    ],
    "name:rus_x_preferred":[
        "\u0421\u0430\u043b\u043b\u0430"
    ],
    "name:sme_x_preferred":[
        "Salla"
    ],
    "name:spa_x_preferred":[
        "Salla"
    ],
    "name:sqi_x_preferred":[
        "Salla"
    ],
    "name:swe_x_preferred":[
        "Salla"
    ],
    "name:tur_x_preferred":[
        "Salla"
    ],
    "name:und_x_variant":[
        "Sulla"
    ],
    "name:vie_x_preferred":[
        "Salla"
    ],
    "name:zho_x_preferred":[
        "\u85a9\u62c9"
    ],
    "wof:name":"Salla",
    "wof:placetype":"locality"
},
  "geometry": {"coordinates":[91.26513,24.5872],"type":"Point"}
}