{
  "type": "Feature",
  "properties": {
    "gn:admin1_code":"86",
    "gn:admin2_code":"6090",
    "gn:admin3_code":"609086.0",
    "gn:admin4_code":"60908695.0",
    "gn:asciiname":"Salla",
    "gn:country_code":"BD",
    "gn:dem":8,
    "gn:feature_class":"P",
    "gn:feature_code":"PPL",
    "gn:name":"Salla",
    "gn:population":0,
    "gn:timezone":"Asia/Dhaka",
    "iso:country":"BD",
    "name:und_x_variant":[
        "Sulla"
    ],
    "wof:name":"Salla",
    "wof:placetype":"locality"
},
  "geometry": {"coordinates":[91.26513,24.5872],"type":"Point"}
}