{
  "type": "Feature",
  "properties": {
    "gn:admin1_code":"83",
    "gn:admin2_code":"5010",
    "gn:admin3_code":"501094.0",
    "gn:admin4_code":"50109487.0",
    "gn:asciiname":"Mankair",
    "gn:country_code":"BD",
    "gn:dem":22,
    "gn:feature_class":"P",
    "gn:feature_code":"PPL",
    "gn:name":"M\u0101nkair",
    "gn:population":0,
    "gn:timezone":"Asia/Dhaka",
    "iso:country":"BD",
    "name:ben_x_preferred":[
        "M\u0101nkair"
    ],
    "wof:name":"Mankair",
    "wof:placetype":"locality"
},
  "geometry": {"coordinates":[89.42563,25.04551],"type":"Point"}
}