{
  "type": "Feature",
  "properties": {
    "gn:admin1_code":"87",
    "gn:admin2_code":"5552",
    "gn:admin3_code":"555255.0",
    "gn:admin4_code":"55525583.0",
    "gn:asciiname":"Qismat Nagarbandh",
    "gn:country_code":"BD",
    "gn:dem":35,
    "gn:feature_class":"P",
    "gn:feature_code":"PPL",
    "gn:name":"Qismat Nagarb\u0101ndh",
    "gn:population":0,
    "gn:timezone":"Asia/Dhaka",
    "iso:country":"BD",
    "name:ben_x_preferred":[
        "Qismat Nagarb\u0101ndh"
    ],
    "wof:name":"Qismat Nagarbandh",
    "wof:placetype":"locality"
},
  "geometry": {"coordinates":[89.52424000000001,25.86175],"type":"Point"}
}