{
  "type": "Feature",
  "properties": {
    "gn:admin1_code":"82",
    "gn:asciiname":"Adampur",
    "gn:country_code":"BD",
    "gn:dem":3,
    "gn:feature_class":"P",
    "gn:feature_code":"PPL",
    "gn:name":"Adampur",
    "gn:population":0,
    "gn:timezone":"Asia/Dhaka",
    "iso:country":"BD",
    "name:ben_x_preferred":[
        "Adampur"
    ],
    "name:ben_x_variant":[
        "\u0100dampur B\u012bl"
    ],
    "wof:name":"Adampur",
    "wof:placetype":"locality"
},
  "geometry": {"coordinates":[90.40251000000001,22.38265],"type":"Point"}
}