{
  "type": "Feature",
  "properties": {
    "gn:admin1_code":"81",
    "gn:admin2_code":"3059",
    "gn:admin3_code":"305944.0",
    "gn:admin4_code":"30594431.0",
    "gn:asciiname":"Palgaon",
    "gn:country_code":"BD",
    "gn:dem":8,
    "gn:feature_class":"P",
    "gn:feature_code":"PPL",
    "gn:name":"P\u0101lgaon",
    "gn:population":0,
    "gn:timezone":"Asia/Dhaka",
    "iso:country":"BD",
    "wof:name":"Palgaon",
    "wof:placetype":"locality"
},
  "geometry": {"coordinates":[90.36633999999999,23.47253],"type":"Point"}
}