{
  "type": "Feature",
  "properties": {
    "gn:admin1_code":"84",
    "gn:admin2_code":"2019.0",
    "gn:admin3_code":"201927.0",
    "gn:admin4_code":"20192779.0",
    "gn:asciiname":"Bhomarkandi",
    "gn:country_code":"BD",
    "gn:dem":14,
    "gn:feature_class":"P",
    "gn:feature_code":"PPL",
    "gn:name":"Bhomark\u0101ndi",
    "gn:population":0,
    "gn:timezone":"Asia/Dhaka",
    "iso:country":"BD",
    "wof:name":"Bhomarkandi",
    "wof:placetype":"locality"
},
  "geometry": {"coordinates":[90.98394999999999,23.41039],"type":"Point"}
}