{
  "type": "Feature",
  "properties": {
    "gn:admin1_code":"81",
    "gn:admin2_code":"3026.0",
    "gn:admin3_code":"302640.0",
    "gn:admin4_code":"30264019.0",
    "gn:asciiname":"Bhola",
    "gn:country_code":"BD",
    "gn:dem":14,
    "gn:feature_class":"P",
    "gn:feature_code":"PPL",
    "gn:name":"Bhola",
    "gn:population":0,
    "gn:timezone":"Asia/Dhaka",
    "iso:country":"BD",
    "wof:name":"Bhola",
    "wof:placetype":"locality"
},
  "geometry": {"coordinates":[90.41667,23.78333],"type":"Point"}
}