{
  "type": "Feature",
  "properties": {
    "gn:admin1_code":"83",
    "gn:admin2_code":"5076.0",
    "gn:admin3_code":"507672.0",
    "gn:admin4_code":"50767260.0",
    "gn:asciiname":"Dariapur",
    "gn:country_code":"BD",
    "gn:dem":13,
    "gn:feature_class":"P",
    "gn:feature_code":"PPL",
    "gn:name":"D\u0101ri\u0101pur",
    "gn:population":0,
    "gn:timezone":"Asia/Dhaka",
    "iso:country":"BD",
    "name:ben_x_preferred":[
        "D\u0101ri\u0101pur"
    ],
    "wof:name":"Dariapur",
    "wof:placetype":"locality"
},
  "geometry": {"coordinates":[89.58750999999999,23.96079],"type":"Point"}
}