{
  "type": "Feature",
  "properties": {
    "gn:admin1_code":"82",
    "gn:admin2_code":"4050.0",
    "gn:admin3_code":"405039.0",
    "gn:admin4_code":"40503906.0",
    "gn:asciiname":"Garura Doripara",
    "gn:country_code":"BD",
    "gn:dem":20,
    "gn:feature_class":"P",
    "gn:feature_code":"PPL",
    "gn:name":"Garura Dorip\u0101ra",
    "gn:population":0,
    "gn:timezone":"Asia/Dhaka",
    "iso:country":"BD",
    "name:ben_x_preferred":[
        "Garura Dorip\u0101ra"
    ],
    "wof:name":"Garura Doripara",
    "wof:placetype":"locality"
},
  "geometry": {"coordinates":[88.77946,23.98172000000001],"type":"Point"}
}