{
  "type": "Feature",
  "properties": {
    "gn:admin1_code":"82",
    "gn:admin2_code":"4050.0",
    "gn:admin3_code":"405039.0",
    "gn:admin4_code":"40503927.0",
    "gn:asciiname":"Amdanighat",
    "gn:country_code":"BD",
    "gn:dem":13,
    "gn:feature_class":"P",
    "gn:feature_code":"PPL",
    "gn:name":"\u0100md\u0101nigh\u0101t",
    "gn:population":0,
    "gn:timezone":"Asia/Dhaka",
    "iso:country":"BD",
    "name:ben_x_preferred":[
        "\u0100md\u0101nigh\u0101t"
    ],
    "wof:name":"Amdanighat",
    "wof:placetype":"locality"
},
  "geometry": {"coordinates":[88.76841999999998,24.08232000000001],"type":"Point"}
}