{
  "type": "Feature",
  "properties": {
    "gn:admin1_code":"81",
    "gn:admin2_code":"3067.0",
    "gn:admin3_code":"306702.0",
    "gn:admin4_code":"30670207.0",
    "gn:asciiname":"Ghazipur",
    "gn:country_code":"BD",
    "gn:dem":11,
    "gn:feature_class":"P",
    "gn:feature_code":"PPL",
    "gn:name":"Gh\u0101zipur",
    "gn:population":0,
    "gn:timezone":"Asia/Dhaka",
    "iso:country":"BD",
    "name:bih_x_preferred":[
        "\u0917\u093e\u091c\u0940\u092a\u0941\u0930"
    ],
    "name:bpy_x_preferred":[
        "\u0998\u09be\u099c\u09bf\u09aa\u09c1\u09b0"
    ],
    "name:cat_x_preferred":[
        "Ghazipur"
    ],
    "name:ceb_x_preferred":[
        "Gh\u0101z\u012bpur"
    ],
    "name:deu_x_preferred":[
        "Ghazipur"
    ],
    "name:fra_x_preferred":[
        "Ghazipur"
    ],
    "name:hin_x_preferred":[
        "\u0917\u093c\u093e\u091c\u093c\u0940\u092a\u0941\u0930"
    ],
    "name:ita_x_preferred":[
        "Ghazipur"
    ],
    "name:jpn_x_preferred":[
        "\u30ac\u30fc\u30ba\u30a3\u30fc\u30d7\u30eb"
    ],
    "name:mlg_x_preferred":[
        "Ghazipur"
    ],
    "name:msa_x_preferred":[
        "Ghazipur"
    ],
    "name:new_x_preferred":[
        "\u0917\u093e\u091c\u093f\u092a\u0941\u0930"
    ],
    "name:nld_x_preferred":[
        "Ghazipur"
    ],
    "name:nor_x_preferred":[
        "Ghazipur"
    ],
    "name:pam_x_preferred":[
        "Ghazipur"
    ],
    "name:pan_x_preferred":[
        "\u0a17\u0a3c\u0a3e\u0a1c\u0a3c\u0a40\u0a2a\u0a41\u0a30"
    ],
    "name:pol_x_preferred":[
        "Ghazipur"
    ],
    "name:rus_x_preferred":[
        "\u0413\u0445\u0430\u0437\u0438\u043f\u0443\u0440"
    ],
    "name:san_x_preferred":[
        "\u0917\u093e\u091d\u093f\u092a\u0941\u0930\u092e\u094d"
    ],
    "name:swe_x_preferred":[
        "Ghazipur"
    ],
    "name:tha_x_preferred":[
        "\u0e04\u0e32\u0e0b\u0e35\u0e1b\u0e38\u0e23\u0e30"
    ],
    "name:und_x_variant":[
        "Gh\u0101zipur",
        "G\u0101zipur"
    ],
    "name:urd_x_preferred":[
        "\u063a\u0627\u0632\u06cc \u067e\u0648\u0631"
    ],
    "name:vie_x_preferred":[
        "Ghazipur"
    ],
    "name:zho_x_preferred":[
        "\u52a0\u9f50\u666e\u5c14"
    ],
    "wof:name":"Ghazipur",
    "wof:placetype":"locality"
},
  "geometry": {"coordinates":[90.64354,23.79762],"type":"Point"}
}