{
  "type": "Feature",
  "properties": {
    "gn:admin1_code":"87",
    "gn:admin2_code":"5594.0",
    "gn:admin3_code":"559451.0",
    "gn:admin4_code":"55945140.0",
    "gn:asciiname":"Magura",
    "gn:country_code":"BD",
    "gn:dem":41,
    "gn:feature_class":"P",
    "gn:feature_code":"PPL",
    "gn:name":"M\u0101gura",
    "gn:population":0,
    "gn:timezone":"Asia/Dhaka",
    "iso:country":"BD",
    "name:ben_x_preferred":[
        "M\u0101gura"
    ],
    "wof:name":"Magura",
    "wof:placetype":"locality"
},
  "geometry": {"coordinates":[88.1908,25.8316],"type":"Point"}
}