{
  "type": "Feature",
  "properties": {
    "gn:admin1_code":"85",
    "gn:admin2_code":"1006.0",
    "gn:admin3_code":"100603.0",
    "gn:admin4_code":"10060367.0",
    "gn:asciiname":"East Rahamatpur",
    "gn:country_code":"BD",
    "gn:dem":12,
    "gn:feature_class":"P",
    "gn:feature_code":"PPL",
    "gn:name":"East Rahamatpur",
    "gn:population":0,
    "gn:timezone":"Asia/Dhaka",
    "iso:country":"BD",
    "wof:name":"East Rahamatpur",
    "wof:placetype":"locality"
},
  "geometry": {"coordinates":[90.30672,22.78956],"type":"Point"}
}