{
  "type": "Feature",
  "properties": {
    "gn:admin1_code":"H",
    "gn:admin2_code":"3089",
    "gn:admin3_code":"308937.0",
    "gn:admin4_code":"30893717.0",
    "gn:asciiname":"Dakurpar",
    "gn:country_code":"BD",
    "gn:dem":23,
    "gn:feature_class":"P",
    "gn:feature_code":"PPL",
    "gn:name":"D\u0101kurpar",
    "gn:population":0,
    "gn:timezone":"Asia/Dhaka",
    "iso:country":"BD",
    "name:ben_x_preferred":[
        "D\u0101kurpar"
    ],
    "wof:name":"Dakurpar",
    "wof:placetype":"locality"
},
  "geometry": {"coordinates":[90.04185,25.10087],"type":"Point"}
}