{
  "type": "Feature",
  "properties": {
    "gn:admin1_code":"81",
    "gn:admin2_code":"3048.0",
    "gn:admin3_code":"304892.0",
    "gn:admin4_code":"30489267.0",
    "gn:asciiname":"Bhawal",
    "gn:country_code":"BD",
    "gn:dem":11,
    "gn:feature_class":"P",
    "gn:feature_code":"PPL",
    "gn:name":"Bh\u0101w\u0101l",
    "gn:population":0,
    "gn:timezone":"Asia/Dhaka",
    "iso:country":"BD",
    "wof:name":"Bhawal",
    "wof:placetype":"locality"
},
  "geometry": {"coordinates":[90.82893,24.56439],"type":"Point"}
}