{
  "type": "Feature",
  "properties": {
    "gn:admin1_code":"87",
    "gn:admin2_code":"5549",
    "gn:admin3_code":"554994.0",
    "gn:admin4_code":"55499422.0",
    "gn:asciiname":"Nutan Anantapur",
    "gn:country_code":"BD",
    "gn:dem":29,
    "gn:feature_class":"P",
    "gn:feature_code":"PPL",
    "gn:name":"Nutan \u0100nantapur",
    "gn:population":0,
    "gn:timezone":"Asia/Dhaka",
    "iso:country":"BD",
    "name:ben_x_preferred":[
        "Nutan \u0100nantapur"
    ],
    "wof:name":"Nutan Anantapur",
    "wof:placetype":"locality"
},
  "geometry": {"coordinates":[89.66275,25.70869],"type":"Point"}
}