{
  "type": "Feature",
  "properties": {
    "gn:admin1_code":"85",
    "gn:admin2_code":"1078.0",
    "gn:admin3_code":"107838.0",
    "gn:admin4_code":"10783835.0",
    "gn:asciiname":"Daspara",
    "gn:country_code":"BD",
    "gn:dem":7,
    "gn:feature_class":"P",
    "gn:feature_code":"PPL",
    "gn:name":"D\u0101sp\u0101ra",
    "gn:population":0,
    "gn:timezone":"Asia/Dhaka",
    "iso:country":"BD",
    "name:ben_x_preferred":[
        "D\u0101sp\u0101ra"
    ],
    "wof:name":"Daspara",
    "wof:placetype":"locality"
},
  "geometry": {"coordinates":[90.57082,22.38731],"type":"Point"}
}