{
  "type": "Feature",
  "properties": {
    "gn:admin1_code":"84",
    "gn:admin2_code":"2019",
    "gn:admin3_code":"201936.0",
    "gn:admin4_code":"20193690.0",
    "gn:asciiname":"Sukipur",
    "gn:country_code":"BD",
    "gn:dem":9,
    "gn:feature_class":"P",
    "gn:feature_code":"PPL",
    "gn:name":"Sukipur",
    "gn:population":0,
    "gn:timezone":"Asia/Dhaka",
    "iso:country":"BD",
    "wof:name":"Sukipur",
    "wof:placetype":"locality"
},
  "geometry": {"coordinates":[90.76692,23.50436],"type":"Point"}
}