{
  "type": "Feature",
  "properties": {
    "gn:admin1_code":"87",
    "gn:admin2_code":"5532",
    "gn:admin3_code":"553291.0",
    "gn:admin4_code":"55329182.0",
    "gn:asciiname":"Sibram",
    "gn:country_code":"BD",
    "gn:dem":28,
    "gn:feature_class":"P",
    "gn:feature_code":"PPL",
    "gn:name":"Sibr\u0101m",
    "gn:population":0,
    "gn:timezone":"Asia/Dhaka",
    "iso:country":"BD",
    "wof:name":"Sibram",
    "wof:placetype":"locality"
},
  "geometry": {"coordinates":[89.45966999999997,25.54744],"type":"Point"}
}