{
  "type": "Feature",
  "properties": {
    "gn:admin1_code":"83",
    "gn:admin2_code":"5064",
    "gn:admin3_code":"506479.0",
    "gn:admin4_code":"50647955.0",
    "gn:asciiname":"Khura Ganoir",
    "gn:country_code":"BD",
    "gn:dem":29,
    "gn:feature_class":"P",
    "gn:feature_code":"PPL",
    "gn:name":"Khura Ganoir",
    "gn:population":0,
    "gn:timezone":"Asia/Dhaka",
    "iso:country":"BD",
    "name:ben_x_preferred":[
        "Khura Ganoir"
    ],
    "name:ben_x_variant":[
        "Khorda G\u0101nair"
    ],
    "name:und_x_variant":[
        "Khord Ganair",
        "Khorda Gunair",
        "Khorda Ganoir"
    ],
    "wof:name":"Khura Ganoir",
    "wof:placetype":"locality"
},
  "geometry": {"coordinates":[88.46006,24.99812],"type":"Point"}
}