{
  "type": "Feature",
  "properties": {
    "gn:admin1_code":"H",
    "gn:admin2_code":"3039",
    "gn:admin3_code":"303915.0",
    "gn:admin4_code":"30391587.0",
    "gn:asciiname":"Jhawdanga",
    "gn:country_code":"BD",
    "gn:dem":27,
    "gn:feature_class":"P",
    "gn:feature_code":"PPL",
    "gn:name":"Jh\u0101wd\u0101nga",
    "gn:population":0,
    "gn:timezone":"Asia/Dhaka",
    "iso:country":"BD",
    "name:ben_x_preferred":[
        "Jh\u0101wd\u0101nga"
    ],
    "wof:name":"Jhawdanga",
    "wof:placetype":"locality"
},
  "geometry": {"coordinates":[89.8359,25.31439],"type":"Point"}
}