{
  "type": "Feature",
  "properties": {
    "gn:admin1_code":"84",
    "gn:admin2_code":"2003.0",
    "gn:admin3_code":"200395.0",
    "gn:admin4_code":"20039538.0",
    "gn:asciiname":"Mowdok",
    "gn:country_code":"BD",
    "gn:dem":83,
    "gn:feature_class":"P",
    "gn:feature_code":"PPL",
    "gn:name":"Mowdok",
    "gn:population":0,
    "gn:timezone":"Asia/Dhaka",
    "iso:country":"BD",
    "name:ben_x_preferred":[
        "Mowdok"
    ],
    "wof:name":"Mowdok",
    "wof:placetype":"locality"
},
  "geometry": {"coordinates":[92.57853,21.57863],"type":"Point"}
}