{
  "type": "Feature",
  "properties": {
    "gn:admin1_code":"83",
    "gn:admin2_code":"5010",
    "gn:admin3_code":"501095.0",
    "gn:admin4_code":"50109584.0",
    "gn:asciiname":"Maheshpara",
    "gn:country_code":"BD",
    "gn:dem":21,
    "gn:feature_class":"P",
    "gn:feature_code":"PPL",
    "gn:name":"Maheshp\u0101ra",
    "gn:population":0,
    "gn:timezone":"Asia/Dhaka",
    "iso:country":"BD",
    "name:ben_x_preferred":[
        "Maheshp\u0101ra"
    ],
    "wof:name":"Maheshpara",
    "wof:placetype":"locality"
},
  "geometry": {"coordinates":[89.56707,25.02458],"type":"Point"}
}