{
  "type": "Feature",
  "properties": {
    "gn:admin1_code":"82",
    "gn:admin2_code":"4087",
    "gn:admin3_code":"408747.0",
    "gn:admin4_code":"40874731.0",
    "gn:asciiname":"Tona",
    "gn:country_code":"BD",
    "gn:dem":8,
    "gn:feature_class":"P",
    "gn:feature_code":"PPL",
    "gn:name":"Tona",
    "gn:population":0,
    "gn:timezone":"Asia/Dhaka",
    "iso:country":"BD",
    "name:ben_x_preferred":[
        "Tona"
    ],
    "wof:name":"Tona",
    "wof:placetype":"locality"
},
  "geometry": {"coordinates":[89.11581,22.47226],"type":"Point"}
}