{
  "type": "Feature",
  "properties": {
    "gn:admin1_code":"82",
    "gn:admin2_code":"4055",
    "gn:admin3_code":"405566.0",
    "gn:admin4_code":"40556642.0",
    "gn:asciiname":"Khajura",
    "gn:country_code":"BD",
    "gn:dem":14,
    "gn:feature_class":"P",
    "gn:feature_code":"PPL",
    "gn:name":"Kh\u0101jura",
    "gn:population":0,
    "gn:timezone":"Asia/Dhaka",
    "iso:country":"BD",
    "wof:name":"Khajura",
    "wof:placetype":"locality"
},
  "geometry": {"coordinates":[89.57259000000001,23.43902000000001],"type":"Point"}
}