{
  "type": "Feature",
  "properties": {
    "gn:admin1_code":"84",
    "gn:admin2_code":"2013",
    "gn:admin3_code":"201349.0",
    "gn:admin4_code":"20134975.0",
    "gn:asciiname":"Kirtankhola",
    "gn:country_code":"BD",
    "gn:dem":11,
    "gn:feature_class":"P",
    "gn:feature_code":"PPL",
    "gn:name":"Kirtankhola",
    "gn:population":0,
    "gn:timezone":"Asia/Dhaka",
    "iso:country":"BD",
    "name:ben_x_preferred":[
        "\u0995\u09c0\u09b0\u09cd\u09a4\u09a8\u0996\u09cb\u09b2\u09be \u09a8\u09a6\u09c0"
    ],
    "name:hin_x_preferred":[
        "\u0915\u0940\u0930\u094d\u0924\u0928\u0916\u094b\u0932\u093e \u0928\u0926\u0940"
    ],
    "wof:name":"Kirtankhola",
    "wof:placetype":"locality"
},
  "geometry": {"coordinates":[90.78628999999999,23.30195],"type":"Point"}
}