{
  "type": "Feature",
  "properties": {
    "gn:admin1_code":"84",
    "gn:admin2_code":"2013.0",
    "gn:admin3_code":"201395.0",
    "gn:admin4_code":"20139520.0",
    "gn:asciiname":"Ekatari",
    "gn:country_code":"BD",
    "gn:dem":11,
    "gn:feature_class":"P",
    "gn:feature_code":"PPL",
    "gn:name":"Ek\u0101tari",
    "gn:population":0,
    "gn:timezone":"Asia/Dhaka",
    "iso:country":"BD",
    "wof:name":"Ekatari",
    "wof:placetype":"locality"
},
  "geometry": {"coordinates":[90.98045999999999,23.18193],"type":"Point"}
}