{
  "type": "Feature",
  "properties": {
    "gn:admin1_code":"83",
    "gn:admin2_code":"5010",
    "gn:admin3_code":"501094.0",
    "gn:admin4_code":"50109463.0",
    "gn:asciiname":"Goneshpur",
    "gn:country_code":"BD",
    "gn:dem":25,
    "gn:feature_class":"P",
    "gn:feature_code":"PPL",
    "gn:name":"Goneshpur",
    "gn:population":0,
    "gn:timezone":"Asia/Dhaka",
    "iso:country":"BD",
    "name:ben_x_preferred":[
        "Goneshpur"
    ],
    "wof:name":"Goneshpur",
    "wof:placetype":"locality"
},
  "geometry": {"coordinates":[89.34496999999998,25.02069],"type":"Point"}
}