{
  "type": "Feature",
  "properties": {
    "gn:admin1_code":"87",
    "gn:admin2_code":"5573.0",
    "gn:admin3_code":"557315.0",
    "gn:admin4_code":"55731547.0",
    "gn:asciiname":"Namazipara",
    "gn:country_code":"BD",
    "gn:dem":60,
    "gn:feature_class":"P",
    "gn:feature_code":"PPL",
    "gn:name":"Nam\u0101zip\u0101ra",
    "gn:population":0,
    "gn:timezone":"Asia/Dhaka",
    "iso:country":"BD",
    "name:ben_x_preferred":[
        "Nam\u0101zip\u0101ra"
    ],
    "wof:name":"Namazipara",
    "wof:placetype":"locality"
},
  "geometry": {"coordinates":[88.82890999999999,26.19822000000001],"type":"Point"}
}