{
  "type": "Feature",
  "properties": {
    "gn:admin1_code":"84",
    "gn:admin2_code":"2015.0",
    "gn:admin3_code":"201570.0",
    "gn:admin4_code":"20157069.0",
    "gn:asciiname":"Bagabili",
    "gn:country_code":"BD",
    "gn:dem":25,
    "gn:feature_class":"P",
    "gn:feature_code":"PPL",
    "gn:name":"Bag\u0101bili",
    "gn:population":0,
    "gn:timezone":"Asia/Dhaka",
    "iso:country":"BD",
    "name:ben_x_preferred":[
        "Bag\u0101bili"
    ],
    "name:und_x_variant":[
        "Bagabile"
    ],
    "wof:name":"Bagabili",
    "wof:placetype":"locality"
},
  "geometry": {"coordinates":[92.04013999999999,22.59486],"type":"Point"}
}