{
  "type": "Feature",
  "properties": {
    "gn:admin1_code":"81",
    "gn:admin2_code":"3026.0",
    "gn:admin3_code":"302672.0",
    "gn:admin4_code":"30267276.0",
    "gn:asciiname":"Ghashirdia",
    "gn:country_code":"BD",
    "gn:dem":5,
    "gn:feature_class":"P",
    "gn:feature_code":"PPL",
    "gn:name":"Gh\u0101shirdia",
    "gn:population":0,
    "gn:timezone":"Asia/Dhaka",
    "iso:country":"BD",
    "wof:name":"Ghashirdia",
    "wof:placetype":"locality"
},
  "geometry": {"coordinates":[90.33333,23.78333],"type":"Point"}
}