{
  "type": "Feature",
  "properties": {
    "gn:admin1_code":"81",
    "gn:admin2_code":"3048",
    "gn:admin3_code":"304842.0",
    "gn:admin4_code":"30484243.0",
    "gn:asciiname":"Madakkhala",
    "gn:country_code":"BD",
    "gn:dem":15,
    "gn:feature_class":"P",
    "gn:feature_code":"PPL",
    "gn:name":"M\u0101d\u0101kkhala",
    "gn:population":0,
    "gn:timezone":"Asia/Dhaka",
    "iso:country":"BD",
    "name:und_x_variant":[
        "M\u0101d\u0101kkhala",
        "Modakhala"
    ],
    "wof:name":"Madakkhala",
    "wof:placetype":"locality"
},
  "geometry": {"coordinates":[90.83485,24.43403],"type":"Point"}
}