{
  "type": "Feature",
  "properties": {
    "gn:admin1_code":"87",
    "gn:admin2_code":"5527.0",
    "gn:admin3_code":"552710.0",
    "gn:admin4_code":"55271023.0",
    "gn:asciiname":"Chak Durgapur",
    "gn:country_code":"BD",
    "gn:dem":28,
    "gn:feature_class":"P",
    "gn:feature_code":"PPL",
    "gn:name":"Chak Durg\u0101pur",
    "gn:population":0,
    "gn:timezone":"Asia/Dhaka",
    "iso:country":"BD",
    "name:ben_x_preferred":[
        "Chak Durg\u0101pur"
    ],
    "wof:name":"Chak Durgapur",
    "wof:placetype":"locality"
},
  "geometry": {"coordinates":[88.95265000000001,25.38379],"type":"Point"}
}