{
  "type": "Feature",
  "properties": {
    "gn:admin1_code":"81",
    "gn:admin2_code":"3093",
    "gn:admin3_code":"309357.0",
    "gn:admin4_code":"30935728.0",
    "gn:asciiname":"Malka",
    "gn:country_code":"BD",
    "gn:dem":13,
    "gn:feature_class":"P",
    "gn:feature_code":"PPL",
    "gn:name":"Malka",
    "gn:population":0,
    "gn:timezone":"Asia/Dhaka",
    "iso:country":"BD",
    "wof:name":"Malka",
    "wof:placetype":"locality"
},
  "geometry": {"coordinates":[90.07550000000001,24.56781],"type":"Point"}
}