{
  "type": "Feature",
  "properties": {
    "gn:admin1_code":"83",
    "gn:admin2_code":"5064",
    "gn:admin3_code":"506460.0",
    "gn:admin4_code":"50646094.0",
    "gn:asciiname":"Kadoa",
    "gn:country_code":"BD",
    "gn:dem":21,
    "gn:feature_class":"P",
    "gn:feature_code":"PPL",
    "gn:name":"K\u0101doa",
    "gn:population":0,
    "gn:timezone":"Asia/Dhaka",
    "iso:country":"BD",
    "name:ben_x_preferred":[
        "K\u0101doa"
    ],
    "wof:name":"Kadoa",
    "wof:placetype":"locality"
},
  "geometry": {"coordinates":[88.95029,24.84095],"type":"Point"}
}