{
  "type": "Feature",
  "properties": {
    "gn:admin1_code":"87",
    "gn:admin2_code":"5549",
    "gn:admin3_code":"554994.0",
    "gn:admin4_code":"55499483.0",
    "gn:asciiname":"Paschim Kaluadanga",
    "gn:country_code":"BD",
    "gn:dem":29,
    "gn:feature_class":"P",
    "gn:feature_code":"PPL",
    "gn:name":"Paschim K\u0101lu\u0101d\u0101nga",
    "gn:population":0,
    "gn:timezone":"Asia/Dhaka",
    "iso:country":"BD",
    "name:ben_x_preferred":[
        "Paschim K\u0101lu\u0101d\u0101nga"
    ],
    "wof:name":"Paschim Kaluadanga",
    "wof:placetype":"locality"
},
  "geometry": {"coordinates":[89.57295999999999,25.66021],"type":"Point"}
}