{
  "type": "Feature",
  "properties": {
    "gn:admin1_code":"83",
    "gn:admin2_code":"5081",
    "gn:admin3_code":"508112.0",
    "gn:admin4_code":"50811212.0",
    "gn:asciiname":"Kismat Behanali",
    "gn:country_code":"BD",
    "gn:dem":18,
    "gn:feature_class":"P",
    "gn:feature_code":"PPL",
    "gn:name":"Kismat Behanali",
    "gn:population":0,
    "gn:timezone":"Asia/Dhaka",
    "iso:country":"BD",
    "name:ben_x_preferred":[
        "Kismat Behanali"
    ],
    "wof:name":"Kismat Behanali",
    "wof:placetype":"locality"
},
  "geometry": {"coordinates":[88.84726999999999,24.60985],"type":"Point"}
}