{
  "type": "Feature",
  "properties": {
    "gn:admin1_code":"87",
    "gn:admin2_code":"5549",
    "gn:admin3_code":"554979.0",
    "gn:admin4_code":"55497971.0",
    "gn:asciiname":"Goalgram",
    "gn:country_code":"BD",
    "gn:dem":28,
    "gn:feature_class":"P",
    "gn:feature_code":"PPL",
    "gn:name":"Go\u0101lgr\u0101m",
    "gn:population":0,
    "gn:timezone":"Asia/Dhaka",
    "iso:country":"BD",
    "name:ben_x_preferred":[
        "Go\u0101lgr\u0101m"
    ],
    "name:ceb_x_preferred":[
        "Go\u0101lgr\u0101m"
    ],
    "name:swe_x_preferred":[
        "Go\u0101lgr\u0101m"
    ],
    "wof:name":"Goalgram",
    "wof:placetype":"locality"
},
  "geometry": {"coordinates":[89.83225,25.54388],"type":"Point"}
}