{
  "type": "Feature",
  "properties": {
    "gn:admin1_code":"84",
    "gn:admin2_code":"2015.0",
    "gn:admin3_code":"201570.0",
    "gn:admin4_code":"20157051.0",
    "gn:asciiname":"Dakhin Khat Chek",
    "gn:country_code":"BD",
    "gn:dem":10,
    "gn:feature_class":"P",
    "gn:feature_code":"PPL",
    "gn:name":"Dakhin Khat Chek",
    "gn:population":0,
    "gn:timezone":"Asia/Dhaka",
    "iso:country":"BD",
    "name:ben_x_preferred":[
        "Dakhin Khat Chek"
    ],
    "wof:name":"Dakhin Khat Chek",
    "wof:placetype":"locality"
},
  "geometry": {"coordinates":[92.0565,22.46114],"type":"Point"}
}