{
  "type": "Feature",
  "properties": {
    "gn:admin1_code":"84",
    "gn:admin2_code":"2013.0",
    "gn:admin3_code":"201379.0",
    "gn:admin4_code":"20137973.0",
    "gn:asciiname":"Bara Ani",
    "gn:cc2":"BD",
    "gn:country_code":"BD",
    "gn:dem":6,
    "gn:feature_class":"P",
    "gn:feature_code":"PPL",
    "gn:name":"B\u0101ra \u0100ni",
    "gn:population":0,
    "gn:timezone":"Asia/Dhaka",
    "iso:country":"BD",
    "name:und_x_variant":[
        "Barani",
        "B\u0101ra \u0100ni"
    ],
    "wof:name":"Bara Ani",
    "wof:placetype":"locality"
},
  "geometry": {"coordinates":[90.59999999999999,23.45],"type":"Point"}
}