{
  "type": "Feature",
  "properties": {
    "gn:admin1_code":"84",
    "gn:admin2_code":"2015.0",
    "gn:admin3_code":"201508.0",
    "gn:admin4_code":"20150850.0",
    "gn:asciiname":"Manikpathan",
    "gn:country_code":"BD",
    "gn:dem":4,
    "gn:feature_class":"P",
    "gn:feature_code":"PPL",
    "gn:name":"M\u0101nikp\u0101th\u0101n",
    "gn:population":0,
    "gn:timezone":"Asia/Dhaka",
    "iso:country":"BD",
    "name:ben_x_preferred":[
        "M\u0101nikp\u0101th\u0101n"
    ],
    "wof:name":"Manikpathan",
    "wof:placetype":"locality"
},
  "geometry": {"coordinates":[91.92241,22.05361],"type":"Point"}
}