{
  "type": "Feature",
  "properties": {
    "gn:admin1_code":"87",
    "gn:admin2_code":"5573",
    "gn:admin3_code":"557345.0",
    "gn:admin4_code":"55734508.0",
    "gn:asciiname":"Purba Daliram",
    "gn:country_code":"BD",
    "gn:dem":43,
    "gn:feature_class":"P",
    "gn:feature_code":"PPL",
    "gn:name":"Purba Dal\u012br\u0101m",
    "gn:population":0,
    "gn:timezone":"Asia/Dhaka",
    "iso:country":"BD",
    "name:ben_x_preferred":[
        "Purba Dal\u012br\u0101m"
    ],
    "wof:name":"Purba Daliram",
    "wof:placetype":"locality"
},
  "geometry": {"coordinates":[89.10858,25.92413],"type":"Point"}
}