{
  "type": "Feature",
  "properties": {
    "gn:admin1_code":"87",
    "gn:admin2_code":"5527.0",
    "gn:admin3_code":"552712.0",
    "gn:admin4_code":"55271234.0",
    "gn:asciiname":"Saldanga Hat",
    "gn:country_code":"BD",
    "gn:dem":47,
    "gn:feature_class":"P",
    "gn:feature_code":"PPL",
    "gn:name":"S\u0101ldanga H\u0101t",
    "gn:population":0,
    "gn:timezone":"Asia/Dhaka",
    "iso:country":"BD",
    "name:ben_x_preferred":[
        "S\u0101ldanga H\u0101t"
    ],
    "wof:name":"Saldanga Hat",
    "wof:placetype":"locality"
},
  "geometry": {"coordinates":[88.66847,25.93612000000001],"type":"Point"}
}