{
  "type": "Feature",
  "properties": {
    "gn:admin1_code":"86",
    "gn:admin2_code":"6090",
    "gn:admin3_code":"609089.0",
    "gn:admin4_code":"60908955.0",
    "gn:asciiname":"Manoharpur",
    "gn:country_code":"BD",
    "gn:dem":15,
    "gn:feature_class":"P",
    "gn:feature_code":"PPL",
    "gn:name":"Manoharpur",
    "gn:population":0,
    "gn:timezone":"Asia/Dhaka",
    "iso:country":"BD",
    "wof:name":"Manoharpur",
    "wof:placetype":"locality"
},
  "geometry": {"coordinates":[91.46473,25.03709],"type":"Point"}
}