{
  "type": "Feature",
  "properties": {
    "gn:admin1_code":"H",
    "gn:admin2_code":"3061",
    "gn:admin3_code":"306194.0",
    "gn:admin4_code":"30619409.0",
    "gn:asciiname":"Kazir Simla",
    "gn:country_code":"BD",
    "gn:dem":19,
    "gn:feature_class":"P",
    "gn:feature_code":"PPL",
    "gn:name":"K\u0101zir Simla",
    "gn:population":0,
    "gn:timezone":"Asia/Dhaka",
    "iso:country":"BD",
    "wof:name":"Kazir Simla",
    "wof:placetype":"locality"
},
  "geometry": {"coordinates":[90.39209,24.65915],"type":"Point"}
}