{
  "type": "Feature",
  "properties": {
    "gn:admin1_code":"H",
    "gn:admin2_code":"3089",
    "gn:admin3_code":"308988.0",
    "gn:admin4_code":"30898806.0",
    "gn:asciiname":"Mrijapur",
    "gn:country_code":"BD",
    "gn:dem":23,
    "gn:feature_class":"P",
    "gn:feature_code":"PPL",
    "gn:name":"Mrijapur",
    "gn:population":0,
    "gn:timezone":"Asia/Dhaka",
    "iso:country":"BD",
    "name:ben_x_preferred":[
        "Mrijapur"
    ],
    "wof:name":"Mrijapur",
    "wof:placetype":"locality"
},
  "geometry": {"coordinates":[90.02576999999999,25.05756],"type":"Point"}
}