{
  "type": "Feature",
  "properties": {
    "gn:admin1_code":"84",
    "gn:admin2_code":"2013.0",
    "gn:admin3_code":"201349.0",
    "gn:admin4_code":"20134935.0",
    "gn:asciiname":"Chanderbagh",
    "gn:country_code":"BD",
    "gn:dem":12,
    "gn:feature_class":"P",
    "gn:feature_code":"PPL",
    "gn:name":"Chanderb\u0101gh",
    "gn:population":0,
    "gn:timezone":"Asia/Dhaka",
    "iso:country":"BD",
    "name:und_x_variant":[
        "Chanderb\u0101gh",
        "Ch\u0101nderb\u0101g"
    ],
    "wof:name":"Chanderbagh",
    "wof:placetype":"locality"
},
  "geometry": {"coordinates":[90.79189,23.22394],"type":"Point"}
}