{
  "type": "Feature",
  "properties": {
    "gn:admin1_code":"87",
    "gn:admin2_code":"5585.0",
    "gn:admin3_code":"558573.0",
    "gn:admin4_code":"55857385.0",
    "gn:asciiname":"Ram Gopal",
    "gn:country_code":"BD",
    "gn:dem":29,
    "gn:feature_class":"P",
    "gn:feature_code":"PPL",
    "gn:name":"R\u0101m Gop\u0101l",
    "gn:population":0,
    "gn:timezone":"Asia/Dhaka",
    "iso:country":"BD",
    "name:ben_x_preferred":[
        "R\u0101m Gop\u0101l"
    ],
    "name:fra_x_preferred":[
        "Ram Gopal"
    ],
    "wof:name":"Ram Gopal",
    "wof:placetype":"locality"
},
  "geometry": {"coordinates":[89.47807,25.65135],"type":"Point"}
}