{
  "type": "Feature",
  "properties": {
    "gn:admin1_code":"87",
    "gn:admin2_code":"5577.0",
    "gn:admin3_code":"557790.0",
    "gn:admin4_code":"55779040.0",
    "gn:asciiname":"Dauforigachh",
    "gn:country_code":"BD",
    "gn:dem":85,
    "gn:feature_class":"P",
    "gn:feature_code":"PPL",
    "gn:name":"Daufor\u012bg\u0101chh",
    "gn:population":0,
    "gn:timezone":"Asia/Dhaka",
    "iso:country":"BD",
    "name:ben_x_preferred":[
        "Daufor\u012bg\u0101chh"
    ],
    "wof:name":"Dauforigachh",
    "wof:placetype":"locality"
},
  "geometry": {"coordinates":[88.49468,26.44899],"type":"Point"}
}