{
  "type": "Feature",
  "properties": {
    "gn:admin1_code":"82",
    "gn:admin2_code":"4065.0",
    "gn:admin3_code":"406552.0",
    "gn:admin4_code":"40655215.0",
    "gn:asciiname":"Pachail",
    "gn:country_code":"BD",
    "gn:dem":11,
    "gn:feature_class":"P",
    "gn:feature_code":"PPL",
    "gn:name":"P\u0101ch\u0101il",
    "gn:population":0,
    "gn:timezone":"Asia/Dhaka",
    "iso:country":"BD",
    "name:ben_x_preferred":[
        "P\u0101ch\u0101il"
    ],
    "wof:name":"Pachail",
    "wof:placetype":"locality"
},
  "geometry": {"coordinates":[89.76026999999998,23.17744],"type":"Point"}
}