{
  "type": "Feature",
  "properties": {
    "gn:admin1_code":"H",
    "gn:admin2_code":"3072.0",
    "gn:admin3_code":"307204.0",
    "gn:admin4_code":"30720411.0",
    "gn:asciiname":"Baniajan",
    "gn:country_code":"BD",
    "gn:dem":17,
    "gn:feature_class":"P",
    "gn:feature_code":"PPL",
    "gn:name":"B\u0101ni\u0101j\u0101n",
    "gn:population":0,
    "gn:timezone":"Asia/Dhaka",
    "iso:country":"BD",
    "wof:name":"Baniajan",
    "wof:placetype":"locality"
},
  "geometry": {"coordinates":[90.85102999999999,24.80656],"type":"Point"}
}