{
  "type": "Feature",
  "properties": {
    "gn:admin1_code":"81",
    "gn:admin2_code":"3026",
    "gn:admin3_code":"302618.0",
    "gn:admin4_code":"30261873.0",
    "gn:asciiname":"Jaymangal",
    "gn:country_code":"BD",
    "gn:dem":5,
    "gn:feature_class":"P",
    "gn:feature_code":"PPL",
    "gn:name":"Jaymangal",
    "gn:population":0,
    "gn:timezone":"Asia/Dhaka",
    "iso:country":"BD",
    "wof:name":"Jaymangal",
    "wof:placetype":"locality"
},
  "geometry": {"coordinates":[90.09999999999999,23.63333],"type":"Point"}
}