{
  "type": "Feature",
  "properties": {
    "gn:admin1_code":"85",
    "gn:admin2_code":"1079.0",
    "gn:admin3_code":"107958.0",
    "gn:admin4_code":"10795860.0",
    "gn:asciiname":"Uttar Mithakhali",
    "gn:country_code":"BD",
    "gn:dem":9,
    "gn:feature_class":"P",
    "gn:feature_code":"PPL",
    "gn:name":"Uttar Mithakhali",
    "gn:population":0,
    "gn:timezone":"Asia/Dhaka",
    "iso:country":"BD",
    "name:ben_x_preferred":[
        "Uttar Mithakhali"
    ],
    "wof:name":"Uttar Mithakhali",
    "wof:placetype":"locality"
},
  "geometry": {"coordinates":[89.94891,22.32526],"type":"Point"}
}