{
  "type": "Feature",
  "properties": {
    "gn:admin1_code":"82",
    "gn:admin2_code":"4018.0",
    "gn:admin3_code":"401831.0",
    "gn:admin4_code":"40183123.0",
    "gn:asciiname":"Chhagharia",
    "gn:country_code":"BD",
    "gn:dem":16,
    "gn:feature_class":"P",
    "gn:feature_code":"PPL",
    "gn:name":"Chhagharia",
    "gn:population":0,
    "gn:timezone":"Asia/Dhaka",
    "iso:country":"BD",
    "name:ben_x_preferred":[
        "Chhagharia"
    ],
    "wof:name":"Chhagharia",
    "wof:placetype":"locality"
},
  "geometry": {"coordinates":[88.77372,23.51024],"type":"Point"}
}