{
  "type": "Feature",
  "properties": {
    "gn:admin1_code":"84",
    "gn:admin2_code":"2022.0",
    "gn:admin3_code":"202224.0",
    "gn:admin4_code":"20222483.0",
    "gn:asciiname":"Ichakali",
    "gn:country_code":"BD",
    "gn:dem":5,
    "gn:feature_class":"P",
    "gn:feature_code":"PPL",
    "gn:name":"Ich\u0101kali",
    "gn:population":0,
    "gn:timezone":"Asia/Dhaka",
    "iso:country":"BD",
    "name:ben_x_preferred":[
        "Ich\u0101kali"
    ],
    "wof:name":"Ichakali",
    "wof:placetype":"locality"
},
  "geometry": {"coordinates":[92.01729,21.55389],"type":"Point"}
}