{
  "type": "Feature",
  "properties": {
    "gn:admin1_code":"H",
    "gn:admin2_code":"3039",
    "gn:admin3_code":"303961.0",
    "gn:admin4_code":"30396128.0",
    "gn:asciiname":"Gokulerpara",
    "gn:country_code":"BD",
    "gn:dem":24,
    "gn:feature_class":"P",
    "gn:feature_code":"PPL",
    "gn:name":"Gokulerpara",
    "gn:population":0,
    "gn:timezone":"Asia/Dhaka",
    "iso:country":"BD",
    "name:ben_x_preferred":[
        "Gokulerpara"
    ],
    "wof:name":"Gokulerpara",
    "wof:placetype":"locality"
},
  "geometry": {"coordinates":[89.82755999999998,25.05351],"type":"Point"}
}