{
  "type": "Feature",
  "properties": {
    "gn:admin1_code":"83",
    "gn:admin2_code":"5064.0",
    "gn:admin3_code":"506450.0",
    "gn:admin4_code":"50645076.0",
    "gn:asciiname":"Damapara",
    "gn:country_code":"BD",
    "gn:dem":23,
    "gn:feature_class":"P",
    "gn:feature_code":"PPL",
    "gn:name":"D\u0101m\u0101p\u0101ra",
    "gn:population":0,
    "gn:timezone":"Asia/Dhaka",
    "iso:country":"BD",
    "name:ben_x_preferred":[
        "D\u0101m\u0101p\u0101ra"
    ],
    "wof:name":"Damapara",
    "wof:placetype":"locality"
},
  "geometry": {"coordinates":[88.83033,24.95246],"type":"Point"}
}