{
  "type": "Feature",
  "properties": {
    "gn:admin1_code":"83",
    "gn:admin2_code":"5010.0",
    "gn:admin3_code":"501006.0",
    "gn:admin4_code":"50100681.0",
    "gn:asciiname":"Dhekra",
    "gn:country_code":"BD",
    "gn:dem":20,
    "gn:feature_class":"P",
    "gn:feature_code":"PPL",
    "gn:name":"Dhekra",
    "gn:population":0,
    "gn:timezone":"Asia/Dhaka",
    "iso:country":"BD",
    "name:ben_x_preferred":[
        "Daik\u0101ra"
    ],
    "name:ben_x_variant":[
        "Dhekra"
    ],
    "wof:name":"Dhekra",
    "wof:placetype":"locality"
},
  "geometry": {"coordinates":[88.97948000000002,24.76135],"type":"Point"}
}