{
  "type": "Feature",
  "properties": {
    "gn:admin1_code":"87",
    "gn:admin2_code":"5594.0",
    "gn:admin3_code":"559482.0",
    "gn:admin4_code":"55948251.0",
    "gn:asciiname":"Dakshin Malancha",
    "gn:country_code":"BD",
    "gn:dem":43,
    "gn:feature_class":"P",
    "gn:feature_code":"PPL",
    "gn:name":"Dakshin Malancha",
    "gn:population":0,
    "gn:timezone":"Asia/Dhaka",
    "iso:country":"BD",
    "name:ben_x_preferred":[
        "Dakshin Malancha"
    ],
    "wof:name":"Dakshin Malancha",
    "wof:placetype":"locality"
},
  "geometry": {"coordinates":[88.36281,25.75788],"type":"Point"}
}