{
  "type": "Feature",
  "properties": {
    "gn:admin1_code":"84",
    "gn:admin2_code":"2084.0",
    "gn:admin3_code":"208425.0",
    "gn:admin4_code":"20842576.0",
    "gn:asciiname":"Majherpara",
    "gn:country_code":"BD",
    "gn:dem":35,
    "gn:feature_class":"P",
    "gn:feature_code":"PPL",
    "gn:name":"M\u0101jherp\u0101ra",
    "gn:population":0,
    "gn:timezone":"Asia/Dhaka",
    "iso:country":"BD",
    "name:ben_x_preferred":[
        "M\u0101jherp\u0101ra"
    ],
    "wof:name":"Majherpara",
    "wof:placetype":"locality"
},
  "geometry": {"coordinates":[92.00436999999999,22.59735],"type":"Point"}
}