{
  "type": "Feature",
  "properties": {
    "gn:admin1_code":"82",
    "gn:admin2_code":"4065.0",
    "gn:admin3_code":"406528.0",
    "gn:admin4_code":"40652831.0",
    "gn:asciiname":"Atgharia",
    "gn:country_code":"BD",
    "gn:dem":8,
    "gn:feature_class":"P",
    "gn:feature_code":"PPL",
    "gn:name":"\u0100tgharia",
    "gn:population":0,
    "gn:timezone":"Asia/Dhaka",
    "iso:country":"BD",
    "name:ben_x_preferred":[
        "\u0100tgharia"
    ],
    "wof:name":"Atgharia",
    "wof:placetype":"locality"
},
  "geometry": {"coordinates":[89.55745999999998,23.08564],"type":"Point"}
}