{
  "type": "Feature",
  "properties": {
    "gn:admin1_code":"83",
    "gn:admin2_code":"5010.0",
    "gn:admin3_code":"501081.0",
    "gn:admin4_code":"50108112.0",
    "gn:asciiname":"Bohali",
    "gn:country_code":"BD",
    "gn:dem":18,
    "gn:feature_class":"P",
    "gn:feature_code":"PPL",
    "gn:name":"Boh\u0101li",
    "gn:population":0,
    "gn:timezone":"Asia/Dhaka",
    "iso:country":"BD",
    "wof:name":"Bohali",
    "wof:placetype":"locality"
},
  "geometry": {"coordinates":[89.63333,24.78333],"type":"Point"}
}