{
  "type": "Feature",
  "properties": {
    "gn:admin1_code":"84",
    "gn:admin2_code":"2084.0",
    "gn:admin3_code":"208407.0",
    "gn:admin4_code":"20840783.0",
    "gn:asciiname":"Haza chhara",
    "gn:country_code":"BD",
    "gn:dem":47,
    "gn:feature_class":"P",
    "gn:feature_code":"PPL",
    "gn:name":"Haza chhara",
    "gn:population":0,
    "gn:timezone":"Asia/Dhaka",
    "iso:country":"BD",
    "name:und_x_variant":[
        "Hajachhari",
        "H\u0101j\u0101chara",
        "Haza chhara"
    ],
    "wof:name":"Haza chhara",
    "wof:placetype":"locality"
},
  "geometry": {"coordinates":[92.21176,23.22895],"type":"Point"}
}