{
  "type": "Feature",
  "properties": {
    "gn:admin1_code":"87",
    "gn:admin2_code":"5527.0",
    "gn:admin3_code":"552777.0",
    "gn:admin4_code":"55277717.0",
    "gn:asciiname":"Kalikabari",
    "gn:country_code":"BD",
    "gn:dem":40,
    "gn:feature_class":"P",
    "gn:feature_code":"PPL",
    "gn:name":"K\u0101lik\u0101b\u0101r\u012b",
    "gn:population":0,
    "gn:timezone":"Asia/Dhaka",
    "iso:country":"BD",
    "name:ben_x_preferred":[
        "K\u0101lik\u0101b\u0101r\u012b"
    ],
    "wof:name":"Kalikabari",
    "wof:placetype":"locality"
},
  "geometry": {"coordinates":[88.91164999999999,25.61814],"type":"Point"}
}