{
  "type": "Feature",
  "properties": {
    "gn:admin1_code":"83",
    "gn:admin2_code":"5064",
    "gn:admin3_code":"506450.0",
    "gn:admin4_code":"50645076.0",
    "gn:asciiname":"Maijora",
    "gn:country_code":"BD",
    "gn:dem":23,
    "gn:feature_class":"P",
    "gn:feature_code":"PPL",
    "gn:name":"Maijora",
    "gn:population":0,
    "gn:timezone":"Asia/Dhaka",
    "iso:country":"BD",
    "name:ben_x_preferred":[
        "Maijora"
    ],
    "wof:name":"Maijora",
    "wof:placetype":"locality"
},
  "geometry": {"coordinates":[88.85438000000001,24.99976],"type":"Point"}
}