{
  "type": "Feature",
  "properties": {
    "gn:admin1_code":"87",
    "gn:admin2_code":"5527",
    "gn:admin3_code":"552743.0",
    "gn:admin4_code":"55274338.0",
    "gn:asciiname":"Haidernagar",
    "gn:country_code":"BD",
    "gn:dem":29,
    "gn:feature_class":"P",
    "gn:feature_code":"PPL",
    "gn:name":"Haidernagar",
    "gn:population":0,
    "gn:timezone":"Asia/Dhaka",
    "iso:country":"BD",
    "name:ben_x_preferred":[
        "Haidernagar"
    ],
    "wof:name":"Haidernagar",
    "wof:placetype":"locality"
},
  "geometry": {"coordinates":[89.24894999999999,25.2518],"type":"Point"}
}