{
  "type": "Feature",
  "properties": {
    "gn:admin1_code":"83",
    "gn:admin2_code":"5010",
    "gn:admin3_code":"501094.0",
    "gn:admin4_code":"50109494.0",
    "gn:asciiname":"Chandina",
    "gn:country_code":"BD",
    "gn:dem":25,
    "gn:feature_class":"P",
    "gn:feature_code":"PPL",
    "gn:name":"Chandina",
    "gn:population":0,
    "gn:timezone":"Asia/Dhaka",
    "iso:country":"BD",
    "name:ben_x_preferred":[
        "Chandina"
    ],
    "wof:name":"Chandina",
    "wof:placetype":"locality"
},
  "geometry": {"coordinates":[89.31786,25.01408],"type":"Point"}
}