{
  "type": "Feature",
  "properties": {
    "gn:admin1_code":"81",
    "gn:admin2_code":"3026",
    "gn:admin3_code":"302618.0",
    "gn:admin4_code":"30261821.0",
    "gn:asciiname":"Kusumhati",
    "gn:country_code":"BD",
    "gn:dem":11,
    "gn:feature_class":"P",
    "gn:feature_code":"PPL",
    "gn:name":"Kusumh\u0101ti",
    "gn:population":0,
    "gn:timezone":"Asia/Dhaka",
    "iso:country":"BD",
    "wof:name":"Kusumhati",
    "wof:placetype":"locality"
},
  "geometry": {"coordinates":[90.06283000000001,23.63043],"type":"Point"}
}