{
  "type": "Feature",
  "properties": {
    "gn:admin1_code":"83",
    "gn:admin2_code":"5070.0",
    "gn:admin3_code":"507037.0",
    "gn:admin4_code":"50703721.0",
    "gn:asciiname":"Shyampur",
    "gn:country_code":"BD",
    "gn:dem":27,
    "gn:feature_class":"P",
    "gn:feature_code":"PPL",
    "gn:name":"Shyampur",
    "gn:population":0,
    "gn:timezone":"Asia/Dhaka",
    "iso:country":"BD",
    "name:ben_x_preferred":[
        "Shyampur"
    ],
    "wof:name":"Shyampur",
    "wof:placetype":"locality"
},
  "geometry": {"coordinates":[88.28223,24.84844],"type":"Point"}
}