{
  "type": "Feature",
  "properties": {
    "gn:admin1_code":"84",
    "gn:admin2_code":"2022.0",
    "gn:admin3_code":"202290.0",
    "gn:admin4_code":"20229047.0",
    "gn:asciiname":"Kodingcharapara",
    "gn:country_code":"BD",
    "gn:dem":9,
    "gn:feature_class":"P",
    "gn:feature_code":"PPL",
    "gn:name":"Kodingcharapara",
    "gn:population":0,
    "gn:timezone":"Asia/Dhaka",
    "iso:country":"BD",
    "name:ben_x_preferred":[
        "Kodingcharapara"
    ],
    "wof:name":"Kodingcharapara",
    "wof:placetype":"locality"
},
  "geometry": {"coordinates":[92.29376000000001,20.82661],"type":"Point"}
}