{
  "type": "Feature",
  "properties": {
    "gn:admin1_code":"82",
    "gn:asciiname":"Ulania",
    "gn:country_code":"BD",
    "gn:dem":8,
    "gn:feature_class":"P",
    "gn:feature_code":"PPL",
    "gn:name":"Ul\u0101nia",
    "gn:population":0,
    "gn:timezone":"Asia/Dhaka",
    "iso:country":"BD",
    "name:ben_x_preferred":[
        "Ul\u0101nia"
    ],
    "name:bpy_x_preferred":[
        "\u0989\u09b0\u09be\u09a8\u09bf\u09af\u09bc\u09be \u0987\u0989\u09a8\u09bf\u09af\u09bc\u09a8"
    ],
    "wof:name":"Ulania",
    "wof:placetype":"locality"
},
  "geometry": {"coordinates":[90.48275,22.19233],"type":"Point"}
}