{
  "type": "Feature",
  "properties": {
    "gn:admin1_code":"H",
    "gn:admin2_code":"3061",
    "gn:admin3_code":"306172.0",
    "gn:admin4_code":"30617263.0",
    "gn:asciiname":"Kamalpur",
    "gn:country_code":"BD",
    "gn:dem":12,
    "gn:feature_class":"P",
    "gn:feature_code":"PPL",
    "gn:name":"K\u0101m\u0101lpur",
    "gn:population":0,
    "gn:timezone":"Asia/Dhaka",
    "iso:country":"BD",
    "wof:name":"Kamalpur",
    "wof:placetype":"locality"
},
  "geometry": {"coordinates":[90.75,24.53333],"type":"Point"}
}