{
  "type": "Feature",
  "properties": {
    "gn:admin1_code":"87",
    "gn:admin2_code":"5549",
    "gn:admin3_code":"554994.0",
    "gn:admin4_code":"55499483.0",
    "gn:asciiname":"Hokadanga",
    "gn:country_code":"BD",
    "gn:dem":30,
    "gn:feature_class":"P",
    "gn:feature_code":"PPL",
    "gn:name":"Hok\u0101d\u0101nga",
    "gn:population":0,
    "gn:timezone":"Asia/Dhaka",
    "iso:country":"BD",
    "name:ben_x_preferred":[
        "Hok\u0101d\u0101nga"
    ],
    "wof:name":"Hokadanga",
    "wof:placetype":"locality"
},
  "geometry": {"coordinates":[89.54979,25.65217],"type":"Point"}
}