{
  "type": "Feature",
  "properties": {
    "gn:admin1_code":"87",
    "gn:admin2_code":"5585",
    "gn:admin3_code":"558503.0",
    "gn:admin4_code":"55850312.0",
    "gn:asciiname":"Bairampur",
    "gn:country_code":"BD",
    "gn:dem":36,
    "gn:feature_class":"P",
    "gn:feature_code":"PPL",
    "gn:name":"Bairampur",
    "gn:population":0,
    "gn:timezone":"Asia/Dhaka",
    "iso:country":"BD",
    "name:ben_x_preferred":[
        "Bairampur"
    ],
    "wof:name":"Bairampur",
    "wof:placetype":"locality"
},
  "geometry": {"coordinates":[89.10054000000002,25.64857],"type":"Point"}
}