{
  "type": "Feature",
  "properties": {
    "gn:admin1_code":"87",
    "gn:admin2_code":"5549",
    "gn:admin3_code":"554979.0",
    "gn:admin4_code":"55497923.0",
    "gn:asciiname":"Masallar Char",
    "gn:country_code":"BD",
    "gn:dem":27,
    "gn:feature_class":"P",
    "gn:feature_code":"PPL",
    "gn:name":"Masallar Char",
    "gn:population":0,
    "gn:timezone":"Asia/Dhaka",
    "iso:country":"BD",
    "name:ben_x_preferred":[
        "Masallar Char"
    ],
    "wof:name":"Masallar Char",
    "wof:placetype":"locality"
},
  "geometry": {"coordinates":[89.82035,25.65047],"type":"Point"}
}