{
  "type": "Feature",
  "properties": {
    "gn:admin1_code":"81",
    "gn:admin2_code":"3056",
    "gn:admin3_code":"305610.0",
    "gn:admin4_code":"30561019.0",
    "gn:asciiname":"Jot Kashi",
    "gn:country_code":"BD",
    "gn:dem":2,
    "gn:feature_class":"P",
    "gn:feature_code":"PPL",
    "gn:name":"Jot K\u0101shi",
    "gn:population":0,
    "gn:timezone":"Asia/Dhaka",
    "iso:country":"BD",
    "name:und_x_variant":[
        "Jot K\u0101si",
        "Jot K\u0101shi"
    ],
    "wof:name":"Jot Kashi",
    "wof:placetype":"locality"
},
  "geometry": {"coordinates":[89.76685999999999,23.92436],"type":"Point"}
}