{
  "type": "Feature",
  "properties": {
    "gn:admin1_code":"82",
    "gn:admin2_code":"4065.0",
    "gn:admin3_code":"406576.0",
    "gn:admin4_code":"40657694.0",
    "gn:asciiname":"Betenga",
    "gn:country_code":"BD",
    "gn:dem":9,
    "gn:feature_class":"P",
    "gn:feature_code":"PPL",
    "gn:name":"Betenga",
    "gn:population":0,
    "gn:timezone":"Asia/Dhaka",
    "iso:country":"BD",
    "name:ben_x_preferred":[
        "Betenga"
    ],
    "wof:name":"Betenga",
    "wof:placetype":"locality"
},
  "geometry": {"coordinates":[89.45499000000002,23.17464],"type":"Point"}
}