{
  "type": "Feature",
  "properties": {
    "gn:admin1_code":"83",
    "gn:asciiname":"Chasakpara",
    "gn:country_code":"BD",
    "gn:dem":25,
    "gn:feature_class":"P",
    "gn:feature_code":"PPL",
    "gn:name":"Chasakp\u0101ra",
    "gn:population":0,
    "gn:timezone":"Asia/Dhaka",
    "iso:country":"BD",
    "name:ben_x_preferred":[
        "Chasakp\u0101ra"
    ],
    "wof:name":"Chasakpara",
    "wof:placetype":"locality"
},
  "geometry": {"coordinates":[89.38009,25.13982],"type":"Point"}
}