{
  "type": "Feature",
  "properties": {
    "gn:admin1_code":"H",
    "gn:admin2_code":"3072.0",
    "gn:admin3_code":"307209.0",
    "gn:admin4_code":"30720983.0",
    "gn:asciiname":"Alokdia",
    "gn:country_code":"BD",
    "gn:dem":14,
    "gn:feature_class":"P",
    "gn:feature_code":"PPL",
    "gn:name":"\u0100lokdia",
    "gn:population":0,
    "gn:timezone":"Asia/Dhaka",
    "iso:country":"BD",
    "wof:name":"Alokdia",
    "wof:placetype":"locality"
},
  "geometry": {"coordinates":[90.96259999999999,24.88221],"type":"Point"}
}