{
  "type": "Feature",
  "properties": {
    "gn:admin1_code":"84",
    "gn:admin2_code":"2015.0",
    "gn:admin3_code":"201512.0",
    "gn:admin4_code":"20151257.0",
    "gn:asciiname":"Purba Khudurkhil",
    "gn:country_code":"BD",
    "gn:dem":7,
    "gn:feature_class":"P",
    "gn:feature_code":"PPL",
    "gn:name":"Purba Khudurkhil",
    "gn:population":0,
    "gn:timezone":"Asia/Dhaka",
    "iso:country":"BD",
    "name:ben_x_preferred":[
        "Purba Khudurkhil"
    ],
    "wof:name":"Purba Khudurkhil",
    "wof:placetype":"locality"
},
  "geometry": {"coordinates":[91.94038999999999,22.39559],"type":"Point"}
}