{
  "type": "Feature",
  "properties": {
    "gn:admin1_code":"82",
    "gn:asciiname":"Dakshin Char Kajal",
    "gn:country_code":"BD",
    "gn:dem":5,
    "gn:feature_class":"P",
    "gn:feature_code":"PPL",
    "gn:name":"Dakshin Char K\u0101jal",
    "gn:population":0,
    "gn:timezone":"Asia/Dhaka",
    "iso:country":"BD",
    "name:ben_x_preferred":[
        "Dakshin Char K\u0101jal"
    ],
    "wof:name":"Dakshin Char Kajal",
    "wof:placetype":"locality"
},
  "geometry": {"coordinates":[90.50606999999999,22.06394],"type":"Point"}
}