{
  "type": "Feature",
  "properties": {
    "gn:admin1_code":"87",
    "gn:admin2_code":"5549",
    "gn:admin3_code":"554994.0",
    "gn:admin4_code":"55499450.0",
    "gn:asciiname":"Gom Bari",
    "gn:country_code":"BD",
    "gn:dem":29,
    "gn:feature_class":"P",
    "gn:feature_code":"PPL",
    "gn:name":"Gom B\u0101ri",
    "gn:population":0,
    "gn:timezone":"Asia/Dhaka",
    "iso:country":"BD",
    "name:ben_x_preferred":[
        "Gom B\u0101ri"
    ],
    "wof:name":"Gom Bari",
    "wof:placetype":"locality"
},
  "geometry": {"coordinates":[89.67134,25.74007000000001],"type":"Point"}
}