{
  "type": "Feature",
  "properties": {
    "gn:admin1_code":"84",
    "gn:admin2_code":"2022.0",
    "gn:admin3_code":"202294.0",
    "gn:admin4_code":"20229447.0",
    "gn:asciiname":"Lambaghona",
    "gn:country_code":"BD",
    "gn:dem":16,
    "gn:feature_class":"P",
    "gn:feature_code":"PPL",
    "gn:name":"Lamb\u0101ghona",
    "gn:population":0,
    "gn:timezone":"Asia/Dhaka",
    "iso:country":"BD",
    "name:ben_x_preferred":[
        "Lamb\u0101ghona"
    ],
    "wof:name":"Lambaghona",
    "wof:placetype":"locality"
},
  "geometry": {"coordinates":[92.16715000000001,21.24056],"type":"Point"}
}