{
  "type": "Feature",
  "properties": {
    "gn:admin1_code":"82",
    "gn:asciiname":"Bahalgachhia",
    "gn:country_code":"BD",
    "gn:dem":5,
    "gn:feature_class":"P",
    "gn:feature_code":"PPL",
    "gn:name":"Bahalgachhia",
    "gn:population":0,
    "gn:timezone":"Asia/Dhaka",
    "iso:country":"BD",
    "name:ben_x_preferred":[
        "Bahalgachhia"
    ],
    "wof:name":"Bahalgachhia",
    "wof:placetype":"locality"
},
  "geometry": {"coordinates":[90.34238999999999,22.33719],"type":"Point"}
}