{
  "type": "Feature",
  "properties": {
    "gn:admin1_code":"85",
    "gn:admin2_code":"1006",
    "gn:admin3_code":"100603.0",
    "gn:admin4_code":"10060367.0",
    "gn:asciiname":"Meghia",
    "gn:country_code":"BD",
    "gn:dem":10,
    "gn:feature_class":"P",
    "gn:feature_code":"PPL",
    "gn:name":"Meghia",
    "gn:population":0,
    "gn:timezone":"Asia/Dhaka",
    "iso:country":"BD",
    "wof:name":"Meghia",
    "wof:placetype":"locality"
},
  "geometry": {"coordinates":[90.32326,22.77229],"type":"Point"}
}