{
  "type": "Feature",
  "properties": {
    "gn:admin1_code":"87",
    "gn:admin2_code":"5585",
    "gn:admin3_code":"558558.0",
    "gn:admin4_code":"55855844.0",
    "gn:asciiname":"Dhorakaba",
    "gn:country_code":"BD",
    "gn:dem":28,
    "gn:feature_class":"P",
    "gn:feature_code":"PPL",
    "gn:name":"Dhorakaba",
    "gn:population":0,
    "gn:timezone":"Asia/Dhaka",
    "iso:country":"BD",
    "name:ben_x_preferred":[
        "Dhorakaba"
    ],
    "wof:name":"Dhorakaba",
    "wof:placetype":"locality"
},
  "geometry": {"coordinates":[89.42444999999999,25.47522],"type":"Point"}
}