{
  "type": "Feature",
  "properties": {
    "gn:admin1_code":"82",
    "gn:admin2_code":"4044.0",
    "gn:admin3_code":"404419.0",
    "gn:admin4_code":"40441963.0",
    "gn:asciiname":"Kharasani",
    "gn:country_code":"BD",
    "gn:dem":13,
    "gn:feature_class":"P",
    "gn:feature_code":"PPL",
    "gn:name":"Kh\u0101r\u0101s\u0101ni",
    "gn:population":0,
    "gn:timezone":"Asia/Dhaka",
    "iso:country":"BD",
    "name:ben_x_preferred":[
        "Kh\u0101r\u0101s\u0101ni"
    ],
    "wof:name":"Kharasani",
    "wof:placetype":"locality"
},
  "geometry": {"coordinates":[89.1734,23.45556],"type":"Point"}
}