{
  "type": "Feature",
  "properties": {
    "gn:admin1_code":"85",
    "gn:admin2_code":"1009.0",
    "gn:admin3_code":"100954.0",
    "gn:admin4_code":"10095447.0",
    "gn:asciiname":"Balurchar",
    "gn:country_code":"BD",
    "gn:dem":9,
    "gn:feature_class":"P",
    "gn:feature_code":"PPL",
    "gn:name":"B\u0101lurchar",
    "gn:population":0,
    "gn:timezone":"Asia/Dhaka",
    "iso:country":"BD",
    "name:ben_x_preferred":[
        "B\u0101lurchar"
    ],
    "wof:name":"Balurchar",
    "wof:placetype":"locality"
},
  "geometry": {"coordinates":[90.73949,22.35859],"type":"Point"}
}