{
  "type": "Feature",
  "properties": {
    "gn:admin1_code":"H",
    "gn:admin2_code":"3061",
    "gn:admin3_code":"306194.0",
    "gn:admin4_code":"30619438.0",
    "gn:asciiname":"Magurjora",
    "gn:country_code":"BD",
    "gn:dem":14,
    "gn:feature_class":"P",
    "gn:feature_code":"PPL",
    "gn:name":"M\u0101gurjora",
    "gn:population":0,
    "gn:timezone":"Asia/Dhaka",
    "iso:country":"BD",
    "wof:name":"Magurjora",
    "wof:placetype":"locality"
},
  "geometry": {"coordinates":[90.41619,24.52659],"type":"Point"}
}