{
  "type": "Feature",
  "properties": {
    "gn:admin1_code":"84",
    "gn:admin2_code":"2015.0",
    "gn:admin3_code":"201512.0",
    "gn:admin4_code":"20151257.0",
    "gn:asciiname":"Hawla",
    "gn:country_code":"BD",
    "gn:dem":8,
    "gn:feature_class":"P",
    "gn:feature_code":"PPL",
    "gn:name":"H\u0101wla",
    "gn:population":0,
    "gn:timezone":"Asia/Dhaka",
    "iso:country":"BD",
    "name:ben_x_preferred":[
        "H\u0101wla"
    ],
    "wof:name":"Hawla",
    "wof:placetype":"locality"
},
  "geometry": {"coordinates":[91.94204000000001,22.38615],"type":"Point"}
}