{
  "type": "Feature",
  "properties": {
    "gn:admin1_code":"87",
    "gn:admin2_code":"5549",
    "gn:admin3_code":"554994.0",
    "gn:admin4_code":"55499478.0",
    "gn:asciiname":"Khamar Tabakpur",
    "gn:country_code":"BD",
    "gn:dem":29,
    "gn:feature_class":"P",
    "gn:feature_code":"PPL",
    "gn:name":"Kh\u0101m\u0101r Tab\u0101kpur",
    "gn:population":0,
    "gn:timezone":"Asia/Dhaka",
    "iso:country":"BD",
    "name:ben_x_preferred":[
        "Kh\u0101m\u0101r Tab\u0101kpur"
    ],
    "wof:name":"Khamar Tabakpur",
    "wof:placetype":"locality"
},
  "geometry": {"coordinates":[89.64034000000002,25.62593],"type":"Point"}
}