{
  "type": "Feature",
  "properties": {
    "gn:admin1_code":"87",
    "gn:admin2_code":"5527",
    "gn:admin3_code":"552712.0",
    "gn:admin4_code":"55271225.0",
    "gn:asciiname":"Lakshmipur",
    "gn:country_code":"BD",
    "gn:dem":52,
    "gn:feature_class":"P",
    "gn:feature_code":"PPL",
    "gn:name":"Lakshmipur",
    "gn:population":0,
    "gn:timezone":"Asia/Dhaka",
    "iso:country":"BD",
    "name:ben_x_preferred":[
        "Lakshmipur"
    ],
    "name:ceb_x_preferred":[
        "Lakshmipur"
    ],
    "name:fra_x_preferred":[
        "Lakshmipur"
    ],
    "name:swe_x_preferred":[
        "Lakshmipur"
    ],
    "wof:name":"Lakshmipur",
    "wof:placetype":"locality"
},
  "geometry": {"coordinates":[88.52200000000001,25.89058],"type":"Point"}
}