{
  "type": "Feature",
  "properties": {
    "gn:admin1_code":"81",
    "gn:admin2_code":"3054",
    "gn:admin3_code":"305454.0",
    "gn:admin4_code":"30545429.0",
    "gn:asciiname":"Jubaradia",
    "gn:country_code":"BD",
    "gn:dem":8,
    "gn:feature_class":"P",
    "gn:feature_code":"PPL",
    "gn:name":"Jub\u0101r\u0101dia",
    "gn:population":0,
    "gn:timezone":"Asia/Dhaka",
    "iso:country":"BD",
    "name:und_x_variant":[
        "Jub\u0101r\u0101dia",
        "Jub\u0101r\u0101n\u0101di"
    ],
    "wof:name":"Jubaradia",
    "wof:placetype":"locality"
},
  "geometry": {"coordinates":[90.20137,23.14531],"type":"Point"}
}