{
  "type": "Feature",
  "properties": {
    "gn:admin1_code":"H",
    "gn:admin2_code":"3061.0",
    "gn:admin3_code":"306172.0",
    "gn:admin4_code":"30617247.0",
    "gn:asciiname":"Beltail",
    "gn:country_code":"BD",
    "gn:dem":17,
    "gn:feature_class":"P",
    "gn:feature_code":"PPL",
    "gn:name":"Beltail",
    "gn:population":0,
    "gn:timezone":"Asia/Dhaka",
    "iso:country":"BD",
    "wof:name":"Beltail",
    "wof:placetype":"locality"
},
  "geometry": {"coordinates":[90.59702,24.50289],"type":"Point"}
}