{
  "type": "Feature",
  "properties": {
    "gn:admin1_code":"84",
    "gn:admin2_code":"2046.0",
    "gn:admin3_code":"204670.0",
    "gn:admin4_code":"20467035.0",
    "gn:asciiname":"Paliyabhanga",
    "gn:country_code":"BD",
    "gn:dem":37,
    "gn:feature_class":"P",
    "gn:feature_code":"PPL",
    "gn:name":"Paliyabh\u0101nga",
    "gn:population":0,
    "gn:timezone":"Asia/Dhaka",
    "iso:country":"BD",
    "name:ben_x_preferred":[
        "Paliyabh\u0101nga"
    ],
    "wof:name":"Paliyabhanga",
    "wof:placetype":"locality"
},
  "geometry": {"coordinates":[91.84256000000001,22.96447],"type":"Point"}
}