{
  "type": "Feature",
  "properties": {
    "gn:admin1_code":"87",
    "gn:admin2_code":"5552",
    "gn:admin3_code":"555239.0",
    "gn:admin4_code":"55523995.0",
    "gn:asciiname":"Uttar Ghanasyam",
    "gn:country_code":"BD",
    "gn:dem":45,
    "gn:feature_class":"P",
    "gn:feature_code":"PPL",
    "gn:name":"Uttar Ghanasyam",
    "gn:population":0,
    "gn:timezone":"Asia/Dhaka",
    "iso:country":"BD",
    "name:ben_x_preferred":[
        "Uttar Ghanasyam"
    ],
    "wof:name":"Uttar Ghanasyam",
    "wof:placetype":"locality"
},
  "geometry": {"coordinates":[89.22671,25.97051],"type":"Point"}
}