{
  "type": "Feature",
  "properties": {
    "gn:admin1_code":"82",
    "gn:admin2_code":"4047.0",
    "gn:admin3_code":"404753.0",
    "gn:admin4_code":"40475372.0",
    "gn:asciiname":"Matbari Dakshin Chak",
    "gn:country_code":"BD",
    "gn:dem":4,
    "gn:feature_class":"P",
    "gn:feature_code":"PPL",
    "gn:name":"Matb\u0101ri Dakshin Chak",
    "gn:population":0,
    "gn:timezone":"Asia/Dhaka",
    "iso:country":"BD",
    "name:ben_x_preferred":[
        "Matb\u0101ri Dakshin Chak"
    ],
    "wof:name":"Matbari Dakshin Chak",
    "wof:placetype":"locality"
},
  "geometry": {"coordinates":[89.31359,22.36297],"type":"Point"}
}