{
  "type": "Feature",
  "properties": {
    "gn:admin1_code":"82",
    "gn:admin2_code":"4041.0",
    "gn:admin3_code":"404190.0",
    "gn:admin4_code":"40419043.0",
    "gn:asciiname":"Ichapur",
    "gn:country_code":"BD",
    "gn:dem":8,
    "gn:feature_class":"P",
    "gn:feature_code":"PPL",
    "gn:name":"Ich\u0101pur",
    "gn:population":0,
    "gn:timezone":"Asia/Dhaka",
    "iso:country":"BD",
    "name:ben_x_preferred":[
        "Ich\u0101pur"
    ],
    "name:cat_x_preferred":[
        "Ichapur"
    ],
    "wof:name":"Ichapur",
    "wof:placetype":"locality"
},
  "geometry": {"coordinates":[88.91455999999999,22.97508],"type":"Point"}
}