{
  "type": "Feature",
  "properties": {
    "gn:admin1_code":"87",
    "gn:admin2_code":"5549",
    "gn:admin3_code":"554994.0",
    "gn:admin4_code":"55499439.0",
    "gn:asciiname":"Bagchar Khamar",
    "gn:country_code":"BD",
    "gn:dem":30,
    "gn:feature_class":"P",
    "gn:feature_code":"PPL",
    "gn:name":"Bagchar Kh\u0101m\u0101r",
    "gn:population":0,
    "gn:timezone":"Asia/Dhaka",
    "iso:country":"BD",
    "name:ben_x_preferred":[
        "Bagchar Kh\u0101m\u0101r"
    ],
    "wof:name":"Bagchar Khamar",
    "wof:placetype":"locality"
},
  "geometry": {"coordinates":[89.6559,25.65097],"type":"Point"}
}