{
  "type": "Feature",
  "properties": {
    "gn:admin1_code":"83",
    "gn:admin2_code":"5010.0",
    "gn:admin3_code":"501033.0",
    "gn:admin4_code":"50103381.0",
    "gn:asciiname":"Barahi",
    "gn:country_code":"BD",
    "gn:dem":19,
    "gn:feature_class":"P",
    "gn:feature_code":"PPL",
    "gn:name":"Barahi",
    "gn:population":0,
    "gn:timezone":"Asia/Dhaka",
    "iso:country":"BD",
    "wof:name":"Barahi",
    "wof:placetype":"locality"
},
  "geometry": {"coordinates":[89.09999999999999,24.93333],"type":"Point"}
}