{
  "type": "Feature",
  "properties": {
    "gn:admin1_code":"81",
    "gn:admin2_code":"3026",
    "gn:admin3_code":"302662.0",
    "gn:admin4_code":"30266206.0",
    "gn:asciiname":"Majhpara",
    "gn:country_code":"BD",
    "gn:dem":9,
    "gn:feature_class":"P",
    "gn:feature_code":"PPL",
    "gn:name":"M\u0101jhp\u0101ra",
    "gn:population":0,
    "gn:timezone":"Asia/Dhaka",
    "iso:country":"BD",
    "wof:name":"Majhpara",
    "wof:placetype":"locality"
},
  "geometry": {"coordinates":[90.21908999999999,23.65295],"type":"Point"}
}