{
  "type": "Feature",
  "properties": {
    "gn:admin1_code":"H",
    "gn:admin2_code":"3061.0",
    "gn:admin3_code":"306165.0",
    "gn:admin4_code":"30616594.0",
    "gn:asciiname":"Dauakhala",
    "gn:country_code":"BD",
    "gn:dem":19,
    "gn:feature_class":"P",
    "gn:feature_code":"PPL",
    "gn:name":"Dau\u0101khala",
    "gn:population":0,
    "gn:timezone":"Asia/Dhaka",
    "iso:country":"BD",
    "wof:name":"Dauakhala",
    "wof:placetype":"locality"
},
  "geometry": {"coordinates":[90.2692,24.78099],"type":"Point"}
}