{
  "type": "Feature",
  "properties": {
    "gn:admin1_code":"82",
    "gn:admin2_code":"4018.0",
    "gn:admin3_code":"401823.0",
    "gn:admin4_code":"40182300.0",
    "gn:asciiname":"Fengramari",
    "gn:country_code":"BD",
    "gn:dem":19,
    "gn:feature_class":"P",
    "gn:feature_code":"PPL",
    "gn:name":"Fengr\u0101m\u0101ri",
    "gn:population":0,
    "gn:timezone":"Asia/Dhaka",
    "iso:country":"BD",
    "name:ben_x_preferred":[
        "Fengr\u0101m\u0101ri"
    ],
    "wof:name":"Fengramari",
    "wof:placetype":"locality"
},
  "geometry": {"coordinates":[88.87040999999998,23.66479],"type":"Point"}
}