{
  "type": "Feature",
  "properties": {
    "gn:admin1_code":"85",
    "gn:admin2_code":"1009.0",
    "gn:admin3_code":"100991.0",
    "gn:admin4_code":"10099157.0",
    "gn:asciiname":"Dari Chandpur",
    "gn:country_code":"BD",
    "gn:dem":8,
    "gn:feature_class":"P",
    "gn:feature_code":"PPL",
    "gn:name":"Dari Ch\u0101ndpur",
    "gn:population":0,
    "gn:timezone":"Asia/Dhaka",
    "iso:country":"BD",
    "name:ben_x_preferred":[
        "Dari Ch\u0101ndpur"
    ],
    "wof:name":"Dari Chandpur",
    "wof:placetype":"locality"
},
  "geometry": {"coordinates":[90.83987,22.39216],"type":"Point"}
}