{
  "type": "Feature",
  "properties": {
    "gn:admin1_code":"81",
    "gn:admin2_code":"3082",
    "gn:admin3_code":"308273.0",
    "gn:admin4_code":"30827305.0",
    "gn:asciiname":"Jaykrishnapur",
    "gn:cc2":"BD",
    "gn:country_code":"BD",
    "gn:dem":2,
    "gn:feature_class":"P",
    "gn:feature_code":"PPL",
    "gn:name":"Jaykrishnapur",
    "gn:population":0,
    "gn:timezone":"Asia/Dhaka",
    "iso:country":"BD",
    "name:und_x_variant":[
        "Joy Krishnapur",
        "Jaykrishnapur"
    ],
    "wof:name":"Jaykrishnapur",
    "wof:placetype":"locality"
},
  "geometry": {"coordinates":[89.40000000000001,23.88333],"type":"Point"}
}