{
  "type": "Feature",
  "properties": {
    "gn:admin1_code":"82",
    "gn:admin2_code":"4041",
    "gn:admin3_code":"404161.0",
    "gn:admin4_code":"40416133.0",
    "gn:asciiname":"Moktarpur",
    "gn:country_code":"BD",
    "gn:dem":13,
    "gn:feature_class":"P",
    "gn:feature_code":"PPL",
    "gn:name":"Mokt\u0101rpur",
    "gn:population":0,
    "gn:timezone":"Asia/Dhaka",
    "iso:country":"BD",
    "name:ben_x_preferred":[
        "Mokt\u0101rpur"
    ],
    "wof:name":"Moktarpur",
    "wof:placetype":"locality"
},
  "geometry": {"coordinates":[89.09239000000002,23.01675],"type":"Point"}
}