{
  "type": "Feature",
  "properties": {
    "gn:admin1_code":"83",
    "gn:admin2_code":"5076.0",
    "gn:admin3_code":"507655.0",
    "gn:admin4_code":"50765525.0",
    "gn:asciiname":"Char Tarapur",
    "gn:country_code":"BD",
    "gn:dem":18,
    "gn:feature_class":"P",
    "gn:feature_code":"PPL",
    "gn:name":"Char T\u0101r\u0101pur",
    "gn:population":0,
    "gn:timezone":"Asia/Dhaka",
    "iso:country":"BD",
    "wof:name":"Char Tarapur",
    "wof:placetype":"locality"
},
  "geometry": {"coordinates":[89.36548000000001,23.95265],"type":"Point"}
}