{
  "type": "Feature",
  "properties": {
    "gn:admin1_code":"83",
    "gn:admin2_code":"5038.0",
    "gn:admin3_code":"503874.0",
    "gn:admin4_code":"50387473.0",
    "gn:asciiname":"Gohara",
    "gn:country_code":"BD",
    "gn:dem":27,
    "gn:feature_class":"P",
    "gn:feature_code":"PPL",
    "gn:name":"Goh\u0101ra",
    "gn:population":0,
    "gn:timezone":"Asia/Dhaka",
    "iso:country":"BD",
    "name:ben_x_preferred":[
        "Goh\u0101ra"
    ],
    "wof:name":"Gohara",
    "wof:placetype":"locality"
},
  "geometry": {"coordinates":[89.12359000000002,25.18214],"type":"Point"}
}