{
  "type": "Feature",
  "properties": {
    "gn:admin1_code":"83",
    "gn:admin2_code":"5010.0",
    "gn:admin3_code":"501021.0",
    "gn:admin4_code":"50102117.0",
    "gn:asciiname":"Barapathar",
    "gn:country_code":"BD",
    "gn:dem":21,
    "gn:feature_class":"P",
    "gn:feature_code":"PPL",
    "gn:name":"Barap\u0101th\u0101r",
    "gn:population":0,
    "gn:timezone":"Asia/Dhaka",
    "iso:country":"BD",
    "wof:name":"Barapathar",
    "wof:placetype":"locality"
},
  "geometry": {"coordinates":[89.43034,24.76723],"type":"Point"}
}