{
  "type": "Feature",
  "properties": {
    "gn:admin1_code":"87",
    "gn:admin2_code":"5585.0",
    "gn:admin3_code":"558592.0",
    "gn:admin4_code":"55859215.0",
    "gn:asciiname":"Chak Tahira",
    "gn:country_code":"BD",
    "gn:dem":42,
    "gn:feature_class":"P",
    "gn:feature_code":"PPL",
    "gn:name":"Chak T\u0101hira",
    "gn:population":0,
    "gn:timezone":"Asia/Dhaka",
    "iso:country":"BD",
    "name:ben_x_preferred":[
        "Chak T\u0101hira"
    ],
    "wof:name":"Chak Tahira",
    "wof:placetype":"locality"
},
  "geometry": {"coordinates":[88.99077,25.77034],"type":"Point"}
}