{
  "type": "Feature",
  "properties": {
    "gn:admin1_code":"83",
    "gn:admin2_code":"5064",
    "gn:admin3_code":"506406.0",
    "gn:admin4_code":"50640663.0",
    "gn:asciiname":"Tethulia",
    "gn:country_code":"BD",
    "gn:dem":21,
    "gn:feature_class":"P",
    "gn:feature_code":"PPL",
    "gn:name":"Tethulia",
    "gn:population":0,
    "gn:timezone":"Asia/Dhaka",
    "iso:country":"BD",
    "name:ben_x_preferred":[
        "Tethulia"
    ],
    "name:ben_x_variant":[
        "Tentulia"
    ],
    "wof:name":"Tethulia",
    "wof:placetype":"locality"
},
  "geometry": {"coordinates":[88.98063,24.94288],"type":"Point"}
}