{
  "type": "Feature",
  "properties": {
    "gn:admin1_code":"87",
    "gn:admin2_code":"5527.0",
    "gn:admin3_code":"552717.0",
    "gn:admin4_code":"55271795.0",
    "gn:asciiname":"Rajarampur",
    "gn:country_code":"BD",
    "gn:dem":42,
    "gn:feature_class":"P",
    "gn:feature_code":"PPL",
    "gn:name":"R\u0101j\u0101r\u0101mpur",
    "gn:population":0,
    "gn:timezone":"Asia/Dhaka",
    "iso:country":"BD",
    "name:ben_x_preferred":[
        "R\u0101j\u0101r\u0101mpur"
    ],
    "wof:name":"Rajarampur",
    "wof:placetype":"locality"
},
  "geometry": {"coordinates":[88.50683000000002,25.71026],"type":"Point"}
}