{
  "type": "Feature",
  "properties": {
    "gn:admin1_code":"83",
    "gn:admin2_code":"5069.0",
    "gn:admin3_code":"506944.0",
    "gn:admin4_code":"50694428.0",
    "gn:asciiname":"Laskarpur",
    "gn:country_code":"BD",
    "gn:dem":19,
    "gn:feature_class":"P",
    "gn:feature_code":"PPL",
    "gn:name":"Laskarpur",
    "gn:population":0,
    "gn:timezone":"Asia/Dhaka",
    "iso:country":"BD",
    "name:ben_x_preferred":[
        "Laskarpur"
    ],
    "wof:name":"Laskarpur",
    "wof:placetype":"locality"
},
  "geometry": {"coordinates":[88.99027,24.24161],"type":"Point"}
}