{
  "type": "Feature",
  "properties": {
    "gn:admin1_code":"84",
    "gn:admin2_code":"2013.0",
    "gn:admin3_code":"201322.0",
    "gn:admin4_code":"20132254.0",
    "gn:asciiname":"Gobindapur",
    "gn:country_code":"BD",
    "gn:dem":13,
    "gn:feature_class":"P",
    "gn:feature_code":"PPL",
    "gn:name":"Gobindapur",
    "gn:population":0,
    "gn:timezone":"Asia/Dhaka",
    "iso:country":"BD",
    "name:und_x_variant":[
        "Govindapur",
        "Gobindapur"
    ],
    "wof:name":"Gobindapur",
    "wof:placetype":"locality"
},
  "geometry": {"coordinates":[90.67863,23.13293],"type":"Point"}
}