{
  "type": "Feature",
  "properties": {
    "gn:admin1_code":"81",
    "gn:admin2_code":"3093.0",
    "gn:admin3_code":"309366.0",
    "gn:admin4_code":"30936655.0",
    "gn:asciiname":"Gorai",
    "gn:country_code":"BD",
    "gn:dem":21,
    "gn:feature_class":"P",
    "gn:feature_code":"PPL",
    "gn:name":"Gor\u0101i",
    "gn:population":0,
    "gn:timezone":"Asia/Dhaka",
    "iso:country":"BD",
    "name:guj_x_preferred":[
        "\u0a97\u0acb\u0ab0\u0abe\u0a87"
    ],
    "wof:name":"Gorai",
    "wof:placetype":"locality"
},
  "geometry": {"coordinates":[90.16226,24.0926],"type":"Point"}
}