{
  "type": "Feature",
  "properties": {
    "gn:admin1_code":"H",
    "gn:admin2_code":"3039.0",
    "gn:admin3_code":"303936.0",
    "gn:admin4_code":"30393647.0",
    "gn:asciiname":"Chhatiani",
    "gn:country_code":"BD",
    "gn:dem":23,
    "gn:feature_class":"P",
    "gn:feature_code":"PPL",
    "gn:name":"Chh\u0101ti\u0101ni",
    "gn:population":0,
    "gn:timezone":"Asia/Dhaka",
    "iso:country":"BD",
    "wof:name":"Chhatiani",
    "wof:placetype":"locality"
},
  "geometry": {"coordinates":[89.85584,24.83509],"type":"Point"}
}