{
  "type": "Feature",
  "properties": {
    "gn:admin1_code":"83",
    "gn:admin2_code":"5069",
    "gn:admin3_code":"506991.0",
    "gn:admin4_code":"50699115.0",
    "gn:asciiname":"Kaliganj",
    "gn:country_code":"BD",
    "gn:dem":15,
    "gn:feature_class":"P",
    "gn:feature_code":"PPL",
    "gn:name":"K\u0101l\u012bganj",
    "gn:population":0,
    "gn:timezone":"Asia/Dhaka",
    "iso:country":"BD",
    "name:ceb_x_preferred":[
        "Kaliganj"
    ],
    "name:ita_x_preferred":[
        "Kaliganj"
    ],
    "name:swe_x_preferred":[
        "Kaliganj"
    ],
    "name:und_x_variant":[
        "Chutardeghee",
        "Chh\u0101t\u0101rdighi",
        "K\u0101l\u012bganj"
    ],
    "name:zho_x_preferred":[
        "\u5361\u5229\u7518\u5091"
    ],
    "wof:name":"Kaliganj",
    "wof:placetype":"locality"
},
  "geometry": {"coordinates":[89.12044,24.64777],"type":"Point"}
}