{
  "type": "Feature",
  "properties": {
    "gn:admin1_code":"83",
    "gn:admin2_code":"5081",
    "gn:admin3_code":"508140.0",
    "gn:admin4_code":"50814028.0",
    "gn:asciiname":"Khozapur",
    "gn:country_code":"BD",
    "gn:dem":22,
    "gn:feature_class":"P",
    "gn:feature_code":"PPL",
    "gn:name":"Khozapur",
    "gn:population":0,
    "gn:timezone":"Asia/Dhaka",
    "iso:country":"BD",
    "name:ben_x_preferred":[
        "Khozapur"
    ],
    "name:ben_x_variant":[
        "Khoj\u0101pur"
    ],
    "wof:name":"Khozapur",
    "wof:placetype":"locality"
},
  "geometry": {"coordinates":[88.6348,24.35683],"type":"Point"}
}