{
  "type": "Feature",
  "properties": {
    "gn:admin1_code":"84",
    "gn:admin2_code":"2013.0",
    "gn:admin3_code":"201345.0",
    "gn:admin4_code":"20134511.0",
    "gn:asciiname":"Baliarpur",
    "gn:country_code":"BD",
    "gn:dem":17,
    "gn:feature_class":"P",
    "gn:feature_code":"PPL",
    "gn:name":"B\u0101li\u0101rpur",
    "gn:population":0,
    "gn:timezone":"Asia/Dhaka",
    "iso:country":"BD",
    "name:und_x_variant":[
        "B\u0101li\u0101rpur"
    ],
    "wof:name":"Baliarpur",
    "wof:placetype":"locality"
},
  "geometry": {"coordinates":[90.73090999999999,23.22122],"type":"Point"}
}