{
  "type": "Feature",
  "properties": {
    "gn:admin1_code":"85",
    "gn:admin2_code":"1078.0",
    "gn:admin3_code":"107866.0",
    "gn:admin4_code":"10786659.0",
    "gn:asciiname":"Safakhali",
    "gn:country_code":"BD",
    "gn:dem":8,
    "gn:feature_class":"P",
    "gn:feature_code":"PPL",
    "gn:name":"S\u0101f\u0101kh\u0101li",
    "gn:population":0,
    "gn:timezone":"Asia/Dhaka",
    "iso:country":"BD",
    "name:ben_x_preferred":[
        "S\u0101f\u0101kh\u0101li"
    ],
    "wof:name":"Safakhali",
    "wof:placetype":"locality"
},
  "geometry": {"coordinates":[90.20018,21.91407],"type":"Point"}
}