{
  "type": "Feature",
  "properties": {
    "gn:admin1_code":"81",
    "gn:admin2_code":"3056.0",
    "gn:admin3_code":"305670.0",
    "gn:admin4_code":"30567076.0",
    "gn:asciiname":"Char Fukurhati",
    "gn:country_code":"BD",
    "gn:dem":14,
    "gn:feature_class":"P",
    "gn:feature_code":"PPL",
    "gn:name":"Char Fukurh\u0101ti",
    "gn:population":0,
    "gn:timezone":"Asia/Dhaka",
    "iso:country":"BD",
    "wof:name":"Char Fukurhati",
    "wof:placetype":"locality"
},
  "geometry": {"coordinates":[90.01334,23.94166],"type":"Point"}
}