{
  "type": "Feature",
  "properties": {
    "gn:admin1_code":"82",
    "gn:admin2_code":"4041.0",
    "gn:admin3_code":"404147.0",
    "gn:admin4_code":"40414705.0",
    "gn:asciiname":"Brahmattar Patingali",
    "gn:country_code":"BD",
    "gn:dem":13,
    "gn:feature_class":"P",
    "gn:feature_code":"PPL",
    "gn:name":"Brahmattar Patingali",
    "gn:population":0,
    "gn:timezone":"Asia/Dhaka",
    "iso:country":"BD",
    "name:ben_x_preferred":[
        "Brahmattar Patingali"
    ],
    "name:ben_x_variant":[
        "Brahmottar Pating\u0101li"
    ],
    "wof:name":"Brahmattar Patingali",
    "wof:placetype":"locality"
},
  "geometry": {"coordinates":[89.17443,23.15032],"type":"Point"}
}