{
  "type": "Feature",
  "properties": {
    "gn:admin1_code":"81",
    "gn:admin2_code":"3067",
    "gn:admin3_code":"306704.0",
    "gn:admin4_code":"30670443.0",
    "gn:asciiname":"Nagar Kachpur",
    "gn:country_code":"BD",
    "gn:dem":9,
    "gn:feature_class":"P",
    "gn:feature_code":"PPL",
    "gn:name":"Nagar K\u0101chpur",
    "gn:population":0,
    "gn:timezone":"Asia/Dhaka",
    "iso:country":"BD",
    "wof:name":"Nagar Kachpur",
    "wof:placetype":"locality"
},
  "geometry": {"coordinates":[90.52482000000001,23.69922],"type":"Point"}
}