{
  "type": "Feature",
  "properties": {
    "gn:admin1_code":"87",
    "gn:admin2_code":"5573.0",
    "gn:admin3_code":"557364.0",
    "gn:admin4_code":"55736406.0",
    "gn:asciiname":"Barua",
    "gn:country_code":"BD",
    "gn:dem":44,
    "gn:feature_class":"P",
    "gn:feature_code":"PPL",
    "gn:name":"Barua",
    "gn:population":0,
    "gn:timezone":"Asia/Dhaka",
    "iso:country":"BD",
    "name:ben_x_preferred":[
        "Barua"
    ],
    "name:deu_x_preferred":[
        "Barua"
    ],
    "name:fra_x_preferred":[
        "Barua"
    ],
    "name:zho_x_preferred":[
        "\u5df4\u9b6f\u963f"
    ],
    "wof:name":"Barua",
    "wof:placetype":"locality"
},
  "geometry": {"coordinates":[88.94830999999998,25.88614],"type":"Point"}
}