{
  "type": "Feature",
  "properties": {
    "gn:admin1_code":"82",
    "gn:admin2_code":"4055.0",
    "gn:admin3_code":"405585.0",
    "gn:admin4_code":"40558571.0",
    "gn:asciiname":"Bahir Mollika",
    "gn:country_code":"BD",
    "gn:dem":10,
    "gn:feature_class":"P",
    "gn:feature_code":"PPL",
    "gn:name":"B\u0101hir Mollika",
    "gn:population":0,
    "gn:timezone":"Asia/Dhaka",
    "iso:country":"BD",
    "name:ben_x_preferred":[
        "B\u0101hir Mollika"
    ],
    "wof:name":"Bahir Mollika",
    "wof:placetype":"locality"
},
  "geometry": {"coordinates":[89.32993,23.3598],"type":"Point"}
}