{
  "type": "Feature",
  "properties": {
    "gn:admin1_code":"81",
    "gn:admin2_code":"3082.0",
    "gn:admin3_code":"308276.0",
    "gn:admin4_code":"30827632.0",
    "gn:asciiname":"Ghorpalan",
    "gn:country_code":"BD",
    "gn:dem":14,
    "gn:feature_class":"P",
    "gn:feature_code":"PPL",
    "gn:name":"Ghorp\u0101l\u0101n",
    "gn:population":0,
    "gn:timezone":"Asia/Dhaka",
    "iso:country":"BD",
    "wof:name":"Ghorpalan",
    "wof:placetype":"locality"
},
  "geometry": {"coordinates":[89.59044,23.73936],"type":"Point"}
}