{
  "type": "Feature",
  "properties": {
    "gn:admin1_code":"87",
    "gn:admin2_code":"5532",
    "gn:admin3_code":"553291.0",
    "gn:admin4_code":"55329188.0",
    "gn:asciiname":"Boalia",
    "gn:country_code":"BD",
    "gn:dem":26,
    "gn:feature_class":"P",
    "gn:feature_code":"PPL",
    "gn:name":"Boalia",
    "gn:population":0,
    "gn:timezone":"Asia/Dhaka",
    "iso:country":"BD",
    "name:ben_x_preferred":[
        "Boalia"
    ],
    "wof:name":"Boalia",
    "wof:placetype":"locality"
},
  "geometry": {"coordinates":[89.59933000000002,25.45559],"type":"Point"}
}