{
  "type": "Feature",
  "properties": {
    "gn:admin1_code":"84",
    "gn:admin2_code":"2022.0",
    "gn:admin3_code":"202290.0",
    "gn:admin4_code":"20229047.0",
    "gn:asciiname":"Repujipara",
    "gn:country_code":"BD",
    "gn:dem":2,
    "gn:feature_class":"P",
    "gn:feature_code":"PPL",
    "gn:name":"Repujip\u0101ra",
    "gn:population":0,
    "gn:timezone":"Asia/Dhaka",
    "iso:country":"BD",
    "name:ben_x_preferred":[
        "Repujip\u0101ra"
    ],
    "wof:name":"Repujipara",
    "wof:placetype":"locality"
},
  "geometry": {"coordinates":[92.32984,20.77771],"type":"Point"}
}