{
  "type": "Feature",
  "properties": {
    "gn:admin1_code":"83",
    "gn:admin2_code":"5038.0",
    "gn:admin3_code":"503861.0",
    "gn:admin4_code":"50386128.0",
    "gn:asciiname":"Sosigram",
    "gn:country_code":"BD",
    "gn:dem":24,
    "gn:feature_class":"P",
    "gn:feature_code":"PPL",
    "gn:name":"Sosigr\u0101m",
    "gn:population":0,
    "gn:timezone":"Asia/Dhaka",
    "iso:country":"BD",
    "name:ben_x_preferred":[
        "Sosigr\u0101m"
    ],
    "wof:name":"Sosigram",
    "wof:placetype":"locality"
},
  "geometry": {"coordinates":[89.13305,25.00714],"type":"Point"}
}