{
  "type": "Feature",
  "properties": {
    "gn:admin1_code":"85",
    "gn:admin2_code":"1042.0",
    "gn:admin3_code":"104243.0",
    "gn:admin4_code":"10424331.0",
    "gn:asciiname":"North Chhitki",
    "gn:country_code":"BD",
    "gn:dem":10,
    "gn:feature_class":"P",
    "gn:feature_code":"PPL",
    "gn:name":"North Chhitki",
    "gn:population":0,
    "gn:timezone":"Asia/Dhaka",
    "iso:country":"BD",
    "name:ben_x_preferred":[
        "North Chhitki"
    ],
    "wof:name":"North Chhitki",
    "wof:placetype":"locality"
},
  "geometry": {"coordinates":[90.16126,22.49499],"type":"Point"}
}