{
  "type": "Feature",
  "properties": {
    "gn:admin1_code":"81",
    "gn:admin2_code":"3056",
    "gn:admin3_code":"305628.0",
    "gn:admin4_code":"30562814.0",
    "gn:asciiname":"Salkhai",
    "gn:country_code":"BD",
    "gn:dem":13,
    "gn:feature_class":"P",
    "gn:feature_code":"PPL",
    "gn:name":"S\u0101lkh\u0101i",
    "gn:population":0,
    "gn:timezone":"Asia/Dhaka",
    "iso:country":"BD",
    "wof:name":"Salkhai",
    "wof:placetype":"locality"
},
  "geometry": {"coordinates":[89.89440999999999,23.77496],"type":"Point"}
}