{
  "type": "Feature",
  "properties": {
    "gn:admin1_code":"85",
    "gn:admin2_code":"1006.0",
    "gn:admin3_code":"100607.0",
    "gn:admin4_code":"10060794.0",
    "gn:asciiname":"Baria",
    "gn:country_code":"BD",
    "gn:dem":10,
    "gn:feature_class":"P",
    "gn:feature_code":"PPL",
    "gn:name":"Baria",
    "gn:population":0,
    "gn:timezone":"Asia/Dhaka",
    "iso:country":"BD",
    "name:ceb_x_preferred":[
        "Baria"
    ],
    "name:fra_x_preferred":[
        "Baria"
    ],
    "name:nld_x_preferred":[
        "Baria"
    ],
    "name:swe_x_preferred":[
        "Baria"
    ],
    "name:vie_x_preferred":[
        "Baria"
    ],
    "wof:name":"Baria",
    "wof:placetype":"locality"
},
  "geometry": {"coordinates":[90.31865000000001,22.56917],"type":"Point"}
}