{
  "type": "Feature",
  "properties": {
    "gn:admin1_code":"87",
    "gn:admin2_code":"5527.0",
    "gn:admin3_code":"552777.0",
    "gn:admin4_code":"55277725.0",
    "gn:asciiname":"Ramraypur",
    "gn:country_code":"BD",
    "gn:dem":39,
    "gn:feature_class":"P",
    "gn:feature_code":"PPL",
    "gn:name":"R\u0101mraypur",
    "gn:population":0,
    "gn:timezone":"Asia/Dhaka",
    "iso:country":"BD",
    "name:ben_x_preferred":[
        "R\u0101mraypur"
    ],
    "wof:name":"Ramraypur",
    "wof:placetype":"locality"
},
  "geometry": {"coordinates":[88.92995000000001,25.57922],"type":"Point"}
}