{
  "type": "Feature",
  "properties": {
    "gn:admin1_code":"84",
    "gn:admin2_code":"2022.0",
    "gn:admin3_code":"202295.0",
    "gn:admin4_code":"20229583.0",
    "gn:asciiname":"Baghachari",
    "gn:country_code":"BD",
    "gn:dem":3,
    "gn:feature_class":"P",
    "gn:feature_code":"PPL",
    "gn:name":"B\u0101ghachari",
    "gn:population":0,
    "gn:timezone":"Asia/Dhaka",
    "iso:country":"BD",
    "name:ben_x_preferred":[
        "B\u0101ghachari"
    ],
    "wof:name":"Baghachari",
    "wof:placetype":"locality"
},
  "geometry": {"coordinates":[91.99292,21.80519],"type":"Point"}
}