{
  "type": "Feature",
  "properties": {
    "gn:admin1_code":"82",
    "gn:admin2_code":"4044.0",
    "gn:admin3_code":"404433.0",
    "gn:admin4_code":"40443300.0",
    "gn:asciiname":"Kashipur",
    "gn:country_code":"BD",
    "gn:dem":12,
    "gn:feature_class":"P",
    "gn:feature_code":"PPL",
    "gn:name":"K\u0101shipur",
    "gn:population":0,
    "gn:timezone":"Asia/Dhaka",
    "iso:country":"BD",
    "name:ben_x_preferred":[
        "K\u0101shipur"
    ],
    "name:hin_x_preferred":[
        "\u0915\u093e\u0936\u0940\u092a\u0941\u0930"
    ],
    "name:rus_x_preferred":[
        "\u041a\u0430\u0448\u0438\u043f\u0443\u0440"
    ],
    "wof:name":"Kashipur",
    "wof:placetype":"locality"
},
  "geometry": {"coordinates":[89.1262,23.3958],"type":"Point"}
}