{
  "type": "Feature",
  "properties": {
    "gn:admin1_code":"87",
    "gn:admin2_code":"5532",
    "gn:admin3_code":"553282.0",
    "gn:admin4_code":"55328269.0",
    "gn:asciiname":"Paika",
    "gn:country_code":"BD",
    "gn:dem":26,
    "gn:feature_class":"P",
    "gn:feature_code":"PPL",
    "gn:name":"Paika",
    "gn:population":0,
    "gn:timezone":"Asia/Dhaka",
    "iso:country":"BD",
    "name:ben_x_preferred":[
        "Paika"
    ],
    "name:mal_x_preferred":[
        "\u0d2a\u0d48\u0d15"
    ],
    "wof:name":"Paika",
    "wof:placetype":"locality"
},
  "geometry": {"coordinates":[89.41949,25.31371],"type":"Point"}
}