{
  "type": "Feature",
  "properties": {
    "gn:admin1_code":"H",
    "gn:asciiname":"Kulkandi",
    "gn:country_code":"BD",
    "gn:dem":21,
    "gn:feature_class":"P",
    "gn:feature_code":"PPL",
    "gn:name":"Kulk\u0101ndi",
    "gn:population":0,
    "gn:timezone":"Asia/Dhaka",
    "iso:country":"BD",
    "name:ben_x_preferred":[
        "Kulk\u0101ndi"
    ],
    "wof:name":"Kulkandi",
    "wof:placetype":"locality"
},
  "geometry": {"coordinates":[89.7146,25.12396],"type":"Point"}
}