{
  "type": "Feature",
  "properties": {
    "gn:admin1_code":"84",
    "gn:admin2_code":"2015.0",
    "gn:admin3_code":"201561.0",
    "gn:admin4_code":"20156188.0",
    "gn:asciiname":"Hatiaghona",
    "gn:country_code":"BD",
    "gn:dem":7,
    "gn:feature_class":"P",
    "gn:feature_code":"PPL",
    "gn:name":"H\u0101ti\u0101ghona",
    "gn:population":0,
    "gn:timezone":"Asia/Dhaka",
    "iso:country":"BD",
    "name:ben_x_preferred":[
        "H\u0101ti\u0101ghona"
    ],
    "wof:name":"Hatiaghona",
    "wof:placetype":"locality"
},
  "geometry": {"coordinates":[91.98509,22.23047],"type":"Point"}
}