{
  "type": "Feature",
  "properties": {
    "gn:admin1_code":"84",
    "gn:admin2_code":"2084.0",
    "gn:admin3_code":"208436.0",
    "gn:admin4_code":"20843676.0",
    "gn:asciiname":"Chandraghona",
    "gn:country_code":"BD",
    "gn:dem":19,
    "gn:feature_class":"P",
    "gn:feature_code":"PPL",
    "gn:name":"Chandraghona",
    "gn:population":0,
    "gn:timezone":"Asia/Dhaka",
    "iso:country":"BD",
    "name:ben_x_preferred":[
        "Chandraghona"
    ],
    "name:und_x_variant":[
        "Chandraghona Kadamtali"
    ],
    "wof:name":"Chandraghona",
    "wof:placetype":"locality"
},
  "geometry": {"coordinates":[92.14171,22.47522],"type":"Point"}
}