{
  "type": "Feature",
  "properties": {
    "gn:admin1_code":"85",
    "gn:admin2_code":"1042",
    "gn:admin3_code":"104284.0",
    "gn:admin4_code":"10428413.0",
    "gn:asciiname":"Palat",
    "gn:country_code":"BD",
    "gn:dem":10,
    "gn:feature_class":"P",
    "gn:feature_code":"PPL",
    "gn:name":"P\u0101lat",
    "gn:population":0,
    "gn:timezone":"Asia/Dhaka",
    "iso:country":"BD",
    "name:bul_x_preferred":[
        "\u041f\u0430\u043b\u0430\u0442"
    ],
    "name:fas_x_preferred":[
        "\u067e\u0627\u0644\u0627\u062a"
    ],
    "name:kaz_x_preferred":[
        "\u041f\u0430\u043b\u0430\u0442"
    ],
    "name:mkd_x_preferred":[
        "\u041f\u0430\u043b\u0430\u0442"
    ],
    "name:ron_x_preferred":[
        "Palat"
    ],
    "name:rus_x_preferred":[
        "\u041f\u0430\u043b\u0430\u0442"
    ],
    "name:ukr_x_preferred":[
        "\u041f\u0430\u043b\u0430\u0442"
    ],
    "wof:name":"Palat",
    "wof:placetype":"locality"
},
  "geometry": {"coordinates":[90.20005999999999,22.51264],"type":"Point"}
}