{
  "type": "Feature",
  "properties": {
    "gn:admin1_code":"83",
    "gn:admin2_code":"5081.0",
    "gn:admin3_code":"508153.0",
    "gn:admin4_code":"50815381.0",
    "gn:asciiname":"Fulsa",
    "gn:country_code":"BD",
    "gn:dem":19,
    "gn:feature_class":"P",
    "gn:feature_code":"PPL",
    "gn:name":"Fulsa",
    "gn:population":0,
    "gn:timezone":"Asia/Dhaka",
    "iso:country":"BD",
    "name:ben_x_preferred":[
        "Fulsa"
    ],
    "wof:name":"Fulsa",
    "wof:placetype":"locality"
},
  "geometry": {"coordinates":[88.64281,24.58323],"type":"Point"}
}