{
  "type": "Feature",
  "properties": {
    "gn:admin1_code":"84",
    "gn:admin2_code":"2084",
    "gn:admin3_code":"208447.0",
    "gn:admin4_code":"20844776.0",
    "gn:asciiname":"Silchari",
    "gn:country_code":"BD",
    "gn:dem":48,
    "gn:feature_class":"P",
    "gn:feature_code":"PPL",
    "gn:name":"Silchari",
    "gn:population":0,
    "gn:timezone":"Asia/Dhaka",
    "iso:country":"BD",
    "wof:name":"Silchari",
    "wof:placetype":"locality"
},
  "geometry": {"coordinates":[92.38039999999999,22.59799],"type":"Point"}
}