{
  "type": "Feature",
  "properties": {
    "gn:admin1_code":"82",
    "gn:asciiname":"Muradnagar",
    "gn:country_code":"BD",
    "gn:dem":8,
    "gn:feature_class":"P",
    "gn:feature_code":"PPL",
    "gn:name":"Mur\u0101dnagar",
    "gn:population":0,
    "gn:timezone":"Asia/Dhaka",
    "iso:country":"BD",
    "name:ben_x_preferred":[
        "Mur\u0101dnagar"
    ],
    "name:bpy_x_preferred":[
        "\u09ae\u09c1\u09b0\u09be\u09a6 \u09a8\u0997\u09b0"
    ],
    "name:ceb_x_preferred":[
        "Mur\u0101dnagar"
    ],
    "name:fas_x_preferred":[
        "\u0645\u0631\u0627\u062f\u0646\u06af\u0631"
    ],
    "name:hin_x_preferred":[
        "\u092e\u0941\u0930\u093e\u0926\u0928\u0917\u0930"
    ],
    "name:ita_x_preferred":[
        "Muradnagar"
    ],
    "name:mlg_x_preferred":[
        "Muradnagar"
    ],
    "name:msa_x_preferred":[
        "Muradnagar"
    ],
    "name:new_x_preferred":[
        "\u092e\u0941\u0930\u093e\u0926\u0928\u0917\u0930"
    ],
    "name:nld_x_preferred":[
        "Muradnagar"
    ],
    "name:pol_x_preferred":[
        "Muradnagar"
    ],
    "name:por_x_preferred":[
        "Muradnagar"
    ],
    "name:swe_x_preferred":[
        "Muradnagar"
    ],
    "name:urd_x_preferred":[
        "\u0645\u0631\u0627\u062f \u0646\u06af\u0631"
    ],
    "name:vie_x_preferred":[
        "Muradnagar"
    ],
    "name:zho_x_preferred":[
        "\u7a46\u62c9\u5fb7\u7eb3\u52a0\u5c14"
    ],
    "wof:name":"Muradnagar",
    "wof:placetype":"locality"
},
  "geometry": {"coordinates":[90.42197,22.14957],"type":"Point"}
}