{
  "type": "Feature",
  "properties": {
    "gn:admin1_code":"H",
    "gn:admin2_code":"3061",
    "gn:admin3_code":"306131.0",
    "gn:admin4_code":"30613190.0",
    "gn:asciiname":"Madhur Baira",
    "gn:country_code":"BD",
    "gn:dem":18,
    "gn:feature_class":"P",
    "gn:feature_code":"PPL",
    "gn:name":"Madhur B\u0101ira",
    "gn:population":0,
    "gn:timezone":"Asia/Dhaka",
    "iso:country":"BD",
    "wof:name":"Madhur Baira",
    "wof:placetype":"locality"
},
  "geometry": {"coordinates":[90.51134999999999,24.66655],"type":"Point"}
}