{
  "type": "Feature",
  "properties": {
    "gn:admin1_code":"84",
    "gn:admin2_code":"2015.0",
    "gn:admin3_code":"201533.0",
    "gn:admin4_code":"20153385.0",
    "gn:asciiname":"Lat Baramasia",
    "gn:country_code":"BD",
    "gn:dem":23,
    "gn:feature_class":"P",
    "gn:feature_code":"PPL",
    "gn:name":"Lat Baramasia",
    "gn:population":0,
    "gn:timezone":"Asia/Dhaka",
    "iso:country":"BD",
    "wof:name":"Lat Baramasia",
    "wof:placetype":"locality"
},
  "geometry": {"coordinates":[91.71917000000001,22.67306],"type":"Point"}
}