{
  "type": "Feature",
  "properties": {
    "gn:admin1_code":"82",
    "gn:admin2_code":"4001.0",
    "gn:admin3_code":"400177.0",
    "gn:admin4_code":"40017738.0",
    "gn:asciiname":"Baniakhali",
    "gn:country_code":"BD",
    "gn:dem":7,
    "gn:feature_class":"P",
    "gn:feature_code":"PPL",
    "gn:name":"Baniakhali",
    "gn:population":0,
    "gn:timezone":"Asia/Dhaka",
    "iso:country":"BD",
    "name:ben_x_preferred":[
        "Baniakhali"
    ],
    "wof:name":"Baniakhali",
    "wof:placetype":"locality"
},
  "geometry": {"coordinates":[89.85600000000002,22.36907],"type":"Point"}
}