{
  "type": "Feature",
  "properties": {
    "gn:admin1_code":"84",
    "gn:admin2_code":"2019",
    "gn:admin3_code":"201909.0",
    "gn:admin4_code":"20190906.0",
    "gn:asciiname":"North Tulagaon",
    "gn:country_code":"BD",
    "gn:dem":12,
    "gn:feature_class":"P",
    "gn:feature_code":"PPL",
    "gn:name":"North Tul\u0101gaon",
    "gn:population":0,
    "gn:timezone":"Asia/Dhaka",
    "iso:country":"BD",
    "name:und_x_variant":[
        "Tul\u0101gaon",
        "North Tul\u0101gaon"
    ],
    "wof:name":"North Tulagaon",
    "wof:placetype":"locality"
},
  "geometry": {"coordinates":[90.97574,23.32601],"type":"Point"}
}