{
  "type": "Feature",
  "properties": {
    "gn:admin1_code":"H",
    "gn:admin2_code":"3039",
    "gn:admin3_code":"303907.0",
    "gn:admin4_code":"30390723.0",
    "gn:asciiname":"Bakshinganj",
    "gn:country_code":"BD",
    "gn:dem":26,
    "gn:feature_class":"P",
    "gn:feature_code":"PPL",
    "gn:name":"Bakshinganj",
    "gn:population":0,
    "gn:timezone":"Asia/Dhaka",
    "iso:country":"BD",
    "name:ben_x_preferred":[
        "Bakshinganj"
    ],
    "name:und_x_variant":[
        "Kachari",
        "Bakshinganj Kachehn"
    ],
    "wof:name":"Bakshinganj",
    "wof:placetype":"locality"
},
  "geometry": {"coordinates":[89.86928,25.1849],"type":"Point"}
}