{
  "type": "Feature",
  "properties": {
    "gn:admin1_code":"81",
    "gn:admin2_code":"3093",
    "gn:admin3_code":"309347.0",
    "gn:admin4_code":"30934765.0",
    "gn:asciiname":"Kagmari Chhatihati",
    "gn:country_code":"BD",
    "gn:dem":18,
    "gn:feature_class":"P",
    "gn:feature_code":"PPL",
    "gn:name":"K\u0101gm\u0101ri Chh\u0101tih\u0101ti",
    "gn:population":0,
    "gn:timezone":"Asia/Dhaka",
    "iso:country":"BD",
    "wof:name":"Kagmari Chhatihati",
    "wof:placetype":"locality"
},
  "geometry": {"coordinates":[90.03859,24.35512],"type":"Point"}
}