{
  "type": "Feature",
  "properties": {
    "gn:admin1_code":"81",
    "gn:admin2_code":"3067",
    "gn:admin3_code":"306704.0",
    "gn:admin4_code":"30670494.0",
    "gn:asciiname":"Paika",
    "gn:country_code":"BD",
    "gn:dem":9,
    "gn:feature_class":"P",
    "gn:feature_code":"PPL",
    "gn:name":"P\u0101ika",
    "gn:population":0,
    "gn:timezone":"Asia/Dhaka",
    "iso:country":"BD",
    "name:mal_x_preferred":[
        "\u0d2a\u0d48\u0d15"
    ],
    "wof:name":"Paika",
    "wof:placetype":"locality"
},
  "geometry": {"coordinates":[90.59884,23.67491],"type":"Point"}
}