{
  "type": "Feature",
  "properties": {
    "gn:admin1_code":"87",
    "gn:admin2_code":"5527.0",
    "gn:admin3_code":"552712.0",
    "gn:admin4_code":"55271251.0",
    "gn:asciiname":"Bajitpur",
    "gn:country_code":"BD",
    "gn:dem":54,
    "gn:feature_class":"P",
    "gn:feature_code":"PPL",
    "gn:name":"B\u0101jitpur",
    "gn:population":0,
    "gn:timezone":"Asia/Dhaka",
    "iso:country":"BD",
    "name:ben_x_preferred":[
        "B\u0101jitpur"
    ],
    "wof:name":"Bajitpur",
    "wof:placetype":"locality"
},
  "geometry": {"coordinates":[88.64374000000002,25.99942],"type":"Point"}
}