{
  "type": "Feature",
  "properties": {
    "gn:admin1_code":"83",
    "gn:admin2_code":"5038",
    "gn:admin3_code":"503861.0",
    "gn:admin4_code":"50386119.0",
    "gn:asciiname":"Telabadal",
    "gn:country_code":"BD",
    "gn:dem":25,
    "gn:feature_class":"P",
    "gn:feature_code":"PPL",
    "gn:name":"Tel\u0101badal",
    "gn:population":0,
    "gn:timezone":"Asia/Dhaka",
    "iso:country":"BD",
    "name:und_x_variant":[
        "Tel\u0101badal",
        "Tel\u0101b\u0101dal"
    ],
    "wof:name":"Telabadal",
    "wof:placetype":"locality"
},
  "geometry": {"coordinates":[89.09663,25.06641],"type":"Point"}
}