{
  "type": "Feature",
  "properties": {
    "gn:admin1_code":"81",
    "gn:admin2_code":"3082.0",
    "gn:admin3_code":"308273.0",
    "gn:admin4_code":"30827305.0",
    "gn:asciiname":"Bholaidangi",
    "gn:country_code":"BD",
    "gn:dem":2,
    "gn:feature_class":"P",
    "gn:feature_code":"PPL",
    "gn:name":"Bhol\u0101id\u0101ngi",
    "gn:population":0,
    "gn:timezone":"Asia/Dhaka",
    "iso:country":"BD",
    "wof:name":"Bholaidangi",
    "wof:placetype":"locality"
},
  "geometry": {"coordinates":[89.38333,23.88333],"type":"Point"}
}