{
  "type": "Feature",
  "properties": {
    "gn:admin1_code":"H",
    "gn:admin2_code":"3061.0",
    "gn:admin3_code":"306181.0",
    "gn:admin4_code":"30618172.0",
    "gn:asciiname":"Charia",
    "gn:country_code":"BD",
    "gn:dem":16,
    "gn:feature_class":"P",
    "gn:feature_code":"PPL",
    "gn:name":"Charia",
    "gn:population":0,
    "gn:timezone":"Asia/Dhaka",
    "iso:country":"BD",
    "name:ell_x_preferred":[
        "\u03a7\u03b1\u03c1\u03b9\u03ac \u0397\u03bb\u03b5\u03af\u03b1\u03c2"
    ],
    "wof:name":"Charia",
    "wof:placetype":"locality"
},
  "geometry": {"coordinates":[90.51057,24.8785],"type":"Point"}
}