{
  "type": "Feature",
  "properties": {
    "gn:admin1_code":"H",
    "gn:admin2_code":"3072",
    "gn:admin3_code":"307204.0",
    "gn:admin4_code":"30720447.0",
    "gn:asciiname":"Madal",
    "gn:country_code":"BD",
    "gn:dem":12,
    "gn:feature_class":"P",
    "gn:feature_code":"PPL",
    "gn:name":"M\u0101dal",
    "gn:population":0,
    "gn:timezone":"Asia/Dhaka",
    "iso:country":"BD",
    "name:cat_x_preferred":[
        "Madal"
    ],
    "name:nep_x_preferred":[
        "\u092e\u093e\u0926\u0932"
    ],
    "name:spa_x_preferred":[
        "Madal"
    ],
    "wof:name":"Madal",
    "wof:placetype":"locality"
},
  "geometry": {"coordinates":[90.81023,24.84097],"type":"Point"}
}