{
  "type": "Feature",
  "properties": {
    "gn:admin1_code":"86",
    "gn:admin2_code":"6036",
    "gn:admin3_code":"603644.0",
    "gn:admin4_code":"60364428.0",
    "gn:asciiname":"Jadabpur",
    "gn:country_code":"BD",
    "gn:dem":9,
    "gn:feature_class":"P",
    "gn:feature_code":"PPL",
    "gn:name":"J\u0101dabpur",
    "gn:population":0,
    "gn:timezone":"Asia/Dhaka",
    "iso:country":"BD",
    "wof:name":"Jadabpur",
    "wof:placetype":"locality"
},
  "geometry": {"coordinates":[91.32102999999999,24.36142000000001],"type":"Point"}
}