{
  "type": "Feature",
  "properties": {
    "gn:admin1_code":"86",
    "gn:admin2_code":"6036.0",
    "gn:admin3_code":"603611.0",
    "gn:admin4_code":"60361144.0",
    "gn:asciiname":"Bogi",
    "gn:country_code":"BD",
    "gn:dem":13,
    "gn:feature_class":"P",
    "gn:feature_code":"PPL",
    "gn:name":"Bogi",
    "gn:population":0,
    "gn:timezone":"Asia/Dhaka",
    "iso:country":"BD",
    "name:und_x_variant":[
        "Bagi",
        "Bogi"
    ],
    "wof:name":"Bogi",
    "wof:placetype":"locality"
},
  "geometry": {"coordinates":[91.39928,24.58385],"type":"Point"}
}