{
  "type": "Feature",
  "properties": {
    "gn:admin1_code":"83",
    "gn:admin2_code":"5081.0",
    "gn:admin3_code":"508153.0",
    "gn:admin4_code":"50815367.0",
    "gn:asciiname":"San Khajura",
    "gn:country_code":"BD",
    "gn:dem":20,
    "gn:feature_class":"P",
    "gn:feature_code":"PPL",
    "gn:name":"San Kh\u0101jura",
    "gn:population":0,
    "gn:timezone":"Asia/Dhaka",
    "iso:country":"BD",
    "name:ben_x_preferred":[
        "San Kh\u0101jura"
    ],
    "wof:name":"San Khajura",
    "wof:placetype":"locality"
},
  "geometry": {"coordinates":[88.62455,24.51814],"type":"Point"}
}