{
  "type": "Feature",
  "properties": {
    "gn:admin1_code":"84",
    "gn:admin2_code":"2046.0",
    "gn:admin3_code":"204680.0",
    "gn:admin4_code":"20468076.0",
    "gn:asciiname":"Godiapara",
    "gn:country_code":"BD",
    "gn:dem":40,
    "gn:feature_class":"P",
    "gn:feature_code":"PPL",
    "gn:name":"Godiapara",
    "gn:population":0,
    "gn:timezone":"Asia/Dhaka",
    "iso:country":"BD",
    "name:ben_x_preferred":[
        "Godiapara"
    ],
    "wof:name":"Godiapara",
    "wof:placetype":"locality"
},
  "geometry": {"coordinates":[91.75266000000001,22.9963],"type":"Point"}
}