{
  "type": "Feature",
  "properties": {
    "gn:admin1_code":"83",
    "gn:admin2_code":"5038.0",
    "gn:admin3_code":"503858.0",
    "gn:admin4_code":"50385885.0",
    "gn:asciiname":"Arbab",
    "gn:country_code":"BD",
    "gn:dem":24,
    "gn:feature_class":"P",
    "gn:feature_code":"PPL",
    "gn:name":"Arb\u0101b",
    "gn:population":0,
    "gn:timezone":"Asia/Dhaka",
    "iso:country":"BD",
    "name:ben_x_preferred":[
        "Arb\u0101b"
    ],
    "wof:name":"Arbab",
    "wof:placetype":"locality"
},
  "geometry": {"coordinates":[89.20432,25.09411],"type":"Point"}
}