{
  "type": "Feature",
  "properties": {
    "gn:admin1_code":"82",
    "gn:admin2_code":"4050.0",
    "gn:admin3_code":"405094.0",
    "gn:admin4_code":"40509407.0",
    "gn:asciiname":"Bhedamari",
    "gn:country_code":"BD",
    "gn:dem":17,
    "gn:feature_class":"P",
    "gn:feature_code":"PPL",
    "gn:name":"Bhedam\u0101ri",
    "gn:population":0,
    "gn:timezone":"Asia/Dhaka",
    "iso:country":"BD",
    "name:ben_x_preferred":[
        "Bhedam\u0101ri"
    ],
    "wof:name":"Bhedamari",
    "wof:placetype":"locality"
},
  "geometry": {"coordinates":[88.96373,23.81789],"type":"Point"}
}