{
  "type": "Feature",
  "properties": {
    "gn:admin1_code":"83",
    "gn:admin2_code":"5038",
    "gn:admin3_code":"503874.0",
    "gn:admin4_code":"50387410.0",
    "gn:asciiname":"Raigaon",
    "gn:country_code":"BD",
    "gn:dem":27,
    "gn:feature_class":"P",
    "gn:feature_code":"PPL",
    "gn:name":"R\u0101igaon",
    "gn:population":0,
    "gn:timezone":"Asia/Dhaka",
    "iso:country":"BD",
    "wof:name":"Raigaon",
    "wof:placetype":"locality"
},
  "geometry": {"coordinates":[89.16986,25.17682000000001],"type":"Point"}
}