{
  "type": "Feature",
  "properties": {
    "gn:admin1_code":"87",
    "gn:admin2_code":"5549",
    "gn:admin3_code":"554961.0",
    "gn:admin4_code":"55496131.0",
    "gn:asciiname":"Hasnabad Khamar",
    "gn:country_code":"BD",
    "gn:dem":31,
    "gn:feature_class":"P",
    "gn:feature_code":"PPL",
    "gn:name":"H\u0101snab\u0101d Kham\u0101r",
    "gn:population":0,
    "gn:timezone":"Asia/Dhaka",
    "iso:country":"BD",
    "name:ben_x_preferred":[
        "H\u0101snab\u0101d Kham\u0101r"
    ],
    "wof:name":"Hasnabad Khamar",
    "wof:placetype":"locality"
},
  "geometry": {"coordinates":[89.67193,25.93509],"type":"Point"}
}