{
  "type": "Feature",
  "properties": {
    "gn:admin1_code":"81",
    "gn:admin2_code":"3056",
    "gn:admin3_code":"305678.0",
    "gn:admin4_code":"30567883.0",
    "gn:asciiname":"Isail",
    "gn:country_code":"BD",
    "gn:dem":12,
    "gn:feature_class":"P",
    "gn:feature_code":"PPL",
    "gn:name":"Is\u0101il",
    "gn:population":0,
    "gn:timezone":"Asia/Dhaka",
    "iso:country":"BD",
    "wof:name":"Isail",
    "wof:placetype":"locality"
},
  "geometry": {"coordinates":[89.81600999999998,23.83412],"type":"Point"}
}