{
  "type": "Feature",
  "properties": {
    "gn:admin1_code":"87",
    "gn:admin2_code":"5527.0",
    "gn:admin3_code":"552712.0",
    "gn:admin4_code":"55271243.0",
    "gn:asciiname":"Aulakuri",
    "gn:country_code":"BD",
    "gn:dem":45,
    "gn:feature_class":"P",
    "gn:feature_code":"PPL",
    "gn:name":"Aul\u0101kuri",
    "gn:population":0,
    "gn:timezone":"Asia/Dhaka",
    "iso:country":"BD",
    "name:ben_x_preferred":[
        "Aul\u0101kuri"
    ],
    "wof:name":"Aulakuri",
    "wof:placetype":"locality"
},
  "geometry": {"coordinates":[88.65907,25.91108],"type":"Point"}
}