{
  "type": "Feature",
  "properties": {
    "gn:admin1_code":"81",
    "gn:admin2_code":"3059",
    "gn:admin3_code":"305944.0",
    "gn:admin4_code":"30594407.0",
    "gn:asciiname":"Kalikata",
    "gn:country_code":"BD",
    "gn:dem":7,
    "gn:feature_class":"P",
    "gn:feature_code":"PPL",
    "gn:name":"Kalik\u0101ta",
    "gn:population":0,
    "gn:timezone":"Asia/Dhaka",
    "iso:country":"BD",
    "name:ben_x_preferred":[
        "\u0995\u09b2\u09bf\u0995\u09be\u09a4\u09be"
    ],
    "wof:name":"Kalikata",
    "wof:placetype":"locality"
},
  "geometry": {"coordinates":[90.35699,23.47896],"type":"Point"}
}