{
  "type": "Feature",
  "properties": {
    "gn:admin1_code":"84",
    "gn:admin2_code":"2084.0",
    "gn:admin3_code":"208425.0",
    "gn:admin4_code":"20842557.0",
    "gn:asciiname":"Baraichari",
    "gn:country_code":"BD",
    "gn:dem":70,
    "gn:feature_class":"P",
    "gn:feature_code":"PPL",
    "gn:name":"Bar\u0101ichari",
    "gn:population":0,
    "gn:timezone":"Asia/Dhaka",
    "iso:country":"BD",
    "name:ben_x_preferred":[
        "Bar\u0101ichari"
    ],
    "wof:name":"Baraichari",
    "wof:placetype":"locality"
},
  "geometry": {"coordinates":[92.00646999999999,22.64505],"type":"Point"}
}