{
  "type": "Feature",
  "properties": {
    "gn:admin1_code":"82",
    "gn:admin2_code":"4050.0",
    "gn:admin3_code":"405079.0",
    "gn:admin4_code":"40507900.0",
    "gn:asciiname":"Harisankarpur",
    "gn:country_code":"BD",
    "gn:dem":17,
    "gn:feature_class":"P",
    "gn:feature_code":"PPL",
    "gn:name":"Harisankarpur",
    "gn:population":0,
    "gn:timezone":"Asia/Dhaka",
    "iso:country":"BD",
    "name:ben_x_preferred":[
        "Harisankarpur"
    ],
    "wof:name":"Harisankarpur",
    "wof:placetype":"locality"
},
  "geometry": {"coordinates":[89.14624999999999,23.89321],"type":"Point"}
}