{
  "type": "Feature",
  "properties": {
    "gn:admin1_code":"85",
    "gn:admin2_code":"1079.0",
    "gn:admin3_code":"107958.0",
    "gn:admin4_code":"10795808.0",
    "gn:asciiname":"Dhupati",
    "gn:country_code":"BD",
    "gn:dem":10,
    "gn:feature_class":"P",
    "gn:feature_code":"PPL",
    "gn:name":"Dhupati",
    "gn:population":0,
    "gn:timezone":"Asia/Dhaka",
    "iso:country":"BD",
    "name:ben_x_preferred":[
        "Dhupati"
    ],
    "wof:name":"Dhupati",
    "wof:placetype":"locality"
},
  "geometry": {"coordinates":[89.92893000000002,22.25577],"type":"Point"}
}