{
  "type": "Feature",
  "properties": {
    "gn:admin1_code":"87",
    "gn:admin2_code":"5585.0",
    "gn:admin3_code":"558573.0",
    "gn:admin4_code":"55857319.0",
    "gn:asciiname":"Hasim",
    "gn:country_code":"BD",
    "gn:dem":30,
    "gn:feature_class":"P",
    "gn:feature_code":"PPL",
    "gn:name":"H\u0101sim",
    "gn:population":0,
    "gn:timezone":"Asia/Dhaka",
    "iso:country":"BD",
    "name:ben_x_preferred":[
        "H\u0101sim"
    ],
    "wof:name":"Hasim",
    "wof:placetype":"locality"
},
  "geometry": {"coordinates":[89.49563000000001,25.68717],"type":"Point"}
}