{
  "type": "Feature",
  "properties": {
    "gn:admin1_code":"83",
    "gn:admin2_code":"5010.0",
    "gn:admin3_code":"501094.0",
    "gn:admin4_code":"50109455.0",
    "gn:asciiname":"Chalunja",
    "gn:country_code":"BD",
    "gn:dem":25,
    "gn:feature_class":"P",
    "gn:feature_code":"PPL",
    "gn:name":"Ch\u0101lunja",
    "gn:population":0,
    "gn:timezone":"Asia/Dhaka",
    "iso:country":"BD",
    "wof:name":"Chalunja",
    "wof:placetype":"locality"
},
  "geometry": {"coordinates":[89.20704000000001,24.92962],"type":"Point"}
}