{
  "type": "Feature",
  "properties": {
    "gn:admin1_code":"87",
    "gn:admin2_code":"5577.0",
    "gn:admin3_code":"557725.0",
    "gn:admin4_code":"55772551.0",
    "gn:asciiname":"Kaihat Manikchand",
    "gn:country_code":"BD",
    "gn:dem":70,
    "gn:feature_class":"P",
    "gn:feature_code":"PPL",
    "gn:name":"K\u0101ih\u0101t Manikchand",
    "gn:population":0,
    "gn:timezone":"Asia/Dhaka",
    "iso:country":"BD",
    "name:ben_x_preferred":[
        "K\u0101ih\u0101t Manikchand"
    ],
    "wof:name":"Kaihat Manikchand",
    "wof:placetype":"locality"
},
  "geometry": {"coordinates":[88.47253000000001,26.26561],"type":"Point"}
}