{
  "type": "Feature",
  "properties": {
    "gn:admin1_code":"81",
    "gn:admin2_code":"3035.0",
    "gn:admin3_code":"303558.0",
    "gn:admin4_code":"30355878.0",
    "gn:asciiname":"Bahirbhag",
    "gn:country_code":"BD",
    "gn:dem":10,
    "gn:feature_class":"P",
    "gn:feature_code":"PPL",
    "gn:name":"B\u0101hirbh\u0101g",
    "gn:population":0,
    "gn:timezone":"Asia/Dhaka",
    "iso:country":"BD",
    "name:und_x_variant":[
        "Bahirbag",
        "B\u0101hirbh\u0101g"
    ],
    "wof:name":"Bahirbhag",
    "wof:placetype":"locality"
},
  "geometry": {"coordinates":[89.80086999999997,23.31406],"type":"Point"}
}