{
  "type": "Feature",
  "properties": {
    "gn:admin1_code":"82",
    "gn:asciiname":"North Dharandi",
    "gn:country_code":"BD",
    "gn:dem":8,
    "gn:feature_class":"P",
    "gn:feature_code":"PPL",
    "gn:name":"North Dharandi",
    "gn:population":0,
    "gn:timezone":"Asia/Dhaka",
    "iso:country":"BD",
    "name:ben_x_preferred":[
        "North Dharandi"
    ],
    "wof:name":"North Dharandi",
    "wof:placetype":"locality"
},
  "geometry": {"coordinates":[90.42457,22.33611],"type":"Point"}
}