{
  "type": "Feature",
  "properties": {
    "gn:admin1_code":"81",
    "gn:admin2_code":"3056",
    "gn:admin3_code":"305682.0",
    "gn:admin4_code":"30568251.0",
    "gn:asciiname":"Kahadia",
    "gn:country_code":"BD",
    "gn:dem":12,
    "gn:feature_class":"P",
    "gn:feature_code":"PPL",
    "gn:name":"K\u0101hadia",
    "gn:population":0,
    "gn:timezone":"Asia/Dhaka",
    "iso:country":"BD",
    "wof:name":"Kahadia",
    "wof:placetype":"locality"
},
  "geometry": {"coordinates":[90.16831999999999,23.80099],"type":"Point"}
}