{
  "type": "Feature",
  "properties": {
    "gn:admin1_code":"H",
    "gn:admin2_code":"3039.0",
    "gn:admin3_code":"303985.0",
    "gn:admin4_code":"30398521.0",
    "gn:asciiname":"Bangali",
    "gn:country_code":"BD",
    "gn:dem":21,
    "gn:feature_class":"P",
    "gn:feature_code":"PPL",
    "gn:name":"B\u0101ng\u0101li",
    "gn:population":0,
    "gn:timezone":"Asia/Dhaka",
    "iso:country":"BD",
    "name:und_x_variant":[
        "Bangallee",
        "B\u0101ng\u0101li"
    ],
    "wof:name":"Bangali",
    "wof:placetype":"locality"
},
  "geometry": {"coordinates":[89.87245,24.80042000000001],"type":"Point"}
}