{
  "type": "Feature",
  "properties": {
    "gn:admin1_code":"87",
    "gn:admin2_code":"5549",
    "gn:admin3_code":"554906.0",
    "gn:admin4_code":"55490666.0",
    "gn:asciiname":"Chirpaiker Chhara",
    "gn:country_code":"BD",
    "gn:dem":34,
    "gn:feature_class":"P",
    "gn:feature_code":"PPL",
    "gn:name":"Chirpaiker Chhara",
    "gn:population":0,
    "gn:timezone":"Asia/Dhaka",
    "iso:country":"BD",
    "name:ben_x_preferred":[
        "Chirpaiker Chhara"
    ],
    "wof:name":"Chirpaiker Chhara",
    "wof:placetype":"locality"
},
  "geometry": {"coordinates":[89.73793000000001,26.11557],"type":"Point"}
}