{
  "type": "Feature",
  "properties": {
    "gn:admin1_code":"85",
    "gn:admin2_code":"1079.0",
    "gn:admin3_code":"107958.0",
    "gn:admin4_code":"10795851.0",
    "gn:asciiname":"Kabutarkhali",
    "gn:country_code":"BD",
    "gn:dem":6,
    "gn:feature_class":"P",
    "gn:feature_code":"PPL",
    "gn:name":"Kabutarkhali",
    "gn:population":0,
    "gn:timezone":"Asia/Dhaka",
    "iso:country":"BD",
    "name:ben_x_preferred":[
        "Kabutarkhali"
    ],
    "wof:name":"Kabutarkhali",
    "wof:placetype":"locality"
},
  "geometry": {"coordinates":[89.95971,22.25712],"type":"Point"}
}