{
  "type": "Feature",
  "properties": {
    "gn:admin1_code":"83",
    "gn:admin2_code":"5064.0",
    "gn:admin3_code":"506486.0",
    "gn:admin4_code":"50648639.0",
    "gn:asciiname":"Dangapara",
    "gn:country_code":"BD",
    "gn:dem":39,
    "gn:feature_class":"P",
    "gn:feature_code":"PPL",
    "gn:name":"D\u0101ng\u0101p\u0101ra",
    "gn:population":0,
    "gn:timezone":"Asia/Dhaka",
    "iso:country":"BD",
    "name:ben_x_preferred":[
        "D\u0101ng\u0101p\u0101ra"
    ],
    "wof:name":"Dangapara",
    "wof:placetype":"locality"
},
  "geometry": {"coordinates":[88.54104,25.12845],"type":"Point"}
}