{
  "type": "Feature",
  "properties": {
    "gn:admin1_code":"81",
    "gn:admin2_code":"3056.0",
    "gn:admin3_code":"305670.0",
    "gn:admin4_code":"30567057.0",
    "gn:asciiname":"Chainta",
    "gn:country_code":"BD",
    "gn:dem":14,
    "gn:feature_class":"P",
    "gn:feature_code":"PPL",
    "gn:name":"Chainta",
    "gn:population":0,
    "gn:timezone":"Asia/Dhaka",
    "iso:country":"BD",
    "wof:name":"Chainta",
    "wof:placetype":"locality"
},
  "geometry": {"coordinates":[90.05561999999998,23.9226],"type":"Point"}
}