{
  "type": "Feature",
  "properties": {
    "gn:admin1_code":"87",
    "gn:admin2_code":"5585",
    "gn:admin3_code":"558549.0",
    "gn:admin4_code":"55854923.0",
    "gn:asciiname":"Manthana",
    "gn:country_code":"BD",
    "gn:dem":40,
    "gn:feature_class":"P",
    "gn:feature_code":"PPL",
    "gn:name":"Manthana",
    "gn:population":0,
    "gn:timezone":"Asia/Dhaka",
    "iso:country":"BD",
    "name:ben_x_preferred":[
        "Manthana"
    ],
    "wof:name":"Manthana",
    "wof:placetype":"locality"
},
  "geometry": {"coordinates":[89.17473000000003,25.80728],"type":"Point"}
}