{
  "type": "Feature",
  "properties": {
    "gn:admin1_code":"82",
    "gn:admin2_code":"4018.0",
    "gn:admin3_code":"401831.0",
    "gn:admin4_code":"40183183.0",
    "gn:asciiname":"Shibnagar",
    "gn:country_code":"BD",
    "gn:dem":17,
    "gn:feature_class":"P",
    "gn:feature_code":"PPL",
    "gn:name":"Shibnagar",
    "gn:population":0,
    "gn:timezone":"Asia/Dhaka",
    "iso:country":"BD",
    "name:ben_x_preferred":[
        "Shibnagar"
    ],
    "wof:name":"Shibnagar",
    "wof:placetype":"locality"
},
  "geometry": {"coordinates":[88.67274,23.61883],"type":"Point"}
}