{
  "type": "Feature",
  "properties": {
    "gn:admin1_code":"87",
    "gn:admin2_code":"5549",
    "gn:admin3_code":"554994.0",
    "gn:admin4_code":"55499489.0",
    "gn:asciiname":"Tanuram",
    "gn:country_code":"BD",
    "gn:dem":31,
    "gn:feature_class":"P",
    "gn:feature_code":"PPL",
    "gn:name":"Tanur\u0101m",
    "gn:population":0,
    "gn:timezone":"Asia/Dhaka",
    "iso:country":"BD",
    "name:ben_x_preferred":[
        "Tanur\u0101m"
    ],
    "wof:name":"Tanuram",
    "wof:placetype":"locality"
},
  "geometry": {"coordinates":[89.59886999999998,25.69325],"type":"Point"}
}