{
  "type": "Feature",
  "properties": {
    "gn:admin1_code":"87",
    "gn:admin2_code":"5585",
    "gn:admin3_code":"558576.0",
    "gn:admin4_code":"55857682.0",
    "gn:asciiname":"Baro Majidpur",
    "gn:country_code":"BD",
    "gn:dem":26,
    "gn:feature_class":"P",
    "gn:feature_code":"PPL",
    "gn:name":"Baro Majidpur",
    "gn:population":0,
    "gn:timezone":"Asia/Dhaka",
    "iso:country":"BD",
    "name:ben_x_preferred":[
        "Baro Majidpur"
    ],
    "wof:name":"Baro Majidpur",
    "wof:placetype":"locality"
},
  "geometry": {"coordinates":[89.31965,25.3917],"type":"Point"}
}