{
  "type": "Feature",
  "properties": {
    "gn:admin1_code":"81",
    "gn:admin2_code":"3082.0",
    "gn:admin3_code":"308207.0",
    "gn:admin4_code":"30820757.0",
    "gn:asciiname":"Alokdia",
    "gn:country_code":"BD",
    "gn:dem":13,
    "gn:feature_class":"P",
    "gn:feature_code":"PPL",
    "gn:name":"\u0100lokdia",
    "gn:population":0,
    "gn:timezone":"Asia/Dhaka",
    "iso:country":"BD",
    "name:fas_x_preferred":[
        "\u0627\u0644\u0648\u06a9\u062f\u06cc\u0627"
    ],
    "wof:name":"Alokdia",
    "wof:placetype":"locality"
},
  "geometry": {"coordinates":[89.61164000000002,23.61484],"type":"Point"}
}