{
  "type": "Feature",
  "properties": {
    "gn:admin1_code":"82",
    "gn:admin2_code":"4087",
    "gn:admin3_code":"408782.0",
    "gn:admin4_code":"40878254.0",
    "gn:asciiname":"Komarpur",
    "gn:country_code":"BD",
    "gn:dem":8,
    "gn:feature_class":"P",
    "gn:feature_code":"PPL",
    "gn:name":"Kom\u0101rpur",
    "gn:population":0,
    "gn:timezone":"Asia/Dhaka",
    "iso:country":"BD",
    "wof:name":"Komarpur",
    "wof:placetype":"locality"
},
  "geometry": {"coordinates":[89.12443,22.64876],"type":"Point"}
}