{
  "type": "Feature",
  "properties": {
    "gn:admin1_code":"83",
    "gn:admin2_code":"5070.0",
    "gn:admin3_code":"507066.0",
    "gn:admin4_code":"50706683.0",
    "gn:asciiname":"Krishna Gobindapur",
    "gn:country_code":"BD",
    "gn:dem":26,
    "gn:feature_class":"P",
    "gn:feature_code":"PPL",
    "gn:name":"Krishna Gobindapur",
    "gn:population":0,
    "gn:timezone":"Asia/Dhaka",
    "iso:country":"BD",
    "name:ben_x_preferred":[
        "Krishna Gobindapur"
    ],
    "wof:name":"Krishna Gobindapur",
    "wof:placetype":"locality"
},
  "geometry": {"coordinates":[88.21595000000001,24.60426],"type":"Point"}
}