{
  "type": "Feature",
  "properties": {
    "gn:admin1_code":"84",
    "gn:admin2_code":"2051",
    "gn:admin3_code":"205165.0",
    "gn:admin4_code":"20516542.0",
    "gn:asciiname":"Jaypura",
    "gn:country_code":"BD",
    "gn:dem":6,
    "gn:feature_class":"P",
    "gn:feature_code":"PPL",
    "gn:name":"Jaypura",
    "gn:population":0,
    "gn:timezone":"Asia/Dhaka",
    "iso:country":"BD",
    "wof:name":"Jaypura",
    "wof:placetype":"locality"
},
  "geometry": {"coordinates":[90.86667,23.15],"type":"Point"}
}