{
  "type": "Feature",
  "properties": {
    "gn:admin1_code":"83",
    "gn:admin2_code":"5081.0",
    "gn:admin3_code":"508112.0",
    "gn:admin4_code":"50811288.0",
    "gn:asciiname":"Dakshin Koalipara",
    "gn:country_code":"BD",
    "gn:dem":17,
    "gn:feature_class":"P",
    "gn:feature_code":"PPL",
    "gn:name":"Dakshin Ko\u0101lip\u0101ra",
    "gn:population":0,
    "gn:timezone":"Asia/Dhaka",
    "iso:country":"BD",
    "name:ben_x_preferred":[
        "Dakshin Ko\u0101lip\u0101ra"
    ],
    "name:und_x_variant":[
        "Dhikshinkoalipara"
    ],
    "wof:name":"Dakshin Koalipara",
    "wof:placetype":"locality"
},
  "geometry": {"coordinates":[88.81851999999998,24.53711],"type":"Point"}
}