{
  "type": "Feature",
  "properties": {
    "gn:admin1_code":"83",
    "gn:admin2_code":"5064.0",
    "gn:admin3_code":"506469.0",
    "gn:admin4_code":"50646931.0",
    "gn:asciiname":"Barabai",
    "gn:country_code":"BD",
    "gn:dem":22,
    "gn:feature_class":"P",
    "gn:feature_code":"PPL",
    "gn:name":"Barabai",
    "gn:population":0,
    "gn:timezone":"Asia/Dhaka",
    "iso:country":"BD",
    "name:ara_x_preferred":[
        "\u0628\u0627\u0631\u0627\u0628\u0627\u064a"
    ],
    "name:ben_x_preferred":[
        "Barabai"
    ],
    "name:bjn_x_preferred":[
        "Barabai"
    ],
    "name:ceb_x_preferred":[
        "Barabai"
    ],
    "name:ind_x_preferred":[
        "Barabai"
    ],
    "name:jav_x_preferred":[
        "Barabai"
    ],
    "name:mlg_x_preferred":[
        "Barabai"
    ],
    "name:msa_x_preferred":[
        "Barabai"
    ],
    "name:nld_x_preferred":[
        "Barabai"
    ],
    "name:rus_x_preferred":[
        "\u0411\u0430\u0440\u0430\u0431\u0430\u0439"
    ],
    "name:swe_x_preferred":[
        "Barabai"
    ],
    "wof:name":"Barabai",
    "wof:placetype":"locality"
},
  "geometry": {"coordinates":[88.59945,24.94704],"type":"Point"}
}