{
  "type": "Feature",
  "properties": {
    "gn:admin1_code":"87",
    "gn:admin2_code":"5577.0",
    "gn:admin3_code":"557725.0",
    "gn:admin4_code":"55772587.0",
    "gn:asciiname":"Balabhir Jamanda Barua",
    "gn:country_code":"BD",
    "gn:dem":63,
    "gn:feature_class":"P",
    "gn:feature_code":"PPL",
    "gn:name":"Balabhir Jamanda Barua",
    "gn:population":0,
    "gn:timezone":"Asia/Dhaka",
    "iso:country":"BD",
    "name:ben_x_preferred":[
        "Balabhir Jamanda Barua"
    ],
    "wof:name":"Balabhir Jamanda Barua",
    "wof:placetype":"locality"
},
  "geometry": {"coordinates":[88.60736999999997,26.15065],"type":"Point"}
}