{
  "type": "Feature",
  "properties": {
    "gn:admin1_code":"81",
    "gn:admin2_code":"3093",
    "gn:admin3_code":"309385.0",
    "gn:admin4_code":"30938567.0",
    "gn:asciiname":"Urichala",
    "gn:country_code":"BD",
    "gn:dem":25,
    "gn:feature_class":"P",
    "gn:feature_code":"PPL",
    "gn:name":"Urich\u0101la",
    "gn:population":0,
    "gn:timezone":"Asia/Dhaka",
    "iso:country":"BD",
    "name:und_x_variant":[
        "Urich\u0101la",
        "Surich\u0101la"
    ],
    "wof:name":"Urichala",
    "wof:placetype":"locality"
},
  "geometry": {"coordinates":[90.1426,24.37828],"type":"Point"}
}