{
  "type": "Feature",
  "properties": {
    "gn:admin1_code":"83",
    "gn:admin2_code":"5081.0",
    "gn:admin3_code":"508131.0",
    "gn:admin4_code":"50813135.0",
    "gn:asciiname":"Gaurihar",
    "gn:country_code":"BD",
    "gn:dem":19,
    "gn:feature_class":"P",
    "gn:feature_code":"PPL",
    "gn:name":"Gaurihar",
    "gn:population":0,
    "gn:timezone":"Asia/Dhaka",
    "iso:country":"BD",
    "name:ben_x_preferred":[
        "Gaurihar"
    ],
    "name:und_x_variant":[
        "Gawrihar"
    ],
    "wof:name":"Gaurihar",
    "wof:placetype":"locality"
},
  "geometry": {"coordinates":[88.71614,24.41809],"type":"Point"}
}