{
  "type": "Feature",
  "properties": {
    "gn:admin1_code":"81",
    "gn:admin2_code":"3093",
    "gn:admin3_code":"309347.0",
    "gn:admin4_code":"30934758.0",
    "gn:asciiname":"Savar",
    "gn:country_code":"BD",
    "gn:dem":17,
    "gn:feature_class":"P",
    "gn:feature_code":"PPL",
    "gn:name":"Savar",
    "gn:population":0,
    "gn:timezone":"Asia/Dhaka",
    "iso:country":"BD",
    "name:und_x_variant":[
        "S\u0101bh\u0101r"
    ],
    "wof:name":"Savar",
    "wof:placetype":"locality"
},
  "geometry": {"coordinates":[89.99715,24.33724],"type":"Point"}
}