{
  "type": "Feature",
  "properties": {
    "gn:admin1_code":"82",
    "gn:admin2_code":"4087.0",
    "gn:admin3_code":"408747.0",
    "gn:admin4_code":"40874763.0",
    "gn:asciiname":"Hasnakati",
    "gn:country_code":"BD",
    "gn:dem":7,
    "gn:feature_class":"P",
    "gn:feature_code":"PPL",
    "gn:name":"H\u0101sn\u0101k\u0101ti",
    "gn:population":0,
    "gn:timezone":"Asia/Dhaka",
    "iso:country":"BD",
    "name:ben_x_preferred":[
        "H\u0101sn\u0101k\u0101ti"
    ],
    "name:und_x_variant":[
        "H\u0101s\u0101nk\u0101ti"
    ],
    "wof:name":"Hasnakati",
    "wof:placetype":"locality"
},
  "geometry": {"coordinates":[89.05993000000002,22.39041],"type":"Point"}
}