{
  "type": "Feature",
  "properties": {
    "gn:admin1_code":"H",
    "gn:admin2_code":"3072.0",
    "gn:admin3_code":"307240.0",
    "gn:admin4_code":"30724035.0",
    "gn:asciiname":"Chamajani",
    "gn:country_code":"BD",
    "gn:dem":8,
    "gn:feature_class":"P",
    "gn:feature_code":"PPL",
    "gn:name":"Ch\u0101maj\u0101ni",
    "gn:population":0,
    "gn:timezone":"Asia/Dhaka",
    "iso:country":"BD",
    "name:und_x_variant":[
        "Chamarjani",
        "Ch\u0101maj\u0101ni"
    ],
    "wof:name":"Chamajani",
    "wof:placetype":"locality"
},
  "geometry": {"coordinates":[90.84932000000001,25.04806],"type":"Point"}
}