{
  "type": "Feature",
  "properties": {
    "gn:admin1_code":"83",
    "gn:admin2_code":"5064",
    "gn:admin3_code":"506450.0",
    "gn:admin4_code":"50645028.0",
    "gn:asciiname":"Padmapukur",
    "gn:country_code":"BD",
    "gn:dem":22,
    "gn:feature_class":"P",
    "gn:feature_code":"PPL",
    "gn:name":"Padmapukur",
    "gn:population":0,
    "gn:timezone":"Asia/Dhaka",
    "iso:country":"BD",
    "name:ben_x_preferred":[
        "Padmapukur"
    ],
    "wof:name":"Padmapukur",
    "wof:placetype":"locality"
},
  "geometry": {"coordinates":[88.81244000000002,24.88934],"type":"Point"}
}