{
  "type": "Feature",
  "properties": {
    "gn:admin1_code":"87",
    "gn:admin2_code":"5532",
    "gn:admin3_code":"553267.0",
    "gn:admin4_code":"55326757.0",
    "gn:asciiname":"Shyampur",
    "gn:country_code":"BD",
    "gn:dem":27,
    "gn:feature_class":"P",
    "gn:feature_code":"PPL",
    "gn:name":"Shyampur",
    "gn:population":0,
    "gn:timezone":"Asia/Dhaka",
    "iso:country":"BD",
    "name:ben_x_preferred":[
        "Shyampur"
    ],
    "wof:name":"Shyampur",
    "wof:placetype":"locality"
},
  "geometry": {"coordinates":[89.4023,25.2962],"type":"Point"}
}