{
  "type": "Feature",
  "properties": {
    "gn:admin1_code":"87",
    "gn:admin2_code":"5527.0",
    "gn:admin3_code":"552738.0",
    "gn:admin4_code":"55273838.0",
    "gn:asciiname":"Janipur",
    "gn:country_code":"BD",
    "gn:dem":34,
    "gn:feature_class":"P",
    "gn:feature_code":"PPL",
    "gn:name":"Janipur",
    "gn:population":0,
    "gn:timezone":"Asia/Dhaka",
    "iso:country":"BD",
    "name:ben_x_preferred":[
        "Janipur"
    ],
    "wof:name":"Janipur",
    "wof:placetype":"locality"
},
  "geometry": {"coordinates":[88.95421999999998,25.40747],"type":"Point"}
}