{
  "type": "Feature",
  "properties": {
    "gn:admin1_code":"81",
    "gn:admin2_code":"3056",
    "gn:admin3_code":"305628.0",
    "gn:admin4_code":"30562829.0",
    "gn:asciiname":"Thana Jatrapur",
    "gn:country_code":"BD",
    "gn:dem":11,
    "gn:feature_class":"P",
    "gn:feature_code":"PPL",
    "gn:name":"Th\u0101na J\u0101tr\u0101pur",
    "gn:population":0,
    "gn:timezone":"Asia/Dhaka",
    "iso:country":"BD",
    "wof:name":"Thana Jatrapur",
    "wof:placetype":"locality"
},
  "geometry": {"coordinates":[89.98156999999998,23.75113],"type":"Point"}
}