{
  "type": "Feature",
  "properties": {
    "gn:admin1_code":"87",
    "gn:admin2_code":"5585",
    "gn:admin3_code":"558558.0",
    "gn:admin4_code":"55855811.0",
    "gn:asciiname":"Chharan",
    "gn:country_code":"BD",
    "gn:dem":33,
    "gn:feature_class":"P",
    "gn:feature_code":"PPL",
    "gn:name":"Chharan",
    "gn:population":0,
    "gn:timezone":"Asia/Dhaka",
    "iso:country":"BD",
    "name:ben_x_preferred":[
        "Chharan"
    ],
    "wof:name":"Chharan",
    "wof:placetype":"locality"
},
  "geometry": {"coordinates":[89.13339999999999,25.53999],"type":"Point"}
}