{
  "type": "Feature",
  "properties": {
    "gn:admin1_code":"84",
    "gn:admin2_code":"2015.0",
    "gn:admin3_code":"201561.0",
    "gn:admin4_code":"20156155.0",
    "gn:asciiname":"Dhangar Char",
    "gn:country_code":"BD",
    "gn:dem":6,
    "gn:feature_class":"P",
    "gn:feature_code":"PPL",
    "gn:name":"Dhangar Char",
    "gn:population":0,
    "gn:timezone":"Asia/Dhaka",
    "iso:country":"BD",
    "name:ben_x_preferred":[
        "Dhangar Char"
    ],
    "wof:name":"Dhangar Char",
    "wof:placetype":"locality"
},
  "geometry": {"coordinates":[91.81101,22.2885],"type":"Point"}
}