{
  "type": "Feature",
  "properties": {
    "gn:admin1_code":"81",
    "gn:admin2_code":"3048.0",
    "gn:admin3_code":"304845.0",
    "gn:admin4_code":"30484585.0",
    "gn:asciiname":"Baghber",
    "gn:country_code":"BD",
    "gn:dem":14,
    "gn:feature_class":"P",
    "gn:feature_code":"PPL",
    "gn:name":"B\u0101ghber",
    "gn:population":0,
    "gn:timezone":"Asia/Dhaka",
    "iso:country":"BD",
    "wof:name":"Baghber",
    "wof:placetype":"locality"
},
  "geometry": {"coordinates":[90.82868000000001,24.28479],"type":"Point"}
}