{
  "type": "Feature",
  "properties": {
    "gn:admin1_code":"83",
    "gn:admin2_code":"5064.0",
    "gn:admin3_code":"506406.0",
    "gn:admin4_code":"50640621.0",
    "gn:asciiname":"Changla",
    "gn:country_code":"BD",
    "gn:dem":23,
    "gn:feature_class":"P",
    "gn:feature_code":"PPL",
    "gn:name":"Ch\u0101ngla",
    "gn:population":0,
    "gn:timezone":"Asia/Dhaka",
    "iso:country":"BD",
    "name:ben_x_preferred":[
        "Ch\u0101ngla"
    ],
    "name:deu_x_preferred":[
        "Changla"
    ],
    "name:und_x_variant":[
        "Changala"
    ],
    "wof:name":"Changla",
    "wof:placetype":"locality"
},
  "geometry": {"coordinates":[88.90639,24.94132],"type":"Point"}
}