{
  "type": "Feature",
  "properties": {
    "gn:admin1_code":"87",
    "gn:admin2_code":"5527",
    "gn:admin3_code":"552738.0",
    "gn:admin4_code":"55273809.0",
    "gn:asciiname":"Sanora",
    "gn:country_code":"BD",
    "gn:dem":35,
    "gn:feature_class":"P",
    "gn:feature_code":"PPL",
    "gn:name":"S\u0101nora",
    "gn:population":0,
    "gn:timezone":"Asia/Dhaka",
    "iso:country":"BD",
    "name:ben_x_preferred":[
        "S\u0101nora"
    ],
    "name:ben_x_variant":[
        "Senra"
    ],
    "wof:name":"Sanora",
    "wof:placetype":"locality"
},
  "geometry": {"coordinates":[88.91144,25.47089],"type":"Point"}
}