{
  "type": "Feature",
  "properties": {
    "gn:admin1_code":"87",
    "gn:admin2_code":"5532.0",
    "gn:admin3_code":"553282.0",
    "gn:admin4_code":"55328251.0",
    "gn:asciiname":"Gobindaray Debottor",
    "gn:country_code":"BD",
    "gn:dem":26,
    "gn:feature_class":"P",
    "gn:feature_code":"PPL",
    "gn:name":"Gobindaray Debottor",
    "gn:population":0,
    "gn:timezone":"Asia/Dhaka",
    "iso:country":"BD",
    "name:und_x_variant":[
        "Gobinda Ray Debottar",
        "Gobind\u0101rai Dev Aut\u0101r",
        "Gobindaray Debottor"
    ],
    "wof:name":"Gobindaray Debottor",
    "wof:placetype":"locality"
},
  "geometry": {"coordinates":[89.387,25.31772],"type":"Point"}
}