{
  "type": "Feature",
  "properties": {
    "gn:country":"BD",
    "gn:fcode":"PPL",
    "gn:pop":40557,
    "iso:country":"BD",
    "name:ben_x_preferred":[
        "Tekn\u0101f"
    ],
    "name:unk_x_variant":[
        "Teknaaf"
    ],
    "qs:name":"Tekn\u0101f",
    "qs:photos_9r":0,
    "qs:photos_sr":0,
    "qs:pop_sr":"7",
    "wof:name":"Tekn\u0101f",
    "wof:placetype":"locality",
    "wof:population":40557
},
  "geometry": {"coordinates":[92.30153,20.86382],"type":"Point"}
}