{
  "type": "Feature",
  "properties": {
    "gn:admin1_code":"85",
    "gn:admin2_code":"1004.0",
    "gn:admin3_code":"100428.0",
    "gn:admin4_code":"10042857.0",
    "gn:asciiname":"Bakultali",
    "gn:country_code":"BD",
    "gn:dem":13,
    "gn:feature_class":"P",
    "gn:feature_code":"PPL",
    "gn:name":"Bakultali",
    "gn:population":0,
    "gn:timezone":"Asia/Dhaka",
    "iso:country":"BD",
    "name:ben_x_preferred":[
        "Bakultali"
    ],
    "wof:name":"Bakultali",
    "wof:placetype":"locality"
},
  "geometry": {"coordinates":[90.15066,22.24076],"type":"Point"}
}