{
  "type": "Feature",
  "properties": {
    "gn:admin1_code":"84",
    "gn:admin2_code":"2015.0",
    "gn:admin3_code":"201570.0",
    "gn:admin4_code":"20157017.0",
    "gn:asciiname":"Dhopaghata",
    "gn:country_code":"BD",
    "gn:dem":15,
    "gn:feature_class":"P",
    "gn:feature_code":"PPL",
    "gn:name":"Dhopaghata",
    "gn:population":0,
    "gn:timezone":"Asia/Dhaka",
    "iso:country":"BD",
    "name:ben_x_preferred":[
        "Dhopaghata"
    ],
    "wof:name":"Dhopaghata",
    "wof:placetype":"locality"
},
  "geometry": {"coordinates":[92.09999000000001,22.44796],"type":"Point"}
}