{
  "type": "Feature",
  "properties": {
    "gn:admin1_code":"H",
    "gn:admin2_code":"3061",
    "gn:admin3_code":"306123.0",
    "gn:admin4_code":"30612322.0",
    "gn:asciiname":"Nizamabad",
    "gn:country_code":"BD",
    "gn:dem":19,
    "gn:feature_class":"P",
    "gn:feature_code":"PPL",
    "gn:name":"Niz\u0101m\u0101b\u0101d",
    "gn:population":0,
    "gn:timezone":"Asia/Dhaka",
    "iso:country":"BD",
    "wof:name":"Nizamabad",
    "wof:placetype":"locality"
},
  "geometry": {"coordinates":[90.58928,24.73249],"type":"Point"}
}