{
  "type": "Feature",
  "properties": {
    "gn:admin1_code":"87",
    "gn:admin2_code":"5585",
    "gn:admin3_code":"558527.0",
    "gn:admin4_code":"55852721.0",
    "gn:asciiname":"Char Ani Sherpur",
    "gn:country_code":"BD",
    "gn:dem":39,
    "gn:feature_class":"P",
    "gn:feature_code":"PPL",
    "gn:name":"Ch\u0101r \u0100ni Sherpur",
    "gn:population":0,
    "gn:timezone":"Asia/Dhaka",
    "iso:country":"BD",
    "name:ben_x_preferred":[
        "Ch\u0101r \u0100ni Sherpur"
    ],
    "wof:name":"Char Ani Sherpur",
    "wof:placetype":"locality"
},
  "geometry": {"coordinates":[89.13888,25.86999],"type":"Point"}
}