{
  "type": "Feature",
  "properties": {
    "gn:admin1_code":"85",
    "gn:admin2_code":"1006",
    "gn:admin3_code":"100632.0",
    "gn:admin4_code":"10063271.0",
    "gn:asciiname":"Sankarpasa",
    "gn:country_code":"BD",
    "gn:dem":11,
    "gn:feature_class":"P",
    "gn:feature_code":"PPL",
    "gn:name":"Sankarp\u0101sa",
    "gn:population":0,
    "gn:timezone":"Asia/Dhaka",
    "iso:country":"BD",
    "wof:name":"Sankarpasa",
    "wof:placetype":"locality"
},
  "geometry": {"coordinates":[90.26808,22.94981],"type":"Point"}
}