{
  "type": "Feature",
  "properties": {
    "gn:admin1_code":"87",
    "gn:admin2_code":"5577.0",
    "gn:admin3_code":"557773.0",
    "gn:admin4_code":"55777343.0",
    "gn:asciiname":"Sipahipara",
    "gn:country_code":"BD",
    "gn:dem":80,
    "gn:feature_class":"P",
    "gn:feature_code":"PPL",
    "gn:name":"Sip\u0101hip\u0101ra",
    "gn:population":0,
    "gn:timezone":"Asia/Dhaka",
    "iso:country":"BD",
    "name:ben_x_preferred":[
        "Sip\u0101hip\u0101ra"
    ],
    "wof:name":"Sipahipara",
    "wof:placetype":"locality"
},
  "geometry": {"coordinates":[88.49975000000001,26.33343],"type":"Point"}
}