{
  "type": "Feature",
  "properties": {
    "gn:admin1_code":"H",
    "gn:admin2_code":"3061.0",
    "gn:admin3_code":"306172.0",
    "gn:admin4_code":"30617207.0",
    "gn:asciiname":"Achargaon",
    "gn:country_code":"BD",
    "gn:dem":14,
    "gn:feature_class":"P",
    "gn:feature_code":"PPL",
    "gn:name":"\u0100ch\u0101rgaon",
    "gn:population":0,
    "gn:timezone":"Asia/Dhaka",
    "iso:country":"BD",
    "name:ceb_x_preferred":[
        "\u0100ch\u0101rgaon"
    ],
    "name:fas_x_preferred":[
        "\u0627\u0686\u0627\u0631\u06af\u0627\u0626\u0648\u0646"
    ],
    "wof:name":"Achargaon",
    "wof:placetype":"locality"
},
  "geometry": {"coordinates":[90.69928,24.5511],"type":"Point"}
}