{
  "type": "Feature",
  "properties": {
    "gn:admin1_code":"83",
    "gn:admin2_code":"5070.0",
    "gn:admin3_code":"507056.0",
    "gn:admin4_code":"50705619.0",
    "gn:asciiname":"Chauka Gazipur",
    "gn:country_code":"BD",
    "gn:dem":26,
    "gn:feature_class":"P",
    "gn:feature_code":"PPL",
    "gn:name":"Chauka G\u0101zipur",
    "gn:population":0,
    "gn:timezone":"Asia/Dhaka",
    "iso:country":"BD",
    "name:ben_x_preferred":[
        "Chauka G\u0101zipur"
    ],
    "name:ben_x_variant":[
        "G\u0101zipur"
    ],
    "name:und_x_variant":[
        "Gazipara"
    ],
    "wof:name":"Chauka Gazipur",
    "wof:placetype":"locality"
},
  "geometry": {"coordinates":[88.3061,24.71509],"type":"Point"}
}