{
  "type": "Feature",
  "properties": {
    "gn:admin1_code":"84",
    "gn:admin2_code":"2022.0",
    "gn:admin3_code":"202294.0",
    "gn:admin4_code":"20229415.0",
    "gn:asciiname":"Barabil",
    "gn:country_code":"BD",
    "gn:dem":19,
    "gn:feature_class":"P",
    "gn:feature_code":"PPL",
    "gn:name":"Bar\u0101bil",
    "gn:population":0,
    "gn:timezone":"Asia/Dhaka",
    "iso:country":"BD",
    "name:ben_x_preferred":[
        "Bar\u0101bil"
    ],
    "wof:name":"Barabil",
    "wof:placetype":"locality"
},
  "geometry": {"coordinates":[92.13661999999999,21.3364],"type":"Point"}
}