{
  "type": "Feature",
  "properties": {
    "gn:admin1_code":"83",
    "gn:asciiname":"Shyampur",
    "gn:country_code":"BD",
    "gn:dem":24,
    "gn:feature_class":"P",
    "gn:feature_code":"PPL",
    "gn:name":"Shy\u0101mpur",
    "gn:population":0,
    "gn:timezone":"Asia/Dhaka",
    "iso:country":"BD",
    "name:ben_x_preferred":[
        "Shy\u0101mpur"
    ],
    "wof:name":"Shyampur",
    "wof:placetype":"locality"
},
  "geometry": {"coordinates":[89.54484000000002,25.15256],"type":"Point"}
}