{
  "type": "Feature",
  "properties": {
    "gn:admin1_code":"83",
    "gn:asciiname":"Birat",
    "gn:country_code":"BD",
    "gn:dem":28,
    "gn:feature_class":"P",
    "gn:feature_code":"PPL",
    "gn:name":"Birat",
    "gn:population":0,
    "gn:timezone":"Asia/Dhaka",
    "iso:country":"BD",
    "name:ben_x_preferred":[
        "Birat"
    ],
    "name:ceb_x_preferred":[
        "Birat"
    ],
    "name:mai_x_preferred":[
        "\u092c\u093f\u0930\u093e\u091f"
    ],
    "name:msa_x_preferred":[
        "Birat"
    ],
    "name:nep_x_preferred":[
        "\u092c\u093f\u0930\u093e\u091f"
    ],
    "name:new_x_preferred":[
        "\u092c\u093f\u0930\u093e\u091f"
    ],
    "name:pol_x_preferred":[
        "Birat"
    ],
    "wof:name":"Birat",
    "wof:placetype":"locality"
},
  "geometry": {"coordinates":[89.24700000000001,25.14978],"type":"Point"}
}