{
  "type": "Feature",
  "properties": {
    "gn:admin1_code":"83",
    "gn:admin2_code":"5070.0",
    "gn:admin3_code":"507066.0",
    "gn:admin4_code":"50706627.0",
    "gn:asciiname":"Ibrahin Mandaigram",
    "gn:country_code":"BD",
    "gn:dem":22,
    "gn:feature_class":"P",
    "gn:feature_code":"PPL",
    "gn:name":"Ibrahin Mandaigram",
    "gn:population":0,
    "gn:timezone":"Asia/Dhaka",
    "iso:country":"BD",
    "name:ben_x_preferred":[
        "Ibrahin Mandaigram"
    ],
    "wof:name":"Ibrahin Mandaigram",
    "wof:placetype":"locality"
},
  "geometry": {"coordinates":[88.25487,24.50784],"type":"Point"}
}