{
  "type": "Feature",
  "properties": {
    "gn:admin1_code":"84",
    "gn:admin2_code":"2015.0",
    "gn:admin3_code":"201561.0",
    "gn:admin4_code":"20156142.0",
    "gn:asciiname":"Haidgaon",
    "gn:country_code":"BD",
    "gn:dem":14,
    "gn:feature_class":"P",
    "gn:feature_code":"PPL",
    "gn:name":"Haidgaon",
    "gn:population":0,
    "gn:timezone":"Asia/Dhaka",
    "iso:country":"BD",
    "name:ben_x_preferred":[
        "Haidgaon"
    ],
    "wof:name":"Haidgaon",
    "wof:placetype":"locality"
},
  "geometry": {"coordinates":[92.01345999999999,22.30224],"type":"Point"}
}