{
  "type": "Feature",
  "properties": {
    "gn:admin1_code":"87",
    "gn:admin2_code":"5532",
    "gn:admin3_code":"553267.0",
    "gn:admin4_code":"55326719.0",
    "gn:asciiname":"Mostafapur",
    "gn:country_code":"BD",
    "gn:dem":24,
    "gn:feature_class":"P",
    "gn:feature_code":"PPL",
    "gn:name":"Mostafapur",
    "gn:population":0,
    "gn:timezone":"Asia/Dhaka",
    "iso:country":"BD",
    "name:ben_x_preferred":[
        "Mostafapur"
    ],
    "wof:name":"Mostafapur",
    "wof:placetype":"locality"
},
  "geometry": {"coordinates":[89.44614,25.30241],"type":"Point"}
}