{
  "type": "Feature",
  "properties": {
    "gn:admin1_code":"H",
    "gn:admin2_code":"3039",
    "gn:admin3_code":"303929.0",
    "gn:admin4_code":"30392987.0",
    "gn:asciiname":"Krishnanagar",
    "gn:country_code":"BD",
    "gn:dem":24,
    "gn:feature_class":"P",
    "gn:feature_code":"PPL",
    "gn:name":"Krishnanagar",
    "gn:population":0,
    "gn:timezone":"Asia/Dhaka",
    "iso:country":"BD",
    "name:deu_x_preferred":[
        "Krishnanagar"
    ],
    "wof:name":"Krishnanagar",
    "wof:placetype":"locality"
},
  "geometry": {"coordinates":[89.75,25.13333],"type":"Point"}
}