{
  "type": "Feature",
  "properties": {
    "gn:admin1_code":"82",
    "gn:admin2_code":"4044",
    "gn:admin3_code":"404471.0",
    "gn:admin4_code":"40447165.0",
    "gn:asciiname":"Pantapara",
    "gn:country_code":"BD",
    "gn:dem":16,
    "gn:feature_class":"P",
    "gn:feature_code":"PPL",
    "gn:name":"P\u0101nt\u0101para",
    "gn:population":0,
    "gn:timezone":"Asia/Dhaka",
    "iso:country":"BD",
    "name:ben_x_preferred":[
        "P\u0101nt\u0101para"
    ],
    "wof:name":"Pantapara",
    "wof:placetype":"locality"
},
  "geometry": {"coordinates":[88.84886999999998,23.32485],"type":"Point"}
}