{
  "type": "Feature",
  "properties": {
    "gn:admin1_code":"84",
    "gn:admin2_code":"2019.0",
    "gn:admin3_code":"201975.0",
    "gn:admin4_code":"20197519.0",
    "gn:asciiname":"Bhasania Dari Char",
    "gn:country_code":"BD",
    "gn:dem":8,
    "gn:feature_class":"P",
    "gn:feature_code":"PPL",
    "gn:name":"Bh\u0101s\u0101nia Dari Char",
    "gn:population":0,
    "gn:timezone":"Asia/Dhaka",
    "iso:country":"BD",
    "wof:name":"Bhasania Dari Char",
    "wof:placetype":"locality"
},
  "geometry": {"coordinates":[90.64910999999999,23.65754],"type":"Point"}
}