{
  "type": "Feature",
  "properties": {
    "gn:admin1_code":"85",
    "gn:admin2_code":"1079.0",
    "gn:admin3_code":"107914.0",
    "gn:admin4_code":"10791435.0",
    "gn:asciiname":"Irojpur",
    "gn:country_code":"BD",
    "gn:dem":12,
    "gn:feature_class":"P",
    "gn:feature_code":"PPL",
    "gn:name":"Irojpur",
    "gn:population":0,
    "gn:timezone":"Asia/Dhaka",
    "iso:country":"BD",
    "name:ben_x_preferred":[
        "Irojpur"
    ],
    "wof:name":"Irojpur",
    "wof:placetype":"locality"
},
  "geometry": {"coordinates":[89.999,22.4607],"type":"Point"}
}