{
  "type": "Feature",
  "properties": {
    "gn:admin1_code":"83",
    "gn:admin2_code":"5069.0",
    "gn:admin3_code":"506909.0",
    "gn:admin4_code":"50690938.0",
    "gn:asciiname":"Dayarampur",
    "gn:country_code":"BD",
    "gn:dem":17,
    "gn:feature_class":"P",
    "gn:feature_code":"PPL",
    "gn:name":"Day\u0101r\u0101mpur",
    "gn:population":0,
    "gn:timezone":"Asia/Dhaka",
    "iso:country":"BD",
    "wof:name":"Dayarampur",
    "wof:placetype":"locality"
},
  "geometry": {"coordinates":[89.0063,24.29515],"type":"Point"}
}