{
  "type": "Feature",
  "properties": {
    "gn:admin1_code":"H",
    "gn:admin2_code":"3072",
    "gn:admin3_code":"307283.0",
    "gn:admin4_code":"30728307.0",
    "gn:asciiname":"Kalduar",
    "gn:country_code":"BD",
    "gn:dem":17,
    "gn:feature_class":"P",
    "gn:feature_code":"PPL",
    "gn:name":"K\u0101ldu\u0101r",
    "gn:population":0,
    "gn:timezone":"Asia/Dhaka",
    "iso:country":"BD",
    "wof:name":"Kalduar",
    "wof:placetype":"locality"
},
  "geometry": {"coordinates":[90.58678,24.95006],"type":"Point"}
}