{
  "type": "Feature",
  "properties": {
    "gn:admin1_code":"82",
    "gn:admin2_code":"4050",
    "gn:admin3_code":"405079.0",
    "gn:admin4_code":"40507994.0",
    "gn:asciiname":"Ujan Gram",
    "gn:country_code":"BD",
    "gn:dem":18,
    "gn:feature_class":"P",
    "gn:feature_code":"PPL",
    "gn:name":"Ujan Gram",
    "gn:population":0,
    "gn:timezone":"Asia/Dhaka",
    "iso:country":"BD",
    "name:ben_x_preferred":[
        "Ujan Gram"
    ],
    "wof:name":"Ujan Gram",
    "wof:placetype":"locality"
},
  "geometry": {"coordinates":[89.1041,23.795],"type":"Point"}
}