{
  "type": "Feature",
  "properties": {
    "gn:admin1_code":"81",
    "gn:admin2_code":"3054.0",
    "gn:admin3_code":"305480.0",
    "gn:admin4_code":"30548066.0",
    "gn:asciiname":"Fulkumari",
    "gn:country_code":"BD",
    "gn:dem":7,
    "gn:feature_class":"P",
    "gn:feature_code":"PPL",
    "gn:name":"Fulkum\u0101ri",
    "gn:population":0,
    "gn:timezone":"Asia/Dhaka",
    "iso:country":"BD",
    "name:ben_x_preferred":[
        "Fulkum\u0101ri"
    ],
    "wof:name":"Fulkumari",
    "wof:placetype":"locality"
},
  "geometry": {"coordinates":[89.98075,23.19046],"type":"Point"}
}