{
  "type": "Feature",
  "properties": {
    "gn:admin1_code":"87",
    "gn:admin2_code":"5532",
    "gn:admin3_code":"553224.0",
    "gn:admin4_code":"55322414.0",
    "gn:asciiname":"Chak Gayeshpur",
    "gn:country_code":"BD",
    "gn:dem":30,
    "gn:feature_class":"P",
    "gn:feature_code":"PPL",
    "gn:name":"Chak Gayeshpur",
    "gn:population":0,
    "gn:timezone":"Asia/Dhaka",
    "iso:country":"BD",
    "name:ben_x_preferred":[
        "Chak Gayeshpur"
    ],
    "wof:name":"Chak Gayeshpur",
    "wof:placetype":"locality"
},
  "geometry": {"coordinates":[89.48373000000002,25.36829],"type":"Point"}
}