{
  "type": "Feature",
  "properties": {
    "gn:admin1_code":"82",
    "gn:admin2_code":"4065.0",
    "gn:admin3_code":"406576.0",
    "gn:admin4_code":"40657647.0",
    "gn:asciiname":"Ramnagar Char",
    "gn:country_code":"BD",
    "gn:dem":11,
    "gn:feature_class":"P",
    "gn:feature_code":"PPL",
    "gn:name":"R\u0101mnagar Char",
    "gn:population":0,
    "gn:timezone":"Asia/Dhaka",
    "iso:country":"BD",
    "name:ben_x_preferred":[
        "R\u0101mnagar Char"
    ],
    "wof:name":"Ramnagar Char",
    "wof:placetype":"locality"
},
  "geometry": {"coordinates":[89.48084,23.10609],"type":"Point"}
}