{
  "type": "Feature",
  "properties": {
    "gn:admin1_code":"84",
    "gn:admin2_code":"2022.0",
    "gn:admin3_code":"202216.0",
    "gn:admin4_code":"20221650.0",
    "gn:asciiname":"Kattali",
    "gn:country_code":"BD",
    "gn:dem":20,
    "gn:feature_class":"P",
    "gn:feature_code":"PPL",
    "gn:name":"K\u0101ttali",
    "gn:population":0,
    "gn:timezone":"Asia/Dhaka",
    "iso:country":"BD",
    "name:ben_x_preferred":[
        "K\u0101ttali"
    ],
    "wof:name":"Kattali",
    "wof:placetype":"locality"
},
  "geometry": {"coordinates":[92.04819000000001,21.8866],"type":"Point"}
}