{
  "type": "Feature",
  "properties": {
    "gn:admin1_code":"83",
    "gn:admin2_code":"5038.0",
    "gn:admin3_code":"503858.0",
    "gn:admin4_code":"50385876.0",
    "gn:asciiname":"Bofalgari",
    "gn:country_code":"BD",
    "gn:dem":25,
    "gn:feature_class":"P",
    "gn:feature_code":"PPL",
    "gn:name":"Bofalg\u0101ri",
    "gn:population":0,
    "gn:timezone":"Asia/Dhaka",
    "iso:country":"BD",
    "name:ben_x_preferred":[
        "Bofalg\u0101ri"
    ],
    "wof:name":"Bofalgari",
    "wof:placetype":"locality"
},
  "geometry": {"coordinates":[89.21496999999999,25.02981],"type":"Point"}
}