{
  "type": "Feature",
  "properties": {
    "gn:admin1_code":"84",
    "gn:admin2_code":"2013.0",
    "gn:admin3_code":"201358.0",
    "gn:admin4_code":"20135847.0",
    "gn:asciiname":"Akania",
    "gn:country_code":"BD",
    "gn:dem":11,
    "gn:feature_class":"P",
    "gn:feature_code":"PPL",
    "gn:name":"\u0100kania",
    "gn:population":0,
    "gn:timezone":"Asia/Dhaka",
    "iso:country":"BD",
    "name:fas_x_preferred":[
        "\u0627\u06a9\u0627\u0646\u06cc\u0627"
    ],
    "name:und_x_variant":[
        "\u0100kania"
    ],
    "wof:name":"Akania",
    "wof:placetype":"locality"
},
  "geometry": {"coordinates":[90.88558999999999,23.3542],"type":"Point"}
}