{
  "type": "Feature",
  "properties": {
    "gn:admin1_code":"81",
    "gn:admin2_code":"3093.0",
    "gn:admin3_code":"309328.0",
    "gn:admin4_code":"30932894.0",
    "gn:asciiname":"Chakpara",
    "gn:country_code":"BD",
    "gn:dem":15,
    "gn:feature_class":"P",
    "gn:feature_code":"PPL",
    "gn:name":"Chakp\u0101ra",
    "gn:population":0,
    "gn:timezone":"Asia/Dhaka",
    "iso:country":"BD",
    "wof:name":"Chakpara",
    "wof:placetype":"locality"
},
  "geometry": {"coordinates":[90.07895000000001,24.47624],"type":"Point"}
}