{
  "type": "Feature",
  "properties": {
    "gn:admin1_code":"87",
    "gn:admin2_code":"5585",
    "gn:admin3_code":"558549.0",
    "gn:admin4_code":"55854900.0",
    "gn:asciiname":"Nilkantha",
    "gn:country_code":"BD",
    "gn:dem":38,
    "gn:feature_class":"P",
    "gn:feature_code":"PPL",
    "gn:name":"Nilk\u0101ntha",
    "gn:population":0,
    "gn:timezone":"Asia/Dhaka",
    "iso:country":"BD",
    "name:ben_x_preferred":[
        "Nilk\u0101ntha"
    ],
    "wof:name":"Nilkantha",
    "wof:placetype":"locality"
},
  "geometry": {"coordinates":[89.23520000000001,25.77003],"type":"Point"}
}