{
  "type": "Feature",
  "properties": {
    "gn:admin1_code":"84",
    "gn:admin2_code":"2015.0",
    "gn:admin3_code":"201533.0",
    "gn:admin4_code":"20153314.0",
    "gn:asciiname":"Saktapur",
    "gn:country_code":"BD",
    "gn:dem":15,
    "gn:feature_class":"P",
    "gn:feature_code":"PPL",
    "gn:name":"Saktapur",
    "gn:population":0,
    "gn:timezone":"Asia/Dhaka",
    "iso:country":"BD",
    "name:ben_x_preferred":[
        "Saktapur"
    ],
    "wof:name":"Saktapur",
    "wof:placetype":"locality"
},
  "geometry": {"coordinates":[91.85893,22.61048],"type":"Point"}
}