{
  "type": "Feature",
  "properties": {
    "gn:admin1_code":"82",
    "gn:admin2_code":"4041",
    "gn:admin3_code":"404111.0",
    "gn:admin4_code":"40411160.0",
    "gn:asciiname":"Matsyaranga",
    "gn:country_code":"BD",
    "gn:dem":14,
    "gn:feature_class":"P",
    "gn:feature_code":"PPL",
    "gn:name":"Matsyaranga",
    "gn:population":0,
    "gn:timezone":"Asia/Dhaka",
    "iso:country":"BD",
    "name:ben_x_preferred":[
        "Matsyaranga"
    ],
    "name:und_x_variant":[
        "Matsvaranga"
    ],
    "wof:name":"Matsyaranga",
    "wof:placetype":"locality"
},
  "geometry": {"coordinates":[89.07573000000002,23.19024],"type":"Point"}
}