{
  "type": "Feature",
  "properties": {
    "gn:admin1_code":"81",
    "gn:admin2_code":"3033.0",
    "gn:admin3_code":"303330.0",
    "gn:admin4_code":"30333047.0",
    "gn:asciiname":"Basan",
    "gn:country_code":"BD",
    "gn:dem":11,
    "gn:feature_class":"P",
    "gn:feature_code":"PPL",
    "gn:name":"B\u0101san",
    "gn:population":0,
    "gn:timezone":"Asia/Dhaka",
    "iso:country":"BD",
    "name:fra_x_preferred":[
        "Basan"
    ],
    "name:por_x_preferred":[
        "Basan"
    ],
    "name:rus_x_preferred":[
        "\u0411\u0430\u0441\u0430\u043d"
    ],
    "name:spa_x_preferred":[
        "Basan"
    ],
    "wof:name":"Basan",
    "wof:placetype":"locality"
},
  "geometry": {"coordinates":[90.33405,23.96022],"type":"Point"}
}