{
  "type": "Feature",
  "properties": {
    "gn:admin1_code":"85",
    "gn:admin2_code":"1079",
    "gn:admin3_code":"107958.0",
    "gn:admin4_code":"10795886.0",
    "gn:asciiname":"Ghoser Tikikata",
    "gn:country_code":"BD",
    "gn:dem":9,
    "gn:feature_class":"P",
    "gn:feature_code":"PPL",
    "gn:name":"Ghoser Tikikata",
    "gn:population":0,
    "gn:timezone":"Asia/Dhaka",
    "iso:country":"BD",
    "name:ben_x_preferred":[
        "Ghoser Tikikata"
    ],
    "wof:name":"Ghoser Tikikata",
    "wof:placetype":"locality"
},
  "geometry": {"coordinates":[89.98751,22.2738],"type":"Point"}
}