{
  "type": "Feature",
  "properties": {
    "gn:admin1_code":"83",
    "gn:admin2_code":"5070.0",
    "gn:admin3_code":"507037.0",
    "gn:admin4_code":"50703752.0",
    "gn:asciiname":"Khairpur",
    "gn:country_code":"BD",
    "gn:dem":30,
    "gn:feature_class":"P",
    "gn:feature_code":"PPL",
    "gn:name":"Khairpur",
    "gn:population":0,
    "gn:timezone":"Asia/Dhaka",
    "iso:country":"BD",
    "name:ben_x_preferred":[
        "Khairpur"
    ],
    "wof:name":"Khairpur",
    "wof:placetype":"locality"
},
  "geometry": {"coordinates":[88.31529999999999,24.81102000000001],"type":"Point"}
}