{
  "type": "Feature",
  "properties": {
    "gn:admin1_code":"83",
    "gn:admin2_code":"5070.0",
    "gn:admin3_code":"507037.0",
    "gn:admin4_code":"50703752.0",
    "gn:asciiname":"Khairpur",
    "gn:country_code":"BD",
    "gn:dem":30,
    "gn:feature_class":"P",
    "gn:feature_code":"PPL",
    "gn:name":"Khairpur",
    "gn:population":0,
    "gn:timezone":"Asia/Dhaka",
    "iso:country":"BD",
    "name:ben_x_preferred":[
        "Khairpur"
    ],
    "name:ben_x_variant":[
        "\u0996\u09c8\u09b0\u09aa\u09c1\u09b0"
    ],
    "name:cat_x_preferred":[
        "Khairpur"
    ],
    "name:ceb_x_preferred":[
        "Khairpur"
    ],
    "name:fas_x_preferred":[
        "\u062e\u06cc\u0631\u067e\u0648\u0631"
    ],
    "name:fra_x_preferred":[
        "Khairpur"
    ],
    "name:glg_x_preferred":[
        "Khairpur"
    ],
    "name:hin_x_preferred":[
        "\u0916\u0948\u0930\u092a\u0941\u0930"
    ],
    "name:ita_x_preferred":[
        "Khairpur"
    ],
    "name:lit_x_preferred":[
        "Chairpuras"
    ],
    "name:pnb_x_preferred":[
        "\u062e\u06cc\u0631\u067e\u0648\u0631"
    ],
    "name:pol_x_preferred":[
        "Khairpur"
    ],
    "name:pus_x_preferred":[
        "\u062e\u064a\u0631\u067e\u0648\u0631"
    ],
    "name:rus_x_preferred":[
        "\u0425\u0430\u0439\u0440\u043f\u0443\u0440"
    ],
    "name:snd_x_preferred":[
        "\u062e\u064a\u0631\u067e\u0648\u0631"
    ],
    "name:spa_x_preferred":[
        "Khairpur"
    ],
    "name:srp_x_preferred":[
        "\u0425\u0430\u0458\u0440\u043f\u0443\u0440"
    ],
    "name:swe_x_preferred":[
        "Khairpur"
    ],
    "name:urd_x_preferred":[
        "\u062e\u06cc\u0631\u067e\u0648\u0631"
    ],
    "name:war_x_preferred":[
        "Khairpur"
    ],
    "name:zho_x_preferred":[
        "\u6d77\u723e\u5e03\u723e"
    ],
    "wof:name":"Khairpur",
    "wof:placetype":"locality"
},
  "geometry": {"coordinates":[88.31529999999999,24.81102000000001],"type":"Point"}
}