{
  "type": "Feature",
  "properties": {
    "gn:admin1_code":"84",
    "gn:admin2_code":"2015.0",
    "gn:admin3_code":"201570.0",
    "gn:admin4_code":"20157077.0",
    "gn:asciiname":"Khil Para",
    "gn:country_code":"BD",
    "gn:dem":9,
    "gn:feature_class":"P",
    "gn:feature_code":"PPL",
    "gn:name":"Khil P\u0101ra",
    "gn:population":0,
    "gn:timezone":"Asia/Dhaka",
    "iso:country":"BD",
    "name:ben_x_preferred":[
        "Khil P\u0101ra"
    ],
    "wof:name":"Khil Para",
    "wof:placetype":"locality"
},
  "geometry": {"coordinates":[92.08686,22.49174],"type":"Point"}
}