{
  "type": "Feature",
  "properties": {
    "gn:admin1_code":"82",
    "gn:admin2_code":"4055",
    "gn:admin3_code":"405595.0",
    "gn:admin4_code":"40559542.0",
    "gn:asciiname":"Kupuria",
    "gn:country_code":"BD",
    "gn:dem":17,
    "gn:feature_class":"P",
    "gn:feature_code":"PPL",
    "gn:name":"Kupuria",
    "gn:population":0,
    "gn:timezone":"Asia/Dhaka",
    "iso:country":"BD",
    "name:und_x_variant":[
        "Kupuria Village",
        "Kupuria"
    ],
    "wof:name":"Kupuria",
    "wof:placetype":"locality"
},
  "geometry": {"coordinates":[89.45902,23.58175],"type":"Point"}
}