{
  "type": "Feature",
  "properties": {
    "gn:admin1_code":"87",
    "gn:admin2_code":"5549",
    "gn:admin3_code":"554906.0",
    "gn:admin4_code":"55490619.0",
    "gn:asciiname":"Golbari",
    "gn:country_code":"BD",
    "gn:dem":35,
    "gn:feature_class":"P",
    "gn:feature_code":"PPL",
    "gn:name":"Golbari",
    "gn:population":0,
    "gn:timezone":"Asia/Dhaka",
    "iso:country":"BD",
    "name:ben_x_preferred":[
        "Golbari"
    ],
    "wof:name":"Golbari",
    "wof:placetype":"locality"
},
  "geometry": {"coordinates":[89.63624,26.11938],"type":"Point"}
}