{
  "type": "Feature",
  "properties": {
    "gn:admin1_code":"82",
    "gn:admin2_code":"4001.0",
    "gn:admin3_code":"400160.0",
    "gn:admin4_code":"40016053.0",
    "gn:asciiname":"Barai Khali",
    "gn:country_code":"BD",
    "gn:dem":9,
    "gn:feature_class":"P",
    "gn:feature_code":"PPL",
    "gn:name":"Barai Khali",
    "gn:population":0,
    "gn:timezone":"Asia/Dhaka",
    "iso:country":"BD",
    "name:ben_x_preferred":[
        "Barai Khali"
    ],
    "wof:name":"Barai Khali",
    "wof:placetype":"locality"
},
  "geometry": {"coordinates":[89.76000000000001,22.4758],"type":"Point"}
}