{
  "type": "Feature",
  "properties": {
    "gn:admin1_code":"81",
    "gn:admin2_code":"3048",
    "gn:admin3_code":"304811.0",
    "gn:admin4_code":"30481100.0",
    "gn:asciiname":"Ramshankarpur",
    "gn:country_code":"BD",
    "gn:dem":13,
    "gn:feature_class":"P",
    "gn:feature_code":"PPL",
    "gn:name":"R\u0101mshankarpur",
    "gn:population":0,
    "gn:timezone":"Asia/Dhaka",
    "iso:country":"BD",
    "name:und_x_variant":[
        "R\u0101mshankarpur",
        "R\u0101msankarpur"
    ],
    "wof:name":"Ramshankarpur",
    "wof:placetype":"locality"
},
  "geometry": {"coordinates":[90.99164,24.07465],"type":"Point"}
}