{
  "type": "Feature",
  "properties": {
    "gn:admin1_code":"82",
    "gn:admin2_code":"4041.0",
    "gn:admin3_code":"404190.0",
    "gn:admin4_code":"40419086.0",
    "gn:asciiname":"Samlagachi Potapara",
    "gn:country_code":"BD",
    "gn:dem":14,
    "gn:feature_class":"P",
    "gn:feature_code":"PPL",
    "gn:name":"S\u0101ml\u0101gachi Pot\u0101p\u0101ra",
    "gn:population":0,
    "gn:timezone":"Asia/Dhaka",
    "iso:country":"BD",
    "name:ben_x_preferred":[
        "S\u0101ml\u0101gachi Pot\u0101p\u0101ra"
    ],
    "wof:name":"Samlagachi Potapara",
    "wof:placetype":"locality"
},
  "geometry": {"coordinates":[88.96241999999999,23.05295],"type":"Point"}
}