{
  "type": "Feature",
  "properties": {
    "gn:admin1_code":"83",
    "gn:admin2_code":"5081",
    "gn:admin3_code":"508153.0",
    "gn:admin4_code":"50815327.0",
    "gn:asciiname":"Panchpara",
    "gn:country_code":"BD",
    "gn:dem":22,
    "gn:feature_class":"P",
    "gn:feature_code":"PPL",
    "gn:name":"P\u0101nchp\u0101ra",
    "gn:population":0,
    "gn:timezone":"Asia/Dhaka",
    "iso:country":"BD",
    "name:ben_x_preferred":[
        "P\u0101nchp\u0101ra"
    ],
    "wof:name":"Panchpara",
    "wof:placetype":"locality"
},
  "geometry": {"coordinates":[88.58705999999999,24.53185],"type":"Point"}
}