{
  "type": "Feature",
  "properties": {
    "gn:admin1_code":"83",
    "gn:asciiname":"Barapaika",
    "gn:country_code":"BD",
    "gn:dem":24,
    "gn:feature_class":"P",
    "gn:feature_code":"PPL",
    "gn:name":"B\u0101rap\u0101ika",
    "gn:population":0,
    "gn:timezone":"Asia/Dhaka",
    "iso:country":"BD",
    "name:ben_x_preferred":[
        "B\u0101rap\u0101ika"
    ],
    "wof:name":"Barapaika",
    "wof:placetype":"locality"
},
  "geometry": {"coordinates":[89.46269000000002,25.06765],"type":"Point"}
}