{
  "type": "Feature",
  "properties": {
    "gn:admin1_code":"87",
    "gn:admin2_code":"5585",
    "gn:admin3_code":"558549.0",
    "gn:admin4_code":"55854923.0",
    "gn:asciiname":"Sardartari",
    "gn:country_code":"BD",
    "gn:dem":40,
    "gn:feature_class":"P",
    "gn:feature_code":"PPL",
    "gn:name":"Sard\u0101rt\u0101ri",
    "gn:population":0,
    "gn:timezone":"Asia/Dhaka",
    "iso:country":"BD",
    "name:ben_x_preferred":[
        "Sard\u0101rt\u0101ri"
    ],
    "wof:name":"Sardartari",
    "wof:placetype":"locality"
},
  "geometry": {"coordinates":[89.14397,25.75861],"type":"Point"}
}