{
  "type": "Feature",
  "properties": {
    "gn:admin1_code":"81",
    "gn:admin2_code":"3033",
    "gn:admin3_code":"303330.0",
    "gn:admin4_code":"30333047.0",
    "gn:asciiname":"Sarupaitali",
    "gn:country_code":"BD",
    "gn:dem":19,
    "gn:feature_class":"P",
    "gn:feature_code":"PPL",
    "gn:name":"Sarup\u0101itali",
    "gn:population":0,
    "gn:timezone":"Asia/Dhaka",
    "iso:country":"BD",
    "wof:name":"Sarupaitali",
    "wof:placetype":"locality"
},
  "geometry": {"coordinates":[90.31984,23.96688],"type":"Point"}
}