{
  "type": "Feature",
  "properties": {
    "gn:admin1_code":"87",
    "gn:admin2_code":"5527.0",
    "gn:admin3_code":"552712.0",
    "gn:admin4_code":"55271243.0",
    "gn:asciiname":"Damalkshetra",
    "gn:country_code":"BD",
    "gn:dem":48,
    "gn:feature_class":"P",
    "gn:feature_code":"PPL",
    "gn:name":"D\u0101m\u0101lkshetra",
    "gn:population":0,
    "gn:timezone":"Asia/Dhaka",
    "iso:country":"BD",
    "name:ben_x_preferred":[
        "D\u0101m\u0101ikshetra"
    ],
    "name:ben_x_variant":[
        "D\u0101m\u0101lkshetra"
    ],
    "wof:name":"Damalkshetra",
    "wof:placetype":"locality"
},
  "geometry": {"coordinates":[88.62747,25.89925],"type":"Point"}
}