{
  "type": "Feature",
  "properties": {
    "gn:admin1_code":"H",
    "gn:admin2_code":"3039",
    "gn:admin3_code":"303929.0",
    "gn:admin4_code":"30392915.0",
    "gn:asciiname":"Uttar Goalnir Char",
    "gn:country_code":"BD",
    "gn:dem":21,
    "gn:feature_class":"P",
    "gn:feature_code":"PPL",
    "gn:name":"Uttar Goalnir Char",
    "gn:population":0,
    "gn:timezone":"Asia/Dhaka",
    "iso:country":"BD",
    "wof:name":"Uttar Goalnir Char",
    "wof:placetype":"locality"
},
  "geometry": {"coordinates":[89.85545999999999,25.06005],"type":"Point"}
}