{
  "type": "Feature",
  "properties": {
    "gn:admin1_code":"84",
    "gn:admin2_code":"2019.0",
    "gn:admin3_code":"201915.0",
    "gn:admin4_code":"20191550.0",
    "gn:asciiname":"Dighipar",
    "gn:country_code":"BD",
    "gn:dem":10,
    "gn:feature_class":"P",
    "gn:feature_code":"PPL",
    "gn:name":"D\u012bgh\u012bp\u0101r",
    "gn:population":0,
    "gn:timezone":"Asia/Dhaka",
    "iso:country":"BD",
    "wof:name":"Dighipar",
    "wof:placetype":"locality"
},
  "geometry": {"coordinates":[91.06667,23.66667],"type":"Point"}
}