{
  "type": "Feature",
  "properties": {
    "gn:admin1_code":"82",
    "gn:asciiname":"Kauabania",
    "gn:country_code":"BD",
    "gn:dem":8,
    "gn:feature_class":"P",
    "gn:feature_code":"PPL",
    "gn:name":"Kauabania",
    "gn:population":0,
    "gn:timezone":"Asia/Dhaka",
    "iso:country":"BD",
    "name:ben_x_preferred":[
        "Kauabania"
    ],
    "wof:name":"Kauabania",
    "wof:placetype":"locality"
},
  "geometry": {"coordinates":[90.31305999999999,22.38692],"type":"Point"}
}