{
  "type": "Feature",
  "properties": {
    "gn:admin1_code":"82",
    "gn:asciiname":"Kuralla",
    "gn:country_code":"BD",
    "gn:dem":7,
    "gn:feature_class":"P",
    "gn:feature_code":"PPL",
    "gn:name":"Kur\u0101lla",
    "gn:population":0,
    "gn:timezone":"Asia/Dhaka",
    "iso:country":"BD",
    "name:ben_x_preferred":[
        "Kur\u0101lla"
    ],
    "wof:name":"Kuralla",
    "wof:placetype":"locality"
},
  "geometry": {"coordinates":[90.26676999999999,22.31796],"type":"Point"}
}