{
  "type": "Feature",
  "properties": {
    "gn:admin1_code":"81",
    "gn:admin2_code":"3068.0",
    "gn:admin3_code":"306876.0",
    "gn:admin4_code":"30687684.0",
    "gn:asciiname":"Dakshin Karardi Char",
    "gn:country_code":"BD",
    "gn:dem":15,
    "gn:feature_class":"P",
    "gn:feature_code":"PPL",
    "gn:name":"Dakshin K\u0101r\u0101rdi Char",
    "gn:population":0,
    "gn:timezone":"Asia/Dhaka",
    "iso:country":"BD",
    "wof:name":"Dakshin Karardi Char",
    "wof:placetype":"locality"
},
  "geometry": {"coordinates":[90.69880999999999,23.94183],"type":"Point"}
}