{
  "type": "Feature",
  "properties": {
    "gn:admin1_code":"84",
    "gn:admin2_code":"2046.0",
    "gn:admin3_code":"204670.0",
    "gn:admin4_code":"20467076.0",
    "gn:asciiname":"Diwanbari",
    "gn:country_code":"BD",
    "gn:dem":52,
    "gn:feature_class":"P",
    "gn:feature_code":"PPL",
    "gn:name":"D\u012bw\u0101nb\u0101ri",
    "gn:population":0,
    "gn:timezone":"Asia/Dhaka",
    "iso:country":"BD",
    "wof:name":"Diwanbari",
    "wof:placetype":"locality"
},
  "geometry": {"coordinates":[91.78167000000001,23.2467],"type":"Point"}
}