{
  "type": "Feature",
  "properties": {
    "gn:admin1_code":"83",
    "gn:admin2_code":"5038.0",
    "gn:admin3_code":"503847.0",
    "gn:admin4_code":"50384747.0",
    "gn:asciiname":"Dogachhi",
    "gn:country_code":"BD",
    "gn:dem":25,
    "gn:feature_class":"P",
    "gn:feature_code":"PPL",
    "gn:name":"Dog\u0101chhi",
    "gn:population":0,
    "gn:timezone":"Asia/Dhaka",
    "iso:country":"BD",
    "name:ben_x_preferred":[
        "Dog\u0101chhi"
    ],
    "wof:name":"Dogachhi",
    "wof:placetype":"locality"
},
  "geometry": {"coordinates":[88.98366,25.11224],"type":"Point"}
}