{
  "type": "Feature",
  "properties": {
    "gn:admin1_code":"81",
    "gn:admin2_code":"3056.0",
    "gn:admin3_code":"305628.0",
    "gn:admin4_code":"30562880.0",
    "gn:asciiname":"Bhagaban Char",
    "gn:country_code":"BD",
    "gn:dem":1,
    "gn:feature_class":"P",
    "gn:feature_code":"PPL",
    "gn:name":"Bhagab\u0101n Char",
    "gn:population":0,
    "gn:timezone":"Asia/Dhaka",
    "iso:country":"BD",
    "wof:name":"Bhagaban Char",
    "wof:placetype":"locality"
},
  "geometry": {"coordinates":[89.93333,23.66667],"type":"Point"}
}