{
  "type": "Feature",
  "properties": {
    "gn:admin1_code":"82",
    "gn:admin2_code":"4041.0",
    "gn:admin3_code":"404123.0",
    "gn:admin4_code":"40412335.0",
    "gn:asciiname":"Beniali",
    "gn:country_code":"BD",
    "gn:dem":15,
    "gn:feature_class":"P",
    "gn:feature_code":"PPL",
    "gn:name":"Beni\u0101li",
    "gn:population":0,
    "gn:timezone":"Asia/Dhaka",
    "iso:country":"BD",
    "name:ben_x_preferred":[
        "Beni\u0101li"
    ],
    "wof:name":"Beniali",
    "wof:placetype":"locality"
},
  "geometry": {"coordinates":[89.06854,23.0842],"type":"Point"}
}