{
  "type": "Feature",
  "properties": {
    "gn:admin1_code":"83",
    "gn:admin2_code":"5064.0",
    "gn:admin3_code":"506450.0",
    "gn:admin4_code":"50645009.0",
    "gn:asciiname":"Harshi",
    "gn:country_code":"BD",
    "gn:dem":17,
    "gn:feature_class":"P",
    "gn:feature_code":"PPL",
    "gn:name":"Harshi",
    "gn:population":0,
    "gn:timezone":"Asia/Dhaka",
    "iso:country":"BD",
    "name:ben_x_preferred":[
        "Harshi"
    ],
    "wof:name":"Harshi",
    "wof:placetype":"locality"
},
  "geometry": {"coordinates":[88.87894,24.8474],"type":"Point"}
}