{
  "type": "Feature",
  "properties": {
    "gn:admin1_code":"87",
    "gn:admin2_code":"5577.0",
    "gn:admin3_code":"557725.0",
    "gn:admin4_code":"55772514.0",
    "gn:asciiname":"Chunchpara",
    "gn:country_code":"BD",
    "gn:dem":71,
    "gn:feature_class":"P",
    "gn:feature_code":"PPL",
    "gn:name":"Chunchpara",
    "gn:population":0,
    "gn:timezone":"Asia/Dhaka",
    "iso:country":"BD",
    "name:ben_x_preferred":[
        "Chunchpara"
    ],
    "wof:name":"Chunchpara",
    "wof:placetype":"locality"
},
  "geometry": {"coordinates":[88.59333000000002,26.2376],"type":"Point"}
}