{
  "type": "Feature",
  "properties": {
    "gn:admin1_code":"87",
    "gn:admin2_code":"5532",
    "gn:admin3_code":"553267.0",
    "gn:admin4_code":"55326738.0",
    "gn:asciiname":"Sitalgram",
    "gn:country_code":"BD",
    "gn:dem":28,
    "gn:feature_class":"P",
    "gn:feature_code":"PPL",
    "gn:name":"Sitalgr\u0101m",
    "gn:population":0,
    "gn:timezone":"Asia/Dhaka",
    "iso:country":"BD",
    "name:ben_x_preferred":[
        "Sitalgr\u0101m"
    ],
    "wof:name":"Sitalgram",
    "wof:placetype":"locality"
},
  "geometry": {"coordinates":[89.33626,25.24561],"type":"Point"}
}