{
  "type": "Feature",
  "properties": {
    "gn:admin1_code":"81",
    "gn:admin2_code":"3035.0",
    "gn:admin3_code":"303543.0",
    "gn:admin4_code":"30354394.0",
    "gn:asciiname":"Andharkota",
    "gn:country_code":"BD",
    "gn:dem":6,
    "gn:feature_class":"P",
    "gn:feature_code":"PPL",
    "gn:name":"Andh\u0101rkota",
    "gn:population":0,
    "gn:timezone":"Asia/Dhaka",
    "iso:country":"BD",
    "name:ben_x_preferred":[
        "Andh\u0101rkota"
    ],
    "wof:name":"Andharkota",
    "wof:placetype":"locality"
},
  "geometry": {"coordinates":[89.89493,23.15391],"type":"Point"}
}