{
  "type": "Feature",
  "properties": {
    "gn:admin1_code":"83",
    "gn:admin2_code":"5010",
    "gn:admin3_code":"501094.0",
    "gn:admin4_code":"50109431.0",
    "gn:asciiname":"Durlabhpur",
    "gn:country_code":"BD",
    "gn:dem":28,
    "gn:feature_class":"P",
    "gn:feature_code":"PPL",
    "gn:name":"Durlabhpur",
    "gn:population":0,
    "gn:timezone":"Asia/Dhaka",
    "iso:country":"BD",
    "name:ben_x_preferred":[
        "Durlabhpur"
    ],
    "wof:name":"Durlabhpur",
    "wof:placetype":"locality"
},
  "geometry": {"coordinates":[89.40434999999999,25.05855],"type":"Point"}
}