{
  "type": "Feature",
  "properties": {
    "gn:admin1_code":"81",
    "gn:admin2_code":"3029",
    "gn:admin3_code":"302918.0",
    "gn:admin4_code":"30291895.0",
    "gn:asciiname":"Sheikhpura",
    "gn:country_code":"BD",
    "gn:dem":11,
    "gn:feature_class":"P",
    "gn:feature_code":"PPL",
    "gn:name":"Sheikhpura",
    "gn:population":0,
    "gn:timezone":"Asia/Dhaka",
    "iso:country":"BD",
    "name:und_x_variant":[
        "Shekhpura",
        "Shekpura",
        "Sheikhpura"
    ],
    "wof:name":"Sheikhpura",
    "wof:placetype":"locality"
},
  "geometry": {"coordinates":[89.70340999999998,23.3046],"type":"Point"}
}