{
  "type": "Feature",
  "properties": {
    "gn:admin1_code":"87",
    "gn:admin2_code":"5594.0",
    "gn:admin3_code":"559494.0",
    "gn:admin4_code":"55949405.0",
    "gn:asciiname":"Debiganj",
    "gn:country_code":"BD",
    "gn:dem":63,
    "gn:feature_class":"P",
    "gn:feature_code":"PPL",
    "gn:name":"Debiganj",
    "gn:population":0,
    "gn:timezone":"Asia/Dhaka",
    "iso:country":"BD",
    "name:ben_x_preferred":[
        "Debiganj"
    ],
    "wof:name":"Debiganj",
    "wof:placetype":"locality"
},
  "geometry": {"coordinates":[88.42711,26.08045],"type":"Point"}
}