{
  "type": "Feature",
  "properties": {
    "gn:admin1_code":"83",
    "gn:asciiname":"Pabantair",
    "gn:country_code":"BD",
    "gn:dem":24,
    "gn:feature_class":"P",
    "gn:feature_code":"PPL",
    "gn:name":"Pabantair",
    "gn:population":0,
    "gn:timezone":"Asia/Dhaka",
    "iso:country":"BD",
    "name:ben_x_preferred":[
        "Pabantair"
    ],
    "wof:name":"Pabantair",
    "wof:placetype":"locality"
},
  "geometry": {"coordinates":[89.56673000000001,25.09265],"type":"Point"}
}