{
  "type": "Feature",
  "properties": {
    "gn:admin1_code":"81",
    "gn:admin2_code":"3082.0",
    "gn:admin3_code":"308273.0",
    "gn:admin4_code":"30827360.0",
    "gn:asciiname":"Arazi Gariana",
    "gn:country_code":"BD",
    "gn:dem":13,
    "gn:feature_class":"P",
    "gn:feature_code":"PPL",
    "gn:name":"\u0100r\u0101zi G\u0101ri\u0101na",
    "gn:population":0,
    "gn:timezone":"Asia/Dhaka",
    "iso:country":"BD",
    "name:und_x_variant":[
        "Araji Gariana",
        "\u0100r\u0101zi G\u0101ri\u0101na"
    ],
    "wof:name":"Arazi Gariana",
    "wof:placetype":"locality"
},
  "geometry": {"coordinates":[89.54943,23.74814],"type":"Point"}
}