{
  "type": "Feature",
  "properties": {
    "gn:admin1_code":"83",
    "gn:asciiname":"Chandpur",
    "gn:country_code":"BD",
    "gn:dem":22,
    "gn:feature_class":"P",
    "gn:feature_code":"PPL",
    "gn:name":"Chandpur",
    "gn:population":0,
    "gn:timezone":"Asia/Dhaka",
    "iso:country":"BD",
    "name:ben_x_preferred":[
        "Chandpur"
    ],
    "name:ben_x_variant":[
        "\u099a\u09be\u0981\u09a6\u09aa\u09c1\u09b0"
    ],
    "name:ceb_x_preferred":[
        "Chandpur"
    ],
    "name:deu_x_preferred":[
        "Chandpur"
    ],
    "name:ita_x_preferred":[
        "Chandpur"
    ],
    "name:nld_x_preferred":[
        "Chandpur"
    ],
    "name:pol_x_preferred":[
        "Chandpur"
    ],
    "name:rus_x_preferred":[
        "\u0427\u0430\u043d\u0434\u043f\u0443\u0440"
    ],
    "name:swe_x_preferred":[
        "Chandpur"
    ],
    "wof:name":"Chandpur",
    "wof:placetype":"locality"
},
  "geometry": {"coordinates":[89.38388,25.14884],"type":"Point"}
}