{
  "type": "Feature",
  "properties": {
    "gn:admin1_code":"83",
    "gn:admin2_code":"5070",
    "gn:admin3_code":"507056.0",
    "gn:admin4_code":"50705676.0",
    "gn:asciiname":"Kendua",
    "gn:country_code":"BD",
    "gn:dem":44,
    "gn:feature_class":"P",
    "gn:feature_code":"PPL",
    "gn:name":"Kendua",
    "gn:population":0,
    "gn:timezone":"Asia/Dhaka",
    "iso:country":"BD",
    "name:ben_x_preferred":[
        "Kendua"
    ],
    "wof:name":"Kendua",
    "wof:placetype":"locality"
},
  "geometry": {"coordinates":[88.37791999999997,24.68686],"type":"Point"}
}