{
  "type": "Feature",
  "properties": {
    "gn:admin1_code":"82",
    "gn:asciiname":"Padrisibpur",
    "gn:country_code":"BD",
    "gn:dem":9,
    "gn:feature_class":"P",
    "gn:feature_code":"PPL",
    "gn:name":"P\u0101drisibpur",
    "gn:population":0,
    "gn:timezone":"Asia/Dhaka",
    "iso:country":"BD",
    "name:ben_x_preferred":[
        "P\u0101drisibpur"
    ],
    "name:und_x_variant":[
        "Padrishibpur"
    ],
    "wof:name":"Padrisibpur",
    "wof:placetype":"locality"
},
  "geometry": {"coordinates":[90.29822,22.49908],"type":"Point"}
}