{
  "type": "Feature",
  "properties": {
    "gn:admin1_code":"84",
    "gn:admin2_code":"2015",
    "gn:admin3_code":"201561.0",
    "gn:admin4_code":"20156185.0",
    "gn:asciiname":"Kalapul",
    "gn:country_code":"BD",
    "gn:dem":9,
    "gn:feature_class":"P",
    "gn:feature_code":"PPL",
    "gn:name":"K\u0101l\u0101pul",
    "gn:population":0,
    "gn:timezone":"Asia/Dhaka",
    "iso:country":"BD",
    "name:ben_x_preferred":[
        "K\u0101l\u0101pul"
    ],
    "name:und_x_variant":[
        "K\u0101l\u0101put"
    ],
    "wof:name":"Kalapul",
    "wof:placetype":"locality"
},
  "geometry": {"coordinates":[91.8617,22.31224],"type":"Point"}
}