{
  "type": "Feature",
  "properties": {
    "gn:admin1_code":"H",
    "gn:admin2_code":"3089",
    "gn:admin3_code":"308970.0",
    "gn:admin4_code":"30897069.0",
    "gn:asciiname":"Manikchandpara",
    "gn:country_code":"BD",
    "gn:dem":30,
    "gn:feature_class":"P",
    "gn:feature_code":"PPL",
    "gn:name":"M\u0101nikchandp\u0101ra",
    "gn:population":0,
    "gn:timezone":"Asia/Dhaka",
    "iso:country":"BD",
    "name:ben_x_preferred":[
        "M\u0101nikchandp\u0101ra"
    ],
    "wof:name":"Manikchandpara",
    "wof:placetype":"locality"
},
  "geometry": {"coordinates":[90.17915000000001,25.1749],"type":"Point"}
}