{
  "type": "Feature",
  "properties": {
    "gn:admin1_code":"87",
    "gn:admin2_code":"5585.0",
    "gn:admin3_code":"558573.0",
    "gn:admin4_code":"55857328.0",
    "gn:asciiname":"Radhakrishna",
    "gn:country_code":"BD",
    "gn:dem":32,
    "gn:feature_class":"P",
    "gn:feature_code":"PPL",
    "gn:name":"R\u0101dh\u0101krishna",
    "gn:population":0,
    "gn:timezone":"Asia/Dhaka",
    "iso:country":"BD",
    "name:ben_x_preferred":[
        "R\u0101dh\u0101krishna"
    ],
    "wof:name":"Radhakrishna",
    "wof:placetype":"locality"
},
  "geometry": {"coordinates":[89.41045,25.69765],"type":"Point"}
}