{
  "type": "Feature",
  "properties": {
    "gn:admin1_code":"H",
    "gn:admin2_code":"3039.0",
    "gn:admin3_code":"303929.0",
    "gn:admin4_code":"30392955.0",
    "gn:asciiname":"Gangapara",
    "gn:country_code":"BD",
    "gn:dem":25,
    "gn:feature_class":"P",
    "gn:feature_code":"PPL",
    "gn:name":"Gangapara",
    "gn:population":0,
    "gn:timezone":"Asia/Dhaka",
    "iso:country":"BD",
    "name:und_x_variant":[
        "Gang\u0101p\u0101ra"
    ],
    "wof:name":"Gangapara",
    "wof:placetype":"locality"
},
  "geometry": {"coordinates":[89.76527,25.07677],"type":"Point"}
}