{
  "type": "Feature",
  "properties": {
    "gn:admin1_code":"83",
    "gn:admin2_code":"5064.0",
    "gn:admin3_code":"506428.0",
    "gn:admin4_code":"50642810.0",
    "gn:asciiname":"Konrail",
    "gn:country_code":"BD",
    "gn:dem":29,
    "gn:feature_class":"P",
    "gn:feature_code":"PPL",
    "gn:name":"Konrail",
    "gn:population":0,
    "gn:timezone":"Asia/Dhaka",
    "iso:country":"BD",
    "name:ben_x_preferred":[
        "Konrail"
    ],
    "wof:name":"Konrail",
    "wof:placetype":"locality"
},
  "geometry": {"coordinates":[88.68073000000003,25.20179],"type":"Point"}
}