{
  "type": "Feature",
  "properties": {
    "gn:admin1_code":"87",
    "gn:admin2_code":"5573.0",
    "gn:admin3_code":"557315.0",
    "gn:admin4_code":"55731585.0",
    "gn:asciiname":"Sundarkhata",
    "gn:country_code":"BD",
    "gn:dem":58,
    "gn:feature_class":"P",
    "gn:feature_code":"PPL",
    "gn:name":"Sund\u0101rkh\u0101ta",
    "gn:population":0,
    "gn:timezone":"Asia/Dhaka",
    "iso:country":"BD",
    "name:ben_x_preferred":[
        "Sund\u0101rkh\u0101ta"
    ],
    "wof:name":"Sundarkhata",
    "wof:placetype":"locality"
},
  "geometry": {"coordinates":[88.88495,26.15736],"type":"Point"}
}