{
  "type": "Feature",
  "properties": {
    "gn:admin1_code":"84",
    "gn:admin2_code":"2022.0",
    "gn:admin3_code":"202216.0",
    "gn:admin4_code":"20221616.0",
    "gn:asciiname":"Baraitali",
    "gn:country_code":"BD",
    "gn:dem":10,
    "gn:feature_class":"P",
    "gn:feature_code":"PPL",
    "gn:name":"Baraitali",
    "gn:population":0,
    "gn:timezone":"Asia/Dhaka",
    "iso:country":"BD",
    "name:ben_x_preferred":[
        "Baraitali"
    ],
    "wof:name":"Baraitali",
    "wof:placetype":"locality"
},
  "geometry": {"coordinates":[92.0688,21.83039],"type":"Point"}
}