{
  "type": "Feature",
  "properties": {
    "gn:admin1_code":"81",
    "gn:admin2_code":"3068",
    "gn:admin3_code":"306860.0",
    "gn:admin4_code":"30686065.0",
    "gn:asciiname":"Matia",
    "gn:country_code":"BD",
    "gn:dem":14,
    "gn:feature_class":"P",
    "gn:feature_code":"PPL",
    "gn:name":"Matia",
    "gn:population":0,
    "gn:timezone":"Asia/Dhaka",
    "iso:country":"BD",
    "name:ceb_x_preferred":[
        "Matia"
    ],
    "name:swe_x_preferred":[
        "Matia"
    ],
    "wof:name":"Matia",
    "wof:placetype":"locality"
},
  "geometry": {"coordinates":[90.66296,23.88904],"type":"Point"}
}