{
  "type": "Feature",
  "properties": {
    "gn:admin1_code":"87",
    "gn:admin2_code":"5585",
    "gn:admin3_code":"558573.0",
    "gn:admin4_code":"55857338.0",
    "gn:asciiname":"Kista Jamirjan",
    "gn:country_code":"BD",
    "gn:dem":30,
    "gn:feature_class":"P",
    "gn:feature_code":"PPL",
    "gn:name":"Kista J\u0101mirj\u0101n",
    "gn:population":0,
    "gn:timezone":"Asia/Dhaka",
    "iso:country":"BD",
    "name:ben_x_preferred":[
        "Kista J\u0101mirj\u0101n"
    ],
    "wof:name":"Kista Jamirjan",
    "wof:placetype":"locality"
},
  "geometry": {"coordinates":[89.41289999999999,25.61888],"type":"Point"}
}