{
  "type": "Feature",
  "properties": {
    "gn:admin1_code":"82",
    "gn:admin2_code":"4055",
    "gn:admin3_code":"405595.0",
    "gn:admin4_code":"40559510.0",
    "gn:asciiname":"Karandi",
    "gn:country_code":"BD",
    "gn:dem":14,
    "gn:feature_class":"P",
    "gn:feature_code":"PPL",
    "gn:name":"Karandi",
    "gn:population":0,
    "gn:timezone":"Asia/Dhaka",
    "iso:country":"BD",
    "wof:name":"Karandi",
    "wof:placetype":"locality"
},
  "geometry": {"coordinates":[89.41672,23.64094],"type":"Point"}
}