{
  "type": "Feature",
  "properties": {
    "gn:admin1_code":"82",
    "gn:admin2_code":"4044.0",
    "gn:admin3_code":"404419.0",
    "gn:admin4_code":"40441963.0",
    "gn:asciiname":"Kursi",
    "gn:country_code":"BD",
    "gn:dem":12,
    "gn:feature_class":"P",
    "gn:feature_code":"PPL",
    "gn:name":"Kursi",
    "gn:population":0,
    "gn:timezone":"Asia/Dhaka",
    "iso:country":"BD",
    "name:ben_x_preferred":[
        "Kursi"
    ],
    "wof:name":"Kursi",
    "wof:placetype":"locality"
},
  "geometry": {"coordinates":[89.19738000000002,23.46892],"type":"Point"}
}