{
  "type": "Feature",
  "properties": {
    "gn:admin1_code":"82",
    "gn:admin2_code":"4087.0",
    "gn:admin3_code":"408747.0",
    "gn:admin4_code":"40874731.0",
    "gn:asciiname":"Berakhali",
    "gn:country_code":"BD",
    "gn:dem":6,
    "gn:feature_class":"P",
    "gn:feature_code":"PPL",
    "gn:name":"Ber\u0101kh\u0101li",
    "gn:population":0,
    "gn:timezone":"Asia/Dhaka",
    "iso:country":"BD",
    "name:ben_x_preferred":[
        "Ber\u0101kh\u0101li"
    ],
    "wof:name":"Berakhali",
    "wof:placetype":"locality"
},
  "geometry": {"coordinates":[89.12753000000002,22.4502],"type":"Point"}
}