{
  "type": "Feature",
  "properties": {
    "gn:admin1_code":"81",
    "gn:admin2_code":"3026",
    "gn:admin3_code":"302638.0",
    "gn:admin4_code":"30263825.0",
    "gn:asciiname":"Saraspur",
    "gn:country_code":"BD",
    "gn:dem":8,
    "gn:feature_class":"P",
    "gn:feature_code":"PPL",
    "gn:name":"Saraspur",
    "gn:population":0,
    "gn:timezone":"Asia/Dhaka",
    "iso:country":"BD",
    "name:und_x_variant":[
        "Sabaspur",
        "Saraspur"
    ],
    "wof:name":"Saraspur",
    "wof:placetype":"locality"
},
  "geometry": {"coordinates":[90.28917,23.69061],"type":"Point"}
}