{
  "type": "Feature",
  "properties": {
    "gn:admin1_code":"82",
    "gn:admin2_code":"4041.0",
    "gn:admin3_code":"404109.0",
    "gn:admin4_code":"40410909.0",
    "gn:asciiname":"Dakshin Srirampur",
    "gn:country_code":"BD",
    "gn:dem":13,
    "gn:feature_class":"P",
    "gn:feature_code":"PPL",
    "gn:name":"Dakshin Sr\u012br\u0101mpur",
    "gn:population":0,
    "gn:timezone":"Asia/Dhaka",
    "iso:country":"BD",
    "name:ben_x_preferred":[
        "Dakshin Sr\u012br\u0101mpur"
    ],
    "wof:name":"Dakshin Srirampur",
    "wof:placetype":"locality"
},
  "geometry": {"coordinates":[89.3539,23.17574],"type":"Point"}
}