{
  "type": "Feature",
  "properties": {
    "gn:admin1_code":"87",
    "gn:admin2_code":"5527",
    "gn:admin3_code":"552743.0",
    "gn:admin4_code":"55274376.0",
    "gn:asciiname":"Rishighat",
    "gn:country_code":"BD",
    "gn:dem":29,
    "gn:feature_class":"P",
    "gn:feature_code":"PPL",
    "gn:name":"Rishighat",
    "gn:population":0,
    "gn:timezone":"Asia/Dhaka",
    "iso:country":"BD",
    "name:ben_x_preferred":[
        "Rishighat"
    ],
    "wof:name":"Rishighat",
    "wof:placetype":"locality"
},
  "geometry": {"coordinates":[89.26045999999999,25.2802],"type":"Point"}
}