{
  "type": "Feature",
  "properties": {
    "gn:admin1_code":"85",
    "gn:admin2_code":"1006.0",
    "gn:admin3_code":"100694.0",
    "gn:admin4_code":"10069421.0",
    "gn:asciiname":"Gabbari",
    "gn:country_code":"BD",
    "gn:dem":13,
    "gn:feature_class":"P",
    "gn:feature_code":"PPL",
    "gn:name":"G\u0101bb\u0101ri",
    "gn:population":0,
    "gn:timezone":"Asia/Dhaka",
    "iso:country":"BD",
    "wof:name":"Gabbari",
    "wof:placetype":"locality"
},
  "geometry": {"coordinates":[90.21491,22.84755],"type":"Point"}
}