{
  "type": "Feature",
  "properties": {
    "gn:admin1_code":"87",
    "gn:admin2_code":"5594.0",
    "gn:admin3_code":"559494.0",
    "gn:admin4_code":"55949410.0",
    "gn:asciiname":"Akhanagar",
    "gn:country_code":"BD",
    "gn:dem":66,
    "gn:feature_class":"P",
    "gn:feature_code":"PPL",
    "gn:name":"\u0100kh\u0101nagar",
    "gn:population":0,
    "gn:timezone":"Asia/Dhaka",
    "iso:country":"BD",
    "name:ben_x_preferred":[
        "\u0100kh\u0101nagar"
    ],
    "wof:name":"Akhanagar",
    "wof:placetype":"locality"
},
  "geometry": {"coordinates":[88.37751999999998,26.11297],"type":"Point"}
}