{
  "type": "Feature",
  "properties": {
    "gn:admin1_code":"83",
    "gn:admin2_code":"5076.0",
    "gn:admin3_code":"507683.0",
    "gn:admin4_code":"50768338.0",
    "gn:asciiname":"Hatkhali",
    "gn:country_code":"BD",
    "gn:dem":13,
    "gn:feature_class":"P",
    "gn:feature_code":"PPL",
    "gn:name":"H\u0101tkh\u0101li",
    "gn:population":0,
    "gn:timezone":"Asia/Dhaka",
    "iso:country":"BD",
    "wof:name":"Hatkhali",
    "wof:placetype":"locality"
},
  "geometry": {"coordinates":[89.49268000000002,23.87028],"type":"Point"}
}