{
  "type": "Feature",
  "properties": {
    "gn:admin1_code":"81",
    "gn:admin2_code":"3035",
    "gn:admin3_code":"303543.0",
    "gn:admin4_code":"30354313.0",
    "gn:asciiname":"Tarail",
    "gn:country_code":"BD",
    "gn:dem":13,
    "gn:feature_class":"P",
    "gn:feature_code":"PPL",
    "gn:name":"T\u0101r\u0101il",
    "gn:population":0,
    "gn:timezone":"Asia/Dhaka",
    "iso:country":"BD",
    "name:ben_x_preferred":[
        "T\u0101r\u0101il"
    ],
    "wof:name":"Tarail",
    "wof:placetype":"locality"
},
  "geometry": {"coordinates":[89.76036999999999,23.16412],"type":"Point"}
}