{
  "type": "Feature",
  "properties": {
    "gn:admin1_code":"85",
    "gn:admin2_code":"1004.0",
    "gn:admin3_code":"100409.0",
    "gn:admin4_code":"10040939.0",
    "gn:asciiname":"Tatepara",
    "gn:country_code":"BD",
    "gn:dem":5,
    "gn:feature_class":"P",
    "gn:feature_code":"PPL",
    "gn:name":"Tatepara",
    "gn:population":0,
    "gn:timezone":"Asia/Dhaka",
    "iso:country":"BD",
    "name:ben_x_preferred":[
        "Tatepara"
    ],
    "wof:name":"Tatepara",
    "wof:placetype":"locality"
},
  "geometry": {"coordinates":[90.06175999999998,21.92806],"type":"Point"}
}