{
  "type": "Feature",
  "properties": {
    "gn:admin1_code":"81",
    "gn:admin2_code":"3068.0",
    "gn:admin3_code":"306860.0",
    "gn:admin4_code":"30686011.0",
    "gn:asciiname":"Aolat",
    "gn:country_code":"BD",
    "gn:dem":8,
    "gn:feature_class":"P",
    "gn:feature_code":"PPL",
    "gn:name":"\u0100olat",
    "gn:population":0,
    "gn:timezone":"Asia/Dhaka",
    "iso:country":"BD",
    "wof:name":"Aolat",
    "wof:placetype":"locality"
},
  "geometry": {"coordinates":[90.63333,23.88333],"type":"Point"}
}