{
  "type": "Feature",
  "properties": {
    "gn:admin1_code":"87",
    "gn:admin2_code":"5527.0",
    "gn:admin3_code":"552760.0",
    "gn:admin4_code":"55276094.0",
    "gn:asciiname":"Madhubanpur",
    "gn:country_code":"BD",
    "gn:dem":48,
    "gn:feature_class":"P",
    "gn:feature_code":"PPL",
    "gn:name":"Madhubanpur",
    "gn:population":0,
    "gn:timezone":"Asia/Dhaka",
    "iso:country":"BD",
    "name:ben_x_preferred":[
        "Madhubanpur"
    ],
    "wof:name":"Madhubanpur",
    "wof:placetype":"locality"
},
  "geometry": {"coordinates":[88.7323,25.85947],"type":"Point"}
}