{
  "type": "Feature",
  "properties": {
    "gn:admin1_code":"H",
    "gn:admin2_code":"3061.0",
    "gn:admin3_code":"306131.0",
    "gn:admin4_code":"30613167.0",
    "gn:asciiname":"Bri Ghagra",
    "gn:country_code":"BD",
    "gn:dem":18,
    "gn:feature_class":"P",
    "gn:feature_code":"PPL",
    "gn:name":"Bri Gh\u0101gra",
    "gn:population":0,
    "gn:timezone":"Asia/Dhaka",
    "iso:country":"BD",
    "wof:name":"Bri Ghagra",
    "wof:placetype":"locality"
},
  "geometry": {"coordinates":[90.55471,24.61265],"type":"Point"}
}