{
  "type": "Feature",
  "properties": {
    "gn:admin1_code":"83",
    "gn:admin2_code":"5081.0",
    "gn:admin3_code":"508131.0",
    "gn:admin4_code":"50813111.0",
    "gn:asciiname":"Gorkhal",
    "gn:country_code":"BD",
    "gn:dem":20,
    "gn:feature_class":"P",
    "gn:feature_code":"PPL",
    "gn:name":"Gorkh\u0101l",
    "gn:population":0,
    "gn:timezone":"Asia/Dhaka",
    "iso:country":"BD",
    "name:ben_x_preferred":[
        "Gorkh\u0101l"
    ],
    "wof:name":"Gorkhal",
    "wof:placetype":"locality"
},
  "geometry": {"coordinates":[88.74551,24.44853],"type":"Point"}
}