{
  "type": "Feature",
  "properties": {
    "gn:admin1_code":"81",
    "gn:admin2_code":"3067",
    "gn:admin3_code":"306758.0",
    "gn:admin4_code":"30675863.0",
    "gn:asciiname":"Kasipur",
    "gn:country_code":"BD",
    "gn:dem":10,
    "gn:feature_class":"P",
    "gn:feature_code":"PPL",
    "gn:name":"K\u0101sipur",
    "gn:population":0,
    "gn:timezone":"Asia/Dhaka",
    "iso:country":"BD",
    "wof:name":"Kasipur",
    "wof:placetype":"locality"
},
  "geometry": {"coordinates":[90.48268,23.61222],"type":"Point"}
}