{
  "type": "Feature",
  "properties": {
    "gn:admin1_code":"81",
    "gn:admin2_code":"3067",
    "gn:admin3_code":"306768.0",
    "gn:admin4_code":"30676807.0",
    "gn:asciiname":"Kutubpur",
    "gn:country_code":"BD",
    "gn:dem":10,
    "gn:feature_class":"P",
    "gn:feature_code":"PPL",
    "gn:name":"Kutubpur",
    "gn:population":0,
    "gn:timezone":"Asia/Dhaka",
    "iso:country":"BD",
    "wof:name":"Kutubpur",
    "wof:placetype":"locality"
},
  "geometry": {"coordinates":[90.58492,23.84993],"type":"Point"}
}