{
  "type": "Feature",
  "properties": {
    "gn:admin1_code":"H",
    "gn:admin2_code":"3089",
    "gn:admin3_code":"308990.0",
    "gn:admin4_code":"30899039.0",
    "gn:asciiname":"Chiuria",
    "gn:country_code":"BD",
    "gn:dem":23,
    "gn:feature_class":"P",
    "gn:feature_code":"PPL",
    "gn:name":"Chiuria",
    "gn:population":0,
    "gn:timezone":"Asia/Dhaka",
    "iso:country":"BD",
    "name:ben_x_preferred":[
        "Chiuria"
    ],
    "wof:name":"Chiuria",
    "wof:placetype":"locality"
},
  "geometry": {"coordinates":[90.00046,25.12779],"type":"Point"}
}