{
  "type": "Feature",
  "properties": {
    "gn:admin1_code":"82",
    "gn:admin2_code":"4050.0",
    "gn:admin3_code":"405015.0",
    "gn:admin4_code":"40501540.0",
    "gn:asciiname":"Chandipur",
    "gn:country_code":"BD",
    "gn:dem":16,
    "gn:feature_class":"P",
    "gn:feature_code":"PPL",
    "gn:name":"Chandipur",
    "gn:population":0,
    "gn:timezone":"Asia/Dhaka",
    "iso:country":"BD",
    "name:ben_x_preferred":[
        "Chandipur"
    ],
    "wof:name":"Chandipur",
    "wof:placetype":"locality"
},
  "geometry": {"coordinates":[89.00204000000002,23.99381],"type":"Point"}
}