{
  "type": "Feature",
  "properties": {
    "gn:admin1_code":"83",
    "gn:admin2_code":"5081.0",
    "gn:admin3_code":"508182.0",
    "gn:admin4_code":"50818227.0",
    "gn:asciiname":"Domadi",
    "gn:country_code":"BD",
    "gn:dem":21,
    "gn:feature_class":"P",
    "gn:feature_code":"PPL",
    "gn:name":"Dom\u0101di",
    "gn:population":0,
    "gn:timezone":"Asia/Dhaka",
    "iso:country":"BD",
    "name:ben_x_preferred":[
        "Dom\u0101di"
    ],
    "wof:name":"Domadi",
    "wof:placetype":"locality"
},
  "geometry": {"coordinates":[88.76361,24.39752],"type":"Point"}
}