{
  "type": "Feature",
  "properties": {
    "gn:admin1_code":"87",
    "gn:admin2_code":"5585",
    "gn:admin3_code":"558542.0",
    "gn:admin4_code":"55854281.0",
    "gn:asciiname":"Nij Dhuppah",
    "gn:country_code":"BD",
    "gn:dem":33,
    "gn:feature_class":"P",
    "gn:feature_code":"PPL",
    "gn:name":"Nij Dhuppah",
    "gn:population":0,
    "gn:timezone":"Asia/Dhaka",
    "iso:country":"BD",
    "name:ben_x_preferred":[
        "Nij Dhuppah"
    ],
    "wof:name":"Nij Dhuppah",
    "wof:placetype":"locality"
},
  "geometry": {"coordinates":[89.44525,25.75337],"type":"Point"}
}