{
  "type": "Feature",
  "properties": {
    "gn:admin1_code":"82",
    "gn:admin2_code":"4065.0",
    "gn:admin3_code":"406528.0",
    "gn:admin4_code":"40652823.0",
    "gn:asciiname":"Silimpur",
    "gn:country_code":"BD",
    "gn:dem":7,
    "gn:feature_class":"P",
    "gn:feature_code":"PPL",
    "gn:name":"Silimpur",
    "gn:population":0,
    "gn:timezone":"Asia/Dhaka",
    "iso:country":"BD",
    "name:ben_x_preferred":[
        "Silimpur"
    ],
    "wof:name":"Silimpur",
    "wof:placetype":"locality"
},
  "geometry": {"coordinates":[89.58969,22.98514],"type":"Point"}
}