{
  "type": "Feature",
  "properties": {
    "gn:admin1_code":"87",
    "gn:admin2_code":"5585",
    "gn:admin3_code":"558549.0",
    "gn:admin4_code":"55854987.0",
    "gn:asciiname":"Topodhan",
    "gn:country_code":"BD",
    "gn:dem":38,
    "gn:feature_class":"P",
    "gn:feature_code":"PPL",
    "gn:name":"Topodhan",
    "gn:population":0,
    "gn:timezone":"Asia/Dhaka",
    "iso:country":"BD",
    "name:ben_x_preferred":[
        "Topodhan"
    ],
    "wof:name":"Topodhan",
    "wof:placetype":"locality"
},
  "geometry": {"coordinates":[89.27866999999998,25.79245],"type":"Point"}
}