{
  "type": "Feature",
  "properties": {
    "gn:admin1_code":"82",
    "gn:admin2_code":"4044.0",
    "gn:admin3_code":"404433.0",
    "gn:admin4_code":"40443381.0",
    "gn:asciiname":"Rakhalgachhi",
    "gn:country_code":"BD",
    "gn:dem":14,
    "gn:feature_class":"P",
    "gn:feature_code":"PPL",
    "gn:name":"R\u0101kh\u0101lg\u0101chhi",
    "gn:population":0,
    "gn:timezone":"Asia/Dhaka",
    "iso:country":"BD",
    "name:ben_x_preferred":[
        "R\u0101kh\u0101lg\u0101chhi"
    ],
    "wof:name":"Rakhalgachhi",
    "wof:placetype":"locality"
},
  "geometry": {"coordinates":[89.0874,23.33651],"type":"Point"}
}