{
  "type": "Feature",
  "properties": {
    "gn:admin1_code":"81",
    "gn:admin2_code":"3033",
    "gn:admin3_code":"303334.0",
    "gn:admin4_code":"30333417.0",
    "gn:asciiname":"Kauchan",
    "gn:country_code":"BD",
    "gn:dem":12,
    "gn:feature_class":"P",
    "gn:feature_code":"PPL",
    "gn:name":"Kauch\u0101n",
    "gn:population":0,
    "gn:timezone":"Asia/Dhaka",
    "iso:country":"BD",
    "wof:name":"Kauchan",
    "wof:placetype":"locality"
},
  "geometry": {"coordinates":[90.55983999999999,23.99046],"type":"Point"}
}