{
  "type": "Feature",
  "properties": {
    "gn:admin1_code":"82",
    "gn:admin2_code":"4065",
    "gn:admin3_code":"406552.0",
    "gn:admin4_code":"40655294.0",
    "gn:asciiname":"Siarbar",
    "gn:country_code":"BD",
    "gn:dem":7,
    "gn:feature_class":"P",
    "gn:feature_code":"PPL",
    "gn:name":"Si\u0101rbar",
    "gn:population":0,
    "gn:timezone":"Asia/Dhaka",
    "iso:country":"BD",
    "wof:name":"Siarbar",
    "wof:placetype":"locality"
},
  "geometry": {"coordinates":[89.62505,23.26691],"type":"Point"}
}