{
  "type": "Feature",
  "properties": {
    "gn:admin1_code":"84",
    "gn:admin2_code":"2019.0",
    "gn:admin3_code":"201936.0",
    "gn:admin4_code":"20193694.0",
    "gn:asciiname":"Dhakargaon",
    "gn:country_code":"BD",
    "gn:dem":9,
    "gn:feature_class":"P",
    "gn:feature_code":"PPL",
    "gn:name":"Dh\u0101k\u0101rgaon",
    "gn:population":0,
    "gn:timezone":"Asia/Dhaka",
    "iso:country":"BD",
    "wof:name":"Dhakargaon",
    "wof:placetype":"locality"
},
  "geometry": {"coordinates":[90.74236000000001,23.51863],"type":"Point"}
}