{
  "type": "Feature",
  "properties": {
    "gn:admin1_code":"82",
    "gn:admin2_code":"4041.0",
    "gn:admin3_code":"404147.0",
    "gn:admin4_code":"40414705.0",
    "gn:asciiname":"Bhikutia",
    "gn:country_code":"BD",
    "gn:dem":14,
    "gn:feature_class":"P",
    "gn:feature_code":"PPL",
    "gn:name":"Bhikutia",
    "gn:population":0,
    "gn:timezone":"Asia/Dhaka",
    "iso:country":"BD",
    "name:ben_x_preferred":[
        "Bhikutia"
    ],
    "wof:name":"Bhikutia",
    "wof:placetype":"locality"
},
  "geometry": {"coordinates":[89.16946999999998,23.16242],"type":"Point"}
}