{
  "type": "Feature",
  "properties": {
    "gn:admin1_code":"84",
    "gn:admin2_code":"2015.0",
    "gn:admin3_code":"201586.0",
    "gn:admin4_code":"20158676.0",
    "gn:asciiname":"Eyakobnagar",
    "gn:country_code":"BD",
    "gn:dem":14,
    "gn:feature_class":"P",
    "gn:feature_code":"PPL",
    "gn:name":"Eyakobnagar",
    "gn:population":0,
    "gn:timezone":"Asia/Dhaka",
    "iso:country":"BD",
    "wof:name":"Eyakobnagar",
    "wof:placetype":"locality"
},
  "geometry": {"coordinates":[91.65028,22.64139],"type":"Point"}
}