{
  "type": "Feature",
  "properties": {
    "gn:admin1_code":"87",
    "gn:admin2_code":"5532",
    "gn:admin3_code":"553267.0",
    "gn:admin4_code":"55326747.0",
    "gn:asciiname":"Buznik",
    "gn:country_code":"BD",
    "gn:dem":27,
    "gn:feature_class":"P",
    "gn:feature_code":"PPL",
    "gn:name":"Buznik",
    "gn:population":0,
    "gn:timezone":"Asia/Dhaka",
    "iso:country":"BD",
    "name:ben_x_preferred":[
        "Buznik"
    ],
    "wof:name":"Buznik",
    "wof:placetype":"locality"
},
  "geometry": {"coordinates":[89.30303000000001,25.27977000000001],"type":"Point"}
}