{
  "type": "Feature",
  "properties": {
    "gn:admin1_code":"82",
    "gn:admin2_code":"4018.0",
    "gn:admin3_code":"401823.0",
    "gn:admin4_code":"40182371.0",
    "gn:asciiname":"Dingadaha",
    "gn:country_code":"BD",
    "gn:dem":16,
    "gn:feature_class":"P",
    "gn:feature_code":"PPL",
    "gn:name":"Dingadaha",
    "gn:population":0,
    "gn:timezone":"Asia/Dhaka",
    "iso:country":"BD",
    "name:ben_x_preferred":[
        "Dingadaha"
    ],
    "wof:name":"Dingadaha",
    "wof:placetype":"locality"
},
  "geometry": {"coordinates":[88.88193000000003,23.60991],"type":"Point"}
}