{
  "type": "Feature",
  "properties": {
    "gn:admin1_code":"81",
    "gn:admin2_code":"3026",
    "gn:admin3_code":"302640.0",
    "gn:admin4_code":"30264009.0",
    "gn:asciiname":"Paschim Durgapur",
    "gn:country_code":"BD",
    "gn:dem":8,
    "gn:feature_class":"P",
    "gn:feature_code":"PPL",
    "gn:name":"Paschim Durg\u0101pur",
    "gn:population":0,
    "gn:timezone":"Asia/Dhaka",
    "iso:country":"BD",
    "wof:name":"Paschim Durgapur",
    "wof:placetype":"locality"
},
  "geometry": {"coordinates":[90.46156999999999,23.74681],"type":"Point"}
}