{
  "type": "Feature",
  "properties": {
    "gn:admin1_code":"82",
    "gn:admin2_code":"4041.0",
    "gn:admin3_code":"404123.0",
    "gn:admin4_code":"40412365.0",
    "gn:asciiname":"Balla",
    "gn:country_code":"BD",
    "gn:dem":13,
    "gn:feature_class":"P",
    "gn:feature_code":"PPL",
    "gn:name":"Balla",
    "gn:population":0,
    "gn:timezone":"Asia/Dhaka",
    "iso:country":"BD",
    "name:ben_x_preferred":[
        "Balla"
    ],
    "name:ceb_x_preferred":[
        "Balla"
    ],
    "name:ces_x_preferred":[
        "Balla"
    ],
    "name:deu_x_preferred":[
        "Balla"
    ],
    "name:fra_x_preferred":[
        "Balla"
    ],
    "name:hun_x_preferred":[
        "Balla"
    ],
    "name:ind_x_preferred":[
        "Balla"
    ],
    "name:ita_x_preferred":[
        "Balla"
    ],
    "name:nld_x_preferred":[
        "Balla"
    ],
    "name:pol_x_preferred":[
        "Balla"
    ],
    "name:rus_x_preferred":[
        "\u0411\u0430\u043b\u043b\u0430"
    ],
    "name:srp_x_preferred":[
        "Balla"
    ],
    "name:swe_x_preferred":[
        "Balla"
    ],
    "name:ukr_x_preferred":[
        "\u0411\u0430\u043b\u043b\u0430"
    ],
    "wof:name":"Balla",
    "wof:placetype":"locality"
},
  "geometry": {"coordinates":[89.08129,23.02687],"type":"Point"}
}