{
  "type": "Feature",
  "properties": {
    "gn:admin1_code":"82",
    "gn:admin2_code":"4018.0",
    "gn:admin3_code":"401807.0",
    "gn:admin4_code":"40180794.0",
    "gn:asciiname":"Bhedamari",
    "gn:country_code":"BD",
    "gn:dem":15,
    "gn:feature_class":"P",
    "gn:feature_code":"PPL",
    "gn:name":"Bhed\u0101m\u0101ri",
    "gn:population":0,
    "gn:timezone":"Asia/Dhaka",
    "iso:country":"BD",
    "name:ben_x_preferred":[
        "Bhed\u0101m\u0101ri"
    ],
    "wof:name":"Bhedamari",
    "wof:placetype":"locality"
},
  "geometry": {"coordinates":[88.95103,23.68861],"type":"Point"}
}