{
  "type": "Feature",
  "properties": {
    "gn:admin1_code":"83",
    "gn:asciiname":"Sonatala Shakhail",
    "gn:country_code":"BD",
    "gn:dem":24,
    "gn:feature_class":"P",
    "gn:feature_code":"PPL",
    "gn:name":"Son\u0101tala Sh\u0101khail",
    "gn:population":0,
    "gn:timezone":"Asia/Dhaka",
    "iso:country":"BD",
    "name:ben_x_preferred":[
        "Son\u0101tala Sh\u0101khail"
    ],
    "wof:name":"Sonatala Shakhail",
    "wof:placetype":"locality"
},
  "geometry": {"coordinates":[89.44296999999997,25.14397],"type":"Point"}
}