{
  "type": "Feature",
  "properties": {
    "gn:admin1_code":"87",
    "gn:admin2_code":"5527.0",
    "gn:admin3_code":"552721.0",
    "gn:admin4_code":"55272113.0",
    "gn:asciiname":"Atgaon",
    "gn:country_code":"BD",
    "gn:dem":43,
    "gn:feature_class":"P",
    "gn:feature_code":"PPL",
    "gn:name":"\u0100tg\u0101on",
    "gn:population":0,
    "gn:timezone":"Asia/Dhaka",
    "iso:country":"BD",
    "name:ben_x_preferred":[
        "\u0100tgaon"
    ],
    "wof:name":"Atgaon",
    "wof:placetype":"locality"
},
  "geometry": {"coordinates":[88.50297,25.77171],"type":"Point"}
}