{
  "type": "Feature",
  "properties": {
    "gn:admin1_code":"H",
    "gn:admin2_code":"3061.0",
    "gn:admin3_code":"306122.0",
    "gn:admin4_code":"30612231.0",
    "gn:asciiname":"Bharail",
    "gn:country_code":"BD",
    "gn:dem":14,
    "gn:feature_class":"P",
    "gn:feature_code":"PPL",
    "gn:name":"Bh\u0101r\u0101il",
    "gn:population":0,
    "gn:timezone":"Asia/Dhaka",
    "iso:country":"BD",
    "wof:name":"Bharail",
    "wof:placetype":"locality"
},
  "geometry": {"coordinates":[90.49986,24.45979],"type":"Point"}
}