{
  "type": "Feature",
  "properties": {
    "gn:admin1_code":"87",
    "gn:admin2_code":"5585.0",
    "gn:admin3_code":"558573.0",
    "gn:admin4_code":"55857309.0",
    "gn:asciiname":"Gobrapara",
    "gn:country_code":"BD",
    "gn:dem":34,
    "gn:feature_class":"P",
    "gn:feature_code":"PPL",
    "gn:name":"Gobr\u0101p\u0101ra",
    "gn:population":0,
    "gn:timezone":"Asia/Dhaka",
    "iso:country":"BD",
    "name:ben_x_preferred":[
        "Gobr\u0101p\u0101ra"
    ],
    "wof:name":"Gobrapara",
    "wof:placetype":"locality"
},
  "geometry": {"coordinates":[89.46081,25.70818],"type":"Point"}
}