{
  "type": "Feature",
  "properties": {
    "gn:admin1_code":"81",
    "gn:admin2_code":"3086.0",
    "gn:admin3_code":"308665.0",
    "gn:admin4_code":"30866518.0",
    "gn:asciiname":"Bijhari",
    "gn:country_code":"BD",
    "gn:dem":12,
    "gn:feature_class":"P",
    "gn:feature_code":"PPL",
    "gn:name":"Bijh\u0101ri",
    "gn:population":0,
    "gn:timezone":"Asia/Dhaka",
    "iso:country":"BD",
    "wof:name":"Bijhari",
    "wof:placetype":"locality"
},
  "geometry": {"coordinates":[90.40586,23.23659],"type":"Point"}
}