{
  "type": "Feature",
  "properties": {
    "gn:admin1_code":"84",
    "gn:admin2_code":"2022.0",
    "gn:admin3_code":"202224.0",
    "gn:admin4_code":"20222435.0",
    "gn:asciiname":"Chaufaldandi",
    "gn:country_code":"BD",
    "gn:dem":3,
    "gn:feature_class":"P",
    "gn:feature_code":"PPL",
    "gn:name":"Chaufaldand\u012b",
    "gn:population":0,
    "gn:timezone":"Asia/Dhaka",
    "iso:country":"BD",
    "name:ben_x_preferred":[
        "Chaufaldand\u012b"
    ],
    "wof:name":"Chaufaldandi",
    "wof:placetype":"locality"
},
  "geometry": {"coordinates":[92.04282000000001,21.54021],"type":"Point"}
}