{
  "type": "Feature",
  "properties": {
    "gn:admin1_code":"87",
    "gn:admin2_code":"5585",
    "gn:admin3_code":"558558.0",
    "gn:admin4_code":"55855883.0",
    "gn:asciiname":"Mainpur",
    "gn:country_code":"BD",
    "gn:dem":33,
    "gn:feature_class":"P",
    "gn:feature_code":"PPL",
    "gn:name":"Mainpur",
    "gn:population":0,
    "gn:timezone":"Asia/Dhaka",
    "iso:country":"BD",
    "name:mai_x_preferred":[
        "\u092e\u0948\u0928\u092a\u0941\u0930 \u092a\u0915\u093e\u0939\u093e"
    ],
    "name:msa_x_preferred":[
        "Mainpur"
    ],
    "name:nep_x_preferred":[
        "\u092e\u0948\u0928\u092a\u0941\u0930 \u092a\u0915\u093e\u0939\u093e"
    ],
    "name:pol_x_preferred":[
        "Mainpur"
    ],
    "name:und_x_variant":[
        "Myanpoor",
        "Mayenpur"
    ],
    "wof:name":"Mainpur",
    "wof:placetype":"locality"
},
  "geometry": {"coordinates":[89.15408000000002,25.60494],"type":"Point"}
}