{
  "type": "Feature",
  "properties": {
    "gn:admin1_code":"85",
    "gn:admin2_code":"1004.0",
    "gn:admin3_code":"100447.0",
    "gn:admin4_code":"10044747.0",
    "gn:asciiname":"Anor Jailsha",
    "gn:country_code":"BD",
    "gn:dem":6,
    "gn:feature_class":"P",
    "gn:feature_code":"PPL",
    "gn:name":"Anor Jailsha",
    "gn:population":0,
    "gn:timezone":"Asia/Dhaka",
    "iso:country":"BD",
    "name:ben_x_preferred":[
        "Anor Jailsha"
    ],
    "wof:name":"Anor Jailsha",
    "wof:placetype":"locality"
},
  "geometry": {"coordinates":[90.17937000000001,22.36762],"type":"Point"}
}