{
  "type": "Feature",
  "properties": {
    "gn:admin1_code":"87",
    "gn:admin2_code":"5573.0",
    "gn:admin3_code":"557364.0",
    "gn:admin4_code":"55736453.0",
    "gn:asciiname":"Lakhichap",
    "gn:country_code":"BD",
    "gn:dem":53,
    "gn:feature_class":"P",
    "gn:feature_code":"PPL",
    "gn:name":"Lakhich\u0101p",
    "gn:population":0,
    "gn:timezone":"Asia/Dhaka",
    "iso:country":"BD",
    "name:ben_x_preferred":[
        "Lakhich\u0101p"
    ],
    "wof:name":"Lakhichap",
    "wof:placetype":"locality"
},
  "geometry": {"coordinates":[88.86979000000002,26.04806],"type":"Point"}
}