{
  "type": "Feature",
  "properties": {
    "gn:admin1_code":"84",
    "gn:admin2_code":"2013.0",
    "gn:admin3_code":"201322.0",
    "gn:admin4_code":"20132281.0",
    "gn:asciiname":"Chhota Saliata",
    "gn:country_code":"BD",
    "gn:dem":12,
    "gn:feature_class":"P",
    "gn:feature_code":"PPL",
    "gn:name":"Chhota Sali\u0101ta",
    "gn:population":0,
    "gn:timezone":"Asia/Dhaka",
    "iso:country":"BD",
    "name:und_x_variant":[
        "Chhota Sali\u0101ta",
        "Chhota S\u0101h\u0101tali"
    ],
    "wof:name":"Chhota Saliata",
    "wof:placetype":"locality"
},
  "geometry": {"coordinates":[90.73090000000001,23.23803],"type":"Point"}
}