{
  "type": "Feature",
  "properties": {
    "gn:admin1_code":"81",
    "gn:admin2_code":"3059",
    "gn:admin3_code":"305956.0",
    "gn:admin4_code":"30595619.0",
    "gn:asciiname":"Nahapara",
    "gn:country_code":"BD",
    "gn:dem":8,
    "gn:feature_class":"P",
    "gn:feature_code":"PPL",
    "gn:name":"N\u0101h\u0101p\u0101ra",
    "gn:population":0,
    "gn:timezone":"Asia/Dhaka",
    "iso:country":"BD",
    "wof:name":"Nahapara",
    "wof:placetype":"locality"
},
  "geometry": {"coordinates":[90.49605,23.5206],"type":"Point"}
}