{
  "type": "Feature",
  "properties": {
    "gn:admin1_code":"84",
    "gn:admin2_code":"2075",
    "gn:admin3_code":"207507.0",
    "gn:admin4_code":"20750704.0",
    "gn:asciiname":"Mulayempur",
    "gn:country_code":"BD",
    "gn:dem":10,
    "gn:feature_class":"P",
    "gn:feature_code":"PPL",
    "gn:name":"Mul\u0101yempur",
    "gn:population":0,
    "gn:timezone":"Asia/Dhaka",
    "iso:country":"BD",
    "wof:name":"Mulayempur",
    "wof:placetype":"locality"
},
  "geometry": {"coordinates":[90.99361,22.93674],"type":"Point"}
}