{
  "type": "Feature",
  "properties": {
    "gn:admin1_code":"H",
    "gn:admin2_code":"3072.0",
    "gn:admin3_code":"307274.0",
    "gn:admin4_code":"30727431.0",
    "gn:asciiname":"Chapan",
    "gn:country_code":"BD",
    "gn:dem":16,
    "gn:feature_class":"P",
    "gn:feature_code":"PPL",
    "gn:name":"Ch\u0101p\u0101n",
    "gn:population":0,
    "gn:timezone":"Asia/Dhaka",
    "iso:country":"BD",
    "name:kaz_x_preferred":[
        "\u0428\u0430\u043f\u0430\u043d"
    ],
    "name:nld_x_preferred":[
        "Chapan"
    ],
    "name:rus_x_preferred":[
        "\u0427\u0430\u043f\u0430\u043d"
    ],
    "wof:name":"Chapan",
    "wof:placetype":"locality"
},
  "geometry": {"coordinates":[90.70536,24.83319],"type":"Point"}
}