{
  "type": "Feature",
  "properties": {
    "gn:admin1_code":"87",
    "gn:admin2_code":"5532",
    "gn:admin3_code":"553282.0",
    "gn:admin4_code":"55328260.0",
    "gn:asciiname":"Gayespur",
    "gn:country_code":"BD",
    "gn:dem":27,
    "gn:feature_class":"P",
    "gn:feature_code":"PPL",
    "gn:name":"Gayespur",
    "gn:population":0,
    "gn:timezone":"Asia/Dhaka",
    "iso:country":"BD",
    "name:ben_x_preferred":[
        "Gayespur"
    ],
    "wof:name":"Gayespur",
    "wof:placetype":"locality"
},
  "geometry": {"coordinates":[89.43389000000001,25.40123],"type":"Point"}
}