{
  "type": "Feature",
  "properties": {
    "gn:admin1_code":"87",
    "gn:admin2_code":"5532",
    "gn:admin3_code":"553282.0",
    "gn:admin4_code":"55328260.0",
    "gn:asciiname":"Gayespur",
    "gn:country_code":"BD",
    "gn:dem":27,
    "gn:feature_class":"P",
    "gn:feature_code":"PPL",
    "gn:name":"Gayespur",
    "gn:population":0,
    "gn:timezone":"Asia/Dhaka",
    "iso:country":"BD",
    "name:ben_x_preferred":[
        "Gayespur"
    ],
    "name:ben_x_variant":[
        "\u0997\u09af\u09bc\u09c7\u09b6\u09aa\u09c1\u09b0"
    ],
    "name:bpy_x_preferred":[
        "\u0997\u09be\u09af\u09bc\u09c7\u09b6\u09aa\u09c1\u09b0"
    ],
    "name:ita_x_preferred":[
        "Gayespur"
    ],
    "name:msa_x_preferred":[
        "Gayespur"
    ],
    "name:new_x_preferred":[
        "\u0917\u092f\u0947\u0938\u094d\u092a\u0941\u0930"
    ],
    "name:por_x_preferred":[
        "Gayespur"
    ],
    "name:spa_x_preferred":[
        "Gayespur"
    ],
    "name:tam_x_preferred":[
        "\u0b95\u0bbe\u0baf\u0bc7\u0b9a\u0bc1\u0baa\u0bcd\u0baa\u0bc2\u0bb0\u0bcd"
    ],
    "name:vie_x_preferred":[
        "Gayespur"
    ],
    "name:zho_x_preferred":[
        "\u52a0\u8036\u65af\u666e\u5c14"
    ],
    "wof:name":"Gayespur",
    "wof:placetype":"locality"
},
  "geometry": {"coordinates":[89.43389000000001,25.40123],"type":"Point"}
}