{
  "type": "Feature",
  "properties": {
    "gn:admin1_code":"81",
    "gn:admin2_code":"3093",
    "gn:admin3_code":"309309.0",
    "gn:admin4_code":"30930983.0",
    "gn:asciiname":"Kaoaljani",
    "gn:country_code":"BD",
    "gn:dem":17,
    "gn:feature_class":"P",
    "gn:feature_code":"PPL",
    "gn:name":"K\u0101o\u0101lj\u0101ni",
    "gn:population":0,
    "gn:timezone":"Asia/Dhaka",
    "iso:country":"BD",
    "wof:name":"Kaoaljani",
    "wof:placetype":"locality"
},
  "geometry": {"coordinates":[90.0476,24.2898],"type":"Point"}
}