{
  "type": "Feature",
  "properties": {
    "gn:admin1_code":"81",
    "gn:admin2_code":"3059.0",
    "gn:admin3_code":"305994.0",
    "gn:admin4_code":"30599439.0",
    "gn:asciiname":"Dhipur",
    "gn:country_code":"BD",
    "gn:dem":9,
    "gn:feature_class":"P",
    "gn:feature_code":"PPL",
    "gn:name":"Dhipur",
    "gn:population":0,
    "gn:timezone":"Asia/Dhaka",
    "iso:country":"BD",
    "wof:name":"Dhipur",
    "wof:placetype":"locality"
},
  "geometry": {"coordinates":[90.46898,23.4766],"type":"Point"}
}