{
  "type": "Feature",
  "properties": {
    "gn:admin1_code":"82",
    "gn:admin2_code":"4050.0",
    "gn:admin3_code":"405039.0",
    "gn:admin4_code":"40503954.0",
    "gn:asciiname":"Hatkholapara",
    "gn:country_code":"BD",
    "gn:dem":19,
    "gn:feature_class":"P",
    "gn:feature_code":"PPL",
    "gn:name":"H\u0101tkhol\u0101p\u0101ra",
    "gn:population":0,
    "gn:timezone":"Asia/Dhaka",
    "iso:country":"BD",
    "name:ben_x_preferred":[
        "H\u0101tkhol\u0101p\u0101ra"
    ],
    "wof:name":"Hatkholapara",
    "wof:placetype":"locality"
},
  "geometry": {"coordinates":[88.91958000000002,24.09258],"type":"Point"}
}