{
  "type": "Feature",
  "properties": {
    "gn:admin1_code":"81",
    "gn:admin2_code":"3035.0",
    "gn:admin3_code":"303558.0",
    "gn:admin4_code":"30355861.0",
    "gn:asciiname":"Chhota Banagram",
    "gn:country_code":"BD",
    "gn:dem":13,
    "gn:feature_class":"P",
    "gn:feature_code":"PPL",
    "gn:name":"Chhota Banagr\u0101m",
    "gn:population":0,
    "gn:timezone":"Asia/Dhaka",
    "iso:country":"BD",
    "wof:name":"Chhota Banagram",
    "wof:placetype":"locality"
},
  "geometry": {"coordinates":[89.92178,23.30525],"type":"Point"}
}