{
  "type": "Feature",
  "properties": {
    "gn:admin1_code":"83",
    "gn:admin2_code":"5081",
    "gn:admin3_code":"508131.0",
    "gn:admin4_code":"50813171.0",
    "gn:asciiname":"Kismat Hoja",
    "gn:country_code":"BD",
    "gn:dem":17,
    "gn:feature_class":"P",
    "gn:feature_code":"PPL",
    "gn:name":"Kismat Hoja",
    "gn:population":0,
    "gn:timezone":"Asia/Dhaka",
    "iso:country":"BD",
    "name:ben_x_preferred":[
        "Kismat Hoja"
    ],
    "wof:name":"Kismat Hoja",
    "wof:placetype":"locality"
},
  "geometry": {"coordinates":[88.81421,24.44765],"type":"Point"}
}