{
  "type": "Feature",
  "properties": {
    "gn:admin1_code":"81",
    "gn:admin2_code":"3056.0",
    "gn:admin3_code":"305678.0",
    "gn:admin4_code":"30567811.0",
    "gn:asciiname":"Dhuturabari",
    "gn:country_code":"BD",
    "gn:dem":12,
    "gn:feature_class":"P",
    "gn:feature_code":"PPL",
    "gn:name":"Dhutur\u0101b\u0101ri",
    "gn:population":0,
    "gn:timezone":"Asia/Dhaka",
    "iso:country":"BD",
    "wof:name":"Dhuturabari",
    "wof:placetype":"locality"
},
  "geometry": {"coordinates":[89.81310000000001,23.79375],"type":"Point"}
}