{
  "type": "Feature",
  "properties": {
    "gn:admin1_code":"81",
    "gn:admin2_code":"3056",
    "gn:admin3_code":"305682.0",
    "gn:admin4_code":"30568208.0",
    "gn:asciiname":"Jamalpur",
    "gn:country_code":"BD",
    "gn:dem":17,
    "gn:feature_class":"P",
    "gn:feature_code":"PPL",
    "gn:name":"J\u0101m\u0101lpur",
    "gn:population":0,
    "gn:timezone":"Asia/Dhaka",
    "iso:country":"BD",
    "wof:name":"Jamalpur",
    "wof:placetype":"locality"
},
  "geometry": {"coordinates":[90.09587000000001,23.82655],"type":"Point"}
}