{
  "type": "Feature",
  "properties": {
    "gn:admin1_code":"83",
    "gn:admin2_code":"5064.0",
    "gn:admin3_code":"506486.0",
    "gn:admin4_code":"50648607.0",
    "gn:asciiname":"Sundarail",
    "gn:country_code":"BD",
    "gn:dem":31,
    "gn:feature_class":"P",
    "gn:feature_code":"PPL",
    "gn:name":"Sund\u0101rail",
    "gn:population":0,
    "gn:timezone":"Asia/Dhaka",
    "iso:country":"BD",
    "name:ben_x_preferred":[
        "Sund\u0101rail"
    ],
    "wof:name":"Sundarail",
    "wof:placetype":"locality"
},
  "geometry": {"coordinates":[88.52448000000003,25.19803],"type":"Point"}
}