{
  "type": "Feature",
  "properties": {
    "gn:admin1_code":"81",
    "gn:admin2_code":"3026.0",
    "gn:admin3_code":"302672.0",
    "gn:admin4_code":"30267289.0",
    "gn:asciiname":"Chandulia",
    "gn:country_code":"BD",
    "gn:dem":11,
    "gn:feature_class":"P",
    "gn:feature_code":"PPL",
    "gn:name":"Ch\u0101ndulia",
    "gn:population":0,
    "gn:timezone":"Asia/Dhaka",
    "iso:country":"BD",
    "wof:name":"Chandulia",
    "wof:placetype":"locality"
},
  "geometry": {"coordinates":[90.28191,23.79658],"type":"Point"}
}