{
  "type": "Feature",
  "properties": {
    "gn:admin1_code":"82",
    "gn:admin2_code":"4018.0",
    "gn:admin3_code":"401855.0",
    "gn:admin4_code":"40185557.0",
    "gn:asciiname":"Hariharnagar",
    "gn:country_code":"BD",
    "gn:dem":15,
    "gn:feature_class":"P",
    "gn:feature_code":"PPL",
    "gn:name":"Hariharnagar",
    "gn:population":0,
    "gn:timezone":"Asia/Dhaka",
    "iso:country":"BD",
    "name:ben_x_preferred":[
        "Hariharnagar"
    ],
    "wof:name":"Hariharnagar",
    "wof:placetype":"locality"
},
  "geometry": {"coordinates":[88.75875000000001,23.40282],"type":"Point"}
}