{
  "type": "Feature",
  "properties": {
    "gn:admin1_code":"81",
    "gn:admin2_code":"3026",
    "gn:admin3_code":"302614.0",
    "gn:admin4_code":"30261459.0",
    "gn:asciiname":"Qasimnagar",
    "gn:country_code":"BD",
    "gn:dem":15,
    "gn:feature_class":"P",
    "gn:feature_code":"PPL",
    "gn:name":"Q\u0101simnagar",
    "gn:population":0,
    "gn:timezone":"Asia/Dhaka",
    "iso:country":"BD",
    "name:und_x_variant":[
        "Q\u0101simnagar",
        "K\u0101simnagar"
    ],
    "wof:name":"Qasimnagar",
    "wof:placetype":"locality"
},
  "geometry": {"coordinates":[90.09121,23.97575],"type":"Point"}
}