{
  "type": "Feature",
  "properties": {
    "gn:admin1_code":"82",
    "gn:admin2_code":"4087.0",
    "gn:admin3_code":"408786.0",
    "gn:admin4_code":"40878639.0",
    "gn:asciiname":"Bheirabnagar",
    "gn:country_code":"BD",
    "gn:dem":4,
    "gn:feature_class":"P",
    "gn:feature_code":"PPL",
    "gn:name":"Bheirabnagar",
    "gn:population":0,
    "gn:timezone":"Asia/Dhaka",
    "iso:country":"BD",
    "name:ben_x_preferred":[
        "Bheirabnagar"
    ],
    "wof:name":"Bheirabnagar",
    "wof:placetype":"locality"
},
  "geometry": {"coordinates":[89.09611,22.26057],"type":"Point"}
}