{
  "type": "Feature",
  "properties": {
    "gn:admin1_code":"82",
    "gn:admin2_code":"4087",
    "gn:admin3_code":"408747.0",
    "gn:admin4_code":"40874779.0",
    "gn:asciiname":"Ichhapur",
    "gn:country_code":"BD",
    "gn:dem":7,
    "gn:feature_class":"P",
    "gn:feature_code":"PPL",
    "gn:name":"Ichh\u0101pur",
    "gn:population":0,
    "gn:timezone":"Asia/Dhaka",
    "iso:country":"BD",
    "wof:name":"Ichhapur",
    "wof:placetype":"locality"
},
  "geometry": {"coordinates":[89.03553000000002,22.51775],"type":"Point"}
}