{
  "type": "Feature",
  "properties": {
    "gn:admin1_code":"82",
    "gn:admin2_code":"4047",
    "gn:admin3_code":"404764.0",
    "gn:admin4_code":"40476489.0",
    "gn:asciiname":"Par Bayar Jhapa",
    "gn:country_code":"BD",
    "gn:dem":2,
    "gn:feature_class":"P",
    "gn:feature_code":"PPL",
    "gn:name":"P\u0101r Bay\u0101r Jh\u0101pa",
    "gn:population":0,
    "gn:timezone":"Asia/Dhaka",
    "iso:country":"BD",
    "name:und_x_variant":[
        "Par Boyarjhapa",
        "P\u0101r Bay\u0101r Jh\u0101pa"
    ],
    "wof:name":"Par Bayar Jhapa",
    "wof:placetype":"locality"
},
  "geometry": {"coordinates":[89.39825,22.56078],"type":"Point"}
}