{
  "type": "Feature",
  "properties": {
    "gn:admin1_code":"83",
    "gn:admin2_code":"5069.0",
    "gn:admin3_code":"506909.0",
    "gn:admin4_code":"50690957.0",
    "gn:asciiname":"Chak Goas",
    "gn:country_code":"BD",
    "gn:dem":22,
    "gn:feature_class":"P",
    "gn:feature_code":"PPL",
    "gn:name":"Chak Go\u0101s",
    "gn:population":0,
    "gn:timezone":"Asia/Dhaka",
    "iso:country":"BD",
    "name:ben_x_preferred":[
        "Chak Go\u0101s"
    ],
    "wof:name":"Chak Goas",
    "wof:placetype":"locality"
},
  "geometry": {"coordinates":[88.92956,24.30581],"type":"Point"}
}