{
  "type": "Feature",
  "properties": {
    "gn:admin1_code":"83",
    "gn:admin2_code":"5064",
    "gn:admin3_code":"506460.0",
    "gn:admin4_code":"50646094.0",
    "gn:asciiname":"Ulipur",
    "gn:country_code":"BD",
    "gn:dem":20,
    "gn:feature_class":"P",
    "gn:feature_code":"PPL",
    "gn:name":"Ulipur",
    "gn:population":0,
    "gn:timezone":"Asia/Dhaka",
    "iso:country":"BD",
    "name:ben_x_preferred":[
        "Ulipur"
    ],
    "name:ben_x_variant":[
        "Olipur"
    ],
    "wof:name":"Ulipur",
    "wof:placetype":"locality"
},
  "geometry": {"coordinates":[88.99462,24.88593],"type":"Point"}
}