{
  "type": "Feature",
  "properties": {
    "gn:admin1_code":"82",
    "gn:admin2_code":"4044.0",
    "gn:admin3_code":"404433.0",
    "gn:admin4_code":"40443374.0",
    "gn:asciiname":"Megar Khirda",
    "gn:country_code":"BD",
    "gn:dem":14,
    "gn:feature_class":"P",
    "gn:feature_code":"PPL",
    "gn:name":"Megar Khirda",
    "gn:population":0,
    "gn:timezone":"Asia/Dhaka",
    "iso:country":"BD",
    "name:ben_x_preferred":[
        "Megar Khirda"
    ],
    "wof:name":"Megar Khirda",
    "wof:placetype":"locality"
},
  "geometry": {"coordinates":[89.15813,23.36879],"type":"Point"}
}