{
  "type": "Feature",
  "properties": {
    "gn:admin1_code":"82",
    "gn:admin2_code":"4050.0",
    "gn:admin3_code":"405039.0",
    "gn:admin4_code":"40503967.0",
    "gn:asciiname":"Satgacha",
    "gn:country_code":"BD",
    "gn:dem":16,
    "gn:feature_class":"P",
    "gn:feature_code":"PPL",
    "gn:name":"S\u0101tgacha",
    "gn:population":0,
    "gn:timezone":"Asia/Dhaka",
    "iso:country":"BD",
    "name:ben_x_preferred":[
        "S\u0101tgacha"
    ],
    "wof:name":"Satgacha",
    "wof:placetype":"locality"
},
  "geometry": {"coordinates":[88.95501,23.98409],"type":"Point"}
}