{
  "type": "Feature",
  "properties": {
    "gn:admin1_code":"82",
    "gn:asciiname":"Golkhali",
    "gn:country_code":"BD",
    "gn:dem":9,
    "gn:feature_class":"P",
    "gn:feature_code":"PPL",
    "gn:name":"Golkhali",
    "gn:population":0,
    "gn:timezone":"Asia/Dhaka",
    "iso:country":"BD",
    "name:ben_x_preferred":[
        "Golkhali"
    ],
    "wof:name":"Golkhali",
    "wof:placetype":"locality"
},
  "geometry": {"coordinates":[90.38041,22.16181],"type":"Point"}
}