{
  "type": "Feature",
  "properties": {
    "gn:admin1_code":"81",
    "gn:admin2_code":"3026",
    "gn:admin3_code":"302662.0",
    "gn:admin4_code":"30266227.0",
    "gn:asciiname":"Maliail",
    "gn:country_code":"BD",
    "gn:dem":11,
    "gn:feature_class":"P",
    "gn:feature_code":"PPL",
    "gn:name":"M\u0101li\u0101il",
    "gn:population":0,
    "gn:timezone":"Asia/Dhaka",
    "iso:country":"BD",
    "wof:name":"Maliail",
    "wof:placetype":"locality"
},
  "geometry": {"coordinates":[90.21026999999999,23.6636],"type":"Point"}
}