{
  "type": "Feature",
  "properties": {
    "gn:admin1_code":"87",
    "gn:admin2_code":"5594.0",
    "gn:admin3_code":"559486.0",
    "gn:admin4_code":"55948679.0",
    "gn:asciiname":"Gorkai",
    "gn:country_code":"BD",
    "gn:dem":46,
    "gn:feature_class":"P",
    "gn:feature_code":"PPL",
    "gn:name":"Gorkai",
    "gn:population":0,
    "gn:timezone":"Asia/Dhaka",
    "iso:country":"BD",
    "name:ben_x_preferred":[
        "Gorkai"
    ],
    "wof:name":"Gorkai",
    "wof:placetype":"locality"
},
  "geometry": {"coordinates":[88.2239,25.9698],"type":"Point"}
}