{
  "type": "Feature",
  "properties": {
    "gn:admin1_code":"83",
    "gn:admin2_code":"5064.0",
    "gn:admin3_code":"506469.0",
    "gn:admin4_code":"50646973.0",
    "gn:asciiname":"Purohit",
    "gn:country_code":"BD",
    "gn:dem":43,
    "gn:feature_class":"P",
    "gn:feature_code":"PPL",
    "gn:name":"Purohit",
    "gn:population":0,
    "gn:timezone":"Asia/Dhaka",
    "iso:country":"BD",
    "name:ben_x_preferred":[
        "Purohit"
    ],
    "name:fra_x_preferred":[
        "Purohita"
    ],
    "name:hin_x_preferred":[
        "\u092a\u0941\u0930\u094b\u0939\u093f\u0924"
    ],
    "name:nep_x_preferred":[
        "\u092a\u0941\u0930\u094b\u0939\u093f\u0924"
    ],
    "name:spa_x_preferred":[
        "Purohita"
    ],
    "name:tam_x_preferred":[
        "\u0baa\u0bc1\u0bb0\u0bcb\u0b95\u0bbf\u0ba4\u0bb0\u0bcd"
    ],
    "name:tel_x_preferred":[
        "\u0c2a\u0c41\u0c30\u0c4b\u0c39\u0c3f\u0c24\u0c41\u0c21\u0c41"
    ],
    "wof:name":"Purohit",
    "wof:placetype":"locality"
},
  "geometry": {"coordinates":[88.46409,24.84366],"type":"Point"}
}