{
  "type": "Feature",
  "properties": {
    "gn:admin1_code":"85",
    "gn:admin2_code":"1006",
    "gn:admin3_code":"100651.0",
    "gn:admin4_code":"10065194.0",
    "gn:asciiname":"Patang",
    "gn:country_code":"BD",
    "gn:dem":9,
    "gn:feature_class":"P",
    "gn:feature_code":"PPL",
    "gn:name":"Pat\u0101ng",
    "gn:population":0,
    "gn:timezone":"Asia/Dhaka",
    "iso:country":"BD",
    "wof:name":"Patang",
    "wof:placetype":"locality"
},
  "geometry": {"coordinates":[90.46733999999999,22.6671],"type":"Point"}
}