{
  "type": "Feature",
  "properties": {
    "gn:admin1_code":"87",
    "gn:admin2_code":"5585",
    "gn:admin3_code":"558576.0",
    "gn:admin4_code":"55857656.0",
    "gn:asciiname":"Mithipur",
    "gn:country_code":"BD",
    "gn:dem":29,
    "gn:feature_class":"P",
    "gn:feature_code":"PPL",
    "gn:name":"Mithipur",
    "gn:population":0,
    "gn:timezone":"Asia/Dhaka",
    "iso:country":"BD",
    "name:und_x_variant":[
        "Mith\u0101pur"
    ],
    "wof:name":"Mithipur",
    "wof:placetype":"locality"
},
  "geometry": {"coordinates":[89.36117,25.43499],"type":"Point"}
}