{
  "type": "Feature",
  "properties": {
    "gn:admin1_code":"81",
    "gn:admin2_code":"3093",
    "gn:admin3_code":"309323.0",
    "gn:admin4_code":"30932347.0",
    "gn:asciiname":"Musuria",
    "gn:country_code":"BD",
    "gn:dem":16,
    "gn:feature_class":"P",
    "gn:feature_code":"PPL",
    "gn:name":"Musuria",
    "gn:population":0,
    "gn:timezone":"Asia/Dhaka",
    "iso:country":"BD",
    "wof:name":"Musuria",
    "wof:placetype":"locality"
},
  "geometry": {"coordinates":[89.92107,24.15105],"type":"Point"}
}