{
  "type": "Feature",
  "properties": {
    "gn:admin1_code":"83",
    "gn:admin2_code":"5064.0",
    "gn:admin3_code":"506486.0",
    "gn:admin4_code":"50648694.0",
    "gn:asciiname":"Khuthapara",
    "gn:country_code":"BD",
    "gn:dem":26,
    "gn:feature_class":"P",
    "gn:feature_code":"PPL",
    "gn:name":"Khuth\u0101p\u0101ra",
    "gn:population":0,
    "gn:timezone":"Asia/Dhaka",
    "iso:country":"BD",
    "name:ben_x_preferred":[
        "Khuth\u0101p\u0101ra"
    ],
    "wof:name":"Khuthapara",
    "wof:placetype":"locality"
},
  "geometry": {"coordinates":[88.59774,25.04512],"type":"Point"}
}