{
  "type": "Feature",
  "properties": {
    "gn:admin1_code":"81",
    "gn:admin2_code":"3026.0",
    "gn:admin3_code":"302640.0",
    "gn:admin4_code":"30264058.0",
    "gn:asciiname":"Enayetganj",
    "gn:country_code":"BD",
    "gn:dem":13,
    "gn:feature_class":"P",
    "gn:feature_code":"PPL",
    "gn:name":"En\u0101yetganj",
    "gn:population":0,
    "gn:timezone":"Asia/Dhaka",
    "iso:country":"BD",
    "wof:name":"Enayetganj",
    "wof:placetype":"locality"
},
  "geometry": {"coordinates":[90.37223,23.72563],"type":"Point"}
}