{
  "type": "Feature",
  "properties": {
    "gn:admin1_code":"81",
    "gn:admin2_code":"3056.0",
    "gn:admin3_code":"305628.0",
    "gn:admin4_code":"30562865.0",
    "gn:asciiname":"Gopinathdi",
    "gn:country_code":"BD",
    "gn:dem":9,
    "gn:feature_class":"P",
    "gn:feature_code":"PPL",
    "gn:name":"Gopin\u0101thdi",
    "gn:population":0,
    "gn:timezone":"Asia/Dhaka",
    "iso:country":"BD",
    "wof:name":"Gopinathdi",
    "wof:placetype":"locality"
},
  "geometry": {"coordinates":[90.02011,23.7263],"type":"Point"}
}