{
  "type": "Feature",
  "properties": {
    "gn:admin1_code":"87",
    "gn:admin2_code":"5527.0",
    "gn:admin3_code":"552756.0",
    "gn:admin4_code":"55275694.0",
    "gn:asciiname":"Daulatpur",
    "gn:country_code":"BD",
    "gn:dem":43,
    "gn:feature_class":"P",
    "gn:feature_code":"PPL",
    "gn:name":"Daulatpur",
    "gn:population":0,
    "gn:timezone":"Asia/Dhaka",
    "iso:country":"BD",
    "name:ben_x_preferred":[
        "Daulatpur"
    ],
    "name:ben_x_variant":[
        "\u09a6\u09cc\u09b2\u09a4\u09aa\u09c1\u09b0"
    ],
    "name:bpy_x_preferred":[
        "\u09a6\u09cc\u09b2\u09a4\u09aa\u09c1\u09b0"
    ],
    "name:ceb_x_preferred":[
        "Daulatpur"
    ],
    "name:fra_x_preferred":[
        "Daulatpur"
    ],
    "name:ita_x_preferred":[
        "Daulatpur"
    ],
    "name:nld_x_preferred":[
        "Daulatpur"
    ],
    "name:pol_x_preferred":[
        "Daulatpur"
    ],
    "name:swe_x_preferred":[
        "Daulatpur"
    ],
    "name:zho_x_preferred":[
        "\u8fbe\u4e4c\u62c9\u7279\u666e\u5c14"
    ],
    "wof:name":"Daulatpur",
    "wof:placetype":"locality"
},
  "geometry": {"coordinates":[88.56971999999998,25.78493],"type":"Point"}
}