{
  "type": "Feature",
  "properties": {
    "gn:admin1_code":"86",
    "gn:admin2_code":"6036.0",
    "gn:admin3_code":"603668.0",
    "gn:admin4_code":"60366813.0",
    "gn:asciiname":"Bamai",
    "gn:country_code":"BD",
    "gn:dem":12,
    "gn:feature_class":"P",
    "gn:feature_code":"PPL",
    "gn:name":"Bamai",
    "gn:population":0,
    "gn:timezone":"Asia/Dhaka",
    "iso:country":"BD",
    "name:und_x_variant":[
        "Bamoi",
        "Bamai"
    ],
    "wof:name":"Bamai",
    "wof:placetype":"locality"
},
  "geometry": {"coordinates":[91.25824,24.28611],"type":"Point"}
}