{
  "type": "Feature",
  "properties": {
    "gn:admin1_code":"H",
    "gn:admin2_code":"3061.0",
    "gn:admin3_code":"306165.0",
    "gn:admin4_code":"30616534.0",
    "gn:asciiname":"Ghayaspur",
    "gn:country_code":"BD",
    "gn:dem":19,
    "gn:feature_class":"P",
    "gn:feature_code":"PPL",
    "gn:name":"Ghay\u0101spur",
    "gn:population":0,
    "gn:timezone":"Asia/Dhaka",
    "iso:country":"BD",
    "name:und_x_variant":[
        "Ghay\u0101spur",
        "Gayespur"
    ],
    "wof:name":"Ghayaspur",
    "wof:placetype":"locality"
},
  "geometry": {"coordinates":[90.13982,24.75501],"type":"Point"}
}