{
  "type": "Feature",
  "properties": {
    "gn:admin1_code":"83",
    "gn:admin2_code":"5070",
    "gn:admin3_code":"507056.0",
    "gn:admin4_code":"50705676.0",
    "gn:asciiname":"Padchakandar",
    "gn:country_code":"BD",
    "gn:dem":45,
    "gn:feature_class":"P",
    "gn:feature_code":"PPL",
    "gn:name":"Padch\u0101kandar",
    "gn:population":0,
    "gn:timezone":"Asia/Dhaka",
    "iso:country":"BD",
    "name:ben_x_preferred":[
        "Padch\u0101kandar"
    ],
    "name:ben_x_variant":[
        "Pach\u0101kandar"
    ],
    "name:und_x_variant":[
        "Bach\u0101kandar"
    ],
    "wof:name":"Padchakandar",
    "wof:placetype":"locality"
},
  "geometry": {"coordinates":[88.41483000000002,24.66438],"type":"Point"}
}