{
  "type": "Feature",
  "properties": {
    "gn:admin1_code":"81",
    "gn:admin2_code":"3093",
    "gn:admin3_code":"309366.0",
    "gn:admin4_code":"30936663.0",
    "gn:asciiname":"Jamurki",
    "gn:country_code":"BD",
    "gn:dem":15,
    "gn:feature_class":"P",
    "gn:feature_code":"PPL",
    "gn:name":"J\u0101murki",
    "gn:population":0,
    "gn:timezone":"Asia/Dhaka",
    "iso:country":"BD",
    "wof:name":"Jamurki",
    "wof:placetype":"locality"
},
  "geometry": {"coordinates":[90.02176999999998,24.14792000000001],"type":"Point"}
}