{
  "type": "Feature",
  "properties": {
    "gn:admin1_code":"H",
    "gn:admin2_code":"3072.0",
    "gn:admin3_code":"307256.0",
    "gn:admin4_code":"30725684.0",
    "gn:asciiname":"Bagajan",
    "gn:country_code":"BD",
    "gn:dem":15,
    "gn:feature_class":"P",
    "gn:feature_code":"PPL",
    "gn:name":"B\u0101g\u0101j\u0101n",
    "gn:population":0,
    "gn:timezone":"Asia/Dhaka",
    "iso:country":"BD",
    "wof:name":"Bagajan",
    "wof:placetype":"locality"
},
  "geometry": {"coordinates":[90.94587,24.68501],"type":"Point"}
}