{
  "type": "Feature",
  "properties": {
    "gn:admin1_code":"84",
    "gn:admin2_code":"2051",
    "gn:admin3_code":"205143.0",
    "gn:admin4_code":"20514390.0",
    "gn:asciiname":"Jehanabad",
    "gn:country_code":"BD",
    "gn:dem":17,
    "gn:feature_class":"P",
    "gn:feature_code":"PPL",
    "gn:name":"Jehanabad",
    "gn:population":0,
    "gn:timezone":"Asia/Dhaka",
    "iso:country":"BD",
    "name:und_x_variant":[
        "J\u0101h\u0101n\u0101b\u0101d"
    ],
    "wof:name":"Jehanabad",
    "wof:placetype":"locality"
},
  "geometry": {"coordinates":[90.83099,22.98532],"type":"Point"}
}