{
  "type": "Feature",
  "properties": {
    "gn:admin1_code":"84",
    "gn:admin2_code":"2051",
    "gn:admin3_code":"205143.0",
    "gn:admin4_code":"20514390.0",
    "gn:asciiname":"Jehanabad",
    "gn:country_code":"BD",
    "gn:dem":17,
    "gn:feature_class":"P",
    "gn:feature_code":"PPL",
    "gn:name":"Jehanabad",
    "gn:population":0,
    "gn:timezone":"Asia/Dhaka",
    "iso:country":"BD",
    "name:ara_x_preferred":[
        "\u062c\u064a\u0647\u0627\u0646 \u0623\u0628\u0627\u062f"
    ],
    "name:ben_x_preferred":[
        "\u099c\u09c7\u09b9\u09be\u09a8\u09be\u09ac\u09be\u09a6"
    ],
    "name:bih_x_preferred":[
        "\u091c\u0939\u093e\u0928\u093e\u092c\u093e\u0926"
    ],
    "name:bpy_x_preferred":[
        "\u099c\u09c7\u09b9\u09be\u09a8\u09be\u09ac\u09be\u09a6"
    ],
    "name:cat_x_preferred":[
        "Jahanabad"
    ],
    "name:fas_x_preferred":[
        "\u062c\u0647\u0627\u0646\u200c\u0622\u0628\u0627\u062f"
    ],
    "name:fra_x_preferred":[
        "Jehanabad"
    ],
    "name:hif_x_preferred":[
        "Jehanabad"
    ],
    "name:hin_x_preferred":[
        "\u091c\u0939\u093e\u0928\u093e\u092c\u093e\u0926"
    ],
    "name:ita_x_preferred":[
        "Jehanabad"
    ],
    "name:mar_x_preferred":[
        "\u091c\u0939\u093e\u0928\u093e\u092c\u093e\u0926"
    ],
    "name:mlg_x_preferred":[
        "Jehanabad"
    ],
    "name:msa_x_preferred":[
        "Jehanabad"
    ],
    "name:new_x_preferred":[
        "\u091c\u0939\u093e\u0928\u093e\u092c\u093e\u0926"
    ],
    "name:ori_x_preferred":[
        "\u0b1c\u0b47\u0b39\u0b3e\u0b28\u0b3e\u0b2c\u0b3e\u0b26"
    ],
    "name:por_x_preferred":[
        "Jehanabad"
    ],
    "name:rus_x_preferred":[
        "\u0414\u0436\u0435\u0445\u0430\u043d\u0430\u0431\u0430\u0434"
    ],
    "name:san_x_preferred":[
        "\u091c\u0939\u093e\u0928\u093e\u092c\u093e\u0926\u0928\u0917\u0930\u092e\u094d"
    ],
    "name:spa_x_preferred":[
        "Jehanabad"
    ],
    "name:swe_x_preferred":[
        "Jehanabad"
    ],
    "name:und_x_variant":[
        "J\u0101h\u0101n\u0101b\u0101d"
    ],
    "name:urd_x_preferred":[
        "\u062c\u06c1\u0627\u0646 \u0622\u0628\u0627\u062f"
    ],
    "name:vie_x_preferred":[
        "Jehanabad"
    ],
    "name:xmf_x_preferred":[
        "\u10ef\u10d4\u10f0\u10d0\u10dc\u10d0\u10d1\u10d0\u10d3\u10d8"
    ],
    "name:zho_x_preferred":[
        "\u6770\u54c8\u7eb3\u5df4\u5fb7"
    ],
    "wof:name":"Jehanabad",
    "wof:placetype":"locality"
},
  "geometry": {"coordinates":[90.83099,22.98532],"type":"Point"}
}