{
  "type": "Feature",
  "properties": {
    "gn:admin1_code":"81",
    "gn:admin2_code":"3048.0",
    "gn:admin3_code":"304879.0",
    "gn:admin4_code":"30487957.0",
    "gn:asciiname":"Char Lakshmi",
    "gn:country_code":"BD",
    "gn:dem":16,
    "gn:feature_class":"P",
    "gn:feature_code":"PPL",
    "gn:name":"Char Lakshmi",
    "gn:population":0,
    "gn:timezone":"Asia/Dhaka",
    "iso:country":"BD",
    "wof:name":"Char Lakshmi",
    "wof:placetype":"locality"
},
  "geometry": {"coordinates":[90.64444,24.36354],"type":"Point"}
}