{
  "type": "Feature",
  "properties": {
    "gn:admin1_code":"81",
    "gn:admin2_code":"3054",
    "gn:admin3_code":"305454.0",
    "gn:admin4_code":"30545494.0",
    "gn:asciiname":"Kalima",
    "gn:country_code":"BD",
    "gn:dem":9,
    "gn:feature_class":"P",
    "gn:feature_code":"PPL",
    "gn:name":"Kalima",
    "gn:population":0,
    "gn:timezone":"Asia/Dhaka",
    "iso:country":"BD",
    "name:ceb_x_preferred":[
        "Kalima"
    ],
    "name:deu_x_preferred":[
        "Kalima"
    ],
    "name:epo_x_preferred":[
        "Kalima"
    ],
    "name:fin_x_preferred":[
        "Kalima"
    ],
    "name:pol_x_preferred":[
        "Kalima"
    ],
    "name:swe_x_preferred":[
        "Kalima"
    ],
    "wof:name":"Kalima",
    "wof:placetype":"locality"
},
  "geometry": {"coordinates":[90.12425,23.23634],"type":"Point"}
}