{
  "type": "Feature",
  "properties": {
    "gn:admin1_code":"81",
    "gn:admin2_code":"3054",
    "gn:admin3_code":"305454.0",
    "gn:admin4_code":"30545494.0",
    "gn:asciiname":"Kalima",
    "gn:country_code":"BD",
    "gn:dem":9,
    "gn:feature_class":"P",
    "gn:feature_code":"PPL",
    "gn:name":"Kalima",
    "gn:population":0,
    "gn:timezone":"Asia/Dhaka",
    "iso:country":"BD",
    "name:ben_x_preferred":[
        "\u0995\u09be\u09b2\u09bf\u09ae\u09be"
    ],
    "name:ceb_x_preferred":[
        "Kalima"
    ],
    "name:deu_x_preferred":[
        "Kalima"
    ],
    "name:ell_x_preferred":[
        "\u039a\u03b1\u03bb\u03af\u03bc\u03b1"
    ],
    "name:epo_x_preferred":[
        "Kalima"
    ],
    "name:fas_x_preferred":[
        "\u06a9\u0644\u06cc\u0645\u0627"
    ],
    "name:fin_x_preferred":[
        "Kalima"
    ],
    "name:heb_x_preferred":[
        "\u05e7\u05dc\u05d9\u05de\u05d4"
    ],
    "name:hin_x_preferred":[
        "\u0915\u0932\u0940\u092e\u093e"
    ],
    "name:ind_x_preferred":[
        "Kalima"
    ],
    "name:ita_x_preferred":[
        "Kalima"
    ],
    "name:kor_x_preferred":[
        "\uce7c\ub9ac\ub9c8"
    ],
    "name:pol_x_preferred":[
        "Kalima"
    ],
    "name:swe_x_preferred":[
        "Kalima"
    ],
    "name:tur_x_preferred":[
        "Kalima"
    ],
    "name:urd_x_preferred":[
        "\u06a9\u0627\u0644\u06cc\u0645\u0627"
    ],
    "name:vie_x_preferred":[
        "Kalima"
    ],
    "name:zho_cn_x_preferred":[
        "\u5361\u5229\u9a6c"
    ],
    "name:zho_tw_x_preferred":[
        "\u5361\u5229\u99ac"
    ],
    "wof:name":"Kalima",
    "wof:placetype":"locality"
},
  "geometry": {"coordinates":[90.12425,23.23634],"type":"Point"}
}