{
  "type": "Feature",
  "properties": {
    "gn:admin1_code":"84",
    "gn:admin2_code":"2084.0",
    "gn:admin3_code":"208425.0",
    "gn:admin4_code":"20842519.0",
    "gn:asciiname":"Lungjipara",
    "gn:country_code":"BD",
    "gn:dem":66,
    "gn:feature_class":"P",
    "gn:feature_code":"PPL",
    "gn:name":"Lungjip\u0101ra",
    "gn:population":0,
    "gn:timezone":"Asia/Dhaka",
    "iso:country":"BD",
    "name:ben_x_preferred":[
        "Lungjip\u0101ra"
    ],
    "wof:name":"Lungjipara",
    "wof:placetype":"locality"
},
  "geometry": {"coordinates":[91.98813,22.50273],"type":"Point"}
}