{
  "type": "Feature",
  "properties": {
    "gn:admin1_code":"84",
    "gn:admin2_code":"2051",
    "gn:admin3_code":"205143.0",
    "gn:admin4_code":"20514320.0",
    "gn:asciiname":"Panchpara",
    "gn:country_code":"BD",
    "gn:dem":12,
    "gn:feature_class":"P",
    "gn:feature_code":"PPL",
    "gn:name":"P\u0101nchp\u0101ra",
    "gn:population":0,
    "gn:timezone":"Asia/Dhaka",
    "iso:country":"BD",
    "wof:name":"Panchpara",
    "wof:placetype":"locality"
},
  "geometry": {"coordinates":[90.97338000000001,22.96944],"type":"Point"}
}