{
  "type": "Feature",
  "properties": {
    "gn:admin1_code":"84",
    "gn:admin2_code":"2051",
    "gn:admin3_code":"205143.0",
    "gn:admin4_code":"20514320.0",
    "gn:asciiname":"Panchpara",
    "gn:country_code":"BD",
    "gn:dem":12,
    "gn:feature_class":"P",
    "gn:feature_code":"PPL",
    "gn:name":"P\u0101nchp\u0101ra",
    "gn:population":0,
    "gn:timezone":"Asia/Dhaka",
    "iso:country":"BD",
    "name:ben_x_preferred":[
        "\u09aa\u09be\u0981\u099a\u09aa\u09be\u09a1\u09bc\u09be"
    ],
    "name:bpy_x_preferred":[
        "\u09aa\u09be\u0981\u099a\u09aa\u09be\u09a1\u09bc\u09be"
    ],
    "name:hif_x_preferred":[
        "Panchpara"
    ],
    "name:ita_x_preferred":[
        "Panchpara"
    ],
    "name:msa_x_preferred":[
        "Panchpara"
    ],
    "name:nld_x_preferred":[
        "Panchpara"
    ],
    "name:por_x_preferred":[
        "Panchpara"
    ],
    "name:vie_x_preferred":[
        "Panchpara"
    ],
    "name:zho_x_preferred":[
        "\u6f58\u5947\u5e15\u62c9"
    ],
    "wof:name":"Panchpara",
    "wof:placetype":"locality"
},
  "geometry": {"coordinates":[90.97338000000001,22.96944],"type":"Point"}
}