{
  "type": "Feature",
  "properties": {
    "gn:admin1_code":"85",
    "gn:admin2_code":"1006.0",
    "gn:admin3_code":"100603.0",
    "gn:admin4_code":"10060313.0",
    "gn:asciiname":"Char Jahapur",
    "gn:country_code":"BD",
    "gn:dem":14,
    "gn:feature_class":"P",
    "gn:feature_code":"PPL",
    "gn:name":"Char J\u0101h\u0101pur",
    "gn:population":0,
    "gn:timezone":"Asia/Dhaka",
    "iso:country":"BD",
    "name:und_x_variant":[
        "Char J\u0101h\u0101pur"
    ],
    "wof:name":"Char Jahapur",
    "wof:placetype":"locality"
},
  "geometry": {"coordinates":[90.33677,22.91258],"type":"Point"}
}