{
  "type": "Feature",
  "properties": {
    "gn:admin1_code":"84",
    "gn:admin2_code":"2022",
    "gn:admin3_code":"202249.0",
    "gn:admin4_code":"20224935.0",
    "gn:asciiname":"Maheshkhali",
    "gn:country_code":"BD",
    "gn:dem":8,
    "gn:feature_class":"P",
    "gn:feature_code":"PPL",
    "gn:name":"Maheshkh\u0101li",
    "gn:population":0,
    "gn:timezone":"Asia/Dhaka",
    "iso:country":"BD",
    "name:ben_x_preferred":[
        "Maheshkh\u0101li"
    ],
    "name:und_x_variant":[
        "Mahesh Khal",
        "Maiskh\u0101l"
    ],
    "wof:name":"Maheshkhali",
    "wof:placetype":"locality"
},
  "geometry": {"coordinates":[91.96953999999999,21.52021],"type":"Point"}
}