{
  "type": "Feature",
  "properties": {
    "gn:admin1_code":"81",
    "gn:admin2_code":"3035.0",
    "gn:admin3_code":"303558.0",
    "gn:admin4_code":"30355816.0",
    "gn:asciiname":"Paraihati",
    "gn:country_code":"BD",
    "gn:dem":7,
    "gn:feature_class":"P",
    "gn:feature_code":"PPL",
    "gn:name":"P\u0101raih\u0101ti",
    "gn:population":0,
    "gn:timezone":"Asia/Dhaka",
    "iso:country":"BD",
    "name:ben_x_preferred":[
        "P\u0101raih\u0101ti"
    ],
    "wof:name":"Paraihati",
    "wof:placetype":"locality"
},
  "geometry": {"coordinates":[89.89184,23.24042],"type":"Point"}
}