{
  "type": "Feature",
  "properties": {
    "gn:admin1_code":"83",
    "gn:admin2_code":"5081",
    "gn:admin3_code":"508112.0",
    "gn:admin4_code":"50811225.0",
    "gn:asciiname":"Paharpur",
    "gn:country_code":"BD",
    "gn:dem":20,
    "gn:feature_class":"P",
    "gn:feature_code":"PPL",
    "gn:name":"P\u0101harpur",
    "gn:population":0,
    "gn:timezone":"Asia/Dhaka",
    "iso:country":"BD",
    "name:ben_x_preferred":[
        "P\u0101harpur"
    ],
    "name:ben_x_variant":[
        "\u09aa\u09be\u09b9\u09be\u09a1\u09bc\u09aa\u09c1\u09b0"
    ],
    "name:ceb_x_preferred":[
        "Paharpur"
    ],
    "name:nld_x_preferred":[
        "Paharpur"
    ],
    "wof:name":"Paharpur",
    "wof:placetype":"locality"
},
  "geometry": {"coordinates":[88.83502,24.6058],"type":"Point"}
}