{
  "type": "Feature",
  "properties": {
    "gn:admin1_code":"87",
    "gn:admin2_code":"5577.0",
    "gn:admin3_code":"557790.0",
    "gn:admin4_code":"55779054.0",
    "gn:asciiname":"Bahmanpara",
    "gn:country_code":"BD",
    "gn:dem":87,
    "gn:feature_class":"P",
    "gn:feature_code":"PPL",
    "gn:name":"B\u0101hmanpara",
    "gn:population":0,
    "gn:timezone":"Asia/Dhaka",
    "iso:country":"BD",
    "name:ben_x_preferred":[
        "B\u0101hmanpara"
    ],
    "wof:name":"Bahmanpara",
    "wof:placetype":"locality"
},
  "geometry": {"coordinates":[88.47019,26.47151],"type":"Point"}
}