{
  "type": "Feature",
  "properties": {
    "gn:admin1_code":"85",
    "gn:admin2_code":"1078.0",
    "gn:admin3_code":"107876.0",
    "gn:admin4_code":"10787654.0",
    "gn:asciiname":"Lebubunia",
    "gn:country_code":"BD",
    "gn:dem":2,
    "gn:feature_class":"P",
    "gn:feature_code":"PPL",
    "gn:name":"Lebubunia",
    "gn:population":0,
    "gn:timezone":"Asia/Dhaka",
    "iso:country":"BD",
    "name:ben_x_preferred":[
        "Lebubunia"
    ],
    "wof:name":"Lebubunia",
    "wof:placetype":"locality"
},
  "geometry": {"coordinates":[90.24648999999999,22.43389],"type":"Point"}
}