{
  "type": "Feature",
  "properties": {
    "gn:admin1_code":"81",
    "gn:admin2_code":"3035",
    "gn:admin3_code":"303551.0",
    "gn:admin4_code":"30355194.0",
    "gn:asciiname":"Jayrampatti",
    "gn:country_code":"BD",
    "gn:dem":8,
    "gn:feature_class":"P",
    "gn:feature_code":"PPL",
    "gn:name":"Jayr\u0101mpatti",
    "gn:population":0,
    "gn:timezone":"Asia/Dhaka",
    "iso:country":"BD",
    "wof:name":"Jayrampatti",
    "wof:placetype":"locality"
},
  "geometry": {"coordinates":[90.05658000000003,22.94731],"type":"Point"}
}