{
  "type": "Feature",
  "properties": {
    "gn:admin1_code":"81",
    "gn:admin2_code":"3067",
    "gn:admin3_code":"306704.0",
    "gn:admin4_code":"30670434.0",
    "gn:asciiname":"Kahena",
    "gn:country_code":"BD",
    "gn:dem":11,
    "gn:feature_class":"P",
    "gn:feature_code":"PPL",
    "gn:name":"K\u0101hena",
    "gn:population":0,
    "gn:timezone":"Asia/Dhaka",
    "iso:country":"BD",
    "wof:name":"Kahena",
    "wof:placetype":"locality"
},
  "geometry": {"coordinates":[90.58087999999999,23.76156],"type":"Point"}
}