{
  "type": "Feature",
  "properties": {
    "gn:admin1_code":"83",
    "gn:admin2_code":"5010.0",
    "gn:admin3_code":"501054.0",
    "gn:admin4_code":"50105466.0",
    "gn:asciiname":"Birpalla",
    "gn:country_code":"BD",
    "gn:dem":22,
    "gn:feature_class":"P",
    "gn:feature_code":"PPL",
    "gn:name":"B\u012brp\u0101lla",
    "gn:population":0,
    "gn:timezone":"Asia/Dhaka",
    "iso:country":"BD",
    "wof:name":"Birpalla",
    "wof:placetype":"locality"
},
  "geometry": {"coordinates":[89.2946,24.82937],"type":"Point"}
}