{
  "type": "Feature",
  "properties": {
    "gn:admin1_code":"83",
    "gn:admin2_code":"5010",
    "gn:admin3_code":"501095.0",
    "gn:admin4_code":"50109510.0",
    "gn:asciiname":"Dighal Kandi",
    "gn:country_code":"BD",
    "gn:dem":23,
    "gn:feature_class":"P",
    "gn:feature_code":"PPL",
    "gn:name":"Dighal Kandi",
    "gn:population":0,
    "gn:timezone":"Asia/Dhaka",
    "iso:country":"BD",
    "name:ben_x_preferred":[
        "Dighal Kandi"
    ],
    "wof:name":"Dighal Kandi",
    "wof:placetype":"locality"
},
  "geometry": {"coordinates":[89.46420000000001,25.011],"type":"Point"}
}