{
  "type": "Feature",
  "properties": {
    "gn:admin1_code":"87",
    "gn:admin2_code":"5527.0",
    "gn:admin3_code":"552756.0",
    "gn:admin4_code":"55275663.0",
    "gn:asciiname":"Kamar Digha",
    "gn:country_code":"BD",
    "gn:dem":45,
    "gn:feature_class":"P",
    "gn:feature_code":"PPL",
    "gn:name":"K\u0101mar Digha",
    "gn:population":0,
    "gn:timezone":"Asia/Dhaka",
    "iso:country":"BD",
    "name:ben_x_preferred":[
        "K\u0101mar Digha"
    ],
    "wof:name":"Kamar Digha",
    "wof:placetype":"locality"
},
  "geometry": {"coordinates":[88.56748,25.85097],"type":"Point"}
}