{
  "type": "Feature",
  "properties": {
    "gn:admin1_code":"87",
    "gn:admin2_code":"5573.0",
    "gn:admin3_code":"557315.0",
    "gn:admin4_code":"55731538.0",
    "gn:asciiname":"Chikanmati",
    "gn:country_code":"BD",
    "gn:dem":56,
    "gn:feature_class":"P",
    "gn:feature_code":"PPL",
    "gn:name":"Chikanm\u0101ti",
    "gn:population":0,
    "gn:timezone":"Asia/Dhaka",
    "iso:country":"BD",
    "name:ben_x_preferred":[
        "Chikanm\u0101ti"
    ],
    "wof:name":"Chikanmati",
    "wof:placetype":"locality"
},
  "geometry": {"coordinates":[88.83481,26.08143],"type":"Point"}
}