{
  "type": "Feature",
  "properties": {
    "gn:admin1_code":"82",
    "gn:admin2_code":"4018.0",
    "gn:admin3_code":"401855.0",
    "gn:admin4_code":"40185538.0",
    "gn:asciiname":"Baidyanathpur",
    "gn:country_code":"BD",
    "gn:dem":17,
    "gn:feature_class":"P",
    "gn:feature_code":"PPL",
    "gn:name":"Baidyanathpur",
    "gn:population":0,
    "gn:timezone":"Asia/Dhaka",
    "iso:country":"BD",
    "name:ben_x_preferred":[
        "Baidyanathpur"
    ],
    "wof:name":"Baidyanathpur",
    "wof:placetype":"locality"
},
  "geometry": {"coordinates":[88.85566,23.41454],"type":"Point"}
}