{
  "type": "Feature",
  "properties": {
    "gn:admin1_code":"87",
    "gn:admin2_code":"5594.0",
    "gn:admin3_code":"559451.0",
    "gn:admin4_code":"55945154.0",
    "gn:asciiname":"Tarbagan",
    "gn:country_code":"BD",
    "gn:dem":41,
    "gn:feature_class":"P",
    "gn:feature_code":"PPL",
    "gn:name":"Tarbagan",
    "gn:population":0,
    "gn:timezone":"Asia/Dhaka",
    "iso:country":"BD",
    "name:ben_x_preferred":[
        "Tarbagan"
    ],
    "wof:name":"Tarbagan",
    "wof:placetype":"locality"
},
  "geometry": {"coordinates":[88.13231,25.83492],"type":"Point"}
}