{
  "type": "Feature",
  "properties": {
    "gn:admin1_code":"82",
    "gn:admin2_code":"4044.0",
    "gn:admin3_code":"404419.0",
    "gn:admin4_code":"40441947.0",
    "gn:asciiname":"Goalbarti",
    "gn:country_code":"BD",
    "gn:dem":14,
    "gn:feature_class":"P",
    "gn:feature_code":"PPL",
    "gn:name":"Goalb\u0101rti",
    "gn:population":0,
    "gn:timezone":"Asia/Dhaka",
    "iso:country":"BD",
    "name:ben_x_preferred":[
        "Goalb\u0101rti"
    ],
    "wof:name":"Goalbarti",
    "wof:placetype":"locality"
},
  "geometry": {"coordinates":[89.11874,23.53556],"type":"Point"}
}