{
  "type": "Feature",
  "properties": {
    "gn:admin1_code":"84",
    "gn:admin2_code":"2019",
    "gn:admin3_code":"201981.0",
    "gn:admin4_code":"20198194.0",
    "gn:asciiname":"Saiyidagope",
    "gn:country_code":"BD",
    "gn:dem":11,
    "gn:feature_class":"P",
    "gn:feature_code":"PPL",
    "gn:name":"Saiyid\u0101gope",
    "gn:population":0,
    "gn:timezone":"Asia/Dhaka",
    "iso:country":"BD",
    "name:und_x_variant":[
        "Sahedagopa",
        "S\u0101yed\u0101gope",
        "Saiyid\u0101gope"
    ],
    "wof:name":"Saiyidagope",
    "wof:placetype":"locality"
},
  "geometry": {"coordinates":[90.96992,23.77376],"type":"Point"}
}