{
  "type": "Feature",
  "properties": {
    "gn:admin1_code":"82",
    "gn:admin2_code":"4018.0",
    "gn:admin3_code":"401807.0",
    "gn:admin4_code":"40180794.0",
    "gn:asciiname":"Marahashi",
    "gn:country_code":"BD",
    "gn:dem":15,
    "gn:feature_class":"P",
    "gn:feature_code":"PPL",
    "gn:name":"Marah\u0101shi",
    "gn:population":0,
    "gn:timezone":"Asia/Dhaka",
    "iso:country":"BD",
    "name:ben_x_preferred":[
        "Marah\u0101shi"
    ],
    "wof:name":"Marahashi",
    "wof:placetype":"locality"
},
  "geometry": {"coordinates":[88.94461,23.63154],"type":"Point"}
}