{
  "type": "Feature",
  "properties": {
    "gn:admin1_code":"82",
    "gn:admin2_code":"4044.0",
    "gn:admin3_code":"404480.0",
    "gn:admin4_code":"40448025.0",
    "gn:asciiname":"Dahaktila",
    "gn:country_code":"BD",
    "gn:dem":18,
    "gn:feature_class":"P",
    "gn:feature_code":"PPL",
    "gn:name":"Dahaktila",
    "gn:population":0,
    "gn:timezone":"Asia/Dhaka",
    "iso:country":"BD",
    "name:ben_x_preferred":[
        "Dahaktila"
    ],
    "wof:name":"Dahaktila",
    "wof:placetype":"locality"
},
  "geometry": {"coordinates":[89.20058,23.68344],"type":"Point"}
}