{
  "type": "Feature",
  "properties": {
    "gn:admin1_code":"83",
    "gn:asciiname":"Katia",
    "gn:country_code":"BD",
    "gn:dem":11,
    "gn:feature_class":"P",
    "gn:feature_code":"PPL",
    "gn:name":"K\u0101tia",
    "gn:population":0,
    "gn:timezone":"Asia/Dhaka",
    "iso:country":"BD",
    "wof:name":"Katia",
    "wof:placetype":"locality"
},
  "geometry": {"coordinates":[91.59798000000001,24.69015],"type":"Point"}
}