{
  "type": "Feature",
  "properties": {
    "gn:admin1_code":"87",
    "gn:admin2_code":"5527",
    "gn:admin3_code":"552743.0",
    "gn:admin4_code":"55274338.0",
    "gn:asciiname":"Nur Jahanpur",
    "gn:country_code":"BD",
    "gn:dem":30,
    "gn:feature_class":"P",
    "gn:feature_code":"PPL",
    "gn:name":"Nur Jahanpur",
    "gn:population":0,
    "gn:timezone":"Asia/Dhaka",
    "iso:country":"BD",
    "name:ben_x_preferred":[
        "Nur Jahanpur"
    ],
    "wof:name":"Nur Jahanpur",
    "wof:placetype":"locality"
},
  "geometry": {"coordinates":[89.28189999999999,25.24493],"type":"Point"}
}