{
  "type": "Feature",
  "properties": {
    "gn:admin1_code":"81",
    "gn:admin2_code":"3026",
    "gn:admin3_code":"302614.0",
    "gn:admin4_code":"30261488.0",
    "gn:asciiname":"Sainpara",
    "gn:country_code":"BD",
    "gn:dem":7,
    "gn:feature_class":"P",
    "gn:feature_code":"PPL",
    "gn:name":"S\u0101inp\u0101ra",
    "gn:population":0,
    "gn:timezone":"Asia/Dhaka",
    "iso:country":"BD",
    "wof:name":"Sainpara",
    "wof:placetype":"locality"
},
  "geometry": {"coordinates":[90.16992,23.86843],"type":"Point"}
}