{
  "type": "Feature",
  "properties": {
    "gn:admin1_code":"83",
    "gn:admin2_code":"5064",
    "gn:admin3_code":"506469.0",
    "gn:admin4_code":"50646984.0",
    "gn:asciiname":"Srimantapur",
    "gn:country_code":"BD",
    "gn:dem":26,
    "gn:feature_class":"P",
    "gn:feature_code":"PPL",
    "gn:name":"Srimantapur",
    "gn:population":0,
    "gn:timezone":"Asia/Dhaka",
    "iso:country":"BD",
    "name:ben_x_preferred":[
        "Srimantapur"
    ],
    "wof:name":"Srimantapur",
    "wof:placetype":"locality"
},
  "geometry": {"coordinates":[88.58256,24.8103],"type":"Point"}
}