{
  "type": "Feature",
  "properties": {
    "gn:admin1_code":"83",
    "gn:admin2_code":"5076",
    "gn:admin3_code":"507633.0",
    "gn:admin4_code":"50763363.0",
    "gn:asciiname":"Moudh",
    "gn:country_code":"BD",
    "gn:dem":12,
    "gn:feature_class":"P",
    "gn:feature_code":"PPL",
    "gn:name":"Moudh",
    "gn:population":0,
    "gn:timezone":"Asia/Dhaka",
    "iso:country":"BD",
    "name:und_x_variant":[
        "Maud",
        "Maudh",
        "Moudh"
    ],
    "wof:name":"Moudh",
    "wof:placetype":"locality"
},
  "geometry": {"coordinates":[89.40165,24.12031],"type":"Point"}
}