{
  "type": "Feature",
  "properties": {
    "gn:admin1_code":"82",
    "gn:admin2_code":"4050.0",
    "gn:admin3_code":"405039.0",
    "gn:admin4_code":"40503913.0",
    "gn:asciiname":"Chhatarpara",
    "gn:country_code":"BD",
    "gn:dem":19,
    "gn:feature_class":"P",
    "gn:feature_code":"PPL",
    "gn:name":"Chhat\u0101rp\u0101ra",
    "gn:population":0,
    "gn:timezone":"Asia/Dhaka",
    "iso:country":"BD",
    "name:ben_x_preferred":[
        "Chhat\u0101rp\u0101ra"
    ],
    "wof:name":"Chhatarpara",
    "wof:placetype":"locality"
},
  "geometry": {"coordinates":[88.90963000000001,23.92845],"type":"Point"}
}