{
  "type": "Feature",
  "properties": {
    "gn:admin1_code":"83",
    "gn:admin2_code":"5064.0",
    "gn:admin3_code":"506447.0",
    "gn:admin4_code":"50644747.0",
    "gn:asciiname":"Chak Balu",
    "gn:country_code":"BD",
    "gn:dem":16,
    "gn:feature_class":"P",
    "gn:feature_code":"PPL",
    "gn:name":"Chak Balu",
    "gn:population":0,
    "gn:timezone":"Asia/Dhaka",
    "iso:country":"BD",
    "name:ben_x_preferred":[
        "Chak Balu"
    ],
    "wof:name":"Chak Balu",
    "wof:placetype":"locality"
},
  "geometry": {"coordinates":[88.78870999999999,24.71127000000001],"type":"Point"}
}