{
  "type": "Feature",
  "properties": {
    "gn:admin1_code":"86",
    "gn:admin2_code":"6091",
    "gn:admin3_code":"609141.0",
    "gn:admin4_code":"60914162.0",
    "gn:asciiname":"Goyainghat",
    "gn:country_code":"BD",
    "gn:dem":16,
    "gn:feature_class":"P",
    "gn:feature_code":"PPL",
    "gn:name":"Goyainghat",
    "gn:population":0,
    "gn:timezone":"Asia/Dhaka",
    "iso:country":"BD",
    "name:und_x_variant":[
        "Goy\u0101in",
        "Goain",
        "Gowainghat",
        "Goyainghat"
    ],
    "wof:name":"Goyainghat",
    "wof:placetype":"locality"
},
  "geometry": {"coordinates":[91.9807,25.09214],"type":"Point"}
}