{
  "type": "Feature",
  "properties": {
    "gn:admin1_code":"84",
    "gn:admin2_code":"2075",
    "gn:admin3_code":"207587.0",
    "gn:admin4_code":"20758775.0",
    "gn:asciiname":"Lakshminarayanpur",
    "gn:cc2":"BD",
    "gn:country_code":"BD",
    "gn:dem":6,
    "gn:feature_class":"P",
    "gn:feature_code":"PPL",
    "gn:name":"Lakshm\u012bn\u0101r\u0101yanpur",
    "gn:population":0,
    "gn:timezone":"Asia/Dhaka",
    "iso:country":"BD",
    "name:und_x_variant":[
        "East Lakshminarayanpur",
        "Lakshm\u012bn\u0101r\u0101yanpur"
    ],
    "wof:name":"Lakshminarayanpur",
    "wof:placetype":"locality"
},
  "geometry": {"coordinates":[91.11667,22.86667000000001],"type":"Point"}
}