{
  "type": "Feature",
  "properties": {
    "gn:admin1_code":"85",
    "gn:admin2_code":"1009.0",
    "gn:admin3_code":"100929.0",
    "gn:admin4_code":"10092928.0",
    "gn:asciiname":"Char Pata",
    "gn:country_code":"BD",
    "gn:dem":10,
    "gn:feature_class":"P",
    "gn:feature_code":"PPL",
    "gn:name":"Char P\u0101ta",
    "gn:population":0,
    "gn:timezone":"Asia/Dhaka",
    "iso:country":"BD",
    "wof:name":"Char Pata",
    "wof:placetype":"locality"
},
  "geometry": {"coordinates":[90.69156,22.62679],"type":"Point"}
}