{
  "type": "Feature",
  "properties": {
    "gn:admin1_code":"87",
    "gn:admin2_code":"5573.0",
    "gn:admin3_code":"557364.0",
    "gn:admin4_code":"55736418.0",
    "gn:asciiname":"Natibari",
    "gn:country_code":"BD",
    "gn:dem":58,
    "gn:feature_class":"P",
    "gn:feature_code":"PPL",
    "gn:name":"Natib\u0101ri",
    "gn:population":0,
    "gn:timezone":"Asia/Dhaka",
    "iso:country":"BD",
    "name:ben_x_preferred":[
        "Natib\u0101ri"
    ],
    "wof:name":"Natibari",
    "wof:placetype":"locality"
},
  "geometry": {"coordinates":[88.78314,26.01172],"type":"Point"}
}