{
  "type": "Feature",
  "properties": {
    "gn:admin1_code":"84",
    "gn:admin2_code":"2075",
    "gn:admin3_code":"207589.0",
    "gn:admin4_code":"20758910.0",
    "gn:asciiname":"Ramdi",
    "gn:country_code":"BD",
    "gn:dem":9,
    "gn:feature_class":"P",
    "gn:feature_code":"PPL",
    "gn:name":"R\u0101mdi",
    "gn:population":0,
    "gn:timezone":"Asia/Dhaka",
    "iso:country":"BD",
    "name:ceb_x_preferred":[
        "Ramdi"
    ],
    "name:mai_x_preferred":[
        "\u0930\u092e\u094d\u0926\u0940"
    ],
    "name:msa_x_preferred":[
        "Ramdi"
    ],
    "name:nep_x_preferred":[
        "\u0930\u092e\u094d\u0926\u0940"
    ],
    "name:new_x_preferred":[
        "\u0930\u093e\u092e\u094d\u0926\u0940"
    ],
    "name:pol_x_preferred":[
        "Ramdi"
    ],
    "wof:name":"Ramdi",
    "wof:placetype":"locality"
},
  "geometry": {"coordinates":[91.23333,22.86667000000001],"type":"Point"}
}