{
  "type": "Feature",
  "properties": {
    "gn:admin1_code":"87",
    "gn:admin2_code":"5549",
    "gn:admin3_code":"554918.0",
    "gn:admin4_code":"55491827.0",
    "gn:asciiname":"Nagarajpur",
    "gn:country_code":"BD",
    "gn:dem":35,
    "gn:feature_class":"P",
    "gn:feature_code":"PPL",
    "gn:name":"Nag\u0101r\u0101jpur",
    "gn:population":0,
    "gn:timezone":"Asia/Dhaka",
    "iso:country":"BD",
    "name:ben_x_preferred":[
        "Nag\u0101r\u0101jpur"
    ],
    "wof:name":"Nagarajpur",
    "wof:placetype":"locality"
},
  "geometry": {"coordinates":[89.63507,25.90654],"type":"Point"}
}