{
  "type": "Feature",
  "properties": {
    "gn:admin1_code":"83",
    "gn:admin2_code":"5081.0",
    "gn:admin3_code":"508131.0",
    "gn:admin4_code":"50813135.0",
    "gn:asciiname":"Sardarpara",
    "gn:country_code":"BD",
    "gn:dem":17,
    "gn:feature_class":"P",
    "gn:feature_code":"PPL",
    "gn:name":"Sardarpara",
    "gn:population":0,
    "gn:timezone":"Asia/Dhaka",
    "iso:country":"BD",
    "name:ben_x_preferred":[
        "Sardarpara"
    ],
    "wof:name":"Sardarpara",
    "wof:placetype":"locality"
},
  "geometry": {"coordinates":[88.73455,24.44039],"type":"Point"}
}