{
  "type": "Feature",
  "properties": {
    "gn:admin1_code":"82",
    "gn:admin2_code":"4087",
    "gn:admin3_code":"408790.0",
    "gn:admin4_code":"40879071.0",
    "gn:asciiname":"Nagarghata",
    "gn:country_code":"BD",
    "gn:dem":9,
    "gn:feature_class":"P",
    "gn:feature_code":"PPL",
    "gn:name":"Nagargh\u0101ta",
    "gn:population":0,
    "gn:timezone":"Asia/Dhaka",
    "iso:country":"BD",
    "wof:name":"Nagarghata",
    "wof:placetype":"locality"
},
  "geometry": {"coordinates":[89.11428000000002,22.77045],"type":"Point"}
}