{
  "type": "Feature",
  "properties": {
    "gn:admin1_code":"82",
    "gn:admin2_code":"4041.0",
    "gn:admin3_code":"404138.0",
    "gn:admin4_code":"40413876.0",
    "gn:asciiname":"Arua",
    "gn:country_code":"BD",
    "gn:dem":7,
    "gn:feature_class":"P",
    "gn:feature_code":"PPL",
    "gn:name":"\u0100rua",
    "gn:population":0,
    "gn:timezone":"Asia/Dhaka",
    "iso:country":"BD",
    "name:bul_x_preferred":[
        "\u0410\u0440\u0443\u0430"
    ],
    "name:ceb_x_preferred":[
        "Arua"
    ],
    "name:dan_x_preferred":[
        "Arua"
    ],
    "name:deu_x_preferred":[
        "Arua"
    ],
    "name:fra_x_preferred":[
        "Arua"
    ],
    "name:hun_x_preferred":[
        "Arua"
    ],
    "name:ita_x_preferred":[
        "Arua"
    ],
    "name:kor_x_preferred":[
        "\uc544\ub8e8\uc544"
    ],
    "name:lit_x_preferred":[
        "Arua"
    ],
    "name:lug_x_preferred":[
        "Arua"
    ],
    "name:nds_x_preferred":[
        "Arua"
    ],
    "name:nld_x_preferred":[
        "Arua"
    ],
    "name:pol_x_preferred":[
        "Arua"
    ],
    "name:por_x_preferred":[
        "Arua"
    ],
    "name:ron_x_preferred":[
        "Arua"
    ],
    "name:rus_x_preferred":[
        "\u0410\u0440\u0443\u0430"
    ],
    "name:swa_x_preferred":[
        "Arua"
    ],
    "name:urd_x_preferred":[
        "\u0627\u0631\u0648\u0627"
    ],
    "name:zho_x_preferred":[
        "\u963f\u9c81\u963f"
    ],
    "wof:name":"Arua",
    "wof:placetype":"locality"
},
  "geometry": {"coordinates":[89.32581999999999,22.90128],"type":"Point"}
}