{
  "type": "Feature",
  "properties": {
    "gn:admin1_code":"82",
    "gn:admin2_code":"4041.0",
    "gn:admin3_code":"404138.0",
    "gn:admin4_code":"40413876.0",
    "gn:asciiname":"Arua",
    "gn:country_code":"BD",
    "gn:dem":7,
    "gn:feature_class":"P",
    "gn:feature_code":"PPL",
    "gn:name":"\u0100rua",
    "gn:population":0,
    "gn:timezone":"Asia/Dhaka",
    "iso:country":"BD",
    "wof:name":"Arua",
    "wof:placetype":"locality"
},
  "geometry": {"coordinates":[89.32581999999999,22.90128],"type":"Point"}
}