{
  "type": "Feature",
  "properties": {
    "gn:admin1_code":"82",
    "gn:admin2_code":"4041.0",
    "gn:admin3_code":"404109.0",
    "gn:admin4_code":"40410909.0",
    "gn:asciiname":"Mahmudpur Taraf",
    "gn:country_code":"BD",
    "gn:dem":13,
    "gn:feature_class":"P",
    "gn:feature_code":"PPL",
    "gn:name":"Mahmudpur Taraf",
    "gn:population":0,
    "gn:timezone":"Asia/Dhaka",
    "iso:country":"BD",
    "name:ben_x_preferred":[
        "Mahmudpur Taraf"
    ],
    "wof:name":"Mahmudpur Taraf",
    "wof:placetype":"locality"
},
  "geometry": {"coordinates":[89.34193,23.17723],"type":"Point"}
}