{
  "type": "Feature",
  "properties": {
    "gn:admin1_code":"85",
    "gn:admin2_code":"1006.0",
    "gn:admin3_code":"100662.0",
    "gn:admin4_code":"10066247.0",
    "gn:asciiname":"Bahir Char",
    "gn:country_code":"BD",
    "gn:dem":4,
    "gn:feature_class":"P",
    "gn:feature_code":"PPL",
    "gn:name":"B\u0101hir Char",
    "gn:population":0,
    "gn:timezone":"Asia/Dhaka",
    "iso:country":"BD",
    "wof:name":"Bahir Char",
    "wof:placetype":"locality"
},
  "geometry": {"coordinates":[90.53333000000001,22.88333],"type":"Point"}
}