{
  "type": "Feature",
  "properties": {
    "gn:admin1_code":"81",
    "gn:admin2_code":"3035.0",
    "gn:admin3_code":"303532.0",
    "gn:admin4_code":"30353277.0",
    "gn:asciiname":"Ghosalkandi",
    "gn:country_code":"BD",
    "gn:dem":9,
    "gn:feature_class":"P",
    "gn:feature_code":"PPL",
    "gn:name":"Ghos\u0101lk\u0101ndi",
    "gn:population":0,
    "gn:timezone":"Asia/Dhaka",
    "iso:country":"BD",
    "name:ben_x_preferred":[
        "Ghos\u0101lk\u0101ndi"
    ],
    "wof:name":"Ghosalkandi",
    "wof:placetype":"locality"
},
  "geometry": {"coordinates":[89.91539,23.09643],"type":"Point"}
}