{
  "type": "Feature",
  "properties": {
    "gn:admin1_code":"81",
    "gn:admin2_code":"3082.0",
    "gn:admin3_code":"308229.0",
    "gn:admin4_code":"30822957.0",
    "gn:asciiname":"Dakshin Dhobaghat",
    "gn:country_code":"BD",
    "gn:dem":15,
    "gn:feature_class":"P",
    "gn:feature_code":"PPL",
    "gn:name":"Dakshin Dhob\u0101gh\u0101t",
    "gn:population":0,
    "gn:timezone":"Asia/Dhaka",
    "iso:country":"BD",
    "name:ben_x_preferred":[
        "Dakshin Dhob\u0101gh\u0101t"
    ],
    "wof:name":"Dakshin Dhobaghat",
    "wof:placetype":"locality"
},
  "geometry": {"coordinates":[89.7475,23.78207],"type":"Point"}
}