{
  "type": "Feature",
  "properties": {
    "gn:admin1_code":"82",
    "gn:admin2_code":"4055",
    "gn:admin3_code":"405557.0",
    "gn:admin4_code":"40555788.0",
    "gn:asciiname":"Ragnaboair",
    "gn:country_code":"BD",
    "gn:dem":12,
    "gn:feature_class":"P",
    "gn:feature_code":"PPL",
    "gn:name":"Ragnaboair",
    "gn:population":0,
    "gn:timezone":"Asia/Dhaka",
    "iso:country":"BD",
    "name:ben_x_preferred":[
        "Ragnaboair"
    ],
    "name:ben_x_variant":[
        "R\u0101ghabd\u0101ir"
    ],
    "wof:name":"Ragnaboair",
    "wof:placetype":"locality"
},
  "geometry": {"coordinates":[89.33865,23.42474],"type":"Point"}
}