{
  "type": "Feature",
  "properties": {
    "gn:admin1_code":"83",
    "gn:admin2_code":"5081.0",
    "gn:admin3_code":"508125.0",
    "gn:admin4_code":"50812547.0",
    "gn:asciiname":"Belgharia",
    "gn:country_code":"BD",
    "gn:dem":24,
    "gn:feature_class":"P",
    "gn:feature_code":"PPL",
    "gn:name":"Belgharia",
    "gn:population":0,
    "gn:timezone":"Asia/Dhaka",
    "iso:country":"BD",
    "name:ben_x_preferred":[
        "Belgharia"
    ],
    "name:ben_x_variant":[
        "\u09ac\u09c7\u09b2\u0998\u09b0\u09bf\u09af\u09bc\u09be"
    ],
    "wof:name":"Belgharia",
    "wof:placetype":"locality"
},
  "geometry": {"coordinates":[88.67231,24.35243],"type":"Point"}
}