{
  "type": "Feature",
  "properties": {
    "gn:admin1_code":"87",
    "gn:admin2_code":"5527.0",
    "gn:admin3_code":"552717.0",
    "gn:admin4_code":"55271757.0",
    "gn:asciiname":"Biswanathpur",
    "gn:country_code":"BD",
    "gn:dem":36,
    "gn:feature_class":"P",
    "gn:feature_code":"PPL",
    "gn:name":"Biswan\u0101thpur",
    "gn:population":0,
    "gn:timezone":"Asia/Dhaka",
    "iso:country":"BD",
    "name:ben_x_preferred":[
        "Biswan\u0101thpur"
    ],
    "wof:name":"Biswanathpur",
    "wof:placetype":"locality"
},
  "geometry": {"coordinates":[88.58077,25.55038],"type":"Point"}
}