{
  "type": "Feature",
  "properties": {
    "gn:admin1_code":"87",
    "gn:admin2_code":"5594.0",
    "gn:admin3_code":"559494.0",
    "gn:admin4_code":"55949452.0",
    "gn:asciiname":"Maligaon",
    "gn:country_code":"BD",
    "gn:dem":57,
    "gn:feature_class":"P",
    "gn:feature_code":"PPL",
    "gn:name":"M\u0101ligaon",
    "gn:population":0,
    "gn:timezone":"Asia/Dhaka",
    "iso:country":"BD",
    "name:ben_x_preferred":[
        "M\u0101ligaon"
    ],
    "wof:name":"Maligaon",
    "wof:placetype":"locality"
},
  "geometry": {"coordinates":[88.36882,25.98716],"type":"Point"}
}