{
  "type": "Feature",
  "properties": {
    "gn:admin1_code":"81",
    "gn:admin2_code":"3029",
    "gn:admin3_code":"302956.0",
    "gn:admin4_code":"30295631.0",
    "gn:asciiname":"Naopara",
    "gn:country_code":"BD",
    "gn:dem":17,
    "gn:feature_class":"P",
    "gn:feature_code":"PPL",
    "gn:name":"Naop\u0101ra",
    "gn:population":0,
    "gn:timezone":"Asia/Dhaka",
    "iso:country":"BD",
    "name:und_x_variant":[
        "Noapara",
        "Naop\u0101ra"
    ],
    "wof:name":"Naopara",
    "wof:placetype":"locality"
},
  "geometry": {"coordinates":[89.61525,23.58792],"type":"Point"}
}