{
  "type": "Feature",
  "properties": {
    "gn:admin1_code":"84",
    "gn:admin2_code":"2019.0",
    "gn:admin3_code":"201981.0",
    "gn:admin4_code":"20198109.0",
    "gn:asciiname":"Parba Bangam",
    "gn:country_code":"BD",
    "gn:dem":6,
    "gn:feature_class":"P",
    "gn:feature_code":"PPL",
    "gn:name":"Parba Bangam",
    "gn:population":0,
    "gn:timezone":"Asia/Dhaka",
    "iso:country":"BD",
    "wof:name":"Parba Bangam",
    "wof:placetype":"locality"
},
  "geometry": {"coordinates":[91.03806,23.76861],"type":"Point"}
}