{
  "type": "Feature",
  "properties": {
    "gn:admin1_code":"87",
    "gn:admin2_code":"5577.0",
    "gn:admin3_code":"557790.0",
    "gn:admin4_code":"55779081.0",
    "gn:asciiname":"Dhudhagachh",
    "gn:country_code":"BD",
    "gn:dem":92,
    "gn:feature_class":"P",
    "gn:feature_code":"PPL",
    "gn:name":"Dhudhag\u0101chh",
    "gn:population":0,
    "gn:timezone":"Asia/Dhaka",
    "iso:country":"BD",
    "name:ben_x_preferred":[
        "Dhudhag\u0101chh"
    ],
    "wof:name":"Dhudhagachh",
    "wof:placetype":"locality"
},
  "geometry": {"coordinates":[88.36350999999998,26.49457],"type":"Point"}
}