{
  "type": "Feature",
  "properties": {
    "gn:admin1_code":"81",
    "gn:admin2_code":"3082",
    "gn:admin3_code":"308273.0",
    "gn:admin4_code":"30827370.0",
    "gn:asciiname":"Sarbba Kulatia",
    "gn:country_code":"BD",
    "gn:dem":7,
    "gn:feature_class":"P",
    "gn:feature_code":"PPL",
    "gn:name":"Sarbba Kulatia",
    "gn:population":0,
    "gn:timezone":"Asia/Dhaka",
    "iso:country":"BD",
    "name:und_x_variant":[
        "Sarbbakultia",
        "Sarbba Kulatia"
    ],
    "wof:name":"Sarbba Kulatia",
    "wof:placetype":"locality"
},
  "geometry": {"coordinates":[89.46131,23.71795],"type":"Point"}
}