{
  "type": "Feature",
  "properties": {
    "gn:admin1_code":"87",
    "gn:admin2_code":"5549",
    "gn:admin3_code":"554918.0",
    "gn:admin4_code":"55491813.0",
    "gn:asciiname":"Baralai",
    "gn:country_code":"BD",
    "gn:dem":33,
    "gn:feature_class":"P",
    "gn:feature_code":"PPL",
    "gn:name":"Baral\u0101i",
    "gn:population":0,
    "gn:timezone":"Asia/Dhaka",
    "iso:country":"BD",
    "name:ben_x_preferred":[
        "Baral\u0101i"
    ],
    "wof:name":"Baralai",
    "wof:placetype":"locality"
},
  "geometry": {"coordinates":[89.59939,25.90681],"type":"Point"}
}