{
  "type": "Feature",
  "properties": {
    "gn:admin1_code":"83",
    "gn:admin2_code":"5064.0",
    "gn:admin3_code":"506450.0",
    "gn:admin4_code":"50645076.0",
    "gn:asciiname":"Shimulia",
    "gn:country_code":"BD",
    "gn:dem":23,
    "gn:feature_class":"P",
    "gn:feature_code":"PPL",
    "gn:name":"Shimulia",
    "gn:population":0,
    "gn:timezone":"Asia/Dhaka",
    "iso:country":"BD",
    "name:ben_x_preferred":[
        "Shimulia"
    ],
    "wof:name":"Shimulia",
    "wof:placetype":"locality"
},
  "geometry": {"coordinates":[88.86743,25.00322],"type":"Point"}
}