{
  "type": "Feature",
  "properties": {
    "gn:admin1_code":"H",
    "gn:admin2_code":"3089",
    "gn:admin3_code":"308988.0",
    "gn:admin4_code":"30898867.0",
    "gn:asciiname":"Raghunathpur",
    "gn:country_code":"BD",
    "gn:dem":20,
    "gn:feature_class":"P",
    "gn:feature_code":"PPL",
    "gn:name":"Raghun\u0101thpur",
    "gn:population":0,
    "gn:timezone":"Asia/Dhaka",
    "iso:country":"BD",
    "wof:name":"Raghunathpur",
    "wof:placetype":"locality"
},
  "geometry": {"coordinates":[90.08732999999999,24.9584],"type":"Point"}
}