{
  "type": "Feature",
  "properties": {
    "gn:admin1_code":"86",
    "gn:admin2_code":"6090",
    "gn:admin3_code":"609086.0",
    "gn:admin4_code":"60908671.0",
    "gn:asciiname":"Putka",
    "gn:country_code":"BD",
    "gn:dem":9,
    "gn:feature_class":"P",
    "gn:feature_code":"PPL",
    "gn:name":"Putka",
    "gn:population":0,
    "gn:timezone":"Asia/Dhaka",
    "iso:country":"BD",
    "name:bul_x_preferred":[
        "\u041f\u0443\u0442\u043a\u0430"
    ],
    "wof:name":"Putka",
    "wof:placetype":"locality"
},
  "geometry": {"coordinates":[91.33449,24.71933],"type":"Point"}
}