{
  "type": "Feature",
  "properties": {
    "gn:admin1_code":"87",
    "gn:admin2_code":"5527.0",
    "gn:admin3_code":"552738.0",
    "gn:admin4_code":"55273809.0",
    "gn:asciiname":"Gokul",
    "gn:country_code":"BD",
    "gn:dem":35,
    "gn:feature_class":"P",
    "gn:feature_code":"PPL",
    "gn:name":"Gokul",
    "gn:population":0,
    "gn:timezone":"Asia/Dhaka",
    "iso:country":"BD",
    "name:ben_x_preferred":[
        "Gokul"
    ],
    "wof:name":"Gokul",
    "wof:placetype":"locality"
},
  "geometry": {"coordinates":[88.91483000000002,25.47526],"type":"Point"}
}