{
  "type": "Feature",
  "properties": {
    "gn:admin1_code":"82",
    "gn:admin2_code":"4041",
    "gn:admin3_code":"404111.0",
    "gn:admin4_code":"40411186.0",
    "gn:asciiname":"Jagannathpur",
    "gn:country_code":"BD",
    "gn:dem":13,
    "gn:feature_class":"P",
    "gn:feature_code":"PPL",
    "gn:name":"Jagann\u0101thpur",
    "gn:population":0,
    "gn:timezone":"Asia/Dhaka",
    "iso:country":"BD",
    "name:ben_x_preferred":[
        "Jagann\u0101thpur"
    ],
    "wof:name":"Jagannathpur",
    "wof:placetype":"locality"
},
  "geometry": {"coordinates":[89.06459,23.23089],"type":"Point"}
}