{
  "type": "Feature",
  "properties": {
    "gn:admin1_code":"81",
    "gn:admin2_code":"3056",
    "gn:admin3_code":"305682.0",
    "gn:admin4_code":"30568251.0",
    "gn:asciiname":"Bahadia Imambagar High School",
    "gn:country_code":"BD",
    "gn:dem":11,
    "gn:feature_class":"P",
    "gn:feature_code":"PPLL",
    "gn:name":"Bahadia Imambagar High School",
    "gn:population":0,
    "gn:timezone":"Asia/Dhaka",
    "iso:country":"BD",
    "wof:name":"Bahadia Imambagar High School",
    "wof:placetype":"locality"
},
  "geometry": {"coordinates":[90.16737999999999,23.78988],"type":"Point"}
}