{
  "type": "Feature",
  "properties": {
    "gn:admin1_code":"82",
    "gn:admin2_code":"4050.0",
    "gn:admin3_code":"405079.0",
    "gn:admin4_code":"40507956.0",
    "gn:asciiname":"Goshpara",
    "gn:country_code":"BD",
    "gn:dem":14,
    "gn:feature_class":"P",
    "gn:feature_code":"PPL",
    "gn:name":"Goshp\u0101ra",
    "gn:population":0,
    "gn:timezone":"Asia/Dhaka",
    "iso:country":"BD",
    "name:ben_x_preferred":[
        "Goshp\u0101ra"
    ],
    "wof:name":"Goshpara",
    "wof:placetype":"locality"
},
  "geometry": {"coordinates":[89.12406,23.83438],"type":"Point"}
}