{
  "type": "Feature",
  "properties": {
    "gn:admin1_code":"83",
    "gn:admin2_code":"5070.0",
    "gn:admin3_code":"507088.0",
    "gn:admin4_code":"50708841.0",
    "gn:asciiname":"Guchha Gram",
    "gn:country_code":"BD",
    "gn:dem":29,
    "gn:feature_class":"P",
    "gn:feature_code":"PPL",
    "gn:name":"Guchha Gr\u0101m",
    "gn:population":0,
    "gn:timezone":"Asia/Dhaka",
    "iso:country":"BD",
    "name:ben_x_preferred":[
        "Guchha Gr\u0101m"
    ],
    "wof:name":"Guchha Gram",
    "wof:placetype":"locality"
},
  "geometry": {"coordinates":[88.17808000000002,24.72943],"type":"Point"}
}