{
  "type": "Feature",
  "properties": {
    "gn:admin1_code":"81",
    "gn:admin2_code":"3059",
    "gn:admin3_code":"305974.0",
    "gn:admin4_code":"30597467.0",
    "gn:asciiname":"Kanthaltali",
    "gn:country_code":"BD",
    "gn:dem":10,
    "gn:feature_class":"P",
    "gn:feature_code":"PPL",
    "gn:name":"K\u0101nth\u0101ltali",
    "gn:population":0,
    "gn:timezone":"Asia/Dhaka",
    "iso:country":"BD",
    "wof:name":"Kanthaltali",
    "wof:placetype":"locality"
},
  "geometry": {"coordinates":[90.38772,23.53952],"type":"Point"}
}