{
  "type": "Feature",
  "properties": {
    "gn:admin1_code":"81",
    "gn:admin2_code":"3068.0",
    "gn:admin3_code":"306852.0",
    "gn:admin4_code":"30685206.0",
    "gn:asciiname":"Aloakandi",
    "gn:country_code":"BD",
    "gn:dem":16,
    "gn:feature_class":"P",
    "gn:feature_code":"PPL",
    "gn:name":"\u0100lo\u0101k\u0101ndi",
    "gn:population":0,
    "gn:timezone":"Asia/Dhaka",
    "iso:country":"BD",
    "wof:name":"Aloakandi",
    "wof:placetype":"locality"
},
  "geometry": {"coordinates":[90.74668,24.19638],"type":"Point"}
}