{
  "type": "Feature",
  "properties": {
    "gn:admin1_code":"H",
    "gn:admin2_code":"3072",
    "gn:admin3_code":"307204.0",
    "gn:admin4_code":"30720459.0",
    "gn:asciiname":"Sonajur",
    "gn:country_code":"BD",
    "gn:dem":11,
    "gn:feature_class":"P",
    "gn:feature_code":"PPL",
    "gn:name":"Son\u0101jur",
    "gn:population":0,
    "gn:timezone":"Asia/Dhaka",
    "iso:country":"BD",
    "name:und_x_variant":[
        "Sonajpur",
        "Son\u0101jor",
        "Son\u0101jur"
    ],
    "wof:name":"Sonajur",
    "wof:placetype":"locality"
},
  "geometry": {"coordinates":[90.92157,24.76628],"type":"Point"}
}