{
  "type": "Feature",
  "properties": {
    "gn:admin1_code":"84",
    "gn:admin2_code":"2015.0",
    "gn:admin3_code":"201582.0",
    "gn:admin4_code":"20158265.0",
    "gn:asciiname":"Babunagar",
    "gn:country_code":"BD",
    "gn:dem":19,
    "gn:feature_class":"P",
    "gn:feature_code":"PPL",
    "gn:name":"B\u0101bunagar",
    "gn:population":0,
    "gn:timezone":"Asia/Dhaka",
    "iso:country":"BD",
    "name:ben_x_preferred":[
        "B\u0101bunagar"
    ],
    "name:ben_x_variant":[
        "B\u0101hunagar"
    ],
    "wof:name":"Babunagar",
    "wof:placetype":"locality"
},
  "geometry": {"coordinates":[92.01497999999999,22.07347],"type":"Point"}
}