{
  "type": "Feature",
  "properties": {
    "gn:admin1_code":"84",
    "gn:admin2_code":"2022.0",
    "gn:admin3_code":"202216.0",
    "gn:admin4_code":"20221694.0",
    "gn:asciiname":"Demusia",
    "gn:country_code":"BD",
    "gn:dem":6,
    "gn:feature_class":"P",
    "gn:feature_code":"PPL",
    "gn:name":"Demusia",
    "gn:population":0,
    "gn:timezone":"Asia/Dhaka",
    "iso:country":"BD",
    "name:ben_x_preferred":[
        "Demusia"
    ],
    "wof:name":"Demusia",
    "wof:placetype":"locality"
},
  "geometry": {"coordinates":[91.96964,21.74584],"type":"Point"}
}