{
  "type": "Feature",
  "properties": {
    "gn:admin1_code":"84",
    "gn:admin2_code":"2013",
    "gn:admin3_code":"201349.0",
    "gn:admin4_code":"20134955.0",
    "gn:asciiname":"Kalocho",
    "gn:country_code":"BD",
    "gn:dem":9,
    "gn:feature_class":"P",
    "gn:feature_code":"PPL",
    "gn:name":"K\u0101locho",
    "gn:population":0,
    "gn:timezone":"Asia/Dhaka",
    "iso:country":"BD",
    "wof:name":"Kalocho",
    "wof:placetype":"locality"
},
  "geometry": {"coordinates":[90.83338999999999,23.29436],"type":"Point"}
}