{
  "type": "Feature",
  "properties": {
    "gn:admin1_code":"81",
    "gn:admin2_code":"3067.0",
    "gn:admin3_code":"306768.0",
    "gn:admin4_code":"30676871.0",
    "gn:asciiname":"Baimakanda",
    "gn:country_code":"BD",
    "gn:dem":17,
    "gn:feature_class":"P",
    "gn:feature_code":"PPL",
    "gn:name":"B\u0101im\u0101k\u0101nda",
    "gn:population":0,
    "gn:timezone":"Asia/Dhaka",
    "iso:country":"BD",
    "wof:name":"Baimakanda",
    "wof:placetype":"locality"
},
  "geometry": {"coordinates":[90.48077000000001,23.88308],"type":"Point"}
}