{
  "type": "Feature",
  "properties": {
    "gn:admin1_code":"H",
    "gn:admin2_code":"3072.0",
    "gn:admin3_code":"307209.0",
    "gn:admin4_code":"30720983.0",
    "gn:asciiname":"Geria",
    "gn:country_code":"BD",
    "gn:dem":15,
    "gn:feature_class":"P",
    "gn:feature_code":"PPL",
    "gn:name":"Geria",
    "gn:population":0,
    "gn:timezone":"Asia/Dhaka",
    "iso:country":"BD",
    "name:arg_x_preferred":[
        "Geria"
    ],
    "name:ast_x_preferred":[
        "Geria"
    ],
    "name:cat_x_preferred":[
        "Geria"
    ],
    "name:ceb_x_preferred":[
        "Geria"
    ],
    "name:eus_x_preferred":[
        "Geria"
    ],
    "name:fas_x_preferred":[
        "\u062e\u0631\u06cc\u0627"
    ],
    "name:fra_x_preferred":[
        "Geria"
    ],
    "name:hun_x_preferred":[
        "Geria"
    ],
    "name:hye_x_preferred":[
        "\u053d\u0565\u0580\u056b\u0561"
    ],
    "name:ina_x_preferred":[
        "Geria"
    ],
    "name:ita_x_preferred":[
        "Geria"
    ],
    "name:msa_x_preferred":[
        "Geria"
    ],
    "name:nld_x_preferred":[
        "Geria"
    ],
    "name:oci_x_preferred":[
        "Geria"
    ],
    "name:pol_x_preferred":[
        "Geria"
    ],
    "name:por_x_preferred":[
        "Geria"
    ],
    "name:rus_x_preferred":[
        "\u0425\u0435\u0440\u0438\u044f"
    ],
    "name:spa_x_preferred":[
        "Geria"
    ],
    "name:swe_x_preferred":[
        "Geria"
    ],
    "name:ukr_x_preferred":[
        "\u0425\u0435\u0440\u0456\u044f"
    ],
    "name:vie_x_preferred":[
        "Geria"
    ],
    "name:war_x_preferred":[
        "Geria"
    ],
    "name:zho_x_preferred":[
        "\u8d6b\u91cc\u4e9a"
    ],
    "wof:name":"Geria",
    "wof:placetype":"locality"
},
  "geometry": {"coordinates":[90.95569999999999,24.90931],"type":"Point"}
}