{
  "type": "Feature",
  "properties": {
    "gn:admin1_code":"87",
    "gn:admin2_code":"5594.0",
    "gn:admin3_code":"559486.0",
    "gn:admin4_code":"55948631.0",
    "gn:asciiname":"Kashipur",
    "gn:country_code":"BD",
    "gn:dem":52,
    "gn:feature_class":"P",
    "gn:feature_code":"PPL",
    "gn:name":"K\u0101sh\u012bpur",
    "gn:population":0,
    "gn:timezone":"Asia/Dhaka",
    "iso:country":"BD",
    "name:ben_x_preferred":[
        "K\u0101sh\u012bpur"
    ],
    "wof:name":"Kashipur",
    "wof:placetype":"locality"
},
  "geometry": {"coordinates":[88.19932,26.02921],"type":"Point"}
}