{
  "type": "Feature",
  "properties": {
    "gn:admin1_code":"82",
    "gn:admin2_code":"4050.0",
    "gn:admin3_code":"405094.0",
    "gn:admin4_code":"40509436.0",
    "gn:asciiname":"Bharal",
    "gn:country_code":"BD",
    "gn:dem":18,
    "gn:feature_class":"P",
    "gn:feature_code":"PPL",
    "gn:name":"Bh\u0101ral",
    "gn:population":0,
    "gn:timezone":"Asia/Dhaka",
    "iso:country":"BD",
    "name:ava_x_preferred":[
        "\u041d\u0430\u0445\u0443\u0440"
    ],
    "name:ben_x_preferred":[
        "Bh\u0101ral"
    ],
    "name:ben_x_variant":[
        "\u09ad\u09b0\u09be\u09b2"
    ],
    "name:bod_x_preferred":[
        "\u0f42\u0f53\u0f60\u0f0b\u0f56\u0f0d"
    ],
    "name:bre_x_preferred":[
        "Bharal bras"
    ],
    "name:bul_x_preferred":[
        "\u0411\u0430\u0440\u0430\u043b"
    ],
    "name:cat_x_preferred":[
        "B\u00e0ral"
    ],
    "name:ceb_x_preferred":[
        "Pseudois nayaur"
    ],
    "name:ces_x_preferred":[
        "Nahur modr\u00fd"
    ],
    "name:deu_x_preferred":[
        "Blauschaf"
    ],
    "name:eus_x_preferred":[
        "Pseudois nayaur"
    ],
    "name:fin_x_preferred":[
        "Puolilammas"
    ],
    "name:fra_x_preferred":[
        "Pseudois nayaur"
    ],
    "name:hin_x_preferred":[
        "\u092d\u0921\u093c\u0932"
    ],
    "name:hun_x_preferred":[
        "Bharal"
    ],
    "name:ind_x_preferred":[
        "Bharal"
    ],
    "name:ita_x_preferred":[
        "Pseudois nayaur"
    ],
    "name:kat_x_preferred":[
        "\u10d9\u10e3\u10d9\u10e3-\u10d8\u10d0\u10db\u10d0\u10dc\u10d8"
    ],
    "name:mhr_x_preferred":[
        "\u041d\u0430\u0445\u0443\u0440"
    ],
    "name:nep_x_preferred":[
        "\u0928\u093e\u0909\u0930"
    ],
    "name:nld_x_preferred":[
        "Blauwschaap"
    ],
    "name:nno_x_preferred":[
        "Bl\u00e5sau"
    ],
    "name:pnb_x_preferred":[
        "\u0628\u06be\u0631\u0644"
    ],
    "name:pol_x_preferred":[
        "Nahur g\u00f3rski"
    ],
    "name:por_x_preferred":[
        "Pseudois nayaur"
    ],
    "name:rus_x_preferred":[
        "\u0413\u043e\u043b\u0443\u0431\u043e\u0439 \u0431\u0430\u0440\u0430\u043d"
    ],
    "name:spa_x_preferred":[
        "Pseudois nayaur"
    ],
    "name:swe_x_preferred":[
        "Bl\u00e5f\u00e5r"
    ],
    "name:tur_x_preferred":[
        "Bharal"
    ],
    "name:udm_x_preferred":[
        "\u041d\u0430\u0445\u0443\u0440"
    ],
    "name:uig_x_preferred":[
        "\u0643\u06c6\u0643\u0645\u06d5\u062a"
    ],
    "name:ukr_x_preferred":[
        "\u041d\u0430\u0445\u0443\u0440 \u0431\u043b\u0430\u043a\u0438\u0442\u043d\u0438\u0439"
    ],
    "name:vie_x_preferred":[
        "C\u1eebu Bharal"
    ],
    "name:war_x_preferred":[
        "Pseudois nayaur"
    ],
    "wof:name":"Bharal",
    "wof:placetype":"locality"
},
  "geometry": {"coordinates":[89.02807,23.88945],"type":"Point"}
}