{
  "type": "Feature",
  "properties": {
    "gn:admin1_code":"81",
    "gn:admin2_code":"3056.0",
    "gn:admin3_code":"305646.0",
    "gn:admin4_code":"30564655.0",
    "gn:asciiname":"Angutia",
    "gn:country_code":"BD",
    "gn:dem":16,
    "gn:feature_class":"P",
    "gn:feature_code":"PPL",
    "gn:name":"\u0100ngutia",
    "gn:population":0,
    "gn:timezone":"Asia/Dhaka",
    "iso:country":"BD",
    "wof:name":"Angutia",
    "wof:placetype":"locality"
},
  "geometry": {"coordinates":[90.03147,23.88223],"type":"Point"}
}