{
  "type": "Feature",
  "properties": {
    "gn:admin1_code":"84",
    "gn:admin2_code":"2051.0",
    "gn:admin3_code":"205143.0",
    "gn:admin4_code":"20514325.0",
    "gn:asciiname":"Gobindapur",
    "gn:country_code":"BD",
    "gn:dem":8,
    "gn:feature_class":"P",
    "gn:feature_code":"PPL",
    "gn:name":"Gobindapur",
    "gn:population":0,
    "gn:timezone":"Asia/Dhaka",
    "iso:country":"BD",
    "wof:name":"Gobindapur",
    "wof:placetype":"locality"
},
  "geometry": {"coordinates":[90.94595,22.88864],"type":"Point"}
}