{
  "type": "Feature",
  "properties": {
    "gn:admin1_code":"83",
    "gn:admin2_code":"5081.0",
    "gn:admin3_code":"508194.0",
    "gn:admin4_code":"50819454.0",
    "gn:asciiname":"Chimna",
    "gn:country_code":"BD",
    "gn:dem":26,
    "gn:feature_class":"P",
    "gn:feature_code":"PPL",
    "gn:name":"Chimna",
    "gn:population":0,
    "gn:timezone":"Asia/Dhaka",
    "iso:country":"BD",
    "name:ben_x_preferred":[
        "Chimna"
    ],
    "wof:name":"Chimna",
    "wof:placetype":"locality"
},
  "geometry": {"coordinates":[88.52108,24.60899],"type":"Point"}
}