{
  "type": "Feature",
  "properties": {
    "gn:admin1_code":"84",
    "gn:admin2_code":"2019.0",
    "gn:admin3_code":"201937.0",
    "gn:admin4_code":"20193777.0",
    "gn:asciiname":"Gopalpur Joar",
    "gn:country_code":"BD",
    "gn:dem":10,
    "gn:feature_class":"P",
    "gn:feature_code":"PPL",
    "gn:name":"Gop\u0101lpur Jo\u0101r",
    "gn:population":0,
    "gn:timezone":"Asia/Dhaka",
    "iso:country":"BD",
    "wof:name":"Gopalpur Joar",
    "wof:placetype":"locality"
},
  "geometry": {"coordinates":[90.79239,23.54972],"type":"Point"}
}