{
  "type": "Feature",
  "properties": {
    "gn:admin1_code":"81",
    "gn:admin2_code":"3026.0",
    "gn:admin3_code":"302672.0",
    "gn:admin4_code":"30267222.0",
    "gn:asciiname":"Baliarpur",
    "gn:country_code":"BD",
    "gn:dem":13,
    "gn:feature_class":"P",
    "gn:feature_code":"PPL",
    "gn:name":"Bali\u0101rpur",
    "gn:population":0,
    "gn:timezone":"Asia/Dhaka",
    "iso:country":"BD",
    "wof:name":"Baliarpur",
    "wof:placetype":"locality"
},
  "geometry": {"coordinates":[90.28989,23.79667],"type":"Point"}
}