{
  "type": "Feature",
  "properties": {
    "gn:admin1_code":"84",
    "gn:admin2_code":"2084",
    "gn:admin3_code":"208447.0",
    "gn:admin4_code":"20844776.0",
    "gn:asciiname":"Jarulchari",
    "gn:country_code":"BD",
    "gn:dem":50,
    "gn:feature_class":"P",
    "gn:feature_code":"PPL",
    "gn:name":"J\u0101rulchari",
    "gn:population":0,
    "gn:timezone":"Asia/Dhaka",
    "iso:country":"BD",
    "name:und_x_variant":[
        "Jarulchhari",
        "J\u0101rulchari"
    ],
    "wof:name":"Jarulchari",
    "wof:placetype":"locality"
},
  "geometry": {"coordinates":[92.38894000000001,22.5588],"type":"Point"}
}