{
  "type": "Feature",
  "properties": {
    "gn:admin1_code":"85",
    "gn:admin2_code":"1004",
    "gn:admin3_code":"100485.0",
    "gn:admin4_code":"10048583.0",
    "gn:asciiname":"Hogalpati",
    "gn:country_code":"BD",
    "gn:dem":6,
    "gn:feature_class":"P",
    "gn:feature_code":"PPL",
    "gn:name":"Hogalpati",
    "gn:population":0,
    "gn:timezone":"Asia/Dhaka",
    "iso:country":"BD",
    "name:ben_x_preferred":[
        "Hogalpati"
    ],
    "name:und_x_variant":[
        "Hoglapati"
    ],
    "wof:name":"Hogalpati",
    "wof:placetype":"locality"
},
  "geometry": {"coordinates":[90.00825999999998,22.21807],"type":"Point"}
}