{
  "type": "Feature",
  "properties": {
    "gn:admin1_code":"87",
    "gn:admin2_code":"5552",
    "gn:admin3_code":"555202.0",
    "gn:admin4_code":"55520241.0",
    "gn:asciiname":"Gobadha",
    "gn:country_code":"BD",
    "gn:dem":37,
    "gn:feature_class":"P",
    "gn:feature_code":"PPL",
    "gn:name":"Gob\u0101dha",
    "gn:population":0,
    "gn:timezone":"Asia/Dhaka",
    "iso:country":"BD",
    "name:ben_x_preferred":[
        "Gob\u0101dha"
    ],
    "wof:name":"Gobadha",
    "wof:placetype":"locality"
},
  "geometry": {"coordinates":[89.40369,26.00402],"type":"Point"}
}