{
  "type": "Feature",
  "properties": {
    "gn:admin1_code":"81",
    "gn:admin2_code":"3056.0",
    "gn:admin3_code":"305678.0",
    "gn:admin4_code":"30567835.0",
    "gn:asciiname":"Ag Simulia",
    "gn:country_code":"BD",
    "gn:dem":8,
    "gn:feature_class":"P",
    "gn:feature_code":"PPL",
    "gn:name":"\u0100g Simulia",
    "gn:population":0,
    "gn:timezone":"Asia/Dhaka",
    "iso:country":"BD",
    "wof:name":"Ag Simulia",
    "wof:placetype":"locality"
},
  "geometry": {"coordinates":[89.90000000000001,23.81667],"type":"Point"}
}