{
  "type": "Feature",
  "properties": {
    "gn:admin1_code":"83",
    "gn:asciiname":"Guinaniganj",
    "gn:country_code":"BD",
    "gn:dem":24,
    "gn:feature_class":"P",
    "gn:feature_code":"PPL",
    "gn:name":"Guin\u0101niganj",
    "gn:population":0,
    "gn:timezone":"Asia/Dhaka",
    "iso:country":"BD",
    "name:ben_x_preferred":[
        "Guin\u0101niganj"
    ],
    "wof:name":"Guinaniganj",
    "wof:placetype":"locality"
},
  "geometry": {"coordinates":[89.36856999999998,25.10489],"type":"Point"}
}