{
  "type": "Feature",
  "properties": {
    "gn:admin1_code":"H",
    "gn:admin2_code":"3072",
    "gn:admin3_code":"307283.0",
    "gn:admin4_code":"30728307.0",
    "gn:asciiname":"Kharchail",
    "gn:country_code":"BD",
    "gn:dem":15,
    "gn:feature_class":"P",
    "gn:feature_code":"PPL",
    "gn:name":"Kh\u0101rch\u0101il",
    "gn:population":0,
    "gn:timezone":"Asia/Dhaka",
    "iso:country":"BD",
    "wof:name":"Kharchail",
    "wof:placetype":"locality"
},
  "geometry": {"coordinates":[90.5478,24.96347],"type":"Point"}
}