{
  "type": "Feature",
  "properties": {
    "gn:admin1_code":"H",
    "gn:admin2_code":"3039",
    "gn:admin3_code":"303915.0",
    "gn:admin4_code":"30391565.0",
    "gn:asciiname":"Hari Chandi",
    "gn:country_code":"BD",
    "gn:dem":28,
    "gn:feature_class":"P",
    "gn:feature_code":"PPL",
    "gn:name":"Hari Chandi",
    "gn:population":0,
    "gn:timezone":"Asia/Dhaka",
    "iso:country":"BD",
    "name:ben_x_preferred":[
        "Hari Chandi"
    ],
    "wof:name":"Hari Chandi",
    "wof:placetype":"locality"
},
  "geometry": {"coordinates":[89.75320000000001,25.26728],"type":"Point"}
}