{
  "type": "Feature",
  "properties": {
    "gn:admin1_code":"83",
    "gn:admin2_code":"5081.0",
    "gn:admin3_code":"508182.0",
    "gn:admin4_code":"50818213.0",
    "gn:asciiname":"Shibpur",
    "gn:country_code":"BD",
    "gn:dem":20,
    "gn:feature_class":"P",
    "gn:feature_code":"PPL",
    "gn:name":"Shibpur",
    "gn:population":0,
    "gn:timezone":"Asia/Dhaka",
    "iso:country":"BD",
    "name:ben_x_preferred":[
        "Shibpur"
    ],
    "name:urd_x_preferred":[
        "\u0634\u06cc\u0628 \u067e\u0648\u0631"
    ],
    "wof:name":"Shibpur",
    "wof:placetype":"locality"
},
  "geometry": {"coordinates":[88.74641,24.35769],"type":"Point"}
}