{
  "type": "Feature",
  "properties": {
    "gn:admin1_code":"84",
    "gn:admin2_code":"2075",
    "gn:admin3_code":"207510.0",
    "gn:admin4_code":"20751066.0",
    "gn:asciiname":"Jamirtali",
    "gn:country_code":"BD",
    "gn:dem":13,
    "gn:feature_class":"P",
    "gn:feature_code":"PPL",
    "gn:name":"J\u0101mirtali",
    "gn:population":0,
    "gn:timezone":"Asia/Dhaka",
    "iso:country":"BD",
    "wof:name":"Jamirtali",
    "wof:placetype":"locality"
},
  "geometry": {"coordinates":[90.94356999999999,23.07401],"type":"Point"}
}