{
  "type": "Feature",
  "properties": {
    "gn:admin1_code":"87",
    "gn:admin2_code":"5527.0",
    "gn:admin3_code":"552712.0",
    "gn:admin4_code":"55271243.0",
    "gn:asciiname":"Chak Banarasi",
    "gn:country_code":"BD",
    "gn:dem":49,
    "gn:feature_class":"P",
    "gn:feature_code":"PPL",
    "gn:name":"Chak B\u0101n\u0101rasi",
    "gn:population":0,
    "gn:timezone":"Asia/Dhaka",
    "iso:country":"BD",
    "name:ben_x_preferred":[
        "Chak B\u0101n\u0101rasi"
    ],
    "wof:name":"Chak Banarasi",
    "wof:placetype":"locality"
},
  "geometry": {"coordinates":[88.67641,25.91742],"type":"Point"}
}