{
  "type": "Feature",
  "properties": {
    "gn:admin1_code":"87",
    "gn:admin2_code":"5527.0",
    "gn:admin3_code":"552730.0",
    "gn:admin4_code":"55273055.0",
    "gn:asciiname":"Uttar Dogarbari",
    "gn:country_code":"BD",
    "gn:dem":43,
    "gn:feature_class":"P",
    "gn:feature_code":"PPL",
    "gn:name":"Uttar Dogarb\u0101ri",
    "gn:population":0,
    "gn:timezone":"Asia/Dhaka",
    "iso:country":"BD",
    "name:ben_x_preferred":[
        "Uttar Dogarb\u0101ri"
    ],
    "wof:name":"Uttar Dogarbari",
    "wof:placetype":"locality"
},
  "geometry": {"coordinates":[88.86284999999999,25.74173],"type":"Point"}
}