{
  "type": "Feature",
  "properties": {
    "gn:admin1_code":"81",
    "gn:admin2_code":"3033",
    "gn:admin3_code":"303332.0",
    "gn:admin4_code":"30333285.0",
    "gn:asciiname":"Kathalia",
    "gn:country_code":"BD",
    "gn:dem":20,
    "gn:feature_class":"P",
    "gn:feature_code":"PPL",
    "gn:name":"K\u0101th\u0101lia",
    "gn:population":0,
    "gn:timezone":"Asia/Dhaka",
    "iso:country":"BD",
    "wof:name":"Kathalia",
    "wof:placetype":"locality"
},
  "geometry": {"coordinates":[90.18317,24.07713],"type":"Point"}
}