{
  "type": "Feature",
  "properties": {
    "gn:admin1_code":"83",
    "gn:admin2_code":"5064.0",
    "gn:admin3_code":"506475.0",
    "gn:admin4_code":"50647543.0",
    "gn:asciiname":"Mahimapur",
    "gn:country_code":"BD",
    "gn:dem":25,
    "gn:feature_class":"P",
    "gn:feature_code":"PPL",
    "gn:name":"Mahim\u0101pur",
    "gn:population":0,
    "gn:timezone":"Asia/Dhaka",
    "iso:country":"BD",
    "name:ben_x_preferred":[
        "Mahim\u0101pur"
    ],
    "wof:name":"Mahimapur",
    "wof:placetype":"locality"
},
  "geometry": {"coordinates":[88.73286999999998,25.07389],"type":"Point"}
}