{
  "type": "Feature",
  "properties": {
    "gn:admin1_code":"85",
    "gn:admin2_code":"1004.0",
    "gn:admin3_code":"100428.0",
    "gn:admin4_code":"10042885.0",
    "gn:asciiname":"Amtali",
    "gn:country_code":"BD",
    "gn:dem":8,
    "gn:feature_class":"P",
    "gn:feature_code":"PPL",
    "gn:name":"Amtali",
    "gn:population":0,
    "gn:timezone":"Asia/Dhaka",
    "iso:country":"BD",
    "name:ben_x_preferred":[
        "Amtali"
    ],
    "wof:name":"Amtali",
    "wof:placetype":"locality"
},
  "geometry": {"coordinates":[90.09103,22.09462000000001],"type":"Point"}
}