{
  "type": "Feature",
  "properties": {
    "gn:admin1_code":"85",
    "gn:admin2_code":"1078",
    "gn:admin3_code":"107876.0",
    "gn:admin4_code":"10787681.0",
    "gn:asciiname":"Mirzaganj",
    "gn:country_code":"BD",
    "gn:dem":7,
    "gn:feature_class":"P",
    "gn:feature_code":"PPL",
    "gn:name":"Mirz\u0101ganj",
    "gn:population":0,
    "gn:timezone":"Asia/Dhaka",
    "iso:country":"BD",
    "name:ben_x_preferred":[
        "Mirz\u0101ganj"
    ],
    "name:und_x_variant":[
        "Mirjagonj"
    ],
    "wof:name":"Mirzaganj",
    "wof:placetype":"locality"
},
  "geometry": {"coordinates":[90.23326,22.35814],"type":"Point"}
}