{
  "type": "Feature",
  "properties": {
    "gn:admin1_code":"H",
    "gn:admin2_code":"3061.0",
    "gn:admin3_code":"306172.0",
    "gn:admin4_code":"30617279.0",
    "gn:asciiname":"Ahdullabpur Banati",
    "gn:country_code":"BD",
    "gn:dem":15,
    "gn:feature_class":"P",
    "gn:feature_code":"PPL",
    "gn:name":"Ahdullabpur Ban\u0101ti",
    "gn:population":0,
    "gn:timezone":"Asia/Dhaka",
    "iso:country":"BD",
    "name:und_x_variant":[
        "Ahdullabpur Ban\u0101ti",
        "Abdull\u0101pur Ban\u0101ti"
    ],
    "wof:name":"Ahdullabpur Banati",
    "wof:placetype":"locality"
},
  "geometry": {"coordinates":[90.80653,24.55835],"type":"Point"}
}