{
  "type": "Feature",
  "properties": {
    "gn:admin1_code":"82",
    "gn:admin2_code":"4065.0",
    "gn:admin3_code":"406576.0",
    "gn:admin4_code":"40657674.0",
    "gn:asciiname":"Zadanandakati",
    "gn:country_code":"BD",
    "gn:dem":9,
    "gn:feature_class":"P",
    "gn:feature_code":"PPL",
    "gn:name":"Zadanandak\u0101ti",
    "gn:population":0,
    "gn:timezone":"Asia/Dhaka",
    "iso:country":"BD",
    "name:ben_x_preferred":[
        "Zadanandak\u0101ti"
    ],
    "wof:name":"Zadanandakati",
    "wof:placetype":"locality"
},
  "geometry": {"coordinates":[89.48234000000002,23.20129],"type":"Point"}
}