{
  "type": "Feature",
  "properties": {
    "gn:admin1_code":"87",
    "gn:admin2_code":"5585",
    "gn:admin3_code":"558576.0",
    "gn:admin4_code":"55857637.0",
    "gn:asciiname":"Nij Kabilpur",
    "gn:country_code":"BD",
    "gn:dem":28,
    "gn:feature_class":"P",
    "gn:feature_code":"PPL",
    "gn:name":"Nij Kabilpur",
    "gn:population":0,
    "gn:timezone":"Asia/Dhaka",
    "iso:country":"BD",
    "name:ben_x_preferred":[
        "Nij Kabilpur"
    ],
    "wof:name":"Nij Kabilpur",
    "wof:placetype":"locality"
},
  "geometry": {"coordinates":[89.33014,25.31526],"type":"Point"}
}