{
  "type": "Feature",
  "properties": {
    "gn:admin1_code":"84",
    "gn:admin2_code":"2003.0",
    "gn:admin3_code":"200395.0",
    "gn:admin4_code":"20039538.0",
    "gn:asciiname":"Tukpui",
    "gn:country_code":"BD",
    "gn:dem":101,
    "gn:feature_class":"P",
    "gn:feature_code":"PPL",
    "gn:name":"Tukpui",
    "gn:population":0,
    "gn:timezone":"Asia/Dhaka",
    "iso:country":"BD",
    "name:ben_x_preferred":[
        "Tukpui"
    ],
    "wof:name":"Tukpui",
    "wof:placetype":"locality"
},
  "geometry": {"coordinates":[92.52616999999999,21.59954],"type":"Point"}
}