{
  "type": "Feature",
  "properties": {
    "gn:admin1_code":"85",
    "gn:admin2_code":"1006.0",
    "gn:admin3_code":"100610.0",
    "gn:admin4_code":"10061021.0",
    "gn:asciiname":"Baisari",
    "gn:country_code":"BD",
    "gn:dem":8,
    "gn:feature_class":"P",
    "gn:feature_code":"PPL",
    "gn:name":"B\u0101is\u0101ri",
    "gn:population":0,
    "gn:timezone":"Asia/Dhaka",
    "iso:country":"BD",
    "name:und_x_variant":[
        "B\u0101is\u0101ri"
    ],
    "wof:name":"Baisari",
    "wof:placetype":"locality"
},
  "geometry": {"coordinates":[90.12589,22.79588],"type":"Point"}
}