{
  "type": "Feature",
  "properties": {
    "gn:admin1_code":"83",
    "gn:admin2_code":"5076",
    "gn:admin3_code":"507616.0",
    "gn:admin4_code":"50761652.0",
    "gn:asciiname":"Kalikapur",
    "gn:country_code":"BD",
    "gn:dem":9,
    "gn:feature_class":"P",
    "gn:feature_code":"PPL",
    "gn:name":"Kalikapur",
    "gn:population":0,
    "gn:timezone":"Asia/Dhaka",
    "iso:country":"BD",
    "name:ben_x_preferred":[
        "Kalikapur"
    ],
    "name:ben_x_variant":[
        "K\u0101l\u012bk\u0101b\u0101ri"
    ],
    "wof:name":"Kalikapur",
    "wof:placetype":"locality"
},
  "geometry": {"coordinates":[89.65524000000001,23.87549],"type":"Point"}
}