{
  "type": "Feature",
  "properties": {
    "gn:admin1_code":"82",
    "gn:admin2_code":"4047",
    "gn:admin3_code":"404753.0",
    "gn:admin4_code":"40475372.0",
    "gn:asciiname":"Simuliar Ait",
    "gn:cc2":"BD",
    "gn:country_code":"BD",
    "gn:dem":2,
    "gn:feature_class":"P",
    "gn:feature_code":"PPL",
    "gn:name":"Simuli\u0101r \u0100it",
    "gn:population":0,
    "gn:timezone":"Asia/Dhaka",
    "iso:country":"BD",
    "name:und_x_variant":[
        "Simulier Ait",
        "Simuli\u0101r \u0100it"
    ],
    "wof:name":"Simuliar Ait",
    "wof:placetype":"locality"
},
  "geometry": {"coordinates":[89.28333000000001,22.38333],"type":"Point"}
}