{
  "type": "Feature",
  "properties": {
    "gn:admin1_code":"84",
    "gn:admin2_code":"2019.0",
    "gn:admin3_code":"201968.0",
    "gn:admin4_code":"20196821.0",
    "gn:asciiname":"Bijoypur",
    "gn:country_code":"BD",
    "gn:dem":13,
    "gn:feature_class":"P",
    "gn:feature_code":"PPL",
    "gn:name":"Bijoypur",
    "gn:population":0,
    "gn:timezone":"Asia/Dhaka",
    "iso:country":"BD",
    "wof:name":"Bijoypur",
    "wof:placetype":"locality"
},
  "geometry": {"coordinates":[91.15611,23.44],"type":"Point"}
}