{
  "type": "Feature",
  "properties": {
    "gn:admin1_code":"84",
    "gn:admin2_code":"2012",
    "gn:admin3_code":"201285.0",
    "gn:admin4_code":"20128547.0",
    "gn:asciiname":"Laur Fatehpur",
    "gn:country_code":"BD",
    "gn:dem":14,
    "gn:feature_class":"P",
    "gn:feature_code":"PPL",
    "gn:name":"L\u0101ur Fatehpur",
    "gn:population":0,
    "gn:timezone":"Asia/Dhaka",
    "iso:country":"BD",
    "name:und_x_variant":[
        "Laur Fetepur",
        "L\u0101ur Fatehpur"
    ],
    "wof:name":"Laur Fatehpur",
    "wof:placetype":"locality"
},
  "geometry": {"coordinates":[90.99850000000001,23.80934],"type":"Point"}
}