{
  "type": "Feature",
  "properties": {
    "gn:admin1_code":"H",
    "gn:admin2_code":"3089",
    "gn:admin3_code":"308937.0",
    "gn:admin4_code":"30893717.0",
    "gn:asciiname":"Kurili Kanda",
    "gn:country_code":"BD",
    "gn:dem":21,
    "gn:feature_class":"P",
    "gn:feature_code":"PPL",
    "gn:name":"Kurili K\u0101nda",
    "gn:population":0,
    "gn:timezone":"Asia/Dhaka",
    "iso:country":"BD",
    "name:ben_x_preferred":[
        "Kurili K\u0101nda"
    ],
    "name:und_x_variant":[
        "B\u0101ndhaboul"
    ],
    "wof:name":"Kurili Kanda",
    "wof:placetype":"locality"
},
  "geometry": {"coordinates":[90.06905,25.09309],"type":"Point"}
}