{
  "type": "Feature",
  "properties": {
    "gn:admin1_code":"87",
    "gn:admin2_code":"5552",
    "gn:admin3_code":"555239.0",
    "gn:admin4_code":"55523995.0",
    "gn:asciiname":"Matukpur",
    "gn:country_code":"BD",
    "gn:dem":38,
    "gn:feature_class":"P",
    "gn:feature_code":"PPL",
    "gn:name":"Matukpur",
    "gn:population":0,
    "gn:timezone":"Asia/Dhaka",
    "iso:country":"BD",
    "name:ben_x_preferred":[
        "Matukpur"
    ],
    "wof:name":"Matukpur",
    "wof:placetype":"locality"
},
  "geometry": {"coordinates":[89.22181999999999,25.92273],"type":"Point"}
}