{
  "type": "Feature",
  "properties": {
    "gn:admin1_code":"82",
    "gn:admin2_code":"4044.0",
    "gn:admin3_code":"404419.0",
    "gn:admin4_code":"40441952.0",
    "gn:asciiname":"Berasula",
    "gn:country_code":"BD",
    "gn:dem":11,
    "gn:feature_class":"P",
    "gn:feature_code":"PPL",
    "gn:name":"Ber\u0101sula",
    "gn:population":0,
    "gn:timezone":"Asia/Dhaka",
    "iso:country":"BD",
    "name:ben_x_preferred":[
        "Ber\u0101sula"
    ],
    "wof:name":"Berasula",
    "wof:placetype":"locality"
},
  "geometry": {"coordinates":[89.05625999999999,23.52081],"type":"Point"}
}