{
  "type": "Feature",
  "properties": {
    "gn:admin1_code":"83",
    "gn:admin2_code":"5069",
    "gn:admin3_code":"506991.0",
    "gn:admin4_code":"50699123.0",
    "gn:asciiname":"Hulhulia",
    "gn:country_code":"BD",
    "gn:dem":18,
    "gn:feature_class":"P",
    "gn:feature_code":"PPL",
    "gn:name":"Hulhulia",
    "gn:population":0,
    "gn:timezone":"Asia/Dhaka",
    "iso:country":"BD",
    "wof:name":"Hulhulia",
    "wof:placetype":"locality"
},
  "geometry": {"coordinates":[89.12905000000001,24.57258],"type":"Point"}
}