{
  "type": "Feature",
  "properties": {
    "gn:admin1_code":"83",
    "gn:admin2_code":"5081.0",
    "gn:admin3_code":"508112.0",
    "gn:admin4_code":"50811269.0",
    "gn:asciiname":"Boalipara",
    "gn:country_code":"BD",
    "gn:dem":20,
    "gn:feature_class":"P",
    "gn:feature_code":"PPL",
    "gn:name":"Boalip\u0101ra",
    "gn:population":0,
    "gn:timezone":"Asia/Dhaka",
    "iso:country":"BD",
    "name:ben_x_preferred":[
        "Boalip\u0101ra"
    ],
    "wof:name":"Boalipara",
    "wof:placetype":"locality"
},
  "geometry": {"coordinates":[88.90846999999999,24.59135],"type":"Point"}
}