{
  "type": "Feature",
  "properties": {
    "gn:admin1_code":"83",
    "gn:admin2_code":"5081.0",
    "gn:admin3_code":"508112.0",
    "gn:admin4_code":"50811250.0",
    "gn:asciiname":"Bhaturio",
    "gn:country_code":"BD",
    "gn:dem":21,
    "gn:feature_class":"P",
    "gn:feature_code":"PPL",
    "gn:name":"Bh\u0101turio",
    "gn:population":0,
    "gn:timezone":"Asia/Dhaka",
    "iso:country":"BD",
    "name:ben_x_preferred":[
        "Bh\u0101turio"
    ],
    "wof:name":"Bhaturio",
    "wof:placetype":"locality"
},
  "geometry": {"coordinates":[88.74302,24.5715],"type":"Point"}
}