{
  "type": "Feature",
  "properties": {
    "gn:admin1_code":"87",
    "gn:admin2_code":"5573.0",
    "gn:admin3_code":"557312.0",
    "gn:admin4_code":"55731266.0",
    "gn:asciiname":"Akashkori",
    "gn:country_code":"BD",
    "gn:dem":59,
    "gn:feature_class":"P",
    "gn:feature_code":"PPL",
    "gn:name":"Akashkori",
    "gn:population":0,
    "gn:timezone":"Asia/Dhaka",
    "iso:country":"BD",
    "name:ben_x_preferred":[
        "Akashkori"
    ],
    "wof:name":"Akashkori",
    "wof:placetype":"locality"
},
  "geometry": {"coordinates":[88.96449,26.17356],"type":"Point"}
}