{
  "type": "Feature",
  "properties": {
    "gn:admin1_code":"82",
    "gn:admin2_code":"4047.0",
    "gn:admin3_code":"404794.0",
    "gn:admin4_code":"40479467.0",
    "gn:asciiname":"Masundia",
    "gn:country_code":"BD",
    "gn:dem":7,
    "gn:feature_class":"P",
    "gn:feature_code":"PPL",
    "gn:name":"M\u0101sundia",
    "gn:population":0,
    "gn:timezone":"Asia/Dhaka",
    "iso:country":"BD",
    "name:ben_x_preferred":[
        "M\u0101sundia"
    ],
    "wof:name":"Masundia",
    "wof:placetype":"locality"
},
  "geometry": {"coordinates":[89.67607,22.91007],"type":"Point"}
}