{
  "type": "Feature",
  "properties": {
    "gn:admin1_code":"82",
    "gn:admin2_code":"4044.0",
    "gn:admin3_code":"404480.0",
    "gn:admin4_code":"40448031.0",
    "gn:asciiname":"Nutan Tripura Kandi",
    "gn:country_code":"BD",
    "gn:dem":14,
    "gn:feature_class":"P",
    "gn:feature_code":"PPL",
    "gn:name":"Nutan Tripura Kandi",
    "gn:population":0,
    "gn:timezone":"Asia/Dhaka",
    "iso:country":"BD",
    "name:ben_x_preferred":[
        "Nutan Tripura Kandi"
    ],
    "wof:name":"Nutan Tripura Kandi",
    "wof:placetype":"locality"
},
  "geometry": {"coordinates":[89.21525,23.62632],"type":"Point"}
}