{
  "type": "Feature",
  "properties": {
    "gn:admin1_code":"81",
    "gn:admin2_code":"3056.0",
    "gn:admin3_code":"305610.0",
    "gn:admin4_code":"30561076.0",
    "gn:asciiname":"Agkalia",
    "gn:country_code":"BD",
    "gn:dem":16,
    "gn:feature_class":"P",
    "gn:feature_code":"PPL",
    "gn:name":"Agkalia",
    "gn:population":0,
    "gn:timezone":"Asia/Dhaka",
    "iso:country":"BD",
    "name:und_x_variant":[
        "\u0100g Kalia"
    ],
    "wof:name":"Agkalia",
    "wof:placetype":"locality"
},
  "geometry": {"coordinates":[89.91745999999998,23.96698],"type":"Point"}
}