{
  "type": "Feature",
  "properties": {
    "gn:admin1_code":"83",
    "gn:admin2_code":"5064.0",
    "gn:admin3_code":"506403.0",
    "gn:admin4_code":"50640384.0",
    "gn:asciiname":"Choudhuri Bhabanipur",
    "gn:country_code":"BD",
    "gn:dem":18,
    "gn:feature_class":"P",
    "gn:feature_code":"PPL",
    "gn:name":"Choudhuri Bhabanipur",
    "gn:population":0,
    "gn:timezone":"Asia/Dhaka",
    "iso:country":"BD",
    "name:ben_x_preferred":[
        "Choudhuri Bhabanipur"
    ],
    "name:ben_x_variant":[
        "Chaudhuri Bhab\u0101nipur"
    ],
    "wof:name":"Choudhuri Bhabanipur",
    "wof:placetype":"locality"
},
  "geometry": {"coordinates":[88.94615999999998,24.65098],"type":"Point"}
}