{
  "type": "Feature",
  "properties": {
    "gn:admin1_code":"87",
    "gn:admin2_code":"5549",
    "gn:admin3_code":"554906.0",
    "gn:admin4_code":"55490628.0",
    "gn:asciiname":"Kedar",
    "gn:country_code":"BD",
    "gn:dem":32,
    "gn:feature_class":"P",
    "gn:feature_code":"PPL",
    "gn:name":"Kedar",
    "gn:population":0,
    "gn:timezone":"Asia/Dhaka",
    "iso:country":"BD",
    "name:deu_x_preferred":[
        "Kedar"
    ],
    "name:fas_x_preferred":[
        "\u0642\u06cc\u062f\u0627\u0631"
    ],
    "name:fra_x_preferred":[
        "Kedar"
    ],
    "name:heb_x_preferred":[
        "\u05e7\u05d9\u05d3\u05e8"
    ],
    "name:por_x_preferred":[
        "Quedar"
    ],
    "wof:name":"Kedar",
    "wof:placetype":"locality"
},
  "geometry": {"coordinates":[89.77773000000001,26.07421],"type":"Point"}
}