{
  "type": "Feature",
  "properties": {
    "gn:admin1_code":"81",
    "gn:admin2_code":"3029",
    "gn:admin3_code":"302903.0",
    "gn:admin4_code":"30290352.0",
    "gn:asciiname":"North Char Narayandia",
    "gn:cc2":"BD",
    "gn:country_code":"BD",
    "gn:dem":7,
    "gn:feature_class":"P",
    "gn:feature_code":"PPL",
    "gn:name":"North Char N\u0101r\u0101yandia",
    "gn:population":0,
    "gn:timezone":"Asia/Dhaka",
    "iso:country":"BD",
    "name:und_x_variant":[
        "Uttar Char Narayandia",
        "North Char N\u0101r\u0101yandia"
    ],
    "wof:name":"North Char Narayandia",
    "wof:placetype":"locality"
},
  "geometry": {"coordinates":[89.61667,23.36667000000001],"type":"Point"}
}