{
  "type": "Feature",
  "properties": {
    "gn:admin1_code":"H",
    "gn:admin2_code":"3072.0",
    "gn:admin3_code":"307240.0",
    "gn:admin4_code":"30724083.0",
    "gn:asciiname":"Dhopapara",
    "gn:country_code":"BD",
    "gn:dem":13,
    "gn:feature_class":"P",
    "gn:feature_code":"PPL",
    "gn:name":"Dhop\u0101p\u0101ra",
    "gn:population":0,
    "gn:timezone":"Asia/Dhaka",
    "iso:country":"BD",
    "wof:name":"Dhopapara",
    "wof:placetype":"locality"
},
  "geometry": {"coordinates":[90.86869,24.97007],"type":"Point"}
}