{
  "type": "Feature",
  "properties": {
    "gn:admin1_code":"87",
    "gn:admin2_code":"5573.0",
    "gn:admin3_code":"557315.0",
    "gn:admin4_code":"55731595.0",
    "gn:asciiname":"Khanabari",
    "gn:country_code":"BD",
    "gn:dem":57,
    "gn:feature_class":"P",
    "gn:feature_code":"PPL",
    "gn:name":"Kh\u0101nab\u0101ri",
    "gn:population":0,
    "gn:timezone":"Asia/Dhaka",
    "iso:country":"BD",
    "name:ben_x_preferred":[
        "Kh\u0101nab\u0101ri"
    ],
    "wof:name":"Khanabari",
    "wof:placetype":"locality"
},
  "geometry": {"coordinates":[88.78804000000002,26.09726],"type":"Point"}
}