{
  "type": "Feature",
  "properties": {
    "gn:admin1_code":"85",
    "gn:admin2_code":"1004.0",
    "gn:admin3_code":"100419.0",
    "gn:admin4_code":"10041923.0",
    "gn:asciiname":"Kalagachia",
    "gn:country_code":"BD",
    "gn:dem":9,
    "gn:feature_class":"P",
    "gn:feature_code":"PPL",
    "gn:name":"Kal\u0101g\u0101chia",
    "gn:population":0,
    "gn:timezone":"Asia/Dhaka",
    "iso:country":"BD",
    "name:ben_x_preferred":[
        "Kal\u0101g\u0101chia"
    ],
    "wof:name":"Kalagachia",
    "wof:placetype":"locality"
},
  "geometry": {"coordinates":[90.08835000000001,22.3161],"type":"Point"}
}