{
  "type": "Feature",
  "properties": {
    "gn:admin1_code":"82",
    "gn:admin2_code":"4001.0",
    "gn:admin3_code":"400177.0",
    "gn:admin4_code":"40017776.0",
    "gn:asciiname":"Tafalbaria",
    "gn:country_code":"BD",
    "gn:dem":13,
    "gn:feature_class":"P",
    "gn:feature_code":"PPL",
    "gn:name":"Tafalbaria",
    "gn:population":0,
    "gn:timezone":"Asia/Dhaka",
    "iso:country":"BD",
    "name:ben_x_preferred":[
        "Tafalbaria"
    ],
    "wof:name":"Tafalbaria",
    "wof:placetype":"locality"
},
  "geometry": {"coordinates":[89.82186,22.26494],"type":"Point"}
}