{
  "type": "Feature",
  "properties": {
    "gn:admin1_code":"87",
    "gn:admin2_code":"5585",
    "gn:admin3_code":"558527.0",
    "gn:admin4_code":"55852731.0",
    "gn:asciiname":"Arazi Niamat",
    "gn:country_code":"BD",
    "gn:dem":39,
    "gn:feature_class":"P",
    "gn:feature_code":"PPL",
    "gn:name":"Ar\u0101zi Ni\u0101mat",
    "gn:population":0,
    "gn:timezone":"Asia/Dhaka",
    "iso:country":"BD",
    "name:ben_x_preferred":[
        "Ar\u0101zi Ni\u0101mat"
    ],
    "wof:name":"Arazi Niamat",
    "wof:placetype":"locality"
},
  "geometry": {"coordinates":[89.22748,25.82106],"type":"Point"}
}