{
  "type": "Feature",
  "properties": {
    "gn:admin1_code":"87",
    "gn:admin2_code":"5552",
    "gn:admin3_code":"555233.0",
    "gn:admin4_code":"55523328.0",
    "gn:asciiname":"Kishmat Nohali",
    "gn:country_code":"BD",
    "gn:dem":42,
    "gn:feature_class":"P",
    "gn:feature_code":"PPL",
    "gn:name":"Kishmat Nohali",
    "gn:population":0,
    "gn:timezone":"Asia/Dhaka",
    "iso:country":"BD",
    "name:ben_x_preferred":[
        "Kishmat Nohali"
    ],
    "wof:name":"Kishmat Nohali",
    "wof:placetype":"locality"
},
  "geometry": {"coordinates":[89.12402,25.99089],"type":"Point"}
}