{
  "type": "Feature",
  "properties": {
    "gn:admin1_code":"83",
    "gn:admin2_code":"5064.0",
    "gn:admin3_code":"506447.0",
    "gn:admin4_code":"50644740.0",
    "gn:asciiname":"Chak Ramananda",
    "gn:country_code":"BD",
    "gn:dem":18,
    "gn:feature_class":"P",
    "gn:feature_code":"PPL",
    "gn:name":"Chak R\u0101m\u0101nanda",
    "gn:population":0,
    "gn:timezone":"Asia/Dhaka",
    "iso:country":"BD",
    "name:ben_x_preferred":[
        "Chak R\u0101m\u0101nanda"
    ],
    "name:und_x_variant":[
        "Chak Ramonanda"
    ],
    "wof:name":"Chak Ramananda",
    "wof:placetype":"locality"
},
  "geometry": {"coordinates":[88.77061999999999,24.73811],"type":"Point"}
}