{
  "type": "Feature",
  "properties": {
    "gn:admin1_code":"83",
    "gn:admin2_code":"5064",
    "gn:admin3_code":"506450.0",
    "gn:admin4_code":"50645057.0",
    "gn:asciiname":"Ramchandrapur",
    "gn:country_code":"BD",
    "gn:dem":23,
    "gn:feature_class":"P",
    "gn:feature_code":"PPL",
    "gn:name":"R\u0101mchandrapur",
    "gn:population":0,
    "gn:timezone":"Asia/Dhaka",
    "iso:country":"BD",
    "name:ben_x_preferred":[
        "R\u0101mchandrapur"
    ],
    "wof:name":"Ramchandrapur",
    "wof:placetype":"locality"
},
  "geometry": {"coordinates":[88.74008000000001,24.93969],"type":"Point"}
}