{
  "type": "Feature",
  "properties": {
    "gn:admin1_code":"84",
    "gn:admin2_code":"2003.0",
    "gn:admin3_code":"200351.0",
    "gn:admin4_code":"20035115.0",
    "gn:asciiname":"Aziznagar",
    "gn:country_code":"BD",
    "gn:dem":33,
    "gn:feature_class":"P",
    "gn:feature_code":"PPL",
    "gn:name":"Aziznagar",
    "gn:population":0,
    "gn:timezone":"Asia/Dhaka",
    "iso:country":"BD",
    "name:ben_x_preferred":[
        "Aziznagar"
    ],
    "wof:name":"Aziznagar",
    "wof:placetype":"locality"
},
  "geometry": {"coordinates":[92.06637000000001,21.90475],"type":"Point"}
}