{
  "type": "Feature",
  "properties": {
    "gn:admin1_code":"H",
    "gn:admin2_code":"3089",
    "gn:admin3_code":"308990.0",
    "gn:admin4_code":"30899094.0",
    "gn:asciiname":"Tatihati",
    "gn:country_code":"BD",
    "gn:dem":27,
    "gn:feature_class":"P",
    "gn:feature_code":"PPL",
    "gn:name":"Tatihati",
    "gn:population":0,
    "gn:timezone":"Asia/Dhaka",
    "iso:country":"BD",
    "wof:name":"Tatihati",
    "wof:placetype":"locality"
},
  "geometry": {"coordinates":[89.9375,25.1626],"type":"Point"}
}