{
  "type": "Feature",
  "properties": {
    "gn:admin1_code":"82",
    "gn:asciiname":"Bhaijora",
    "gn:country_code":"BD",
    "gn:dem":12,
    "gn:feature_class":"P",
    "gn:feature_code":"PPL",
    "gn:name":"Bhaijora",
    "gn:population":0,
    "gn:timezone":"Asia/Dhaka",
    "iso:country":"BD",
    "name:ben_x_preferred":[
        "Bhaijora"
    ],
    "wof:name":"Bhaijora",
    "wof:placetype":"locality"
},
  "geometry": {"coordinates":[89.91054,22.21478],"type":"Point"}
}