{
  "type": "Feature",
  "properties": {
    "gn:admin1_code":"81",
    "gn:admin2_code":"3086.0",
    "gn:admin3_code":"308669.0",
    "gn:admin4_code":"30866966.0",
    "gn:asciiname":"Chandsar",
    "gn:country_code":"BD",
    "gn:dem":10,
    "gn:feature_class":"P",
    "gn:feature_code":"PPL",
    "gn:name":"Ch\u0101nds\u0101r",
    "gn:population":0,
    "gn:timezone":"Asia/Dhaka",
    "iso:country":"BD",
    "wof:name":"Chandsar",
    "wof:placetype":"locality"
},
  "geometry": {"coordinates":[90.38663,23.21827],"type":"Point"}
}