{
  "type": "Feature",
  "properties": {
    "gn:admin1_code":"H",
    "gn:admin2_code":"3072",
    "gn:admin3_code":"307274.0",
    "gn:admin4_code":"30727487.0",
    "gn:asciiname":"Thakurkona",
    "gn:country_code":"BD",
    "gn:dem":14,
    "gn:feature_class":"P",
    "gn:feature_code":"PPL",
    "gn:name":"Th\u0101kurkona",
    "gn:population":0,
    "gn:timezone":"Asia/Dhaka",
    "iso:country":"BD",
    "name:und_x_variant":[
        "Th\u0101kurkona",
        "Th\u0101kur\u0101kona"
    ],
    "wof:name":"Thakurkona",
    "wof:placetype":"locality"
},
  "geometry": {"coordinates":[90.76622999999999,24.90683],"type":"Point"}
}