{
  "type": "Feature",
  "properties": {
    "gn:admin1_code":"87",
    "gn:admin2_code":"5594.0",
    "gn:admin3_code":"559494.0",
    "gn:admin4_code":"55949468.0",
    "gn:asciiname":"Paikpara",
    "gn:country_code":"BD",
    "gn:dem":57,
    "gn:feature_class":"P",
    "gn:feature_code":"PPL",
    "gn:name":"P\u0101ikp\u0101ra",
    "gn:population":0,
    "gn:timezone":"Asia/Dhaka",
    "iso:country":"BD",
    "name:ben_x_preferred":[
        "P\u0101ikp\u0101ra"
    ],
    "wof:name":"Paikpara",
    "wof:placetype":"locality"
},
  "geometry": {"coordinates":[88.37815000000001,26.0216],"type":"Point"}
}