{
  "type": "Feature",
  "properties": {
    "gn:admin1_code":"85",
    "gn:admin2_code":"1042",
    "gn:admin3_code":"104284.0",
    "gn:admin4_code":"10428467.0",
    "gn:asciiname":"West Phulahar",
    "gn:country_code":"BD",
    "gn:dem":13,
    "gn:feature_class":"P",
    "gn:feature_code":"PPL",
    "gn:name":"West Phulah\u0101r",
    "gn:population":0,
    "gn:timezone":"Asia/Dhaka",
    "iso:country":"BD",
    "name:und_x_variant":[
        "West Phulhar",
        "West Phulah\u0101r"
    ],
    "wof:name":"West Phulahar",
    "wof:placetype":"locality"
},
  "geometry": {"coordinates":[90.08349,22.54351],"type":"Point"}
}