{
  "type": "Feature",
  "properties": {
    "gn:admin1_code":"81",
    "gn:admin2_code":"3067.0",
    "gn:admin3_code":"306768.0",
    "gn:admin4_code":"30676894.0",
    "gn:asciiname":"Bhetair",
    "gn:country_code":"BD",
    "gn:dem":13,
    "gn:feature_class":"P",
    "gn:feature_code":"PPL",
    "gn:name":"Bhetair",
    "gn:population":0,
    "gn:timezone":"Asia/Dhaka",
    "iso:country":"BD",
    "wof:name":"Bhetair",
    "wof:placetype":"locality"
},
  "geometry": {"coordinates":[90.53968999999999,23.92485],"type":"Point"}
}