{
  "type": "Feature",
  "properties": {
    "gn:admin1_code":"87",
    "gn:admin2_code":"5585",
    "gn:admin3_code":"558576.0",
    "gn:admin4_code":"55857606.0",
    "gn:asciiname":"Tatarpur",
    "gn:country_code":"BD",
    "gn:dem":33,
    "gn:feature_class":"P",
    "gn:feature_code":"PPL",
    "gn:name":"Tatarpur",
    "gn:population":0,
    "gn:timezone":"Asia/Dhaka",
    "iso:country":"BD",
    "name:ben_x_preferred":[
        "Tatarpur"
    ],
    "wof:name":"Tatarpur",
    "wof:placetype":"locality"
},
  "geometry": {"coordinates":[89.23501,25.37326],"type":"Point"}
}