{
  "type": "Feature",
  "properties": {
    "gn:admin1_code":"87",
    "gn:admin2_code":"5527.0",
    "gn:admin3_code":"552738.0",
    "gn:admin4_code":"55273847.0",
    "gn:asciiname":"Shaharapur",
    "gn:country_code":"BD",
    "gn:dem":38,
    "gn:feature_class":"P",
    "gn:feature_code":"PPL",
    "gn:name":"Sh\u0101h\u0101r\u0101pur",
    "gn:population":0,
    "gn:timezone":"Asia/Dhaka",
    "iso:country":"BD",
    "name:ben_x_preferred":[
        "Sh\u0101h\u0101r\u0101pur"
    ],
    "wof:name":"Shaharapur",
    "wof:placetype":"locality"
},
  "geometry": {"coordinates":[88.8691,25.49948],"type":"Point"}
}