{
  "type": "Feature",
  "properties": {
    "gn:admin1_code":"87",
    "gn:admin2_code":"5527",
    "gn:admin3_code":"552743.0",
    "gn:admin4_code":"55274319.0",
    "gn:asciiname":"Chak Baira",
    "gn:country_code":"BD",
    "gn:dem":31,
    "gn:feature_class":"P",
    "gn:feature_code":"PPL",
    "gn:name":"Chak Baira",
    "gn:population":0,
    "gn:timezone":"Asia/Dhaka",
    "iso:country":"BD",
    "name:ben_x_preferred":[
        "Chak Baira"
    ],
    "wof:name":"Chak Baira",
    "wof:placetype":"locality"
},
  "geometry": {"coordinates":[89.17644,25.31029],"type":"Point"}
}