{
  "type": "Feature",
  "properties": {
    "gn:admin1_code":"85",
    "gn:admin2_code":"1006",
    "gn:admin3_code":"100632.0",
    "gn:admin4_code":"10063223.0",
    "gn:asciiname":"Uttar Dhandoba",
    "gn:country_code":"BD",
    "gn:dem":9,
    "gn:feature_class":"P",
    "gn:feature_code":"PPL",
    "gn:name":"Uttar Dh\u0101ndoba",
    "gn:population":0,
    "gn:timezone":"Asia/Dhaka",
    "iso:country":"BD",
    "name:und_x_variant":[
        "Uttar Dh\u0101ndoba",
        "North Dh\u0101n Doba"
    ],
    "wof:name":"Uttar Dhandoba",
    "wof:placetype":"locality"
},
  "geometry": {"coordinates":[90.20502999999999,23.01191],"type":"Point"}
}