{
  "type": "Feature",
  "properties": {
    "gn:admin1_code":"82",
    "gn:admin2_code":"4050.0",
    "gn:admin3_code":"405039.0",
    "gn:admin4_code":"40503947.0",
    "gn:asciiname":"Pratabpur",
    "gn:country_code":"BD",
    "gn:dem":20,
    "gn:feature_class":"P",
    "gn:feature_code":"PPL",
    "gn:name":"Prat\u0101bpur",
    "gn:population":0,
    "gn:timezone":"Asia/Dhaka",
    "iso:country":"BD",
    "name:ben_x_preferred":[
        "Prat\u0101bpur"
    ],
    "wof:name":"Pratabpur",
    "wof:placetype":"locality"
},
  "geometry": {"coordinates":[88.86939,23.93486],"type":"Point"}
}