{
  "type": "Feature",
  "properties": {
    "gn:country":"BD",
    "gn:fcode":"PPL",
    "gn:population":127481,
    "iso:country":"BD",
    "name:ben_x_preferred":[
        "\u09b8\u09bf\u09b0\u09be\u099c\u0997\u099e\u09cd\u099c"
    ],
    "name:ceb_x_preferred":[
        "Sir\u0101jganj"
    ],
    "name:eng_x_preferred":[
        "Sirajganj"
    ],
    "name:epo_x_preferred":[
        "Sira\u011dgan\u011d"
    ],
    "name:fra_x_preferred":[
        "Sirajganj"
    ],
    "name:ita_x_preferred":[
        "Sirajganj"
    ],
    "name:kaz_x_preferred":[
        "\u0421\u0438\u0440\u0430\u0434\u0436\u0433\u0430\u043d\u0434\u0436"
    ],
    "name:lit_x_preferred":[
        "Sirad\u017egand\u017eas"
    ],
    "name:nld_x_preferred":[
        "Sirajganj"
    ],
    "name:pol_x_preferred":[
        "Sirajganj"
    ],
    "name:ron_x_preferred":[
        "Sirajganj"
    ],
    "name:rus_x_preferred":[
        "\u0421\u0438\u0440\u0430\u0434\u0436\u0433\u0430\u043d\u0434\u0436"
    ],
    "name:spa_x_preferred":[
        "Sirajganj"
    ],
    "name:swe_x_preferred":[
        "Sirajganj"
    ],
    "name:tha_x_preferred":[
        "\u0e2a\u0e34\u0e23\u0e32\u0e0a\u0e02\u0e31\u0e19\u0e0a\u0e4c"
    ],
    "name:und_x_variant":[
        "Serajganj Municipality"
    ],
    "name:urd_x_preferred":[
        "\u0633\u0631\u0627\u062c \u06af\u0646\u062c"
    ],
    "qs:name":"Sir\u0101jganj",
    "qs:photos_9r":0,
    "qs:photos_sr":0,
    "qs:pop_sr":"9",
    "wof:name":"Sir\u0101jganj",
    "wof:placetype":"locality",
    "wof:population":127481
},
  "geometry": {"coordinates":[89.70802,24.45771],"type":"Point"}
}