{
  "type": "Feature",
  "properties": {
    "gn:admin1_code":"87",
    "gn:admin2_code":"5549",
    "gn:admin3_code":"554918.0",
    "gn:admin4_code":"55491854.0",
    "gn:asciiname":"Kasipur",
    "gn:country_code":"BD",
    "gn:dem":34,
    "gn:feature_class":"P",
    "gn:feature_code":"PPL",
    "gn:name":"K\u0101sipur",
    "gn:population":0,
    "gn:timezone":"Asia/Dhaka",
    "iso:country":"BD",
    "name:ben_x_preferred":[
        "K\u0101sipur"
    ],
    "wof:name":"Kasipur",
    "wof:placetype":"locality"
},
  "geometry": {"coordinates":[89.61173000000002,26.00677],"type":"Point"}
}