{
  "type": "Feature",
  "properties": {
    "gn:admin1_code":"84",
    "gn:admin2_code":"2022.0",
    "gn:admin3_code":"202266.0",
    "gn:admin4_code":"20226647.0",
    "gn:asciiname":"Ghilatalipara",
    "gn:country_code":"BD",
    "gn:dem":20,
    "gn:feature_class":"P",
    "gn:feature_code":"PPL",
    "gn:name":"Ghil\u0101talip\u0101ra",
    "gn:population":0,
    "gn:timezone":"Asia/Dhaka",
    "iso:country":"BD",
    "name:ben_x_preferred":[
        "Ghil\u0101talip\u0101ra"
    ],
    "wof:name":"Ghilatalipara",
    "wof:placetype":"locality"
},
  "geometry": {"coordinates":[92.21414,21.46768],"type":"Point"}
}