{
  "type": "Feature",
  "properties": {
    "gn:admin1_code":"82",
    "gn:admin2_code":"4041.0",
    "gn:admin3_code":"404161.0",
    "gn:admin4_code":"40416133.0",
    "gn:asciiname":"Bara Chetla",
    "gn:country_code":"BD",
    "gn:dem":12,
    "gn:feature_class":"P",
    "gn:feature_code":"PPL",
    "gn:name":"Bara Chetla",
    "gn:population":0,
    "gn:timezone":"Asia/Dhaka",
    "iso:country":"BD",
    "wof:name":"Bara Chetla",
    "wof:placetype":"locality"
},
  "geometry": {"coordinates":[89.09926999999998,23.00765],"type":"Point"}
}