{
  "type": "Feature",
  "properties": {
    "gn:admin1_code":"87",
    "gn:admin2_code":"5527",
    "gn:admin3_code":"552710.0",
    "gn:admin4_code":"55271035.0",
    "gn:asciiname":"Uttar Kandipur",
    "gn:country_code":"BD",
    "gn:dem":32,
    "gn:feature_class":"P",
    "gn:feature_code":"PPL",
    "gn:name":"Uttar Kandipur",
    "gn:population":0,
    "gn:timezone":"Asia/Dhaka",
    "iso:country":"BD",
    "name:ben_x_preferred":[
        "Uttar Kandipur"
    ],
    "wof:name":"Uttar Kandipur",
    "wof:placetype":"locality"
},
  "geometry": {"coordinates":[89.01517,25.38444],"type":"Point"}
}