{
  "type": "Feature",
  "properties": {
    "gn:admin1_code":"82",
    "gn:admin2_code":"4041.0",
    "gn:admin3_code":"404161.0",
    "gn:admin4_code":"40416116.0",
    "gn:asciiname":"Champakana",
    "gn:country_code":"BD",
    "gn:dem":11,
    "gn:feature_class":"P",
    "gn:feature_code":"PPL",
    "gn:name":"Champ\u0101kana",
    "gn:population":0,
    "gn:timezone":"Asia/Dhaka",
    "iso:country":"BD",
    "name:ben_x_preferred":[
        "Champ\u0101kana"
    ],
    "wof:name":"Champakana",
    "wof:placetype":"locality"
},
  "geometry": {"coordinates":[89.28328,23.0872],"type":"Point"}
}