{
  "type": "Feature",
  "properties": {
    "gn:admin1_code":"85",
    "gn:admin2_code":"1078.0",
    "gn:admin3_code":"107866.0",
    "gn:admin4_code":"10786611.0",
    "gn:asciiname":"Nishanbaria",
    "gn:country_code":"BD",
    "gn:dem":10,
    "gn:feature_class":"P",
    "gn:feature_code":"PPL",
    "gn:name":"Nishanbaria",
    "gn:population":0,
    "gn:timezone":"Asia/Dhaka",
    "iso:country":"BD",
    "name:ben_x_preferred":[
        "Nishanbaria"
    ],
    "wof:name":"Nishanbaria",
    "wof:placetype":"locality"
},
  "geometry": {"coordinates":[90.21997,22.00955],"type":"Point"}
}