{
  "type": "Feature",
  "properties": {
    "gn:admin1_code":"83",
    "gn:admin2_code":"5070.0",
    "gn:admin3_code":"507018.0",
    "gn:admin4_code":"50701837.0",
    "gn:asciiname":"Adatala",
    "gn:country_code":"BD",
    "gn:dem":29,
    "gn:feature_class":"P",
    "gn:feature_code":"PPL",
    "gn:name":"\u0100d\u0101tala",
    "gn:population":0,
    "gn:timezone":"Asia/Dhaka",
    "iso:country":"BD",
    "name:ben_x_preferred":[
        "\u0100d\u0101tala"
    ],
    "wof:name":"Adatala",
    "wof:placetype":"locality"
},
  "geometry": {"coordinates":[88.25301,24.91176],"type":"Point"}
}