{
  "type": "Feature",
  "properties": {
    "gn:admin1_code":"82",
    "gn:admin2_code":"4087.0",
    "gn:admin3_code":"408747.0",
    "gn:admin4_code":"40874779.0",
    "gn:asciiname":"Khenji",
    "gn:country_code":"BD",
    "gn:dem":6,
    "gn:feature_class":"P",
    "gn:feature_code":"PPL",
    "gn:name":"Khenji",
    "gn:population":0,
    "gn:timezone":"Asia/Dhaka",
    "iso:country":"BD",
    "name:ben_x_preferred":[
        "Khenji"
    ],
    "wof:name":"Khenji",
    "wof:placetype":"locality"
},
  "geometry": {"coordinates":[88.97825,22.51666],"type":"Point"}
}