{
  "type": "Feature",
  "properties": {
    "gn:admin1_code":"H",
    "gn:admin2_code":"3072",
    "gn:admin3_code":"307209.0",
    "gn:admin4_code":"30720983.0",
    "gn:asciiname":"Sindha",
    "gn:country_code":"BD",
    "gn:dem":12,
    "gn:feature_class":"P",
    "gn:feature_code":"PPL",
    "gn:name":"Sindha",
    "gn:population":0,
    "gn:timezone":"Asia/Dhaka",
    "iso:country":"BD",
    "wof:name":"Sindha",
    "wof:placetype":"locality"
},
  "geometry": {"coordinates":[90.97968,24.89885],"type":"Point"}
}