{
  "type": "Feature",
  "properties": {
    "gn:admin1_code":"81",
    "gn:admin2_code":"3033",
    "gn:admin3_code":"303386.0",
    "gn:admin4_code":"30338676.0",
    "gn:asciiname":"Lohagachh",
    "gn:country_code":"BD",
    "gn:dem":21,
    "gn:feature_class":"P",
    "gn:feature_code":"PPL",
    "gn:name":"Loh\u0101g\u0101chh",
    "gn:population":0,
    "gn:timezone":"Asia/Dhaka",
    "iso:country":"BD",
    "wof:name":"Lohagachh",
    "wof:placetype":"locality"
},
  "geometry": {"coordinates":[90.47208999999999,24.18455],"type":"Point"}
}