{
  "type": "Feature",
  "properties": {
    "gn:admin1_code":"82",
    "gn:admin2_code":"4065",
    "gn:admin3_code":"406552.0",
    "gn:admin4_code":"40655247.0",
    "gn:asciiname":"Jhamarghop",
    "gn:country_code":"BD",
    "gn:dem":10,
    "gn:feature_class":"P",
    "gn:feature_code":"PPL",
    "gn:name":"Jh\u0101m\u0101rghop",
    "gn:population":0,
    "gn:timezone":"Asia/Dhaka",
    "iso:country":"BD",
    "wof:name":"Jhamarghop",
    "wof:placetype":"locality"
},
  "geometry": {"coordinates":[89.55461,23.30248],"type":"Point"}
}