{
  "type": "Feature",
  "properties": {
    "gn:admin1_code":"84",
    "gn:admin2_code":"2019",
    "gn:admin3_code":"201981.0",
    "gn:admin4_code":"20198122.0",
    "gn:asciiname":"Nairpar",
    "gn:country_code":"BD",
    "gn:dem":12,
    "gn:feature_class":"P",
    "gn:feature_code":"PPL",
    "gn:name":"Nairp\u0101r",
    "gn:population":0,
    "gn:timezone":"Asia/Dhaka",
    "iso:country":"BD",
    "wof:name":"Nairpar",
    "wof:placetype":"locality"
},
  "geometry": {"coordinates":[90.98975,23.70329],"type":"Point"}
}