{
  "type": "Feature",
  "properties": {
    "gn:admin1_code":"83",
    "gn:admin2_code":"5069",
    "gn:admin3_code":"506991.0",
    "gn:admin4_code":"50699147.0",
    "gn:asciiname":"Tajpur",
    "gn:country_code":"BD",
    "gn:dem":16,
    "gn:feature_class":"P",
    "gn:feature_code":"PPL",
    "gn:name":"T\u0101jpur",
    "gn:population":0,
    "gn:timezone":"Asia/Dhaka",
    "iso:country":"BD",
    "name:urd_x_preferred":[
        "\u062a\u0627\u062c\u067e\u0648\u0631"
    ],
    "wof:name":"Tajpur",
    "wof:placetype":"locality"
},
  "geometry": {"coordinates":[89.19211999999997,24.48892],"type":"Point"}
}