{
  "type": "Feature",
  "properties": {
    "gn:admin1_code":"85",
    "gn:admin2_code":"1079.0",
    "gn:admin3_code":"107914.0",
    "gn:admin4_code":"10791447.0",
    "gn:asciiname":"Tewaripur",
    "gn:country_code":"BD",
    "gn:dem":8,
    "gn:feature_class":"P",
    "gn:feature_code":"PPL",
    "gn:name":"Tewaripur",
    "gn:population":0,
    "gn:timezone":"Asia/Dhaka",
    "iso:country":"BD",
    "name:ben_x_preferred":[
        "Tewaripur"
    ],
    "wof:name":"Tewaripur",
    "wof:placetype":"locality"
},
  "geometry": {"coordinates":[90.08946,22.4451],"type":"Point"}
}