{
  "type": "Feature",
  "properties": {
    "gn:admin1_code":"83",
    "gn:admin2_code":"5064.0",
    "gn:admin3_code":"506403.0",
    "gn:admin4_code":"50640384.0",
    "gn:asciiname":"Bahala",
    "gn:country_code":"BD",
    "gn:dem":19,
    "gn:feature_class":"P",
    "gn:feature_code":"PPL",
    "gn:name":"Bahala",
    "gn:population":0,
    "gn:timezone":"Asia/Dhaka",
    "iso:country":"BD",
    "name:ben_x_preferred":[
        "Bahala"
    ],
    "wof:name":"Bahala",
    "wof:placetype":"locality"
},
  "geometry": {"coordinates":[88.96736999999997,24.68776],"type":"Point"}
}