{
  "type": "Feature",
  "properties": {
    "gn:admin1_code":"82",
    "gn:admin2_code":"4047",
    "gn:admin3_code":"404753.0",
    "gn:admin4_code":"40475311.0",
    "gn:asciiname":"Islampur",
    "gn:country_code":"BD",
    "gn:dem":7,
    "gn:feature_class":"P",
    "gn:feature_code":"PPL",
    "gn:name":"Isl\u0101mpur",
    "gn:population":0,
    "gn:timezone":"Asia/Dhaka",
    "iso:country":"BD",
    "name:ben_x_preferred":[
        "Isl\u0101mpur"
    ],
    "name:ben_x_variant":[
        "\u0987\u09b8\u09b2\u09be\u09ae\u09aa\u09c1\u09b0"
    ],
    "name:ceb_x_preferred":[
        "Islampur"
    ],
    "name:deu_x_preferred":[
        "Islampur"
    ],
    "name:new_x_preferred":[
        "\u0907\u0938\u094d\u0932\u093e\u092e\u092a\u0941\u0930"
    ],
    "name:ori_x_preferred":[
        "\u0b07\u0b38\u0b32\u0b3e\u0b2e\u0b2a\u0b41\u0b30"
    ],
    "name:swe_x_preferred":[
        "Islampur"
    ],
    "name:vie_x_preferred":[
        "Islampur"
    ],
    "wof:name":"Islampur",
    "wof:placetype":"locality"
},
  "geometry": {"coordinates":[89.28491,22.45428],"type":"Point"}
}