{
  "type": "Feature",
  "properties": {
    "gn:admin1_code":"84",
    "gn:admin2_code":"2019",
    "gn:admin3_code":"201915.0",
    "gn:admin4_code":"20191556.0",
    "gn:asciiname":"Makimpur",
    "gn:country_code":"BD",
    "gn:dem":8,
    "gn:feature_class":"P",
    "gn:feature_code":"PPL",
    "gn:name":"Mak\u012bmpur",
    "gn:population":0,
    "gn:timezone":"Asia/Dhaka",
    "iso:country":"BD",
    "wof:name":"Makimpur",
    "wof:placetype":"locality"
},
  "geometry": {"coordinates":[91.06667,23.71667],"type":"Point"}
}