{
  "type": "Feature",
  "properties": {
    "gn:admin1_code":"81",
    "gn:admin2_code":"3086",
    "gn:admin3_code":"308614.0",
    "gn:admin4_code":"30861477.0",
    "gn:asciiname":"Kartikpur",
    "gn:country_code":"BD",
    "gn:dem":11,
    "gn:feature_class":"P",
    "gn:feature_code":"PPL",
    "gn:name":"K\u0101rtikpur",
    "gn:population":0,
    "gn:timezone":"Asia/Dhaka",
    "iso:country":"BD",
    "name:und_x_variant":[
        "Padm\u0101hogla",
        "K\u0101rtikpur"
    ],
    "wof:name":"Kartikpur",
    "wof:placetype":"locality"
},
  "geometry": {"coordinates":[90.47284999999999,23.23908],"type":"Point"}
}