{
  "type": "Feature",
  "properties": {
    "gn:admin1_code":"83",
    "gn:admin2_code":"5076.0",
    "gn:admin3_code":"507683.0",
    "gn:admin4_code":"50768309.0",
    "gn:asciiname":"Sonatola",
    "gn:country_code":"BD",
    "gn:dem":15,
    "gn:feature_class":"P",
    "gn:feature_code":"PPL",
    "gn:name":"Son\u0101tola",
    "gn:population":0,
    "gn:timezone":"Asia/Dhaka",
    "iso:country":"BD",
    "name:ben_x_preferred":[
        "Son\u0101tola"
    ],
    "wof:name":"Sonatola",
    "wof:placetype":"locality"
},
  "geometry": {"coordinates":[89.56208000000002,23.95272000000001],"type":"Point"}
}