{
  "type": "Feature",
  "properties": {
    "gn:admin1_code":"84",
    "gn:admin2_code":"2013.0",
    "gn:admin3_code":"201358.0",
    "gn:admin4_code":"20135863.0",
    "gn:asciiname":"Basabari",
    "gn:country_code":"BD",
    "gn:dem":7,
    "gn:feature_class":"P",
    "gn:feature_code":"PPL",
    "gn:name":"B\u0101s\u0101b\u0101ri",
    "gn:population":0,
    "gn:timezone":"Asia/Dhaka",
    "iso:country":"BD",
    "wof:name":"Basabari",
    "wof:placetype":"locality"
},
  "geometry": {"coordinates":[90.89924000000001,23.31982],"type":"Point"}
}