{
  "type": "Feature",
  "properties": {
    "gn:admin1_code":"81",
    "gn:admin2_code":"3056",
    "gn:admin3_code":"305678.0",
    "gn:admin4_code":"30567859.0",
    "gn:asciiname":"Maidinagar",
    "gn:country_code":"BD",
    "gn:dem":9,
    "gn:feature_class":"P",
    "gn:feature_code":"PPL",
    "gn:name":"Maidinagar",
    "gn:population":0,
    "gn:timezone":"Asia/Dhaka",
    "iso:country":"BD",
    "wof:name":"Maidinagar",
    "wof:placetype":"locality"
},
  "geometry": {"coordinates":[89.75353,23.88883],"type":"Point"}
}