{
  "type": "Feature",
  "properties": {
    "gn:admin1_code":"81",
    "gn:admin2_code":"3048",
    "gn:admin3_code":"304806.0",
    "gn:admin4_code":"30480686.0",
    "gn:asciiname":"Nilakhi Hapania",
    "gn:country_code":"BD",
    "gn:dem":12,
    "gn:feature_class":"P",
    "gn:feature_code":"PPL",
    "gn:name":"Nilakhi H\u0101p\u0101nia",
    "gn:population":0,
    "gn:timezone":"Asia/Dhaka",
    "iso:country":"BD",
    "wof:name":"Nilakhi Hapania",
    "wof:placetype":"locality"
},
  "geometry": {"coordinates":[90.86571000000001,24.24441],"type":"Point"}
}