{
  "type": "Feature",
  "properties": {
    "gn:admin1_code":"81",
    "gn:admin2_code":"3054",
    "gn:admin3_code":"305454.0",
    "gn:admin4_code":"30545429.0",
    "gn:asciiname":"Jhikarhati",
    "gn:country_code":"BD",
    "gn:dem":11,
    "gn:feature_class":"P",
    "gn:feature_code":"PPL",
    "gn:name":"Jhikarh\u0101ti",
    "gn:population":0,
    "gn:timezone":"Asia/Dhaka",
    "iso:country":"BD",
    "wof:name":"Jhikarhati",
    "wof:placetype":"locality"
},
  "geometry": {"coordinates":[90.15236,23.14359],"type":"Point"}
}