{
  "type": "Feature",
  "properties": {
    "gn:admin1_code":"81",
    "gn:admin2_code":"3059",
    "gn:admin3_code":"305944.0",
    "gn:admin4_code":"30594463.0",
    "gn:asciiname":"Kazirgaon",
    "gn:country_code":"BD",
    "gn:dem":7,
    "gn:feature_class":"P",
    "gn:feature_code":"PPL",
    "gn:name":"Kazirgaon",
    "gn:population":0,
    "gn:timezone":"Asia/Dhaka",
    "iso:country":"BD",
    "wof:name":"Kazirgaon",
    "wof:placetype":"locality"
},
  "geometry": {"coordinates":[90.40000000000001,23.48333],"type":"Point"}
}