{
  "type": "Feature",
  "properties": {
    "gn:admin1_code":"81",
    "gn:admin2_code":"3029.0",
    "gn:admin3_code":"302910.0",
    "gn:admin4_code":"30291055.0",
    "gn:asciiname":"Deora",
    "gn:country_code":"BD",
    "gn:dem":8,
    "gn:feature_class":"P",
    "gn:feature_code":"PPL",
    "gn:name":"Deora",
    "gn:population":0,
    "gn:timezone":"Asia/Dhaka",
    "iso:country":"BD",
    "wof:name":"Deora",
    "wof:placetype":"locality"
},
  "geometry": {"coordinates":[90.06010999999999,23.32791],"type":"Point"}
}