{
  "type": "Feature",
  "properties": {
    "gn:admin1_code":"81",
    "gn:admin2_code":"3056",
    "gn:admin3_code":"305670.0",
    "gn:admin4_code":"30567038.0",
    "gn:asciiname":"Uttar Kaziail",
    "gn:country_code":"BD",
    "gn:dem":11,
    "gn:feature_class":"P",
    "gn:feature_code":"PPL",
    "gn:name":"Uttar K\u0101zi\u0101il",
    "gn:population":0,
    "gn:timezone":"Asia/Dhaka",
    "iso:country":"BD",
    "wof:name":"Uttar Kaziail",
    "wof:placetype":"locality"
},
  "geometry": {"coordinates":[89.98079,23.96719],"type":"Point"}
}