{
  "type": "Feature",
  "properties": {
    "gn:admin1_code":"H",
    "gn:admin2_code":"3061.0",
    "gn:admin3_code":"306172.0",
    "gn:admin4_code":"30617255.0",
    "gn:asciiname":"Bahadurpur",
    "gn:country_code":"BD",
    "gn:dem":14,
    "gn:feature_class":"P",
    "gn:feature_code":"PPL",
    "gn:name":"B\u0101h\u0101durpur",
    "gn:population":0,
    "gn:timezone":"Asia/Dhaka",
    "iso:country":"BD",
    "name:fra_x_preferred":[
        "Bahadurpur"
    ],
    "name:pol_x_preferred":[
        "Bahadurpur"
    ],
    "wof:name":"Bahadurpur",
    "wof:placetype":"locality"
},
  "geometry": {"coordinates":[90.62801,24.55413],"type":"Point"}
}