{
  "type": "Feature",
  "properties": {
    "gn:admin1_code":"84",
    "gn:admin2_code":"2019",
    "gn:admin3_code":"201936.0",
    "gn:admin4_code":"20193682.0",
    "gn:asciiname":"Panchgachhia",
    "gn:country_code":"BD",
    "gn:dem":9,
    "gn:feature_class":"P",
    "gn:feature_code":"PPL",
    "gn:name":"P\u0101nchg\u0101chhia",
    "gn:population":0,
    "gn:timezone":"Asia/Dhaka",
    "iso:country":"BD",
    "name:und_x_variant":[
        "Panchgharia",
        "P\u0101nchg\u0101chhia"
    ],
    "wof:name":"Panchgachhia",
    "wof:placetype":"locality"
},
  "geometry": {"coordinates":[90.74876999999999,23.459],"type":"Point"}
}