{
  "type": "Feature",
  "properties": {
    "gn:admin1_code":"81",
    "gn:admin2_code":"3086.0",
    "gn:admin3_code":"308614.0",
    "gn:admin4_code":"30861443.0",
    "gn:asciiname":"Char Chanda",
    "gn:country_code":"BD",
    "gn:dem":11,
    "gn:feature_class":"P",
    "gn:feature_code":"PPL",
    "gn:name":"Char Ch\u0101nda",
    "gn:population":0,
    "gn:timezone":"Asia/Dhaka",
    "iso:country":"BD",
    "wof:name":"Char Chanda",
    "wof:placetype":"locality"
},
  "geometry": {"coordinates":[90.50488,23.2233],"type":"Point"}
}