{
  "type": "Feature",
  "properties": {
    "gn:admin1_code":"83",
    "gn:admin2_code":"5064",
    "gn:admin3_code":"506450.0",
    "gn:admin4_code":"50645095.0",
    "gn:asciiname":"Srirampur",
    "gn:country_code":"BD",
    "gn:dem":20,
    "gn:feature_class":"P",
    "gn:feature_code":"PPL",
    "gn:name":"Srir\u0101mpur",
    "gn:population":0,
    "gn:timezone":"Asia/Dhaka",
    "iso:country":"BD",
    "name:ben_x_preferred":[
        "Srir\u0101mpur"
    ],
    "wof:name":"Srirampur",
    "wof:placetype":"locality"
},
  "geometry": {"coordinates":[88.78615000000001,24.85338],"type":"Point"}
}