{
  "type": "Feature",
  "properties": {
    "gn:admin1_code":"82",
    "gn:admin2_code":"4041",
    "gn:admin3_code":"404123.0",
    "gn:admin4_code":"40412359.0",
    "gn:asciiname":"Kalagachhi",
    "gn:country_code":"BD",
    "gn:dem":8,
    "gn:feature_class":"P",
    "gn:feature_code":"PPL",
    "gn:name":"Kal\u0101g\u0101chhi",
    "gn:population":0,
    "gn:timezone":"Asia/Dhaka",
    "iso:country":"BD",
    "wof:name":"Kalagachhi",
    "wof:placetype":"locality"
},
  "geometry": {"coordinates":[89.03333000000001,23.06667],"type":"Point"}
}