{
  "type": "Feature",
  "properties": {
    "gn:admin1_code":"81",
    "gn:admin2_code":"3035.0",
    "gn:admin3_code":"303543.0",
    "gn:admin4_code":"30354381.0",
    "gn:asciiname":"Chapta Khairsakhari",
    "gn:country_code":"BD",
    "gn:dem":11,
    "gn:feature_class":"P",
    "gn:feature_code":"PPL",
    "gn:name":"Ch\u0101pta Khairs\u0101kh\u0101ri",
    "gn:population":0,
    "gn:timezone":"Asia/Dhaka",
    "iso:country":"BD",
    "name:ben_x_preferred":[
        "Ch\u0101pta Khairs\u0101kh\u0101ri"
    ],
    "wof:name":"Chapta Khairsakhari",
    "wof:placetype":"locality"
},
  "geometry": {"coordinates":[89.76002,23.19629],"type":"Point"}
}