{
  "type": "Feature",
  "properties": {
    "gn:admin1_code":"85",
    "gn:admin2_code":"1004.0",
    "gn:admin3_code":"100428.0",
    "gn:admin4_code":"10042895.0",
    "gn:asciiname":"Kumirmara",
    "gn:country_code":"BD",
    "gn:dem":9,
    "gn:feature_class":"P",
    "gn:feature_code":"PPL",
    "gn:name":"Kumirmara",
    "gn:population":0,
    "gn:timezone":"Asia/Dhaka",
    "iso:country":"BD",
    "name:ben_x_preferred":[
        "Kumirmara"
    ],
    "wof:name":"Kumirmara",
    "wof:placetype":"locality"
},
  "geometry": {"coordinates":[90.02589999999999,21.99371],"type":"Point"}
}