{
  "type": "Feature",
  "properties": {
    "gn:admin1_code":"83",
    "gn:admin2_code":"5070",
    "gn:admin3_code":"507066.0",
    "gn:admin4_code":"50706644.0",
    "gn:asciiname":"Shekhpur",
    "gn:country_code":"BD",
    "gn:dem":39,
    "gn:feature_class":"P",
    "gn:feature_code":"PPL",
    "gn:name":"Shekhpur",
    "gn:population":0,
    "gn:timezone":"Asia/Dhaka",
    "iso:country":"BD",
    "name:ben_x_preferred":[
        "Shekhpur"
    ],
    "name:ben_x_variant":[
        "Sheikhpur"
    ],
    "name:und_x_variant":[
        "Sekhpur"
    ],
    "wof:name":"Shekhpur",
    "wof:placetype":"locality"
},
  "geometry": {"coordinates":[88.37558,24.62239],"type":"Point"}
}