{
  "type": "Feature",
  "properties": {
    "gn:admin1_code":"87",
    "gn:admin2_code":"5527.0",
    "gn:admin3_code":"552710.0",
    "gn:admin4_code":"55271047.0",
    "gn:asciiname":"Bhaigarh",
    "gn:country_code":"BD",
    "gn:dem":32,
    "gn:feature_class":"P",
    "gn:feature_code":"PPL",
    "gn:name":"Bhaigarh",
    "gn:population":0,
    "gn:timezone":"Asia/Dhaka",
    "iso:country":"BD",
    "name:ben_x_preferred":[
        "Bhaigarh"
    ],
    "wof:name":"Bhaigarh",
    "wof:placetype":"locality"
},
  "geometry": {"coordinates":[88.93956999999997,25.322],"type":"Point"}
}