{
  "type": "Feature",
  "properties": {
    "gn:admin1_code":"83",
    "gn:admin2_code":"5038.0",
    "gn:admin3_code":"503874.0",
    "gn:admin4_code":"50387431.0",
    "gn:asciiname":"Malidaha",
    "gn:country_code":"BD",
    "gn:dem":25,
    "gn:feature_class":"P",
    "gn:feature_code":"PPL",
    "gn:name":"Malid\u0101ha",
    "gn:population":0,
    "gn:timezone":"Asia/Dhaka",
    "iso:country":"BD",
    "name:ben_x_preferred":[
        "Malid\u0101ha"
    ],
    "name:und_x_variant":[
        "M\u0101lidaha"
    ],
    "wof:name":"Malidaha",
    "wof:placetype":"locality"
},
  "geometry": {"coordinates":[88.99189,25.16237000000001],"type":"Point"}
}