{
  "type": "Feature",
  "properties": {
    "iso:country":"BD",
    "name:ben_x_preferred":[
        "\u09a8\u09af\u09bc\u09be\u09ac\u09be\u099c\u09be\u09b0"
    ],
    "name:ben_x_variant":[
        "Nayabari"
    ],
    "name:bpy_x_preferred":[
        "\u09a8\u09f1\u09be\u09ac\u09be\u099c\u09be\u09b0"
    ],
    "name:cym_x_preferred":[
        "Naya Bazaar"
    ],
    "name:eng_x_preferred":[
        "Nayabazar"
    ],
    "name:fra_x_preferred":[
        "Nayabazar"
    ],
    "name:hin_x_preferred":[
        "\u0928\u092f\u093e\u092c\u093e\u091c\u093c\u093e\u0930"
    ],
    "name:ita_x_preferred":[
        "Nayabazar"
    ],
    "name:msa_x_preferred":[
        "Nayabazar"
    ],
    "name:new_x_preferred":[
        "\u0928\u092f\u093e\u092c\u091c\u093e\u0930"
    ],
    "name:nld_x_preferred":[
        "Nayabazar"
    ],
    "name:ori_x_preferred":[
        "\u0b28\u0b5f\u0b3e\u0b2c\u0b1c\u0b3e\u0b30"
    ],
    "name:por_x_preferred":[
        "Nayabazar"
    ],
    "name:spa_x_preferred":[
        "Nayabazar"
    ],
    "name:vie_x_preferred":[
        "Nayabazar"
    ],
    "name:zho_x_preferred":[
        "\u7eb3\u8036\u5df4\u624e\u5c14"
    ],
    "qs:gn_country":"BD",
    "qs:gn_fcode":"PPL",
    "qs:gn_pop":0,
    "qs:name":"Nayabazar",
    "qs:name_adm0":"India",
    "qs:name_adm1":"Sikkim",
    "qs:photos":9,
    "qs:photos_1k":2,
    "qs:photos_9k":1,
    "qs:photos_9r":1,
    "qs:photos_all":9,
    "qs:photos_sr":1,
    "qs:placetype":"Town",
    "qs:pop_sr":"0",
    "qs:woe_adm0":23424848,
    "wd:wordcount":143,
    "wof:name":"Nayabazar",
    "wof:placetype":"locality"
},
  "geometry": {"coordinates":[88.44146000000001,26.33902],"type":"Point"}
}