{
  "type": "Feature",
  "properties": {
    "gn:admin1_code":"82",
    "gn:asciiname":"Saula",
    "gn:country_code":"BD",
    "gn:dem":5,
    "gn:feature_class":"P",
    "gn:feature_code":"PPL",
    "gn:name":"Saula",
    "gn:population":0,
    "gn:timezone":"Asia/Dhaka",
    "iso:country":"BD",
    "name:ben_x_preferred":[
        "Saula"
    ],
    "name:ceb_x_preferred":[
        "Saula"
    ],
    "name:swe_x_preferred":[
        "Saula"
    ],
    "wof:name":"Saula",
    "wof:placetype":"locality"
},
  "geometry": {"coordinates":[90.40210999999999,22.35995],"type":"Point"}
}