{
  "type": "Feature",
  "properties": {
    "gn:admin1_code":"84",
    "gn:admin2_code":"2015.0",
    "gn:admin3_code":"201586.0",
    "gn:admin4_code":"20158695.0",
    "gn:asciiname":"Sahidpur",
    "gn:country_code":"BD",
    "gn:dem":9,
    "gn:feature_class":"P",
    "gn:feature_code":"PPL",
    "gn:name":"Sahidpur",
    "gn:population":0,
    "gn:timezone":"Asia/Dhaka",
    "iso:country":"BD",
    "wof:name":"Sahidpur",
    "wof:placetype":"locality"
},
  "geometry": {"coordinates":[91.61221999999999,22.63278],"type":"Point"}
}