{
  "type": "Feature",
  "properties": {
    "gn:admin1_code":"87",
    "gn:admin2_code":"5573.0",
    "gn:admin3_code":"557315.0",
    "gn:admin4_code":"55731576.0",
    "gn:asciiname":"Bakshir Kamat",
    "gn:country_code":"BD",
    "gn:dem":63,
    "gn:feature_class":"P",
    "gn:feature_code":"PPL",
    "gn:name":"Bakshir Kam\u0101t",
    "gn:population":0,
    "gn:timezone":"Asia/Dhaka",
    "iso:country":"BD",
    "name:ben_x_preferred":[
        "Bakshir Kam\u0101t"
    ],
    "wof:name":"Bakshir Kamat",
    "wof:placetype":"locality"
},
  "geometry": {"coordinates":[88.80407,26.23483],"type":"Point"}
}