{
  "type": "Feature",
  "properties": {
    "gn:admin1_code":"87",
    "gn:admin2_code":"5549",
    "gn:admin3_code":"554977.0",
    "gn:admin4_code":"55497752.0",
    "gn:asciiname":"Patwaripara",
    "gn:country_code":"BD",
    "gn:dem":31,
    "gn:feature_class":"P",
    "gn:feature_code":"PPL",
    "gn:name":"P\u0101tw\u0101rip\u0101ra",
    "gn:population":0,
    "gn:timezone":"Asia/Dhaka",
    "iso:country":"BD",
    "name:ben_x_preferred":[
        "P\u0101tw\u0101rip\u0101ra"
    ],
    "wof:name":"Patwaripara",
    "wof:placetype":"locality"
},
  "geometry": {"coordinates":[89.57259999999999,25.72785],"type":"Point"}
}