{
  "type": "Feature",
  "properties": {
    "gn:admin1_code":"83",
    "gn:admin2_code":"5064.0",
    "gn:admin3_code":"506475.0",
    "gn:admin4_code":"50647586.0",
    "gn:asciiname":"Kuaran",
    "gn:country_code":"BD",
    "gn:dem":28,
    "gn:feature_class":"P",
    "gn:feature_code":"PPL",
    "gn:name":"Kuaran",
    "gn:population":0,
    "gn:timezone":"Asia/Dhaka",
    "iso:country":"BD",
    "name:ben_x_preferred":[
        "Kuaran"
    ],
    "wof:name":"Kuaran",
    "wof:placetype":"locality"
},
  "geometry": {"coordinates":[88.69895,25.06404],"type":"Point"}
}