{
  "type": "Feature",
  "properties": {
    "gn:admin1_code":"81",
    "gn:admin2_code":"3067",
    "gn:admin3_code":"306702.0",
    "gn:admin4_code":"30670239.0",
    "gn:asciiname":"Kalyanpur",
    "gn:country_code":"BD",
    "gn:dem":13,
    "gn:feature_class":"P",
    "gn:feature_code":"PPL",
    "gn:name":"Kaly\u0101npur",
    "gn:population":0,
    "gn:timezone":"Asia/Dhaka",
    "iso:country":"BD",
    "wof:name":"Kalyanpur",
    "wof:placetype":"locality"
},
  "geometry": {"coordinates":[90.68271,23.79497000000001],"type":"Point"}
}