{
  "type": "Feature",
  "properties": {
    "gn:admin1_code":"84",
    "gn:admin2_code":"2015.0",
    "gn:admin3_code":"201586.0",
    "gn:admin4_code":"20158685.0",
    "gn:asciiname":"Duluchara",
    "gn:country_code":"BD",
    "gn:dem":51,
    "gn:feature_class":"P",
    "gn:feature_code":"PPL",
    "gn:name":"Duluchara",
    "gn:population":0,
    "gn:timezone":"Asia/Dhaka",
    "iso:country":"BD",
    "name:ben_x_preferred":[
        "Duluchara"
    ],
    "wof:name":"Duluchara",
    "wof:placetype":"locality"
},
  "geometry": {"coordinates":[91.75937,22.46088],"type":"Point"}
}