{
  "type": "Feature",
  "properties": {
    "gn:admin1_code":"84",
    "gn:admin2_code":"2019",
    "gn:admin3_code":"201954.0",
    "gn:admin4_code":"20195428.0",
    "gn:asciiname":"South Baluakandi",
    "gn:country_code":"BD",
    "gn:dem":10,
    "gn:feature_class":"P",
    "gn:feature_code":"PPL",
    "gn:name":"South B\u0101lu\u0101k\u0101ndi",
    "gn:population":0,
    "gn:timezone":"Asia/Dhaka",
    "iso:country":"BD",
    "name:und_x_variant":[
        "Balunkandi",
        "South B\u0101lu\u0101k\u0101ndi"
    ],
    "wof:name":"South Baluakandi",
    "wof:placetype":"locality"
},
  "geometry": {"coordinates":[90.86869,23.70545],"type":"Point"}
}