{
  "type": "Feature",
  "properties": {
    "gn:admin1_code":"82",
    "gn:asciiname":"Bhajna",
    "gn:country_code":"BD",
    "gn:dem":11,
    "gn:feature_class":"P",
    "gn:feature_code":"PPL",
    "gn:name":"Bhajna",
    "gn:population":0,
    "gn:timezone":"Asia/Dhaka",
    "iso:country":"BD",
    "name:ben_x_preferred":[
        "Bhajna"
    ],
    "wof:name":"Bhajna",
    "wof:placetype":"locality"
},
  "geometry": {"coordinates":[90.25391,22.37441],"type":"Point"}
}