{
  "type": "Feature",
  "properties": {
    "gn:admin1_code":"84",
    "gn:admin2_code":"2019",
    "gn:admin3_code":"201936.0",
    "gn:admin4_code":"20193690.0",
    "gn:asciiname":"Rangasimulia",
    "gn:country_code":"BD",
    "gn:dem":8,
    "gn:feature_class":"P",
    "gn:feature_code":"PPL",
    "gn:name":"R\u0101ng\u0101simulia",
    "gn:population":0,
    "gn:timezone":"Asia/Dhaka",
    "iso:country":"BD",
    "name:und_x_variant":[
        "Rangashimulia",
        "R\u0101ng\u0101simulia"
    ],
    "wof:name":"Rangasimulia",
    "wof:placetype":"locality"
},
  "geometry": {"coordinates":[90.77314,23.51052],"type":"Point"}
}