{
  "type": "Feature",
  "properties": {
    "gn:admin1_code":"81",
    "gn:admin2_code":"3056",
    "gn:admin3_code":"305670.0",
    "gn:admin4_code":"30567095.0",
    "gn:asciiname":"Purba Bhatra",
    "gn:country_code":"BD",
    "gn:dem":7,
    "gn:feature_class":"P",
    "gn:feature_code":"PPL",
    "gn:name":"Purba Bh\u0101tra",
    "gn:population":0,
    "gn:timezone":"Asia/Dhaka",
    "iso:country":"BD",
    "wof:name":"Purba Bhatra",
    "wof:placetype":"locality"
},
  "geometry": {"coordinates":[89.95,23.91667],"type":"Point"}
}