{
  "type": "Feature",
  "properties": {
    "gn:admin1_code":"84",
    "gn:admin2_code":"2022.0",
    "gn:admin3_code":"202216.0",
    "gn:admin4_code":"20221639.0",
    "gn:asciiname":"Purba Barabheola",
    "gn:country_code":"BD",
    "gn:dem":10,
    "gn:feature_class":"P",
    "gn:feature_code":"PPL",
    "gn:name":"Purba Bar\u0101bheola",
    "gn:population":0,
    "gn:timezone":"Asia/Dhaka",
    "iso:country":"BD",
    "name:ben_x_preferred":[
        "Purba Bar\u0101bheola"
    ],
    "wof:name":"Purba Barabheola",
    "wof:placetype":"locality"
},
  "geometry": {"coordinates":[92.03660000000001,21.76755],"type":"Point"}
}