{
  "type": "Feature",
  "properties": {
    "gn:admin1_code":"83",
    "gn:admin2_code":"5010",
    "gn:admin3_code":"501040.0",
    "gn:admin4_code":"50104047.0",
    "gn:asciiname":"Sahapur",
    "gn:country_code":"BD",
    "gn:dem":23,
    "gn:feature_class":"P",
    "gn:feature_code":"PPL",
    "gn:name":"S\u0101h\u0101pur",
    "gn:population":0,
    "gn:timezone":"Asia/Dhaka",
    "iso:country":"BD",
    "wof:name":"Sahapur",
    "wof:placetype":"locality"
},
  "geometry": {"coordinates":[89.38065,24.9848],"type":"Point"}
}