{
  "type": "Feature",
  "properties": {
    "gn:admin1_code":"81",
    "gn:admin2_code":"3068",
    "gn:admin3_code":"306876.0",
    "gn:admin4_code":"30687684.0",
    "gn:asciiname":"Telia",
    "gn:country_code":"BD",
    "gn:dem":15,
    "gn:feature_class":"P",
    "gn:feature_code":"PPL",
    "gn:name":"Telia",
    "gn:population":0,
    "gn:timezone":"Asia/Dhaka",
    "iso:country":"BD",
    "name:bar_x_preferred":[
        "Telia"
    ],
    "name:bih_x_preferred":[
        "\u0924\u0947\u0932\u093f\u092f\u093e"
    ],
    "name:cat_x_preferred":[
        "Telia"
    ],
    "name:ceb_x_preferred":[
        "Telia"
    ],
    "name:deu_x_preferred":[
        "Telia"
    ],
    "name:nep_x_preferred":[
        "\u0924\u0947\u0932\u093f\u092f\u093e"
    ],
    "name:new_x_preferred":[
        "\u0924\u0947\u0932\u093f\u092f\u093e"
    ],
    "name:pol_x_preferred":[
        "Telia"
    ],
    "wof:name":"Telia",
    "wof:placetype":"locality"
},
  "geometry": {"coordinates":[90.72418999999999,24.00788],"type":"Point"}
}