{
  "type": "Feature",
  "properties": {
    "gn:admin1_code":"81",
    "gn:admin2_code":"3054.0",
    "gn:admin3_code":"305440.0",
    "gn:admin4_code":"30544088.0",
    "gn:asciiname":"Andar Char",
    "gn:country_code":"BD",
    "gn:dem":6,
    "gn:feature_class":"P",
    "gn:feature_code":"PPL",
    "gn:name":"\u0100nd\u0101r Char",
    "gn:population":0,
    "gn:timezone":"Asia/Dhaka",
    "iso:country":"BD",
    "name:fas_x_preferred":[
        "\u0627\u0646\u062f\u0631 \u0686\u0627\u0631"
    ],
    "name:spa_x_preferred":[
        "Andar Char"
    ],
    "name:und_x_variant":[
        "Andherchar",
        "\u0100nd\u0101r Char"
    ],
    "wof:name":"Andar Char",
    "wof:placetype":"locality"
},
  "geometry": {"coordinates":[90.29015,23.03728],"type":"Point"}
}