{
  "type": "Feature",
  "properties": {
    "gn:admin1_code":"85",
    "gn:admin2_code":"1006",
    "gn:admin3_code":"100694.0",
    "gn:admin4_code":"10069421.0",
    "gn:asciiname":"Penatali",
    "gn:country_code":"BD",
    "gn:dem":8,
    "gn:feature_class":"P",
    "gn:feature_code":"PPL",
    "gn:name":"Pen\u0101tali",
    "gn:population":0,
    "gn:timezone":"Asia/Dhaka",
    "iso:country":"BD",
    "wof:name":"Penatali",
    "wof:placetype":"locality"
},
  "geometry": {"coordinates":[90.22172999999999,22.84598],"type":"Point"}
}