{
  "type": "Feature",
  "properties": {
    "gn:admin1_code":"81",
    "gn:admin2_code":"3059.0",
    "gn:admin3_code":"305974.0",
    "gn:admin4_code":"30597413.0",
    "gn:asciiname":"Char Biswanath",
    "gn:country_code":"BD",
    "gn:dem":10,
    "gn:feature_class":"P",
    "gn:feature_code":"PPL",
    "gn:name":"Char Biswan\u0101th",
    "gn:population":0,
    "gn:timezone":"Asia/Dhaka",
    "iso:country":"BD",
    "wof:name":"Char Biswanath",
    "wof:placetype":"locality"
},
  "geometry": {"coordinates":[90.34837,23.60845],"type":"Point"}
}