{
  "type": "Feature",
  "properties": {
    "gn:admin1_code":"H",
    "gn:admin2_code":"3039",
    "gn:admin3_code":"303929.0",
    "gn:admin4_code":"30392923.0",
    "gn:asciiname":"Chinar",
    "gn:country_code":"BD",
    "gn:dem":22,
    "gn:feature_class":"P",
    "gn:feature_code":"PPL",
    "gn:name":"Chinar",
    "gn:population":0,
    "gn:timezone":"Asia/Dhaka",
    "iso:country":"BD",
    "wof:name":"Chinar",
    "wof:placetype":"locality"
},
  "geometry": {"coordinates":[89.88643,25.0694],"type":"Point"}
}