{
  "type": "Feature",
  "properties": {
    "gn:admin1_code":"83",
    "gn:admin2_code":"5081.0",
    "gn:admin3_code":"508172.0",
    "gn:admin4_code":"50817223.0",
    "gn:asciiname":"Bliaharampur East",
    "gn:country_code":"BD",
    "gn:dem":23,
    "gn:feature_class":"P",
    "gn:feature_code":"PPL",
    "gn:name":"Bliaharampur East",
    "gn:population":0,
    "gn:timezone":"Asia/Dhaka",
    "iso:country":"BD",
    "name:ben_x_preferred":[
        "Bliaharampur East"
    ],
    "wof:name":"Bliaharampur East",
    "wof:placetype":"locality"
},
  "geometry": {"coordinates":[88.54024,24.47908],"type":"Point"}
}