{
  "type": "Feature",
  "properties": {
    "gn:admin1_code":"81",
    "gn:admin2_code":"3026",
    "gn:admin3_code":"302662.0",
    "gn:admin4_code":"30266267.0",
    "gn:asciiname":"Masail",
    "gn:country_code":"BD",
    "gn:dem":10,
    "gn:feature_class":"P",
    "gn:feature_code":"PPL",
    "gn:name":"M\u0101s\u0101il",
    "gn:population":0,
    "gn:timezone":"Asia/Dhaka",
    "iso:country":"BD",
    "wof:name":"Masail",
    "wof:placetype":"locality"
},
  "geometry": {"coordinates":[90.26748000000001,23.69068],"type":"Point"}
}