{
  "type": "Feature",
  "properties": {
    "gn:admin1_code":"83",
    "gn:admin2_code":"5081.0",
    "gn:admin3_code":"508134.0",
    "gn:admin4_code":"50813466.0",
    "gn:asciiname":"Bailkay Hati",
    "gn:country_code":"BD",
    "gn:dem":34,
    "gn:feature_class":"P",
    "gn:feature_code":"PPL",
    "gn:name":"Bailkay Hati",
    "gn:population":0,
    "gn:timezone":"Asia/Dhaka",
    "iso:country":"BD",
    "name:ben_x_preferred":[
        "Bailkay Hati"
    ],
    "name:ben_x_variant":[
        "B\u0101lk\u0101h\u0101ti"
    ],
    "wof:name":"Bailkay Hati",
    "wof:placetype":"locality"
},
  "geometry": {"coordinates":[88.41828000000002,24.58346],"type":"Point"}
}