{
  "type": "Feature",
  "properties": {
    "gn:admin1_code":"82",
    "gn:admin2_code":"4044",
    "gn:admin3_code":"404442.0",
    "gn:admin4_code":"40444213.0",
    "gn:asciiname":"Baluhar",
    "gn:country_code":"BD",
    "gn:dem":10,
    "gn:feature_class":"P",
    "gn:feature_code":"PPL",
    "gn:name":"B\u0101luh\u0101r",
    "gn:population":0,
    "gn:timezone":"Asia/Dhaka",
    "iso:country":"BD",
    "name:ben_x_preferred":[
        "B\u0101luh\u0101r"
    ],
    "wof:name":"Baluhar",
    "wof:placetype":"locality"
},
  "geometry": {"coordinates":[89.001,23.4233],"type":"Point"}
}