{
  "type": "Feature",
  "properties": {
    "gn:admin1_code":"82",
    "gn:admin2_code":"4087.0",
    "gn:admin3_code":"408786.0",
    "gn:admin4_code":"40878694.0",
    "gn:asciiname":"Kalamegha",
    "gn:country_code":"BD",
    "gn:dem":4,
    "gn:feature_class":"P",
    "gn:feature_code":"PPL",
    "gn:name":"K\u0101l\u0101megh\u0101",
    "gn:population":0,
    "gn:timezone":"Asia/Dhaka",
    "iso:country":"BD",
    "name:ben_x_preferred":[
        "K\u0101l\u0101megh\u0101"
    ],
    "wof:name":"Kalamegha",
    "wof:placetype":"locality"
},
  "geometry": {"coordinates":[89.08133000000002,22.31977],"type":"Point"}
}