{
  "type": "Feature",
  "properties": {
    "gn:admin1_code":"81",
    "gn:admin2_code":"3026.0",
    "gn:admin3_code":"302662.0",
    "gn:admin4_code":"30266227.0",
    "gn:asciiname":"Bara Bahra",
    "gn:country_code":"BD",
    "gn:dem":14,
    "gn:feature_class":"P",
    "gn:feature_code":"PPL",
    "gn:name":"Bara B\u0101hra",
    "gn:population":0,
    "gn:timezone":"Asia/Dhaka",
    "iso:country":"BD",
    "wof:name":"Bara Bahra",
    "wof:placetype":"locality"
},
  "geometry": {"coordinates":[90.19242,23.66026],"type":"Point"}
}