{
  "type": "Feature",
  "properties": {
    "gn:admin1_code":"81",
    "gn:admin2_code":"3026.0",
    "gn:admin3_code":"302638.0",
    "gn:admin4_code":"30263877.0",
    "gn:asciiname":"Deuli",
    "gn:country_code":"BD",
    "gn:dem":10,
    "gn:feature_class":"P",
    "gn:feature_code":"PPL",
    "gn:name":"Deuli",
    "gn:population":0,
    "gn:timezone":"Asia/Dhaka",
    "iso:country":"BD",
    "wof:name":"Deuli",
    "wof:placetype":"locality"
},
  "geometry": {"coordinates":[90.31005,23.74411],"type":"Point"}
}