{
  "type": "Feature",
  "properties": {
    "gn:admin1_code":"82",
    "gn:admin2_code":"4047",
    "gn:admin3_code":"404764.0",
    "gn:admin4_code":"40476489.0",
    "gn:asciiname":"Patan",
    "gn:country_code":"BD",
    "gn:dem":2,
    "gn:feature_class":"P",
    "gn:feature_code":"PPL",
    "gn:name":"Patan",
    "gn:population":0,
    "gn:timezone":"Asia/Dhaka",
    "iso:country":"BD",
    "name:bpy_x_preferred":[
        "\u09aa\u09be\u09a4\u09be\u09a8"
    ],
    "name:cat_x_preferred":[
        "Patan"
    ],
    "name:ceb_x_preferred":[
        "Patan"
    ],
    "name:ces_x_preferred":[
        "P\u00e1tan"
    ],
    "name:deu_x_preferred":[
        "Patan"
    ],
    "name:fin_x_preferred":[
        "Patan"
    ],
    "name:fra_x_preferred":[
        "Patan"
    ],
    "name:hin_x_preferred":[
        "\u092a\u093e\u091f\u0928"
    ],
    "name:ita_x_preferred":[
        "Patan"
    ],
    "name:new_x_preferred":[
        "\u092a\u093e\u091f\u0928"
    ],
    "name:nld_x_preferred":[
        "Patan"
    ],
    "name:pol_x_preferred":[
        "Patan"
    ],
    "name:por_x_preferred":[
        "Patan"
    ],
    "name:spa_x_preferred":[
        "Patan"
    ],
    "name:swe_x_preferred":[
        "Patan"
    ],
    "wof:name":"Patan",
    "wof:placetype":"locality"
},
  "geometry": {"coordinates":[89.40733,22.54649],"type":"Point"}
}