{
  "type": "Feature",
  "properties": {
    "gn:admin1_code":"83",
    "gn:admin2_code":"5010",
    "gn:admin3_code":"501040.0",
    "gn:admin4_code":"50104074.0",
    "gn:asciiname":"Mominhata",
    "gn:country_code":"BD",
    "gn:dem":20,
    "gn:feature_class":"P",
    "gn:feature_code":"PPL",
    "gn:name":"Mominh\u0101ta",
    "gn:population":0,
    "gn:timezone":"Asia/Dhaka",
    "iso:country":"BD",
    "name:und_x_variant":[
        "Maminhata",
        "Mominh\u0101ta"
    ],
    "wof:name":"Mominhata",
    "wof:placetype":"locality"
},
  "geometry": {"coordinates":[89.49609,24.90544],"type":"Point"}
}