{
  "type": "Feature",
  "properties": {
    "gn:admin1_code":"84",
    "gn:admin2_code":"2019.0",
    "gn:admin3_code":"201968.0",
    "gn:admin4_code":"20196858.0",
    "gn:asciiname":"Bhatra",
    "gn:country_code":"BD",
    "gn:dem":12,
    "gn:feature_class":"P",
    "gn:feature_code":"PPL",
    "gn:name":"Bh\u0101tra",
    "gn:population":0,
    "gn:timezone":"Asia/Dhaka",
    "iso:country":"BD",
    "name:fra_x_preferred":[
        "Bhatra"
    ],
    "wof:name":"Bhatra",
    "wof:placetype":"locality"
},
  "geometry": {"coordinates":[91.23333,23.41667],"type":"Point"}
}