{
  "type": "Feature",
  "properties": {
    "iso:country":"BD",
    "name:unk_x_variant":[
        "Bajutpur"
    ],
    "qs:gn_country":"BD",
    "qs:gn_fcode":"PPL",
    "qs:gn_pop":34560,
    "qs:name":"Bajitpur",
    "qs:name_adm0":"Bangladesh",
    "qs:name_adm1":"Dhaka",
    "qs:photos":0,
    "qs:photos_1k":0,
    "qs:photos_9k":1,
    "qs:photos_9r":1,
    "qs:photos_all":17,
    "qs:photos_sr":0,
    "qs:placetype":"Town",
    "qs:pop_sr":"7",
    "qs:woe_adm0":23424759,
    "wof:name":"Bajitpur",
    "wof:placetype":"locality",
    "wof:population":34560
},
  "geometry": {"coordinates":[90.95001999999999,24.21623],"type":"Point"}
}