{
  "type": "Feature",
  "properties": {
    "iso:country":"BD",
    "name:ben_x_preferred":[
        "\u09ac\u09be\u099c\u09bf\u09a4\u09aa\u09c1\u09b0 \u0989\u09aa\u099c\u09c7\u09b2\u09be"
    ],
    "name:bpy_x_preferred":[
        "\u09ac\u09be\u099c\u09bf\u09a4\u09aa\u09c1\u09b0 \u0989\u09aa\u099c\u09bf\u09b2\u09be"
    ],
    "name:ceb_x_preferred":[
        "Bajitpur"
    ],
    "name:cos_x_preferred":[
        "Bajitpur"
    ],
    "name:deu_x_preferred":[
        "Bajitpur"
    ],
    "name:eng_x_preferred":[
        "Bajitpur Upazila"
    ],
    "name:fra_x_preferred":[
        "Bajitpur"
    ],
    "name:hin_x_preferred":[
        "\u092c\u093e\u091c\u093f\u0924\u092a\u0941\u0930 \u0909\u092a\u091c\u093c\u093f\u0932\u093e"
    ],
    "name:ita_x_preferred":[
        "Bajitpur"
    ],
    "name:rus_x_preferred":[
        "\u0411\u0430\u0434\u0436\u0438\u0442\u043f\u0443\u0440"
    ],
    "name:sdc_x_preferred":[
        "Bajitpur"
    ],
    "name:srd_x_preferred":[
        "Bajitpur"
    ],
    "name:und_x_variant":[
        "Bajutpur"
    ],
    "name:zho_x_preferred":[
        "\u5df4\u5409\u7279\u5e03\u723e\u70cf\u5e15\u9f4a\u62c9"
    ],
    "qs:gn_country":"BD",
    "qs:gn_fcode":"PPL",
    "qs:gn_pop":34560,
    "qs:name":"Bajitpur",
    "qs:name_adm0":"Bangladesh",
    "qs:name_adm1":"Dhaka",
    "qs:photos":0,
    "qs:photos_1k":0,
    "qs:photos_9k":1,
    "qs:photos_9r":1,
    "qs:photos_all":17,
    "qs:photos_sr":0,
    "qs:placetype":"Town",
    "qs:pop_sr":"7",
    "qs:woe_adm0":23424759,
    "wof:name":"Bajitpur",
    "wof:placetype":"locality",
    "wof:population":34560
},
  "geometry": {"coordinates":[90.95001999999999,24.21623],"type":"Point"}
}