{
  "type": "Feature",
  "properties": {
    "gn:admin1_code":"83",
    "gn:admin2_code":"5070.0",
    "gn:admin3_code":"507088.0",
    "gn:admin4_code":"50708817.0",
    "gn:asciiname":"Chaksriram",
    "gn:country_code":"BD",
    "gn:dem":27,
    "gn:feature_class":"P",
    "gn:feature_code":"PPL",
    "gn:name":"Chaksrir\u0101m",
    "gn:population":0,
    "gn:timezone":"Asia/Dhaka",
    "iso:country":"BD",
    "name:ben_x_preferred":[
        "Chaksrir\u0101m"
    ],
    "wof:name":"Chaksriram",
    "wof:placetype":"locality"
},
  "geometry": {"coordinates":[88.19358000000003,24.80976],"type":"Point"}
}