{
  "type": "Feature",
  "properties": {
    "gn:admin1_code":"84",
    "gn:admin2_code":"2015.0",
    "gn:admin3_code":"201586.0",
    "gn:admin4_code":"20158647.0",
    "gn:asciiname":"Uttar Sanaichari",
    "gn:country_code":"BD",
    "gn:dem":8,
    "gn:feature_class":"P",
    "gn:feature_code":"PPL",
    "gn:name":"Uttar Sanaichari",
    "gn:population":0,
    "gn:timezone":"Asia/Dhaka",
    "iso:country":"BD",
    "wof:name":"Uttar Sanaichari",
    "wof:placetype":"locality"
},
  "geometry": {"coordinates":[91.70639,22.49611],"type":"Point"}
}