{
  "type": "Feature",
  "properties": {
    "gn:admin1_code":"82",
    "gn:admin2_code":"4041",
    "gn:admin3_code":"404138.0",
    "gn:admin4_code":"40413857.0",
    "gn:asciiname":"Manoharnagar",
    "gn:country_code":"BD",
    "gn:dem":12,
    "gn:feature_class":"P",
    "gn:feature_code":"PPL",
    "gn:name":"Manoharnagar",
    "gn:population":0,
    "gn:timezone":"Asia/Dhaka",
    "iso:country":"BD",
    "wof:name":"Manoharnagar",
    "wof:placetype":"locality"
},
  "geometry": {"coordinates":[89.28381999999998,22.91621],"type":"Point"}
}