{
  "type": "Feature",
  "properties": {
    "gn:admin1_code":"82",
    "gn:admin2_code":"4044.0",
    "gn:admin3_code":"404471.0",
    "gn:admin4_code":"40447183.0",
    "gn:asciiname":"Khurd Khalishpur",
    "gn:country_code":"BD",
    "gn:dem":16,
    "gn:feature_class":"P",
    "gn:feature_code":"PPL",
    "gn:name":"Khurd Kh\u0101lishpur",
    "gn:population":0,
    "gn:timezone":"Asia/Dhaka",
    "iso:country":"BD",
    "name:ben_x_preferred":[
        "Khurd Kh\u0101lishpur"
    ],
    "wof:name":"Khurd Khalishpur",
    "wof:placetype":"locality"
},
  "geometry": {"coordinates":[88.93366999999998,23.40496],"type":"Point"}
}