{
  "type": "Feature",
  "properties": {
    "gn:admin1_code":"82",
    "gn:admin2_code":"4044.0",
    "gn:admin3_code":"404433.0",
    "gn:admin4_code":"40443333.0",
    "gn:asciiname":"Par Srirampur",
    "gn:country_code":"BD",
    "gn:dem":16,
    "gn:feature_class":"P",
    "gn:feature_code":"PPL",
    "gn:name":"P\u0101r Srir\u0101mpur",
    "gn:population":0,
    "gn:timezone":"Asia/Dhaka",
    "iso:country":"BD",
    "name:ben_x_preferred":[
        "P\u0101r Srir\u0101mpur"
    ],
    "wof:name":"Par Srirampur",
    "wof:placetype":"locality"
},
  "geometry": {"coordinates":[89.10746999999998,23.42413],"type":"Point"}
}