{
  "type": "Feature",
  "properties": {
    "gn:admin1_code":"85",
    "gn:admin2_code":"1042",
    "gn:admin3_code":"104273.0",
    "gn:admin4_code":"10427310.0",
    "gn:asciiname":"Sekherkati",
    "gn:country_code":"BD",
    "gn:dem":10,
    "gn:feature_class":"P",
    "gn:feature_code":"PPL",
    "gn:name":"Sekherk\u0101ti",
    "gn:population":0,
    "gn:timezone":"Asia/Dhaka",
    "iso:country":"BD",
    "wof:name":"Sekherkati",
    "wof:placetype":"locality"
},
  "geometry": {"coordinates":[90.33932,22.61824],"type":"Point"}
}