{
  "type": "Feature",
  "properties": {
    "gn:admin1_code":"81",
    "gn:admin2_code":"3029.0",
    "gn:admin3_code":"302962.0",
    "gn:admin4_code":"30296255.0",
    "gn:asciiname":"Ainpur",
    "gn:country_code":"BD",
    "gn:dem":8,
    "gn:feature_class":"P",
    "gn:feature_code":"PPL",
    "gn:name":"Ainpur",
    "gn:population":0,
    "gn:timezone":"Asia/Dhaka",
    "iso:country":"BD",
    "name:fas_x_preferred":[
        "\u0627\u06cc\u0646\u067e\u0648\u0631"
    ],
    "wof:name":"Ainpur",
    "wof:placetype":"locality"
},
  "geometry": {"coordinates":[89.8537,23.43045],"type":"Point"}
}