{
  "type": "Feature",
  "properties": {
    "gn:admin1_code":"82",
    "gn:admin2_code":"4041.0",
    "gn:admin3_code":"404111.0",
    "gn:admin4_code":"40411143.0",
    "gn:asciiname":"Shogerdari",
    "gn:country_code":"BD",
    "gn:dem":14,
    "gn:feature_class":"P",
    "gn:feature_code":"PPL",
    "gn:name":"Shogerd\u0101ri",
    "gn:population":0,
    "gn:timezone":"Asia/Dhaka",
    "iso:country":"BD",
    "name:ben_x_preferred":[
        "Shogerd\u0101ri"
    ],
    "wof:name":"Shogerdari",
    "wof:placetype":"locality"
},
  "geometry": {"coordinates":[88.99914,23.26694],"type":"Point"}
}