{
  "type": "Feature",
  "properties": {
    "gn:admin1_code":"82",
    "gn:admin2_code":"4047.0",
    "gn:admin3_code":"404753.0",
    "gn:admin4_code":"40475322.0",
    "gn:asciiname":"Pata Khali",
    "gn:country_code":"BD",
    "gn:dem":3,
    "gn:feature_class":"P",
    "gn:feature_code":"PPL",
    "gn:name":"P\u0101t\u0101 Kh\u0101li",
    "gn:population":0,
    "gn:timezone":"Asia/Dhaka",
    "iso:country":"BD",
    "name:ben_x_preferred":[
        "P\u0101t\u0101 Kh\u0101li"
    ],
    "wof:name":"Pata Khali",
    "wof:placetype":"locality"
},
  "geometry": {"coordinates":[89.32916999999998,22.2488],"type":"Point"}
}