{
  "type": "Feature",
  "properties": {
    "gn:admin1_code":"81",
    "gn:admin2_code":"3029",
    "gn:admin3_code":"302947.0",
    "gn:admin4_code":"30294755.0",
    "gn:asciiname":"Tulagram",
    "gn:country_code":"BD",
    "gn:dem":11,
    "gn:feature_class":"P",
    "gn:feature_code":"PPL",
    "gn:name":"Tul\u0101gr\u0101m",
    "gn:population":0,
    "gn:timezone":"Asia/Dhaka",
    "iso:country":"BD",
    "wof:name":"Tulagram",
    "wof:placetype":"locality"
},
  "geometry": {"coordinates":[89.81883000000001,23.55606],"type":"Point"}
}