{
  "type": "Feature",
  "properties": {
    "gn:admin1_code":"81",
    "gn:admin2_code":"3082.0",
    "gn:admin3_code":"308229.0",
    "gn:admin4_code":"30822976.0",
    "gn:asciiname":"Durjyodhan Kandi",
    "gn:cc2":"BD",
    "gn:country_code":"BD",
    "gn:dem":1,
    "gn:feature_class":"P",
    "gn:feature_code":"PPL",
    "gn:name":"Durjyodhan K\u0101ndi",
    "gn:population":0,
    "gn:timezone":"Asia/Dhaka",
    "iso:country":"BD",
    "name:und_x_variant":[
        "Durjya Dhankandhi",
        "Durjyodhan K\u0101ndi"
    ],
    "wof:name":"Durjyodhan Kandi",
    "wof:placetype":"locality"
},
  "geometry": {"coordinates":[89.83333,23.73333],"type":"Point"}
}