{
  "type": "Feature",
  "properties": {
    "gn:admin1_code":"87",
    "gn:admin2_code":"5532",
    "gn:admin3_code":"553291.0",
    "gn:admin4_code":"55329106.0",
    "gn:asciiname":"Manira",
    "gn:country_code":"BD",
    "gn:dem":29,
    "gn:feature_class":"P",
    "gn:feature_code":"PPL",
    "gn:name":"Manira",
    "gn:population":0,
    "gn:timezone":"Asia/Dhaka",
    "iso:country":"BD",
    "wof:name":"Manira",
    "wof:placetype":"locality"
},
  "geometry": {"coordinates":[89.45577,25.57236],"type":"Point"}
}