{
  "type": "Feature",
  "properties": {
    "gn:admin1_code":"82",
    "gn:admin2_code":"4041",
    "gn:admin3_code":"404161.0",
    "gn:admin4_code":"40416105.0",
    "gn:asciiname":"Mollahdanga",
    "gn:country_code":"BD",
    "gn:dem":12,
    "gn:feature_class":"P",
    "gn:feature_code":"PPL",
    "gn:name":"Moll\u0101hd\u0101nga",
    "gn:population":0,
    "gn:timezone":"Asia/Dhaka",
    "iso:country":"BD",
    "name:ben_x_preferred":[
        "Moll\u0101hd\u0101nga"
    ],
    "name:ben_x_variant":[
        "Moll\u0101d\u0101nga"
    ],
    "name:und_x_variant":[
        "Mulladanga"
    ],
    "wof:name":"Mollahdanga",
    "wof:placetype":"locality"
},
  "geometry": {"coordinates":[89.22121,23.0847],"type":"Point"}
}