{
  "type": "Feature",
  "properties": {
    "gn:admin1_code":"82",
    "gn:admin2_code":"4087.0",
    "gn:admin3_code":"408786.0",
    "gn:admin4_code":"40878607.0",
    "gn:asciiname":"Jogendranagar",
    "gn:country_code":"BD",
    "gn:dem":3,
    "gn:feature_class":"P",
    "gn:feature_code":"PPL",
    "gn:name":"Jogendranagar",
    "gn:population":0,
    "gn:timezone":"Asia/Dhaka",
    "iso:country":"BD",
    "name:ben_x_preferred":[
        "Jogendranagar"
    ],
    "name:ben_x_variant":[
        "\u09af\u09cb\u0997\u09c7\u09a8\u09cd\u09a6\u09cd\u09b0\u09a8\u0997\u09b0"
    ],
    "name:bpy_x_preferred":[
        "\u09af\u09cb\u0997\u09c7\u09a8\u09cd\u09a6\u09cd\u09b0\u09a8\u0997\u09b0"
    ],
    "name:ita_x_preferred":[
        "Jogendranagar"
    ],
    "name:mlg_x_preferred":[
        "Jogendranagar"
    ],
    "name:msa_x_preferred":[
        "Jogendranagar"
    ],
    "name:new_x_preferred":[
        "\u091c\u094b\u0917\u0947\u0928\u094d\u0926\u094d\u0930\u0928\u0917\u0930"
    ],
    "name:nld_x_preferred":[
        "Jogendranagar"
    ],
    "name:por_x_preferred":[
        "Jogendranagar"
    ],
    "name:vie_x_preferred":[
        "Jogendranagar"
    ],
    "name:zho_x_preferred":[
        "\u4e54\u6839\u5fb7\u62c9\u7eb3\u52a0\u5c14"
    ],
    "wof:name":"Jogendranagar",
    "wof:placetype":"locality"
},
  "geometry": {"coordinates":[89.19032,22.32483],"type":"Point"}
}