{
  "type": "Feature",
  "properties": {
    "gn:admin1_code":"86",
    "gn:admin2_code":"6091.0",
    "gn:admin3_code":"609153.0",
    "gn:admin4_code":"60915363.0",
    "gn:asciiname":"Bhitrikhel",
    "gn:country_code":"BD",
    "gn:dem":20,
    "gn:feature_class":"P",
    "gn:feature_code":"PPL",
    "gn:name":"Bhitrikhel",
    "gn:population":0,
    "gn:timezone":"Asia/Dhaka",
    "iso:country":"BD",
    "wof:name":"Bhitrikhel",
    "wof:placetype":"locality"
},
  "geometry": {"coordinates":[92.17313,25.09271],"type":"Point"}
}