{
  "type": "Feature",
  "properties": {
    "gn:admin1_code":"81",
    "gn:admin2_code":"3048.0",
    "gn:admin3_code":"304806.0",
    "gn:admin4_code":"30480651.0",
    "gn:asciiname":"Halimpur",
    "gn:country_code":"BD",
    "gn:dem":13,
    "gn:feature_class":"P",
    "gn:feature_code":"PPL",
    "gn:name":"Hal\u012bmpur",
    "gn:population":0,
    "gn:timezone":"Asia/Dhaka",
    "iso:country":"BD",
    "wof:name":"Halimpur",
    "wof:placetype":"locality"
},
  "geometry": {"coordinates":[90.87785,24.24786],"type":"Point"}
}