{
  "type": "Feature",
  "properties": {
    "gn:admin1_code":"87",
    "gn:admin2_code":"5577.0",
    "gn:admin3_code":"557734.0",
    "gn:admin4_code":"55773409.0",
    "gn:asciiname":"Dhana Mandal",
    "gn:country_code":"BD",
    "gn:dem":55,
    "gn:feature_class":"P",
    "gn:feature_code":"PPL",
    "gn:name":"Dhana Mandal",
    "gn:population":0,
    "gn:timezone":"Asia/Dhaka",
    "iso:country":"BD",
    "name:ben_x_preferred":[
        "Dhana Mandal"
    ],
    "wof:name":"Dhana Mandal",
    "wof:placetype":"locality"
},
  "geometry": {"coordinates":[88.67215999999998,26.0628],"type":"Point"}
}