{
  "type": "Feature",
  "properties": {
    "gn:admin1_code":"81",
    "gn:admin2_code":"3082",
    "gn:admin3_code":"308207.0",
    "gn:admin4_code":"30820785.0",
    "gn:asciiname":"Jadab Panchbaria",
    "gn:country_code":"BD",
    "gn:dem":16,
    "gn:feature_class":"P",
    "gn:feature_code":"PPL",
    "gn:name":"J\u0101dab P\u0101nchb\u0101ria",
    "gn:population":0,
    "gn:timezone":"Asia/Dhaka",
    "iso:country":"BD",
    "wof:name":"Jadab Panchbaria",
    "wof:placetype":"locality"
},
  "geometry": {"coordinates":[89.45192,23.66149],"type":"Point"}
}