{
  "type": "Feature",
  "properties": {
    "gn:admin1_code":"83",
    "gn:admin2_code":"5076.0",
    "gn:admin3_code":"507616.0",
    "gn:admin4_code":"50761684.0",
    "gn:asciiname":"Kazi Sharifpur",
    "gn:country_code":"BD",
    "gn:dem":14,
    "gn:feature_class":"P",
    "gn:feature_code":"PPL",
    "gn:name":"K\u0101zi Sharifpur",
    "gn:population":0,
    "gn:timezone":"Asia/Dhaka",
    "iso:country":"BD",
    "name:ben_x_preferred":[
        "K\u0101zi Sharifpur"
    ],
    "wof:name":"Kazi Sharifpur",
    "wof:placetype":"locality"
},
  "geometry": {"coordinates":[89.66514000000002,23.88548],"type":"Point"}
}