{
  "type": "Feature",
  "properties": {
    "gn:admin1_code":"82",
    "gn:admin2_code":"4087.0",
    "gn:admin3_code":"408786.0",
    "gn:admin4_code":"40878647.0",
    "gn:asciiname":"Karikhal",
    "gn:country_code":"BD",
    "gn:dem":2,
    "gn:feature_class":"P",
    "gn:feature_code":"PPL",
    "gn:name":"Karikh\u0101l",
    "gn:population":0,
    "gn:timezone":"Asia/Dhaka",
    "iso:country":"BD",
    "name:ben_x_preferred":[
        "Karikh\u0101l"
    ],
    "wof:name":"Karikhal",
    "wof:placetype":"locality"
},
  "geometry": {"coordinates":[89.02580999999998,22.26365],"type":"Point"}
}