{
  "type": "Feature",
  "properties": {
    "gn:admin1_code":"84",
    "gn:admin2_code":"2015.0",
    "gn:admin3_code":"201508.0",
    "gn:admin4_code":"20150875.0",
    "gn:asciiname":"Ratarkul",
    "gn:country_code":"BD",
    "gn:dem":8,
    "gn:feature_class":"P",
    "gn:feature_code":"PPL",
    "gn:name":"Rat\u0101rkul",
    "gn:population":0,
    "gn:timezone":"Asia/Dhaka",
    "iso:country":"BD",
    "name:ben_x_preferred":[
        "Rat\u0101rkul"
    ],
    "wof:name":"Ratarkul",
    "wof:placetype":"locality"
},
  "geometry": {"coordinates":[91.90192,22.11798],"type":"Point"}
}