{
  "type": "Feature",
  "properties": {
    "gn:admin1_code":"87",
    "gn:admin2_code":"5527.0",
    "gn:admin3_code":"552756.0",
    "gn:admin4_code":"55275694.0",
    "gn:asciiname":"Sukdebpur",
    "gn:country_code":"BD",
    "gn:dem":44,
    "gn:feature_class":"P",
    "gn:feature_code":"PPL",
    "gn:name":"Sukdebpur",
    "gn:population":0,
    "gn:timezone":"Asia/Dhaka",
    "iso:country":"BD",
    "name:ben_x_preferred":[
        "Sukdebpur"
    ],
    "wof:name":"Sukdebpur",
    "wof:placetype":"locality"
},
  "geometry": {"coordinates":[88.52030000000001,25.77751],"type":"Point"}
}