{
  "type": "Feature",
  "properties": {
    "gn:admin1_code":"83",
    "gn:admin2_code":"5081.0",
    "gn:admin3_code":"508172.0",
    "gn:admin4_code":"50817247.0",
    "gn:asciiname":"Tangramari",
    "gn:country_code":"BD",
    "gn:dem":20,
    "gn:feature_class":"P",
    "gn:feature_code":"PPL",
    "gn:name":"Tangr\u0101m\u0101ri",
    "gn:population":0,
    "gn:timezone":"Asia/Dhaka",
    "iso:country":"BD",
    "name:ben_x_preferred":[
        "Tangr\u0101m\u0101ri"
    ],
    "wof:name":"Tangramari",
    "wof:placetype":"locality"
},
  "geometry": {"coordinates":[88.50089,24.38201],"type":"Point"}
}