{
  "type": "Feature",
  "properties": {
    "gn:admin1_code":"H",
    "gn:admin2_code":"3072",
    "gn:admin3_code":"307283.0",
    "gn:admin4_code":"30728355.0",
    "gn:asciiname":"Saldigha Raynagar",
    "gn:country_code":"BD",
    "gn:dem":17,
    "gn:feature_class":"P",
    "gn:feature_code":"PPL",
    "gn:name":"S\u0101ldigha R\u0101ynagar",
    "gn:population":0,
    "gn:timezone":"Asia/Dhaka",
    "iso:country":"BD",
    "wof:name":"Saldigha Raynagar",
    "wof:placetype":"locality"
},
  "geometry": {"coordinates":[90.58693,24.86517000000001],"type":"Point"}
}