{
  "type": "Feature",
  "properties": {
    "gn:admin1_code":"82",
    "gn:admin2_code":"4065.0",
    "gn:admin3_code":"406576.0",
    "gn:admin4_code":"40657600.0",
    "gn:asciiname":"Brahmandanga",
    "gn:country_code":"BD",
    "gn:dem":12,
    "gn:feature_class":"P",
    "gn:feature_code":"PPL",
    "gn:name":"Brahmand\u0101nga",
    "gn:population":0,
    "gn:timezone":"Asia/Dhaka",
    "iso:country":"BD",
    "name:ben_x_preferred":[
        "Brahmand\u0101nga"
    ],
    "wof:name":"Brahmandanga",
    "wof:placetype":"locality"
},
  "geometry": {"coordinates":[89.51659000000002,23.14691],"type":"Point"}
}