{
  "type": "Feature",
  "properties": {
    "gn:admin1_code":"82",
    "gn:admin2_code":"4044",
    "gn:admin3_code":"404433.0",
    "gn:admin4_code":"40443333.0",
    "gn:asciiname":"Naldanga",
    "gn:country_code":"BD",
    "gn:dem":15,
    "gn:feature_class":"P",
    "gn:feature_code":"PPL",
    "gn:name":"Nald\u0101nga",
    "gn:population":0,
    "gn:timezone":"Asia/Dhaka",
    "iso:country":"BD",
    "name:ben_x_preferred":[
        "Nald\u0101nga"
    ],
    "name:cat_x_preferred":[
        "Naldanga"
    ],
    "wof:name":"Naldanga",
    "wof:placetype":"locality"
},
  "geometry": {"coordinates":[89.16840999999999,23.43902000000001],"type":"Point"}
}