{
  "type": "Feature",
  "properties": {
    "gn:admin1_code":"81",
    "gn:admin2_code":"3029.0",
    "gn:admin3_code":"302984.0",
    "gn:admin4_code":"30298409.0",
    "gn:asciiname":"Akater Char",
    "gn:country_code":"BD",
    "gn:dem":10,
    "gn:feature_class":"P",
    "gn:feature_code":"PPL",
    "gn:name":"\u0100kater Char",
    "gn:population":0,
    "gn:timezone":"Asia/Dhaka",
    "iso:country":"BD",
    "wof:name":"Akater Char",
    "wof:placetype":"locality"
},
  "geometry": {"coordinates":[90.05393000000002,23.51835],"type":"Point"}
}