{
  "type": "Feature",
  "properties": {
    "gn:admin1_code":"87",
    "gn:admin2_code":"5552",
    "gn:admin3_code":"555239.0",
    "gn:admin4_code":"55523953.0",
    "gn:asciiname":"Rudreswar",
    "gn:country_code":"BD",
    "gn:dem":38,
    "gn:feature_class":"P",
    "gn:feature_code":"PPL",
    "gn:name":"Rudreswar",
    "gn:population":0,
    "gn:timezone":"Asia/Dhaka",
    "iso:country":"BD",
    "name:ben_x_preferred":[
        "Rudreswar"
    ],
    "name:ben_x_variant":[
        "Rudreshwar"
    ],
    "wof:name":"Rudreswar",
    "wof:placetype":"locality"
},
  "geometry": {"coordinates":[89.27619,25.90826],"type":"Point"}
}