{
  "type": "Feature",
  "properties": {
    "gn:admin1_code":"H",
    "gn:admin2_code":"3061",
    "gn:admin3_code":"306123.0",
    "gn:admin4_code":"30612322.0",
    "gn:asciiname":"Krishnapur",
    "gn:country_code":"BD",
    "gn:dem":17,
    "gn:feature_class":"P",
    "gn:feature_code":"PPL",
    "gn:name":"Krishnapur",
    "gn:population":0,
    "gn:timezone":"Asia/Dhaka",
    "iso:country":"BD",
    "name:ceb_x_preferred":[
        "Krishnapur"
    ],
    "name:swe_x_preferred":[
        "Krishnapur"
    ],
    "wof:name":"Krishnapur",
    "wof:placetype":"locality"
},
  "geometry": {"coordinates":[90.59524,24.75607],"type":"Point"}
}