{
  "type": "Feature",
  "properties": {
    "gn:admin1_code":"H",
    "gn:admin2_code":"3089",
    "gn:admin3_code":"308988.0",
    "gn:admin4_code":"30898820.0",
    "gn:asciiname":"Nabin Char",
    "gn:country_code":"BD",
    "gn:dem":23,
    "gn:feature_class":"P",
    "gn:feature_code":"PPL",
    "gn:name":"Nabin Char",
    "gn:population":0,
    "gn:timezone":"Asia/Dhaka",
    "iso:country":"BD",
    "name:ben_x_preferred":[
        "Nabin Char"
    ],
    "wof:name":"Nabin Char",
    "wof:placetype":"locality"
},
  "geometry": {"coordinates":[90.02763,25.00076],"type":"Point"}
}