{
  "type": "Feature",
  "properties": {
    "gn:admin1_code":"83",
    "gn:admin2_code":"5069",
    "gn:admin3_code":"506944.0",
    "gn:admin4_code":"50694466.0",
    "gn:asciiname":"Majpara",
    "gn:cc2":"BD",
    "gn:country_code":"BD",
    "gn:dem":18,
    "gn:feature_class":"P",
    "gn:feature_code":"PPL",
    "gn:name":"M\u0101jp\u0101ra",
    "gn:population":0,
    "gn:timezone":"Asia/Dhaka",
    "iso:country":"BD",
    "name:und_x_variant":[
        "Majhpara",
        "M\u0101jp\u0101ra"
    ],
    "wof:name":"Majpara",
    "wof:placetype":"locality"
},
  "geometry": {"coordinates":[89.01666999999998,24.16667],"type":"Point"}
}