{
  "type": "Feature",
  "properties": {
    "gn:admin1_code":"84",
    "gn:admin2_code":"2022.0",
    "gn:admin3_code":"202224.0",
    "gn:admin4_code":"20222483.0",
    "gn:asciiname":"Pakkhali",
    "gn:country_code":"BD",
    "gn:dem":8,
    "gn:feature_class":"P",
    "gn:feature_code":"PPL",
    "gn:name":"Pakkh\u0101li",
    "gn:population":0,
    "gn:timezone":"Asia/Dhaka",
    "iso:country":"BD",
    "name:ben_x_preferred":[
        "Pakkh\u0101li"
    ],
    "wof:name":"Pakkhali",
    "wof:placetype":"locality"
},
  "geometry": {"coordinates":[92.01468,21.54872],"type":"Point"}
}