{
  "type": "Feature",
  "properties": {
    "gn:admin1_code":"84",
    "gn:admin2_code":"2013",
    "gn:admin3_code":"201349.0",
    "gn:admin4_code":"20134950.0",
    "gn:asciiname":"Muhabbatpur Sihircho",
    "gn:country_code":"BD",
    "gn:dem":10,
    "gn:feature_class":"P",
    "gn:feature_code":"PPL",
    "gn:name":"Muhabbatpur Sihircho",
    "gn:population":0,
    "gn:timezone":"Asia/Dhaka",
    "iso:country":"BD",
    "name:und_x_variant":[
        "Mahabbatpur"
    ],
    "wof:name":"Muhabbatpur Sihircho",
    "wof:placetype":"locality"
},
  "geometry": {"coordinates":[90.83611000000001,23.30301],"type":"Point"}
}