{
  "type": "Feature",
  "properties": {
    "gn:admin1_code":"81",
    "gn:admin2_code":"3067",
    "gn:admin3_code":"306702.0",
    "gn:admin4_code":"30670239.0",
    "gn:asciiname":"Kaempur",
    "gn:country_code":"BD",
    "gn:dem":8,
    "gn:feature_class":"P",
    "gn:feature_code":"PPL",
    "gn:name":"K\u0101empur",
    "gn:population":0,
    "gn:timezone":"Asia/Dhaka",
    "iso:country":"BD",
    "wof:name":"Kaempur",
    "wof:placetype":"locality"
},
  "geometry": {"coordinates":[90.66667,23.76667],"type":"Point"}
}