{
  "type": "Feature",
  "properties": {
    "gn:admin1_code":"84",
    "gn:admin2_code":"2046.0",
    "gn:admin3_code":"204643.0",
    "gn:admin4_code":"20464315.0",
    "gn:asciiname":"Chatrachara",
    "gn:country_code":"BD",
    "gn:dem":81,
    "gn:feature_class":"P",
    "gn:feature_code":"PPL",
    "gn:name":"Chatr\u0101chara",
    "gn:population":0,
    "gn:timezone":"Asia/Dhaka",
    "iso:country":"BD",
    "name:und_x_variant":[
        "Chatarachhara",
        "Chatr\u0101chara"
    ],
    "wof:name":"Chatrachara",
    "wof:placetype":"locality"
},
  "geometry": {"coordinates":[92.00324000000001,23.37946],"type":"Point"}
}