{
  "type": "Feature",
  "properties": {
    "gn:admin1_code":"87",
    "gn:admin2_code":"5577.0",
    "gn:admin3_code":"557773.0",
    "gn:admin4_code":"55777365.0",
    "gn:asciiname":"Nayani",
    "gn:country_code":"BD",
    "gn:dem":76,
    "gn:feature_class":"P",
    "gn:feature_code":"PPL",
    "gn:name":"Nayani",
    "gn:population":0,
    "gn:timezone":"Asia/Dhaka",
    "iso:country":"BD",
    "name:ben_x_preferred":[
        "Nayani"
    ],
    "wof:name":"Nayani",
    "wof:placetype":"locality"
},
  "geometry": {"coordinates":[88.48719,26.2791],"type":"Point"}
}