{
  "type": "Feature",
  "properties": {
    "gn:admin1_code":"83",
    "gn:asciiname":"Bhag Gopal",
    "gn:country_code":"BD",
    "gn:dem":24,
    "gn:feature_class":"P",
    "gn:feature_code":"PPL",
    "gn:name":"Bh\u0101g Gop\u0101l",
    "gn:population":0,
    "gn:timezone":"Asia/Dhaka",
    "iso:country":"BD",
    "name:ben_x_preferred":[
        "Bh\u0101g Gop\u0101l"
    ],
    "wof:name":"Bhag Gopal",
    "wof:placetype":"locality"
},
  "geometry": {"coordinates":[89.40194,25.10312],"type":"Point"}
}