{
  "type": "Feature",
  "properties": {
    "gn:admin1_code":"85",
    "gn:admin2_code":"1078.0",
    "gn:admin3_code":"107897.0",
    "gn:admin4_code":"10789727.0",
    "gn:asciiname":"Khashmahal",
    "gn:country_code":"BD",
    "gn:dem":8,
    "gn:feature_class":"P",
    "gn:feature_code":"PPL",
    "gn:name":"Kh\u0101shmahal",
    "gn:population":0,
    "gn:timezone":"Asia/Dhaka",
    "iso:country":"BD",
    "name:ben_x_preferred":[
        "Kh\u0101shmahal"
    ],
    "wof:name":"Khashmahal",
    "wof:placetype":"locality"
},
  "geometry": {"coordinates":[90.33069,21.86676],"type":"Point"}
}