{
  "type": "Feature",
  "properties": {
    "gn:admin1_code":"87",
    "gn:admin2_code":"5549",
    "gn:admin3_code":"554961.0",
    "gn:admin4_code":"55496169.0",
    "gn:asciiname":"Sukhati",
    "gn:country_code":"BD",
    "gn:dem":33,
    "gn:feature_class":"P",
    "gn:feature_code":"PPL",
    "gn:name":"Sukh\u0101ti",
    "gn:population":0,
    "gn:timezone":"Asia/Dhaka",
    "iso:country":"BD",
    "name:ben_x_preferred":[
        "Sukh\u0101ti"
    ],
    "wof:name":"Sukhati",
    "wof:placetype":"locality"
},
  "geometry": {"coordinates":[89.67695999999999,25.96124],"type":"Point"}
}