{
  "type": "Feature",
  "properties": {
    "gn:admin1_code":"82",
    "gn:admin2_code":"4041.0",
    "gn:admin3_code":"404147.0",
    "gn:admin4_code":"40414711.0",
    "gn:asciiname":"Basundia",
    "gn:country_code":"BD",
    "gn:dem":15,
    "gn:feature_class":"P",
    "gn:feature_code":"PPL",
    "gn:name":"Basundia",
    "gn:population":0,
    "gn:timezone":"Asia/Dhaka",
    "iso:country":"BD",
    "name:ben_x_preferred":[
        "Basundia"
    ],
    "wof:name":"Basundia",
    "wof:placetype":"locality"
},
  "geometry": {"coordinates":[89.37085999999999,23.12449],"type":"Point"}
}