{
  "type": "Feature",
  "properties": {
    "gn:admin1_code":"84",
    "gn:admin2_code":"2019.0",
    "gn:admin3_code":"201915.0",
    "gn:admin4_code":"20191588.0",
    "gn:asciiname":"Dhusia",
    "gn:country_code":"BD",
    "gn:dem":9,
    "gn:feature_class":"P",
    "gn:feature_code":"PPL",
    "gn:name":"Dhusia",
    "gn:population":0,
    "gn:timezone":"Asia/Dhaka",
    "iso:country":"BD",
    "name:und_x_variant":[
        "Chhota Dhusia"
    ],
    "wof:name":"Dhusia",
    "wof:placetype":"locality"
},
  "geometry": {"coordinates":[91.11982,23.66106],"type":"Point"}
}