{
  "type": "Feature",
  "properties": {
    "gn:admin1_code":"81",
    "gn:admin2_code":"3048.0",
    "gn:admin3_code":"304892.0",
    "gn:admin4_code":"30489294.0",
    "gn:asciiname":"Dari Jahangirpur",
    "gn:country_code":"BD",
    "gn:dem":13,
    "gn:feature_class":"P",
    "gn:feature_code":"PPL",
    "gn:name":"Dari Jah\u0101ng\u012brpur",
    "gn:population":0,
    "gn:timezone":"Asia/Dhaka",
    "iso:country":"BD",
    "wof:name":"Dari Jahangirpur",
    "wof:placetype":"locality"
},
  "geometry": {"coordinates":[90.85299999999999,24.54359],"type":"Point"}
}