{
  "type": "Feature",
  "properties": {
    "gn:admin1_code":"87",
    "gn:admin2_code":"5594.0",
    "gn:admin3_code":"559482.0",
    "gn:admin4_code":"55948251.0",
    "gn:asciiname":"Chandra",
    "gn:country_code":"BD",
    "gn:dem":46,
    "gn:feature_class":"P",
    "gn:feature_code":"PPL",
    "gn:name":"Ch\u0101ndra",
    "gn:population":0,
    "gn:timezone":"Asia/Dhaka",
    "iso:country":"BD",
    "name:ben_x_preferred":[
        "Ch\u0101ndra"
    ],
    "wof:name":"Chandra",
    "wof:placetype":"locality"
},
  "geometry": {"coordinates":[88.32675,25.74045],"type":"Point"}
}