{
  "type": "Feature",
  "properties": {
    "gn:admin1_code":"85",
    "gn:admin2_code":"1078.0",
    "gn:admin3_code":"107852.0",
    "gn:admin4_code":"10785231.0",
    "gn:asciiname":"Nijala",
    "gn:country_code":"BD",
    "gn:dem":9,
    "gn:feature_class":"P",
    "gn:feature_code":"PPL",
    "gn:name":"Nij\u0101la",
    "gn:population":0,
    "gn:timezone":"Asia/Dhaka",
    "iso:country":"BD",
    "name:ben_x_preferred":[
        "Nij\u0101la"
    ],
    "wof:name":"Nijala",
    "wof:placetype":"locality"
},
  "geometry": {"coordinates":[90.57514,22.29445],"type":"Point"}
}