{
  "type": "Feature",
  "properties": {
    "gn:admin1_code":"87",
    "gn:admin2_code":"5594.0",
    "gn:admin3_code":"559494.0",
    "gn:admin4_code":"55949410.0",
    "gn:asciiname":"Chotrakhora",
    "gn:country_code":"BD",
    "gn:dem":62,
    "gn:feature_class":"P",
    "gn:feature_code":"PPL",
    "gn:name":"Chotr\u0101khor\u0101",
    "gn:population":0,
    "gn:timezone":"Asia/Dhaka",
    "iso:country":"BD",
    "name:ben_x_preferred":[
        "Chotr\u0101khor\u0101"
    ],
    "wof:name":"Chotrakhora",
    "wof:placetype":"locality"
},
  "geometry": {"coordinates":[88.35824000000002,26.10238],"type":"Point"}
}