{
  "type": "Feature",
  "properties": {
    "gn:admin1_code":"84",
    "gn:admin2_code":"2051.0",
    "gn:admin3_code":"205165.0",
    "gn:admin4_code":"20516523.0",
    "gn:asciiname":"Chandipur",
    "gn:country_code":"BD",
    "gn:dem":14,
    "gn:feature_class":"P",
    "gn:feature_code":"PPL",
    "gn:name":"Chandipur",
    "gn:population":0,
    "gn:timezone":"Asia/Dhaka",
    "iso:country":"BD",
    "wof:name":"Chandipur",
    "wof:placetype":"locality"
},
  "geometry": {"coordinates":[90.83181,23.07684],"type":"Point"}
}