{
  "type": "Feature",
  "properties": {
    "gn:admin1_code":"85",
    "gn:admin2_code":"1078.0",
    "gn:admin3_code":"107838.0",
    "gn:admin4_code":"10783883.0",
    "gn:asciiname":"Batkajal",
    "gn:country_code":"BD",
    "gn:dem":8,
    "gn:feature_class":"P",
    "gn:feature_code":"PPL",
    "gn:name":"Batk\u0101jal",
    "gn:population":0,
    "gn:timezone":"Asia/Dhaka",
    "iso:country":"BD",
    "name:ben_x_preferred":[
        "Batk\u0101jal"
    ],
    "wof:name":"Batkajal",
    "wof:placetype":"locality"
},
  "geometry": {"coordinates":[90.50476999999999,22.38107],"type":"Point"}
}