{
  "type": "Feature",
  "properties": {
    "gn:admin1_code":"81",
    "gn:admin2_code":"3035.0",
    "gn:admin3_code":"303551.0",
    "gn:admin4_code":"30355155.0",
    "gn:asciiname":"Digrarpar",
    "gn:country_code":"BD",
    "gn:dem":6,
    "gn:feature_class":"P",
    "gn:feature_code":"PPL",
    "gn:name":"Digrarp\u0101r",
    "gn:population":0,
    "gn:timezone":"Asia/Dhaka",
    "iso:country":"BD",
    "name:ben_x_preferred":[
        "Digrarp\u0101r"
    ],
    "wof:name":"Digrarpar",
    "wof:placetype":"locality"
},
  "geometry": {"coordinates":[89.98704000000002,23.02719],"type":"Point"}
}