{
  "type": "Feature",
  "properties": {
    "gn:admin1_code":"86",
    "gn:admin2_code":"6091.0",
    "gn:admin3_code":"609138.0",
    "gn:admin4_code":"60913817.0",
    "gn:asciiname":"Bhadeswar",
    "gn:country_code":"BD",
    "gn:dem":18,
    "gn:feature_class":"P",
    "gn:feature_code":"PPL",
    "gn:name":"Bh\u0101deswar",
    "gn:population":0,
    "gn:timezone":"Asia/Dhaka",
    "iso:country":"BD",
    "wof:name":"Bhadeswar",
    "wof:placetype":"locality"
},
  "geometry": {"coordinates":[92.03333000000001,24.76667],"type":"Point"}
}