{
  "type": "Feature",
  "properties": {
    "gn:admin1_code":"83",
    "gn:admin2_code":"5076.0",
    "gn:admin3_code":"507672.0",
    "gn:admin4_code":"50767260.0",
    "gn:asciiname":"Huikhali Parbbati",
    "gn:country_code":"BD",
    "gn:dem":10,
    "gn:feature_class":"P",
    "gn:feature_code":"PPL",
    "gn:name":"Huikh\u0101li Parbbati",
    "gn:population":0,
    "gn:timezone":"Asia/Dhaka",
    "iso:country":"BD",
    "name:ben_x_preferred":[
        "Huikh\u0101li Parbbati"
    ],
    "wof:name":"Huikhali Parbbati",
    "wof:placetype":"locality"
},
  "geometry": {"coordinates":[89.58301,23.98848],"type":"Point"}
}