{
  "type": "Feature",
  "properties": {
    "gn:admin1_code":"87",
    "gn:admin2_code":"5577.0",
    "gn:admin3_code":"557704.0",
    "gn:admin4_code":"55770440.0",
    "gn:asciiname":"Sajnapara",
    "gn:country_code":"BD",
    "gn:dem":75,
    "gn:feature_class":"P",
    "gn:feature_code":"PPL",
    "gn:name":"Sajn\u0101p\u0101ra",
    "gn:population":0,
    "gn:timezone":"Asia/Dhaka",
    "iso:country":"BD",
    "name:ben_x_preferred":[
        "Sajn\u0101p\u0101ra"
    ],
    "wof:name":"Sajnapara",
    "wof:placetype":"locality"
},
  "geometry": {"coordinates":[88.39778000000003,26.29461],"type":"Point"}
}