{
  "type": "Feature",
  "properties": {
    "gn:admin1_code":"83",
    "gn:admin2_code":"5070",
    "gn:admin3_code":"507056.0",
    "gn:admin4_code":"50705676.0",
    "gn:asciiname":"Jangla Dogachhi",
    "gn:country_code":"BD",
    "gn:dem":43,
    "gn:feature_class":"P",
    "gn:feature_code":"PPL",
    "gn:name":"Jangla Dog\u0101chhi",
    "gn:population":0,
    "gn:timezone":"Asia/Dhaka",
    "iso:country":"BD",
    "name:ben_x_preferred":[
        "Jangla Dog\u0101chhi"
    ],
    "name:und_x_variant":[
        "Jangla Dogachi"
    ],
    "wof:name":"Jangla Dogachhi",
    "wof:placetype":"locality"
},
  "geometry": {"coordinates":[88.45106,24.67216],"type":"Point"}
}