{
  "type": "Feature",
  "properties": {
    "gn:admin1_code":"81",
    "gn:admin2_code":"3035",
    "gn:admin3_code":"303532.0",
    "gn:admin4_code":"30353251.0",
    "gn:asciiname":"Raypasa",
    "gn:country_code":"BD",
    "gn:dem":6,
    "gn:feature_class":"P",
    "gn:feature_code":"PPL",
    "gn:name":"R\u0101yp\u0101sa",
    "gn:population":0,
    "gn:timezone":"Asia/Dhaka",
    "iso:country":"BD",
    "name:ben_x_preferred":[
        "R\u0101yp\u0101sa"
    ],
    "name:und_x_variant":[
        "Raipasha"
    ],
    "wof:name":"Raypasa",
    "wof:placetype":"locality"
},
  "geometry": {"coordinates":[89.91343000000001,23.02767],"type":"Point"}
}