{
  "type": "Feature",
  "properties": {
    "gn:admin1_code":"82",
    "gn:admin2_code":"4087",
    "gn:admin3_code":"408747.0",
    "gn:admin4_code":"40874739.0",
    "gn:asciiname":"Khubdipur",
    "gn:country_code":"BD",
    "gn:dem":7,
    "gn:feature_class":"P",
    "gn:feature_code":"PPL",
    "gn:name":"Khubdipur",
    "gn:population":0,
    "gn:timezone":"Asia/Dhaka",
    "iso:country":"BD",
    "name:ben_x_preferred":[
        "Khubdipur"
    ],
    "name:und_x_variant":[
        "Khudkipur"
    ],
    "wof:name":"Khubdipur",
    "wof:placetype":"locality"
},
  "geometry": {"coordinates":[89.03038000000002,22.36667000000001],"type":"Point"}
}