{
  "type": "Feature",
  "properties": {
    "gn:admin1_code":"83",
    "gn:admin2_code":"5064.0",
    "gn:admin3_code":"506447.0",
    "gn:admin4_code":"50644767.0",
    "gn:asciiname":"Bandaipur",
    "gn:country_code":"BD",
    "gn:dem":19,
    "gn:feature_class":"P",
    "gn:feature_code":"PPL",
    "gn:name":"B\u0101ndaipur",
    "gn:population":0,
    "gn:timezone":"Asia/Dhaka",
    "iso:country":"BD",
    "name:ben_x_preferred":[
        "B\u0101ndaipur"
    ],
    "wof:name":"Bandaipur",
    "wof:placetype":"locality"
},
  "geometry": {"coordinates":[88.67782,24.79535],"type":"Point"}
}