{
  "type": "Feature",
  "properties": {
    "gn:admin1_code":"83",
    "gn:admin2_code":"5064.0",
    "gn:admin3_code":"506450.0",
    "gn:admin4_code":"50645038.0",
    "gn:asciiname":"Chak Hariballabh",
    "gn:country_code":"BD",
    "gn:dem":21,
    "gn:feature_class":"P",
    "gn:feature_code":"PPL",
    "gn:name":"Chak Hariballabh",
    "gn:population":0,
    "gn:timezone":"Asia/Dhaka",
    "iso:country":"BD",
    "wof:name":"Chak Hariballabh",
    "wof:placetype":"locality"
},
  "geometry": {"coordinates":[88.74429000000001,24.94658],"type":"Point"}
}