{
  "type": "Feature",
  "properties": {
    "gn:admin1_code":"84",
    "gn:admin2_code":"2022.0",
    "gn:admin3_code":"202266.0",
    "gn:admin4_code":"20226657.0",
    "gn:asciiname":"Uttar Khuniapalong",
    "gn:country_code":"BD",
    "gn:dem":15,
    "gn:feature_class":"P",
    "gn:feature_code":"PPL",
    "gn:name":"Uttar Khuniap\u0101long",
    "gn:population":0,
    "gn:timezone":"Asia/Dhaka",
    "iso:country":"BD",
    "name:ben_x_preferred":[
        "Uttar Khuniap\u0101long"
    ],
    "wof:name":"Uttar Khuniapalong",
    "wof:placetype":"locality"
},
  "geometry": {"coordinates":[92.07731,21.35394],"type":"Point"}
}