{
  "type": "Feature",
  "properties": {
    "gn:admin1_code":"81",
    "gn:admin2_code":"3035.0",
    "gn:admin3_code":"303532.0",
    "gn:admin4_code":"30353282.0",
    "gn:asciiname":"Elharkelia",
    "gn:country_code":"BD",
    "gn:dem":7,
    "gn:feature_class":"P",
    "gn:feature_code":"PPL",
    "gn:name":"Elh\u0101rkelia",
    "gn:population":0,
    "gn:timezone":"Asia/Dhaka",
    "iso:country":"BD",
    "name:ben_x_preferred":[
        "Elh\u0101rkelia"
    ],
    "wof:name":"Elharkelia",
    "wof:placetype":"locality"
},
  "geometry": {"coordinates":[89.91514000000002,23.13673],"type":"Point"}
}