{
  "type": "Feature",
  "properties": {
    "gn:admin1_code":"87",
    "gn:admin2_code":"5527.0",
    "gn:admin3_code":"552738.0",
    "gn:admin4_code":"55273828.0",
    "gn:asciiname":"Karai",
    "gn:country_code":"BD",
    "gn:dem":36,
    "gn:feature_class":"P",
    "gn:feature_code":"PPL",
    "gn:name":"Karai",
    "gn:population":0,
    "gn:timezone":"Asia/Dhaka",
    "iso:country":"BD",
    "name:ben_x_preferred":[
        "Karai"
    ],
    "wof:name":"Karai",
    "wof:placetype":"locality"
},
  "geometry": {"coordinates":[88.87373000000002,25.41447],"type":"Point"}
}