{
  "type": "Feature",
  "properties": {
    "gn:admin1_code":"84",
    "gn:admin2_code":"2019",
    "gn:admin3_code":"201972.0",
    "gn:admin4_code":"20197217.0",
    "gn:asciiname":"Udhair",
    "gn:country_code":"BD",
    "gn:dem":8,
    "gn:feature_class":"P",
    "gn:feature_code":"PPL",
    "gn:name":"Udh\u0101ir",
    "gn:population":0,
    "gn:timezone":"Asia/Dhaka",
    "iso:country":"BD",
    "wof:name":"Udhair",
    "wof:placetype":"locality"
},
  "geometry": {"coordinates":[91.08333,23.28333],"type":"Point"}
}