{
  "type": "Feature",
  "properties": {
    "gn:admin1_code":"84",
    "gn:admin2_code":"2046.0",
    "gn:admin3_code":"204661.0",
    "gn:admin4_code":"20466147.0",
    "gn:asciiname":"Ekchari",
    "gn:country_code":"BD",
    "gn:dem":61,
    "gn:feature_class":"P",
    "gn:feature_code":"PPL",
    "gn:name":"Ekchari",
    "gn:population":0,
    "gn:timezone":"Asia/Dhaka",
    "iso:country":"BD",
    "name:ben_x_preferred":[
        "Ekchari"
    ],
    "wof:name":"Ekchari",
    "wof:placetype":"locality"
},
  "geometry": {"coordinates":[91.88517,22.86013],"type":"Point"}
}