{
  "type": "Feature",
  "properties": {
    "gn:admin1_code":"81",
    "gn:admin2_code":"3086",
    "gn:admin3_code":"308665.0",
    "gn:admin4_code":"30866582.0",
    "gn:asciiname":"Udaytara",
    "gn:country_code":"BD",
    "gn:dem":12,
    "gn:feature_class":"P",
    "gn:feature_code":"PPL",
    "gn:name":"Udayt\u0101ra",
    "gn:population":0,
    "gn:timezone":"Asia/Dhaka",
    "iso:country":"BD",
    "wof:name":"Udaytara",
    "wof:placetype":"locality"
},
  "geometry": {"coordinates":[90.34935,23.28061],"type":"Point"}
}