{
  "type": "Feature",
  "properties": {
    "gn:admin1_code":"H",
    "gn:admin2_code":"3089",
    "gn:admin3_code":"308970.0",
    "gn:admin4_code":"30897077.0",
    "gn:asciiname":"Mandirtala",
    "gn:country_code":"BD",
    "gn:dem":24,
    "gn:feature_class":"P",
    "gn:feature_code":"PPL",
    "gn:name":"Mandirtala",
    "gn:population":0,
    "gn:timezone":"Asia/Dhaka",
    "iso:country":"BD",
    "name:ben_x_preferred":[
        "Mandirtala"
    ],
    "wof:name":"Mandirtala",
    "wof:placetype":"locality"
},
  "geometry": {"coordinates":[90.12204,25.13494],"type":"Point"}
}