{
  "type": "Feature",
  "properties": {
    "gn:admin1_code":"85",
    "gn:admin2_code":"1042.0",
    "gn:admin3_code":"104273.0",
    "gn:admin4_code":"10427384.0",
    "gn:asciiname":"Purba Siddakati",
    "gn:country_code":"BD",
    "gn:dem":9,
    "gn:feature_class":"P",
    "gn:feature_code":"PPL",
    "gn:name":"Purba Siddakati",
    "gn:population":0,
    "gn:timezone":"Asia/Dhaka",
    "iso:country":"BD",
    "name:und_x_variant":[
        "East Siddhak\u0101ti"
    ],
    "wof:name":"Purba Siddakati",
    "wof:placetype":"locality"
},
  "geometry": {"coordinates":[90.29835,22.60906],"type":"Point"}
}