{
  "type": "Feature",
  "properties": {
    "gn:admin1_code":"H",
    "gn:admin2_code":"3061",
    "gn:admin3_code":"306152.0",
    "gn:admin4_code":"30615274.0",
    "gn:asciiname":"Matiamtala",
    "gn:country_code":"BD",
    "gn:dem":19,
    "gn:feature_class":"P",
    "gn:feature_code":"PPL",
    "gn:name":"M\u0101ti\u0101mtala",
    "gn:population":0,
    "gn:timezone":"Asia/Dhaka",
    "iso:country":"BD",
    "wof:name":"Matiamtala",
    "wof:placetype":"locality"
},
  "geometry": {"coordinates":[90.25445000000001,24.82029],"type":"Point"}
}