{
  "type": "Feature",
  "properties": {
    "gn:admin1_code":"82",
    "gn:admin2_code":"4041",
    "gn:admin3_code":"404104.0",
    "gn:admin4_code":"40410421.0",
    "gn:asciiname":"Magura",
    "gn:country_code":"BD",
    "gn:dem":9,
    "gn:feature_class":"P",
    "gn:feature_code":"PPL",
    "gn:name":"M\u0101gura",
    "gn:population":0,
    "gn:timezone":"Asia/Dhaka",
    "iso:country":"BD",
    "name:ben_x_preferred":[
        "M\u0101gura"
    ],
    "name:ceb_x_preferred":[
        "Magura"
    ],
    "name:ces_x_preferred":[
        "Magura"
    ],
    "name:deu_x_preferred":[
        "Magura"
    ],
    "name:epo_x_preferred":[
        "Magura"
    ],
    "name:nld_x_preferred":[
        "Magura"
    ],
    "name:pol_x_preferred":[
        "Magura"
    ],
    "name:ron_x_preferred":[
        "Magura"
    ],
    "name:rus_x_preferred":[
        "\u041c\u0430\u0433\u0443\u0440\u0430"
    ],
    "name:slk_x_preferred":[
        "Magura"
    ],
    "name:srp_x_preferred":[
        "\u041c\u0430\u0433\u0443\u0440\u0430"
    ],
    "name:swe_x_preferred":[
        "Magura"
    ],
    "name:ukr_x_preferred":[
        "\u041c\u0430\u0491\u0443\u0440\u0430"
    ],
    "wof:name":"Magura",
    "wof:placetype":"locality"
},
  "geometry": {"coordinates":[89.32638,23.08072],"type":"Point"}
}