{
  "type": "Feature",
  "properties": {
    "gn:admin1_code":"82",
    "gn:admin2_code":"4041",
    "gn:admin3_code":"404104.0",
    "gn:admin4_code":"40410421.0",
    "gn:asciiname":"Magura",
    "gn:country_code":"BD",
    "gn:dem":9,
    "gn:feature_class":"P",
    "gn:feature_code":"PPL",
    "gn:name":"M\u0101gura",
    "gn:population":0,
    "gn:timezone":"Asia/Dhaka",
    "iso:country":"BD",
    "name:ben_x_preferred":[
        "M\u0101gura"
    ],
    "wof:name":"Magura",
    "wof:placetype":"locality"
},
  "geometry": {"coordinates":[89.32638,23.08072],"type":"Point"}
}