{
  "type": "Feature",
  "properties": {
    "gn:admin1_code":"82",
    "gn:admin2_code":"4055.0",
    "gn:admin3_code":"405585.0",
    "gn:admin4_code":"40558523.0",
    "gn:asciiname":"Radhadanga",
    "gn:country_code":"BD",
    "gn:dem":14,
    "gn:feature_class":"P",
    "gn:feature_code":"PPL",
    "gn:name":"Radhad\u0101nga",
    "gn:population":0,
    "gn:timezone":"Asia/Dhaka",
    "iso:country":"BD",
    "name:ben_x_preferred":[
        "Radhad\u0101nga"
    ],
    "wof:name":"Radhadanga",
    "wof:placetype":"locality"
},
  "geometry": {"coordinates":[89.43195,23.29474],"type":"Point"}
}