{
  "type": "Feature",
  "properties": {
    "gn:admin1_code":"81",
    "gn:admin2_code":"3035.0",
    "gn:admin3_code":"303551.0",
    "gn:admin4_code":"30355131.0",
    "gn:asciiname":"Majhbari",
    "gn:country_code":"BD",
    "gn:dem":7,
    "gn:feature_class":"P",
    "gn:feature_code":"PPL",
    "gn:name":"M\u0101jhb\u0101ri",
    "gn:population":0,
    "gn:timezone":"Asia/Dhaka",
    "iso:country":"BD",
    "name:ben_x_preferred":[
        "M\u0101jhb\u0101ri"
    ],
    "wof:name":"Majhbari",
    "wof:placetype":"locality"
},
  "geometry": {"coordinates":[89.9712,23.00121],"type":"Point"}
}