{
  "type": "Feature",
  "properties": {
    "gn:admin1_code":"83",
    "gn:admin2_code":"5064.0",
    "gn:admin3_code":"506475.0",
    "gn:admin4_code":"50647577.0",
    "gn:asciiname":"Raskanai",
    "gn:country_code":"BD",
    "gn:dem":28,
    "gn:feature_class":"P",
    "gn:feature_code":"PPL",
    "gn:name":"Rask\u0101n\u0101i",
    "gn:population":0,
    "gn:timezone":"Asia/Dhaka",
    "iso:country":"BD",
    "name:ben_x_preferred":[
        "Rask\u0101n\u0101i"
    ],
    "wof:name":"Raskanai",
    "wof:placetype":"locality"
},
  "geometry": {"coordinates":[88.79454,25.09785],"type":"Point"}
}