{
  "type": "Feature",
  "properties": {
    "gn:admin1_code":"83",
    "gn:admin2_code":"5088.0",
    "gn:admin3_code":"508850.0",
    "gn:admin4_code":"50885025.0",
    "gn:asciiname":"Dokshia Gandhail",
    "gn:country_code":"BD",
    "gn:dem":21,
    "gn:feature_class":"P",
    "gn:feature_code":"PPL",
    "gn:name":"Dokshia G\u0101ndh\u0101il",
    "gn:population":0,
    "gn:timezone":"Asia/Dhaka",
    "iso:country":"BD",
    "name:und_x_variant":[
        "Gandial",
        "Gandi\u0101il",
        "Dokshia G\u0101ndh\u0101il"
    ],
    "wof:name":"Dokshia Gandhail",
    "wof:placetype":"locality"
},
  "geometry": {"coordinates":[89.63278000000003,24.61147],"type":"Point"}
}