{
  "type": "Feature",
  "properties": {
    "gn:admin1_code":"81",
    "gn:admin2_code":"3068.0",
    "gn:admin3_code":"306864.0",
    "gn:admin4_code":"30686433.0",
    "gn:asciiname":"Char Madhua",
    "gn:country_code":"BD",
    "gn:dem":10,
    "gn:feature_class":"P",
    "gn:feature_code":"PPL",
    "gn:name":"Char Madhua",
    "gn:population":0,
    "gn:timezone":"Asia/Dhaka",
    "iso:country":"BD",
    "wof:name":"Char Madhua",
    "wof:placetype":"locality"
},
  "geometry": {"coordinates":[90.8755,23.89836],"type":"Point"}
}