{
  "type": "Feature",
  "properties": {
    "gn:admin1_code":"82",
    "gn:admin2_code":"4057.0",
    "gn:admin3_code":"405747.0",
    "gn:admin4_code":"40574763.0",
    "gn:asciiname":"Baotpara",
    "gn:country_code":"BD",
    "gn:dem":21,
    "gn:feature_class":"P",
    "gn:feature_code":"PPL",
    "gn:name":"B\u0101otp\u0101ra",
    "gn:population":0,
    "gn:timezone":"Asia/Dhaka",
    "iso:country":"BD",
    "name:ben_x_preferred":[
        "B\u0101otp\u0101ra"
    ],
    "wof:name":"Baotpara",
    "wof:placetype":"locality"
},
  "geometry": {"coordinates":[88.83974000000001,23.88505],"type":"Point"}
}