{
  "type": "Feature",
  "properties": {
    "gn:admin1_code":"82",
    "gn:admin2_code":"4047",
    "gn:admin3_code":"404730.0",
    "gn:admin4_code":"40473013.0",
    "gn:asciiname":"Ula",
    "gn:country_code":"BD",
    "gn:dem":7,
    "gn:feature_class":"P",
    "gn:feature_code":"PPL",
    "gn:name":"Ula",
    "gn:population":0,
    "gn:timezone":"Asia/Dhaka",
    "iso:country":"BD",
    "name:bel_x_preferred":[
        "\u0423\u043b\u0430"
    ],
    "name:est_x_preferred":[
        "Ula"
    ],
    "name:fra_x_preferred":[
        "Ula"
    ],
    "name:nld_x_preferred":[
        "Ula"
    ],
    "name:nno_x_preferred":[
        "Ula"
    ],
    "name:nor_x_preferred":[
        "Ula"
    ],
    "name:pol_x_preferred":[
        "Ula"
    ],
    "name:rus_x_preferred":[
        "\u0423\u043b\u0430"
    ],
    "name:ukr_x_preferred":[
        "\u0423\u043b\u0430"
    ],
    "name:vol_x_preferred":[
        "Ula"
    ],
    "wof:name":"Ula",
    "wof:placetype":"locality"
},
  "geometry": {"coordinates":[89.42388000000003,22.74286],"type":"Point"}
}