{
  "type": "Feature",
  "properties": {
    "gn:admin1_code":"83",
    "gn:admin2_code":"5070.0",
    "gn:admin3_code":"507037.0",
    "gn:admin4_code":"50703752.0",
    "gn:asciiname":"Begunbari",
    "gn:country_code":"BD",
    "gn:dem":29,
    "gn:feature_class":"P",
    "gn:feature_code":"PPL",
    "gn:name":"Begunb\u0101ri",
    "gn:population":0,
    "gn:timezone":"Asia/Dhaka",
    "iso:country":"BD",
    "name:ben_x_preferred":[
        "Begunb\u0101ri"
    ],
    "wof:name":"Begunbari",
    "wof:placetype":"locality"
},
  "geometry": {"coordinates":[88.30982,24.82675],"type":"Point"}
}