{
  "type": "Feature",
  "properties": {
    "gn:admin1_code":"87",
    "gn:admin2_code":"5585",
    "gn:admin3_code":"558576.0",
    "gn:admin4_code":"55857618.0",
    "gn:asciiname":"Panthapukur",
    "gn:country_code":"BD",
    "gn:dem":32,
    "gn:feature_class":"P",
    "gn:feature_code":"PPL",
    "gn:name":"Panthapukur",
    "gn:population":0,
    "gn:timezone":"Asia/Dhaka",
    "iso:country":"BD",
    "name:ben_x_preferred":[
        "Panthapukur"
    ],
    "wof:name":"Panthapukur",
    "wof:placetype":"locality"
},
  "geometry": {"coordinates":[89.20838000000001,25.50691],"type":"Point"}
}