{
  "type": "Feature",
  "properties": {
    "gn:admin1_code":"85",
    "gn:admin2_code":"1006",
    "gn:admin3_code":"100651.0",
    "gn:admin4_code":"10065194.0",
    "gn:asciiname":"Mollar Haola",
    "gn:country_code":"BD",
    "gn:dem":12,
    "gn:feature_class":"P",
    "gn:feature_code":"PPL",
    "gn:name":"Moll\u0101r H\u0101ola",
    "gn:population":0,
    "gn:timezone":"Asia/Dhaka",
    "iso:country":"BD",
    "wof:name":"Mollar Haola",
    "wof:placetype":"locality"
},
  "geometry": {"coordinates":[90.46928,22.68359],"type":"Point"}
}