{
  "type": "Feature",
  "properties": {
    "gn:admin1_code":"83",
    "gn:admin2_code":"5081.0",
    "gn:admin3_code":"508125.0",
    "gn:admin4_code":"50812547.0",
    "gn:asciiname":"Naudapara",
    "gn:country_code":"BD",
    "gn:dem":22,
    "gn:feature_class":"P",
    "gn:feature_code":"PPL",
    "gn:name":"Naud\u0101para",
    "gn:population":0,
    "gn:timezone":"Asia/Dhaka",
    "iso:country":"BD",
    "name:ben_x_preferred":[
        "Naud\u0101para"
    ],
    "wof:name":"Naudapara",
    "wof:placetype":"locality"
},
  "geometry": {"coordinates":[88.69185999999998,24.34509],"type":"Point"}
}