{
  "type": "Feature",
  "properties": {
    "gn:admin1_code":"81",
    "gn:admin2_code":"3048.0",
    "gn:admin3_code":"304892.0",
    "gn:admin4_code":"30489281.0",
    "gn:asciiname":"Ghoshpara",
    "gn:country_code":"BD",
    "gn:dem":11,
    "gn:feature_class":"P",
    "gn:feature_code":"PPL",
    "gn:name":"Ghoshp\u0101ra",
    "gn:population":0,
    "gn:timezone":"Asia/Dhaka",
    "iso:country":"BD",
    "wof:name":"Ghoshpara",
    "wof:placetype":"locality"
},
  "geometry": {"coordinates":[90.84036999999999,24.53571],"type":"Point"}
}