{
  "type": "Feature",
  "properties": {
    "gn:admin1_code":"84",
    "gn:admin2_code":"2003.0",
    "gn:admin3_code":"200314.0",
    "gn:admin4_code":"20031415.0",
    "gn:asciiname":"Kulkianmuapara",
    "gn:country_code":"BD",
    "gn:dem":31,
    "gn:feature_class":"P",
    "gn:feature_code":"PPL",
    "gn:name":"Kulki\u0101nmu\u0101p\u0101ra",
    "gn:population":0,
    "gn:timezone":"Asia/Dhaka",
    "iso:country":"BD",
    "name:ben_x_preferred":[
        "Kulki\u0101nmu\u0101p\u0101ra"
    ],
    "wof:name":"Kulkianmuapara",
    "wof:placetype":"locality"
},
  "geometry": {"coordinates":[92.23875,22.22551],"type":"Point"}
}