{
  "type": "Feature",
  "properties": {
    "gn:admin1_code":"82",
    "gn:admin2_code":"4050",
    "gn:admin3_code":"405071.0",
    "gn:admin4_code":"40507177.0",
    "gn:asciiname":"Jantasi",
    "gn:country_code":"BD",
    "gn:dem":14,
    "gn:feature_class":"P",
    "gn:feature_code":"PPL",
    "gn:name":"Jantasi",
    "gn:population":0,
    "gn:timezone":"Asia/Dhaka",
    "iso:country":"BD",
    "name:ben_x_preferred":[
        "Jantasi"
    ],
    "name:ben_x_variant":[
        "Janbasi"
    ],
    "wof:name":"Jantasi",
    "wof:placetype":"locality"
},
  "geometry": {"coordinates":[89.22362,23.78083],"type":"Point"}
}