{
  "type": "Feature",
  "properties": {
    "gn:admin1_code":"81",
    "gn:admin2_code":"3067",
    "gn:admin3_code":"306768.0",
    "gn:admin4_code":"30676863.0",
    "gn:asciiname":"Mirkuti Chhar",
    "gn:country_code":"BD",
    "gn:dem":11,
    "gn:feature_class":"P",
    "gn:feature_code":"PPL",
    "gn:name":"Mirkuti Chhar",
    "gn:population":0,
    "gn:timezone":"Asia/Dhaka",
    "iso:country":"BD",
    "name:und_x_variant":[
        "Mirkuti Chhao"
    ],
    "wof:name":"Mirkuti Chhar",
    "wof:placetype":"locality"
},
  "geometry": {"coordinates":[90.54415,23.77613],"type":"Point"}
}