{
  "type": "Feature",
  "properties": {
    "gn:admin1_code":"82",
    "gn:admin2_code":"4055.0",
    "gn:admin3_code":"405585.0",
    "gn:admin4_code":"40558535.0",
    "gn:asciiname":"Dhapuapar",
    "gn:country_code":"BD",
    "gn:dem":10,
    "gn:feature_class":"P",
    "gn:feature_code":"PPL",
    "gn:name":"Dh\u0101pu\u0101par",
    "gn:population":0,
    "gn:timezone":"Asia/Dhaka",
    "iso:country":"BD",
    "name:ben_x_preferred":[
        "Dh\u0101pu\u0101par"
    ],
    "wof:name":"Dhapuapar",
    "wof:placetype":"locality"
},
  "geometry": {"coordinates":[89.27683,23.43043],"type":"Point"}
}