{
  "type": "Feature",
  "properties": {
    "gn:admin1_code":"82",
    "gn:admin2_code":"4047.0",
    "gn:admin3_code":"404753.0",
    "gn:admin4_code":"40475311.0",
    "gn:asciiname":"Bansal",
    "gn:country_code":"BD",
    "gn:dem":2,
    "gn:feature_class":"P",
    "gn:feature_code":"PPL",
    "gn:name":"B\u0101ns\u0101l",
    "gn:population":0,
    "gn:timezone":"Asia/Dhaka",
    "iso:country":"BD",
    "name:hin_x_preferred":[
        "\u092c\u0902\u0938\u0932"
    ],
    "wof:name":"Bansal",
    "wof:placetype":"locality"
},
  "geometry": {"coordinates":[89.31667,22.41667],"type":"Point"}
}