{
  "type": "Feature",
  "properties": {
    "gn:admin1_code":"83",
    "gn:admin2_code":"5070",
    "gn:admin3_code":"507066.0",
    "gn:admin4_code":"50706644.0",
    "gn:asciiname":"Kitka",
    "gn:country_code":"BD",
    "gn:dem":42,
    "gn:feature_class":"P",
    "gn:feature_code":"PPL",
    "gn:name":"Kitka",
    "gn:population":0,
    "gn:timezone":"Asia/Dhaka",
    "iso:country":"BD",
    "name:ben_x_preferred":[
        "Kitka"
    ],
    "name:und_x_variant":[
        "Khitta"
    ],
    "wof:name":"Kitka",
    "wof:placetype":"locality"
},
  "geometry": {"coordinates":[88.38195999999998,24.61915],"type":"Point"}
}