{
  "type": "Feature",
  "properties": {
    "gn:admin1_code":"83",
    "gn:admin2_code":"5081.0",
    "gn:admin3_code":"508182.0",
    "gn:admin4_code":"50818281.0",
    "gn:asciiname":"Tultulipara",
    "gn:country_code":"BD",
    "gn:dem":19,
    "gn:feature_class":"P",
    "gn:feature_code":"PPL",
    "gn:name":"Tultulip\u0101ra",
    "gn:population":0,
    "gn:timezone":"Asia/Dhaka",
    "iso:country":"BD",
    "name:ben_x_preferred":[
        "Tultulip\u0101ra"
    ],
    "wof:name":"Tultulipara",
    "wof:placetype":"locality"
},
  "geometry": {"coordinates":[88.88753,24.48487],"type":"Point"}
}