{
  "type": "Feature",
  "properties": {
    "gn:admin1_code":"87",
    "gn:admin2_code":"5577.0",
    "gn:admin3_code":"557773.0",
    "gn:admin4_code":"55777323.0",
    "gn:asciiname":"Sardarpara",
    "gn:country_code":"BD",
    "gn:dem":74,
    "gn:feature_class":"P",
    "gn:feature_code":"PPL",
    "gn:name":"Sardarp\u0101ra",
    "gn:population":0,
    "gn:timezone":"Asia/Dhaka",
    "iso:country":"BD",
    "name:ben_x_preferred":[
        "Sardarp\u0101ra"
    ],
    "wof:name":"Sardarpara",
    "wof:placetype":"locality"
},
  "geometry": {"coordinates":[88.66559000000002,26.34298],"type":"Point"}
}