{
  "type": "Feature",
  "properties": {
    "gn:admin1_code":"82",
    "gn:admin2_code":"4087.0",
    "gn:admin3_code":"408786.0",
    "gn:admin4_code":"40878687.0",
    "gn:asciiname":"Sora",
    "gn:country_code":"BD",
    "gn:dem":4,
    "gn:feature_class":"P",
    "gn:feature_code":"PPL",
    "gn:name":"Sora",
    "gn:population":0,
    "gn:timezone":"Asia/Dhaka",
    "iso:country":"BD",
    "name:arg_x_preferred":[
        "Sora"
    ],
    "name:ben_x_preferred":[
        "Sora"
    ],
    "name:bos_x_preferred":[
        "Sora"
    ],
    "name:cat_x_preferred":[
        "Sora"
    ],
    "name:ceb_x_preferred":[
        "Sora"
    ],
    "name:deu_x_preferred":[
        "Sora"
    ],
    "name:eus_x_preferred":[
        "Sora"
    ],
    "name:fin_x_preferred":[
        "Sora"
    ],
    "name:fra_x_preferred":[
        "Sora"
    ],
    "name:hun_x_preferred":[
        "Sora"
    ],
    "name:ita_x_preferred":[
        "Sora"
    ],
    "name:kor_x_preferred":[
        "\uc18c\ub77c"
    ],
    "name:kur_x_preferred":[
        "Sora"
    ],
    "name:lat_x_preferred":[
        "Sora"
    ],
    "name:nld_x_preferred":[
        "Sora"
    ],
    "name:por_x_preferred":[
        "Sora"
    ],
    "name:ron_x_preferred":[
        "Sora"
    ],
    "name:rus_x_preferred":[
        "\u0421\u043e\u0440\u0430"
    ],
    "name:slv_x_preferred":[
        "Sora"
    ],
    "name:spa_x_preferred":[
        "Sora"
    ],
    "name:srp_x_preferred":[
        "Sora"
    ],
    "name:swe_x_preferred":[
        "Sora"
    ],
    "name:war_x_preferred":[
        "Sora"
    ],
    "name:zho_x_preferred":[
        "Sora"
    ],
    "wof:name":"Sora",
    "wof:placetype":"locality"
},
  "geometry": {"coordinates":[89.07292,22.24584],"type":"Point"}
}