{
  "type": "Feature",
  "properties": {
    "gn:admin1_code":"82",
    "gn:admin2_code":"4050.0",
    "gn:admin3_code":"405015.0",
    "gn:admin4_code":"40501581.0",
    "gn:asciiname":"Gopalnagar",
    "gn:country_code":"BD",
    "gn:dem":20,
    "gn:feature_class":"P",
    "gn:feature_code":"PPL",
    "gn:name":"Gop\u0101lnagar",
    "gn:population":0,
    "gn:timezone":"Asia/Dhaka",
    "iso:country":"BD",
    "name:ben_x_preferred":[
        "Gop\u0101lnagar"
    ],
    "name:hif_x_preferred":[
        "Gopalnagar"
    ],
    "wof:name":"Gopalnagar",
    "wof:placetype":"locality"
},
  "geometry": {"coordinates":[88.98522,24.08189],"type":"Point"}
}