{
  "type": "Feature",
  "properties": {
    "gn:admin1_code":"83",
    "gn:admin2_code":"5069",
    "gn:admin3_code":"506944.0",
    "gn:admin4_code":"50694485.0",
    "gn:asciiname":"Maminpur",
    "gn:country_code":"BD",
    "gn:dem":20,
    "gn:feature_class":"P",
    "gn:feature_code":"PPL",
    "gn:name":"Maminpur",
    "gn:population":0,
    "gn:timezone":"Asia/Dhaka",
    "iso:country":"BD",
    "name:ben_x_preferred":[
        "Maminpur"
    ],
    "name:und_x_variant":[
        "Mominpur",
        "Maminpore"
    ],
    "wof:name":"Maminpur",
    "wof:placetype":"locality"
},
  "geometry": {"coordinates":[88.93125000000001,24.17741],"type":"Point"}
}