{
  "type": "Feature",
  "properties": {
    "gn:admin1_code":"82",
    "gn:admin2_code":"4050",
    "gn:admin3_code":"405063.0",
    "gn:admin4_code":"40506371.0",
    "gn:asciiname":"Padmajani",
    "gn:country_code":"BD",
    "gn:dem":15,
    "gn:feature_class":"P",
    "gn:feature_code":"PPL",
    "gn:name":"Padmaj\u0101ni",
    "gn:population":0,
    "gn:timezone":"Asia/Dhaka",
    "iso:country":"BD",
    "wof:name":"Padmajani",
    "wof:placetype":"locality"
},
  "geometry": {"coordinates":[89.31639,23.82861],"type":"Point"}
}