{
  "type": "Feature",
  "properties": {
    "gn:admin1_code":"81",
    "gn:admin2_code":"3082",
    "gn:admin3_code":"308276.0",
    "gn:admin4_code":"30827629.0",
    "gn:asciiname":"Udaypur",
    "gn:country_code":"BD",
    "gn:dem":12,
    "gn:feature_class":"P",
    "gn:feature_code":"PPL",
    "gn:name":"Udaypur",
    "gn:population":0,
    "gn:timezone":"Asia/Dhaka",
    "iso:country":"BD",
    "name:und_x_variant":[
        "Udaipur",
        "Udaypur"
    ],
    "wof:name":"Udaypur",
    "wof:placetype":"locality"
},
  "geometry": {"coordinates":[89.67965,23.63604],"type":"Point"}
}