{
  "type": "Feature",
  "properties": {
    "gn:admin1_code":"84",
    "gn:admin2_code":"2051.0",
    "gn:admin3_code":"205165.0",
    "gn:admin4_code":"20516557.0",
    "gn:asciiname":"Daspara",
    "gn:country_code":"BD",
    "gn:dem":8,
    "gn:feature_class":"P",
    "gn:feature_code":"PPL",
    "gn:name":"D\u0101sp\u0101ra",
    "gn:population":0,
    "gn:timezone":"Asia/Dhaka",
    "iso:country":"BD",
    "wof:name":"Daspara",
    "wof:placetype":"locality"
},
  "geometry": {"coordinates":[90.84969,23.0515],"type":"Point"}
}