{
  "type": "Feature",
  "properties": {
    "gn:admin1_code":"H",
    "gn:admin2_code":"3061.0",
    "gn:admin3_code":"306181.0",
    "gn:admin4_code":"30618158.0",
    "gn:asciiname":"Alakdia",
    "gn:country_code":"BD",
    "gn:dem":17,
    "gn:feature_class":"P",
    "gn:feature_code":"PPL",
    "gn:name":"\u0100lakdia",
    "gn:population":0,
    "gn:timezone":"Asia/Dhaka",
    "iso:country":"BD",
    "name:und_x_variant":[
        "Alakdi",
        "\u0100lakdia"
    ],
    "wof:name":"Alakdia",
    "wof:placetype":"locality"
},
  "geometry": {"coordinates":[90.37009999999999,24.98226],"type":"Point"}
}