{
  "type": "Feature",
  "properties": {
    "gn:admin1_code":"84",
    "gn:admin2_code":"2022.0",
    "gn:admin3_code":"202249.0",
    "gn:admin4_code":"20224911.0",
    "gn:asciiname":"Fakirakhata",
    "gn:country_code":"BD",
    "gn:dem":7,
    "gn:feature_class":"P",
    "gn:feature_code":"PPL",
    "gn:name":"Fakirakh\u0101ta",
    "gn:population":0,
    "gn:timezone":"Asia/Dhaka",
    "iso:country":"BD",
    "name:ben_x_preferred":[
        "Fakirakh\u0101ta"
    ],
    "wof:name":"Fakirakhata",
    "wof:placetype":"locality"
},
  "geometry": {"coordinates":[91.92624000000001,21.55389],"type":"Point"}
}