{
  "type": "Feature",
  "properties": {
    "gn:admin1_code":"81",
    "gn:admin2_code":"3093",
    "gn:admin3_code":"309366.0",
    "gn:admin4_code":"30936647.0",
    "gn:asciiname":"Thalpara",
    "gn:country_code":"BD",
    "gn:dem":11,
    "gn:feature_class":"P",
    "gn:feature_code":"PPL",
    "gn:name":"Thalp\u0101ra",
    "gn:population":0,
    "gn:timezone":"Asia/Dhaka",
    "iso:country":"BD",
    "wof:name":"Thalpara",
    "wof:placetype":"locality"
},
  "geometry": {"coordinates":[90.08417,24.1512],"type":"Point"}
}