{
  "type": "Feature",
  "properties": {
    "gn:admin1_code":"83",
    "gn:admin2_code":"5081.0",
    "gn:admin3_code":"508112.0",
    "gn:admin4_code":"50811256.0",
    "gn:asciiname":"Baynapur",
    "gn:country_code":"BD",
    "gn:dem":19,
    "gn:feature_class":"P",
    "gn:feature_code":"PPL",
    "gn:name":"Bayn\u0101pur",
    "gn:population":0,
    "gn:timezone":"Asia/Dhaka",
    "iso:country":"BD",
    "name:ben_x_preferred":[
        "Bayn\u0101pur"
    ],
    "name:und_x_variant":[
        "Raynapur"
    ],
    "wof:name":"Baynapur",
    "wof:placetype":"locality"
},
  "geometry": {"coordinates":[88.89431999999999,24.55401],"type":"Point"}
}