{
  "type": "Feature",
  "properties": {
    "gn:admin1_code":"84",
    "gn:admin2_code":"2015.0",
    "gn:admin3_code":"201582.0",
    "gn:admin4_code":"20158247.0",
    "gn:asciiname":"Malayabad",
    "gn:country_code":"BD",
    "gn:dem":13,
    "gn:feature_class":"P",
    "gn:feature_code":"PPL",
    "gn:name":"Malay\u0101b\u0101d",
    "gn:population":0,
    "gn:timezone":"Asia/Dhaka",
    "iso:country":"BD",
    "name:ben_x_preferred":[
        "Malay\u0101b\u0101d"
    ],
    "wof:name":"Malayabad",
    "wof:placetype":"locality"
},
  "geometry": {"coordinates":[92.07039,22.15504],"type":"Point"}
}