{
  "type": "Feature",
  "properties": {
    "gn:admin1_code":"85",
    "gn:admin2_code":"1006",
    "gn:admin3_code":"100602.0",
    "gn:admin4_code":"10060215.0",
    "gn:asciiname":"Jasar",
    "gn:country_code":"BD",
    "gn:dem":7,
    "gn:feature_class":"P",
    "gn:feature_code":"PPL",
    "gn:name":"Jas\u0101r",
    "gn:population":0,
    "gn:timezone":"Asia/Dhaka",
    "iso:country":"BD",
    "wof:name":"Jasar",
    "wof:placetype":"locality"
},
  "geometry": {"coordinates":[90.16240999999999,22.98113],"type":"Point"}
}