{
  "type": "Feature",
  "properties": {
    "gn:admin1_code":"87",
    "gn:admin2_code":"5585",
    "gn:admin3_code":"558558.0",
    "gn:admin4_code":"55855850.0",
    "gn:asciiname":"Krishnapur Tentulbari",
    "gn:country_code":"BD",
    "gn:dem":33,
    "gn:feature_class":"P",
    "gn:feature_code":"PPL",
    "gn:name":"Krishnapur Tentulbari",
    "gn:population":0,
    "gn:timezone":"Asia/Dhaka",
    "iso:country":"BD",
    "name:ben_x_preferred":[
        "Krishnapur Tentulbari"
    ],
    "wof:name":"Krishnapur Tentulbari",
    "wof:placetype":"locality"
},
  "geometry": {"coordinates":[89.17971,25.53689],"type":"Point"}
}