{
  "type": "Feature",
  "properties": {
    "gn:admin1_code":"83",
    "gn:admin2_code":"5064.0",
    "gn:admin3_code":"506475.0",
    "gn:admin4_code":"50647534.0",
    "gn:asciiname":"Ghoshnagar",
    "gn:country_code":"BD",
    "gn:dem":26,
    "gn:feature_class":"P",
    "gn:feature_code":"PPL",
    "gn:name":"Ghoshnagar",
    "gn:population":0,
    "gn:timezone":"Asia/Dhaka",
    "iso:country":"BD",
    "name:ben_x_preferred":[
        "Ghoshnagar"
    ],
    "wof:name":"Ghoshnagar",
    "wof:placetype":"locality"
},
  "geometry": {"coordinates":[88.82745,25.02053],"type":"Point"}
}