{
  "type": "Feature",
  "properties": {
    "gn:admin1_code":"81",
    "gn:admin2_code":"3082.0",
    "gn:admin3_code":"308273.0",
    "gn:admin4_code":"30827325.0",
    "gn:asciiname":"Dalagila",
    "gn:country_code":"BD",
    "gn:dem":13,
    "gn:feature_class":"P",
    "gn:feature_code":"PPL",
    "gn:name":"Dal\u0101gila",
    "gn:population":0,
    "gn:timezone":"Asia/Dhaka",
    "iso:country":"BD",
    "wof:name":"Dalagila",
    "wof:placetype":"locality"
},
  "geometry": {"coordinates":[89.40105,23.80589],"type":"Point"}
}