{
  "type": "Feature",
  "properties": {
    "gn:admin1_code":"H",
    "gn:admin2_code":"3061.0",
    "gn:admin3_code":"306131.0",
    "gn:admin4_code":"30613154.0",
    "gn:asciiname":"Banasram",
    "gn:country_code":"BD",
    "gn:dem":15,
    "gn:feature_class":"P",
    "gn:feature_code":"PPL",
    "gn:name":"B\u0101n\u0101sr\u0101m",
    "gn:population":0,
    "gn:timezone":"Asia/Dhaka",
    "iso:country":"BD",
    "wof:name":"Banasram",
    "wof:placetype":"locality"
},
  "geometry": {"coordinates":[90.59999999999999,24.61667000000001],"type":"Point"}
}