{
  "type": "Feature",
  "properties": {
    "gn:admin1_code":"84",
    "gn:admin2_code":"2019.0",
    "gn:admin3_code":"201967.0",
    "gn:admin4_code":"20196790.0",
    "gn:asciiname":"Baraipur",
    "gn:country_code":"BD",
    "gn:dem":11,
    "gn:feature_class":"P",
    "gn:feature_code":"PPL",
    "gn:name":"B\u0101raipur",
    "gn:population":0,
    "gn:timezone":"Asia/Dhaka",
    "iso:country":"BD",
    "name:ceb_x_preferred":[
        "Baraipur"
    ],
    "name:msa_x_preferred":[
        "Baraipur"
    ],
    "name:pol_x_preferred":[
        "Baraipur"
    ],
    "wof:name":"Baraipur",
    "wof:placetype":"locality"
},
  "geometry": {"coordinates":[91.23333,23.48333],"type":"Point"}
}