{
  "type": "Feature",
  "properties": {
    "gn:admin1_code":"83",
    "gn:admin2_code":"5070.0",
    "gn:admin3_code":"507018.0",
    "gn:admin4_code":"50701818.0",
    "gn:asciiname":"Hataspur",
    "gn:country_code":"BD",
    "gn:dem":27,
    "gn:feature_class":"P",
    "gn:feature_code":"PPL",
    "gn:name":"Hataspur",
    "gn:population":0,
    "gn:timezone":"Asia/Dhaka",
    "iso:country":"BD",
    "name:ben_x_preferred":[
        "Hataspur"
    ],
    "wof:name":"Hataspur",
    "wof:placetype":"locality"
},
  "geometry": {"coordinates":[88.18134999999999,24.93874],"type":"Point"}
}