{
  "type": "Feature",
  "properties": {
    "gn:admin1_code":"84",
    "gn:admin2_code":"2013.0",
    "gn:admin3_code":"201376.0",
    "gn:admin4_code":"20137651.0",
    "gn:asciiname":"Dhanarpar",
    "gn:country_code":"BD",
    "gn:dem":12,
    "gn:feature_class":"P",
    "gn:feature_code":"PPL",
    "gn:name":"Dhan\u0101rp\u0101r",
    "gn:population":0,
    "gn:timezone":"Asia/Dhaka",
    "iso:country":"BD",
    "wof:name":"Dhanarpar",
    "wof:placetype":"locality"
},
  "geometry": {"coordinates":[90.73333,23.35],"type":"Point"}
}