{
  "type": "Feature",
  "properties": {
    "gn:admin1_code":"87",
    "gn:admin2_code":"5594.0",
    "gn:admin3_code":"559494.0",
    "gn:admin4_code":"55949452.0",
    "gn:asciiname":"Futkibari",
    "gn:country_code":"BD",
    "gn:dem":57,
    "gn:feature_class":"P",
    "gn:feature_code":"PPL",
    "gn:name":"Futkib\u0101ri",
    "gn:population":0,
    "gn:timezone":"Asia/Dhaka",
    "iso:country":"BD",
    "name:ben_x_preferred":[
        "Futkib\u0101ri"
    ],
    "wof:name":"Futkibari",
    "wof:placetype":"locality"
},
  "geometry": {"coordinates":[88.36620000000001,25.9943],"type":"Point"}
}