{
  "type": "Feature",
  "properties": {
    "gn:admin1_code":"84",
    "gn:admin2_code":"2019.0",
    "gn:admin3_code":"201927.0",
    "gn:admin4_code":"20192723.0",
    "gn:asciiname":"Bamanda",
    "gn:country_code":"BD",
    "gn:dem":13,
    "gn:feature_class":"P",
    "gn:feature_code":"PPL",
    "gn:name":"B\u0101manda",
    "gn:population":0,
    "gn:timezone":"Asia/Dhaka",
    "iso:country":"BD",
    "wof:name":"Bamanda",
    "wof:placetype":"locality"
},
  "geometry": {"coordinates":[90.96111999999999,23.39136],"type":"Point"}
}