{
  "type": "Feature",
  "properties": {
    "gn:admin1_code":"87",
    "gn:admin2_code":"5527.0",
    "gn:admin3_code":"552756.0",
    "gn:admin4_code":"55275631.0",
    "gn:asciiname":"Dipikura",
    "gn:country_code":"BD",
    "gn:dem":42,
    "gn:feature_class":"P",
    "gn:feature_code":"PPL",
    "gn:name":"Dipikura",
    "gn:population":0,
    "gn:timezone":"Asia/Dhaka",
    "iso:country":"BD",
    "name:ben_x_preferred":[
        "Dipikura"
    ],
    "wof:name":"Dipikura",
    "wof:placetype":"locality"
},
  "geometry": {"coordinates":[88.65016,25.79603],"type":"Point"}
}