{
  "type": "Feature",
  "properties": {
    "gn:admin1_code":"82",
    "gn:admin2_code":"4087.0",
    "gn:admin3_code":"408790.0",
    "gn:admin4_code":"40879047.0",
    "gn:asciiname":"Dakshin Shahapur",
    "gn:country_code":"BD",
    "gn:dem":7,
    "gn:feature_class":"P",
    "gn:feature_code":"PPL",
    "gn:name":"Dakshin Sh\u0101h\u0101pur",
    "gn:population":0,
    "gn:timezone":"Asia/Dhaka",
    "iso:country":"BD",
    "name:und_x_variant":[
        "Dakshin Sahapur",
        "Dakshin Sh\u0101h\u0101pur"
    ],
    "wof:name":"Dakshin Shahapur",
    "wof:placetype":"locality"
},
  "geometry": {"coordinates":[89.22819,22.64725],"type":"Point"}
}