{
  "type": "Feature",
  "properties": {
    "gn:admin1_code":"81",
    "gn:admin2_code":"3048.0",
    "gn:admin3_code":"304854.0",
    "gn:admin4_code":"30485483.0",
    "gn:asciiname":"Bazra",
    "gn:country_code":"BD",
    "gn:dem":13,
    "gn:feature_class":"P",
    "gn:feature_code":"PPL",
    "gn:name":"B\u0101zra",
    "gn:population":0,
    "gn:timezone":"Asia/Dhaka",
    "iso:country":"BD",
    "wof:name":"Bazra",
    "wof:placetype":"locality"
},
  "geometry": {"coordinates":[90.89407,24.15649],"type":"Point"}
}