{
  "type": "Feature",
  "properties": {
    "gn:admin1_code":"83",
    "gn:asciiname":"Chandrapur",
    "gn:country_code":"BD",
    "gn:dem":17,
    "gn:feature_class":"P",
    "gn:feature_code":"PPL",
    "gn:name":"Chandrapur",
    "gn:population":0,
    "gn:timezone":"Asia/Dhaka",
    "iso:country":"BD",
    "name:azb_x_preferred":[
        "\u0686\u0646\u062f\u0631\u0627\u067e\u0648\u0631"
    ],
    "name:ben_x_preferred":[
        "\u099a\u09a8\u09cd\u09a6\u09cd\u09b0\u09aa\u09c1\u09b0"
    ],
    "name:bih_x_preferred":[
        "\u091a\u0902\u0926\u094d\u0930\u092a\u0941\u0930"
    ],
    "name:bpy_x_preferred":[
        "\u099a\u09a8\u09cd\u09a6\u09cd\u09b0\u09aa\u09c1\u09b0"
    ],
    "name:cat_x_preferred":[
        "Chandrapur"
    ],
    "name:ceb_x_preferred":[
        "Chandrapur"
    ],
    "name:deu_x_preferred":[
        "Chandrapur"
    ],
    "name:fas_x_preferred":[
        "\u0686\u0646\u062f\u0631\u0627\u067e\u0648\u0631"
    ],
    "name:fra_x_preferred":[
        "Chandrapur"
    ],
    "name:guj_x_preferred":[
        "\u0a9a\u0a82\u0aa6\u0acd\u0ab0\u0aaa\u0ac2\u0ab0"
    ],
    "name:hin_x_preferred":[
        "\u091a\u0928\u094d\u0926\u094d\u0930\u092a\u0941\u0930"
    ],
    "name:ita_x_preferred":[
        "Chandrapur"
    ],
    "name:kan_x_preferred":[
        "\u0c9a\u0c82\u0ca6\u0ccd\u0cb0\u0caa\u0cc1\u0cb0 \u0c9c\u0cbf\u0cb2\u0ccd\u0cb2\u0cc6"
    ],
    "name:mar_x_preferred":[
        "\u091a\u0902\u0926\u094d\u0930\u092a\u0942\u0930"
    ],
    "name:mlg_x_preferred":[
        "Chandrapur"
    ],
    "name:msa_x_preferred":[
        "Chandrapur"
    ],
    "name:new_x_preferred":[
        "\u091a\u0928\u094d\u0926\u094d\u0930\u092a\u0941\u0930"
    ],
    "name:nld_x_preferred":[
        "Chandrapur"
    ],
    "name:pam_x_preferred":[
        "Chandrapur"
    ],
    "name:pnb_x_preferred":[
        "\u0686\u0627\u0646\u062f\u0631\u0627\u067e\u0648\u0631"
    ],
    "name:pol_x_preferred":[
        "\u0106andrapur"
    ],
    "name:rus_x_preferred":[
        "\u0427\u0430\u043d\u0434\u0440\u0430\u043f\u0443\u0440"
    ],
    "name:san_x_preferred":[
        "\u091a\u0928\u094d\u0926\u094d\u0930\u092a\u0941\u0930\u092e\u094d"
    ],
    "name:srp_x_preferred":[
        "\u0427\u0430\u043d\u0434\u0440\u0430\u043f\u0443\u0440"
    ],
    "name:swe_x_preferred":[
        "Chandrapur"
    ],
    "name:tel_x_preferred":[
        "\u0c1a\u0c02\u0c26\u0c4d\u0c30\u0c2a\u0c42\u0c30\u0c4d"
    ],
    "name:urd_x_preferred":[
        "\u0686\u0646\u062f\u0631\u067e\u0648\u0631"
    ],
    "name:vie_x_preferred":[
        "Chandrapur"
    ],
    "name:war_x_preferred":[
        "Chandrapur"
    ],
    "name:xmf_x_preferred":[
        "\u10e9\u10d0\u10dc\u10d3\u10e0\u10d0\u10de\u10e3\u10e0\u10d8"
    ],
    "name:zho_x_preferred":[
        "\u94b1\u5fb7\u62c9\u666e\u5c14"
    ],
    "wof:name":"Chandrapur",
    "wof:placetype":"locality"
},
  "geometry": {"coordinates":[91.22982,25.15179],"type":"Point"}
}