{
  "type": "Feature",
  "properties": {
    "gn:admin1_code":"83",
    "gn:asciiname":"Chandrapur",
    "gn:country_code":"BD",
    "gn:dem":17,
    "gn:feature_class":"P",
    "gn:feature_code":"PPL",
    "gn:name":"Chandrapur",
    "gn:population":0,
    "gn:timezone":"Asia/Dhaka",
    "iso:country":"BD",
    "wof:name":"Chandrapur",
    "wof:placetype":"locality"
},
  "geometry": {"coordinates":[91.22982,25.15179],"type":"Point"}
}