{
  "type": "Feature",
  "properties": {
    "gn:admin1_code":"84",
    "gn:admin2_code":"2075",
    "gn:admin3_code":"207536.0",
    "gn:admin4_code":"20753657.0",
    "gn:asciiname":"Jahajmara",
    "gn:country_code":"BD",
    "gn:dem":2,
    "gn:feature_class":"P",
    "gn:feature_code":"PPL",
    "gn:name":"Jah\u0101jm\u0101ra",
    "gn:population":0,
    "gn:timezone":"Asia/Dhaka",
    "iso:country":"BD",
    "wof:name":"Jahajmara",
    "wof:placetype":"locality"
},
  "geometry": {"coordinates":[91.06694,22.10444],"type":"Point"}
}