{
  "type": "Feature",
  "properties": {
    "gn:admin1_code":"84",
    "gn:admin2_code":"2019.0",
    "gn:admin3_code":"201927.0",
    "gn:admin4_code":"20192739.0",
    "gn:asciiname":"Dakshin Barera",
    "gn:country_code":"BD",
    "gn:dem":13,
    "gn:feature_class":"P",
    "gn:feature_code":"PPL",
    "gn:name":"Dakshin Barera",
    "gn:population":0,
    "gn:timezone":"Asia/Dhaka",
    "iso:country":"BD",
    "wof:name":"Dakshin Barera",
    "wof:placetype":"locality"
},
  "geometry": {"coordinates":[91.01972000000001,23.46194],"type":"Point"}
}