{
  "type": "Feature",
  "properties": {
    "gn:admin1_code":"82",
    "gn:admin2_code":"4047.0",
    "gn:admin3_code":"404794.0",
    "gn:admin4_code":"40479467.0",
    "gn:asciiname":"Ichhamati",
    "gn:country_code":"BD",
    "gn:dem":7,
    "gn:feature_class":"P",
    "gn:feature_code":"PPL",
    "gn:name":"Ichh\u0101mati",
    "gn:population":0,
    "gn:timezone":"Asia/Dhaka",
    "iso:country":"BD",
    "name:ben_x_preferred":[
        "Ichh\u0101mati"
    ],
    "wof:name":"Ichhamati",
    "wof:placetype":"locality"
},
  "geometry": {"coordinates":[89.69200000000002,22.89356],"type":"Point"}
}