{
  "type": "Feature",
  "properties": {
    "gn:admin1_code":"87",
    "gn:admin2_code":"5585",
    "gn:admin3_code":"558542.0",
    "gn:admin4_code":"55854267.0",
    "gn:asciiname":"Sabdi",
    "gn:country_code":"BD",
    "gn:dem":36,
    "gn:feature_class":"P",
    "gn:feature_code":"PPL",
    "gn:name":"Sabdi",
    "gn:population":0,
    "gn:timezone":"Asia/Dhaka",
    "iso:country":"BD",
    "name:ben_x_preferred":[
        "Sabdi"
    ],
    "wof:name":"Sabdi",
    "wof:placetype":"locality"
},
  "geometry": {"coordinates":[89.39291999999998,25.77073],"type":"Point"}
}