{
  "type": "Feature",
  "properties": {
    "gn:admin1_code":"81",
    "gn:admin2_code":"3059",
    "gn:admin3_code":"305984.0",
    "gn:admin4_code":"30598433.0",
    "gn:asciiname":"Salepur",
    "gn:country_code":"BD",
    "gn:dem":9,
    "gn:feature_class":"P",
    "gn:feature_code":"PPL",
    "gn:name":"S\u0101lepur",
    "gn:population":0,
    "gn:timezone":"Asia/Dhaka",
    "iso:country":"BD",
    "name:ceb_x_preferred":[
        "S\u0101lepur"
    ],
    "name:ori_x_preferred":[
        "\u0b38\u0b3e\u0b32\u0b47\u0b2a\u0b41\u0b30"
    ],
    "name:swe_x_preferred":[
        "S\u0101lepur"
    ],
    "wof:name":"Salepur",
    "wof:placetype":"locality"
},
  "geometry": {"coordinates":[90.31985,23.5586],"type":"Point"}
}