{
  "type": "Feature",
  "properties": {
    "gn:admin1_code":"82",
    "gn:admin2_code":"4044.0",
    "gn:admin3_code":"404419.0",
    "gn:admin4_code":"40441942.0",
    "gn:asciiname":"Magarkhali",
    "gn:country_code":"BD",
    "gn:dem":14,
    "gn:feature_class":"P",
    "gn:feature_code":"PPL",
    "gn:name":"Magarkh\u0101li",
    "gn:population":0,
    "gn:timezone":"Asia/Dhaka",
    "iso:country":"BD",
    "name:ben_x_preferred":[
        "Magarkh\u0101li"
    ],
    "wof:name":"Magarkhali",
    "wof:placetype":"locality"
},
  "geometry": {"coordinates":[89.20166999999999,23.506],"type":"Point"}
}