{
  "type": "Feature",
  "properties": {
    "gn:admin1_code":"82",
    "gn:asciiname":"Ayeshabag",
    "gn:country_code":"BD",
    "gn:dem":7,
    "gn:feature_class":"P",
    "gn:feature_code":"PPL",
    "gn:name":"Ayesh\u0101b\u0101g",
    "gn:population":0,
    "gn:timezone":"Asia/Dhaka",
    "iso:country":"BD",
    "name:ben_x_preferred":[
        "Ayesh\u0101b\u0101g"
    ],
    "wof:name":"Ayeshabag",
    "wof:placetype":"locality"
},
  "geometry": {"coordinates":[90.81573,22.18187],"type":"Point"}
}