{
  "type": "Feature",
  "properties": {
    "gn:admin1_code":"84",
    "gn:admin2_code":"2015.0",
    "gn:admin3_code":"201561.0",
    "gn:admin4_code":"20156130.0",
    "gn:asciiname":"Baghdandi",
    "gn:country_code":"BD",
    "gn:dem":9,
    "gn:feature_class":"P",
    "gn:feature_code":"PPL",
    "gn:name":"B\u0101ghdandi",
    "gn:population":0,
    "gn:timezone":"Asia/Dhaka",
    "iso:country":"BD",
    "name:ben_x_preferred":[
        "B\u0101ghdandi"
    ],
    "wof:name":"Baghdandi",
    "wof:placetype":"locality"
},
  "geometry": {"coordinates":[91.95694,22.34137],"type":"Point"}
}