{
  "type": "Feature",
  "properties": {
    "gn:admin1_code":"87",
    "gn:admin2_code":"5532",
    "gn:admin3_code":"553282.0",
    "gn:admin4_code":"55328251.0",
    "gn:asciiname":"Jogipara",
    "gn:country_code":"BD",
    "gn:dem":28,
    "gn:feature_class":"P",
    "gn:feature_code":"PPL",
    "gn:name":"Jogipara",
    "gn:population":0,
    "gn:timezone":"Asia/Dhaka",
    "iso:country":"BD",
    "name:und_x_variant":[
        "Jugibari",
        "Jug\u012bb\u0101i",
        "Jogipara"
    ],
    "wof:name":"Jogipara",
    "wof:placetype":"locality"
},
  "geometry": {"coordinates":[89.39411,25.32753],"type":"Point"}
}