{
  "type": "Feature",
  "properties": {
    "gn:admin1_code":"83",
    "gn:admin2_code":"5076.0",
    "gn:admin3_code":"507655.0",
    "gn:admin4_code":"50765543.0",
    "gn:asciiname":"Kumarpur",
    "gn:country_code":"BD",
    "gn:dem":16,
    "gn:feature_class":"P",
    "gn:feature_code":"PPL",
    "gn:name":"Kumarpur",
    "gn:population":0,
    "gn:timezone":"Asia/Dhaka",
    "iso:country":"BD",
    "name:ben_x_preferred":[
        "Kumarpur"
    ],
    "wof:name":"Kumarpur",
    "wof:placetype":"locality"
},
  "geometry": {"coordinates":[89.23172,23.96489],"type":"Point"}
}