{
  "type": "Feature",
  "properties": {
    "gn:admin1_code":"H",
    "gn:admin2_code":"3061.0",
    "gn:admin3_code":"306123.0",
    "gn:admin4_code":"30612327.0",
    "gn:asciiname":"Char Ghoramara",
    "gn:country_code":"BD",
    "gn:dem":20,
    "gn:feature_class":"P",
    "gn:feature_code":"PPL",
    "gn:name":"Char Ghor\u0101m\u0101ra",
    "gn:population":0,
    "gn:timezone":"Asia/Dhaka",
    "iso:country":"BD",
    "wof:name":"Char Ghoramara",
    "wof:placetype":"locality"
},
  "geometry": {"coordinates":[90.4893,24.72872000000001],"type":"Point"}
}