{
  "type": "Feature",
  "properties": {
    "gn:admin1_code":"81",
    "gn:admin2_code":"3082",
    "gn:admin3_code":"308273.0",
    "gn:admin4_code":"30827335.0",
    "gn:asciiname":"Kailmahar",
    "gn:country_code":"BD",
    "gn:dem":18,
    "gn:feature_class":"P",
    "gn:feature_code":"PPL",
    "gn:name":"Kailmahar",
    "gn:population":0,
    "gn:timezone":"Asia/Dhaka",
    "iso:country":"BD",
    "name:und_x_variant":[
        "Kalimahor",
        "Kailmahar"
    ],
    "wof:name":"Kailmahar",
    "wof:placetype":"locality"
},
  "geometry": {"coordinates":[89.32388,23.7512],"type":"Point"}
}