{
  "type": "Feature",
  "properties": {
    "gn:admin1_code":"81",
    "gn:admin2_code":"3048.0",
    "gn:admin3_code":"304849.0",
    "gn:admin4_code":"30484969.0",
    "gn:asciiname":"Bhashkarkhila",
    "gn:country_code":"BD",
    "gn:dem":14,
    "gn:feature_class":"P",
    "gn:feature_code":"PPL",
    "gn:name":"Bh\u0101shkarkhila",
    "gn:population":0,
    "gn:timezone":"Asia/Dhaka",
    "iso:country":"BD",
    "wof:name":"Bhashkarkhila",
    "wof:placetype":"locality"
},
  "geometry": {"coordinates":[90.78607,24.48389],"type":"Point"}
}