{
  "type": "Feature",
  "properties": {
    "gn:admin1_code":"83",
    "gn:admin2_code":"5064.0",
    "gn:admin3_code":"506447.0",
    "gn:admin4_code":"50644754.0",
    "gn:asciiname":"Nurullabad",
    "gn:country_code":"BD",
    "gn:dem":20,
    "gn:feature_class":"P",
    "gn:feature_code":"PPL",
    "gn:name":"Nurull\u0101b\u0101d",
    "gn:population":0,
    "gn:timezone":"Asia/Dhaka",
    "iso:country":"BD",
    "name:ben_x_preferred":[
        "Nurull\u0101b\u0101d"
    ],
    "wof:name":"Nurullabad",
    "wof:placetype":"locality"
},
  "geometry": {"coordinates":[88.723,24.7297],"type":"Point"}
}