{
  "type": "Feature",
  "properties": {
    "gn:admin1_code":"84",
    "gn:admin2_code":"2003.0",
    "gn:admin3_code":"200373.0",
    "gn:admin4_code":"20037338.0",
    "gn:asciiname":"Khuyopara",
    "gn:country_code":"BD",
    "gn:dem":70,
    "gn:feature_class":"P",
    "gn:feature_code":"PPL",
    "gn:name":"Khuyop\u0101ra",
    "gn:population":0,
    "gn:timezone":"Asia/Dhaka",
    "iso:country":"BD",
    "name:ben_x_preferred":[
        "Khuyop\u0101ra"
    ],
    "wof:name":"Khuyopara",
    "wof:placetype":"locality"
},
  "geometry": {"coordinates":[92.24486,21.5216],"type":"Point"}
}