{
  "type": "Feature",
  "properties": {
    "gn:admin1_code":"85",
    "gn:admin2_code":"1006.0",
    "gn:admin3_code":"100607.0",
    "gn:admin4_code":"10060754.0",
    "gn:asciiname":"Hiradhar",
    "gn:country_code":"BD",
    "gn:dem":6,
    "gn:feature_class":"P",
    "gn:feature_code":"PPL",
    "gn:name":"Hir\u0101dhar",
    "gn:population":0,
    "gn:timezone":"Asia/Dhaka",
    "iso:country":"BD",
    "wof:name":"Hiradhar",
    "wof:placetype":"locality"
},
  "geometry": {"coordinates":[90.36561,22.54592],"type":"Point"}
}