{
  "type": "Feature",
  "properties": {
    "gn:admin1_code":"84",
    "gn:admin2_code":"2084.0",
    "gn:admin3_code":"208425.0",
    "gn:admin4_code":"20842519.0",
    "gn:asciiname":"Lungipara",
    "gn:country_code":"BD",
    "gn:dem":34,
    "gn:feature_class":"P",
    "gn:feature_code":"PPL",
    "gn:name":"Lungip\u0101ra",
    "gn:population":0,
    "gn:timezone":"Asia/Dhaka",
    "iso:country":"BD",
    "name:ben_x_preferred":[
        "Lungip\u0101ra"
    ],
    "wof:name":"Lungipara",
    "wof:placetype":"locality"
},
  "geometry": {"coordinates":[92.00156,22.50896],"type":"Point"}
}