{
  "type": "Feature",
  "properties": {
    "gn:admin1_code":"84",
    "gn:admin2_code":"2019",
    "gn:admin3_code":"201967.0",
    "gn:admin4_code":"20196765.0",
    "gn:asciiname":"Kartikpur",
    "gn:country_code":"BD",
    "gn:dem":12,
    "gn:feature_class":"P",
    "gn:feature_code":"PPL",
    "gn:name":"K\u0101rtikpur",
    "gn:population":0,
    "gn:timezone":"Asia/Dhaka",
    "iso:country":"BD",
    "wof:name":"Kartikpur",
    "wof:placetype":"locality"
},
  "geometry": {"coordinates":[91.21666999999999,23.43333],"type":"Point"}
}