{
  "type": "Feature",
  "properties": {
    "gn:admin1_code":"87",
    "gn:admin2_code":"5527.0",
    "gn:admin3_code":"552721.0",
    "gn:admin4_code":"55272154.0",
    "gn:asciiname":"Dhantala",
    "gn:country_code":"BD",
    "gn:dem":47,
    "gn:feature_class":"P",
    "gn:feature_code":"PPL",
    "gn:name":"Dhantala",
    "gn:population":0,
    "gn:timezone":"Asia/Dhaka",
    "iso:country":"BD",
    "name:ben_x_preferred":[
        "Dhantala"
    ],
    "wof:name":"Dhantala",
    "wof:placetype":"locality"
},
  "geometry": {"coordinates":[88.47084,25.80785],"type":"Point"}
}