{
  "type": "Feature",
  "properties": {
    "gn:admin1_code":"87",
    "gn:admin2_code":"5577.0",
    "gn:admin3_code":"557773.0",
    "gn:admin4_code":"55777365.0",
    "gn:asciiname":"Gumti",
    "gn:country_code":"BD",
    "gn:dem":79,
    "gn:feature_class":"P",
    "gn:feature_code":"PPL",
    "gn:name":"Gumti",
    "gn:population":0,
    "gn:timezone":"Asia/Dhaka",
    "iso:country":"BD",
    "name:ben_x_preferred":[
        "Gumti"
    ],
    "wof:name":"Gumti",
    "wof:placetype":"locality"
},
  "geometry": {"coordinates":[88.47326,26.30859],"type":"Point"}
}