{
  "type": "Feature",
  "properties": {
    "gn:admin1_code":"82",
    "gn:asciiname":"Bara Gabua",
    "gn:country_code":"BD",
    "gn:dem":7,
    "gn:feature_class":"P",
    "gn:feature_code":"PPL",
    "gn:name":"Bara G\u0101bua",
    "gn:population":0,
    "gn:timezone":"Asia/Dhaka",
    "iso:country":"BD",
    "name:ben_x_preferred":[
        "Bara G\u0101bua"
    ],
    "wof:name":"Bara Gabua",
    "wof:placetype":"locality"
},
  "geometry": {"coordinates":[90.38463,22.18512],"type":"Point"}
}