{
  "type": "Feature",
  "properties": {
    "gn:admin1_code":"82",
    "gn:admin2_code":"4055.0",
    "gn:admin3_code":"405566.0",
    "gn:admin4_code":"40556621.0",
    "gn:asciiname":"Dhoail",
    "gn:country_code":"BD",
    "gn:dem":13,
    "gn:feature_class":"P",
    "gn:feature_code":"PPL",
    "gn:name":"Dho\u0101il",
    "gn:population":0,
    "gn:timezone":"Asia/Dhaka",
    "iso:country":"BD",
    "wof:name":"Dhoail",
    "wof:placetype":"locality"
},
  "geometry": {"coordinates":[89.56511,23.42093],"type":"Point"}
}