{
  "type": "Feature",
  "properties": {
    "gn:admin1_code":"83",
    "gn:admin2_code":"5010",
    "gn:admin3_code":"501021.0",
    "gn:admin4_code":"50102151.0",
    "gn:asciiname":"Lakshmikhola",
    "gn:country_code":"BD",
    "gn:dem":24,
    "gn:feature_class":"P",
    "gn:feature_code":"PPL",
    "gn:name":"Lakshmikhola",
    "gn:population":0,
    "gn:timezone":"Asia/Dhaka",
    "iso:country":"BD",
    "name:und_x_variant":[
        "Lakshikhola",
        "Lakshmikhola"
    ],
    "wof:name":"Lakshmikhola",
    "wof:placetype":"locality"
},
  "geometry": {"coordinates":[89.44363,24.81088],"type":"Point"}
}