{
  "type": "Feature",
  "properties": {
    "gn:admin1_code":"83",
    "gn:admin2_code":"5081",
    "gn:admin3_code":"508134.0",
    "gn:admin4_code":"50813438.0",
    "gn:asciiname":"Sultanganj",
    "gn:country_code":"BD",
    "gn:dem":23,
    "gn:feature_class":"P",
    "gn:feature_code":"PPL",
    "gn:name":"Sult\u0101nganj",
    "gn:population":0,
    "gn:timezone":"Asia/Dhaka",
    "iso:country":"BD",
    "name:ben_x_preferred":[
        "Sult\u0101nganj"
    ],
    "wof:name":"Sultanganj",
    "wof:placetype":"locality"
},
  "geometry": {"coordinates":[88.30861999999998,24.48834],"type":"Point"}
}