{
  "type": "Feature",
  "properties": {
    "gn:admin1_code":"81",
    "gn:admin2_code":"3068.0",
    "gn:admin3_code":"306852.0",
    "gn:admin4_code":"30685267.0",
    "gn:asciiname":"Dakshin Ghoshgaon",
    "gn:country_code":"BD",
    "gn:dem":14,
    "gn:feature_class":"P",
    "gn:feature_code":"PPL",
    "gn:name":"Dakshin Ghoshgaon",
    "gn:population":0,
    "gn:timezone":"Asia/Dhaka",
    "iso:country":"BD",
    "wof:name":"Dakshin Ghoshgaon",
    "wof:placetype":"locality"
},
  "geometry": {"coordinates":[90.75551,24.1644],"type":"Point"}
}