{
  "type": "Feature",
  "properties": {
    "gn:admin1_code":"87",
    "gn:admin2_code":"5594.0",
    "gn:admin3_code":"559494.0",
    "gn:admin4_code":"55949479.0",
    "gn:asciiname":"Uttar Batina",
    "gn:country_code":"BD",
    "gn:dem":64,
    "gn:feature_class":"P",
    "gn:feature_code":"PPL",
    "gn:name":"Uttar B\u0101tina",
    "gn:population":0,
    "gn:timezone":"Asia/Dhaka",
    "iso:country":"BD",
    "name:ben_x_preferred":[
        "Uttar B\u0101tina"
    ],
    "wof:name":"Uttar Batina",
    "wof:placetype":"locality"
},
  "geometry": {"coordinates":[88.45236,26.14442],"type":"Point"}
}