{
  "type": "Feature",
  "properties": {
    "gn:admin1_code":"81",
    "gn:admin2_code":"3029.0",
    "gn:admin3_code":"302918.0",
    "gn:admin4_code":"30291830.0",
    "gn:asciiname":"Hasamdia",
    "gn:country_code":"BD",
    "gn:dem":9,
    "gn:feature_class":"P",
    "gn:feature_code":"PPL",
    "gn:name":"H\u0101s\u0101mdia",
    "gn:population":0,
    "gn:timezone":"Asia/Dhaka",
    "iso:country":"BD",
    "name:und_x_variant":[
        "Hashamdia",
        "H\u0101s\u0101mdia"
    ],
    "wof:name":"Hasamdia",
    "wof:placetype":"locality"
},
  "geometry": {"coordinates":[89.71295000000001,23.45772],"type":"Point"}
}