{
  "type": "Feature",
  "properties": {
    "gn:admin1_code":"82",
    "gn:asciiname":"Panbatti and Char Harka",
    "gn:country_code":"BD",
    "gn:dem":7,
    "gn:feature_class":"P",
    "gn:feature_code":"PPL",
    "gn:name":"P\u0101nbatti and Char Harka",
    "gn:population":0,
    "gn:timezone":"Asia/Dhaka",
    "iso:country":"BD",
    "name:ben_x_preferred":[
        "P\u0101nbatti and Char Harka"
    ],
    "name:ben_x_variant":[
        "P\u0101npatti"
    ],
    "wof:name":"Panbatti and Char Harka",
    "wof:placetype":"locality"
},
  "geometry": {"coordinates":[90.43952,22.09659],"type":"Point"}
}