{
  "type": "Feature",
  "properties": {
    "gn:admin1_code":"85",
    "gn:admin2_code":"1042",
    "gn:admin3_code":"104240.0",
    "gn:admin4_code":"10424019.0",
    "gn:asciiname":"Sugandia",
    "gn:country_code":"BD",
    "gn:dem":7,
    "gn:feature_class":"P",
    "gn:feature_code":"PPL",
    "gn:name":"Sugandia",
    "gn:population":0,
    "gn:timezone":"Asia/Dhaka",
    "iso:country":"BD",
    "name:und_x_variant":[
        "Sugandhia"
    ],
    "wof:name":"Sugandia",
    "wof:placetype":"locality"
},
  "geometry": {"coordinates":[90.26182,22.71143],"type":"Point"}
}