{
  "type": "Feature",
  "properties": {
    "gn:admin1_code":"84",
    "gn:admin2_code":"2013.0",
    "gn:admin3_code":"201347.0",
    "gn:admin4_code":"20134711.0",
    "gn:asciiname":"Haoakandi",
    "gn:country_code":"BD",
    "gn:dem":7,
    "gn:feature_class":"P",
    "gn:feature_code":"PPL",
    "gn:name":"H\u0101o\u0101k\u0101ndi",
    "gn:population":0,
    "gn:timezone":"Asia/Dhaka",
    "iso:country":"BD",
    "name:und_x_variant":[
        "Howakandi",
        "H\u0101o\u0101k\u0101ndi"
    ],
    "wof:name":"Haoakandi",
    "wof:placetype":"locality"
},
  "geometry": {"coordinates":[90.68487,23.12152],"type":"Point"}
}