{
  "type": "Feature",
  "properties": {
    "gn:admin1_code":"82",
    "gn:asciiname":"Aligaon",
    "gn:country_code":"BD",
    "gn:dem":14,
    "gn:feature_class":"P",
    "gn:feature_code":"PPL",
    "gn:name":"Aligaon",
    "gn:population":0,
    "gn:timezone":"Asia/Dhaka",
    "iso:country":"BD",
    "name:ben_x_preferred":[
        "Aligaon"
    ],
    "wof:name":"Aligaon",
    "wof:placetype":"locality"
},
  "geometry": {"coordinates":[90.75423000000001,22.24818],"type":"Point"}
}