{
  "type": "Feature",
  "properties": {
    "gn:admin1_code":"85",
    "gn:admin2_code":"1079.0",
    "gn:admin3_code":"107914.0",
    "gn:admin4_code":"10791435.0",
    "gn:asciiname":"Purbba Dhawa",
    "gn:country_code":"BD",
    "gn:dem":12,
    "gn:feature_class":"P",
    "gn:feature_code":"PPL",
    "gn:name":"Purbba Dhawa",
    "gn:population":0,
    "gn:timezone":"Asia/Dhaka",
    "iso:country":"BD",
    "name:ben_x_preferred":[
        "Purbba Dhawa"
    ],
    "wof:name":"Purbba Dhawa",
    "wof:placetype":"locality"
},
  "geometry": {"coordinates":[90.03169,22.45084],"type":"Point"}
}