{
  "type": "Feature",
  "properties": {
    "gn:admin1_code":"83",
    "gn:admin2_code":"5081",
    "gn:admin3_code":"508182.0",
    "gn:admin4_code":"50818240.0",
    "gn:asciiname":"Ramkrishnapur",
    "gn:country_code":"BD",
    "gn:dem":18,
    "gn:feature_class":"P",
    "gn:feature_code":"PPL",
    "gn:name":"R\u0101mkrishnapur",
    "gn:population":0,
    "gn:timezone":"Asia/Dhaka",
    "iso:country":"BD",
    "name:ben_x_preferred":[
        "R\u0101mkrishnapur"
    ],
    "wof:name":"Ramkrishnapur",
    "wof:placetype":"locality"
},
  "geometry": {"coordinates":[88.84054999999999,24.42197],"type":"Point"}
}