{
  "type": "Feature",
  "properties": {
    "gn:admin1_code":"87",
    "gn:admin2_code":"5552",
    "gn:admin3_code":"555239.0",
    "gn:admin4_code":"55523947.0",
    "gn:asciiname":"Shabakdas Nitha",
    "gn:country_code":"BD",
    "gn:dem":37,
    "gn:feature_class":"P",
    "gn:feature_code":"PPL",
    "gn:name":"Shab\u0101kd\u0101s Nitha",
    "gn:population":0,
    "gn:timezone":"Asia/Dhaka",
    "iso:country":"BD",
    "name:ben_x_preferred":[
        "Shab\u0101kd\u0101s Nitha"
    ],
    "wof:name":"Shabakdas Nitha",
    "wof:placetype":"locality"
},
  "geometry": {"coordinates":[89.33029999999999,26.02212],"type":"Point"}
}