{
  "type": "Feature",
  "properties": {
    "gn:admin1_code":"85",
    "gn:admin2_code":"1006",
    "gn:admin3_code":"100636.0",
    "gn:admin4_code":"10063694.0",
    "gn:asciiname":"Sonatala",
    "gn:country_code":"BD",
    "gn:dem":1,
    "gn:feature_class":"P",
    "gn:feature_code":"PPL",
    "gn:name":"Son\u0101tala",
    "gn:population":0,
    "gn:timezone":"Asia/Dhaka",
    "iso:country":"BD",
    "wof:name":"Sonatala",
    "wof:placetype":"locality"
},
  "geometry": {"coordinates":[90.48707,22.97136],"type":"Point"}
}