{
  "type": "Feature",
  "properties": {
    "gn:admin1_code":"H",
    "gn:admin2_code":"3039.0",
    "gn:admin3_code":"303958.0",
    "gn:admin4_code":"30395811.0",
    "gn:asciiname":"Dudhigachha",
    "gn:country_code":"BD",
    "gn:dem":23,
    "gn:feature_class":"P",
    "gn:feature_code":"PPL",
    "gn:name":"Dudhig\u0101chha",
    "gn:population":0,
    "gn:timezone":"Asia/Dhaka",
    "iso:country":"BD",
    "wof:name":"Dudhigachha",
    "wof:placetype":"locality"
},
  "geometry": {"coordinates":[89.79649000000001,24.85087],"type":"Point"}
}