{
  "type": "Feature",
  "properties": {
    "gn:admin1_code":"87",
    "gn:admin2_code":"5585",
    "gn:admin3_code":"558576.0",
    "gn:admin4_code":"55857644.0",
    "gn:asciiname":"Chandipur",
    "gn:country_code":"BD",
    "gn:dem":31,
    "gn:feature_class":"P",
    "gn:feature_code":"PPL",
    "gn:name":"Chandipur",
    "gn:population":0,
    "gn:timezone":"Asia/Dhaka",
    "iso:country":"BD",
    "name:ben_x_preferred":[
        "Chandipur"
    ],
    "wof:name":"Chandipur",
    "wof:placetype":"locality"
},
  "geometry": {"coordinates":[89.24763,25.44873],"type":"Point"}
}