{
  "type": "Feature",
  "properties": {
    "gn:admin1_code":"84",
    "gn:admin2_code":"2012",
    "gn:admin3_code":"201285.0",
    "gn:admin4_code":"20128588.0",
    "gn:asciiname":"Syamgaon",
    "gn:country_code":"BD",
    "gn:dem":10,
    "gn:feature_class":"P",
    "gn:feature_code":"PPL",
    "gn:name":"Syamgaon",
    "gn:population":0,
    "gn:timezone":"Asia/Dhaka",
    "iso:country":"BD",
    "name:und_x_variant":[
        "Shy\u0101mgaon",
        "Syamgram",
        "Shyamagram",
        "Sy\u0101mgron",
        "Syamgaon"
    ],
    "wof:name":"Syamgaon",
    "wof:placetype":"locality"
},
  "geometry": {"coordinates":[90.90246,23.83646],"type":"Point"}
}