{
  "type": "Feature",
  "properties": {
    "gn:admin1_code":"83",
    "gn:admin2_code":"5081",
    "gn:admin3_code":"508131.0",
    "gn:admin4_code":"50813135.0",
    "gn:asciiname":"Palasbari",
    "gn:country_code":"BD",
    "gn:dem":18,
    "gn:feature_class":"P",
    "gn:feature_code":"PPL",
    "gn:name":"Pal\u0101sb\u0101ri",
    "gn:population":0,
    "gn:timezone":"Asia/Dhaka",
    "iso:country":"BD",
    "name:asm_x_preferred":[
        "\u09aa\u09b2\u09be\u09b6\u09ac\u09be\u09f0\u09c0"
    ],
    "name:ben_x_preferred":[
        "Pal\u0101sb\u0101ri"
    ],
    "name:ben_x_variant":[
        "\u09aa\u09b2\u09be\u09b6\u09ac\u09be\u09a1\u09bc\u09bf"
    ],
    "name:bpy_x_preferred":[
        "\u09aa\u09b2\u09be\u09b6\u09ac\u09be\u09a1\u09bc\u09bf"
    ],
    "name:ceb_x_preferred":[
        "Pal\u0101sb\u0101ri"
    ],
    "name:hin_x_preferred":[
        "\u092a\u0932\u093e\u0938\u092c\u093e\u0921\u093c\u0940"
    ],
    "name:ita_x_preferred":[
        "Palasbari"
    ],
    "name:msa_x_preferred":[
        "Palasbari"
    ],
    "name:nld_x_preferred":[
        "Palasbari"
    ],
    "name:oci_x_preferred":[
        "Palasbari"
    ],
    "name:por_x_preferred":[
        "Palasbari"
    ],
    "name:swe_x_preferred":[
        "Pal\u0101sb\u0101ri"
    ],
    "name:tam_x_preferred":[
        "\u0baa\u0bb2\u0bbe\u0b9a\u0bc1\u0baa\u0bb0\u0bbf"
    ],
    "name:vie_x_preferred":[
        "Palasbari"
    ],
    "name:zho_x_preferred":[
        "\u5e15\u62c9\u65af\u5df4\u91cc"
    ],
    "wof:name":"Palasbari",
    "wof:placetype":"locality"
},
  "geometry": {"coordinates":[88.70565999999999,24.4378],"type":"Point"}
}