{
  "type": "Feature",
  "properties": {
    "gn:admin1_code":"83",
    "gn:admin2_code":"5081",
    "gn:admin3_code":"508131.0",
    "gn:admin4_code":"50813135.0",
    "gn:asciiname":"Palasbari",
    "gn:country_code":"BD",
    "gn:dem":18,
    "gn:feature_class":"P",
    "gn:feature_code":"PPL",
    "gn:name":"Pal\u0101sb\u0101ri",
    "gn:population":0,
    "gn:timezone":"Asia/Dhaka",
    "iso:country":"BD",
    "name:ben_x_preferred":[
        "Pal\u0101sb\u0101ri"
    ],
    "wof:name":"Palasbari",
    "wof:placetype":"locality"
},
  "geometry": {"coordinates":[88.70565999999999,24.4378],"type":"Point"}
}