{
  "type": "Feature",
  "properties": {
    "gn:admin1_code":"82",
    "gn:asciiname":"Raghunathpur",
    "gn:country_code":"BD",
    "gn:dem":8,
    "gn:feature_class":"P",
    "gn:feature_code":"PPL",
    "gn:name":"Raghun\u0101thpur",
    "gn:population":0,
    "gn:timezone":"Asia/Dhaka",
    "iso:country":"BD",
    "name:ben_x_preferred":[
        "Raghun\u0101thpur"
    ],
    "name:bpy_x_preferred":[
        "\u09b0\u0998\u09c1\u09a8\u09be\u09a5\u09aa\u09c1\u09b0"
    ],
    "name:ceb_x_preferred":[
        "Raghunathpur"
    ],
    "name:fra_x_preferred":[
        "Raghunathpur"
    ],
    "name:hif_x_preferred":[
        "Raghunathpur"
    ],
    "name:new_x_preferred":[
        "\u0930\u0918\u0941\u0928\u093e\u0925\u092a\u0941\u0930"
    ],
    "name:nld_x_preferred":[
        "Raghunathpur"
    ],
    "name:pol_x_preferred":[
        "Raghunathpur"
    ],
    "name:swe_x_preferred":[
        "Raghunathpur"
    ],
    "wof:name":"Raghunathpur",
    "wof:placetype":"locality"
},
  "geometry": {"coordinates":[90.26024,22.47067],"type":"Point"}
}