{
  "type": "Feature",
  "properties": {
    "gn:admin1_code":"83",
    "gn:admin2_code":"5010",
    "gn:admin3_code":"501040.0",
    "gn:admin4_code":"50104081.0",
    "gn:asciiname":"Satihara",
    "gn:country_code":"BD",
    "gn:dem":26,
    "gn:feature_class":"P",
    "gn:feature_code":"PPL",
    "gn:name":"Sat\u012bh\u0101ra",
    "gn:population":0,
    "gn:timezone":"Asia/Dhaka",
    "iso:country":"BD",
    "wof:name":"Satihara",
    "wof:placetype":"locality"
},
  "geometry": {"coordinates":[89.40656,24.93662],"type":"Point"}
}