{
  "type": "Feature",
  "properties": {
    "gn:admin1_code":"82",
    "gn:admin2_code":"4044.0",
    "gn:admin3_code":"404419.0",
    "gn:admin4_code":"40441942.0",
    "gn:asciiname":"Badanpur",
    "gn:country_code":"BD",
    "gn:dem":12,
    "gn:feature_class":"P",
    "gn:feature_code":"PPL",
    "gn:name":"Badanpur",
    "gn:population":0,
    "gn:timezone":"Asia/Dhaka",
    "iso:country":"BD",
    "name:ben_x_preferred":[
        "Badanpur"
    ],
    "wof:name":"Badanpur",
    "wof:placetype":"locality"
},
  "geometry": {"coordinates":[89.20543000000001,23.50333],"type":"Point"}
}