{
  "type": "Feature",
  "properties": {
    "gn:admin1_code":"81",
    "gn:admin2_code":"3093.0",
    "gn:admin3_code":"309357.0",
    "gn:admin4_code":"30935776.0",
    "gn:asciiname":"Madhupur",
    "gn:country_code":"BD",
    "gn:dem":19,
    "gn:feature_class":"P",
    "gn:feature_code":"PPL",
    "gn:name":"Madhupur",
    "gn:population":0,
    "gn:timezone":"Asia/Dhaka",
    "iso:country":"BD",
    "name:ita_x_preferred":[
        "Madhupur"
    ],
    "name:msa_x_preferred":[
        "Madhupur"
    ],
    "wof:name":"Madhupur",
    "wof:placetype":"locality"
},
  "geometry": {"coordinates":[90.03149000000001,24.61186],"type":"Point"}
}