{
  "type": "Feature",
  "properties": {
    "gn:admin1_code":"H",
    "gn:admin2_code":"3061",
    "gn:admin3_code":"306181.0",
    "gn:admin4_code":"30618145.0",
    "gn:asciiname":"Wai",
    "gn:country_code":"BD",
    "gn:dem":18,
    "gn:feature_class":"P",
    "gn:feature_code":"PPL",
    "gn:name":"W\u0101i",
    "gn:population":0,
    "gn:timezone":"Asia/Dhaka",
    "iso:country":"BD",
    "wof:name":"Wai",
    "wof:placetype":"locality"
},
  "geometry": {"coordinates":[90.51815999999999,24.89552],"type":"Point"}
}