{
  "type": "Feature",
  "properties": {
    "gn:admin1_code":"85",
    "gn:admin2_code":"1078.0",
    "gn:admin3_code":"107852.0",
    "gn:admin4_code":"10785242.0",
    "gn:asciiname":"Tafalbaria",
    "gn:country_code":"BD",
    "gn:dem":7,
    "gn:feature_class":"P",
    "gn:feature_code":"PPL",
    "gn:name":"Tafalb\u0101ria",
    "gn:population":0,
    "gn:timezone":"Asia/Dhaka",
    "iso:country":"BD",
    "name:ben_x_preferred":[
        "Tafalb\u0101ria"
    ],
    "wof:name":"Tafalbaria",
    "wof:placetype":"locality"
},
  "geometry": {"coordinates":[90.51008,22.31993],"type":"Point"}
}