{
  "type": "Feature",
  "properties": {
    "gn:admin1_code":"83",
    "gn:admin2_code":"5064.0",
    "gn:admin3_code":"506479.0",
    "gn:admin4_code":"50647931.0",
    "gn:asciiname":"Bazinapukur",
    "gn:country_code":"BD",
    "gn:dem":43,
    "gn:feature_class":"P",
    "gn:feature_code":"PPL",
    "gn:name":"B\u0101zin\u0101pukur",
    "gn:population":0,
    "gn:timezone":"Asia/Dhaka",
    "iso:country":"BD",
    "name:ben_x_preferred":[
        "B\u0101zin\u0101pukur"
    ],
    "name:ben_x_variant":[
        "B\u0101jen\u0101pukhar"
    ],
    "name:und_x_variant":[
        "Bajinapukur"
    ],
    "wof:name":"Bazinapukur",
    "wof:placetype":"locality"
},
  "geometry": {"coordinates":[88.53194000000001,24.96457],"type":"Point"}
}