{
  "type": "Feature",
  "properties": {
    "gn:admin1_code":"H",
    "gn:admin2_code":"3072",
    "gn:admin3_code":"307247.0",
    "gn:admin4_code":"30724706.0",
    "gn:asciiname":"Para Gangahari",
    "gn:country_code":"BD",
    "gn:dem":12,
    "gn:feature_class":"P",
    "gn:feature_code":"PPL",
    "gn:name":"P\u0101ra Gang\u0101hari",
    "gn:population":0,
    "gn:timezone":"Asia/Dhaka",
    "iso:country":"BD",
    "name:und_x_variant":[
        "Para Gangahati",
        "P\u0101ra Gang\u0101hari"
    ],
    "wof:name":"Para Gangahari",
    "wof:placetype":"locality"
},
  "geometry": {"coordinates":[90.79501,24.73613],"type":"Point"}
}