{
  "type": "Feature",
  "properties": {
    "gn:admin1_code":"81",
    "gn:admin2_code":"3082",
    "gn:admin3_code":"308276.0",
    "gn:admin4_code":"30827651.0",
    "gn:asciiname":"Lakshmikol",
    "gn:country_code":"BD",
    "gn:dem":13,
    "gn:feature_class":"P",
    "gn:feature_code":"PPL",
    "gn:name":"Lakshmikol",
    "gn:population":0,
    "gn:timezone":"Asia/Dhaka",
    "iso:country":"BD",
    "name:ben_x_preferred":[
        "Lakshmikol"
    ],
    "name:und_x_variant":[
        "Lakshmikole"
    ],
    "wof:name":"Lakshmikol",
    "wof:placetype":"locality"
},
  "geometry": {"coordinates":[89.66438000000002,23.77174],"type":"Point"}
}