{
  "type": "Feature",
  "properties": {
    "gn:admin1_code":"81",
    "gn:admin2_code":"3029.0",
    "gn:admin3_code":"302956.0",
    "gn:admin4_code":"30295621.0",
    "gn:asciiname":"Duman",
    "gn:country_code":"BD",
    "gn:dem":17,
    "gn:feature_class":"P",
    "gn:feature_code":"PPL",
    "gn:name":"Duman",
    "gn:population":0,
    "gn:timezone":"Asia/Dhaka",
    "iso:country":"BD",
    "name:deu_x_preferred":[
        "Duman"
    ],
    "name:und_x_variant":[
        "Dumain"
    ],
    "wof:name":"Duman",
    "wof:placetype":"locality"
},
  "geometry": {"coordinates":[89.51333000000002,23.56167],"type":"Point"}
}