{
  "type": "Feature",
  "properties": {
    "gn:admin1_code":"81",
    "gn:admin2_code":"3068",
    "gn:admin3_code":"306860.0",
    "gn:admin4_code":"30686053.0",
    "gn:asciiname":"Uriam",
    "gn:country_code":"BD",
    "gn:dem":12,
    "gn:feature_class":"P",
    "gn:feature_code":"PPL",
    "gn:name":"Uri\u0101m",
    "gn:population":0,
    "gn:timezone":"Asia/Dhaka",
    "iso:country":"BD",
    "wof:name":"Uriam",
    "wof:placetype":"locality"
},
  "geometry": {"coordinates":[90.65479999999999,23.85672000000001],"type":"Point"}
}