{
  "type": "Feature",
  "properties": {
    "gn:admin1_code":"81",
    "gn:admin2_code":"3035.0",
    "gn:admin3_code":"303558.0",
    "gn:admin4_code":"30355833.0",
    "gn:asciiname":"East Bhakuri",
    "gn:country_code":"BD",
    "gn:dem":8,
    "gn:feature_class":"P",
    "gn:feature_code":"PPL",
    "gn:name":"East Bh\u0101kuri",
    "gn:population":0,
    "gn:timezone":"Asia/Dhaka",
    "iso:country":"BD",
    "name:und_x_variant":[
        "Purbba Bhakuri",
        "East Bh\u0101kuri"
    ],
    "wof:name":"East Bhakuri",
    "wof:placetype":"locality"
},
  "geometry": {"coordinates":[89.8428,23.29549],"type":"Point"}
}