{
  "type": "Feature",
  "properties": {
    "gn:admin1_code":"87",
    "gn:admin2_code":"5577.0",
    "gn:admin3_code":"557773.0",
    "gn:admin4_code":"55777336.0",
    "gn:asciiname":"Lathuapara",
    "gn:country_code":"BD",
    "gn:dem":82,
    "gn:feature_class":"P",
    "gn:feature_code":"PPL",
    "gn:name":"Lathuap\u0101ra",
    "gn:population":0,
    "gn:timezone":"Asia/Dhaka",
    "iso:country":"BD",
    "name:ben_x_preferred":[
        "Lathuap\u0101ra"
    ],
    "wof:name":"Lathuapara",
    "wof:placetype":"locality"
},
  "geometry": {"coordinates":[88.54675999999998,26.35988],"type":"Point"}
}