{
  "type": "Feature",
  "properties": {
    "gn:admin1_code":"82",
    "gn:admin2_code":"4065.0",
    "gn:admin3_code":"406528.0",
    "gn:admin4_code":"40652863.0",
    "gn:asciiname":"Tona",
    "gn:country_code":"BD",
    "gn:dem":13,
    "gn:feature_class":"P",
    "gn:feature_code":"PPL",
    "gn:name":"Tona",
    "gn:population":0,
    "gn:timezone":"Asia/Dhaka",
    "iso:country":"BD",
    "name:ben_x_preferred":[
        "Tona"
    ],
    "wof:name":"Tona",
    "wof:placetype":"locality"
},
  "geometry": {"coordinates":[89.69579,23.07781],"type":"Point"}
}