{
  "type": "Feature",
  "properties": {
    "gn:admin1_code":"84",
    "gn:admin2_code":"2019",
    "gn:admin3_code":"201968.0",
    "gn:admin4_code":"20196807.0",
    "gn:asciiname":"Kishanpur",
    "gn:cc2":"BD",
    "gn:country_code":"BD",
    "gn:dem":9,
    "gn:feature_class":"P",
    "gn:feature_code":"PPL",
    "gn:name":"Kishanpur",
    "gn:population":0,
    "gn:timezone":"Asia/Dhaka",
    "iso:country":"BD",
    "name:und_x_variant":[
        "Kesanpar",
        "Kishanpur"
    ],
    "wof:name":"Kishanpur",
    "wof:placetype":"locality"
},
  "geometry": {"coordinates":[91.11667,23.33333],"type":"Point"}
}