{
  "type": "Feature",
  "properties": {
    "gn:admin1_code":"H",
    "gn:admin2_code":"3089",
    "gn:admin3_code":"308970.0",
    "gn:admin4_code":"30897069.0",
    "gn:asciiname":"Chihattala",
    "gn:country_code":"BD",
    "gn:dem":27,
    "gn:feature_class":"P",
    "gn:feature_code":"PPL",
    "gn:name":"Chihattala",
    "gn:population":0,
    "gn:timezone":"Asia/Dhaka",
    "iso:country":"BD",
    "wof:name":"Chihattala",
    "wof:placetype":"locality"
},
  "geometry": {"coordinates":[90.13168,25.16904],"type":"Point"}
}