{
  "type": "Feature",
  "properties": {
    "gn:admin1_code":"84",
    "gn:admin2_code":"2019",
    "gn:admin3_code":"201918.0",
    "gn:admin4_code":"20191831.0",
    "gn:asciiname":"Takai",
    "gn:country_code":"BD",
    "gn:dem":12,
    "gn:feature_class":"P",
    "gn:feature_code":"PPL",
    "gn:name":"T\u0101kai",
    "gn:population":0,
    "gn:timezone":"Asia/Dhaka",
    "iso:country":"BD",
    "name:ceb_x_preferred":[
        "Takai"
    ],
    "name:fra_x_preferred":[
        "Takai"
    ],
    "name:hau_x_preferred":[
        "Takai"
    ],
    "name:ita_x_preferred":[
        "Takai"
    ],
    "name:spa_x_preferred":[
        "Takai"
    ],
    "wof:name":"Takai",
    "wof:placetype":"locality"
},
  "geometry": {"coordinates":[91.11667,23.58333],"type":"Point"}
}