{
  "type": "Feature",
  "properties": {
    "gn:admin1_code":"83",
    "gn:admin2_code":"5064",
    "gn:admin3_code":"506450.0",
    "gn:admin4_code":"50645085.0",
    "gn:asciiname":"Krishna Gopalpur",
    "gn:country_code":"BD",
    "gn:dem":20,
    "gn:feature_class":"P",
    "gn:feature_code":"PPL",
    "gn:name":"Krishna Gop\u0101lpur",
    "gn:population":0,
    "gn:timezone":"Asia/Dhaka",
    "iso:country":"BD",
    "wof:name":"Krishna Gopalpur",
    "wof:placetype":"locality"
},
  "geometry": {"coordinates":[88.75053,24.82298],"type":"Point"}
}