{
  "type": "Feature",
  "properties": {
    "gn:admin1_code":"82",
    "gn:admin2_code":"4050.0",
    "gn:admin3_code":"405039.0",
    "gn:admin4_code":"40503981.0",
    "gn:asciiname":"Shaikhpara Meghna",
    "gn:country_code":"BD",
    "gn:dem":21,
    "gn:feature_class":"P",
    "gn:feature_code":"PPL",
    "gn:name":"Shaikhp\u0101ra Meghna",
    "gn:population":0,
    "gn:timezone":"Asia/Dhaka",
    "iso:country":"BD",
    "name:ben_x_preferred":[
        "Shaikhp\u0101ra Meghna"
    ],
    "wof:name":"Shaikhpara Meghna",
    "wof:placetype":"locality"
},
  "geometry": {"coordinates":[88.7466,24.0293],"type":"Point"}
}