{
  "type": "Feature",
  "properties": {
    "gn:admin1_code":"83",
    "gn:admin2_code":"5076.0",
    "gn:admin3_code":"507622.0",
    "gn:admin4_code":"50762208.0",
    "gn:asciiname":"Boalmara",
    "gn:country_code":"BD",
    "gn:dem":18,
    "gn:feature_class":"P",
    "gn:feature_code":"PPL",
    "gn:name":"Bo\u0101lm\u0101ra",
    "gn:population":0,
    "gn:timezone":"Asia/Dhaka",
    "iso:country":"BD",
    "wof:name":"Boalmara",
    "wof:placetype":"locality"
},
  "geometry": {"coordinates":[89.28788,24.26686],"type":"Point"}
}