{
  "type": "Feature",
  "properties": {
    "gn:admin1_code":"83",
    "gn:admin2_code":"5064.0",
    "gn:admin3_code":"506460.0",
    "gn:admin4_code":"50646000.0",
    "gn:asciiname":"Chak Enayet",
    "gn:country_code":"BD",
    "gn:dem":18,
    "gn:feature_class":"P",
    "gn:feature_code":"PPL",
    "gn:name":"Chak En\u0101yet",
    "gn:population":0,
    "gn:timezone":"Asia/Dhaka",
    "iso:country":"BD",
    "name:ben_x_preferred":[
        "Chak En\u0101yet"
    ],
    "wof:name":"Chak Enayet",
    "wof:placetype":"locality"
},
  "geometry": {"coordinates":[88.93012,24.82412],"type":"Point"}
}