{
  "type": "Feature",
  "properties": {
    "gn:admin1_code":"87",
    "gn:admin2_code":"5573",
    "gn:admin3_code":"557385.0",
    "gn:admin4_code":"55738527.0",
    "gn:asciiname":"Kismat Kadikol",
    "gn:country_code":"BD",
    "gn:dem":45,
    "gn:feature_class":"P",
    "gn:feature_code":"PPL",
    "gn:name":"Kismat Kadikol",
    "gn:population":0,
    "gn:timezone":"Asia/Dhaka",
    "iso:country":"BD",
    "name:ben_x_preferred":[
        "Kismat Kadikol"
    ],
    "wof:name":"Kismat Kadikol",
    "wof:placetype":"locality"
},
  "geometry": {"coordinates":[88.85722,25.81703],"type":"Point"}
}