{
  "type": "Feature",
  "properties": {
    "gn:admin1_code":"83",
    "gn:admin2_code":"5081.0",
    "gn:admin3_code":"508112.0",
    "gn:admin4_code":"50811244.0",
    "gn:asciiname":"Gobindapara",
    "gn:country_code":"BD",
    "gn:dem":21,
    "gn:feature_class":"P",
    "gn:feature_code":"PPL",
    "gn:name":"Gobindap\u0101ra",
    "gn:population":0,
    "gn:timezone":"Asia/Dhaka",
    "iso:country":"BD",
    "name:ben_x_preferred":[
        "Gobindap\u0101ra"
    ],
    "wof:name":"Gobindapara",
    "wof:placetype":"locality"
},
  "geometry": {"coordinates":[88.73609999999999,24.65651],"type":"Point"}
}