{
  "type": "Feature",
  "properties": {
    "gn:admin1_code":"87",
    "gn:admin2_code":"5527.0",
    "gn:admin3_code":"552738.0",
    "gn:admin4_code":"55273809.0",
    "gn:asciiname":"Sindurhat",
    "gn:country_code":"BD",
    "gn:dem":34,
    "gn:feature_class":"P",
    "gn:feature_code":"PPL",
    "gn:name":"Sindurh\u0101t",
    "gn:population":0,
    "gn:timezone":"Asia/Dhaka",
    "iso:country":"BD",
    "name:ben_x_preferred":[
        "Sindurh\u0101t"
    ],
    "wof:name":"Sindurhat",
    "wof:placetype":"locality"
},
  "geometry": {"coordinates":[88.90137,25.49654],"type":"Point"}
}