{
  "type": "Feature",
  "properties": {
    "gn:admin1_code":"83",
    "gn:admin2_code":"5081.0",
    "gn:admin3_code":"508182.0",
    "gn:admin4_code":"50818254.0",
    "gn:asciiname":"Basudebpur",
    "gn:country_code":"BD",
    "gn:dem":20,
    "gn:feature_class":"P",
    "gn:feature_code":"PPL",
    "gn:name":"B\u0101sudebpur",
    "gn:population":0,
    "gn:timezone":"Asia/Dhaka",
    "iso:country":"BD",
    "name:ben_x_preferred":[
        "B\u0101sudebpur"
    ],
    "wof:name":"Basudebpur",
    "wof:placetype":"locality"
},
  "geometry": {"coordinates":[88.88164999999999,24.42143],"type":"Point"}
}