{
  "type": "Feature",
  "properties": {
    "gn:admin1_code":"84",
    "gn:admin2_code":"2084.0",
    "gn:admin3_code":"208475.0",
    "gn:admin4_code":"20847576.0",
    "gn:asciiname":"Agaralyachara",
    "gn:country_code":"BD",
    "gn:dem":47,
    "gn:feature_class":"P",
    "gn:feature_code":"PPL",
    "gn:name":"Agaralyachara",
    "gn:population":0,
    "gn:timezone":"Asia/Dhaka",
    "iso:country":"BD",
    "name:ben_x_preferred":[
        "Agaralyachara"
    ],
    "wof:name":"Agaralyachara",
    "wof:placetype":"locality"
},
  "geometry": {"coordinates":[92.11194999999999,22.91619],"type":"Point"}
}