{
  "type": "Feature",
  "properties": {
    "gn:admin1_code":"81",
    "gn:admin2_code":"3033",
    "gn:admin3_code":"303334.0",
    "gn:admin4_code":"30333417.0",
    "gn:asciiname":"Satanipara",
    "gn:country_code":"BD",
    "gn:dem":12,
    "gn:feature_class":"P",
    "gn:feature_code":"PPL",
    "gn:name":"S\u0101t\u0101nip\u0101ra",
    "gn:population":0,
    "gn:timezone":"Asia/Dhaka",
    "iso:country":"BD",
    "wof:name":"Satanipara",
    "wof:placetype":"locality"
},
  "geometry": {"coordinates":[90.536,23.94393],"type":"Point"}
}