{
  "type": "Feature",
  "properties": {
    "gn:admin1_code":"87",
    "gn:admin2_code":"5527.0",
    "gn:admin3_code":"552777.0",
    "gn:admin4_code":"55277760.0",
    "gn:asciiname":"Saidpur",
    "gn:country_code":"BD",
    "gn:dem":39,
    "gn:feature_class":"P",
    "gn:feature_code":"PPL",
    "gn:name":"Saidpur",
    "gn:population":0,
    "gn:timezone":"Asia/Dhaka",
    "iso:country":"BD",
    "name:ben_x_preferred":[
        "Saidpur"
    ],
    "wof:name":"Saidpur",
    "wof:placetype":"locality"
},
  "geometry": {"coordinates":[88.83076,25.61619],"type":"Point"}
}