{
  "type": "Feature",
  "properties": {
    "gn:admin1_code":"87",
    "gn:admin2_code":"5549",
    "gn:admin3_code":"554961.0",
    "gn:admin4_code":"55496150.0",
    "gn:asciiname":"Bishnupur",
    "gn:country_code":"BD",
    "gn:dem":33,
    "gn:feature_class":"P",
    "gn:feature_code":"PPL",
    "gn:name":"Bishnupur",
    "gn:population":0,
    "gn:timezone":"Asia/Dhaka",
    "iso:country":"BD",
    "name:ben_x_preferred":[
        "Bishnupur"
    ],
    "wof:name":"Bishnupur",
    "wof:placetype":"locality"
},
  "geometry": {"coordinates":[89.77490999999998,26.03192],"type":"Point"}
}