{
  "type": "Feature",
  "properties": {
    "gn:admin1_code":"83",
    "gn:admin2_code":"5064",
    "gn:admin3_code":"506450.0",
    "gn:admin4_code":"50645085.0",
    "gn:asciiname":"Srinagar",
    "gn:country_code":"BD",
    "gn:dem":20,
    "gn:feature_class":"P",
    "gn:feature_code":"PPL",
    "gn:name":"Srinagar",
    "gn:population":0,
    "gn:timezone":"Asia/Dhaka",
    "iso:country":"BD",
    "name:ben_x_preferred":[
        "Srinagar"
    ],
    "wof:name":"Srinagar",
    "wof:placetype":"locality"
},
  "geometry": {"coordinates":[88.71311999999998,24.8288],"type":"Point"}
}