{
  "type": "Feature",
  "properties": {
    "gn:admin1_code":"83",
    "gn:asciiname":"Pathanpara",
    "gn:country_code":"BD",
    "gn:dem":24,
    "gn:feature_class":"P",
    "gn:feature_code":"PPL",
    "gn:name":"P\u0101thanp\u0101ra",
    "gn:population":0,
    "gn:timezone":"Asia/Dhaka",
    "iso:country":"BD",
    "name:ben_x_preferred":[
        "P\u0101thanp\u0101ra"
    ],
    "wof:name":"Pathanpara",
    "wof:placetype":"locality"
},
  "geometry": {"coordinates":[89.53171999999998,25.11916],"type":"Point"}
}