{
  "type": "Feature",
  "properties": {
    "gn:admin1_code":"84",
    "gn:admin2_code":"2022.0",
    "gn:admin3_code":"202216.0",
    "gn:admin4_code":"20221655.0",
    "gn:asciiname":"Bilchari",
    "gn:country_code":"BD",
    "gn:dem":20,
    "gn:feature_class":"P",
    "gn:feature_code":"PPL",
    "gn:name":"Bilchari",
    "gn:population":0,
    "gn:timezone":"Asia/Dhaka",
    "iso:country":"BD",
    "name:ben_x_preferred":[
        "Bilchari"
    ],
    "name:und_x_variant":[
        "Bilchhari"
    ],
    "wof:name":"Bilchari",
    "wof:placetype":"locality"
},
  "geometry": {"coordinates":[92.20641000000001,21.79174],"type":"Point"}
}