{
  "type": "Feature",
  "properties": {
    "gn:admin1_code":"87",
    "gn:admin2_code":"5549",
    "gn:admin3_code":"554961.0",
    "gn:admin4_code":"55496188.0",
    "gn:asciiname":"Naharganj",
    "gn:country_code":"BD",
    "gn:dem":37,
    "gn:feature_class":"P",
    "gn:feature_code":"PPL",
    "gn:name":"Naharganj",
    "gn:population":0,
    "gn:timezone":"Asia/Dhaka",
    "iso:country":"BD",
    "name:ben_x_preferred":[
        "Naharganj"
    ],
    "wof:name":"Naharganj",
    "wof:placetype":"locality"
},
  "geometry": {"coordinates":[89.63927,26.03438],"type":"Point"}
}