{
  "type": "Feature",
  "properties": {
    "gn:admin1_code":"82",
    "gn:admin2_code":"4044.0",
    "gn:admin3_code":"404419.0",
    "gn:admin4_code":"40441926.0",
    "gn:asciiname":"Natabaria",
    "gn:country_code":"BD",
    "gn:dem":16,
    "gn:feature_class":"P",
    "gn:feature_code":"PPL",
    "gn:name":"N\u0101t\u0101baria",
    "gn:population":0,
    "gn:timezone":"Asia/Dhaka",
    "iso:country":"BD",
    "name:ben_x_preferred":[
        "N\u0101t\u0101baria"
    ],
    "wof:name":"Natabaria",
    "wof:placetype":"locality"
},
  "geometry": {"coordinates":[89.09308,23.56909],"type":"Point"}
}