{
  "type": "Feature",
  "properties": {
    "gn:admin1_code":"82",
    "gn:admin2_code":"4001",
    "gn:admin3_code":"400114.0",
    "gn:admin4_code":"40011466.0",
    "gn:asciiname":"Saildaha",
    "gn:country_code":"BD",
    "gn:dem":10,
    "gn:feature_class":"P",
    "gn:feature_code":"PPL",
    "gn:name":"Saildaha",
    "gn:population":0,
    "gn:timezone":"Asia/Dhaka",
    "iso:country":"BD",
    "name:und_x_variant":[
        "Sailadaha",
        "Saildaha"
    ],
    "wof:name":"Saildaha",
    "wof:placetype":"locality"
},
  "geometry": {"coordinates":[89.94055,22.84054],"type":"Point"}
}