{
  "type": "Feature",
  "properties": {
    "gn:admin1_code":"82",
    "gn:admin2_code":"4001",
    "gn:admin3_code":"400114.0",
    "gn:admin4_code":"40011466.0",
    "gn:asciiname":"Saildaha",
    "gn:country_code":"BD",
    "gn:dem":10,
    "gn:feature_class":"P",
    "gn:feature_code":"PPL",
    "gn:name":"Saildaha",
    "gn:population":0,
    "gn:timezone":"Asia/Dhaka",
    "iso:country":"BD",
    "name:arz_x_preferred":[
        "\u0635\u0627\u064a\u0644\u0636\u0647\u0627"
    ],
    "name:und_x_variant":[
        "Sailadaha",
        "Saildaha"
    ],
    "name:urd_x_preferred":[
        "\u0633\u06cc\u0644\u062f\u06c1\u0627"
    ],
    "name:zho_x_preferred":[
        "\u8d5b\u5c14\u8fbe\u54c8"
    ],
    "wof:name":"Saildaha",
    "wof:placetype":"locality"
},
  "geometry": {"coordinates":[89.94055,22.84054],"type":"Point"}
}