{
  "type": "Feature",
  "properties": {
    "gn:admin1_code":"87",
    "gn:admin2_code":"5585",
    "gn:admin3_code":"558558.0",
    "gn:admin4_code":"55855805.0",
    "gn:asciiname":"Buzruk Santoshpur",
    "gn:country_code":"BD",
    "gn:dem":36,
    "gn:feature_class":"P",
    "gn:feature_code":"PPL",
    "gn:name":"Buzruk Santoshpur",
    "gn:population":0,
    "gn:timezone":"Asia/Dhaka",
    "iso:country":"BD",
    "name:ben_x_preferred":[
        "Buzruk Santoshpur"
    ],
    "wof:name":"Buzruk Santoshpur",
    "wof:placetype":"locality"
},
  "geometry": {"coordinates":[89.17133000000003,25.54698],"type":"Point"}
}