{
  "type": "Feature",
  "properties": {
    "gn:admin1_code":"82",
    "gn:admin2_code":"4087.0",
    "gn:admin3_code":"408790.0",
    "gn:admin4_code":"40879063.0",
    "gn:asciiname":"Dhulanda",
    "gn:country_code":"BD",
    "gn:dem":9,
    "gn:feature_class":"P",
    "gn:feature_code":"PPL",
    "gn:name":"Dhulanda",
    "gn:population":0,
    "gn:timezone":"Asia/Dhaka",
    "iso:country":"BD",
    "wof:name":"Dhulanda",
    "wof:placetype":"locality"
},
  "geometry": {"coordinates":[89.25175,22.72712000000001],"type":"Point"}
}