{
  "type": "Feature",
  "properties": {
    "gn:admin1_code":"87",
    "gn:admin2_code":"5549",
    "gn:admin3_code":"554979.0",
    "gn:admin4_code":"55497983.0",
    "gn:asciiname":"Baraikandi",
    "gn:country_code":"BD",
    "gn:dem":30,
    "gn:feature_class":"P",
    "gn:feature_code":"PPL",
    "gn:name":"Baraik\u0101ndi",
    "gn:population":0,
    "gn:timezone":"Asia/Dhaka",
    "iso:country":"BD",
    "name:ben_x_preferred":[
        "Baraik\u0101ndi"
    ],
    "wof:name":"Baraikandi",
    "wof:placetype":"locality"
},
  "geometry": {"coordinates":[89.84978000000002,25.61364],"type":"Point"}
}