{
  "type": "Feature",
  "properties": {
    "gn:admin1_code":"81",
    "gn:admin2_code":"3035.0",
    "gn:admin3_code":"303558.0",
    "gn:admin4_code":"30355827.0",
    "gn:asciiname":"Barni",
    "gn:country_code":"BD",
    "gn:dem":7,
    "gn:feature_class":"P",
    "gn:feature_code":"PPL",
    "gn:name":"Barni",
    "gn:population":0,
    "gn:timezone":"Asia/Dhaka",
    "iso:country":"BD",
    "wof:name":"Barni",
    "wof:placetype":"locality"
},
  "geometry": {"coordinates":[89.98819,23.31132],"type":"Point"}
}