{
  "type": "Feature",
  "properties": {
    "gn:admin1_code":"81",
    "gn:admin2_code":"3035.0",
    "gn:admin3_code":"303558.0",
    "gn:admin4_code":"30355827.0",
    "gn:asciiname":"Barni",
    "gn:country_code":"BD",
    "gn:dem":7,
    "gn:feature_class":"P",
    "gn:feature_code":"PPL",
    "gn:name":"Barni",
    "gn:population":0,
    "gn:timezone":"Asia/Dhaka",
    "iso:country":"BD",
    "name:azb_x_preferred":[
        "\u0628\u0627\u0631\u0646\u06cc"
    ],
    "name:bel_x_preferred":[
        "\u0411\u0430\u0440\u043d\u0456"
    ],
    "name:ceb_x_preferred":[
        "Barni"
    ],
    "name:deu_x_preferred":[
        "Barni"
    ],
    "name:epo_x_preferred":[
        "Barni"
    ],
    "name:eus_x_preferred":[
        "Barni"
    ],
    "name:fas_x_preferred":[
        "\u0628\u0627\u0631\u0646\u06cc"
    ],
    "name:fra_x_preferred":[
        "Barni"
    ],
    "name:hun_x_preferred":[
        "Barni"
    ],
    "name:hye_x_preferred":[
        "\u0532\u0561\u0580\u0576\u056b"
    ],
    "name:ita_x_preferred":[
        "Barni"
    ],
    "name:jpn_x_preferred":[
        "\u30d0\u30eb\u30cb"
    ],
    "name:kaz_x_preferred":[
        "\u0411\u0430\u0440\u043d\u0438"
    ],
    "name:lat_x_preferred":[
        "Barnum"
    ],
    "name:lmo_x_preferred":[
        "Barni"
    ],
    "name:msa_x_preferred":[
        "Barni"
    ],
    "name:nap_x_preferred":[
        "Barni"
    ],
    "name:nld_x_preferred":[
        "Barni"
    ],
    "name:pms_x_preferred":[
        "Barni"
    ],
    "name:pol_x_preferred":[
        "Barni"
    ],
    "name:por_x_preferred":[
        "Barni"
    ],
    "name:ron_x_preferred":[
        "Barni"
    ],
    "name:rus_x_preferred":[
        "\u0411\u0430\u0440\u043d\u0438"
    ],
    "name:scn_x_preferred":[
        "Barni"
    ],
    "name:spa_x_preferred":[
        "Barni"
    ],
    "name:srp_x_preferred":[
        "\u0411\u0430\u0440\u043d\u0438"
    ],
    "name:tgl_x_preferred":[
        "Barni"
    ],
    "name:ukr_x_preferred":[
        "\u0411\u0430\u0440\u043d\u0456"
    ],
    "name:uzb_x_preferred":[
        "Barni"
    ],
    "name:vie_x_preferred":[
        "Barni"
    ],
    "name:vol_x_preferred":[
        "Barni"
    ],
    "name:war_x_preferred":[
        "Barni"
    ],
    "name:zho_x_preferred":[
        "\u5df4\u5c14\u5c3c"
    ],
    "wof:name":"Barni",
    "wof:placetype":"locality"
},
  "geometry": {"coordinates":[89.98819,23.31132],"type":"Point"}
}