{
  "type": "Feature",
  "properties": {
    "gn:admin1_code":"83",
    "gn:admin2_code":"5038.0",
    "gn:admin3_code":"503847.0",
    "gn:admin4_code":"50384700.0",
    "gn:asciiname":"Balupora",
    "gn:country_code":"BD",
    "gn:dem":25,
    "gn:feature_class":"P",
    "gn:feature_code":"PPL",
    "gn:name":"Balup\u014dra",
    "gn:population":0,
    "gn:timezone":"Asia/Dhaka",
    "iso:country":"BD",
    "name:ben_x_preferred":[
        "Balup\u014dra"
    ],
    "wof:name":"Balupora",
    "wof:placetype":"locality"
},
  "geometry": {"coordinates":[89.01823,25.11804],"type":"Point"}
}