{
  "type": "Feature",
  "properties": {
    "gn:admin1_code":"85",
    "gn:admin2_code":"1006",
    "gn:admin3_code":"100603.0",
    "gn:admin4_code":"10060381.0",
    "gn:asciiname":"Rajkar",
    "gn:country_code":"BD",
    "gn:dem":14,
    "gn:feature_class":"P",
    "gn:feature_code":"PPL",
    "gn:name":"R\u0101jkar",
    "gn:population":0,
    "gn:timezone":"Asia/Dhaka",
    "iso:country":"BD",
    "wof:name":"Rajkar",
    "wof:placetype":"locality"
},
  "geometry": {"coordinates":[90.31873,22.81436],"type":"Point"}
}