{
  "type": "Feature",
  "properties": {
    "gn:admin1_code":"87",
    "gn:admin2_code":"5527.0",
    "gn:admin3_code":"552747.0",
    "gn:admin4_code":"55274781.0",
    "gn:asciiname":"Uttar Madhabpur",
    "gn:country_code":"BD",
    "gn:dem":31,
    "gn:feature_class":"P",
    "gn:feature_code":"PPL",
    "gn:name":"Uttar M\u0101dh\u0101bpur",
    "gn:population":0,
    "gn:timezone":"Asia/Dhaka",
    "iso:country":"BD",
    "name:ben_x_preferred":[
        "Uttar M\u0101dh\u0101bpur"
    ],
    "wof:name":"Uttar Madhabpur",
    "wof:placetype":"locality"
},
  "geometry": {"coordinates":[88.98931999999998,25.33892],"type":"Point"}
}