{
  "type": "Feature",
  "properties": {
    "gn:admin1_code":"82",
    "gn:admin2_code":"4047.0",
    "gn:admin3_code":"404751.0",
    "gn:admin4_code":"40475131.0",
    "gn:asciiname":"Labanchora",
    "gn:country_code":"BD",
    "gn:dem":6,
    "gn:feature_class":"P",
    "gn:feature_code":"PPL",
    "gn:name":"Labanchora",
    "gn:population":0,
    "gn:timezone":"Asia/Dhaka",
    "iso:country":"BD",
    "name:ben_x_preferred":[
        "Labanchora"
    ],
    "wof:name":"Labanchora",
    "wof:placetype":"locality"
},
  "geometry": {"coordinates":[89.57564000000001,22.78844],"type":"Point"}
}