{
  "type": "Feature",
  "properties": {
    "gn:admin1_code":"87",
    "gn:admin2_code":"5577.0",
    "gn:admin3_code":"557773.0",
    "gn:admin4_code":"55777343.0",
    "gn:asciiname":"Putkibari",
    "gn:country_code":"BD",
    "gn:dem":78,
    "gn:feature_class":"P",
    "gn:feature_code":"PPL",
    "gn:name":"Putkib\u0101ri",
    "gn:population":0,
    "gn:timezone":"Asia/Dhaka",
    "iso:country":"BD",
    "name:ben_x_preferred":[
        "Putkib\u0101ri"
    ],
    "wof:name":"Putkibari",
    "wof:placetype":"locality"
},
  "geometry": {"coordinates":[88.4717,26.32585],"type":"Point"}
}