{
  "type": "Feature",
  "properties": {
    "gn:admin1_code":"83",
    "gn:admin2_code":"5064",
    "gn:admin3_code":"506406.0",
    "gn:admin4_code":"50640610.0",
    "gn:asciiname":"Madhabpara",
    "gn:country_code":"BD",
    "gn:dem":22,
    "gn:feature_class":"P",
    "gn:feature_code":"PPL",
    "gn:name":"Madhabpara",
    "gn:population":0,
    "gn:timezone":"Asia/Dhaka",
    "iso:country":"BD",
    "name:ben_x_preferred":[
        "Madhabpara"
    ],
    "wof:name":"Madhabpara",
    "wof:placetype":"locality"
},
  "geometry": {"coordinates":[88.92270000000001,24.97355],"type":"Point"}
}