{
  "type": "Feature",
  "properties": {
    "gn:admin1_code":"87",
    "gn:admin2_code":"5532",
    "gn:admin3_code":"553267.0",
    "gn:admin4_code":"55326766.0",
    "gn:asciiname":"Beltali Balua",
    "gn:country_code":"BD",
    "gn:dem":25,
    "gn:feature_class":"P",
    "gn:feature_code":"PPL",
    "gn:name":"Beltali Balua",
    "gn:population":0,
    "gn:timezone":"Asia/Dhaka",
    "iso:country":"BD",
    "name:ben_x_preferred":[
        "Beltali Balua"
    ],
    "wof:name":"Beltali Balua",
    "wof:placetype":"locality"
},
  "geometry": {"coordinates":[89.48639,25.25508],"type":"Point"}
}