{
  "type": "Feature",
  "properties": {
    "gn:admin1_code":"82",
    "gn:admin2_code":"4001",
    "gn:admin3_code":"400160.0",
    "gn:admin4_code":"40016089.0",
    "gn:asciiname":"Kachubunia",
    "gn:country_code":"BD",
    "gn:dem":7,
    "gn:feature_class":"P",
    "gn:feature_code":"PPL",
    "gn:name":"Kachubunia",
    "gn:population":0,
    "gn:timezone":"Asia/Dhaka",
    "iso:country":"BD",
    "wof:name":"Kachubunia",
    "wof:placetype":"locality"
},
  "geometry": {"coordinates":[89.90000000000001,22.56667],"type":"Point"}
}