{
  "type": "Feature",
  "properties": {
    "gn:admin1_code":"82",
    "gn:admin2_code":"4055.0",
    "gn:admin3_code":"405585.0",
    "gn:admin4_code":"40558559.0",
    "gn:asciiname":"Satapara",
    "gn:country_code":"BD",
    "gn:dem":13,
    "gn:feature_class":"P",
    "gn:feature_code":"PPL",
    "gn:name":"Satap\u0101ra",
    "gn:population":0,
    "gn:timezone":"Asia/Dhaka",
    "iso:country":"BD",
    "name:ben_x_preferred":[
        "Satap\u0101ra"
    ],
    "wof:name":"Satapara",
    "wof:placetype":"locality"
},
  "geometry": {"coordinates":[89.396,23.29567],"type":"Point"}
}