{
  "type": "Feature",
  "properties": {
    "gn:admin1_code":"85",
    "gn:admin2_code":"1006",
    "gn:admin3_code":"100602.0",
    "gn:admin4_code":"10060215.0",
    "gn:asciiname":"Paysa",
    "gn:country_code":"BD",
    "gn:dem":8,
    "gn:feature_class":"P",
    "gn:feature_code":"PPL",
    "gn:name":"Paysa",
    "gn:population":0,
    "gn:timezone":"Asia/Dhaka",
    "iso:country":"BD",
    "wof:name":"Paysa",
    "wof:placetype":"locality"
},
  "geometry": {"coordinates":[90.07799,22.9731],"type":"Point"}
}