{
  "type": "Feature",
  "properties": {
    "gn:admin1_code":"H",
    "gn:admin2_code":"3072.0",
    "gn:admin3_code":"307204.0",
    "gn:admin4_code":"30720447.0",
    "gn:asciiname":"Desiura",
    "gn:country_code":"BD",
    "gn:dem":13,
    "gn:feature_class":"P",
    "gn:feature_code":"PPL",
    "gn:name":"Des\u012bura",
    "gn:population":0,
    "gn:timezone":"Asia/Dhaka",
    "iso:country":"BD",
    "wof:name":"Desiura",
    "wof:placetype":"locality"
},
  "geometry": {"coordinates":[90.80671,24.78492],"type":"Point"}
}