{
  "type": "Feature",
  "properties": {
    "gn:admin1_code":"82",
    "gn:asciiname":"Thakaraura",
    "gn:country_code":"BD",
    "gn:dem":8,
    "gn:feature_class":"P",
    "gn:feature_code":"PPL",
    "gn:name":"Th\u0101k\u0101raura",
    "gn:population":0,
    "gn:timezone":"Asia/Dhaka",
    "iso:country":"BD",
    "name:ben_x_preferred":[
        "Th\u0101k\u0101raura"
    ],
    "wof:name":"Thakaraura",
    "wof:placetype":"locality"
},
  "geometry": {"coordinates":[90.33805,22.27353],"type":"Point"}
}