{
  "type": "Feature",
  "properties": {
    "gn:admin1_code":"84",
    "gn:admin2_code":"2084.0",
    "gn:admin3_code":"208421.0",
    "gn:admin4_code":"20842131.0",
    "gn:asciiname":"Daluchari",
    "gn:country_code":"BD",
    "gn:dem":58,
    "gn:feature_class":"P",
    "gn:feature_code":"PPL",
    "gn:name":"Daluchari",
    "gn:population":0,
    "gn:timezone":"Asia/Dhaka",
    "iso:country":"BD",
    "name:und_x_variant":[
        "Daluchhari",
        "Daluchari"
    ],
    "wof:name":"Daluchari",
    "wof:placetype":"locality"
},
  "geometry": {"coordinates":[92.36976,22.94284],"type":"Point"}
}