{
  "type": "Feature",
  "properties": {
    "gn:admin1_code":"83",
    "gn:admin2_code":"5064",
    "gn:admin3_code":"506406.0",
    "gn:admin4_code":"50640631.0",
    "gn:asciiname":"Kusharmuri",
    "gn:country_code":"BD",
    "gn:dem":20,
    "gn:feature_class":"P",
    "gn:feature_code":"PPL",
    "gn:name":"Kush\u0101rmuri",
    "gn:population":0,
    "gn:timezone":"Asia/Dhaka",
    "iso:country":"BD",
    "name:ben_x_preferred":[
        "Kush\u0101rmuri"
    ],
    "name:ben_x_variant":[
        "Kusarmuri"
    ],
    "wof:name":"Kusharmuri",
    "wof:placetype":"locality"
},
  "geometry": {"coordinates":[88.91798,24.91587],"type":"Point"}
}