{
  "type": "Feature",
  "properties": {
    "gn:admin1_code":"82",
    "gn:admin2_code":"4041.0",
    "gn:admin3_code":"404111.0",
    "gn:admin4_code":"40411169.0",
    "gn:asciiname":"Berbari",
    "gn:country_code":"BD",
    "gn:dem":11,
    "gn:feature_class":"P",
    "gn:feature_code":"PPL",
    "gn:name":"Berb\u0101ri",
    "gn:population":0,
    "gn:timezone":"Asia/Dhaka",
    "iso:country":"BD",
    "name:ben_x_preferred":[
        "Berb\u0101ri"
    ],
    "wof:name":"Berbari",
    "wof:placetype":"locality"
},
  "geometry": {"coordinates":[89.01956,23.27878],"type":"Point"}
}