{
  "type": "Feature",
  "properties": {
    "gn:admin1_code":"84",
    "gn:admin2_code":"2013",
    "gn:admin3_code":"201358.0",
    "gn:admin4_code":"20135831.0",
    "gn:asciiname":"Kandirpar",
    "gn:country_code":"BD",
    "gn:dem":13,
    "gn:feature_class":"P",
    "gn:feature_code":"PPL",
    "gn:name":"K\u0101ndirp\u0101r",
    "gn:population":0,
    "gn:timezone":"Asia/Dhaka",
    "iso:country":"BD",
    "wof:name":"Kandirpar",
    "wof:placetype":"locality"
},
  "geometry": {"coordinates":[90.9323,23.31216],"type":"Point"}
}