{
  "type": "Feature",
  "properties": {
    "gn:admin1_code":"H",
    "gn:admin2_code":"3089.0",
    "gn:admin3_code":"308988.0",
    "gn:admin4_code":"30898888.0",
    "gn:asciiname":"Betmari",
    "gn:country_code":"BD",
    "gn:dem":19,
    "gn:feature_class":"P",
    "gn:feature_code":"PPL",
    "gn:name":"Betm\u0101ri",
    "gn:population":0,
    "gn:timezone":"Asia/Dhaka",
    "iso:country":"BD",
    "wof:name":"Betmari",
    "wof:placetype":"locality"
},
  "geometry": {"coordinates":[90.0513,24.92252],"type":"Point"}
}