{
  "type": "Feature",
  "properties": {
    "gn:admin1_code":"81",
    "gn:admin2_code":"3068",
    "gn:admin3_code":"306807.0",
    "gn:admin4_code":"30680725.0",
    "gn:asciiname":"Lohajuri Chak",
    "gn:country_code":"BD",
    "gn:dem":13,
    "gn:feature_class":"P",
    "gn:feature_code":"PPL",
    "gn:name":"Loh\u0101juri Chak",
    "gn:population":0,
    "gn:timezone":"Asia/Dhaka",
    "iso:country":"BD",
    "wof:name":"Lohajuri Chak",
    "wof:placetype":"locality"
},
  "geometry": {"coordinates":[90.82158,24.16248],"type":"Point"}
}