{
  "type": "Feature",
  "properties": {
    "gn:admin1_code":"82",
    "gn:admin2_code":"4044.0",
    "gn:admin3_code":"404480.0",
    "gn:admin4_code":"40448069.0",
    "gn:asciiname":"Kshudra Rara",
    "gn:country_code":"BD",
    "gn:dem":10,
    "gn:feature_class":"P",
    "gn:feature_code":"PPL",
    "gn:name":"Kshudra Rara",
    "gn:population":0,
    "gn:timezone":"Asia/Dhaka",
    "iso:country":"BD",
    "name:ben_x_preferred":[
        "Kshudra Rara"
    ],
    "wof:name":"Kshudra Rara",
    "wof:placetype":"locality"
},
  "geometry": {"coordinates":[89.24361,23.61272],"type":"Point"}
}