{
  "type": "Feature",
  "properties": {
    "gn:admin1_code":"81",
    "gn:admin2_code":"3048.0",
    "gn:admin3_code":"304806.0",
    "gn:admin4_code":"30480643.0",
    "gn:asciiname":"Ghazir Char",
    "gn:country_code":"BD",
    "gn:dem":10,
    "gn:feature_class":"P",
    "gn:feature_code":"PPL",
    "gn:name":"Gh\u0101zir Char",
    "gn:population":0,
    "gn:timezone":"Asia/Dhaka",
    "iso:country":"BD",
    "name:und_x_variant":[
        "Gh\u0101zir Char",
        "G\u0101zir Char"
    ],
    "wof:name":"Ghazir Char",
    "wof:placetype":"locality"
},
  "geometry": {"coordinates":[90.92319000000001,24.18778],"type":"Point"}
}