{
  "type": "Feature",
  "properties": {
    "gn:admin1_code":"85",
    "gn:admin2_code":"1042",
    "gn:admin3_code":"104240.0",
    "gn:admin4_code":"10424095.0",
    "gn:asciiname":"Srimantakati",
    "gn:country_code":"BD",
    "gn:dem":12,
    "gn:feature_class":"P",
    "gn:feature_code":"PPL",
    "gn:name":"Srimantak\u0101ti",
    "gn:population":0,
    "gn:timezone":"Asia/Dhaka",
    "iso:country":"BD",
    "name:und_x_variant":[
        "Srimantak\u0101ti"
    ],
    "wof:name":"Srimantakati",
    "wof:placetype":"locality"
},
  "geometry": {"coordinates":[90.12311,22.61812],"type":"Point"}
}