{
  "type": "Feature",
  "properties": {
    "gn:admin1_code":"83",
    "gn:asciiname":"Dimla Padumsahar",
    "gn:country_code":"BD",
    "gn:dem":23,
    "gn:feature_class":"P",
    "gn:feature_code":"PPL",
    "gn:name":"Dimla Padumsahar",
    "gn:population":0,
    "gn:timezone":"Asia/Dhaka",
    "iso:country":"BD",
    "name:ben_x_preferred":[
        "Dimla Padumsahar"
    ],
    "wof:name":"Dimla Padumsahar",
    "wof:placetype":"locality"
},
  "geometry": {"coordinates":[89.54928000000002,25.19714],"type":"Point"}
}