{
  "type": "Feature",
  "properties": {
    "gn:admin1_code":"82",
    "gn:asciiname":"North Kanthaltali",
    "gn:country_code":"BD",
    "gn:dem":7,
    "gn:feature_class":"P",
    "gn:feature_code":"PPL",
    "gn:name":"North K\u0101nth\u0101ltali",
    "gn:population":0,
    "gn:timezone":"Asia/Dhaka",
    "iso:country":"BD",
    "name:ben_x_preferred":[
        "North K\u0101nth\u0101ltali"
    ],
    "wof:name":"North Kanthaltali",
    "wof:placetype":"locality"
},
  "geometry": {"coordinates":[90.27782999999999,22.46217],"type":"Point"}
}