{
  "type": "Feature",
  "properties": {
    "gn:admin1_code":"82",
    "gn:admin2_code":"4057.0",
    "gn:admin3_code":"405747.0",
    "gn:admin4_code":"40574710.0",
    "gn:asciiname":"Haduri Bil",
    "gn:country_code":"BD",
    "gn:dem":20,
    "gn:feature_class":"P",
    "gn:feature_code":"PPL",
    "gn:name":"Haduri Bil",
    "gn:population":0,
    "gn:timezone":"Asia/Dhaka",
    "iso:country":"BD",
    "name:ben_x_preferred":[
        "Haduri Bil"
    ],
    "wof:name":"Haduri Bil",
    "wof:placetype":"locality"
},
  "geometry": {"coordinates":[88.80174,23.86696],"type":"Point"}
}