{
  "type": "Feature",
  "properties": {
    "gn:admin1_code":"83",
    "gn:admin2_code":"5076.0",
    "gn:admin3_code":"507616.0",
    "gn:admin4_code":"50761673.0",
    "gn:asciiname":"Feghat",
    "gn:country_code":"BD",
    "gn:dem":12,
    "gn:feature_class":"P",
    "gn:feature_code":"PPL",
    "gn:name":"Feghat",
    "gn:population":0,
    "gn:timezone":"Asia/Dhaka",
    "iso:country":"BD",
    "name:ben_x_preferred":[
        "Feghat"
    ],
    "wof:name":"Feghat",
    "wof:placetype":"locality"
},
  "geometry": {"coordinates":[89.6503,23.94969],"type":"Point"}
}