{
  "type": "Feature",
  "properties": {
    "gn:admin1_code":"81",
    "gn:admin2_code":"3026",
    "gn:admin3_code":"302640.0",
    "gn:admin4_code":"30264011.0",
    "gn:asciiname":"Paradagar",
    "gn:country_code":"BD",
    "gn:dem":8,
    "gn:feature_class":"P",
    "gn:feature_code":"PPL",
    "gn:name":"Par\u0101dag\u0101r",
    "gn:population":0,
    "gn:timezone":"Asia/Dhaka",
    "iso:country":"BD",
    "wof:name":"Paradagar",
    "wof:placetype":"locality"
},
  "geometry": {"coordinates":[90.47211,23.71401],"type":"Point"}
}