{
  "type": "Feature",
  "properties": {
    "gn:admin1_code":"82",
    "gn:admin2_code":"4044.0",
    "gn:admin3_code":"404471.0",
    "gn:admin4_code":"40447108.0",
    "gn:asciiname":"Naoda",
    "gn:country_code":"BD",
    "gn:dem":16,
    "gn:feature_class":"P",
    "gn:feature_code":"PPL",
    "gn:name":"Naoda",
    "gn:population":0,
    "gn:timezone":"Asia/Dhaka",
    "iso:country":"BD",
    "name:ben_x_preferred":[
        "Naoda"
    ],
    "wof:name":"Naoda",
    "wof:placetype":"locality"
},
  "geometry": {"coordinates":[88.95674,23.33299],"type":"Point"}
}