{
  "type": "Feature",
  "properties": {
    "gn:admin1_code":"83",
    "gn:admin2_code":"5064.0",
    "gn:admin3_code":"506428.0",
    "gn:admin4_code":"50642821.0",
    "gn:asciiname":"Taherpur",
    "gn:country_code":"BD",
    "gn:dem":26,
    "gn:feature_class":"P",
    "gn:feature_code":"PPL",
    "gn:name":"T\u0101herpur",
    "gn:population":0,
    "gn:timezone":"Asia/Dhaka",
    "iso:country":"BD",
    "name:ben_x_preferred":[
        "T\u0101herpur"
    ],
    "name:ben_x_variant":[
        "\u09a4\u09be\u09b9\u09c7\u09b0\u09aa\u09c1\u09b0"
    ],
    "name:bpy_x_preferred":[
        "\u09a4\u09be\u09b9\u09c7\u09b0\u09aa\u09c1\u09b0"
    ],
    "name:ita_x_preferred":[
        "Taherpur"
    ],
    "name:msa_x_preferred":[
        "Taherpur"
    ],
    "name:nld_x_preferred":[
        "Taherpur"
    ],
    "name:por_x_preferred":[
        "Taherpur"
    ],
    "name:tam_x_preferred":[
        "\u0ba4\u0bc6\u0b95\u0bc6\u0bb0\u0bcd\u0baa\u0bc2\u0bb0\u0bcd"
    ],
    "name:vie_x_preferred":[
        "Taherpur"
    ],
    "name:zho_x_preferred":[
        "\u5854\u8d6b\u5c14\u666e\u5c14"
    ],
    "wof:name":"Taherpur",
    "wof:placetype":"locality"
},
  "geometry": {"coordinates":[88.7792,25.1536],"type":"Point"}
}