{
  "type": "Feature",
  "properties": {
    "gn:admin1_code":"81",
    "gn:admin2_code":"3059.0",
    "gn:admin3_code":"305974.0",
    "gn:admin4_code":"30597420.0",
    "gn:asciiname":"Bara Pauldia",
    "gn:country_code":"BD",
    "gn:dem":10,
    "gn:feature_class":"P",
    "gn:feature_code":"PPL",
    "gn:name":"Bara Pauldia",
    "gn:population":0,
    "gn:timezone":"Asia/Dhaka",
    "iso:country":"BD",
    "wof:name":"Bara Pauldia",
    "wof:placetype":"locality"
},
  "geometry": {"coordinates":[90.40476,23.57018],"type":"Point"}
}