{
  "type": "Feature",
  "properties": {
    "gn:admin1_code":"81",
    "gn:admin2_code":"3054",
    "gn:admin3_code":"305487.0",
    "gn:admin4_code":"30548731.0",
    "gn:asciiname":"North Char Janajat",
    "gn:country_code":"BD",
    "gn:dem":1,
    "gn:feature_class":"P",
    "gn:feature_code":"PPL",
    "gn:name":"North Char Jan\u0101j\u0101t",
    "gn:population":0,
    "gn:timezone":"Asia/Dhaka",
    "iso:country":"BD",
    "name:und_x_variant":[
        "North Char Jonajat",
        "North Char Jan\u0101j\u0101t"
    ],
    "wof:name":"North Char Janajat",
    "wof:placetype":"locality"
},
  "geometry": {"coordinates":[90.17565999999999,23.45181],"type":"Point"}
}