{
  "type": "Feature",
  "properties": {
    "gn:admin1_code":"82",
    "gn:admin2_code":"4087",
    "gn:admin3_code":"408747.0",
    "gn:admin4_code":"40874771.0",
    "gn:asciiname":"Lakshminathpur",
    "gn:country_code":"BD",
    "gn:dem":7,
    "gn:feature_class":"P",
    "gn:feature_code":"PPL",
    "gn:name":"Lakshm\u012bn\u0101thpur",
    "gn:population":0,
    "gn:timezone":"Asia/Dhaka",
    "iso:country":"BD",
    "name:ben_x_preferred":[
        "Lakshm\u012bn\u0101thpur"
    ],
    "name:und_x_variant":[
        "Lakshm\u012bn\u0101thpur Bara"
    ],
    "wof:name":"Lakshminathpur",
    "wof:placetype":"locality"
},
  "geometry": {"coordinates":[89.08578,22.42157000000001],"type":"Point"}
}