{
  "type": "Feature",
  "properties": {
    "gn:admin1_code":"81",
    "gn:admin2_code":"3048.0",
    "gn:admin3_code":"304879.0",
    "gn:admin4_code":"30487976.0",
    "gn:asciiname":"Chaliagop",
    "gn:country_code":"BD",
    "gn:dem":17,
    "gn:feature_class":"P",
    "gn:feature_code":"PPL",
    "gn:name":"Ch\u0101li\u0101gop",
    "gn:population":0,
    "gn:timezone":"Asia/Dhaka",
    "iso:country":"BD",
    "name:und_x_variant":[
        "Challia Gop",
        "Ch\u0101li\u0101gop"
    ],
    "wof:name":"Chaliagop",
    "wof:placetype":"locality"
},
  "geometry": {"coordinates":[90.66236000000001,24.30927],"type":"Point"}
}