{
  "type": "Feature",
  "properties": {
    "gn:admin1_code":"81",
    "gn:admin2_code":"3054.0",
    "gn:admin3_code":"305454.0",
    "gn:admin4_code":"30545423.0",
    "gn:asciiname":"Bolsha",
    "gn:country_code":"BD",
    "gn:dem":8,
    "gn:feature_class":"P",
    "gn:feature_code":"PPL",
    "gn:name":"Bolsha",
    "gn:population":0,
    "gn:timezone":"Asia/Dhaka",
    "iso:country":"BD",
    "wof:name":"Bolsha",
    "wof:placetype":"locality"
},
  "geometry": {"coordinates":[90.14637,23.201],"type":"Point"}
}