{
  "type": "Feature",
  "properties": {
    "gn:admin1_code":"85",
    "gn:admin2_code":"1042.0",
    "gn:admin3_code":"104273.0",
    "gn:admin4_code":"10427384.0",
    "gn:asciiname":"Boalia",
    "gn:country_code":"BD",
    "gn:dem":9,
    "gn:feature_class":"P",
    "gn:feature_code":"PPL",
    "gn:name":"Bo\u0101lia",
    "gn:population":0,
    "gn:timezone":"Asia/Dhaka",
    "iso:country":"BD",
    "wof:name":"Boalia",
    "wof:placetype":"locality"
},
  "geometry": {"coordinates":[90.3494,22.5809],"type":"Point"}
}