{
  "type": "Feature",
  "properties": {
    "gn:admin1_code":"H",
    "gn:admin2_code":"3039.0",
    "gn:admin3_code":"303936.0",
    "gn:admin4_code":"30393695.0",
    "gn:asciiname":"Char Madhabdi",
    "gn:country_code":"BD",
    "gn:dem":13,
    "gn:feature_class":"P",
    "gn:feature_code":"PPL",
    "gn:name":"Char M\u0101dhabdi",
    "gn:population":0,
    "gn:timezone":"Asia/Dhaka",
    "iso:country":"BD",
    "wof:name":"Char Madhabdi",
    "wof:placetype":"locality"
},
  "geometry": {"coordinates":[90.06667,24.88333],"type":"Point"}
}