{
  "type": "Feature",
  "properties": {
    "gn:admin1_code":"H",
    "gn:admin2_code":"3072.0",
    "gn:admin3_code":"307283.0",
    "gn:admin4_code":"30728315.0",
    "gn:asciiname":"Dakshin Kajlapota",
    "gn:country_code":"BD",
    "gn:dem":14,
    "gn:feature_class":"P",
    "gn:feature_code":"PPL",
    "gn:name":"Dakshin K\u0101jl\u0101pota",
    "gn:population":0,
    "gn:timezone":"Asia/Dhaka",
    "iso:country":"BD",
    "wof:name":"Dakshin Kajlapota",
    "wof:placetype":"locality"
},
  "geometry": {"coordinates":[90.60753,24.81958],"type":"Point"}
}