{
  "type": "Feature",
  "properties": {
    "gn:admin1_code":"87",
    "gn:admin2_code":"5585",
    "gn:admin3_code":"558549.0",
    "gn:admin4_code":"55854923.0",
    "gn:asciiname":"Dabripara",
    "gn:country_code":"BD",
    "gn:dem":39,
    "gn:feature_class":"P",
    "gn:feature_code":"PPL",
    "gn:name":"D\u0101brip\u0101ra",
    "gn:population":0,
    "gn:timezone":"Asia/Dhaka",
    "iso:country":"BD",
    "name:ben_x_preferred":[
        "D\u0101brip\u0101ra"
    ],
    "wof:name":"Dabripara",
    "wof:placetype":"locality"
},
  "geometry": {"coordinates":[89.15844,25.76961],"type":"Point"}
}