{
  "type": "Feature",
  "properties": {
    "gn:admin1_code":"H",
    "gn:admin2_code":"3061",
    "gn:admin3_code":"306123.0",
    "gn:admin4_code":"30612381.0",
    "gn:asciiname":"Iswarpur",
    "gn:country_code":"BD",
    "gn:dem":16,
    "gn:feature_class":"P",
    "gn:feature_code":"PPL",
    "gn:name":"Iswarpur",
    "gn:population":0,
    "gn:timezone":"Asia/Dhaka",
    "iso:country":"BD",
    "wof:name":"Iswarpur",
    "wof:placetype":"locality"
},
  "geometry": {"coordinates":[90.71738999999999,24.73803],"type":"Point"}
}