{
  "type": "Feature",
  "properties": {
    "gn:admin1_code":"81",
    "gn:admin2_code":"3068",
    "gn:admin3_code":"306876.0",
    "gn:admin4_code":"30687652.0",
    "gn:asciiname":"Machhimnagar",
    "gn:country_code":"BD",
    "gn:dem":15,
    "gn:feature_class":"P",
    "gn:feature_code":"PPL",
    "gn:name":"M\u0101chhimnagar",
    "gn:population":0,
    "gn:timezone":"Asia/Dhaka",
    "iso:country":"BD",
    "wof:name":"Machhimnagar",
    "wof:placetype":"locality"
},
  "geometry": {"coordinates":[90.8176,24.00322],"type":"Point"}
}