{
  "type": "Feature",
  "properties": {
    "gn:admin1_code":"00",
    "gn:asciiname":"Hazari",
    "gn:country_code":"BD",
    "gn:dem":1,
    "gn:feature_class":"P",
    "gn:feature_code":"PPL",
    "gn:name":"H\u0101z\u0101ri",
    "gn:population":0,
    "gn:timezone":"Asia/Dhaka",
    "iso:country":"BD",
    "name:hrv_x_preferred":[
        "Hazari"
    ],
    "wof:name":"Hazari",
    "wof:placetype":"locality"
},
  "geometry": {"coordinates":[90.76667,22.65],"type":"Point"}
}