{
  "type": "Feature",
  "properties": {
    "gn:admin1_code":"85",
    "gn:admin2_code":"1009.0",
    "gn:admin3_code":"100925.0",
    "gn:admin4_code":"10092547.0",
    "gn:asciiname":"Shahbajpur",
    "gn:country_code":"BD",
    "gn:dem":7,
    "gn:feature_class":"P",
    "gn:feature_code":"PPL",
    "gn:name":"Shahbajpur",
    "gn:population":0,
    "gn:timezone":"Asia/Dhaka",
    "iso:country":"BD",
    "name:ben_x_preferred":[
        "Shahbajpur"
    ],
    "wof:name":"Shahbajpur",
    "wof:placetype":"locality"
},
  "geometry": {"coordinates":[90.65008,21.9297],"type":"Point"}
}