{
  "type": "Feature",
  "properties": {
    "gn:admin1_code":"82",
    "gn:admin2_code":"4041.0",
    "gn:admin3_code":"404123.0",
    "gn:admin4_code":"40412329.0",
    "gn:asciiname":"Benga",
    "gn:country_code":"BD",
    "gn:dem":12,
    "gn:feature_class":"P",
    "gn:feature_code":"PPL",
    "gn:name":"Benga",
    "gn:population":0,
    "gn:timezone":"Asia/Dhaka",
    "iso:country":"BD",
    "name:ben_x_preferred":[
        "Benga"
    ],
    "name:ceb_x_preferred":[
        "Benga"
    ],
    "name:deu_x_preferred":[
        "Benga"
    ],
    "name:fin_x_preferred":[
        "Benga"
    ],
    "name:fra_x_preferred":[
        "Benga"
    ],
    "name:por_x_preferred":[
        "Benga"
    ],
    "name:ron_x_preferred":[
        "Benga"
    ],
    "name:swe_x_preferred":[
        "Benga"
    ],
    "wof:name":"Benga",
    "wof:placetype":"locality"
},
  "geometry": {"coordinates":[88.9932,23.20399],"type":"Point"}
}