{
  "type": "Feature",
  "properties": {
    "gn:admin1_code":"82",
    "gn:admin2_code":"4001.0",
    "gn:admin3_code":"400160.0",
    "gn:admin4_code":"40016029.0",
    "gn:asciiname":"Betbunia Chandipur",
    "gn:country_code":"BD",
    "gn:dem":11,
    "gn:feature_class":"P",
    "gn:feature_code":"PPL",
    "gn:name":"Betbunia Chandipur",
    "gn:population":0,
    "gn:timezone":"Asia/Dhaka",
    "iso:country":"BD",
    "name:ben_x_preferred":[
        "Betbunia Chandipur"
    ],
    "wof:name":"Betbunia Chandipur",
    "wof:placetype":"locality"
},
  "geometry": {"coordinates":[89.9413,22.49698],"type":"Point"}
}