{
  "type": "Feature",
  "properties": {
    "gn:admin1_code":"H",
    "gn:admin2_code":"3089",
    "gn:admin3_code":"308988.0",
    "gn:admin4_code":"30898827.0",
    "gn:asciiname":"Munshi Char",
    "gn:country_code":"BD",
    "gn:dem":20,
    "gn:feature_class":"P",
    "gn:feature_code":"PPL",
    "gn:name":"Munshi Char",
    "gn:population":0,
    "gn:timezone":"Asia/Dhaka",
    "iso:country":"BD",
    "name:ben_x_preferred":[
        "Munshi Char"
    ],
    "wof:name":"Munshi Char",
    "wof:placetype":"locality"
},
  "geometry": {"coordinates":[89.93677,25.00192],"type":"Point"}
}