{
  "type": "Feature",
  "properties": {
    "gn:admin1_code":"83",
    "gn:admin2_code":"5070.0",
    "gn:admin3_code":"507088.0",
    "gn:admin4_code":"50708853.0",
    "gn:asciiname":"Chouk",
    "gn:country_code":"BD",
    "gn:dem":30,
    "gn:feature_class":"P",
    "gn:feature_code":"PPL",
    "gn:name":"Chouk",
    "gn:population":0,
    "gn:timezone":"Asia/Dhaka",
    "iso:country":"BD",
    "name:ben_x_preferred":[
        "Chouk"
    ],
    "name:ben_x_variant":[
        "Chauka"
    ],
    "name:und_x_variant":[
        "Chouka"
    ],
    "wof:name":"Chouk",
    "wof:placetype":"locality"
},
  "geometry": {"coordinates":[88.07720999999999,24.72511],"type":"Point"}
}