{
  "type": "Feature",
  "properties": {
    "gn:admin1_code":"82",
    "gn:admin2_code":"4041.0",
    "gn:admin3_code":"404147.0",
    "gn:admin4_code":"40414789.0",
    "gn:asciiname":"Arpara",
    "gn:country_code":"BD",
    "gn:dem":11,
    "gn:feature_class":"P",
    "gn:feature_code":"PPL",
    "gn:name":"\u0100rp\u0101ra",
    "gn:population":0,
    "gn:timezone":"Asia/Dhaka",
    "iso:country":"BD",
    "name:ben_x_preferred":[
        "\u0100rp\u0101ra"
    ],
    "wof:name":"Arpara",
    "wof:placetype":"locality"
},
  "geometry": {"coordinates":[89.23560999999999,23.20102],"type":"Point"}
}