{
  "type": "Feature",
  "properties": {
    "gn:admin1_code":"H",
    "gn:admin2_code":"3072",
    "gn:admin3_code":"307283.0",
    "gn:admin4_code":"30728371.0",
    "gn:asciiname":"Jaria Jhanjail",
    "gn:country_code":"BD",
    "gn:dem":15,
    "gn:feature_class":"P",
    "gn:feature_code":"PPL",
    "gn:name":"J\u0101ria Jh\u0101njail",
    "gn:population":0,
    "gn:timezone":"Asia/Dhaka",
    "iso:country":"BD",
    "wof:name":"Jaria Jhanjail",
    "wof:placetype":"locality"
},
  "geometry": {"coordinates":[90.64772000000001,25.01003],"type":"Point"}
}