{
  "type": "Feature",
  "properties": {
    "gn:admin1_code":"H",
    "gn:admin2_code":"3061.0",
    "gn:admin3_code":"306181.0",
    "gn:admin4_code":"30618172.0",
    "gn:asciiname":"Goalkandi",
    "gn:country_code":"BD",
    "gn:dem":16,
    "gn:feature_class":"P",
    "gn:feature_code":"PPL",
    "gn:name":"Go\u0101lk\u0101ndi",
    "gn:population":0,
    "gn:timezone":"Asia/Dhaka",
    "iso:country":"BD",
    "wof:name":"Goalkandi",
    "wof:placetype":"locality"
},
  "geometry": {"coordinates":[90.47611000000001,24.85124],"type":"Point"}
}