{
  "type": "Feature",
  "properties": {
    "gn:admin1_code":"84",
    "gn:admin2_code":"2012.0",
    "gn:admin3_code":"201285.0",
    "gn:admin4_code":"20128572.0",
    "gn:asciiname":"Damla",
    "gn:country_code":"BD",
    "gn:dem":6,
    "gn:feature_class":"P",
    "gn:feature_code":"PPL",
    "gn:name":"D\u0101mla",
    "gn:population":0,
    "gn:timezone":"Asia/Dhaka",
    "iso:country":"BD",
    "name:tur_x_preferred":[
        "Damla"
    ],
    "wof:name":"Damla",
    "wof:placetype":"locality"
},
  "geometry": {"coordinates":[90.90000000000001,23.78333],"type":"Point"}
}