{
  "type": "Feature",
  "properties": {
    "gn:admin1_code":"82",
    "gn:admin2_code":"4018.0",
    "gn:admin3_code":"401831.0",
    "gn:admin4_code":"40183183.0",
    "gn:asciiname":"Patharpara",
    "gn:country_code":"BD",
    "gn:dem":16,
    "gn:feature_class":"P",
    "gn:feature_code":"PPL",
    "gn:name":"P\u0101tharp\u0101ra",
    "gn:population":0,
    "gn:timezone":"Asia/Dhaka",
    "iso:country":"BD",
    "name:ben_x_preferred":[
        "P\u0101tharp\u0101ra"
    ],
    "wof:name":"Patharpara",
    "wof:placetype":"locality"
},
  "geometry": {"coordinates":[88.74258,23.67973],"type":"Point"}
}