{
  "type": "Feature",
  "properties": {
    "gn:admin1_code":"81",
    "gn:admin2_code":"3029.0",
    "gn:admin3_code":"302903.0",
    "gn:admin4_code":"30290331.0",
    "gn:asciiname":"Hidadanga",
    "gn:country_code":"BD",
    "gn:dem":11,
    "gn:feature_class":"P",
    "gn:feature_code":"PPL",
    "gn:name":"Hid\u0101d\u0101nga",
    "gn:population":0,
    "gn:timezone":"Asia/Dhaka",
    "iso:country":"BD",
    "wof:name":"Hidadanga",
    "wof:placetype":"locality"
},
  "geometry": {"coordinates":[89.69473000000001,23.30742],"type":"Point"}
}