{
  "type": "Feature",
  "properties": {
    "gn:admin1_code":"82",
    "gn:admin2_code":"4041",
    "gn:admin3_code":"404123.0",
    "gn:admin4_code":"40412389.0",
    "gn:asciiname":"Simulia Gobinathpur",
    "gn:country_code":"BD",
    "gn:dem":13,
    "gn:feature_class":"P",
    "gn:feature_code":"PPL",
    "gn:name":"Simulia Gobin\u0101thpur",
    "gn:population":0,
    "gn:timezone":"Asia/Dhaka",
    "iso:country":"BD",
    "name:ben_x_preferred":[
        "Simulia Gobin\u0101thpur"
    ],
    "name:ben_x_variant":[
        "Simulia Gopin\u0101thpur"
    ],
    "wof:name":"Simulia Gobinathpur",
    "wof:placetype":"locality"
},
  "geometry": {"coordinates":[89.03634,23.10122],"type":"Point"}
}