{
  "type": "Feature",
  "properties": {
    "gn:admin1_code":"85",
    "gn:admin2_code":"1004.0",
    "gn:admin3_code":"100428.0",
    "gn:admin4_code":"10042800.0",
    "gn:asciiname":"Bansbunia",
    "gn:country_code":"BD",
    "gn:dem":9,
    "gn:feature_class":"P",
    "gn:feature_code":"PPL",
    "gn:name":"Bansbunia",
    "gn:population":0,
    "gn:timezone":"Asia/Dhaka",
    "iso:country":"BD",
    "name:ben_x_preferred":[
        "Bansbunia"
    ],
    "wof:name":"Bansbunia",
    "wof:placetype":"locality"
},
  "geometry": {"coordinates":[90.12492,22.13884],"type":"Point"}
}