{
  "type": "Feature",
  "properties": {
    "gn:admin1_code":"87",
    "gn:admin2_code":"5573.0",
    "gn:admin3_code":"557385.0",
    "gn:admin4_code":"55738513.0",
    "gn:asciiname":"Baraisalpara",
    "gn:country_code":"BD",
    "gn:dem":37,
    "gn:feature_class":"P",
    "gn:feature_code":"PPL",
    "gn:name":"B\u0101r\u0101is\u0101lp\u0101ra",
    "gn:population":0,
    "gn:timezone":"Asia/Dhaka",
    "iso:country":"BD",
    "name:ben_x_preferred":[
        "B\u0101r\u0101is\u0101lp\u0101ra"
    ],
    "wof:name":"Baraisalpara",
    "wof:placetype":"locality"
},
  "geometry": {"coordinates":[88.94523000000002,25.75072],"type":"Point"}
}