{
  "type": "Feature",
  "properties": {
    "gn:admin1_code":"84",
    "gn:admin2_code":"2075",
    "gn:admin3_code":"207510.0",
    "gn:admin4_code":"20751066.0",
    "gn:asciiname":"Ramdebpur",
    "gn:country_code":"BD",
    "gn:dem":14,
    "gn:feature_class":"P",
    "gn:feature_code":"PPL",
    "gn:name":"R\u0101mdebpur",
    "gn:population":0,
    "gn:timezone":"Asia/Dhaka",
    "iso:country":"BD",
    "wof:name":"Ramdebpur",
    "wof:placetype":"locality"
},
  "geometry": {"coordinates":[90.93537000000001,23.05808],"type":"Point"}
}