{
  "type": "Feature",
  "properties": {
    "gn:admin1_code":"82",
    "gn:admin2_code":"4044.0",
    "gn:admin3_code":"404414.0",
    "gn:admin4_code":"40441463.0",
    "gn:asciiname":"Bhaluki Sitali",
    "gn:country_code":"BD",
    "gn:dem":11,
    "gn:feature_class":"P",
    "gn:feature_code":"PPL",
    "gn:name":"Bh\u0101luki Sitali",
    "gn:population":0,
    "gn:timezone":"Asia/Dhaka",
    "iso:country":"BD",
    "name:ben_x_preferred":[
        "Bh\u0101luki Sitali"
    ],
    "wof:name":"Bhaluki Sitali",
    "wof:placetype":"locality"
},
  "geometry": {"coordinates":[89.06395000000001,23.61705],"type":"Point"}
}