{
  "type": "Feature",
  "properties": {
    "gn:admin1_code":"82",
    "gn:admin2_code":"4050.0",
    "gn:admin3_code":"405094.0",
    "gn:admin4_code":"40509443.0",
    "gn:asciiname":"Singpur",
    "gn:country_code":"BD",
    "gn:dem":18,
    "gn:feature_class":"P",
    "gn:feature_code":"PPL",
    "gn:name":"Singpur",
    "gn:population":0,
    "gn:timezone":"Asia/Dhaka",
    "iso:country":"BD",
    "name:ben_x_preferred":[
        "Singpur"
    ],
    "wof:name":"Singpur",
    "wof:placetype":"locality"
},
  "geometry": {"coordinates":[88.98374,23.95978],"type":"Point"}
}