{
  "type": "Feature",
  "properties": {
    "gn:admin1_code":"81",
    "gn:admin2_code":"3082.0",
    "gn:admin3_code":"308276.0",
    "gn:admin4_code":"30827632.0",
    "gn:asciiname":"Bobupur",
    "gn:country_code":"BD",
    "gn:dem":16,
    "gn:feature_class":"P",
    "gn:feature_code":"PPL",
    "gn:name":"Bobupur",
    "gn:population":0,
    "gn:timezone":"Asia/Dhaka",
    "iso:country":"BD",
    "name:ben_x_preferred":[
        "Bobupur"
    ],
    "wof:name":"Bobupur",
    "wof:placetype":"locality"
},
  "geometry": {"coordinates":[89.56173000000003,23.77922],"type":"Point"}
}