{
  "type": "Feature",
  "properties": {
    "gn:admin1_code":"83",
    "gn:admin2_code":"5038.0",
    "gn:admin3_code":"503861.0",
    "gn:admin4_code":"50386128.0",
    "gn:asciiname":"Telal Muraripur",
    "gn:country_code":"BD",
    "gn:dem":23,
    "gn:feature_class":"P",
    "gn:feature_code":"PPL",
    "gn:name":"Telal Mur\u0101ripur",
    "gn:population":0,
    "gn:timezone":"Asia/Dhaka",
    "iso:country":"BD",
    "name:ben_x_preferred":[
        "Telal Mur\u0101ripur"
    ],
    "wof:name":"Telal Muraripur",
    "wof:placetype":"locality"
},
  "geometry": {"coordinates":[89.11487,25.01841],"type":"Point"}
}