{
  "type": "Feature",
  "properties": {
    "gn:admin1_code":"82",
    "gn:asciiname":"Ballabhpur",
    "gn:country_code":"BD",
    "gn:dem":7,
    "gn:feature_class":"P",
    "gn:feature_code":"PPL",
    "gn:name":"Ballabhpur",
    "gn:population":0,
    "gn:timezone":"Asia/Dhaka",
    "iso:country":"BD",
    "name:ben_x_preferred":[
        "Ballabhpur"
    ],
    "wof:name":"Ballabhpur",
    "wof:placetype":"locality"
},
  "geometry": {"coordinates":[90.32686,22.32379],"type":"Point"}
}