{
  "type": "Feature",
  "properties": {
    "gn:admin1_code":"83",
    "gn:admin2_code":"5064.0",
    "gn:admin3_code":"506475.0",
    "gn:admin4_code":"50647551.0",
    "gn:asciiname":"Gokulbui",
    "gn:country_code":"BD",
    "gn:dem":22,
    "gn:feature_class":"P",
    "gn:feature_code":"PPL",
    "gn:name":"Gokulbui",
    "gn:population":0,
    "gn:timezone":"Asia/Dhaka",
    "iso:country":"BD",
    "name:ben_x_preferred":[
        "Gokulbui"
    ],
    "wof:name":"Gokulbui",
    "wof:placetype":"locality"
},
  "geometry": {"coordinates":[88.64339,24.99662],"type":"Point"}
}