{
  "type": "Feature",
  "properties": {
    "gn:admin1_code":"87",
    "gn:admin2_code":"5527.0",
    "gn:admin3_code":"552710.0",
    "gn:admin4_code":"55271035.0",
    "gn:asciiname":"Bizul",
    "gn:country_code":"BD",
    "gn:dem":29,
    "gn:feature_class":"P",
    "gn:feature_code":"PPL",
    "gn:name":"Bizul",
    "gn:population":0,
    "gn:timezone":"Asia/Dhaka",
    "iso:country":"BD",
    "name:ben_x_preferred":[
        "Bizul"
    ],
    "name:ben_x_variant":[
        "Bijul"
    ],
    "wof:name":"Bizul",
    "wof:placetype":"locality"
},
  "geometry": {"coordinates":[89.02024,25.34532],"type":"Point"}
}