{
  "type": "Feature",
  "properties": {
    "gn:admin1_code":"84",
    "gn:admin2_code":"2046.0",
    "gn:admin3_code":"204665.0",
    "gn:admin4_code":"20466563.0",
    "gn:asciiname":"Mupachari",
    "gn:country_code":"BD",
    "gn:dem":43,
    "gn:feature_class":"P",
    "gn:feature_code":"PPL",
    "gn:name":"Mupachari",
    "gn:population":0,
    "gn:timezone":"Asia/Dhaka",
    "iso:country":"BD",
    "name:ben_x_preferred":[
        "Mupachari"
    ],
    "wof:name":"Mupachari",
    "wof:placetype":"locality"
},
  "geometry": {"coordinates":[92.05692000000001,22.95645],"type":"Point"}
}