{
  "type": "Feature",
  "properties": {
    "gn:admin1_code":"87",
    "gn:admin2_code":"5577.0",
    "gn:admin3_code":"557790.0",
    "gn:admin4_code":"55779027.0",
    "gn:asciiname":"Bagulahagi",
    "gn:country_code":"BD",
    "gn:dem":97,
    "gn:feature_class":"P",
    "gn:feature_code":"PPL",
    "gn:name":"Bagul\u0101h\u0101gi",
    "gn:population":0,
    "gn:timezone":"Asia/Dhaka",
    "iso:country":"BD",
    "name:ben_x_preferred":[
        "Bagul\u0101h\u0101gi"
    ],
    "wof:name":"Bagulahagi",
    "wof:placetype":"locality"
},
  "geometry": {"coordinates":[88.46975,26.53158],"type":"Point"}
}