{
  "type": "Feature",
  "properties": {
    "gn:admin1_code":"84",
    "gn:admin2_code":"2015.0",
    "gn:admin3_code":"201561.0",
    "gn:admin4_code":"20156139.0",
    "gn:asciiname":"Goahkhil",
    "gn:country_code":"BD",
    "gn:dem":10,
    "gn:feature_class":"P",
    "gn:feature_code":"PPL",
    "gn:name":"Goahkhil",
    "gn:population":0,
    "gn:timezone":"Asia/Dhaka",
    "iso:country":"BD",
    "name:ben_x_preferred":[
        "Goahkhil"
    ],
    "wof:name":"Goahkhil",
    "wof:placetype":"locality"
},
  "geometry": {"coordinates":[91.9401,22.34092],"type":"Point"}
}