{
  "type": "Feature",
  "properties": {
    "gn:admin1_code":"84",
    "gn:admin2_code":"2046.0",
    "gn:admin3_code":"204680.0",
    "gn:admin4_code":"20468076.0",
    "gn:asciiname":"Torcharapara",
    "gn:country_code":"BD",
    "gn:dem":31,
    "gn:feature_class":"P",
    "gn:feature_code":"PPL",
    "gn:name":"Torchar\u0101para",
    "gn:population":0,
    "gn:timezone":"Asia/Dhaka",
    "iso:country":"BD",
    "name:ben_x_preferred":[
        "Torchar\u0101para"
    ],
    "wof:name":"Torcharapara",
    "wof:placetype":"locality"
},
  "geometry": {"coordinates":[91.75346999999999,22.9847],"type":"Point"}
}