{
  "type": "Feature",
  "properties": {
    "gn:admin1_code":"87",
    "gn:admin2_code":"5532",
    "gn:admin3_code":"553230.0",
    "gn:admin4_code":"55323094.0",
    "gn:asciiname":"Phulbari",
    "gn:country_code":"BD",
    "gn:dem":25,
    "gn:feature_class":"P",
    "gn:feature_code":"PPL",
    "gn:name":"Phulb\u0101ri",
    "gn:population":0,
    "gn:timezone":"Asia/Dhaka",
    "iso:country":"BD",
    "name:ben_x_preferred":[
        "Phulb\u0101ri"
    ],
    "wof:name":"Phulbari",
    "wof:placetype":"locality"
},
  "geometry": {"coordinates":[89.40299999999998,25.22701],"type":"Point"}
}