{
  "type": "Feature",
  "properties": {
    "gn:admin1_code":"82",
    "gn:admin2_code":"4044",
    "gn:admin3_code":"404480.0",
    "gn:admin4_code":"40448069.0",
    "gn:asciiname":"Nij Palasi",
    "gn:country_code":"BD",
    "gn:dem":12,
    "gn:feature_class":"P",
    "gn:feature_code":"PPL",
    "gn:name":"Nij Pal\u0101si",
    "gn:population":0,
    "gn:timezone":"Asia/Dhaka",
    "iso:country":"BD",
    "wof:name":"Nij Palasi",
    "wof:placetype":"locality"
},
  "geometry": {"coordinates":[89.27767,23.5983],"type":"Point"}
}