{
  "type": "Feature",
  "properties": {
    "gn:admin1_code":"82",
    "gn:admin2_code":"4055.0",
    "gn:admin3_code":"405557.0",
    "gn:admin4_code":"40555774.0",
    "gn:asciiname":"Nidhipur",
    "gn:country_code":"BD",
    "gn:dem":11,
    "gn:feature_class":"P",
    "gn:feature_code":"PPL",
    "gn:name":"Nidhipur",
    "gn:population":0,
    "gn:timezone":"Asia/Dhaka",
    "iso:country":"BD",
    "name:ben_x_preferred":[
        "Nidhipur"
    ],
    "wof:name":"Nidhipur",
    "wof:placetype":"locality"
},
  "geometry": {"coordinates":[89.38814000000001,23.40568],"type":"Point"}
}