{
  "type": "Feature",
  "properties": {
    "gn:admin1_code":"82",
    "gn:asciiname":"Premahar",
    "gn:country_code":"BD",
    "gn:dem":9,
    "gn:feature_class":"P",
    "gn:feature_code":"PPL",
    "gn:name":"Premahar",
    "gn:population":0,
    "gn:timezone":"Asia/Dhaka",
    "iso:country":"BD",
    "name:und_x_variant":[
        "Premhar",
        "Premahar"
    ],
    "wof:name":"Premahar",
    "wof:placetype":"locality"
},
  "geometry": {"coordinates":[90.25644,22.66509],"type":"Point"}
}