{
  "type": "Feature",
  "properties": {
    "gn:admin1_code":"84",
    "gn:admin2_code":"2019.0",
    "gn:admin3_code":"201987.0",
    "gn:admin4_code":"20198751.0",
    "gn:asciiname":"Daulkhar",
    "gn:country_code":"BD",
    "gn:dem":10,
    "gn:feature_class":"P",
    "gn:feature_code":"PPL",
    "gn:name":"Daulkh\u0101r",
    "gn:population":0,
    "gn:timezone":"Asia/Dhaka",
    "iso:country":"BD",
    "wof:name":"Daulkhar",
    "wof:placetype":"locality"
},
  "geometry": {"coordinates":[91.20954,23.08127],"type":"Point"}
}