{
  "type": "Feature",
  "properties": {
    "gn:admin1_code":"83",
    "gn:admin2_code":"5088",
    "gn:admin3_code":"508867.0",
    "gn:admin4_code":"50886773.0",
    "gn:asciiname":"Potajia",
    "gn:country_code":"BD",
    "gn:dem":18,
    "gn:feature_class":"P",
    "gn:feature_code":"PPL",
    "gn:name":"Pot\u0101jia",
    "gn:population":0,
    "gn:timezone":"Asia/Dhaka",
    "iso:country":"BD",
    "wof:name":"Potajia",
    "wof:placetype":"locality"
},
  "geometry": {"coordinates":[89.56822,24.15736],"type":"Point"}
}