{
  "type": "Feature",
  "properties": {
    "gn:admin1_code":"83",
    "gn:admin2_code":"5069",
    "gn:admin3_code":"506944.0",
    "gn:admin4_code":"50694419.0",
    "gn:asciiname":"Udhanpara",
    "gn:country_code":"BD",
    "gn:dem":17,
    "gn:feature_class":"P",
    "gn:feature_code":"PPL",
    "gn:name":"Udhanp\u0101ra",
    "gn:population":0,
    "gn:timezone":"Asia/Dhaka",
    "iso:country":"BD",
    "name:ben_x_preferred":[
        "Udhanp\u0101ra"
    ],
    "wof:name":"Udhanpara",
    "wof:placetype":"locality"
},
  "geometry": {"coordinates":[88.91093000000002,24.1914],"type":"Point"}
}