{
  "type": "Feature",
  "properties": {
    "gn:admin1_code":"83",
    "gn:admin2_code":"5069",
    "gn:admin3_code":"506944.0",
    "gn:admin4_code":"50694428.0",
    "gn:asciiname":"Tarapur",
    "gn:country_code":"BD",
    "gn:dem":21,
    "gn:feature_class":"P",
    "gn:feature_code":"PPL",
    "gn:name":"T\u0101r\u0101pur",
    "gn:population":0,
    "gn:timezone":"Asia/Dhaka",
    "iso:country":"BD",
    "name:ben_x_preferred":[
        "T\u0101r\u0101pur"
    ],
    "name:deu_x_preferred":[
        "Tarapur"
    ],
    "wof:name":"Tarapur",
    "wof:placetype":"locality"
},
  "geometry": {"coordinates":[88.98195,24.26382000000001],"type":"Point"}
}