{
  "type": "Feature",
  "properties": {
    "gn:admin1_code":"82",
    "gn:admin2_code":"4055",
    "gn:admin3_code":"405566.0",
    "gn:admin4_code":"40556631.0",
    "gn:asciiname":"Rahamatpur",
    "gn:country_code":"BD",
    "gn:dem":14,
    "gn:feature_class":"P",
    "gn:feature_code":"PPL",
    "gn:name":"Rahamatpur",
    "gn:population":0,
    "gn:timezone":"Asia/Dhaka",
    "iso:country":"BD",
    "wof:name":"Rahamatpur",
    "wof:placetype":"locality"
},
  "geometry": {"coordinates":[89.51178,23.45689],"type":"Point"}
}