{
  "type": "Feature",
  "properties": {
    "gn:admin1_code":"83",
    "gn:admin2_code":"5038.0",
    "gn:admin3_code":"503847.0",
    "gn:admin4_code":"50384709.0",
    "gn:asciiname":"Muraripur",
    "gn:country_code":"BD",
    "gn:dem":23,
    "gn:feature_class":"P",
    "gn:feature_code":"PPL",
    "gn:name":"Mur\u0101ripur",
    "gn:population":0,
    "gn:timezone":"Asia/Dhaka",
    "iso:country":"BD",
    "name:ben_x_preferred":[
        "Mur\u0101ripur"
    ],
    "wof:name":"Muraripur",
    "wof:placetype":"locality"
},
  "geometry": {"coordinates":[89.08766,25.11561],"type":"Point"}
}