{
  "type": "Feature",
  "properties": {
    "gn:admin1_code":"81",
    "gn:admin2_code":"3086.0",
    "gn:admin3_code":"308694.0",
    "gn:admin4_code":"30869458.0",
    "gn:asciiname":"Hamgaon",
    "gn:country_code":"BD",
    "gn:dem":13,
    "gn:feature_class":"P",
    "gn:feature_code":"PPL",
    "gn:name":"H\u0101mgaon",
    "gn:population":0,
    "gn:timezone":"Asia/Dhaka",
    "iso:country":"BD",
    "wof:name":"Hamgaon",
    "wof:placetype":"locality"
},
  "geometry": {"coordinates":[90.3027,23.30143],"type":"Point"}
}