{
  "type": "Feature",
  "properties": {
    "gn:admin1_code":"84",
    "gn:admin2_code":"2015",
    "gn:admin3_code":"201512.0",
    "gn:admin4_code":"20151266.0",
    "gn:asciiname":"Purba Gomdandi",
    "gn:country_code":"BD",
    "gn:dem":9,
    "gn:feature_class":"P",
    "gn:feature_code":"PPL",
    "gn:name":"Purba Gomdandi",
    "gn:population":0,
    "gn:timezone":"Asia/Dhaka",
    "iso:country":"BD",
    "name:ben_x_preferred":[
        "Purba Gomdandi"
    ],
    "name:und_x_variant":[
        "Purbba Gomdandi"
    ],
    "wof:name":"Purba Gomdandi",
    "wof:placetype":"locality"
},
  "geometry": {"coordinates":[91.93980000000001,22.36897],"type":"Point"}
}