{
  "type": "Feature",
  "properties": {
    "gn:admin1_code":"82",
    "gn:admin2_code":"4065.0",
    "gn:admin3_code":"406576.0",
    "gn:admin4_code":"40657654.0",
    "gn:asciiname":"Kallankhali",
    "gn:country_code":"BD",
    "gn:dem":10,
    "gn:feature_class":"P",
    "gn:feature_code":"PPL",
    "gn:name":"Kallankhali",
    "gn:population":0,
    "gn:timezone":"Asia/Dhaka",
    "iso:country":"BD",
    "name:ben_x_preferred":[
        "Kallankhali"
    ],
    "wof:name":"Kallankhali",
    "wof:placetype":"locality"
},
  "geometry": {"coordinates":[89.45971,23.24051],"type":"Point"}
}