{
  "type": "Feature",
  "properties": {
    "gn:admin1_code":"81",
    "gn:admin2_code":"3029",
    "gn:admin3_code":"302947.0",
    "gn:admin4_code":"30294755.0",
    "gn:asciiname":"Muraridaha",
    "gn:country_code":"BD",
    "gn:dem":13,
    "gn:feature_class":"P",
    "gn:feature_code":"PPL",
    "gn:name":"Mur\u0101ridaha",
    "gn:population":0,
    "gn:timezone":"Asia/Dhaka",
    "iso:country":"BD",
    "wof:name":"Muraridaha",
    "wof:placetype":"locality"
},
  "geometry": {"coordinates":[89.80986,23.57053],"type":"Point"}
}