{
  "type": "Feature",
  "properties": {
    "gn:admin1_code":"87",
    "gn:admin2_code":"5585.0",
    "gn:admin3_code":"558549.0",
    "gn:admin4_code":"55854900.0",
    "gn:asciiname":"Lalbag",
    "gn:country_code":"BD",
    "gn:dem":35,
    "gn:feature_class":"P",
    "gn:feature_code":"PPL",
    "gn:name":"L\u0101lb\u0101g",
    "gn:population":0,
    "gn:timezone":"Asia/Dhaka",
    "iso:country":"BD",
    "name:ben_x_preferred":[
        "L\u0101lb\u0101g"
    ],
    "wof:name":"Lalbag",
    "wof:placetype":"locality"
},
  "geometry": {"coordinates":[89.25457,25.72591],"type":"Point"}
}