{
  "type": "Feature",
  "properties": {
    "gn:admin1_code":"82",
    "gn:asciiname":"Godanga",
    "gn:country_code":"BD",
    "gn:dem":7,
    "gn:feature_class":"P",
    "gn:feature_code":"PPL",
    "gn:name":"God\u0101nga",
    "gn:population":0,
    "gn:timezone":"Asia/Dhaka",
    "iso:country":"BD",
    "name:ben_x_preferred":[
        "God\u0101nga"
    ],
    "wof:name":"Godanga",
    "wof:placetype":"locality"
},
  "geometry": {"coordinates":[90.34362,22.20491],"type":"Point"}
}