{
  "type": "Feature",
  "properties": {
    "gn:admin1_code":"84",
    "gn:admin2_code":"2015.0",
    "gn:admin3_code":"201574.0",
    "gn:admin4_code":"20157418.0",
    "gn:asciiname":"Chikdair",
    "gn:country_code":"BD",
    "gn:dem":9,
    "gn:feature_class":"P",
    "gn:feature_code":"PPL",
    "gn:name":"Chikd\u0101ir",
    "gn:population":0,
    "gn:timezone":"Asia/Dhaka",
    "iso:country":"BD",
    "name:ben_x_preferred":[
        "Chikd\u0101ir"
    ],
    "wof:name":"Chikdair",
    "wof:placetype":"locality"
},
  "geometry": {"coordinates":[91.88764,22.53558],"type":"Point"}
}