{
  "type": "Feature",
  "properties": {
    "gn:admin1_code":"83",
    "gn:admin2_code":"5064.0",
    "gn:admin3_code":"506428.0",
    "gn:admin4_code":"50642842.0",
    "gn:asciiname":"Jagathnagar",
    "gn:country_code":"BD",
    "gn:dem":27,
    "gn:feature_class":"P",
    "gn:feature_code":"PPL",
    "gn:name":"Jagathnagar",
    "gn:population":0,
    "gn:timezone":"Asia/Dhaka",
    "iso:country":"BD",
    "name:ben_x_preferred":[
        "Jagathnagar"
    ],
    "wof:name":"Jagathnagar",
    "wof:placetype":"locality"
},
  "geometry": {"coordinates":[88.88851,25.15275],"type":"Point"}
}