{
  "type": "Feature",
  "properties": {
    "gn:admin1_code":"85",
    "gn:admin2_code":"1042.0",
    "gn:admin3_code":"104273.0",
    "gn:admin4_code":"10427394.0",
    "gn:asciiname":"Bhojpur",
    "gn:country_code":"BD",
    "gn:dem":7,
    "gn:feature_class":"P",
    "gn:feature_code":"PPL",
    "gn:name":"Bhojpur",
    "gn:population":0,
    "gn:timezone":"Asia/Dhaka",
    "iso:country":"BD",
    "wof:name":"Bhojpur",
    "wof:placetype":"locality"
},
  "geometry": {"coordinates":[90.24532000000001,22.57802],"type":"Point"}
}