{
  "type": "Feature",
  "properties": {
    "gn:admin1_code":"85",
    "gn:admin2_code":"1042.0",
    "gn:admin3_code":"104273.0",
    "gn:admin4_code":"10427394.0",
    "gn:asciiname":"Bhojpur",
    "gn:country_code":"BD",
    "gn:dem":7,
    "gn:feature_class":"P",
    "gn:feature_code":"PPL",
    "gn:name":"Bhojpur",
    "gn:population":0,
    "gn:timezone":"Asia/Dhaka",
    "iso:country":"BD",
    "name:ara_x_preferred":[
        "\u0628\u0648\u062c \u0628\u0648\u0631"
    ],
    "name:ceb_x_preferred":[
        "Bhojpur"
    ],
    "name:deu_x_preferred":[
        "Bhojpur"
    ],
    "name:fra_x_preferred":[
        "Bhojpur"
    ],
    "name:hin_x_preferred":[
        "\u092d\u094b\u091c\u092a\u0941\u0930"
    ],
    "name:nld_x_preferred":[
        "Bhojpur"
    ],
    "name:swe_x_preferred":[
        "Bhojpur"
    ],
    "name:vie_x_preferred":[
        "Bhojpur"
    ],
    "wof:name":"Bhojpur",
    "wof:placetype":"locality"
},
  "geometry": {"coordinates":[90.24532000000001,22.57802],"type":"Point"}
}