{
  "type": "Feature",
  "properties": {
    "gn:admin1_code":"83",
    "gn:admin2_code":"5064",
    "gn:admin3_code":"506460.0",
    "gn:admin4_code":"50646000.0",
    "gn:asciiname":"Razzakpur",
    "gn:country_code":"BD",
    "gn:dem":19,
    "gn:feature_class":"P",
    "gn:feature_code":"PPL",
    "gn:name":"R\u0101zz\u0101kpur",
    "gn:population":0,
    "gn:timezone":"Asia/Dhaka",
    "iso:country":"BD",
    "name:ben_x_preferred":[
        "R\u0101zz\u0101kpur"
    ],
    "name:ben_x_variant":[
        "Rajakpur"
    ],
    "wof:name":"Razzakpur",
    "wof:placetype":"locality"
},
  "geometry": {"coordinates":[88.95296999999999,24.80742],"type":"Point"}
}