{
  "type": "Feature",
  "properties": {
    "gn:admin1_code":"81",
    "gn:admin2_code":"3093.0",
    "gn:admin3_code":"309357.0",
    "gn:admin4_code":"30935709.0",
    "gn:asciiname":"Golpath",
    "gn:country_code":"BD",
    "gn:dem":17,
    "gn:feature_class":"P",
    "gn:feature_code":"PPL",
    "gn:name":"Golpath",
    "gn:population":0,
    "gn:timezone":"Asia/Dhaka",
    "iso:country":"BD",
    "name:und_x_variant":[
        "Gopath"
    ],
    "wof:name":"Golpath",
    "wof:placetype":"locality"
},
  "geometry": {"coordinates":[89.99495999999998,24.5884],"type":"Point"}
}