{
  "type": "Feature",
  "properties": {
    "gn:admin1_code":"87",
    "gn:admin2_code":"5585.0",
    "gn:admin3_code":"558576.0",
    "gn:admin4_code":"55857637.0",
    "gn:asciiname":"Bishnupur",
    "gn:country_code":"BD",
    "gn:dem":29,
    "gn:feature_class":"P",
    "gn:feature_code":"PPL",
    "gn:name":"Bishnupur",
    "gn:population":0,
    "gn:timezone":"Asia/Dhaka",
    "iso:country":"BD",
    "wof:name":"Bishnupur",
    "wof:placetype":"locality"
},
  "geometry": {"coordinates":[89.33924,25.34081],"type":"Point"}
}