{
  "type": "Feature",
  "properties": {
    "gn:admin1_code":"87",
    "gn:admin2_code":"5549",
    "gn:admin3_code":"554952.0",
    "gn:admin4_code":"55495219.0",
    "gn:asciiname":"Jhankuthi",
    "gn:country_code":"BD",
    "gn:dem":28,
    "gn:feature_class":"P",
    "gn:feature_code":"PPL",
    "gn:name":"Jh\u0101nkuthi",
    "gn:population":0,
    "gn:timezone":"Asia/Dhaka",
    "iso:country":"BD",
    "name:ben_x_preferred":[
        "Jh\u0101nkuthi"
    ],
    "wof:name":"Jhankuthi",
    "wof:placetype":"locality"
},
  "geometry": {"coordinates":[89.66027,25.85538],"type":"Point"}
}