{
  "type": "Feature",
  "properties": {
    "gn:admin1_code":"85",
    "gn:admin2_code":"1078.0",
    "gn:admin3_code":"107838.0",
    "gn:admin4_code":"10783889.0",
    "gn:asciiname":"Chhota Dalima",
    "gn:country_code":"BD",
    "gn:dem":10,
    "gn:feature_class":"P",
    "gn:feature_code":"PPL",
    "gn:name":"Chhota Dalima",
    "gn:population":0,
    "gn:timezone":"Asia/Dhaka",
    "iso:country":"BD",
    "name:ben_x_preferred":[
        "Chhota Dalima"
    ],
    "wof:name":"Chhota Dalima",
    "wof:placetype":"locality"
},
  "geometry": {"coordinates":[90.57073,22.42449],"type":"Point"}
}