{
  "type": "Feature",
  "properties": {
    "gn:admin1_code":"81",
    "gn:admin2_code":"3035.0",
    "gn:admin3_code":"303551.0",
    "gn:admin4_code":"30355115.0",
    "gn:asciiname":"Bandhabari",
    "gn:country_code":"BD",
    "gn:dem":7,
    "gn:feature_class":"P",
    "gn:feature_code":"PPL",
    "gn:name":"B\u0101ndh\u0101b\u0101ri",
    "gn:population":0,
    "gn:timezone":"Asia/Dhaka",
    "iso:country":"BD",
    "name:und_x_variant":[
        "Banodhabari",
        "B\u0101ndh\u0101b\u0101ri"
    ],
    "wof:name":"Bandhabari",
    "wof:placetype":"locality"
},
  "geometry": {"coordinates":[90.06570000000001,23.01644],"type":"Point"}
}