{
  "type": "Feature",
  "properties": {
    "gn:admin1_code":"83",
    "gn:admin2_code":"5081.0",
    "gn:admin3_code":"508134.0",
    "gn:admin4_code":"50813419.0",
    "gn:asciiname":"Diar Manikchak",
    "gn:country_code":"BD",
    "gn:dem":25,
    "gn:feature_class":"P",
    "gn:feature_code":"PPL",
    "gn:name":"Di\u0101r M\u0101nikchak",
    "gn:population":0,
    "gn:timezone":"Asia/Dhaka",
    "iso:country":"BD",
    "name:ben_x_preferred":[
        "Di\u0101r M\u0101nikchak"
    ],
    "wof:name":"Diar Manikchak",
    "wof:placetype":"locality"
},
  "geometry": {"coordinates":[88.30858000000001,24.42319],"type":"Point"}
}