{
  "type": "Feature",
  "properties": {
    "gn:admin1_code":"82",
    "gn:admin2_code":"4044.0",
    "gn:admin3_code":"404480.0",
    "gn:admin4_code":"40448069.0",
    "gn:asciiname":"Bhabanipur",
    "gn:country_code":"BD",
    "gn:dem":14,
    "gn:feature_class":"P",
    "gn:feature_code":"PPL",
    "gn:name":"Bhab\u0101n\u012bpur",
    "gn:population":0,
    "gn:timezone":"Asia/Dhaka",
    "iso:country":"BD",
    "name:ben_x_preferred":[
        "\u09ad\u09ac\u09be\u09a8\u09c0\u09aa\u09c1\u09b0"
    ],
    "wof:name":"Bhabanipur",
    "wof:placetype":"locality"
},
  "geometry": {"coordinates":[89.27655,23.59548],"type":"Point"}
}