{
  "type": "Feature",
  "properties": {
    "gn:admin1_code":"85",
    "gn:admin2_code":"1006",
    "gn:admin3_code":"100669.0",
    "gn:admin4_code":"10066959.0",
    "gn:asciiname":"North Galaibhanga",
    "gn:country_code":"BD",
    "gn:dem":5,
    "gn:feature_class":"P",
    "gn:feature_code":"PPL",
    "gn:name":"North Gal\u0101ibh\u0101nga",
    "gn:population":0,
    "gn:timezone":"Asia/Dhaka",
    "iso:country":"BD",
    "wof:name":"North Galaibhanga",
    "wof:placetype":"locality"
},
  "geometry": {"coordinates":[90.39053,22.95942],"type":"Point"}
}