{
  "type": "Feature",
  "properties": {
    "gn:admin1_code":"84",
    "gn:admin2_code":"2030",
    "gn:admin3_code":"203014.0",
    "gn:admin4_code":"20301495.0",
    "gn:asciiname":"Subhapur",
    "gn:country_code":"BD",
    "gn:dem":6,
    "gn:feature_class":"P",
    "gn:feature_code":"PPL",
    "gn:name":"Subhapur",
    "gn:population":0,
    "gn:timezone":"Asia/Dhaka",
    "iso:country":"BD",
    "wof:name":"Subhapur",
    "wof:placetype":"locality"
},
  "geometry": {"coordinates":[91.53333000000001,22.96667],"type":"Point"}
}