{
  "type": "Feature",
  "properties": {
    "gn:admin1_code":"87",
    "gn:admin2_code":"5594.0",
    "gn:admin3_code":"559494.0",
    "gn:admin4_code":"55949410.0",
    "gn:asciiname":"Maheshpur",
    "gn:country_code":"BD",
    "gn:dem":68,
    "gn:feature_class":"P",
    "gn:feature_code":"PPL",
    "gn:name":"Maheshpur",
    "gn:population":0,
    "gn:timezone":"Asia/Dhaka",
    "iso:country":"BD",
    "name:ben_x_preferred":[
        "Maheshpur"
    ],
    "name:ceb_x_preferred":[
        "Maheshpur"
    ],
    "name:fra_x_preferred":[
        "Maheshpur"
    ],
    "name:hin_x_preferred":[
        "\u092e\u0939\u0947\u0936\u092a\u0941\u0930 \u0968"
    ],
    "name:new_x_preferred":[
        "\u092e\u0939\u0947\u0936\u092a\u0941\u0930 \u0917\u093e\u0935\u093f\u0938"
    ],
    "name:pol_x_preferred":[
        "Maheshpur"
    ],
    "name:swe_x_preferred":[
        "Maheshpur"
    ],
    "wof:name":"Maheshpur",
    "wof:placetype":"locality"
},
  "geometry": {"coordinates":[88.3698,26.13254],"type":"Point"}
}