{
  "type": "Feature",
  "properties": {
    "gn:admin1_code":"84",
    "gn:admin2_code":"2013.0",
    "gn:admin3_code":"201345.0",
    "gn:admin4_code":"20134589.0",
    "gn:asciiname":"Baragaon",
    "gn:country_code":"BD",
    "gn:dem":11,
    "gn:feature_class":"P",
    "gn:feature_code":"PPL",
    "gn:name":"Baragaon",
    "gn:population":0,
    "gn:timezone":"Asia/Dhaka",
    "iso:country":"BD",
    "name:ita_x_preferred":[
        "Baragaon"
    ],
    "name:nld_x_preferred":[
        "Baragaon"
    ],
    "name:pol_x_preferred":[
        "Baragaon"
    ],
    "wof:name":"Baragaon",
    "wof:placetype":"locality"
},
  "geometry": {"coordinates":[90.81565999999999,23.18408],"type":"Point"}
}