{
  "type": "Feature",
  "properties": {
    "gn:admin1_code":"82",
    "gn:admin2_code":"4018.0",
    "gn:admin3_code":"401807.0",
    "gn:admin4_code":"40180731.0",
    "gn:asciiname":"Ananadadham",
    "gn:country_code":"BD",
    "gn:dem":18,
    "gn:feature_class":"P",
    "gn:feature_code":"PPL",
    "gn:name":"\u0100nanadadh\u0101m",
    "gn:population":0,
    "gn:timezone":"Asia/Dhaka",
    "iso:country":"BD",
    "name:ben_x_preferred":[
        "\u0100nanadadh\u0101m"
    ],
    "wof:name":"Ananadadham",
    "wof:placetype":"locality"
},
  "geometry": {"coordinates":[88.95640999999998,23.74954],"type":"Point"}
}