{
  "type": "Feature",
  "properties": {
    "gn:admin1_code":"84",
    "gn:admin2_code":"2013.0",
    "gn:admin3_code":"201322.0",
    "gn:admin4_code":"20132281.0",
    "gn:asciiname":"Bimalergaon",
    "gn:country_code":"BD",
    "gn:dem":10,
    "gn:feature_class":"P",
    "gn:feature_code":"PPL",
    "gn:name":"Bimalergaon",
    "gn:population":0,
    "gn:timezone":"Asia/Dhaka",
    "iso:country":"BD",
    "wof:name":"Bimalergaon",
    "wof:placetype":"locality"
},
  "geometry": {"coordinates":[90.75754000000001,23.25539],"type":"Point"}
}