{
  "type": "Feature",
  "properties": {
    "gn:admin1_code":"81",
    "gn:admin2_code":"3035.0",
    "gn:admin3_code":"303551.0",
    "gn:admin4_code":"30355139.0",
    "gn:asciiname":"Kumaria",
    "gn:country_code":"BD",
    "gn:dem":4,
    "gn:feature_class":"P",
    "gn:feature_code":"PPL",
    "gn:name":"Kum\u0101ria",
    "gn:population":0,
    "gn:timezone":"Asia/Dhaka",
    "iso:country":"BD",
    "name:ben_x_preferred":[
        "Kum\u0101ria"
    ],
    "wof:name":"Kumaria",
    "wof:placetype":"locality"
},
  "geometry": {"coordinates":[89.97917,23.07612],"type":"Point"}
}