{
  "type": "Feature",
  "properties": {
    "gn:admin1_code":"81",
    "gn:admin2_code":"3068.0",
    "gn:admin3_code":"306860.0",
    "gn:admin4_code":"30686083.0",
    "gn:asciiname":"Bhater Kandi",
    "gn:country_code":"BD",
    "gn:dem":8,
    "gn:feature_class":"P",
    "gn:feature_code":"PPL",
    "gn:name":"Bh\u0101ter K\u0101ndi",
    "gn:population":0,
    "gn:timezone":"Asia/Dhaka",
    "iso:country":"BD",
    "wof:name":"Bhater Kandi",
    "wof:placetype":"locality"
},
  "geometry": {"coordinates":[90.71778,23.80476],"type":"Point"}
}