{
  "type": "Feature",
  "properties": {
    "gn:admin1_code":"H",
    "gn:admin2_code":"3061.0",
    "gn:admin3_code":"306131.0",
    "gn:admin4_code":"30613167.0",
    "gn:asciiname":"Hat Bhulsoma",
    "gn:country_code":"BD",
    "gn:dem":15,
    "gn:feature_class":"P",
    "gn:feature_code":"PPL",
    "gn:name":"H\u0101t Bhulsoma",
    "gn:population":0,
    "gn:timezone":"Asia/Dhaka",
    "iso:country":"BD",
    "wof:name":"Hat Bhulsoma",
    "wof:placetype":"locality"
},
  "geometry": {"coordinates":[90.55283,24.60893],"type":"Point"}
}