{
  "type": "Feature",
  "properties": {
    "gn:admin1_code":"87",
    "gn:admin2_code":"5549",
    "gn:admin3_code":"554909.0",
    "gn:admin4_code":"55490971.0",
    "gn:asciiname":"Kalibari",
    "gn:country_code":"BD",
    "gn:dem":27,
    "gn:feature_class":"P",
    "gn:feature_code":"PPL",
    "gn:name":"K\u0101lib\u0101ri",
    "gn:population":0,
    "gn:timezone":"Asia/Dhaka",
    "iso:country":"BD",
    "name:ben_x_preferred":[
        "K\u0101lib\u0101ri"
    ],
    "wof:name":"Kalibari",
    "wof:placetype":"locality"
},
  "geometry": {"coordinates":[89.68361,25.62521],"type":"Point"}
}