{
  "type": "Feature",
  "properties": {
    "gn:admin1_code":"H",
    "gn:admin2_code":"3072.0",
    "gn:admin3_code":"307283.0",
    "gn:admin4_code":"30728315.0",
    "gn:asciiname":"Dilnagar",
    "gn:country_code":"BD",
    "gn:dem":15,
    "gn:feature_class":"P",
    "gn:feature_code":"PPL",
    "gn:name":"Dilnagar",
    "gn:population":0,
    "gn:timezone":"Asia/Dhaka",
    "iso:country":"BD",
    "wof:name":"Dilnagar",
    "wof:placetype":"locality"
},
  "geometry": {"coordinates":[90.64767000000001,24.80109],"type":"Point"}
}