{
  "type": "Feature",
  "properties": {
    "gn:admin1_code":"81",
    "gn:admin2_code":"3068",
    "gn:admin3_code":"306876.0",
    "gn:admin4_code":"30687684.0",
    "gn:asciiname":"Jhawakandi",
    "gn:country_code":"BD",
    "gn:dem":15,
    "gn:feature_class":"P",
    "gn:feature_code":"PPL",
    "gn:name":"Jh\u0101w\u0101k\u0101ndi",
    "gn:population":0,
    "gn:timezone":"Asia/Dhaka",
    "iso:country":"BD",
    "name:und_x_variant":[
        "Jhowakandi",
        "Jh\u0101w\u0101k\u0101ndi"
    ],
    "wof:name":"Jhawakandi",
    "wof:placetype":"locality"
},
  "geometry": {"coordinates":[90.72041,24.00727],"type":"Point"}
}