{
  "type": "Feature",
  "properties": {
    "gn:admin1_code":"87",
    "gn:admin2_code":"5532",
    "gn:admin3_code":"553288.0",
    "gn:admin4_code":"55328876.0",
    "gn:asciiname":"Rifaitpur Taluk",
    "gn:country_code":"BD",
    "gn:dem":23,
    "gn:feature_class":"P",
    "gn:feature_code":"PPL",
    "gn:name":"Rif\u0101itpur T\u0101luk",
    "gn:population":0,
    "gn:timezone":"Asia/Dhaka",
    "iso:country":"BD",
    "name:ben_x_preferred":[
        "Rif\u0101itpur T\u0101luk"
    ],
    "wof:name":"Rifaitpur Taluk",
    "wof:placetype":"locality"
},
  "geometry": {"coordinates":[89.54233000000001,25.22725],"type":"Point"}
}