{
  "type": "Feature",
  "properties": {
    "gn:admin1_code":"87",
    "gn:admin2_code":"5549",
    "gn:admin3_code":"554979.0",
    "gn:admin4_code":"55497971.0",
    "gn:asciiname":"Bancharchar",
    "gn:country_code":"BD",
    "gn:dem":30,
    "gn:feature_class":"P",
    "gn:feature_code":"PPL",
    "gn:name":"Bancharchar",
    "gn:population":0,
    "gn:timezone":"Asia/Dhaka",
    "iso:country":"BD",
    "name:ben_x_preferred":[
        "Bancharchar"
    ],
    "wof:name":"Bancharchar",
    "wof:placetype":"locality"
},
  "geometry": {"coordinates":[89.86173000000002,25.55119],"type":"Point"}
}