{
  "type": "Feature",
  "properties": {
    "gn:admin1_code":"83",
    "gn:admin2_code":"5064",
    "gn:admin3_code":"506460.0",
    "gn:admin4_code":"50646094.0",
    "gn:asciiname":"Namanurpur",
    "gn:country_code":"BD",
    "gn:dem":22,
    "gn:feature_class":"P",
    "gn:feature_code":"PPL",
    "gn:name":"N\u0101m\u0101nurpur",
    "gn:population":0,
    "gn:timezone":"Asia/Dhaka",
    "iso:country":"BD",
    "name:ben_x_preferred":[
        "N\u0101m\u0101nurpur"
    ],
    "name:und_x_variant":[
        "Namanupur"
    ],
    "wof:name":"Namanurpur",
    "wof:placetype":"locality"
},
  "geometry": {"coordinates":[88.97886,24.87135],"type":"Point"}
}