{
  "type": "Feature",
  "properties": {
    "gn:admin1_code":"84",
    "gn:admin2_code":"2084.0",
    "gn:admin3_code":"208436.0",
    "gn:admin4_code":"20843676.0",
    "gn:asciiname":"Dhongchari",
    "gn:country_code":"BD",
    "gn:dem":38,
    "gn:feature_class":"P",
    "gn:feature_code":"PPL",
    "gn:name":"Dhongchari",
    "gn:population":0,
    "gn:timezone":"Asia/Dhaka",
    "iso:country":"BD",
    "name:ben_x_preferred":[
        "Dhongchari"
    ],
    "wof:name":"Dhongchari",
    "wof:placetype":"locality"
},
  "geometry": {"coordinates":[92.12690000000001,22.40626],"type":"Point"}
}