{
  "type": "Feature",
  "properties": {
    "gn:admin1_code":"82",
    "gn:admin2_code":"4057.0",
    "gn:admin3_code":"405747.0",
    "gn:admin4_code":"40574710.0",
    "gn:asciiname":"Chidaha",
    "gn:country_code":"BD",
    "gn:dem":20,
    "gn:feature_class":"P",
    "gn:feature_code":"PPL",
    "gn:name":"Chidaha",
    "gn:population":0,
    "gn:timezone":"Asia/Dhaka",
    "iso:country":"BD",
    "name:ben_x_preferred":[
        "Chidaha"
    ],
    "wof:name":"Chidaha",
    "wof:placetype":"locality"
},
  "geometry": {"coordinates":[88.79207,23.86698],"type":"Point"}
}