{
  "type": "Feature",
  "properties": {
    "gn:admin1_code":"83",
    "gn:admin2_code":"5064.0",
    "gn:admin3_code":"506406.0",
    "gn:admin4_code":"50640631.0",
    "gn:asciiname":"Hazratpur",
    "gn:country_code":"BD",
    "gn:dem":22,
    "gn:feature_class":"P",
    "gn:feature_code":"PPL",
    "gn:name":"Hazratpur",
    "gn:population":0,
    "gn:timezone":"Asia/Dhaka",
    "iso:country":"BD",
    "name:ben_x_preferred":[
        "Hazratpur"
    ],
    "wof:name":"Hazratpur",
    "wof:placetype":"locality"
},
  "geometry": {"coordinates":[88.94759000000001,24.88673],"type":"Point"}
}