{
  "type": "Feature",
  "properties": {
    "gn:admin1_code":"86",
    "gn:admin2_code":"6091",
    "gn:admin3_code":"609141.0",
    "gn:admin4_code":"60914125.0",
    "gn:asciiname":"Kamaid",
    "gn:country_code":"BD",
    "gn:dem":20,
    "gn:feature_class":"P",
    "gn:feature_code":"PPL",
    "gn:name":"K\u0101m\u0101id",
    "gn:population":0,
    "gn:timezone":"Asia/Dhaka",
    "iso:country":"BD",
    "name:und_x_variant":[
        "Uttarpara",
        "K\u0101m\u0101id"
    ],
    "wof:name":"Kamaid",
    "wof:placetype":"locality"
},
  "geometry": {"coordinates":[92.00427000000001,25.03186],"type":"Point"}
}