{
  "type": "Feature",
  "properties": {
    "gn:admin1_code":"87",
    "gn:admin2_code":"5585",
    "gn:admin3_code":"558549.0",
    "gn:admin4_code":"55854994.0",
    "gn:asciiname":"Uttam",
    "gn:country_code":"BD",
    "gn:dem":38,
    "gn:feature_class":"P",
    "gn:feature_code":"PPL",
    "gn:name":"Uttam",
    "gn:population":0,
    "gn:timezone":"Asia/Dhaka",
    "iso:country":"BD",
    "name:ben_x_preferred":[
        "Uttam"
    ],
    "wof:name":"Uttam",
    "wof:placetype":"locality"
},
  "geometry": {"coordinates":[89.20475,25.7952],"type":"Point"}
}