{
  "type": "Feature",
  "properties": {
    "gn:admin1_code":"82",
    "gn:admin2_code":"4087.0",
    "gn:admin3_code":"408786.0",
    "gn:admin4_code":"40878615.0",
    "gn:asciiname":"Sirajpur",
    "gn:country_code":"BD",
    "gn:dem":8,
    "gn:feature_class":"P",
    "gn:feature_code":"PPL",
    "gn:name":"Sir\u0101jpur",
    "gn:population":0,
    "gn:timezone":"Asia/Dhaka",
    "iso:country":"BD",
    "name:ben_x_preferred":[
        "Sir\u0101jpur"
    ],
    "wof:name":"Sirajpur",
    "wof:placetype":"locality"
},
  "geometry": {"coordinates":[89.0595,22.35474],"type":"Point"}
}