{
  "type": "Feature",
  "properties": {
    "gn:admin1_code":"82",
    "gn:asciiname":"Gazalia",
    "gn:country_code":"BD",
    "gn:dem":1,
    "gn:feature_class":"P",
    "gn:feature_code":"PPL",
    "gn:name":"Gaz\u0101lia",
    "gn:population":0,
    "gn:timezone":"Asia/Dhaka",
    "iso:country":"BD",
    "name:ben_x_preferred":[
        "Gaz\u0101lia"
    ],
    "name:ben_x_variant":[
        "Char Gaz\u0101lia"
    ],
    "wof:name":"Gazalia",
    "wof:placetype":"locality"
},
  "geometry": {"coordinates":[90.42551,22.47269],"type":"Point"}
}