{
  "type": "Feature",
  "properties": {
    "gn:admin1_code":"82",
    "gn:admin2_code":"4041.0",
    "gn:admin3_code":"404111.0",
    "gn:admin4_code":"40411169.0",
    "gn:asciiname":"Teghari",
    "gn:country_code":"BD",
    "gn:dem":13,
    "gn:feature_class":"P",
    "gn:feature_code":"PPL",
    "gn:name":"Teghari",
    "gn:population":0,
    "gn:timezone":"Asia/Dhaka",
    "iso:country":"BD",
    "name:ben_x_preferred":[
        "Teghari"
    ],
    "name:spa_x_preferred":[
        "Teghari"
    ],
    "wof:name":"Teghari",
    "wof:placetype":"locality"
},
  "geometry": {"coordinates":[89.04831999999998,23.28539],"type":"Point"}
}