{
  "type": "Feature",
  "properties": {
    "gn:admin1_code":"81",
    "gn:admin2_code":"3056.0",
    "gn:admin3_code":"305646.0",
    "gn:admin4_code":"30564615.0",
    "gn:asciiname":"Char Budhuti",
    "gn:country_code":"BD",
    "gn:dem":13,
    "gn:feature_class":"P",
    "gn:feature_code":"PPL",
    "gn:name":"Char Budhuti",
    "gn:population":0,
    "gn:timezone":"Asia/Dhaka",
    "iso:country":"BD",
    "wof:name":"Char Budhuti",
    "wof:placetype":"locality"
},
  "geometry": {"coordinates":[90.04366999999998,23.76019],"type":"Point"}
}