{
  "type": "Feature",
  "properties": {
    "gn:admin1_code":"82",
    "gn:asciiname":"Siher ruk",
    "gn:country_code":"BD",
    "gn:dem":11,
    "gn:feature_class":"P",
    "gn:feature_code":"PPL",
    "gn:name":"Siher ruk",
    "gn:population":0,
    "gn:timezone":"Asia/Dhaka",
    "iso:country":"BD",
    "name:ben_x_preferred":[
        "Siher ruk"
    ],
    "wof:name":"Siher ruk",
    "wof:placetype":"locality"
},
  "geometry": {"coordinates":[90.4939,22.33809],"type":"Point"}
}