{
  "type": "Feature",
  "properties": {
    "gn:admin1_code":"83",
    "gn:asciiname":"Syampur",
    "gn:country_code":"BD",
    "gn:dem":27,
    "gn:feature_class":"P",
    "gn:feature_code":"PPL",
    "gn:name":"Syampur",
    "gn:population":0,
    "gn:timezone":"Asia/Dhaka",
    "iso:country":"BD",
    "name:ben_x_preferred":[
        "Syampur"
    ],
    "wof:name":"Syampur",
    "wof:placetype":"locality"
},
  "geometry": {"coordinates":[89.41301999999997,25.16387000000001],"type":"Point"}
}