{
  "type": "Feature",
  "properties": {
    "gn:admin1_code":"82",
    "gn:admin2_code":"4044.0",
    "gn:admin3_code":"404480.0",
    "gn:admin4_code":"40448063.0",
    "gn:asciiname":"Alamdanga",
    "gn:country_code":"BD",
    "gn:dem":15,
    "gn:feature_class":"P",
    "gn:feature_code":"PPL",
    "gn:name":"Alamd\u0101nga",
    "gn:population":0,
    "gn:timezone":"Asia/Dhaka",
    "iso:country":"BD",
    "name:ben_x_preferred":[
        "Alamd\u0101nga"
    ],
    "wof:name":"Alamdanga",
    "wof:placetype":"locality"
},
  "geometry": {"coordinates":[89.16466,23.67822],"type":"Point"}
}