{
  "type": "Feature",
  "properties": {
    "gn:admin1_code":"81",
    "gn:admin2_code":"3093.0",
    "gn:admin3_code":"309395.0",
    "gn:admin4_code":"30939577.0",
    "gn:asciiname":"Bil Muril",
    "gn:country_code":"BD",
    "gn:dem":17,
    "gn:feature_class":"P",
    "gn:feature_code":"PPL",
    "gn:name":"B\u012bl Muril",
    "gn:population":0,
    "gn:timezone":"Asia/Dhaka",
    "iso:country":"BD",
    "wof:name":"Bil Muril",
    "wof:placetype":"locality"
},
  "geometry": {"coordinates":[89.85507,24.30931],"type":"Point"}
}