{
  "type": "Feature",
  "properties": {
    "gn:admin1_code":"83",
    "gn:admin2_code":"5081.0",
    "gn:admin3_code":"508153.0",
    "gn:admin4_code":"50815367.0",
    "gn:asciiname":"Berabari",
    "gn:country_code":"BD",
    "gn:dem":21,
    "gn:feature_class":"P",
    "gn:feature_code":"PPL",
    "gn:name":"Ber\u0101b\u0101ri",
    "gn:population":0,
    "gn:timezone":"Asia/Dhaka",
    "iso:country":"BD",
    "name:ben_x_preferred":[
        "Ber\u0101b\u0101ri"
    ],
    "wof:name":"Berabari",
    "wof:placetype":"locality"
},
  "geometry": {"coordinates":[88.59423000000002,24.49954],"type":"Point"}
}