{
  "type": "Feature",
  "properties": {
    "gn:admin1_code":"83",
    "gn:admin2_code":"5081.0",
    "gn:admin3_code":"508134.0",
    "gn:admin4_code":"50813485.0",
    "gn:asciiname":"Ramtalipara",
    "gn:country_code":"BD",
    "gn:dem":32,
    "gn:feature_class":"P",
    "gn:feature_code":"PPL",
    "gn:name":"R\u0101mtalipara",
    "gn:population":0,
    "gn:timezone":"Asia/Dhaka",
    "iso:country":"BD",
    "name:ben_x_preferred":[
        "R\u0101mtalipara"
    ],
    "wof:name":"Ramtalipara",
    "wof:placetype":"locality"
},
  "geometry": {"coordinates":[88.4684,24.47639],"type":"Point"}
}