{
  "type": "Feature",
  "properties": {
    "gn:admin1_code":"87",
    "gn:admin2_code":"5577.0",
    "gn:admin3_code":"557773.0",
    "gn:admin4_code":"55777347.0",
    "gn:asciiname":"Baliadangi",
    "gn:country_code":"BD",
    "gn:dem":76,
    "gn:feature_class":"P",
    "gn:feature_code":"PPL",
    "gn:name":"B\u0101li\u0101d\u0101ngi",
    "gn:population":0,
    "gn:timezone":"Asia/Dhaka",
    "iso:country":"BD",
    "name:ben_x_preferred":[
        "B\u0101li\u0101d\u0101ngi"
    ],
    "wof:name":"Baliadangi",
    "wof:placetype":"locality"
},
  "geometry": {"coordinates":[88.65104000000002,26.37363],"type":"Point"}
}