{
  "type": "Feature",
  "properties": {
    "gn:admin1_code":"H",
    "gn:admin2_code":"3072.0",
    "gn:admin3_code":"307283.0",
    "gn:admin4_code":"30728331.0",
    "gn:asciiname":"Basati Kandarpa",
    "gn:country_code":"BD",
    "gn:dem":15,
    "gn:feature_class":"P",
    "gn:feature_code":"PPL",
    "gn:name":"B\u0101s\u0101ti Kandarpa",
    "gn:population":0,
    "gn:timezone":"Asia/Dhaka",
    "iso:country":"BD",
    "wof:name":"Basati Kandarpa",
    "wof:placetype":"locality"
},
  "geometry": {"coordinates":[90.67512000000001,24.93095],"type":"Point"}
}