{
  "type": "Feature",
  "properties": {
    "gn:admin1_code":"82",
    "gn:admin2_code":"4050.0",
    "gn:admin3_code":"405079.0",
    "gn:admin4_code":"40507925.0",
    "gn:asciiname":"Dhaka Jhalpara",
    "gn:country_code":"BD",
    "gn:dem":19,
    "gn:feature_class":"P",
    "gn:feature_code":"PPL",
    "gn:name":"Dh\u0101k\u0101 Jh\u0101lp\u0101ra",
    "gn:population":0,
    "gn:timezone":"Asia/Dhaka",
    "iso:country":"BD",
    "name:ben_x_preferred":[
        "Dh\u0101k\u0101 Jh\u0101lp\u0101ra"
    ],
    "wof:name":"Dhaka Jhalpara",
    "wof:placetype":"locality"
},
  "geometry": {"coordinates":[89.08196,23.89425],"type":"Point"}
}