{
  "type": "Feature",
  "properties": {
    "gn:admin1_code":"87",
    "gn:admin2_code":"5573",
    "gn:admin3_code":"557345.0",
    "gn:admin4_code":"55734508.0",
    "gn:asciiname":"Sat Ani Sherpur",
    "gn:country_code":"BD",
    "gn:dem":40,
    "gn:feature_class":"P",
    "gn:feature_code":"PPL",
    "gn:name":"S\u0101t \u0100ni Sherpur",
    "gn:population":0,
    "gn:timezone":"Asia/Dhaka",
    "iso:country":"BD",
    "name:ben_x_preferred":[
        "S\u0101t \u0100ni Sherpur"
    ],
    "wof:name":"Sat Ani Sherpur",
    "wof:placetype":"locality"
},
  "geometry": {"coordinates":[89.14249000000002,25.88945],"type":"Point"}
}