{
  "type": "Feature",
  "properties": {
    "gn:admin1_code":"H",
    "gn:admin2_code":"3061.0",
    "gn:admin3_code":"306123.0",
    "gn:admin4_code":"30612385.0",
    "gn:asciiname":"Chitratia",
    "gn:country_code":"BD",
    "gn:dem":15,
    "gn:feature_class":"P",
    "gn:feature_code":"PPL",
    "gn:name":"Chitr\u0101tia",
    "gn:population":0,
    "gn:timezone":"Asia/Dhaka",
    "iso:country":"BD",
    "name:und_x_variant":[
        "Chitaratia",
        "Chitr\u0101tia"
    ],
    "wof:name":"Chitratia",
    "wof:placetype":"locality"
},
  "geometry": {"coordinates":[90.54515000000001,24.87816],"type":"Point"}
}