{
  "type": "Feature",
  "properties": {
    "gn:admin1_code":"H",
    "gn:admin2_code":"3089",
    "gn:admin3_code":"308967.0",
    "gn:admin4_code":"30896785.0",
    "gn:asciiname":"Singua",
    "gn:country_code":"BD",
    "gn:dem":21,
    "gn:feature_class":"P",
    "gn:feature_code":"PPL",
    "gn:name":"Singua",
    "gn:population":0,
    "gn:timezone":"Asia/Dhaka",
    "iso:country":"BD",
    "wof:name":"Singua",
    "wof:placetype":"locality"
},
  "geometry": {"coordinates":[90.20088,24.99333],"type":"Point"}
}