{
  "type": "Feature",
  "properties": {
    "gn:admin1_code":"87",
    "gn:admin2_code":"5527.0",
    "gn:admin3_code":"552730.0",
    "gn:admin4_code":"55273039.0",
    "gn:asciiname":"Bhiail",
    "gn:country_code":"BD",
    "gn:dem":37,
    "gn:feature_class":"P",
    "gn:feature_code":"PPL",
    "gn:name":"Bhi\u0101il",
    "gn:population":0,
    "gn:timezone":"Asia/Dhaka",
    "iso:country":"BD",
    "name:ben_x_preferred":[
        "Bhi\u0101il"
    ],
    "wof:name":"Bhiail",
    "wof:placetype":"locality"
},
  "geometry": {"coordinates":[88.78072,25.59346],"type":"Point"}
}