{
  "type": "Feature",
  "properties": {
    "gn:admin1_code":"H",
    "gn:admin2_code":"3072.0",
    "gn:admin3_code":"307274.0",
    "gn:admin4_code":"30727407.0",
    "gn:asciiname":"Deopur",
    "gn:country_code":"BD",
    "gn:dem":13,
    "gn:feature_class":"P",
    "gn:feature_code":"PPL",
    "gn:name":"Deopur",
    "gn:population":0,
    "gn:timezone":"Asia/Dhaka",
    "iso:country":"BD",
    "name:und_x_variant":[
        "Debpur"
    ],
    "wof:name":"Deopur",
    "wof:placetype":"locality"
},
  "geometry": {"coordinates":[90.76476,24.84651],"type":"Point"}
}