{
  "type": "Feature",
  "properties": {
    "gn:admin1_code":"83",
    "gn:admin2_code":"5010.0",
    "gn:admin3_code":"501094.0",
    "gn:admin4_code":"50109455.0",
    "gn:asciiname":"Bahelagari",
    "gn:country_code":"BD",
    "gn:dem":23,
    "gn:feature_class":"P",
    "gn:feature_code":"PPL",
    "gn:name":"Bahel\u0101g\u0101ri",
    "gn:population":0,
    "gn:timezone":"Asia/Dhaka",
    "iso:country":"BD",
    "wof:name":"Bahelagari",
    "wof:placetype":"locality"
},
  "geometry": {"coordinates":[89.19799,24.9494],"type":"Point"}
}