{
  "type": "Feature",
  "properties": {
    "gn:admin1_code":"83",
    "gn:asciiname":"Kalpani",
    "gn:country_code":"BD",
    "gn:dem":25,
    "gn:feature_class":"P",
    "gn:feature_code":"PPL",
    "gn:name":"Kalpani",
    "gn:population":0,
    "gn:timezone":"Asia/Dhaka",
    "iso:country":"BD",
    "name:ben_x_preferred":[
        "Kalpani"
    ],
    "wof:name":"Kalpani",
    "wof:placetype":"locality"
},
  "geometry": {"coordinates":[89.54558,25.16791],"type":"Point"}
}