{
  "type": "Feature",
  "properties": {
    "gn:admin1_code":"87",
    "gn:admin2_code":"5585",
    "gn:admin3_code":"558558.0",
    "gn:admin4_code":"55855883.0",
    "gn:asciiname":"Krishnanagar",
    "gn:country_code":"BD",
    "gn:dem":38,
    "gn:feature_class":"P",
    "gn:feature_code":"PPL",
    "gn:name":"Krishnanagar",
    "gn:population":0,
    "gn:timezone":"Asia/Dhaka",
    "iso:country":"BD",
    "name:ara_x_preferred":[
        "\u0643\u0631\u064a\u0634\u0646\u0627\u0646\u062c\u0627\u0631"
    ],
    "name:ben_x_preferred":[
        "Krishnanagar"
    ],
    "name:deu_x_preferred":[
        "Krishnanagar"
    ],
    "name:fas_x_preferred":[
        "\u06a9\u0631\u06cc\u0634\u0646\u0627\u0646\u06af\u0627\u0631"
    ],
    "name:heb_x_preferred":[
        "\u05e7\u05e8\u05d9\u05e9\u05e0\u05e0\u05d0\u05d2\u05e8"
    ],
    "name:hun_x_preferred":[
        "Krishnanagar"
    ],
    "name:ind_x_preferred":[
        "Krishnanagar"
    ],
    "name:kor_x_preferred":[
        "\ud06c\ub9ac\uc288\ub098\uac00\ub974"
    ],
    "name:por_x_preferred":[
        "Krishnanagar"
    ],
    "name:tur_x_preferred":[
        "Krishnanagar"
    ],
    "wof:name":"Krishnanagar",
    "wof:placetype":"locality"
},
  "geometry": {"coordinates":[89.14053,25.5983],"type":"Point"}
}