{
  "type": "Feature",
  "properties": {
    "gn:admin1_code":"83",
    "gn:asciiname":"Sapmara",
    "gn:country_code":"BD",
    "gn:dem":26,
    "gn:feature_class":"P",
    "gn:feature_code":"PPL",
    "gn:name":"S\u0101pm\u0101ra",
    "gn:population":0,
    "gn:timezone":"Asia/Dhaka",
    "iso:country":"BD",
    "name:ben_x_preferred":[
        "S\u0101pm\u0101ra"
    ],
    "wof:name":"Sapmara",
    "wof:placetype":"locality"
},
  "geometry": {"coordinates":[89.32514,25.15353],"type":"Point"}
}