{
  "type": "Feature",
  "properties": {
    "gn:admin1_code":"81",
    "gn:admin2_code":"3035.0",
    "gn:admin3_code":"303543.0",
    "gn:admin4_code":"30354340.0",
    "gn:asciiname":"Hirankandi",
    "gn:country_code":"BD",
    "gn:dem":10,
    "gn:feature_class":"P",
    "gn:feature_code":"PPL",
    "gn:name":"Hirank\u0101ndi",
    "gn:population":0,
    "gn:timezone":"Asia/Dhaka",
    "iso:country":"BD",
    "name:und_x_variant":[
        "Hiron Kandi",
        "Hirank\u0101ndi"
    ],
    "wof:name":"Hirankandi",
    "wof:placetype":"locality"
},
  "geometry": {"coordinates":[89.76318000000001,23.2611],"type":"Point"}
}