{
  "type": "Feature",
  "properties": {
    "gn:admin1_code":"82",
    "gn:admin2_code":"4041.0",
    "gn:admin3_code":"404147.0",
    "gn:admin4_code":"40414777.0",
    "gn:asciiname":"Katamara",
    "gn:country_code":"BD",
    "gn:dem":13,
    "gn:feature_class":"P",
    "gn:feature_code":"PPL",
    "gn:name":"K\u0101t\u0101m\u0101ra",
    "gn:population":0,
    "gn:timezone":"Asia/Dhaka",
    "iso:country":"BD",
    "name:ben_x_preferred":[
        "K\u0101t\u0101m\u0101ra"
    ],
    "wof:name":"Katamara",
    "wof:placetype":"locality"
},
  "geometry": {"coordinates":[89.21115999999998,23.30937],"type":"Point"}
}