{
  "type": "Feature",
  "properties": {
    "gn:admin1_code":"81",
    "gn:admin2_code":"3059.0",
    "gn:admin3_code":"305944.0",
    "gn:admin4_code":"30594423.0",
    "gn:asciiname":"Dhaidia",
    "gn:country_code":"BD",
    "gn:dem":0,
    "gn:feature_class":"P",
    "gn:feature_code":"PPL",
    "gn:name":"Dh\u0101idia",
    "gn:population":0,
    "gn:timezone":"Asia/Dhaka",
    "iso:country":"BD",
    "wof:name":"Dhaidia",
    "wof:placetype":"locality"
},
  "geometry": {"coordinates":[90.3925,23.44612],"type":"Point"}
}