{
  "type": "Feature",
  "properties": {
    "gn:admin1_code":"82",
    "gn:admin2_code":"4001.0",
    "gn:admin3_code":"400156.0",
    "gn:admin4_code":"40015628.0",
    "gn:asciiname":"Chunkhola",
    "gn:country_code":"BD",
    "gn:dem":11,
    "gn:feature_class":"P",
    "gn:feature_code":"PPL",
    "gn:name":"Chunkhola",
    "gn:population":0,
    "gn:timezone":"Asia/Dhaka",
    "iso:country":"BD",
    "wof:name":"Chunkhola",
    "wof:placetype":"locality"
},
  "geometry": {"coordinates":[89.75963,22.96265],"type":"Point"}
}