{
  "type": "Feature",
  "properties": {
    "gn:admin1_code":"82",
    "gn:admin2_code":"4050.0",
    "gn:admin3_code":"405039.0",
    "gn:admin4_code":"40503933.0",
    "gn:asciiname":"Daperpara",
    "gn:country_code":"BD",
    "gn:dem":21,
    "gn:feature_class":"P",
    "gn:feature_code":"PPL",
    "gn:name":"Daperp\u0101ra",
    "gn:population":0,
    "gn:timezone":"Asia/Dhaka",
    "iso:country":"BD",
    "name:ben_x_preferred":[
        "Daperp\u0101ra"
    ],
    "wof:name":"Daperpara",
    "wof:placetype":"locality"
},
  "geometry": {"coordinates":[88.82323000000002,24.01557],"type":"Point"}
}