{
  "type": "Feature",
  "properties": {
    "gn:admin1_code":"82",
    "gn:admin2_code":"4057.0",
    "gn:admin3_code":"405747.0",
    "gn:admin4_code":"40574731.0",
    "gn:asciiname":"Malsadaha",
    "gn:country_code":"BD",
    "gn:dem":20,
    "gn:feature_class":"P",
    "gn:feature_code":"PPL",
    "gn:name":"M\u0101ls\u0101daha",
    "gn:population":0,
    "gn:timezone":"Asia/Dhaka",
    "iso:country":"BD",
    "name:ben_x_preferred":[
        "M\u0101ls\u0101daha"
    ],
    "wof:name":"Malsadaha",
    "wof:placetype":"locality"
},
  "geometry": {"coordinates":[88.76281999999998,23.82172000000001],"type":"Point"}
}