{
  "type": "Feature",
  "properties": {
    "gn:admin1_code":"H",
    "gn:admin2_code":"3061.0",
    "gn:admin3_code":"306123.0",
    "gn:admin4_code":"30612349.0",
    "gn:asciiname":"Dhitpur",
    "gn:country_code":"BD",
    "gn:dem":16,
    "gn:feature_class":"P",
    "gn:feature_code":"PPL",
    "gn:name":"Dhitpur",
    "gn:population":0,
    "gn:timezone":"Asia/Dhaka",
    "iso:country":"BD",
    "wof:name":"Dhitpur",
    "wof:placetype":"locality"
},
  "geometry": {"coordinates":[90.57398999999999,24.81654],"type":"Point"}
}