{
  "type": "Feature",
  "properties": {
    "gn:admin1_code":"84",
    "gn:admin2_code":"2013",
    "gn:admin3_code":"201345.0",
    "gn:admin4_code":"20134541.0",
    "gn:asciiname":"Subhan",
    "gn:country_code":"BD",
    "gn:dem":15,
    "gn:feature_class":"P",
    "gn:feature_code":"PPL",
    "gn:name":"Subhan",
    "gn:population":0,
    "gn:timezone":"Asia/Dhaka",
    "iso:country":"BD",
    "name:und_x_variant":[
        "Sobhanpur",
        "Sobh\u0101n",
        "Subhan"
    ],
    "name:urd_x_preferred":[
        "\u0633\u0628\u062d\u0627\u0646"
    ],
    "wof:name":"Subhan",
    "wof:placetype":"locality"
},
  "geometry": {"coordinates":[90.70549,23.17748],"type":"Point"}
}