{
  "type": "Feature",
  "properties": {
    "gn:admin1_code":"84",
    "gn:admin2_code":"2019.0",
    "gn:admin3_code":"201927.0",
    "gn:admin4_code":"20192763.0",
    "gn:asciiname":"Barimura",
    "gn:country_code":"BD",
    "gn:dem":11,
    "gn:feature_class":"P",
    "gn:feature_code":"PPL",
    "gn:name":"Barimura",
    "gn:population":0,
    "gn:timezone":"Asia/Dhaka",
    "iso:country":"BD",
    "wof:name":"Barimura",
    "wof:placetype":"locality"
},
  "geometry": {"coordinates":[90.92504,23.41721],"type":"Point"}
}