{
  "type": "Feature",
  "properties": {
    "gn:admin1_code":"84",
    "gn:admin2_code":"2046.0",
    "gn:admin3_code":"204677.0",
    "gn:admin4_code":"20467738.0",
    "gn:asciiname":"Biswarambari",
    "gn:country_code":"BD",
    "gn:dem":97,
    "gn:feature_class":"P",
    "gn:feature_code":"PPL",
    "gn:name":"Biswar\u0101mb\u0101ri",
    "gn:population":0,
    "gn:timezone":"Asia/Dhaka",
    "iso:country":"BD",
    "wof:name":"Biswarambari",
    "wof:placetype":"locality"
},
  "geometry": {"coordinates":[91.96477,23.29729],"type":"Point"}
}