{
  "type": "Feature",
  "properties": {
    "gn:admin1_code":"81",
    "gn:admin2_code":"3026.0",
    "gn:admin3_code":"302614.0",
    "gn:admin4_code":"30261435.0",
    "gn:asciiname":"Hajipur",
    "gn:country_code":"BD",
    "gn:dem":14,
    "gn:feature_class":"P",
    "gn:feature_code":"PPL",
    "gn:name":"H\u0101jipur",
    "gn:population":0,
    "gn:timezone":"Asia/Dhaka",
    "iso:country":"BD",
    "name:und_x_variant":[
        "Hazipur",
        "H\u0101jipur"
    ],
    "wof:name":"Hajipur",
    "wof:placetype":"locality"
},
  "geometry": {"coordinates":[90.22423000000001,23.92519],"type":"Point"}
}