{
  "type": "Feature",
  "properties": {
    "gn:admin1_code":"87",
    "gn:admin2_code":"5527",
    "gn:admin3_code":"552717.0",
    "gn:admin4_code":"55271719.0",
    "gn:asciiname":"Pakura",
    "gn:country_code":"BD",
    "gn:dem":36,
    "gn:feature_class":"P",
    "gn:feature_code":"PPL",
    "gn:name":"P\u0101kura",
    "gn:population":0,
    "gn:timezone":"Asia/Dhaka",
    "iso:country":"BD",
    "name:ben_x_preferred":[
        "P\u0101kura"
    ],
    "wof:name":"Pakura",
    "wof:placetype":"locality"
},
  "geometry": {"coordinates":[88.47289000000001,25.64987],"type":"Point"}
}