{
  "type": "Feature",
  "properties": {
    "gn:admin1_code":"81",
    "gn:admin2_code":"3059.0",
    "gn:admin3_code":"305924.0",
    "gn:admin4_code":"30592421.0",
    "gn:asciiname":"Haglakandi",
    "gn:country_code":"BD",
    "gn:dem":9,
    "gn:feature_class":"P",
    "gn:feature_code":"PPL",
    "gn:name":"H\u0101gl\u0101k\u0101ndi",
    "gn:population":0,
    "gn:timezone":"Asia/Dhaka",
    "iso:country":"BD",
    "wof:name":"Haglakandi",
    "wof:placetype":"locality"
},
  "geometry": {"coordinates":[90.64446,23.53718],"type":"Point"}
}