{
  "type": "Feature",
  "properties": {
    "gn:admin1_code":"84",
    "gn:admin2_code":"2084.0",
    "gn:admin3_code":"208425.0",
    "gn:admin4_code":"20842557.0",
    "gn:asciiname":"Mitiyachari",
    "gn:country_code":"BD",
    "gn:dem":62,
    "gn:feature_class":"P",
    "gn:feature_code":"PPL",
    "gn:name":"Mitiy\u0101chari",
    "gn:population":0,
    "gn:timezone":"Asia/Dhaka",
    "iso:country":"BD",
    "name:ben_x_preferred":[
        "Mitiy\u0101chari"
    ],
    "name:ben_x_variant":[
        "Mity\u0101chari"
    ],
    "wof:name":"Mitiyachari",
    "wof:placetype":"locality"
},
  "geometry": {"coordinates":[92.06007,22.6256],"type":"Point"}
}