{
  "type": "Feature",
  "properties": {
    "gn:admin1_code":"85",
    "gn:admin2_code":"1009.0",
    "gn:admin3_code":"100921.0",
    "gn:admin4_code":"10092147.0",
    "gn:asciiname":"Char Kalidas",
    "gn:country_code":"BD",
    "gn:dem":9,
    "gn:feature_class":"P",
    "gn:feature_code":"PPL",
    "gn:name":"Char K\u0101lid\u0101s",
    "gn:population":0,
    "gn:timezone":"Asia/Dhaka",
    "iso:country":"BD",
    "name:ben_x_preferred":[
        "Char K\u0101lid\u0101s"
    ],
    "wof:name":"Char Kalidas",
    "wof:placetype":"locality"
},
  "geometry": {"coordinates":[90.74221,22.4221],"type":"Point"}
}