{
  "type": "Feature",
  "properties": {
    "gn:admin1_code":"81",
    "gn:admin2_code":"3035.0",
    "gn:admin3_code":"303532.0",
    "gn:admin4_code":"30353212.0",
    "gn:asciiname":"Chandra Dighalia",
    "gn:country_code":"BD",
    "gn:dem":8,
    "gn:feature_class":"P",
    "gn:feature_code":"PPL",
    "gn:name":"Chandra Dighalia",
    "gn:population":0,
    "gn:timezone":"Asia/Dhaka",
    "iso:country":"BD",
    "name:ben_x_preferred":[
        "Chandra Dighalia"
    ],
    "wof:name":"Chandra Dighalia",
    "wof:placetype":"locality"
},
  "geometry": {"coordinates":[89.77043,23.06559],"type":"Point"}
}