{
  "type": "Feature",
  "properties": {
    "gn:admin1_code":"83",
    "gn:admin2_code":"5064",
    "gn:admin3_code":"506469.0",
    "gn:admin4_code":"50646984.0",
    "gn:asciiname":"Jhajira",
    "gn:country_code":"BD",
    "gn:dem":27,
    "gn:feature_class":"P",
    "gn:feature_code":"PPL",
    "gn:name":"Jhajira",
    "gn:population":0,
    "gn:timezone":"Asia/Dhaka",
    "iso:country":"BD",
    "name:ben_x_preferred":[
        "Jhajira"
    ],
    "name:ben_x_variant":[
        "Jh\u0101njhira"
    ],
    "name:und_x_variant":[
        "Jhanjira"
    ],
    "wof:name":"Jhajira",
    "wof:placetype":"locality"
},
  "geometry": {"coordinates":[88.57443000000001,24.79129],"type":"Point"}
}