{
  "type": "Feature",
  "properties": {
    "gn:admin1_code":"82",
    "gn:admin2_code":"4087",
    "gn:admin3_code":"408704.0",
    "gn:admin4_code":"40870443.0",
    "gn:asciiname":"Tentulia",
    "gn:country_code":"BD",
    "gn:dem":7,
    "gn:feature_class":"P",
    "gn:feature_code":"PPL",
    "gn:name":"Tentulia",
    "gn:population":0,
    "gn:timezone":"Asia/Dhaka",
    "iso:country":"BD",
    "wof:name":"Tentulia",
    "wof:placetype":"locality"
},
  "geometry": {"coordinates":[89.21901,22.57023],"type":"Point"}
}