{
  "type": "Feature",
  "properties": {
    "gn:admin1_code":"83",
    "gn:admin2_code":"5081.0",
    "gn:admin3_code":"508153.0",
    "gn:admin4_code":"50815381.0",
    "gn:asciiname":"Belgharia Hat",
    "gn:country_code":"BD",
    "gn:dem":20,
    "gn:feature_class":"P",
    "gn:feature_code":"PPL",
    "gn:name":"Belgharia H\u0101t",
    "gn:population":0,
    "gn:timezone":"Asia/Dhaka",
    "iso:country":"BD",
    "name:ben_x_preferred":[
        "Belgharia H\u0101t"
    ],
    "wof:name":"Belgharia Hat",
    "wof:placetype":"locality"
},
  "geometry": {"coordinates":[88.67334,24.63021],"type":"Point"}
}