{
  "type": "Feature",
  "properties": {
    "gn:admin1_code":"83",
    "gn:admin2_code":"5064",
    "gn:admin3_code":"506469.0",
    "gn:admin4_code":"50646931.0",
    "gn:asciiname":"Kistapur",
    "gn:country_code":"BD",
    "gn:dem":23,
    "gn:feature_class":"P",
    "gn:feature_code":"PPL",
    "gn:name":"Kistapur",
    "gn:population":0,
    "gn:timezone":"Asia/Dhaka",
    "iso:country":"BD",
    "name:ben_x_preferred":[
        "Kistapur"
    ],
    "name:ben_x_variant":[
        "Krishnapur"
    ],
    "wof:name":"Kistapur",
    "wof:placetype":"locality"
},
  "geometry": {"coordinates":[88.64749,24.90073],"type":"Point"}
}