{
  "type": "Feature",
  "properties": {
    "gn:admin1_code":"H",
    "gn:admin2_code":"3061.0",
    "gn:admin3_code":"306122.0",
    "gn:admin4_code":"30612288.0",
    "gn:asciiname":"Bade Bashia",
    "gn:country_code":"BD",
    "gn:dem":14,
    "gn:feature_class":"P",
    "gn:feature_code":"PPL",
    "gn:name":"Bade B\u0101shia",
    "gn:population":0,
    "gn:timezone":"Asia/Dhaka",
    "iso:country":"BD",
    "name:und_x_variant":[
        "Bade B\u0101shia",
        "B\u0101de B\u0101sia"
    ],
    "wof:name":"Bade Bashia",
    "wof:placetype":"locality"
},
  "geometry": {"coordinates":[90.62390000000001,24.32965],"type":"Point"}
}