{
  "type": "Feature",
  "properties": {
    "gn:admin1_code":"84",
    "gn:admin2_code":"2075.0",
    "gn:admin3_code":"207587.0",
    "gn:admin4_code":"20758740.0",
    "gn:asciiname":"Bobarkandi",
    "gn:country_code":"BD",
    "gn:dem":12,
    "gn:feature_class":"P",
    "gn:feature_code":"PPL",
    "gn:name":"Bobark\u0101ndi",
    "gn:population":0,
    "gn:timezone":"Asia/Dhaka",
    "iso:country":"BD",
    "wof:name":"Bobarkandi",
    "wof:placetype":"locality"
},
  "geometry": {"coordinates":[90.97375,22.86682],"type":"Point"}
}