{
  "type": "Feature",
  "properties": {
    "gn:admin1_code":"87",
    "gn:admin2_code":"5527",
    "gn:admin3_code":"552712.0",
    "gn:admin4_code":"55271217.0",
    "gn:asciiname":"Nagri Sagri",
    "gn:country_code":"BD",
    "gn:dem":57,
    "gn:feature_class":"P",
    "gn:feature_code":"PPL",
    "gn:name":"Nagri S\u0101gri",
    "gn:population":0,
    "gn:timezone":"Asia/Dhaka",
    "iso:country":"BD",
    "name:ben_x_preferred":[
        "Nagri S\u0101gri"
    ],
    "wof:name":"Nagri Sagri",
    "wof:placetype":"locality"
},
  "geometry": {"coordinates":[88.66719999999999,25.96876],"type":"Point"}
}