{
  "type": "Feature",
  "properties": {
    "gn:admin1_code":"87",
    "gn:admin2_code":"5585",
    "gn:admin3_code":"558558.0",
    "gn:admin4_code":"55855816.0",
    "gn:asciiname":"Sherpur",
    "gn:country_code":"BD",
    "gn:dem":33,
    "gn:feature_class":"P",
    "gn:feature_code":"PPL",
    "gn:name":"Sherpur",
    "gn:population":0,
    "gn:timezone":"Asia/Dhaka",
    "iso:country":"BD",
    "name:ceb_x_preferred":[
        "Sherpur"
    ],
    "name:nld_x_preferred":[
        "Sherpur"
    ],
    "name:rus_x_preferred":[
        "\u0428\u0435\u0440\u043f\u0443\u0440"
    ],
    "name:swe_x_preferred":[
        "Sherpur"
    ],
    "wof:name":"Sherpur",
    "wof:placetype":"locality"
},
  "geometry": {"coordinates":[89.33445999999998,25.57317],"type":"Point"}
}