{
  "type": "Feature",
  "properties": {
    "gn:admin1_code":"81",
    "gn:admin2_code":"3048",
    "gn:admin3_code":"304845.0",
    "gn:admin4_code":"30484576.0",
    "gn:asciiname":"Kareha",
    "gn:country_code":"BD",
    "gn:dem":16,
    "gn:feature_class":"P",
    "gn:feature_code":"PPL",
    "gn:name":"Kareha",
    "gn:population":0,
    "gn:timezone":"Asia/Dhaka",
    "iso:country":"BD",
    "wof:name":"Kareha",
    "wof:placetype":"locality"
},
  "geometry": {"coordinates":[90.72629000000001,24.2658],"type":"Point"}
}