{
  "type": "Feature",
  "properties": {
    "gn:admin1_code":"82",
    "gn:admin2_code":"4057.0",
    "gn:admin3_code":"405787.0",
    "gn:admin4_code":"40578795.0",
    "gn:asciiname":"Patkelpota",
    "gn:country_code":"BD",
    "gn:dem":19,
    "gn:feature_class":"P",
    "gn:feature_code":"PPL",
    "gn:name":"P\u0101tkelpota",
    "gn:population":0,
    "gn:timezone":"Asia/Dhaka",
    "iso:country":"BD",
    "name:ben_x_preferred":[
        "P\u0101tkelpota"
    ],
    "wof:name":"Patkelpota",
    "wof:placetype":"locality"
},
  "geometry": {"coordinates":[88.74699,23.72114],"type":"Point"}
}