{
  "type": "Feature",
  "properties": {
    "gn:admin1_code":"84",
    "gn:admin2_code":"2022.0",
    "gn:admin3_code":"202224.0",
    "gn:admin4_code":"20222459.0",
    "gn:asciiname":"Hariardeil",
    "gn:country_code":"BD",
    "gn:dem":11,
    "gn:feature_class":"P",
    "gn:feature_code":"PPL",
    "gn:name":"Hariardeil",
    "gn:population":0,
    "gn:timezone":"Asia/Dhaka",
    "iso:country":"BD",
    "name:ben_x_preferred":[
        "Hariardeil"
    ],
    "wof:name":"Hariardeil",
    "wof:placetype":"locality"
},
  "geometry": {"coordinates":[91.9958,21.46648],"type":"Point"}
}