{
  "type": "Feature",
  "properties": {
    "gn:admin1_code":"81",
    "gn:admin2_code":"3086",
    "gn:admin3_code":"308665.0",
    "gn:admin4_code":"30866537.0",
    "gn:asciiname":"Kalargaon",
    "gn:country_code":"BD",
    "gn:dem":13,
    "gn:feature_class":"P",
    "gn:feature_code":"PPL",
    "gn:name":"Kal\u0101rgaon",
    "gn:population":0,
    "gn:timezone":"Asia/Dhaka",
    "iso:country":"BD",
    "wof:name":"Kalargaon",
    "wof:placetype":"locality"
},
  "geometry": {"coordinates":[90.47931,23.26699],"type":"Point"}
}