{
  "type": "Feature",
  "properties": {
    "gn:admin1_code":"87",
    "gn:admin2_code":"5594.0",
    "gn:admin3_code":"559482.0",
    "gn:admin4_code":"55948260.0",
    "gn:asciiname":"Habibpur",
    "gn:country_code":"BD",
    "gn:dem":52,
    "gn:feature_class":"P",
    "gn:feature_code":"PPL",
    "gn:name":"H\u0101bibpur",
    "gn:population":0,
    "gn:timezone":"Asia/Dhaka",
    "iso:country":"BD",
    "name:ben_x_preferred":[
        "H\u0101bibpur"
    ],
    "wof:name":"Habibpur",
    "wof:placetype":"locality"
},
  "geometry": {"coordinates":[88.43552,25.94789],"type":"Point"}
}