{
  "type": "Feature",
  "properties": {
    "gn:admin1_code":"87",
    "gn:admin2_code":"5594.0",
    "gn:admin3_code":"559482.0",
    "gn:admin4_code":"55948260.0",
    "gn:asciiname":"Habibpur",
    "gn:country_code":"BD",
    "gn:dem":52,
    "gn:feature_class":"P",
    "gn:feature_code":"PPL",
    "gn:name":"H\u0101bibpur",
    "gn:population":0,
    "gn:timezone":"Asia/Dhaka",
    "iso:country":"BD",
    "name:ben_x_preferred":[
        "H\u0101bibpur"
    ],
    "name:ben_x_variant":[
        "\u09b9\u09be\u09ac\u09bf\u09ac\u09aa\u09c1\u09b0"
    ],
    "name:bpy_x_preferred":[
        "\u09b9\u09be\u09ac\u09bf\u09ac\u09aa\u09c1\u09b0"
    ],
    "name:ita_x_preferred":[
        "Habibpur"
    ],
    "name:msa_x_preferred":[
        "Habibpur"
    ],
    "name:new_x_preferred":[
        "\u0939\u092c\u093f\u092c\u092a\u0941\u0930"
    ],
    "name:nld_x_preferred":[
        "Habibpur"
    ],
    "name:por_x_preferred":[
        "Habibpur"
    ],
    "name:tam_x_preferred":[
        "\u0b85\u0baa\u0bbf\u0baa\u0bcd\u0baa\u0bc2\u0bb0\u0bcd"
    ],
    "name:urd_x_preferred":[
        "\u062d\u0628\u06cc\u0628 \u067e\u0648\u0631"
    ],
    "name:vie_x_preferred":[
        "Habibpur"
    ],
    "name:zho_x_preferred":[
        "\u54c8\u6bd4\u5e03\u666e\u5c14"
    ],
    "wof:name":"Habibpur",
    "wof:placetype":"locality"
},
  "geometry": {"coordinates":[88.43552,25.94789],"type":"Point"}
}