{
  "type": "Feature",
  "properties": {
    "gn:admin1_code":"85",
    "gn:admin2_code":"1042",
    "gn:admin3_code":"104243.0",
    "gn:admin4_code":"10424379.0",
    "gn:asciiname":"Marichbunia",
    "gn:country_code":"BD",
    "gn:dem":7,
    "gn:feature_class":"P",
    "gn:feature_code":"PPL",
    "gn:name":"Marichbunia",
    "gn:population":0,
    "gn:timezone":"Asia/Dhaka",
    "iso:country":"BD",
    "name:ben_x_preferred":[
        "Marichbunia"
    ],
    "name:ben_x_variant":[
        "Marichbania"
    ],
    "wof:name":"Marichbunia",
    "wof:placetype":"locality"
},
  "geometry": {"coordinates":[90.05539,22.36804],"type":"Point"}
}