{
  "type": "Feature",
  "properties": {
    "gn:admin1_code":"82",
    "gn:admin2_code":"4044.0",
    "gn:admin3_code":"404433.0",
    "gn:admin4_code":"40443347.0",
    "gn:asciiname":"Bara Baysa",
    "gn:country_code":"BD",
    "gn:dem":12,
    "gn:feature_class":"P",
    "gn:feature_code":"PPL",
    "gn:name":"Bara B\u0101ysa",
    "gn:population":0,
    "gn:timezone":"Asia/Dhaka",
    "iso:country":"BD",
    "name:ben_x_preferred":[
        "Bara B\u0101ysa"
    ],
    "wof:name":"Bara Baysa",
    "wof:placetype":"locality"
},
  "geometry": {"coordinates":[89.25034000000002,23.3986],"type":"Point"}
}