{
  "type": "Feature",
  "properties": {
    "gn:admin1_code":"87",
    "gn:admin2_code":"5552.0",
    "gn:admin3_code":"555270.0",
    "gn:admin4_code":"55527027.0",
    "gn:asciiname":"Dhara Kanta",
    "gn:country_code":"BD",
    "gn:dem":59,
    "gn:feature_class":"P",
    "gn:feature_code":"PPL",
    "gn:name":"Dhara Kanta",
    "gn:population":0,
    "gn:timezone":"Asia/Dhaka",
    "iso:country":"BD",
    "name:ben_x_preferred":[
        "Dhara Kanta"
    ],
    "wof:name":"Dhara Kanta",
    "wof:placetype":"locality"
},
  "geometry": {"coordinates":[89.06934,26.36078],"type":"Point"}
}