{
  "type": "Feature",
  "properties": {
    "gn:admin1_code":"82",
    "gn:admin2_code":"4050.0",
    "gn:admin3_code":"405015.0",
    "gn:admin4_code":"40501540.0",
    "gn:asciiname":"Laksmilnardia",
    "gn:country_code":"BD",
    "gn:dem":22,
    "gn:feature_class":"P",
    "gn:feature_code":"PPL",
    "gn:name":"Laksmilnardia",
    "gn:population":0,
    "gn:timezone":"Asia/Dhaka",
    "iso:country":"BD",
    "name:ben_x_preferred":[
        "Laksmilnardia"
    ],
    "wof:name":"Laksmilnardia",
    "wof:placetype":"locality"
},
  "geometry": {"coordinates":[88.98954000000001,23.99889],"type":"Point"}
}