{
  "type": "Feature",
  "properties": {
    "gn:admin1_code":"84",
    "gn:admin2_code":"2030.0",
    "gn:admin3_code":"203029.0",
    "gn:admin4_code":"20302951.0",
    "gn:asciiname":"Chandpur",
    "gn:country_code":"BD",
    "gn:dem":8,
    "gn:feature_class":"P",
    "gn:feature_code":"PPL",
    "gn:name":"Ch\u0101ndpur",
    "gn:population":0,
    "gn:timezone":"Asia/Dhaka",
    "iso:country":"BD",
    "name:ben_x_preferred":[
        "\u099a\u09be\u0981\u09a6\u09aa\u09c1\u09b0"
    ],
    "name:ceb_x_preferred":[
        "Chandpur"
    ],
    "name:deu_x_preferred":[
        "Chandpur"
    ],
    "name:ita_x_preferred":[
        "Chandpur"
    ],
    "name:nld_x_preferred":[
        "Chandpur"
    ],
    "name:pol_x_preferred":[
        "Chandpur"
    ],
    "name:rus_x_preferred":[
        "\u0427\u0430\u043d\u0434\u043f\u0443\u0440"
    ],
    "name:swe_x_preferred":[
        "Chandpur"
    ],
    "wof:name":"Chandpur",
    "wof:placetype":"locality"
},
  "geometry": {"coordinates":[91.43333,22.96667],"type":"Point"}
}