{
  "type": "Feature",
  "properties": {
    "gn:admin1_code":"81",
    "gn:admin2_code":"3035",
    "gn:admin3_code":"303558.0",
    "gn:admin4_code":"30355833.0",
    "gn:asciiname":"Palpara",
    "gn:country_code":"BD",
    "gn:dem":6,
    "gn:feature_class":"P",
    "gn:feature_code":"PPL",
    "gn:name":"P\u0101lp\u0101ra",
    "gn:population":0,
    "gn:timezone":"Asia/Dhaka",
    "iso:country":"BD",
    "name:ben_x_preferred":[
        "P\u0101lp\u0101ra"
    ],
    "wof:name":"Palpara",
    "wof:placetype":"locality"
},
  "geometry": {"coordinates":[89.83456,23.24523],"type":"Point"}
}