{
  "type": "Feature",
  "properties": {
    "gn:admin1_code":"82",
    "gn:admin2_code":"4087.0",
    "gn:admin3_code":"408747.0",
    "gn:admin4_code":"40874787.0",
    "gn:asciiname":"Chak Ramgobindapur",
    "gn:country_code":"BD",
    "gn:dem":3,
    "gn:feature_class":"P",
    "gn:feature_code":"PPL",
    "gn:name":"Chak R\u0101mgobindapur",
    "gn:population":0,
    "gn:timezone":"Asia/Dhaka",
    "iso:country":"BD",
    "wof:name":"Chak Ramgobindapur",
    "wof:placetype":"locality"
},
  "geometry": {"coordinates":[89.03333000000001,22.35],"type":"Point"}
}