{
  "type": "Feature",
  "properties": {
    "gn:admin1_code":"87",
    "gn:admin2_code":"5549",
    "gn:admin3_code":"554961.0",
    "gn:admin4_code":"55496106.0",
    "gn:asciiname":"Dhariarhat",
    "gn:country_code":"BD",
    "gn:dem":32,
    "gn:feature_class":"P",
    "gn:feature_code":"PPL",
    "gn:name":"Dh\u0101ri\u0101rh\u0101t",
    "gn:population":0,
    "gn:timezone":"Asia/Dhaka",
    "iso:country":"BD",
    "name:ben_x_preferred":[
        "Dh\u0101ri\u0101rh\u0101t"
    ],
    "wof:name":"Dhariarhat",
    "wof:placetype":"locality"
},
  "geometry": {"coordinates":[89.78322,25.98231],"type":"Point"}
}