{
  "type": "Feature",
  "properties": {
    "gn:admin1_code":"87",
    "gn:admin2_code":"5549",
    "gn:admin3_code":"554977.0",
    "gn:admin4_code":"55497721.0",
    "gn:asciiname":"Nilir Kuthir",
    "gn:country_code":"BD",
    "gn:dem":32,
    "gn:feature_class":"P",
    "gn:feature_code":"PPL",
    "gn:name":"Nilir Kuthir",
    "gn:population":0,
    "gn:timezone":"Asia/Dhaka",
    "iso:country":"BD",
    "name:ben_x_preferred":[
        "Nilir Kuthir"
    ],
    "wof:name":"Nilir Kuthir",
    "wof:placetype":"locality"
},
  "geometry": {"coordinates":[89.55998000000002,25.77099],"type":"Point"}
}