{
  "type": "Feature",
  "properties": {
    "gn:admin1_code":"85",
    "gn:admin2_code":"1079.0",
    "gn:admin3_code":"107958.0",
    "gn:admin4_code":"10795869.0",
    "gn:asciiname":"Mirukhalikhas",
    "gn:country_code":"BD",
    "gn:dem":5,
    "gn:feature_class":"P",
    "gn:feature_code":"PPL",
    "gn:name":"Mirukhalikhas",
    "gn:population":0,
    "gn:timezone":"Asia/Dhaka",
    "iso:country":"BD",
    "name:ben_x_preferred":[
        "Mirukhalikhas"
    ],
    "wof:name":"Mirukhalikhas",
    "wof:placetype":"locality"
},
  "geometry": {"coordinates":[89.98818,22.33661],"type":"Point"}
}