{
  "type": "Feature",
  "properties": {
    "gn:admin1_code":"83",
    "gn:asciiname":"Jankhur",
    "gn:country_code":"BD",
    "gn:dem":29,
    "gn:feature_class":"P",
    "gn:feature_code":"PPL",
    "gn:name":"Jankhur",
    "gn:population":0,
    "gn:timezone":"Asia/Dhaka",
    "iso:country":"BD",
    "name:ben_x_preferred":[
        "Jankhur"
    ],
    "wof:name":"Jankhur",
    "wof:placetype":"locality"
},
  "geometry": {"coordinates":[89.23421999999999,25.15665],"type":"Point"}
}