{
  "type": "Feature",
  "properties": {
    "gn:admin1_code":"84",
    "gn:admin2_code":"2015.0",
    "gn:admin3_code":"201561.0",
    "gn:admin4_code":"20156176.0",
    "gn:asciiname":"Gorankhain",
    "gn:country_code":"BD",
    "gn:dem":9,
    "gn:feature_class":"P",
    "gn:feature_code":"PPL",
    "gn:name":"Gorankh\u0101in",
    "gn:population":0,
    "gn:timezone":"Asia/Dhaka",
    "iso:country":"BD",
    "name:ben_x_preferred":[
        "Gorankh\u0101in"
    ],
    "wof:name":"Gorankhain",
    "wof:placetype":"locality"
},
  "geometry": {"coordinates":[91.91063,22.29835],"type":"Point"}
}