{
  "type": "Feature",
  "properties": {
    "gn:admin1_code":"83",
    "gn:admin2_code":"5064.0",
    "gn:admin3_code":"506450.0",
    "gn:admin4_code":"50645066.0",
    "gn:asciiname":"Akhera",
    "gn:country_code":"BD",
    "gn:dem":21,
    "gn:feature_class":"P",
    "gn:feature_code":"PPL",
    "gn:name":"Akhera",
    "gn:population":0,
    "gn:timezone":"Asia/Dhaka",
    "iso:country":"BD",
    "name:ben_x_preferred":[
        "Akhera"
    ],
    "name:ben_x_variant":[
        "Akhra"
    ],
    "wof:name":"Akhera",
    "wof:placetype":"locality"
},
  "geometry": {"coordinates":[88.77014,24.9058],"type":"Point"}
}