{
  "type": "Feature",
  "properties": {
    "gn:admin1_code":"83",
    "gn:admin2_code":"5038.0",
    "gn:admin3_code":"503861.0",
    "gn:admin4_code":"50386109.0",
    "gn:asciiname":"Dhamsunda",
    "gn:country_code":"BD",
    "gn:dem":26,
    "gn:feature_class":"P",
    "gn:feature_code":"PPL",
    "gn:name":"Dh\u0101msunda",
    "gn:population":0,
    "gn:timezone":"Asia/Dhaka",
    "iso:country":"BD",
    "wof:name":"Dhamsunda",
    "wof:placetype":"locality"
},
  "geometry": {"coordinates":[89.17276,24.97641],"type":"Point"}
}