{
  "type": "Feature",
  "properties": {
    "iso:country":"BD",
    "name:ben_x_preferred":[
        "S\u0101tkania"
    ],
    "qs:gn_country":"BD",
    "qs:gn_fcode":"PPL",
    "qs:gn_pop":52005,
    "qs:name":"Satkania",
    "qs:name_adm0":"Bangladesh",
    "qs:name_adm1":"Chittagong",
    "qs:photos":0,
    "qs:photos_1k":0,
    "qs:photos_9k":1,
    "qs:photos_9r":1,
    "qs:photos_all":1,
    "qs:photos_sr":0,
    "qs:placetype":"Town",
    "qs:pop_sr":"8",
    "qs:woe_adm0":23424759,
    "wof:name":"Satkania",
    "wof:placetype":"locality",
    "wof:population":52005
},
  "geometry": {"coordinates":[92.04955,22.07639],"type":"Point"}
}