{
  "type": "Feature",
  "properties": {
    "gn:admin1_code":"87",
    "gn:admin2_code":"5527.0",
    "gn:admin3_code":"552756.0",
    "gn:admin4_code":"55275663.0",
    "gn:asciiname":"Mathurapur",
    "gn:country_code":"BD",
    "gn:dem":46,
    "gn:feature_class":"P",
    "gn:feature_code":"PPL",
    "gn:name":"Mathur\u0101pur",
    "gn:population":0,
    "gn:timezone":"Asia/Dhaka",
    "iso:country":"BD",
    "name:ben_x_preferred":[
        "Mathur\u0101pur"
    ],
    "wof:name":"Mathurapur",
    "wof:placetype":"locality"
},
  "geometry": {"coordinates":[88.56719,25.81654],"type":"Point"}
}