{
  "type": "Feature",
  "properties": {
    "gn:admin1_code":"81",
    "gn:admin2_code":"3059",
    "gn:admin3_code":"305994.0",
    "gn:admin4_code":"30599439.0",
    "gn:asciiname":"Nayananda",
    "gn:country_code":"BD",
    "gn:dem":10,
    "gn:feature_class":"P",
    "gn:feature_code":"PPL",
    "gn:name":"Nay\u0101nanda",
    "gn:population":0,
    "gn:timezone":"Asia/Dhaka",
    "iso:country":"BD",
    "wof:name":"Nayananda",
    "wof:placetype":"locality"
},
  "geometry": {"coordinates":[90.45326,23.48997],"type":"Point"}
}