{
  "type": "Feature",
  "properties": {
    "gn:admin1_code":"82",
    "gn:asciiname":"Chandrailer Char",
    "gn:country_code":"BD",
    "gn:dem":9,
    "gn:feature_class":"P",
    "gn:feature_code":"PPL",
    "gn:name":"Chandr\u0101iler Char",
    "gn:population":0,
    "gn:timezone":"Asia/Dhaka",
    "iso:country":"BD",
    "name:ben_x_preferred":[
        "Chandr\u0101iler Char"
    ],
    "wof:name":"Chandrailer Char",
    "wof:placetype":"locality"
},
  "geometry": {"coordinates":[90.40678,22.22206],"type":"Point"}
}