{
  "type": "Feature",
  "properties": {
    "gn:admin1_code":"87",
    "gn:admin2_code":"5552.0",
    "gn:admin3_code":"555255.0",
    "gn:admin4_code":"55525583.0",
    "gn:asciiname":"Bairagi Kumar",
    "gn:country_code":"BD",
    "gn:dem":38,
    "gn:feature_class":"P",
    "gn:feature_code":"PPL",
    "gn:name":"Bair\u0101gi Kum\u0101r",
    "gn:population":0,
    "gn:timezone":"Asia/Dhaka",
    "iso:country":"BD",
    "name:ben_x_preferred":[
        "Bair\u0101gi Kum\u0101r"
    ],
    "wof:name":"Bairagi Kumar",
    "wof:placetype":"locality"
},
  "geometry": {"coordinates":[89.49123,25.8284],"type":"Point"}
}