{
  "type": "Feature",
  "properties": {
    "gn:admin1_code":"83",
    "gn:admin2_code":"5081",
    "gn:admin3_code":"508182.0",
    "gn:admin4_code":"50818213.0",
    "gn:asciiname":"Nandanpur",
    "gn:country_code":"BD",
    "gn:dem":19,
    "gn:feature_class":"P",
    "gn:feature_code":"PPL",
    "gn:name":"Nandanpur",
    "gn:population":0,
    "gn:timezone":"Asia/Dhaka",
    "iso:country":"BD",
    "name:ben_x_preferred":[
        "Nandanpur"
    ],
    "wof:name":"Nandanpur",
    "wof:placetype":"locality"
},
  "geometry": {"coordinates":[88.78830000000001,24.3928],"type":"Point"}
}