{
  "type": "Feature",
  "properties": {
    "gn:admin1_code":"84",
    "gn:admin2_code":"2019",
    "gn:admin3_code":"201937.0",
    "gn:admin4_code":"20193760.0",
    "gn:asciiname":"Kaikhakhali",
    "gn:country_code":"BD",
    "gn:dem":7,
    "gn:feature_class":"P",
    "gn:feature_code":"PPL",
    "gn:name":"K\u0101ikh\u0101kh\u0101li",
    "gn:population":0,
    "gn:timezone":"Asia/Dhaka",
    "iso:country":"BD",
    "wof:name":"Kaikhakhali",
    "wof:placetype":"locality"
},
  "geometry": {"coordinates":[90.74155,23.59262],"type":"Point"}
}