{
  "type": "Feature",
  "properties": {
    "gn:admin1_code":"82",
    "gn:admin2_code":"4055.0",
    "gn:admin3_code":"405557.0",
    "gn:admin4_code":"40555761.0",
    "gn:asciiname":"Durgapur",
    "gn:country_code":"BD",
    "gn:dem":15,
    "gn:feature_class":"P",
    "gn:feature_code":"PPL",
    "gn:name":"Durg\u0101pur",
    "gn:population":0,
    "gn:timezone":"Asia/Dhaka",
    "iso:country":"BD",
    "wof:name":"Durgapur",
    "wof:placetype":"locality"
},
  "geometry": {"coordinates":[89.48688,23.52306],"type":"Point"}
}