{
  "type": "Feature",
  "properties": {
    "gn:admin1_code":"81",
    "gn:admin2_code":"3048",
    "gn:admin3_code":"304849.0",
    "gn:admin4_code":"30484986.0",
    "gn:asciiname":"Salpamaria",
    "gn:country_code":"BD",
    "gn:dem":14,
    "gn:feature_class":"P",
    "gn:feature_code":"PPL",
    "gn:name":"Salpam\u0101ria",
    "gn:population":0,
    "gn:timezone":"Asia/Dhaka",
    "iso:country":"BD",
    "wof:name":"Salpamaria",
    "wof:placetype":"locality"
},
  "geometry": {"coordinates":[90.76836,24.41595],"type":"Point"}
}