{
  "type": "Feature",
  "properties": {
    "gn:admin1_code":"87",
    "gn:admin2_code":"5549",
    "gn:admin3_code":"554994.0",
    "gn:admin4_code":"55499483.0",
    "gn:asciiname":"Dari Kishorpur",
    "gn:country_code":"BD",
    "gn:dem":31,
    "gn:feature_class":"P",
    "gn:feature_code":"PPL",
    "gn:name":"Dari Kishorpur",
    "gn:population":0,
    "gn:timezone":"Asia/Dhaka",
    "iso:country":"BD",
    "name:ben_x_preferred":[
        "Dari Kishorpur"
    ],
    "name:ben_x_variant":[
        "Kishorpur Dari",
        "Dari Kisorpur"
    ],
    "name:und_x_variant":[
        "Dari Kisorpur",
        "Kishorpur Dari"
    ],
    "wof:name":"Dari Kishorpur",
    "wof:placetype":"locality"
},
  "geometry": {"coordinates":[89.55588,25.6758],"type":"Point"}
}