{
  "type": "Feature",
  "properties": {
    "gn:admin1_code":"84",
    "gn:admin2_code":"2019",
    "gn:admin3_code":"201940.0",
    "gn:admin4_code":"20194005.0",
    "gn:asciiname":"Laruchu",
    "gn:country_code":"BD",
    "gn:dem":13,
    "gn:feature_class":"P",
    "gn:feature_code":"PPL",
    "gn:name":"L\u0101ruchu",
    "gn:population":0,
    "gn:timezone":"Asia/Dhaka",
    "iso:country":"BD",
    "name:und_x_variant":[
        "Larachu",
        "L\u0101ruchu"
    ],
    "wof:name":"Laruchu",
    "wof:placetype":"locality"
},
  "geometry": {"coordinates":[91.05573,23.6699],"type":"Point"}
}