{
  "type": "Feature",
  "properties": {
    "gn:admin1_code":"81",
    "gn:admin2_code":"3068.0",
    "gn:admin3_code":"306852.0",
    "gn:admin4_code":"30685233.0",
    "gn:asciiname":"Asadnagar",
    "gn:country_code":"BD",
    "gn:dem":16,
    "gn:feature_class":"P",
    "gn:feature_code":"PPL",
    "gn:name":"Asadnagar",
    "gn:population":0,
    "gn:timezone":"Asia/Dhaka",
    "iso:country":"BD",
    "name:und_x_variant":[
        "\u0100chh\u0101dnagar",
        "Asadnagar"
    ],
    "wof:name":"Asadnagar",
    "wof:placetype":"locality"
},
  "geometry": {"coordinates":[90.69346,24.16835],"type":"Point"}
}