{
  "type": "Feature",
  "properties": {
    "gn:admin1_code":"84",
    "gn:admin2_code":"2003.0",
    "gn:admin3_code":"200373.0",
    "gn:admin4_code":"20037376.0",
    "gn:asciiname":"Jalachharipara",
    "gn:country_code":"BD",
    "gn:dem":84,
    "gn:feature_class":"P",
    "gn:feature_code":"PPL",
    "gn:name":"Jal\u0101chhar\u012bp\u0101ra",
    "gn:population":0,
    "gn:timezone":"Asia/Dhaka",
    "iso:country":"BD",
    "name:ben_x_preferred":[
        "Jal\u0101chhar\u012bp\u0101ra"
    ],
    "wof:name":"Jalachharipara",
    "wof:placetype":"locality"
},
  "geometry": {"coordinates":[92.16992,21.41589],"type":"Point"}
}