{
  "type": "Feature",
  "properties": {
    "gn:admin1_code":"H",
    "gn:admin2_code":"3072.0",
    "gn:admin3_code":"307218.0",
    "gn:admin4_code":"30721877.0",
    "gn:asciiname":"Deodukan",
    "gn:country_code":"BD",
    "gn:dem":15,
    "gn:feature_class":"P",
    "gn:feature_code":"PPL",
    "gn:name":"Deoduk\u0101n",
    "gn:population":0,
    "gn:timezone":"Asia/Dhaka",
    "iso:country":"BD",
    "name:und_x_variant":[
        "Deotokan",
        "Deoduk\u0101n"
    ],
    "wof:name":"Deodukan",
    "wof:placetype":"locality"
},
  "geometry": {"coordinates":[90.68407999999999,24.98802],"type":"Point"}
}