{
  "type": "Feature",
  "properties": {
    "gn:admin1_code":"83",
    "gn:admin2_code":"5070.0",
    "gn:admin3_code":"507037.0",
    "gn:admin4_code":"50703731.0",
    "gn:asciiname":"Maracar",
    "gn:country_code":"BD",
    "gn:dem":31,
    "gn:feature_class":"P",
    "gn:feature_code":"PPL",
    "gn:name":"Maracar",
    "gn:population":0,
    "gn:timezone":"Asia/Dhaka",
    "iso:country":"BD",
    "name:ben_x_preferred":[
        "Maracar"
    ],
    "wof:name":"Maracar",
    "wof:placetype":"locality"
},
  "geometry": {"coordinates":[88.29188000000001,24.82286],"type":"Point"}
}