{
  "type": "Feature",
  "properties": {
    "gn:admin1_code":"84",
    "gn:admin2_code":"2015.0",
    "gn:admin3_code":"201508.0",
    "gn:admin4_code":"20150875.0",
    "gn:asciiname":"Bholmara",
    "gn:country_code":"BD",
    "gn:dem":6,
    "gn:feature_class":"P",
    "gn:feature_code":"PPL",
    "gn:name":"Bholm\u0101ra",
    "gn:population":0,
    "gn:timezone":"Asia/Dhaka",
    "iso:country":"BD",
    "name:ben_x_preferred":[
        "Bholm\u0101ra"
    ],
    "wof:name":"Bholmara",
    "wof:placetype":"locality"
},
  "geometry": {"coordinates":[91.90971999999999,22.113],"type":"Point"}
}