{
  "type": "Feature",
  "properties": {
    "gn:admin1_code":"81",
    "gn:admin2_code":"3086",
    "gn:admin3_code":"308614.0",
    "gn:admin4_code":"30861477.0",
    "gn:asciiname":"Satyapur",
    "gn:country_code":"BD",
    "gn:dem":12,
    "gn:feature_class":"P",
    "gn:feature_code":"PPL",
    "gn:name":"Satyapur",
    "gn:population":0,
    "gn:timezone":"Asia/Dhaka",
    "iso:country":"BD",
    "wof:name":"Satyapur",
    "wof:placetype":"locality"
},
  "geometry": {"coordinates":[90.44946,23.21772],"type":"Point"}
}