{
  "type": "Feature",
  "properties": {
    "gn:admin1_code":"83",
    "gn:admin2_code":"5064.0",
    "gn:admin3_code":"506469.0",
    "gn:admin4_code":"50646942.0",
    "gn:asciiname":"Chak Ramjiban",
    "gn:country_code":"BD",
    "gn:dem":28,
    "gn:feature_class":"P",
    "gn:feature_code":"PPL",
    "gn:name":"Chak Ramjiban",
    "gn:population":0,
    "gn:timezone":"Asia/Dhaka",
    "iso:country":"BD",
    "name:ben_x_preferred":[
        "Chak Ramjiban"
    ],
    "wof:name":"Chak Ramjiban",
    "wof:placetype":"locality"
},
  "geometry": {"coordinates":[88.57592,24.93161],"type":"Point"}
}