{
  "type": "Feature",
  "properties": {
    "gn:admin1_code":"84",
    "gn:admin2_code":"2015.0",
    "gn:admin3_code":"201574.0",
    "gn:admin4_code":"20157450.0",
    "gn:asciiname":"Mangalkhali",
    "gn:country_code":"BD",
    "gn:dem":7,
    "gn:feature_class":"P",
    "gn:feature_code":"PPL",
    "gn:name":"Mangalkh\u0101li",
    "gn:population":0,
    "gn:timezone":"Asia/Dhaka",
    "iso:country":"BD",
    "name:ben_x_preferred":[
        "Mangalkh\u0101li"
    ],
    "wof:name":"Mangalkhali",
    "wof:placetype":"locality"
},
  "geometry": {"coordinates":[91.92802,22.50126],"type":"Point"}
}