{
  "type": "Feature",
  "properties": {
    "gn:admin1_code":"87",
    "gn:admin2_code":"5594",
    "gn:admin3_code":"559482.0",
    "gn:admin4_code":"55948225.0",
    "gn:asciiname":"Rajair",
    "gn:country_code":"BD",
    "gn:dem":51,
    "gn:feature_class":"P",
    "gn:feature_code":"PPL",
    "gn:name":"R\u0101jair",
    "gn:population":0,
    "gn:timezone":"Asia/Dhaka",
    "iso:country":"BD",
    "name:ben_x_preferred":[
        "R\u0101jair"
    ],
    "name:ben_x_variant":[
        "R\u0101jor"
    ],
    "wof:name":"Rajair",
    "wof:placetype":"locality"
},
  "geometry": {"coordinates":[88.32708000000002,25.91248],"type":"Point"}
}