{
  "type": "Feature",
  "properties": {
    "gn:admin1_code":"82",
    "gn:admin2_code":"4041",
    "gn:admin3_code":"404104.0",
    "gn:admin4_code":"40410473.0",
    "gn:asciiname":"Sridharpur",
    "gn:country_code":"BD",
    "gn:dem":9,
    "gn:feature_class":"P",
    "gn:feature_code":"PPL",
    "gn:name":"Sridharpur",
    "gn:population":0,
    "gn:timezone":"Asia/Dhaka",
    "iso:country":"BD",
    "name:ben_x_preferred":[
        "Sridharpur"
    ],
    "wof:name":"Sridharpur",
    "wof:placetype":"locality"
},
  "geometry": {"coordinates":[89.41773000000001,23.07475],"type":"Point"}
}