{
  "type": "Feature",
  "properties": {
    "gn:admin1_code":"85",
    "gn:admin2_code":"1042",
    "gn:admin3_code":"104273.0",
    "gn:admin4_code":"10427331.0",
    "gn:asciiname":"Phaira",
    "gn:country_code":"BD",
    "gn:dem":6,
    "gn:feature_class":"P",
    "gn:feature_code":"PPL",
    "gn:name":"Phaira",
    "gn:population":0,
    "gn:timezone":"Asia/Dhaka",
    "iso:country":"BD",
    "wof:name":"Phaira",
    "wof:placetype":"locality"
},
  "geometry": {"coordinates":[90.28721,22.59107],"type":"Point"}
}