{
  "type": "Feature",
  "properties": {
    "gn:admin1_code":"81",
    "gn:admin2_code":"3048",
    "gn:admin3_code":"304879.0",
    "gn:admin4_code":"30487938.0",
    "gn:asciiname":"Meher Dhanbari",
    "gn:country_code":"BD",
    "gn:dem":15,
    "gn:feature_class":"P",
    "gn:feature_code":"PPL",
    "gn:name":"Meher Dhanb\u0101ri",
    "gn:population":0,
    "gn:timezone":"Asia/Dhaka",
    "iso:country":"BD",
    "wof:name":"Meher Dhanbari",
    "wof:placetype":"locality"
},
  "geometry": {"coordinates":[90.65458,24.27841],"type":"Point"}
}