{
  "type": "Feature",
  "properties": {
    "gn:admin1_code":"83",
    "gn:admin2_code":"5064",
    "gn:admin3_code":"506460.0",
    "gn:admin4_code":"50646043.0",
    "gn:asciiname":"Khidirpur",
    "gn:country_code":"BD",
    "gn:dem":19,
    "gn:feature_class":"P",
    "gn:feature_code":"PPL",
    "gn:name":"Khidirpur",
    "gn:population":0,
    "gn:timezone":"Asia/Dhaka",
    "iso:country":"BD",
    "name:ben_x_preferred":[
        "Khidirpur"
    ],
    "wof:name":"Khidirpur",
    "wof:placetype":"locality"
},
  "geometry": {"coordinates":[88.965,24.7847],"type":"Point"}
}