{
  "type": "Feature",
  "properties": {
    "gn:admin1_code":"83",
    "gn:admin2_code":"5069.0",
    "gn:admin3_code":"506909.0",
    "gn:admin4_code":"50690976.0",
    "gn:asciiname":"Chaipara",
    "gn:country_code":"BD",
    "gn:dem":19,
    "gn:feature_class":"P",
    "gn:feature_code":"PPL",
    "gn:name":"Ch\u0101ip\u0101ra",
    "gn:population":0,
    "gn:timezone":"Asia/Dhaka",
    "iso:country":"BD",
    "wof:name":"Chaipara",
    "wof:placetype":"locality"
},
  "geometry": {"coordinates":[88.84999999999999,24.31667],"type":"Point"}
}