{
  "type": "Feature",
  "properties": {
    "gn:admin1_code":"87",
    "gn:admin2_code":"5594.0",
    "gn:admin3_code":"559486.0",
    "gn:admin4_code":"55948631.0",
    "gn:asciiname":"Bhadreswari",
    "gn:country_code":"BD",
    "gn:dem":49,
    "gn:feature_class":"P",
    "gn:feature_code":"PPL",
    "gn:name":"Bhadresw\u0101ri",
    "gn:population":0,
    "gn:timezone":"Asia/Dhaka",
    "iso:country":"BD",
    "name:ben_x_preferred":[
        "Bhadresw\u0101ri"
    ],
    "wof:name":"Bhadreswari",
    "wof:placetype":"locality"
},
  "geometry": {"coordinates":[88.15342,26.00946],"type":"Point"}
}