{
  "type": "Feature",
  "properties": {
    "gn:admin1_code":"84",
    "gn:admin2_code":"2019.0",
    "gn:admin3_code":"201936.0",
    "gn:admin4_code":"20193630.0",
    "gn:asciiname":"Bhaskhola",
    "gn:country_code":"BD",
    "gn:dem":10,
    "gn:feature_class":"P",
    "gn:feature_code":"PPL",
    "gn:name":"Bh\u0101skhola",
    "gn:population":0,
    "gn:timezone":"Asia/Dhaka",
    "iso:country":"BD",
    "wof:name":"Bhaskhola",
    "wof:placetype":"locality"
},
  "geometry": {"coordinates":[90.86767,23.53564],"type":"Point"}
}