{
  "type": "Feature",
  "properties": {
    "gn:admin1_code":"84",
    "gn:admin2_code":"2022.0",
    "gn:admin3_code":"202290.0",
    "gn:admin4_code":"20229015.0",
    "gn:asciiname":"Kachhadia",
    "gn:country_code":"BD",
    "gn:dem":7,
    "gn:feature_class":"P",
    "gn:feature_code":"PPL",
    "gn:name":"Kachhadia",
    "gn:population":0,
    "gn:timezone":"Asia/Dhaka",
    "iso:country":"BD",
    "wof:name":"Kachhadia",
    "wof:placetype":"locality"
},
  "geometry": {"coordinates":[92.21903,20.92895],"type":"Point"}
}