{
  "type": "Feature",
  "properties": {
    "gn:admin1_code":"84",
    "gn:admin2_code":"2084",
    "gn:admin3_code":"208407.0",
    "gn:admin4_code":"20840783.0",
    "gn:asciiname":"Chipui",
    "gn:country_code":"BD",
    "gn:dem":375,
    "gn:feature_class":"P",
    "gn:feature_code":"PPL",
    "gn:name":"Chipui",
    "gn:population":0,
    "gn:timezone":"Asia/Dhaka",
    "iso:country":"BD",
    "name:ben_x_preferred":[
        "Chipui"
    ],
    "wof:name":"Chipui",
    "wof:placetype":"locality"
},
  "geometry": {"coordinates":[92.25762,23.47999],"type":"Point"}
}