{
  "type": "Feature",
  "properties": {
    "gn:admin1_code":"H",
    "gn:admin2_code":"3072.0",
    "gn:admin3_code":"307263.0",
    "gn:admin4_code":"30726373.0",
    "gn:asciiname":"Ballabhpur",
    "gn:country_code":"BD",
    "gn:dem":16,
    "gn:feature_class":"P",
    "gn:feature_code":"PPL",
    "gn:name":"Ballabhpur",
    "gn:population":0,
    "gn:timezone":"Asia/Dhaka",
    "iso:country":"BD",
    "wof:name":"Ballabhpur",
    "wof:placetype":"locality"
},
  "geometry": {"coordinates":[90.99365,24.78222],"type":"Point"}
}