{
  "type": "Feature",
  "properties": {
    "gn:admin1_code":"83",
    "gn:admin2_code":"5081.0",
    "gn:admin3_code":"508112.0",
    "gn:admin4_code":"50811294.0",
    "gn:asciiname":"Dhamin Kamnagar",
    "gn:country_code":"BD",
    "gn:dem":22,
    "gn:feature_class":"P",
    "gn:feature_code":"PPL",
    "gn:name":"Dh\u0101min K\u0101mnagar",
    "gn:population":0,
    "gn:timezone":"Asia/Dhaka",
    "iso:country":"BD",
    "name:ben_x_preferred":[
        "Dh\u0101min K\u0101mnagar"
    ],
    "wof:name":"Dhamin Kamnagar",
    "wof:placetype":"locality"
},
  "geometry": {"coordinates":[88.75758,24.5782],"type":"Point"}
}