{
  "type": "Feature",
  "properties": {
    "gn:admin1_code":"82",
    "gn:admin2_code":"4047.0",
    "gn:admin3_code":"404730.0",
    "gn:admin4_code":"40473047.0",
    "gn:asciiname":"Baylahara",
    "gn:country_code":"BD",
    "gn:dem":5,
    "gn:feature_class":"P",
    "gn:feature_code":"PPL",
    "gn:name":"Bayl\u0101hara",
    "gn:population":0,
    "gn:timezone":"Asia/Dhaka",
    "iso:country":"BD",
    "name:und_x_variant":[
        "Bailahara",
        "Bayl\u0101hara"
    ],
    "wof:name":"Baylahara",
    "wof:placetype":"locality"
},
  "geometry": {"coordinates":[89.34739999999999,22.7168],"type":"Point"}
}