{
  "type": "Feature",
  "properties": {
    "gn:admin1_code":"84",
    "gn:admin2_code":"2015",
    "gn:admin3_code":"201578.0",
    "gn:admin4_code":"20157865.0",
    "gn:asciiname":"Musapur",
    "gn:country_code":"BD",
    "gn:dem":6,
    "gn:feature_class":"P",
    "gn:feature_code":"PPL",
    "gn:name":"Mus\u0101pur",
    "gn:population":0,
    "gn:timezone":"Asia/Dhaka",
    "iso:country":"BD",
    "wof:name":"Musapur",
    "wof:placetype":"locality"
},
  "geometry": {"coordinates":[91.51000000000001,22.46306],"type":"Point"}
}