{
  "type": "Feature",
  "properties": {
    "gn:admin1_code":"87",
    "gn:admin2_code":"5532",
    "gn:admin3_code":"553230.0",
    "gn:admin4_code":"55323055.0",
    "gn:asciiname":"Kalugari",
    "gn:country_code":"BD",
    "gn:dem":24,
    "gn:feature_class":"P",
    "gn:feature_code":"PPL",
    "gn:name":"Kalug\u0101ri",
    "gn:population":0,
    "gn:timezone":"Asia/Dhaka",
    "iso:country":"BD",
    "name:ben_x_preferred":[
        "Kalug\u0101ri"
    ],
    "wof:name":"Kalugari",
    "wof:placetype":"locality"
},
  "geometry": {"coordinates":[89.4293,25.21308],"type":"Point"}
}