{
  "type": "Feature",
  "properties": {
    "gn:admin1_code":"82",
    "gn:admin2_code":"4044.0",
    "gn:admin3_code":"404419.0",
    "gn:admin4_code":"40441926.0",
    "gn:asciiname":"Sonardair",
    "gn:country_code":"BD",
    "gn:dem":16,
    "gn:feature_class":"P",
    "gn:feature_code":"PPL",
    "gn:name":"Son\u0101rd\u0101ir",
    "gn:population":0,
    "gn:timezone":"Asia/Dhaka",
    "iso:country":"BD",
    "name:ben_x_preferred":[
        "Son\u0101rd\u0101ir"
    ],
    "wof:name":"Sonardair",
    "wof:placetype":"locality"
},
  "geometry": {"coordinates":[89.06914999999999,23.53314],"type":"Point"}
}