{
  "type": "Feature",
  "properties": {
    "gn:admin1_code":"82",
    "gn:admin2_code":"4041",
    "gn:admin3_code":"404147.0",
    "gn:admin4_code":"40414723.0",
    "gn:asciiname":"Maidia",
    "gn:country_code":"BD",
    "gn:dem":8,
    "gn:feature_class":"P",
    "gn:feature_code":"PPL",
    "gn:name":"Maidia",
    "gn:population":0,
    "gn:timezone":"Asia/Dhaka",
    "iso:country":"BD",
    "name:ben_x_preferred":[
        "Maidia"
    ],
    "wof:name":"Maidia",
    "wof:placetype":"locality"
},
  "geometry": {"coordinates":[89.18545,23.1243],"type":"Point"}
}