{
  "type": "Feature",
  "properties": {
    "gn:admin1_code":"83",
    "gn:admin2_code":"5064.0",
    "gn:admin3_code":"506450.0",
    "gn:admin4_code":"50645066.0",
    "gn:asciiname":"Fazilpur",
    "gn:country_code":"BD",
    "gn:dem":22,
    "gn:feature_class":"P",
    "gn:feature_code":"PPL",
    "gn:name":"F\u0101zilpur",
    "gn:population":0,
    "gn:timezone":"Asia/Dhaka",
    "iso:country":"BD",
    "name:pol_x_preferred":[
        "Fazilpur"
    ],
    "name:urd_x_preferred":[
        "\u0641\u0627\u0636\u0644 \u067e\u0648\u0631"
    ],
    "wof:name":"Fazilpur",
    "wof:placetype":"locality"
},
  "geometry": {"coordinates":[88.75041999999998,24.93223],"type":"Point"}
}