{
  "type": "Feature",
  "properties": {
    "gn:admin1_code":"81",
    "gn:admin2_code":"3082",
    "gn:admin3_code":"308207.0",
    "gn:admin4_code":"30820719.0",
    "gn:asciiname":"Khurd Megchami",
    "gn:country_code":"BD",
    "gn:dem":15,
    "gn:feature_class":"P",
    "gn:feature_code":"PPL",
    "gn:name":"Khurd Megch\u0101mi",
    "gn:population":0,
    "gn:timezone":"Asia/Dhaka",
    "iso:country":"BD",
    "name:und_x_variant":[
        "Khordamegchami",
        "Khurd Megch\u0101mi"
    ],
    "wof:name":"Khurd Megchami",
    "wof:placetype":"locality"
},
  "geometry": {"coordinates":[89.56635,23.6088],"type":"Point"}
}