{
  "type": "Feature",
  "properties": {
    "gn:admin1_code":"84",
    "gn:admin2_code":"2013.0",
    "gn:admin3_code":"201345.0",
    "gn:admin4_code":"20134529.0",
    "gn:asciiname":"Barali",
    "gn:country_code":"BD",
    "gn:dem":12,
    "gn:feature_class":"P",
    "gn:feature_code":"PPL",
    "gn:name":"Bar\u0101li",
    "gn:population":0,
    "gn:timezone":"Asia/Dhaka",
    "iso:country":"BD",
    "wof:name":"Barali",
    "wof:placetype":"locality"
},
  "geometry": {"coordinates":[90.76239,23.11866],"type":"Point"}
}