{
  "type": "Feature",
  "properties": {
    "gn:admin1_code":"85",
    "gn:admin2_code":"1006",
    "gn:admin3_code":"100636.0",
    "gn:admin4_code":"10063654.0",
    "gn:asciiname":"Tar Goari Bhanga",
    "gn:country_code":"BD",
    "gn:dem":10,
    "gn:feature_class":"P",
    "gn:feature_code":"PPL",
    "gn:name":"Tar Go\u0101ri Bh\u0101nga",
    "gn:population":0,
    "gn:timezone":"Asia/Dhaka",
    "iso:country":"BD",
    "wof:name":"Tar Goari Bhanga",
    "wof:placetype":"locality"
},
  "geometry": {"coordinates":[90.45650000000001,22.93751],"type":"Point"}
}