{
  "type": "Feature",
  "properties": {
    "gn:admin1_code":"81",
    "gn:admin2_code":"3068",
    "gn:admin3_code":"306864.0",
    "gn:admin4_code":"30686427.0",
    "gn:asciiname":"Purba Husainnagar",
    "gn:country_code":"BD",
    "gn:dem":14,
    "gn:feature_class":"P",
    "gn:feature_code":"PPL",
    "gn:name":"Purba Husainnagar",
    "gn:population":0,
    "gn:timezone":"Asia/Dhaka",
    "iso:country":"BD",
    "name:und_x_variant":[
        "Purba Hosennagar",
        "Purba Husainnagar"
    ],
    "wof:name":"Purba Husainnagar",
    "wof:placetype":"locality"
},
  "geometry": {"coordinates":[90.93003,23.93864],"type":"Point"}
}