{
  "type": "Feature",
  "properties": {
    "gn:admin1_code":"87",
    "gn:admin2_code":"5585",
    "gn:admin3_code":"558549.0",
    "gn:admin4_code":"55854939.0",
    "gn:asciiname":"Fakirtari",
    "gn:country_code":"BD",
    "gn:dem":39,
    "gn:feature_class":"P",
    "gn:feature_code":"PPL",
    "gn:name":"Fakirt\u0101ri",
    "gn:population":0,
    "gn:timezone":"Asia/Dhaka",
    "iso:country":"BD",
    "name:ben_x_preferred":[
        "Fakirt\u0101ri"
    ],
    "wof:name":"Fakirtari",
    "wof:placetype":"locality"
},
  "geometry": {"coordinates":[89.22874,25.80102],"type":"Point"}
}