{
  "type": "Feature",
  "properties": {
    "gn:admin1_code":"82",
    "gn:admin2_code":"4044.0",
    "gn:admin3_code":"404414.0",
    "gn:admin4_code":"40441484.0",
    "gn:asciiname":"Chatkabaria",
    "gn:country_code":"BD",
    "gn:dem":16,
    "gn:feature_class":"P",
    "gn:feature_code":"PPL",
    "gn:name":"Ch\u0101tk\u0101b\u0101ria",
    "gn:population":0,
    "gn:timezone":"Asia/Dhaka",
    "iso:country":"BD",
    "name:ben_x_preferred":[
        "Ch\u0101tk\u0101b\u0101ria"
    ],
    "wof:name":"Chatkabaria",
    "wof:placetype":"locality"
},
  "geometry": {"coordinates":[89.04323000000002,23.65689],"type":"Point"}
}