{
  "type": "Feature",
  "properties": {
    "gn:admin1_code":"82",
    "gn:admin2_code":"4050.0",
    "gn:admin3_code":"405079.0",
    "gn:admin4_code":"40507912.0",
    "gn:asciiname":"Ballabhpur",
    "gn:country_code":"BD",
    "gn:dem":18,
    "gn:feature_class":"P",
    "gn:feature_code":"PPL",
    "gn:name":"Ballabhpur",
    "gn:population":0,
    "gn:timezone":"Asia/Dhaka",
    "iso:country":"BD",
    "name:ben_x_preferred":[
        "Ballabhpur"
    ],
    "wof:name":"Ballabhpur",
    "wof:placetype":"locality"
},
  "geometry": {"coordinates":[89.04791999999998,23.8602],"type":"Point"}
}