{
  "type": "Feature",
  "properties": {
    "gn:admin1_code":"81",
    "gn:admin2_code":"3026",
    "gn:admin3_code":"302618.0",
    "gn:admin4_code":"30261873.0",
    "gn:asciiname":"Khalpar",
    "gn:country_code":"BD",
    "gn:dem":13,
    "gn:feature_class":"P",
    "gn:feature_code":"PPL",
    "gn:name":"Kh\u0101lp\u0101r",
    "gn:population":0,
    "gn:timezone":"Asia/Dhaka",
    "iso:country":"BD",
    "wof:name":"Khalpar",
    "wof:placetype":"locality"
},
  "geometry": {"coordinates":[90.13126,23.62978],"type":"Point"}
}