{
  "type": "Feature",
  "properties": {
    "gn:admin1_code":"87",
    "gn:admin2_code":"5585.0",
    "gn:admin3_code":"558558.0",
    "gn:admin4_code":"55855827.0",
    "gn:asciiname":"Betgara",
    "gn:country_code":"BD",
    "gn:dem":31,
    "gn:feature_class":"P",
    "gn:feature_code":"PPL",
    "gn:name":"Betgara",
    "gn:population":0,
    "gn:timezone":"Asia/Dhaka",
    "iso:country":"BD",
    "name:ben_x_preferred":[
        "Betgara"
    ],
    "wof:name":"Betgara",
    "wof:placetype":"locality"
},
  "geometry": {"coordinates":[89.32825,25.65625],"type":"Point"}
}