{
  "type": "Feature",
  "properties": {
    "gn:admin1_code":"84",
    "gn:admin2_code":"2013.0",
    "gn:admin3_code":"201345.0",
    "gn:admin4_code":"20134535.0",
    "gn:asciiname":"Char Pata",
    "gn:country_code":"BD",
    "gn:dem":13,
    "gn:feature_class":"P",
    "gn:feature_code":"PPL",
    "gn:name":"Char Pata",
    "gn:population":0,
    "gn:timezone":"Asia/Dhaka",
    "iso:country":"BD",
    "name:und_x_variant":[
        "Char P\u0101ra"
    ],
    "wof:name":"Char Pata",
    "wof:placetype":"locality"
},
  "geometry": {"coordinates":[90.75364,23.11081],"type":"Point"}
}