{
  "type": "Feature",
  "properties": {
    "gn:admin1_code":"84",
    "gn:admin2_code":"2046.0",
    "gn:admin3_code":"204661.0",
    "gn:admin4_code":"20466147.0",
    "gn:asciiname":"Chalyatali",
    "gn:country_code":"BD",
    "gn:dem":59,
    "gn:feature_class":"P",
    "gn:feature_code":"PPL",
    "gn:name":"Chalyatali",
    "gn:population":0,
    "gn:timezone":"Asia/Dhaka",
    "iso:country":"BD",
    "name:ben_x_preferred":[
        "Chalyatali"
    ],
    "wof:name":"Chalyatali",
    "wof:placetype":"locality"
},
  "geometry": {"coordinates":[91.92627,22.84999],"type":"Point"}
}