{
  "type": "Feature",
  "properties": {
    "gn:admin1_code":"H",
    "gn:admin2_code":"3089.0",
    "gn:admin3_code":"308967.0",
    "gn:admin4_code":"30896766.0",
    "gn:asciiname":"Dudher Char",
    "gn:country_code":"BD",
    "gn:dem":21,
    "gn:feature_class":"P",
    "gn:feature_code":"PPL",
    "gn:name":"Dudher Char",
    "gn:population":0,
    "gn:timezone":"Asia/Dhaka",
    "iso:country":"BD",
    "wof:name":"Dudher Char",
    "wof:placetype":"locality"
},
  "geometry": {"coordinates":[90.18248,24.91435],"type":"Point"}
}