{
  "type": "Feature",
  "properties": {
    "gn:admin1_code":"87",
    "gn:admin2_code":"5585",
    "gn:admin3_code":"558576.0",
    "gn:admin4_code":"55857695.0",
    "gn:asciiname":"Ramkanupur",
    "gn:country_code":"BD",
    "gn:dem":30,
    "gn:feature_class":"P",
    "gn:feature_code":"PPL",
    "gn:name":"Ramkanupur",
    "gn:population":0,
    "gn:timezone":"Asia/Dhaka",
    "iso:country":"BD",
    "name:ben_x_preferred":[
        "Ramkanupur"
    ],
    "wof:name":"Ramkanupur",
    "wof:placetype":"locality"
},
  "geometry": {"coordinates":[89.19615,25.4006],"type":"Point"}
}