{
  "type": "Feature",
  "properties": {
    "gn:admin1_code":"87",
    "gn:admin2_code":"5573.0",
    "gn:admin3_code":"557315.0",
    "gn:admin4_code":"55731547.0",
    "gn:asciiname":"Khalpara",
    "gn:country_code":"BD",
    "gn:dem":60,
    "gn:feature_class":"P",
    "gn:feature_code":"PPL",
    "gn:name":"Kh\u0101lp\u0101ra",
    "gn:population":0,
    "gn:timezone":"Asia/Dhaka",
    "iso:country":"BD",
    "name:ben_x_preferred":[
        "Kh\u0101lp\u0101ra"
    ],
    "wof:name":"Khalpara",
    "wof:placetype":"locality"
},
  "geometry": {"coordinates":[88.87385999999999,26.20381],"type":"Point"}
}