{
  "type": "Feature",
  "properties": {
    "gn:admin1_code":"81",
    "gn:admin2_code":"3033.0",
    "gn:admin3_code":"303336.0",
    "gn:admin4_code":"30333608.0",
    "gn:asciiname":"Barjapur",
    "gn:country_code":"BD",
    "gn:dem":14,
    "gn:feature_class":"P",
    "gn:feature_code":"PPL",
    "gn:name":"Barj\u0101pur",
    "gn:population":0,
    "gn:timezone":"Asia/Dhaka",
    "iso:country":"BD",
    "wof:name":"Barjapur",
    "wof:placetype":"locality"
},
  "geometry": {"coordinates":[90.67146,24.20625],"type":"Point"}
}