{
  "type": "Feature",
  "properties": {
    "gn:admin1_code":"84",
    "gn:admin2_code":"2012",
    "gn:admin3_code":"201204.0",
    "gn:admin4_code":"20120477.0",
    "gn:asciiname":"Radhanagar",
    "gn:country_code":"BD",
    "gn:dem":12,
    "gn:feature_class":"P",
    "gn:feature_code":"PPL",
    "gn:name":"R\u0101dh\u0101nagar",
    "gn:population":0,
    "gn:timezone":"Asia/Dhaka",
    "iso:country":"BD",
    "wof:name":"Radhanagar",
    "wof:placetype":"locality"
},
  "geometry": {"coordinates":[90.77722,23.70056],"type":"Point"}
}