{
  "type": "Feature",
  "properties": {
    "gn:admin1_code":"87",
    "gn:admin2_code":"5594.0",
    "gn:admin3_code":"559494.0",
    "gn:admin4_code":"55949415.0",
    "gn:asciiname":"Madarganj",
    "gn:country_code":"BD",
    "gn:dem":60,
    "gn:feature_class":"P",
    "gn:feature_code":"PPL",
    "gn:name":"M\u0101d\u0101rganj",
    "gn:population":0,
    "gn:timezone":"Asia/Dhaka",
    "iso:country":"BD",
    "name:ben_x_preferred":[
        "M\u0101d\u0101rganj"
    ],
    "wof:name":"Madarganj",
    "wof:placetype":"locality"
},
  "geometry": {"coordinates":[88.50281,26.09298],"type":"Point"}
}