{
  "type": "Feature",
  "properties": {
    "gn:admin1_code":"84",
    "gn:admin2_code":"2019.0",
    "gn:admin3_code":"201954.0",
    "gn:admin4_code":"20195476.0",
    "gn:asciiname":"Banda Dulali",
    "gn:cc2":"BD",
    "gn:country_code":"BD",
    "gn:dem":0,
    "gn:feature_class":"P",
    "gn:feature_code":"PPL",
    "gn:name":"Banda Dul\u0101li",
    "gn:population":0,
    "gn:timezone":"Asia/Dhaka",
    "iso:country":"BD",
    "name:und_x_variant":[
        "Banda-Duali",
        "Banda Dul\u0101li"
    ],
    "wof:name":"Banda Dulali",
    "wof:placetype":"locality"
},
  "geometry": {"coordinates":[90.76667,23.65],"type":"Point"}
}