{
  "type": "Feature",
  "properties": {
    "gn:admin1_code":"83",
    "gn:admin2_code":"5064.0",
    "gn:admin3_code":"506450.0",
    "gn:admin4_code":"50645047.0",
    "gn:asciiname":"Harekrishnapur",
    "gn:country_code":"BD",
    "gn:dem":25,
    "gn:feature_class":"P",
    "gn:feature_code":"PPL",
    "gn:name":"Harekrishnapur",
    "gn:population":0,
    "gn:timezone":"Asia/Dhaka",
    "iso:country":"BD",
    "name:ben_x_preferred":[
        "Harekrishnapur"
    ],
    "name:und_x_variant":[
        "Herekrishnapur"
    ],
    "wof:name":"Harekrishnapur",
    "wof:placetype":"locality"
},
  "geometry": {"coordinates":[88.69033,24.9928],"type":"Point"}
}