{
  "type": "Feature",
  "properties": {
    "gn:admin1_code":"H",
    "gn:admin2_code":"3072.0",
    "gn:admin3_code":"307263.0",
    "gn:admin4_code":"30726342.0",
    "gn:asciiname":"Bara Betham",
    "gn:country_code":"BD",
    "gn:dem":14,
    "gn:feature_class":"P",
    "gn:feature_code":"PPL",
    "gn:name":"Bara Beth\u0101m",
    "gn:population":0,
    "gn:timezone":"Asia/Dhaka",
    "iso:country":"BD",
    "wof:name":"Bara Betham",
    "wof:placetype":"locality"
},
  "geometry": {"coordinates":[90.98589,24.83103],"type":"Point"}
}