{
  "type": "Feature",
  "properties": {
    "iso:country":"BD",
    "name:ben_x_preferred":[
        "Dakshinp\u0101ra"
    ],
    "name:ben_x_variant":[
        "Dakhinp\u0101ra"
    ],
    "qs:gn_country":"BD",
    "qs:gn_fcode":"PPL",
    "qs:gn_pop":0,
    "qs:name":"Dakhinpara",
    "qs:name_adm0":"Bangladesh",
    "qs:name_adm1":"Chittagong",
    "qs:photos":80,
    "qs:photos_1k":16,
    "qs:photos_9k":1,
    "qs:photos_9r":3,
    "qs:photos_all":80,
    "qs:photos_sr":3,
    "qs:placetype":"Town",
    "qs:pop_sr":"3",
    "qs:woe_adm0":23424759,
    "wof:name":"Dakhinpara",
    "wof:placetype":"locality"
},
  "geometry": {"coordinates":[92.33341,20.75729],"type":"Point"}
}