{
  "type": "Feature",
  "properties": {
    "gn:admin1_code":"87",
    "gn:admin2_code":"5532.0",
    "gn:admin3_code":"553230.0",
    "gn:admin4_code":"55323033.0",
    "gn:asciiname":"Nayapara",
    "gn:country_code":"BD",
    "gn:dem":27,
    "gn:feature_class":"P",
    "gn:feature_code":"PPL",
    "gn:name":"Nayap\u0101ra",
    "gn:population":0,
    "gn:timezone":"Asia/Dhaka",
    "iso:country":"BD",
    "name:ben_x_preferred":[
        "Nayap\u0101ra"
    ],
    "wof:name":"Nayapara",
    "wof:placetype":"locality"
},
  "geometry": {"coordinates":[89.21047,25.2274],"type":"Point"}
}