{
  "type": "Feature",
  "properties": {
    "gn:admin1_code":"87",
    "gn:admin2_code":"5585.0",
    "gn:admin3_code":"558527.0",
    "gn:admin4_code":"55852710.0",
    "gn:asciiname":"Barabil",
    "gn:country_code":"BD",
    "gn:dem":41,
    "gn:feature_class":"P",
    "gn:feature_code":"PPL",
    "gn:name":"Bar\u0101b\u012bl",
    "gn:population":0,
    "gn:timezone":"Asia/Dhaka",
    "iso:country":"BD",
    "name:ben_x_preferred":[
        "Bar\u0101b\u012bl"
    ],
    "wof:name":"Barabil",
    "wof:placetype":"locality"
},
  "geometry": {"coordinates":[89.17744,25.88606],"type":"Point"}
}