{
  "type": "Feature",
  "properties": {
    "gn:admin1_code":"83",
    "gn:admin2_code":"5070.0",
    "gn:admin3_code":"507018.0",
    "gn:admin4_code":"50701818.0",
    "gn:asciiname":"Ohorampur",
    "gn:country_code":"BD",
    "gn:dem":31,
    "gn:feature_class":"P",
    "gn:feature_code":"PPL",
    "gn:name":"Ohorampur",
    "gn:population":0,
    "gn:timezone":"Asia/Dhaka",
    "iso:country":"BD",
    "name:ben_x_preferred":[
        "Ohorampur"
    ],
    "wof:name":"Ohorampur",
    "wof:placetype":"locality"
},
  "geometry": {"coordinates":[88.21247,24.9466],"type":"Point"}
}