{
  "type": "Feature",
  "properties": {
    "gn:admin1_code":"85",
    "gn:admin2_code":"1006",
    "gn:admin3_code":"100669.0",
    "gn:admin4_code":"10066983.0",
    "gn:asciiname":"Paschim Char Bheduria",
    "gn:country_code":"BD",
    "gn:dem":11,
    "gn:feature_class":"P",
    "gn:feature_code":"PPL",
    "gn:name":"Paschim Char Bheduria",
    "gn:population":0,
    "gn:timezone":"Asia/Dhaka",
    "iso:country":"BD",
    "name:und_x_variant":[
        "West Char Bheduria"
    ],
    "wof:name":"Paschim Char Bheduria",
    "wof:placetype":"locality"
},
  "geometry": {"coordinates":[90.37926,23.0298],"type":"Point"}
}