{
  "type": "Feature",
  "properties": {
    "gn:admin1_code":"84",
    "gn:admin2_code":"2022.0",
    "gn:admin3_code":"202224.0",
    "gn:admin4_code":"20222411.0",
    "gn:asciiname":"Chaufaldandi Ghar",
    "gn:country_code":"BD",
    "gn:dem":11,
    "gn:feature_class":"P",
    "gn:feature_code":"PPL",
    "gn:name":"Chaufaldandi Gh\u0101r",
    "gn:population":0,
    "gn:timezone":"Asia/Dhaka",
    "iso:country":"BD",
    "name:ben_x_preferred":[
        "Chaufaldandi Gh\u0101r"
    ],
    "wof:name":"Chaufaldandi Ghar",
    "wof:placetype":"locality"
},
  "geometry": {"coordinates":[92.01324,21.51676],"type":"Point"}
}