{
  "type": "Feature",
  "properties": {
    "gn:admin1_code":"87",
    "gn:admin2_code":"5573.0",
    "gn:admin3_code":"557364.0",
    "gn:admin4_code":"55736469.0",
    "gn:asciiname":"Itakhola",
    "gn:country_code":"BD",
    "gn:dem":52,
    "gn:feature_class":"P",
    "gn:feature_code":"PPL",
    "gn:name":"Itakhola",
    "gn:population":0,
    "gn:timezone":"Asia/Dhaka",
    "iso:country":"BD",
    "name:ben_x_preferred":[
        "Itakhola"
    ],
    "wof:name":"Itakhola",
    "wof:placetype":"locality"
},
  "geometry": {"coordinates":[88.84479,25.98188],"type":"Point"}
}