{
  "type": "Feature",
  "properties": {
    "gn:admin1_code":"87",
    "gn:admin2_code":"5527.0",
    "gn:admin3_code":"552712.0",
    "gn:admin4_code":"55271260.0",
    "gn:asciiname":"Sengram",
    "gn:country_code":"BD",
    "gn:dem":46,
    "gn:feature_class":"P",
    "gn:feature_code":"PPL",
    "gn:name":"Sengr\u0101m",
    "gn:population":0,
    "gn:timezone":"Asia/Dhaka",
    "iso:country":"BD",
    "name:ben_x_preferred":[
        "Sengr\u0101m"
    ],
    "wof:name":"Sengram",
    "wof:placetype":"locality"
},
  "geometry": {"coordinates":[88.72978000000001,25.83146],"type":"Point"}
}