{
  "type": "Feature",
  "properties": {
    "gn:admin1_code":"84",
    "gn:admin2_code":"2022.0",
    "gn:admin3_code":"202249.0",
    "gn:admin4_code":"20224911.0",
    "gn:asciiname":"Jagiraghona",
    "gn:country_code":"BD",
    "gn:dem":9,
    "gn:feature_class":"P",
    "gn:feature_code":"PPL",
    "gn:name":"J\u0101g\u012braghona",
    "gn:population":0,
    "gn:timezone":"Asia/Dhaka",
    "iso:country":"BD",
    "wof:name":"Jagiraghona",
    "wof:placetype":"locality"
},
  "geometry": {"coordinates":[91.94589000000001,21.52936],"type":"Point"}
}