{
  "type": "Feature",
  "properties": {
    "gn:admin1_code":"81",
    "gn:admin2_code":"3048",
    "gn:admin3_code":"304845.0",
    "gn:admin4_code":"30484547.0",
    "gn:asciiname":"Pachlipara",
    "gn:country_code":"BD",
    "gn:dem":13,
    "gn:feature_class":"P",
    "gn:feature_code":"PPL",
    "gn:name":"P\u0101chlip\u0101ra",
    "gn:population":0,
    "gn:timezone":"Asia/Dhaka",
    "iso:country":"BD",
    "wof:name":"Pachlipara",
    "wof:placetype":"locality"
},
  "geometry": {"coordinates":[90.89140999999999,24.33725],"type":"Point"}
}