{
  "type": "Feature",
  "properties": {
    "gn:admin1_code":"84",
    "gn:admin2_code":"2022.0",
    "gn:admin3_code":"202295.0",
    "gn:admin4_code":"20229511.0",
    "gn:asciiname":"Pahariakhalipara",
    "gn:country_code":"BD",
    "gn:dem":12,
    "gn:feature_class":"P",
    "gn:feature_code":"PPL",
    "gn:name":"P\u0101h\u0101ri\u0101kh\u0101lip\u0101ra",
    "gn:population":0,
    "gn:timezone":"Asia/Dhaka",
    "iso:country":"BD",
    "name:ben_x_preferred":[
        "P\u0101h\u0101ri\u0101kh\u0101lip\u0101ra"
    ],
    "wof:name":"Pahariakhalipara",
    "wof:placetype":"locality"
},
  "geometry": {"coordinates":[91.98742,21.84433],"type":"Point"}
}