{
  "type": "Feature",
  "properties": {
    "gn:admin1_code":"81",
    "gn:admin2_code":"3035.0",
    "gn:admin3_code":"303532.0",
    "gn:admin4_code":"30353282.0",
    "gn:asciiname":"Betbhita",
    "gn:country_code":"BD",
    "gn:dem":5,
    "gn:feature_class":"P",
    "gn:feature_code":"PPL",
    "gn:name":"Betbhita",
    "gn:population":0,
    "gn:timezone":"Asia/Dhaka",
    "iso:country":"BD",
    "name:ben_x_preferred":[
        "Betbhita"
    ],
    "wof:name":"Betbhita",
    "wof:placetype":"locality"
},
  "geometry": {"coordinates":[89.93208,23.1357],"type":"Point"}
}