{
  "type": "Feature",
  "properties": {
    "gn:admin1_code":"00",
    "gn:asciiname":"Rajapur",
    "gn:country_code":"BD",
    "gn:dem":1,
    "gn:feature_class":"P",
    "gn:feature_code":"PPL",
    "gn:name":"R\u0101j\u0101pur",
    "gn:population":0,
    "gn:timezone":"Asia/Dhaka",
    "iso:country":"BD",
    "wof:name":"Rajapur",
    "wof:placetype":"locality"
},
  "geometry": {"coordinates":[90.43019,22.75452],"type":"Point"}
}