{
  "type": "Feature",
  "properties": {
    "gn:admin1_code":"83",
    "gn:admin2_code":"5038.0",
    "gn:admin3_code":"503874.0",
    "gn:admin4_code":"50387484.0",
    "gn:asciiname":"Sukurmai",
    "gn:country_code":"BD",
    "gn:dem":26,
    "gn:feature_class":"P",
    "gn:feature_code":"PPL",
    "gn:name":"Sukurm\u0101i",
    "gn:population":0,
    "gn:timezone":"Asia/Dhaka",
    "iso:country":"BD",
    "name:ben_x_preferred":[
        "Sukurm\u0101i"
    ],
    "wof:name":"Sukurmai",
    "wof:placetype":"locality"
},
  "geometry": {"coordinates":[89.10939,25.19997],"type":"Point"}
}