{
  "type": "Feature",
  "properties": {
    "gn:admin1_code":"87",
    "gn:admin2_code":"5527",
    "gn:admin3_code":"552730.0",
    "gn:admin4_code":"55273087.0",
    "gn:asciiname":"Ranipur",
    "gn:country_code":"BD",
    "gn:dem":46,
    "gn:feature_class":"P",
    "gn:feature_code":"PPL",
    "gn:name":"R\u0101nipur",
    "gn:population":0,
    "gn:timezone":"Asia/Dhaka",
    "iso:country":"BD",
    "name:ben_x_preferred":[
        "R\u0101nipur"
    ],
    "name:pol_x_preferred":[
        "Ranipur"
    ],
    "name:snd_x_preferred":[
        "\u0631\u0627\u06bb\u064a \u067e\u0648\u0631"
    ],
    "name:urd_x_preferred":[
        "\u0631\u0627\u0646\u06cc \u067e\u0648\u0631"
    ],
    "wof:name":"Ranipur",
    "wof:placetype":"locality"
},
  "geometry": {"coordinates":[88.78787,25.7662],"type":"Point"}
}