{
  "type": "Feature",
  "properties": {
    "gn:admin1_code":"85",
    "gn:admin2_code":"1078.0",
    "gn:admin3_code":"107866.0",
    "gn:admin4_code":"10786635.0",
    "gn:asciiname":"Naopara",
    "gn:country_code":"BD",
    "gn:dem":7,
    "gn:feature_class":"P",
    "gn:feature_code":"PPL",
    "gn:name":"N\u0101op\u0101ra",
    "gn:population":0,
    "gn:timezone":"Asia/Dhaka",
    "iso:country":"BD",
    "name:ben_x_preferred":[
        "N\u0101op\u0101ra"
    ],
    "wof:name":"Naopara",
    "wof:placetype":"locality"
},
  "geometry": {"coordinates":[90.29572,21.94616],"type":"Point"}
}