{
  "type": "Feature",
  "properties": {
    "gn:admin1_code":"87",
    "gn:admin2_code":"5532",
    "gn:admin3_code":"553291.0",
    "gn:admin4_code":"55329131.0",
    "gn:asciiname":"Jhinia",
    "gn:country_code":"BD",
    "gn:dem":27,
    "gn:feature_class":"P",
    "gn:feature_code":"PPL",
    "gn:name":"Jhini\u0101",
    "gn:population":0,
    "gn:timezone":"Asia/Dhaka",
    "iso:country":"BD",
    "name:ben_x_preferred":[
        "Jhini\u0101"
    ],
    "wof:name":"Jhinia",
    "wof:placetype":"locality"
},
  "geometry": {"coordinates":[89.54862,25.53541],"type":"Point"}
}