{
  "type": "Feature",
  "properties": {
    "gn:admin1_code":"H",
    "gn:admin2_code":"3072.0",
    "gn:admin3_code":"307283.0",
    "gn:admin4_code":"30728394.0",
    "gn:asciiname":"Bara Iiaspur",
    "gn:country_code":"BD",
    "gn:dem":11,
    "gn:feature_class":"P",
    "gn:feature_code":"PPL",
    "gn:name":"Bara Ii\u0101spur",
    "gn:population":0,
    "gn:timezone":"Asia/Dhaka",
    "iso:country":"BD",
    "name:und_x_variant":[
        "Bara Ii\u0101spur",
        "Bara Il\u0101spur"
    ],
    "wof:name":"Bara Iiaspur",
    "wof:placetype":"locality"
},
  "geometry": {"coordinates":[90.61042999999999,24.92628],"type":"Point"}
}