{
  "type": "Feature",
  "properties": {
    "gn:admin1_code":"82",
    "gn:admin2_code":"4018",
    "gn:admin3_code":"401831.0",
    "gn:admin4_code":"40183135.0",
    "gn:asciiname":"Loknathpur",
    "gn:country_code":"BD",
    "gn:dem":18,
    "gn:feature_class":"P",
    "gn:feature_code":"PPL",
    "gn:name":"Lokn\u0101thpur",
    "gn:population":0,
    "gn:timezone":"Asia/Dhaka",
    "iso:country":"BD",
    "name:ben_x_preferred":[
        "Lokn\u0101thpur"
    ],
    "wof:name":"Loknathpur",
    "wof:placetype":"locality"
},
  "geometry": {"coordinates":[88.77970000000001,23.55513],"type":"Point"}
}