{
  "type": "Feature",
  "properties": {
    "gn:admin1_code":"81",
    "gn:admin2_code":"3026",
    "gn:admin3_code":"302638.0",
    "gn:admin4_code":"30263869.0",
    "gn:asciiname":"Mirerbag",
    "gn:country_code":"BD",
    "gn:dem":10,
    "gn:feature_class":"P",
    "gn:feature_code":"PPL",
    "gn:name":"Mirerb\u0101g",
    "gn:population":0,
    "gn:timezone":"Asia/Dhaka",
    "iso:country":"BD",
    "wof:name":"Mirerbag",
    "wof:placetype":"locality"
},
  "geometry": {"coordinates":[90.41508,23.69256],"type":"Point"}
}