{
  "type": "Feature",
  "properties": {
    "gn:admin1_code":"81",
    "gn:admin2_code":"3093",
    "gn:admin3_code":"309319.0",
    "gn:admin4_code":"30931927.0",
    "gn:asciiname":"Nikla",
    "gn:country_code":"BD",
    "gn:dem":21,
    "gn:feature_class":"P",
    "gn:feature_code":"PPL",
    "gn:name":"Nikla",
    "gn:population":0,
    "gn:timezone":"Asia/Dhaka",
    "iso:country":"BD",
    "name:epo_x_preferred":[
        "Nikla"
    ],
    "name:fas_x_preferred":[
        "\u0646\u06cc\u06a9\u0644\u0627"
    ],
    "name:fra_x_preferred":[
        "Nikla"
    ],
    "name:hun_x_preferred":[
        "Nikla"
    ],
    "name:ita_x_preferred":[
        "Nikla"
    ],
    "name:msa_x_preferred":[
        "Nikla"
    ],
    "name:nld_x_preferred":[
        "Nikla"
    ],
    "name:ron_x_preferred":[
        "Nikla"
    ],
    "name:slk_x_preferred":[
        "Nikla"
    ],
    "name:slv_x_preferred":[
        "Nikla"
    ],
    "name:vie_x_preferred":[
        "Nikla"
    ],
    "name:zho_x_preferred":[
        "\u5c3c\u514b\u6d1b"
    ],
    "wof:name":"Nikla",
    "wof:placetype":"locality"
},
  "geometry": {"coordinates":[89.84869,24.4409],"type":"Point"}
}