{
  "type": "Feature",
  "properties": {
    "gn:admin1_code":"83",
    "gn:admin2_code":"5010",
    "gn:admin3_code":"501095.0",
    "gn:admin4_code":"50109573.0",
    "gn:asciiname":"Chak Nandan",
    "gn:country_code":"BD",
    "gn:dem":25,
    "gn:feature_class":"P",
    "gn:feature_code":"PPL",
    "gn:name":"Chak Nandan",
    "gn:population":0,
    "gn:timezone":"Asia/Dhaka",
    "iso:country":"BD",
    "name:ben_x_preferred":[
        "Chak Nandan"
    ],
    "wof:name":"Chak Nandan",
    "wof:placetype":"locality"
},
  "geometry": {"coordinates":[89.51527,25.02815],"type":"Point"}
}