{
  "type": "Feature",
  "properties": {
    "gn:admin1_code":"83",
    "gn:admin2_code":"5069",
    "gn:admin3_code":"506909.0",
    "gn:admin4_code":"50690976.0",
    "gn:asciiname":"Meri",
    "gn:cc2":"BD",
    "gn:country_code":"BD",
    "gn:dem":17,
    "gn:feature_class":"P",
    "gn:feature_code":"PPL",
    "gn:name":"Meri",
    "gn:population":0,
    "gn:timezone":"Asia/Dhaka",
    "iso:country":"BD",
    "name:ceb_x_preferred":[
        "Meri"
    ],
    "name:deu_x_preferred":[
        "Meri"
    ],
    "name:fin_x_preferred":[
        "Meri"
    ],
    "name:fra_x_preferred":[
        "Meri"
    ],
    "name:hye_x_preferred":[
        "\u0544\u0565\u0580\u056b"
    ],
    "name:lav_x_preferred":[
        "Meri"
    ],
    "name:nld_x_preferred":[
        "Meri"
    ],
    "name:pol_x_preferred":[
        "Meri"
    ],
    "name:ron_x_preferred":[
        "Meri"
    ],
    "name:rus_x_preferred":[
        "\u041c\u0435\u0440\u0438"
    ],
    "name:srp_x_preferred":[
        "\u041c\u0435\u0440\u0438"
    ],
    "name:swe_x_preferred":[
        "Meri"
    ],
    "name:ukr_x_preferred":[
        "\u041c\u0435\u0440\u0456"
    ],
    "name:und_x_variant":[
        "Mari",
        "Meri"
    ],
    "wof:name":"Meri",
    "wof:placetype":"locality"
},
  "geometry": {"coordinates":[88.88333,24.33333],"type":"Point"}
}