{
  "type": "Feature",
  "properties": {
    "gn:admin1_code":"82",
    "gn:admin2_code":"4041.0",
    "gn:admin3_code":"404190.0",
    "gn:admin4_code":"40419025.0",
    "gn:asciiname":"Benapol",
    "gn:country_code":"BD",
    "gn:dem":13,
    "gn:feature_class":"P",
    "gn:feature_code":"PPL",
    "gn:name":"Ben\u0101pol",
    "gn:population":0,
    "gn:timezone":"Asia/Dhaka",
    "iso:country":"BD",
    "name:ben_x_preferred":[
        "Ben\u0101pol"
    ],
    "name:und_x_variant":[
        "Benapole"
    ],
    "wof:name":"Benapol",
    "wof:placetype":"locality"
},
  "geometry": {"coordinates":[88.9059,23.04697],"type":"Point"}
}