{
  "type": "Feature",
  "properties": {
    "gn:admin1_code":"82",
    "gn:admin2_code":"4041.0",
    "gn:admin3_code":"404190.0",
    "gn:admin4_code":"40419025.0",
    "gn:asciiname":"Benapol",
    "gn:country_code":"BD",
    "gn:dem":13,
    "gn:feature_class":"P",
    "gn:feature_code":"PPL",
    "gn:name":"Ben\u0101pol",
    "gn:population":0,
    "gn:timezone":"Asia/Dhaka",
    "iso:country":"BD",
    "name:ben_x_preferred":[
        "Ben\u0101pol"
    ],
    "name:ben_x_variant":[
        "\u09ac\u09c7\u09a8\u09be\u09aa\u09cb\u09b2"
    ],
    "name:fra_x_preferred":[
        "Benapole"
    ],
    "name:hin_x_preferred":[
        "\u092c\u0947\u0928\u093e\u092a\u094b\u0932"
    ],
    "name:pan_x_preferred":[
        "\u0a2c\u0a48\u0a02\u0a28\u0a3e\u0a2a\u0a4b\u0a32"
    ],
    "wof:name":"Benapol",
    "wof:placetype":"locality"
},
  "geometry": {"coordinates":[88.9059,23.04697],"type":"Point"}
}