{
  "type": "Feature",
  "properties": {
    "gn:admin1_code":"82",
    "gn:asciiname":"Raybala",
    "gn:country_code":"BD",
    "gn:dem":7,
    "gn:feature_class":"P",
    "gn:feature_code":"PPL",
    "gn:name":"R\u0101yb\u0101la",
    "gn:population":0,
    "gn:timezone":"Asia/Dhaka",
    "iso:country":"BD",
    "name:ben_x_preferred":[
        "R\u0101yb\u0101la"
    ],
    "wof:name":"Raybala",
    "wof:placetype":"locality"
},
  "geometry": {"coordinates":[90.3099,22.2208],"type":"Point"}
}