{
  "type": "Feature",
  "properties": {
    "gn:admin1_code":"85",
    "gn:admin2_code":"1009.0",
    "gn:admin3_code":"100991.0",
    "gn:admin4_code":"10099157.0",
    "gn:asciiname":"Uttar Chanchra",
    "gn:country_code":"BD",
    "gn:dem":8,
    "gn:feature_class":"P",
    "gn:feature_code":"PPL",
    "gn:name":"Uttar Ch\u0101nchra",
    "gn:population":0,
    "gn:timezone":"Asia/Dhaka",
    "iso:country":"BD",
    "name:ben_x_preferred":[
        "Uttar Ch\u0101nchra"
    ],
    "wof:name":"Uttar Chanchra",
    "wof:placetype":"locality"
},
  "geometry": {"coordinates":[90.82935000000001,22.38222],"type":"Point"}
}