{
  "type": "Feature",
  "properties": {
    "gn:admin1_code":"83",
    "gn:admin2_code":"5064.0",
    "gn:admin3_code":"506460.0",
    "gn:admin4_code":"50646065.0",
    "gn:asciiname":"Chak Abros",
    "gn:country_code":"BD",
    "gn:dem":19,
    "gn:feature_class":"P",
    "gn:feature_code":"PPL",
    "gn:name":"Chak \u0100bros",
    "gn:population":0,
    "gn:timezone":"Asia/Dhaka",
    "iso:country":"BD",
    "name:ben_x_preferred":[
        "Chak \u0100bros"
    ],
    "name:ben_x_variant":[
        "Chak \u0100br\u0101s"
    ],
    "name:und_x_variant":[
        "Chakabrash"
    ],
    "wof:name":"Chak Abros",
    "wof:placetype":"locality"
},
  "geometry": {"coordinates":[88.81777,24.76056],"type":"Point"}
}