{
  "type": "Feature",
  "properties": {
    "gn:admin1_code":"81",
    "gn:admin2_code":"3056",
    "gn:admin3_code":"305678.0",
    "gn:admin4_code":"30567871.0",
    "gn:asciiname":"Nilgram",
    "gn:country_code":"BD",
    "gn:dem":12,
    "gn:feature_class":"P",
    "gn:feature_code":"PPL",
    "gn:name":"Nilgr\u0101m",
    "gn:population":0,
    "gn:timezone":"Asia/Dhaka",
    "iso:country":"BD",
    "wof:name":"Nilgram",
    "wof:placetype":"locality"
},
  "geometry": {"coordinates":[89.83364,23.79109],"type":"Point"}
}