{
  "type": "Feature",
  "properties": {
    "gn:admin1_code":"87",
    "gn:admin2_code":"5549",
    "gn:admin3_code":"554994.0",
    "gn:admin4_code":"55499455.0",
    "gn:asciiname":"Sukdeb Kundu",
    "gn:country_code":"BD",
    "gn:dem":28,
    "gn:feature_class":"P",
    "gn:feature_code":"PPL",
    "gn:name":"Sukdeb Kundu",
    "gn:population":0,
    "gn:timezone":"Asia/Dhaka",
    "iso:country":"BD",
    "name:ben_x_preferred":[
        "Sukdeb Kundu"
    ],
    "wof:name":"Sukdeb Kundu",
    "wof:placetype":"locality"
},
  "geometry": {"coordinates":[89.57625999999998,25.62834],"type":"Point"}
}