{
  "type": "Feature",
  "properties": {
    "gn:admin1_code":"84",
    "gn:admin2_code":"2019",
    "gn:admin3_code":"201915.0",
    "gn:admin4_code":"20191550.0",
    "gn:asciiname":"Sidlai",
    "gn:country_code":"BD",
    "gn:dem":12,
    "gn:feature_class":"P",
    "gn:feature_code":"PPL",
    "gn:name":"Sidl\u0101i",
    "gn:population":0,
    "gn:timezone":"Asia/Dhaka",
    "iso:country":"BD",
    "wof:name":"Sidlai",
    "wof:placetype":"locality"
},
  "geometry": {"coordinates":[91.08524,23.64954],"type":"Point"}
}