{
  "type": "Feature",
  "properties": {
    "gn:admin1_code":"H",
    "gn:admin2_code":"3061",
    "gn:admin3_code":"306120.0",
    "gn:admin4_code":"30612053.0",
    "gn:asciiname":"Susuti",
    "gn:country_code":"BD",
    "gn:dem":15,
    "gn:feature_class":"P",
    "gn:feature_code":"PPL",
    "gn:name":"Susuti",
    "gn:population":0,
    "gn:timezone":"Asia/Dhaka",
    "iso:country":"BD",
    "wof:name":"Susuti",
    "wof:placetype":"locality"
},
  "geometry": {"coordinates":[90.22479,24.54664],"type":"Point"}
}