{
  "type": "Feature",
  "properties": {
    "gn:admin1_code":"82",
    "gn:admin2_code":"4044.0",
    "gn:admin3_code":"404480.0",
    "gn:admin4_code":"40448031.0",
    "gn:asciiname":"Puran Tripura Kandi",
    "gn:country_code":"BD",
    "gn:dem":11,
    "gn:feature_class":"P",
    "gn:feature_code":"PPL",
    "gn:name":"Pur\u0101n Tripura Kandi",
    "gn:population":0,
    "gn:timezone":"Asia/Dhaka",
    "iso:country":"BD",
    "name:ben_x_preferred":[
        "Pur\u0101n Tripura Kandi"
    ],
    "wof:name":"Puran Tripura Kandi",
    "wof:placetype":"locality"
},
  "geometry": {"coordinates":[89.21191999999998,23.61615],"type":"Point"}
}