{
  "type": "Feature",
  "properties": {
    "gn:admin1_code":"87",
    "gn:admin2_code":"5585",
    "gn:admin3_code":"558558.0",
    "gn:admin4_code":"55855811.0",
    "gn:asciiname":"Hasia Chharan",
    "gn:country_code":"BD",
    "gn:dem":32,
    "gn:feature_class":"P",
    "gn:feature_code":"PPL",
    "gn:name":"Hasia Chharan",
    "gn:population":0,
    "gn:timezone":"Asia/Dhaka",
    "iso:country":"BD",
    "name:ben_x_preferred":[
        "Hasia Chharan"
    ],
    "wof:name":"Hasia Chharan",
    "wof:placetype":"locality"
},
  "geometry": {"coordinates":[89.11823000000003,25.53123],"type":"Point"}
}