{
  "type": "Feature",
  "properties": {
    "gn:admin1_code":"85",
    "gn:admin2_code":"1006.0",
    "gn:admin3_code":"100694.0",
    "gn:admin4_code":"10069421.0",
    "gn:asciiname":"Garia",
    "gn:country_code":"BD",
    "gn:dem":14,
    "gn:feature_class":"P",
    "gn:feature_code":"PPL",
    "gn:name":"Garia",
    "gn:population":0,
    "gn:timezone":"Asia/Dhaka",
    "iso:country":"BD",
    "name:ben_x_preferred":[
        "\u0997\u09a1\u09bc\u09bf\u09af\u09bc\u09be"
    ],
    "wof:name":"Garia",
    "wof:placetype":"locality"
},
  "geometry": {"coordinates":[90.22929000000001,22.8524],"type":"Point"}
}