{
  "type": "Feature",
  "properties": {
    "gn:admin1_code":"84",
    "gn:admin2_code":"2051.0",
    "gn:admin3_code":"205143.0",
    "gn:admin4_code":"20514300.0",
    "gn:asciiname":"Banchhanagar",
    "gn:country_code":"BD",
    "gn:dem":15,
    "gn:feature_class":"P",
    "gn:feature_code":"PPL",
    "gn:name":"B\u0101nchh\u0101nagar",
    "gn:population":0,
    "gn:timezone":"Asia/Dhaka",
    "iso:country":"BD",
    "wof:name":"Banchhanagar",
    "wof:placetype":"locality"
},
  "geometry": {"coordinates":[90.81985,22.97126],"type":"Point"}
}