{
  "type": "Feature",
  "properties": {
    "gn:admin1_code":"82",
    "gn:admin2_code":"4065.0",
    "gn:admin3_code":"406528.0",
    "gn:admin4_code":"40652847.0",
    "gn:asciiname":"Bil Aphar",
    "gn:country_code":"BD",
    "gn:dem":8,
    "gn:feature_class":"P",
    "gn:feature_code":"PPL",
    "gn:name":"B\u012bl \u0100ph\u0101r",
    "gn:population":0,
    "gn:timezone":"Asia/Dhaka",
    "iso:country":"BD",
    "name:ben_x_preferred":[
        "B\u012bl \u0100ph\u0101r"
    ],
    "wof:name":"Bil Aphar",
    "wof:placetype":"locality"
},
  "geometry": {"coordinates":[89.71554,22.98745],"type":"Point"}
}