{
  "type": "Feature",
  "properties": {
    "gn:admin1_code":"85",
    "gn:admin2_code":"1079.0",
    "gn:admin3_code":"107914.0",
    "gn:admin4_code":"10791411.0",
    "gn:asciiname":"Gazipur",
    "gn:country_code":"BD",
    "gn:dem":15,
    "gn:feature_class":"P",
    "gn:feature_code":"PPL",
    "gn:name":"G\u0101zipur",
    "gn:population":0,
    "gn:timezone":"Asia/Dhaka",
    "iso:country":"BD",
    "name:ben_x_preferred":[
        "G\u0101zipur"
    ],
    "wof:name":"Gazipur",
    "wof:placetype":"locality"
},
  "geometry": {"coordinates":[90.04876999999998,22.44869],"type":"Point"}
}