{
  "type": "Feature",
  "properties": {
    "gn:admin1_code":"82",
    "gn:admin2_code":"4087",
    "gn:admin3_code":"408790.0",
    "gn:admin4_code":"40879031.0",
    "gn:asciiname":"Prasadpur",
    "gn:country_code":"BD",
    "gn:dem":9,
    "gn:feature_class":"P",
    "gn:feature_code":"PPL",
    "gn:name":"Pras\u0101dpur",
    "gn:population":0,
    "gn:timezone":"Asia/Dhaka",
    "iso:country":"BD",
    "wof:name":"Prasadpur",
    "wof:placetype":"locality"
},
  "geometry": {"coordinates":[89.31307,22.7356],"type":"Point"}
}