{
  "type": "Feature",
  "properties": {
    "gn:admin1_code":"87",
    "gn:admin2_code":"5573.0",
    "gn:admin3_code":"557364.0",
    "gn:admin4_code":"55736444.0",
    "gn:asciiname":"Dhukuri",
    "gn:country_code":"BD",
    "gn:dem":54,
    "gn:feature_class":"P",
    "gn:feature_code":"PPL",
    "gn:name":"Dhukuri",
    "gn:population":0,
    "gn:timezone":"Asia/Dhaka",
    "iso:country":"BD",
    "name:ben_x_preferred":[
        "Dhukuri"
    ],
    "name:ben_x_variant":[
        "Dukuri"
    ],
    "wof:name":"Dhukuri",
    "wof:placetype":"locality"
},
  "geometry": {"coordinates":[88.75745000000001,25.94446],"type":"Point"}
}