{
  "type": "Feature",
  "properties": {
    "gn:admin1_code":"81",
    "gn:admin2_code":"3054.0",
    "gn:admin3_code":"305440.0",
    "gn:admin4_code":"30544012.0",
    "gn:asciiname":"Purba Botla",
    "gn:country_code":"BD",
    "gn:dem":6,
    "gn:feature_class":"P",
    "gn:feature_code":"PPL",
    "gn:name":"Purba Botla",
    "gn:population":0,
    "gn:timezone":"Asia/Dhaka",
    "iso:country":"BD",
    "name:und_x_variant":[
        "East Botla"
    ],
    "wof:name":"Purba Botla",
    "wof:placetype":"locality"
},
  "geometry": {"coordinates":[90.16540999999999,23.11509],"type":"Point"}
}