{
  "type": "Feature",
  "properties": {
    "gn:admin1_code":"83",
    "gn:admin2_code":"5081.0",
    "gn:admin3_code":"508172.0",
    "gn:admin4_code":"50817231.0",
    "gn:asciiname":"Baraipara",
    "gn:country_code":"BD",
    "gn:dem":19,
    "gn:feature_class":"P",
    "gn:feature_code":"PPL",
    "gn:name":"B\u0101raipara",
    "gn:population":0,
    "gn:timezone":"Asia/Dhaka",
    "iso:country":"BD",
    "name:ben_x_preferred":[
        "B\u0101raipara"
    ],
    "wof:name":"Baraipara",
    "wof:placetype":"locality"
},
  "geometry": {"coordinates":[88.58197,24.3963],"type":"Point"}
}