{
  "type": "Feature",
  "properties": {
    "gn:admin1_code":"81",
    "gn:admin2_code":"3026.0",
    "gn:admin3_code":"302640.0",
    "gn:admin4_code":"30264056.0",
    "gn:asciiname":"Shahbag",
    "gn:country_code":"BD",
    "gn:dem":16,
    "gn:feature_class":"P",
    "gn:feature_code":"PPL",
    "gn:name":"Shahbag",
    "gn:population":0,
    "gn:timezone":"Asia/Dhaka",
    "iso:country":"BD",
    "name:ben_x_preferred":[
        "\u09b6\u09be\u09b9\u09ac\u09be\u0997"
    ],
    "name:fas_x_preferred":[
        "\u0634\u0627\u0647\u200c\u0628\u0627\u063a"
    ],
    "name:mar_x_preferred":[
        "\u0936\u093e\u0939\u092c\u093e\u0917"
    ],
    "wof:name":"Shahbag",
    "wof:placetype":"locality"
},
  "geometry": {"coordinates":[90.40000000000001,23.738],"type":"Point"}
}