{
  "type": "Feature",
  "properties": {
    "gn:admin1_code":"87",
    "gn:admin2_code":"5532",
    "gn:admin3_code":"553230.0",
    "gn:admin4_code":"55323050.0",
    "gn:asciiname":"Pantair",
    "gn:country_code":"BD",
    "gn:dem":23,
    "gn:feature_class":"P",
    "gn:feature_code":"PPL",
    "gn:name":"Pantair",
    "gn:population":0,
    "gn:timezone":"Asia/Dhaka",
    "iso:country":"BD",
    "name:und_x_variant":[
        "Pant\u0101i"
    ],
    "wof:name":"Pantair",
    "wof:placetype":"locality"
},
  "geometry": {"coordinates":[89.47691999999998,25.1294],"type":"Point"}
}