{
  "type": "Feature",
  "properties": {
    "gn:admin1_code":"87",
    "gn:admin2_code":"5577.0",
    "gn:admin3_code":"557704.0",
    "gn:admin4_code":"55770481.0",
    "gn:asciiname":"Guditola",
    "gn:country_code":"BD",
    "gn:dem":69,
    "gn:feature_class":"P",
    "gn:feature_code":"PPL",
    "gn:name":"Gud\u012btola",
    "gn:population":0,
    "gn:timezone":"Asia/Dhaka",
    "iso:country":"BD",
    "name:ben_x_preferred":[
        "Gud\u012btola"
    ],
    "wof:name":"Guditola",
    "wof:placetype":"locality"
},
  "geometry": {"coordinates":[88.35854999999999,26.24922],"type":"Point"}
}