{
  "type": "Feature",
  "properties": {
    "gn:admin1_code":"84",
    "gn:admin2_code":"2013.0",
    "gn:admin3_code":"201379.0",
    "gn:admin4_code":"20137908.0",
    "gn:asciiname":"Chhota Char Kalia",
    "gn:cc2":"BD",
    "gn:country_code":"BD",
    "gn:dem":5,
    "gn:feature_class":"P",
    "gn:feature_code":"PPL",
    "gn:name":"Chhota Char K\u0101lia",
    "gn:population":0,
    "gn:timezone":"Asia/Dhaka",
    "iso:country":"BD",
    "name:und_x_variant":[
        "Chotto Charkalia",
        "Chhota Char K\u0101lia"
    ],
    "wof:name":"Chhota Char Kalia",
    "wof:placetype":"locality"
},
  "geometry": {"coordinates":[90.63333,23.33333],"type":"Point"}
}