{
  "type": "Feature",
  "properties": {
    "gn:admin1_code":"82",
    "gn:admin2_code":"4050.0",
    "gn:admin3_code":"405079.0",
    "gn:admin4_code":"40507912.0",
    "gn:asciiname":"Alichara",
    "gn:country_code":"BD",
    "gn:dem":15,
    "gn:feature_class":"P",
    "gn:feature_code":"PPL",
    "gn:name":"Alichara",
    "gn:population":0,
    "gn:timezone":"Asia/Dhaka",
    "iso:country":"BD",
    "name:ben_x_preferred":[
        "Alichara"
    ],
    "name:ben_x_variant":[
        "Bara \u0100ilch\u0101ra"
    ],
    "wof:name":"Alichara",
    "wof:placetype":"locality"
},
  "geometry": {"coordinates":[89.03804000000002,23.85267],"type":"Point"}
}