{
  "type": "Feature",
  "properties": {
    "gn:admin1_code":"87",
    "gn:admin2_code":"5577.0",
    "gn:admin3_code":"557725.0",
    "gn:admin4_code":"55772529.0",
    "gn:asciiname":"Nagar Khalil Khan",
    "gn:country_code":"BD",
    "gn:dem":65,
    "gn:feature_class":"P",
    "gn:feature_code":"PPL",
    "gn:name":"Nagar Khalil Khan",
    "gn:population":0,
    "gn:timezone":"Asia/Dhaka",
    "iso:country":"BD",
    "name:ben_x_preferred":[
        "Nagar Khalil Khan"
    ],
    "wof:name":"Nagar Khalil Khan",
    "wof:placetype":"locality"
},
  "geometry": {"coordinates":[88.56398,26.17564],"type":"Point"}
}