{
  "type": "Feature",
  "properties": {
    "gn:admin1_code":"83",
    "gn:admin2_code":"5010.0",
    "gn:admin3_code":"501040.0",
    "gn:admin4_code":"50104061.0",
    "gn:asciiname":"Hamidpur",
    "gn:country_code":"BD",
    "gn:dem":24,
    "gn:feature_class":"P",
    "gn:feature_code":"PPL",
    "gn:name":"H\u0101midpur",
    "gn:population":0,
    "gn:timezone":"Asia/Dhaka",
    "iso:country":"BD",
    "wof:name":"Hamidpur",
    "wof:placetype":"locality"
},
  "geometry": {"coordinates":[89.43494,24.88573],"type":"Point"}
}