{
  "type": "Feature",
  "properties": {
    "gn:admin1_code":"87",
    "gn:admin2_code":"5573.0",
    "gn:admin3_code":"557312.0",
    "gn:admin4_code":"55731257.0",
    "gn:asciiname":"Balapara",
    "gn:country_code":"BD",
    "gn:dem":62,
    "gn:feature_class":"P",
    "gn:feature_code":"PPL",
    "gn:name":"B\u0101l\u0101p\u0101ra",
    "gn:population":0,
    "gn:timezone":"Asia/Dhaka",
    "iso:country":"BD",
    "name:ben_x_preferred":[
        "B\u0101l\u0101p\u0101ra"
    ],
    "wof:name":"Balapara",
    "wof:placetype":"locality"
},
  "geometry": {"coordinates":[88.92752,26.20462],"type":"Point"}
}