{
  "type": "Feature",
  "properties": {
    "gn:admin1_code":"81",
    "gn:admin2_code":"3029.0",
    "gn:admin3_code":"302947.0",
    "gn:admin4_code":"30294763.0",
    "gn:asciiname":"Gazaria",
    "gn:country_code":"BD",
    "gn:dem":14,
    "gn:feature_class":"P",
    "gn:feature_code":"PPL",
    "gn:name":"Gaz\u0101ria",
    "gn:population":0,
    "gn:timezone":"Asia/Dhaka",
    "iso:country":"BD",
    "name:ita_x_preferred":[
        "Gazaria"
    ],
    "wof:name":"Gazaria",
    "wof:placetype":"locality"
},
  "geometry": {"coordinates":[89.75041999999998,23.52955],"type":"Point"}
}