{
  "type": "Feature",
  "properties": {
    "gn:admin1_code":"82",
    "gn:admin2_code":"4018.0",
    "gn:admin3_code":"401831.0",
    "gn:admin4_code":"40183159.0",
    "gn:asciiname":"Chalisagar",
    "gn:country_code":"BD",
    "gn:dem":19,
    "gn:feature_class":"P",
    "gn:feature_code":"PPL",
    "gn:name":"Chalisagar",
    "gn:population":0,
    "gn:timezone":"Asia/Dhaka",
    "iso:country":"BD",
    "name:ben_x_preferred":[
        "Chalisagar"
    ],
    "wof:name":"Chalisagar",
    "wof:placetype":"locality"
},
  "geometry": {"coordinates":[88.66046,23.62435],"type":"Point"}
}