{
  "type": "Feature",
  "properties": {
    "gn:admin1_code":"82",
    "gn:admin2_code":"4044.0",
    "gn:admin3_code":"404419.0",
    "gn:admin4_code":"40441989.0",
    "gn:asciiname":"Bardi",
    "gn:country_code":"BD",
    "gn:dem":17,
    "gn:feature_class":"P",
    "gn:feature_code":"PPL",
    "gn:name":"Bardi",
    "gn:population":0,
    "gn:timezone":"Asia/Dhaka",
    "iso:country":"BD",
    "name:ben_x_preferred":[
        "Bardi"
    ],
    "name:ceb_x_preferred":[
        "Bardi"
    ],
    "name:deu_x_preferred":[
        "Bardi"
    ],
    "name:fra_x_preferred":[
        "Bardi"
    ],
    "name:glg_x_preferred":[
        "Bardi"
    ],
    "name:hye_x_preferred":[
        "\u0532\u0561\u0580\u0564\u056b"
    ],
    "name:ita_x_preferred":[
        "Bardi"
    ],
    "name:jpn_x_preferred":[
        "\u30d0\u30eb\u30c7\u30a3"
    ],
    "name:nld_x_preferred":[
        "Bardi"
    ],
    "name:pol_x_preferred":[
        "Bardi"
    ],
    "name:slv_x_preferred":[
        "Bardi"
    ],
    "name:swe_x_preferred":[
        "Bardi"
    ],
    "name:uzb_x_preferred":[
        "Bardi"
    ],
    "name:vie_x_preferred":[
        "Bardi"
    ],
    "wof:name":"Bardi",
    "wof:placetype":"locality"
},
  "geometry": {"coordinates":[89.00845,23.56921],"type":"Point"}
}