{
  "type": "Feature",
  "properties": {
    "gn:admin1_code":"81",
    "gn:admin2_code":"3054.0",
    "gn:admin3_code":"305454.0",
    "gn:admin4_code":"30545423.0",
    "gn:asciiname":"Patiladi",
    "gn:country_code":"BD",
    "gn:dem":9,
    "gn:feature_class":"P",
    "gn:feature_code":"PPL",
    "gn:name":"Patil\u0101di",
    "gn:population":0,
    "gn:timezone":"Asia/Dhaka",
    "iso:country":"BD",
    "name:und_x_variant":[
        "Patil\u0101di",
        "H\u0101usdi P\u0101til\u0101di"
    ],
    "wof:name":"Patiladi",
    "wof:placetype":"locality"
},
  "geometry": {"coordinates":[90.16118,23.20407],"type":"Point"}
}