{
  "type": "Feature",
  "properties": {
    "gn:admin1_code":"83",
    "gn:admin2_code":"5064",
    "gn:admin3_code":"506406.0",
    "gn:admin4_code":"50640663.0",
    "gn:asciiname":"Pukhuria",
    "gn:country_code":"BD",
    "gn:dem":24,
    "gn:feature_class":"P",
    "gn:feature_code":"PPL",
    "gn:name":"Pukhuria",
    "gn:population":0,
    "gn:timezone":"Asia/Dhaka",
    "iso:country":"BD",
    "name:ben_x_preferred":[
        "Pukhuria"
    ],
    "name:und_x_variant":[
        "Pukuria"
    ],
    "wof:name":"Pukhuria",
    "wof:placetype":"locality"
},
  "geometry": {"coordinates":[88.96153000000002,24.94517],"type":"Point"}
}