{
  "type": "Feature",
  "properties": {
    "gn:admin1_code":"83",
    "gn:asciiname":"Jamira",
    "gn:country_code":"BD",
    "gn:dem":20,
    "gn:feature_class":"P",
    "gn:feature_code":"PPL",
    "gn:name":"Jamira",
    "gn:population":0,
    "gn:timezone":"Asia/Dhaka",
    "iso:country":"BD",
    "name:ben_x_preferred":[
        "Jamira"
    ],
    "wof:name":"Jamira",
    "wof:placetype":"locality"
},
  "geometry": {"coordinates":[89.59975,25.11373],"type":"Point"}
}