{
  "type": "Feature",
  "properties": {
    "gn:admin1_code":"82",
    "gn:admin2_code":"4047.0",
    "gn:admin3_code":"404753.0",
    "gn:admin4_code":"40475305.0",
    "gn:asciiname":"Bhandarpol",
    "gn:country_code":"BD",
    "gn:dem":6,
    "gn:feature_class":"P",
    "gn:feature_code":"PPL",
    "gn:name":"Bh\u0101ndarpol",
    "gn:population":0,
    "gn:timezone":"Asia/Dhaka",
    "iso:country":"BD",
    "name:ben_x_preferred":[
        "Bh\u0101ndarpol"
    ],
    "name:ben_x_variant":[
        "Bh\u0101nd\u0101rpole"
    ],
    "wof:name":"Bhandarpol",
    "wof:placetype":"locality"
},
  "geometry": {"coordinates":[89.33564,22.47463],"type":"Point"}
}