{
  "type": "Feature",
  "properties": {
    "gn:admin1_code":"87",
    "gn:admin2_code":"5527",
    "gn:admin3_code":"552777.0",
    "gn:admin4_code":"55277751.0",
    "gn:asciiname":"Khorakhai",
    "gn:country_code":"BD",
    "gn:dem":43,
    "gn:feature_class":"P",
    "gn:feature_code":"PPL",
    "gn:name":"Khor\u0101kh\u0101i",
    "gn:population":0,
    "gn:timezone":"Asia/Dhaka",
    "iso:country":"BD",
    "name:ben_x_preferred":[
        "Khor\u0101kh\u0101i"
    ],
    "name:ben_x_variant":[
        "Khor\u0101kh\u0101l"
    ],
    "wof:name":"Khorakhai",
    "wof:placetype":"locality"
},
  "geometry": {"coordinates":[88.84302,25.68732],"type":"Point"}
}