{
  "type": "Feature",
  "properties": {
    "gn:admin1_code":"87",
    "gn:admin2_code":"5577.0",
    "gn:admin3_code":"557790.0",
    "gn:admin4_code":"55779067.0",
    "gn:asciiname":"Howragachh",
    "gn:country_code":"BD",
    "gn:dem":95,
    "gn:feature_class":"P",
    "gn:feature_code":"PPL",
    "gn:name":"Howr\u0101g\u0101chh",
    "gn:population":0,
    "gn:timezone":"Asia/Dhaka",
    "iso:country":"BD",
    "name:ben_x_preferred":[
        "Howr\u0101g\u0101chh"
    ],
    "wof:name":"Howragachh",
    "wof:placetype":"locality"
},
  "geometry": {"coordinates":[88.4194,26.51616],"type":"Point"}
}