{
  "type": "Feature",
  "properties": {
    "gn:admin1_code":"83",
    "gn:admin2_code":"5010.0",
    "gn:admin3_code":"501027.0",
    "gn:admin4_code":"50102719.0",
    "gn:asciiname":"Chaukibari",
    "gn:country_code":"BD",
    "gn:dem":19,
    "gn:feature_class":"P",
    "gn:feature_code":"PPL",
    "gn:name":"Chaukib\u0101ri",
    "gn:population":0,
    "gn:timezone":"Asia/Dhaka",
    "iso:country":"BD",
    "wof:name":"Chaukibari",
    "wof:placetype":"locality"
},
  "geometry": {"coordinates":[89.53825999999999,24.6397],"type":"Point"}
}