{
  "type": "Feature",
  "properties": {
    "gn:admin1_code":"87",
    "gn:admin2_code":"5573.0",
    "gn:admin3_code":"557315.0",
    "gn:admin4_code":"55731528.0",
    "gn:asciiname":"Jogipara",
    "gn:country_code":"BD",
    "gn:dem":57,
    "gn:feature_class":"P",
    "gn:feature_code":"PPL",
    "gn:name":"Jogip\u0101ra",
    "gn:population":0,
    "gn:timezone":"Asia/Dhaka",
    "iso:country":"BD",
    "name:ben_x_preferred":[
        "Jogip\u0101ra"
    ],
    "wof:name":"Jogipara",
    "wof:placetype":"locality"
},
  "geometry": {"coordinates":[88.83865,26.12537],"type":"Point"}
}