{
  "type": "Feature",
  "properties": {
    "gn:admin1_code":"H",
    "gn:admin2_code":"3061",
    "gn:admin3_code":"306131.0",
    "gn:admin4_code":"30613113.0",
    "gn:asciiname":"Narayanpur",
    "gn:country_code":"BD",
    "gn:dem":15,
    "gn:feature_class":"P",
    "gn:feature_code":"PPL",
    "gn:name":"N\u0101ray\u0101npur",
    "gn:population":0,
    "gn:timezone":"Asia/Dhaka",
    "iso:country":"BD",
    "name:ceb_x_preferred":[
        "Narayanpur"
    ],
    "name:fra_x_preferred":[
        "Narayanpur"
    ],
    "name:pol_x_preferred":[
        "Narayanpur"
    ],
    "name:swe_x_preferred":[
        "Narayanpur"
    ],
    "name:tel_x_preferred":[
        "\u0c28\u0c3e\u0c30\u0c3e\u0c2f\u0c23\u0c4d\u200c\u0c2a\u0c42\u0c30\u0c4d"
    ],
    "name:und_x_variant":[
        "N\u0101ray\u0101npur",
        "P\u0101ra N\u0101r\u0101yanpur"
    ],
    "wof:name":"Narayanpur",
    "wof:placetype":"locality"
},
  "geometry": {"coordinates":[90.57999,24.6413],"type":"Point"}
}