{
  "type": "Feature",
  "properties": {
    "gn:admin1_code":"86",
    "gn:admin2_code":"6091",
    "gn:admin3_code":"609120.0",
    "gn:admin4_code":"60912031.0",
    "gn:asciiname":"Karpara",
    "gn:country_code":"BD",
    "gn:dem":20,
    "gn:feature_class":"P",
    "gn:feature_code":"PPL",
    "gn:name":"Karp\u0101ra",
    "gn:population":0,
    "gn:timezone":"Asia/Dhaka",
    "iso:country":"BD",
    "name:und_x_variant":[
        "Karp\u0101ra"
    ],
    "wof:name":"Karpara",
    "wof:placetype":"locality"
},
  "geometry": {"coordinates":[91.68737,24.8533],"type":"Point"}
}