{
  "type": "Feature",
  "properties": {
    "gn:admin1_code":"87",
    "gn:admin2_code":"5549",
    "gn:admin3_code":"554977.0",
    "gn:admin4_code":"55497773.0",
    "gn:asciiname":"Natadanga",
    "gn:country_code":"BD",
    "gn:dem":31,
    "gn:feature_class":"P",
    "gn:feature_code":"PPL",
    "gn:name":"N\u0101t\u0101d\u0101nga",
    "gn:population":0,
    "gn:timezone":"Asia/Dhaka",
    "iso:country":"BD",
    "name:ben_x_preferred":[
        "N\u0101t\u0101d\u0101nga"
    ],
    "wof:name":"Natadanga",
    "wof:placetype":"locality"
},
  "geometry": {"coordinates":[89.52011,25.78134],"type":"Point"}
}