{
  "type": "Feature",
  "properties": {
    "gn:admin1_code":"82",
    "gn:admin2_code":"4041",
    "gn:admin3_code":"404147.0",
    "gn:admin4_code":"40414729.0",
    "gn:asciiname":"Kshitibdia",
    "gn:country_code":"BD",
    "gn:dem":14,
    "gn:feature_class":"P",
    "gn:feature_code":"PPL",
    "gn:name":"Kshitibdia",
    "gn:population":0,
    "gn:timezone":"Asia/Dhaka",
    "iso:country":"BD",
    "name:ben_x_preferred":[
        "Kshitibdia"
    ],
    "wof:name":"Kshitibdia",
    "wof:placetype":"locality"
},
  "geometry": {"coordinates":[89.16871999999999,23.2043],"type":"Point"}
}