{
  "type": "Feature",
  "properties": {
    "gn:admin1_code":"87",
    "gn:admin2_code":"5577.0",
    "gn:admin3_code":"557773.0",
    "gn:admin4_code":"55777323.0",
    "gn:asciiname":"Ramaipara",
    "gn:country_code":"BD",
    "gn:dem":69,
    "gn:feature_class":"P",
    "gn:feature_code":"PPL",
    "gn:name":"Ram\u0101ip\u0101ra",
    "gn:population":0,
    "gn:timezone":"Asia/Dhaka",
    "iso:country":"BD",
    "name:ben_x_preferred":[
        "Ram\u0101ip\u0101ra"
    ],
    "wof:name":"Ramaipara",
    "wof:placetype":"locality"
},
  "geometry": {"coordinates":[88.67213000000002,26.3268],"type":"Point"}
}