{
  "type": "Feature",
  "properties": {
    "gn:admin1_code":"84",
    "gn:admin2_code":"2019",
    "gn:admin3_code":"201981.0",
    "gn:admin4_code":"20198136.0",
    "gn:asciiname":"Siddheswari",
    "gn:country_code":"BD",
    "gn:dem":11,
    "gn:feature_class":"P",
    "gn:feature_code":"PPL",
    "gn:name":"Siddheswari",
    "gn:population":0,
    "gn:timezone":"Asia/Dhaka",
    "iso:country":"BD",
    "wof:name":"Siddheswari",
    "wof:placetype":"locality"
},
  "geometry": {"coordinates":[90.92422000000001,23.59189],"type":"Point"}
}