{
  "type": "Feature",
  "properties": {
    "gn:admin1_code":"83",
    "gn:admin2_code":"5038.0",
    "gn:admin3_code":"503874.0",
    "gn:admin4_code":"50387410.0",
    "gn:asciiname":"Shailatti",
    "gn:country_code":"BD",
    "gn:dem":28,
    "gn:feature_class":"P",
    "gn:feature_code":"PPL",
    "gn:name":"Shailatti",
    "gn:population":0,
    "gn:timezone":"Asia/Dhaka",
    "iso:country":"BD",
    "name:ben_x_preferred":[
        "Shailatti"
    ],
    "wof:name":"Shailatti",
    "wof:placetype":"locality"
},
  "geometry": {"coordinates":[89.18853,25.18392],"type":"Point"}
}