{
  "type": "Feature",
  "properties": {
    "gn:admin1_code":"87",
    "gn:admin2_code":"5532.0",
    "gn:admin3_code":"553288.0",
    "gn:admin4_code":"55328809.0",
    "gn:asciiname":"Bharatkhali",
    "gn:country_code":"BD",
    "gn:dem":23,
    "gn:feature_class":"P",
    "gn:feature_code":"PPL",
    "gn:name":"Bharatkh\u0101li",
    "gn:population":0,
    "gn:timezone":"Asia/Dhaka",
    "iso:country":"BD",
    "wof:name":"Bharatkhali",
    "wof:placetype":"locality"
},
  "geometry": {"coordinates":[89.58664,25.17205],"type":"Point"}
}