{
  "type": "Feature",
  "properties": {
    "gn:admin1_code":"82",
    "gn:admin2_code":"4055.0",
    "gn:admin3_code":"405557.0",
    "gn:admin4_code":"40555774.0",
    "gn:asciiname":"Satyipur",
    "gn:country_code":"BD",
    "gn:dem":13,
    "gn:feature_class":"P",
    "gn:feature_code":"PPL",
    "gn:name":"Satyipur",
    "gn:population":0,
    "gn:timezone":"Asia/Dhaka",
    "iso:country":"BD",
    "name:ben_x_preferred":[
        "Satyipur"
    ],
    "wof:name":"Satyipur",
    "wof:placetype":"locality"
},
  "geometry": {"coordinates":[89.39284000000001,23.44806],"type":"Point"}
}