{
  "type": "Feature",
  "properties": {
    "gn:admin1_code":"82",
    "gn:asciiname":"Char Ar Kalmi",
    "gn:country_code":"BD",
    "gn:dem":8,
    "gn:feature_class":"P",
    "gn:feature_code":"PPL",
    "gn:name":"Char Ar Kalmi",
    "gn:population":0,
    "gn:timezone":"Asia/Dhaka",
    "iso:country":"BD",
    "name:ben_x_preferred":[
        "Char Ar Kalmi"
    ],
    "name:ben_x_variant":[
        "\u0100r Kalmi"
    ],
    "name:und_x_variant":[
        "Arkamli"
    ],
    "wof:name":"Char Ar Kalmi",
    "wof:placetype":"locality"
},
  "geometry": {"coordinates":[90.65246,22.08139],"type":"Point"}
}