{
  "type": "Feature",
  "properties": {
    "gn:admin1_code":"83",
    "gn:admin2_code":"5010",
    "gn:admin3_code":"501040.0",
    "gn:admin4_code":"50104088.0",
    "gn:asciiname":"Sonaray Muchikhali",
    "gn:country_code":"BD",
    "gn:dem":21,
    "gn:feature_class":"P",
    "gn:feature_code":"PPL",
    "gn:name":"Son\u0101ray Muchikh\u0101li",
    "gn:population":0,
    "gn:timezone":"Asia/Dhaka",
    "iso:country":"BD",
    "name:und_x_variant":[
        "Sonarai Muchikhali",
        "Son\u0101ray Muchikh\u0101li"
    ],
    "wof:name":"Sonaray Muchikhali",
    "wof:placetype":"locality"
},
  "geometry": {"coordinates":[89.43751,24.9474],"type":"Point"}
}