{
  "type": "Feature",
  "properties": {
    "gn:admin1_code":"85",
    "gn:admin2_code":"1042",
    "gn:admin3_code":"104273.0",
    "gn:admin4_code":"10427384.0",
    "gn:asciiname":"Madhabpasa",
    "gn:country_code":"BD",
    "gn:dem":7,
    "gn:feature_class":"P",
    "gn:feature_code":"PPL",
    "gn:name":"M\u0101dhabp\u0101sa",
    "gn:population":0,
    "gn:timezone":"Asia/Dhaka",
    "iso:country":"BD",
    "wof:name":"Madhabpasa",
    "wof:placetype":"locality"
},
  "geometry": {"coordinates":[90.29402,22.61283],"type":"Point"}
}