{
  "type": "Feature",
  "properties": {
    "gn:admin1_code":"81",
    "gn:admin2_code":"3068",
    "gn:admin3_code":"306863.0",
    "gn:admin4_code":"30686347.0",
    "gn:asciiname":"Nagar Narasingpur",
    "gn:country_code":"BD",
    "gn:dem":9,
    "gn:feature_class":"P",
    "gn:feature_code":"PPL",
    "gn:name":"Nagar Narasingpur",
    "gn:population":0,
    "gn:timezone":"Asia/Dhaka",
    "iso:country":"BD",
    "wof:name":"Nagar Narasingpur",
    "wof:placetype":"locality"
},
  "geometry": {"coordinates":[90.69042,23.96465],"type":"Point"}
}