{
  "type": "Feature",
  "properties": {
    "gn:admin1_code":"84",
    "gn:admin2_code":"2013.0",
    "gn:admin3_code":"201322.0",
    "gn:admin4_code":"20132222.0",
    "gn:asciiname":"Brahman Sakhua",
    "gn:country_code":"BD",
    "gn:dem":11,
    "gn:feature_class":"P",
    "gn:feature_code":"PPL",
    "gn:name":"Br\u0101hman S\u0101khua",
    "gn:population":0,
    "gn:timezone":"Asia/Dhaka",
    "iso:country":"BD",
    "wof:name":"Brahman Sakhua",
    "wof:placetype":"locality"
},
  "geometry": {"coordinates":[90.67953,23.18134],"type":"Point"}
}