{
  "type": "Feature",
  "properties": {
    "gn:admin1_code":"85",
    "gn:admin2_code":"1042.0",
    "gn:admin3_code":"104240.0",
    "gn:admin4_code":"10424095.0",
    "gn:asciiname":"Guatan",
    "gn:country_code":"BD",
    "gn:dem":14,
    "gn:feature_class":"P",
    "gn:feature_code":"PPL",
    "gn:name":"Gu\u0101tan",
    "gn:population":0,
    "gn:timezone":"Asia/Dhaka",
    "iso:country":"BD",
    "name:und_x_variant":[
        "Gu\u0101tan"
    ],
    "wof:name":"Guatan",
    "wof:placetype":"locality"
},
  "geometry": {"coordinates":[90.10971000000001,22.61342],"type":"Point"}
}