{
  "type": "Feature",
  "properties": {
    "gn:admin1_code":"83",
    "gn:admin2_code":"5070.0",
    "gn:admin3_code":"507037.0",
    "gn:admin4_code":"50703773.0",
    "gn:asciiname":"Tegharia",
    "gn:country_code":"BD",
    "gn:dem":35,
    "gn:feature_class":"P",
    "gn:feature_code":"PPL",
    "gn:name":"Tegharia",
    "gn:population":0,
    "gn:timezone":"Asia/Dhaka",
    "iso:country":"BD",
    "name:ben_x_preferred":[
        "Tegharia"
    ],
    "wof:name":"Tegharia",
    "wof:placetype":"locality"
},
  "geometry": {"coordinates":[88.40859,24.90198],"type":"Point"}
}