{
  "type": "Feature",
  "properties": {
    "gn:admin1_code":"81",
    "gn:admin2_code":"3033.0",
    "gn:admin3_code":"303334.0",
    "gn:admin4_code":"30333460.0",
    "gn:asciiname":"Chhailadi",
    "gn:country_code":"BD",
    "gn:dem":14,
    "gn:feature_class":"P",
    "gn:feature_code":"PPL",
    "gn:name":"Chhail\u0101di",
    "gn:population":0,
    "gn:timezone":"Asia/Dhaka",
    "iso:country":"BD",
    "wof:name":"Chhailadi",
    "wof:placetype":"locality"
},
  "geometry": {"coordinates":[90.58355,23.98396],"type":"Point"}
}