{
  "type": "Feature",
  "properties": {
    "gn:admin1_code":"82",
    "gn:admin2_code":"4055",
    "gn:admin3_code":"405566.0",
    "gn:admin4_code":"40556663.0",
    "gn:asciiname":"Saldha",
    "gn:country_code":"BD",
    "gn:dem":10,
    "gn:feature_class":"P",
    "gn:feature_code":"PPL",
    "gn:name":"S\u0101ldha",
    "gn:population":0,
    "gn:timezone":"Asia/Dhaka",
    "iso:country":"BD",
    "wof:name":"Saldha",
    "wof:placetype":"locality"
},
  "geometry": {"coordinates":[89.54519999999999,23.32343],"type":"Point"}
}