{
  "type": "Feature",
  "properties": {
    "gn:admin1_code":"81",
    "gn:admin2_code":"3033",
    "gn:admin3_code":"303334.0",
    "gn:admin4_code":"30333408.0",
    "gn:asciiname":"Iswarpur",
    "gn:country_code":"BD",
    "gn:dem":13,
    "gn:feature_class":"P",
    "gn:feature_code":"PPL",
    "gn:name":"Iswarpur",
    "gn:population":0,
    "gn:timezone":"Asia/Dhaka",
    "iso:country":"BD",
    "wof:name":"Iswarpur",
    "wof:placetype":"locality"
},
  "geometry": {"coordinates":[90.58641,23.95271],"type":"Point"}
}