{
  "type": "Feature",
  "properties": {
    "gn:admin1_code":"84",
    "gn:admin2_code":"2051.0",
    "gn:admin3_code":"205143.0",
    "gn:admin4_code":"20514355.0",
    "gn:asciiname":"Chiladi",
    "gn:country_code":"BD",
    "gn:dem":9,
    "gn:feature_class":"P",
    "gn:feature_code":"PPL",
    "gn:name":"Chil\u0101di",
    "gn:population":0,
    "gn:timezone":"Asia/Dhaka",
    "iso:country":"BD",
    "wof:name":"Chiladi",
    "wof:placetype":"locality"
},
  "geometry": {"coordinates":[90.91759999999999,22.8836],"type":"Point"}
}