{
  "type": "Feature",
  "properties": {
    "gn:admin1_code":"84",
    "gn:admin2_code":"2019.0",
    "gn:admin3_code":"201936.0",
    "gn:admin4_code":"20193647.0",
    "gn:asciiname":"Chhota Lakshmipur",
    "gn:country_code":"BD",
    "gn:dem":9,
    "gn:feature_class":"P",
    "gn:feature_code":"PPL",
    "gn:name":"Chhota Lakshmipur",
    "gn:population":0,
    "gn:timezone":"Asia/Dhaka",
    "iso:country":"BD",
    "name:und_x_variant":[
        "Chotta Lakshm\u012bpur"
    ],
    "wof:name":"Chhota Lakshmipur",
    "wof:placetype":"locality"
},
  "geometry": {"coordinates":[90.79730000000001,23.51075],"type":"Point"}
}