{
  "type": "Feature",
  "properties": {
    "gn:admin1_code":"85",
    "gn:admin2_code":"1006.0",
    "gn:admin3_code":"100602.0",
    "gn:admin4_code":"10060287.0",
    "gn:asciiname":"Chaukati",
    "gn:country_code":"BD",
    "gn:dem":10,
    "gn:feature_class":"P",
    "gn:feature_code":"PPL",
    "gn:name":"Chauk\u0101ti",
    "gn:population":0,
    "gn:timezone":"Asia/Dhaka",
    "iso:country":"BD",
    "name:und_x_variant":[
        "Chauk\u0101ti"
    ],
    "wof:name":"Chaukati",
    "wof:placetype":"locality"
},
  "geometry": {"coordinates":[90.21392,22.91545],"type":"Point"}
}