{
  "type": "Feature",
  "properties": {
    "gn:admin1_code":"82",
    "gn:admin2_code":"4041",
    "gn:admin3_code":"404161.0",
    "gn:admin4_code":"40416116.0",
    "gn:asciiname":"Uttarpara",
    "gn:country_code":"BD",
    "gn:dem":10,
    "gn:feature_class":"P",
    "gn:feature_code":"PPL",
    "gn:name":"Uttarp\u0101ra",
    "gn:population":0,
    "gn:timezone":"Asia/Dhaka",
    "iso:country":"BD",
    "name:ben_x_preferred":[
        "Uttarp\u0101ra"
    ],
    "wof:name":"Uttarpara",
    "wof:placetype":"locality"
},
  "geometry": {"coordinates":[89.26778,23.08887],"type":"Point"}
}