{
  "type": "Feature",
  "properties": {
    "gn:admin1_code":"84",
    "gn:admin2_code":"2013",
    "gn:admin3_code":"201376.0",
    "gn:admin4_code":"20137656.0",
    "gn:asciiname":"Tushpur",
    "gn:country_code":"BD",
    "gn:dem":11,
    "gn:feature_class":"P",
    "gn:feature_code":"PPL",
    "gn:name":"Tushpur",
    "gn:population":0,
    "gn:timezone":"Asia/Dhaka",
    "iso:country":"BD",
    "wof:name":"Tushpur",
    "wof:placetype":"locality"
},
  "geometry": {"coordinates":[90.78719,23.40956],"type":"Point"}
}