{
  "type": "Feature",
  "properties": {
    "gn:admin1_code":"83",
    "gn:admin2_code":"5064.0",
    "gn:admin3_code":"506447.0",
    "gn:admin4_code":"50644706.0",
    "gn:asciiname":"Chapra Bil",
    "gn:country_code":"BD",
    "gn:dem":25,
    "gn:feature_class":"P",
    "gn:feature_code":"PPL",
    "gn:name":"Chapra Bil",
    "gn:population":0,
    "gn:timezone":"Asia/Dhaka",
    "iso:country":"BD",
    "name:ben_x_preferred":[
        "Chapra Bil"
    ],
    "wof:name":"Chapra Bil",
    "wof:placetype":"locality"
},
  "geometry": {"coordinates":[88.66668,24.83464],"type":"Point"}
}