{
  "type": "Feature",
  "properties": {
    "gn:admin1_code":"83",
    "gn:admin2_code":"5038.0",
    "gn:admin3_code":"503813.0",
    "gn:admin4_code":"50381315.0",
    "gn:asciiname":"Dulali",
    "gn:country_code":"BD",
    "gn:dem":25,
    "gn:feature_class":"P",
    "gn:feature_code":"PPL",
    "gn:name":"Dulali",
    "gn:population":0,
    "gn:timezone":"Asia/Dhaka",
    "iso:country":"BD",
    "wof:name":"Dulali",
    "wof:placetype":"locality"
},
  "geometry": {"coordinates":[89.07675999999999,24.9455],"type":"Point"}
}