{
  "type": "Feature",
  "properties": {
    "gn:admin1_code":"82",
    "gn:admin2_code":"4050",
    "gn:admin3_code":"405094.0",
    "gn:admin4_code":"40509451.0",
    "gn:asciiname":"Paikpara",
    "gn:country_code":"BD",
    "gn:dem":17,
    "gn:feature_class":"P",
    "gn:feature_code":"PPL",
    "gn:name":"Paikpara",
    "gn:population":0,
    "gn:timezone":"Asia/Dhaka",
    "iso:country":"BD",
    "name:ben_x_preferred":[
        "Paikpara"
    ],
    "wof:name":"Paikpara",
    "wof:placetype":"locality"
},
  "geometry": {"coordinates":[88.95142,23.79697],"type":"Point"}
}