{
  "type": "Feature",
  "properties": {
    "gn:admin1_code":"81",
    "gn:admin2_code":"3033",
    "gn:admin3_code":"303330.0",
    "gn:admin4_code":"30333000.0",
    "gn:asciiname":"Pagar",
    "gn:country_code":"BD",
    "gn:dem":13,
    "gn:feature_class":"P",
    "gn:feature_code":"PPL",
    "gn:name":"P\u0101g\u0101r",
    "gn:population":0,
    "gn:timezone":"Asia/Dhaka",
    "iso:country":"BD",
    "wof:name":"Pagar",
    "wof:placetype":"locality"
},
  "geometry": {"coordinates":[90.41698,23.89328],"type":"Point"}
}