{
  "type": "Feature",
  "properties": {
    "gn:admin1_code":"82",
    "gn:admin2_code":"4044.0",
    "gn:admin3_code":"404442.0",
    "gn:admin4_code":"40444267.0",
    "gn:asciiname":"Golimpur",
    "gn:country_code":"BD",
    "gn:dem":17,
    "gn:feature_class":"P",
    "gn:feature_code":"PPL",
    "gn:name":"Golimpur",
    "gn:population":0,
    "gn:timezone":"Asia/Dhaka",
    "iso:country":"BD",
    "name:ben_x_preferred":[
        "Golimpur"
    ],
    "wof:name":"Golimpur",
    "wof:placetype":"locality"
},
  "geometry": {"coordinates":[89.02913000000002,23.44058],"type":"Point"}
}