{
  "type": "Feature",
  "properties": {
    "gn:admin1_code":"85",
    "gn:admin2_code":"1078.0",
    "gn:admin3_code":"107852.0",
    "gn:admin4_code":"10785210.0",
    "gn:asciiname":"Jauta",
    "gn:country_code":"BD",
    "gn:dem":5,
    "gn:feature_class":"P",
    "gn:feature_code":"PPL",
    "gn:name":"Jauta",
    "gn:population":0,
    "gn:timezone":"Asia/Dhaka",
    "iso:country":"BD",
    "name:ben_x_preferred":[
        "Jauta"
    ],
    "wof:name":"Jauta",
    "wof:placetype":"locality"
},
  "geometry": {"coordinates":[90.52152,22.2514],"type":"Point"}
}