{
  "type": "Feature",
  "properties": {
    "gn:admin1_code":"83",
    "gn:admin2_code":"5064.0",
    "gn:admin3_code":"506475.0",
    "gn:admin4_code":"50647577.0",
    "gn:asciiname":"Paharkata",
    "gn:country_code":"BD",
    "gn:dem":26,
    "gn:feature_class":"P",
    "gn:feature_code":"PPL",
    "gn:name":"P\u0101h\u0101rk\u0101ta",
    "gn:population":0,
    "gn:timezone":"Asia/Dhaka",
    "iso:country":"BD",
    "name:ben_x_preferred":[
        "P\u0101h\u0101rk\u0101ta"
    ],
    "wof:name":"Paharkata",
    "wof:placetype":"locality"
},
  "geometry": {"coordinates":[88.79838000000002,25.07191],"type":"Point"}
}