{
  "type": "Feature",
  "properties": {
    "gn:admin1_code":"87",
    "gn:admin2_code":"5527.0",
    "gn:admin3_code":"552717.0",
    "gn:admin4_code":"55271728.0",
    "gn:asciiname":"Bishnupur",
    "gn:country_code":"BD",
    "gn:dem":37,
    "gn:feature_class":"P",
    "gn:feature_code":"PPL",
    "gn:name":"Bishnupur",
    "gn:population":0,
    "gn:timezone":"Asia/Dhaka",
    "iso:country":"BD",
    "name:ben_x_preferred":[
        "Bishnupur"
    ],
    "wof:name":"Bishnupur",
    "wof:placetype":"locality"
},
  "geometry": {"coordinates":[88.55660999999998,25.61977000000001],"type":"Point"}
}