{
  "type": "Feature",
  "properties": {
    "gn:admin1_code":"82",
    "gn:admin2_code":"4044.0",
    "gn:admin3_code":"404419.0",
    "gn:admin4_code":"40441952.0",
    "gn:asciiname":"Hajidanga",
    "gn:country_code":"BD",
    "gn:dem":16,
    "gn:feature_class":"P",
    "gn:feature_code":"PPL",
    "gn:name":"H\u0101jid\u0101nga",
    "gn:population":0,
    "gn:timezone":"Asia/Dhaka",
    "iso:country":"BD",
    "name:ben_x_preferred":[
        "H\u0101jid\u0101nga"
    ],
    "wof:name":"Hajidanga",
    "wof:placetype":"locality"
},
  "geometry": {"coordinates":[89.02976,23.48834],"type":"Point"}
}