{
  "type": "Feature",
  "properties": {
    "gn:admin1_code":"82",
    "gn:admin2_code":"4050",
    "gn:admin3_code":"405063.0",
    "gn:admin4_code":"40506347.0",
    "gn:asciiname":"Jagalra",
    "gn:country_code":"BD",
    "gn:dem":16,
    "gn:feature_class":"P",
    "gn:feature_code":"PPL",
    "gn:name":"J\u0101galra",
    "gn:population":0,
    "gn:timezone":"Asia/Dhaka",
    "iso:country":"BD",
    "name:und_x_variant":[
        "Jagalba",
        "J\u0101galra"
    ],
    "wof:name":"Jagalra",
    "wof:placetype":"locality"
},
  "geometry": {"coordinates":[89.27428,23.7727],"type":"Point"}
}