{
  "type": "Feature",
  "properties": {
    "gn:admin1_code":"83",
    "gn:admin2_code":"5088",
    "gn:admin3_code":"508878.0",
    "gn:admin4_code":"50887894.0",
    "gn:asciiname":"Panch Thakuri",
    "gn:country_code":"BD",
    "gn:dem":17,
    "gn:feature_class":"P",
    "gn:feature_code":"PPL",
    "gn:name":"P\u0101nch Th\u0101kuri",
    "gn:population":0,
    "gn:timezone":"Asia/Dhaka",
    "iso:country":"BD",
    "name:und_x_variant":[
        "Pach Thakuri",
        "P\u0101nch Th\u0101kuri"
    ],
    "wof:name":"Panch Thakuri",
    "wof:placetype":"locality"
},
  "geometry": {"coordinates":[89.67674,24.5438],"type":"Point"}
}