{
  "type": "Feature",
  "properties": {
    "gn:admin1_code":"81",
    "gn:admin2_code":"3068",
    "gn:admin3_code":"306852.0",
    "gn:admin4_code":"30685281.0",
    "gn:asciiname":"Jhalpara",
    "gn:country_code":"BD",
    "gn:dem":15,
    "gn:feature_class":"P",
    "gn:feature_code":"PPL",
    "gn:name":"Jh\u0101lp\u0101ra",
    "gn:population":0,
    "gn:timezone":"Asia/Dhaka",
    "iso:country":"BD",
    "wof:name":"Jhalpara",
    "wof:placetype":"locality"
},
  "geometry": {"coordinates":[90.70206,24.23272],"type":"Point"}
}