{
  "type": "Feature",
  "properties": {
    "gn:admin1_code":"84",
    "gn:admin2_code":"2051",
    "gn:admin3_code":"205165.0",
    "gn:admin4_code":"20516566.0",
    "gn:asciiname":"Saudherkhil",
    "gn:country_code":"BD",
    "gn:dem":12,
    "gn:feature_class":"P",
    "gn:feature_code":"PPL",
    "gn:name":"S\u0101udherkhil",
    "gn:population":0,
    "gn:timezone":"Asia/Dhaka",
    "iso:country":"BD",
    "name:und_x_variant":[
        "Sandherkhil",
        "S\u0101udherkhil"
    ],
    "wof:name":"Saudherkhil",
    "wof:placetype":"locality"
},
  "geometry": {"coordinates":[90.87949,23.12715],"type":"Point"}
}