{
  "type": "Feature",
  "properties": {
    "gn:admin1_code":"87",
    "gn:admin2_code":"5573.0",
    "gn:admin3_code":"557336.0",
    "gn:admin4_code":"55733687.0",
    "gn:asciiname":"Kansana Bil",
    "gn:country_code":"BD",
    "gn:dem":52,
    "gn:feature_class":"P",
    "gn:feature_code":"PPL",
    "gn:name":"Kansana B\u012bl",
    "gn:population":0,
    "gn:timezone":"Asia/Dhaka",
    "iso:country":"BD",
    "name:ben_x_preferred":[
        "Kansana B\u012bl"
    ],
    "wof:name":"Kansana Bil",
    "wof:placetype":"locality"
},
  "geometry": {"coordinates":[88.91815,26.04575],"type":"Point"}
}