{
  "type": "Feature",
  "properties": {
    "gn:admin1_code":"87",
    "gn:admin2_code":"5577.0",
    "gn:admin3_code":"557773.0",
    "gn:admin4_code":"55777336.0",
    "gn:asciiname":"Dwarikamari",
    "gn:country_code":"BD",
    "gn:dem":80,
    "gn:feature_class":"P",
    "gn:feature_code":"PPL",
    "gn:name":"Dw\u0101rik\u0101m\u0101ri",
    "gn:population":0,
    "gn:timezone":"Asia/Dhaka",
    "iso:country":"BD",
    "name:ben_x_preferred":[
        "Dw\u0101rik\u0101m\u0101ri"
    ],
    "wof:name":"Dwarikamari",
    "wof:placetype":"locality"
},
  "geometry": {"coordinates":[88.54722,26.36313],"type":"Point"}
}