{
  "type": "Feature",
  "properties": {
    "gn:admin1_code":"82",
    "gn:admin2_code":"4044.0",
    "gn:admin3_code":"404471.0",
    "gn:admin4_code":"40447153.0",
    "gn:asciiname":"Nasti",
    "gn:country_code":"BD",
    "gn:dem":17,
    "gn:feature_class":"P",
    "gn:feature_code":"PPL",
    "gn:name":"Nasti",
    "gn:population":0,
    "gn:timezone":"Asia/Dhaka",
    "iso:country":"BD",
    "name:ben_x_preferred":[
        "Nasti"
    ],
    "wof:name":"Nasti",
    "wof:placetype":"locality"
},
  "geometry": {"coordinates":[88.88773,23.33889],"type":"Point"}
}