{
  "type": "Feature",
  "properties": {
    "gn:admin1_code":"81",
    "gn:admin2_code":"3082",
    "gn:admin3_code":"308273.0",
    "gn:admin4_code":"30827380.0",
    "gn:asciiname":"Puijor",
    "gn:country_code":"BD",
    "gn:dem":15,
    "gn:feature_class":"P",
    "gn:feature_code":"PPL",
    "gn:name":"Puijor",
    "gn:population":0,
    "gn:timezone":"Asia/Dhaka",
    "iso:country":"BD",
    "wof:name":"Puijor",
    "wof:placetype":"locality"
},
  "geometry": {"coordinates":[89.42843000000001,23.71812000000001],"type":"Point"}
}