{
  "type": "Feature",
  "properties": {
    "gn:admin1_code":"87",
    "gn:admin2_code":"5527.0",
    "gn:admin3_code":"552738.0",
    "gn:admin4_code":"55273847.0",
    "gn:asciiname":"Rajkkhanda",
    "gn:country_code":"BD",
    "gn:dem":34,
    "gn:feature_class":"P",
    "gn:feature_code":"PPL",
    "gn:name":"R\u0101jkkh\u0101nda",
    "gn:population":0,
    "gn:timezone":"Asia/Dhaka",
    "iso:country":"BD",
    "name:ben_x_preferred":[
        "R\u0101jkkh\u0101nda"
    ],
    "wof:name":"Rajkkhanda",
    "wof:placetype":"locality"
},
  "geometry": {"coordinates":[88.87373000000002,25.4761],"type":"Point"}
}