{
  "type": "Feature",
  "properties": {
    "gn:admin1_code":"84",
    "gn:admin2_code":"2003.0",
    "gn:admin3_code":"200314.0",
    "gn:admin4_code":"20031415.0",
    "gn:asciiname":"Meyaksipara",
    "gn:country_code":"BD",
    "gn:dem":25,
    "gn:feature_class":"P",
    "gn:feature_code":"PPL",
    "gn:name":"Meyaksip\u0101ra",
    "gn:population":0,
    "gn:timezone":"Asia/Dhaka",
    "iso:country":"BD",
    "name:ben_x_preferred":[
        "Meyaksip\u0101ra"
    ],
    "wof:name":"Meyaksipara",
    "wof:placetype":"locality"
},
  "geometry": {"coordinates":[92.21783000000001,22.18287],"type":"Point"}
}