{
  "type": "Feature",
  "properties": {
    "gn:admin1_code":"82",
    "gn:admin2_code":"4041.0",
    "gn:admin3_code":"404161.0",
    "gn:admin4_code":"40416194.0",
    "gn:asciiname":"Pardia",
    "gn:country_code":"BD",
    "gn:dem":11,
    "gn:feature_class":"P",
    "gn:feature_code":"PPL",
    "gn:name":"Pardia",
    "gn:population":0,
    "gn:timezone":"Asia/Dhaka",
    "iso:country":"BD",
    "name:ben_x_preferred":[
        "Pardia"
    ],
    "wof:name":"Pardia",
    "wof:placetype":"locality"
},
  "geometry": {"coordinates":[89.1977,22.99959],"type":"Point"}
}