{
  "type": "Feature",
  "properties": {
    "gn:admin1_code":"87",
    "gn:admin2_code":"5527",
    "gn:admin3_code":"552710.0",
    "gn:admin4_code":"55271035.0",
    "gn:asciiname":"Beparitola",
    "gn:country_code":"BD",
    "gn:dem":32,
    "gn:feature_class":"P",
    "gn:feature_code":"PPL",
    "gn:name":"Beparitola",
    "gn:population":0,
    "gn:timezone":"Asia/Dhaka",
    "iso:country":"BD",
    "name:ben_x_preferred":[
        "Beparitola"
    ],
    "wof:name":"Beparitola",
    "wof:placetype":"locality"
},
  "geometry": {"coordinates":[89.05329999999999,25.39125],"type":"Point"}
}