{
  "type": "Feature",
  "properties": {
    "gn:admin1_code":"83",
    "gn:admin2_code":"5010.0",
    "gn:admin3_code":"501020.0",
    "gn:admin4_code":"50102025.0",
    "gn:asciiname":"Belail",
    "gn:country_code":"BD",
    "gn:dem":25,
    "gn:feature_class":"P",
    "gn:feature_code":"PPL",
    "gn:name":"Bel\u0101il",
    "gn:population":0,
    "gn:timezone":"Asia/Dhaka",
    "iso:country":"BD",
    "wof:name":"Belail",
    "wof:placetype":"locality"
},
  "geometry": {"coordinates":[89.34321,24.83846],"type":"Point"}
}