{
  "type": "Feature",
  "properties": {
    "gn:admin1_code":"83",
    "gn:admin2_code":"5010",
    "gn:admin3_code":"501033.0",
    "gn:admin4_code":"50103354.0",
    "gn:asciiname":"Jhinai",
    "gn:country_code":"BD",
    "gn:dem":23,
    "gn:feature_class":"P",
    "gn:feature_code":"PPL",
    "gn:name":"Jhin\u0101i",
    "gn:population":0,
    "gn:timezone":"Asia/Dhaka",
    "iso:country":"BD",
    "name:und_x_variant":[
        "Jhenai",
        "Jhin\u0101i"
    ],
    "wof:name":"Jhinai",
    "wof:placetype":"locality"
},
  "geometry": {"coordinates":[89.10848,24.90956],"type":"Point"}
}