{
  "type": "Feature",
  "properties": {
    "gn:admin1_code":"87",
    "gn:admin2_code":"5585",
    "gn:admin3_code":"558558.0",
    "gn:admin4_code":"55855822.0",
    "gn:asciiname":"Kharga Kumarpur",
    "gn:country_code":"BD",
    "gn:dem":31,
    "gn:feature_class":"P",
    "gn:feature_code":"PPL",
    "gn:name":"Kharga Kum\u0101rpur",
    "gn:population":0,
    "gn:timezone":"Asia/Dhaka",
    "iso:country":"BD",
    "name:ben_x_preferred":[
        "Kharga Kum\u0101rpur"
    ],
    "wof:name":"Kharga Kumarpur",
    "wof:placetype":"locality"
},
  "geometry": {"coordinates":[89.36837,25.5935],"type":"Point"}
}