{
  "type": "Feature",
  "properties": {
    "gn:admin1_code":"82",
    "gn:admin2_code":"4050.0",
    "gn:admin3_code":"405015.0",
    "gn:admin4_code":"40501581.0",
    "gn:asciiname":"Char Mokarimpur",
    "gn:country_code":"BD",
    "gn:dem":16,
    "gn:feature_class":"P",
    "gn:feature_code":"PPL",
    "gn:name":"Char Mok\u0101rimpur",
    "gn:population":0,
    "gn:timezone":"Asia/Dhaka",
    "iso:country":"BD",
    "name:und_x_variant":[
        "Chak Mokarimpur",
        "Char Mok\u0101rimpur"
    ],
    "wof:name":"Char Mokarimpur",
    "wof:placetype":"locality"
},
  "geometry": {"coordinates":[89.00554,24.06381],"type":"Point"}
}