{
  "type": "Feature",
  "properties": {
    "gn:admin1_code":"81",
    "gn:admin2_code":"3029.0",
    "gn:admin3_code":"302984.0",
    "gn:admin4_code":"30298485.0",
    "gn:asciiname":"Baisrasi",
    "gn:country_code":"BD",
    "gn:dem":13,
    "gn:feature_class":"P",
    "gn:feature_code":"PPL",
    "gn:name":"B\u0101israsi",
    "gn:population":0,
    "gn:timezone":"Asia/Dhaka",
    "iso:country":"BD",
    "name:und_x_variant":[
        "Bais Rashi",
        "B\u0101israsi"
    ],
    "wof:name":"Baisrasi",
    "wof:placetype":"locality"
},
  "geometry": {"coordinates":[90.01098,23.45648],"type":"Point"}
}