{
  "type": "Feature",
  "properties": {
    "gn:admin1_code":"81",
    "gn:admin2_code":"3035",
    "gn:admin3_code":"303558.0",
    "gn:admin4_code":"30355816.0",
    "gn:asciiname":"Suasur",
    "gn:country_code":"BD",
    "gn:dem":6,
    "gn:feature_class":"P",
    "gn:feature_code":"PPL",
    "gn:name":"Su\u0101sur",
    "gn:population":0,
    "gn:timezone":"Asia/Dhaka",
    "iso:country":"BD",
    "wof:name":"Suasur",
    "wof:placetype":"locality"
},
  "geometry": {"coordinates":[89.91523000000002,23.26462],"type":"Point"}
}