{
  "type": "Feature",
  "properties": {
    "gn:admin1_code":"83",
    "gn:admin2_code":"5081",
    "gn:admin3_code":"508182.0",
    "gn:admin4_code":"50818227.0",
    "gn:asciiname":"Taras",
    "gn:country_code":"BD",
    "gn:dem":19,
    "gn:feature_class":"P",
    "gn:feature_code":"PPL",
    "gn:name":"T\u0101r\u0101s",
    "gn:population":0,
    "gn:timezone":"Asia/Dhaka",
    "iso:country":"BD",
    "name:bel_x_preferred":[
        "\u0422\u0430\u0440\u0430\u0441"
    ],
    "name:ben_x_preferred":[
        "T\u0101r\u0101s"
    ],
    "name:ceb_x_preferred":[
        "Taras"
    ],
    "name:ces_x_preferred":[
        "Taras"
    ],
    "name:deu_x_preferred":[
        "Taras"
    ],
    "name:fra_x_preferred":[
        "Taras"
    ],
    "name:ita_x_preferred":[
        "Taras"
    ],
    "name:jpn_x_preferred":[
        "\u30bf\u30e9\u30b9"
    ],
    "name:nld_x_preferred":[
        "Taras"
    ],
    "name:pol_x_preferred":[
        "Taras"
    ],
    "name:rus_x_preferred":[
        "\u0422\u0430\u0440\u0430\u0441"
    ],
    "name:spa_x_preferred":[
        "Taras"
    ],
    "name:swe_x_preferred":[
        "Taras"
    ],
    "name:ukr_x_preferred":[
        "\u0422\u0430\u0440\u0430\u0441"
    ],
    "wof:name":"Taras",
    "wof:placetype":"locality"
},
  "geometry": {"coordinates":[88.73304,24.38198],"type":"Point"}
}