{
  "type": "Feature",
  "properties": {
    "gn:admin1_code":"H",
    "gn:admin2_code":"3072.0",
    "gn:admin3_code":"307218.0",
    "gn:admin4_code":"30721869.0",
    "gn:asciiname":"Gaon Kandia",
    "gn:country_code":"BD",
    "gn:dem":15,
    "gn:feature_class":"P",
    "gn:feature_code":"PPL",
    "gn:name":"Gaon K\u0101ndia",
    "gn:population":0,
    "gn:timezone":"Asia/Dhaka",
    "iso:country":"BD",
    "name:und_x_variant":[
        "Gaokandia",
        "Gaon K\u0101ndia"
    ],
    "wof:name":"Gaon Kandia",
    "wof:placetype":"locality"
},
  "geometry": {"coordinates":[90.62554,25.08343],"type":"Point"}
}