{
  "type": "Feature",
  "properties": {
    "gn:admin1_code":"84",
    "gn:admin2_code":"2046.0",
    "gn:admin3_code":"204661.0",
    "gn:admin4_code":"20466171.0",
    "gn:asciiname":"Punapara",
    "gn:country_code":"BD",
    "gn:dem":43,
    "gn:feature_class":"P",
    "gn:feature_code":"PPL",
    "gn:name":"Punap\u0101ra",
    "gn:population":0,
    "gn:timezone":"Asia/Dhaka",
    "iso:country":"BD",
    "name:ben_x_preferred":[
        "Punap\u0101ra"
    ],
    "wof:name":"Punapara",
    "wof:placetype":"locality"
},
  "geometry": {"coordinates":[91.88196000000001,22.78971],"type":"Point"}
}