{
  "type": "Feature",
  "properties": {
    "gn:admin1_code":"83",
    "gn:admin2_code":"5064.0",
    "gn:admin3_code":"506479.0",
    "gn:admin4_code":"50647987.0",
    "gn:asciiname":"Daihar",
    "gn:country_code":"BD",
    "gn:dem":40,
    "gn:feature_class":"P",
    "gn:feature_code":"PPL",
    "gn:name":"Daih\u0101r",
    "gn:population":0,
    "gn:timezone":"Asia/Dhaka",
    "iso:country":"BD",
    "name:ben_x_preferred":[
        "Daih\u0101r"
    ],
    "wof:name":"Daihar",
    "wof:placetype":"locality"
},
  "geometry": {"coordinates":[88.54204,25.01018],"type":"Point"}
}