{
  "type": "Feature",
  "properties": {
    "gn:admin1_code":"87",
    "gn:admin2_code":"5549",
    "gn:admin3_code":"554952.0",
    "gn:admin4_code":"55495247.0",
    "gn:asciiname":"Ghanashyampur",
    "gn:country_code":"BD",
    "gn:dem":32,
    "gn:feature_class":"P",
    "gn:feature_code":"PPL",
    "gn:name":"Ghanashy\u0101mpur",
    "gn:population":0,
    "gn:timezone":"Asia/Dhaka",
    "iso:country":"BD",
    "name:ben_x_preferred":[
        "Ghanashy\u0101mpur"
    ],
    "wof:name":"Ghanashyampur",
    "wof:placetype":"locality"
},
  "geometry": {"coordinates":[89.72017,25.81063],"type":"Point"}
}