{
  "type": "Feature",
  "properties": {
    "gn:admin1_code":"87",
    "gn:admin2_code":"5527.0",
    "gn:admin3_code":"552756.0",
    "gn:admin4_code":"55275615.0",
    "gn:asciiname":"Katgaon",
    "gn:country_code":"BD",
    "gn:dem":46,
    "gn:feature_class":"P",
    "gn:feature_code":"PPL",
    "gn:name":"K\u0101tgaon",
    "gn:population":0,
    "gn:timezone":"Asia/Dhaka",
    "iso:country":"BD",
    "name:ben_x_preferred":[
        "K\u0101tgaon"
    ],
    "wof:name":"Katgaon",
    "wof:placetype":"locality"
},
  "geometry": {"coordinates":[88.52254000000001,25.81429],"type":"Point"}
}