{
  "type": "Feature",
  "properties": {
    "gn:admin1_code":"84",
    "gn:admin2_code":"2015.0",
    "gn:admin3_code":"201537.0",
    "gn:admin4_code":"20153765.0",
    "gn:asciiname":"Uttar Mekhal",
    "gn:country_code":"BD",
    "gn:dem":6,
    "gn:feature_class":"P",
    "gn:feature_code":"PPL",
    "gn:name":"Uttar Mekhal",
    "gn:population":0,
    "gn:timezone":"Asia/Dhaka",
    "iso:country":"BD",
    "name:ben_x_preferred":[
        "Uttar Mekhal"
    ],
    "wof:name":"Uttar Mekhal",
    "wof:placetype":"locality"
},
  "geometry": {"coordinates":[91.84121,22.50344],"type":"Point"}
}