{
  "type": "Feature",
  "properties": {
    "gn:admin1_code":"81",
    "gn:admin2_code":"3068.0",
    "gn:admin3_code":"306860.0",
    "gn:admin4_code":"30686047.0",
    "gn:asciiname":"Dasturdi",
    "gn:country_code":"BD",
    "gn:dem":11,
    "gn:feature_class":"P",
    "gn:feature_code":"PPL",
    "gn:name":"Dasturdi",
    "gn:population":0,
    "gn:timezone":"Asia/Dhaka",
    "iso:country":"BD",
    "wof:name":"Dasturdi",
    "wof:placetype":"locality"
},
  "geometry": {"coordinates":[90.65163,23.80488],"type":"Point"}
}