{
  "type": "Feature",
  "properties": {
    "gn:admin1_code":"H",
    "gn:admin2_code":"3061",
    "gn:admin3_code":"306165.0",
    "gn:admin4_code":"30616517.0",
    "gn:asciiname":"Muranpur",
    "gn:country_code":"BD",
    "gn:dem":16,
    "gn:feature_class":"P",
    "gn:feature_code":"PPL",
    "gn:name":"Muranpur",
    "gn:population":0,
    "gn:timezone":"Asia/Dhaka",
    "iso:country":"BD",
    "name:und_x_variant":[
        "Mur\u0101ripur"
    ],
    "wof:name":"Muranpur",
    "wof:placetype":"locality"
},
  "geometry": {"coordinates":[90.26414,24.7258],"type":"Point"}
}