{
  "type": "Feature",
  "properties": {
    "gn:admin1_code":"84",
    "gn:admin2_code":"2075",
    "gn:admin3_code":"207507.0",
    "gn:admin4_code":"20750728.0",
    "gn:asciiname":"Talibpur",
    "gn:country_code":"BD",
    "gn:dem":6,
    "gn:feature_class":"P",
    "gn:feature_code":"PPL",
    "gn:name":"T\u0101libpur",
    "gn:population":0,
    "gn:timezone":"Asia/Dhaka",
    "iso:country":"BD",
    "wof:name":"Talibpur",
    "wof:placetype":"locality"
},
  "geometry": {"coordinates":[91.01667,22.88333],"type":"Point"}
}