{
  "type": "Feature",
  "properties": {
    "gn:admin1_code":"87",
    "gn:admin2_code":"5585",
    "gn:admin3_code":"558576.0",
    "gn:admin4_code":"55857644.0",
    "gn:asciiname":"Mitharpara",
    "gn:country_code":"BD",
    "gn:dem":32,
    "gn:feature_class":"P",
    "gn:feature_code":"PPL",
    "gn:name":"Mitharpara",
    "gn:population":0,
    "gn:timezone":"Asia/Dhaka",
    "iso:country":"BD",
    "name:ben_x_preferred":[
        "Mitharpara"
    ],
    "wof:name":"Mitharpara",
    "wof:placetype":"locality"
},
  "geometry": {"coordinates":[89.26866,25.47459],"type":"Point"}
}