{
  "type": "Feature",
  "properties": {
    "gn:admin1_code":"87",
    "gn:admin2_code":"5585",
    "gn:admin3_code":"558503.0",
    "gn:admin4_code":"55850388.0",
    "gn:asciiname":"Dakshin Muksudpur",
    "gn:country_code":"BD",
    "gn:dem":38,
    "gn:feature_class":"P",
    "gn:feature_code":"PPL",
    "gn:name":"Dakshin Muksudpur",
    "gn:population":0,
    "gn:timezone":"Asia/Dhaka",
    "iso:country":"BD",
    "name:ben_x_preferred":[
        "Dakshin Muksudpur"
    ],
    "wof:name":"Dakshin Muksudpur",
    "wof:placetype":"locality"
},
  "geometry": {"coordinates":[88.9996,25.6749],"type":"Point"}
}