{
  "type": "Feature",
  "properties": {
    "gn:admin1_code":"83",
    "gn:admin2_code":"5038",
    "gn:admin3_code":"503861.0",
    "gn:admin4_code":"50386157.0",
    "gn:asciiname":"Paschim Durgapur",
    "gn:country_code":"BD",
    "gn:dem":22,
    "gn:feature_class":"P",
    "gn:feature_code":"PPL",
    "gn:name":"Paschim Durg\u0101pur",
    "gn:population":0,
    "gn:timezone":"Asia/Dhaka",
    "iso:country":"BD",
    "name:ben_x_preferred":[
        "Paschim Durg\u0101pur"
    ],
    "wof:name":"Paschim Durgapur",
    "wof:placetype":"locality"
},
  "geometry": {"coordinates":[89.04836999999998,25.03525],"type":"Point"}
}