{
  "type": "Feature",
  "properties": {
    "gn:admin1_code":"82",
    "gn:admin2_code":"4065.0",
    "gn:admin3_code":"406528.0",
    "gn:admin4_code":"40652823.0",
    "gn:asciiname":"Narayanpur",
    "gn:country_code":"BD",
    "gn:dem":6,
    "gn:feature_class":"P",
    "gn:feature_code":"PPL",
    "gn:name":"N\u0101rayanpur",
    "gn:population":0,
    "gn:timezone":"Asia/Dhaka",
    "iso:country":"BD",
    "name:ben_x_preferred":[
        "N\u0101rayanpur"
    ],
    "name:ceb_x_preferred":[
        "Narayanpur"
    ],
    "name:fra_x_preferred":[
        "Narayanpur"
    ],
    "name:pol_x_preferred":[
        "Narayanpur"
    ],
    "name:swe_x_preferred":[
        "Narayanpur"
    ],
    "name:tel_x_preferred":[
        "\u0c28\u0c3e\u0c30\u0c3e\u0c2f\u0c23\u0c4d\u200c\u0c2a\u0c42\u0c30\u0c4d"
    ],
    "wof:name":"Narayanpur",
    "wof:placetype":"locality"
},
  "geometry": {"coordinates":[89.5924,22.97522],"type":"Point"}
}