{
  "type": "Feature",
  "properties": {
    "gn:admin1_code":"83",
    "gn:admin2_code":"5070.0",
    "gn:admin3_code":"507066.0",
    "gn:admin4_code":"50706622.0",
    "gn:asciiname":"Malbagdanga",
    "gn:country_code":"BD",
    "gn:dem":25,
    "gn:feature_class":"P",
    "gn:feature_code":"PPL",
    "gn:name":"M\u0101lb\u0101gd\u0101nga",
    "gn:population":0,
    "gn:timezone":"Asia/Dhaka",
    "iso:country":"BD",
    "name:ben_x_preferred":[
        "M\u0101lb\u0101gd\u0101nga"
    ],
    "wof:name":"Malbagdanga",
    "wof:placetype":"locality"
},
  "geometry": {"coordinates":[88.19150999999999,24.50683],"type":"Point"}
}