{
  "type": "Feature",
  "properties": {
    "gn:admin1_code":"82",
    "gn:admin2_code":"4047.0",
    "gn:admin3_code":"404712.0",
    "gn:admin4_code":"40471259.0",
    "gn:asciiname":"Balabunia",
    "gn:country_code":"BD",
    "gn:dem":6,
    "gn:feature_class":"P",
    "gn:feature_code":"PPL",
    "gn:name":"Bal\u0101bunia",
    "gn:population":0,
    "gn:timezone":"Asia/Dhaka",
    "iso:country":"BD",
    "wof:name":"Balabunia",
    "wof:placetype":"locality"
},
  "geometry": {"coordinates":[89.49629,22.70433],"type":"Point"}
}