{
  "type": "Feature",
  "properties": {
    "gn:admin1_code":"83",
    "gn:admin2_code":"5070.0",
    "gn:admin3_code":"507088.0",
    "gn:admin4_code":"50708800.0",
    "gn:asciiname":"Sheiktola",
    "gn:country_code":"BD",
    "gn:dem":31,
    "gn:feature_class":"P",
    "gn:feature_code":"PPL",
    "gn:name":"Sheiktola",
    "gn:population":0,
    "gn:timezone":"Asia/Dhaka",
    "iso:country":"BD",
    "name:ben_x_preferred":[
        "Sheiktola"
    ],
    "wof:name":"Sheiktola",
    "wof:placetype":"locality"
},
  "geometry": {"coordinates":[88.16381,24.66706],"type":"Point"}
}