{
  "type": "Feature",
  "properties": {
    "gn:admin1_code":"82",
    "gn:asciiname":"Parsibpur South",
    "gn:country_code":"BD",
    "gn:dem":6,
    "gn:feature_class":"P",
    "gn:feature_code":"PPL",
    "gn:name":"P\u0101rsibpur South",
    "gn:population":0,
    "gn:timezone":"Asia/Dhaka",
    "iso:country":"BD",
    "name:ben_x_preferred":[
        "P\u0101rsibpur South"
    ],
    "wof:name":"Parsibpur South",
    "wof:placetype":"locality"
},
  "geometry": {"coordinates":[90.27811,22.47508],"type":"Point"}
}