{
  "type": "Feature",
  "properties": {
    "gn:admin1_code":"81",
    "gn:admin2_code":"3035.0",
    "gn:admin3_code":"303543.0",
    "gn:admin4_code":"30354340.0",
    "gn:asciiname":"Byaspur",
    "gn:country_code":"BD",
    "gn:dem":12,
    "gn:feature_class":"P",
    "gn:feature_code":"PPL",
    "gn:name":"Byaspur",
    "gn:population":0,
    "gn:timezone":"Asia/Dhaka",
    "iso:country":"BD",
    "name:und_x_variant":[
        "Byuspur",
        "Bynashpur",
        "Byaspur"
    ],
    "wof:name":"Byaspur",
    "wof:placetype":"locality"
},
  "geometry": {"coordinates":[89.75394,23.28274],"type":"Point"}
}