{
  "type": "Feature",
  "properties": {
    "gn:admin1_code":"83",
    "gn:admin2_code":"5070.0",
    "gn:admin3_code":"507066.0",
    "gn:admin4_code":"50706644.0",
    "gn:asciiname":"Laharapara",
    "gn:country_code":"BD",
    "gn:dem":46,
    "gn:feature_class":"P",
    "gn:feature_code":"PPL",
    "gn:name":"Lah\u0101r\u0101p\u0101ra",
    "gn:population":0,
    "gn:timezone":"Asia/Dhaka",
    "iso:country":"BD",
    "name:ben_x_preferred":[
        "Lah\u0101r\u0101p\u0101ra"
    ],
    "wof:name":"Laharapara",
    "wof:placetype":"locality"
},
  "geometry": {"coordinates":[88.40835,24.61767],"type":"Point"}
}