{
  "type": "Feature",
  "properties": {
    "gn:admin1_code":"83",
    "gn:admin2_code":"5081.0",
    "gn:admin3_code":"508131.0",
    "gn:admin4_code":"50813159.0",
    "gn:asciiname":"Gopalpara",
    "gn:country_code":"BD",
    "gn:dem":21,
    "gn:feature_class":"P",
    "gn:feature_code":"PPL",
    "gn:name":"Gop\u0101lp\u0101ra",
    "gn:population":0,
    "gn:timezone":"Asia/Dhaka",
    "iso:country":"BD",
    "name:ben_x_preferred":[
        "Gop\u0101lp\u0101ra"
    ],
    "name:und_x_variant":[
        "Gopalpur"
    ],
    "wof:name":"Gopalpara",
    "wof:placetype":"locality"
},
  "geometry": {"coordinates":[88.82411,24.5055],"type":"Point"}
}