{
  "type": "Feature",
  "properties": {
    "gn:admin1_code":"87",
    "gn:admin2_code":"5549",
    "gn:admin3_code":"554918.0",
    "gn:admin4_code":"55491840.0",
    "gn:asciiname":"Phulbari",
    "gn:country_code":"BD",
    "gn:dem":34,
    "gn:feature_class":"P",
    "gn:feature_code":"PPL",
    "gn:name":"Phulb\u0101ri",
    "gn:population":0,
    "gn:timezone":"Asia/Dhaka",
    "iso:country":"BD",
    "name:ben_x_preferred":[
        "Phulb\u0101ri"
    ],
    "name:ben_x_variant":[
        "Fulb\u0101ri"
    ],
    "name:und_x_variant":[
        "Phulb\u0101ri",
        "Fulb\u0101ri"
    ],
    "wof:name":"Phulbari",
    "wof:placetype":"locality"
},
  "geometry": {"coordinates":[89.55591,25.94902],"type":"Point"}
}