{
  "type": "Feature",
  "properties": {
    "gn:admin1_code":"84",
    "gn:admin2_code":"2012.0",
    "gn:admin3_code":"201285.0",
    "gn:admin4_code":"20128583.0",
    "gn:asciiname":"Chechra",
    "gn:country_code":"BD",
    "gn:dem":10,
    "gn:feature_class":"P",
    "gn:feature_code":"PPL",
    "gn:name":"Chechra",
    "gn:population":0,
    "gn:timezone":"Asia/Dhaka",
    "iso:country":"BD",
    "wof:name":"Chechra",
    "wof:placetype":"locality"
},
  "geometry": {"coordinates":[90.96322000000001,23.79058],"type":"Point"}
}