{
  "type": "Feature",
  "properties": {
    "gn:admin1_code":"83",
    "gn:admin2_code":"5064.0",
    "gn:admin3_code":"506486.0",
    "gn:admin4_code":"50648607.0",
    "gn:asciiname":"Gouripur",
    "gn:country_code":"BD",
    "gn:dem":31,
    "gn:feature_class":"P",
    "gn:feature_code":"PPL",
    "gn:name":"Gouripur",
    "gn:population":0,
    "gn:timezone":"Asia/Dhaka",
    "iso:country":"BD",
    "name:ben_x_preferred":[
        "Gouripur"
    ],
    "name:ben_x_variant":[
        "Gauripur"
    ],
    "wof:name":"Gouripur",
    "wof:placetype":"locality"
},
  "geometry": {"coordinates":[88.52475,25.18936],"type":"Point"}
}