{
  "type": "Feature",
  "properties": {
    "gn:admin1_code":"83",
    "gn:admin2_code":"5076.0",
    "gn:admin3_code":"507655.0",
    "gn:admin4_code":"50765543.0",
    "gn:asciiname":"Balarampur",
    "gn:country_code":"BD",
    "gn:dem":18,
    "gn:feature_class":"P",
    "gn:feature_code":"PPL",
    "gn:name":"Balar\u0101mpur",
    "gn:population":0,
    "gn:timezone":"Asia/Dhaka",
    "iso:country":"BD",
    "name:cat_x_preferred":[
        "Balrampur"
    ],
    "name:ceb_x_preferred":[
        "Balrampur"
    ],
    "name:ita_x_preferred":[
        "Balarampur"
    ],
    "name:nld_x_preferred":[
        "Balrampur"
    ],
    "name:pol_x_preferred":[
        "Balarampur"
    ],
    "name:rus_x_preferred":[
        "\u0411\u0430\u043b\u0440\u0430\u043c\u043f\u0443\u0440"
    ],
    "name:swe_x_preferred":[
        "Balrampur"
    ],
    "wof:name":"Balarampur",
    "wof:placetype":"locality"
},
  "geometry": {"coordinates":[89.24897,23.98947],"type":"Point"}
}