{
  "type": "Feature",
  "properties": {
    "gn:admin1_code":"83",
    "gn:admin2_code":"5070.0",
    "gn:admin3_code":"507088.0",
    "gn:admin4_code":"50708889.0",
    "gn:asciiname":"Purba Shampur",
    "gn:country_code":"BD",
    "gn:dem":26,
    "gn:feature_class":"P",
    "gn:feature_code":"PPL",
    "gn:name":"Purba Shampur",
    "gn:population":0,
    "gn:timezone":"Asia/Dhaka",
    "iso:country":"BD",
    "name:ben_x_preferred":[
        "Purba Shampur"
    ],
    "wof:name":"Purba Shampur",
    "wof:placetype":"locality"
},
  "geometry": {"coordinates":[88.14268,24.70956],"type":"Point"}
}