{
  "type": "Feature",
  "properties": {
    "gn:admin1_code":"83",
    "gn:admin2_code":"5064.0",
    "gn:admin3_code":"506428.0",
    "gn:admin4_code":"50642877.0",
    "gn:asciiname":"Deshahar",
    "gn:country_code":"BD",
    "gn:dem":25,
    "gn:feature_class":"P",
    "gn:feature_code":"PPL",
    "gn:name":"Desh\u0101h\u0101r",
    "gn:population":0,
    "gn:timezone":"Asia/Dhaka",
    "iso:country":"BD",
    "name:ben_x_preferred":[
        "Desh\u0101h\u0101r"
    ],
    "wof:name":"Deshahar",
    "wof:placetype":"locality"
},
  "geometry": {"coordinates":[88.70129,25.13571],"type":"Point"}
}