{
  "type": "Feature",
  "properties": {
    "gn:admin1_code":"82",
    "gn:admin2_code":"4055.0",
    "gn:admin3_code":"405566.0",
    "gn:admin4_code":"40556663.0",
    "gn:asciiname":"Joyrampur",
    "gn:country_code":"BD",
    "gn:dem":9,
    "gn:feature_class":"P",
    "gn:feature_code":"PPL",
    "gn:name":"Joyrampur",
    "gn:population":0,
    "gn:timezone":"Asia/Dhaka",
    "iso:country":"BD",
    "name:ben_x_preferred":[
        "Joyrampur"
    ],
    "wof:name":"Joyrampur",
    "wof:placetype":"locality"
},
  "geometry": {"coordinates":[89.49008000000001,23.30246],"type":"Point"}
}