{
  "type": "Feature",
  "properties": {
    "gn:admin1_code":"84",
    "gn:admin2_code":"2003.0",
    "gn:admin3_code":"200373.0",
    "gn:admin4_code":"20037319.0",
    "gn:asciiname":"Kaimmapapara",
    "gn:country_code":"BD",
    "gn:dem":33,
    "gn:feature_class":"P",
    "gn:feature_code":"PPL",
    "gn:name":"Kaimm\u0101p\u0101p\u0101ra",
    "gn:population":0,
    "gn:timezone":"Asia/Dhaka",
    "iso:country":"BD",
    "name:ben_x_preferred":[
        "Kaimm\u0101p\u0101p\u0101ra"
    ],
    "wof:name":"Kaimmapapara",
    "wof:placetype":"locality"
},
  "geometry": {"coordinates":[92.15022,21.62306],"type":"Point"}
}