{
  "type": "Feature",
  "properties": {
    "gn:admin1_code":"82",
    "gn:admin2_code":"4050",
    "gn:admin3_code":"405071.0",
    "gn:admin4_code":"40507194.0",
    "gn:asciiname":"Noathi",
    "gn:country_code":"BD",
    "gn:dem":15,
    "gn:feature_class":"P",
    "gn:feature_code":"PPL",
    "gn:name":"Noathi",
    "gn:population":0,
    "gn:timezone":"Asia/Dhaka",
    "iso:country":"BD",
    "name:ben_x_preferred":[
        "Noathi"
    ],
    "name:ben_x_variant":[
        "Nauthi"
    ],
    "wof:name":"Noathi",
    "wof:placetype":"locality"
},
  "geometry": {"coordinates":[89.21850000000001,23.89769],"type":"Point"}
}