{
  "type": "Feature",
  "properties": {
    "gn:admin1_code":"84",
    "gn:admin2_code":"2019",
    "gn:admin3_code":"201967.0",
    "gn:admin4_code":"20196794.0",
    "gn:asciiname":"Sankarpur",
    "gn:country_code":"BD",
    "gn:dem":11,
    "gn:feature_class":"P",
    "gn:feature_code":"PPL",
    "gn:name":"Sankarpur",
    "gn:population":0,
    "gn:timezone":"Asia/Dhaka",
    "iso:country":"BD",
    "name:ceb_x_preferred":[
        "Sankarpur"
    ],
    "name:fra_x_preferred":[
        "Sankarpur"
    ],
    "name:pol_x_preferred":[
        "Sankarpur"
    ],
    "name:swe_x_preferred":[
        "Sankarpur"
    ],
    "wof:name":"Sankarpur",
    "wof:placetype":"locality"
},
  "geometry": {"coordinates":[91.13333,23.46667],"type":"Point"}
}