{
  "type": "Feature",
  "properties": {
    "gn:admin1_code":"81",
    "gn:admin2_code":"3048",
    "gn:admin3_code":"304806.0",
    "gn:admin4_code":"30480660.0",
    "gn:asciiname":"Rahenda",
    "gn:country_code":"BD",
    "gn:dem":12,
    "gn:feature_class":"P",
    "gn:feature_code":"PPL",
    "gn:name":"R\u0101henda",
    "gn:population":0,
    "gn:timezone":"Asia/Dhaka",
    "iso:country":"BD",
    "wof:name":"Rahenda",
    "wof:placetype":"locality"
},
  "geometry": {"coordinates":[90.92176000000001,24.21685],"type":"Point"}
}