{
  "type": "Feature",
  "properties": {
    "gn:admin1_code":"83",
    "gn:admin2_code":"5038",
    "gn:admin3_code":"503813.0",
    "gn:admin4_code":"50381363.0",
    "gn:asciiname":"Kathalbari",
    "gn:country_code":"BD",
    "gn:dem":25,
    "gn:feature_class":"P",
    "gn:feature_code":"PPL",
    "gn:name":"K\u0101th\u0101lb\u0101ri",
    "gn:population":0,
    "gn:timezone":"Asia/Dhaka",
    "iso:country":"BD",
    "wof:name":"Kathalbari",
    "wof:placetype":"locality"
},
  "geometry": {"coordinates":[89.03661,24.93657],"type":"Point"}
}