{
  "type": "Feature",
  "properties": {
    "gn:admin1_code":"82",
    "gn:admin2_code":"4065.0",
    "gn:admin3_code":"406528.0",
    "gn:admin4_code":"40652879.0",
    "gn:asciiname":"Pakhimara",
    "gn:country_code":"BD",
    "gn:dem":9,
    "gn:feature_class":"P",
    "gn:feature_code":"PPL",
    "gn:name":"P\u0101khim\u0101ra",
    "gn:population":0,
    "gn:timezone":"Asia/Dhaka",
    "iso:country":"BD",
    "name:ben_x_preferred":[
        "P\u0101khim\u0101ra"
    ],
    "wof:name":"Pakhimara",
    "wof:placetype":"locality"
},
  "geometry": {"coordinates":[89.73942,22.97283],"type":"Point"}
}