{
  "type": "Feature",
  "properties": {
    "gn:admin1_code":"H",
    "gn:admin2_code":"3072.0",
    "gn:admin3_code":"307274.0",
    "gn:admin4_code":"30727487.0",
    "gn:asciiname":"Hariangati",
    "gn:country_code":"BD",
    "gn:dem":15,
    "gn:feature_class":"P",
    "gn:feature_code":"PPL",
    "gn:name":"Hari\u0101ng\u0101ti",
    "gn:population":0,
    "gn:timezone":"Asia/Dhaka",
    "iso:country":"BD",
    "name:und_x_variant":[
        "Hari\u0101ng\u0101ti",
        "Hari\u0101rg\u0101ti"
    ],
    "wof:name":"Hariangati",
    "wof:placetype":"locality"
},
  "geometry": {"coordinates":[90.79798,24.8943],"type":"Point"}
}