{
  "type": "Feature",
  "properties": {
    "gn:admin1_code":"87",
    "gn:asciiname":"Sirta",
    "gn:country_code":"BD",
    "gn:dem":29,
    "gn:feature_class":"P",
    "gn:feature_code":"PPL",
    "gn:name":"Sirta",
    "gn:population":0,
    "gn:timezone":"Asia/Dhaka",
    "iso:country":"BD",
    "name:ben_x_preferred":[
        "Sirta"
    ],
    "wof:name":"Sirta",
    "wof:placetype":"locality"
},
  "geometry": {"coordinates":[89.16124000000001,25.22342],"type":"Point"}
}